Workbook

Sheet Acadia
D1: Acadia Combined Balance Sheet
D2: Issued: December 31, 2013
K4: General | L4: Parish Road Fund | M4: Sales Tax Fund | N4: 1% Sales Tax District No. 2 Fund | O4: Sales Tax Road Bond Construction Fund | P4: LCDBG Ike-Gustav Disaster Recovery Grant Fund | Q4: Other Governmental Funds | R4: Total Governmental Funds
A5: Assets:
B6: Cash | K6: 284024 | L6: 928317 | M6: 950888 | N6: 130207 | O6: 523402 | P6: 94 | Q6: 3570123 | R6: =SUM(K6:Q6) -> 6387055
B7: Investments | K7: 107505 | L7: 12732 | M7: 3954843 | N7: 136092 | Q7: 3147964 | R7: =SUM(K7:Q7) -> 7359136
B8: Taxes receivable | K8: 169205 | L8: 104453 | Q8: 139272 | R8: =SUM(K8:Q8) -> 412930
B9: Special assessments receivable | Q9: 29556 | R9: =SUM(K9:Q9) -> 29556
B10: Other receivables | K10: 70322 | L10: 2600 | Q10: 4875 | R10: =SUM(K10:Q10) -> 77797
B11: Due from other governmental entities, net of
C12: allowance for doubtful accounts | K12: 1989847 | L12: 1137887 | M12: 627654 | N12: 184794 | O12: 432 | P12: 134931 | Q12: 1533184 | R12: =SUM(K12:Q12) -> 5608729
B13: Due from other funds | K13: 87504 | R13: =SUM(K13:Q13) -> 87504
B14: Due from component units | K14: 20793 | R14: =SUM(K14:Q14) -> 20793
E16: Total assets: | K16: =SUM(K6:K14) -> 2729200 | L16: =SUM(L6:L14) -> 2185989 | M16: =SUM(M6:M14) -> 5533385 | N16: =SUM(N6:N14) -> 451093 | O16: =SUM(O6:O14) -> 523834 | P16: =SUM(P6:P14) -> 135025 | Q16: =SUM(Q6:Q14) -> 8424974 | R16: =SUM(R6:R14) -> 19983500
A18: LIABILITIES AND FUND BALANCES
B19: Liabilities:
C20: Accounts payable | K20: 153148 | L20: 23523 | M20: 263877 | N20: 2929 | O20: 127068 | P20: 134931 | Q20: 94381 | R20: =SUM(K20:Q20) -> 799857
C21: Retainage payable | O21: 30559 | R21: =SUM(K21:Q21) -> 30559
C22: Accrued liabilities and other payables | K22: 230524 | L22: 41019 | Q22: 54692 | R22: =SUM(K22:Q22) -> 326235
C23: Unearned revenue | L23: 26500 | R23: =SUM(K23:Q23) -> 26500
C24: Due to other funds | L24: 46135 | M24: 29407 | Q24: 11962 | R24: =SUM(K24:Q24) -> 87504
E26: Total liabilities: | K26: =SUM(K20:K24) -> 383672 | L26: =SUM(L20:L24) -> 137177 | M26: =SUM(M20:M24) -> 293284 | N26: =SUM(N20:N24) -> 2929 | O26: =SUM(O20:O24) -> 157627 | P26: =SUM(P20:P24) -> 134931 | Q26: =SUM(Q20:Q24) -> 161035 | R26: =SUM(R20:R24) -> 1270655
A28: DEFERRED INFLOWS OF RESOURCES
B29: Unavailable revenue - special assessments | Q29: 29556 | R29: =SUM(K29:Q29) -> 29556
B31: Fund Balances:
C32: Restricted for:
D33: Property tax dedication | K33: 547451 | L33: 2048812 | R33: =SUM(K33:Q33) -> 2596263
D34: Sales tax dedication | M34: 5240101 | N34: 448164 | R34: =SUM(K34:Q34) -> 5688265
D35: Debt retirement | Q35: 1587612 | R35: =SUM(K35:Q35) -> 1587612
D36: Mosquito control | Q36: 1541983 | R36: =SUM(K36:Q36) -> 1541983
D37: Cooperative extension operation and maintenance | Q37: 1361388 | R37: =SUM(K37:Q37) -> 1361388
C38: Committed to:
D39: Road maintenance and construction | Q39: 665302 | R39: =SUM(K39:Q39) -> 665302
D40: Health unit operation and maintenance | Q40: 1470338 | R40: =SUM(K40:Q40) -> 1470338
D41: Rice arena operation and maintenance | Q41: 726543 | R41: =SUM(K41:Q41) -> 726543
C42: Assigned to:
D43: Debt service | Q43: 3822 | R43: =SUM(K43:Q43) -> 3822
D44: Capital projects | O44: 366207 | P44: 94 | Q44: 8881 | R44: =SUM(K44:Q44) -> 375182
D45: Economic development | Q45: 658066 | R45: =SUM(K45:Q45) -> 658066
D46: Airport | Q46: 165470 | R46: =SUM(K46:Q46) -> 165470
D47: Other | Q47: 44978 | R47: =SUM(K47:Q47) -> 44978
C48: Unassigned | K48: 1798077 | R48: =SUM(K48:Q48) -> 1798077
E50: Total fund balance: | K50: =SUM(K33:K48) -> 2345528 | L50: =SUM(L33:L48) -> 2048812 | M50: =SUM(M33:M48) -> 5240101 | N50: =SUM(N33:N48) -> 448164 | O50: =SUM(O33:O48) -> 366207 | P50: =SUM(P33:P48) -> 94 | Q50: =SUM(Q33:Q48) -> 8234383 | R50: =SUM(R33:R48) -> 18683289
E52: Total liabilities and fund balances: | K52: =SUM(K50,K26) -> 2729200 | L52: =SUM(L50,L26) -> 2185989 | M52: =SUM(M50,M26) -> 5533385 | N52: =SUM(N50,N26) -> 451093 | O52: =SUM(O50,O26) -> 523834 | P52: =SUM(P26,P50) -> 135025 | Q52: =Q50+Q29+Q26 -> 8424974 | R52: =R50+R29+R26 -> 19983500

Sheet Allen
D1: Allen Combined Balance Sheet
D2: Issued: December 31, 2013
K4: General Fund | L4: Solid Waste Fund | M4: Hospital Retrofit Fund | N4: Compact Fund | O4: Parish Road Fund | P4: Road District #2 MTC. Fund | Q4: Road District #3 MTC. Fund | R4: Nonmajor Governmental Funds | S4: Total Governmental Funds
A5: Assets:
B6: Cash | K6: 333065 | L6: 553695 | M6: 103600 | N6: 546048 | O6: 48 | P6: 606522 | Q6: 1397497 | R6: 978046 | S6: =SUM(K6:R6) -> 4518521
B7: Receivables | K7: 246603 | N7: 108339 | P7: 616160 | Q7: 636424 | R7: 1351112 | S7: =SUM(K7:R7) -> 2958638
B8: Due from other governments | K8: 333701 | L8: 139221 | O8: 64248 | R8: 12210 | S8: =SUM(K8:R8) -> 549380
B9: Inventory | R9: 25276 | S9: =SUM(K9:R9) -> 25276
B10: Due from other funds | K10: 37786 | P10: 224 | R10: 37065 | S10: =SUM(K10:R10) -> 75075
B11: Prepaid assets | K11: 4443 | S11: =SUM(K11:R11) -> 4443
E13: Total assets: | K13: =SUM(K6:K11) -> 955598 | L13: =SUM(L6:L11) -> 692916 | M13: =SUM(M6:M11) -> 103600 | N13: =SUM(N6:N11) -> 654387 | O13: =SUM(O6:O11) -> 64296 | P13: =SUM(P6:P11) -> 1222906 | Q13: =SUM(Q6:Q11) -> 2033921 | R13: =SUM(R6:R11) -> 2403709 | S13: =SUM(S6:S11) -> 8131333
A15: LIABILITIES AND FUND BALANCES
B16: Liabilities:
C17: Accounts payable | K17: 99341 | L17: 117700 | M17: 22888 | N17: 9411 | O17: 50034 | P17: 70560 | Q17: 31393 | R17: 84928 | S17: =SUM(K17:R17) -> 486255
C18: Unearned revenue | M18: 80554 | R18: 53913 | S18: =SUM(K18:R18) -> 134467
C19: Due to other funds | K19: 4923 | O19: 24829 | R19: 45323 | S19: =SUM(K19:R19) -> 75075
E21: Total liabilities: | K21: =SUM(K17:K19) -> 104264 | L21: =SUM(L17:L19) -> 117700 | M21: =SUM(M17:M19) -> 103442 | N21: =SUM(N17:N19) -> 9411 | O21: =SUM(O17:O19) -> 74863 | P21: =SUM(P17:P19) -> 70560 | Q21: =SUM(Q17:Q19) -> 31393 | R21: =SUM(R17:R19) -> 184164 | S21: =SUM(S17:S19) -> 695797
A23: DEFERRED INFLOWS OF RESOURCES
B24: Unavailable revenue | K24: 19870 | P24: 55725 | Q24: 33057 | R24: 124248 | S24: =SUM(K24:R24) -> 232900
B26: Fund Balances:
C27: Nonspendable - prepaids | K27: 4443 | S27: =SUM(K27:R27) -> 4443
C28: Nonspendable - inventory | R28: 25276 | S28: =SUM(K28:R28) -> 25276
C29: Restricted: | S29: =SUM(K29:R29) -> 0
D30: Judicial | R30: 349325 | S30: =SUM(K30:R30) -> 349325
D31: Other general government | N31: 644976 | S31: =SUM(K31:R31) -> 644976
D32: Public safety | R32: 874 | S32: =SUM(K32:R32) -> 874
D33: Public works | O33: 64248 | P33: 1096621 | Q33: 1969471 | R33: 1350120 | S33: =SUM(K33:R33) -> 4480460
D34: Economic development | R34: 37419 | S34: =SUM(K34:R34) -> 37419
D35: Sanitation | L35: 575216 | S35: =SUM(K35:R35) -> 575216
D36: Capital projects | M36: 158 | R36: 299866 | S36: =SUM(K36:R36) -> 300024
D37: Debt service | R37: 258 | S37: =SUM(K37:R37) -> 258
C38: Committed:
D39: Other general government | R39: 2041 | S39: =SUM(K39:R39) -> 2041
C40: Assigned:
D41: Other general government | R41: 28611 | S41: =SUM(K41:R41) -> 28611
D42: Public works | R42: 8696 | S42: =SUM(K42:R42) -> 8696
C43: Negative unassigned | O43: -74815 | R43: -7189 | S43: =SUM(K43:R43) -> -82004
C44: Unassigned | K44: 827021 | S44: =SUM(K44:R44) -> 827021
E46: Total fund balance: | K46: =SUM(K27:K44) -> 831464 | L46: =SUM(L27:L44) -> 575216 | M46: =SUM(M27:M44) -> 158 | N46: =SUM(N27:N44) -> 644976 | O46: =SUM(O27:O44) -> -10567 | P46: =SUM(P27:P44) -> 1096621 | Q46: =SUM(Q27:Q44) -> 1969471 | R46: =SUM(R27:R44) -> 2095297 | S46: =SUM(S27:S44) -> 7202636
E48: Total liabilities and fund balances: | K48: =K46+K24+K21 -> 955598 | L48: =L46+L24+L21 -> 692916 | M48: =M46+M24+M21 -> 103600 | N48: =N46+N24+N21 -> 654387 | O48: =O46+O24+O21 -> 64296 | P48: =P46+P24+P21 -> 1222906 | Q48: =Q46+Q24+Q21 -> 2033921 | R48: =R46+R24+R21 -> 2403709 | S48: =S46+S24+S21 -> 8131333

Sheet Ascension
D1: Ascension Combined Balance Sheet
D2: Issued: December 31, 2013
K4: General Fund | L4: East Ascension Frainage | M4: Road Project | N4: East Ascension Drainage Project | O4: Other Governmental Funds | P4: Total Governmental Funds
A5: Assets:
B6: Cash and Cash Equivalents | K6: 7650256 | L6: 10698675 | M6: 6271012 | N6: 2126894 | O6: 13491929 | P6: =SUM(K6:O6) -> 40238766
B7: Investments | K7: 13771194 | L7: 17691739 | M7: 10430652 | N7: 27003583 | O7: 20307033 | P7: =SUM(K7:O7) -> 89204201
B8: Accounts receivable, net:
C9: Ad valorem taxes | K9: 3836435 | L9: 4813187 | O9: 17811843 | P9: =SUM(K9:O9) -> 26461465
C10: Sales and use taxes | K10: 2542387 | L10: 1100217 | P10: =SUM(K10:O10) -> 3642604
C11: Other | K11: 729071 | L11: 30829 | M11: 18152 | N11: 53285 | O11: 796566 | P11: =SUM(K11:O11) -> 1627903
B12: Due from other governments:
C13: LA - State revenue sharing | K13: 85184 | L13: 148662 | O13: 705377 | P13: =SUM(K13:O13) -> 939223
C14: LA - Severance | K14: 26535 | P14: =SUM(K14:O14) -> 26535
C15: LA - Beer and Parish Transportation | K15: 17600 | O15: 227167 | P15: =SUM(K15:O15) -> 244767
C16: Grants | K16: 1333304 | L16: 652123 | O16: 1809555 | P16: =SUM(K16:O16) -> 3794982
B17: Due from other funds | K17: 3010 | L17: 117437 | M17: 430455 | O17: 592540 | P17: =SUM(K17:O17) -> 1143442
B18: Prepaid assets | O18: 43968 | P18: =SUM(K18:O18) -> 43968
B19: Other assets | K19: 54900 | L19: 42273 | P19: =SUM(K19:O19) -> 97173
E21: Total assets: | K21: =SUM(K6:K19) -> 30049876 | L21: =SUM(L6:L19) -> 35295142 | M21: =SUM(M6:M19) -> 17150271 | N21: =SUM(N6:N19) -> 29183762 | O21: =SUM(O6:O20) -> 55785978 | P21: =SUM(P6:P19) -> 167465029
A23: LIABILITIES AND FUND BALANCES
B24: Liabilities:
C25: Accounts payable and accrued liabilities | K25: 797442 | L25: 295446 | O25: 642993 | P25: =SUM(K25:O25) -> 1735881
C26: Contracts payable | K26: 22470 | L26: 48195 | M26: 614028 | N26: 2388718 | O26: 906633 | P26: =SUM(K26:O26) -> 3980044
C27: Accrued payroll | K27: 216728 | L27: 76127 | O27: 209360 | P27: =SUM(K27:O27) -> 502215
C28: Deductions from ad valorem taxes:
D29: Contribution to retirement system | K29: 121316 | L29: 159071 | O29: 591388 | P29: =SUM(K29:O29) -> 871775
C30: Due to Other Funds | K30: 1140432 | O30: 3005 | P30: =SUM(K30:O30) -> 1143437
C31: Due to other governments | L31: 269707 | P31: =SUM(K31:O31) -> 269707
C32: Sales tax rebate reserve | K32: 4524981 | P32: =SUM(K32:O32) -> 4524981
E34: Total liabilities: | K34: =SUM(K25:K32) -> 6823369 | L34: =SUM(L25:L32) -> 848546 | M34: =SUM(M25:M32) -> 614028 | N34: =SUM(N25:N32) -> 2388718 | O34: =SUM(O25:O33) -> 2353379 | P34: =SUM(P25:P32) -> 13028040
A36: DEFERRED INFLOWS OF RESOURCES
C37: Grant advances | K37: 133325 | O37: 496532 | P37: =SUM(K37:O37) -> 629857
C38: Unavailable revenues | K38: 13067 | L38: 50978 | O38: 1228120 | P38: =SUM(K38:O38) -> 1292165
E40: Total deferred inflows of resources | K40: =SUM(K37:K38) -> 146392 | L40: =SUM(L37:L38) -> 50978 | M40: =SUM(M37:M38) -> 0 | N40: =SUM(N37:N38) -> 0 | O40: =SUM(O37:O38) -> 1724652 | P40: =SUM(P37:P38) -> 1922022
B42: Fund Balances
C43: Nonspendable | O43: 43968 | P43: =SUM(K43:O43) -> 43968
C44: Restricted for:
D45: Construction of capital assets | N45: 26795044 | O45: 4741219 | P45: =SUM(K45:O45) -> 31536263
D46: Debt service | O46: 2137091 | P46: =SUM(K46:O46) -> 2137091
D47: Fire protection | O47: 13884329 | P47: =SUM(K47:O47) -> 13884329
D48: Drainage maintenance | L48: 29815753 | O48: 1594035 | P48: =SUM(K48:O48) -> 31409788
D49: Health and mental health services | O49: 2351372 | P49: =SUM(K49:O49) -> 2351372
D50: Law enforcement | O50: 130182 | P50: =SUM(K50:O50) -> 130182
D51: Road lighting | O51: 2830126 | P51: =SUM(K51:O51) -> 2830126
D52: Other purposes | K52: 122986 | O52: 2188641 | P52: =SUM(K52:O52) -> 2311627
C53: Committed to:
D54: Construction of capital assets | M54: 16536243 | O54: 6928978 | P54: =SUM(K54:O54) -> 23465221
D55: Culture and recreation | K55: 4942471 | P55: =SUM(K55:O55) -> 4942471
D56: Drainage maintenance | L56: 4579865 | O56: 117353 | P56: =SUM(K56:O56) -> 4697218
D57: Health and mental health services | O57: 4767334 | P57: =SUM(K57:O57) -> 4767334
D58: Law enforcement | K58: 341132 | P58: =SUM(K58:O58) -> 341132
D59: Road lighting | O59: 440244 | P59: =SUM(K59:O59) -> 440244
D60: Other purposes | K60: 897400 | O60: 9553075 | P60: =SUM(K60:O60) -> 10450475
C61: Unassigned | K61: 16776126 | P61: =SUM(K61:O61) -> 16776126
E63: Total fund balance: | K63: =SUM(K43:K61) -> 23080115 | L63: =SUM(L43:L61) -> 34395618 | M63: =SUM(M43:M61) -> 16536243 | N63: =SUM(N43:N61) -> 26795044 | O63: =SUM(O43:O61) -> 51707947 | P63: =SUM(P43:P61) -> 152514967
E65: Total liabilities and fund balances: | K65: =SUM(K63,K34,K40) -> 30049876 | L65: =SUM(L63,L34,L40) -> 35295142 | M65: =SUM(M63,M34,M40) -> 17150271 | N65: =SUM(N63,N34,N40) -> 29183762 | O65: =SUM(O63,O34,O40) -> 55785978 | P65: =SUM(P63,P34,P40) -> 167465029

Sheet Assumption
D1: Assumption Combined Balance Sheet
D2: Issued: December 31, 2013
K4: General | L4: Sales and Use Tax | M4: Solid Waste | N4: Section Eight Housing | O4: LCDBG Disaster Recovery | P4: Office of Emergency Preparedness | Q4: Other Governmental Funds | R4: Total Governmental Funds
A5: Assets:
B6: Cash and Cash Equivalents | K6: 1169651 | L6: 278184 | M6: 212663 | N6: 49165 | P6: 57492 | Q6: 2026649 | R6: =SUM(K6:Q6) -> 3793804
B7: Investments | K7: 4863676 | L7: 1191222 | M7: 905818 | P7: 202778 | Q7: 6692305 | R7: =SUM(K7:Q7) -> 13855799
B8: Receivables | K8: 1037836 | L8: 263060 | M8: 183707 | O8: 72263 | P8: 507955 | Q8: 3056849 | R8: =SUM(K8:Q8) -> 5121670
B9: Due from other funds | K9: 697185 | L9: 2848 | P9: 7724 | Q9: 33996 | R9: =SUM(K9:Q9) -> 741753
B10: Other assets | O10: 21100 | Q10: 6065 | R10: =SUM(K10:Q10) -> 27165
E12: Total assets: | K12: =SUM(K6:K10) -> 7768348 | L12: =SUM(L6:L10) -> 1735314 | M12: =SUM(M6:M10) -> 1302188 | N12: =SUM(N6:N10) -> 49165 | O12: =SUM(O6:O10) -> 93363 | P12: =SUM(P6:P10) -> 775949 | Q12: =SUM(Q6:Q10) -> 11815864 | R12: =SUM(R6:R10) -> 23540191
A14: LIABILITIES AND FUND BALANCES
B15: Liabilities:
C16: Accounts payable | K16: 28944 | L16: 28840 | M16: 272 | N16: 23 | O16: 31597 | P16: 274 | Q16: 587961 | R16: =SUM(K16:Q16) -> 677911
C17: Salaries payable | K17: 17481 | L17: 15698 | O17: 21100 | P17: 8539 | Q17: 76504 | R17: =SUM(K17:Q17) -> 139322
C18: Due to other funds | K18: 8766 | L18: 2371 | O18: 40666 | P18: 650013 | Q18: 39937 | R18: =SUM(K18:Q18) -> 741753
C19: Other liabilities | K19: 165591 | L19: 1703 | N19: 1238 | P19: 430 | Q19: 132264 | R19: =SUM(K19:Q19) -> 301226
E21: Total liabilities: | K21: =SUM(K16:K19) -> 220782 | L21: =SUM(L16:L19) -> 48612 | M21: =SUM(M16:M19) -> 272 | N21: =SUM(N16:N19) -> 1261 | O21: =SUM(O16:O19) -> 93363 | P21: =SUM(P16:P19) -> 659256 | Q21: =SUM(Q16:Q19) -> 836666 | R21: =SUM(R16:R19) -> 1860212
B23: Fund Balances
C24: Restricted | L24: 1686702 | N24: 40774 | Q24: 10503604 | R24: =SUM(K24:Q24) -> 12231080
C25: Assigned | K25: 19345 | M25: 1301916 | N25: 7130 | P25: 116693 | Q25: 475594 | R25: =SUM(K25:Q25) -> 1920678
C26: Unassigned | K26: 7528221 | R26: =SUM(K26:Q26) -> 7528221
E28: Total fund balance: | K28: =SUM(K24:K26) -> 7547566 | L28: =SUM(L24:L26) -> 1686702 | M28: =SUM(M24:M26) -> 1301916 | N28: =SUM(N24:N26) -> 47904 | O28: =SUM(O24:O26) -> 0 | P28: =SUM(P24:P26) -> 116693 | Q28: =SUM(Q24:Q26) -> 10979198 | R28: =SUM(R24:R26) -> 21679979
E30: Total liabilities and fund balances: | K30: =SUM(K28,K21) -> 7768348 | L30: =SUM(L28,L21) -> 1735314 | M30: =SUM(M28,M21) -> 1302188 | N30: =SUM(N28,N21) -> 49165 | O30: =SUM(O28,O21) -> 93363 | P30: =SUM(P21,P28) -> 775949 | Q30: =SUM(Q21,Q28) -> 11815864 | R30: =SUM(R21,R28) -> 23540191

Sheet Avoyelles
D1: Avoyelles Combined Balance Sheet
D2: Issued: December 31, 2013
K5: General | L5: Road & Bridge | M5: Solid Waste | N5: Drainage | O5: Health Unit | P5: Library | Q5: Section 8 | R5: Brudd Construction LCDBG | S5: Other Governmental Funds | T5: Total Governmental Funds
A6: Assets:
B7: Cash and interest-bearing deposits | K7: 666471 | L7: 1028187 | M7: 3132246 | N7: 426259 | O7: 1398435 | P7: 771760 | Q7: 233896 | S7: 150825 | T7: =SUM(K7:S7) -> 7808079
B8: Receivables | K8: 342206 | L8: 184936 | M8: 287174 | N8: 350440 | O8: 400149 | P8: 620385 | S8: 774 | T8: =SUM(K8:S8) -> 2186064
B9: Due from other governmental units | K9: 199650 | N9: 42822 | O9: 49559 | P9: 75840 | R9: 80073 | S9: 6717 | T9: =SUM(K9:S9) -> 454661
B10: Other assets | K10: 23691 | L10: 19602 | M10: 23953 | N10: 15559 | O10: 6465 | P10: 14414 | Q10: 1116 | T10: =SUM(K10:S10) -> 104800
E12: Total Assets: | K12: =SUM(K7:K10) -> 1232018 | L12: =SUM(L7:L10) -> 1232725 | M12: =SUM(M7:M10) -> 3443373 | N12: =SUM(N7:N10) -> 835080 | O12: =SUM(O7:O10) -> 1854608 | P12: =SUM(P7:P10) -> 1482399 | Q12: =SUM(Q7:Q10) -> 235012 | R12: =SUM(R7:R10) -> 80073 | ... T12: =SUM(T7:T10) -> 10553604
A14: DEFERRED OUTFLOWS OF RESOURCES
A16: LIABILITIES AND FUND BALANCES
B17: Liabilities:
C18: Accounts, salaries, and other payables | K18: 161498 | L18: 36204 | M18: 194682 | N18: 30154 | O18: 23931 | P18: 55804 | Q18: 1504 | R18: 75031 | S18: 9335 | T18: =SUM(K18:S18) -> 588143
C19: Deferred revenue | Q19: 36260 | T19: =SUM(K19:S19) -> 36260
C20: Due to other governmental units | Q20: 540 | R20: 5042 | S20: 32321 | T20: =SUM(K20:S20) -> 37903
E22: Total liabilities: | K22: =SUM(K18:K20) -> 161498 | L22: =SUM(L18:L20) -> 36204 | M22: =SUM(M18:M20) -> 194682 | N22: =SUM(N18:N21) -> 30154 | O22: =SUM(O18:O20) -> 23931 | P22: =SUM(P18:P20) -> 55804 | Q22: =SUM(Q18:Q20) -> 38304 | R22: =SUM(R18:R20) -> 80073 | S22: =SUM(S18:S20) -> 41656 | T22: =SUM(T18:T20) -> 662306
A24: DEFERRED INFLOWS OF RESOURCES
B26: Fund Balances
C27: Nonspendable | K27: 23691 | L27: 19602 | M27: 23953 | N27: 15559 | O27: 6465 | P27: 14414 | Q27: 1116 | T27: =SUM(K27:S27) -> 104800
C28: Restricted | L28: 1176919 | M28: 3224738 | N28: 789367 | O28: 1824212 | P28: 1412181 | Q28: 195592 | S28: 116660 | T28: =SUM(K28:S28) -> 8739669
C29: Unassigned | K29: 1046829 | T29: =SUM(K29:S29) -> 1046829
E31: Total fund balance: | K31: =SUM(K27:K30) -> 1070520 | L31: =SUM(L27:L29) -> 1196521 | M31: =SUM(M27:M29) -> 3248691 | N31: =SUM(N27:N29) -> 804926 | O31: =SUM(O27:O29) -> 1830677 | P31: =SUM(P27:P29) -> 1426595 | Q31: =SUM(Q27:Q29) -> 196708 | R31: =SUM(R27:R29) -> 0 | S31: =SUM(S27:S29) -> 116660 | T31: =SUM(T27:T29) -> 9891298
E33: Total liabilities and fund balances: | K33: =SUM(K31,K22) -> 1232018 | L33: =SUM(L22,L31) -> 1232725 | M33: =SUM(M22,M31) -> 3443373 | N33: =SUM(N22,N31) -> 835080 | O33: =SUM(O31+O22) -> 1854608 | P33: =SUM(P31+P22) -> 1482399 | Q33: =SUM(Q31+Q22) -> 235012 | R33: =SUM(R31+R22) -> 80073 | S33: =SUM(S31+S22) -> 158316 | T33: =SUM(T31+T22) -> 10553604

Sheet Beauregard
D1: Beauregard Combined Balance Sheet
D2: Issued: December 31, 2013
K4: General Fund | L4: Parishwide Road Special Revenue | M4: Road District No. 6 Special Revenue | N4: Sales Tax District No. 1 Special Revenue | O4: Health Unit Special Revenue | P4: Criminal Court Special Revenue | Q4: South Beau. Rec. Dist. No. 2 Special Revenue | R4: South Beau. Rec. Dist. No. 2 Capital Projects | S4: Nonmajor Governmental Funds | T4: Total Governmental Funds
A5: Assets:
B6: Equity in pooled cash | K6: 630917 | L6: 874419 | M6: 1310997 | N6: 3003371 | O6: 1952781 | P6: 1216 | Q6: 702741 | R6: 1350098 | S6: 5031826 | T6: =SUM(K6:S6) -> 14858366
B7: Receivables | K7: 1081445 | L7: 42651 | M7: 947010 | N7: 390403 | O7: 548293 | P7: 66507 | Q7: 540009 | S7: 2868443 | T7: =SUM(K7:S7) -> 6484761
B8: Interfund receivable | K8: 58266 | L8: 11404 | R8: 25603 | T8: =SUM(K8:S8) -> 95273
B9: Inventory | K9: 32875 | M9: 27795 | S9: 253133 | T9: =SUM(K9:S9) -> 313803
E11: Total assets: | K11: =SUM(K6:K9) -> 1803503 | L11: =SUM(L6:L9) -> 928474 | M11: =SUM(M6:M9) -> 2285802 | N11: =SUM(N6:N9) -> 3393774 | O11: =SUM(O6:O9) -> 2501074 | P11: =SUM(P6:P9) -> 67723 | Q11: =SUM(Q6:Q9) -> 1242750 | R11: =SUM(R6:R9) -> 1375701 | ... T11: =SUM(T6:T9) -> 21752203
A13: LIABILITIES AND FUND BALANCES
B14: Liabilities:
C15: Accounts payable | K15: 188832 | L15: 21559 | M15: 35677 | N15: 118771 | O15: 19707 | P15: 16838 | Q15: 82909 | R15: 39354 | S15: 160864 | T15: =SUM(K15:S15) -> 684511
C16: Payroll liabilities | K16: 164679 | T16: =SUM(K16:S16) -> 164679
C17: Interfund payable | P17: 39041 | Q17: 25603 | S17: 30629 | T17: =SUM(K17:S17) -> 95273
E19: Total liabilities: | K19: =SUM(K15:K17) -> 353511 | L19: =SUM(L15:L17) -> 21559 | M19: =SUM(M15:M17) -> 35677 | N19: =SUM(N15:N17) -> 118771 | O19: =SUM(O15:O17) -> 19707 | P19: =SUM(P15:P17) -> 55879 | Q19: =SUM(Q15:Q17) -> 108512 | R19: =SUM(R15:R17) -> 39354 | ... T19: =SUM(T15:T17) -> 944463
A21: DEFERRED INFLOWS OF RESOURCES
B22: Unavailable revenue | K22: 44721 | M22: 20738 | O22: 18269 | Q22: 8081 | S22: 103534 | T22: =SUM(K22:S22) -> 195343
B24: Fund Balances:
C25: Nonspendable - inventory | K25: 32875 | M25: 27795 | S25: 253133 | T25: =SUM(K25:S25) -> 313803
C26: Restricted:
D27: Purchases of equipment | L27: 324072 | T27: =SUM(K27:S27) -> 324072
D28: Public safety | S28: 1810976 | T28: =SUM(K28:S28) -> 1810976
D29: Public works | L29: 582843 | M29: 2201592 | S29: 3608240 | T29: =SUM(K29:S29) -> 6392675
D30: Health and welfare | O30: 2463098 | T30: =SUM(K30:S30) -> 2463098
D31: Culture and recreation | S31: 607692 | T31: =SUM(K31:S31) -> 607692
D32: Sanitation | N32: 3275003 | T32: =SUM(K32:S32) -> 3275003
D33: Other general government | S33: 136917 | T33: =SUM(K33:S33) -> 136917
D34: Capital projects | S34: 1275201 | T34: =SUM(K34:S34) -> 1275201
D35: Debt service | S35: 166216 | T35: =SUM(K35:S35) -> 166216
C36: Unassigned | K36: 1372396 | P36: 11844 | Q36: 1126157 | R36: 1336347 | T36: =SUM(K36:S36) -> 3846744
E38: Total fund balance: | K38: =SUM(K25:K36) -> 1405271 | L38: =SUM(L25:L36) -> 906915 | M38: =SUM(M25:M36) -> 2229387 | N38: =SUM(N25:N36) -> 3275003 | O38: =SUM(O25:O36) -> 2463098 | P38: =SUM(P25:P36) -> 11844 | Q38: =SUM(Q25:Q36) -> 1126157 | R38: =SUM(R25:R36) -> 1336347 | ... T38: =SUM(T25:T36) -> 20612397
E40: Total liabilities and fund balances: | K40: =K38+K22+K19 -> 1803503 | L40: =L38+L22+L19 -> 928474 | M40: =M38+M22+M19 -> 2285802 | N40: =N38+N22+N19 -> 3393774 | O40: =O38+O22+O19 -> 2501074 | P40: =P38+P22+P19 -> 67723 | Q40: =Q38+Q22+Q19 -> 1242750 | R40: =R38+R22+R19 -> 1375701 | ... T40: =T38+T22+T19 -> 21752203

Sheet Bienville
D1: Bienville Combined Balance Sheet
D2: Issued: December 31, 2013
K5: General | L5: Road Maintenance | M5: Solid Waste | N5: Construction Fund | O5: Debt Service Fund | P5: CDBG Fund | Q5: Other Governmental Funds | R5: Total Governmental Funds
A6: Assets:
B7: Cash and equivalents | K7: 4224843 | L7: 8417207 | M7: 3571253 | N7: 10786 | O7: 752937 | P7: 16 | Q7: 247299 | R7: =SUM(K7:Q7) -> 17224341
B8: Receivables | K8: 1912568 | L8: 2022233 | M8: 279239 | O8: 1182712 | P8: 44464 | Q8: 7190 | R8: =SUM(K8:Q8) -> 5448406
E10: Total Assets: | K10: =SUM(K7:K8) -> 6137411 | L10: =SUM(L7:L8) -> 10439440 | M10: =SUM(M7:M8) -> 3850492 | N10: =SUM(N7:N8) -> 10786 | O10: =SUM(O7:O8) -> 1935649 | P10: =SUM(P7:P8) -> 44480 | Q10: =SUM(Q7:Q8) -> 254489 | R10: =SUM(R7:R8) -> 22672747
A12: LIABILITIES AND FUND BALANCES
B13: Liabilities:
C14: Accounts payable | K14: 74312 | L14: 41142 | M14: 89788 | P14: 44464 | R14: =SUM(K14:Q14) -> 249706
C15: Salaries and related payable | K15: 4993 | L15: 17633 | R15: =SUM(K15:Q15) -> 22626
C16: Deferred revenues | K16: 70000 | R16: =SUM(K16:Q16) -> 70000
E18: Total liabilities: | K18: =SUM(K14:K16) -> 149305 | L18: =SUM(L14:L16) -> 58775 | M18: =SUM(M14:M16) -> 89788 | N18: =SUM(N14:N16) -> 0 | O18: =SUM(O14:O16) -> 0 | P18: =SUM(P14:P16) -> 44464 | Q18: =SUM(Q14:Q16) -> 0 | R18: =SUM(R14:R16) -> 342332
B20: Fund Balances
C21: Non Spendable | P21: 16 | R21: =SUM(K21:Q21) -> 16
C22: Restricted:
D23: Other general government | Q23: 124851 | R23: =SUM(K23:Q23) -> 124851
D24: Public works | L24: 10380665 | Q24: 14456 | R24: =SUM(K24:Q24) -> 10395121
D25: Health & welfare | Q25: 68320 | R25: =SUM(K25:Q25) -> 68320
D26: Economic development | Q26: 46862 | R26: =SUM(K26:Q26) -> 46862
C27: Assigned | M27: 3760704 | N27: 10786 | O27: 1935649 | R27: =SUM(K27:Q27) -> 5707139
C28: Unassigned | K28: 5988106 | R28: =SUM(K28:Q28) -> 5988106
E30: Total fund balance: | K30: =SUM(K21:K28) -> 5988106 | L30: =SUM(L21:L28) -> 10380665 | M30: =SUM(M21:M28) -> 3760704 | N30: =SUM(N21:N28) -> 10786 | O30: =SUM(O21:O28) -> 1935649 | P30: =SUM(P21:P28) -> 16 | Q30: =SUM(Q21:Q28) -> 254489 | R30: =SUM(R21:R28) -> 22330415
E32: Total liabilities and fund balances: | K32: =SUM(K30,K18) -> 6137411 | L32: =SUM(L18,L30) -> 10439440 | M32: =SUM(M18,M30) -> 3850492 | N32: =SUM(N18,N30) -> 10786 | O32: =SUM(O30+O18) -> 1935649 | P32: =SUM(P30+P18) -> 44480 | Q32: =SUM(Q30+Q18) -> 254489 | R32: =SUM(R30+R18) -> 22672747

Sheet Bossier
D1: Bossier Combined Balance Sheet
D2: Issued: December 31, 2013
K5: General | L5: Highway | M5: Library | N5: Capital Improvements | O5: LCDA Sewer Construction | P5: Other Governmental Funds | Q5: Total Governmental Funds
A6: Assets:
B7: Cash and cash equivalents | K7: 3553861 | L7: 3586860 | M7: 7489233 | N7: 6706530 | O7: 240534 | P7: 15129338 | Q7: =SUM(K7:P7) -> 36706356
B8: Receivables | K8: 2732041 | L8: 3144974 | M8: 6974940 | N8: 863968 | O8: 46698 | P8: 4077264 | Q8: =SUM(K8:P8) -> 17839885
B9: Restricted cash | O9: 3245700 | P9: 1889644 | Q9: =SUM(K9:P9) -> 5135344
B10: Due from other fund | K10: 129211 | P10: 6373 | Q10: =SUM(K10:P10) -> 135584
B11: Advance to Waterworks/Sewer District | O11: 8185472 | Q11: =SUM(K11:P11) -> 8185472
E13: Total Assets: | K13: =SUM(K7:K11) -> 6415113 | L13: =SUM(L7:L11) -> 6731834 | M13: =SUM(M7:M11) -> 14464173 | N13: =SUM(N7:N11) -> 7570498 | O13: =SUM(O7:O11) -> 11718404 | P13: =SUM(P7:P11) -> 21102619 | Q13: =SUM(Q7:Q11) -> 68002641
A15: LIABILITIES AND FUND BALANCES
B16: Liabilities:
C17: Accounts payable | K17: 309582 | L17: 681792 | M17: 413737 | N17: 57397 | O17: 134440 | P17: 808819 | Q17: =SUM(K17:P17) -> 2405767
C18: Due to other funds | K18: 6373 | L18: 55782 | N18: 11300 | P18: 62129 | Q18: =SUM(K18:P18) -> 135584
E20: Total liabilities: | K20: =SUM(K17:K18) -> 315955 | L20: =SUM(L17:L18) -> 737574 | M20: =SUM(M17:M18) -> 413737 | N20: =SUM(N17:N18) -> 68697 | O20: =SUM(O17:O18) -> 134440 | P20: =SUM(P17:P18) -> 870948 | Q20: =SUM(Q17:Q18) -> 2541351
A22: DEFERRED INFLOWS OF RESROUCES
B23: Unavailable revenue:
C24: Property taxes | K24: 89511 | L24: 110685 | M24: 416912 | P24: 210825 | Q24: =SUM(K24:P24) -> 827933
C25: Other | K25: 127732 | L25: 199365 | M25: 115229 | P25: 420391 | Q25: =SUM(K25:P25) -> 862717
E27: Total deferred inflows of resources: | K27: =SUM(K24:K25) -> 217243 | L27: =SUM(L24:L25) -> 310050 | M27: =SUM(M24:M25) -> 532141 | N27: =SUM(N24:N26) -> 0 | O27: =SUM(O24:O25) -> 0 | P27: =SUM(P24:P25) -> 631216 | Q27: =SUM(Q24:Q25) -> 1690650
B29: Fund Balances
C30: Nonspendable | O30: 8185472 | Q30: =SUM(K30:P30) -> 8185472
C31: Restricted | M31: 13233707 | N31: 7367576 | O31: 3398492 | P31: 10772365 | Q31: =SUM(K31:P31) -> 34772140
C32: Assigned | K32: 2285906 | L32: 5684210 | M32: 284588 | N32: 134226 | P32: 8889950 | Q32: =SUM(K32:P32) -> 17278880
C33: Unassigned | K33: 3596009 | P33: -61860 | Q33: =SUM(K33:P33) -> 3534149
E35: Total fund balance: | K35: =SUM(K30:K33) -> 5881915 | L35: =SUM(L30:L33) -> 5684210 | M35: =SUM(M30:M33) -> 13518295 | N35: =SUM(N30:N33) -> 7501802 | O35: =SUM(O30:O33) -> 11583964 | P35: =SUM(P30:P33) -> 19600455 | Q35: =SUM(Q30:Q33) -> 63770641
E37: Total liabilities and fund balances: | K37: =SUM(K35,K20,K27) -> 6415113 | L37: =SUM(L35,L20,L27) -> 6731834 | M37: =SUM(M35,M20,M27) -> 14464173 | N37: =SUM(N35,N20,N27) -> 7570499 | O37: =SUM(O35,O20,O27) -> 11718404 | P37: =SUM(P35,P20,P27) -> 21102619 | Q37: =SUM(Q35,Q20,Q27) -> 68002642

Sheet Caddo
D1: Caddo Combined Balance Sheet
D2: Issued: December 31, 2013
K4: General Fund | L4: Shreve Memorial Library Fund | M4: Detention Facilities Fund | N4: Solid Waste Disposal Fund | O4: Public Works Fund | P4: Head Start Fund | Q4: Biomedical Fund | R4: Capital Outlay Fund | S4: Criminal Justice Fund | T4: Other Governmental Funds | U4: Total Governmental Funds
A5: Assets:
B6: Cash and cash equivalents | K6: 4590414 | L6: 3286688 | M6: 64920 | N6: 1942202 | O6: 1145700 | R6: 1568910 | T6: 3319307 | U6: =SUM(K6:T6) -> 15918141
B7: Investments | K7: 41057969 | M7: 583805 | N7: 17369431 | O7: 10242821 | R7: 14025541 | T7: 29659730 | U7: =SUM(K7:T7) -> 112939297
B8: Receivables, net:
C9: Ad valorem taxes | K9: 6184670 | L9: 13778148 | M9: 7855428 | O9: 5773733 | Q9: 2604426 | S9: 5150541 | T9: 13965173 | U9: =SUM(K9:T9) -> 55312119
C10: Paving assessments | O10: 170000 | U10: =SUM(K10:T10) -> 170000
C11: Other | K11: 29642 | M11: 156 | N11: 211985 | O11: 455821 | T11: 437966 | U11: =SUM(K11:T11) -> 1135570
C12: Accrued interest | K12: 144136 | M12: 2037 | N12: 60984 | O12: 35970 | R12: 49263 | T12: 104216 | U12: =SUM(K12:T12) -> 396606
B13: Due from other funds | K13: 1136576 | L13: 200521 | M13: 109628 | N13: 409147 | O13: 448368 | R13: 627700 | T13: 1821958 | U13: =SUM(K13:T13) -> 4753898
B14: Due from other governments | K14: 212255 | L14: 258244 | M14: 161219 | N14: 179788 | O14: 705921 | Q14: 49004 | S14: 103002 | T14: 495034 | U14: =SUM(K14:T14) -> 2164467
B15: Inventories | O15: 82196 | U15: =SUM(K15:T15) -> 82196
B16: Other assets | L16: 112394 | U16: =SUM(K16:T16) -> 112394
E18: Total assets: | K18: =SUM(K6:K16) -> 53355662 | L18: =SUM(L6:L16) -> 17635995 | M18: =SUM(M6:M16) -> 8777193 | N18: =SUM(N6:N16) -> 20173537 | O18: =SUM(O6:O16) -> 19060530 | P18: =SUM(P6:P16) -> 0 | Q18: =SUM(Q6:Q16) -> 2653430 | R18: =SUM(R6:R16) -> 16271414 | ... U18: =SUM(U6:U16) -> 192984688
A20: LIABILITIES AND FUND BALANCES
B21: Liabilities:
C22: Accounts payable | K22: 130305 | L22: 412443 | M22: 181041 | N22: 163437 | O22: 258881 | R22: 1000244 | T22: 588645 | U22: =SUM(K22:T22) -> 2734996
C23: Accrued liabilities | K23: 139340 | L23: 219860 | M23: 25174 | N23: 44408 | O23: 136523 | T23: 330930 | U23: =SUM(K23:T23) -> 896235
C24: Retainage payable | R24: 779557 | U24: =SUM(K24:T24) -> 779557
C25: Due to other funds | Q25: 1913254 | S25: 2771732 | T25: 68912 | U25: =SUM(K25:T25) -> 4753898
C26: Unearned revenue | K26: 73941 | O26: 100 | T26: 8954 | U26: =SUM(K26:T26) -> 82995
C27: Due to component units | M27: 859366 | U27: =SUM(K27:T27) -> 859366
C28: Due to other governments | K28: 4906 | N28: 2596 | O28: 46297 | S28: 430133 | T28: 71053 | U28: =SUM(K28:T28) -> 554985
E30: Total liabilities: | K30: =SUM(K22:K28) -> 348492 | L30: =SUM(L22:L28) -> 632303 | M30: =SUM(M22:M28) -> 1065581 | N30: =SUM(N22:N28) -> 210441 | O30: =SUM(O22:O28) -> 441801 | P30: =SUM(P22:P28) -> 0 | Q30: =SUM(Q22:Q28) -> 1913254 | R30: =SUM(R22:R28) -> 1779801 | ... U30: =SUM(U22:U28) -> 10662032
A32: DEFERRED INFLOWS OF RESOURCES
B33: Unavailable revenue - property taxes | K33: 53502 | L33: 35574 | M33: 26261 | O33: 2234 | S33: 1663 | T33: 31830 | U33: =SUM(K33:T33) -> 151064
B34: Unavailable revenue - special assessments | O34: 62293 | U34: =SUM(K34:T34) -> 62293
E36: Total deferred inflows: | K36: =SUM(K33:K34) -> 53502 | L36: =SUM(L33:L34) -> 35574 | M36: =SUM(M33:M34) -> 26261 | N36: =SUM(N33:N34) -> 0 | O36: =SUM(O33:O34) -> 64527 | P36: =SUM(P33:P34) -> 0 | Q36: =SUM(Q33:Q34) -> 0 | R36: =SUM(R33:R34) -> 0 | ... U36: =SUM(U33:U34) -> 213357
B38: Fund Balances:
C39: Nonspendable:
D40: Prepaid expenses | L40: 112394 | U40: =SUM(K40:T40) -> 112394
C41: Restricted for:
D42: Criminal justice | M42: 7685351 | S42: 1953089 | T42: 3119183 | U42: =SUM(K42:T42) -> 12757623
D43: Health and welfare | T43: 4310288 | U43: =SUM(K43:T43) -> 4310288
D44: Highways, streets and drainage | O44: 18418298 | U44: =SUM(K44:T44) -> 18418298
D45: Building facilities | T45: 7551677 | U45: =SUM(K45:T45) -> 7551677
D46: Sanitation | N46: 19963096 | U46: =SUM(K46:T46) -> 19963096
D47: Culture and recreation | L47: 16855724 | T47: 2954148 | U47: =SUM(K47:T47) -> 19809872
D48: Economic development | Q48: 666506 | U48: =SUM(K48:T48) -> 666506
D49: Debt service | T49: 2960859 | U49: =SUM(K49:T49) -> 2960859
D50: Capital projects | R50: 14491613 | T50: 14657797 | U50: =SUM(K50:T50) -> 29149410
C51: Committed to:
D52: Contingencies | K52: 36963755 | U52: =SUM(K52:T52) -> 36963755
D53: Economic development | T53: 645202 | U53: =SUM(K53:T53) -> 645202
D54: Subsequent year's expenditures | O54: 135904 | Q54: 73670 | S54: 96926 | T54: 2131374 | U54: =SUM(K54:T54) -> 2437874
C55: Assigned to:
D56: Special services | K56: 6046 | T56: 10372532 | U56: =SUM(K56:T56) -> 10378578
D57: Future claims | K57: 600000 | U57: =SUM(K57:T57) -> 600000
C58: Unassigned | K58: 15383867 | U58: =SUM(K58:T58) -> 15383867
E60: Total fund balance: | K60: =SUM(K39:K58) -> 52953668 | L60: =SUM(L39:L58) -> 16968118 | M60: =SUM(M39:M58) -> 7685351 | N60: =SUM(N39:N58) -> 19963096 | O60: =SUM(O39:O58) -> 18554202 | P60: =SUM(P39:P58) -> 0 | Q60: =SUM(Q39:Q58) -> 740176 | R60: =SUM(R39:R58) -> 14491613 | ... U60: =SUM(U39:U58) -> 182109299
E62: Total liabilities and fund balances: | K62: =K60+K36+K30 -> 53355662 | L62: =L60+L36+L30 -> 17635995 | M62: =M60+M36+M30 -> 8777193 | N62: =N60+N36+N30 -> 20173537 | O62: =O60+O36+O30 -> 19060530 | P62: =P60+P36+P30 -> 0 | Q62: =Q60+Q36+Q30 -> 2653430 | R62: =R60+R36+R30 -> 16271414 | ... U62: =U60+U36+U30 -> 192984688

Sheet Calcasieu
D1: Calcasieu Combined Balance Sheet
D2: Issued: December 31, 2013
K4: General Fund | L4: Public Works Operating Fund | M4: Calcasieu Parish Library Fund | N4: Road Capital Improvement Fund | O4: Other Governmental Funds | P4: Total Governmental Funds
A5: Assets:
B6: Cash and Cash Equivalents | K6: 14067607 | L6: 7166488 | M6: 1171331 | N6: 24479124 | O6: 12610292 | P6: =SUM(K6:O6) -> 59494842
B7: Investments | K7: 43137940 | L7: 23116500 | M7: 3780323 | N7: 78964727 | O7: 38215571 | P7: =SUM(K7:O7) -> 187215061
B8: Receivable (net of allowance for uncollectibles):
C9: Property taxes | K9: 10322837 | M9: 9388259 | N9: 4743635 | O9: 21860013 | P9: =SUM(K9:O9) -> 46314744
C10: Sales taxes | L10: 900763 | N10: 1697729 | O10: 623673 | P10: =SUM(K10:O10) -> 3222165
C11: Franchise taxes | K11: 303886 | P11: =SUM(K11:O11) -> 303886
B12: Interest receivable | K12: 86114 | L12: 41635 | M12: 8380 | N12: 142478 | O12: 69709 | P12: =SUM(K12:O12) -> 348316
B13: Intergovernmental receivable | K13: 290120 | L13: 47016 | N13: 149595 | O13: 5226734 | P13: =SUM(K13:O13) -> 5713465
B14: Due from other funds | K14: 1916165 | O14: 70691 | P14: =SUM(K14:O14) -> 1986856
B15: Due from component units | K15: 82064 | L15: 140834 | P15: =SUM(K15:O15) -> 222898
B16: Loans receivable | K16: 48138 | P16: =SUM(K16:O16) -> 48138
B17: Prepaid items | K17: 201 | O17: 64299 | P17: =SUM(K17:O17) -> 64500
B18: Other receivables | K18: 3439616 | L18: 4179 | M18: 25002 | O18: 467401 | P18: =SUM(K18:O18) -> 3936198
B19: Inventory | L19: 726865 | O19: 365836 | P19: =SUM(K19:O19) -> 1092701
E21: Total assets: | K21: =SUM(K6:K19) -> 73694688 | L21: =SUM(L6:L19) -> 32144280 | M21: =SUM(M6:M19) -> 14373295 | N21: =SUM(N6:N19) -> 110177288 | O21: =SUM(O6:O19) -> 79574219 | P21: =SUM(P6:P19) -> 309963770
A23: LIABILITIES AND FUND BALANCES
B24: Liabilities:
C25: Accounts payable | K25: 1461786 | L25: 306028 | M25: 244155 | N25: 1048785 | O25: 3024293 | P25: =SUM(K25:O25) -> 6085047
C26: Accrued liabilities | K26: 244277 | L26: 187080 | M26: 112619 | O26: 261884 | P26: =SUM(K26:O26) -> 805860
C27: Intergovernmental payable | K27: 73382 | L27: 826 | O27: 304917 | P27: =SUM(K27:O27) -> 379125
C28: Due to other funds | K28: 58606 | O28: 1987476 | P28: =SUM(K28:O28) -> 2046082
C29: Due to component units | L29: 3494 | O29: 173042 | P29: =SUM(K29:O29) -> 176536
C30: Unearned revenue | O30: 1097584 | P30: =SUM(K30:O30) -> 1097584
C31: Retainage payable | L31: 12532 | M31: 5780 | N31: 978108 | O31: 248817 | P31: =SUM(K31:O31) -> 1245237
C32: Enterprise zone rebate liability | L32: 394200 | P32: =SUM(K32:O32) -> 394200
C33: Other liabilities | K33: 86366 | L33: 1120 | O33: 50315 | P33: =SUM(K33:O33) -> 137801
E35: Total liabilities: | K35: =SUM(K25:K33) -> 1924417 | L35: =SUM(L25:L33) -> 905280 | M35: =SUM(M25:M33) -> 362554 | N35: =SUM(N25:N33) -> 2026893 | O35: =SUM(O25:O33) -> 7148328 | P35: =SUM(P25:P33) -> 12367472
A37: DEFERRED INFLOWS OF RESOURCES
C38: Unavailable revenue | K38: 10947710 | M38: 9456106 | N38: 4785105 | O38: 22397566 | P38: =SUM(K38:O38) -> 47586487
E40: Total deferred inflows of resources | K40: =SUM(K38:K38) -> 10947710 | L40: =SUM(L38:L38) -> 0 | M40: =SUM(M38:M38) -> 9456106 | N40: =SUM(N38:N38) -> 4785105 | O40: =SUM(O38:O38) -> 22397566 | P40: =SUM(P38:P38) -> 47586487
B42: Fund Balances
C43: Nonspendable:
D44: Prepaid items | K44: 201 | O44: 64214 | P44: =SUM(K44:O44) -> 64415
D45: Inventories | L45: 726865 | O45: 365836 | P45: =SUM(K45:O45) -> 1092701
D46: Component unit - long term receivable | K46: 26195 | P46: =SUM(K46:O46) -> 26195
D47: Loans receivable | K47: 33189 | P47: =SUM(K47:O47) -> 33189
C48: Restricted:
D49: Agriculture and community services | K49: 569470 | P49: =SUM(K49:O49) -> 569470
D50: Public works operations | L50: 30512135 | P50: =SUM(K50:O50) -> 30512135
D51: Library purposes | M51: 4554635 | P51: =SUM(K51:O51) -> 4554635
D52: Roads and infrastructure | N52: 103365290 | P52: =SUM(K52:O52) -> 103365290
D53: Other restrictions | O53: 36554527 | P53: =SUM(K53:O53) -> 36554527
C54: Assigned:
D55: Animal services | K55: 78725 | P55: =SUM(K55:O55) -> 78725
D56: Parks operations | K56: 587465 | P56: =SUM(K56:O56) -> 587465
D57: Training center operations | K57: 373322 | P57: =SUM(K57:O57) -> 373322
D58: Future capital needs | K58: 13909837 | O58: 13069259 | P58: =SUM(K58:O58) -> 26979096
D59: Matching funds for capital grants | K59: 10663729 | P59: =SUM(K59:O59) -> 10663729
D60: Major infrastructure | K60: 5175000 | P60: =SUM(K60:O60) -> 5175000
D61: Cooperative endeavor agreements | K61: 1435743 | P61: =SUM(K61:O61) -> 1435743
C62: Unassigned | K62: 27969685 | O62: -25511 | P62: =SUM(K62:O62) -> 27944174
E64: Total fund balances: | K64: =SUM(K44:K62) -> 60822561 | L64: =SUM(L44:L62) -> 31239000 | M64: =SUM(M44:M62) -> 4554635 | N64: =SUM(N44:N62) -> 103365290 | O64: =SUM(O44:O62) -> 50028325 | P64: =SUM(P44:P62) -> 250009811
E66: Total liabilities and fund balances: | K66: =SUM(K64,K35,K40) -> 73694688 | L66: =SUM(L64,L35,L40) -> 32144280 | M66: =SUM(M64,M35,M40) -> 14373295 | N66: =SUM(N64,N35,N40) -> 110177288 | O66: =SUM(O64,O35,O40) -> 79574219 | P66: =SUM(P64,P35,P40) -> 309963770

Sheet Caldwell
D1: Caldwell Combined Balance Sheet
D2: Issued: December 31, 2013
K5: General | L5: Road Maintenance | M5: Recreation | N5: Solid Waste | O5: Blacktop Road | P5: Bayou Dechene Reservoir | Q5: LCDBG | R5: Other Governmental Funds | S5: Total Governmental Funds
A6: Assets:
B7: Cash and equivalents | K7: 1153518 | L7: 257017 | M7: 600892 | N7: 1820469 | O7: 1304493 | P7: 47545 | Q7: 40 | R7: 1298113 | S7: =SUM(K7:R7) -> 6482087
B8: Receivables | K8: 411401 | L8: 541089 | M8: 312565 | N8: 113245 | R8: 600285 | S8: =SUM(K8:R8) -> 1978585
B9: Due from other funds | K9: 2700 | L9: 25652 | R9: 36402 | S9: =SUM(K9:R9) -> 64754
E11: Total Assets: | K11: =SUM(K7:K9) -> 1567619 | L11: =SUM(L7:L9) -> 823758 | M11: =SUM(M7:M9) -> 913457 | N11: =SUM(N7:N9) -> 1933714 | O11: =SUM(O7:O9) -> 1304493 | P11: =SUM(P7:P9) -> 47545 | Q11: =SUM(Q7:Q9) -> 40 | R11: =SUM(R7:R9) -> 1934800 | S11: =SUM(S7:S9) -> 8525426
A13: LIABILITIES AND FUND BALANCES
B14: Liabilities:
C15: Accounts payable | K15: 39554 | L15: 21784 | M15: 15326 | O15: 12251 | R15: 28567 | S15: =SUM(K15:R15) -> 117482
C16: Salaries and related payable | K16: 14464 | L16: 12121 | M16: 1913 | R16: 6581 | S16: =SUM(K16:R16) -> 35079
C17: Due to other agencies | K17: 57698 | S17: =SUM(K17:R17) -> 57698
C18: Due to other funds | K18: 62054 | L18: 2700 | S18: =SUM(K18:R18) -> 64754
E20: Total liabilities: | K20: =SUM(K15:K18) -> 173770 | L20: =SUM(L15:L18) -> 36605 | M20: =SUM(M15:M18) -> 17239 | N20: =SUM(N15:N18) -> 0 | O20: =SUM(O15:O18) -> 12251 | P20: =SUM(P15:P18) -> 0 | Q20: =SUM(Q15:Q18) -> 0 | R20: =SUM(R15:R18) -> 35148 | S20: =SUM(S15:S18) -> 275013
B22: Fund Balances
C23: Unassigned | K23: 1393849 | S23: =SUM(K23:R23) -> 1393849
C24: Restricted | L24: 787153 | M24: 896218 | N24: 1933714 | O24: 1292242 | P24: 47545 | Q24: 40 | R24: 1899652 | S24: =SUM(K24:R24) -> 6856564
E26: Total fund balance: | K26: =SUM(K23:K24) -> 1393849 | L26: =SUM(L23:L24) -> 787153 | M26: =SUM(M23:M24) -> 896218 | N26: =SUM(N23:N24) -> 1933714 | O26: =SUM(O23:O24) -> 1292242 | P26: =SUM(P23:P24) -> 47545 | Q26: =SUM(Q23:Q24) -> 40 | R26: =SUM(R23:R24) -> 1899652 | S26: =SUM(S23:S24) -> 8250413
E28: Total liabilities and fund balances: | K28: =SUM(K26,K20) -> 1567619 | L28: =SUM(L20,L26) -> 823758 | M28: =SUM(M20,M26) -> 913457 | N28: =SUM(N20,N26) -> 1933714 | O28: =SUM(O26+O20) -> 1304493 | P28: =SUM(P26+P20) -> 47545 | Q28: =SUM(Q26+Q20) -> 40 | R28: =SUM(R26+R20) -> 1934800 | S28: =SUM(S26+S20) -> 8525426

Sheet Cameron
D1: Cameron Combined Balance Sheet
D2: Issued: December 31, 2013
K4: General Fund | L4: Road and Bridge Maintenance | M4: Long-Term Community Recovery | N4: Other Governmental Funds | O4: Total Governmental Funds
A5: Assets:
B6: Cash | K6: 10742848 | L6: -13706 | M6: 100 | N6: 17366412 | O6: =SUM(K6:N6) -> 28095654
B7: Receivables, net | K7: 11324586 | L7: 1613896 | M7: 2989883 | N7: 4002464 | O7: =SUM(K7:N7) -> 19930829
B8: Inventory, at cost | K8: 1793767 | L8: 45788 | O8: =SUM(K8:N8) -> 1839555
B9: Other assets | K9: 21195 | L9: 40364 | N9: 23595 | O9: =SUM(K9:N9) -> 85154
B10: Interfund receivables | K10: 5596860 | L10: 534197 | N10: 4120692 | O10: =SUM(K10:N10) -> 10251749
E12: Total assets: | K12: =SUM(K6:K10) -> 29479256 | L12: =SUM(L6:L10) -> 2220539 | M12: =SUM(M6:M10) -> 2989983 | N12: =SUM(N6:N10) -> 25513163 | O12: =SUM(O6:O10) -> 60202941
A14: DEFERRED OUTFLOWS OF RESOURCES
A16: LIABILITIES AND FUND BALANCES
B17: Liabilities:
C18: Accounts, salaries, and other payables | K18: 1493747 | L18: 136088 | M18: 2682682 | N18: 298003 | O18: =SUM(K18:N18) -> 4610520
C19: Due to other agencies | K19: 3695066 | O19: =SUM(K19:N19) -> 3695066
C20: Unearned revenues | K20: 7413 | M20: 9818 | O20: =SUM(K20:N20) -> 17231
C21: Interfund payables | K21: 4654889 | M21: 2073564 | N21: 3523296 | O21: =SUM(K21:N21) -> 10251749
E23: Total liabilities: | K23: =SUM(K18:K21) -> 9851115 | L23: =SUM(L18:L21) -> 136088 | M23: =SUM(M18:M21) -> 4766064 | N23: =SUM(N18:N21) -> 3821299 | O23: =SUM(O18:O21) -> 18574566
A25: DEFERRED INFLOWS OF RESOURCES
B27: Fund Balances:
C28: Nonspendable:
D29: Inventories | K29: 1793767 | L29: 45788 | O29: =SUM(K29:N29) -> 1839555
D30: Prepaid expenses | K30: 21195 | L30: 40364 | N30: 2593 | O30: =SUM(K30:N30) -> 64152
C31: Restricted for: | O31: =SUM(K31:N31) -> 0
D32: Judicial | N32: 6377 | O32: =SUM(K32:N32) -> 6377
D33: Debt service | N33: 1468574 | O33: =SUM(K33:N33) -> 1468574
D34: Tourism development | N34: 35404 | O34: =SUM(K34:N34) -> 35404
C35: Committed to: | O35: =SUM(K35:N35) -> 0
D36: Infrastructure maintenance | L36: 1977480 | O36: =SUM(K36:N36) -> 1977480
D37: Culture and recreation | N37: 5971020 | O37: =SUM(K37:N37) -> 5971020
D38: Public safety | N38: 4389545 | O38: =SUM(K38:N38) -> 4389545
D39: Judicial | N39: 3353389 | O39: =SUM(K39:N39) -> 3353389
D40: Health and welfare | N40: 5926056 | O40: =SUM(K40:N40) -> 5926056
D41: Law enforcement building construction | N41: 208078 | O41: =SUM(K41:N41) -> 208078
D42: Library construction | N42: 42777 | O42: =SUM(K42:N42) -> 42777
D43: Administrative building construction | N43: 171838 | O43: =SUM(K43:N43) -> 171838
D44: Other capital projects | L44: 20819 | N44: -38000 | O44: =SUM(K44:N44) -> -17181
D45: Other purposes | K45: 221320 | O45: =SUM(K45:N45) -> 221320
C46: Assigned: | O46: =SUM(K46:N46) -> 0
D47: Judicial | N47: 4676 | O47: =SUM(K47:N47) -> 4676
D48: Health and welfare | N48: 12509 | O48: =SUM(K48:N48) -> 12509
D49: Public safety | N49: 120286 | O49: =SUM(K49:N49) -> 120286
D50: Culture and recreation | N50: 16742 | O50: =SUM(K50:N50) -> 16742
D51: Other capital projects | M51: -1776081 | O51: =SUM(K51:N51) -> -1776081
C52: Unassigned | K52: 17591859 | O52: =SUM(K52:N52) -> 17591859
E54: Total fund balance: | K54: =SUM(K28:K52) -> 19628141 | L54: =SUM(L28:L52) -> 2084451 | M54: =SUM(M28:M52) -> -1776081 | N54: =SUM(N28:N52) -> 21691864 | O54: =SUM(O28:O52) -> 41628375
E56: Total liabilities and fund balances: | K56: =K54+K23 -> 29479256 | L56: =L54+L23 -> 2220539 | M56: =M54+M23 -> 2989983 | N56: =N54+N23 -> 25513163 | O56: =O54+O23 -> 60202941

Sheet Catahoula
D1: Catahoula Combined Balance Sheet
D2: Issued: December 31, 2013
K4: General | L4: Road and Bridge | M4: Hard Surfacing | N4: Sanitation | O4: Library | P4: Health Unit | Q4: Other Governmental Funds | R4: Total Governmental Funds
A5: Assets:
B6: Cash and Cash Equivalents | K6: 634725 | L6: 116054 | M6: 210606 | N6: 296413 | O6: 246720 | P6: 317490 | Q6: 86971 | R6: =SUM(K6:Q6) -> 1908979
B7: Cash restricted for debt service | Q7: 26325
B8: Investments | R8: =SUM(K8:Q8) -> 0
B9: Receivables | K9: 870802 | L9: 44113 | M9: 48137 | N9: 30086 | O9: 285043 | P9: 71122 | Q9: 62183 | R9: =SUM(K9:Q9) -> 1411486
B10: Due from other funds | R10: =SUM(K10:Q10) -> 0
B11: Due from inmates
B12: Capital assets, net of accumulated depreciation
B13: Other assets | K13: 33515 | L13: 16553 | M13: 25177 | P13: 2805 | Q13: 3716 | R13: =SUM(K13:Q13) -> 81766
E15: Total assets: | K15: =SUM(K6:K13) -> 1539042 | L15: =SUM(L6:L13) -> 176720 | M15: =SUM(M6:M13) -> 283920 | N15: =SUM(N6:N13) -> 326499 | O15: =SUM(O6:O13) -> 531763 | P15: =SUM(P6:P13) -> 391417 | Q15: =SUM(Q6:Q13) -> 179195 | R15: =SUM(R6:R13) -> 3402231
A17: LIABILITIES AND FUND BALANCES
B18: Liabilities:
C19: Accounts payable | K19: 461676 | L19: 6380 | M19: 6509 | N19: 36750 | O19: 15313 | P19: 5266 | Q19: 5348 | R19: =SUM(K19:Q19) -> 537242
C20: Salaries and related payables | K20: 2814 | L20: 5948 | M20: 2966 | Q20: 2824 | R20: =SUM(K20:Q20) -> 14552
E22: Total liabilities: | K22: =SUM(K19:K20) -> 464490 | L22: =SUM(L19:L20) -> 12328 | M22: =SUM(M19:M20) -> 9475 | N22: =SUM(N19:N20) -> 36750 | O22: =SUM(O19:O20) -> 15313 | P22: =SUM(P19:P20) -> 5266 | Q22: =SUM(Q19:Q20) -> 8172 | R22: =SUM(R19:R20) -> 551794
B24: Deferred inflows:
C25: Ad valorem taxes - unavailable | K25: 54080 | O25: 41790 | P25: 10448 | Q25: 6787 | R25: =SUM(K25:Q25) -> 113105
C26: Grant revenue - pending | Q26: 14777 | R26: =SUM(K26:Q26) -> 14777
E28: Total deferred inflows: | K28: =SUM(K25:K26) -> 54080 | L28: =SUM(L25:L26) -> 0 | M28: =SUM(M25:M26) -> 0 | N28: =SUM(N25:N26) -> 0 | O28: =SUM(O25:O26) -> 41790 | P28: =SUM(P25:P26) -> 10448 | Q28: =SUM(Q25:Q26) -> 21564 | R28: =SUM(R25:R26) -> 127882
B30: Fund Balances
C31: Nonspendable | K31: 33515 | L31: 16553 | M31: 25177 | P31: 2805 | Q31: 3716 | R31: =SUM(K31:Q31) -> 81766
C32: Restricted | K32: 69325 | L32: 147839 | M32: 249268 | N32: 289749 | O32: 474660 | P32: 372898 | Q32: 161066 | R32: =SUM(K32:Q32) -> 1764805
C33: Unassigned | K33: 917632 | Q33: -15323 | R33: =SUM(K33:Q33) -> 902309
E35: Total fund balance: | K35: =SUM(K31:K33) -> 1020472 | L35: =SUM(L31:L33) -> 164392 | M35: =SUM(M31:M33) -> 274445 | N35: =SUM(N31:N33) -> 289749 | O35: =SUM(O31:O33) -> 474660 | P35: =SUM(P31:P33) -> 375703 | Q35: =SUM(Q31:Q33) -> 149459 | R35: =SUM(R31:R33) -> 2748880
E37: Total liabilities and fund balances: | K37: =K35+K28+K22 -> 1539042 | L37: =L35+L28+L22 -> 176720 | M37: =M35+M28+M22 -> 283920 | N37: =N35+N28+N22 -> 326499 | O37: =O35+O28+O22 -> 531763 | P37: =P35+P28+P22 -> 391417 | Q37: =Q35+Q28+Q22 -> 179195 | R37: =R35+R28+R22 -> 3428556

Sheet Claiborne
D1: Claiborne Combined Balance Sheet
D2: Issued: December 31, 2013
K4: General | L4: Parish Road | M4: Library Maintenance | N4: Sales Tax | O4: Criminal Court | P4: Section 8 | Q4: Other Governmental Funds | R4: Total Governmental Funds
A5: Assets:
B6: Cash and Cash Equivalents | K6: 3274232 | L6: 93857 | M6: 1895670 | N6: 1335641 | O6: 23194 | P6: 61114 | Q6: 863403 | R6: =SUM(K6:Q6) -> 7547111
B7: Investments | K7: 7643 | L7: 3040 | M7: 6248 | N7: 5374 | Q7: 5777 | R7: =SUM(K7:Q7) -> 28082
B8: Receivables | K8: 622061 | L8: 1090093 | M8: 755820 | N8: 74617 | O8: 8595 | Q8: 664142 | R8: =SUM(K8:Q8) -> 3215328
B9: Due from other funds | K9: 1094 | R9: =SUM(K9:Q9) -> 1094
B10: Deferred charges | K10: 113163 | R10: =SUM(K10:Q10) -> 113163
E12: Total assets: | K12: =SUM(K6:K10) -> 4018193 | L12: =SUM(L6:L10) -> 1186990 | M12: =SUM(M6:M10) -> 2657738 | N12: =SUM(N6:N10) -> 1415632 | O12: =SUM(O6:O10) -> 31789 | P12: =SUM(P6:P10) -> 61114 | Q12: =SUM(Q6:Q10) -> 1533322 | R12: =SUM(R6:R10) -> 10904778
A14: LIABILITIES AND FUND BALANCES
B15: Liabilities:
C16: Accounts, salaries and other payables | K16: 205075 | L16: 59446 | M16: 266802 | N16: 53982 | O16: 32187 | Q16: 26079 | R16: =SUM(K16:Q16) -> 643571
C17: Due to other funds | L17: 538 | M17: 456 | Q17: 100 | R17: =SUM(K17:Q17) -> 1094
C18: Due to other agencies | K18: 2343 | P18: 14025 | R18: =SUM(K18:Q18) -> 16368
E20: Total liabilities: | K20: =SUM(K16:K18) -> 207418 | L20: =SUM(L16:L18) -> 59984 | M20: =SUM(M16:M18) -> 267258 | N20: =SUM(N16:N18) -> 53982 | O20: =SUM(O16:O18) -> 32187 | P20: =SUM(P16:P18) -> 14025 | Q20: =SUM(Q16:Q18) -> 26179 | R20: =SUM(R16:R18) -> 661033
B22: Deferred inflows:
C23: Unavailable ad valorem tax revenue | K23: 68100 | L23: 131125 | M23: 87380 | P23: 15626 | Q23: 80639 | R23: =SUM(K23:Q23) -> 382870
E25: Total deferred inflows: | K25: =SUM(K23:K23) -> 68100 | L25: =SUM(L23:L23) -> 131125 | M25: =SUM(M23:M23) -> 87380 | N25: =SUM(N23:N23) -> 0 | O25: =SUM(O23:O23) -> 0 | P25: =SUM(P23:P23) -> 15626 | Q25: =SUM(Q23:Q23) -> 80639 | R25: =SUM(R23:R23) -> 382870
B27: Fund Balances
C28: Restricted fund balances | K28: 592115 | L28: 995881 | M28: 2303100 | N28: 1361650 | O28: -398 | P28: 31463 | Q28: 1426504 | R28: =SUM(K28:Q28) -> 6710315
C29: Unassigned fund balances | K29: 3150560 | R29: =SUM(K29:Q29) -> 3150560
E31: Total fund balance: | K31: =SUM(K28:K29) -> 3742675 | L31: =SUM(L28:L29) -> 995881 | M31: =SUM(M28:M29) -> 2303100 | N31: =SUM(N28:N29) -> 1361650 | O31: =SUM(O28:O29) -> -398 | P31: =SUM(P28:P29) -> 31463 | Q31: =SUM(Q28:Q29) -> 1426504 | R31: =SUM(R28:R29) -> 9860875
E33: Total liabilities and fund balances: | K33: =K31+K25+K20 -> 4018193 | L33: =L31+L25+L20 -> 1186990 | M33: =M31+M25+M20 -> 2657738 | N33: =N31+N25+N20 -> 1415632 | O33: =O31+O25+O20 -> 31789 | P33: =P31+P25+P20 -> 61114 | Q33: =Q31+Q25+Q20 -> 1533322 | R33: =R31+R25+R20 -> 10904778

Sheet Concordia
D1: Concordia Combined Balance Sheet
D2: Issued: December 31, 2013
K5: General Fund | L5: Drainage Fund | M5: Sales Tax Fund | N5: Road Debt Service Fund | O5: Solid Waste Fund | P5: Public Health Fund | Q5: Other Governmental Funds | R5: Total Governmental Funds
A6: Assets:
B7: Cash and cash equivalents | K7: 2454254 | L7: 810545 | M7: 1412343 | O7: 85520 | P7: 304584 | Q7: 486878 | R7: =SUM(K7:Q7) -> 5554124
B8: Cash - restricted for debt service | N8: 2396243 | R8: =SUM(K8:Q8) -> 2396243
B9: Receivables | K9: 767695 | L9: 845413 | M9: 271185 | P9: 207025 | Q9: 33745 | R9: =SUM(K9:Q9) -> 2125063
B10: Accrued interest | K10: 1904 | L10: 325 | M10: 376 | R10: =SUM(K10:Q10) -> 2605
E12: Total Assets: | K12: =SUM(K7:K10) -> 3223853 | L12: =SUM(L7:L10) -> 1656283 | M12: =SUM(M7:M10) -> 1683904 | N12: =SUM(N7:N10) -> 2396243 | O12: =SUM(O7:O10) -> 85520 | P12: =SUM(P7:P10) -> 511609 | Q12: =SUM(Q7:Q10) -> 520623 | R12: =SUM(R7:R10) -> 10078035
A14: LIABILITIES AND FUND BALANCES
B15: Liabilities:
C16: Account, salaries, and payable | K16: 38787 | L16: 18461 | O16: 29483 | P16: 1723 | Q16: 13639 | R16: =SUM(K16:Q16) -> 102093
E18: Total liabilities: | K18: =SUM(K16:K16) -> 38787 | L18: =SUM(L16:L16) -> 18461 | M18: =SUM(M16:M16) -> 0 | N18: =SUM(N16:N16) -> 0 | O18: =SUM(O16:O16) -> 29483 | P18: =SUM(P16:P16) -> 1723 | Q18: =SUM(Q16:Q16) -> 13639 | R18: =SUM(R16:R16) -> 102093
B20: Fund Balances:
C21: Restricted for:
D22: Debt Service | N22: 2396243 | R22: =SUM(K22:Q22) -> 2396243
C23: Committed for:
D24: Special revenue projects | L24: 1637822 | M24: 1683904 | O24: 56037 | P24: 509886 | Q24: 506984 | R24: =SUM(K24:Q24) -> 4394633
C25: Unassigned, reported in: | R25: =SUM(K25:Q25) -> 0
D26: General | K26: 3185066 | R26: =SUM(K26:Q26) -> 3185066
E28: Total fund balance: | K28: =SUM(K22:K26) -> 3185066 | L28: =SUM(L22:L26) -> 1637822 | M28: =SUM(M22:M26) -> 1683904 | N28: =SUM(N22:N26) -> 2396243 | O28: =SUM(O22:O26) -> 56037 | P28: =SUM(P22:P26) -> 509886 | Q28: =SUM(Q22:Q26) -> 506984 | R28: =SUM(R22:R26) -> 9975942
E30: Total liabilities and fund balances: | K30: =SUM(K28,K18,) -> 3223853 | L30: =SUM(L28,L18,) -> 1656283 | M30: =SUM(M28,M18,) -> 1683904 | N30: =SUM(N28,N18,) -> 2396243 | O30: =SUM(O28,O18,) -> 85520 | P30: =SUM(P28,P18,) -> 511609 | Q30: =SUM(Q28,Q18,) -> 520623 | R30: =SUM(R28,R18,) -> 10078035

Sheet DeSoto
D1: DeSoto Combined Balance Sheet
D2: Issued: December 31, 2013
K4: General Fund | L4: Solid Waste Fund | M4: Road Fund | N4: Airport Fund | O4: Jail Fund | P4: Sales Tax | Q4: Criminal Court Fund | R4: Other Governmental Funds | S4: Total Governmental Funds
A5: Assets:
B6: Cash and cash equivalents | K6: 1330631 | L6: 2288828 | M6: 94129 | N6: 606834 | O6: 4639231 | P6: 3000 | Q6: 1447841 | R6: 803131 | S6: =SUM(K6:R6) -> 11213625
B7: Investments | K7: 5807752 | L7: 6347657 | M7: 10696 | N7: 7735241 | S7: =SUM(K7:R7) -> 19901346
B8: Receivables (net of allowance for uncollectibles) | K8: 4018916 | L8: 4079786 | M8: 3950744 | N8: 91183 | O8: 296 | P8: 1051370 | Q8: 98843 | R8: 236842 | S8: =SUM(K8:R8) -> 13527980
B9: Inventory | N9: 40185 | S9: =SUM(K9:R9) -> 40185
B10: Due from other governments | K10: 2650 | S10: =SUM(K10:R10) -> 2650
B11: Due from other funds | K11: 1367048 | L11: 156097 | M11: 520322 | O11: 104065 | S11: =SUM(K11:R11) -> 2147532
B12: Noncurrent receivable | M12: 55000 | S12: =SUM(K12:R12) -> 55000
E14: Total assets: | K14: =SUM(K6:K12) -> 12526997 | L14: =SUM(L6:L12) -> 12872368 | M14: =SUM(M6:M12) -> 4630891 | N14: =SUM(N6:N12) -> 8473443 | O14: =SUM(O6:O12) -> 4743592 | P14: =SUM(P6:P12) -> 1054370 | Q14: =SUM(Q6:Q12) -> 1546684 | R14: =SUM(R6:R12) -> 1039973 | S14: =SUM(S6:S12) -> 46888318
A16: LIABILITIES AND FUND BALANCES
B17: Liabilities:
C18: Accounts payable | K18: 270768 | L18: 329947 | M18: 226143 | N18: 70987 | O18: 35469 | P18: 10723 | Q18: 140911 | R18: 88810 | S18: =SUM(K18:R18) -> 1173758
C19: Due to other funds | N19: 1000000 | P19: 783485 | Q19: 98447 | R19: 265600 | S19: =SUM(K19:R19) -> 2147532
C20: Master bank overdrafts | K20: 31222 | Q20: 1208876 | R20: 182703 | S20: =SUM(K20:R20) -> 1422801
C21: Due to other governments | K21: 4 | P21: 260162 | S21: =SUM(K21:R21) -> 260166
C22: Advance from grantors | R22: 67825 | S22: =SUM(K22:R22) -> 67825
C23: Deposits | K23: 1100 | S23: =SUM(K23:R23) -> 1100
E25: Total liabilities: | K25: =SUM(K18:K23) -> 303094 | L25: =SUM(L18:L23) -> 329947 | M25: =SUM(M18:M23) -> 226143 | N25: =SUM(N18:N23) -> 1070987 | O25: =SUM(O18:O23) -> 35469 | P25: =SUM(P18:P23) -> 1054370 | Q25: =SUM(Q18:Q23) -> 1448234 | R25: =SUM(R18:R23) -> 604938 | S25: =SUM(S18:S23) -> 5073182
A27: DEFERRED INFLOWS OF RESOURCES
B28: Unavailable property taxes | K28: 168000 | L28: 123521 | M28: 171568 | S28: =SUM(K28:R28) -> 463089
E30: Total deferred inflows: | K30: =SUM(K28:K28) -> 168000 | L30: =SUM(L28:L28) -> 123521 | M30: =SUM(M28:M28) -> 171568 | N30: =SUM(N28:N28) -> 0 | O30: =SUM(O28:O28) -> 0 | P30: =SUM(P28:P28) -> 0 | Q30: =SUM(Q28:Q28) -> 0 | R30: =SUM(R28:R28) -> 0 | S30: =SUM(S28:S28) -> 463089
B32: Fund Balances:
C33: Nonspendable:
D34: Inventory | N34: 40185 | S34: =SUM(K34:R34) -> 40185
C35: Restricted for:
D36: Airport | N36: 7362271 | S36: =SUM(K36:R36) -> 7362271
D37: Judicial | Q37: 98450 | S37: =SUM(K37:R37) -> 98450
D38: Public safety | O38: 4708123 | R38: 22724 | S38: =SUM(K38:R38) -> 4730847
D39: Roads | M39: 4233180 | S39: =SUM(K39:R39) -> 4233180
D40: Sanitation | L40: 12418900 | S40: =SUM(K40:R40) -> 12418900
D41: Health and welfare | R41: 6995 | S41: =SUM(K41:R41) -> 6995
D42: Witness and juror fees | R42: 394991 | S42: =SUM(K42:R42) -> 394991
C43: Assigned to:
D44: Animal control | R44: 10325 | S44: =SUM(K44:R44) -> 10325
C45: Unassigned | K45: 12055903 | S45: =SUM(K45:R45) -> 12055903
E47: Total fund balance: | K47: =SUM(K33:K45) -> 12055903 | L47: =SUM(L33:L45) -> 12418900 | M47: =SUM(M33:M45) -> 4233180 | N47: =SUM(N33:N45) -> 7402456 | O47: =SUM(O33:O45) -> 4708123 | P47: =SUM(P33:P45) -> 0 | Q47: =SUM(Q33:Q45) -> 98450 | R47: =SUM(R33:R45) -> 435035 | S47: =SUM(S33:S45) -> 41352047
E49: Total liabilities and fund balances: | K49: =K47+K30+K25 -> 12526997 | L49: =L47+L30+L25 -> 12872368 | M49: =M47+M30+M25 -> 4630891 | N49: =N47+N30+N25 -> 8473443 | O49: =O47+O30+O25 -> 4743592 | P49: =P47+P30+P25 -> 1054370 | Q49: =Q47+Q30+Q25 -> 1546684 | R49: =R47+R30+R25 -> 1039973 | S49: =S47+S30+S25 -> 46888318

Sheet East Baton Rouge
D1: East Baton Rouge Combined Balance Sheet
D2: Issued: October 31, 2013
K4: General Fund | L4: Library Board of Control | M4: Grants | N4: Capital Projects Fund | O4: Other Governmental Funds | P4: Total Governmental Funds
A5: Assets:
B6: Cash and cash equivalents | K6: 52185904 | L6: 34081246 | M6: 2949710 | N6: 57614513 | O6: 38610250 | P6: =SUM(K6:O6) -> 185441623
B7: Investments | K7: 54315942 | L7: 35472317 | M7: 3070106 | N7: 57738466 | O7: 29741176 | P7: =SUM(K7:O7) -> 180338007
B8: Property taxes receivable - net | K8: 6004073 | L8: 8670001 | O8: 6877280 | P8: =SUM(K8:O8) -> 21551354
B9: Gross receipts business taxes receivable | K9: 4393186 | P9: =SUM(K9:O9) -> 4393186
B10: Sales taxes receivable | K10: 17089481 | N10: 2665986 | O10: 1502072 | P10: =SUM(K10:O10) -> 21257539
B11: Interest and penalties receivable on taxes | K11: 78595 | P11: =SUM(K11:O11) -> 78595
B12: Accounts receivable - net | K12: 1977504 | L12: 20578 | N12: 365864 | O12: 2096353 | P12: =SUM(K12:O12) -> 4460299
B13: Accrued interest receivable | K13: 47675 | L13: 36246 | M13: 3105 | N13: 51473 | O13: 24400 | P13: =SUM(K13:O13) -> 162899
B14: Due from other funds | K14: 7976168 | N14: 36255347 | P14: =SUM(K14:O14) -> 44231515
B15: Due from other governments | K15: 20133213 | L15: 29501049 | M15: 7535120 | N15: 2973657 | O15: 22237571 | P15: =SUM(K15:O15) -> 82380610
B16: Loans receivable | K16: 596224 | M16: 2934399 | P16: =SUM(K16:O16) -> 3530623
B17: Inventory | K17: 615439 | P17: =SUM(K17:O17) -> 615439
E19: Total assets: | K19: =SUM(K6:K17) -> 165413404 | L19: =SUM(L6:L17) -> 107781437 | M19: =SUM(M6:M17) -> 16492440 | N19: =SUM(N6:N17) -> 157665306 | O19: =SUM(O6:O17) -> 101089102 | P19: =SUM(P6:P17) -> 548441689
A21: LIABILITIES AND FUND BALANCES
B22: Liabilities:
C23: Accounts and contracts payable | K23: 16075632 | L23: 1875231 | M23: 3337321 | N23: 11702869 | O23: 3275049 | P23: =SUM(K23:O23) -> 36266102
C24: Due to other funds | L24: 35678938 | O24: 8552577 | P24: =SUM(K24:O24) -> 44231515
C25: Due to other governments | K25: 7095596 | O25: 294934 | P25: =SUM(K25:O25) -> 7390530
C26: Accrued payables | K26: 7064989 | L26: 797116 | M26: 650639 | N26: 11927 | O26: 1299271 | P26: =SUM(K26:O26) -> 9823942
C27: Unearned revenue | K27: 13000 | M27: 707137 | N27: 988957 | P27: =SUM(K27:O27) -> 1709094
C28: Deposits and escrow accounts | K28: 22364573 | M28: 138981 | P28: =SUM(K28:O28) -> 22503554
E30: Total liabilities: | K30: =SUM(K23:K28) -> 52613790 | L30: =SUM(L23:L28) -> 38351285 | M30: =SUM(M23:M28) -> 4834078 | N30: =SUM(N23:N28) -> 12703753 | O30: =SUM(O23:O28) -> 13421831 | P30: =SUM(P23:P28) -> 121924737
A32: DEFERRED INFLOWS OF RESOURCES
C33: Unavailable revenue - property taxes | K33: 793073 | L33: 1074827 | O33: 897168 | P33: =SUM(K33:O33) -> 2765068
C34: Unavailable revenue - revenue sharing | K34: 659910 | O34: 78110 | P34: =SUM(K34:O34) -> 738020
C35: Resources received before time requirements | M35: 526276 | P35: =SUM(K35:O35) -> 526276
E37: Total deferred inflows of resources: | K37: =SUM(K33:K35) -> 1452983 | L37: =SUM(L33:L35) -> 1074827 | M37: =SUM(M33:M35) -> 526276 | N37: =SUM(N33:N35) -> 0 | O37: =SUM(O33:O35) -> 975278 | P37: =SUM(P33:P35) -> 4029364
B39: Fund Balances
C40: Nonspendable | K40: 615439 | P40: =SUM(K40:O40) -> 615439
C41: Restricted | K41: 705538 | L41: 68355325 | M41: 11132086 | N41: 124171658 | O41: 78810662 | P41: =SUM(K41:O41) -> 283175269
C42: Committed | K42: 64390991 | N42: 20789895 | O42: 7881331 | P42: =SUM(K42:O42) -> 93062217
C43: Assigned | K43: 29980644 | P43: =SUM(K43:O43) -> 29980644
C44: Unrestricted | K44: 15654019 | P44: =SUM(K44:O44) -> 15654019
E46: Total fund balance: | K46: =SUM(K40:K44) -> 111346631 | L46: =SUM(L40:L44) -> 68355325 | M46: =SUM(M40:M44) -> 11132086 | N46: =SUM(N40:N44) -> 144961553 | O46: =SUM(O40:O44) -> 86691993 | P46: =SUM(P40:P44) -> 422487588
E48: Total liabilities and fund balances: | K48: =SUM(K46,K30,K37) -> 165413404 | L48: =SUM(L46,L30,L37) -> 107781437 | M48: =SUM(M46,M30,M37) -> 16492440 | N48: =SUM(N46,N30,N37) -> 157665306 | O48: =SUM(O46,O30,O37) -> 101089102 | P48: =SUM(P46,P30,P37) -> 548441689

Sheet East Carroll
D1: East Carroll Combined Balance Sheet
D2: Issued: December 31, 2013
K4: General | L4: Road Maintenance and Construction | M4: Garbage District No. 1 | N4: Library | O4: Drainage Maintenance | P4: Criminal Court | Q4: Nonmajor Governmental | R4: Total Governmental Funds
A5: Assets:
B6: Cash and Cash Equivalents | K6: 336645 | L6: 905539 | M6: 230383 | N6: 113864 | O6: 462268 | P6: 7775 | Q6: 698457 | R6: =SUM(K6:Q6) -> 2754931
B7: Investments | L7: 191528 | M7: 272650 | N7: 211580 | O7: 61659 | Q7: 99439 | R7: =SUM(K7:Q7) -> 836856
B8: Receivables | K8: 684348 | L8: 345819 | M8: 295021 | N8: 256164 | O8: 271292 | P8: 15584 | Q8: 376537 | R8: =SUM(K8:Q8) -> 2244765
B9: Interfund receivables | K9: 149037 | N9: 9383 | R9: =SUM(K9:Q9) -> 158420
E11: Total assets: | K11: =SUM(K6:K9) -> 1170030 | L11: =SUM(L6:L9) -> 1442886 | M11: =SUM(M6:M9) -> 798054 | N11: =SUM(N6:N9) -> 590991 | O11: =SUM(O6:O9) -> 795219 | P11: =SUM(P6:P9) -> 23359 | Q11: =SUM(Q6:Q9) -> 1174433 | R11: =SUM(R6:R9) -> 5994972
A13: LIABILITIES AND FUND BALANCES
B14: Liabilities:
C15: Accounts payable | K15: 189268 | L15: 2426 | M15: 6627 | N15: 24 | P15: 20344 | Q15: 214 | R15: =SUM(K15:Q15) -> 218903
C16: Interfund payables | K16: 9383 | P16: 149037 | R16: =SUM(K16:Q16) -> 158420
E18: Total liabilities: | K18: =SUM(K15:K16) -> 198651 | L18: =SUM(L15:L16) -> 2426 | M18: =SUM(M15:M16) -> 6627 | N18: =SUM(N15:N16) -> 24 | O18: =SUM(O15:O16) -> 0 | P18: =SUM(P15:P16) -> 169381 | Q18: =SUM(Q15:Q16) -> 214 | R18: =SUM(R15:R16) -> 377323
B20: Fund Balances
C21: Restricted | L21: 1440460 | M21: 791427 | N21: 590967 | O21: 795219 | Q21: 1174219 | R21: =SUM(K21:Q21) -> 4792292
C22: Unassigned | K22: 971379 | P22: -146022 | R22: =SUM(K22:Q22) -> 825357
E24: Total fund balance: | K24: =SUM(K21:K22) -> 971379 | L24: =SUM(L21:L22) -> 1440460 | M24: =SUM(M21:M22) -> 791427 | N24: =SUM(N21:N22) -> 590967 | O24: =SUM(O21:O22) -> 795219 | P24: =SUM(P21:P22) -> -146022 | Q24: =SUM(Q21:Q22) -> 1174219 | R24: =SUM(R21:R22) -> 5617649
E26: Total liabilities and fund balances: | K26: =K24+K18 -> 1170030 | L26: =L24+L18 -> 1442886 | M26: =M24+M18 -> 798054 | N26: =N24+N18 -> 590991 | O26: =O24+O18 -> 795219 | P26: =P24+P18 -> 23359 | Q26: =Q24+Q18 -> 1174433 | R26: =R24+R18 -> 5994972

Sheet East Feliciana
D1: East Feliciana Combined Balance Sheet
D2: Issued: December 31, 2013
K4: General Fund | L4: Roads and Bridges | M4: Solid Waste | N4: Other Governmental Funds | O4: Total Governmental Funds
A5: Assets:
B6: Cash and cash equivalents | K6: 1090218.1 | L6: 2214339.9 | M6: 2062588 | N6: 146265.77 | O6: =SUM(K6:N6) -> 5513411.8
B7: Receivables, net:
C8: Accounts | K8: 2996.99 | N8: 6961.2 | O8: =SUM(K8:N8) -> 9958.19
C9: Taxes | K9: 345031.11 | M9: 112599.85 | N9: 370612.95 | O9: =SUM(K9:N9) -> 828243.91
B10: Due from other funds | K10: 207683.02 | L10: 115077 | M10: 1275000 | O10: =SUM(K10:N10) -> 1597760
B11: Due from other govt agencies | K11: 57338.6 | L11: 23723.36 | N11: 41871 | O11: =SUM(K11:N11) -> 122932.96
E13: Total assets: | K13: =SUM(K6:K11) -> 1703267.8 | L13: =SUM(L6:L11) -> 2353140.3 | M13: =SUM(M6:M11) -> 3450187.9 | N13: =SUM(N6:N11) -> 565710.92 | O13: =SUM(O6:O11) -> 8072306.8
A15: LIABILITIES AND FUND BALANCES
B16: Liabilities:
C17: Accounts payable | K17: 60416.02 | L17: 88163.13 | M17: 84757.3 | N17: 2605.57 | O17: =SUM(K17:N17) -> 235942.02
C18: Due to other funds | L18: 1275000 | M18: 22920.89 | N18: 154480.04 | O18: =SUM(K18:N18) -> 1452400.9
C19: Due to other govt agencies | N19: 12350.44 | O19: =SUM(K19:N19) -> 12350.44
E21: Total liabilities: | K21: =SUM(K17:K19) -> 60416.02 | L21: =SUM(L17:L19) -> 1363163.1 | M21: =SUM(M17:M19) -> 107678.19 | N21: =SUM(N17:N19) -> 169436.05 | O21: =SUM(O17:O19) -> 1700693.4
B23: Fund Balances (Deficit):
C24: Restricted for: | O24: =SUM(K24:N24) -> 0
D25: Health unit oper/maintenance | N25: 532497.89 | O25: =SUM(K25:N25) -> 532497.89
D26: Homeland security | K26: 49454.42 | O26: =SUM(K26:N26) -> 49454.42
D27: Solid waste management | M27: 3342509.7 | O27: =SUM(K27:N27) -> 3342509.7
C28: Committed to:
D29: Debt service | K29: 8131.4 | O29: =SUM(K29:N29) -> 8131.4
D30: Road improvements | L30: 989977.15 | O30: =SUM(K30:N30) -> 989977.15
D31: Coroner/court operations | N31: -136223.02 | O31: =SUM(K31:N31) -> -136223.02
D32: Claims and judgements | K32: 152370.09 | O32: =SUM(K32:N32) -> 152370.09
C33: Unassigned | K33: 1432895.9 | O33: =SUM(K33:N33) -> 1432895.9
E35: Total fund balance: | K35: =SUM(K25:K33) -> 1642851.8 | L35: =SUM(L25:L33) -> 989977.15 | M35: =SUM(M25:M33) -> 3342509.7 | N35: =SUM(N25:N33) -> 396274.87 | O35: =SUM(O25:O33) -> 6371613.5
E37: Total liabilities and fund balances: | K37: =K35+K21 -> 1703267.8 | L37: =L35+L21 -> 2353140.3 | M37: =M35+M21 -> 3450187.9 | N37: =N35+N21 -> 565710.92 | O37: =O35+O21 -> 8072306.8

Sheet Evangeline
D1: Evangeline Combined Balance Sheet
D2: Issued: December 31, 2013
K4: General Fund | L4: Special Grant | M4: Road District Maintenance | N4: Industrial District No. 1 | O4: 2% Sales Tax District #1 Capital Projects | P4: Other Governmental Funds | Q4: Total Governmental Funds
A5: Assets:
B6: Cash and interest-bearing deposits | K6: 566864 | L6: 134551 | M6: 1629614 | O6: 3401559 | P6: 4039532 | Q6: =SUM(K6:P6) -> 9772120
B7: Receivables, net | K7: 851112 | M7: 2390358 | N7: 275000 | P7: 2018241 | Q7: =SUM(K7:P7) -> 5534711
B8: Due from other funds | K8: 180547 | Q8: =SUM(K8:P8) -> 180547
B9: Due from other governmental units | K9: 142342 | L9: 96568 | M9: 6696 | P9: 126896 | Q9: =SUM(K9:P9) -> 372502
B10: Other assets | K10: 15960 | N10: 5000 | Q10: =SUM(K10:P10) -> 20960
B11: Restricted assets:
C12: Investments | O12: 28970121 | Q12: =SUM(K12:P12) -> 28970121
E14: Total Assets: | K14: =SUM(K6:K12) -> 1756825 | L14: =SUM(L6:L12) -> 231119 | M14: =SUM(M6:M12) -> 4026668 | N14: =SUM(N6:N12) -> 280000 | O14: =SUM(O6:O12) -> 32371680 | P14: =SUM(P6:P12) -> 6184669 | Q14: =SUM(Q6:Q12) -> 44850961
A16: LIABILITIES AND FUND BALANCES
B17: Liabilities:
C18: Cash overdraft | N18: 33015 | P18: 11271 | Q18: =SUM(K18:P18) -> 44286
C19: Accounts, salaries, and other payables | K19: 230455 | L19: 42753 | M19: 54954 | O19: 72502 | P19: 52460 | Q19: =SUM(K19:P19) -> 453124
C20: Unearned revenue | L20: 69456 | Q20: =SUM(K20:P20) -> 69456
C21: Due to other funds | L21: 63013 | M21: 102795 | P21: 14739 | Q21: =SUM(K21:P21) -> 180547
C22: Performance bonds payable | K22: 300318 | Q22: =SUM(K22:P22) -> 300318
C23: Compensated absences payable | K23: 5868 | M23: 2801 | Q23: =SUM(K23:P23) -> 8669
C24: Sewer deposits payable | P24: 10182 | Q24: =SUM(K24:P24) -> 10182
E26: Total liabilities: | K26: =SUM(K18:K24) -> 536641 | L26: =SUM(L18:L24) -> 175222 | M26: =SUM(M18:M24) -> 160550 | N26: =SUM(N18:N24) -> 33015 | O26: =SUM(O18:O24) -> 72502 | P26: =SUM(P18:P24) -> 88652 | Q26: =SUM(Q18:Q24) -> 1066582
A28: DEFERRED INFLOWS OF RESOURCES
B29: Unearned rent | L29: 0 | N29: 271333 | Q29: =SUM(K29:P29) -> 271333
B31: Fund Balances
C32: Restricted:
D33: Debt service | P33: 97233 | Q33: =SUM(K33:P33) -> 97233
D34: Public works | O34: 28970121 | Q34: =SUM(K34:P34) -> 28970121
C35: Assigned: | Q35: =SUM(K35:P35) -> 0
D36: Public works | L36: 55897 | M36: 3866118 | O36: 3329057 | P36: 1822830 | Q36: =SUM(K36:P36) -> 9073902
D37: Health and welfare | P37: 1442622 | Q37: =SUM(K37:P37) -> 1442622
D38: Culture and recreation | P38: 2718302 | Q38: =SUM(K38:P38) -> 2718302
D39: Drainage improvements | P39: 42628 | Q39: =SUM(K39:P39) -> 42628
C40: Unassigned (deficit) | K40: 1220184 | N40: -24348 | P40: -27598 | Q40: =SUM(K40:P40) -> 1168238
E42: Total fund balances: | K42: =SUM(K33:K41) -> 1220184 | L42: =SUM(L34:L40) -> 55897 | M42: =SUM(M33:M40) -> 3866118 | N42: =SUM(N34:N40) -> -24348 | O42: =SUM(O33:O40) -> 32299178 | P42: =SUM(P33:P40) -> 6096017 | Q42: =SUM(Q31:Q40) -> 43513046
E44: Total liabilities and fund balances: | K44: =SUM(K42,K26,K29) -> 1756825 | L44: =SUM(L42,L26,L29) -> 231119 | M44: =SUM(M42,M26,M29) -> 4026668 | N44: =SUM(N42,N26,N29) -> 280000 | O44: =SUM(O42,O26,O29) -> 32371680 | P44: =SUM(P42,P26,P29) -> 6184669 | Q44: =SUM(Q42,Q26,Q29) -> 44850961

Sheet Franklin
D1: Franklin Combined Balance Sheet
D2: Issued: December 31, 2013
K4: General Fund | L4: Road and Bridge | M4: Drainage Maintenance | N4: Parish Equipment | O4: Sales Tax | P4: Acquisition Elevation | Q4: Other Governmental Funds | R4: Total Governmental Funds
A5: Assets:
B6: Cash and equivalents | K6: 229344 | L6: 2073028 | M6: 414083 | N6: 836674 | O6: 1571432 | P6: 822 | Q6: 2144281 | R6: =SUM(K6:Q6) -> 7269664
B7: Receivables | K7: 255196 | L7: 247820 | M7: 762354 | N7: 554191 | O7: 93354 | P7: 765506 | Q7: 981425 | R7: =SUM(K7:Q7) -> 3659846
B8: Prepaid assets | N8: 4140 | R8: =SUM(K8:Q8) -> 4140
B9: Due from other funds | K9: 104161 | L9: 2583 | M9: 1862 | N9: 215 | Q9: 9968 | R9: =SUM(K9:Q9) -> 118789
E11: Total assets: | K11: =SUM(K6:K9) -> 588701 | L11: =SUM(L6:L9) -> 2323431 | M11: =SUM(M6:M9) -> 1178299 | N11: =SUM(N6:N9) -> 1395220 | O11: =SUM(O6:O9) -> 1664786 | P11: =SUM(P6:P9) -> 766328 | Q11: =SUM(Q6:Q9) -> 3135674 | R11: =SUM(R6:R9) -> 11052439
A13: LIABILITIES AND FUND BALANCES
B14: Liabilities:
C15: Accounts payable | K15: 9347 | M15: 32605 | N15: 23702 | P15: 251384 | Q15: 65116 | R15: =SUM(K15:Q15) -> 382154
C16: Payroll withholdings payable | K16: 66901 | L16: 62 | R16: =SUM(K16:Q16) -> 66963
C17: Due to other funds | K17: 23716 | L17: 3950 | M17: 1820 | N17: 3882 | O17: 53058 | Q17: 32363 | R17: =SUM(K17:Q17) -> 118789
C18: Due to others (damage deposits) | L18: 20000 | R18: =SUM(K18:Q18) -> 20000
E20: Total liabilities: | K20: =SUM(K15:K18) -> 99964 | L20: =SUM(L15:L18) -> 24012 | M20: =SUM(M15:M18) -> 34425 | N20: =SUM(N15:N18) -> 27584 | O20: =SUM(O15:O18) -> 53058 | P20: =SUM(P15:P18) -> 251384 | Q20: =SUM(Q15:Q18) -> 97479 | R20: =SUM(R15:R18) -> 587906
B22: Fund Balances:
C23: Nonspendable | L23: 20000 | N23: 4140 | R23: =SUM(K23:Q23) -> 24140
C24: Restricted:
D25: Other general government | Q25: 925861 | R25: =SUM(K25:Q25) -> 925861
D26: Health and welfare | Q26: 492432 | R26: =SUM(K26:Q26) -> 492432
D27: Culture and recreation | Q27: 6223 | R27: =SUM(K27:Q27) -> 6223
D28: Public safety | Q28: 756266 | R28: =SUM(K28:Q28) -> 756266
D29: Public works | L29: 2279419 | M29: 1143874 | N29: 1363496 | O29: 1611728 | Q29: 643728 | R29: =SUM(K29:Q29) -> 7042245
D30: Economic development | Q30: 175688 | R30: =SUM(K30:Q30) -> 175688
D31: Committed | Q31: 37856 | R31: =SUM(K31:Q31) -> 37856
C32: Assigned | P32: 514944 | Q32: 141 | R32: =SUM(K32:Q32) -> 515085
C33: Unassigned | K33: 488737 | R33: =SUM(K33:Q33) -> 488737
E35: Total fund balance: | K35: =SUM(K23:K33) -> 488737 | L35: =SUM(L23:L33) -> 2299419 | M35: =SUM(M23:M33) -> 1143874 | N35: =SUM(N23:N33) -> 1367636 | O35: =SUM(O23:O33) -> 1611728 | P35: =SUM(P23:P33) -> 514944 | Q35: =SUM(Q23:Q33) -> 3038195 | R35: =SUM(R23:R33) -> 10464533
E37: Total liabilities and fund balances: | K37: =K35+K20 -> 588701 | L37: =L35+L20 -> 2323431 | M37: =M35+M20 -> 1178299 | N37: =N35+N20 -> 1395220 | O37: =O35+O20 -> 1664786 | P37: =P35+P20 -> 766328 | Q37: =Q35+Q20 -> 3135674 | R37: =R35+R20 -> 11052439

Sheet Grant
D1: Grant Combined Balance Sheet
D2: Issued: December 31, 2013
K4: General Fund | L4: Parish Road Maintenance | M4: Sanitary Landfill Maintenance | N4: Head Start | O4: CDBG Herman Park Sewer | P4: Other Governmental Funds | Q4: Total Governmental Funds
A5: Assets:
B6: Cash and cash equivalents | K6: 316101 | L6: 349202 | M6: 261965 | N6: 74993 | P6: 679292 | Q6: =SUM(K6:P6) -> 1681553
B7: Receivables (net) | K7: 390066 | L7: 416153 | M7: 270987 | O7: 103340 | P7: 305583 | Q7: =SUM(K7:P7) -> 1486129
B8: Interfund receivables | K8: 32928 | L8: 62006 | M8: 3016 | P8: 10000 | Q8: =SUM(K8:P8) -> 107950
E10: Total assets: | K10: =SUM(K6:K8) -> 739095 | L10: =SUM(L6:L8) -> 827361 | M10: =SUM(M6:M8) -> 535968 | N10: =SUM(N6:N8) -> 74993 | O10: =SUM(O6:O8) -> 103340 | P10: =SUM(P6:P8) -> 994875 | Q10: =SUM(Q6:Q8) -> 3275632
A12: LIABILITIES AND FUND BALANCES
B13: Liabilities:
C14: Accounts payable | K14: 125801 | L14: 19528 | M14: 24323 | N14: 74993 | O14: 103340 | P14: 31096 | Q14: =SUM(K14:P14) -> 379081
C15: Interfund payables | K15: 5000 | L15: 1176 | M15: 66857 | P15: 34917 | Q15: =SUM(K15:P15) -> 107950
C16: Unearned revenues | K16: 2266 | Q16: =SUM(K16:P16) -> 2266
E18: Total liabilities: | K18: =SUM(K14:K16) -> 133067 | L18: =SUM(L14:L16) -> 20704 | M18: =SUM(M14:M16) -> 91180 | N18: =SUM(N14:N16) -> 74993 | O18: =SUM(O14:O16) -> 103340 | P18: =SUM(P14:P16) -> 66013 | Q18: =SUM(Q14:Q16) -> 489297
B20: Fund Balances:
C21: Restricted for:
D22: Maintenance | L22: 806657 | M22: 444788 | P22: 642079 | Q22: =SUM(K22:P22) -> 1893524
D23: Judicial | P23: 24781 | Q23: =SUM(K23:P23) -> 24781
D24: Construction | P24: 51625 | Q24: =SUM(K24:P24) -> 51625
C25: Committed to:
D26: Maintenance | P26: 21677 | Q26: =SUM(K26:P26) -> 21677
D27: Construction | P27: 88346 | Q27: =SUM(K27:P27) -> 88346
D28: Litter abatement | P28: 12139 | Q28: =SUM(K28:P28) -> 12139
D29: General purposes | P29: 92402 | Q29: =SUM(K29:P29) -> 92402
C30: Unassigned | K30: 606028 | P30: -4187 | Q30: =SUM(K30:P30) -> 601841
E32: Total fund balance: | K32: =SUM(K21:K30) -> 606028 | L32: =SUM(L21:L30) -> 806657 | M32: =SUM(M21:M30) -> 444788 | N32: =SUM(N21:N30) -> 0 | O32: =SUM(O21:O30) -> 0 | P32: =SUM(P21:P30) -> 928862 | Q32: =SUM(Q21:Q30) -> 2786335
E34: Total liabilities and fund balances: | K34: =K32+K18 -> 739095 | L34: =L32+L18 -> 827361 | M34: =M32+M18 -> 535968 | N34: =N32+N18 -> 74993 | O34: =O32+O18 -> 103340 | P34: =P32+P18 -> 994875 | Q34: =Q32+Q18 -> 3275632

Sheet Iberia
D1: Iberia Combined Balance Sheet
D2: Issued: December 31, 2013
K4: General Fund | L4: Public Library | M4: Sales Tax | N4: Criminal Justice Facility | O4: Parish Wide Drainage Maintenance | P4: Royalty | Q4: Texaco Royalty | R4: Other Governmental Funds | S4: Total Governmental Funds
A5: Assets:
B6: Cash and interest-bearing deposits | K6: 1706810 | L6: 4379297 | M6: 5876513 | N6: 459480 | O6: 4538640 | P6: 5127300 | Q6: 4954573 | R6: 10858237 | S6: =SUM(K6:R6) -> 37900850
B7: Investments | L7: 83378 | S7: =SUM(K7:R7) -> 83378
B8: Receivables | K8: 1156120 | L8: 2005084 | N8: 223895 | O8: 1376935 | R8: 3129676 | S8: =SUM(K8:R8) -> 7891710
B9: Due from other funds | K9: 156359 | L9: 260 | R9: 50696 | S9: =SUM(K9:R9) -> 207315
B10: Advance to component units | K10: 1056944 | P10: 35000 | R10: 324467 | S10: =SUM(K10:R10) -> 1416411
B11: Due from other governmental agencies | K11: 207796 | L11: 79556 | M11: 192285 | N11: 22266 | O11: 38852 | P11: 3262112 | R11: 1396120 | S11: =SUM(K11:R11) -> 5198987
E13: Total assets: | K13: =SUM(K6:K11) -> 4284029 | L13: =SUM(L6:L11) -> 6547575 | M13: =SUM(M6:M11) -> 6068798 | N13: =SUM(N6:N11) -> 705641 | O13: =SUM(O6:O11) -> 5954427 | P13: =SUM(P6:P11) -> 8424412 | Q13: =SUM(Q6:Q11) -> 4954573 | R13: =SUM(R6:R11) -> 15759196 | S13: =SUM(S6:S11) -> 52698651
A15: LIABILITIES AND FUND BALANCES
B16: Liabilities:
C17: Accounts payable | K17: 141995 | L17: 18122 | M17: 237079 | N17: 256130 | O17: 42640 | P17: 65193 | R17: 1034377 | S17: =SUM(K17:R17) -> 1795536
C18: Accrued expenses | K18: 73484 | L18: 25031 | M18: 2072 | N18: 2180 | O18: 18202 | P18: 9094 | R18: 51476 | S18: =SUM(K18:R18) -> 181539
C19: Contracts payable | P19: 268323 | S19: =SUM(K19:R19) -> 268323
C20: Retainage payable | P20: 336389 | S20: =SUM(K20:R20) -> 336389
C21: Due to other funds | N21: 156114 | P21: 50696 | R21: 505 | S21: =SUM(K21:R21) -> 207315
C22: Due to other governmental agencies | K22: 48115 | L22: 88588 | N22: 10208 | O22: 60192 | R22: 130081 | S22: =SUM(K22:R22) -> 337184
C23: Due to component units | K23: 692 | R23: 299497 | S23: =SUM(K23:R23) -> 300189
C24: Advances from grantors and assessments | R24: 171235 | S24: =SUM(K24:R24) -> 171235
E26: Total liabilities: | K26: =SUM(K17:K24) -> 264286 | L26: =SUM(L17:L24) -> 131741 | M26: =SUM(M17:M24) -> 239151 | N26: =SUM(N17:N24) -> 424632 | O26: =SUM(O17:O24) -> 121034 | P26: =SUM(P17:P24) -> 729695 | Q26: =SUM(Q17:Q24) -> 0 | R26: =SUM(R17:R24) -> 1687171 | S26: =SUM(S17:S24) -> 3597710
B28: Fund Balances:
C29: Nonspendable | R29: 68863 | S29: =SUM(K29:R29) -> 68863
C30: Restricted | L30: 6415834 | M30: 5829647 | N30: 281009 | O30: 5833393 | R30: 9225177 | S30: =SUM(K30:R30) -> 27585060
C31: Committed | K31: 515153 | Q31: 4954573 | R31: 172897 | S31: =SUM(K31:R31) -> 5642623
C32: Assigned | K32: 2038654 | P32: 7694717 | R32: 4605088 | S32: =SUM(K32:R32) -> 14338459
C33: Unassigned | K33: 1465936 | S33: =SUM(K33:R33) -> 1465936
E35: Total fund balance: | K35: =SUM(K29:K33) -> 4019743 | L35: =SUM(L29:L33) -> 6415834 | M35: =SUM(M29:M33) -> 5829647 | N35: =SUM(N29:N33) -> 281009 | O35: =SUM(O29:O33) -> 5833393 | P35: =SUM(P29:P33) -> 7694717 | Q35: =SUM(Q29:Q33) -> 4954573 | R35: =SUM(R29:R33) -> 14072025 | S35: =SUM(S29:S33) -> 49100941
E37: Total liabilities and fund balances: | K37: =K35+K26 -> 4284029 | L37: =L35+L26 -> 6547575 | M37: =M35+M26 -> 6068798 | N37: =N35+N26 -> 705641 | O37: =O35+O26 -> 5954427 | P37: =P35+P26 -> 8424412 | Q37: =Q35+Q26 -> 4954573 | R37: =R35+R26 -> 15759196 | S37: =S35+S26 -> 52698651

Sheet Iberville
D1: Iberville Combined Balance Sheet
D2: Issued: December 31, 2013
K5: General | L5: Drainage Maintenance | M5: Public Building Maintenance | N5: Sales Tax Roads | O5: Solid Waste | P5: Capital Improvement | Q5: Iberville Parish Medical Facility CSBG | R5: Other Governmental Funds | S5: Total Governmental Funds
A6: Assets:
B7: Cash and cash equivalents | K7: 1830428 | L7: 64545 | M7: 15044 | N7: 2291631 | O7: 2544362 | P7: 2958857 | Q7: 67147 | R7: 6638557 | S7: =SUM(K7:R7) -> 16410571
B8: Receivables (net of allowance for uncollectible) | K8: 2344775 | L8: 2558001 | M8: 1461418 | N8: 464269 | O8: 596513 | P8: 642884 | Q8: 229691 | R8: 776983 | S8: =SUM(K8:R8) -> 9074534
B9: Prepaid items | K9: 431673 | L9: 63904 | M9: 216700 | N9: 73000 | O9: 8150 | R9: 77276 | S9: =SUM(K9:R9) -> 870703
B10: Due from other funds | K10: 427702 | S10: =SUM(K10:R10) -> 427702
B11: Cash - restricted | K11: 100000 | S11: =SUM(K11:R11) -> 100000
B12: Other assets | S12: =SUM(K12:R12) -> 0
E14: Total Assets: | K14: =SUM(K7:K12) -> 5134578 | L14: =SUM(L7:L12) -> 2686450 | M14: =SUM(M7:M12) -> 1693162 | N14: =SUM(N7:N12) -> 2828900 | O14: =SUM(O7:O12) -> 3149025 | P14: =SUM(P7:P12) -> 3601741 | Q14: =SUM(Q7:Q12) -> 296838 | R14: =SUM(R7:R12) -> 7492816 | S14: =SUM(S7:S12) -> 26883510
A16: LIABILITIES AND FUND BALANCES
B17: Liabilities:
C18: Accounts payable | K18: 489329 | L18: 84806 | M18: 98127 | N18: 76760 | O18: 254246 | P18: 573551 | Q18: 229691 | R18: 237310 | S18: =SUM(K18:R18) -> 2043820
C19: Due to other funds | M19: 427702 | S19: =SUM(K19:R19) -> 427702
C20: Other payables | K20: 470321 | L20: 135718 | M20: 79933 | N20: 43833 | O20: 8008 | R20: 57561 | S20: =SUM(K20:R20) -> 795374
E22: Total liabilities: | K22: =SUM(K18:K20) -> 959650 | L22: =SUM(L18:L20) -> 220524 | M22: =SUM(M18:M20) -> 605762 | N22: =SUM(N18:N21) -> 120593 | O22: =SUM(O18:O20) -> 262254 | P22: =SUM(P18:P20) -> 573551 | Q22: =SUM(Q18:Q20) -> 229691 | R22: =SUM(R18:R20) -> 294871 | S22: =SUM(S18:S20) -> 3266896
B24: Fund Balances
C25: Non Spendable | K25: 431673 | L25: 45132 | M25: 216700 | N25: 73000 | O25: 8150 | S25: =SUM(K25:R25) -> 774655
C26: Restricted | K26: 150000 | L26: 2420794 | M26: 870700 | N26: 2635307 | O26: 2878621 | P26: 3028190 | Q26: 67147 | R26: 6347344 | S26: =SUM(K26:R26) -> 18398103
C27: Committed | R27: 850601 | S27: =SUM(K27:R27) -> 850601
C28: Assigned | S28: =SUM(K28:R28) -> 0
C29: Unassigned | K29: 3593255 | S29: =SUM(K29:R29) -> 3593255
E31: Total fund balance: | K31: =SUM(K25:K30) -> 4174928 | L31: =SUM(L25:L29) -> 2465926 | M31: =SUM(M25:M29) -> 1087400 | N31: =SUM(N25:N29) -> 2708307 | O31: =SUM(O25:O29) -> 2886771 | P31: =SUM(P25:P29) -> 3028190 | Q31: =SUM(Q26:Q29) -> 67147 | R31: =SUM(R25:R29) -> 7197945 | S31: =SUM(S26:S29) -> 22841959
E33: Total liabilities and fund balances: | K33: =SUM(K31,K22) -> 5134578 | L33: =SUM(L22,L31) -> 2686450 | M33: =SUM(M22,M31) -> 1693162 | N33: =SUM(N22,N31) -> 2828900 | O33: =SUM(O31+O22) -> 3149025 | P33: =SUM(P31+P22) -> 3601741 | Q33: =SUM(Q31+Q22) -> 296838 | R33: =SUM(R31+R22) -> 7492816
I35: Amounts reported for governmental activities in the statement of net position are different because:
J36: Capital assets used in governmental activities are not financial resources and,
J37: therefore, are not reported in the funds. | S37: 100186393
J39: Long-term liabilities, including bonds payable, are not due and payable in the current period
J40: other post employment benefits and therefore are not reported in the funds. | S40: -18835396
I42: Net position of governmental activities | S42: 104967612

Sheet Jackson
D1: Jackson Combined Balance Sheet
D2: Issued: December 31, 2013
K4: General Fund | L4: Road Fund | M4: Solid Waste | N4: Library | O4: Asphalt Fund | P4: Health Unit | Q4: LCDBG | R4: Nonmajor Governmental | S4: Total Governmental Funds
A5: Assets:
B6: Cash and cash equivalents | K6: 2555510 | L6: 994401 | M6: 1355932 | N6: 2794786 | O6: 1003144 | P6: 15445 | Q6: 10 | R6: 903063 | S6: =SUM(K6:R6) -> 9622291
B7: Receivables | K7: 1313659 | L7: 1278046 | M7: 214761 | N7: 503407 | O7: 1069740 | P7: 188757 | Q7: 44845 | R7: 142766 | S7: =SUM(K7:R7) -> 4755981
B8: Interfund receivables | K8: 50000 | S8: =SUM(K8:Q8) -> 50000
B9: Prepaid items | K9: 4916 | L9: 4988 | M9: 5171 | N9: 54788 | P9: 393 | S9: =SUM(K9:Q9) -> 70256
E11: Total Assets: | K11: =SUM(K6:K9) -> 3924085 | L11: =SUM(L6:L9) -> 2277435 | M11: =SUM(M6:M9) -> 1575864 | N11: =SUM(N6:N9) -> 3352981 | O11: =SUM(O6:O9) -> 2072884 | P11: =SUM(P6:P9) -> 204595 | Q11: =SUM(Q6:Q9) -> 44855 | R11: =SUM(R6:R9) -> 1045829 | S11: =SUM(S6:S9) -> 14498528
A13: LIABILITIES AND FUND BALANCES
B14: Liabilities:
C15: Accounts, salaries and other payables | K15: 83471 | L15: 23438 | M15: 57398 | N15: 126122 | O15: 4559 | P15: 2232 | Q15: 44845 | S15: =SUM(K15:Q15) -> 342065
C16: Interfund payables | P16: 50000 | S16: =SUM(K16:Q16) -> 50000
C17: Security deposits | K17: 4525 | L17: 26724 | S17: =SUM(K17:Q17) -> 31249
E19: Total liabilities: | K19: =SUM(K15:K17) -> 87996 | L19: =SUM(L15:L17) -> 50162 | M19: =SUM(M15:M17) -> 57398 | N19: =SUM(N15:N17) -> 126122 | O19: =SUM(O15:O17) -> 4559 | P19: =SUM(P15:P17) -> 52232 | Q19: =SUM(Q15:Q17) -> 44845 | R19: =SUM(R15:R17) -> 0 | S19: =SUM(S15:S17) -> 423314
A21: DEFERRED INFLOWS OF RESOURCES
B22: Unavailable revenue-property taxes | K22: 98282 | L22: 105621 | N22: 43199 | O22: 91798 | P22: 16179 | S22: =SUM(K22:Q22) -> 355079
E23: Total Deferred Inflows of Resources | K23: =SUM(K22) -> 98282 | L23: =SUM(L22) -> 105621 | M23: =SUM(M22) -> 0 | N23: =SUM(N22) -> 43199 | O23: =SUM(O22) -> 91798 | P23: =SUM(P22) -> 16179 | Q23: =SUM(Q22) -> 0 | R23: =SUM(R22) -> 0 | S23: =SUM(S22) -> 355079
B25: Fund Balances
C26: Nonspendable - prepaid items | K26: 4916 | L26: 4988 | M26: 5171 | N26: 54788 | P26: 393 | S26: =SUM(K26:R26) -> 70256
C27: Restricted | K27: 285538 | L27: 2116664 | M27: 1513295 | N27: 3128872 | O27: 1976527 | P27: 135791 | R27: 1023173 | S27: =SUM(K27:R27) -> 10179860
C28: Committed | K28: 1007675 | Q28: 10 | R28: 22656 | S28: =SUM(K28:R28) -> 1030341
C29: Unassigned | K29: 2439678 | S29: =SUM(K29:R29) -> 2439678
E31: Total fund balance: | K31: =SUM(K26:K30) -> 3737807 | L31: =SUM(L26:L30) -> 2121652 | M31: =SUM(M26:M30) -> 1518466 | N31: =SUM(N26:N30) -> 3183660 | O31: =SUM(O26:O30) -> 1976527 | P31: =SUM(P26:P29) -> 136184 | Q31: =SUM(Q26:Q29) -> 10 | R31: =SUM(R26:R29) -> 1045829 | S31: =SUM(S25:S29) -> 13720135
E33: Total liabilities and fund balances: | K33: =SUM(K31,K19,K23) -> 3924085 | L33: =SUM(L19,L31) -> 2171814 | M33: =SUM(M19,M31,M23) -> 1575864 | N33: =SUM(N19,N31,N23) -> 3352981 | O33: =SUM(O31+O19+O23) -> 2072884 | P33: =SUM(P31+P23+P19) -> 204595 | Q33: =SUM(Q31+Q19+Q23) -> 44855 | R33: =SUM(R31+R19+R23) -> 1045829 | S33: =SUM(S19,S31,S23) -> 14498528

Sheet Jefferson Davis
D1: Jefferson Davis Combined Balance Sheet
D2: Issued: December 31, 2013
K4: General Fund | L4: Road Sales Tax No. 1 Sales Tax Fund | M4: Criminal Court Fund | N4: Section 8 Housing Fund | O4: Road Sales Tax No. 1 Sinking Fund | P4: Other Governmental Funds | Q4: Total Governmental Funds
A5: Assets:
B6: Cash and cash equivalents | K6: 6873169 | L6: 5177897 | M6: 4053 | N6: 23208 | P6: 5627442 | Q6: =SUM(K6:P6) -> 17705769
B7: Investments | K7: 674530 | P7: 1426503 | Q7: =SUM(K7:P7) -> 2101033
B8: Receivables | K8: 38483 | L8: 204575 | M8: 178061 | N8: 147 | P8: 347863 | Q8: =SUM(K8:P8) -> 769129
B9: Due from other funds | K9: 31870 | P9: 67311 | Q9: =SUM(K9:P9) -> 99181
B10: Restricted cash and cash equivalents | L10: 1552823 | O10: 1054038 | P10: 88551 | Q10: =SUM(K10:P10) -> 2695412
E12: Total assets: | K12: =SUM(K6:K10) -> 7618052 | L12: =SUM(L6:L10) -> 6935295 | M12: =SUM(M6:M10) -> 182114 | N12: =SUM(N6:N10) -> 23355 | O12: =SUM(O6:O10) -> 1054038 | P12: =SUM(P6:P10) -> 7557670 | Q12: =SUM(Q6:Q10) -> 23370524
A14: LIABILITIES AND FUND BALANCES
B15: Liabilities:
C16: Accounts, salaries, and other payables | K16: 155925 | M16: 474173 | N16: 218 | P16: 196816 | Q16: =SUM(K16:P16) -> 827132
C17: Contracts payable | P17: 31096 | Q17: =SUM(K17:P17) -> 31096
C18: Deposits to others | K18: 368500 | Q18: =SUM(K18:P18) -> 368500
C19: Other liabilities | K19: 140 | Q19: =SUM(K19:P19) -> 140
C20: Due to other funds | K20: 19844 | P20: 79337 | Q20: =SUM(K20:P20) -> 99181
E22: Total liabilities: | K22: =SUM(K16:K20) -> 544409 | L22: =SUM(L16:L20) -> 0 | M22: =SUM(M16:M20) -> 474173 | N22: =SUM(N16:N20) -> 218 | O22: =SUM(O16:O20) -> 0 | P22: =SUM(P16:P20) -> 307249 | Q22: =SUM(Q16:Q20) -> 1326049
A24: DEFERRED INFLOWS OF RESOURCES
C25: Deferred revenues | K25: 30672 | P25: 16306 | Q25: =SUM(K25:P25) -> 46978
B27: Fund Balances:
C28: Restricted for:
D29: Public safety | P29: 3901978 | Q29: =SUM(K29:P29) -> 3901978
D30: Public works | L30: 5382472 | P30: 1705234 | Q30: =SUM(K30:P30) -> 7087706
D31: Health and welfare | N31: 23137 | P31: 343571 | Q31: =SUM(K31:P31) -> 366708
D32: Debt service | L32: 1552823 | O32: 1054038 | P32: 45316 | Q32: =SUM(K32:P32) -> 2652177
D33: Capital projects | P33: 2477 | Q33: =SUM(K33:P33) -> 2477
D34: Other general government | P34: 1251900 | Q34: =SUM(K34:P34) -> 1251900
C35: Assigned for:
D36: Jail capital project | K36: 538003 | Q36: =SUM(K36:P36) -> 538003
C37: Unassigned | K37: 6504968 | M37: -292059 | P37: -16361 | Q37: =SUM(K37:P37) -> 6196548
E39: Total fund balance: | K39: =SUM(K28:K37) -> 7042971 | L39: =SUM(L28:L37) -> 6935295 | M39: =SUM(M28:M37) -> -292059 | N39: =SUM(N28:N37) -> 23137 | O39: =SUM(O28:O37) -> 1054038 | P39: =SUM(P28:P37) -> 7234115 | Q39: =SUM(Q28:Q37) -> 21997497
E41: Total liabilities and fund balances: | K41: =K39+K25+K22 -> 7618052 | L41: =L39+L25+L22 -> 6935295 | M41: =M39+M25+M22 -> 182114 | N41: =N39+N25+N22 -> 23355 | O41: =O39+O25+O22 -> 1054038 | P41: =P39+P25+P22 -> 7557670 | Q41: =Q39+Q25+Q22 -> 23370524

Sheet Jefferson
D1: Jefferson Combined Balance Sheet
D2: Issued: December 31, 2013
I3: (amounts in thousands)
K5: General Fund | L5: Federal and State Grants | M5: East Bank Consolidated Fire District | N5: Library | O5: Drainage and Pump Station Capital | P5: Road & Street Capital Improvements | Q5: Other Governmental Funds | R5: Total Governmental Funds
A6: Assets:
B7: Cash | K7: 3791000 | O7: 696000 | P7: 689000 | Q7: 13466000 | R7: =SUM(K7:Q7) -> 18642000
B8: Investments | O8: 29084000 | P8: 22487000 | Q8: 3841000 | R8: =SUM(K8:Q8) -> 55412000
B9: Accounts receivable, net | K9: 13040000 | L9: 951000 | M9: 9783000 | N9: 25966000 | O9: 99675000 | P9: 92203000 | Q9: 194051000 | R9: =SUM(K9:Q9) -> 435669000
B10: Loans receivable | R10: =SUM(K10:Q10) -> 0
B11: Accounts receivable, net
C12: Interest | P12: 4000 | R12: =SUM(K12:Q12) -> 4000
C13: Ad valorem tax | K13: 4061000 | M13: 37591000 | N13: 20598000 | Q13: 114007000 | R13: =SUM(K13:Q13) -> 176257000
C14: Accounts | K14: 941000 | Q14: 4274000 | R14: =SUM(K14:Q14) -> 5215000
C15: Intergovernmental | K15: 13207000 | L15: 17365000 | M15: 183000 | N15: 65000 | O15: 7499000 | P15: 1477000 | Q15: 25300000 | R15: =SUM(K15:Q15) -> 65096000
B16: Inventories | Q16: 1739000 | R16: =SUM(K16:Q16) -> 1739000
B17: Deposits and other assets | K17: 1159000 | R17: =SUM(K17:N17) -> 1159000
E19: Total Assets: | K19: =SUM(K7:K17) -> 36199000 | L19: =SUM(L7:L17) -> 18316000 | M19: =SUM(M7:M17) -> 47557000 | N19: =SUM(N7:N17) -> 46629000 | O19: =SUM(O7:O17) -> 136954000 | P19: =SUM(P7:P17) -> 116860000 | Q19: =SUM(Q7:Q17) -> 356678000 | R19: =SUM(R7:R17) -> 759193000
A21: LIABILITIES AND FUND BALANCES
B22: Liabilities:
C23: Accounts and contracts payable | K23: 2024000 | L23: 3953000 | M23: 201000 | N23: 317000 | O23: 2630000 | P23: 7324000 | Q23: 19762000 | R23: =SUM(K23:Q23) -> 36211000
C24: Intergovernmental payable | K24: 25000 | L24: 236000 | O24: 2000 | Q24: 1926000 | R24: =SUM(K24:Q24) -> 2189000
C25: Due to other funds | L25: 10985000 | Q25: 591000 | R25: =SUM(K25:Q25) -> 11576000
C26: Deposits | K26: 81000 | R26: =SUM(K26:Q26) -> 81000
C27: Other payables and accruals | K27: 4036000 | R27: =SUM(K27:Q27) -> 4036000
E29: Total liabilities: | K29: =SUM(K23:K27) -> 6166000 | L29: =SUM(L23:L27) -> 15174000 | M29: =SUM(M23:M27) -> 201000 | N29: =SUM(N23:N27) -> 317000 | O29: =SUM(O23:O27) -> 2632000 | P29: =SUM(P23:P27) -> 7324000 | Q29: =SUM(Q23:Q27) -> 22279000 | R29: =SUM(R23:R27) -> 54093000
A31: DEFERRED INFLOWS OF RESOURCES
B32: Unavailable revenue-property taxes | K32: 4065000 | L32: 0 | M32: 37632000 | N32: 20617000 | O32: 3644000 | P32: 0 | Q32: 114112000 | R32: =SUM(K32:Q32) -> 180070000
E33: Total Deferred Inflows of Resources | K33: =SUM(K32) -> 4065000 | L33: 0 | M33: =SUM(M32) -> 37632000 | N33: =SUM(N32) -> 20617000 | O33: =SUM(O32) -> 3644000 | P33: 0 | Q33: =SUM(Q32) -> 114112000 | R33: =SUM(R32) -> 180070000
B35: Fund Balances
C36: Nonspendable | Q36: 1740000 | R36: =SUM(K36:Q36) -> 1740000
C37: Restricted | K37: 1681000 | L37: 3142000 | M37: 9724000 | N37: 25695000 | O37: 130678000 | P37: 109536000 | Q37: 124384000 | R37: =SUM(K37:Q37) -> 404840000
C38: Committed | K38: 9912000 | Q38: 94164000 | R38: =SUM(K38:Q38) -> 104076000
C39: Assigned | R39: =SUM(K39:Q39) -> 0
C40: Unassigned | K40: 14374000 | R40: =SUM(K40:N40) -> 14374000
E42: Total fund balance: | K42: =SUM(K36:K41) -> 25967000 | L42: =SUM(L37:L40) -> 3142000 | M42: =SUM(M36:M40) -> 9724000 | N42: =SUM(N37:N40) -> 25695000 | O42: =SUM(O36:O40) -> 130678000 | P42: =SUM(P36:P40) -> 109536000 | Q42: =SUM(Q36:Q40) -> 220288000 | R42: =SUM(R35:R40) -> 525030000
E44: Total liabilities and fund balances: | K44: =SUM(K42,K29,K33) -> 36198000 | L44: =SUM(L29,L42) -> 18316000 | M44: =SUM(M29,M42,M33) -> 47557000 | N44: =SUM(N29,N42,N33) -> 46629000 | O44: =SUM(O42+O29+O33) -> 136954000 | P44: =SUM(P42+P33+P29) -> 116860000 | Q44: =SUM(Q42+Q29+Q33) -> 356679000 | R44: =SUM(R29,R42,R33) -> 759193000

Sheet LaSalle
D1: LaSalle Combined Balance Sheet
D2: Issued: December 31, 2013
K4: General Fund | L4: Road and Bridge | M4: Courthouse Maintenance | N4: Garbage District | O4: Library | P4: Criminal Court | Q4: Other Governmental Funds | R4: Total Governmental Funds
A5: Assets:
B6: Cash and equivalents | K6: 346112 | M6: 32856 | N6: 264955 | O6: 964889 | Q6: 895887 | R6: =SUM(K6:Q6) -> 2504699
B7: Prepaid lease payments | N7: 3783 | Q7: 3693 | R7: =SUM(K7:Q7) -> 7476
B8: Receivables | K8: 377587 | L8: 657496 | M8: 501864 | N8: 620658 | O8: 588538 | P8: 792 | Q8: 619970 | R8: =SUM(K8:Q8) -> 3366905
E10: Total assets: | K10: =SUM(K6:K8) -> 723699 | L10: =SUM(L6:L8) -> 657496 | M10: =SUM(M6:M8) -> 534720 | N10: =SUM(N6:N8) -> 889396 | O10: =SUM(O6:O8) -> 1553427 | P10: =SUM(P6:P8) -> 792 | Q10: =SUM(Q6:Q8) -> 1519550 | R10: =SUM(R6:R8) -> 5879080
A12: LIABILITIES AND FUND BALANCES
B13: Liabilities:
C14: Cash overdraft | L14: 40657 | P14: 175701 | R14: =SUM(K14:Q14) -> 216358
C15: Accounts payable | K15: 63104 | L15: 36913 | M15: 35818 | N15: 49488 | O15: 25662 | P15: 14391 | Q15: 49656 | R15: =SUM(K15:Q15) -> 275032
C16: Salaries and related payable | K16: 28201 | L16: 3984 | M16: 635 | N16: 1062 | O16: 1576 | P16: 2182 | Q16: 215 | R16: =SUM(K16:Q16) -> 37855
E18: Total liabilities: | K18: =SUM(K14:K16) -> 91305 | L18: =SUM(L14:L16) -> 81554 | M18: =SUM(M14:M16) -> 36453 | N18: =SUM(N14:N16) -> 50550 | O18: =SUM(O14:O16) -> 27238 | P18: =SUM(P14:P16) -> 192274 | Q18: =SUM(Q14:Q16) -> 49871 | R18: =SUM(R14:R16) -> 529245
B20: Fund Balances:
C21: Nonspendable | N21: 9146 | Q21: 3693 | R21: =SUM(K21:Q21) -> 12839
C22: Restricted:
D23: Other general government | M23: 498267 | R23: =SUM(K23:Q23) -> 498267
D24: Public works | L24: 575942 | N24: 829700 | Q24: 1169692 | R24: =SUM(K24:Q24) -> 2575334
D25: Health and welfare | Q25: 211954 | R25: =SUM(K25:Q25) -> 211954
D26: Culture and recreation | O26: 1526189 | R26: =SUM(K26:Q26) -> 1526189
C27: Committed | K27: 4262 | Q27: 84340 | R27: =SUM(K27:Q27) -> 88602
C28: Unassigned | K28: 628132 | P28: -191482 | R28: =SUM(K28:Q28) -> 436650
E30: Total fund balance: | K30: =SUM(K21:K28) -> 632394 | L30: =SUM(L21:L28) -> 575942 | M30: =SUM(M21:M28) -> 498267 | N30: =SUM(N21:N28) -> 838846 | O30: =SUM(O21:O28) -> 1526189 | P30: =SUM(P21:P28) -> -191482 | Q30: =SUM(Q21:Q28) -> 1469679 | R30: =SUM(R21:R28) -> 5349835
E32: Total liabilities and fund balances: | K32: =K30+K18 -> 723699 | L32: =L30+L18 -> 657496 | M32: =M30+M18 -> 534720 | N32: =N30+N18 -> 889396 | O32: =O30+O18 -> 1553427 | P32: =P30+P18 -> 792 | Q32: =Q30+Q18 -> 1519550 | R32: =R30+R18 -> 5879080

Sheet Lafayette
D1: Lafayette Combined Balance Sheet
D2: Issued: October 31, 2013
K4: General | L4: Sales Tax Capital Improvements | M4: Other Governmental Funds | N4: Total Governmental Funds
A5: Assets:
B6: Cash | K6: 1116295 | L6: 1164918 | M6: 8483066 | N6: =SUM(K6:M6) -> 10764279
B7: Investments | K7: 26766265 | L7: 27360596 | M7: 217211552 | N7: =SUM(K7:M7) -> 271338413
B8: Accounts receivable, net | K8: 1424075 | L8: 5000 | M8: 565371 | N8: =SUM(K8:M8) -> 1994446
B9: Loans receivable | M9: 2203058 | N9: =SUM(K9:M9) -> 2203058
B10: Allowance for uncollectible loans | M10: -62647 | N10: =SUM(K10:M10) -> -62647
B11: Assessments receivable | M11: 273120 | N11: =SUM(K11:M11) -> 273120
B12: Accrued interest receivable | K12: 28651 | L12: 29288 | M12: 244031 | N12: =SUM(K12:M12) -> 301970
B13: Due from other funds | K13: 3771741 | L13: 4312314 | M13: 2542283 | N13: =SUM(K13:M13) -> 10626338
B14: Due from component units | K14: 177735 | N14: =SUM(K14:M14) -> 177735
B15: Due from other governmental agencies | K15: 878798 | M15: 10644753 | N15: =SUM(K15:M15) -> 11523551
B16: Inventories, at cost | L16: 238224 | M16: 21878 | N16: =SUM(K16:M16) -> 260102
B17: Prepaid items | K17: 2583 | M17: 44984 | N17: =SUM(K17:M17) -> 47567
E19: Total assets: | K19: =SUM(K6:K17) -> 34166143 | L19: =SUM(L6:L17) -> 33110340 | M19: =SUM(M6:M18) -> 242171449 | N19: =SUM(N6:N17) -> 309447932
A21: LIABILITIES AND FUND BALANCES
B22: Liabilities:
C23: Cash overdraft | M23: 2980058 | N23: =SUM(K23:M23) -> 2980058
C24: Accounts payable | K24: 868695 | L24: 665618 | M24: 1177697 | N24: =SUM(K24:M24) -> 2712010
C25: Accrued salaries and benefits | K25: 2321112 | L25: 110052 | M25: 855468 | N25: =SUM(K25:M25) -> 3286632
C26: Accrued liabilities | K26: 830783 | N26: =SUM(K26:M26) -> 830783
C27: Contracts payable | M27: 2352712 | N27: =SUM(K27:M27) -> 2352712
C28: Retainage payable | K28: 6238 | L28: 314687 | M28: 1746489 | N28: =SUM(K28:M28) -> 2067414
C29: Other payables | K29: 311513 | M29: 113872 | N29: =SUM(K29:M29) -> 425385
C30: Due to other funds | K30: 1089171 | L30: 89419 | M30: 9630932 | N30: =SUM(K30:M30) -> 10809522
C31: Due to component units | K31: 73188 | N31: =SUM(K31:M31) -> 73188
C32: Due to other governmental agencies | M32: 714973 | N32: =SUM(K32:M32) -> 714973
C33: Deferred revenue | K33: 6461 | L33: 31005 | M33: 243642 | N33: =SUM(K33:M33) -> 281108
E35: Total liabilities: | K35: =SUM(K23:K33) -> 5507161 | L35: =SUM(L23:L33) -> 1210781 | M35: =SUM(M23:M33) -> 19815843 | N35: =SUM(N23:N33) -> 26533785
B37: Fund Balances
C38: Nonspendable -
D39: Inventories | L39: 238224 | N39: =SUM(K39:M39) -> 238224
D40: Prepaid items | K40: 2583 | M40: 44984 | N40: =SUM(K40:M40) -> 47567
C41: Restricted -
D42: Debt service | M42: 46792726 | N42: =SUM(K42:M42) -> 46792726
C43: Committed -
D44: Incomplete projects | K44: 1281910 | L44: 19767085 | M44: 124687212 | N44: =SUM(K44:M44) -> 145736207
C45: Assigned -
D46: Capital expenditures | M46: 4698739 | N46: =SUM(K46:M46) -> 4698739
D47: Housing | M47: 3761469 | N47: =SUM(K47:M47) -> 3761469
D48: Subsequent year's expenditures | K48: 1158166 | L48: 11894250 | M48: 42370476 | N48: =SUM(K48:M48) -> 55422892
C49: Unassigned | K49: 26216323 | N49: =SUM(K49:M49) -> 26216323
E51: Total fund balance: | K51: =SUM(K39:K49) -> 28658982 | L51: =SUM(L39:L49) -> 31899559 | M51: =SUM(M39:M49) -> 222355606 | N51: =SUM(N38:N49) -> 282914147
E53: Total liabilities and fund balances: | K53: =SUM(K51,K35) -> 34166143 | L53: =SUM(L35,L51) -> 33110340 | M53: =SUM(M35,M51) -> 242171449 | N53: =SUM(N35,N51) -> 309447932

Sheet Lafourche
D1: Lafourche Combined Balance Sheet
D2: Issued: December 31, 2013
K4: Major Funds
K5: General | L5: Drainage Maintenance | M5: Solid Waste | N5: Library Commission | O5: 2005 Road Construction | P5: Capital Projects Fund | Q5: Non-Major Funds | R5: Total
A6: Assets:
B7: Cash and cash equivalents | K7: 2330101 | N7: 1019105 | O7: 20995597 | Q7: 3984822 | R7: =SUM(K7:Q7) -> 28329625
B8: Investments | K8: 91 | L8: 642 | M8: 81578 | N8: 7124638 | O8: 11697 | Q8: 12078923 | R8: =SUM(K8:Q8) -> 19297569
B9: Receivables | K9: 779641 | L9: 647944 | M9: 82716 | N9: 42010 | Q9: 964974 | R9: =SUM(K9:Q9) -> 2517285
B10: Due from other governmental units | K10: 6318575 | L10: 4887803 | M10: 1688238 | N10: 5271155 | Q10: 14478889 | R10: =SUM(K10:Q10) -> 32644660
B11: Due from other funds | K11: 12885548 | M11: 622673 | P11: 3414996 | Q11: 8503357 | R11: =SUM(K11:Q11) -> 25426574
B12: Other current assets | Q12: 1485383 | R12: =SUM(K12:Q12) -> 1485383
B13: Prepaid assets | K13: 17300 | N13: 14093 | R13: =SUM(K13:Q13) -> 31393
E15: Total Assets: | K15: =SUM(K7:K13) -> 22331256 | L15: =SUM(L7:L13) -> 5536389 | M15: =SUM(M7:M13) -> 2475205 | N15: =SUM(N7:N13) -> 13471001 | O15: =SUM(O7:O13) -> 21007294 | P15: =SUM(P7:P13) -> 3414996 | Q15: =SUM(Q7:Q13) -> 41496348 | R15: =SUM(R7:R13) -> 109732489
A17: LIABILITIES AND FUND BALANCES
B18: Liabilities:
C19: Accounts payable and accrued expenses | K19: 56171 | L19: 162307 | M19: 820457 | N19: 114107 | O19: 43622 | P19: 733933 | Q19: 537578 | R19: =SUM(K19:Q19) -> 2468175
C20: Contracts and retainages payable | K20: 84550 | L20: 25722 | P20: 3198341 | Q20: 374034 | R20: =SUM(K20:Q20) -> 3682647
C21: Salaries and benefits payable | K21: 294856 | L21: 129043 | M21: 9940 | N21: 173227 | Q21: 445189 | R21: =SUM(K21:Q21) -> 1052255
C22: Due to other funds | K22: 18666216 | L22: 3557972 | N22: 1459 | O22: 827488 | Q22: 3747173 | R22: =SUM(K22:Q22) -> 26800308
C23: Due to other governmental units | K23: 305633 | Q23: 78291 | R23: =SUM(K23:Q23) -> 383924
C24: Other current liabilities | K24: 2103 | Q24: 521619 | R24: =SUM(K24:Q24) -> 523722
E26: Total liabilities: | K26: =SUM(K19:K24) -> 19409529 | L26: =SUM(L19:L24) -> 3875044 | M26: =SUM(M19:M24) -> 830397 | N26: =SUM(N19:N24) -> 288793 | O26: =SUM(O19:O24) -> 871110 | P26: =SUM(P19:P24) -> 3932274 | Q26: =SUM(Q19:Q24) -> 5703884 | R26: =SUM(R19:R24) -> 34911031
B28: Fund Balances
C29: Non-spendable for prepaid assets | K29: 17300 | R29: =SUM(K29:Q29) -> 17300
C30: Restricted:
D31: Capital projects | O31: 20136184 | Q31: 11115521 | R31: =SUM(K31:Q31) -> 31251705
D32: Judicial programs | Q32: 2938694 | R32: =SUM(K32:Q32) -> 2938694
D33: Federal and state grant programs | Q33: 839005 | R33: =SUM(K33:Q33) -> 839005
D34: Debt service | Q34: 6243097 | R34: =SUM(K34:Q34) -> 6243097
C35: Commited:
D36: Public safety | Q36: 887397 | R36: =SUM(K36:Q36) -> 887397
D37: Public works | L37: 1661345 | M37: 1644808 | Q37: 9727815 | R37: =SUM(K37:Q37) -> 13033968
D38: Culture and recreation | N38: 13182208 | Q38: 1913162 | R38: =SUM(K38:Q38) -> 15095370
D39: Health and community services | Q39: 2141021 | R39: =SUM(K39:Q39) -> 2141021
C40: Unassigned | K40: 2904427 | P40: -517278 | Q40: -13248 | R40: =SUM(K40:Q40) -> 2373901
E42: Total fund balance: | K42: =SUM(K29:K41) -> 2921727 | L42: =SUM(L29:L40) -> 1661345 | M42: =SUM(M29:M40) -> 1644808 | N42: =SUM(N29:N40) -> 13182208 | O42: =SUM(O29:O40) -> 20136184 | P42: =SUM(P29:P40) -> -517278 | Q42: =SUM(Q29:Q40) -> 35792464 | R42: =SUM(R29:R40) -> 74821458
E44: Total liabilities and fund balances: | K44: =SUM(K42,K26) -> 22331256 | L44: =SUM(L26,L42) -> 5536389 | M44: =SUM(M26,M42) -> 2475205 | N44: =SUM(N26,N42) -> 13471001 | O44: =SUM(O26,O42) -> 21007294 | P44: =SUM(P26,P42) -> 3414996 | Q44: =SUM(Q26,Q42) -> 41496348 | R44: =SUM(R26,R42) -> 109732489

Sheet Lincoln
D1: Lincoln Combined Balance Sheet
D2: Issued: December 31, 2013
K4: General Fund | L4: Road Construction Fund | M4: Road Maintenance Fund | N4: Library Fund | O4: Solid Waste Disposal Fund | P4: Solid Waste Disposal Equipment Reserve Fund | Q4: Hospital Proceeds Fund | R4: Nonmajor Governmental Funds | S4: Total Governmental Funds
A5: Assets:
B6: Cash and cash equivalents | K6: 971435 | L6: 1517134 | M6: 1182154 | N6: 484535 | O6: 5111 | P6: 94773 | Q6: 516981 | R6: 4498578 | S6: =SUM(K6:R6) -> 9270701
B7: Investments | K7: 2056263 | L7: 530911 | M7: 1012717 | N7: 2414426 | P7: 2954793 | Q7: 9967615 | R7: 3489905 | S7: =SUM(K7:R7) -> 22426630
B8: Receivables | K8: 1108654 | L8: 1570816 | M8: 1570581 | N8: 1725722 | O8: 433301 | P8: 2345 | R8: 828019 | S8: =SUM(K8:R8) -> 7239438
B9: Prepaid expenses | K9: 3008 | S9: =SUM(K9:R9) -> 3008
B10: Due from other funds | K10: 122689 | L10: 4013 | M10: 4019 | N10: 6447 | O10: 3995 | R10: 1411322 | S10: =SUM(K10:R10) -> 1552485
B11: Due from other entities | K11: 233959 | L11: 184 | M11: 184 | R11: 471482 | S11: =SUM(K11:R11) -> 705809
B12: Inventory | L12: 11582 | S12: =SUM(K12:N12) -> 11582
E14: Total Assets: | K14: =SUM(K6:K12) -> 4496008 | L14: =SUM(L6:L12) -> 3634640 | M14: =SUM(M6:M12) -> 3769655 | N14: =SUM(N6:N12) -> 4631130 | O14: =SUM(O6:O12) -> 442407 | P14: =SUM(P6:P12) -> 3051911 | Q14: =SUM(Q6:Q12) -> 10484596 | R14: =SUM(R6:R12) -> 10699306 | S14: =SUM(S6:S12) -> 41209653
A16: LIABILITIES AND FUND BALANCES
B17: Liabilities:
C18: Accounts payable | K18: 284999 | L18: 64188 | M18: 265074 | N18: 107257 | O18: 391651 | Q18: 4486 | R18: 254826 | S18: =SUM(K18:R18) -> 1372481
C19: Due to other funds | K19: 488691 | Q19: 480110 | R19: 583684 | S19: =SUM(K19:R19) -> 1552485
C20: Due to other entities | K20: 390539 | R20: 939463 | S20: =SUM(K20:R20) -> 1330002
E22: Total liabilities: | K22: =SUM(K18:K20) -> 1164229 | L22: =SUM(L18:L20) -> 64188 | M22: =SUM(M18:M20) -> 265074 | N22: =SUM(N18:N20) -> 107257 | O22: =SUM(O18:O20) -> 391651 | P22: =SUM(P18:P20) -> 0 | Q22: =SUM(Q18:Q20) -> 484596 | R22: =SUM(R18:R20) -> 1777973 | S22: =SUM(S18:S20) -> 4254968
B24: Fund Balances
C25: Nonspendable | K25: 3008 | L25: 11582 | S25: =SUM(K25:R25) -> 14590
C26: Restricted | R26: 436325 | S26: =SUM(K26:R26) -> 436325
C27: Committed | S27: =SUM(K27:R27) -> 0
C28: Assigned | L28: 3558870 | M28: 3504581 | N28: 4523873 | O28: 50756 | P28: 3051911 | Q28: 10000000 | R28: 8485008 | S28: =SUM(K28:R28) -> 33174999
C29: Unassigned | K29: 3328771 | S29: =SUM(K29:N29) -> 3328771
E31: Total fund balance: | K31: =SUM(K25:K30) -> 3331779 | L31: =SUM(L25:L29) -> 3570452 | M31: =SUM(M25:M29) -> 3504581 | N31: =SUM(N25:N29) -> 4523873 | O31: =SUM(O25:O29) -> 50756 | P31: =SUM(P25:P29) -> 3051911 | Q31: =SUM(Q25:Q29) -> 10000000 | R31: =SUM(R25:R29) -> 8921333 | S31: =SUM(S24:S29) -> 36954685
E33: Total liabilities and fund balances: | K33: =K31+K22 -> 4496008 | L33: =L31+L22 -> 3634640 | M33: =M31+M22 -> 3769655 | N33: =N31+N22 -> 4631130 | O33: =O31+O22 -> 442407 | P33: =P31+P22 -> 3051911 | Q33: =Q31+Q22 -> 10484596 | R33: =R31+R22 -> 10699306 | S33: =S31+S22 -> 41209653

Sheet Livingston
D1: Livingston Combined Balance Sheet
D2: Issued: December 31, 2013
K4: Major Funds
K5: General | L5: Health Unit Fund | M5: Jail Sales Tax Fund | N5: Road Fund | O5: Courthouse Capital Outlay Fund | P5: Road 06 Sinking Fund | Q5: Other Governemntal Funds | R5: Total Governmental Funds
A6: Assets:
B7: Cash and cash equivalents | K7: 471368 | L7: 895643 | N7: 1128695 | Q7: 3013824 | R7: =SUM(K7:Q7) -> 5509530
B8: Investments | K8: 71227 | L8: 3067339 | N8: 268695 | R8: =SUM(K8:Q8) -> 3407261
B9: Receivables, net of allowance | K9: 489489 | L9: 40 | M9: 1222 | Q9: 421520 | R9: =SUM(K9:Q9) -> 912271
B10: Restricted assets: | R10: =SUM(K10:Q10) -> 0
C11: Cash | K11: 92784 | P11: 3341264 | Q11: 3437380 | R11: =SUM(K11:Q11) -> 6871428
C12: Investments | O12: 8630079 | R12: =SUM(K12:Q12) -> 8630079
B13: Inventory | M13: 18217 | N13: 168387 | R13: =SUM(K13:Q13) -> 186604
B14: Due from component units | Q14: 2945 | R14: =SUM(K14:Q14) -> 2945
B15: Due from other funds | K15: 4026470 | N15: 1388509 | Q15: 153329 | R15: =SUM(K15:Q15) -> 5568308
B16: Due from other governments | K16: 2236624 | L16: 1953706 | M16: 610687 | N16: 5276560 | Q16: 2242698 | R16: =SUM(K16:Q16) -> 12320275
B17: Advance to jail sales tax fund | K17: 3431708 | L17: 300000 | R17: =SUM(K17:N17) -> 3731708
E19: Total Assets: | K19: =SUM(K7:K17) -> 10819670 | L19: =SUM(L7:L17) -> 6216728 | M19: =SUM(M7:M17) -> 630126 | N19: =SUM(N7:N17) -> 8230846 | O19: =SUM(O7:O17) -> 8630079 | P19: =SUM(P7:P17) -> 3341264 | Q19: =SUM(Q7:Q17) -> 9271696 | R19: =SUM(R7:R17) -> 47140409
A21: LIABILITIES AND FUND BALANCES
B22: Liabilities:
C23: Accounts payables | K23: 908024 | L23: 11560 | M23: 211379 | N23: 152368 | O23: 2587318 | Q23: 1157813 | R23: =SUM(K23:Q23) -> 5028462
C24: Overdraft payable | M24: 898663 | Q24: 193903 | R24: =SUM(K24:Q24) -> 1092566
C25: Accrued expenses payable | K25: 171242 | L25: 42769 | M25: 28283 | N25: 217873 | Q25: 23625 | R25: =SUM(K25:Q25) -> 483792
C26: Due to component units | Q26: 25414 | R26: =SUM(K26:Q26) -> 25414
C27: Due to other governments | K27: 102933 | L27: 81657 | M27: 128301 | N27: 97464 | Q27: 164413 | R27: =SUM(K27:Q27) -> 574768
C28: Due to other funds | K28: 791277 | L28: 227549 | M28: 2624842 | N28: 1303434 | Q28: 398823 | R28: =SUM(K28:Q28) -> 5345925
C29: Unearned revenue | K29: 19700 | R29: =SUM(K29:Q29) -> 19700
C30: Advances from other funds | M30: 3731708 | R30: =SUM(K30:Q30) -> 3731708
E32: Total liabilities: | K32: =SUM(K23:K30) -> 1993176 | L32: =SUM(L23:L30) -> 363535 | M32: =SUM(M23:M30) -> 7623176 | N32: =SUM(N23:N30) -> 1771139 | O32: =SUM(O23:O30) -> 2587318 | P32: =SUM(P23:P30) -> 0 | Q32: =SUM(Q23:Q30) -> 1963991 | R32: =SUM(R23:R30) -> 16302335
B34: Fund Balances
C35: Non-spendable:
D36: Inventory | M36: 18217 | N36: 168387 | R36: =SUM(K36:Q36) -> 186604
D37: Advances | K37: 3431708 | L37: 300000 | R37: =SUM(K37:Q37) -> 3731708
C38: Restricted for:
D39: Construction | O39: 6042761 | Q39: 1450155 | R39: =SUM(K39:Q39) -> 7492916
D40: Criminal court | Q40: 7870 | R40: =SUM(K40:Q40) -> 7870
D41: Criminal court witness | Q41: 47125 | R41: =SUM(K41:Q41) -> 47125
D42: Debt service | P42: 3341264 | Q42: 5480322 | R42: =SUM(K42:Q42) -> 8821586
D43: Grant expenditures | K43: 92784 | R43: =SUM(K43:Q43) -> 92784
C44: Commited to:
D45: Construction | N45: 467590 | R45: =SUM(K45:Q45) -> 467590
D46: State grant programs | N46: 448367 | R46: =SUM(K46:Q46) -> 448367
D47: Federal grant programs | K47: 22500 | R47: =SUM(K47:Q47) -> 22500
D48: Other purposes | K48: 15233 | R48: =SUM(K48:Q48) -> 15233
C49: Assigned to:
D50: Bingo | Q50: 28140 | R50: =SUM(K50:Q50) -> 28140
D51: Construction | Q51: 238269 | R51: =SUM(K51:Q51) -> 238269
D52: Court fees | Q52: 351256 | R52: =SUM(K52:Q52) -> 351256
D53: Health unit | L53: 5553193 | R53: =SUM(K53:Q53) -> 5553193
D54: Road | N54: 5375363 | R54: =SUM(K54:Q54) -> 5375363
D55: Other purposes | K55: 248113 | Q55: 29957 | R55: =SUM(K55:Q55) -> 278070
C56: Unassigned | K56: 5016156 | M56: -7011267 | Q56: -325389 | R56: =SUM(K56:Q56) -> -2320500
E58: Total fund balance: | K58: =SUM(K35:K57) -> 8826494 | L58: =SUM(L36:L56) -> 5853193 | M58: =SUM(M35:M56) -> -6993050 | N58: =SUM(N36:N56) -> 6459707 | O58: =SUM(O36:O56) -> 6042761 | P58: =SUM(P36:P56) -> 3341264 | Q58: =SUM(Q36:Q56) -> 7307705 | R58: =SUM(R36:R56) -> 30838074
E60: Total liabilities and fund balances: | K60: =SUM(K58,K32) -> 10819670 | L60: =SUM(L32,L58) -> 6216728 | M60: =SUM(M32,M58) -> 630126 | N60: =SUM(N32,N58) -> 8230846 | O60: =SUM(O32,O58) -> 8630079 | P60: =SUM(P32,P58) -> 3341264 | Q60: =SUM(Q32,Q58) -> 9271696 | R60: =SUM(R32,R58) -> 47140409

Sheet Madison
D1: Madison Combined Balance Sheet
D2: Issued: December 31, 2013
K5: General Fund | L5: Library | M5: Garbage Maintenance | N5: Health Unit | O5: Public Works | P5: Courthouse and Jail | Q5: Other Governmental Funds | R5: Total Governmental Funds
A6: Assets:
B7: Cash and cash equivalents | K7: 144718 | L7: 484768 | M7: 1013880 | N7: 727316 | O7: 34490 | P7: 1544392 | Q7: 499366 | R7: =SUM(K7:Q7) -> 4448930
B8: Investments | L8: 251664 | P8: 2029651 | Q8: 668350 | R8: =SUM(K8:Q8) -> 2949665
B9: Receivables | K9: 548595 | L9: 553789 | M9: 523068 | N9: 271032 | O9: 1788708 | P9: 1424480 | Q9: 341373 | R9: =SUM(K9:Q9) -> 5451045
B10: Interfund receivables | K10: 276108 | P10: 1770 | Q10: 2074 | R10: =SUM(K10:Q10) -> 279952
E12: Total Assets: | K12: =SUM(K7:K10) -> 969421 | L12: =SUM(L7:L10) -> 1290221 | M12: =SUM(M7:M10) -> 1536948 | N12: =SUM(N7:N10) -> 998348 | O12: =SUM(O7:O10) -> 1823198 | P12: =SUM(P7:P10) -> 5000293 | Q12: =SUM(Q7:Q10) -> 1511163 | R12: =SUM(R7:R10) -> 13129592
A14: LIABILITIES AND FUND BALANCES
B15: Liabilities:
C16: Accounts, salaries and other payables | K16: 112032 | L16: 2638 | M16: 8136 | N16: 8152 | O16: 25667 | P16: 53814 | Q16: 62431 | R16: =SUM(K16:Q16) -> 272870
C17: Interfund payables | K17: 1770 | O17: 120015 | Q17: 158167 | R17: =SUM(K17:Q17) -> 279952
E19: Total liabilities: | K19: =SUM(K16:K17) -> 113802 | L19: =SUM(L16:L17) -> 2638 | M19: =SUM(M16:M17) -> 8136 | N19: =SUM(N16:N17) -> 8152 | O19: =SUM(O16:O17) -> 145682 | P19: =SUM(P16:P17) -> 53814 | Q19: =SUM(Q16:Q17) -> 220598 | R19: =SUM(R16:R17) -> 552822
B21: Fund Balances
C22: Restricted | L22: 1287583 | M22: 1528812 | N22: 990196 | O22: 1677516 | P22: 4946479 | Q22: 1290565 | R22: =SUM(K22:Q22) -> 11721151
C23: Unassigned | K23: 855619 | R23: =SUM(K23:Q23) -> 855619
E25: Total fund balance: | K25: =SUM(K22:K24) -> 855619 | L25: =SUM(L22:L23) -> 1287583 | M25: =SUM(M22:M23) -> 1528812 | N25: =SUM(N22:N23) -> 990196 | O25: =SUM(O22:O23) -> 1677516 | P25: =SUM(P22:P23) -> 4946479 | Q25: =SUM(Q22:Q23) -> 1290565 | R25: =SUM(R22:R23) -> 12576770
E27: Total liabilities and fund balances: | K27: =K25+K19 -> 969421 | L27: =L25+L19 -> 1290221 | M27: =M25+M19 -> 1536948 | N27: =N25+N19 -> 998348 | O27: =O25+O19 -> 1823198 | P27: =P25+P19 -> 5000293 | Q27: =Q25+Q19 -> 1511163 | R27: =R25+R19 -> 13129592

Sheet Morehouse
D1: Morehouse Combined Balance Sheet
D2: Issued: December 31, 2013
K5: General Fund | L5: Capital Projects | M5: Road Maintenance | N5: Drainage Maintenance | O5: Building Maintenance | P5: Solid Waste | Q5: Health Unit | R5: Criminal Court | S5: Other Governmental Funds | T5: Total Governmental Funds
A6: Assets:
B7: Cash | L7: 77 | M7: 742330 | N7: 992004 | P7: 1161580 | Q7: 675294 | S7: 283889 | T7: =SUM(K7:S7) -> 3855174
B8: Investments | K8: 25000 | M8: 100000 | N8: 375000 | Q8: 25000 | T8: =SUM(K8:S8) -> 525000
B9: Receivables | K9: 564067 | M9: 790942 | N9: 331287 | O9: 209135 | P9: 165 | Q9: 126251 | R9: 54015 | S9: 74876 | T9: =SUM(K9:S9) -> 2150738
B10: Due from other Funds | K10: 73462 | L10: 1500 | M10: 8697 | N10: 2603 | O10: 62359 | P10: 3548 | Q10: 1228 | R10: 2505 | T10: =SUM(K10:S10) -> 155902
E12: Total Assets: | K12: =SUM(K7:K10) -> 662529 | L12: =SUM(L7:L10) -> 1577 | M12: =SUM(M7:M10) -> 1641969 | N12: =SUM(N7:N10) -> 1700894 | O12: =SUM(O7:O10) -> 271494 | P12: =SUM(P7:P10) -> 1165293 | Q12: =SUM(Q7:Q10) -> 827773 | R12: =SUM(R7:R10) -> 56520 | ... T12: =SUM(T7:T10) -> 6686814
A14: LIABILITIES AND FUND BALANCES
B15: Liabilities:
C16: Bank overdraft | K16: 1557417 | O16: 187862 | R16: 321808 | T16: =SUM(K16:S16) -> 2067087
C17: Accounts payable | K17: 175162 | L17: 1500 | M17: 23895 | N17: 6698 | O17: 15935 | P17: 27865 | Q17: 332 | R17: 487 | S17: 1618 | T17: =SUM(K17:S17) -> 253492
C18: Payroll accruals and withholdings | K18: 23698 | R18: 3798 | T18: =SUM(K18:S18) -> 27496
C19: Due to other funds | K19: 49393 | M19: 13654 | N19: 2129 | O19: 3630 | P19: 8460 | Q19: 39389 | R19: 39247 | T19: =SUM(K19:S19) -> 155902
E21: Total liabilities: | K21: =SUM(K16:K19) -> 1805670 | L21: =SUM(L16:L19) -> 1500 | M21: =SUM(M16:M19) -> 37549 | N21: =SUM(N16:N19) -> 8827 | O21: =SUM(O16:O19) -> 207427 | P21: =SUM(P16:P19) -> 36325 | Q21: =SUM(Q16:Q19) -> 39721 | R21: =SUM(R16:R19) -> 365340 | ... T21: =SUM(T16:T19) -> 2503977
A23: DEFERRED INFLOWS OF RESOURCES
C24: Property taxes | K24: 529535 | M24: 779339 | N24: 356157 | O24: 226255 | Q24: 139666 | S24: 79616 | T24: =SUM(K24:S24) -> 2110568
B26: Fund Balances
C27: Restricted for special revenue | M27: 825081 | N27: 1335910 | P27: 1128968 | Q27: 648386 | S27: 277531 | T27: =SUM(K27:S27) -> 4215876
C28: Unassigned for special revenue | O28: -162188 | R28: -308820 | T28: =SUM(K28:S28) -> -471008
C29: Unassigned | K29: -1672676 | L29: 77 | T29: =SUM(K29:S29) -> -1672599
E31: Total fund balance: | K31: =SUM(K27:K30) -> -1672676 | L31: =SUM(L27:L29) -> 77 | M31: =SUM(M27:M29) -> 825081 | N31: =SUM(N27:N29) -> 1335910 | O31: =SUM(O27:O29) -> -162188 | P31: =SUM(P27:P29) -> 1128968 | Q31: =SUM(Q27:Q29) -> 648386 | R31: =SUM(R27:R29) -> -308820 | S31: =SUM(S27:S29) -> 277531 | T31: =SUM(T27:T29) -> 2072269
E33: Total liabilities and fund balances: | K33: =K31+K24+K21 -> 662529 | L33: =L31+L24+L21 -> 1577 | M33: =M31+M24+M21 -> 1641969 | N33: =N31+N24+N21 -> 1700894 | O33: =O31+O24+O21 -> 271494 | P33: =P31+P24+P21 -> 1165293 | Q33: =Q31+Q24+Q21 -> 827773 | R33: =R31+R24+R21 -> 56520 | ... T33: =T31+T24+T21 -> 6686814

Sheet Natchitoches
D1: Natchitoches Combined Balance Sheet
D2: Issued: December 31, 2013
K5: General Fund | L5: Road Maintenance Fund | M5: Sales Tax Fund | N5: Parish Library Fund | O5: Health Unit Fund | P5: Government Building Fund | Q5: Head Start Fund | R5: Nonmajor Funds | S5: Total Governmental Funds
A6: Assets:
B7: Cash and cash equivalents | K7: 711107 | L7: 1282630 | M7: 1443237 | N7: 1365273 | O7: 515770 | P7: 745674 | R7: 628623 | S7: =SUM(K7:R7) -> 6692314
B8: Revenue receivables | K8: 1066676 | L8: 1292764 | M8: 228799 | N8: 1994247 | O8: 805338 | P8: 805338 | Q8: 123038 | R8: 264776 | S8: =SUM(K8:R8) -> 6580976
B9: Due from other Funds | R9: 1000 | S9: =SUM(K9:R9) -> 1000
E11: Total Assets: | K11: =SUM(K7:K9) -> 1777783 | L11: =SUM(L7:L9) -> 2575394 | M11: =SUM(M7:M9) -> 1672036 | N11: =SUM(N7:N9) -> 3359520 | O11: =SUM(O7:O9) -> 1321108 | P11: =SUM(P7:P9) -> 1551012 | Q11: =SUM(Q7:Q9) -> 123038 | R11: =SUM(R7:R9) -> 894399 | S11: =SUM(S7:S9) -> 13274290
A13: LIABILITIES AND FUND BALANCES
B14: Liabilities:
C15: Cash overdraft | Q15: 5843 | R15: 21174 | S15: =SUM(K15:R15) -> 27017
C16: Accounts payable | K16: 316775 | L16: 74189 | N16: 29827 | O16: 22550 | P16: 19068 | Q16: 21324 | R16: 140061 | S16: =SUM(K16:R16) -> 623794
C17: Accrued payroll | K17: 30146 | L17: 40721 | N17: 81205 | O17: 10399 | P17: 8832 | Q17: 114780 | R17: 116378 | S17: =SUM(K17:R17) -> 402461
C18: Due to other governments | R18: 894223 | S18: =SUM(K18:R18) -> 894223
C19: Due to other funds | R19: 1000 | S19: =SUM(K19:R19) -> 1000
E21: Total liabilities: | K21: =SUM(K15:K19) -> 346921 | L21: =SUM(L15:L19) -> 114910 | M21: =SUM(M15:M19) -> 0 | N21: =SUM(N15:N19) -> 111032 | O21: =SUM(O15:O19) -> 32949 | P21: =SUM(P15:P19) -> 27900 | Q21: =SUM(Q15:Q19) -> 141947 | R21: =SUM(R15:R19) -> 1172836 | S21: =SUM(S15:S19) -> 1948495
B23: Fund Balances
C24: Restricted | L24: 2460484 | M24: 1672036 | N24: 3248488 | O24: 1288159 | P24: 1523112 | R24: 544187 | S24: =SUM(K24:R24) -> 10736466
C25: Unassigned | K25: 1430862 | Q25: -18909 | R25: -822624 | S25: =SUM(K25:R25) -> 589329
E27: Total fund balance: | K27: =SUM(K24:K26) -> 1430862 | L27: =SUM(L24:L25) -> 2460484 | M27: =SUM(M24:M25) -> 1672036 | N27: =SUM(N24:N25) -> 3248488 | O27: =SUM(O24:O25) -> 1288159 | P27: =SUM(P24:P25) -> 1523112 | Q27: =SUM(Q24:Q25) -> -18909 | R27: =SUM(R24:R25) -> -278437 | S27: =SUM(S24:S25) -> 11325795
E29: Total liabilities and fund balances: | K29: =K27+K21 -> 1777783 | L29: =L27+L21 -> 2575394 | M29: =M27+M21 -> 1672036 | N29: =N27+N21 -> 3359520 | O29: =O27+O21 -> 1321108 | P29: =P27+P21 -> 1551012 | Q29: =Q27+Q21 -> 123038 | R29: =R27+R21 -> 894399 | S29: =S27+S21 -> 13274290

Sheet Orleans
D1: Orleans Combined Balance Sheet
D2: Issued: December 31, 2012
I3: (amounts in thousands)
K5: General Fund | L5: HUD | M5: Federal UDAG | N5: FEMA | O5: Debt Service | P5: Capital Projects | Q5: Louisiana Office of Community Development | R5: Nonmajor Governmental | S5: Total Governmental Funds
A6: Assets:
B7: Cash and cash equivalents | K7: 13309000 | M7: 12815000 | O7: 360000 | P7: 13034000 | Q7: 1781000 | R7: 20826000 | S7: =SUM(K7:R7) -> 62125000
B8: Investments | K8: 1372000 | O8: 79535000 | P8: 73779000 | R8: 10958000 | S8: =SUM(K8:R8) -> 165644000
B9: Receivables (net of allowance for uncollectibles): | S9: =SUM(K9:R9) -> 0
C10: Sales taxes | K10: 17117000 | S10: =SUM(K10:R10) -> 17117000
C11: Property taxes | K11: 3806000 | O11: 2338000 | R11: 335000 | S11: =SUM(K11:R11) -> 6479000
C12: Franchise taxes | K12: 7847000 | S12: =SUM(K12:R12) -> 7847000
C13: Accounts | K13: 9112000 | L13: 153000 | P13: 1345000 | R13: 231000 | S13: =SUM(K13:R13) -> 10841000
C14: Grantee loans | M14: 1517000 | S14: =SUM(K14:R14) -> 1517000
C15: Interest | S15: =SUM(K15:R15) -> 0
B16: Due from other funds | K16: 29580000 | N16: 3935000 | P16: 28437000 | R16: 177000 | S16: =SUM(K16:R16) -> 62129000
B17: Due from other governments | K17: 1534000 | L17: 9005000 | N17: 6802000 | P17: 22754000 | Q17: 7709000 | R17: 5409000 | S17: =SUM(K17:R17) -> 53213000
B18: Due from component units | K18: 5308000 | P18: 14319000 | S18: =SUM(K18:R18) -> 19627000
B19: Advances to other funds | K19: 2000 | S19: =SUM(K19:R19) -> 2000
B20: Other assets | K20: 4000 | L20: 1000 | R20: 19000 | S20: =SUM(K20:R20) -> 24000
E22: Total Assets: | K22: =SUM(K7:K21) -> 88991000 | L22: =SUM(L7:L20) -> 9159000 | M22: =SUM(M7:M20) -> 14332000 | N22: =SUM(N7:N20) -> 10737000 | O22: =SUM(O7:O20) -> 82233000 | P22: =SUM(P7:P20) -> 153668000 | Q22: =SUM(Q7:Q20) -> 9490000 | R22: =SUM(R7:R20) -> 37955000 | S22: =SUM(S7:S20) -> 406565000
A24: LIABILITIES AND FUND BALANCES
B25: Liabilities:
C26: Accounts payable | K26: 32039000 | L26: 4768000 | N26: 2156000 | P26: 33546000 | Q26: 7366000 | R26: 5078000 | S26: =SUM(K26:R26) -> 84953000
C27: Retainages payable | P27: 3728000 | S27: =SUM(K27:R27) -> 3728000
C28: Accrued expenses | L28: 129000 | N28: 155000 | O28: 416000 | Q28: 94000 | R28: 207000 | S28: =SUM(K28:R28) -> 1001000
C29: Due to other funds | K29: 27449000 | L29: 7281000 | M29: 430000 | N29: 15815000 | P29: 3935000 | Q29: 243000 | R29: 6976000 | S29: =SUM(K29:R29) -> 62129000
C30: Due to other governments | K30: 3845000 | N30: 8018000 | Q30: 494000 | R30: 688000 | S30: =SUM(K30:R30) -> 13045000
C31: Due to component units | P31: 59000 | S31: =SUM(K31:R31) -> 59000
C32: Advances from other funds | R32: 2000 | S32: =SUM(K32:R32) -> 2000
C33: Unearned revenue | L33: 2744000 | S33: =SUM(K33:R33) -> 2744000
E35: Total liabilities: | K35: =SUM(K26:K33) -> 63333000 | L35: =SUM(L26:L33) -> 14922000 | M35: =SUM(M26:M31) -> 430000 | N35: =SUM(N26:N33) -> 26144000 | O35: =SUM(O26:O33) -> 416000 | P35: =SUM(P26:P34) -> 41268000 | Q35: =SUM(Q26:Q33) -> 8197000 | R35: =SUM(R26:R33) -> 12951000 | S35: =SUM(S26:S33) -> 167661000
A37: DEFERRED INFLOWS OF RESOURCES
C38: Unavailable revenue | K38: 8702000 | L38: 3136000 | N38: 3862000 | O38: 4058000 | P38: 33354000 | Q38: 3719000 | R38: 3047000 | S38: =SUM(K38:R38) -> 59878000
E40: Total deferred inflows of resources: | K40: =SUM(K38) -> 8702000 | L40: =SUM(L38) -> 3136000 | M40: =SUM(M38) -> 0 | N40: =SUM(N38) -> 3862000 | O40: =SUM(O38) -> 4058000 | P40: =SUM(P38) -> 33354000 | Q40: =SUM(Q38) -> 3719000 | R40: =SUM(R38) -> 3047000 | S40: =SUM(S38) -> 59878000
B42: Fund Balances
C43: Nonspendable | M43: 1517000 | R43: 890000 | S43: =SUM(K43:R43) -> 2407000
C44: Restricted | M44: 12385000 | O44: 77759000 | P44: 35445000 | R44: 11524000 | S44: =SUM(K44:R44) -> 137113000
C45: Committed | K45: 6036000 | P45: 43601000 | R45: 15281000 | S45: =SUM(K45:R45) -> 64918000
C46: Assigned | R46: 225000 | S46: =SUM(K46:R46) -> 225000
C47: Unassigned | K47: 10920000 | L47: -8899000 | N47: -19269000 | Q47: -2426000 | R47: -5963000 | S47: =SUM(K47:R47) -> -25637000
E49: Total fund balance: | K49: =SUM(K43:K48) -> 16956000 | L49: =SUM(L44:L47) -> -8899000 | M49: =SUM(M43:M47) -> 13902000 | N49: =SUM(N44:N47) -> -19269000 | O49: =SUM(O43:O47) -> 77759000 | P49: =SUM(P43:P47) -> 79046000 | Q49: =SUM(Q43:Q47) -> -2426000 | R49: =SUM(R43:R47) -> 21957000 | S49: =SUM(S42:S47) -> 179026000
E51: Total liabilities and fund balances: | K51: =SUM(K49+K35+K40) -> 88991000 | L51: =SUM(L49+L35+L40) -> 9159000 | M51: =SUM(M49+M35+M40) -> 14332000 | N51: =SUM(N49+N35+N40) -> 10737000 | O51: =SUM(O49+O35+O40) -> 82233000 | P51: =SUM(P49+P35+P40) -> 153668000 | Q51: =SUM(Q49+Q35+Q40) -> 9490000 | R51: =SUM(R49+R35+R40) -> 37955000 | S51: =SUM(S49+S35+S40) -> 406565000

Sheet Ouachita
D1: Ouachita Combined Balance Sheet
D2: Issued: December 31, 2013
K4: Major Funds
K5: General | L5: Public Works Fund | M5: Fire Protection District No. 1 Fund | N5: Public Library Fund | O5: Green Oaks Detention Center Fund | P5: Correctional Center Fund | Q5: Other Governemntal Funds | R5: Total Governmental Funds
A6: Assets:
B7: Cash and cash equivalents | K7: 2380204 | L7: 3228736 | M7: 3372706 | N7: 3034986 | O7: 2489341 | P7: 2747178 | Q7: 18935706 | R7: =SUM(K7:Q7) -> 36188857
B8: Investments | K8: 2750000 | M8: 5263974 | O8: 1250000 | Q8: 1250000 | R8: =SUM(K8:Q8) -> 10513974
B9: Receivables:
C10: Ad valorem taxes | K10: 2925265 | M10: 9018083 | N10: 6984184 | O10: 2468301 | P10: 8466355 | Q10: 1707734 | R10: =SUM(K10:Q10) -> 31569922
C11: Sales taxes | L11: 1140452 | M11: 1142548 | R11: =SUM(K11:Q11) -> 2283000
C12: Special assessments | L12: 7050 | Q12: 191018 | R12: =SUM(K12:Q12) -> 198068
C13: Other receivables | K13: 429040 | L13: 52943 | M13: 3699 | N13: 2448 | O13: 757 | P13: 40996 | Q13: 344861 | R13: =SUM(K13:Q13) -> 874744
B14: Due from other funds | K14: 1497763 | R14: =SUM(K14:Q14) -> 1497763
B15: Due from other governments | K15: 400993 | O15: 36637 | P15: 675508 | Q15: 3005576 | R15: =SUM(K15:Q15) -> 4118714
B16: Prepaid expenses and other assets | K16: 45 | N16: 200 | Q16: 68751 | R16: =SUM(K16:Q16) -> 68996
B17: Inventories | K17: 5747 | L17: 239283 | O17: 19844 | P17: 110862 | Q17: 234586 | R17: =SUM(K17:Q17) -> 610322
E19: Total Assets: | K19: =SUM(K7:K17) -> 10389057 | L19: =SUM(L7:L17) -> 4668464 | M19: =SUM(M7:M17) -> 18801010 | N19: =SUM(N7:N17) -> 10021818 | O19: =SUM(O7:O17) -> 6264880 | P19: =SUM(P7:P17) -> 12040899 | Q19: =SUM(Q7:Q17) -> 25738232 | R19: =SUM(R7:R17) -> 87924360
A21: LIABILITIES AND FUND BALANCES
B22: Liabilities:
C23: Accounts payable and accrued expenses | K23: 1001520 | L23: 387943 | M23: 619763 | N23: 441069 | O23: 188536 | P23: 736264 | Q23: 1818824 | R23: =SUM(K23:Q23) -> 5193919
C24: Due to other funds | K24: 138336 | Q24: 1413914 | R24: =SUM(K24:Q24) -> 1552250
C25: Unearned revenues | K25: 317461 | L25: 27555 | Q25: 950170 | R25: =SUM(K25:Q25) -> 1295186
C26: Deposits held | K26: 3470 | L26: 180079 | P26: 5542 | Q26: 10975 | R26: =SUM(K26:Q26) -> 200066
E28: Total liabilities: | K28: =SUM(K23:K26) -> 1460787 | L28: =SUM(L23:L26) -> 595577 | M28: =SUM(M23:M26) -> 619763 | N28: =SUM(N23:N26) -> 441069 | O28: =SUM(O23:O26) -> 188536 | P28: =SUM(P23:P26) -> 741806 | Q28: =SUM(Q23:Q26) -> 4193883 | R28: =SUM(R23:R26) -> 8241421
B30: Fund Balances
C31: Non-spendable:
D32: Prepaid expenses and other assets | K32: 45 | N32: 200 | Q32: 68751 | R32: =SUM(K32:Q32) -> 68996
D33: Inventories | K33: 5747 | L33: 239283 | O33: 19844 | P33: 110862 | Q33: 234586 | R33: =SUM(K33:Q33) -> 610322
C34: Spendable:
D35: Restricted | L35: 3833604 | M35: 18181247 | N35: 9580549 | O35: 6056500 | P35: 11188231 | Q35: 20583760 | R35: =SUM(K35:Q35) -> 69423891
D36: Committed | K36: 4101769 | Q36: 657252 | R36: =SUM(K36:Q36) -> 4759021
D37: Unassigned | K37: 4820709 | R37: =SUM(K37:Q37) -> 4820709
E39: Total fund balance: | K39: =SUM(K31:K38) -> 8928270 | L39: =SUM(L32:L37) -> 4072887 | M39: =SUM(M32:M37) -> 18181247 | N39: =SUM(N32:N37) -> 9580749 | O39: =SUM(O32:O37) -> 6076344 | P39: =SUM(P32:P37) -> 11299093 | Q39: =SUM(Q32:Q37) -> 21544349 | R39: =SUM(R32:R37) -> 79682939
E41: Total liabilities and fund balances: | K41: =SUM(K39,K28) -> 10389057 | L41: =SUM(L28,L39) -> 4668464 | M41: =SUM(M28,M39) -> 18801010 | N41: =SUM(N28,N39) -> 10021818 | O41: =SUM(O28,O39) -> 6264880 | P41: =SUM(P28,P39) -> 12040899 | Q41: =SUM(Q28,Q39) -> 25738232 | R41: =SUM(R28,R39) -> 87924360

Sheet Plaquemines
D1: Plaquemines Combined Balance Sheet
D2: Issued: December 31, 2013
K5: General Fund | L5: Road Maintenance | M5: Public Health | N5: Solid Waste | O5: Fire Fighting | P5: FEMA Management | Q5: Series 2012A Coastal Restorations | R5: Capital Improvements | S5: Other Governmental Funds | T5: Total Governmental Funds
A6: Assets:
B7: Cash and cash equivalents | K7: 15002557 | L7: 114796 | M7: 144637 | N7: 1101304 | O7: 12104008 | Q7: 59682371 | S7: 44555927 | T7: =SUM(K7:S7) -> 132705600
B8: Investments | K8: 876035 | L8: 3684 | N8: 20402 | O8: 93672 | S8: 4004663 | T8: =SUM(K8:S8) -> 4998456
B9: Receivables (net of allowances for uncollectibles) | K9: 19315448 | L9: 1727930 | M9: 1234709 | N9: 4360176 | O9: 1412201 | P9: 56363187 | S9: 6682251 | T9: =SUM(K9:S9) -> 91095902
B10: Due from other funds | K10: 42684293 | S10: 106839 | T10: =SUM(K10:S10) -> 42791132
B11: Prepaid items | K11: 904373 | T11: =SUM(K11:R11) -> 904373
B12: Interfund loan | K12: 2073727 | T12: =SUM(K12:R12) -> 2073727
E14: Total Assets: | K14: =SUM(K7:K12) -> 80856433 | L14: =SUM(L7:L12) -> 1846410 | M14: =SUM(M7:M12) -> 1379346 | N14: =SUM(N7:N12) -> 5481882 | O14: =SUM(O7:O12) -> 13609881 | P14: =SUM(P7:P12) -> 56363187 | Q14: =SUM(Q7:Q12) -> 59682371 | R14: =SUM(R7:R12) -> 0 | ... T14: =SUM(T7:T12) -> 274569190
A16: LIABILITIES AND FUND BALANCES
B17: Liabilities:
C18: Accounts, salaries and other payables | K18: 6960299 | L18: 53674 | M18: 61497 | N18: 200228 | O18: 901718 | P18: 6274036 | Q18: 309215 | S18: 4575140 | T18: =SUM(K18:S18) -> 19335807
C19: Unearned revenues | P19: 6684526 | T19: =SUM(K19:S19) -> 6684526
C20: Compensated absences payable | K20: 768053 | L20: 93237 | M20: 140608 | N20: 85558 | S20: 47400 | T20: =SUM(K20:S20) -> 1134856
C21: Deposits due others | K21: 51445 | M21: 880 | T21: =SUM(K21:S21) -> 52325
C22: Due to other funds | K22: 44918 | P22: 38314818 | Q22: 1307853 | S22: 3063543 | T22: =SUM(K22:S22) -> 42731132
C23: Other | K23: 839837 | L23: 47958 | M23: 31761 | N23: 126406 | O23: 5981 | S23: 53068 | T23: =SUM(K23:S23) -> 1105011
E25: Total liabilities: | K25: =SUM(K18:K23) -> 8664552 | L25: =SUM(L18:L23) -> 194869 | M25: =SUM(M18:M23) -> 234746 | N25: =SUM(N18:N24) -> 412192 | O25: =SUM(O18:O23) -> 907699 | P25: =SUM(P18:P23) -> 51273380 | Q25: =SUM(Q18:Q22) -> 1617068 | R25: =SUM(R18:R23) -> 0 | S25: =SUM(S18:S23) -> 7739151 | T25: =SUM(T18:T23) -> 71043657
A27: DEFERRED INFLOWS OF RESROUCES
C28: Deferred revenues | K28: 3757812 | L28: 1527566 | M28: 1011650 | N28: 4026287 | R28: 1613200 | S28: 5926915 | T28: =SUM(K28:S28) -> 17863430
B30: Fund Balances
C31: Non Spendable | K31: 2978100 | T31: =SUM(K31:R31) -> 2978100
C32: Restricted | K32: 2481206 | N32: 1038966 | O32: 12653272 | P32: 5089807 | Q32: 58065303 | S32: 46594679 | T32: =SUM(K32:S32) -> 125923233
C33: Committed | K33: 67089646 | T33: =SUM(K33:R33) -> 67089646
C34: Assigned | K34: 1672432 | L34: 123975 | M34: 132950 | N34: 4437 | O34: 48910 | S34: 4200 | T34: =SUM(K34:S34) -> 1986904
C35: Unassigned (Deficit) | K35: -5787315 | R35: -1613200 | S35: -4915265 | T35: =SUM(K35:S35) -> -12315780
E37: Total fund balance: | K37: =SUM(K31:K36) -> 68434069 | L37: =SUM(L31:L35) -> 123975 | M37: =SUM(M31:M35) -> 132950 | N37: =SUM(N31:N35) -> 1043403 | O37: =SUM(O31:O35) -> 12702182 | P37: =SUM(P31:P35) -> 5089807 | Q37: =SUM(Q31:Q35) -> 58065303 | R37: =SUM(R31:R35) -> -1613200 | S37: =SUM(S31:S35) -> 41683614 | T37: =SUM(T31:T35) -> 185662103
E39: Total liabilities and fund balances: | K39: =SUM(K37,K25,K28) -> 80856433 | L39: =SUM(L37,L25,L28) -> 1846410 | M39: =SUM(M37,M25,M28) -> 1379346 | N39: =SUM(N37,N25,N28) -> 5481882 | O39: =SUM(O37,O25,O28) -> 13609881 | P39: =SUM(P37,P25,P28) -> 56363187 | Q39: =SUM(Q37,Q25,Q28) -> 59682371 | R39: =SUM(R37,R25,R28) -> 0 | ... T39: =SUM(T37,T25,T28) -> 274569190

Sheet Pointe Coupee
D1: Pointe Coupee Combined Balance Sheet
D2: Issued: December 31, 2013
K5: General | L5: Drainage | M5: Roads and Bridges | N5: Pointe Coupee Library | O5: Detention Center | P5: Road Construction | Q5: Debt Service Road Improvement | R5: Other Governmental Funds | S5: Total Governmental Funds
A6: Assets:
B7: Cash and cash equivalents | K7: 237950 | L7: 732 | M7: 58223 | N7: 1174269 | O7: 623 | P7: 773131 | Q7: 182398 | R7: 50353 | S7: =SUM(K7:R7) -> 2477679
B8: Investments | N8: 702328 | S8: =SUM(K8:R8) -> 702328
B9: Accounts receivable, net | K9: 1370598 | L9: 103813 | N9: 1658671 | O9: 21308 | P9: 47592 | Q9: 178974 | R9: 67474 | S9: =SUM(K9:R9) -> 3448430
B10: Due from other governments | K10: 553559 | L10: 73613 | M10: 40398 | R10: 11523 | S10: =SUM(K10:R10) -> 679093
B11: Due from other funds | K11: 1918860 | Q11: 1190000 | R11: 174000 | S11: =SUM(K11:R11) -> 3282860
B12: Prepaid items | K12: 62339 | R12: 18 | S12: =SUM(K12:R12) -> 62357
B13: Other assets | K13: 8585 | L13: 13 | R13: 410 | S13: =SUM(K13:R13) -> 9008
E15: Total Assets: | K15: =SUM(K7:K13) -> 4151891 | L15: =SUM(L7:L13) -> 178171 | M15: =SUM(M7:M13) -> 98621 | N15: =SUM(N7:N13) -> 3535268 | O15: =SUM(O7:O13) -> 21931 | P15: =SUM(P7:P13) -> 820723 | Q15: =SUM(Q7:Q13) -> 1551372 | R15: =SUM(R7:R13) -> 303778 | S15: =SUM(S7:S13) -> 10661755
A17: LIABILITIES AND FUND BALANCES
B18: Liabilities:
C19: Accounts payable and accrued expenses | K19: 602549 | L19: 94425 | M19: 88579 | N19: 254546 | O19: 73264 | P19: 259240 | R19: 28602 | S19: =SUM(K19:R19) -> 1401205
C20: Due to other governments | K20: 421609 | O20: 1 | S20: =SUM(K20:R20) -> 421610
C21: Due to other funds | K21: 2976000 | L21: 92000 | O21: 925000 | P21: 122000 | R21: 14000 | S21: =SUM(K21:R21) -> 4129000
E23: Total liabilities: | K23: =SUM(K19:K21) -> 4000158 | L23: =SUM(L19:L21) -> 186425 | M23: =SUM(M19:M21) -> 88579 | N23: =SUM(N19:N22) -> 254546 | O23: =SUM(O19:O21) -> 998265 | P23: =SUM(P19:P21) -> 381240 | Q23: =SUM(Q19:Q21) -> 0 | R23: =SUM(R19:R21) -> 42602 | S23: =SUM(S19:S21) -> 5951815
A25: DEFERRED INFLOWS OF RESROUCES
C26: Grants received in advance | K26: 2473 | S26: =SUM(K26:R26) -> 2473
B28: Fund Balances
C29: Restricted | N29: 159340 | P29: 439483 | Q29: 1551372 | S29: =SUM(K29:R29) -> 2150195
C30: Committed | K30: 149260 | L30: -8254 | M30: 10042 | N30: 3121382 | R30: 261176 | S30: =SUM(K30:R30) -> 3533606
C31: Unassigned | O31: -976334 | S31: =SUM(K31:R31) -> -976334
E33: Total fund balance: | K33: =SUM(K29:K32) -> 149260 | L33: =SUM(L29:L31) -> -8254 | M33: =SUM(M29:M31) -> 10042 | N33: =SUM(N29:N31) -> 3280722 | O33: =SUM(O29:O31) -> -976334 | P33: =SUM(P29:P31) -> 439483 | Q33: =SUM(Q29:Q31) -> 1551372 | R33: =SUM(R29:R31) -> 261176 | S33: =SUM(S29:S31) -> 4707467
E35: Total liabilities and fund balances: | K35: =SUM(K33,K23,K26) -> 4151891 | L35: =SUM(L33,L23,L26) -> 178171 | M35: =SUM(M33,M23,M26) -> 98621 | N35: =SUM(N33,N23,N26) -> 3535268 | O35: =SUM(O33,O23,O26) -> 21931 | P35: =SUM(P33,P23,P26) -> 820723 | Q35: =SUM(Q33,Q23,Q26) -> 1551372 | R35: =SUM(R33,R23,R26) -> 303778 | S35: =SUM(S33,S23,S26) -> 10661755

Sheet Rapides
D1: Rapides Combined Balance Sheet
D2: Issued: December 31, 2013
K5: General Fund | L5: Road and Bridge Fund | M5: Fire Protection District No. 2 Fund | N5: Other Governmental Funds | O5: 2013 Total Governmental Funds | P5: 2012 Total Governmental Funds
A6: Assets:
B7: Cash and cash equivalents | K7: 3068852 | L7: 1122621 | M7: 4533386 | N7: 41299174 | O7: =SUM(K7:N7) -> 50024033 | P7: 25937860
B8: Receivables | K8: 2698736 | L8: 482191 | M8: 4522300 | N8: 14881844 | O8: =SUM(K8:N8) -> 22585071 | P8: 18491555
B9: Interfund receivables | K9: 83842 | N9: 22702 | O9: =SUM(K9:N9) -> 106544 | P9: 338529
B10: Other | N10: 492 | O10: =SUM(K10:N10) -> 492 | P10: 13514
E12: Total Assets: | K12: =SUM(K7:K10) -> 5851430 | L12: =SUM(L7:L9) -> 1604812 | M12: =SUM(M7:M9) -> 9055686 | N12: =SUM(N7:N10) -> 56204212 | O12: =SUM(O7:O9) -> 72715648 | P12: =SUM(P7:P10) -> 44781458
A14: LIABILITIES AND FUND BALANCES
B15: Liabilities:
C16: Accounts payable | K16: 568291 | L16: 17574 | M16: 201080 | N16: 489514 | O16: =SUM(K16:N16) -> 1276459 | P16: 618828
C17: Interfund payables | K17: 22702 | N17: 83842 | O17: =SUM(K17:N17) -> 106544 | P17: 338529
C18: Deferred revenues | N18: 1693311 | O18: =SUM(K18:N18) -> 1693311 | P18: 412472
E20: Total liabilities: | K20: =SUM(K16:K18) -> 590993 | L20: =SUM(L16:L18) -> 17574 | M20: =SUM(M16:M18) -> 201080 | N20: =SUM(N16:N18) -> 2266667 | O20: =SUM(O16:O18) -> 3076314 | P20: =SUM(P16:P18) -> 1369829
B22: Fund Balances
C23: Reserved for:
D24: Judicial | N24: 168416 | O24: =SUM(K24:N24) -> 168416 | P24: 184692
D25: Other general government | K25: 177898 | N25: 179080 | O25: =SUM(K25:N25) -> 356978 | P25: 192616
D26: Public safety | K26: 298273 | M26: 8854605 | N26: 11194167 | O26: =SUM(K26:N26) -> 20347045 | P26: 19732027
D27: Public works | L27: 1587239 | N27: 13436732 | O27: =SUM(K27:N27) -> 15023971 | P27: 14431426
D28: Health and welfare | N28: 3791353 | O28: =SUM(K28:N28) -> 3791353 | P28: 3544591
D29: Culture and recreation | N29: 22222089 | O29: =SUM(K29:N29) -> 22222089 | P29: 110389
D30: Debt service | N30: 2945708 | O30: =SUM(K30:N30) -> 2945708 | P30: 41385
D31: Employee benefits | K31: 998122 | O31: =SUM(K31:N31) -> 998122 | P31: 1040372
C32: Unassigned | K32: 3786144 | O32: =SUM(K32:N32) -> 3786144 | P32: 4134130
E34: Total fund balance: | K34: =SUM(K23:K32) -> 5260437 | L34: =SUM(L23:L32) -> 1587239 | M34: =SUM(M23:M32) -> 8854605 | N34: =SUM(N23:N32) -> 53937545 | O34: =SUM(O23:O32) -> 69639826 | P34: =SUM(P23:P33) -> 43411628
E36: Total liabilities and fund balances: | K36: =SUM(K34,K20) -> 5851430 | L36: =SUM(L20,L34) -> 1604813 | M36: =SUM(M20,M34) -> 9055685 | N36: =SUM(N20,N34) -> 56204212 | O36: =SUM(O20,O34) -> 72716140 | P36: =SUM(P20+P34) -> 44781457

Sheet Red River
D1: Red River Combined Balance Sheet
D2: Issued: December 31, 2013
K4: General | L4: Sales Tax Fund | M4: Ambulance Service Fund | N4: Library Fund | O4: Unit 1 Road Fund | P4: Other non-major Governmental Funds | Q4: Total
A5: Assets:
B6: Cash | K6: 4372969 | L6: 1146962 | M6: 3619573 | N6: 2554456 | O6: 576549 | P6: 2668650 | Q6: =SUM(K6:P6) -> 14939159
B7: Investments | L7: 10572611 | M7: 4469391 | N7: 645906 | P7: 239190 | Q7: =SUM(K7:P7) -> 15927098
B8: Receivables | K8: 1175017 | L8: 116314 | M8: 98041 | N8: 1572449 | O8: 57649 | P8: 1212392 | Q8: =SUM(K8:P8) -> 4231862
B9: Due from other funds | K9: 31662 | Q9: =SUM(K9:P9) -> 31662
B10: Prepaid expenses | K10: 9185 | M10: 8158 | P10: 2958 | Q10: =SUM(K10:P10) -> 20301
E12: Total Assets: | K12: =SUM(K6:K10) -> 5588833 | L12: =SUM(L6:L10) -> 11835887 | M12: =SUM(M6:M10) -> 8195163 | N12: =SUM(N6:N10) -> 4772811 | O12: =SUM(O6:O10) -> 634198 | P12: =SUM(P6:P10) -> 4123190 | Q12: =SUM(Q6:Q10) -> 35150082
A14: LIABILITIES AND FUND BALANCES
B15: Liabilities:
C16: Accounts payable and accrued expenses | K16: 143962 | M16: 23664 | N16: 84131 | O16: 85824 | P16: 44878 | Q16: =SUM(K16:P16) -> 382459
C17: Due to other funds | P17: 31662 | Q17: =SUM(K17:P17) -> 31662
E19: Total liabilities: | K19: =SUM(K16:K17) -> 143962 | L19: =SUM(L16:L17) -> 0 | M19: =SUM(M16:M17) -> 23664 | N19: =SUM(N16:N17) -> 84131 | O19: =SUM(O16:O17) -> 85824 | P19: =SUM(P16:P17) -> 76540 | Q19: =SUM(Q16:Q17) -> 414121
A21: DEFERRED INFLOWS OF RESOURCES | K21: 87620 | N21: 151269 | P21: 108114 | Q21: =SUM(K21:P21) -> 347003
B23: Fund Balances
C24: Nonspendable:
D25: Prepaid expenses | K25: 9185 | M25: 8158 | P25: 2958 | Q25: =SUM(K25:P25) -> 20301
C26: Spendable:
C27: Restricted:
D28: Dedicated property taxes | K28: 2588727 | N28: 4537411 | P28: 3087146 | Q28: =SUM(K28:P28) -> 10213284
D29: Dedicated sales taxes | M29: 6204590 | P29: 102438 | Q29: =SUM(K29:P29) -> 6307028
D30: Court fees for juror compensation | P30: 206111 | Q30: =SUM(K30:P30) -> 206111
D31: Federal and state grant programs | P31: 284597 | Q31: =SUM(K31:P31) -> 284597
C32: Committed:
D33: Criminal court costs | P33: 100151 | Q33: =SUM(K33:P33) -> 100151
D34: Ambulance services | M34: 1958751 | Q34: =SUM(K34:P34) -> 1958751
D35: Road maintenance and improvements | O35: 548374 | P35: 409 | Q35: =SUM(K35:P35) -> 548783
D36: Public facilities maintenance | P36: 154726 | Q36: =SUM(K36:P36) -> 154726
D37: Buildings and infrastructure | L37: 11835887 | Q37: =SUM(K37:P37) -> 11835887
C38: Unassigned | K38: 2759339 | Q38: =SUM(K38:P38) -> 2759339
E40: Total fund balance: | K40: =SUM(K25:K39) -> 5357251 | L40: =SUM(L25:L38) -> 11835887 | M40: =SUM(M25:M38) -> 8171499 | N40: =SUM(N25:N38) -> 4537411 | O40: =SUM(O25:O38) -> 548374 | P40: =SUM(P25:P38) -> 3938536 | Q40: =SUM(Q25:Q38) -> 34388958
E42: Total liabilities and fund balances: | K42: =K40+K21+K19 -> 5588833 | L42: =L40+L21+L19 -> 11835887 | M42: =M40+M21+M19 -> 8195163 | N42: =N40+N21+N19 -> 4772811 | O42: =O40+O21+O19 -> 634198 | P42: =P40+P21+P19 -> 4123190 | Q42: =Q40+Q21+Q19 -> 35150082

Sheet Richland
D1: Richland Combined Balance Sheet
D2: Issued: December 31, 2013
K5: General | L5: Capital Projects | M5: Road Maintenance | N5: Drainage Maintenance | O5: Library | P5: Other Governmental Funds | Q5: Total Governmental Funds
A6: Assets:
B7: Cash | K7: 1633419 | L7: 10760 | M7: 1368509 | N7: 1554023 | O7: 2672884 | P7: 637416 | Q7: =SUM(K7:P7) -> 7877011
B8: Receivables | K8: 1120447 | L8: 51750 | M8: 52545 | O8: 1343506 | P8: 235669 | Q8: =SUM(K8:P8) -> 2803917
B9: Due from other funds | N9: 8035 | O9: 3811 | P9: 690 | Q9: =SUM(K9:P9) -> 12536
E11: Total Assets: | K11: =SUM(K7:K9) -> 2753866 | L11: =SUM(L7:L9) -> 62510 | M11: =SUM(M7:M9) -> 1421054 | N11: =SUM(N7:N9) -> 1562058 | O11: =SUM(O7:O9) -> 4020201 | P11: =SUM(P7:P9) -> 873775 | Q11: =SUM(Q7:Q9) -> 10693464
A13: LIABILITIES AND FUND BALANCES
B14: Liabilities:
C15: Accounts payable | K15: 28572 | L15: 62510 | M15: 79535 | N15: 10947 | O15: 7993 | P15: 30278 | Q15: =SUM(K15:P15) -> 219835
C16: Payroll accruals and withholdings | K16: 94972 | Q16: =SUM(K16:P16) -> 94972
C17: Due to other funds | K17: 4501 | M17: 8035 | Q17: =SUM(K17:P17) -> 12536
E19: Total liabilities: | K19: =SUM(K15:K17) -> 128045 | L19: =SUM(L15:L17) -> 62510 | M19: =SUM(M15:M17) -> 87570 | N19: =SUM(N15:N18) -> 10947 | O19: =SUM(O15:O17) -> 7993 | P19: =SUM(P15:P17) -> 30278 | Q19: =SUM(Q15:Q17) -> 327343
A21: DEFERRED INFLOWS OF RESROUCES
C22: Property taxes | K22: 1101174 | O22: 1343506 | P22: 235669 | Q22: =SUM(K22:P22) -> 2680349
B24: Fund Balances
C25: Restricted for special revenue | M25: 1333484 | N25: 1551111 | O25: 2668702 | P25: 607828 | Q25: =SUM(K25:P25) -> 6161125
C26: Unassigned | K26: 1524647 | Q26: =SUM(K26:P26) -> 1524647
E28: Total fund balance: | K28: =SUM(K25:K27) -> 1524647 | L28: =SUM(L25:L26) -> 0 | M28: =SUM(M25:M26) -> 1333484 | N28: =SUM(N25:N26) -> 1551111 | O28: =SUM(O25:O26) -> 2668702 | P28: =SUM(P25:P26) -> 607828 | Q28: =SUM(Q25:Q26) -> 7685772
E30: Total liabilities and fund balances: | K30: =SUM(K28,K19,K22) -> 2753866 | L30: =SUM(L28,L19,L22) -> 62510 | M30: =SUM(M28,M19,M22) -> 1421054 | N30: =SUM(N28,N19,N22) -> 1562058 | O30: =SUM(O28,O19,O22) -> 4020201 | P30: =SUM(P28,P19,P22) -> 873775 | Q30: =SUM(Q28,Q19,Q22) -> 10693464

Sheet Sabine
D1: Sabine Combined Balance Sheet
D2: Issued: December 31, 2013
R4: Total
K5: General Fund | L5: Transportation Fund | M5: Sales Tax Fund | N5: Criminal Court Fund | O5: Road District Fund No. 20 | P5: Health Unit Fund | Q5: Other Governmental Funds | R5: 2013 | S5: 2012
A6: Assets:
B7: Cash and cash equivalents | K7: 3374636 | L7: 483394 | M7: 358657 | N7: 22023 | O7: 61038 | P7: 1767191 | Q7: 2864826 | R7: =SUM(K7:Q7) -> 8931765 | S7: 10539101
B8: Receivables | K8: 1303622 | L8: 57042 | M8: 6457 | N8: 10834 | O8: 72978 | P8: 154144 | Q8: 2310925 | R8: =SUM(K8:Q8) -> 3916002 | S8: 3153470
B9: Interfund receivables | K9: 59226 | R9: =SUM(K9:Q9) -> 59226 | S9: 58500
E11: Total Assets: | K11: =SUM(K7:K9) -> 4737484 | L11: =SUM(L7:L9) -> 540436 | M11: =SUM(M7:M9) -> 365114 | N11: =SUM(N7:N9) -> 32857 | O11: =SUM(O7:O9) -> 134016 | P11: =SUM(P7:P9) -> 1921335 | Q11: =SUM(Q7:Q9) -> 5175751 | R11: =SUM(R7:R9) -> 12906993 | S11: =SUM(S7:S9) -> 13751071
A13: LIABILITIES AND FUND BALANCES
B14: Liabilities:
C15: Accounts, salaries, and other payables | K15: 57685 | L15: 47072 | M15: 43307 | N15: 11360 | O15: 6426 | P15: 6108 | Q15: 580634 | R15: =SUM(K15:Q15) -> 752592 | S15: 822300
C16: Interfund payables | N16: 10748 | Q16: 48478 | R16: =SUM(K16:Q16) -> 59226 | S16: 58500
E18: Total liabilities: | K18: =SUM(K15:K16) -> 57685 | L18: =SUM(L15:L16) -> 47072 | M18: =SUM(M15:M16) -> 43307 | N18: =SUM(N15:N16) -> 22108 | O18: =SUM(O15:O16) -> 6426 | P18: =SUM(P15:P16) -> 6108 | Q18: =SUM(Q15:Q16) -> 629112 | R18: =SUM(R15:R16) -> 811818 | S18: =SUM(S15:S16) -> 880800
B20: Fund Balances
C21: Restricted for maintenance and operation | L21: 493364 | M21: 321806 | N21: 10749 | O21: 127590 | P21: 1915227 | Q21: 4595334 | R21: =SUM(K21:Q21) -> 7464070 | S21: 184692
C22: Unassigned | K22: 4679800 | Q22: -48696 | R22: =SUM(K22:Q22) -> 4631104 | S22: 4134130
E24: Total fund balance: | K24: =SUM(K21:K22) -> 4679800 | L24: =SUM(L21:L22) -> 493364 | M24: =SUM(M21:M22) -> 321806 | N24: =SUM(N21:N22) -> 10749 | O24: =SUM(O21:O22) -> 127590 | P24: =SUM(P21:P22) -> 1915227 | Q24: =SUM(Q21:Q22) -> 4546638 | R24: =SUM(R21:R22) -> 12095174 | S24: =SUM(S21:S23) -> 4318822
E26: Total liabilities and fund balances: | K26: =SUM(K24,K18) -> 4737485 | L26: =SUM(L18,L24) -> 540436 | M26: =SUM(M18,M24) -> 365113 | N26: =SUM(N18,N24) -> 32857 | O26: =SUM(O18,O24) -> 134016 | P26: =SUM(P18,P24) -> 1921335 | Q26: =SUM(Q18,Q24) -> 5175750 | R26: =SUM(R18,R24) -> 12906992 | S26: =SUM(S18+S24) -> 5199622

Sheet St. Bernard
D1: St. Bernard Combined Balance Sheet
D2: Issued: December 31, 2013
K5: General Fund | L5: CDBG Disaster Fund | M5: Disaster Recovery Fund | N5: Non-Major Governmental Funds | O5: Total Governmental Funds
A6: Assets:
B7: Cash and cash equivalents | K7: 4180606 | L7: 122278 | M7: 7487436 | N7: 19689446 | O7: =SUM(K7:N7) -> 31479766
B8: Investments - land held for sale | K8: 5326500 | O8: =SUM(K8:N8) -> 5326500
B9: Receivables: | O9: =SUM(K9:N9) -> 0
C10: Sales and use taxes | K10: 1729591 | N10: 576530 | O10: =SUM(K10:N10) -> 2306121
C11: Property taxes | K11: 804293 | N11: 11459352 | O11: =SUM(K11:N11) -> 12263645
C12: Cable franchise fees | K12: 99097 | O12: =SUM(K12:N12) -> 99097
C13: Intergovernmental | K13: 1393626 | L13: 3760961 | M13: 11764277 | N13: 1087389 | O13: =SUM(K13:N13) -> 18006253
C14: Other | K14: 391967 | N14: 1299016 | O14: =SUM(K14:N14) -> 1690983
B15: Due from other funds | K15: 9104788 | M15: 14025396 | N15: 3825691 | O15: =SUM(K15:N15) -> 26955875
B16: Prepaids | K16: 84990 | N16: 113744 | O16: =SUM(K16:N16) -> 198734
B17: Other assets | K17: 9714 | O17: =SUM(K17:N17) -> 9714
E19: Total Assets: | K19: =SUM(K7:K17) -> 23125172 | L19: =SUM(L7:L15) -> 3883239 | M19: =SUM(M7:M15) -> 33277109 | N19: =SUM(N7:N16) -> 38051168 | O19: =SUM(O7:O17) -> 98336688
A21: LIABILITIES AND FUND BALANCES
B22: Liabilities:
C23: Accounts payable | K23: 1710730 | L23: 2255110 | M23: 9055049 | N23: 3420121 | O23: =SUM(K23:N23) -> 16441010
C24: Retainage payable | K24: 20669 | L24: 1710274 | M24: 6097437 | N24: 221812 | O24: =SUM(K24:N24) -> 8050192
C25: Salaries and payroll deductions payable | K25: 528595 | N25: 839236 | O25: =SUM(K25:N25) -> 1367831
C26: Due to other funds | K26: 8760076 | L26: 58026 | M26: 14088714 | N26: 7057585 | O26: =SUM(K26:N26) -> 29964401
C27: Short-term certificates of indebtedness | K27: 3150000 | N27: 6206000 | O27: =SUM(K27:N27) -> 9356000
E29: Total liabilities: | K29: =SUM(K23:K27) -> 14170070 | L29: =SUM(L23:L27) -> 4023410 | M29: =SUM(M23:M27) -> 29241200 | N29: =SUM(N23:N27) -> 17744754 | O29: =SUM(O23:O27) -> 65179434
B31: Deferred Inflows | K31: 6342461 | L31: 2486566 | M31: 6810124 | N31: 2007573 | O31: =SUM(K31:N31) -> 17646724
B33: Fund Balances
C34: Nonspendable amounts:
D35: Prepaid items | K35: 84990 | N35: 113744 | O35: =SUM(K35:N35) -> 198734
C36: Restricted for:
D37: Mortgage refunding | K37: 91185 | O37: =SUM(K37:N37) -> 91185
D38: Debt service | N38: 1232224 | O38: =SUM(K38:N38) -> 1232224
D39: Federal programs | N39: 4324697 | O39: =SUM(K39:N39) -> 4324697
D40: Council on aging | N40: 383237 | O40: =SUM(K40:N40) -> 383237
D41: Road lighting | O41: =SUM(K41:N41) -> 0
D42: Health | N42: 795290 | O42: =SUM(K42:N42) -> 795290
D43: Communication | N43: 385777 | O43: =SUM(K43:N43) -> 385777
D44: Public safety | N44: 1805358 | O44: =SUM(K44:N44) -> 1805358
D45: Capital outlay | N45: 452609 | O45: =SUM(K45:N45) -> 452609
C46: Commited to:
D47: Capital outlay | N47: 1803029 | O47: =SUM(K47:N47) -> 1803029
C48: Assigned to:
D49: Court operations | N49: 138907 | O49: =SUM(K49:N49) -> 138907
D50: Recreation | N50: 1180614 | O50: =SUM(K50:N50) -> 1180614
D51: Recovery | N51: 5778104 | O51: =SUM(K51:N51) -> 5778104
C52: Unassigned | K52: 2436466 | L52: -2626737 | M52: -2774215 | N52: -94749 | O52: =SUM(K52:N52) -> -3059235
E54: Total fund balance: | K54: =SUM(K35:K52) -> 2612641 | L54: =SUM(L36:L52) -> -2626737 | M54: =SUM(M36:M52) -> -2774215 | N54: =SUM(N36:N52) -> 18185097 | O54: =SUM(O35:O53) -> 15510530
E56: Total liabilities and fund balances: | K56: =SUM(K54,K29,K31) -> 23125172 | L56: =SUM(L54,L29,L31) -> 3883239 | M56: =SUM(M54,M29,M31) -> 33277109 | N56: =SUM(N54,N29,N31) -> 37937424 | O56: =SUM(O54,O29,O31) -> 98336688

Sheet St. Charles
D1: St. Charles Combined Balance Sheet
D2: Issued: December 31, 2013
K5: General Fund | L5: Road & Drainage Maintenance & Operation | M5: Recreation Maintenance & Operation | N5: Sewer General Obligation Sinking | O5: Nonmajor Governmental Funds | P5: Total Governmental Funds
A6: Assets:
B7: Cash and Cash equivalents | K7: 1886129 | L7: 1518524 | M7: 970 | N7: 1595 | O7: 70261 | P7: =SUM(K7:O7) -> 3477479
B8: Investments | K8: 40234565 | L8: 33207131 | M8: 335100 | N8: 3818504 | O8: 8407062 | P8: =SUM(K8:O8) -> 86002362
B9: Receivables, net
C10: Ad valorem taxes | K10: 3701000 | L10: 6936000 | M10: 3468000 | N10: 3036000 | O10: 7761000 | P10: =SUM(K10:O10) -> 24902000
C11: Sales taxes | K11: 1604853 | L11: 1834115 | O11: 229265 | P11: =SUM(K11:O11) -> 3668233
C12: Accounts | K12: 21919 | M12: 1857 | P12: =SUM(K12:O12) -> 23776
C13: Other | K13: 1162159 | L13: 67242 | M13: 5479 | N13: 1819 | O13: 45583 | P13: =SUM(K13:O13) -> 1282282
B14: Due from other funds | K14: 12875 | L14: 170400 | O14: 17746 | P14: =SUM(K14:O14) -> 201021
B15: Due from component units | K15: 40 | P15: =SUM(K15:O15) -> 40
B16: Due from other governments | K16: 1143430 | L16: 1281960 | M16: 1888 | O16: 793149 | P16: =SUM(K16:O16) -> 3220427
B17: Prepaid fees | K17: 556807 | L17: 852 | M17: 1000 | O17: 1476 | P17: =SUM(K17:O17) -> 560135
B18: Other assets | K18: 2170 | L18: 1123 | M18: 450 | O18: 600 | P18: =SUM(K18:O18) -> 4343
E20: Total Assets: | K20: =SUM(K7:K18) -> 50325947 | L20: =SUM(L7:L18) -> 45017347 | M20: =SUM(M7:M18) -> 3814744 | N20: =SUM(N7:N18) -> 6857918 | O20: =SUM(O7:O18) -> 17326142 | P20: =SUM(P7:P18) -> 123342098
A22: LIABILITIES AND FUND BALANCES
B23: Liabilities:
D24: Accounts payable | K24: 3874507 | L24: 1451174 | M24: 159534 | N24: 152 | O24: 699121 | P24: =SUM(K24:O24) -> 6184488
D25: Contracts payable | K25: 39998 | L25: 312664 | M25: 13261 | P25: =SUM(K25:O25) -> 365923
D26: Due to other funds | K26: 52621 | L26: 4669 | M26: 654 | O26: 178821 | P26: =SUM(K26:O26) -> 236765
D27: Due to component units | O27: 85495 | P27: =SUM(K27:O27) -> 85495
D28: Due to other governments | K28: 97331 | L28: 93392 | O28: 179323 | P28: =SUM(K28:O28) -> 370046
D29: Other liabilities | K29: 852690 | L29: 251766 | M29: 50295 | O29: 70141 | P29: =SUM(K29:O29) -> 1224892
E31: Total liabilities: | K31: =SUM(K24:K29) -> 4917147 | L31: =SUM(L24:L29) -> 2113665 | M31: =SUM(M24:M29) -> 223744 | N31: =SUM(N24:N29) -> 152 | O31: =SUM(O24:O29) -> 1212901 | P31: =SUM(P24:P29) -> 8467609
A33: DEFERRED INFLOWS OF RESOURCES
D34: Advances | K34: 3857754 | L34: 6981699 | M34: 3468000 | N34: 3036000 | O34: 7767764 | P34: =SUM(K34:O34) -> 25111217
E36: Total deferred inflows of resources: | K36: =SUM(K34) -> 3857754 | L36: =SUM(L34) -> 6981699 | M36: =SUM(M34) -> 3468000 | N36: =SUM(N34) -> 3036000 | O36: =SUM(O34) -> 7767764 | P36: =SUM(P34) -> 25111217
B38: Fund Balances
C39: Nonspendable | K39: 556807 | L39: 852 | M39: 1000 | O39: 1476 | P39: =SUM(K39:O39) -> 560135
C40: Restricted | K40: 373827 | L40: 32059049 | N40: 3821766 | O40: 6849828 | P40: =SUM(K40:O40) -> 43104470
C41: Commited | K41: 11017325 | L41: 3862082 | M41: 122000 | O41: 1459907 | P41: =SUM(K41:O41) -> 16461314
C42: Assigned | K42: 21550766 | O42: 35742 | P42: =SUM(K42:O42) -> 21586508
C43: Unassigned | K43: 8052321 | O43: -1476 | P43: =SUM(K43:O43) -> 8050845
E45: Total fund balance: | K45: =SUM(K39:K43) -> 41551046 | L45: =SUM(L39:L43) -> 35921983 | M45: =SUM(M39:M43) -> 123000 | N45: =SUM(N40:N43) -> 3821766 | O45: =SUM(O39:O43) -> 8345477 | P45: =SUM(P39:P43) -> 89763272
E47: Total liabilities and fund balances: | K47: =SUM(K45,K31,K36) -> 50325947 | L47: =SUM(L45,L31,L36) -> 45017347 | M47: =SUM(M45,M31,M36) -> 3814744 | N47: =SUM(N45,N31,N36) -> 6857918 | O47: =SUM(O45,O31,O36) -> 17326142 | P47: =SUM(P45,P31,P36) -> 123342098

Sheet St. Helena
D1: St. Helena Combined Balance Sheet
D2: Issued: December 31, 2013
K4: General Fund | L4: Road Building & Maintenance Fund | M4: Solid Waste Fund | N4: CDBG Housing Fund | O4: LRA CDBG Fund | P4: Hospital Hazard Mitigation | Q4: Other Governmental Funds | R4: Total Governmental Funds
A5: Assets:
B6: Cash and equivalents | K6: 572576 | L6: 2615496 | M6: 1074056 | N6: 67853 | O6: 6121 | P6: 141712 | Q6: 1552353 | R6: =SUM(K6:Q6) -> 6030167
B7: Investments | M7: 425323 | Q7: 555285 | R7: =SUM(K7:Q7) -> 980608
B8: Receivables, net | K8: 362286 | L8: 535437 | M8: 59309 | N8: 34948 | O8: 52698 | P8: 9020 | Q8: 1164540 | R8: =SUM(K8:Q8) -> 2218238
B9: Due from other funds | K9: 224619 | Q9: 174716 | R9: =SUM(K9:Q9) -> 399335
B10: Restricted cash | Q10: 420892 | R10: =SUM(K10:Q10) -> 420892
E12: Total assets: | K12: =SUM(K6:K10) -> 1159481 | L12: =SUM(L6:L10) -> 3150933 | M12: =SUM(M6:M10) -> 1558688 | N12: =SUM(N6:N10) -> 102801 | O12: =SUM(O6:O10) -> 58819 | P12: =SUM(P6:P10) -> 150732 | Q12: =SUM(Q6:Q11) -> 3867786 | R12: =SUM(R6:R10) -> 10049240
A14: LIABILITIES AND FUND BALANCES
B15: Liabilities:
C16: Accounts payable | K16: 89242 | L16: 101578 | M16: 5253 | N16: 767 | O16: 123513 | P16: 12026 | Q16: 74899 | R16: =SUM(K16:Q16) -> 407278
C17: Other accrued liabilities | K17: 3751 | L17: 15962 | Q17: 40525 | R17: =SUM(K17:Q17) -> 60238
C18: Due to other funds | N18: 122139 | O18: 14706 | P18: 162492 | Q18: 99998 | R18: =SUM(K18:Q18) -> 399335
E20: Total liabilities: | K20: =SUM(K16:K18) -> 92993 | L20: =SUM(L16:L18) -> 117540 | M20: =SUM(M16:M18) -> 5253 | N20: =SUM(N16:N18) -> 122906 | O20: =SUM(O16:O18) -> 138219 | P20: =SUM(P16:P18) -> 174518 | Q20: =SUM(Q16:Q18) -> 215422 | R20: =SUM(R16:R18) -> 866851
B22: Fund Balances
C23: Restricted | L23: 3033393 | M23: 1553435 | Q23: 3769731 | R23: =SUM(K23:Q23) -> 8356559
C24: Unassigned | K24: 1066488 | N24: -20105 | O24: -79400 | P24: -23786 | Q24: -117367 | R24: =SUM(K24:Q24) -> 825830
E26: Total fund balance: | K26: =SUM(K23:K24) -> 1066488 | L26: =SUM(L23:L24) -> 3033393 | M26: =SUM(M23:M24) -> 1553435 | N26: =SUM(N23:N24) -> -20105 | O26: =SUM(O23:O24) -> -79400 | P26: =SUM(P23:P24) -> -23786 | Q26: =SUM(Q23:Q24) -> 3652364 | R26: =SUM(R23:R24) -> 9182389
E28: Total liabilities and fund balances: | K28: =SUM(K26,K20) -> 1159481 | L28: =SUM(L20,L26) -> 3150933 | M28: =SUM(M20,M26) -> 1558688 | N28: =SUM(N20,N26) -> 102801 | O28: =SUM(O20+O26) -> 58819 | P28: =SUM(P20+P26) -> 150732 | Q28: =SUM(Q20,Q26) -> 3867786 | R28: =SUM(R20,R26) -> 10049240

Sheet St. James
D1: St. James Combined Balance Sheet
D2: Issued: December 31, 2013
K5: General | L5: Wetlands Mitigation | M5: Courthouse, Jail, and Public Buildings Maintenance | N5: CDBG Diaster Recovery Projects | O5: Parishwide Road Improvement | P5: Other Governmental Funds | Q5: Totale Governmental Funds
A6: Assets:
B7: Cash and cash equivalents | K7: 4427207 | L7: 16964 | M7: 2217465 | N7: 10222 | O7: 1123344 | P7: 12364115 | Q7: =SUM(K7:P7) -> 20159317
B8: Investments | K8: 132105 | M8: 1121034 | P8: 8664579 | Q8: =SUM(K8:P8) -> 9917718
B9: Receivables (net of allowances for uncollectibles) | K9: 4627510 | M9: 2724967 | N9: 490221 | P9: 12082573 | Q9: =SUM(K9:P9) -> 19925271
B10: Due from other funds | K10: 671240 | L10: 500 | M10: 604976 | N10: 0 | P10: 48763 | Q10: =SUM(K10:P10) -> 1325479
B11: Inventory | K11: 35049 | Q11: =SUM(K11:P11) -> 35049
E13: Total Assets: | K13: =SUM(K7:K11) -> 9893111 | L13: =SUM(L7:L10) -> 17464 | M13: =SUM(M7:M10) -> 6668442 | N13: =SUM(N7:N10) -> 500443 | O13: =SUM(O7:O10) -> 1123344 | P13: =SUM(P7:P10) -> 33160030 | Q13: =SUM(Q7:Q11) -> 51362834
A15: LIABILITIES AND FUND BALANCES
B16: Liabilities:
C17: Accounts payable | K17: 1103652 | L17: 4732 | M17: 212243 | N17: 31182 | O17: 811197 | P17: 1085702 | Q17: =SUM(K17:P17) -> 3248708
C18: Payroll deductions and withholdings payable | K18: 151989 | M18: 43308 | P18: 298328 | Q18: =SUM(K18:P18) -> 493625
C19: Due to other funds | K19: 4684 | N19: 506377 | P19: 770431 | Q19: =SUM(K19:P19) -> 1281492
C20: Other liabilities | P20: 59973 | Q20: =SUM(K20:P20) -> 59973
E22: Total liabilities: | K22: =SUM(K17:K20) -> 1260325 | L22: =SUM(L17:L20) -> 4732 | M22: =SUM(M17:M20) -> 255551 | N22: =SUM(N17:N20) -> 537559 | O22: =SUM(O17:O20) -> 811197 | P22: =SUM(P17:P20) -> 2214434 | Q22: =SUM(Q17:Q20) -> 5083798
B24: Fund Balances
C25: Nonspendable -Inventory | K25: 35049 | Q25: =SUM(K25:P25) -> 35049
C26: Restricted for
D27: Culture and recreation | P27: 5902557 | Q27: =SUM(K27:P27) -> 5902557
D28: Debt service | P28: 1799099 | Q28: =SUM(K28:P28) -> 1799099
D29: Capital projects | P29: 1107620 | Q29: =SUM(K29:P29) -> 1107620
D30: Health and welfare | K30: 4370193 | P30: 1318493 | Q30: =SUM(K30:P30) -> 5688686
D31: Highways and streets | P31: 4446611 | Q31: =SUM(K31:P31) -> 4446611
D32: Public safety | P32: 12088337 | Q32: =SUM(K32:P32) -> 12088337
D33: Sanitation | P33: 3537788 | Q33: =SUM(K33:P33) -> 3537788
D34: Other purposes | M34: 6412891 | P34: 0 | Q34: =SUM(K34:P34) -> 6412891
C35: Commited for
D36: Judicial | P36: 479074 | Q36: =SUM(K36:P36) -> 479074
D37: Highways and streets | O37: 312147 | P37: 90270 | Q37: =SUM(K37:P37) -> 402417
D38: Public transportation | P38: 27385 | Q38: =SUM(K38:P38) -> 27385
C39: Assigned for
D40: Judicial | P40: 4819 | Q40: =SUM(K40:P40) -> 4819
D41: Health and welfare | P41: 9026 | Q41: =SUM(K41:P41) -> 9026
D42: Other purposes | L42: 12732 | P42: 134822 | Q42: =SUM(K42:P42) -> 147554
C43: Unassigned | K43: 4227544 | N43: -37116 | P43: -305 | Q43: =SUM(K43:P43) -> 4190123
E45: Total fund balance: | K45: =SUM(K25:K43) -> 8632786 | L45: =SUM(L26:L43) -> 12732 | M45: =SUM(M26:M43) -> 6412891 | N45: =SUM(N26:N43) -> -37116 | O45: =SUM(O26:O43) -> 312147 | P45: =SUM(P26:P43) -> 30945596 | Q45: =SUM(Q25:Q44) -> 46279036
E47: Total liabilities and fund balances: | K47: =SUM(K45,K22) -> 9893111 | L47: =SUM(L22,L45) -> 17464 | M47: =SUM(M22,M45) -> 6668442 | N47: =SUM(N22,N45) -> 500443 | O47: =SUM(O22,O45) -> 1123344 | P47: =SUM(P45+P22) -> 33160030 | Q47: =SUM(Q22+Q45) -> 51362834

Sheet St. John the Baptist
D1: St. John the Baptist Combined Balance Sheet
D2: Issued: December 31, 2013
K4: General Fund | L4: Sales Tax District | M4: Roads and Bridges | N4: 1992 General Obligation Sinking | O4: 2010 Sewer Construction Bond | P4: Non-Major Governmental Funds | Q4: Total Governmental Funds
A5: Assets:
B6: Cash and cash equivalents | K6: 161547 | L6: 7415314 | M6: 488643 | N6: 5951233 | O6: 13947003 | P6: 30282362 | Q6: =SUM(K6:P6) -> 58246102
B7: Receivables (net of allowances for uncollectible) | Q7: =SUM(K7:P7) -> 0
C8: Accounts | K8: 99973 | M8: 2152 | P8: 1342810 | Q8: =SUM(K8:P8) -> 1444935
C9: Ad valorem taxes | K9: 2129855 | N9: 5240979 | P9: 4531205 | Q9: =SUM(K9:P9) -> 11902039
C10: Sales and use taxes | K10: 17499 | L10: 1452780 | M10: 603362 | P10: 1407838 | Q10: =SUM(K10:P10) -> 3481479
C11: Other | M11: 216103 | P11: 99804 | Q11: =SUM(K11:P11) -> 315907
B12: Due from other funds | K12: 1689144 | L12: 1629607 | M12: 1818687 | P12: 692780 | Q12: =SUM(K12:P12) -> 5830218
B13: Due from other governments | K13: 48109 | M13: 698633 | P13: 35301 | Q13: =SUM(K13:P13) -> 782043
B14: Prepaid items | K14: 45599 | M14: 72560 | P14: 19701 | Q14: =SUM(K14:P14) -> 137860
E16: Total assets: | K16: =SUM(K6:K14) -> 4191726 | L16: =SUM(L6:L14) -> 10497701 | M16: =SUM(M6:M14) -> 3900140 | N16: =SUM(N6:N14) -> 11192212 | O16: =SUM(O6:O14) -> 13947003 | P16: =SUM(P6:P15) -> 38411801 | Q16: =SUM(Q6:Q14) -> 82140583
A18: LIABILITIES AND FUND BALANCES
B19: Liabilities:
C20: Accounts, salaries and other payables | K20: 617444 | M20: 1655831 | O20: 17573 | P20: 1465140 | Q20: =SUM(K20:P20) -> 3755988
C21: Contracts payable | M21: 19863 | P21: 58929 | Q21: =SUM(K21:P21) -> 78792
C22: Due to other funds | K22: 1393948 | L22: 700000 | M22: 515238 | P22: 2818688 | Q22: =SUM(K22:P22) -> 5427874
C23: Other liabilities | K23: 417 | P23: 53187 | Q23: =SUM(K23:P23) -> 53604
E25: Total liabilities: | K25: =SUM(K20:K23) -> 2011809 | L25: =SUM(L20:L22) -> 700000 | M25: =SUM(M20:M22) -> 2190932 | N25: =SUM(N20:N22) -> 0 | O25: =SUM(O20:O22) -> 17573 | P25: =SUM(P20:P23) -> 4395944 | Q25: =SUM(Q20:Q23) -> 9316258
A27: DEFERRED INFLOWS OF RESOURCES
C28: Unavailable revenue | M28: 187531 | Q28: =SUM(K28:P28) -> 187531
E30: Total deferred inflows of resources: | K30: =K28 -> 0 | L30: =SUM(L28) -> 0 | M30: =SUM(M28) -> 187531 | N30: =SUM(N28) -> 0 | O30: =SUM(O28) -> 0 | P30: =SUM(P28) -> 0 | Q30: =SUM(Q28) -> 187531
B32: Fund Balances
C33: Non-spendable: | K33: 45599 | M33: 72560 | P33: 19701 | Q33: =SUM(K33:P33) -> 137860
C34: Restricted | L34: 9797701 | M34: 1449117 | N34: 11192212 | P34: 34117159 | Q34: =SUM(K34:P34) -> 56556189
C35: Committed | O35: 13929430 | Q35: =SUM(K35:P35) -> 13929430
C36: Unassigned | K36: 2134318 | P36: -121003 | Q36: =SUM(K36:P36) -> 2013315
E38: Total fund balance: | K38: =SUM(K33:K36) -> 2179917 | L38: =SUM(L33:L36) -> 9797701 | M38: =SUM(M33:M36) -> 1521677 | N38: =SUM(N33:N36) -> 11192212 | O38: =SUM(O33:O36) -> 13929430 | P38: =SUM(P33:P36) -> 34015857 | Q38: =SUM(Q33:Q36) -> 72636794
E40: Total liabilities and fund balances: | K40: =SUM(K38,K25,K30) -> 4191726 | L40: =SUM(L38,L25,L30) -> 10497701 | M40: =SUM(M38,M25,M30) -> 3900140 | N40: =SUM(N38,N25,N30) -> 11192212 | O40: =SUM(O38,O25,O30) -> 13947003 | P40: =SUM(P38,P25,P30) -> 38411801 | Q40: =SUM(Q38,Q25,Q30) -> 82140583

Sheet St. Landry
D1: St. Landry Combined Balance Sheet
D2: Issued: December 31, 2013
K4: General Fund | L4: Road and Bridge Maintenance Fund | M4: Health Unit Maintenance Fund | N4: Airport Maintenance Fund | O4: LCDBG Disaster Recovery Fund | P4: Jail Tax Construction Fund | Q4: Other Governmental Funds | R4: Total Governmental Funds
A5: Assets:
B6: Cash and interest-bearing deposits | K6: 1006494 | L6: 74476 | M6: 56318 | N6: 10170 | O6: 4750 | Q6: 403056 | R6: =SUM(K6:Q6) -> 1555264
B7: Receivables | K7: 2266186 | L7: 138273 | M7: 1297324 | N7: 38070 | O7: 511211 | Q7: 1441141 | R7: =SUM(K7:Q7) -> 5692205
B8: Prepaid items | K8: 24303 | L8: 10682 | M8: 6405 | N8: 712 | Q8: 356 | R8: =SUM(K8:Q8) -> 42458
B9: Due from other funds | K9: 448010 | L9: 104 | M9: 110463 | O9: 4980 | Q9: 98906 | R9: =SUM(K9:Q9) -> 662463
B10: Due from agency funds | K10: 46354 | L10: 240833 | N10: 3067 | R10: =SUM(K10:Q10) -> 290254
B11: Due from component units | K11: 4357 | R11: =SUM(K11:Q11) -> 4357
B12: Due from other governments | K12: 20051 | R12: =SUM(K12:Q12) -> 20051
E14: Total assets: | K14: =SUM(K6:K12) -> 3815755 | L14: =SUM(L6:L12) -> 464368 | M14: =SUM(M6:M12) -> 1470510 | N14: =SUM(N6:N12) -> 52019 | O14: =SUM(O6:O12) -> 520941 | P14: =SUM(P6:P12) -> 0 | Q14: =SUM(Q6:Q13) -> 1943459 | R14: =SUM(R6:R12) -> 8267052
A16: LIABILITIES AND FUND BALANCES
B17: Liabilities:
C18: Accounts payable | K18: 635457 | L18: 314127 | M18: 98348 | N18: 34864 | O18: 738580 | Q18: 278707 | R18: =SUM(K18:Q18) -> 2100083
C19: Accrued expenditures | K19: 214419 | R19: =SUM(K19:Q19) -> 214419
C20: Defered revenue | N20: 4737 | R20: =SUM(K20:Q20) -> 4737
C21: Due to agency funds | K21: 95000 | R21: =SUM(K21:Q21) -> 95000
C22: Due to other funds | K22: 120622 | L22: 136307 | M22: 71354 | N22: 53081 | Q22: 281099 | R22: =SUM(K22:Q22) -> 662463
C23: Due to component units | K23: 6389 | R23: =SUM(K23:Q23) -> 6389
E25: Total liabilities: | K25: =SUM(K18:K23) -> 1071887 | L25: =SUM(L18:L23) -> 450434 | M25: =SUM(M18:M23) -> 169702 | N25: =SUM(N18:N23) -> 92682 | O25: =SUM(O18:O23) -> 738580 | P25: =SUM(P18:P23) -> 0 | Q25: =SUM(Q18:Q23) -> 559806 | R25: =SUM(R18:R23) -> 3083091
B27: Fund Balances
C28: Non-spendable:
D29: Prepaids | K29: 24303 | L29: 10682 | M29: 6405 | N29: 712 | Q29: 356 | R29: =SUM(K29:Q29) -> 42458
C30: Restricted for:
D31: Other general government | Q31: 143529 | R31: =SUM(K31:Q31) -> 143529
D32: Public works | Q32: 704905 | R32: =SUM(K32:Q32) -> 704905
D33: Prisoner expense and jury witness | K33: 413037 | R33: =SUM(K33:Q33) -> 413037
D34: Judicial expenses | K34: 25325 | R34: =SUM(K34:Q34) -> 25325
D35: Public safety | Q35: 461814 | R35: =SUM(K35:Q35) -> 461814
D36: Economic development | Q36: 37718 | R36: =SUM(K36:Q36) -> 37718
D37: Health and welfare | M37: 1294403 | R37: =SUM(K37:Q37) -> 1294403
D38: General contigencies | K38: 225153 | R38: =SUM(K38:Q38) -> 225153
D39: Capital projects | Q39: 2587 | R39: =SUM(K39:Q39) -> 2587
D40: Debt service | Q40: 34084 | R40: =SUM(K40:Q40) -> 34084
C41: Assigned to | R41: =SUM(K41:Q41) -> 0
D42: Road and drainage | K42: 5587 | L42: 3252 | R42: =SUM(K42:Q42) -> 8839
D43: Special events | K43: 865 | R43: =SUM(K43:Q43) -> 865
D44: Finance and administration | R44: =SUM(K44:Q44) -> 0
D45: Public works | K45: 148301 | R45: =SUM(K45:Q45) -> 148301
D46: Judicial expenses | K46: 164856 | R46: =SUM(K46:Q46) -> 164856
D47: Public safety | K47: 44708 | R47: =SUM(K47:Q47) -> 44708
C48: Unassigned | K48: 1691733 | N48: -41375 | O48: -217639 | Q48: -1340 | R48: =SUM(K48:Q48) -> 1431379
E50: Total fund balance: | K50: =SUM(K29:K48) -> 2743868 | L50: =SUM(L29:L48) -> 13934 | M50: =SUM(M29:M48) -> 1300808 | N50: =SUM(N29:N48) -> -40663 | O50: =SUM(O29:O48) -> -217639 | P50: =SUM(P29:P48) -> 0 | Q50: =SUM(Q29:Q48) -> 1383653 | R50: =SUM(R29:R48) -> 5183961
E52: Total liabilities and fund balances: | K52: =SUM(K50,K25) -> 3815755 | L52: =SUM(L25,L50) -> 464368 | M52: =SUM(M25,M50) -> 1470510 | N52: =SUM(N25,N50) -> 52019 | O52: =SUM(O25+O50) -> 520941 | P52: =SUM(P25+P50) -> 0 | Q52: =SUM(Q25,Q50) -> 1943459 | R52: =SUM(R25,R50) -> 8267052

Sheet St. Martin
D1: St. Martin Combined Balance Sheet
D2: Issued: December 31, 2013
K5: General Fund | L5: District #1 Sales Tax Revenue Fund | M5: District #2 Sales Tax Revenue Fund | N5: Public Works Fund | O5: Video Poker Fund | P5: Fire Protection Maintenance Fund | Q5: Health Unit Maintenance Fund | R5: Parishwide Bond Sinking Fund | S5: Road Construction Fund | T5: Construction Fund | U5: Capital Outlay Fund | V5: Other Governmental Funds | W5: Total Governmental Funds
A6: Assets:
B7: Cash and cash equivalents | K7: 5092141 | L7: 8633417 | M7: 7524292 | Q7: 55669 | R7: 135805 | S7: 952393 | T7: 11079 | V7: 743776 | W7: =SUM(K7:V7) -> 23148572
B8: Receivables | K8: 853321 | L8: 254460 | M8: 119088 | N8: 4093176 | O8: 144196 | P8: 1441613 | Q8: 850705 | R8: 1258801 | T8: 402078 | V8: 1587257 | W8: =SUM(K8:V8) -> 11004695
B9: Due from other governmental entities | K9: 183431 | W9: =SUM(K9:V9) -> 183431
B10: Due from other funds | N10: 3805601 | O10: 3110193 | P10: 1573308 | Q10: 1054661 | R10: 3072393 | V10: 3618368 | W10: =SUM(K10:V10) -> 16234524
E12: Total Assets: | K12: =SUM(K7:K10) -> 6128893 | L12: =SUM(L7:L10) -> 8887877 | M12: =SUM(M7:M10) -> 7643380 | N12: =SUM(N7:N10) -> 7898777 | O12: =SUM(O7:O10) -> 3254389 | P12: =SUM(P7:P10) -> 3014921 | Q12: =SUM(Q7:Q10) -> 1961035 | R12: =SUM(R7:R10) -> 4466999 | ... W12: =SUM(W7:W10) -> 50571222
A14: LIABILITIES AND FUND BALANCES
B15: Liabilities:
C16: Accounts payable | K16: 164488 | L16: 16100 | M16: 829 | N16: 64309 | P16: 51434 | Q16: 35314 | S16: 45773 | T16: 108820 | U16: 20984 | V16: 255550 | W16: =SUM(K16:V16) -> 763601
C17: Accrued liabilities | K17: 22095 | M17: 1202 | N17: 32798 | O17: 1465 | P17: 1181 | Q17: 12571 | V17: 20168 | W17: =SUM(K17:V17) -> 91480
C18: Due to other funds | K18: 1619718 | L18: 1546354 | M18: 4194714 | Q18: 1231186 | S18: 2352478 | T18: 1132578 | U18: 2553795 | V18: 1398811 | W18: =SUM(K18:V18) -> 16029634
C19: Due to other governmental entities | V19: 93304 | W19: =SUM(K19:V19) -> 93304
C20: Other liabilities | K20: 217436 | W20: =SUM(K20:V20) -> 217436
E22: Total liabilities: | K22: =SUM(K16:K20) -> 2023737 | L22: =SUM(L16:L20) -> 1562454 | M22: =SUM(M16:M20) -> 4196745 | N22: =SUM(N16:N20) -> 97107 | O22: =SUM(O16:O20) -> 1465 | P22: =SUM(P16:P20) -> 52615 | Q22: =SUM(Q16:Q20) -> 1279071 | R22: =SUM(R16:R20) -> 0 | ... W22: =SUM(W16:W20) -> 17195455
A24: DEFERRED INFLOWS OF RESOURCES:
C25: Unavailable revenues | K25: 46150 | M25: 24030 | N25: 105350 | P25: 48600 | Q25: 31138 | V25: 40030 | W25: =SUM(K25:V25) -> 295298
B27: Fund Balances:
C28: Restricted for:
D29: Sales tax dedications | L29: 7325423 | M29: 3422605 | W29: =SUM(K29:V29) -> 10748028
D30: Other general government | V30: 119840 | W30: =SUM(K30:V30) -> 119840
D31: Public works | N31: 7696320 | V31: 590667 | W31: =SUM(K31:V31) -> 8286987
D32: Public safety | P32: 2913706 | V32: 379995 | W32: =SUM(K32:V32) -> 3293701
D33: Economic development | V33: 1408560 | W33: =SUM(K33:V33) -> 1408560
D34: Health and welfare | Q34: 650826 | V34: 81171 | W34: =SUM(K34:V34) -> 731997
D35: Debt service | R35: 4466999 | V35: 141472 | W35: =SUM(K35:V35) -> 4608471
D36: Capital outlay | S36: -1445858 | W36: =SUM(K36:V36) -> -1445858
C37: Commited to: | W37: =SUM(K37:V37) -> 0
D38: Other general government | O38: 2920764 | V38: 223623 | W38: =SUM(K38:V38) -> 3144387
D39: Public works | O39: 150000 | V39: 316403 | W39: =SUM(K39:V39) -> 466403
D40: Public safety | O40: 78600 | W40: =SUM(K40:V40) -> 78600
D41: Economic development | O41: 103560 | W41: =SUM(K41:V41) -> 103560
D42: Capital outlay | W42: =SUM(K42:V42) -> 0
C43: Assigned to: | W43: =SUM(K43:V43) -> 0
D44: Economic development | V44: 1273149 | W44: =SUM(K44:V44) -> 1273149
D45: Debt service | V45: 18053 | W45: =SUM(K45:V45) -> 18053
C46: Unassigned | K46: 4059006 | T46: -828241 | U46: -2574779 | V46: -411395 | W46: =SUM(K46:V46) -> 244591
E48: Total fund balance: | K48: =SUM(K28:K46) -> 4059006 | L48: =SUM(L28:L46) -> 7325423 | M48: =SUM(M28:M46) -> 3422605 | N48: =SUM(N28:N46) -> 7696320 | O48: =SUM(O28:O46) -> 3252924 | P48: =SUM(P28:P46) -> 2913706 | Q48: =SUM(Q28:Q46) -> 650826 | R48: =SUM(R28:R46) -> 4466999 | ... W48: =SUM(W28:W46) -> 33080469
E50: Total liabilities and fund balances: | K50: =SUM(K48,K22,K25) -> 6128893 | L50: =SUM(L48,L22,L25) -> 8887877 | M50: =SUM(M48,M22,M25) -> 7643380 | N50: =SUM(N48,N22,N25) -> 7898777 | O50: =SUM(O48,O22,O25) -> 3254389 | P50: =SUM(P48,P22,P25) -> 3014921 | Q50: =SUM(Q48,Q22,Q25) -> 1961035 | R50: =SUM(R48,R22,R25) -> 4466999 | ... W50: =SUM(W48,W22,W25) -> 50571222

Sheet St. Mary
D1: St. Mary Combined Balance Sheet
D2: Issued: December 31, 2013
K5: General Fund | L5: Road Construction & Maintenance Fund | M5: Sanitation Fund | N5: Capital Improvement Fund | O5: CDBG Recovery Fund | P5: Combined Sewer Construction Fund | Q5: Other Governmental Funds | R5: Total Governmental Funds
A6: Assets:
B7: Cash and cash equivalents | K7: 224283 | L7: 122 | M7: 1 | O7: 125 | Q7: 4167813 | R7: =SUM(K7:Q7) -> 4392344
B8: Investments | L8: 210305 | M8: 1954939 | N8: 4484697 | P8: 4289816 | Q8: 3835744 | R8: =SUM(K8:Q8) -> 14775501
B9: Receivables (net of allowances for uncollectibles) | K9: 494223 | L9: 151285 | M9: 27301 | N9: 4668 | P9: 216891 | Q9: 272590 | R9: =SUM(K9:Q9) -> 1166958
B10: Due from component units | K10: 1572918 | L10: 2125 | M10: 236281 | N10: 2310 | P10: 162246 | R10: =SUM(K10:Q10) -> 1975880
B11: Due from other governments | K11: 3341998 | L11: 2724708 | M11: 609893 | N11: 1678153 | Q11: 2409504 | R11: =SUM(K11:Q11) -> 10764256
B12: Advance to other funds | K12: 246000 | L12: 1365519 | M12: 958000 | P12: 954310 | Q12: 986354 | R12: =SUM(K12:Q12) -> 4510183
B13: Other assets | Q13: 4220 | R13: =SUM(K13:Q13) -> 4220
E15: Total Assets: | K15: =SUM(K7:K13) -> 5879422 | L15: =SUM(L7:L13) -> 4454064 | M15: =SUM(M7:M13) -> 3786415 | N15: =SUM(N7:N13) -> 6169828 | O15: =SUM(O7:O13) -> 125 | P15: =SUM(P7:P13) -> 5623263 | Q15: =SUM(Q7:Q13) -> 11676225 | R15: =SUM(R7:R13) -> 37589342
A17: LIABILITIES AND FUND BALANCES
B18: Liabilities:
C19: Accounts payable | K19: 407973 | L19: 24130 | M19: 193945 | N19: 167735 | Q19: 289763 | R19: =SUM(K19:Q19) -> 1083546
C20: Retainage payable | N20: 159540 | R20: =SUM(K20:Q20) -> 159540
C21: Accrued liabilities | K21: 227211 | L21: 88581 | M21: 2769 | Q21: 109630 | R21: =SUM(K21:Q21) -> 428191
C22: Due to other governments | Q22: 673621 | R22: =SUM(K22:Q22) -> 673621
C23: Advance from other funds | K23: 3391452 | L23: 123000 | M23: 1702378 | N23: 2280642 | P23: 4473594 | Q23: 650290 | R23: =SUM(K23:Q23) -> 12621356
E25: Total liabilities: | K25: =SUM(K19:K23) -> 4026636 | L25: =SUM(L19:L23) -> 235711 | M25: =SUM(M19:M23) -> 1899092 | N25: =SUM(N19:N23) -> 2607917 | O25: =SUM(O19:O23) -> 0 | P25: =SUM(P19:P23) -> 4473594 | Q25: =SUM(Q19:Q23) -> 1723304 | R25: =SUM(R19:R23) -> 14966254
B27: Fund Balances (deficit)
C28: Nonspendable - non-current receivables | K28: 1550000 | L28: 958000 | Q28: 268276 | R28: =SUM(K28:Q28) -> 2776276
C29: Restricted for
D30: Use in specific geographic areas | Q30: 1657063 | R30: =SUM(K30:Q30) -> 1657063
D31: Debt service | Q31: 2600321 | R31: =SUM(K31:Q31) -> 2600321
C32: Commited - public safety | Q32: 832832 | R32: =SUM(K32:Q32) -> 832832
C33: Assigned for
D34: General Government | Q34: 99989 | R34: =SUM(K34:Q34) -> 99989
D35: Public safety | Q35: 60557 | R35: =SUM(K35:Q35) -> 60557
D36: Public works | L36: 3260353 | Q36: 150478 | R36: =SUM(K36:Q36) -> 3410831
D37: Culture & recreation | Q37: 271656 | R37: =SUM(K37:Q37) -> 271656
D38: Health and welfare | Q38: 510139 | R38: =SUM(K38:Q38) -> 510139
D39: Urban redevelopment & housing | Q39: 592 | R39: =SUM(K39:Q39) -> 592
D40: Debt service | Q40: 3332035 | R40: =SUM(K40:Q40) -> 3332035
D41: Capital projects | N41: 3561911 | O41: 125 | P41: 1149669 | Q41: 288837 | R41: =SUM(K41:Q41) -> 5000542
D42: Sanitation | M42: 1887323 | R42: =SUM(K42:Q42) -> 1887323
C43: Unassigned | K43: 302786 | Q43: -119854 | R43: =SUM(K43:Q43) -> 182932
E45: Total fund balance: | K45: =SUM(K28:K43) -> 1852786 | L45: =SUM(L28:L43) -> 4218353 | M45: =SUM(M28:M43) -> 1887323 | N45: =SUM(N28:N43) -> 3561911 | O45: =SUM(O28:O43) -> 125 | P45: =SUM(P28:P43) -> 1149669 | Q45: =SUM(Q28:Q44) -> 9952921 | R45: =SUM(R28:R43) -> 22623088
E47: Total liabilities and fund balances: | K47: =SUM(K45,K25) -> 5879422 | L47: =SUM(L25,L45) -> 4454064 | M47: =SUM(M25,M45) -> 3786415 | N47: =SUM(N25,N45) -> 6169828 | O47: =SUM(O25+O45) -> 125 | P47: =SUM(P45+P25) -> 5623263 | Q47: =SUM(Q25+Q45) -> 11676225 | R47: =SUM(R25,R45) -> 37589342

Sheet St. Tammany
D1: St.Tammany Combined Balance Sheet
D2: Issued: December 31, 2013
K4: Major Funds
K5: 010, 012 General Fund | L5: 013 St. Tammany Parish Library | M5: 015 Public Works | N5: Capital Improvements - General | O5: Total Non-Major Governmental Funds | P5: Total Governmental Funds
A6: Assets:
B7: Cash and Cash equivalents | K7: 937582 | L7: 450596 | M7: 788818 | N7: 1244542 | O7: 28286428 | P7: =SUM(K7:O7) -> 31707966
B8: Investments | K8: 6644390 | M8: 15634184 | N8: 29648369 | O8: 69944229 | P8: =SUM(K8:O8) -> 121871172
B9: Receivables, net of allowances for uncollectibles:
C10: Ad valorem/parcel fees | K10: 4175901 | L10: 8607566 | O10: 15671824 | P10: =SUM(K10:O10) -> 28455291
C11: Sales and use tax | M11: 7014271 | O11: 3966853 | P11: =SUM(K11:O11) -> 10981124
C12: Other | K12: 1714035 | L12: 141173 | M12: 355481 | N12: 89154 | O12: 8015915 | P12: =SUM(K12:O12) -> 10315758
B13: Due from component units | K13: 24006 | P13: =SUM(K13:O13) -> 24006
B14: Prepaid items | K14: 5861 | M14: 3359 | O14: 5883 | P14: =SUM(K14:O14) -> 15103
B15: Restricted assets | O15: 9765448 | P15: =SUM(K15:O15) -> 9765448
E17: Total Assets: | K17: =SUM(K7:K15) -> 13501775 | L17: =SUM(L7:L15) -> 9199335 | M17: =SUM(M7:M15) -> 23796113 | N17: =SUM(N7:N15) -> 30982065 | O17: =SUM(O7:O15) -> 135656580 | P17: =SUM(P7:P15) -> 213135868
A19: LIABILITIES AND FUND BALANCES
B20: Liabilities:
C21: Accounts, salaries, and other payables | K21: 1969499 | L21: 643611 | M21: 1274720 | N21: 2550649 | O21: 12688157 | P21: =SUM(K21:O21) -> 19126636
C22: Due to other funds | O22: 1822508 | P22: =SUM(K22:O22) -> 1822508
C23: Due to component units | L23: 8555724 | P23: =SUM(K23:O23) -> 8555724
C24: Unearned revenue | K24: 8410 | M24: 266990 | O24: 3216506 | P24: =SUM(K24:O24) -> 3491906
C25: Other liabilities | K25: 1513798 | M25: 28500 | O25: 692804 | P25: =SUM(K25:O25) -> 2235102
E27: Total liabilities: | K27: =SUM(K21:K25) -> 3491707 | L27: =SUM(L21:L25) -> 9199335 | M27: =SUM(M21:M25) -> 1570210 | N27: =SUM(N21:N25) -> 2550649 | O27: =SUM(O21:O25) -> 18419975 | P27: =SUM(P21:P25) -> 35231876
B29: Fund Balances
C30: Nonspendable, prepaid items | K30: 5861 | M30: 3359 | O30: 5883 | P30: =SUM(K30:O30) -> 15103
C31: Restricted | M31: 21508462 | N31: 28431416 | O31: 93923422 | P31: =SUM(K31:O31) -> 143863300
C32: Commited | M32: 714082 | O32: 23307300 | P32: =SUM(K32:O32) -> 24021382
C33: Unassigned | K33: 10004207 | P33: =SUM(K33:O33) -> 10004207
E35: Total fund balance: | K35: =SUM(K30:K33) -> 10010068 | L35: =SUM(L30:L33) -> 0 | M35: =SUM(M30:M33) -> 22225903 | N35: =SUM(N30:N33) -> 28431416 | O35: =SUM(O30:O33) -> 117236605 | P35: =SUM(P30:P33) -> 177903992
E37: Total liabilities and fund balances: | K37: =SUM(K35,K27) -> 13501775 | L37: =SUM(L27,L35) -> 9199335 | M37: =SUM(M27,M35) -> 23796113 | N37: =SUM(N27+N35) -> 30982065 | O37: =SUM(O35+O27) -> 135656580
P41: 390668633
P45: 44174936
P48: -95974121
P49: 516773440

Sheet Tangipahoa
D1: Tangipahoa Combined Balance Sheet
D2: Issued: December 31, 2013
K5: General Fund | L5: Road and Bridge Funds | M5: Garbage District No. 1 | N5: Health Unit | O5: Long Term Recovery Fund | P5: Other Governmental Funds | Q5: Total Governmental Funds
A6: Assets:
B7: Cash and Cash equivalents | K7: 88217 | L7: 9236318 | M7: 2147274 | N7: 732325 | O7: 1045110 | P7: 3900107 | Q7: =SUM(K7:P7) -> 17149351
B8: Receivables, net | K8: 1760197 | L8: 1201824 | M8: 2721552 | N8: 2017555 | O8: 402248 | P8: 830272 | Q8: =SUM(K8:P8) -> 8933648
B9: Due from other governments | K9: 42692 | Q9: =SUM(K9:P9) -> 42692
B10: Due from other funds | K10: 328100 | N10: 350000 | P10: 32235 | Q10: =SUM(K10:P10) -> 710335
B11: Restricted assets - cash | K11: 511411 | L11: 77831 | M11: 223918 | N11: 14965 | P11: 61448 | Q11: =SUM(K11:P11) -> 889573
E13: Total Assets: | K13: =SUM(K7:K11) -> 2730617 | L13: =SUM(L7:L11) -> 10515973 | M13: =SUM(M7:M11) -> 5092744 | N13: =SUM(N7:N11) -> 3114845 | O13: =SUM(O7:O11) -> 1447358 | P13: =SUM(P7:P11) -> 4824062 | Q13: =SUM(Q7:Q11) -> 27725599
A15: LIABILITIES AND FUND BALANCES
B16: Liabilities:
C17: Cash overdraft | P17: 515 | Q17: =SUM(K17:P17) -> 515
C18: Accounts, salaries, and other payables | K18: 543569 | L18: 1563052 | M18: 602956 | N18: 177012 | O18: 1023759 | P18: 188452 | Q18: =SUM(K18:P18) -> 4098800
C19: Due to other governments | K19: 47796 | M19: 103807 | P19: 231721 | Q19: =SUM(K19:P19) -> 383324
C20: Due to other funds | K20: 382235 | O20: 129100 | P20: 204400 | Q20: =SUM(K20:P20) -> 715735
E22: Total liabilities: | K22: =SUM(K17:K20) -> 973600 | L22: =SUM(L17:L20) -> 1563052 | M22: =SUM(M17:M19) -> 706763 | N22: =SUM(N17:N21) -> 177012 | O22: =SUM(O17:O20) -> 1152859 | P22: =SUM(P17:P20) -> 625088 | Q22: =SUM(Q17:Q20) -> 5198374
A24: Deferred Inflow of Resources
B25: Hazard Mitigation Funds | K25: 0 | L25: 0 | M25: 0 | N25: 0 | O25: 0 | P25: 53394 | Q25: =SUM(K25:P25) -> 53394
E27: Total Deferred inflow of Resources | K27: 0 | L27: 0 | M27: 0 | N27: 0 | O27: 0 | P27: =SUM(P25:P25) -> 53394 | Q27: =SUM(Q25:Q25) -> 53394
B29: Fund Balances
C30: Restricted | K30: 117349 | L30: 8875090 | M30: 4365264 | N30: 2922869 | O30: 294499 | P30: 4067236 | Q30: =SUM(K30:P30) -> 20642307
C31: Commited | K31: 445733 | P31: 43583 | Q31: =SUM(K31:P31) -> 489316
C32: Assigned | K32: 65678 | L32: 77831 | M32: 20717 | N32: 14964 | P32: 37694 | Q32: =SUM(K32:P32) -> 216884
C33: Unassigned | K33: 1128257 | P33: -2933 | Q33: =SUM(K33:P33) -> 1125324
E35: Total fund balance: | K35: =SUM(K30:K33) -> 1757017 | L35: =SUM(L30:L33) -> 8952921 | M35: =SUM(M30:M33) -> 4385981 | N35: =SUM(N31:N33) -> 14964 | P35: =SUM(P30:P33) -> 4145580 | Q35: =SUM(Q30:Q33) -> 22473831
E37: Total liabilities, Deferred inflow of Resources, | K37: =SUM(K35,K22,K27) -> 2730617 | L37: =SUM(L35,L22,L27) -> 10515973 | M37: =SUM(M35,M22,M27) -> 5092744 | N37: =SUM(N35,N22,N27) -> 191976 | O37: =SUM(O35,O22,O27) -> 1152859 | P37: =SUM(P35,P22,P27) -> 4824062 | Q37: =SUM(Q35,Q22,Q27) -> 27725599
F38: and fund balances:

Sheet Terrebonne
D1: Terrebonne Combined Balance Sheet
D2: Issued: December 31, 2013
K5: General Fund | L5: Public Safety Fund | M5: Grant Fund | N5: Road and Bridge Maintenance Fund | O5: Drainage Maintenance Fund | P5: Terrebonne Levee & Conservation District Fund | Q5: Capital Projects Fund | R5: Other Governmental Funds | S5: Total Governmental Funds
A6: Assets:
B7: Cash and cash equivalents | K7: 2146308 | L7: 379080 | M7: 5293398 | N7: 347316 | O7: 69124 | P7: 2373744 | Q7: 2139098 | R7: 4892979 | S7: =SUM(K7:R7) -> 17641047
B8: Investments | K8: 7394525 | L8: 2639090 | M8: 902 | N8: 1691475 | O8: 6067598 | P8: 7158264 | Q8: 48894771 | R8: 17858297 | S8: =SUM(K8:R8) -> 91704922
B9: Receivables (net, where applicable of | S9: =SUM(K9:Q9) -> 0
C10: allowances for uncollectibles)
C11: Taxes | K11: 392672 | L11: 539101 | O11: 1017678 | R11: 2184694 | S11: =SUM(K11:R11) -> 4134145
C12: Accounts | K12: 565086 | L12: 10661 | M12: 152168 | N12: 989 | O12: 7217 | Q12: 189140 | R12: 32746 | S12: =SUM(K12:R12) -> 958007
C13: Other | K13: 113 | M13: 323 | R13: 119860 | S13: =SUM(K13:R13) -> 120296
C14: Economic loans | M14: 3491084 | S14: =SUM(K14:R14) -> 3491084
B15: Due from other funds | K15: 36726516 | L15: 37029 | M15: 768113 | N15: 683537 | O15: 101273 | Q15: 10711234 | R15: 3215798 | S15: =SUM(K15:R15) -> 52243500
B16: Due from other governmental units | K16: 6449332 | L16: 5545951 | M16: 17614943 | N16: 1293918 | O16: 7491927 | P16: 1136365 | Q16: 16751287 | R16: 13417009 | S16: =SUM(K16:R16) -> 69700732
B17: Due from component units | K17: 28642 | S17: =SUM(K17:R17) -> 28642
B18: Inventories | M18: 18672 | S18: =SUM(K18:R18) -> 18672
B19: Other assets | K19: 3421 | M19: 650 | N19: 40 | S19: =SUM(K19:R19) -> 4111
B20: Restricted assets: | S20: =SUM(K20:R20) -> 0
C21: Cash and cash equivalents | K21: 69690 | M21: 135795 | S21: =SUM(K21:R21) -> 205485
E23: Total Assets: | K23: =SUM(K7:K21) -> 53776305 | L23: =SUM(L7:L21) -> 9150912 | M23: =SUM(M7:M21) -> 27476048 | N23: =SUM(N7:N21) -> 4017275 | O23: =SUM(O7:O21) -> 14754817 | P23: =SUM(P7:P21) -> 10668373 | Q23: =SUM(Q7:Q21) -> 78685530 | R23: =SUM(R7:R21) -> 41721383 | S23: =SUM(S7:S21) -> 240250643
A25: LIABILITIES AND FUND BALANCES
B26: Liabilities:
C27: Accounts payable and accrued expenditures | K27: 711436 | L27: 313647 | M27: 3069784 | N27: 218686 | O27: 302866 | Q27: 3815587 | R27: 309564 | S27: =SUM(K27:R27) -> 8741570
C28: Liability for work completed on contracts | K28: 1446 | M28: 3201 | N28: 12300 | Q28: 1764635 | R28: 5000 | S28: =SUM(K28:R28) -> 1786582
C29: Unavailable revenue | K29: 2558930 | L29: 4335933 | O29: 6504012 | R29: 13795042 | S29: =SUM(K29:R29) -> 27193917
C30: Grant Advancement | M30: 3755911 | S30: =SUM(K30:R30) -> 3755911
C31: Due to other funds | K31: 36282788 | L31: 499669 | M31: 15680023 | N31: 469682 | O31: 910018 | P31: 84265 | Q31: 3173593 | R31: 1781758 | S31: =SUM(K31:R31) -> 58881796
C32: Due to other governmental units | K32: 172092 | L32: 13026 | M32: 12999 | N32: 219 | O32: 12392 | Q32: 7054373 | R32: 323590 | S32: =SUM(K32:R32) -> 7588691
C33: Due to component units | K33: 2438 | S33: =SUM(K33:R33) -> 2438
C34: Payable from restricted assets:
D35: Tenents' escrow accounts | M35: 135065 | S35: =SUM(K35:R35) -> 135065
E37: Total liabilities: | K37: =SUM(K27:K35) -> 39729130 | L37: =SUM(L27:L35) -> 5162275 | M37: =SUM(M27:M35) -> 22656983 | N37: =SUM(N27:N35) -> 700887 | O37: =SUM(O27:O35) -> 7729288 | P37: =SUM(P27:P32) -> 84265 | Q37: =SUM(Q27:Q32) -> 15808188 | R37: =SUM(R27:R35) -> 16214954 | S37: =SUM(S27:S35) -> 108085970
B39: Fund Balances (deficit)
C40: Nonspendable:
D41: Long-term receivables | K41: 65029 | S41: =SUM(K41:R41) -> 65029
C42: Restricted for:
D43: Dedicated emergency | K43: 2163347 | S43: =SUM(K43:Q43) -> 2163347
D44: Broadmoor trees | K44: 69690 | S44: =SUM(K44:Q44) -> 69690
D45: Grants | M45: 3074445 | S45: =SUM(K45:Q45) -> 3074445
D46: Capital projects | Q46: 23418827 | S46: =SUM(K46:Q46) -> 23418827
D47: Road and bridge | N47: 192480 | S47: =SUM(K47:Q47) -> 192480
D48: Drainage | O48: 1583295 | S48: =SUM(K48:Q48) -> 1583295
D49: Levee and conservation | P49: 10584108 | S49: =SUM(K49:R49) -> 10584108
D50: Debt service | R50: 14734095 | S50: =SUM(K50:R50) -> 14734095
D51: Other special purposes | R51: 10187323 | S51: =SUM(K51:R51) -> 10187323
C52: Commited for:
D53: Capital projects | Q53: 2181540 | S53: =SUM(K53:R53) -> 2181540
C54: Assigned for:
D55: Subsequent year's expenditures | K55: 126433 | R55: 54206 | S55: =SUM(K55:R55) -> 180639
D56: Non-district recreation | K56: 226688 | S56: =SUM(K56:R56) -> 226688
D57: Parish prisoners | K57: 702414 | S57: =SUM(K57:R57) -> 702414
D58: City marshall | K58: 199254 | S58: =SUM(K58:R58) -> 199254
D59: Coastal restoration | K59: 211623 | S59: =SUM(K59:R59) -> 211623
D60: Public safety | L60: 3988637 | S60: =SUM(K60:R60) -> 3988637
D61: Capital projects | Q61: 37276975 | S61: =SUM(K61:R61) -> 37276975
D62: Grants | M62: 1744620 | S62: =SUM(K62:R62) -> 1744620
D63: Road and bridge | N63: 3123908 | S63: =SUM(K63:R63) -> 3123908
D64: Drainage | O64: 5442234 | S64: =SUM(K64:R64) -> 5442234
D65: Other special purposes | R65: 530805 | S65: =SUM(K65:R65) -> 530805
C66: Unassigned | K66: 10282697 | S66: =SUM(K66:R66) -> 10282697
E68: Total fund balance: | K68: =SUM(K40:K66) -> 14047175 | L68: =SUM(L42:L66) -> 3988637 | M68: =SUM(M42:M66) -> 4819065 | N68: =SUM(N42:N66) -> 3316388 | O68: =SUM(O41:O66) -> 7025529 | P68: =SUM(P42:P66) -> 10584108 | Q68: =SUM(Q40:Q67) -> 62877342 | R68: =SUM(R41:R66) -> 25506429 | S68: =SUM(S40:S66) -> 132164673
E70: Total liabilities and fund balances: | K70: =SUM(K68,K37,) -> 53776305 | L70: =SUM(L68,L37,) -> 9150912 | M70: =SUM(M68,M37,) -> 27476048 | N70: =SUM(N68,N37,) -> 4017275 | O70: =SUM(O68,O37,) -> 14754817 | P70: =SUM(P68,P37,) -> 10668373 | Q70: =SUM(Q68,Q37,) -> 78685530 | R70: =SUM(R68,R37,) -> 41721383 | S70: =SUM(S68,S37,) -> 240250643

Sheet Tensas
D1: Tensas Combined Balance Sheet
D2: Issued: December 31, 2013
K5: General Fund | L5: Road Fund | M5: Ambulance Fund | N5: Health Unit Fund | O5: Ambulance Rededication Fund | P5: Landfill Site Fund | Q5: Fire Protection Fund | R5: Other Governmental Funds | S5: Total Governmental Funds
A6: Assets:
B7: Cash and cash equivalents | K7: 647472 | L7: 92274 | M7: 50063 | N7: 521608 | P7: 920 | Q7: 26526 | R7: 990980 | S7: =SUM(K7:R7) -> 2329843
B8: Receivables | K8: 267562 | L8: 69172 | M8: 66559 | N8: 88939 | Q8: 15366 | R8: 255511 | S8: =SUM(K8:R8) -> 763109
B9: Amounts held by trustee for landfill closure and
C10: post-closure care costs | P10: 944665 | S10: =SUM(K10:R10) -> 944665
B11: Restricted assets | R11: 29094 | S11: =SUM(K11:R11) -> 29094
B12: Due from other funds | L12: 24330 | M12: 26347 | Q12: 6082 | R12: 28381 | S12: =SUM(K12:R12) -> 85140
E14: Total Assets: | K14: =SUM(K7:K12) -> 915034 | L14: =SUM(L7:L12) -> 185776 | M14: =SUM(M7:M12) -> 142969 | N14: =SUM(N7:N12) -> 610547 | O14: =SUM(O7:O12) -> 0 | P14: =SUM(P7:P12) -> 945585 | Q14: =SUM(Q7:Q12) -> 47974 | R14: =SUM(R7:R12) -> 1303966 | S14: =SUM(S7:S12) -> 4151851
A16: LIABILITIES AND FUND BALANCES
B17: Liabilities:
C18: Accounts, salaries, and other payables | K18: 24370 | L18: 26679 | M18: 30612 | N18: 10235 | R18: 64153 | S18: =SUM(K18:R18) -> 156049
C19: Bank overdraft | O19: 16499 | S19: =SUM(K19:R19) -> 16499
C20: Due to other funds | K20: 85140 | S20: =SUM(K20:R20) -> 85140
C21: Intergovernmental payables | Q21: 54048 | S21: =SUM(K21:R21) -> 54048
E23: Total liabilities: | K23: =SUM(K18:K21) -> 109510 | L23: =SUM(L18:L21) -> 26679 | M23: =SUM(M18:M21) -> 30612 | N23: =SUM(N18:N21) -> 10235 | O23: =SUM(O18:O21) -> 16499 | P23: =SUM(P18:P21) -> 0 | Q23: =SUM(Q18:Q21) -> 54048 | R23: =SUM(R18:R21) -> 64153 | S23: =SUM(S18:S21) -> 311736
B25: Fund Balances (deficit)
C26: Restricted for:
D27: Debt service | R27: 29094 | S27: =SUM(K27:R27) -> 29094
D28: Landfill closure | P28: 945585 | S28: =SUM(K28:R28) -> 945585
C29: Committed for:
D30: Special revenue projects | L30: 159097 | M30: 112357 | N30: 600312 | O30: -16499 | Q30: -6074 | R30: 1210719 | S30: =SUM(K30:R30) -> 2059912
C31: Unassigned, reported in:
D32: General | K32: 805524 | S32: =SUM(K32:R32) -> 805524
E34: Total fund balance: | K34: =SUM(K26:K32) -> 805524 | L34: =SUM(L26:L32) -> 159097 | M34: =SUM(M26:M32) -> 112357 | N34: =SUM(N26:N32) -> 600312 | O34: =SUM(O26:O32) -> -16499 | P34: =SUM(P26:P32) -> 945585 | Q34: =SUM(Q27:Q32) -> -6074 | R34: =SUM(R26:R33) -> 1239813 | S34: =SUM(S26:S32) -> 3840115
E36: Total liabilities and fund balances: | K36: =SUM(K34,K23) -> 915034 | L36: =SUM(L23,L34) -> 185776 | M36: =SUM(M23,M34) -> 142969 | N36: =SUM(N23,N34) -> 610547 | O36: =SUM(O23+O34) -> 0 | P36: =SUM(P34+P23) -> 945585 | Q36: =SUM(Q34+Q23) -> 47974 | R36: =SUM(R23+R34) -> 1303966 | S36: =SUM(S23,S34) -> 4151851

Sheet Union
D1: Union Combined Balance Sheet
D2: Issued: December 31, 2013
K4: General Fund | L4: Road Maintenance | M4: Road Construction | N4: Sales Tax Landfill | O4: Detention Center | P4: Other Governmental Funds | Q4: Total Governmental Funds
A5: Assets:
B6: Cash and cash equivalents | K6: 437663 | L6: 617051 | M6: 1476986 | N6: 2819039 | O6: 500 | P6: 1759235 | Q6: =SUM(K6:P6) -> 7110474
B7: Investments | K7: 499160 | L7: 152352 | M7: 290996 | N7: 5560482 | O7: 37989 | P7: 699304 | Q7: =SUM(K7:P7) -> 7240283
B8: Receivables | K8: 863953 | L8: 1091659 | M8: 808664 | N8: 394789 | O8: 183999 | P8: 1406640 | Q8: =SUM(K8:P8) -> 4749704
E10: Total assets: | K10: =SUM(K6:K8) -> 1800776 | L10: =SUM(L6:L8) -> 1861062 | M10: =SUM(M6:M8) -> 2576646 | N10: =SUM(N6:N8) -> 8774310 | O10: =SUM(O6:O8) -> 222488 | P10: =SUM(P6:P8) -> 3865179 | Q10: =SUM(Q6:Q8) -> 19100461
A12: LIABILITIES AND FUND BALANCES
B13: Liabilities:
C14: Cash overdraft | O14: 963561 | P14: 23604 | Q14: =SUM(K14:P14) -> 987165
C15: Accounts payable | K15: 326744 | L15: 61234 | M15: 34292 | N15: 31553 | O15: 74736 | P15: 619949 | Q15: =SUM(K15:P15) -> 1148508
C16: Salaries and related payables | K16: 139106 | L16: 14426 | N16: 9569 | O16: 44934 | P16: 17302 | Q16: =SUM(K16:P16) -> 225337
C17: Deposits due others | L17: 260020 | Q17: =SUM(K17:P17) -> 260020
E19: Total liabilities: | K19: =SUM(K14:K17) -> 465850 | L19: =SUM(L14:L17) -> 335680 | M19: =SUM(M14:M17) -> 34292 | N19: =SUM(N14:N17) -> 41122 | O19: =SUM(O14:O17) -> 1083231 | P19: =SUM(P14:P17) -> 660855 | Q19: =SUM(Q14:Q17) -> 2621030
A21: Deferred Inflows:
B22: Grant revenues pending | P22: 14194 | Q22: =SUM(K22:P22) -> 14194
B24: Fund Balances
C25: Restricted | L25: 1525382 | M25: 2542354 | N25: 8733188 | P25: 3204697 | Q25: =SUM(K25:P25) -> 16005621
C26: Unassigned | K26: 1334926 | O26: -860743 | P26: -14567 | Q26: =SUM(K26:P26) -> 459616
E28: Total fund balance: | K28: =SUM(K25:K26) -> 1334926 | L28: =SUM(L25:L26) -> 1525382 | M28: =SUM(M25:M26) -> 2542354 | N28: =SUM(N25:N26) -> 8733188 | O28: =SUM(O25:O26) -> -860743 | P28: =SUM(P25:P26) -> 3190130 | Q28: =SUM(Q25:Q26) -> 16465237
E30: Total liabilities and fund balances: | K30: =K28+K22+K19 -> 1800776 | L30: =L28+L22+L19 -> 1861062 | M30: =M28+M22+M19 -> 2576646 | N30: =N28+N22+N19 -> 8774310 | O30: =O28+O22+O19 -> 222488 | P30: =P28+P22+P19 -> 3865179 | Q30: =Q28+Q22+Q19 -> 19100461

Sheet Vermillion
D1: Vermillion Combined Balance Sheet
D2: Issued: December 31, 2013
K5: General | L5: 1976 Sales Tax Fund | M5: 1978 Sales Tax Fund | N5: 1994 Sales Tax Fund | O5: Royalty Road Fund | P5: Parishwide Public Improvement Maintenance Fund | Q5: Project Account Fund | R5: Other Governmental Funds | S5: Total (Memorandum Only)
A6: Assets:
B7: Cash and interest-bearing deposits | K7: 499063 | L7: 10223763 | M7: 10722082 | N7: 12829492 | O7: 9406850 | P7: 660055 | Q7: 321774 | R7: 8465239 | S7: =SUM(K7:R7) -> 53128318
B8: Accounts receivable | N8: 28896 | R8: 81526 | S8: =SUM(K8:R8) -> 110422
B9: Ad valorem tax receivable, net | K9: 39595 | P9: 35575 | R9: 111472 | S9: =SUM(K9:R9) -> 186642
B10: Accrued interest receivable | L10: 12537 | M10: 4235 | N10: 14722 | O10: 7419 | R10: 1216 | S10: =SUM(K10:R10) -> 40129
B11: Due from other funds | K11: 279281 | L11: 6273 | M11: 21634 | O11: 84830 | P11: 41301 | S11: =SUM(K11:R11) -> 433319
B12: Due from component unit | K12: 111 | O12: 519 | S12: =SUM(K12:R12) -> 630
B13: Due from other governmental units | K13: 1141121 | L13: 722841 | M13: 722841 | N13: 722841 | O13: 444794 | P13: 1082785 | Q13: 885246 | R13: 2912573 | S13: =SUM(K13:R13) -> 8635042
B14: Other receivables | K14: 44069 | S14: =SUM(K14:R14) -> 44069
B15: Prepaid expenses | L15: 1345 | N15: 11368 | O15: 35461 | P15: 7768 | R15: 502 | S15: =SUM(K15:R15) -> 56444
E17: Total Assets: | K17: =SUM(K7:K15) -> 2003240 | L17: =SUM(L7:L15) -> 10966759 | M17: =SUM(M7:M15) -> 11470792 | N17: =SUM(N7:N15) -> 13607319 | O17: =SUM(O7:O15) -> 9979873 | P17: =SUM(P7:P15) -> 1827484 | Q17: =SUM(Q7:Q15) -> 1207020 | R17: =SUM(R7:R15) -> 11572528 | S17: =SUM(S7:S15) -> 62635015
A19: LIABILITIES AND FUND BALANCES
B20: Liabilities:
C21: Accounts payable | K21: 109499 | L21: 4339 | M21: 10502 | N21: 204383 | O21: 1990 | P21: 59897 | Q21: 133887 | R21: 290920 | S21: =SUM(K21:R21) -> 815417
C22: Contracts payable | K22: 60845 | O22: 217244 | Q22: 532763 | R22: 7721 | S22: =SUM(K22:R22) -> 818573
C23: Retainage payable | O23: 51592 | Q23: 98647 | R23: 858 | S23: =SUM(K23:R23) -> 151097
C24: Accrued liabilities | K24: 23316 | L24: 10781 | M24: 3962 | N24: 54613 | P24: 66856 | R24: 47404 | S24: =SUM(K24:R24) -> 206932
C25: Due to other funds | K25: 94371 | L25: 3499 | M25: 852 | N25: 67787 | P25: 37298 | Q25: 229032 | R25: 480 | S25: =SUM(K25:R25) -> 433319
C26: Due to other governmental units | Q26: 58759 | S26: =SUM(K26:R26) -> 58759
C27: Other liabilities | K27: 193213 | S27: =SUM(K27:R27) -> 193213
E29: Total liabilities: | K29: =SUM(K21:K27) -> 481244 | L29: =SUM(L21:L27) -> 18619 | M29: =SUM(M21:M27) -> 15316 | N29: =SUM(N21:N28) -> 326783 | O29: =SUM(O21:O27) -> 270826 | P29: =SUM(P21:P27) -> 164051 | Q29: =SUM(Q21:Q27) -> 1053088 | R29: =SUM(R21:R27) -> 347383 | S29: =SUM(S21:S27) -> 2677310
A31: DEFERRED INFLOWS OF RESROUCES
C32: Deferred revenue | K32: 232623 | N32: 17777 | P32: 57882 | Q32: 200789 | R32: 439320 | S32: =SUM(K32:R32) -> 948391
B34: Fund Balances
C35: Nonspendable | L35: 1345 | N35: 11368 | O35: 35461 | P35: 7768 | R35: 502 | S35: =SUM(K35:R35) -> 56444
C36: Restricted | L36: 10946795 | M36: 11455476 | N36: 13251391 | O36: 9673586 | P36: 1597783 | R36: 10785323 | S36: =SUM(K36:R36) -> 57710354
C37: Assigned | K37: 1817 | S37: =SUM(K37:R37) -> 1817
C38: Unassigned | K38: 1287556 | Q38: -46857 | S38: =SUM(K38:R38) -> 1240699
E40: Total fund balance: | K40: =SUM(K35:K38) -> 1289373 | L40: =SUM(L35:L38) -> 10948140 | M40: =SUM(M35:M38) -> 11455476 | N40: =SUM(N35:N38) -> 13262759 | O40: =SUM(O35:O38) -> 9709047 | P40: =SUM(P35:P38) -> 1605551 | Q40: =SUM(Q35:Q38) -> -46857 | R40: =SUM(R35:R38) -> 10785825 | S40: =SUM(S35:S38) -> 59009314
E42: Total liabilities and fund balances: | K42: =SUM(K40,K29,K32) -> 2003240 | L42: =SUM(L40,L29,L32) -> 10966759 | M42: =SUM(M40,M29,M32) -> 11470792 | N42: =SUM(N40,N29,N32) -> 13607319 | O42: =SUM(O40,O29,O32) -> 9979873 | P42: =SUM(P40,P29,P32) -> 1827484 | Q42: =SUM(Q40,Q29,Q32) -> 1207020 | R42: =SUM(R40,R29,R32) -> 11572528 | S42: =SUM(S40,S29,S32) -> 62635015

Sheet Vernon
D1: Vernon Combined Balance Sheet
D2: Issued: December 31, 2013
K5: General Fund | L5: Parishwide Maintenance Fund | M5: Sanitary Landfill Fund | N5: Health Unit Maintenance Fund | O5: Courthouse and Jail Maintenance Fund | P5: Parishwide Overlay Fund | Q5: Criminal Court Fund | R5: Library Maintenance Fund | S5: Workforce Investment Act Fund | T5: Other Governmental Funds | U5: 2013 | V5: 2012
A6: Assets:
B7: Cash and cash equivalents | K7: 10539097 | L7: 839396 | M7: 1625066 | N7: 1415976 | O7: 766734 | P7: 1393251 | Q7: 10944 | R7: 1169382 | S7: 1041 | T7: 6136184 | U7: =SUM(K7:T7) -> 23897071 | V7: 23444012
B8: Investments, at fair value | M8: 697947 | O8: 548074 | U8: =SUM(K8:T8) -> 1246021 | V8: 1243260
B9: Receivables | K9: 654231 | L9: 681317 | N9: 440496 | O9: 1462120 | Q9: 46389 | R9: 1062386 | S9: 9814 | T9: 1775502 | U9: =SUM(K9:T9) -> 6132255 | V9: 5819491
B10: Interfund receivables | K10: 25385 | T10: 24762 | U10: =SUM(K10:T10) -> 50147 | V10: 6743
B11: Other | S11: 21627 | U11: =SUM(K11:T11) -> 21627
E13: Total Assets: | K13: =SUM(K7:K11) -> 11218713 | L13: =SUM(L7:L11) -> 1520713 | M13: =SUM(M7:M11) -> 2323013 | N13: =SUM(N7:N11) -> 1856472 | O13: =SUM(O7:O11) -> 2776928 | P13: =SUM(P7:P11) -> 1393251 | Q13: =SUM(Q7:Q11) -> 57333 | R13: =SUM(R7:R11) -> 2231768 | ... V13: =SUM(V7:V11) -> 30513506
A15: LIABILITIES AND FUND BALANCES
B16: Liabilities:
C17: Accounts, salaries, and other payables | K17: 237917 | L17: 44176 | M17: 212112 | N17: 27374 | O17: 29063 | P17: 3955 | Q17: 6572 | R17: 55810 | S17: 13942 | T17: 200606 | U17: =SUM(K17:T17) -> 831527 | V17: 755784
C18: Interfund payables | O18: 18019 | Q18: 25380 | S18: 5 | T18: 6743 | U18: =SUM(K18:T18) -> 50147 | V18: 6743
C19: Deferred revenues | S19: 18536 | T19: 91473 | U19: =SUM(K19:T19) -> 110009 | V19: 2230
E21: Total liabilities: | K21: =SUM(K17:K19) -> 237917 | L21: =SUM(L17:L19) -> 44176 | M21: =SUM(M17:M19) -> 212112 | N21: =SUM(N17:N19) -> 27374 | O21: =SUM(O17:O19) -> 47082 | P21: =SUM(P17:P19) -> 3955 | Q21: =SUM(Q17:Q19) -> 31952 | R21: =SUM(R17:R19) -> 55810 | ... V21: =SUM(V17:V19) -> 764757
B23: Fund Balances:
C24: Restricted for:
D25: Legislative | T25: 488571 | U25: =SUM(K25:T25) -> 488571 | V25: 426722
D26: Judicial | K26: 1233 | Q26: 25380 | U26: =SUM(K26:T26) -> 26613 | V26: 256
D27: Finance and administration | U27: =SUM(K27:T27) -> 0 | V27: 12453
D28: Other general government | O28: 2729846 | T28: 3359236 | U28: =SUM(K28:T28) -> 6089082 | V28: 5834729
D29: Public safety | T29: 1942288 | U29: =SUM(K29:T29) -> 1942288 | V29: 1926031
D30: Public works | L30: 1476538 | M30: 2110901 | P30: 1389296 | T30: 182885 | U30: =SUM(K30:T30) -> 5159620 | V30: 4667537
D31: Health and welfare | N31: 1829098 | T31: 442155 | U31: =SUM(K31:T31) -> 2271253 | V31: 2539704
D32: Culture and recreation | R32: 2175958 | T32: 99340 | U32: =SUM(K32:T32) -> 2275298 | V32: 2440742
D33: Debt service | T33: 1123151 | U33: =SUM(K33:T33) -> 1123151 | V33: 1186755
D34: Employee benefits | K34: 2213890 | U34: =SUM(K34:T34) -> 2213890 | V34: 2285219
C35: Unassigned | K35: 8765673 | U35: =SUM(K35:T35) -> 8765673 | V35: 8428602
E37: Total fund balance: | K37: =SUM(K24:K35) -> 10980796 | L37: =SUM(L24:L35) -> 1476538 | M37: =SUM(M24:M35) -> 2110901 | N37: =SUM(N24:N35) -> 1829098 | O37: =SUM(O24:O35) -> 2729846 | P37: =SUM(P24:P35) -> 1389296 | Q37: =SUM(Q24:Q35) -> 25380 | R37: =SUM(R24:R35) -> 2175958 | ... U37: =SUM(U24:U35) -> 30355439 | V37: =SUM(V25:V35) -> 29748750
E39: Total liabilities and fund balances: | K39: =K37+K21 -> 11218713 | L39: =L37+L21 -> 1520714 | M39: =M37+M21 -> 2323013 | N39: =N37+N21 -> 1856472 | O39: =O37+O21 -> 2776928 | P39: =P37+P21 -> 1393251 | Q39: =Q37+Q21 -> 57332 | R39: =R37+R21 -> 2231768 | ... V39: =V37+V21 -> 30513507

Sheet Washington
D1: Washington Combined Balance Sheet
D2: Issued: December 31, 2013
K4: General Fund | L4: Sales Tax Split 1% | M4: Parish Transportation Fund | N4: Sales Tax Split .67% | O4: Criminal Court | P4: Debt Service PTF Revenue Bonds | Q4: Library Fund | R4: Nonmajor Governmental Funds | S4: Total Governmental Funds
A5: Assets:
B6: Cash | K6: 645480 | L6: 274958 | Q6: 143671 | R6: 561922 | S6: =SUM(K6:R6) -> 1626031
