Workbook

Sheet Acadia
J1: Acadia County 2013 Statement of Activities
J2: Issued: December 31, 2013
M4: NET (EXPENSE) REVENUE AND CHANGE IN NET ASSETS
J5: PROGRAM REVENUES | M5: PRIMARY GOVERNMENT
A6: FUNCTIONS/PROGRAMS | I6: Expenses | J6: Charges for Services | K6: Operating Grants and Contributions | L6: Capital Grants and Contributions | M6: Total Governmental Activities | N6: Component Units
A7: Primary Government:
B8: Government Activities:
C9: General government | I9: -3475315 | J9: 74560 | L9: 23340 | M9: =SUM(I9:L9) -> -3377415
C10: Public safety | I10: -2252548 | J10: 25010 | K10: 761554 | L10: 488909 | M10: =SUM(I10:L10) -> -977075
C11: Public works | I11: -5747372 | K11: 653955 | L11: 805163 | M11: =SUM(I11:L11) -> -4288254
C12: Economic development and assistance | I12: -530123 | J12: 8189 | K12: 9284 | L12: 740924 | M12: =SUM(I12:L12) -> 228274
C13: Health and welfare | I13: -7195864 | J13: 7940 | K13: 156381 | L13: 57397 | M13: =SUM(I13:L13) -> -6974146
C14: Culture and recreation | I14: -279572 | J14: 79085 | M14: =SUM(I14:L14) -> -200487
C15: Interest on long-term debt | I15: -472119 | M15: =SUM(I15:L15) -> -472119
E17: Total Government Activities | I17: =SUM(I9:I15) -> -19952913 | J17: =SUM(J9:J15) -> 194784 | K17: =SUM(K9:K15) -> 1581174 | L17: =SUM(L9:L15) -> 2115733 | M17: =SUM(M9:M15) -> -16061222
A19: Component units:
B20: Acadia Parish District Criminal Court | I20: -769154 | J20: 209708 | K20: 61151 | L20: 0 | N20: =SUM(I20:M20) -> -498295
G22: General Revenues:
H23: Taxes:
I24: Property | M24: 5081628
I25: Sales | M25: 11701851
I26: Severance | M26: 1010850
I27: Fire insurance premiums | M27: 252516
I28: Occupational and insurance | M28: 503125
I29: Other | M29: 292470
H30: Grants and contributions not restricted to specific programs | M30: 438274
H31: Investment income gains (losses) | M31: -48655
H32: Loss on disposal of capital assets | M32: -33534
H33: Miscellaneous | M33: 446277 | N33: 426
H34: Transfers | M34: -525290 | N34: 505290
H36: Total General Revenues | M36: =SUM(M24:M34) -> 19119512 | N36: =SUM(N24:N34) -> 505716
H38: Change in Net Assets | M38: =SUM(M17,M36) -> 3058290 | N38: =N36+N20 -> 7421
H40: Net position, beginning, as previously stated | M40: 49162484 | N40: 31388
H42: Cumulative effect of change in accounting principle | M42: -110785
H44: Prior period adjustment | M44: 511435
E46: Net Assets- Beginning, restated | M46: 49563134 | N46: 31388
E48: Net Assets- End of Year | M48: =M46+M38 -> 52621424 | N48: =N46+N38 -> 38809

Sheet Sheet3
J1: Calhoun County 2010 Statement of Activities
J2: Issued: December 23,2011
M4: NET (EXPENSES) REVENUES AND CHANGES IN NET ASSETS
J5: PROGRAM REVENUES | M5: PRIMARY GOVERNMENT
A6: FUNCTIONS/PROGRAMS | I6: Expenses | J6: Charges for Services | K6: Operating Grants and Contributions | L6: Capital Grants and Contributions | M6: Governmental Activities | N6: Business-type Activities | O6: Total
A7: Primary Government:
B8: Government Activities:
C9: General government | I9: -16401981 | J9: 4333438.1 | K9: 2704791.7 | M9: =SUM(I9:L9) -> -9363751 | O9: =SUM(M9:N9) -> -9363751
C10: Public safety | I10: -16556688 | J10: 1328868.3 | K10: 3765237.8 | M10: =SUM(I10:L10) -> -11462582 | O10: =SUM(M10:N10) -> -11462582
C11: Highways and roads | I11: -12309705 | J11: 133348.8 | K11: 3792599.2 | L11: 55534.45 | M11: =SUM(I11:L11) -> -8328222.9 | O11: =SUM(M11:N11) -> -8328222.9
C12: Sanitation | I12: -22409528 | K12: 22196827 | M12: =SUM(I12:L12) -> -212701.23 | O12: =SUM(M12:N12) -> -212701.23
C13: Health | I13: -384287.66 | J13: 93696 | K13: 7591.44 | M13: =SUM(I13:L13) -> -283000.22 | O13: =SUM(M13:N13) -> -283000.22
C14: Welfare | I14: -115639.57 | M14: =SUM(I14:L14) -> -115639.57 | O14: =SUM(M14:N14) -> -115639.57
C15: Culture and recreation | I15: -635743.2 | M15: =SUM(I15:L15) -> -635743.2 | O15: =SUM(M15:N15) -> -635743.2
C16: Education | I16: -73000 | M16: =SUM(I16:L16) -> -73000 | O16: =SUM(M16:N16) -> -73000
C17: Interest on long-term debt | I17: -622092.61 | M17: =SUM(I17:L17) -> -622092.61 | O17: =SUM(M17:N17) -> -622092.61
E19: Total Government Activities | I19: =SUM(I9:I17) -> -69508666 | J19: =SUM(J9:J17) -> 5889351.2 | K19: =SUM(K9:K17) -> 32467047 | L19: =SUM(L9:L17) -> 55534.45 | M19: =SUM(M9:M17) -> -31096733 | N19: =SUM(N9:N17) -> 0 | O19: =SUM(O9:O17) -> -31096733
B21: Business-Type Activities:
C22: Solid Waste | I22: -1744754.2 | J22: 2172224.4 | N22: 427470.13 | O22: 427470.13
E24: Total Business-Type Activities | I24: =SUM(I22:I22) -> -1744754.2 | J24: =SUM(J22:J22) -> 2172224.4 | K24: =SUM(K22:K22) -> 0 | L24: =SUM(L22:L22) -> 0 | M24: =SUM(M22:M22) -> 0 | N24: =SUM(N22:N22) -> 427470.13 | O24: =SUM(O22:O22) -> 427470.13
C26: Total Governmental Activities | I26: =SUM(I19+I24) -> -71253420 | J26: =SUM(J19+J24) -> 8061575.5 | K26: =SUM(K19+K24) -> 32467047 | L26: =SUM(L19+L24) -> 55534.45 | M26: =SUM(M19+M24) -> -31096733 | N26: =SUM(N19+N24) -> 427470.13 | O26: =SUM(O19+O24) -> -30669263
G28: General Revenues:
H29: Taxes:
I30: Property taxes for general purposes | M30: 6433134.9 | O30: =SUM(M30:N30) -> 6433134.9
I31: Property taxes for specific purposes | M31: 4562102.7 | O31: =SUM(M31:N31) -> 4562102.7
I32: General Sales Tax | M32: 4286349.5 | O32: =SUM(M32:N32) -> 4286349.5
I33: Other County Sales and Use Taxes | M33: 1673649.7 | O33: =SUM(M33:N33) -> 1673649.7
H34: Grants/contributions not restricted to specific programs | M34: 850414.01 | O34: =SUM(M34:N34) -> 850414.01
H35: Investment Income | M35: 274846.25 | N35: 6565.7 | O35: =SUM(M35:N35) -> 281411.95
H36: Miscellaneous | M36: 3718934.9 | N36: 64169.68 | O36: =SUM(M36:N36) -> 3783104.5
H37: Transfers | M37: 432773 | N37: -432773 | O37: =SUM(M37,N37) -> 0
H38: Extraordinary Item (Note 17) | M38: -73267927 | O38: =SUM(M38,N38) -> -73267927
H40: Total General Revenues and Transfers | M40: =SUM(M30:M38) -> -51035722 | N40: =SUM(N30:N38) -> -362037.62 | O40: =SUM(O30:O38) -> -51397760
H42: Change in Net Assets | M42: =SUM(M40,M26) -> -82132455 | N42: =SUM(N40,N26) -> 65432.51 | O42: =SUM(M42:N42) -> -82067023
E44: Net Assets- Beginning of Year | M44: 1.5180939e+08 | N44: 2795005.4 | O44: =SUM(M44:N44) -> 1.546044e+08
E46: Net Assets- End of Year | M46: =SUM(M42,M44) -> 69676935 | N46: =SUM(N42,N44) -> 2860437.9 | O46: =SUM(O42,O44) -> 72537373

Sheet Allen
J1: Allen County 2013 Statement of Activities
J2: Issued: December 31, 2013
M4: NET (EXPENSE) REVENUE AND CHANGE IN NET POSITIONS
J5: PROGRAM REVENUES | M5: PRIMARY GOVERNMENT
A6: FUNCTIONS/PROGRAMS | I6: Expenses | J6: Fees, Fines, and Charges for Services | K6: Operating Grants and Contributions | L6: Capital Grants and Contributions | M6: Total Governmental Activities
A7: Primary Government:
B8: Government Activities:
C9: General government | I9: -1828189 | J9: 201510 | K9: 13730 | M9: =SUM(I9:L9) -> -1612949
C10: Public safety | I10: -613949 | K10: 25419 | L10: 27776 | M10: =SUM(I10:L10) -> -560754
C11: Public works | I11: -6291960 | K11: 29509 | M11: =SUM(I11:L11) -> -6262451
C12: Economic development | I12: -322491 | J12: 92074 | K12: 96087 | L12: 54290 | M12: =SUM(I12:L12) -> -80040
C13: Other governments | I13: -516630 | K13: 495024 | M13: =SUM(I13:L13) -> -21606
C14: Interest on long-term debt | I14: -5262 | M14: =SUM(I14:L14) -> -5262
E16: Total Government Activities | I16: =SUM(I9:I14) -> -9578481 | J16: =SUM(J9:J14) -> 293584 | K16: =SUM(K9:K14) -> 659769 | L16: =SUM(L9:L14) -> 82066 | M16: =SUM(M9:M14) -> -8543062
G19: General Revenues:
H20: Taxes:
I21: Ad valorem | M21: 2978127
I22: Sales and use | M22: 1915340
I23: Severance | M23: 1165147
I24: Other | M24: 1652
H25: State revenue sharing | M25: 177544
H26: All other revenues | M26: 1340652
H27: Investment earnings | M27: 15570
H28: Special items:
I29: Gain on disposal of assets | M29: 41245
I30: Loss on disposal of assets | M30: -978399
H32: Total General Revenues | M32: =SUM(M21:M30) -> 6656878
H34: Change in Net Assets | M34: =SUM(M16,M32) -> -1886184
E36: Net Assets- Beginning of Year | M36: 32770564
E38: Net Assets- End of Year | M38: =SUM(M34,M36) -> 30884380

Sheet Ascension
J1: Ascension County 2013 Statement of Activities
J2: Issued: December 31, 2013
M4: NET (EXPENSE) REVENUE AND CHANGE IN NET ASSETS
J5: PROGRAM REVENUES | M5: PRIMARY GOVERNMENT | P5: COMPONENT UNITS
A6: FUNCTIONS/PROGRAMS | I6: Expenses | J6: Charges for Services | K6: Operating Grants and Contributions | L6: Capital Grants and Contributions | M6: Governmental Activities | N6: Business-type Activities | O6: Total | P6: Governmental Activities | Q6: Business-type Activities
A7: Primary Government:
B8: Government Activities:
C9: General government | I9: -14935768 | J9: 3911600 | K9: 256912 | L9: 633123 | M9: =SUM(I9:L9) -> -10134133 | O9: =SUM(M9:N9) -> -10134133
C10: Public safety | I10: -9548259 | J10: 552709 | K10: 1041074 | M10: =SUM(I10:L10) -> -7954476 | O10: =SUM(M10:N10) -> -7954476
C11: Public works | I11: -14605186 | K11: 1566915 | M11: =SUM(I11:L11) -> -13038271 | O11: =SUM(M11:N11) -> -13038271
C12: Health and welfare | I12: -5709382 | J12: 59619 | K12: 1684346 | M12: =SUM(I12:L12) -> -3965417 | O12: =SUM(M12:N12) -> -3965417
C13: Culture and recreation | I13: -7695027 | J13: 533345 | K13: 435102 | L13: 443112 | M13: =SUM(I13:L13) -> -6283468 | O13: =SUM(M13:N13) -> -6283468
C14: Transportation and development | I14: -10557421 | L14: 5569290 | M14: =SUM(I14:L14) -> -4988131 | O14: =SUM(M14:N14) -> -4988131
C15: Interest on long-term debt | I15: -3644962 | M15: =SUM(I15:L15) -> -3644962 | O15: =SUM(M15:N15) -> -3644962
E17: Total Government Activities | I17: =SUM(I9:I15) -> -66696005 | J17: =SUM(J9:J15) -> 5057273 | K17: =SUM(K9:K15) -> 4984349 | L17: =SUM(L9:L15) -> 6645525 | M17: =SUM(M9:M15) -> -50008858 | O17: =SUM(O9:O15) -> -50008858 | P17: =SUM(P9:P15) -> 0 | Q17: =SUM(Q9:Q15) -> 0
B19: Business-type Activities:
C20: Waste disposal facilities | I20: -1694248 | J20: 154083 | K20: 737 | L20: 881 | N20: =SUM(I20:L20) -> -1538547 | O20: =N20 -> -1538547
C21: Waterworks services | I21: -250905 | J21: 217437 | N21: =SUM(I21:L21) -> -33468 | O21: =N21 -> -33468
C22: Lamar Dixon Expo center | I22: -2261537 | J22: 1669187 | K22: 419063 | L22: 91592 | N22: =SUM(I22:L22) -> -81695 | O22: =N22 -> -81695
E24: Total business-type Activities | I24: =SUM(I20:I22) -> -4206690 | J24: =SUM(J20:J22) -> 2040707 | K24: =SUM(K20:K22) -> 419800 | L24: =SUM(L20:L22) -> 92473 | M24: =SUM(M20:M22) -> 0 | N24: =SUM(N20:N22) -> -1653710 | O24: =SUM(O20:O22) -> -1653710
E26: Total primary government | I26: =I24+I17 -> -70902695 | J26: =J24+J17 -> 7097980 | K26: =K24+K17 -> 5404149 | L26: =L24+L17 -> 6737998 | M26: =M24+M17 -> -50008858 | N26: =N24+N17 -> -1653710 | O26: =O24+O17 -> -51662568 | P26: =P24+P17 -> 0 | Q26: =Q24+Q17 -> 0
A28: Component units:
B29: Governmental activities | I29: -50001134 | J29: 17673716 | K29: 3785208 | P29: =SUM(I29:L29) -> -28542210
B30: Business-type activities | I30: -7713127 | J30: 6229842 | Q30: =SUM(I30:L30) -> -1483285
E32: Total component units | I32: =SUM(I29:I30) -> -57714261 | J32: =SUM(J29:J30) -> 23903558 | K32: =SUM(K29:K30) -> 3785208 | L32: =SUM(L29:L30) -> 0 | M32: =SUM(M29:M30) -> 0 | N32: =SUM(N29:N30) -> 0 | O32: =SUM(O29:O30) -> 0 | P32: =SUM(P29:P30) -> -28542210 | Q32: =SUM(Q29:Q30) -> -1483285
G34: General Revenues:
H35: Taxes:
I36: Ad valorem | M36: 26337905 | O36: =SUM(M36:N36) -> 26337905 | P36: 17194323 | Q36: 189710
I37: Sales | M37: 47074455 | O37: =SUM(M37:N37) -> 47074455 | P37: 10213682 | Q37: 1273033
I38: Franchise and other | M38: 1831140 | N38: 417113 | O38: =SUM(M38:N38) -> 2248253 | P38: 387957
H39: Grants and contributions not restricted to specific programs | M39: 673943 | O39: =SUM(M39:N39) -> 673943 | P39: 2183790 | Q39: 905000
H40: Investment earnings (loss) | M40: 436804 | N40: 36169 | O40: =SUM(M40:N40) -> 472973 | P40: 8589 | Q40: -667680
H41: Gain on sale of capital assets | M41: 398588 | N41: 4575 | O41: =SUM(M41:N41) -> 403163
G42: Transfers | M42: -1191000 | N42: 1191000 | O42: =SUM(M42:N42) -> 0
H44: Total General Revenues | M44: =SUM(M36:M42) -> 75561835 | N44: =SUM(N36:N42) -> 1648857 | O44: =SUM(O36:O42) -> 77210692 | P44: =SUM(P36:P42) -> 29988341 | Q44: =SUM(Q36:Q42) -> 1700063
H46: Change in Net Assets | M46: =M44+M26 -> 25552977 | N46: =N44+N26 -> -4853 | O46: =O44+O26 -> 25548124 | P46: =P44+P32 -> 1446131 | Q46: =Q44+Q32 -> 216778
E48: Net Assets- Beginning of Year | M48: 259286351 | N48: 18437522 | O48: =SUM(M48:N48) -> 277723873 | P48: 41726517 | Q48: 18505420
E50: Net Assets- End of Year | M50: =SUM(M46,M48) -> 284839328 | N50: =N48+N46 -> 18432669 | O50: =O48+O46 -> 303271997 | P50: =P48+P46 -> 43172648 | Q50: =Q48+Q46 -> 18722198

Sheet Assumption
J1: Assumption County 2013 Statement of Activities
J2: Issued: December 31, 2013
L4: NET (EXPENSE) REVENUE AND CHANGES IN NET ASSETS
J5: PROGRAM REVENUES | L5: PRIMARY GOVERNMENT
A6: FUNCTIONS/PROGRAMS | I6: Expenses | J6: Charges for Services | K6: Operating Grants and Contributions | L6: Governmental Unit | M6: Component Units
A7: Primary Government:
B8: Government Activities:
C9: General government
D10: Legislative | I10: -500036 | L10: =SUM(I10:K10) -> -500036
D11: Judicial | I11: -973086 | J11: 80459 | L11: =SUM(I11:K11) -> -892627
D12: Executive | I12: -41555 | L12: =SUM(I12:K12) -> -41555
D13: Elections | I13: -47260 | L13: =SUM(I13:K13) -> -47260
D14: Financial and administrative | I14: -341977 | L14: =SUM(I14:K14) -> -341977
D15: Other general administration | I15: -149648 | L15: =SUM(I15:K15) -> -149648
C16: Public safety | I16: -3129680 | J16: 713313 | K16: 546282 | L16: =SUM(I16:K16) -> -1870085
C17: Public works | I17: -5670444 | J17: 2211875 | K17: 252864 | L17: =SUM(I17:K17) -> -3205705
C18: Health and welfare | I18: -2903954 | J18: 197975 | K18: 3656931 | L18: =SUM(I18:K18) -> 950952
C19: Culture and recreation | I19: -1221329 | J19: 11198 | K19: 7950 | L19: =SUM(I19:K19) -> -1202181
C20: Economic development | I20: -179461 | J20: 2739 | L20: =SUM(I20:K20) -> -176722
C21: Debt service | I21: -461 | L21: =SUM(I21:K21) -> -461
E23: Total Government Activities | I23: =SUM(I10:I21) -> -15158891 | J23: =SUM(J10:J21) -> 3217559 | K23: =SUM(K10:K21) -> 4464027 | L23: =SUM(L10:L21) -> -7477305
A25: Component units:
B26: Waterworks District No. 1 | I26: -3508343 | J26: 4185201 | M26: =SUM(I26:L26) -> 676858
B27: Assumption parish assessor | I27: -827738 | M27: =SUM(I27:L27) -> -827738
B28: Assumption parish clerk of court | I28: -871957 | J28: 790096 | M28: =SUM(I28:L28) -> -81861
E30: Total component units | I30: =SUM(I26:I28) -> -5208038 | J30: =SUM(J26:J28) -> 4975297 | K30: =SUM(K26:K28) -> 0 | L30: =SUM(L26:L28) -> 0 | M30: =SUM(M26:M28) -> -232741
G32: General Revenues:
G33: Local sources
H34: Taxes:
I35: Ad valorem | L35: 3578953 | M35: 835517
I36: Sales and use taxes | L36: 4938431
I37: Other taxes | L37: 962612
H38: Other revenue | L38: 876717 | M38: 128219
G39: State sources
H40: Unrestricted revenue | L40: 809136 | M40: 36109
H42: Total General Revenues | L42: =SUM(L35:L40) -> 11165849 | M42: =SUM(M35:M40) -> 999845
H44: Change in Net Assets | L44: =L42+L23 -> 3688544 | M44: =M42+M30 -> 767104
E46: Net Assets- Beginning of Year | L46: 60909408 | M46: 17530322
E48: Net Assets- End of Year | L48: =SUM(L44,L46) -> 64597952 | M48: =M46+M44 -> 18297426

Sheet Avoyelles
J1: Avoyelles County 2013 Statement of Activities
J2: Issued: December 31, 2013
M4: NET (EXPENSE) REVENUE AND CHANGE IN NET ASSETS
J5: PROGRAM REVENUES | M5: PRIMARY GOVERNMENT
A6: FUNCTIONS/PROGRAMS | I6: Expenses | J6: Charges for Services | K6: Operating Grants and Contributions | L6: Capital Grants and Contributions | M6: Governmental Activities | N6: Component Units
A7: Primary Government:
B8: Government Activities:
C9: General government | I9: -1799591 | J9: 97332 | M9: =SUM(I9:L9) -> -1702259
C10: Public safety | I10: -851197 | J10: 421565 | K10: 17453 | M10: =SUM(I10:L10) -> -412179
C11: Public works | I11: -4483547 | J11: 1498 | K11: 551866 | L11: 1399959 | M11: =SUM(I11:L11) -> -2530224
C12: Health and welfare | I12: -923688 | K12: 651146 | M12: =SUM(I12:L12) -> -272542
C13: Culture and recreation | I13: -649782 | M13: =SUM(I13:L13) -> -649782
C14: Economic development | I14: -99146 | M14: =SUM(I14:L14) -> -99146
E16: Total Government Activities | I16: =SUM(I9:I14) -> -8806951 | J16: =SUM(J9:J14) -> 520395 | K16: =SUM(K9:K14) -> 1220465 | L16: =SUM(L9:L14) -> 1399959 | M16: =SUM(M9:M14) -> -5666132
A18: Component units:
B19: Governmental activities | I19: -394480 | J19: 158142 | K19: 87500 | N19: =SUM(I19:M19) -> -148838
G21: General Revenues:
H22: Taxes:
I23: Property taxes, levied for general purposes | M23: 2033687
I24: Sales and use taxes, levied for general purposes | M24: 4481433 | N24: 113357
H25: Grants and contributions not restricted to specific programs:
I26: State revenue sharing | M26: 173216
I27: Parish equalization | M27: 372408
I28: State grants | M28: 591608
I29: Casino revenue | M29: 112335
H30: Interest and investment earnings | M30: 23802 | N30: 669
H31: Miscellaneous | M31: 128711 | N31: 14194
H33: Total General Revenues | M33: =SUM(M23:M31) -> 7917200 | N33: =SUM(N23:N31) -> 128220
H35: Change in Net Assets | M35: =SUM(M16,M33) -> 2251068 | N35: =N33+N19 -> -20618
E37: Net Assets- Beginning of Year | M37: 12774390 | N37: 273206
E39: Net Assets- End of Year | M39: =SUM(M35,M37) -> 15025458 | N39: =N37+N35 -> 252588

Sheet Beauregard
J1: Beauregard County 2013 Statement of Activities
J2: Issued: December 31, 2013
M4: NET (EXPENSE) REVENUE AND CHANGES IN NET ASSETS
J5: PROGRAM REVENUES | M5: PRIMARY GOVERNMENT
A6: FUNCTIONS/PROGRAMS | I6: Expenses | J6: Charges for Services | K6: Operating Grants and Contributions | L6: Capital Grants and Contributions | M6: Governmental Unit
A7: Primary Government:
B8: Government Activities:
C9: General government
D10: Legislative | I10: -233073 | M10: =SUM(I10:L10) -> -233073
D11: Judicial | I11: -1228208 | J11: 894833 | K11: 9247 | M11: =SUM(I11:L11) -> -324128
D12: Elections | I12: -73428 | M12: =SUM(I12:L12) -> -73428
D13: Financial and administrative | I13: -883767 | J13: 203327 | M13: =SUM(I13:L13) -> -680440
D14: Other general government activities | I14: -641778 | J14: 171670 | K14: 52950 | M14: =SUM(I14:L14) -> -417158
C15: Public safety | I15: -1649102 | K15: 53092 | M15: =SUM(I15:L15) -> -1596010
C16: Public works | I16: -7046314 | J16: 18000 | K16: 662708 | L16: 359778 | M16: =SUM(I16:L16) -> -6005828
C17: Health and welfare | I17: -531255 | M17: =SUM(I17:L17) -> -531255
C18: Culture and recreation | I18: -1073277 | K18: 75691 | L18: 35000 | M18: =SUM(I18:L18) -> -962586
C19: Sanitation | I19: -1461093 | J19: 66138 | M19: =SUM(I19:L19) -> -1394955
C20: Other activities | I20: -78307 | M20: =SUM(I20:L20) -> -78307
C21: Interest on long-term debt | I21: -106427 | M21: =SUM(I21:L21) -> -106427
E23: Total Government Activities | I23: =SUM(I10:I21) -> -15006029 | J23: =SUM(J10:J21) -> 1353968 | K23: =SUM(K10:K21) -> 853688 | L23: =SUM(L10:L21) -> 394778 | M23: =SUM(M10:M21) -> -12403595
G25: General Revenues:
H26: Taxes:
I27: Ad valorem taxes | M27: 5473137
I28: Severance taxes | M28: 1596193
I29: Sales taxes | M29: 6529270
I30: State revenue sharing, unrestricted | M30: 129957
I31: Other taxes | M31: 178211
H32: Interest and investment earnings | M32: 30993
H33: Special items:
I34: Miscellaneous | M34: 280384
I35: Gain on disposal of assets | M35: 292128
H37: Total General Revenues | M37: =SUM(M27:M35) -> 14510273
H39: Change in Net Assets | M39: =M37+M23 -> 2106678
E41: Net Assets- Beginning of Year | M41: 45699042
E43: Net Assets- End of Year | M43: =SUM(M39,M41) -> 47805720

Sheet Bienville
J1: Bienville County 2013 Statement of Activities
J2: Issued: December 31, 2013
M4: NET (EXPENSE) REVENUE AND CHANGE IN NET ASSETS
J5: PROGRAM REVENUES
A6: FUNCTIONS/PROGRAMS | I6: Expenses | J6: Charges for Services | K6: Operating Grants and Contributions | L6: Capital Grants and Contributions
A7: Primary Government:
B8: Government Activities:
C9: General government | I9: -2274040 | J9: 21531 | K9: 117418 | M9: =SUM(I9:L9) -> -2135091
C10: Public safety | I10: -589526 | M10: =SUM(I10:L10) -> -589526
C11: Public works | I11: -6911006 | K11: 315519 | L11: 933040 | M11: =SUM(I11:L11) -> -5662447
C12: Health and welfare | I12: -366113 | K12: 389793 | M12: =SUM(I12:L12) -> 23680
C13: Conservation of natural resources | I13: -37414 | M13: =SUM(I13:L13) -> -37414
C14: Economic development and assistance | I14: -380167 | K14: 80704 | M14: =SUM(I14:L14) -> -299463
C15: Debt service | I15: -409519 | M15: =SUM(I15:L15) -> -409519
E17: Total Government Activities | I17: =SUM(I9:I15) -> -10967785 | J17: =SUM(J9:J15) -> 21531 | K17: =SUM(K9:K15) -> 903434 | L17: =SUM(L9:L15) -> 933040 | M17: =SUM(M9:M15) -> -9109780
G19: General Revenues:
H20: Taxes:
I21: Property taxes levied for general purposes | M21: 1645255
I22: Property taxes levied for public works | M22: 1942336
I23: Property taxes levied for debt service | M23: 1142496
I24: Sales and use taxes levied for public works | M24: 2259144
H25: Other taxes, penalties, and interest | M25: 32045
H26: Grants and contributions not restricted to specific programs | M26: 1530570
H27: Licenses and permits | M27: 52840
H28: Unrestricted investment earnings | M28: 262524
H29: Special item - Gain (loss) on disposal of assets | M29: 22700
H31: Total General Revenues | M31: =SUM(M21:M29) -> 8889910
H33: Change in Net Assets | M33: =SUM(M17,M31) -> -219870
E35: Net Assets- Beginning of Year | M35: 32795084
E37: Net Assets- End of Year | M37: =SUM(M33,M35) -> 32575214

Sheet Bossier
J1: Bossier County 2013 Statement of Activities
J2: Issued: December 31, 2013
M4: NET (EXPENSE) REVENUE AND CHANGES IN NET ASSETS
J5: PROGRAM REVENUES | M5: PRIMARY GOVERNMENT
A6: FUNCTIONS/PROGRAMS | I6: Expenses | J6: Charges for Services | K6: Operating Grants and Contributions | L6: Capital Grants and Contributions | M6: Governmental Activities | N6: Business-type Activities | O6: Total
A7: Primary Government:
B8: Government Activities:
C9: General government:
D10: Zoning and planning | I10: -6106 | M10: =SUM(I10:L10) -> -6106 | O10: =SUM(M10:N10) -> -6106
D11: Legislative | I11: -349570 | M11: =SUM(I11:L11) -> -349570 | O11: =SUM(M11:N11) -> -349570
D12: Judicial | I12: -2792610 | J12: 1141917 | M12: =SUM(I12:L12) -> -1650693 | O12: =SUM(M12:N12) -> -1650693
D13: Elections | I13: -126899 | M13: =SUM(I13:L13) -> -126899 | O13: =SUM(M13:N13) -> -126899
D14: Finance and administrative | I14: -1726144 | J14: 20700 | M14: =SUM(I14:L14) -> -1705444 | O14: =SUM(M14:N14) -> -1705444
D15: Other | I15: -3196970 | J15: 299550 | K15: 359 | M15: =SUM(I15:L15) -> -2897061 | O15: =SUM(M15:N15) -> -2897061
C16: Public safety | I16: -5059208 | J16: 242010 | M16: =SUM(I16:L16) -> -4817198 | O16: =SUM(M16:N16) -> -4817198
C17: Public works | I17: -16834285 | J17: 251723 | K17: 146235 | L17: 7904940 | M17: =SUM(I17:L17) -> -8531387 | O17: =SUM(M17:N17) -> -8531387
C18: Public utilities | I18: -149734 | L18: 69792 | M18: =SUM(I18:L18) -> -79942 | O18: =SUM(M18:N18) -> -79942
C19: Health and welfare | I19: -3852114 | K19: 3679953 | M19: =SUM(I19:L19) -> -172161 | O19: =SUM(M19:N19) -> -172161
C20: Culture and recreation | I20: -5397105 | J20: 71519 | M20: =SUM(I20:L20) -> -5325586 | O20: =SUM(M20:N20) -> -5325586
C21: Economic development | I21: -2202272 | M21: =SUM(I21:L21) -> -2202272 | O21: =SUM(M21:N21) -> -2202272
C22: Interest on long-term debt | I22: -2194004 | M22: =SUM(I22:L22) -> -2194004 | O22: =SUM(M22:N22) -> -2194004
E24: Total Government Activities | I24: =SUM(I10:I22) -> -43887021 | J24: =SUM(J10:J22) -> 2027419 | K24: =SUM(K10:K22) -> 3826547 | L24: =SUM(L10:L22) -> 7974732 | M24: =SUM(M10:M22) -> -30058323 | O24: =SUM(O10:O22) -> -30058323
B26: Business-type Activities:
C27: Sewer and water | I27: -815573 | J27: 1758109 | N27: =SUM(I27:M27) -> 942536 | O27: =N27 -> 942536
E29: Total business-type Activities | I29: =SUM(I27:I27) -> -815573 | J29: =SUM(J27:J27) -> 1758109 | K29: =SUM(K27:K27) -> 0 | L29: =SUM(L27:L27) -> 0 | M29: =SUM(M27:M27) -> 0 | N29: =SUM(N27:N27) -> 942536 | O29: =SUM(O27:O27) -> 942536
E31: Total government | I31: =I29+I24 -> -44702594 | J31: =J29+J24 -> 3785528 | K31: =K29+K24 -> 3826547 | L31: =L29+L24 -> 7974732 | M31: =M29+M24 -> -30058323 | N31: =N29+N24 -> 942536 | O31: =O29+O24 -> -29115787
G33: General Revenues:
H34: Taxes:
I35: Ad valorem | M35: 14172204 | O35: =SUM(M35:N35) -> 14172204
I36: Sales taxes | M36: 15605483 | O36: =SUM(M36:N36) -> 15605483
I37: Gaming tax revenues | M37: 4207854 | O37: =SUM(M37:N37) -> 4207854
I38: Franchise taxes | M38: 406106 | O38: =SUM(M38:N38) -> 406106
I39: Other taxes | M39: 1164826 | O39: =SUM(M39:N39) -> 1164826
H40: Investment earnings | M40: 39676 | N40: 855 | O40: =SUM(M40:N40) -> 40531
H41: State revenue sharing | M41: 650991 | O41: =SUM(M41:N41) -> 650991
H42: Miscellaneous | M42: 2562419 | N42: 2879 | O42: =SUM(M42:N42) -> 2565298
H43: Transfers | M43: 161824 | N43: -161824 | O43: =SUM(M43:N43) -> 0
H45: Total General Revenues | M45: 38691383 | N45: =SUM(N35:N43) -> -158090 | O45: =SUM(O35:O43) -> 38813293
H47: Change in Net Assets | M47: =M45+M31 -> 8633060 | N47: =N45+N31 -> 784446 | O47: =SUM(M47:N47) -> 9417506
E49: Net Assets- Beginning of Year | M49: 273279268 | N49: 1951163 | O49: =SUM(M49:N49) -> 275230431
E51: Net Assets- End of Year | M51: =SUM(M47,M49) -> 281912328 | N51: =N49+N47 -> 2735609 | O51: =O49+O47 -> 284647937
M53: Can't distinguish the numbers on pdf, too blurry

Sheet Caddo
J1: Caddo County 2013 Statement of Activities
J2: Issued: December 31, 2013
M4: NET (EXPENSE) REVENUE AND CHANGES IN NET ASSETS
J5: PROGRAM REVENUES
A6: FUNCTIONS/PROGRAMS | I6: Expenses | J6: Charges for Services | K6: Operating Grants and Contributions | L6: Capital Grants and Contributions | M6: Primary Government | N6: Component Units
A7: Primary Government:
B8: Government Activities:
C9: General government | I9: -16327879 | J9: 2657856 | K9: 109667 | L9: 28220 | M9: =SUM(I9:L9) -> -13532136
C10: Criminal justice | I10: -21190633 | J10: 31019 | K10: 1335382 | M10: =SUM(I10:L10) -> -19824232
C11: Health and welfare | I11: -14409692 | J11: 162137 | K11: 11280586 | M11: =SUM(I11:L11) -> -2966969
C12: Highways, streets, and drainage | I12: -25884621 | J12: 572258 | K12: 2180422 | L12: 835032 | M12: =SUM(I12:L12) -> -22296909
C13: Building facilities | I13: -6222969 | K13: 114800 | M13: =SUM(I13:K13) -> -6108169
C14: Sanitation | I14: -2290081 | M14: =SUM(I14:K14) -> -2290081
C15: Culture and recreation | I15: -15171125 | J15: 102387 | K15: 425638 | M15: =SUM(I15:K15) -> -14643100
C16: Economic development | I16: -4153012 | K16: 73955 | M16: =SUM(I16:K16) -> -4079057
C17: Interest and fees on long-term debt | I17: -1515768 | M17: =SUM(I17:K17) -> -1515768
E19: Total Government Activities | I19: =SUM(I9:I17) -> -107165780 | J19: =SUM(J9:J17) -> 3525657 | K19: =SUM(K9:K17) -> 15520450 | L19: =SUM(L9:L17) -> 863252 | M19: =SUM(M9:M17) -> -87256421
A21: Component units:
B22: Judicial services | I22: -8462144 | J22: 1539156 | K22: 6584270 | N22: =SUM(I22:M22) -> -338718
B23: Economic development | I23: -6975 | L23: 7500000 | N23: =SUM(I23:M23) -> 7493025
B24: Public safety | I24: -38053859 | J24: 12294218 | N24: =SUM(I24:M24) -> -25759641
B25: Fire protection services | I25: -10980607 | J25: 3013946 | K25: 261553 | L25: 212526 | N25: =SUM(I25:M25) -> -7492582
B26: Sewerage services | I26: -1207390 | J26: 947869 | N26: =SUM(I26:M26) -> -259521
B27: Water services | I27: -1901688 | J27: 2000218 | N27: =SUM(I27:M27) -> 98530
B28: Hospital services | I28: -16701576 | J28: 14603792 | K28: 1377931 | L28: 296277 | N28: =SUM(I28:M28) -> -423576
E30: Total component units | I30: =SUM(I22:I28) -> -77314239 | J30: =SUM(J22:J28) -> 34399199 | K30: =SUM(K22:K28) -> 8223754 | L30: =SUM(L22:L28) -> 8008803 | M30: =SUM(M22:M28) -> 0 | N30: =SUM(N22:N28) -> -26682483
G32: General Revenues:
H33: Taxes:
I34: Property taxes levied for general purposes | M34: 55858768 | N34: 7938894
I35: Property taxes levied for debt service | M35: 2883688
I36: Sales taxes | M36: 9544058 | N36: 15696184
I37: Franchise taxes | M37: 213429
I38: Telephone tariff | N38: 3873072
H39: State revenue sharing and supplemental pay | N39: 522585
H40: Gaming | M40: 1924061
H41: Grants and contributions not restricted to specific programs | M41: 1310860
H42: Oil and gas leases | M42: 1187767
H43: Investment earnings | M43: 175458 | N43: 137926
H44: Inmate work release revenue | N44: 1731328
H45: Fire insurance rebate | N45: 214324
H46: Miscellaneous | M46: 939427 | N46: 1894072
H48: Total General Revenues | M48: =SUM(M33:M46) -> 74037516 | N48: =SUM(N34:N46) -> 32008385
H50: Change in Net Assets | M50: =M48+M19 -> -13218905 | N50: =N48+N30 -> 5325902
H52: Net position - beginning, as previously stated | M52: 369601880 | N52: 50670840
H54: Adjustment - opening net position for component unit included in the current year | N54: 34751
H56: Prior period adjustment | M56: -2608226 | N56: 40503
E58: Net Assets- Beginning, as restated | M58: 366993654 | N58: 50746094
E60: Net Assets- End of Year | M60: =SUM(M50,M58) -> 353774749 | N60: =N58+N50 -> 56071996

Sheet Calcasieu
J1: Calcasieu County 2013 Statement of Activities
J2: Issued: December 31, 2013
M4: NET (EXPENSE) REVENUE AND CHANGE IN NET ASSETS
J5: PROGRAM REVENUES | M5: PRIMARY GOVERNMENT
A6: FUNCTIONS/PROGRAMS | I6: Expenses | J6: Charges for Services | K6: Operating Grants and Contributions | L6: Capital Grants and Contributions | M6: Governmental Activities | N6: Business-type Activities | O6: Total | P6: Component Units
A7: Primary Government:
B8: Government Activities:
C9: General government | I9: -26708294 | J9: 10909651 | K9: 1697421 | L9: 893024 | M9: =SUM(I9:L9) -> -13208198 | O9: =SUM(M9:N9) -> -13208198
C10: Public safety | I10: -14697518 | J10: 1164201 | K10: 2515578 | M10: =SUM(I10:L10) -> -11017739 | O10: =SUM(M10:N10) -> -11017739
C11: Public works | I11: -36610516 | J11: 218293 | K11: 4188992 | L11: 2805046 | M11: =SUM(I11:L11) -> -29398185 | O11: =SUM(M11:N11) -> -29398185
C12: Sanitation | I12: -6166860 | J12: 240 | M12: =SUM(I12:L12) -> -6166620 | O12: =SUM(M12:N12) -> -6166620
C13: Health and welfare | I13: -14842859 | J13: 171434 | K13: 7723418 | L13: 37210 | M13: =SUM(I13:L13) -> -6910797 | O13: =SUM(M13:N13) -> -6910797
C14: Culture and recreation | I14: -13726013 | J14: 511155 | K14: 32730 | L14: 2176242 | M14: =SUM(I14:L14) -> -11005886 | O14: =SUM(M14:N14) -> -11005886
C15: Economic development | I15: -16911643 | J15: 794458 | K15: 87505 | L15: 501988 | M15: =SUM(I15:L15) -> -15527692 | O15: =SUM(M15:N15) -> -15527692
E17: Total Government Activities | I17: =SUM(I9:I15) -> -129663703 | J17: =SUM(J9:J15) -> 13769432 | K17: =SUM(K9:K15) -> 16245644 | L17: =SUM(L9:L15) -> 6413510 | M17: =SUM(M9:M15) -> -93235117 | O17: =SUM(O9:O15) -> -93235117 | P17: =SUM(P9:P15) -> 0
B19: Business-type Activities:
C20: Water | I20: -1173252 | J20: 972811 | N20: =SUM(I20:L20) -> -200441 | O20: =SUM(M20:N20) -> -200441
C21: Sewer | I21: -984594 | J21: 303496 | N21: =SUM(I21:L21) -> -681098 | O21: =SUM(M21:N21) -> -681098
E23: Total Business-type Activities | I23: =SUM(I20:I21) -> -2157846 | J23: =SUM(J20:J21) -> 1276307 | K23: =SUM(K20:K21) -> 0 | L23: =SUM(L20:L21) -> 0 | M23: =SUM(M20:M21) -> 0 | N23: =SUM(N20:N21) -> -881539 | O23: =SUM(O20:O21) -> -881539 | P23: =SUM(P15:P21) -> 0
E25: Total primary government | I25: =I23+I17 -> -131821549 | J25: =J23+J17 -> 15045739 | K25: =SUM(K17+K23) -> 16245644 | L25: =SUM(L17+L23) -> 6413510 | M25: =M23+M17 -> -93235117 | N25: =N23+N17 -> -881539 | O25: =O23+O17 -> -94116656 | P25: =SUM(P16:P23) -> 0
A27: Component units:
B28: Calcasieu Parish public trust authority | I28: -677888 | J28: 524104 | P28: =SUM(I28:M28) -> -153784
B29: West Calcasieu Cameron Hospital | I29: -70501459 | J29: 62399171 | K29: 23240 | P29: =SUM(I29:L29) -> -8079048
B30: Sulfur parks and recreation | I30: -5389452 | J30: 2059927 | P30: =SUM(I30:L30) -> -3329525
B31: Gravity drainage District 4 of Ward 3 | I31: -2568122 | L31: 168820 | P31: =SUM(I31:L31) -> -2399302
B32: Airport authority District No. 1 | I32: -3844490 | J32: 1660328 | K32: 381325 | L32: 3288118 | P32: =SUM(I32:L32) -> 1485281
B33: Other component units | I33: -40655166 | J33: 15439370 | K33: 7198453 | L33: 3190023 | P33: =SUM(I33:L33) -> -14827320
E35: Total component units | I35: =SUM(I28:I33) -> -123636577 | J35: =SUM(J28:J33) -> 82082900 | K35: =SUM(K28:K33) -> 7603018 | L35: =SUM(L28:L33) -> 6646961 | M35: =SUM(M28:M33) -> 0 | N35: =SUM(N28:N33) -> 0 | O35: =SUM(O28:O33) -> 0 | P35: =SUM(P28:P33) -> -27303698
G37: General Revenues:
H38: Taxes:
I39: Property | M39: 47011753 | N39: 339531 | O39: =SUM(M39:N39) -> 47351284 | P39: 41602575
I40: Sales | M40: 38649679 | O40: =SUM(M40:N40) -> 38649679
I41: Franchise | M41: 957265 | O41: =SUM(M41:N41) -> 957265
H42: Gaming revenues | M42: 11424986 | O42: =SUM(M42:N42) -> 11424986
H43: Grants and contributions not restricted to specific programs | M43: 2654935 | O43: =SUM(M43:N43) -> 2654935 | P43: 726870
H44: Investment earnings | M44: 49857 | N44: 8615 | O44: =SUM(M44:N44) -> 58472 | P44: 132952
H45: Gain on sale of capital assets | M45: 229681 | O45: =SUM(M45:N45) -> 229681 | P45: 44048
H46: Miscellaneous | M46: 82419 | N46: 22002 | O46: =SUM(M46:N46) -> 104421 | P46: 4126937
H47: Transfers | M47: -263947 | N47: 263947 | O47: =SUM(M47:N47) -> 0
H49: Total General Revenues | M49: =SUM(M39:M47) -> 100796628 | N49: =SUM(N39:N47) -> 634095 | O49: =SUM(O39:O47) -> 101430723 | P49: =SUM(P39:P46) -> 46633382
H51: Change in Net Assets | M51: =M49+M25 -> 7561511 | N51: =N49+N25 -> -247444 | O51: =O49+O25 -> 7314067 | P51: =P49+P35 -> 19329684
E53: Net Assets- Beginning of Year | M53: 748695349 | N53: 10760427 | O53: =SUM(M53:N53) -> 759455776 | P53: 298255364
E55: Net Assets- End of Year | M55: =SUM(M51,M53) -> 756256860 | N55: =N53+N51 -> 10512983 | O55: =O53+O51 -> 766769843 | P55: =P53+P51 -> 317585048

Sheet Caldwell
J1: Caldwell County 2013 Statement of Activities
J2: Issued: December 31, 2013
J5: PROGRAM REVENUES
A6: FUNCTIONS/PROGRAMS | I6: Expenses | J6: Charges for Services | K6: Operating Grants and Contributions | L6: Capital Grants and Contributions | M6: NET (EXPENSE) REVENUE AND CHANGES IN NET ASSETS
A7: Primary Government:
B8: Government Activities:
C9: General government | I9: -1723572 | J9: 173733 | K9: 264518 | M9: =SUM(I9:L9) -> -1285321
C10: Public safety | I10: -543904 | J10: 68978 | K10: 222356 | L10: 46980 | M10: =SUM(I10:L10) -> -205590
C11: Public works | I11: -2752221 | K11: 1524970 | L11: 578014 | M11: =SUM(I11:L11) -> -649237
C12: Health and welfare | I12: -195994 | M12: =SUM(I12:L12) -> -195994
C13: Culture and recreation | I13: -207512 | J13: 16469 | K13: 15399 | L13: 20670 | M13: =SUM(I13:L13) -> -154974
C14: Economic development and assistance | I14: -238412 | M14: =SUM(I14:L14) -> -238412
C15: Transportation | I15: -27853 | J15: 3841 | K15: 69176 | M15: =SUM(I15:L15) -> 45164
E17: Total Government Activities | I17: =SUM(I9:I15) -> -5689468 | J17: =SUM(J9:J15) -> 263021 | K17: =SUM(K9:K15) -> 2096419 | L17: =SUM(L9:L15) -> 645664 | M17: =SUM(M9:M15) -> -2684364
G19: General Revenues:
H20: Property taxes levied for:
I21: General purposes | M21: 449958
I22: Public works | M22: 510292
I23: Health and welfare | M23: 126841
I24: Culture and recreation | M24: 322042
I25: Economic development and assistance | M25: 326059
H26: Sales and use taxes levied for:
I27: General purposes | M27: 252837
I28: Public works | M28: 1603585
H29: Other taxes, penalties and interest | M29: 11854
H30: Unrestricted investment earnings | M30: 26586
H31: Other revenues | M31: 9807
H33: Total General Revenues | M33: =SUM(M21:M31) -> 3639861
H35: Change in Net Assets | M35: =SUM(M17,M33) -> 955497
E37: Net Assets- Beginning of Year | M37: 18894603
E39: Net Assets- End of Year | M39: =SUM(M35,M37) -> 19850100

Sheet Cameron
I1: Cameron County 2013 Statement of Activities
J2: Issued: December 31, 2013
L5: NET (EXPENSES) REVENUES AND CHANGES IN NET ASSETS
A6: FUNCTIONS/PROGRAMS | I6: Expenses | J6: Operating Grants and Contributions | K6: Capital Grants and Contributions | L6: Governmental Activities
A7: Primary Government:
B8: Government Activities:
B9: General government:
C10: Legislative | I10: -204907 | L10: =SUM(I10:K10) -> -204907
C11: Judicial | I11: -1395672 | L11: =SUM(I11:K11) -> -1395672
C12: Elections | I12: -222 | L12: =SUM(I12:K12) -> -222
C13: Finance and administrative | I13: -1795846 | J13: 124586 | L13: =SUM(I13:K13) -> -1671260
C14: Other general government | I14: -6103072 | L14: =SUM(I14:K14) -> -6103072
C15: Interest on long-term debt | I15: -328311 | L15: =SUM(I15:K15) -> -328311
C16: Public safety | I16: -1288757 | J16: 204251 | K16: 4319561 | L16: =SUM(I16:K16) -> 3235055
C17: Public works | I17: -4883639 | J17: 100943 | K17: 251906 | L17: =SUM(I17:K17) -> -4530790
C18: Culture and recreation | I18: -1289236 | L18: =SUM(I18:K18) -> -1289236
C19: Health and welfare | I19: -395890 | L19: =SUM(I19:K19) -> -395890
C20: Economic development | I20: -2866511 | J20: 13635190 | L20: =SUM(I20:K20) -> 10768679
E22: Total Government Activities | I22: =SUM(I10:I20) -> -20552063 | J22: =SUM(J10:J20) -> 14064970 | K22: =SUM(K10:K20) -> 4571467 | L22: =SUM(L10:L20) -> -1915626
G24: General Revenues:
H25: Taxes:
I26: Property taxes, levied for general purposes | L26: 6689108
I27: Other taxes for general purposes | L27: 1099003
H28: Licenses and permits | L28: 399674
H29: Fines, forfeitures, and court costs | L29: 187131
H30: Intergovernmental:
I31: State | L31: 5939885
I32: Local | L32: -639
H33: Gain (loss) on disposal of capital assets | L33: 151221
H34: Interest earnings | L34: 21036
H35: Other | L35: 451353
H37: Total General Revenues | L37: =SUM(L26:L35) -> 14937772
H39: Change in Net Assets | L39: =SUM(L22,L37) -> 13022146
H41: Net position - beginning | L41: 146125596
H43: Prior period adjustment | L43: -12953737
E45: Net Assets- Beginning of Year | L45: 133171859
E47: Net Assets- End of Year | L47: =SUM(L39,L45) -> 146194005

Sheet Catahoula
J1: Catahoula County 2013 Statement of Activities
J2: Issued: December 31, 2013
J5: PROGRAM REVENUES
A6: FUNCTIONS/PROGRAMS | I6: Expenses | J6: Charges for Services | K6: Operating Grants and Contributions | L6: Capital Grants and Contributions | M6: NET (EXPENSE) REVENUE AND CHANGES IN NET ASSETS
A7: Primary Government:
B8: Government Activities:
C9: General government | I9: -680369 | J9: 113760 | K9: 3293 | M9: =SUM(I9:L9) -> -563316
C10: Public safety | I10: -512635 | J10: 75120 | K10: 171908 | M10: =SUM(I10:L10) -> -265607
C11: Public works | I11: -2382377 | J11: 2365 | K11: 760794 | L11: 60650 | M11: =SUM(I11:L11) -> -1558568
C12: Health and welfare | I12: -242320 | K12: 350621 | M12: =SUM(I12:L12) -> 108301
C13: Culture and recreation | I13: -361409 | J13: 6187 | K13: 26195 | M13: =SUM(I13:L13) -> -329027
C14: Economic development and assistance | I14: -2249 | M14: =SUM(I14:L14) -> -2249
C15: Interest expense | I15: -9343 | M15: =SUM(I15:L15) -> -9343
E17: Total Government Activities | I17: =SUM(I9:I15) -> -4190702 | J17: =SUM(J9:J15) -> 197432 | K17: =SUM(K9:K15) -> 1312811 | L17: =SUM(L9:L15) -> 60650 | M17: =SUM(M9:M15) -> -2619809
G19: General Revenues:
H20: Property taxes | M20: 827325
H21: Sales and use taxes | M21: 1635040
H22: Other taxes, penalties and interest | M22: 5639
H23: Grants and contributions not restricted to specific programs | M23: 324352
H24: Unrestricted investment earnings | M24: 5485
H25: Gain (loss) on sale of capital assets | M25: 18118
H26: Proceeds from insurance | M26: 12050
H27: Other | M27: 28240
H29: Total General Revenues | M29: =SUM(M20:M27) -> 2856249
H31: Change in Net Assets | M31: =SUM(M17,M29) -> 236440
E33: Net Assets- Beginning of Year | M33: 8289746
E35: Net Assets- End of Year | M35: =SUM(M31,M33) -> 8526186

Sheet Claiborne
J1: Claiborne County 2013 Statement of Activities
J2: Issued: December 31, 2013
J5: PROGRAM REVENUES
A6: FUNCTIONS/PROGRAMS | I6: Expenses | J6: Charges for Services | K6: Operating Grants and Contributions | L6: Capital Grants and Contributions | M6: NET (EXPENSE) REVENUE AND CHANGES IN NET ASSETS
A7: Primary Government:
B8: Government Activities:
C9: General government | I9: -1518254 | J9: 402549 | M9: =SUM(I9:L9) -> -1115705
C10: Public safety | I10: -376302 | K10: 110377 | L10: 49781 | M10: =SUM(I10:L10) -> -216144
C11: Public works | I11: -3221702 | K11: 448932 | L11: 130201 | M11: =SUM(I11:L11) -> -2642569
C12: Health and welfare | I12: -875416 | J12: 8533 | K12: 639375 | M12: =SUM(I12:L12) -> -227508
C13: Culture and recreation | I13: -539041 | J13: 1983 | K13: 2438 | M13: =SUM(I13:L13) -> -534620
C14: Economic development and assistance | I14: -60016 | M14: =SUM(I14:L14) -> -60016
C15: Conservation | I15: -5200 | M15: =SUM(I15:L15) -> -5200
C16: Interest expense | I16: -43230 | M16: =SUM(I16:L16) -> -43230
E18: Total Government Activities | I18: =SUM(I9:I16) -> -6639161 | J18: =SUM(J9:J16) -> 413065 | K18: =SUM(K9:K16) -> 1201122 | L18: =SUM(L9:L16) -> 179982 | M18: =SUM(M9:M16) -> -4844992
G20: General Revenues:
H21: Property taxes levied for:
I22: General purposes | M22: 907751
I23: Public works | M23: 1358920
I24: Culture and recreation | M24: 782665
H25: Sales and use taxes levied for public works | M25: 941476
H26: Other taxes, penalties and interest | M26: 12275
H27: Grants and contributions not restricted to specific programs | M27: 1507924
H28: Unrestricted investment earnings | M28: 175700
H29: Gain on sale of capital assets | M29: 37908
H30: Other | M30: 69090
H32: Total General Revenues | M32: =SUM(M22:M30) -> 5793709
H34: Change in Net Assets | M34: =SUM(M18,M32) -> 948717
E36: Net Assets- Beginning of Year | M36: 14433436
E38: Net Assets- End of Year | M38: =SUM(M34,M36) -> 15382153

Sheet Concordia
J1: Concordia County 2013 Statement of Activities
J2: Issued: December 31, 2013
J5: PROGRAM REVENUES
A6: FUNCTIONS/PROGRAMS | I6: Expenses | J6: Charges for Services | K6: Operating Grants and Contributions | L6: Capital Grants and Contributions | M6: NET (EXPENSE) REVENUE AND CHANGES IN NET ASSETS
A7: Primary Government:
B8: Government Activities:
B9: General government:
C10: Legislative | I10: -231502 | M10: =SUM(I10:L10) -> -231502
C11: Judicial | I11: -614792 | M11: =SUM(I11:L11) -> -614792
C12: Elections | I12: -40450 | M12: =SUM(I12:L12) -> -40450
C13: Finance | I13: -348180 | M13: =SUM(I13:L13) -> -348180
C14: Other general | I14: -876320 | K14: 54243 | L14: 171774 | M14: =SUM(I14:L14) -> -650303
B15: Public safety | I15: -230232 | J15: 148144 | K15: 140704 | M15: =SUM(I15:L15) -> 58616
B16: Public works | I16: -2920856 | M16: =SUM(I16:L16) -> -2920856
B17: Health and welfare | I17: -138664 | K17: 2189 | M17: =SUM(I17:L17) -> -136475
B18: Culture and recreation | I18: -31153 | M18: =SUM(I18:L18) -> -31153
B19: Economic development | I19: -188191 | K19: 120413 | M19: =SUM(I19:L19) -> -67778
B20: Transportation | I20: -33545 | M20: =SUM(I20:L20) -> -33545
B21: Interest on long-term debt | I21: -433026 | M21: =SUM(I21:L21) -> -433026
E23: Total Government Activities | I23: =SUM(I10:I21) -> -6086911 | J23: =SUM(J10:J21) -> 148144 | K23: =SUM(K10:K21) -> 317549 | L23: =SUM(L10:L21) -> 171774 | M23: =SUM(M10:M21) -> -5449444
G25: General Revenues:
H26: Taxes:
I27: Property taxes | M27: 1752385
I28: Sales taxes | M28: 2864419
I29: Other taxes | M29: 13437
H30: Licenses and permits | M30: 244385
H31: State funds:
I32: Parish transportation | M32: 274906
I33: State revenue sharing | M33: 66922
I34: Severance | M34: 1032251
H35: Investment income | M35: 22857
H36: Other | M36: 553171
H38: Total General Revenues | M38: =SUM(M27:M36) -> 6824733
H40: Change in Net Assets | M40: =SUM(M23,M38) -> 1375289
E42: Net Assets- Beginning of Year | M42: 9542811
E44: Net Assets- End of Year | M44: =SUM(M40,M42) -> 10918100

Sheet Desoto
J1: Desoto County 2013 Statement of Activities
J2: Issued: December 31, 2013
M4: NET (EXPENSE) REVENUE AND CHANGE IN NET ASSETS
J5: PROGRAM REVENUES | M5: PRIMARY GOVERNMENT
A6: FUNCTIONS/PROGRAMS | I6: Expenses | J6: Charges for Services | K6: Operating Grants and Contributions | L6: Capital Grants and Contributions | M6: Governmental Activities | N6: Business-type Activities | O6: Total
A7: Primary Government:
B8: Government Activities:
B9: General government:
C10: Legislative | I10: -371189 | M10: =SUM(I10:L10) -> -371189 | O10: =SUM(M10:N10) -> -371189
C11: Judicial | I11: -2401455 | J11: 1080171 | M11: =SUM(I11:L11) -> -1321284 | O11: =SUM(M11:N11) -> -1321284
C12: Elections | I12: -46958 | M12: =SUM(I12:L12) -> -46958 | O12: =SUM(M12:N12) -> -46958
C13: Finance and administration | I13: -1317624 | J13: 319261 | K13: 56347 | M13: =SUM(I13:L13) -> -942016 | O13: =SUM(M13:N13) -> -942016
C14: Other | I14: -1492190 | M14: =SUM(I14:L14) -> -1492190 | O14: =SUM(M14:N14) -> -1492190
C15: Public safety | I15: -1012619 | K15: 110561 | M15: =SUM(I15:L15) -> -902058 | O15: =SUM(M15:N15) -> -902058
C16: Public works | I16: -8949274 | J16: 304845 | L16: 442442 | M16: =SUM(I16:L16) -> -8201987 | O16: =SUM(M16:N16) -> -8201987
C17: Sanitation | I17: -3857649 | J17: 1179593 | L17: 20000 | M17: =SUM(I17:L17) -> -2658056 | O17: =SUM(M17:N17) -> -2658056
C18: Culture and recreation | I18: -342350 | M18: =SUM(I18:L18) -> -342350 | O18: =SUM(M18:N18) -> -342350
C19: Health and welfare | I19: -1423093 | K19: 2880298 | M19: =SUM(I19:L19) -> 1457205 | O19: =SUM(M19:N19) -> 1457205
C20: Community development | I20: -2054244 | M20: =SUM(I20:L20) -> -2054244 | O20: =SUM(M20:N20) -> -2054244
C21: Economic development | I21: -3278177 | K21: 2701472 | M21: =SUM(I21:L21) -> -576705 | O21: =SUM(M21:N21) -> -576705
C22: Transportation | I22: -764110 | J22: 243905 | K22: 158838 | M22: =SUM(I22:L22) -> -361367 | O22: =SUM(M22:N22) -> -361367
C23: Animal control | I23: -411754 | J23: 26019 | K23: 5542 | M23: =SUM(I23:L23) -> -380193 | O23: =SUM(M23:N23) -> -380193
C24: Interest on long-term debt | I24: -241 | M24: =SUM(I24:L24) -> -241 | O24: =SUM(M24:N24) -> -241
E26: Total Government Activities | I26: =SUM(I10:I24) -> -27722927 | J26: =SUM(J10:J24) -> 3153794 | K26: =SUM(K10:K24) -> 5913058 | L26: =SUM(L10:L24) -> 462442 | M26: =SUM(M10:M24) -> -18193633 | O26: =SUM(O10:O24) -> -18193633
B28: Business-type Activities:
C29: Eastside sewer | I29: -32468 | J29: 11667 | N29: =SUM(I29:L29) -> -20801 | O29: =N29 -> -20801
E31: Total primary government | I31: =I29+I26 -> -27755395 | J31: =J29+J26 -> 3165461 | K31: =K29+K26 -> 5913058 | L31: =L29+L26 -> 462442 | M31: =M29+M26 -> -18193633 | N31: =N29+N26 -> -20801 | O31: =O29+O26 -> -18214434
G33: General Revenues:
H34: Ad valorem taxes | M34: 11903890 | O34: =SUM(M34:N34) -> 11903890
H35: Sales taxes | M35: 7022500 | O35: =SUM(M35:N35) -> 7022500
H36: Severance taxes | M36: 1412788 | O36: =SUM(M36:N36) -> 1412788
H37: Tourism taxes | M37: 144811 | O37: =SUM(M37:N37) -> 144811
H38: Video poker | M38: 128344 | O38: =SUM(M38:N38) -> 128344
H39: Investment earnings | M39: -79777 | O39: =SUM(M39:N39) -> -79777
H40: State revenue sharing | M40: 56559 | O40: =SUM(M40:N40) -> 56559
H41: Gain on disposal of capital assets | M41: 13390 | O41: =SUM(M41:N41) -> 13390
H42: Rentals, leases and royalties | M42: 731230 | O42: =SUM(M42:N42) -> 731230
H43: Other miscellaneous | M43: 253944 | O43: =SUM(M43:N43) -> 253944
G44: Transfers:
H45: Interfund | M45: -21150 | N45: 21150 | O45: =SUM(M45:N45) -> 0
H47: Total General Revenues | M47: =SUM(M34:M45) -> 21566529 | N47: =SUM(N34:N45) -> 21150 | O47: =SUM(O34:O45) -> 21587679
H49: Change in Net Assets | M49: =M47+M31 -> 3372896 | N49: =N47+N31 -> 349 | O49: =O47+O31 -> 3373245
E51: Net Assets- Beginning of Year | M51: 108886870 | N51: 11562 | O51: 108898432
E53: Net Assets- End of Year | M53: =SUM(M49,M51) -> 112259766 | N53: =N51+N49 -> 11911 | O53: =O51+O49 -> 112271677

Sheet East Baton Rouge
J1: East Baton Rouge County 2013 Statement of Activities
J2: Issued: December 31, 2013
M4: NET (EXPENSE) REVENUE AND CHANGE IN NET ASSETS
J5: PROGRAM REVENUES | M5: PRIMARY GOVERNMENT
A6: FUNCTIONS/PROGRAMS | I6: Expenses | J6: Charges for Services | K6: Operating Grants and Contributions | L6: Capital Grants and Contributions | M6: Governmental Activities | N6: Business-type Activities | O6: Total | P6: Component Units
A7: Primary Government:
B8: Government Activities:
C9: General government | I9: -97833150 | J9: 22638870 | K9: 294653 | M9: =SUM(I9:L9) -> -74899627 | O9: =SUM(M9:N9) -> -74899627
C10: Public safety | I10: -237028010 | J10: 28032000 | K10: 10591272 | L10: 301660 | M10: =SUM(I10:L10) -> -198103078 | O10: =SUM(M10:N10) -> -198103078
C11: Transportation | I11: -68812076 | J11: 269248 | K11: 610377 | L11: 12571646 | M11: =SUM(I11:L11) -> -55360805 | O11: =SUM(M11:N11) -> -55360805
C12: Sanitation | I12: -5791 | J12: 54389 | M12: =SUM(I12:L12) -> 48598 | O12: =SUM(M12:N12) -> 48598
C13: Health and welfare | I13: -9499922 | J13: 798229 | K13: 604950 | M13: =SUM(I13:L13) -> -8096743 | O13: =SUM(M13:N13) -> -8096743
C14: Culture and recreation | I14: -38171468 | J14: 320831 | K14: 966897 | M14: =SUM(I14:L14) -> -36883740 | O14: =SUM(M14:N14) -> -36883740
C15: Conservation and development | I15: -50034044 | J15: 3555210 | K15: 35143291 | L15: 254986 | M15: =SUM(I15:L15) -> -11080557 | O15: =SUM(M15:N15) -> -11080557
C16: Interest and fiscal charges on long-term debt | I16: -15625052 | M16: =SUM(I16:L16) -> -15625052 | O16: =SUM(M16:N16) -> -15625052
E18: Total Government Activities | I18: =SUM(I9:I16) -> -517009513 | J18: =SUM(J9:J16) -> 55668777 | K18: =SUM(K9:K16) -> 48211440 | L18: =SUM(L9:L16) -> 13128292 | M18: =SUM(M9:M16) -> -400001004 | O18: =SUM(O9:O16) -> -400001004 | P18: =SUM(P9:P16) -> 0
B20: Business-type Activities:
C21: Airport | I21: -28608472 | J21: 17581662 | K21: 705204 | L21: 5293273 | N21: =SUM(I21:L21) -> -5028333 | O21: =SUM(M21:N21) -> -5028333
C22: Sewer | I22: -131780088 | J22: 74404748 | K22: 6847548 | L22: 2862431 | N22: =SUM(I22:L22) -> -47665361 | O22: =SUM(M22:N22) -> -47665361
C23: Solid waste collection and disposal | I23: -37196266 | J23: 36332687 | N23: =SUM(I23:L23) -> -863579 | O23: =SUM(M23:N23) -> -863579
C24: Convention center | I24: -13305252 | J24: 6459913 | K24: 59498 | L24: 1470739 | N24: =SUM(I24:L24) -> -5315102 | O24: =SUM(M24:N24) -> -5315102
C25: Parking facilities | I25: -1110612 | J25: 1091019 | N25: =SUM(I25:L25) -> -19593 | O25: =SUM(M25:N25) -> -19593
E27: Total Business-type Activities | I27: =SUM(I21:I25) -> -212000690 | J27: =SUM(J21:J25) -> 135870029 | K27: =SUM(K21:K25) -> 7612250 | L27: =SUM(L21:L25) -> 9626443 | M27: =SUM(M21:M25) -> 0 | N27: =SUM(N21:N25) -> -58891968 | O27: =SUM(O21:O25) -> -58891968 | P27: =SUM(P15:P25) -> 0
E29: Total primary government | I29: =I27+I18 -> -729010203 | J29: =J27+J18 -> 191538806 | K29: =SUM(K18+K27) -> 55823690 | L29: =SUM(L18+L27) -> 22754735 | M29: =M27+M18 -> -400001004 | N29: =N27+N18 -> -58891968 | O29: =O27+O18 -> -458892972 | P29: =SUM(P17:P27) -> 0
A31: Component units:
B32: Judicial court services | I32: -56432777 | J32: 25651979 | K32: 23396868 | P32: =SUM(I32:M32) -> -7383930
B33: Economic development districts | I33: -4029211 | J33: 211925 | K33: 2840925 | P33: =SUM(I33:L33) -> -976361
B34: Mass transit | I34: -19426686 | J34: 2186502 | L34: 2830311 | P34: =SUM(I34:L34) -> -14409873
E36: Total component units | I36: =SUM(I32:I34) -> -79888674 | J36: =SUM(J32:J34) -> 28050406 | K36: =SUM(K32:K34) -> 26237793 | L36: =SUM(L32:L34) -> 2830311 | M36: =SUM(M32:M34) -> 0 | N36: =SUM(N32:N34) -> 0 | O36: =SUM(O32:O34) -> 0 | P36: =SUM(P32:P34) -> -22770164
G38: General Revenues:
H39: Taxes:
I40: Property | M40: 94352140 | O40: =SUM(M40:N40) -> 94352140 | P40: 14612939
I41: Gross receipts business | M41: 23093005 | O41: =SUM(M41:N41) -> 23093005
I42: Sales | M42: 219609518 | N42: 42996932 | O42: =SUM(M42:N42) -> 262606450
I43: Occupancy | M43: 2200681 | O43: =SUM(M43:N43) -> 2200681 | P43: 2085006
I44: Occupational | M44: 10382634 | O44: =SUM(M44:N44) -> 10382634
I45: Insurance premium | M45: 3774099 | O45: =SUM(M45:N45) -> 3774099
I46: Gaming admissions | M46: 9438267 | O46: =SUM(M46:N46) -> 9438267
I47: Interest and penalties - delinquent taxes | M47: 2524919 | O47: =SUM(M47:N47) -> 2524919
H48: Miscellaneous | M48: 11040 | N48: 75000 | O48: =SUM(M48:N48) -> 86040 | P48: 274166
H49: Grants and contributions not restricted to specific programs | M49: 7675158 | O49: =SUM(M49:N49) -> 7675158 | P49: 5915612
H50: Investment earnings | M50: 659477 | N50: 1348565 | O50: =SUM(M50:N50) -> 2008042 | P50: 200832
H51: Gain on sale of capital assets | M51: 595694 | N51: -910915 | O51: =SUM(M51:N51) -> -315221 | P51: 12103
H52: Transfers (to) from other funds | M52: 1330318 | N52: -1330318 | O52: =SUM(M52:N52) -> 0
H54: Total General Revenues | M54: =SUM(M40:M52) -> 375646950 | N54: =SUM(N40:N52) -> 42179264 | O54: =SUM(O40:O52) -> 417826214 | P54: =SUM(P40:P51) -> 23100658
H56: Change in Net Assets | M56: =M54+M29 -> -24354054 | N56: =N54+N29 -> -16712704 | O56: =O54+O29 -> -41066758 | P56: =P54+P36 -> 330494
E58: Net Assets- Beginning of Year | M58: 638987350 | N58: 942239793 | O58: =SUM(M58:N58) -> 1581227143 | P58: 47373642
E60: Net Assets- End of Year | M60: =SUM(M56,M58) -> 614633296 | N60: =N58+N56 -> 925527089 | O60: =O58+O56 -> 1540160385 | P60: =P58+P56 -> 47704136

Sheet East Carroll
J1: East Carroll County 2013 Statement of Activities
J2: Issued: December 31, 2013
M4: NET (EXPENSE) REVENUE AND CHANGES IN NET ASSETS
J5: PROGRAM REVENUES | M5: PRIMARY GOVERNMENT
A6: FUNCTIONS/PROGRAMS | I6: Expenses | J6: Charges for Services | K6: Operating Grants and Contributions | L6: Capital Grants and Contributions | M6: Governmental Activities | N6: Business-type Activities | O6: Total
A7: Primary Government:
B8: Government Activities:
C9: General government:
D10: Legislative | I10: -76402 | M10: =SUM(I10:L10) -> -76402 | O10: =SUM(M10:N10) -> -76402
D11: Judicial | I11: -568012 | J11: 434404 | M11: =SUM(I11:L11) -> -133608 | O11: =SUM(M11:N11) -> -133608
D12: Elections | I12: -39899 | M12: =SUM(I12:L12) -> -39899 | O12: =SUM(M12:N12) -> -39899
D13: Finance and administrative | I13: -208877 | M13: =SUM(I13:L13) -> -208877 | O13: =SUM(M13:N13) -> -208877
D14: Other general government | I14: -578588 | M14: =SUM(I14:L14) -> -578588 | O14: =SUM(M14:N14) -> -578588
C15: Public safety | I15: -278827 | K15: 105136 | L15: 136513 | M15: =SUM(I15:L15) -> -37178 | O15: =SUM(M15:N15) -> -37178
C16: Public works | I16: -1324952 | J16: 106646 | K16: 362463 | L16: 25500 | M16: =SUM(I16:L16) -> -830343 | O16: =SUM(M16:N16) -> -830343
C17: Health and welfare | I17: -111144 | M17: =SUM(I17:L17) -> -111144 | O17: =SUM(M17:N17) -> -111144
C18: Culture and recreation | I18: -333558 | J18: 20571 | L18: 138391 | M18: =SUM(I18:L18) -> -174596 | O18: =SUM(M18:N18) -> -174596
C19: Economic development and assistance | I19: -5949 | M19: =SUM(I19:L19) -> -5949 | O19: =SUM(M19:N19) -> -5949
C20: Transportation | I20: -27398 | M20: =SUM(I20:L20) -> -27398 | O20: =SUM(M20:N20) -> -27398
C21: Interest on long-term debt | I21: -20928 | M21: =SUM(I21:L21) -> -20928 | O21: =SUM(M21:N21) -> -20928
E23: Total Government Activities | I23: =SUM(I10:I21) -> -3574534 | J23: =SUM(J10:J21) -> 561621 | K23: =SUM(K10:K21) -> 467599 | L23: =SUM(L10:L21) -> 300404 | M23: =SUM(M10:M21) -> -2244910 | O23: =SUM(O10:O21) -> -2244910
B25: Business-type Activities:
C26: Health and welfare | I26: -634697 | J26: 212 | K26: 581985 | L26: 0 | N26: =SUM(I26:L26) -> -52500 | O26: =SUM(M26:N26) -> -52500
E28: Total business-type Activities | I28: =SUM(I26:I26) -> -634697 | J28: =SUM(J26:J26) -> 212 | K28: =SUM(K26:K26) -> 581985 | L28: =SUM(L26:L26) -> 0 | M28: =SUM(M26:M26) -> 0 | N28: =SUM(N26:N26) -> -52500 | O28: =SUM(O26:O26) -> -52500
E30: Total government | I30: =I28+I23 -> -4209231 | J30: =J28+J23 -> 561833 | K30: =K28+K23 -> 1049584 | L30: =L28+L23 -> 300404 | M30: =M28+M23 -> -2244910 | N30: =N28+N23 -> -52500 | O30: =O28+O23 -> -2297410
G32: General Revenues:
H33: Taxes:
I34: Property taxes, levied for general purposes | M34: 2038944 | O34: =SUM(M34:N34) -> 2038944
I35: Property taxes, levied for debt services | M35: 74110 | O35: =SUM(M35:N35) -> 74110
I36: Sales taxes, levied for general purposes | M36: 758507 | O36: =SUM(M36:N36) -> 758507
H37: State revenue sharing | M37: 48848 | O37: =SUM(M37:N37) -> 48848
H38: Other taxes | M38: 41050 | O38: =SUM(M38:N38) -> 41050
H39: Grants and contributions not restricted to specific programs | M39: 61417 | O39: =SUM(M39:N39) -> 61417
H40: Licenses and permits | M40: 100927 | O40: =SUM(M40:N40) -> 100927
H41: Interest and investment earnings | M41: 4698 | O41: =SUM(M41:N41) -> 4698
H42: Miscellaneous | M42: 34260 | O42: =SUM(M42:N42) -> 34260
H44: Total General Revenues | M44: =SUM(M34:M42) -> 3162761 | N44: =SUM(N34:N42) -> 0 | O44: =SUM(O34:O42) -> 3162761
H46: Change in Net Assets | M46: =M44+M30 -> 917851 | N46: =N44+N30 -> -52500 | O46: =O44+O30 -> 865351
E48: Net Assets- Beginning of Year | M48: 9704474 | N48: 79839 | O48: =SUM(M48:N48) -> 9784313
E50: Net Assets- End of Year | M50: =SUM(M46,M48) -> 10622325 | N50: =N48+N46 -> 27339 | O50: =O48+O46 -> 10649664

Sheet East Feliciana
J1: East Feliciana County 2013 Statement of Activities
J2: Issued: December 31, 2013
J5: PROGRAM REVENUES
A6: FUNCTIONS/PROGRAMS | I6: Expenses | J6: Charges for Services | K6: Operating Grants and Contributions | L6: Capital Grants and Contributions | M6: NET (EXPENSE) REVENUE AND CHANGES IN NET ASSETS
A7: Primary Government:
B8: Government Activities:
C9: General government | I9: -710683.58 | J9: 191962.61 | K9: 20000 | M9: =SUM(I9:L9) -> -498720.97
C10: Culture and recreation | I10: -4219.33 | M10: =SUM(I10:L10) -> -4219.33
C11: Economic development | I11: -9208.32 | K11: 7250 | M11: =SUM(I11:L11) -> -1958.32
C12: Health and welfare | I12: -462121.51 | K12: 5610.08 | M12: =SUM(I12:L12) -> -456511.43
C13: Public safety | I13: -893111.69 | J13: 324360.27 | K13: 234703.28 | L13: 434068.7 | M13: =SUM(I13:L13) -> 100020.56
C14: Public works | I14: -3295452 | K14: 161713.9 | L14: 192415.13 | M14: =SUM(I14:L14) -> -2941322.9
E16: Total Government Activities | I16: =SUM(I9:I14) -> -5374796.4 | J16: =SUM(J9:J14) -> 516322.88 | K16: =SUM(K9:K14) -> 429277.26 | L16: =SUM(L9:L14) -> 626483.83 | M16: =SUM(M9:M14) -> -3802712.4
G18: General Revenues:
H19: Intergovernmental revenues | M19: 356476.28
H20: Taxes:
I21: Ad valorem | M21: 694605.02
I22: Severance | M22: 613694.88
I23: Sales | M23: 3192203.6
H24: Franchise fees | M24: 11441.73
H25: Insurance rebates | M25: 87634.83
H26: Licenses and permits | M26: 181394.25
H27: Fines and forfeitures | M27: 124880.51
H28: Interest earned | M28: 1604.01
H29: Other revenues | M29: 64680.75
H31: Total General Revenues | M31: =SUM(M19:M29) -> 5328615.9
H33: Change in Net Assets | M33: =SUM(M16,M31) -> 1525903.5
E35: Net Assets- Beginning of Year | M35: 13128810
E37: Net Assets- End of Year | M37: =SUM(M33,M35) -> 14654714

Sheet Evangeline
J1: Evangeline County 2013 Statement of Activities
J2: Issued: December 31, 2013
M4: NET (EXPENSE) REVENUE AND CHANGE IN NET ASSETS
J5: PROGRAM REVENUES | M5: PRIMARY GOVERNMENT | P5: COMPONENT UNITS
A6: FUNCTIONS/PROGRAMS | I6: Expenses | J6: Charges for Services | K6: Operating Grants and Contributions | L6: Capital Grants and Contributions | M6: Governmental Activities | N6: Business-type Activities | O6: Total | P6: Criminal Court Fund
A7: Primary Government:
B8: Government Activities:
C9: General government | I9: -2191744 | J9: 421870 | M9: =SUM(I9:L9) -> -1769874 | O9: =SUM(M9:N9) -> -1769874
C10: Public safety | I10: -797397 | K10: 79627 | M10: =SUM(I10:L10) -> -717770 | O10: =SUM(M10:N10) -> -717770
C11: Public works | I11: -3478839 | J11: 61665 | K11: 588312 | L11: 1699161 | M11: =SUM(I11:L11) -> -1129701 | O11: =SUM(M11:N11) -> -1129701
C12: Health and welfare | I12: -558793 | M12: =SUM(I12:L12) -> -558793 | O12: =SUM(M12:N12) -> -558793
C13: Culture and recreation | I13: -1104898 | J13: 238759 | K13: 26031 | M13: =SUM(I13:L13) -> -840108 | O13: =SUM(M13:N13) -> -840108
C14: Economic development | I14: -228270 | M14: =SUM(I14:L14) -> -228270 | O14: =SUM(M14:N14) -> -228270
C15: Interest on long-term debt | I15: -722085 | M15: =SUM(I15:L15) -> -722085 | O15: =SUM(M15:N15) -> -722085
E17: Total Government Activities | I17: =SUM(I9:I15) -> -9082026 | J17: =SUM(J9:J15) -> 722294 | K17: =SUM(K9:K15) -> 693970 | L17: =SUM(L9:L15) -> 1699161 | M17: =SUM(M9:M15) -> -5966601 | O17: =SUM(O9:O15) -> -5966601 | P17: =SUM(P9:P15) -> 0
B19: Business-type Activities:
C20: Ward One sewer system | I20: -69311 | J20: 38808 | N20: =SUM(I20:L20) -> -30503 | O20: =N20 -> -30503
C21: Section 8 housing program | I21: -521141 | K21: 495212 | N21: =SUM(I21:L21) -> -25929 | O21: =N21 -> -25929
E23: Total business-type Activities | I23: =SUM(I20:I21) -> -590452 | J23: =SUM(J20:J21) -> 38808 | K23: =SUM(K20:K21) -> 495212 | L23: =SUM(L20:L21) -> 0 | M23: =SUM(M20:M21) -> 0 | N23: =SUM(N20:N21) -> -56432 | O23: =SUM(O20:O21) -> -56432
E25: Total primary government | I25: =I23+I17 -> -9672478 | J25: =J23+J17 -> 761102 | K25: =K23+K17 -> 1189182 | L25: =L23+L17 -> 1699161 | M25: =M23+M17 -> -5966601 | N25: =N23+N17 -> -56432 | O25: =O23+O17 -> -6023033
A27: Component units:
B28: Criminal Court fund | I28: -499541 | J28: 382826 | K28: 115627 | P28: =SUM(I28:K28) -> -1088
E30: Total component units | I30: =SUM(I28:I28) -> -499541 | J30: =SUM(J28:J28) -> 382826 | K30: =SUM(K28:K28) -> 115627 | L30: =SUM(L28:L28) -> 0 | M30: =SUM(M28:M28) -> 0 | N30: =SUM(N28:N28) -> 0 | O30: =SUM(O28:O28) -> 0 | P30: =SUM(P28:P28) -> -1088
G32: General Revenues:
H33: Taxes:
I34: Property taxes, levied for general purposes | M34: 4911887 | O34: =SUM(M34:N34) -> 4911887
I35: Sales and use taxes, levied for general purposes | M35: 3115373 | O35: =SUM(M35:N35) -> 3115373
H36: Grants and contributions not restricted to specific programs:
I37: Beer taxes | M37: 5312 | O37: =SUM(M37:N37) -> 5312
I38: State revenue sharing | M38: 236314 | O38: =SUM(M38:N38) -> 236314
I39: Parish equalization | M39: 1167550 | O39: =SUM(M39:N39) -> 1167550
I40: Other state grants | M40: 318858 | O40: =SUM(M40:N40) -> 318858
H41: Interest and investment earnings | M41: 80003 | N41: 225 | O41: =SUM(M41:N41) -> 80228 | P41: 251
H42: Miscellaneous | M42: 547529 | O42: =SUM(M42:N42) -> 547529
H43: Transfers | M43: -6720 | N43: 6720 | O43: =SUM(M43:N43) -> 0
H45: Total General Revenues | M45: =SUM(M34:M43) -> 10376106 | N45: =SUM(N34:N43) -> 6945 | O45: =SUM(O34:O43) -> 10383051 | P45: =SUM(P34:P42) -> 251
H47: Change in Net Assets | M47: =M45+M25 -> 4409505 | N47: =N45+N25 -> -49487 | O47: =O45+O25 -> 4360018 | P47: =P45+P30 -> -837
E49: Net Assets- Beginning of Year | M49: 31466364 | N49: 400291 | O49: =SUM(M49:N49) -> 31866655 | P49: -21249
E51: Net Assets- End of Year | M51: =SUM(M47,M49) -> 35875869 | N51: =N49+N47 -> 350804 | O51: =O49+O47 -> 36226673 | P51: =P49+P47 -> -22086

Sheet Franklin
J1: Franklin County 2013 Statement of Activities
J2: Issued: December 31, 2013
J5: PROGRAM REVENUES
A6: FUNCTIONS/PROGRAMS | I6: Expenses | J6: Charges for Services | K6: Operating Grants and Contributions | L6: Capital Grants and Contributions | M6: NET (EXPENSE) REVENUE AND CHANGES IN NET ASSETS
A7: Primary Government:
B8: Government Activities:
C9: General government | I9: -1292911 | J9: 138177 | M9: =SUM(I9:L9) -> -1154734
C10: Public safety | I10: -552502 | K10: 136598 | L10: 24761 | M10: =SUM(I10:L10) -> -391143
C11: Public works | I11: -6730873 | J11: 6737 | K11: 918999 | L11: 1205103 | M11: =SUM(I11:L11) -> -4600034
C12: Health and welfare | I12: -381552 | J12: 1373 | K12: 60618 | M12: =SUM(I12:L12) -> -319561
C13: Culture and recreation | I13: -101831 | J13: 52926 | M13: =SUM(I13:L13) -> -48905
C14: Economic development and assistance | I14: -5241122 | K14: 5171732 | L14: 203156 | M14: =SUM(I14:L14) -> 133766
E16: Total Government Activities | I16: =SUM(I9:I14) -> -14300791 | J16: =SUM(J9:J14) -> 199213 | K16: =SUM(K9:K14) -> 6287947 | L16: =SUM(L9:L14) -> 1433020 | M16: =SUM(M9:M14) -> -6380611
G18: General Revenues:
H19: Taxes:
I20: Ad valorem | M20: 3579191
I21: Sales taxes | M21: 3931218
I22: State revenue sharing | M22: 174969
I23: Fire insurance rebate | M23: 85771
I24: Other taxes, penalties, and interest | M24: 14253
H25: Grants and contributions not restricted to specific programs | M25: 76406
H26: Licenses and permits | M26: 156765
H27: Unrestricted investment earnings | M27: 71714
H28: Gain (loss) on disposal of assets | M28: -55214
H30: Total General Revenues | M30: =SUM(M20:M28) -> 8035073
H32: Change in Net Assets | M32: =SUM(M16,M30) -> 1654462
E34: Net Assets- Beginning of Year | M34: 25127738
E36: Net Assets- End of Year | M36: =SUM(M32,M34) -> 26782200

Sheet Grant
J1: Grant County 2013 Statement of Activities
J2: Issued: December 31, 2013
M4: NET (EXPENSE) REVENUE AND CHANGES IN NET ASSETS
J5: PROGRAM REVENUES | M5: PRIMARY GOVERNMENT
A6: FUNCTIONS/PROGRAMS | I6: Expenses | J6: Charges for Services | K6: Operating Grants and Contributions | L6: Capital Grants and Contributions | M6: Governmental Activities | N6: Business-type Activities | O6: Total
A7: Primary Government:
B8: Government Activities:
C9: General government:
D10: Legislative | I10: -211784 | M10: =SUM(I10:L10) -> -211784 | O10: =SUM(M10:N10) -> -211784
D11: Judicial | I11: -572080 | J11: 218491 | K11: 162643 | M11: =SUM(I11:L11) -> -190946 | O11: =SUM(M11:N11) -> -190946
D12: Finance and administrative | I12: -276975 | M12: =SUM(I12:L12) -> -276975 | O12: =SUM(M12:N12) -> -276975
D13: Other general government | I13: -248931 | L13: 37900 | M13: =SUM(I13:L13) -> -211031 | O13: =SUM(M13:N13) -> -211031
C14: Public safety | I14: -310029 | K14: 55090 | M14: =SUM(I14:L14) -> -254939 | O14: =SUM(M14:N14) -> -254939
C15: Public works
D16: Road maintenance | I16: -1467342 | K16: 963938 | L16: 242316 | M16: =SUM(I16:L16) -> -261088 | O16: =SUM(M16:N16) -> -261088
D17: Landfill maintenance | I17: -986000 | J17: 59575 | M17: =SUM(I17:L17) -> -926425 | O17: =SUM(M17:N17) -> -926425
D18: CDBG Herman Park Sewer System | I18: -103340 | L18: 103340 | M18: =SUM(I18:L18) -> 0 | O18: =SUM(M18:N18) -> 0
D19: Other public works | I19: -123897 | K19: 46900 | L19: 63871 | M19: =SUM(I19:L19) -> -13126 | O19: =SUM(M19:N19) -> -13126
C20: Economic development | I20: -81442 | K20: 66000 | M20: =SUM(I20:L20) -> -15442 | O20: =SUM(M20:N20) -> -15442
C21: Health and welfare | I21: -69187 | M21: =SUM(I21:L21) -> -69187 | O21: =SUM(M21:N21) -> -69187
C22: Culture and recreation | I22: -15659 | J22: 16883 | M22: =SUM(I22:L22) -> 1224 | O22: =SUM(M22:N22) -> 1224
E24: Total Government Activities | I24: =SUM(I10:I22) -> -4466666 | J24: =SUM(J10:J22) -> 294949 | K24: =SUM(K10:K22) -> 1294571 | L24: =SUM(L10:L22) -> 447427 | M24: =SUM(M10:M22) -> -2429719 | O24: =SUM(O10:O22) -> -2429719
B26: Business-type Activities:
C27: Utility system | I27: -515141 | J27: 554973 | N27: =SUM(I27:L27) -> 39832 | O27: =SUM(M27:N27) -> 39832
E29: Total business-type Activities | I29: =SUM(I27:I27) -> -515141 | J29: =SUM(J27:J27) -> 554973 | K29: =SUM(K27:K27) -> 0 | L29: =SUM(L27:L27) -> 0 | M29: =SUM(M27:M27) -> 0 | N29: =SUM(N27:N27) -> 39832 | O29: =SUM(O27:O27) -> 39832
E31: Total government | I31: =I29+I24 -> -4981807 | J31: =J29+J24 -> 849922 | K31: =K29+K24 -> 1294571 | L31: =L29+L24 -> 447427 | M31: =M29+M24 -> -2429719 | N31: =N29+N24 -> 39832 | O31: =O29+O24 -> -2389887
G33: General Revenues:
H34: Taxes:
I35: Ad valorem | M35: 821547 | O35: =SUM(M35:N35) -> 821547
I36: Sales | M36: 1048580 | O36: =SUM(M36:N36) -> 1048580
I37: Severance | M37: 624428 | O37: =SUM(M37:N37) -> 624428
I38: Other | M38: 156451 | O38: =SUM(M38:N38) -> 156451
H39: Revenue sharing | M39: 80082 | O39: =SUM(M39:N39) -> 80082
H40: Gain on sale of capital assets | M40: 32998 | O40: =SUM(M40:N40) -> 32998
H41: Other | M41: 186442 | N41: 3609 | O41: =SUM(M41:N41) -> 190051
H42: Transfers | M42: 71146 | N42: -71146 | O42: =SUM(M42:N42) -> 0
H44: Total General Revenues | M44: =SUM(M35:M42) -> 3021674 | N44: =SUM(N35:N42) -> -67537 | O44: =SUM(O35:O42) -> 2954137
H46: Change in Net Assets | M46: =M44+M31 -> 591955 | N46: =N44+N31 -> -27705 | O46: =SUM(M46:N46) -> 564250
E48: Net Assets- Beginning of Year | M48: 7803044 | N48: 735755 | O48: =SUM(M48:N48) -> 8538799
E50: Net Assets- End of Year | M50: =SUM(M46,M48) -> 8394999 | N50: =N48+N46 -> 708050 | O50: =O48+O46 -> 9103049

Sheet Iberia
J1: Iberia County 2013 Statement of Activities
J2: Issued: December 31, 2013
M4: NET (EXPENSE) REVENUE AND CHANGE IN NET ASSETS
J5: PROGRAM REVENUES | M5: PRIMARY GOVERNMENT
A6: FUNCTIONS/PROGRAMS | I6: Expenses | J6: Charges for Services | K6: Operating Grants and Contributions | L6: Capital Grants and Contributions | M6: Governmental Activities | N6: Component Units
A7: Primary Government:
B8: Government Activities:
C9: General government | I9: -5083575 | J9: 977521 | K9: 76661 | M9: =SUM(I9:L9) -> -4029393
C10: Public safety | I10: -3557164 | J10: 604424 | K10: 135852 | L10: 119066 | M10: =SUM(I10:L10) -> -2697822
C11: Public works | I11: -9902167 | J11: 5930 | K11: 2082642 | L11: 5462020 | M11: =SUM(I11:L11) -> -2351575
C12: Health and human services | I12: -7626497 | J12: 136587 | K12: 7559439 | M12: =SUM(I12:L12) -> 69529
C13: Culture and recreation | I13: -2213777 | M13: =SUM(I13:L13) -> -2213777
C14: Urban redevelopment and housing | I14: -850522 | K14: 747612 | M14: =SUM(I14:L14) -> -102910
C15: Economic development and assistance | I15: -547525 | K15: 134695 | M15: =SUM(I15:L15) -> -412830
C16: Unallocated depreciation | I16: -3301072 | M16: =SUM(I16:L16) -> -3301072
C17: Interest on long-term debt | I17: -442496 | M17: =SUM(I17:L17) -> -442496
E19: Total Government Activities | I19: =SUM(I9:I17) -> -33524795 | J19: =SUM(J9:J17) -> 1724462 | K19: =SUM(K9:K17) -> 10736901 | L19: =SUM(L9:L17) -> 5581086 | M19: =SUM(M9:M17) -> -15482346 | N19: =SUM(N9:N17) -> 0
B21: Component units | I21: -81769923 | J21: 65130111 | K21: 5095023 | L21: 1365892 | N21: =SUM(I21:L21) -> -10178897
I23: =SUM(I21:I21) -> -81769923 | J23: =SUM(J21:J21) -> 65130111 | K23: =SUM(K21:K21) -> 5095023 | L23: =SUM(L21:L21) -> 1365892 | M23: =SUM(M21:M21) -> 0 | N23: =SUM(N21:N21) -> -10178897
G25: General Revenues:
H26: Taxes:
I27: Property taxes | M27: 9712666 | N27: 2627573
I28: Sales and use taxes | M28: 6674549 | N28: 4219548
I29: Hotel/motel taxes | M29: 254462 | N29: 254081
I30: Severance taxes | M30: 971421
I31: Fire insurance rebate | N31: 140901
I32: Occupational licenses | M32: 913117
H33: Grants and contributions not restricted to specific programs:
I34: State revenue sharing | M34: 445398 | N34: 434267
H35: Interest and investment earnings | M35: 330619 | N35: 273269
H36: Miscellaneous | M36: 418618 | N36: 1573993
H38: Total General Revenues | M38: =SUM(M27:M36) -> 19720850 | N38: =SUM(N27:N36) -> 9523632
H40: Change in Net Assets | M40: =M38+M19 -> 4238504 | N40: =N38+N23 -> -655265
E42: Net Assets- Beginning of Year, as restated | M42: 129193605 | N42: 82354376
E44: Net Assets- End of Year | M44: =SUM(M40,M42) -> 133432109 | N44: =N42+N40 -> 81699111

Sheet Iberville
J1: Iberville County 2013 Statement of Activities
J2: Issued: December 31, 2013
M4: NET (EXPENSE) REVENUE AND CHANGE IN NET ASSETS
J5: PROGRAM REVENUES | M5: PRIMARY GOVERNMENT | P5: COMPONENT UNITS
A6: FUNCTIONS/PROGRAMS | I6: Expenses | J6: Charges for Services | K6: Operating Grants and Contributions | L6: Capital Grants and Contributions | M6: Governmental Activities | N6: Business-type Activities | O6: Total | P6: Governmental Activities | Q6: Business-type Activities
A7: Primary Government:
B8: Government Activities:
C9: General government | I9: -10347217 | J9: 708429 | K9: 195502 | L9: 14157 | M9: =SUM(I9:L9) -> -9429129 | O9: =SUM(M9:N9) -> -9429129
C10: Public safety | I10: -4179132 | J10: 518905 | K10: 307028 | M10: =SUM(I10:L10) -> -3353199 | O10: =SUM(M10:N10) -> -3353199
C11: Public works | I11: -11273247 | J11: 5884 | K11: 923631 | L11: 7485895 | M11: =SUM(I11:L11) -> -2857837 | O11: =SUM(M11:N11) -> -2857837
C12: Public health | I12: -2670552 | J12: 99768 | K12: 654070 | M12: =SUM(I12:L12) -> -1916714 | O12: =SUM(M12:N12) -> -1916714
C13: Economic development | I13: -242675 | M13: =SUM(I13:L13) -> -242675 | O13: =SUM(M13:N13) -> -242675
C14: Culture and recreation | I14: -794222 | J14: 9774 | K14: 118052 | M14: =SUM(I14:L14) -> -666396 | O14: =SUM(M14:N14) -> -666396
C15: Interest on long-term debt | I15: -733654 | M15: =SUM(I15:L15) -> -733654 | O15: =SUM(M15:N15) -> -733654
E17: Total Government Activities | I17: =SUM(I9:I15) -> -30240699 | J17: =SUM(J9:J15) -> 1342760 | K17: =SUM(K9:K15) -> 2198283 | L17: =SUM(L9:L15) -> 7500052 | M17: =SUM(M9:M15) -> -19199604 | O17: =SUM(O9:O15) -> -19199604 | P17: =SUM(P9:P15) -> 0 | Q17: =SUM(Q9:Q15) -> 0
B19: Business-type Activities:
C20: Water, natural gas and sewer | I20: -4567386 | J20: 4737041 | N20: =SUM(I20:L20) -> 169655 | O20: =N20 -> 169655
E22: Total business-type Activities | I22: =SUM(I20:I20) -> -4567386 | J22: =SUM(J20:J20) -> 4737041 | K22: =SUM(K20:K20) -> 0 | L22: =SUM(L20:L20) -> 0 | M22: =SUM(M20:M20) -> 0 | N22: =SUM(N20:N20) -> 169655 | O22: =SUM(O20:O20) -> 169655
E24: Total primary government | I24: =I22+I17 -> -34808085 | J24: =J22+J17 -> 6079801 | K24: =K22+K17 -> 2198283 | L24: =L17+L22 -> 7500052 | M24: =M17 -> -19199604 | N24: =N22 -> 169655 | O24: =O22+O17 -> -19029949
A26: Component units:
B27: Governmental activities | I27: -3169581 | J27: 136759 | K27: 69336 | P27: =SUM(I27:L27) -> -2963486
B28: Business-type activities | I28: -1468049 | J28: 1375295 | K28: 45426 | Q28: =SUM(I28:L28) -> -47328
E30: Total component units | I30: =SUM(I27:I28) -> -4637630 | J30: =SUM(J27:J28) -> 1512054 | K30: =SUM(K27:K28) -> 114762 | L30: =SUM(L27:L28) -> 0 | M30: =SUM(M27:M28) -> 0 | N30: =SUM(N27:N28) -> 0 | O30: =SUM(O27:O28) -> 0 | P30: =SUM(P27:P28) -> -2963486 | Q30: =SUM(Q27:Q28) -> -47328
G32: General Revenues:
H33: Property taxes | M33: 5293941 | O33: =SUM(M33:N33) -> 5293941 | P33: 3383581
H34: Sales taxes | M34: 19895959 | O34: =SUM(M34:N34) -> 19895959
H35: Franchise taxes | M35: 106462 | O35: =SUM(M35:N35) -> 106462
H36: Alcoholic beverage taxes | M36: 15231 | O36: =SUM(M36:N36) -> 15231
H37: Gaming taxes | M37: 134802 | O37: =SUM(M37:N37) -> 134802
H38: Unrestricted grants and contributions | M38: 1079885 | O38: =SUM(M38:N38) -> 1079885
H39: Unrestricted investment earnings | M39: 24141 | N39: 2169 | O39: =SUM(M39:N39) -> 26310 | P39: 2670 | Q39: 1416
H40: Miscellaneous revenues | M40: 4706654 | N40: 175225 | O40: =SUM(M40:N40) -> 4881879 | P40: 20210 | Q40: 356904
H41: Gain on sale of capital assets
H42: Transfers (from) to governmental activities
H44: Total General Revenues and transfers | M44: =SUM(M33:M42) -> 31257075 | N44: =SUM(N33:N42) -> 177394 | O44: =SUM(O33:O42) -> 31434469 | P44: =SUM(P33:P41) -> 3406461 | Q44: =SUM(Q34:Q42) -> 358320
H46: Change in Net Assets | M46: =M44+M24 -> 12057471 | N46: =N44+N24 -> 347049 | O46: =O44+O24 -> 12404520 | P46: =P44+P30 -> 442975 | Q46: =Q44+Q30 -> 310992
E48: Net Assets- Beginning of Year | M48: 92910140 | N48: 12983802 | O48: =SUM(M48:N48) -> 105893942 | P48: 5812594 | Q48: 4478668
E50: Net Assets- End of Year | M50: =SUM(M46,M48) -> 104967611 | N50: =SUM(N46,N48) -> 13330851 | O50: =SUM(O46,O48) -> 118298462 | P50: =SUM(P46,P48) -> 6255569 | Q50: =SUM(Q46,Q48) -> 4789660

Sheet Jackson
J1: Jackson County 2013 Statement of Activities
J2: Issued: December 31, 2013
M4: NET (EXPENSE) REVENUE AND CHANGES IN NET ASSETS
J5: PROGRAM REVENUES | M5: PRIMARY GOVERNMENT
A6: FUNCTIONS/PROGRAMS | I6: Expenses | J6: Charges for Services | K6: Operating Grants and Contributions | L6: Capital Grants and Contributions | M6: Governmental Activities
A7: Primary Government:
B8: Government Activities:
C9: General government:
D10: Legislative | I10: -130792 | M10: =SUM(I10:L10) -> -130792
D11: Judicial | I11: -292978 | J11: 23811 | M11: =SUM(I11:L11) -> -269167
D12: Elections | I12: -24730 | M12: =SUM(I12:L12) -> -24730
D13: Finance and administrative | I13: -280311 | M13: =SUM(I13:L13) -> -280311
D14: Other general government | I14: -535105 | J14: 15295 | K14: 77861 | M14: =SUM(I14:L14) -> -441949
C15: Public safety | I15: -789090 | K15: 66058 | M15: =SUM(I15:L15) -> -723032
C16: Public works | I16: -5242558 | J16: 144347 | K16: 311332 | L16: 396699 | M16: =SUM(I16:L16) -> -4390180
C17: Health and welfare | I17: -243700 | M17: =SUM(I17:L17) -> -243700
C18: Culture and recreation | I18: -1179043 | J18: 27163 | M18: =SUM(I18:L18) -> -1151880
E20: Total Government Activities | I20: =SUM(I10:I18) -> -8718307 | J20: =SUM(J10:J18) -> 210616 | K20: =SUM(K10:K18) -> 455251 | L20: =SUM(L10:L18) -> 396699 | M20: =SUM(M10:M18) -> -7655741
G22: General Revenues:
H23: Taxes:
I24: Property taxes, levied for general purposes | M24: 4478159
I25: Sales taxes, levied for general purposes | M25: 2059337
I26: State revenue sharing | M26: 83486
I27: Severance tax | M27: 847116
I28: Miscellaneous taxes | M28: 152965
H29: Licenses and permits | M29: 39004
H30: Interest and investment earnings | M30: 92810
H31: Miscellaneous | M31: 136598
H33: Total General Revenues | M33: =SUM(M24:M31) -> 7889475
H35: Change in Net Assets | M35: =M33+M20 -> 233734
E37: Net Assets- Beginning of Year | M37: 29658228
E39: Net Assets- End of Year | M39: =SUM(M35,M37) -> 29891962

Sheet Jefferson
J1: Jefferson County 2012 Statement of Activities
J2: Issued: December 31, 2012
K3: (amounts in thousands)
M5: NET (EXPENSE) REVENUE AND CHANGE IN NET ASSETS
J6: PROGRAM REVENUES | M6: PRIMARY GOVERNMENT
A7: FUNCTIONS/PROGRAMS | I7: Expenses | J7: Charges for Services | K7: Operating Grants and Contributions | L7: Capital Grants and Contributions | M7: Governmental Activities | N7: Business-type Activities | O7: Total | P7: Component Units
A8: Primary Government:
B9: Government Activities:
C10: General government | I10: -70963000 | J10: 13529000 | K10: 1234000 | M10: =SUM(I10:L10) -> -56200000 | O10: =SUM(M10:N10) -> -56200000
C11: Public safety | I11: -97982000 | J11: 15744000 | K11: 7348000 | M11: =SUM(I11:L11) -> -74890000 | O11: =SUM(M11:N11) -> -74890000
C12: Public works | I12: -140983000 | J12: 20415000 | K12: 4977000 | L12: 34515000 | M12: =SUM(I12:L12) -> -81076000 | O12: =SUM(M12:N12) -> -81076000
C13: Transit | I13: -17938000 | J13: 3666000 | K13: 426000 | L13: 4234000 | M13: =SUM(I13:L13) -> -9612000 | O13: =SUM(M13:N13) -> -9612000
C14: Health and welfare | I14: -53854000 | J14: 4218000 | K14: 39556000 | L14: 2714000 | M14: =SUM(I14:L14) -> -7366000 | O14: =SUM(M14:N14) -> -7366000
C15: Culture and recreation | I15: -47510000 | J15: 4657000 | K15: 2147000 | L15: 7817000 | M15: =SUM(I15:L15) -> -32889000 | O15: =SUM(M15:N15) -> -32889000
C16: Economic development | K16: 60000 | M16: =SUM(I16:L16) -> 60000 | O16: =SUM(M16:N16) -> 60000
C17: Urban redevelopment and housing | I17: -5580000 | K17: 2643000 | M17: =SUM(I17:L17) -> -2937000 | O17: =SUM(M17:N17) -> -2937000
C18: Interest on long-term debt | I18: -25759000 | M18: =SUM(I18:L18) -> -25759000 | O18: =SUM(M18:N18) -> -25759000
E20: Total Government Activities | I20: =SUM(I10:I18) -> -460569000 | J20: =SUM(J10:J18) -> 62229000 | K20: =SUM(K10:K18) -> 58391000 | L20: =SUM(L10:L18) -> 49280000 | M20: =SUM(M10:M18) -> -290669000 | O20: =SUM(O10:O18) -> -290669000 | P20: =SUM(P10:P18) -> 0
B22: Business-type Activities:
C23: Consolidated Waterworks District No. 1 | I23: -39186000 | J23: 32944000 | L23: 822000 | N23: =SUM(I23:L23) -> -5420000 | O23: =SUM(M23:N23) -> -5420000
C24: Consolidated Sewerage District No. 1 | I24: -50426000 | J24: 24078000 | L24: 5839000 | N24: =SUM(I24:L24) -> -20509000 | O24: =SUM(M24:N24) -> -20509000
E26: Total Business-type Activities | I26: =SUM(I23:I24) -> -89612000 | J26: =SUM(J23:J24) -> 57022000 | K26: =SUM(K23:K24) -> 0 | L26: =SUM(L23:L24) -> 6661000 | M26: =SUM(M23:M24) -> 0 | N26: =SUM(N23:N24) -> -25929000 | O26: =SUM(O23:O24) -> -25929000 | P26: =SUM(P16:P24) -> 0
E28: Total primary government | I28: =I26+I20 -> -550181000 | J28: =J26+J20 -> 119251000 | K28: =SUM(K20+K26) -> 58391000 | L28: =SUM(L20+L26) -> 55941000 | M28: =M26+M20 -> -290669000 | N28: =N26+N20 -> -25929000 | O28: =O26+O20 -> -316598000 | P28: =SUM(P19:P26) -> 0
A30: Component units:
B31: JEDCO | I31: -3123000 | J31: 295000 | K31: 2929000 | L31: 3990000 | P31: =SUM(I31:M31) -> 4091000
B32: Jefferson Facilities, Inc | I32: -548000 | J32: 394000 | P32: =SUM(I32:L32) -> -154000
B33: Jefferson Redevelopment, Inc | I33: -248000 | P33: =SUM(I33:L33) -> -248000
B34: Jefferson Parish Finance Authority | I34: -5006000 | P34: =SUM(I34:L34) -> -5006000
B35: Hospital District No. 1 | I35: -265312000 | J35: 240510000 | P35: =SUM(I35:L35) -> -24802000
B36: Hospital District No. 2 | I36: -385241000 | J36: 346248000 | P36: =SUM(I36:L36) -> -38993000
E38: Total component units | I38: =SUM(I31:I36) -> -659478000 | J38: =SUM(J31:J36) -> 587447000 | K38: =SUM(K31:K36) -> 2929000 | L38: =SUM(L31:L36) -> 3990000 | M38: =SUM(M31:M36) -> 0 | N38: =SUM(N31:N36) -> 0 | O38: =SUM(O31:O36) -> 0 | P38: =SUM(P31:P36) -> -65112000
G40: General Revenues:
H41: Taxes:
I42: Ad valorem | M42: 187717000 | N42: 19456000 | O42: =SUM(M42:N42) -> 207173000
I43: Alcoholic beverage | M43: 269000 | O43: =SUM(M43:N43) -> 269000
I44: Chain store | M44: 272000 | O44: =SUM(M44:N44) -> 272000
I45: Franchise fees | M45: 5141000 | O45: =SUM(M45:N45) -> 5141000
I46: Sales | M46: 146059000 | O46: =SUM(M46:N46) -> 146059000
I47: Hotel/Motel | M47: 3515000 | O47: =SUM(M47:N47) -> 3515000
I48: Auto rental | O48: =SUM(M48:N48) -> 0
I49: Severance | M49: 971000 | O49: =SUM(M49:N49) -> 971000
H50: Unrestricted investment earnings | M50: 3955000 | N50: 278000 | O50: =SUM(M50:N50) -> 4233000 | P50: 2749000
H51: Miscellaneous | M51: 27278000 | N51: 889000 | O51: =SUM(M51:N51) -> 28167000 | P51: 40126000
H52: Gain on extinguishement of debt | M52: 50241000 | N52: 4569000 | O52: =SUM(M52:N52) -> 54810000
H53: Transfers | M53: -6832000 | N53: 6832000 | O53: =SUM(M53:N53) -> 0
H55: Total General Revenues | M55: =SUM(M42:M53) -> 418586000 | N55: =SUM(N42:N53) -> 32024000 | O55: =SUM(O42:O53) -> 450610000 | P55: =SUM(P42:P51) -> 42875000
H57: Change in Net Assets | M57: =M55+M28 -> 127917000 | N57: =N55+N28 -> 6095000 | O57: =O55+O28 -> 134012000 | P57: =P55+P38 -> -22237000
E59: Net Assets- Beginning of Year | M59: 1146493000 | N59: 622113000 | O59: =SUM(M59:N59) -> 1768606000 | P59: 499636000
E61: Net Assets- End of Year | M61: =SUM(M57,M59) -> 1274410000 | N61: =N59+N57 -> 628208000 | O61: =O59+O57 -> 1902618000 | P61: =P59+P57 -> 477399000

Sheet Jefferson Davis
J1: Jefferson Davis County 2013 Statement of Activities
J2: Issued: December 31, 2013
J5: PROGRAM REVENUES
A6: FUNCTIONS/PROGRAMS | I6: Expenses | J6: Charges for Services | K6: Operating Grants and Contributions | L6: Capital Grants and Contributions | M6: NET (EXPENSE) REVENUE AND CHANGES IN NET ASSETS
A7: Primary Government:
B8: Government Activities:
C9: General government | I9: -4320395 | J9: 2395868 | K9: 18539 | M9: =SUM(I9:L9) -> -1905988
C10: Public safety | I10: -1736283 | J10: 415294 | K10: 224071 | L10: 24422 | M10: =SUM(I10:L10) -> -1072496
C11: Public works | I11: -3493885 | K11: 531103 | L11: 1297152 | M11: =SUM(I11:L11) -> -1665630
C12: Culture and recreation | I12: -72901 | J12: 23021 | M12: =SUM(I12:L12) -> -49880
C13: Health and welfare | I13: -1152258 | J13: 25116 | K13: 954107 | M13: =SUM(I13:L13) -> -173035
C14: Economic development | I14: -149084 | K14: 10000 | L14: 139074 | M14: =SUM(I14:L14) -> -10
C15: Interest on long-term debt | I15: -738405 | M15: =SUM(I15:L15) -> -738405
E17: Total Government Activities | I17: =SUM(I9:I15) -> -11663211 | J17: =SUM(J9:J14) -> 2859299 | K17: =SUM(K9:K14) -> 1737820 | L17: =SUM(L9:L14) -> 1460648 | M17: =SUM(M9:M15) -> -5605444
G19: General Revenues:
H20: Property taxes | M20: 4063707
H21: Sales tax | M21: 2598488
H22: Severance taxes | M22: 996726
H23: State revenue sharing | M23: 137277
H24: Occupational licenses and permits | M24: 318659
H25: Grants and contributions not restricted to specific programs | M25: 338271
H26: Investment earnings | M26: 22950
H27: Other general revenues | M27: 654163
H28: Special items:
I29: Gain on sale of capital assets | M29: 44263
H31: Total General Revenues | M31: =SUM(M20:M29) -> 9174504
H33: Change in Net Assets | M33: =SUM(M17,M31) -> 3569060
E35: Net Assets- Beginning of Year | M35: 32713787
E37: Net Assets- End of Year | M37: =SUM(M33,M35) -> 36282847

Sheet Lafayette
J1: Lafayette County 2013 Statement of Activities
J2: Issued: December 31, 2013
M4: NET (EXPENSE) REVENUE AND CHANGE IN NET ASSETS
J5: PROGRAM REVENUES | M5: PRIMARY GOVERNMENT
A6: FUNCTIONS/PROGRAMS | I6: Expenses | J6: Fees, Fines and Charges for Services | K6: Operating Grants and Contributions | L6: Capital Grants and Contributions | M6: Governmental Activities | N6: Business-type Activities | O6: Total | P6: Component Units
A7: Primary Government:
B8: Government Activities:
C9: General government | I9: -37184500 | J9: 9151990 | K9: 1059787 | M9: =SUM(I9:L9) -> -26972723 | O9: =SUM(M9:N9) -> -26972723
C10: Public safety | I10: -65643989 | J10: 2950921 | K10: 5015322 | L10: 711209 | M10: =SUM(I10:L10) -> -56966537 | O10: =SUM(M10:N10) -> -56966537
C11: Traffic and transportation | I11: -13480841 | J11: 3610538 | K11: 2503378 | L11: 3007073 | M11: =SUM(I11:L11) -> -4359852 | O11: =SUM(M11:N11) -> -4359852
C12: Streets and drainage | I12: -21493669 | K12: 1487408 | L12: 1489675 | M12: =SUM(I12:L12) -> -18516586 | O12: =SUM(M12:N12) -> -18516586
C13: Urban redevelopment and housing | I13: -5386889 | K13: 1518591 | L13: 215680 | M13: =SUM(I13:L13) -> -3652618 | O13: =SUM(M13:N13) -> -3652618
C14: Culture and recreation | I14: -24380013 | J14: 6357185 | L14: 479963 | M14: =SUM(I14:L14) -> -17542865 | O14: =SUM(M14:N14) -> -17542865
C15: Health and welfare | I15: -1055317 | M15: =SUM(I15:L15) -> -1055317 | O15: =SUM(M15:N15) -> -1055317
C16: Economic opportunity | I16: -317939 | K16: 275030 | M16: =SUM(I16:L16) -> -42909 | O16: =SUM(M16:N16) -> -42909
C17: Economic development and assistance | I17: -2011600 | K17: 1489808 | M17: =SUM(I17:L17) -> -521792 | O17: =SUM(M17:N17) -> -521792
C18: Unallocated depreciation | I18: -17004422 | M18: =SUM(I18:L18) -> -17004422 | O18: =SUM(M18:N18) -> -17004422
C19: Interest on long-term debt | I19: -19316705 | K19: 1260326 | M19: =SUM(I19:L19) -> -18056379 | O19: =SUM(M19:N19) -> -18056379
E21: Total Government Activities | I21: =SUM(I9:I19) -> -207275884 | J21: =SUM(J9:J19) -> 22070634 | K21: =SUM(K9:K19) -> 14609650 | L21: =SUM(L9:L19) -> 5903600 | M21: =SUM(M9:M19) -> -164692000 | O21: =SUM(O9:O19) -> -164692000 | P21: =SUM(P9:P19) -> 0
B23: Business-type Activities:
C24: Electric | I24: -159498894 | J24: 187153313 | L24: 2737769 | N24: =SUM(I24:L24) -> 30392188 | O24: =SUM(M24:N24) -> 30392188
C25: Water | I25: -16809413 | J25: 17499221 | N25: =SUM(I25:L25) -> 689808 | O25: =SUM(M25:N25) -> 689808
C26: Sewer | I26: -22224144 | J26: 28617206 | N26: =SUM(I26:L26) -> 6393062 | O26: =SUM(M26:N26) -> 6393062
C27: Communications system | I27: -37206383 | J27: 27424453 | N27: -9781930 | O27: =SUM(M27:N27) -> -9781930
C28: Coal-fired electric plant | I28: -59053699 | J28: 60403535 | N28: =SUM(I28:L28) -> 1349836 | O28: =SUM(M28:N28) -> 1349836
C29: Solid waste collection services | I29: -13410942 | J29: 13376335 | L29: 1946 | N29: =SUM(I29:L29) -> -32661 | O29: =SUM(M29:N29) -> -32661
C30: Animal shelter control program | I30: -1453449 | J30: 409783 | L30: 28123 | N30: =SUM(I30:L30) -> -1015543 | O30: =SUM(M30:N30) -> -1015543
C31: CNG Service Station | I31: -101442 | J31: 160355 | N31: =SUM(I31:L31) -> 58913 | O31: =SUM(M31:N31) -> 58913
E33: Total Business-type Activities | I33: =SUM(I24:I31) -> -309758366 | J33: =SUM(J24:J31) -> 335044201 | K33: =SUM(K24:K31) -> 0 | L33: =SUM(L24:L31) -> 2767838 | M33: =SUM(M24:M31) -> 0 | N33: =SUM(N24:N31) -> 28053673 | O33: =SUM(O24:O31) -> 28053673 | P33: =SUM(P17:P31) -> 0
E35: Total primary government | I35: =I33+I21 -> -517034250 | J35: =J33+J21 -> 357114835 | K35: =SUM(K21+K33) -> 14609650 | L35: =SUM(L21+L33) -> 8671438 | M35: =M33+M21 -> -164692000 | N35: =N33+N21 -> 28053673 | O35: =O33+O21 -> -136638327 | P35: =SUM(P20:P33) -> 0
D37: Component units | I37: -49821373 | J37: 31663351 | K37: 8424515 | L37: 10444708 | M37: 0 | N37: 0 | O37: 0 | P37: =SUM(I37:L37) -> 711201
G39: General Revenues:
H40: Taxes:
I41: Property | M41: 70555638 | O41: =SUM(M41:N41) -> 70555638 | P41: 4664041
I42: Sales | M42: 86055088 | O42: =SUM(M42:N42) -> 86055088
I43: Occupational licenses | M43: 2930195 | O43: =SUM(M43:N43) -> 2930195
I44: Insurance premium | M44: 895028 | O44: =SUM(M44:N44) -> 895028
I45: Franchise fees | M45: 2497994 | O45: =SUM(M45:N45) -> 2497994
I46: Interest and penalties - delinquent taxes | M46: 135168 | O46: =SUM(M46:N46) -> 135168
I47: Other | M47: 70407 | O47: =SUM(M47:N47) -> 70407 | P47: 2718203
H48: Grants and contributions not restricted to specific programs | M48: 2319804 | O48: =SUM(M48:N48) -> 2319804 | P48: 47123
H49: Investment earnings | M49: 598252 | N49: 2001821 | O49: =SUM(M49:N49) -> 2600073 | P49: 2302669
H50: Net gain (loss) on sale of capital assets | M50: -358699 | N50: -321589 | O50: =SUM(M50:N50) -> -680288 | P50: -3285
H51: Miscellaneous | M51: 2534118 | N51: 233994 | O51: =SUM(M51:N51) -> 2768112 | P51: 1511714
H52: Transfers | M52: 20970394 | N52: -20970394 | O52: =SUM(M52:N52) -> 0
H54: Total General Revenues | M54: =SUM(M41:M52) -> 189203387 | N54: =SUM(N41:N52) -> -19056168 | O54: =SUM(O41:O52) -> 170147219 | P54: =SUM(P41:P51) -> 11240465
H56: Change in Net Assets | M56: =M54+M21 -> 24511387 | N56: =N54+N33 -> 8997505 | O56: =O54+O35 -> 33508892 | P56: =P54+P37 -> 11951666
E58: Net Assets- Beginning of Year | M58: 422310244 | N58: 496533033 | O58: =SUM(M58:N58) -> 918843277 | P58: 179666695
E60: Net Assets- End of Year | M60: =SUM(M56,M58) -> 446821631 | N60: =N58+N56 -> 505530538 | O60: =O58+O56 -> 952352169 | P60: =P58+P56 -> 191618361

Sheet Lafourche
J1: Lafourche County 2013 Statement of Activities
J2: Issued: December 31, 2013
M4: NET (EXPENSE) REVENUE AND CHANGE IN NET ASSETS
J5: PROGRAM REVENUES | M5: PRIMARY GOVERNMENT
A6: FUNCTIONS/PROGRAMS | I6: Expenses | J6: Charges for Services | K6: Operating Grants and Contributions | L6: Capital Grants and Contributions | M6: Governmental Activities | N6: Business-type Activities | O6: Total | P6: Component Units
A7: Primary Government:
B8: Government Activities:
C9: General government | I9: -9682819 | J9: 3619120 | K9: 3050257 | L9: 8407592 | M9: =SUM(I9:L9) -> 5394150 | O9: =SUM(M9:N9) -> 5394150
C10: Public safety | I10: -10238978 | J10: 92271 | M10: =SUM(I10:L10) -> -10146707 | O10: =SUM(M10:N10) -> -10146707
C11: Public works | I11: -24463108 | J11: 54500 | K11: 6805083 | L11: 1146858 | M11: =SUM(I11:L11) -> -16456667 | O11: =SUM(M11:N11) -> -16456667
C12: Health and community services | I12: -8598011 | J12: 50584 | K12: 4530419 | M12: =SUM(I12:L12) -> -4017008 | O12: =SUM(M12:N12) -> -4017008
C13: Culture and recreation | I13: -8153571 | J13: 1225 | K13: 457381 | M13: =SUM(I13:L13) -> -7694965 | O13: =SUM(M13:N13) -> -7694965
C14: Interest and fiscal charges | I14: -1899510 | M14: =SUM(I14:L14) -> -1899510 | O14: =SUM(M14:N14) -> -1899510
E16: Total Government Activities | I16: =SUM(I9:I14) -> -63035997 | J16: =SUM(J9:J14) -> 3817700 | K16: =SUM(K9:K14) -> 14843140 | L16: =SUM(L9:L14) -> 9554450 | M16: =SUM(M9:M14) -> -34820707 | O16: =SUM(O9:O14) -> -34820707 | P16: =SUM(P9:P14) -> 0
B18: Business-type Activities:
C19: Sewer | I19: -516960 | J19: 208479 | L19: 63850 | N19: =SUM(I19:L19) -> -244631 | O19: =SUM(M19:N19) -> -244631
E21: Total primary government | I21: =I19+I16 -> -63552957 | J21: =J19+J16 -> 4026179 | K21: =K19+K16 -> 14843140 | L21: =L19+L16 -> 9618300 | M21: =M19+M16 -> -34820707 | N21: =N19+N16 -> -244631 | O21: =O19+O16 -> -35065338 | P21: =SUM(P15:P19) -> 0
E23: Component units | I23: -200886888 | J23: 196864241 | K23: 64516 | L23: 3581214 | M23: 0 | N23: 0 | O23: 0 | P23: =SUM(I23:L23) -> -376917
G25: General Revenues:
H26: Taxes:
I27: Ad valorem | M27: 24018997 | O27: =SUM(M27:N27) -> 24018997 | P27: 14586000
I28: Sales | M28: 16480326 | O28: =SUM(M28:N28) -> 16480326 | P28: 617754
I29: Other | M29: 3246168 | O29: =SUM(M29:N29) -> 3246168
H30: Interest and investment earnings | M30: 31276 | O30: =SUM(M30:N30) -> 31276 | P30: 403074
H31: Grants not restricted to specific programs | M31: 4910918 | O31: =SUM(M31:N31) -> 4910918 | P31: 2929792
H32: Other | M32: 625306 | O32: =SUM(M32:N32) -> 625306 | P32: 507727
H34: Total General Revenues | M34: =SUM(M27:M32) -> 49312991 | N34: =SUM(N27:N32) -> 0 | O34: =SUM(O27:O32) -> 49312991 | P34: =SUM(P27:P32) -> 19044347
H36: Change in Net Assets | M36: =M34+M16 -> 14492284 | N36: =N34+N19 -> -244631 | O36: =O34+O21 -> 14247653 | P36: =P34+P23 -> 18667430
E38: Net Assets- Beginning of Year | M38: 90155178 | N38: 3108991 | O38: =SUM(M38:N38) -> 93264169 | P38: 435818102
E40: Net Assets- End of Year | M40: =M38+M36 -> 104647462 | N40: =N38+N36 -> 2864360 | O40: =O38+O36 -> 107511822 | P40: =P38+P36 -> 454485532

Sheet LaSalle
J1: LaSalle County 2013 Statement of Activities
J2: Issued: December 31, 2013
J5: PROGRAM REVENUES
A6: FUNCTIONS/PROGRAMS | I6: Expenses | J6: Charges for Services | K6: Operating Grants and Contributions | L6: Capital Grants and Contributions | M6: NET (EXPENSE) REVENUE AND CHANGES IN NET ASSETS
A7: Primary Government:
B8: Government Activities:
C9: General government | I9: -1710310 | J9: 144781 | K9: 290950 | M9: =SUM(I9:L9) -> -1274579
C10: Public safety | I10: -657416 | M10: =SUM(I10:L10) -> -657416
C11: Public works | I11: -2586245 | K11: 373172 | M11: =SUM(I11:L11) -> -2213073
C12: Health and welfare | I12: -115859 | M12: =SUM(I12:L12) -> -115859
C13: Culture and recreation | I13: -510825 | J13: 2314 | M13: =SUM(I13:L13) -> -508511
C14: Economic development and assistance | I14: -807761 | K14: 776383 | M14: =SUM(I14:L14) -> -31378
C15: Intergovernmental | I15: -64523 | M15: =SUM(I15:L15) -> -64523
E17: Total Government Activities | I17: =SUM(I9:I15) -> -6452939 | J17: =SUM(J9:J14) -> 147095 | K17: =SUM(K9:K14) -> 1440505 | L17: =SUM(L9:L14) -> 0 | M17: =SUM(M9:M15) -> -4865339
G19: General Revenues:
H20: Taxes:
I21: Ad valorem taxes | M21: 3570296
I22: State revenue sharing | M22: 61254
I23: Other taxes, penalties, and interest | M23: 5216
H24: Grants and contributions not restricted to specific programs | M24: 1295754
H25: Licenses and permits | M25: 69339
H26: Unrestricted investment earnings | M26: 57770
H27: Other | M27: 785
H28: Special item - gain (loss) on sale of assets | M28: 4239
H30: Total General Revenues | M30: =SUM(M21:M28) -> 5064653
H32: Change in Net Assets | M32: =SUM(M17,M30) -> 199314
E34: Net Assets- Beginning of Year | M34: 10580211
E36: Net Assets- End of Year | M36: =SUM(M32,M34) -> 10779525

Sheet Lincoln
J1: Lincoln County 2013 Statement of Activities
J2: Issued: December 31, 2013
J5: PROGRAM REVENUES
A6: FUNCTIONS/PROGRAMS | I6: Expenses | J6: Charges for Services | K6: Operating Grants and Contributions | L6: Capital Grants and Contributions | M6: NET (EXPENSE) REVENUE AND CHANGES IN NET ASSETS
A7: Primary Government:
B8: Government Activities:
C9: General government | I9: -2848793 | J9: 20945 | M9: =SUM(I9:L9) -> -2827848
C10: Public safety | I10: -406799 | J10: 292831 | K10: 37236 | L10: 74592 | M10: =SUM(I10:L10) -> -2140
C11: Public works | I11: -7787925 | J11: 325144 | K11: 613873 | M11: =SUM(I11:L11) -> -6848908
C12: Health and welfare | I12: -549578 | K12: 487166 | M12: =SUM(I12:L12) -> -62412
C13: Culture and Recreation | I13: -2785125 | J13: 374727 | M13: =SUM(I13:L13) -> -2410398
C14: Economic development | I14: -24376 | M14: =SUM(I14:L14) -> -24376
C15: Interest on long-term debt | I15: -143171 | M15: =SUM(I15:L15) -> -143171
E17: Total Government Activities | I17: =SUM(I9:I15) -> -14545767 | J17: =SUM(J9:J14) -> 1013647 | K17: =SUM(K9:K14) -> 1138275 | L17: =SUM(L9:L14) -> 74592 | M17: =SUM(M9:M15) -> -12319253
G19: General Revenues:
G20: Taxes:
H21: Property taxes | M21: 6586959
H22: Sales taxes | M22: 3926512
H23: Other taxes | M23: 225811
H24: Severance taxes | M24: 1138669
G25: Intergovernmental revenues | M25: 285232
G26: Fire insurance rebate | M26: 186657
G27: Other revenues | M27: 18448
G28: Rents and royalties | M28: 210404
G29: Transfers to other funds | M29: -554732
G30: Interest earned | M30: 380878
H32: Total General Revenues | M32: =SUM(M21:M30) -> 12404838
H34: Change in Net Assets | M34: =SUM(M17,M32) -> 85585
E36: Net Assets- Beginning of Year | M36: 55077552
E38: Net Assets- End of Year | M38: =SUM(M34,M36) -> 55163137

Sheet Livingston
J1: Livingston County 2013 Statement of Activities
J2: Issued: December 31, 2013
M4: NET (EXPENSE) REVENUE AND CHANGE IN NET ASSETS
J5: PROGRAM REVENUES | M5: PRIMARY GOVERNMENT
A6: FUNCTIONS/PROGRAMS | I6: Expenses | J6: Charges for Services | K6: Operating Grants and Contributions | L6: Capital Grants and Contributions | M6: Governmental Activities | N6: Business-type Activities | O6: Total
A7: Primary Government:
B8: Government Activities:
C9: General government | I9: -5799361 | J9: 1407121 | K9: 497574 | L9: 1394022 | M9: =SUM(I9:L9) -> -2500644 | O9: =SUM(M9:N9) -> -2500644
C10: Public safety | I10: -6135712 | J10: 1378147 | K10: 902763 | L10: 32710 | M10: =SUM(I10:L10) -> -3822092 | O10: =SUM(M10:N10) -> -3822092
C11: Public works | I11: -15781121 | J11: 154023 | K11: 1547697 | L11: 3101467 | M11: =SUM(I11:L11) -> -10977934 | O11: =SUM(M11:N11) -> -10977934
C12: Health and welfare | I12: -1603310 | J12: 35730 | K12: 312705 | M12: =SUM(I12:L12) -> -1254875 | O12: =SUM(M12:N12) -> -1254875
C13: Culture and recreation | I13: -647904 | M13: =SUM(I13:L13) -> -647904 | O13: =SUM(M13:N13) -> -647904
C14: Economic development | I14: -77776 | M14: =SUM(I14:L14) -> -77776 | O14: =SUM(M14:N14) -> -77776
C15: Debt service interest and fees | I15: -4064515 | K15: 1142441 | M15: =SUM(I15:L15) -> -2922074 | O15: =SUM(M15:N15) -> -2922074
E17: Total Government Activities | I17: =SUM(I9:I15) -> -34109699 | J17: =SUM(J9:J15) -> 2975021 | K17: =SUM(K9:K15) -> 4403180 | L17: =SUM(L9:L15) -> 4528199 | M17: =SUM(M9:M15) -> -22203299 | O17: =SUM(O9:O15) -> -22203299
B19: Business-type Activities:
C20: Utilities - water and sewer | I20: -745007 | J20: 199863 | L20: 561148 | N20: =SUM(I20:L20) -> 16004 | O20: =SUM(M20:N20) -> 16004
E22: Total Business-type Activities | I22: =SUM(I20:I20) -> -745007 | J22: =SUM(J20:J20) -> 199863 | K22: =SUM(K20:K20) -> 0 | L22: =SUM(L20:L20) -> 561148 | M22: =SUM(M20:M20) -> 0 | N22: =SUM(N20:N20) -> 16004 | O22: =SUM(O20:O20) -> 16004
E24: Total primary government | I24: =I22+I17 -> -34854706 | J24: =J22+J17 -> 3174884 | K24: =SUM(K17+K22) -> 4403180 | L24: =SUM(L17+L22) -> 5089347 | M24: =M22+M17 -> -22203299 | N24: =N22+N17 -> 16004 | O24: =O22+O17 -> -22187295
G26: General Revenues:
H27: Taxes:
I28: Ad valorem taxes | M28: 5772883 | O28: =SUM(M28:N28) -> 5772883
I29: Sales taxes | M29: 14326519 | O29: =SUM(M29:N29) -> 14326519
I30: Franchise taxes | M30: 1297516 | O30: =SUM(M30:N30) -> 1297516
I31: Occupational | M31: 981353 | O31: =SUM(M31:N31) -> 981353
H32: Royalties | M32: 1728189 | O32: =SUM(M32:N32) -> 1728189
H33: Miscellaneous | M33: 340105 | O33: =SUM(M33:N33) -> 340105
H34: Use of money and property | M34: 39649 | N34: 118 | O34: =SUM(M34:N34) -> 39767
H35: Transfers | M35: -550000 | N35: 550000 | O35: =SUM(M35:N35) -> 0
H37: Total General Revenues | M37: =SUM(M28:M35) -> 23936214 | N37: =SUM(N28:N35) -> 550118 | O37: =SUM(O28:O35) -> 24486332
H39: Change in Net Assets | M39: =M37+M17 -> 1732915 | N39: =N37+N22 -> 566122 | O39: =O37+O24 -> 2299037
E41: Net Assets- Beginning of Year | M41: 86455602 | N41: 5309089 | O41: =SUM(M41:N41) -> 91764691
E43: Net Assets- End of Year | M43: =SUM(M39,M41) -> 88188517 | N43: =N41+N39 -> 5875211 | O43: =O41+O39 -> 94063728

Sheet Madison
J1: Madison Parish 2013 Statement of Activities
J2: Issued: December 31, 2013
J5: PROGRAM REVENUES
A6: FUNCTIONS/PROGRAMS | I6: Expenses | J6: Charges for Services | K6: Operating Grants and Contributions | L6: Capital Grants and Contributions | M6: NET (EXPENSE) REVENUE AND CHANGES IN NET ASSETS
A7: Governmental activities
C8: General government
D9: Legislative | I9: -161075 | M9: =SUM(I9:L9) -> -161075
D10: Judicial | I10: -918022 | J10: 437928 | M10: =SUM(I10:L10) -> -480094
D11: Elections | I11: -31967 | M11: =SUM(I11:L11) -> -31967
D12: Finance and administrative | I12: -407349 | K12: 5219 | M12: =SUM(I12:L12) -> -402130
D13: Other general administrative | I13: -33661 | J13: 2522 | L13: 158471 | M13: =SUM(I13:L13) -> 127332
C14: Public safety | I14: -1032028 | J14: 61858 | K14: 97405 | L14: 44009 | M14: =SUM(I14:L14) -> -828756
C15: Public works | I15: -3199586 | J15: 629273 | K15: 435315 | L15: 56000 | M15: =SUM(I15:L15) -> -2078998
C16: Health and welfare | I16: -235258 | K16: 3575 | L16: 654943 | M16: =SUM(I16:L16) -> 423260
C17: Culture and recreation | I17: -477506 | J17: 413 | K17: 7273 | M17: =SUM(I17:L17) -> -469820
C18: Economic development and assistance | I18: -48588 | M18: =SUM(I18:L18) -> -48588
C19: Transportation | I19: -173759 | K19: 12932 | M19: =SUM(I19:L19) -> -160827
C20: Miscellaneous | I20: -26670 | M20: =SUM(I20:L20) -> -26670
C21: Interest on long-term debt | I21: -6160 | M21: =SUM(I21:L21) -> -6160
E23: Total Government Activities | I23: =SUM(I8:I21) -> -6751629 | J23: =SUM(J8:J18) -> 1131994 | K23: =SUM(K9:K19) -> 561719 | L23: =SUM(L8:L19) -> 913423 | M23: =SUM(M8:M21) -> -4144493
G25: General Revenues:
H26: Taxes:
I27: Property taxes, levied for general purposes | M27: 5258030
I28: Other taxes and penalties | M28: 174944
I29: State revenue sharing | M29: 96933
I30: Severance tax | M30: 64846
I31: Video poker | M31: 290870
H32: Licenses and permits | M32: 212941
H33: Interest and investment earnings | M33: 18076
H34: Miscellaneous | M34: 222214
H36: Total General Revenues and Special Items | M36: =SUM(M27:M34) -> 6338854
H38: Change in Net position | M38: =M23+M36 -> 2194361
E40: Net position- beginning of year | M40: 18281655
E42: Net position- end of year | M42: =M40+M38 -> 20476016

Sheet Morehouse
J1: Morehouse Parish 2013 Statement of Activities
J2: Issued: December 31, 2013
J5: PROGRAM REVENUES
A6: FUNCTIONS/PROGRAMS | I6: Expenses | J6: Charges for Services | K6: Operating Grants and Contributions | L6: Capital Grants and Contributions | M6: NET (EXPENSE) REVENUE AND CHANGES IN NET ASSETS
A7: Governmental activities
C8: General government
D9: Legislative | I9: -103929 | M9: =SUM(I9:L9) -> -103929
D10: Judicial | I10: -752798 | J10: 216189 | K10: 215983 | M10: =SUM(I10:L10) -> -320626
D11: Elections | I11: -48140 | M11: =SUM(I11:L11) -> -48140
D12: Finance and administrative | I12: -315744 | J12: 212428 | M12: =SUM(I12:L12) -> -103316
D13: Other | I13: -65276 | M13: =SUM(I13:L13) -> -65276
C14: Public safety | I14: -637387 | M14: =SUM(I14:L14) -> -637387
C15: Public works | I15: -2992594 | J15: 107136 | K15: 11000 | M15: =SUM(I15:L15) -> -2874458
C16: Building maintenance | I16: -332293 | J16: 6535 | M16: =SUM(I16:L16) -> -325758
C17: Health and welfare | I17: -306302 | M17: =SUM(I17:L17) -> -306302
C18: Economic development and assistance | I18: -555888 | M18: =SUM(I18:L18) -> -555888
C19: Debt service interest | I19: -16994 | M19: =SUM(I19:L19) -> -16994
E21: Total Government Activities | I21: =SUM(I9:I19) -> -6127345 | J21: =SUM(J9:J19) -> 542288 | K21: =SUM(K9:K19) -> 226983 | L21: =SUM(L8:L18) -> 0 | M21: =SUM(M8:M19) -> -5358074
G23: General Revenues:
H24: Taxes | M24: 3953909
H25: Intergovernmental | M25: 1461135
H26: Unrestricted investment earnings and miscellaneous | M26: 97135
H27: Special item:
I28: Gain (loss) on sale of capital assets | M28: -2750
H30: Total General Revenues and Special Items | M30: =SUM(M24:M28) -> 5509429
H32: Change in Net position | M32: =M21+M30 -> 151355
E34: Net position- beginning of year | M34: 15684370
H36: Prior period adjustment | M36: 35287
E38: Net position- end of year | M38: =SUM(M32:M36) -> 15871012

Sheet Natchitoches
J1: Natchitoches County 2013 Statement of Activities
J2: Issued: December 31, 2013
J5: PROGRAM REVENUES
A6: FUNCTIONS/PROGRAMS | I6: Expenses | J6: Charges for Services | K6: Operating Grants and Contributions | L6: Capital Grants and Contributions | M6: NET (EXPENSE) REVENUE AND CHANGES IN NET ASSETS
A7: Primary Government:
B8: Government Activities:
C9: General government | I9: -1498566 | K9: 818386 | M9: =SUM(I9:L9) -> -680180
C10: Public safety | I10: -1903709 | J10: 111972 | K10: 429027 | M10: =SUM(I10:L10) -> -1362710
C11: Public works | I11: -4637270 | J11: 33280 | K11: 2596474 | L11: 1209234 | M11: =SUM(I11:L11) -> -798282
C12: Health and welfare | I12: -4159270 | K12: 3418136 | M12: =SUM(I12:L12) -> -741134
C13: Recreation and culture | I13: -1787106 | J13: 20482 | K13: 1507 | M13: =SUM(I13:L13) -> -1765117
C14: Economic development | I14: -167767 | M14: =SUM(I14:L14) -> -167767
E16: Total Government Activities | I16: =SUM(I9:I14) -> -14153688 | J16: =SUM(J9:J14) -> 165734 | K16: =SUM(K9:K14) -> 7263530 | L16: =SUM(L9:L14) -> 1209234 | M16: =SUM(M9:M14) -> -5515190
G18: General Revenues:
H19: Taxes:
I20: Ad valorem | M20: 6099757
I21: Sales and use | M21: 2242971
H22: Licenses and permits | M22: 416868
H23: Interest | M23: 9491
H24: Miscellaneous | M24: 120933
H26: Total General Revenues | M26: =SUM(M20:M24) -> 8890020
H28: Change in Net Assets | M28: =SUM(M16,M26) -> 3374830
E30: Net Assets- Beginning of Year | M30: 18514828
E32: Net Assets- End of Year | M32: =SUM(M28,M30) -> 21889658

Sheet Orleans
J1: Orleans County 2013 Statement of Activities
J2: Issued: December 31, 2013
K3: (amounts in thousands)
M5: NET (EXPENSE) REVENUE AND CHANGE IN NET ASSETS
J6: PROGRAM REVENUES | M6: PRIMARY GOVERNMENT
A7: FUNCTIONS/PROGRAMS | I7: Expenses | J7: Charges for Services | K7: Operating Grants and Contributions | L7: Capital Grants and Contributions | M7: Governmental Activities | N7: Component Units
A8: Primary Government:
B9: Government Activities:
C10: General government | I10: -247292000 | J10: 70692000 | K10: 71383000 | L10: 31659000 | M10: =SUM(I10:L10) -> -73558000
C11: Public safety | I11: -230231000 | J11: 22331000 | K11: 15605000 | L11: 5137000 | M11: =SUM(I11:L11) -> -187158000
C12: Public works | I12: -124449000 | J12: 37015000 | K12: 3331000 | L12: 84113000 | M12: =SUM(I12:L12) -> 10000
C13: Health and human services | I13: -27981000 | J13: 8003000 | K13: 15510000 | L13: 12412000 | M13: =SUM(I13:L13) -> 7944000
C14: Culture and recreation | I14: -23403000 | J14: 814000 | K14: 4127000 | L14: 8329000 | M14: =SUM(I14:L14) -> -10133000
C15: Urban development and housing | I15: -23891000 | J15: 1735000 | K15: 24179000 | M15: =SUM(I15:L15) -> 2023000
C16: Economic development | I16: -12731000 | K16: 5442000 | M16: =SUM(I16:L16) -> -7289000
C17: Interest and fiscal charges | I17: -59487000 | M17: =SUM(I17:L17) -> -59487000
E19: Total Government Activities | I19: =SUM(I10:I17) -> -749465000 | J19: =SUM(J10:J17) -> 140590000 | K19: =SUM(K10:K17) -> 139577000 | L19: =SUM(L10:L17) -> 141650000 | M19: =SUM(M10:M17) -> -327648000 | N19: =SUM(N10:N17) -> 0
A21: Component units:
B22: Audubon commission | I22: -59061000 | J22: 38829000 | L22: 11273000 | N22: =SUM(I22:M22) -> -8959000
B23: Louis Armstrong New Orleans International Airport | I23: -107820000 | J23: 73485000 | L23: 9187000 | N23: =SUM(I23:L23) -> -25148000
B24: Sewerage and water board | I24: -188712000 | J24: 143577000 | K24: 2054000 | L24: 114318000 | N24: =SUM(I24:L24) -> 71237000
B25: Other nonmajor component units | I25: -55926000 | J25: 35339000 | K25: 5259000 | L25: 10672000 | N25: =SUM(I25:L25) -> -4656000
E27: Total component units | I27: =SUM(I22:I25) -> -411519000 | J27: =SUM(J22:J25) -> 291230000 | K27: =SUM(K22:K25) -> 7313000 | L27: =SUM(L22:L25) -> 145450000 | M27: =SUM(M22:M25) -> 0 | N27: =SUM(N22:N25) -> 32474000
G29: General Revenues:
H30: Taxes:
I31: Property taxes | M31: 204335000 | N31: 67017000
I32: Sales taxes | M32: 176465000
I33: Utility taxes | M33: 10337000
I34: Culture and recreation taxes | M34: 1781000
I35: Parking taxes | M35: 3940000
I36: Franchise fees | M36: 35239000
I37: Beverage taxes | M37: 5837000
H38: Unrestricted investment income | M38: 15231000 | N38: 777000
H39: Passenger facility charges | N39: 30152000
H40: Forgiveness of loan principal and accrued interest | M40: 1027000 | N40: 30061000
H41: Miscellaneous | M41: 29189000 | N41: 17776000
H43: Total General Revenues | M43: =SUM(M31:M41) -> 483381000 | N43: =SUM(N31:N41) -> 145783000
H45: Change in Net Assets | M45: =M43+M19 -> 155733000 | N45: =N43+N27 -> 178257000
H47: Net position - beginning of year | M47: 38619000 | N47: 2211665000
H49: Prior period adjustments | M49: -9550000 | N49: 54819000
E51: Net Assets- Beginning of Year, as restated | M51: 29069000 | N51: 2266484000
E53: Net Assets- End of Year | M53: =SUM(M45,M51) -> 184802000 | N53: =N51+N45 -> 2444741000

Sheet Ouachita
J1: Ouachita County 2013 Statement of Activities
J2: Issued: December 31, 2013
M4: NET (EXPENSE) REVENUE AND CHANGES IN NET ASSETS
J5: PROGRAM REVENUES | M5: PRIMARY GOVERNMENT
A6: FUNCTIONS/PROGRAMS | I6: Expenses | J6: Charges for Services | K6: Operating Grants and Contributions | L6: Capital Grants and Contributions | M6: Governmental Activities | N6: Business-type Activities | O6: Total
A7: Primary Government:
B8: Government Activities:
C9: General government:
D10: Legislative | I10: -218386 | M10: =SUM(I10:L10) -> -218386 | O10: =SUM(M10:N10) -> -218386
D11: Judicial | I11: -8218534 | J11: 209978 | K11: 1828470 | M11: =SUM(I11:L11) -> -6180086 | O11: =SUM(M11:N11) -> -6180086
D12: Elections | I12: -228700 | M12: =SUM(I12:L12) -> -228700 | O12: =SUM(M12:N12) -> -228700
D13: Finance and administration | I13: -2321667 | J13: 1696245 | M13: =SUM(I13:L13) -> -625422 | O13: =SUM(M13:N13) -> -625422
D14: Other general government | I14: -7501400 | M14: =SUM(I14:L14) -> -7501400 | O14: =SUM(M14:N14) -> -7501400
C15: Public safety | I15: -32003955 | J15: 4419912 | K15: 928939 | L15: 30823 | M15: =SUM(I15:L15) -> -26624281 | O15: =SUM(M15:N15) -> -26624281
C16: Public works | I16: -8667310 | J16: 127977 | K16: 654927 | L16: 5508597 | M16: =SUM(I16:L16) -> -2375809 | O16: =SUM(M16:N16) -> -2375809
C17: Health and welfare | I17: -3881585 | J17: 77819 | K17: 135756 | L17: 108675 | M17: =SUM(I17:L17) -> -3559335 | O17: =SUM(M17:N17) -> -3559335
C18: Culture and recreation | I18: -7295422 | J18: 138425 | K18: 2397 | M18: =SUM(I18:L18) -> -7154600 | O18: =SUM(M18:N18) -> -7154600
C19: Economic and governmental assistance | I19: -4635615 | J19: 503283 | K19: 3844401 | L19: 13394 | M19: =SUM(I19:L19) -> -274537 | O19: =SUM(M19:N19) -> -274537
E21: Total Government Activities | I21: =SUM(I10:I19) -> -74972574 | J21: =SUM(J10:J19) -> 7173639 | K21: =SUM(K10:K19) -> 7394890 | L21: =SUM(L10:L19) -> 5661489 | M21: =SUM(M10:M19) -> -54742556 | O21: =SUM(O10:O19) -> -54742556
B23: Business-type Activities:
C24: Sewer | I24: -469146 | J24: 307075 | N24: =SUM(I24:L24) -> -162071 | O24: =SUM(M24:N24) -> -162071
E26: Total business-type Activities | I26: =SUM(I24:I24) -> -469146 | J26: =SUM(J24:J24) -> 307075 | K26: =SUM(K24:K24) -> 0 | L26: =SUM(L24:L24) -> 0 | M26: =SUM(M24:M24) -> 0 | N26: =SUM(N24:N24) -> -162071 | O26: =SUM(O24:O24) -> -162071
E28: Total primary government | I28: =I26+I21 -> -75441720 | J28: =J26+J21 -> 7480714 | K28: =K26+K21 -> 7394890 | L28: =L26+L21 -> 5661489 | M28: =M26+M21 -> -54742556 | N28: =N26+N21 -> -162071 | O28: =O26+O21 -> -54904627
G30: General Revenues:
G31: Taxes
H32: Ad valorem taxes levied for:
I33: General purposes | M33: 3065712 | O33: =SUM(M33:N33) -> 3065712
I34: Special revenue purposes | M34: 30375702 | O34: =SUM(M34:N34) -> 30375702
H35: Sales taxes levied for:
I36: Special revenue purposes | M36: 14836428 | O36: =SUM(M36:N36) -> 14836428
H37: Other taxes | M37: 3492490 | O37: =SUM(M37:N37) -> 3492490
H38: Grants and contributions not restricted to specific programs | M38: 926893 | O38: =SUM(M38:N38) -> 926893
H39: Licenses and permits | M39: 1101874 | O39: =SUM(M39:N39) -> 1101874
H40: Assessments | M40: 133336 | O40: =SUM(M40:N40) -> 133336
H41: Fines and forfeitures | M41: 3317081 | O41: =SUM(M41:N41) -> 3317081
H42: Insurance premiums | M42: 1424320 | O42: =SUM(M42:N42) -> 1424320
H43: Interest and investment earnings | M43: 129125 | N43: 98 | O43: =SUM(M43:N43) -> 129223
H44: Rents and royalties | M44: 182354 | O44: =SUM(M44:N44) -> 182354
H45: Gain on disposals of assets (net) | M45: 44775 | O45: =SUM(M45:N45) -> 44775
H46: Miscellaneous | M46: 1330430 | O46: =SUM(M46:N46) -> 1330430
H48: Total General Revenues | M48: =SUM(M33:M46) -> 60360520 | N48: =SUM(N33:N46) -> 98 | O48: =SUM(O33:O46) -> 60360618
H50: Change in Net Assets | M50: =M48+M28 -> 5617964 | N50: =N48+N28 -> -161973 | O50: =SUM(M50:N50) -> 5455991
E52: Net Assets- Beginning of Year | M52: 256417818 | N52: 2355780 | O52: =SUM(M52:N52) -> 258773598
E54: Net Assets- End of Year | M54: =SUM(M50,M52) -> 262035782 | N54: =N52+N50 -> 2193807 | O54: =O52+O50 -> 264229589

Sheet Plaquemines
J1: Plaquemines Parish 2013 Statement of Activities
J2: Issued: December 31, 2013
J5: PROGRAM REVENUES | M5: NET (EXPENSE) REVENUE AND CHANGES IN NET ASSETS
A6: FUNCTIONS/PROGRAMS | I6: Expenses | J6: Charges for Services | K6: Operating Grants and Contributions | L6: Capital Grants and Contributions | M6: Governmental Activities | N6: Business-Type Activities | O6: Total
A7: Governmental activities:
C8: General government
D9: Legislative | I9: -1737004 | M9: =SUM(I9:L9) -> -1737004 | O9: =SUM(M9:N9) -> -1737004
D10: Judicial | I10: -5634694 | J10: 630809 | K10: 208212 | M10: =SUM(I10:L10) -> -4795673 | O10: =SUM(M10:N10) -> -4795673
D11: Executive | I11: -3922053 | M11: =SUM(I11:L11) -> -3922053 | O11: =SUM(M11:N11) -> -3922053
D12: Elections | I12: -151663 | M12: =SUM(I12:L12) -> -151663 | O12: =SUM(M12:N12) -> -151663
D13: Finance and administrative | I13: -7255051 | J13: 393000 | K13: 288573 | M13: =SUM(I13:L13) -> -6573478 | O13: =SUM(M13:N13) -> -6573478
D14: Other | I14: -10252824 | J14: 607258 | M14: =SUM(I14:L14) -> -9645566 | O14: =SUM(M14:N14) -> -9645566
C15: Public safety | I15: -8176533 | J15: 269580 | K15: 984186 | M15: =SUM(I15:L15) -> -6922767 | O15: =SUM(M15:N15) -> -6922767
C16: Public works | I16: -27674743 | J16: 842046 | K16: 24204845 | L16: 23334880 | M16: =SUM(I16:L16) -> 20707028 | O16: =SUM(M16:N16) -> 20707028
C17: Health and welfare | I17: -5939409 | J17: 220061 | K17: 469270 | M17: =SUM(I17:L17) -> -5250078 | O17: =SUM(M17:N17) -> -5250078
C18: Culture and recreation | I18: -3752039 | J18: 63402 | K18: 15606 | M18: =SUM(I18:L18) -> -3673031 | O18: =SUM(M18:N18) -> -3673031
C19: Economic development and assistance | I19: -882081 | M19: =SUM(I19:L19) -> -882081 | O19: =SUM(M19:N19) -> -882081
C20: Transportation | I20: -4962360 | J20: 127213 | M20: =SUM(I20:L20) -> -4835147 | O20: =SUM(M20:N20) -> -4835147
C21: Interest on long-term debt | I21: -5354736 | M21: =SUM(I21:L21) -> -5354736 | O21: =SUM(M21:N21) -> -5354736
E23: Total Government Activities | I23: =SUM(I9:I21) -> -85695190 | J23: =SUM(J9:J21) -> 3153369 | K23: =SUM(K9:K21) -> 26170692 | L23: =SUM(L9:L21) -> 23334880 | M23: =SUM(M9:M21) -> -33036249 | N23: =SUM(N9:N21) -> 0 | O23: =SUM(O9:O21) -> -33036249
A25: Business-type activities:
C26: Water and sewer | I26: -33641034 | J26: 3448994 | L26: 18672791 | N26: =SUM(I26:L26) -> -11519249 | O26: =N26 -> -11519249
C27: Boat harbors and shipyards | I27: -12583658 | J27: 330568 | L27: 4793676 | N27: =SUM(I27:L27) -> -7459414 | O27: =N27 -> -7459414
E29: Total Business-type activities | I29: =SUM(I26:I27) -> -46224692 | J29: =SUM(J26:J27) -> 3779562 | K29: =SUM(K26:K27) -> 0 | L29: =SUM(L26:L27) -> 23466467 | M29: =SUM(M26:M27) -> 0 | N29: =SUM(N26:N27) -> -18978663 | O29: =SUM(O26:O27) -> -18978663
E31: Total primary government | I31: =I29+I23 -> -131919882 | J31: =J29+J23 -> 6932931 | K31: =K29+K23 -> 26170692 | L31: =L29+L23 -> 46801347 | M31: =M29+M23 -> -33036249 | N31: =N29+N23 -> -18978663 | O31: =O29+O23 -> -52014912
G33: General Revenues:
G34: Taxes:
H35: Property taxes | M35: 12083791 | N35: 4334902 | O35: =SUM(M35:N35) -> 16418693
H36: Sales and use taxes | M36: 22652227 | O36: =SUM(M36:N36) -> 22652227
G37: Grants and contributions not restricted:
H38: Federal | M38: 29139 | N38: 1575 | O38: =SUM(M38:N38) -> 30714
H39: State | M39: 19566418 | N39: 26000 | O39: =SUM(M39:N39) -> 19592418
G40: Other:
H41: Occupational licenses | M41: 824930 | O41: =SUM(M41:N41) -> 824930
H42: Parish oil royalties | M42: 23175502 | O42: =SUM(M42:N42) -> 23175502
H43: Parish gas royalties | M43: 1148282 | O43: =SUM(M43:N43) -> 1148282
H44: Mineral and surface leases | M44: 420898 | O44: =SUM(M44:N44) -> 420898
H45: Property leases | M45: 87517 | N45: 94765 | O45: =SUM(M45:N45) -> 182282
H46: Investment income | M46: 75268 | N46: 2008 | O46: =SUM(M46:N46) -> 77276
H47: Cablevision fee | M47: 126502 | O47: =SUM(M47:N47) -> 126502
H48: Proceeds from sale of assets | M48: 861753 | N48: 350 | O48: =SUM(M48:N48) -> 862103
H49: Settlements | M49: 445165 | O49: =SUM(M49:N49) -> 445165
H50: Miscellaneous | M50: 170708 | N50: 112165 | O50: =SUM(M50:N50) -> 282873
H51: Penalties | N51: 54946 | O51: =SUM(M51:N51) -> 54946
H52: Transfers | M52: -3213465 | N52: 3213465 | O52: =SUM(M52:N52) -> 0
H54: Total General Revenues and Special Items | M54: =SUM(M35:M52) -> 78454635 | N54: =SUM(N35:N52) -> 7840176 | O54: =SUM(O35:O51) -> 86294811
H56: Change in Net position | M56: =M54+M31 -> 45418386 | N56: =N54+N31 -> -11138487 | O56: =O54+O31 -> 34279899
E58: Net position- beginning of year | M58: 435090298 | N58: 98841733 | O58: =SUM(M58:N58) -> 533932031
E60: Net position- end of year | M60: =M58+M56 -> 480508684 | N60: =N58+N56 -> 87703246 | O60: =O58+O56 -> 568211930

Sheet Pointe Coupee
J1: Pointe Coupee County 2013 Statement of Activities
J2: Issued: December 31, 2013
M5: NET (EXPENSE) REVENUE AND CHANGE IN NET ASSETS
J6: PROGRAM REVENUES | M6: PRIMARY GOVERNMENT | P6: Component Units
A7: FUNCTIONS/PROGRAMS | I7: Expenses | J7: Charges for Services | K7: Operating Grants and Contributions | L7: Capital Grants and Contributions | M7: Governmental Activities | N7: Business-type Activities | O7: Total | P7: Governmental Activities | Q7: Business-type Activities
A8: Primary Government:
B9: Government Activities:
C10: General government | I10: -2657151 | J10: 1560064 | K10: 452080 | M10: =SUM(I10:L10) -> -645007 | O10: =SUM(M10:N10) -> -645007
C11: Public safety | I11: -1205124 | J11: 181727 | K11: 103603 | L11: 2884063 | M11: =SUM(I11:L11) -> 1964269 | O11: =SUM(M11:N11) -> 1964269
C12: Transportation and development | I12: -1249402 | J12: 26509 | M12: =SUM(I12:L12) -> -1222893 | O12: =SUM(M12:N12) -> -1222893
C13: Health and welfare | I13: -3057780 | J13: 10603 | K13: 249679 | M13: =SUM(I13:L13) -> -2797498 | O13: =SUM(M13:N13) -> -2797498
C14: Culture and recreation | I14: -2128071 | J14: 49928 | K14: 1291543 | M14: =SUM(I14:L14) -> -786600 | O14: =SUM(M14:N14) -> -786600
C15: Drainage | I15: -1425494 | J15: 182692 | K15: 282496 | L15: 72473 | M15: =SUM(I15:L15) -> -887833 | O15: =SUM(M15:N15) -> -887833
C16: Economic development | I16: -145546 | M16: =SUM(I16:L16) -> -145546 | O16: =SUM(M16:N16) -> -145546
C17: Interest on long-term debt | I17: -261827 | M17: =SUM(I17:L17) -> -261827 | O17: =SUM(M17:N17) -> -261827
E19: Total Government Activities | I19: =SUM(I10:I17) -> -12130395 | J19: =SUM(J10:J17) -> 2011523 | K19: =SUM(K10:K17) -> 2379401 | L19: =SUM(L10:L17) -> 2956536 | M19: =SUM(M10:M17) -> -4782935 | O19: =SUM(O10:O17) -> -4782935 | P19: =SUM(P10:P17) -> 0 | Q19: =SUM(Q10:Q17) -> 0
B21: Business-type Activities:
C22: Gas | I22: -1834512 | J22: 2057186 | N22: =SUM(I22:L22) -> 222674 | O22: =SUM(M22:N22) -> 222674
C23: Water | I23: -68290 | J23: 75989 | N23: =SUM(I23:L23) -> 7699 | O23: =SUM(M23:N23) -> 7699
C24: Solid waste | I24: -2409014 | J24: 2080615 | N24: =SUM(I24:L24) -> -328399 | O24: =SUM(M24:N24) -> -328399
C25: Multi-use center | I25: -181604 | J25: 17792 | K25: 135250 | N25: =SUM(I25:L25) -> -28562 | O25: =SUM(M25:N25) -> -28562
E27: Total Business-type Activities | I27: =SUM(I22:I25) -> -4493420 | J27: =SUM(J22:J25) -> 4231582 | K27: =SUM(K22:K25) -> 135250 | L27: =SUM(L22:L25) -> 0 | M27: =SUM(M22:M25) -> 0 | N27: =SUM(N22:N25) -> -126588 | O27: =SUM(O22:O25) -> -126588 | P27: =SUM(P15:P25) -> 0 | Q27: =SUM(Q15:Q25) -> 0
E29: Total primary government | I29: =I27+I19 -> -16623815 | J29: =J27+J19 -> 6243105 | K29: =SUM(K19+K27) -> 2514651 | L29: =SUM(L19+L27) -> 2956536 | M29: =M27+M19 -> -4782935 | N29: =N27+N19 -> -126588 | O29: =O27+O19 -> -4909523 | P29: =SUM(P18:P27) -> 0 | Q29: =SUM(Q18:Q27) -> 0
A31: Component units:
B32: Governmental activities | I32: -13573016 | J32: 2934473 | K32: 491997 | L32: 461833 | P32: =SUM(I32:L32) -> -9684713
B33: Business-type activities | I33: -24380811 | J33: 21286639 | K33: 1071083 | L33: 739238 | Q33: =SUM(I33:L33) -> -1283851
E35: Total component units | I35: =SUM(I32:I33) -> -37953827 | J35: =SUM(J32:J33) -> 24221112 | K35: =SUM(K32:K33) -> 1563080 | L35: =SUM(L32:L33) -> 1201071 | M35: =SUM(M32:M33) -> 0 | N35: =SUM(N32:N33) -> 0 | O35: =SUM(O32:O33) -> 0 | P35: =SUM(P32:P33) -> -9684713 | Q35: =SUM(Q32:Q33) -> -1283851
G37: General Revenues:
H38: Taxes:
I39: Property | M39: 2823306 | O39: =SUM(M39:N39) -> 2823306 | P39: 8819331 | Q39: 222029
I40: Sales | M40: 3130788 | N40: 659113 | O40: =SUM(M40:N40) -> 3789901 | P40: 997764 | Q40: 1939211
I41: Franchise | M41: 40786 | O41: =SUM(M41:N41) -> 40786 | Q41: 4
I42: Other | M42: 151169 | O42: =SUM(M42:N42) -> 151169 | P42: 144707 | Q42: 2198
H43: Grants and contributions not restricted to specific programs | M43: 39909 | O43: =SUM(M43:N43) -> 39909 | P43: 590985 | Q43: 649634
H44: Investment earnings | M44: 15856 | N44: 18 | O44: =SUM(M44:N44) -> 15874 | P44: 22143 | Q44: 244469
H45: Gain (loss) on sale of capital assets, net | M45: 31626 | N45: 2678 | O45: =SUM(M45:N45) -> 34304 | P45: 19700 | Q45: -3517
H46: Transfers (to) from other funds | M46: 352750 | N46: -352750 | O46: =SUM(M46:N46) -> 0
H48: Total General Revenues | M48: =SUM(M39:M46) -> 6586190 | N48: =SUM(N39:N46) -> 309059 | O48: =SUM(O39:O46) -> 6895249 | P48: =SUM(P39:P46) -> 10594630 | Q48: =SUM(Q39:Q46) -> 3054028
H50: Change in Net Assets | M50: =M48+M19 -> 1803255 | N50: =N48+N29 -> 182471 | O50: =O48+O29 -> 1985726 | P50: =P48+P35 -> 909917 | Q50: =Q48+Q35 -> 1770177
E52: Net Assets- Beginning of Year, as restated | M52: 11697743 | N52: 1838160 | O52: =SUM(M52:N52) -> 13535903 | P52: 26240813 | Q52: 40526584
E54: Net Assets- End of Year | M54: =SUM(M50,M52) -> 13500998 | N54: =N52+N50 -> 2020631 | O54: =O52+O50 -> 15521629 | P54: =P52+P50 -> 27150730 | Q54: =Q52+Q50 -> 42296761

Sheet Rapides
J1: Rapides Parish 2013 Statement of Activities
J2: Issued: December 31, 2013
J5: PROGRAM REVENUES | M5: NET (EXPENSE) REVENUE AND CHANGES IN NET ASSETS
A6: FUNCTIONS/PROGRAMS | I6: Expenses | J6: Charges for Services | K6: Operating Grants and Contributions | L6: Capital Grants and Contributions | M6: 2013 | N6: 2012
A7: Governmental activities:
C8: General government
D9: Legislative | I9: -435329 | M9: =SUM(I9:L9) -> -435329 | N9: -541648
D10: Judicial | I10: -4988816 | J10: 2744332 | K10: 205424 | M10: =SUM(I10:L10) -> -2039060 | N10: -2248970
D11: Elections | I11: -330382 | M11: =SUM(I11:L11) -> -330382 | N11: -372224
D12: Finance and administrative | I12: -4897793 | J12: 1562808 | M12: =SUM(I12:L12) -> -3334985 | N12: -5342496
D13: Other | I13: -2090050 | J13: 36486 | M13: =SUM(I13:L13) -> -2053564 | N13: -271301
C14: Public safety | I14: -11991080 | J14: 2232852 | M14: =SUM(I14:L14) -> -9758228 | N14: -8483108
C15: Public works | I15: -13645028 | K15: 3720448 | M15: =SUM(I15:L15) -> -9924580 | N15: -4545810
C16: Health and welfare | I16: -1372309 | K16: 810148 | M16: =SUM(I16:L16) -> -562161 | N16: -835297
C17: Culture and recreation | I17: -1782374 | J17: 97290 | K17: 58659 | M17: =SUM(I17:L17) -> -1626425 | N17: -767146
C18: Economic development and assistance | I18: -4759645 | K18: 3052723 | M18: =SUM(I18:L18) -> -1706922 | N18: -944513
C19: Debt service | I19: -1097914 | M19: =SUM(I19:L19) -> -1097914 | N19: -72528
E21: Total Government Activities | I21: =SUM(I9:I19) -> -47390720 | J21: =SUM(J9:J19) -> 6673768 | K21: =SUM(K9:K19) -> 7847402 | L21: =SUM(L9:L19) -> 0 | M21: =SUM(M9:M19) -> -32869550 | N21: =SUM(N9:N19) -> -24425041
G23: General Revenues:
H24: Taxes:
I25: Property taxes levied for general purposes | M25: 20306057 | N25: 17386075
I26: Sales and use taxes, levied for general purposes | M26: 2149681 | N26: 2133222
I27: Sales and use taxes, levied for public works | M27: 2523515 | N27: 2468107
I28: Other taxes, licenses, and penalties | M28: 584773 | N28: 577847
H29: Licenses and permits | M29: 602475 | N29: 1090952
H30: Federal grant programs - unrestricted | M30: 994749 | N30: 401310
H31: State grant programs - unrestricted | M31: 872711 | N31: 1396407
H32: Interest and investment earnings | M32: 197709 | N32: 274274
H33: Miscellaneous | M33: 415614 | N33: 915432
H35: Total General Revenues and Special Items | M35: =SUM(M25:M33) -> 28647284 | N35: =SUM(N25:N33) -> 26643626
H37: Change in Net position | M37: =M35+M21 -> -4222266 | N37: =N35+N21 -> 2218585
E39: Net position- beginning of year | M39: 73456911 | N39: 71238327
E41: Net position- end of year | M41: =M39+M37 -> 69234645 | N41: =N39+N37 -> 73456912

Sheet Red River
J1: Red River County 2013 Statement of Activities
J2: Issued: December 31, 2013
L4: NET (EXPENSE) REVENUE AND CHANGE IN NET ASSETS
J5: PROGRAM REVENUES | L5: PRIMARY GOVERNMENT
A6: FUNCTIONS/PROGRAMS | I6: Expenses | J6: Charges for Services | K6: Operating Grants and Contributions | L6: Governmental Activities | M6: Business-type Activities | N6: Total
A7: Primary Government:
B8: Government Activities:
C9: General government | I9: -1306120 | J9: 198181 | K9: 208772 | L9: =SUM(I9:K9) -> -899167 | N9: =SUM(L9:M9) -> -899167
C10: Public safety | I10: -1601309 | J10: 396531 | K10: 80836 | L10: =SUM(I10:K10) -> -1123942 | N10: =SUM(L10:M10) -> -1123942
C11: Public works | I11: -3571534 | J11: 185581 | K11: 316478 | L11: =SUM(I11:K11) -> -3069475 | N11: =SUM(L11:M11) -> -3069475
C12: Health and welfare | I12: -452977 | K12: 181609 | L12: =SUM(I12:K12) -> -271368 | N12: =SUM(L12:M12) -> -271368
C13: Recreation and culture | I13: -303039 | J13: 2006 | L13: =SUM(I13:K13) -> -301033 | N13: =SUM(L13:M13) -> -301033
E15: Total Government Activities | I15: =SUM(I9:I13) -> -7234979 | J15: =SUM(J9:J13) -> 782299 | K15: =SUM(K9:K13) -> 787695 | L15: =SUM(L9:L13) -> -5664985 | N15: =SUM(N9:N13) -> -5664985
B17: Business-type Activities:
C18: Sewer | I18: -124415 | J18: 24982 | M18: =SUM(I18:K18) -> -99433 | N18: =SUM(L18:M18) -> -99433
E20: Total Business-type Activities | I20: =SUM(I18:I18) -> -124415 | J20: =SUM(J18:J18) -> 24982 | K20: =SUM(K18:K18) -> 0 | L20: =SUM(L18:L18) -> 0 | M20: =SUM(M18:M18) -> -99433 | N20: =SUM(N18:N18) -> -99433
E22: Total primary government | I22: =I20+I15 -> -7359394 | J22: =J20+J15 -> 807281 | K22: =SUM(K15+K20) -> 787695 | L22: =L20+L15 -> -5664985 | M22: =M20+M15 -> -99433 | N22: =N20+N15 -> -5764418
G24: General Revenues:
H25: Taxes:
I26: Ad valorem | L26: 3607111 | N26: =SUM(L26:M26) -> 3607111
I27: Sales and use taxes | L27: 2830032 | N27: =SUM(L27:M27) -> 2830032
I28: Severance taxes | L28: 169922 | N28: =SUM(L28:M28) -> 169922
I29: Other | L29: 424304 | N29: =SUM(L29:M29) -> 424304
H30: License and permits | L30: 67664 | N30: =SUM(L30:M30) -> 67664
H31: Gaming revenues | L31: 8492 | N31: =SUM(L31:M31) -> 8492
H32: State revenue sharing | L32: 54562 | N32: =SUM(L32:M32) -> 54562
H33: Interest and investment income (losses) | L33: -349431 | N33: =SUM(L33:M33) -> -349431
H34: Miscellaneous | L34: 56289 | N34: =SUM(L34:M34) -> 56289
H35: Transfers (to) from other funds | L35: -30000 | M35: 30000 | N35: =SUM(L35:M35) -> 0
H37: Total General Revenues and transfers | L37: =SUM(L26:L35) -> 6838945 | M37: =SUM(M26:M35) -> 30000 | N37: =SUM(N26:N35) -> 6868945
H39: Change in Net Assets | L39: =L37+L15 -> 1173960 | M39: =M37+M20 -> -69433 | N39: =N37+N22 -> 1104527
E41: Net Assets- Beginning of Year (restated) | L41: 46634829 | M41: 450052 | N41: =SUM(L41:M41) -> 47084881
E43: Net Assets- End of Year | L43: =SUM(L39,L41) -> 47808789 | M43: =M41+M39 -> 380619 | N43: =N41+N39 -> 48189408

Sheet Richland
J1: Richland Parish 2013 Statement of Activities
J2: Issued: December 31, 2013
J5: PROGRAM REVENUES | M5: NET (EXPENSE) REVENUE AND CHANGES IN NET ASSETS
A6: FUNCTIONS/PROGRAMS | I6: Expenses | J6: Charges for Services | K6: Operating Grants and Contributions | L6: Capital Grants and Contributions | M6: 2013
A7: Governmental activities:
C8: General government
D9: Legislative | I9: -273649 | M9: =SUM(I9:L9) -> -273649
D10: Judicial | I10: -112369 | J10: 7871 | K10: 15126 | M10: =SUM(I10:L10) -> -89372
D11: Elections | I11: -38823 | M11: =SUM(I11:L11) -> -38823
D12: Finance and administrative | I12: -346145 | J12: 159952 | M12: =SUM(I12:L12) -> -186193
D13: Other | I13: -121106 | J13: 41578 | M13: =SUM(I13:L13) -> -79528
C14: Public safety | I14: -560062 | J14: 42218 | K14: 151785 | M14: =SUM(I14:L14) -> -366059
C15: Public works | I15: -4957389 | J15: 120135 | K15: 527782 | M15: =SUM(I15:L15) -> -4309472
C16: Health and welfare | I16: -269329 | M16: =SUM(I16:L16) -> -269329
C17: Culture and recreation | I17: -740850 | J17: 15197 | M17: =SUM(I17:L17) -> -725653
C18: Economic development and assistance | I18: -129347 | M18: =SUM(I18:L18) -> -129347
C19: Debt service:
D20: Interest | I20: -1995 | M20: =SUM(I20:L20) -> -1995
E22: Total Government Activities | I22: =SUM(I9:I20) -> -7551064 | J22: =SUM(J9:J20) -> 386951 | K22: =SUM(K9:K20) -> 694693 | L22: =SUM(L9:L20) -> 0 | M22: =SUM(M9:M20) -> -6469420
G24: General Revenues:
H25: Taxes | M25: 7465263
H26: Intergovernmental | M26: 258034
H27: Unrestricted investment earnings and miscellaneous | M27: 42240
H28: Special item:
I29: Gain on sale of capital assets | M29: 6450
H31: Total General Revenues and Special Items | M31: =SUM(M25:M29) -> 7771987
H33: Change in Net position | M33: =M31+M22 -> 1302567
E35: Net position- beginning of year | M35: 8821225
E37: Net position- end of year | M37: =M35+M33 -> 10123792

Sheet Sabine
J1: Sabine Parish 2013 Statement of Activities
J2: Issued: December 31, 2013
J5: PROGRAM REVENUES | M5: NET (EXPENSE) REVENUE AND CHANGES IN NET ASSETS
A6: FUNCTIONS/PROGRAMS | I6: Expenses | J6: Charges for Services | K6: Operating Grants and Contributions | L6: Capital Grants and Contributions | M6: 2013 | N6: 2012
A7: Governmental activities:
C8: General government
D9: Legislative | I9: -127028 | M9: =SUM(I9:L9) -> -127028 | N9: -130158
D10: Judicial | I10: -577875 | J10: 253163 | M10: =SUM(I10:L10) -> -324712 | N10: -225112
D11: Elections | I11: -68164 | M11: =SUM(I11:L11) -> -68164 | N11: -25646
D12: Finance and administrative | I12: -382749 | M12: =SUM(I12:L12) -> -382749 | N12: -383542
D13: Other | I13: -662550 | M13: =SUM(I13:L13) -> -662550 | N13: -457174
C14: Public safety | I14: -953770 | K14: 809974 | M14: =SUM(I14:L14) -> -143796 | N14: -148093
C15: Public works | I15: -8414454 | J15: 107825 | K15: 405227 | M15: =SUM(I15:L15) -> -7901402 | N15: -9155725
C16: Health and welfare | I16: -155557 | M16: =SUM(I16:L16) -> -155557 | N16: -248501
C17: Culture and recreation | M17: =SUM(I17:L17) -> 0 | N17: -11639
C18: Economic development and assistance | I18: -30591 | M18: =SUM(I18:L18) -> -30591 | N18: -311925
C19: Debt service | I19: -12512 | M19: =SUM(I19:L19) -> -12512 | N19: -14942
E21: Total Government Activities | I21: =SUM(I9:I19) -> -11385250 | J21: =SUM(J9:J19) -> 360988 | K21: =SUM(K9:K19) -> 1215201 | L21: =SUM(L9:L19) -> 0 | M21: =SUM(M9:M19) -> -9809061 | N21: =SUM(N9:N19) -> -11112457
G23: General Revenues:
H24: Taxes:
I25: Property taxes, levied for general purposes | M25: 3214227 | N25: 2857024
I26: Sales and use taxes, levied for general purposes | M26: 3587239 | N26: 5173147
H27: State grant programs | M27: 1525642 | N27: 896123
H28: Interest and investment earnings | M28: 185917 | N28: 102655
H29: Miscellaneous | M29: 157299 | N29: 302140
H31: Total General Revenues and Special Items | M31: =SUM(M25:M29) -> 8670324 | N31: =SUM(N25:N29) -> 9331089
H33: Change in Net position | M33: =M31+M21 -> -1138737 | N33: =N31+N21 -> -1781368
E35: Net position- beginning of year | M35: 24534161 | N35: 26315526
E37: Net position- end of year | M37: =M35+M33 -> 23395424 | N37: =N35+N33 -> 24534158

Sheet St. Bernard
J1: St. Bernard County 2013 Statement of Activities
J2: Issued: December 31, 2013
M4: NET (EXPENSE) REVENUE AND CHANGE IN NET ASSETS
J5: PROGRAM REVENUES | M5: PRIMARY GOVERNMENT
A6: FUNCTIONS/PROGRAMS | I6: Expenses | J6: Charges for Services | K6: Operating Grants and Contributions | L6: Capital Grants and Contributions | M6: Governmental Activities | N6: Business-type Activities | O6: Total
A7: Primary Government:
B8: Government Activities:
C9: General government:
D10: Judicial | I10: -607122 | J10: 49271 | M10: =SUM(I10:L10) -> -557851 | O10: =SUM(M10:N10) -> -557851
D11: Other general government | I11: -29878021 | J11: 2492129 | K11: 15443154 | L11: 54182911 | M11: =SUM(I11:L11) -> 42240173 | O11: =SUM(M11:N11) -> 42240173
C12: Public safety | I12: -10548513 | J12: 13430 | K12: 1935549 | M12: =SUM(I12:L12) -> -8599534 | O12: =SUM(M12:N12) -> -8599534
C13: Public works | I13: -19434223 | J13: 88115 | K13: 624751 | L13: 1147916 | M13: =SUM(I13:L13) -> -17573441 | O13: =SUM(M13:N13) -> -17573441
C14: Culture and recreation | I14: -2889701 | J14: 2156309 | K14: 252892 | M14: =SUM(I14:L14) -> -480500 | O14: =SUM(M14:N14) -> -480500
C15: Health and welfare | I15: -6692893 | K15: 5649464 | M15: =SUM(I15:L15) -> -1043429 | O15: =SUM(M15:N15) -> -1043429
C16: Interest on long-term debt | I16: -1860282 | M16: =SUM(I16:L16) -> -1860282 | O16: =SUM(M16:N16) -> -1860282
E18: Total Government Activities | I18: =SUM(I10:I16) -> -71910755 | J18: =SUM(J10:J16) -> 4799254 | K18: =SUM(K10:K16) -> 23905810 | L18: =SUM(L10:L16) -> 55330827 | M18: =SUM(M10:M16) -> 12125136 | O18: =SUM(O10:O16) -> 12125136
B20: Business-type Activities:
C21: Water and sewer | I21: -10153902 | J21: 5748284 | K21: 12550 | L21: 5690363 | N21: =SUM(I21:L21) -> 1297295 | O21: =SUM(M21:N21) -> 1297295
C22: Interest on long-term debt | I22: -494988 | N22: =SUM(I22:L22) -> -494988 | O22: =SUM(M22:N22) -> -494988
E24: Total Business-type Activities | I24: =SUM(I21:I22) -> -10648890 | J24: =SUM(J21:J22) -> 5748284 | K24: =SUM(K21:K22) -> 12550 | L24: =SUM(L21:L22) -> 5690363 | M24: =SUM(M21:M22) -> 0 | N24: =SUM(N21:N22) -> 802307 | O24: =SUM(O21:O22) -> 802307
E26: Total primary government | I26: =I24+I18 -> -82559645 | J26: =J24+J18 -> 10547538 | K26: =SUM(K18+K24) -> 23918360 | L26: =SUM(L18+L24) -> 61021190 | M26: =M24+M18 -> 12125136 | N26: =N24+N18 -> 802307 | O26: =O24+O18 -> 12927443
G28: General Revenues:
H29: Taxes:
I30: Ad valorem (property) taxes | M30: 12941340 | O30: =SUM(M30:N30) -> 12941340
I31: Sales and use taxes | M31: 15844744 | N31: 3961184 | O31: =SUM(M31:N31) -> 19805928
I32: Severance | M32: 971328 | O32: =SUM(M32:N32) -> 971328
I33: E telephone | M33: 378840 | O33: =SUM(M33:N33) -> 378840
I34: Other | M34: 111949 | O34: =SUM(M34:N34) -> 111949
H35: Interest and investment earnings | M35: 195208 | N35: 37106 | O35: =SUM(M35:N35) -> 232314
H36: Other general revenues (expenses) | M36: 1168627 | N36: 330835 | O36: =SUM(M36:N36) -> 1499462
H37: Loss on disposal of capital assets | M37: -149742 | O37: =SUM(M37:N37) -> -149742
H38: Cancellation of debt | M38: 5403510 | O38: =SUM(M38:N38) -> 5403510
H40: Total General Revenues | M40: =SUM(M30:M38) -> 36865804 | N40: =SUM(N30:N38) -> 4329125 | O40: =SUM(O30:O38) -> 41194929
H42: Transfer in (out) | M42: -14209856 | N42: 14209856 | O42: =SUM(M42:N42) -> 0
H44: Change in Net Assets | M44: 34781084 | N44: 19341288 | O44: =SUM(M44:N44) -> 54122372
E46: Net Assets- Beginning of Year | M46: 343618811 | N46: 197676022 | O46: =SUM(M46:N46) -> 541294833
E48: Net Assets- End of Year | M48: =SUM(M44,M46) -> 378399895 | N48: =N46+N44 -> 217017310 | O48: =O46+O44 -> 595417205

Sheet St. Charles
J1: St. Charles County 2013 Statement of Activities
J2: Issued: December 31, 2013
M4: NET (EXPENSE) REVENUE AND CHANGE IN NET ASSETS
J5: PROGRAM REVENUES | M5: PRIMARY GOVERNMENT
A6: FUNCTIONS/PROGRAMS | I6: Expenses | J6: Charges for Services | K6: Operating Grants and Contributions | L6: Capital Grants and Contributions | M6: Governmental Activities | N6: Business-type Activities | O6: Total | P6: Component Units
A7: Primary Government:
B8: Government Activities:
C9: General government | I9: -18234171 | J9: 3163440 | K9: 8867030 | L9: 3835295 | M9: =SUM(I9:L9) -> -2368406 | O9: =SUM(M9:N9) -> -2368406
C10: Public safety | I10: -8311542 | K10: 214114 | M10: =SUM(I10:L10) -> -8097428 | O10: =SUM(M10:N10) -> -8097428
C11: Public works | I11: -25161360 | J11: 96187 | K11: 1061166 | L11: 1236452 | M11: =SUM(I11:L11) -> -22767555 | O11: =SUM(M11:N11) -> -22767555
C12: Health and welfare | I12: -5799325 | K12: 94882 | M12: =SUM(I12:L12) -> -5704443 | O12: =SUM(M12:N12) -> -5704443
C13: Culture and recreation | I13: -4574464 | J13: 197403 | L13: 138700 | M13: =SUM(I13:L13) -> -4238361 | O13: =SUM(M13:N13) -> -4238361
C14: Economic development and assistance | I14: -2397090 | K14: 1421170 | M14: =SUM(I14:L14) -> -975920 | O14: =SUM(M14:N14) -> -975920
C15: Interest and other charges on long-term debt | I15: -532285 | M15: =SUM(I15:L15) -> -532285 | O15: =SUM(M15:N15) -> -532285
C16: Transfers - capital contributions | L16: 631661 | M16: =SUM(I16:L16) -> 631661 | O16: =SUM(M16:N16) -> 631661
E18: Total Government Activities | I18: =SUM(I9:I16) -> -65010237 | J18: =SUM(J9:J16) -> 3457030 | K18: =SUM(K9:K16) -> 11658362 | L18: =SUM(L9:L16) -> 5842108 | M18: =SUM(M9:M16) -> -44052737 | O18: =SUM(O9:O16) -> -44052737 | P18: =SUM(P9:P15) -> 0
B20: Business-type Activities:
C21: Waterworks utility system | I21: -11300078 | J21: 10427732 | K21: 348468 | L21: 48464 | N21: =SUM(I21:L21) -> -475414 | O21: =SUM(M21:N21) -> -475414
C22: Wastewater utility system | I22: -11557921 | J22: 7990415 | N22: =SUM(I22:L22) -> -3567506 | O22: =SUM(M22:N22) -> -3567506
C23: Solid waste collection and disposal | I23: -3436409 | J23: 3457347 | N23: =SUM(I23:L23) -> 20938 | O23: =SUM(M23:N23) -> 20938
E25: Total Business-type Activities | I25: =SUM(I21:I23) -> -26294408 | J25: =SUM(J21:J23) -> 21875494 | K25: =SUM(K21:K23) -> 348468 | L25: =SUM(L21:L23) -> 48464 | M25: =SUM(M21:M23) -> 0 | N25: =SUM(N21:N23) -> -4021982 | O25: =SUM(O21:O23) -> -4021982 | P25: =SUM(P14:P23) -> 0
E27: Total primary government | I27: =I25+I18 -> -91304645 | J27: =J25+J18 -> 25332524 | K27: =SUM(K18+K25) -> 12006830 | L27: =SUM(L18+L25) -> 5890572 | M27: =M25+M18 -> -44052737 | N27: =N25+N18 -> -4021982 | O27: =O25+O18 -> -48074719 | P27: =SUM(P17:P25) -> 0
A29: Component units:
B30: Communications district | I30: -1501391 | J30: 662632 | K30: 1097480 | P30: =SUM(I30:L30) -> 258721
B31: Library service district no. 1 | I31: -4918378 | J31: 34424 | K31: 73386 | L31: -154756 | P31: =SUM(I31:L31) -> -4965324
B32: Sunset drainage district | I32: -173390 | L32: -476905 | P32: =SUM(I32:L32) -> -650295
B33: Hospital service district | I33: -43629136 | J33: 22328763 | K33: 7173520 | P33: =SUM(I33:L33) -> -14126853
E35: Total component units | I35: =SUM(I30:I33) -> -50222295 | J35: =SUM(J30:J33) -> 23025819 | K35: =SUM(K30:K33) -> 8344386 | L35: =SUM(L30:L33) -> -631661 | M35: =SUM(M30:M33) -> 0 | N35: =SUM(N30:N33) -> 0 | O35: =SUM(O30:O33) -> 0 | P35: =SUM(P30:P33) -> -19483751
G37: General Revenues:
H38: Taxes:
I39: Ad valorem taxes | M39: 24732161 | O39: =SUM(M39:N39) -> 24732161 | P39: 8606913
I40: Sales taxes | M40: 35144273 | O40: =SUM(M40:N40) -> 35144273
I41: Maintenance tax | O41: =SUM(M41:N41) -> 0 | P41: 2773097
I42: Alcoholic beverage tax | M42: 48168 | O42: =SUM(M42:N42) -> 48168
I43: Airport expansion agreement | M43: 296893 | O43: =SUM(M43:N43) -> 296893
I44: Cable TV franchise tax | M44: 767343 | O44: =SUM(M44:N44) -> 767343
H45: Investment earnings | M45: 253115 | N45: 27318 | O45: =SUM(M45:N45) -> 280433 | P45: 30914
H46: Miscellaneous | M46: 1153292 | N46: -21019 | O46: =SUM(M46:N46) -> 1132273 | P46: 19901
H47: Transfers (to) from other funds | M47: -812124 | N47: 812124 | O47: =SUM(M47:N47) -> 0
H49: Total General Revenues and Transfers | M49: =SUM(M39:M47) -> 61583121 | N49: =SUM(N39:N47) -> 818423 | O49: =SUM(O39:O47) -> 62401544 | P49: =SUM(P39:P47) -> 11430825
H51: Change in Net Assets | M51: =M49+M18 -> 17530384 | N51: =N49+N27 -> -3203559 | O51: =O49+O27 -> 14326825 | P51: =P49+P35 -> -8052926
E53: Net Assets- Beginning of Year | M53: 233899646 | N53: 116812375 | O53: =SUM(M53:N53) -> 350712021 | P53: 5854133
E55: Net Assets- End of Year | M55: =SUM(M51,M53) -> 251430030 | N55: =N53+N51 -> 113608816 | O55: =O53+O51 -> 365038846 | P55: =P53+P51 -> -2198793

Sheet St. Helena
J1: St. Helena County 2013 Statement of Activities
J2: Issued: December 31, 2013
M5: NET (EXPENSE) REVENUE AND CHANGE IN NET ASSETS
J6: PROGRAM REVENUES | N6: Discretely Presented Component Units
A7: FUNCTIONS/PROGRAMS | I7: Expenses | J7: Charges for Services | K7: Operating Grants and Contributions | L7: Capital Grants and Contributions | M7: Governmental Activities | N7: St. Helena Par Hospital Serv Dist 1 & Subsidiary | O7: Water Works Dist No. 2 of St. Helena Par | P7: Other Component Units | Q7: Total Component Units
A8: Primary Government:
B9: Government Activities:
C10: General government | I10: -1671772 | J10: 235019 | K10: 14400 | L10: 8466 | M10: =SUM(I10:L10) -> -1413887 | Q10: =SUM(N10:P10) -> 0
C11: Public safety | I11: -1168293 | J11: 111490 | K11: 56820 | L11: 59399 | M11: =SUM(I11:L11) -> -940584 | Q11: =SUM(N11:P11) -> 0
C12: Public works | I12: -2607340 | J12: 6400 | K12: 237191 | L12: 422626 | M12: =SUM(I12:L12) -> -1941123 | Q12: =SUM(N12:P12) -> 0
C13: Health and welfare | I13: -338845 | J13: 2993 | K13: 139490 | L13: 11792 | M13: =SUM(I13:L13) -> -184570 | Q13: =SUM(N13:P13) -> 0
C14: Recreation | I14: -21760 | L14: 476426 | M14: =SUM(I14:L14) -> 454666 | Q14: =SUM(N14:P14) -> 0
C15: Economic development | I15: -163375 | K15: 71914 | M15: =SUM(I15:L15) -> -91461 | Q15: =SUM(N15:P15) -> 0
C16: Interest on long-term indebtedness | I16: -60913 | M16: =SUM(I16:L16) -> -60913 | Q16: =SUM(N16:P16) -> 0
E18: Total Government Activities | I18: =SUM(I10:I16) -> -6032298 | J18: =SUM(J10:J16) -> 355902 | K18: =SUM(K10:K16) -> 519815 | L18: =SUM(L10:L16) -> 978709 | M18: =SUM(M10:M16) -> -4177872 | N18: =SUM(N10:N16) -> 0 | Q18: =SUM(Q10:Q16) -> 0
A20: Discretely Presented Component Units
B21: St. Helena Parish Hospital Serv Dist 1 & Subsidary | I21: -13465977 | J21: 16698936 | N21: =SUM(I21:L21) -> 3232959 | Q21: =N21 -> 3232959
B22: Water works district No. 2 of St. Helena Parish | I22: -855472 | J22: 930431 | L22: 23750 | O22: =SUM(I22:L22) -> 98709 | Q22: =O22 -> 98709
B23: Other component units | I23: -327397 | J23: 30000 | K23: 2446 | L23: 17510 | P23: =SUM(I23:L23) -> -277441 | Q23: =P23 -> -277441
E25: Total component units | I25: =SUM(I21:I23) -> -14648846 | J25: =SUM(J21:J23) -> 17659367 | K25: =SUM(K21:K23) -> 2446 | L25: =SUM(L21:L23) -> 41260 | M25: =SUM(M21:M23) -> 0 | N25: =SUM(N21:N23) -> 3232959 | O25: =SUM(O21:O23) -> 98709 | P25: =SUM(P21:P23) -> -277441 | Q25: =SUM(Q21:Q23) -> 3054227
G27: General Revenues:
H28: Taxes:
I29: Property taxes | M29: 1784933 | P29: 348720 | Q29: =SUM(N29:P29) -> 348720
I30: Sales taxes | M30: 2164307 | P30: 1329 | Q30: =SUM(N30:P30) -> 1329
I31: Other taxes | M31: 8854 | Q31: =SUM(N31:P31) -> 0
H32: Fire Insurance rebates | M32: 31076 | P32: 7055 | Q32: =SUM(N32:P32) -> 7055
H33: Intergovernmental: | Q33: =SUM(N33:P33) -> 0
I34: Gaming | M34: 918051 | Q34: =SUM(N34:P34) -> 0
I35: Severance Taxes | M35: 900080 | Q35: =SUM(N35:P35) -> 0
I36: State revenue sharing | M36: 86586 | Q36: =SUM(N36:P36) -> 0
H37: Investment earnings | M37: 25720 | N37: 2761 | O37: 2988 | P37: 739 | Q37: =SUM(N37:P37) -> 6488
H38: Recovery of bad debts | O38: 2545 | Q38: =SUM(N38:P38) -> 2545
H39: Miscellaneous | M39: 50299 | O39: 6088 | P39: 5414 | Q39: =SUM(N39:P39) -> 11502
H40: Payments (to) from other local governments | M40: -143193 | P40: 20753 | Q40: =SUM(N40:P40) -> 20753
H41: Gain (loss) on sale or Acquisition (Disposition) of assets | M41: 31016 | O41: 4222 | Q41: =SUM(N41:P41) -> 4222
H43: Total General Revenues and transfers | M43: =SUM(M29:M41) -> 5857729 | N43: =SUM(N29:N41) -> 2761 | O43: =SUM(O29:O41) -> 15843 | P43: =SUM(P29:P41) -> 384010 | Q43: =SUM(Q29:Q41) -> 402614
H45: Change in Net Assets | M45: =M43+M18 -> 1679857 | N45: =N43+N25 -> 3235720 | O45: =O43+O25 -> 114552 | P45: =P43+P25 -> 106569 | Q45: =Q43+Q25+Q18 -> 3456841
H47: Net Position - beginning | M47: 17716886 | N47: 2034604 | O47: 3828155 | P47: 1065353 | Q47: =SUM(N47:P47) -> 6928112
H49: Prior period adjustments | O49: -3166 | Q49: =SUM(N49:P49) -> -3166
E51: Net Assets- Beginning of Year (restated) | M51: =M47+M49 -> 17716886 | N51: =N47+N49 -> 2034604 | O51: =O47+O49 -> 3824989 | P51: =P47+P49 -> 1065353 | Q51: =Q47+Q49 -> 6924946
E53: Net Assets- End of Year | M53: =M51+M45 -> 19396743 | N53: =N51+N45 -> 5270324 | O53: =O51+O45 -> 3939541 | P53: =P51+P45 -> 1171922 | Q53: =Q51+Q45 -> 10381787

Sheet St. James
J1: St. James County 2013 Statement of Activities
J2: Issued: December 31, 2013
M4: NET (EXPENSE) REVENUE AND CHANGE IN NET ASSETS
J5: PROGRAM REVENUES | M5: PRIMARY GOVERNMENT
A6: FUNCTIONS/PROGRAMS | I6: Expenses | J6: Charges for Services | K6: Operating Grants and Contributions | L6: Capital Grants and Contributions | M6: Governmental Activities | N6: Business-type Activities | O6: Total | P6: Business-type Activities
A7: Primary Government:
B8: Government Activities:
C9: General government | I9: -8236128 | J9: 618451 | K9: 1100449 | M9: =SUM(I9:L9) -> -6517228 | O9: =SUM(M9:N9) -> -6517228
C10: Public safety | I10: -4267863 | J10: 246649 | K10: 11343 | L10: 4298189 | M10: =SUM(I10:L10) -> 288318 | O10: =SUM(M10:N10) -> 288318
C11: Highways and streets | I11: -4986297 | K11: 385456 | L11: 17879 | M11: =SUM(I11:L11) -> -4582962 | O11: =SUM(M11:N11) -> -4582962
C12: Sanitation | I12: -2114685 | J12: 943799 | K12: 38281 | M12: =SUM(I12:L12) -> -1132605 | O12: =SUM(M12:N12) -> -1132605
C13: Public housing | I13: -1520 | M13: =SUM(I13:L13) -> -1520 | O13: =SUM(M13:N13) -> -1520
C14: Public transportation | I14: -1109617 | J14: 80648 | K14: 781583 | M14: =SUM(I14:L14) -> -247386 | O14: =SUM(M14:N14) -> -247386
C15: Health and welfare | I15: -4267848 | K15: 925781 | M15: =SUM(I15:L15) -> -3342067 | O15: =SUM(M15:N15) -> -3342067
C16: Culture and recreation | I16: -2651854 | J16: 34852 | K16: 26234 | M16: =SUM(I16:L16) -> -2590768 | O16: =SUM(M16:N16) -> -2590768
C17: Economic development and assistance | I17: -2531181 | K17: 1445071 | M17: =SUM(I17:L17) -> -1086110 | O17: =SUM(M17:N17) -> -1086110
C18: Interest on long-term debt | I18: -303918 | M18: =SUM(I18:L18) -> -303918 | O18: =SUM(M18:N18) -> -303918
E20: Total Government Activities | I20: =SUM(I9:I18) -> -30470911 | J20: =SUM(J9:J18) -> 1924399 | K20: =SUM(K9:K18) -> 4714198 | L20: =SUM(L9:L18) -> 4316068 | M20: =SUM(M9:M18) -> -19516246 | O20: =SUM(O9:O18) -> -19516246 | P20: =SUM(P9:P18) -> 0
B22: Business-type Activities:
C23: Gas and water | I23: -4651137 | J23: 5371779 | K23: 104990 | L23: 9116 | N23: =SUM(I23:L23) -> 834748 | O23: =SUM(M23:N23) -> 834748
C24: Youth detention | I24: -1162960 | J24: 588071 | K24: 14903 | N24: =SUM(I24:L24) -> -559986 | O24: =SUM(M24:N24) -> -559986
E26: Total Business-type Activities | I26: =SUM(I23:I24) -> -5814097 | J26: =SUM(J23:J24) -> 5959850 | K26: =SUM(K23:K24) -> 119893 | L26: =SUM(L23:L24) -> 9116 | M26: =SUM(M23:M24) -> 0 | N26: =SUM(N23:N24) -> 274762 | O26: =SUM(O23:O24) -> 274762 | P26: =SUM(P17:P24) -> 0
E28: Total primary government | I28: =I26+I20 -> -36285008 | J28: =J26+J20 -> 7884249 | K28: =SUM(K20+K26) -> 4834091 | L28: =SUM(L20+L26) -> 4325184 | M28: =M26+M20 -> -19516246 | N28: =N26+N20 -> 274762 | O28: =O26+O20 -> -19241484 | P28: =SUM(P19:P26) -> 0
A30: Component units:
B31: St. James Parish Hospital | I31: -20763895 | J31: 21287518 | L31: 92155 | P31: =SUM(I31:L31) -> 615778
E33: Total component units | I33: =SUM(I31:I31) -> -20763895 | J33: =SUM(J31:J31) -> 21287518 | K33: =SUM(K31:K31) -> 0 | L33: =SUM(L31:L31) -> 92155 | M33: =SUM(M31:M31) -> 0 | N33: =SUM(N31:N31) -> 0 | O33: =SUM(O31:O31) -> 0 | P33: =SUM(P31:P31) -> 615778
G35: General Revenues:
H36: Taxes:
I37: Property taxes | M37: 16742024 | N37: 535074 | O37: =SUM(M37:N37) -> 17277098 | P37: 2280766
I38: Voluntary payments in lieu of taxes | M38: 90507 | O38: =SUM(M38:N38) -> 90507
I39: Sales and use taxes | M39: 6930580 | O39: =SUM(M39:N39) -> 6930580
I40: Alcoholic beverages | M40: 21255 | O40: =SUM(M40:N40) -> 21255
I41: Franchise fees | M41: 103044 | O41: =SUM(M41:N41) -> 103044
I42: Other | M42: 488466 | O42: =SUM(M42:N42) -> 488466
H43: Fines and forfeits | M43: 179042 | N43: 550 | O43: =SUM(M43:N43) -> 179592
H44: Unrestricted grants and contributions | M44: 449066 | O44: =SUM(M44:N44) -> 449066
H45: Interest on investments | M45: 16005 | N45: 3841 | O45: =SUM(M45:N45) -> 19846 | P45: 80985
H46: Other | M46: 2126963 | O46: =SUM(M46:N46) -> 2126963 | P46: 396639
H47: Contributions | N47: 990000 | O47: =SUM(M47:N47) -> 990000
H48: Gain (loss) on sale of fixed assets | M48: -91862 | O48: =SUM(M48:N48) -> -91862
H49: Transfers | M49: -3772 | N49: 90007 | O49: =SUM(M49:N49) -> 86235
H51: Total General Revenues and Transfers | M51: =SUM(M37:M49) -> 27051318 | N51: =SUM(N37:N49) -> 1619472 | O51: =SUM(O37:O49) -> 28670790 | P51: =SUM(P37:P49) -> 2758390
H53: Change in Net Assets before extraordinary item | M53: =M51+M20 -> 7535072 | N53: =N51+N28 -> 1894234 | O53: =O51+O28 -> 9429306 | P53: =P51+P33 -> 3374168
H55: Extraordinary item - loss on impairment of capital asset | N55: -1839861 | O55: =SUM(M55:N55) -> -1839861
H57: Change in net assets | M57: =M53+M55 -> 7535072 | N57: =N53+N55 -> 54373 | O57: =O53+O55 -> 7589445 | P57: =P53+P55 -> 3374168
H59: Net position - beginning as previously reported | M59: 88699508 | N59: 22345181 | O59: =SUM(M59:N59) -> 111044689 | P59: 21857085
H61: Adjustment for sales tax liability | M61: -418267 | O61: =SUM(M61:N61) -> -418267
H63: Adjustment for implementation of GASB 65 | M63: -115899 | O63: =SUM(M63:N63) -> -115899
E65: Net Assets- Beginning of Year, restated | M65: 88165342 | N65: 22345181 | O65: =SUM(M65:N65) -> 110510523 | P65: 21857085
E67: Net Assets- End of Year | M67: =M65+M57 -> 95700414 | N67: =N65+N57 -> 22399554 | O67: =O65+O57 -> 118099968 | P67: =P65+P57 -> 25231253

Sheet St. John the Baptist
J1: St. John the Baptist County 2013 Statement of Activities
J2: Issued: December 31, 2013
M4: NET (EXPENSE) REVENUE AND CHANGE IN NET ASSETS
J5: PROGRAM REVENUES | M5: PRIMARY GOVERNMENT | P5: Component Units
A6: FUNCTIONS/PROGRAMS | I6: Expenses | J6: Charges for Services | K6: Operating Grants and Contributions | L6: Capital Grants and Contributions | M6: Governmental Activities | N6: Business-type Activities | O6: Total | P6: Library
A7: Primary Government:
B8: Government Activities:
C9: General government | I9: -11787695 | J9: 114470 | K9: 631537 | M9: =SUM(I9:L9) -> -11041688 | O9: =SUM(M9:N9) -> -11041688
C10: Public safety | I10: -7732696 | J10: 1750157 | K10: 200374 | M10: =SUM(I10:L10) -> -5782165 | O10: =SUM(M10:N10) -> -5782165
C11: Public works and transportation | I11: -13105441 | J11: 312206 | K11: 1580125 | M11: =SUM(I11:L11) -> -11213110 | O11: =SUM(M11:N11) -> -11213110
C12: Health and welfare | I12: -1761793 | J12: 482003 | K12: 566548 | M12: =SUM(I12:L12) -> -713242 | O12: =SUM(M12:N12) -> -713242
C13: Economic development | I13: -1268936 | K13: 1395669 | M13: =SUM(I13:L13) -> 126733 | O13: =SUM(M13:N13) -> 126733
C14: Culture and recreation | I14: -1850395 | J14: 141601 | K14: 57379 | M14: =SUM(I14:L14) -> -1651415 | O14: =SUM(M14:N14) -> -1651415
C15: Interest and other charges on long-term debt | I15: -2902003 | M15: =SUM(I15:L15) -> -2902003 | O15: =SUM(M15:N15) -> -2902003
E17: Total Government Activities | I17: =SUM(I9:I15) -> -40408959 | J17: =SUM(J9:J15) -> 2800437 | K17: =SUM(K9:K15) -> 4431632 | L17: =SUM(L9:L15) -> 0 | M17: =SUM(M9:M15) -> -33176890 | O17: =SUM(O9:O15) -> -33176890 | P17: =SUM(P9:P15) -> 0
B19: Business-type Activities:
C20: Solid waste | I20: -3489574 | J20: 3817651 | N20: =SUM(I20:L20) -> 328077 | O20: =SUM(M20:N20) -> 328077
C21: Mosquito | I21: -763696 | J21: 530937 | N21: =SUM(I21:L21) -> -232759 | O21: =SUM(M21:N21) -> -232759
C22: Utilities | I22: -8929638 | J22: 6606629 | L22: 1205171 | N22: =SUM(I22:L22) -> -1117838 | O22: =SUM(M22:N22) -> -1117838
C23: Sewer | I23: -10459148 | J23: 5453223 | N23: =SUM(I23:L23) -> -5005925 | O23: =SUM(M23:N23) -> -5005925
E25: Total Business-type Activities | I25: =SUM(I20:I23) -> -23642056 | J25: =SUM(J20:J23) -> 16408440 | K25: =SUM(K20:K23) -> 0 | L25: =SUM(L20:L23) -> 1205171 | M25: =SUM(M20:M23) -> 0 | N25: =SUM(N20:N23) -> -6028445 | O25: =SUM(O20:O23) -> -6028445 | P25: =SUM(P14:P23) -> 0
E27: Total primary government | I27: =I25+I17 -> -64051015 | J27: =J25+J17 -> 19208877 | K27: =SUM(K17+K25) -> 4431632 | L27: =SUM(L17+L25) -> 1205171 | M27: =M25+M17 -> -33176890 | N27: =N25+N17 -> -6028445 | O27: =O25+O17 -> -39205335 | P27: =SUM(P16:P25) -> 0
A29: Component units:
B30: Library | I30: -3582288 | J30: 50974 | K30: 62009 | P30: =SUM(I30:L30) -> -3469305
E32: Total component units | I32: =SUM(I30:I30) -> -3582288 | J32: =SUM(J30:J30) -> 50974 | K32: =SUM(K30:K30) -> 62009 | L32: =SUM(L30:L30) -> 0 | M32: =SUM(M30:M30) -> 0 | N32: =SUM(N30:N30) -> 0 | O32: =SUM(O30:O30) -> 0 | P32: =SUM(P30:P30) -> -3469305
G34: General Revenues:
H35: Ad valorem | M35: 12559687 | N35: 211838 | O35: =SUM(M35:N35) -> 12771525 | P35: 4539543
H36: Sales taxes | M36: 20891882 | O36: =SUM(M36:N36) -> 20891882
H37: Franchise taxes | M37: 935809 | O37: =SUM(M37:N37) -> 935809
H38: Beer taxes | M38: 47394 | O38: =SUM(M38:N38) -> 47394
H39: Severance taxes | M39: 54423 | O39: =SUM(M39:N39) -> 54423
H40: Video poker taxes | M40: 604691 | O40: =SUM(M40:N40) -> 604691
H41: Occupational licenses | M41: 1228691 | O41: =SUM(M41:N41) -> 1228691
H42: State revenue sharing (unrestricted) | M42: 100771 | O42: =SUM(M42:N42) -> 100771 | P42: 96003
H43: Grants and contributions not restricted | M43: 28113 | N43: 680716 | O43: =SUM(M43:N43) -> 708829
H44: Investment earnings | M44: 239854 | N44: 14617 | O44: =SUM(M44:N44) -> 254471 | P44: 2770
H45: Other general revenues | M45: 646469 | N45: 283386 | O45: =SUM(M45:N45) -> 929855
H46: Transfers | M46: -2107590 | N46: 2107590 | O46: =SUM(M46:N46) -> 0
H48: Total General Revenues and Transfers | M48: =SUM(M35:M46) -> 35230194 | N48: =SUM(N35:N46) -> 3298147 | O48: =SUM(O35:O46) -> 38528341 | P48: =SUM(P35:P46) -> 4638316
H50: Change in Net Assets | M50: =M48+M17 -> 2053304 | N50: =N48+N27 -> -2730298 | O50: =O48+O27 -> -676994 | P50: =P48+P32 -> 1169011
H52: Net assets - beginning of year | M52: 72509109 | N52: 129699910 | O52: =SUM(M52:N52) -> 202209019 | P52: 11097361
H54: Restatement | M54: -555139 | N54: -58129 | O54: =SUM(M54:N54) -> -613268
E56: Net Assets- Beginning of Year, as restated | M56: =M52+M54 -> 71953970 | N56: =N52+N54 -> 129641781 | O56: =O52+O54 -> 201595751 | P56: =P52+P54 -> 11097361
E58: Net Assets- End of Year | M58: =SUM(M50,M56) -> 74007274 | N58: =N56+N50 -> 126911483 | O58: =O56+O50 -> 200918757 | P58: =P56+P50 -> 12266372

Sheet St. Landry
J1: St. Landry County 2013 Statement of Activities
J2: Issued: December 31, 2013
M5: NET (EXPENSE) REVENUE AND CHANGE IN NET ASSETS
J6: PROGRAM REVENUES | M6: PRIMARY GOVERNMENT
A7: FUNCTIONS/PROGRAMS | I7: Expenses | J7: Charges for Services | K7: Operating Grants and Contributions | L7: Capital Grants and Contributions | M7: Governmental Activities | N7: Component Units | O7: Total
A8: Primary Government:
B9: Government Activities:
C10: General government | I10: -4964564 | J10: 826027 | K10: 553768 | M10: =SUM(I10:L10) -> -3584769 | O10: =SUM(M10:N10) -> -3584769
C11: Public safety | I11: -2743464 | J11: 485732 | K11: 58166 | L11: 30598 | M11: =SUM(I11:L11) -> -2168968 | O11: =SUM(M11:N11) -> -2168968
C12: Public works | I12: -9699501 | J12: 68486 | K12: 5108707 | M12: =SUM(I12:L12) -> -4522308 | O12: =SUM(M12:N12) -> -4522308
C13: Health and welfare | I13: -1465377 | J13: 6176 | K13: 107307 | M13: =SUM(I13:L13) -> -1351894 | O13: =SUM(M13:N13) -> -1351894
C14: Interest on long-term debt | I14: -4820 | M14: =SUM(I14:L14) -> -4820 | O14: =SUM(M14:N14) -> -4820
E16: Total Government Activities | I16: =SUM(I10:I14) -> -18877726 | J16: =SUM(J10:J14) -> 1386421 | K16: =SUM(K10:K14) -> 5827948 | L16: =SUM(L10:L14) -> 30598 | M16: =SUM(M10:M14) -> -11632759 | N16: =SUM(N10:N14) -> 0 | O16: =SUM(O10:O14) -> -11632759
A18: Component units:
B19: Tourist commission | I19: -580587 | N19: =SUM(I19:M19) -> -580587 | O19: =N19 -> -580587
B20: Criminal court | I20: -176937 | J20: 186777 | N20: =SUM(I20:L20) -> 9840 | O20: =N20 -> 9840
B21: Workforce investment board | I21: -3080928 | K21: 3061766 | N21: =SUM(I21:L21) -> -19162 | O21: =N21 -> -19162
B22: Ag Arena Authority | I22: -29650 | J22: 10008 | N22: =SUM(I22:L22) -> -19642 | O22: =N22 -> -19642
B23: Registrar of voters | I23: -40953 | N23: =SUM(I23:L23) -> -40953 | O23: =N23 -> -40953
B24: Fire Protection District No. 6 | I24: -232458 | N24: =SUM(I24:L24) -> -232458 | O24: =N24 -> -232458
B25: Historical development commission | I25: -300 | N25: =SUM(I25:L25) -> -300 | O25: =N25 -> -300
E27: Total component units | I27: =SUM(I19:I25) -> -4141813 | J27: =SUM(J19:J25) -> 196785 | K27: =SUM(K19:K25) -> 3061766 | L27: =SUM(L19:L25) -> 0 | M27: =SUM(M19:M25) -> 0 | N27: =SUM(N19:N25) -> -883262 | O27: =SUM(O19:O25) -> -883262
G29: General Revenues:
H30: Taxes:
I31: Property taxes - general | M31: 4353998 | N31: 352047 | O31: =SUM(M31:N31) -> 4706045
I32: Hotel/motel tax | M32: 495177 | N32: 546650 | O32: =SUM(M32:N32) -> 1041827
I33: 4% slot tax | M33: 1645804 | N33: 44121 | O33: =SUM(M33:N33) -> 1689925
I34: Video poker | M34: 511095 | O34: =SUM(M34:N34) -> 511095
I35: Severance tax | M35: 834140 | O35: =SUM(M35:N35) -> 834140
I36: Insurance premium tax | M36: 294601 | O36: =SUM(M36:N36) -> 294601
I37: Alcohol tax | M37: 14908 | O37: =SUM(M37:N37) -> 14908
H38: Royalties, commissions and fees | M38: 286970 | O38: =SUM(M38:N38) -> 286970
H39: 2% fire insurance rebate | M39: 335780 | O39: =SUM(M39:N39) -> 335780
H40: Payments in lieu of taxes | M40: 2946 | O40: =SUM(M40:N40) -> 2946
H41: Grants and contributions not restricted to specific programs:
I42: State sources | M42: 373490 | N42: 37322 | O42: =SUM(M42:N42) -> 410812
H43: Interest and investment earnings | M43: 5223 | N43: 1779 | O43: =SUM(M43:N43) -> 7002
H44: Special item - sales tax allocation (solid waste) | M44: 231250 | O44: =SUM(M44:N44) -> 231250
H45: Special item - gain on sale of equipment | M45: 6444 | O45: =SUM(M45:N45) -> 6444
H46: Miscellaneous | M46: 541528 | N46: 18929 | O46: =SUM(M46:N46) -> 560457
H48: Total General Revenues and transfers | M48: =SUM(M31:M46) -> 9933354 | N48: =SUM(N31:N46) -> 1000848 | O48: =SUM(O31:O46) -> 10934202
H50: Change in Net Assets | M50: =M48+M16 -> -1699405 | N50: =N48+N27 -> 117586 | O50: =O48+O27+O16 -> -1581819
E52: Net Assets- Beginning of Year | M52: 15975749 | N52: 3152517 | O52: =SUM(M52:N52) -> 19128266
E54: Net Assets- End of Year | M54: =M52+M50 -> 14276344 | N54: =N52+N50 -> 3270103 | O54: =O52+O50 -> 17546447

Sheet St. Martin
J1: St. Martin Parish 2013 Statement of Activities
J2: Issued: December 31, 2013
J4: PROGRAM REVENUES | M4: Net Revenues (Expenses
A5: FUNCTIONS/PROGRAMS | I5: Expenses | J5: Charges for Services | K5: Operating Grants and Contributions | L5: Capital Grants and Contributions | M5: Governmental Activities | N5: Business-type Activities | O5: Total
A6: Primary Government:
B7: Government Activities:
C8: General government | I8: -5962814 | J8: 961314 | K8: 767146 | M8: =SUM(I8:L8) -> -4234354 | O8: =SUM(M8:N8) -> -4234354
C9: Public safety | I9: -2472980 | J9: 580 | M9: =SUM(I9:L9) -> -2472400 | O9: =SUM(M9:N9) -> -2472400
C10: Public works | I10: -4591193 | J10: 16168 | K10: 124241 | L10: 3302652 | M10: =SUM(I10:L10) -> -1148132 | O10: =SUM(M10:N10) -> -1148132
C11: Economic development | I11: -1340504 | J11: 104124 | K11: 155670 | M11: =SUM(I11:L11) -> -1080710 | O11: =SUM(M11:N11) -> -1080710
C12: Health and welfare | I12: -3766875 | J12: 29108 | K12: 1535559 | M12: =SUM(I12:L12) -> -2202208 | O12: =SUM(M12:N12) -> -2202208
C13: Culture and recreation | I13: -613652 | J13: 165039 | K13: 30525 | M13: =SUM(I13:L13) -> -418088 | O13: =SUM(M13:N13) -> -418088
C14: Interest and fiscal charges on long-term debt | I14: -833413 | M14: =SUM(I14:L14) -> -833413 | O14: =SUM(M14:N14) -> -833413
E16: Total Government Activities | I16: =SUM(I8:I14) -> -19581431 | J16: =SUM(J8:J14) -> 1276333 | K16: =SUM(K8:K14) -> 2613141 | L16: =SUM(L8:L14) -> 3302652 | M16: =SUM(M8:M14) -> -12389305 | O16: =SUM(O8:O14) -> -12389305
B18: Business-type Activities:
C19: Expenses | I19: -1618050 | J19: 1321592 | N19: =SUM(I19:L19) -> -296458 | O19: =SUM(M19:N19) -> -296458
E21: Total business-type activities | I21: =I19 -> -1618050 | J21: =J19 -> 1321592 | K21: =K19 -> 0 | L21: =L19 -> 0 | M21: 0 | N21: =SUM(N19:N19) -> -296458 | O21: =SUM(O19:O19) -> -296458
E23: Total primary government | I23: =I21+I16 -> -21199481 | J23: =J21+J16 -> 2597925 | K23: =K21+K16 -> 2613141 | L23: =L21+L16 -> 3302652 | M23: =M21+M16 -> -12389305 | N23: =N21+N16 -> -296458 | O23: =O21+O16 -> -12685763
G25: General Revenues:
H26: Taxes:
I27: Property taxes | M27: 10198768 | O27: =SUM(M27:N27) -> 10198768
I28: Sales taxes | M28: 4905730 | O28: =SUM(M28:N28) -> 4905730
I29: Severance taxes | M29: 993204 | O29: =SUM(M29:N29) -> 993204
H30: Transportation funds | M30: 604073 | O30: =SUM(M30:N30) -> 604073
H31: Video poker fees | M31: 1367976 | O31: =SUM(M31:N31) -> 1367976
H32: State revenue sharing | M32: 432477 | O32: =SUM(M32:N32) -> 432477
H33: Fire insurance rebate | M33: 212184 | O33: =SUM(M33:N33) -> 212184
H34: Licenses and permits | M34: 1324455 | O34: =SUM(M34:N34) -> 1324455
H35: Investment income | M35: 116423 | O35: =SUM(M35:N35) -> 116423
H36: Gain on sale of asset | M36: 80000 | O36: =SUM(M36:N36) -> 80000
H37: Miscellaneous | M37: 568451 | O37: =SUM(M37:N37) -> 568451
H38: Transfers-other govts. | M38: -1935296 | O38: =SUM(M38:N38) -> -1935296
H39: Transfers-internal | M39: -293760 | N39: 293760 | O39: =SUM(M39:N39) -> 0
H41: Total general revenue and transfers | M41: =SUM(M25:M39) -> 18574685 | N41: =SUM(N25:N39) -> 293760 | O41: =SUM(O27:O39) -> 18868445
H43: Change in Net Position | M43: =M41+M23 -> 6185380 | N43: =N41+N23 -> -2698 | O43: =O41+O23 -> 6182682
E45: Net Position, beginning | M45: 66644072 | N45: -45568 | O45: =SUM(M45:N45) -> 66598504
E47: Net Assets- End of Year | M47: =M45+M43 -> 72829452 | N47: =N45+N43 -> -48266 | O47: =O45+O43 -> 72781186

Sheet St. Mary
J1: St. Mary County 2013 Statement of Activities
J2: Issued: December 31, 2013
M4: NET (EXPENSE) REVENUE AND CHANGE IN NET ASSETS
J5: PROGRAM REVENUES | M5: PRIMARY GOVERNMENT
A6: FUNCTIONS/PROGRAMS | I6: Expenses | J6: Charges for Services | K6: Operating Grants and Contributions | L6: Capital Grants and Contributions | M6: Governmental Activities | N6: Business-type Activities | O6: Total
A7: Primary Government:
B8: Government Activities:
C9: General government | I9: -6781408 | J9: 1388664 | K9: 1118695 | M9: =SUM(I9:L9) -> -4274049 | O9: =SUM(M9:N9) -> -4274049
C10: Public safety | I10: -5130578 | J10: 8565 | K10: 1414535 | L10: 52000 | M10: =SUM(I10:L10) -> -3655478 | O10: =SUM(M10:N10) -> -3655478
C11: Public works | I11: -9411807 | K11: 2111259 | L11: 1850660 | M11: =SUM(I11:L11) -> -5449888 | O11: =SUM(M11:N11) -> -5449888
C12: Sanitation | I12: -2321650 | J12: 1380548 | K12: 149538 | M12: =SUM(I12:L12) -> -791564 | O12: =SUM(M12:N12) -> -791564
C13: Culture and recreation | I13: -2520440 | J13: 50852 | K13: 103344 | L13: 379997 | M13: =SUM(I13:L13) -> -1986247 | O13: =SUM(M13:N13) -> -1986247
C14: Health and welfare | I14: -5540942 | J14: 331474 | K14: 3999032 | M14: =SUM(I14:L14) -> -1210436 | O14: =SUM(M14:N14) -> -1210436
C15: Urban redevelopment & housing | I15: -459802 | K15: 345555 | L15: 102445 | M15: =SUM(I15:L15) -> -11802 | O15: =SUM(M15:N15) -> -11802
C16: Economic development and assistance | I16: -231272 | M16: =SUM(I16:L16) -> -231272 | O16: =SUM(M16:N16) -> -231272
C17: Interest on long-term debt | I17: -857912 | M17: =SUM(I17:L17) -> -857912 | O17: =SUM(M17:N17) -> -857912
C18: Fees on long-term debt | I18: -33662 | M18: =SUM(I18:L18) -> -33662 | O18: =SUM(M18:N18) -> -33662
E20: Total Government Activities | I20: =SUM(I9:I18) -> -33289473 | J20: =SUM(J9:J18) -> 3160103 | K20: =SUM(K9:K18) -> 9241958 | L20: =SUM(L9:L18) -> 2385102 | M20: =SUM(M9:M18) -> -18502310 | O20: =SUM(O9:O18) -> -18502310
B22: Business-type Activities:
C23: Solid waste landfill | I23: -4573742 | J23: 3977579 | N23: =SUM(I23:L23) -> -596163 | O23: =SUM(M23:N23) -> -596163
C24: Small animal control | I24: -309181 | J24: 144678 | N24: =SUM(I24:L24) -> -164503 | O24: =SUM(M24:N24) -> -164503
C25: Kemper Williams Park | I25: -672266 | J25: 165643 | K25: 33578 | N25: =SUM(I25:L25) -> -473045 | O25: =SUM(M25:N25) -> -473045
E27: Total Business-type Activities | I27: =SUM(I23:I25) -> -5555189 | J27: =SUM(J23:J25) -> 4287900 | K27: =SUM(K23:K25) -> 33578 | L27: =SUM(L23:L25) -> 0 | M27: =SUM(M23:M25) -> 0 | N27: =SUM(N23:N25) -> -1233711 | O27: =SUM(O23:O25) -> -1233711
E29: Total primary government | I29: =I27+I20 -> -38844662 | J29: =J27+J20 -> 7448003 | K29: =SUM(K20+K27) -> 9275536 | L29: =SUM(L20+L27) -> 2385102 | M29: =M27+M20 -> -18502310 | N29: =N27+N20 -> -1233711 | O29: =O27+O20 -> -19736021
G31: General Revenues:
H32: Taxes:
I33: Sales and use | M33: 7601464 | O33: =SUM(M33:N33) -> 7601464
I34: Ad valorem taxes levied for general purposes | M34: 2928208 | O34: =SUM(M34:N34) -> 2928208
I35: Ad valorem taxes levied for debt service | M35: 516743 | O35: =SUM(M35:N35) -> 516743
I36: Severance taxes | M36: 971266 | O36: =SUM(M36:N36) -> 971266
I37: Other taxes, penalties, and interest, etc. | M37: 67243 | O37: =SUM(M37:N37) -> 67243
H38: Royalty road funds | M38: 8859854 | O38: =SUM(M38:N38) -> 8859854
H39: State shared revenue | M39: 551451 | O39: =SUM(M39:N39) -> 551451
H40: Investment earnings and interest | M40: 123005 | N40: 148 | O40: =SUM(M40:N40) -> 123153
H41: Proceeds from loss/damage of assets | M41: 51313 | O41: =SUM(M41:N41) -> 51313
H42: Gain on sale of equipment | N42: 17788 | O42: =SUM(M42:N42) -> 17788
H43: Transfers:
I44: Operating | M44: -2390500 | N44: 2390500 | O44: =SUM(M44:N44) -> 0
H46: Total General Revenues, special items, and Transfers | M46: =SUM(M33:M44) -> 19280047 | N46: =SUM(N33:N44) -> 2408436 | O46: =SUM(O33:O44) -> 21688483
H48: Change in Net Assets | M48: =M46+M20 -> 777737 | N48: =N46+N29 -> 1174725 | O48: =O46+O29 -> 1952462
H50: Net position - beginning of year (as previously stated) | M50: 98925278 | N50: 15869458 | O50: =SUM(M50:N50) -> 114794736
H52: Prior period adjustments | M52: 329776 | N52: -193058 | O52: 136718
E54: Net Assets- Beginning of Year (as adjusted) | M54: 99255054 | N54: 15676400 | O54: =SUM(M54:N54) -> 114931454
E56: Net Assets- End of Year | M56: =SUM(M48,M54) -> 100032791 | N56: =N54+N48 -> 16851125 | O56: =O54+O48 -> 116883916

Sheet St. Tammany
J1: St. Tammany County 2013 Statement of Activities
J2: Issued: December 31, 2013
M4: NET (EXPENSE) REVENUE AND CHANGE IN NET ASSETS
J5: PROGRAM REVENUES | M5: PRIMARY GOVERNMENT
A6: FUNCTIONS/PROGRAMS | I6: Expenses | J6: Charges for Services | K6: Operating Grants and Contributions | L6: Capital Grants and Contributions | M6: Governmental Activities | N6: Business-type Activities | O6: Total | P6: Component Units
A7: Primary Government:
B8: Government Activities:
C9: General government | I9: -22890790 | J9: 7869235 | K9: 346857 | L9: 1278356 | M9: =SUM(I9:L9) -> -13396342 | O9: =SUM(M9:N9) -> -13396342
C10: Public safety | I10: -16260579 | J10: 2075778 | K10: 7937034 | L10: 1261553 | M10: =SUM(I10:L10) -> -4986214 | O10: =SUM(M10:N10) -> -4986214
C11: Highways and streets | I11: -36628105 | J11: 2657351 | K11: 4139595 | L11: 4570473 | M11: =SUM(I11:L11) -> -25260686 | O11: =SUM(M11:N11) -> -25260686
C12: Sanitation | I12: -1053250 | J12: 1390199 | K12: 29715 | L12: 100702 | M12: =SUM(I12:L12) -> 467366 | O12: =SUM(M12:N12) -> 467366
C13: Health and welfare | I13: -10042280 | J13: 352946 | K13: 3046632 | L13: 8000 | M13: =SUM(I13:L13) -> -6634702 | O13: =SUM(M13:N13) -> -6634702
C14: Culture and recreation | I14: -10339088 | J14: 281 | K14: 337565 | L14: 5553 | M14: =SUM(I14:L14) -> -9995689 | O14: =SUM(M14:N14) -> -9995689
C15: Economic development | I15: -952898 | K15: 1386279 | L15: 149841 | M15: =SUM(I15:L15) -> 583222 | O15: =SUM(M15:N15) -> 583222
C16: Interest on long-term debt | I16: -4790681 | M16: =SUM(I16:L16) -> -4790681 | O16: =SUM(M16:N16) -> -4790681
E18: Total Government Activities | I18: =SUM(I9:I16) -> -102957671 | J18: =SUM(J9:J16) -> 14345790 | K18: =SUM(K9:K16) -> 17223677 | L18: =SUM(L9:L16) -> 7374478 | M18: =SUM(M9:M16) -> -64013726 | O18: =SUM(O9:O16) -> -64013726 | P18: =SUM(P9:P16) -> 0
B20: Business-type Activities:
C21: Water/Sewer | I21: -11146235 | J21: 11207575 | L21: 50800 | N21: =SUM(I21:L21) -> 112140 | O21: =SUM(M21:N21) -> 112140
E23: Total Business-type Activities | I23: =SUM(I21:I21) -> -11146235 | J23: =SUM(J21:J21) -> 11207575 | K23: =SUM(K21:K21) -> 0 | L23: =SUM(L21:L21) -> 50800 | M23: =SUM(M21:M21) -> 0 | N23: =SUM(N21:N21) -> 112140 | O23: =SUM(O21:O21) -> 112140 | P23: =SUM(P21:P21) -> 0
E25: Total primary government | I25: =I23+I18 -> -114103906 | J25: =J23+J18 -> 25553365 | K25: =SUM(K18+K23) -> 17223677 | L25: =SUM(L18+L23) -> 7425278 | M25: =M23+M18 -> -64013726 | N25: =N23+N18 -> 112140 | O25: =O23+O18 -> -63901586 | P25: =P23+P18 -> 0
A27: Component units:
B28: Total component units | I28: -78836568 | J28: 6591546 | K28: 353647 | L28: 223434 | P28: =SUM(I28:L28) -> -71667941
E30: Total component units | I30: =SUM(I28:I28) -> -78836568 | J30: =SUM(J28:J28) -> 6591546 | K30: =SUM(K28:K28) -> 353647 | L30: =SUM(L28:L28) -> 223434 | M30: =SUM(M28:M28) -> 0 | N30: =SUM(N28:N28) -> 0 | O30: =SUM(O28:O28) -> 0 | P30: =SUM(P28:P28) -> -71667941
G32: General Revenues:
I33: Property taxes, general (Ad valorem, parcel fees, etc.) | M33: 4335248 | O33: =SUM(M33:N33) -> 4335248
I34: Property taxes, special purpose (Ad valorem, parcel fees, etc.) | M34: 24226067 | O34: =SUM(M34:N34) -> 24226067 | P34: 59328624
I35: Sales and use taxes | M35: 61868200 | O35: =SUM(M35:N35) -> 61868200
I36: Franchise taxes | M36: 2095607 | O36: =SUM(M36:N36) -> 2095607
I37: Hotel/Motel tax | M37: 546352 | O37: =SUM(M37:N37) -> 546352 | P37: 375131
I38: Timber severance tax | M38: 65772 | O38: =SUM(M38:N38) -> 65772
I39: Mineral severance tax | M39: 12932 | O39: =SUM(M39:N39) -> 12932
I40: Alcohol tax | M40: 58815 | O40: =SUM(M40:N40) -> 58815
I41: Cigarette paper tax | M41: 10234 | O41: =SUM(M41:N41) -> 10234
I42: Gaming revenue tax | M42: 199057 | O42: =SUM(M42:N42) -> 199057
I43: Telephone service tax
I44: Fire insurance tax | O44: =SUM(M44:N44) -> 0 | P44: 911746
I45: State revenue sharing (unrestricted) | M45: 280397 | O45: =SUM(M45:N45) -> 280397 | P45: 1369732
I46: Federal payment in lieu of ad valorem | M46: 30493 | O46: =SUM(M46:N46) -> 30493
I47: Investment earnings | M47: -1178328 | N47: -58711 | O47: =SUM(M47:N47) -> -1237039 | P47: 208689
I48: Sale of revocated property | M48: 11400 | O48: =SUM(M48:N48) -> 11400
I49: GNOE excess revenue | M49: 50000 | O49: =SUM(M49:N49) -> 50000
I50: Grants and contributions not restricted to specific programs | O50: =SUM(M50:N50) -> 0 | P50: 9675914
I51: Other general revenues | O51: =SUM(M51:N51) -> 0 | P51: 997660
H52: Extraordinary item - CDL forgiveness | M52: 14454779 | O52: =SUM(M52:N52) -> 14454779
H53: Transfers | M53: 327811 | N53: -327811 | O53: =SUM(M53:N53) -> 0
H55: Total General Revenues and Transfers | M55: =SUM(M33:M53) -> 107394836 | N55: =SUM(N33:N53) -> -386522 | O55: =SUM(O33:O53) -> 107008314 | P55: =SUM(P33:P53) -> 72867496
H57: Change in Net Assets | M57: =M55+M18 -> 43381110 | N57: =N55+N25 -> -274382 | O57: =O55+O25 -> 43106728 | P57: =P55+P30 -> 1199555
E59: Net Assets- Beginning | M59: 473392330 | N59: 11837156 | O59: =SUM(M59:N59) -> 485229486 | P59: 172916179
E61: Net Assets- Ending | M61: =SUM(M57,M59) -> 516773440 | N61: =N59+N57 -> 11562774 | O61: =O59+O57 -> 528336214 | P61: =P59+P57 -> 174115734

Sheet Tangipahoa
J1: Tangipahoa Parish 2013 Statement of Activities
J2: Issued: December 31, 2013
J4: PROGRAM REVENUES | M4: Net Revenues (Expenses) Revenues and Changes in Net Position
A5: FUNCTIONS/PROGRAMS | I5: Expenses | J5: Charges for Services | K5: Operating Grants and Contributions | L5: Capital Grants and Contributions | M5: Governmental Activities | N5: Component Units
A6: Primary Government:
B7: Government Activities:
C8: General government | I8: -6711679 | J8: 3153820 | K8: 388019 | L8: 159652 | M8: =SUM(I8:L8) -> -3010188
C9: Culture and recreation | I9: -4269662 | J9: 134393 | K9: 56436 | M9: =SUM(I9:L9) -> -4078833
C10: Public safety | I10: -3515241 | J10: 944615 | L10: 4497065 | M10: =SUM(I10:L10) -> 1926439
C11: Public works | I11: -23111916 | J11: 3653212 | K11: 1194449 | L11: 3643373 | M11: =SUM(I11:L11) -> -14620882
C12: Health and welfare | I12: -295220 | J12: 216401 | K12: 2507043 | M12: =SUM(I12:L12) -> 2428224
C13: Interest on long-term debt | I13: -58171 | M13: =SUM(I13:L13) -> -58171
E15: Total Government Activities | I15: =SUM(I8:I13) -> -37961889 | J15: =SUM(J8:J13) -> 8102441 | K15: =SUM(K8:K13) -> 4145947 | L15: =SUM(L8:L13) -> 8300090 | M15: =SUM(M8:M13) -> -17413411
B17: Component Units:
C18: Fire protection services | I18: -5461956 | J18: 242696 | K18: 285697 | N18: =SUM(I18:L18) -> -4933563
E20: Total component units | I20: =I18 -> -5461956 | J20: =J18 -> 242696 | K20: =K18 -> 285697 | L20: =L18 -> 0 | M20: 0 | N20: =SUM(N18:N18) -> -4933563
G22: General Revenues:
H23: Taxes:
I24: Sales taxes | M24: 17671536
I25: Ad valorem taxes | M25: 6313647 | N25: 4732967
I26: Franchise taxes | M26: 626483
I27: Severance taxes | M27: 214153
I28: Alcoholic beverage taxes | M28: 39173
H29: Occupational licenses | M29: 701002
H30: State revenue sharing | M30: 482207 | N30: 463904
H31: 2% Fire insurance rebate | N31: 315915
H32: Donations | M32: 13043
H33: Miscellaneous | M33: 340303 | N33: 155315
H34: Investment earnings | M34: 85505 | N34: 48312
H35: Gain from disposition of capital assets | M35: 17720
H36: Transfer and contributions | M36: 1502622
H38: Total general revenues, transfers, and contributions | M38: =SUM(M22:M36) -> 28007394 | N38: =SUM(N22:N36) -> 5716413
H40: Change in Net Position | M40: =M38+M15 -> 10593983 | N40: =N38+N20 -> 782850
E42: Net Position, beginning (as restated) | M42: 180535135 | N42: 18239099
E44: Net Assets- End of Year | M44: =M42+M40 -> 191129118 | N44: =N42+N40 -> 19021949

Sheet Tensas
J1: Tensas Parish 2013 Statement of Activities
J2: Issued: December 31, 2013
J5: PROGRAM REVENUES | M5: NET (EXPENSE) REVENUE AND CHANGES IN NET ASSETS
A6: FUNCTIONS/PROGRAMS | I6: Expenses | J6: Charges for Services | K6: Operating Grants and Contributions | L6: Capital Grants and Contributions | M6: Governmental Activities
A7: Governmental activities:
C8: General government
D9: Legislative | I9: -175453 | M9: =SUM(I9:L9) -> -175453
D10: Judicial | I10: -383006 | M10: =SUM(I10:L10) -> -383006
D11: Elections | I11: -31365 | M11: =SUM(I11:L11) -> -31365
D12: Finance and administrative | I12: -458456 | M12: =SUM(I12:L12) -> -458456
D13: Other general adminstrative | I13: -522991 | M13: =SUM(I13:L13) -> -522991
C14: Public safety | I14: -377338 | J14: 227193 | L14: 673141 | M14: =SUM(I14:L14) -> 522996
C15: Public works | I15: -1586730 | J15: 104725 | M15: =SUM(I15:L15) -> -1482005
C16: Health and welfare | I16: -571876 | K16: 20000 | M16: =SUM(I16:L16) -> -551876
C17: Culture and recreation | I17: -298903 | M17: =SUM(I17:L17) -> -298903
C18: Economic development | I18: -246621 | J18: 2347 | M18: =SUM(I18:L18) -> -244274
C19: Interest on long-term debt | I19: -57351 | M19: =SUM(I19:L19) -> -57351
E21: Total Government Activities | I21: =SUM(I9:I19) -> -4710090 | J21: =SUM(J9:J19) -> 334265 | K21: =SUM(K9:K19) -> 20000 | L21: =SUM(L9:L19) -> 673141 | M21: =SUM(M9:M19) -> -3682684
G23: General Revenues:
H24: Taxes:
I25: Ad valorem | M25: 1435114
I26: Sales | M26: 1966008
I27: Other taxes | M27: 292874
H28: Licenses and permits | M28: 60592
H29: State funds:
I30: Parish transportation | M30: 93500
I31: State revenue sharing | M31: 41796
I32: Fire insurance rebates | M32: 20445
H33: Investment income | M33: 12352
H34: Other revenues | M34: 257556
H36: Total General Revenues and Special Items | M36: =SUM(M25:M34) -> 4180237
H38: Change in Net position | M38: =M36+M21 -> 497553
E40: Net position- beginning of year | M40: 10615368
E42: Net position- end of year | M42: =M40+M38 -> 11112921

Sheet Terrebonne
J1: Terrebonne County 2013 Statement of Activities
J2: Issued: December 31, 2013
M4: NET (EXPENSE) REVENUE AND CHANGE IN NET ASSETS
J5: PROGRAM REVENUES | M5: PRIMARY GOVERNMENT
A6: FUNCTIONS/PROGRAMS | I6: Expenses | J6: Charges for Services | K6: Operating Grants and Contributions | L6: Capital Grants and Contributions | M6: Governmental Activities | N6: Business-type Activities | O6: Total | P6: Component Units
A7: Primary Government:
B8: Government Activities:
C9: General government | I9: -23040130 | J9: 11055966 | K9: 1128605 | M9: =SUM(I9:L9) -> -10855559 | O9: =SUM(M9:N9) -> -10855559
C10: Public safety | I10: -38431578 | J10: 2291841 | K10: 4038506 | L10: 12267 | M10: =SUM(I10:L10) -> -32088964 | O10: =SUM(M10:N10) -> -32088964
C11: Streets and drainage | I11: -28105188 | J11: 59576 | K11: 866304 | L11: 10933139 | M11: =SUM(I11:L11) -> -16246169 | O11: =SUM(M11:N11) -> -16246169
C12: Health and welfare | I12: -12532038 | K12: 5483376 | M12: =SUM(I12:L12) -> -7048662 | O12: =SUM(M12:N12) -> -7048662
C13: Culture and recreation | I13: -4137673 | J13: 95522 | K13: 1493567 | L13: 6281 | M13: =SUM(I13:L13) -> -2542303 | O13: =SUM(M13:N13) -> -2542303
C14: Education | I14: -95407 | M14: =SUM(I14:L14) -> -95407 | O14: =SUM(M14:N14) -> -95407
C15: Urban redevelopment and housing | I15: -2823848 | K15: 2893004 | M15: =SUM(I15:L15) -> 69156 | O15: =SUM(M15:N15) -> 69156
C16: Economic development and assistance | I16: -12430728 | K16: 10885733 | M16: =SUM(I16:L16) -> -1544995 | O16: =SUM(M16:N16) -> -1544995
C17: Conservation and development | I17: -7264312 | L17: 7160614 | M17: =SUM(I17:L17) -> -103698 | O17: =SUM(M17:N17) -> -103698
C18: Interest on long-term debt | I18: -4996850 | M18: =SUM(I18:L18) -> -4996850 | O18: =SUM(M18:N18) -> -4996850
E20: Total Government Activities | I20: =SUM(I9:I18) -> -133857752 | J20: =SUM(J9:J18) -> 13502905 | K20: =SUM(K9:K18) -> 26789095 | L20: =SUM(L9:L18) -> 18112301 | M20: =SUM(M9:M18) -> -75453451 | O20: =SUM(O9:O18) -> -75453451 | P20: =SUM(P9:P18) -> 0
B22: Business-type Activities:
C23: Electric and gas | I23: -36040328 | J23: 41548905 | N23: =SUM(I23:L23) -> 5508577 | O23: =SUM(M23:N23) -> 5508577
C24: Sewerage | I24: -9117703 | J24: 8080542 | K24: 3326 | L24: 66841 | N24: =SUM(I24:L24) -> -966994 | O24: =SUM(M24:N24) -> -966994
C25: Sanitation | I25: -13052212 | J25: 8027436 | K25: 318187 | N25: =SUM(I25:L25) -> -4706589 | O25: =SUM(M25:N25) -> -4706589
C26: Civic center | I26: -2297804 | J26: 571530 | N26: =SUM(I26:L26) -> -1726274 | O26: =SUM(M26:N26) -> -1726274
E28: Total Business-type Activities | I28: =SUM(I23:I26) -> -60508047 | J28: =SUM(J23:J26) -> 58228413 | K28: =SUM(K23:K26) -> 321513 | L28: =SUM(L23:L26) -> 66841 | M28: =SUM(M23:M26) -> 0 | N28: =SUM(N23:N26) -> -1891280 | O28: =SUM(O23:O26) -> -1891280 | P28: =SUM(P23:P26) -> 0
E30: Total primary government | I30: =I28+I20 -> -194365799 | J30: =J28+J20 -> 71731318 | K30: =SUM(K20+K28) -> 27110608 | L30: =SUM(L20+L28) -> 18179142 | M30: =M28+M20 -> -75453451 | N30: =N28+N20 -> -1891280 | O30: =O28+O20 -> -77344731 | P30: =P28+P20 -> 0
A32: Component units:
B33: General government | I33: -3220912 | J33: 1249242 | K33: 247434 | P33: =SUM(I33:L33) -> -1724236
B34: Judicial services | I34: -13179341 | J34: 8480376 | K34: 3690342 | P34: =SUM(I34:L34) -> -1008623
B35: Public safety | I35: -23528564 | J35: 1819552 | K35: 1699228 | L35: 23052874 | P35: =SUM(I35:L35) -> 3043090
B36: Health and welfare services | I36: -189283046 | J36: 182228481 | K36: 1312028 | L36: 1028647 | P36: =SUM(I36:L36) -> -4713890
B37: Culture and recreation | I37: -12632340 | J37: 678592 | K37: 585166 | L37: 12750 | P37: =SUM(I37:L37) -> -11355832
B38: Economic development and assistance | I38: -7559305 | J38: 690423 | K38: 2677202 | L38: 10297397 | P38: =SUM(I38:L38) -> 6105717
B39: Utilities | I39: -14824841 | J39: 16066542 | L39: 892900 | P39: =SUM(I39:L39) -> 2134601
E41: Total component units | I41: =SUM(I33:I39) -> -264228349 | J41: =SUM(J33:J39) -> 211213208 | K41: =SUM(K33:K39) -> 10211400 | L41: =SUM(L33:L39) -> 35284568 | M41: =SUM(M33:M39) -> 0 | N41: =SUM(N33:N39) -> 0 | O41: =SUM(O33:O39) -> 0 | P41: =SUM(P33:P39) -> -7519173
G43: General Revenues:
H44: Taxes:
I45: Property | M45: 26473371 | N45: 9306627 | O45: =SUM(M45:N45) -> 35779998 | P45: 39000364
I46: Sales and use | M46: 43251970 | O46: =SUM(M46:N46) -> 43251970 | P46: 6489521
I47: Franchise | M47: 1469029 | O47: =SUM(M47:N47) -> 1469029
I48: Occupancy | N48: 319165 | O48: =SUM(M48:N48) -> 319165 | P48: 1634583
H49: Grants and contributions not restricted to specific programs | M49: 9964976 | O49: =SUM(M49:N49) -> 9964976 | P49: 7596899
H50: Unrestricted investment earnings | M50: -524487 | N50: -576549 | O50: =SUM(M50:N50) -> -1101036 | P50: 3793202
H51: Miscellaneous | M51: 644340 | O51: =SUM(M51:N51) -> 644340 | P51: 578607
H52: Transfers | M52: 3456622 | N52: -3456622 | O52: =SUM(M52:N52) -> 0
H54: Total General Revenues and Transfers | M54: =SUM(M45:M52) -> 84735821 | N54: =SUM(N45:N52) -> 5592621 | O54: =SUM(O45:O52) -> 90328442 | P54: =SUM(P45:P52) -> 59093176
H56: Change in Net Assets | M56: 9282370 | N56: 3701341 | O56: =SUM(M56:N56) -> 12983711 | P56: =P54+P41 -> 51574003
E58: Net Assets- Beginning | M58: 307085428 | N58: 180158167 | O58: =SUM(M58:N58) -> 487243595 | P58: 771916175
E60: Net Assets- Ending | M60: =SUM(M56,M58) -> 316367798 | N60: =N58+N56 -> 183859508 | O60: =O58+O56 -> 500227306 | P60: =P58+P56 -> 823490178

Sheet Union
J1: Union County 2013 Statement of Activities
J2: Issued: December 31, 2013
J5: PROGRAM REVENUES | M5: PRIMARY GOVERNMENT
A6: FUNCTIONS/PROGRAMS | I6: Expenses | J6: Charges for Services | K6: Operating Grants and Contributions | L6: Capital Grants and Contributions | M6: NET (EXPENSE) REVENUE AND CHANGE IN NET ASSETS
A7: Primary Government:
B8: Government Activities:
C9: General government | I9: -1352780 | J9: 168966 | K9: 47978 | M9: =SUM(I9:L9) -> -1135836
C10: Public safety | I10: -4089011 | J10: 2771319 | K10: 198925 | M10: =SUM(I10:L10) -> -1118767
C11: Public works | I11: -4696057 | J11: 1361595 | K11: 614095 | M11: =SUM(I11:L11) -> -2720367
C12: Health and welfare | I12: -1860674 | K12: 1480318 | L12: 40868 | M12: =SUM(I12:L12) -> -339488
C13: Culture and recreation | I13: -437844 | J13: 10557 | K13: 54150 | M13: =SUM(I13:L13) -> -373137
C14: Economic development and assistance | I14: -45444 | M14: =SUM(I14:L14) -> -45444
C15: Transportation | I15: -79300 | J15: 590 | L15: 1129047 | M15: =SUM(I15:L15) -> 1050337
C16: Interest expense | I16: -26344 | M16: =SUM(I16:L16) -> -26344
C17: OPEB obligation | I17: -157611 | M17: =SUM(I17:L17) -> -157611
E19: Total Government Activities | I19: =SUM(I9:I17) -> -12745065 | J19: =SUM(J9:J17) -> 4313027 | K19: =SUM(K9:K17) -> 2395466 | L19: =SUM(L9:L17) -> 1169915 | M19: =SUM(M9:M17) -> -4866657
G21: General Revenues:
H22: Property taxes levied for:
I23: General purposes | M23: 693298
I24: Public works | M24: 1766312
I25: Health and welfare | M25: 266208
I26: Culture and recreation | M26: 532246
H27: Sales and use taxes levied for public works | M27: 2460071
H28: Other taxes, penalties and interest | M28: 35475
H29: Grants and contributions not restricted to specific programs | M29: 818830
H30: Unrestricted investment earnings | M30: 6274
H31: Restricted investment earnings | M31: 3246
H32: Gain on sale of capital assets | M32: 31820
H33: Donations | M33: 435
H34: Other | M34: 132756
H36: Total General Revenues | M36: =SUM(M23:M34) -> 6746971
H38: Change in Net Assets | M38: =M36+M19 -> 1880314
E40: Net Assets- Beginning of Year | M40: 18046481
E42: Net Assets- End of Year | M42: =SUM(M38,M40) -> 19926795

Sheet Vermillion
J1: Vermillion County 2013 Statement of Activities
J2: Issued: December 31, 2013
M5: NET (EXPENSE) REVENUE AND CHANGE IN NET ASSETS
J6: PROGRAM REVENUES | M6: PRIMARY GOVERNMENT | N6: Component Units
A7: FUNCTIONS/PROGRAMS | I7: Expenses | J7: Charges for Services | K7: Operating Grants and Contributions | L7: Capital Grants and Contributions | M7: Governmental Activities | N7: Criminal Court Fund | O7: Tourist Commission
A8: Primary Government:
B9: Government Activities:
C10: General government | I10: -3767935 | J10: 657 | M10: =SUM(I10:L10) -> -3767278
C11: Public works | I11: -13216209 | K11: 2629340 | L11: 8002605 | M11: =SUM(I11:L11) -> -2584264
C12: Public safety | I12: -3425127 | J12: 670708 | K12: 27102 | L12: 114902 | M12: =SUM(I12:L12) -> -2612415
C13: Sanitation and waste disposal | I13: -5485143 | J13: 664715 | K13: 15344 | M13: =SUM(I13:L13) -> -4805084
C14: Health and welfare | I14: -2027128 | J14: 28991 | K14: 350464 | M14: =SUM(I14:L14) -> -1647673
C15: Economic development | I15: -79108 | M15: =SUM(I15:L15) -> -79108
C16: Culture and recreation | I16: -107341 | M16: =SUM(I16:L16) -> -107341
C17: Interest on long-term debt | I17: -96059 | M17: =SUM(I17:L17) -> -96059
E19: Total Government Activities | I19: =SUM(I10:I17) -> -28204050 | J19: =SUM(J10:J17) -> 1365071 | K19: =SUM(K10:K17) -> 3022250 | L19: =SUM(L10:L17) -> 8117507 | M19: =SUM(M10:M17) -> -15699222 | N19: =SUM(N10:N17) -> 0 | O19: =SUM(O10:O17) -> 0
A21: Component units:
B22: Criminal court fund | I22: -866203 | J22: 250489 | K22: 219747 | N22: =SUM(I22:L22) -> -395967
B23: Tourist commission | I23: -481889 | K23: 452743 | O23: =SUM(I23:L23) -> -29146
E25: Total component units | I25: =SUM(I22:I23) -> -1348092 | J25: =SUM(J22:J23) -> 250489 | K25: =SUM(K22:K23) -> 672490 | L25: =SUM(L22:L23) -> 0 | M25: =SUM(M22:M23) -> 0 | N25: =SUM(N22:N23) -> -395967 | O25: =SUM(O22:O23) -> -29146
G27: General Revenues:
H28: Taxes:
I29: Property taxes, levied for general purposes | M29: 5534910
I30: Property taxes, levied for debt service | M30: 375226
I31: Sales and use taxes, levied for general purposes | M31: 12652866 | O31: 65781
I32: Severance tax | M32: 975706
I33: Franchise tax | M33: 139766
I34: Beer taxes | M34: 9483
H35: Grants and contributions not restricted to specific programs:
I36: State revenue sharing | M36: 338954
I37: Fire insurance rebate | M37: 238724
H38: Occupational licenses and other permits | M38: 547804
H39: Interest income | M39: 293902 | N39: 54 | O39: 1848
H40: Miscellaneous | M40: 180388 | O40: 11487
H41: Gain on sale of capital assets | M41: 15565
H42: Appropriation of capital expenditures to other governmental entities | M42: -176651
H43: Transfers | M43: -408057 | N43: 408057
H45: Total General Revenues and transfers | M45: =SUM(M29:M43) -> 20718586 | N45: =SUM(N29:N43) -> 408111 | O45: =SUM(O29:O43) -> 79116
H47: Change in Net Assets | M47: =M45+M19 -> 5019364 | N47: =N45+N25 -> 12144 | O47: =O45+O25+O19 -> 49970
E49: Net Assets- Beginning of Year | M49: 130630613 | N49: 205604 | O49: 194195
E51: Net Assets- End of Year | M51: =M49+M47 -> 135649977 | N51: =N49+N47 -> 217748 | O51: =O49+O47 -> 244165

Sheet Vernon
J1: Vernon Parish 2013 Statement of Activities
J2: Issued: December 31, 2013
J5: PROGRAM REVENUES | M5: NET (EXPENSE) REVENUE AND CHANGES IN NET ASSETS
A6: FUNCTIONS/PROGRAMS | I6: Expenses | J6: Charges for Services | K6: Operating Grants and Contributions | L6: Capital Grants and Contributions | M6: 2013 | N6: 2012
A7: Governmental activities:
C8: General government
D9: Legislative | I9: -514101 | M9: =SUM(I9:L9) -> -514101 | N9: -521857
D10: Judicial | I10: -1508435 | J10: 808543 | K10: 83974 | M10: =SUM(I10:L10) -> -615918 | N10: -1160815
D11: Elections | I11: -83787 | M11: =SUM(I11:L11) -> -83787 | N11: -61855
D12: Finance and administrative | I12: -2618264 | J12: 302516 | M12: =SUM(I12:L12) -> -2315748 | N12: -2421602
D13: Other | I13: -3128836 | M13: =SUM(I13:L13) -> -3128836 | N13: -2739397
C14: Public safety | I14: -1518408 | K14: 224094 | M14: =SUM(I14:L14) -> -1294314 | N14: -961313
C15: Public works | I15: -9584539 | J15: 16666 | K15: 594933 | M15: =SUM(I15:L15) -> -8972940 | N15: -8874765
C16: Health and welfare | I16: -855271 | K16: 221704 | M16: =SUM(I16:L16) -> -633567 | N16: -721689
C17: Culture and recreation | I17: -2093398 | J17: 165214 | K17: 9474 | M17: =SUM(I17:L17) -> -1918710 | N17: -1423772
C18: Economic development and assistance | I18: -883329 | K18: 50943 | L18: 214262 | M18: =SUM(I18:L18) -> -618124 | N18: -621067
C19: Debt service | I19: -382172 | M19: =SUM(I19:L19) -> -382172 | N19: -391196
E21: Total Government Activities | I21: =SUM(I9:I19) -> -23170540 | J21: =SUM(J9:J19) -> 1292939 | K21: =SUM(K9:K19) -> 1185122 | L21: =SUM(L9:L19) -> 214262 | M21: =SUM(M9:M19) -> -20478217 | N21: =SUM(N9:N19) -> -19899328
G23: General Revenues:
H24: Taxes:
I25: Property taxes, levied for general purposes | M25: 5068036 | N25: 4984332
I26: Property taxes, levied for debt services | M26: 587004 | N26: 543788
I27: Sales and use taxes, levied for general purposes | M27: 8614270 | N27: 9567176
H28: Grants and contributions not restricted to specific purposes:
I29: Federal grant programs | M29: 786815 | N29: 1075978
I30: State grant programs | M30: 2129891 | N30: 2567177
H31: Interest and investment earnings | M31: 187464 | N31: 103413
H32: Miscellaneous | M32: 2416157 | N32: 1801664
H34: Total General Revenues and Special Items | M34: =SUM(M25:M32) -> 19789637 | N34: =SUM(N25:N32) -> 20643528
H36: Change in Net position | M36: =M34+M21 -> -688580 | N36: =N34+N21 -> 744200
E38: Net position- beginning | M38: 55493004 | N38: 54748805
E40: Net position- ending | M40: =M38+M36 -> 54804424 | N40: =N38+N36 -> 55493005

Sheet Washington
J1: Washington Parish 2013 Statement of Activities
J2: Issued: December 31, 2013
J4: PROGRAM REVENUES | M4: Net Revenues (Expenses) Revenues & Changes in Net Position
A5: FUNCTIONS/PROGRAMS | I5: Expenses | J5: Charges for Services | K5: Operating Grants and Contributions | L5: Capital Grants and Contributions | M5: Governmental Activities | N5: Business-type Activities | O5: Total
A6: Primary Government:
B7: Government Activities:
C8: General government | I8: -4034520 | J8: 671539 | K8: 597470 | M8: =SUM(I8:L8) -> -2765511 | O8: =SUM(M8:N8) -> -2765511
C9: Public safety | I9: -772552 | L9: 671494 | M9: =SUM(I9:L9) -> -101058 | O9: =SUM(M9:N9) -> -101058
C10: Highways and streets | I10: -3634098 | K10: 678300 | L10: 438948 | M10: =SUM(I10:L10) -> -2516850 | O10: =SUM(M10:N10) -> -2516850
C11: Health and welfare | I11: -971511 | K11: 330965 | M11: =SUM(I11:L11) -> -640546 | O11: =SUM(M11:N11) -> -640546
C12: Culture and recreation | I12: -910745 | J12: 7400 | K12: 155462 | L12: 23878 | M12: =SUM(I12:L12) -> -724005 | O12: =SUM(M12:N12) -> -724005
C13: Sanitation | I13: -514578 | M13: =SUM(I13:L13) -> -514578 | O13: =SUM(M13:N13) -> -514578
C14: Hurricane relief and restoration | I14: -474924 | K14: 139474 | M14: =SUM(I14:L14) -> -335450 | O14: =SUM(M14:N14) -> -335450
C15: Interest on long-term debt | I15: -296858 | M15: =SUM(I15:L15) -> -296858 | O15: =SUM(M15:N15) -> -296858
E17: Total Government Activities | I17: =SUM(I8:I15) -> -11609786 | J17: =SUM(J8:J15) -> 678939 | K17: =SUM(K8:K15) -> 1901671 | L17: =SUM(L8:L15) -> 1134320 | M17: =SUM(M8:M15) -> -7894856 | O17: =SUM(O8:O15) -> -7894856
B19: Business-type Activities:
C20: Revenues | N20: =SUM(I20:L20) -> 0 | O20: =SUM(M20:N20) -> 0
E22: Total business-type activities | I22: =I20 -> 0 | J22: =J20 -> 0 | K22: =K20 -> 0 | L22: =L20 -> 0 | M22: 0 | N22: =SUM(N20:N20) -> 0 | O22: =SUM(O20:O20) -> 0
E24: Total primary government | I24: =I22+I17 -> -11609786 | J24: =J22+J17 -> 678939 | K24: =K22+K17 -> 1901671 | L24: =L22+L17 -> 1134320 | M24: =M22+M17 -> -7894856 | N24: =N22+N17 -> 0 | O24: =O22+O17 -> -7894856
G26: General Revenues:
H27: Property taxes, levied for general purpose | M27: 4199263 | O27: =SUM(M27:N27) -> 4199263
H28: Property taxes, levied for debt service
H29: Sales taxes | M29: 4720164 | O29: =SUM(M29:N29) -> 4720164
H30: State revenue sharing | M30: 204361 | O30: =SUM(M30:N30) -> 204361
H31: Timber severance | M31: 170784 | O31: =SUM(M31:N31) -> 170784
H32: Mineral severance | M32: 15293 | O32: =SUM(M32:N32) -> 15293
H33: Other tax | M33: 19181 | O33: =SUM(M33:N33) -> 19181
H34: Fire insurance rebate | M34: 191385 | O34: =SUM(M34:N34) -> 191385
H35: Occupational licenses | M35: 607276 | O35: =SUM(M35:N35) -> 607276
H36: Unrestricted interest | M36: 10164 | N36: 4330 | O36: =SUM(M36:N36) -> 14494
H37: Loss on disposal | M37: -24238 | O37: =SUM(M37:N37) -> -24238
H38: Miscellaneous | M38: 593288 | O38: =SUM(M38:N38) -> 593288
H40: Total general revenue and transfers | M40: =SUM(M26:M38) -> 10706921 | N40: =SUM(N26:N38) -> 4330 | O40: =SUM(O27:O38) -> 10711251
H42: Change in Net Position | M42: =M40+M24 -> 2812065 | N42: =N40+N24 -> 4330 | O42: =O40+O24 -> 2816395
E44: Net Position, beginning | M44: 39163566 | N44: 188021 | O44: =SUM(M44:N44) -> 39351587
E46: Net Assets- End of Year | M46: =M44+M42 -> 41975631 | N46: =N44+N42 -> 192351 | O46: =O44+O42 -> 42167982

Sheet Webster
J1: Webster Parish 2013 Statement of Activities
J2: Issued: December 31, 2013
J5: PROGRAM REVENUES | M5: NET (EXPENSE) REVENUE AND CHANGES IN NET ASSETS
A6: FUNCTIONS/PROGRAMS | I6: Expenses | J6: Charges for Services | K6: Operating Grants and Contributions | L6: Capital Grants and Contributions | M6: Governmental Activities | N6: Component Units
A7: Governmental activities:
C8: General government
D9: Legislative | I9: -248734 | M9: =SUM(I9:L9) -> -248734
D10: Judicial | I10: -1724673 | J10: 385091 | M10: =SUM(I10:L10) -> -1339582
D11: Elections | I11: -42547 | M11: =SUM(I11:L11) -> -42547
D12: Finance and administrative | I12: -1169587 | M12: =SUM(I12:L12) -> -1169587
D13: Other general government | I13: -596497 | K13: 32152 | M13: =SUM(I13:L13) -> -564345
C14: Public safety | I14: -2080464 | K14: 12807 | L14: 85523 | M14: =SUM(I14:L14) -> -1982134
C15: Public works | I15: -2625579 | K15: 569727 | L15: 150946 | M15: =SUM(I15:L15) -> -1904906
C16: Health and welfare | I16: -1005348 | M16: =SUM(I16:L16) -> -1005348
C17: Culture and recreation | I17: -2449843 | J17: 36809 | M17: =SUM(I17:L17) -> -2413034
C18: Economic development and assistance | I18: -33624 | M18: =SUM(I18:L18) -> -33624
C19: Interest on long-term debt | I19: -36920 | M19: =SUM(I19:L19) -> -36920
E21: Total Government Activities | I21: =SUM(I9:I19) -> -12013816 | J21: =SUM(J9:J19) -> 421900 | K21: =SUM(K9:K19) -> 614686 | L21: =SUM(L9:L19) -> 236469 | M21: =SUM(M9:M19) -> -10740761 | N21: =SUM(N9:N19) -> 0
A23: Component Units:
C24: Community services | I24: -4721369 | J24: 61628 | K24: 4726910 | N24: =SUM(I24:L24) -> 67169
C25: E-911 | I25: -457448 | J25: 443721 | N25: =SUM(I25:L25) -> -13727
E27: Total Component Units | I27: =SUM(I24:I25) -> -5178817 | J27: =SUM(J24:J25) -> 505349 | K27: =SUM(K24:K25) -> 4726910 | L27: =SUM(L24:L25) -> 0 | M27: =SUM(M24:M25) -> 0 | N27: =SUM(N24:N25) -> 53442
G29: General Revenues:
H30: Taxes:
I31: Property taxes, levied for general purposes | M31: 5415085
I32: Property taxes, levied for debt service | M32: 93168
I33: Sales taxes, levied for general purposes | M33: 3007111
H34: State revenue sharing | M34: 260094
H35: Severance tax | M35: 1171189
H36: Grants and contributions not restricted for a specific purpose | M36: 367884
H37: Fees, charges and commissions | M37: 171006
H38: Licenses and permits | M38: 426648
H39: Interest and investment earnings | M39: 632510 | N39: 2072
H40: Miscellaneous | M40: 512378 | N40: 37154
H42: Total General Revenues | M42: =SUM(M31:M40) -> 12057073 | N42: =SUM(N31:N40) -> 39226
H44: Changes in Net position | M44: =M42+M21 -> 1316312 | N44: =N42+N27 -> 92668
E46: Net position- beginning | M46: 21523624 | N46: 2851892
E48: Net position- ending | M48: =M46+M44 -> 22839936 | N48: =N46+N44 -> 2944560

Sheet West Baton Rouge
J1: West Baton Rouge County 2013 Statement of Activities
J2: Issued: December 31, 2013
J5: PROGRAM REVENUES | L5: PRIMARY GOVERNMENT
A6: FUNCTIONS/PROGRAMS | I6: Expenses | J6: Charges for Services | K6: Operating Grants and Contributions | L6: NET (EXPENSE) REVENUE AND CHANGE IN NET ASSETS
A7: Primary Government:
B8: Government Activities:
C9: General government | I9: -5833701 | J9: 1995899 | K9: 49763 | L9: =SUM(I9:K9) -> -3788039
C10: Public safety | I10: -6826163 | K10: 3878362 | L10: =SUM(I10:K10) -> -2947801
C11: Public works | I11: -9764007 | J11: 107972 | K11: 2383927 | L11: =SUM(I11:K11) -> -7272108
C12: Culture and recreation | I12: -2421416 | J12: 172352 | K12: 25836 | L12: =SUM(I12:K12) -> -2223228
C13: Health and welfare | I13: -1393022 | K13: 246596 | L13: =SUM(I13:K13) -> -1146426
C14: Economic development | I14: -97262 | K14: 478046 | L14: =SUM(I14:K14) -> 380784
C15: Urban housing | I15: -320456 | K15: 320456 | L15: =SUM(I15:K15) -> 0
C16: Interest and fiscal charges on long-term debt | I16: -178937 | L16: =SUM(I16:K16) -> -178937
E18: Total Government Activities | I18: =SUM(I9:I16) -> -26834964 | J18: =SUM(J9:J16) -> 2276223 | K18: =SUM(K9:K16) -> 7382986 | L18: =SUM(L9:L16) -> -17175755
G20: General Revenues:
H21: Taxes:
I22: Ad valorem | L22: 8729244
I23: Sales and use | L23: 9418569
I24: Video poker | L24: 1103354
I25: Other | L25: 28835
H26: Licenses and permits | L26: 838805
H27: Interest | L27: 57363
H28: Rent | L28: 16600
H29: Miscellaneous | L29: 802027
H31: Total General Revenues | L31: =SUM(L22:L29) -> 20994797
H33: Change in Net Assets | L33: =L31+L18 -> 3819042
E35: Net Assets- Beginning of Year, restated | L35: 73356099
E37: Net Assets- End of Year | L37: =SUM(L33,L35) -> 77175141

Sheet West Carroll
J1: West Carroll County 2013 Statement of Activities
J2: Issued: December 31, 2013
M5: NET (EXPENSE) REVENUE AND CHANGE IN NET ASSETS
J6: PROGRAM REVENUES | M6: PRIMARY GOVERNMENT
A7: FUNCTIONS/PROGRAMS | I7: Expenses | J7: Charges for Services | K7: Operating Grants and Contributions | L7: Capital Grants and Contributions | M7: Governmental Activities
A8: Primary Government:
