Workbook

Sheet Acadia
D1: Acadia Parish 2013 Statement of Net Assets
D2: Issued: December 31, 2013
H4: Primary Government
H5: Governmental Activities | I5: Component Unit
A6: ASSETS
B7: Current Assets
C8: Cash | H8: 6387055 | I8: 18001
C9: Investments | H9: 7359136
C10: Taxes receivable | H10: 412930
C11: Special assessments receivable | H11: 29556
C12: Other receivables | H12: 77797 | I12: 14656
C13: Due from other governmental entities | H13: 6687029 | I13: 31151
C14: Due from component units | H14: 20793
C15: Capital assets:
D16: Non-depreciable | H16: 11576953
D17: Depreciable, net | H17: 42893333 | I17: 376
C19: Total Assets | H19: =SUM(H8:H17) -> 75444582 | I19: =SUM(I8:I17) -> 64184
A21: DEFERRED OUTFLOWS OF RESOURCES
C22: Deferred loss on refunding | H22: 40499
A24: LIABILITIES
C25: Accounts payable | H25: 799857 | I25: 4582
C26: Retainage payable | H26: 30559
C27: Accrued liabilities and other payables | H27: 326235
C28: Unearned revenue | H28: 26500
C29: Accrued interest payable | H29: 79052
C30: Due to primary government | I30: 20793
C31: Long-term liabilities:
D32: Portion due or payable within one year:
E33: Bonds payable | H33: 1531435
E34: Compensated absences | H34: 185605
D35: Portion due or payable after one year:
E36: Bonds payable | H36: 12775783
E37: Compensated absences | H37: 185605
E38: Landfill closure and postclosure care costs liability | H38: 6893470
D40: Total Liabilities | H40: =SUM(H25:H38) -> 22834101 | I40: =SUM(I25:I38) -> 25375
A42: DEFERRED INFLOWS OF RESOURCES
C43: Unavailable revenue - special assessments | H43: 29556
A45: NET ASSETS
B46: Net investment in capital assets | H46: 40203566
B47: Restricted for:
C48: Debt service | H48: 1512382
C49: Capital projects | H49: 1040484
C50: Other purposes | H50: 5372731
B51: Unrestricted | H51: 4492261 | I51: 38809
C53: Total Net Assets | H53: =SUM(H46:H51) -> 52621424 | I53: =SUM(I45:I51) -> 38809
C55: Total Liabilities and Net Assets | H55: =H53+H43+H40 -> 75485081 | I55: =I53+I43+I40 -> 64184

Sheet Allen
C1: Allen Parish 2013 Statement of Net Assets
C2: Issued: December 31, 2013
G4: Governmental Activities
A5: ASSETS
B6: Cash | G6: 4518521
B7: Receivables | G7: 2958638
B8: Due from other governments | G8: 549380
B9: Inventory | G9: 25276
B10: Prepaid assets | G10: 4443
B11: Capital assets, net of accumulated depreciation | G11: 24665755
B13: Total Assets | G13: =SUM(G6:G11) -> 32722013
A15: LIABILITIES
B16: Accounts payable | G16: 486255
B17: Accrued interest payable | G17: 1691
B18: Unearned revenue | G18: 134467
B19: Bonds payable - due within one year | G19: 33000
B20: Compensated absences payable - due within one year | G20: 37649
B21: OPEB obligations - due in more than one year | G21: 989571
B22: Bonds payable - due in more than one year | G22: 155000
C24: Total Liabilities | G24: =SUM(G16:G22) -> 1837633
A26: NET ASSETS
B27: Net, investment in capital assets | G27: 24477755
B28: Restricted for:
C29: Inventory | G29: 25276
C30: Judicial | G30: 349325
C31: Other general government | G31: 644976
C32: Public safety | G32: 874
C33: Public works | G33: 4480460
C34: Economic development | G34: 37419
C35: Sanitation | G35: 575216
C36: Capital projects | G36: 300024
C37: Debt service | G37: 258
B38: Unrestricted | G38: -7203
B40: Total Net Assets | G40: =SUM(G27:G38) -> 30884380
B42: Total Liabilities and Net Assets | G42: =SUM(G24+G40) -> 32722013

Sheet Ascension
D1: Ascension Parish 2013 Statement of Net Assets
D2: Issued: December 31, 2013
I4: Primary Government | L4: Component Unit
I5: Governmental Activities | J5: Business-type Activities | K5: Total | L5: Governmental Activities | M5: Business-type Activities
A6: ASSETS
B7: Current Assets
C8: Cash and cash equivalents | I8: 42404828 | J8: 3686409 | K8: =SUM(I8:J8) -> 46091237 | L8: 30169983 | M8: 457571
C9: Investments | I9: 93691087 | J9: 4127466 | K9: =SUM(I9:J9) -> 97818553 | L9: 4943491 | M9: 9681370
C10: Accounts receivable, net | I10: 31751994 | J10: 211156 | K10: =SUM(I10:J10) -> 31963150 | L10: 3767692 | M10: 1153256
C11: Due from other governments | I11: 5021470 | J11: 104475 | K11: =SUM(I11:J11) -> 5125945 | L11: 1125619
C12: Internal balances | I12: 5 | J12: -5 | K12: =SUM(I12:J12) -> 0
C13: Prepaid assets | I13: 1008407 | J13: 281 | K13: =SUM(I13:J13) -> 1008688 | L13: 173484
C14: Inventory | J14: 22147 | K14: =SUM(I14:J14) -> 22147 | M14: 240233
C15: Restricted assets | J15: 36464 | K15: =SUM(I15:J15) -> 36464 | L15: 709316 | M15: 548502
C16: Other assets | I16: 97173 | K16: =SUM(I16:J16) -> 97173 | L16: 6681 | M16: 116241
C17: Capital assets:
E18: Nondepreciable | I18: 73100022 | J18: 941205 | K18: =SUM(I18:J18) -> 74041227 | L18: 1945991 | M18: 110902
E19: Depreciable, net | I19: 136464488 | J19: 9952083 | K19: =SUM(I19:J19) -> 146416571 | L19: 11921812 | M19: 11753708
C21: Total Assets | I21: =SUM(I8:I19) -> 383539474 | J21: =SUM(J8:J19) -> 19081681 | K21: =SUM(K8:K19) -> 402621155 | L21: =SUM(L8:L19) -> 54764069 | M21: =SUM(M7:M19) -> 24061783
A23: Deferred Outflows of Resources
B24: Deferred loss on refunding bonds, net | I24: 294404 | J24: 0 | K24: =SUM(I24:J24) -> 294404 | L24: 0 | M24: 0
C26: Total assets and deferred outflows of resources | I26: =SUM(I24+I21) -> 383833878 | J26: =J21 -> 19081681 | K26: =K24+K21 -> 402915559 | L26: =L21 -> 54764069 | M26: =M21 -> 24061783
A28: LIABILITIES
C29: Accounts payable and accrued liabilities | I29: 3198900 | J29: 565558 | K29: =SUM(I29:J29) -> 3764458 | L29: 3210186 | M29: 352605
C30: Contracts payable | I30: 3980044 | K30: =SUM(I30:J30) -> 3980044
C31: Due to other goevernments | I31: 269707 | K31: =SUM(I31:J31) -> 269707 | L31: 1136146
C32: Accrued payroll | I32: 540668 | J32: 28220 | K32: =SUM(I32:J32) -> 568888
C33: Customer deposits | J33: 36464 | K33: =SUM(I33:J33) -> 36464 | M33: 43501
C34: Sales tax rebate reserve | I34: 4524981 | K34: =SUM(I34:J34) -> 4524981
C35: Claims reserve | K35: =SUM(I35:J35) -> 0
D36: Due within one year | I36: 235409 | K36: =SUM(I36:J36) -> 235409
D37: Due in more than one year | I37: 667416 | K37: =SUM(I37:J37) -> 667416
C38: Long-term payable | K38: =SUM(I38:J38) -> 0
D39: Due within one year | I39: 4335000 | K39: =SUM(I39:J39) -> 4335000 | L39: 551031 | M39: 176485
D40: Due in more than one year | I40: 80612569 | K40: =SUM(I40:J40) -> 80612569 | L40: 6694058 | M40: 4766994
D42: Total Liabilities | I42: =SUM(I29:I40) -> 98364694 | J42: =SUM(J29:J40) -> 630242 | K42: =SUM(K29:K40) -> 98994936 | L42: =SUM(L29:L40) -> 11591421 | M42: =SUM(M29:M40) -> 5339585
A44: Deferred Inflows of Resources
B45: Grant Advances | I45: 629856 | J45: 0 | K45: =SUM(I45:J45) -> 629856 | L45: 0 | M45: 0
B46: Unearned Revenue | I46: 0 | J46: 18770 | K46: =SUM(I46:J46) -> 18770 | L46: 0 | M46: 0
D48: Total deferred inflows of resources | I48: =SUM(I45:I46) -> 629856 | J48: =SUM(J45:J46) -> 18770 | K48: =SUM(K45:K46) -> 648626 | L48: 0 | M48: 0
A50: NET ASSETS
B51: Investment in capital assets, net of related debt | I51: 127427898 | J51: 10893288 | K51: =SUM(I51:J51) -> 138321186 | L51: 12884726 | M51: 6921131
B52: Restricted for:
C53: Capital Projects | I53: 55001484 | K53: =SUM(I53:J53) -> 55001484
C54: External legal constraints | I54: 77707027 | K54: =SUM(I54:J54) -> 77707027
C55: Debt service | I55: 2519611 | K55: =SUM(I55:J55) -> 2519611 | M55: 505001
C56: Other Purposes | L56: 2627035
B57: Unrestricted | I57: 22183308 | J57: 7539381 | K57: =SUM(I57:J57) -> 29722689 | L57: 27660887 | M57: 11296066
C59: Total Net Assets | I59: =SUM(I51:I57) -> 284839328 | J59: =SUM(J51:J57) -> 18432669 | K59: =SUM(K51:K57) -> 303271997 | L59: =SUM(L51:L57) -> 43172648 | M59: =SUM(M51:M57) -> 18722198
C61: Total Liabilities, deferred inflows of resources, and Net Assets | I61: =SUM(I42+I59+I48) -> 383833878 | J61: =SUM(J42+J59+J48) -> 19081681 | K61: =SUM(K42+K59+K48) -> 402915559 | L61: =SUM(L42+L59+L48) -> 54764069 | M61: =SUM(M42+M59+M48) -> 24061783

Sheet Assumption
D1: Assumption Parish 2013 Statement of Net Assets
D2: Issued: December 31, 2013
H4: 2013 | I4: 2012
A5: ASSETS
B6: Current Assets
C7: Cash and cash equivalents | H7: 3793804 | I7: 5837144
C8: Investments | H8: 13855799 | I8: 11713813
C9: Receivables | H9: 5121670 | I9: 5328610
C10: Other assets | H10: 27165 | I10: 619979
C11: Land, Building, and Equipment - net | H11: 43733131 | I11: 41316993
C13: Total Assets | H13: =SUM(H7:H11) -> 66531569 | I13: =SUM(I7:I11) -> 64816539
A15: LIABILITIES
C16: Accounts payable | H16: 677911 | I16: 1848741
C17: Salaries payable | H17: 139322 | I17: 146265
C18: Compensated absences payable | H18: 155373 | I18: 158422
C19: Other post-employment benefits payable | H19: 659785 | I19: 553095
C20: Other liabilities | H20: 301226 | I20: 1143608
C21: Long-term liabilities:
D22: Due within one year | I22: 57000
D23: Due in more than one year
D25: Total Liabilities | H25: =SUM(H16:H23) -> 1933617 | I25: =SUM(I16:I23) -> 3907131
A27: NET ASSETS
B28: Invested in capital assets, net of related debt | H28: 43733131 | I28: 41259993
B29: Unrestricted | H29: 20864821 | I29: 19649415
C31: Total Net Assets | H31: =SUM(H28:H29) -> 64597952 | I31: =SUM(I27:I29) -> 60909408
C33: Total Liabilities and Net Assets | H33: =SUM(H25+H31) -> 66531569 | I33: =SUM(I31+I25) -> 64816539

Sheet Avoyelles
D1: Avoyelles Parish 2013 Statement of Net Assets
D2: Issued: December 31, 2013
H4: Primary Government | I4: Component Units
A5: ASSETS
B6: Current Assets
C7: Cash and interest-bearing deposits | H7: 7808079 | I7: 226394
C8: Receivables, net | H8: 2186064 | I8: 17410
C9: Due from other governmental units | H9: 454661
C10: Other assets | H10: 104800 | I10: 5933
C12: Total Current Assets | H12: =SUM(H7:H10) -> 10553604 | I12: =SUM(I7:I11) -> 249737
B14: Non-current Assets:
C15: Land and construction in progress | H15: 1667856
C16: Capital assets, net | H16: 3564386 | I16: 24978
C18: Total Non-current Assets | H18: =SUM(H14:H16) -> 5232242 | I18: =SUM(I14:I16) -> 24978
C20: Total Assets | H20: =SUM(H12+H18) -> 15785846 | I20: =SUM(I12+I18) -> 274715
A22: LIABILITIES
B23: Current Liabilities:
C24: Accounts, salaries and other payables | H24: 588143 | I24: 22127
C25: Deferred revenue | H25: 36260
C26: Due to other governmental units | H26: 37903
C27: Compensated absences payable | H27: 32052
D29: Total Current Liabilities | H29: =SUM(H24:H27) -> 694358 | I29: =SUM(I24:I27) -> 22127
B31: Non-current Liabilities
C32: Compensated absences payable | H32: 66030
D34: Total Non-current Liabilities | H34: =SUM(H32:H32) -> 66030 | I34: =SUM(I32:I32) -> 0
D36: Total Liabilities | H36: =SUM(H29+H34) -> 760388 | I36: =SUM(I34+I29) -> 22127
A38: NET ASSETS
B39: Investment in capital assets | H39: 5232242 | I39: 24978
B40: Unrestricted net position | H40: 9793216 | I40: 227610
C42: Total Net Assets | H42: =SUM(H39:H40) -> 15025458 | I42: =SUM(I39:I40) -> 252588
C44: Total Liabilities and Net Assets | H44: =SUM(H36+H42) -> 15785846 | I44: =SUM(I42+I36) -> 274715

Sheet Beauregard
C1: Beauregard Parish 2013 Statement of Net Assets
C2: Issued: December 31, 2013
G4: Governmental Activities
A5: ASSETS
B6: Cash and cash equivalents | G6: 14858366
B7: Receivables | G7: 6484761
B8: Inventory | G8: 313803
B9: Capital assets (net of accumulated depreciation):
C10: Land | G10: 806735
C11: Buildings and improvements | G11: 9930994
C12: Furniture and equipment | G12: 3990003
C13: Infrastructure | G13: 15989047
C14: Construction in progress | G14: 790379
B16: Total Assets | G16: =SUM(G6:G14) -> 53164088
A18: LIABILITIES
B19: Accounts, salaries, and other payables | G19: 849191
B20: Interest payable | G20: 25658
B21: Long-term liabilities:
C22: Due within one year | G22: 1760644
C23: Due in more than one year | G23: 2722875
C25: Total Liabilities | G25: =SUM(G19:G23) -> 5358368
A27: NET ASSETS
B28: Invested in capital assets, net of related debt | G28: 27191700
B29: Restricted for:
C30: Inventory | G30: 313803
C31: Equipment purchases | G31: 324072
C32: Public safety | G32: 1810976
C33: Public works | G33: 6392675
C34: Health and welfare | G34: 2463098
C35: Culture and recreation | G35: 607692
C36: Sanitation | G36: 3275003
C37: Other general government | G37: 136917
C38: Capital projects | G38: 1275201
C39: Debt service | G39: 166216
B40: Unrestricted | G40: 3848367
B42: Total Net Assets | G42: =SUM(G28:G40) -> 47805720
B44: Total Liabilities and Net Assets | G44: =SUM(G25+G42) -> 53164088

Sheet Bienville
C1: Bienville Parish 2013 Statement of Net Assets
C2: Issued: December 31, 2013
G4: Governmental Activities
A5: ASSETS
B6: Cash and cash equivalents | G6: 17224341
B7: Receivables | G7: 5448406
B8: Capital assets, net | G8: 22814176
B10: Total Assets | G10: =SUM(G6:G8) -> 45486923
A12: LIABILITIES
B13: Accounts payable | G13: 249706
B14: Wages and related payable | G14: 22626
B15: Interest payable | G15: 141079
B16: Bonds payable | G16: 10820000
B17: Premium on bonds | G17: 290088
B18: Deferred revenues | G18: 70000
B19: Compensated absences payable | G19: 81369
B20: Other post-employment benefits | G20: 1236841
C22: Total Liabilities | G22: =SUM(G13:G20) -> 12911709
A24: NET ASSETS
B25: Invested in capital assets, net of related debt | G25: 11994176
B26: Unrestricted | G26: 20581038
B28: Total Net Assets | G28: =SUM(G25:G26) -> 32575214
B30: Total Liabilities and Net Assets | G30: =SUM(G22+G28) -> 45486923

Sheet Bossier
D1: Bossier Parish 2013 Statement of Net Assets
D2: Issued: December 31, 2013
H4: Primary Government
H5: Governmental Activities | I5: Business-Type Activities | J5: Total
A6: ASSETS
B7: Current Assets
C8: Cash and cash equivalents | H8: 36706356 | I8: 766450 | J8: =SUM(H8:I8) -> 37472806
C9: Restricted cash | H9: 5135344 | I9: 386253 | J9: =SUM(H9:I9) -> 5521597
C10: Receivables | H10: 17839886 | I10: 243838 | J10: =SUM(H10:I10) -> 18083724
C11: Prepaid expenses | H11: 964155 | I11: 39816 | J11: =SUM(H11:I11) -> 1003971
C12: Capital assets, net:
D13: Non-depreciable | H13: 18249363 | I13: 5807576 | J13: =SUM(H13:I13) -> 24056939
D14: Depreciable (net) | H14: 263054104 | I14: 4654569 | J14: =SUM(H14:I14) -> 267708673
C15: Internal balances | H15: 8185472 | I15: -8185472 | J15: =SUM(H15:I15) -> 0
C17: Total Assets | H17: =SUM(H8:H15) -> 350134680 | I17: =SUM(I8:I15) -> 3713030 | J17: =SUM(J8:J15) -> 353847710
A19: LIABILITIES
B20: Current liabilities
C21: Accounts payable and accrued expenses | H21: 3002767 | I21: 313454 | J21: =SUM(H21:I21) -> 3316221
C22: Payable from restricted assets:
D23: Customer deposits | I23: 91817 | J23: =SUM(H23:I23) -> 91817
D25: Total Current Liabilities | H25: =SUM(H21:H23) -> 3002767 | I25: =SUM(I21:I23) -> 405271 | J25: =SUM(J21:J23) -> 3408038
B27: Noncurrent liabilities
C28: Due within one year | H28: 4678377 | J28: =SUM(H28:I28) -> 4678377
C29: Due in more than one year | H29: 60341208 | I29: 572460 | J29: =SUM(H29:I29) -> 60913668
D31: Total Noncurrent Liabilities | H31: =SUM(H27:H29) -> 65019585 | I31: =SUM(I27:I29) -> 572460 | J31: =SUM(J27:J29) -> 65592045
D33: Total Liabilities | H33: =SUM(H25+H31) -> 68022352 | I33: =SUM(I31+I25) -> 977731 | J33: =SUM(J31+J25) -> 69000083
A35: NET ASSETS
B36: Net investment in capital assets | H36: 226860112 | I36: 1704213 | J36: =SUM(H36:I36) -> 228564325
B37: Restricted for:
C38: Capital projects | H38: 8902048 | J38: =SUM(H38:I38) -> 8902048
C39: Public works | H39: 541580 | J39: =SUM(H39:I39) -> 541580
C40: Public safety | H40: 3674946 | J40: =SUM(H40:I40) -> 3674946
C41: Economic development | H41: 159526 | J41: =SUM(H41) -> 159526
C42: Culture and recreation | H42: 11586703 | J42: =SUM(H42) -> 11586703
C43: Debt service | H43: 3467975 | J43: =SUM(H43) -> 3467975
C44: Health and welfare | H44: 3000381 | J44: =SUM(H44) -> 3000381
C45: Sewer operations | H45: 330557 | J45: =SUM(H45:I45) -> 330557
B46: Unrestricted | H46: 23588500 | I46: 1031086 | J46: =SUM(H46:I46) -> 24619586
C48: Total Net Assets | H48: =SUM(H36:H46) -> 282112328 | I48: =SUM(I36:I46) -> 2735299 | J48: =SUM(J36:J46) -> 284847627
C50: Total Liabilities and Net Assets | H50: =H33+H48 -> 350134680 | I50: =I33+I48 -> 3713030 | J50: =J33+J48 -> 353847710

Sheet Caddo
D1: Caddo Parish 2013 Statement of Net Assets
D2: Issued: December 31, 2013
H4: Primary Government
H5: Governmental Activities | I5: Component Units
A6: ASSETS
C7: Cash and cash equivalents | H7: 16689898 | I7: 14220362
C8: Investments | H8: 117520729 | I8: 5613349
C9: Receivables, net | H9: 57370497 | I9: 14484609
C10: Due from other governments | H10: 2164467 | I10: 642973
C11: Due from primary government | I11: 866635
C12: Inventories | H12: 82196 | I12: 390937
C13: Other assets | H13: 112394 | I13: 8614948
C14: Capital assets:
D15: Land and construction in progress | H15: 28561293 | I15: 2604168
D16: Other capital assets, net of depreciation | H16: 181707632 | I16: 38525961
C18: Total Assets | H18: =SUM(H7:H16) -> 404209106 | I18: =SUM(I7:I16) -> 85963942
A20: DEFERRED OUTFLOWS OF RESOURCES
C21: Deferred loss on refunding bonds, net | I21: 167647
E23: Total assets and deferred outlfows of resources | H23: =H21+H18 -> 404209106 | I23: =I21+I18 -> 86131589
A25: LIABILITIES
C26: Accounts payable | H26: 2761704 | I26: 2888481
C27: Accrued liabilities | H27: 897757 | I27: 1186374
C28: Accrued interest payable | H28: 548514 | I28: 36663
C29: Retainage payable | H29: 779557
C30: Accrued insurance claims payable | H30: 726491 | I30: 486000
C31: Due to component units | H31: 859366
C32: Due to other governmental agencies | H32: 554985 | I32: 28025
C33: Unearned revenue | H33: 82995 | I33: 181892
C34: Noncurrent liabilities:
D35: Due within one year | H35: 2989243 | I35: 3510509
D36: Due in more than one year | H36: 40233745 | I36: 21741649
D38: Total Liabilities | H38: =SUM(H26:H36) -> 50434357 | I38: =SUM(I26:I36) -> 30059593
A40: NET ASSETS
B41: Net investment in capital assets | H41: 180201711 | I41: 27322309
B42: Restricted for:
C43: Criminal justice | H43: 14820873
C44: Health and welfare | H44: 4403804
C45: Highways, streets and drainage | H45: 29075379
C46: Building facilities | H46: 8754267
C47: Sanitation | H47: 20167034
C48: Culture and recreation | H48: 25670154
C49: Economic development | H49: 740175 | I49: 7500000
C50: Debt service | H50: 2966081 | I50: 2002012
C51: Capital outlay | I51: 232162
B52: Unrestricted (deficit) | H52: 66975271 | I52: 19015513
C54: Total Net Assets | H54: =SUM(H41:H52) -> 353774749 | I54: =SUM(I41:I52) -> 56071996
C56: Total Liabilities and Net Assets | H56: =SUM(H38+H54) -> 404209106 | I56: =SUM(I54+I38) -> 86131589

Sheet Calcasieu
D1: Calcasieu Parish 2013 Statement of Net Assets
D2: Issued: December 31, 2013
H4: Primary Government
H5: Governmental Activities | I5: Business-Type Activities | J5: Total | K5: Component Unit
A6: ASSETS
B7: Current Assets
C8: Cash and cash equivalents | H8: 61403447 | I8: 286431 | J8: =SUM(H8:I8) -> 61689878 | K8: 32642434
C9: Investments | H9: 193319389 | I9: 770334 | J9: =SUM(H9:I9) -> 194089723 | K9: 42289149
C10: Receivables (net of allowance for uncollectibles) | H10: 54312100 | I10: 631792 | J10: =SUM(H10:I10) -> 54943892 | K10: 56808950
C11: Intergovernmental receivable | H11: 5763494 | I11: 21180 | J11: =SUM(H11:I11) -> 5784674 | K11: 1140772
C12: Internal balances | H12: 43458 | I12: -43458 | J12: =SUM(H12:I12) -> 0
C13: Due from component units | H13: 222898 | J13: =SUM(H13:I13) -> 222898
C14: Due from primary government | J14: =SUM(H14:I14) -> 0 | K14: 458224
C15: Loan receivable | H15: 48138 | J15: =SUM(H15:I15) -> 48138
C16: Prepaid items | H16: 220683 | I16: 33427 | J16: =SUM(H16:I16) -> 254110 | K16: 1621791
C17: Inventory | H17: 1092701 | J17: =SUM(H17:I17) -> 1092701 | K17: 1957810
C18: Other assets | I18: 320 | J18: =SUM(H18:I18) -> 320 | K18: 500683
C19: Restricted assets:
D20: Cash and cash equivalents | I20: 13717 | J20: =SUM(H20:I20) -> 13717 | K20: 5461536
D21: Investments | I21: 199758 | J21: =SUM(H21:I21) -> 199758 | K21: 6924342
D22: Receivables - net | K22: 3027184
C23: Capital assets:
D24: Non-depreciable | H24: 417714348 | I24: 946740 | J24: =SUM(H24:I24) -> 418661088 | K24: 40031303
D25: Depreciable, net | H25: 92729097 | I25: 8300519 | J25: =SUM(H25:I25) -> 101029616 | K25: 205634180
C27: Total Assets | H27: =SUM(H8:H25) -> 826869753 | I27: =SUM(I8:I25) -> 11160760 | J27: =SUM(J8:J25) -> 838030513 | K27: =SUM(K8:K25) -> 398498358
A29: DEFERRED OUTFLOWS OF RESOURCES
C30: Deferred amount on refunding | K30: 346864
A32: LIABILITIES
C33: Accounts payable and other accrued liabilities | H33: 8484448 | I33: 176343 | J33: =SUM(H33:I33) -> 8660791 | K33: 9637074
C34: Intergovernmental payable | H34: 3403953 | J34: =SUM(H34:I34) -> 3403953 | K34: 1157830
C35: Due to primary government | J35: =SUM(H35:I35) -> 0 | K35: 222898
C36: Due to component units | H36: 458224 | J36: =SUM(H36:I36) -> 458224
C37: Unearned revenue | H37: 1102114 | J37: =SUM(H37:I37) -> 1102114 | K37: 100462
C38: Liabilities payable from restricted assets | I38: 114513 | J38: =SUM(H38:I38) -> 114513 | K38: 729820
C39: Other liabilities | H39: 532001 | J39: =SUM(H39:I39) -> 532001 | K39: 391374
C40: Noncurrent liabilities:
D41: Due within one year | H41: 2847845 | I41: 40835 | J41: =SUM(H41:I41) -> 2888680 | K41: 7644678
D42: Due in more than one year | H42: 6582203 | I42: 316086 | J42: =SUM(H42:I42) -> 6898289 | K42: 45777600
D44: Total Liabilities | H44: =SUM(H33:H42) -> 23410788 | I44: =SUM(I33:I42) -> 647777 | J44: =SUM(J33:J42) -> 24058565 | K44: =SUM(K33:K42) -> 65661736
A46: DEFERRED INFLOWS OF RESOURCES
C47: Uavailable revenue - property taxes | H47: 47202105 | J47: =SUM(H47:I47) -> 47202105 | K47: 15598437
A49: NET ASSETS
B50: Net investment in capital assets | H50: 510443445 | I50: 8890338 | J50: =SUM(H50:I50) -> 519333783 | K50: 210897698
B51: Restricted for:
C52: Debt service | I52: 103710 | J52: =SUM(H52:I52) -> 103710 | K52: 2971793
C53: External legal constraints | H53: 106738240 | J53: =SUM(H53:I53) -> 106738240
C54: Capital improvement projects | H54: 59552603 | J54: =SUM(H54:I54) -> 59552603 | K54: 1975847
B55: Unrestricted | H55: 79522572 | I55: 1518935 | J55: =SUM(H55:I55) -> 81041507 | K55: 101739710
C57: Total Net Assets | H57: =SUM(H50:H55) -> 756256860 | I57: =SUM(I50:I55) -> 10512983 | J57: =SUM(J50:J55) -> 766769843 | K57: =SUM(K49:K55) -> 317585048
C59: Total Liabilities and Net Assets | H59: =SUM(H44+H57+H47) -> 826869753 | I59: =SUM(I44+I57+I47) -> 11160760 | J59: =SUM(J44+J57+J47) -> 838030513 | K59: =SUM(K44+K57+K47) -> 398845221

Sheet Caldwell
C1: Caldwell Parish 2013 Statement of Net Assets
C2: Issued: December 31, 2013
G4: Governmental Activities
A5: ASSETS
B6: Cash and cash equivalents | G6: 6482087
B7: Receivables | G7: 1978585
B8: Capital assets, net of accumulated depreciation | G8: 11719166
B10: Total Assets | G10: =SUM(G6:G8) -> 20179838
A12: LIABILITIES
B13: Accounts, salaries, and other payables | G13: 152562
B14: Due to other agencies | G14: 57698
B15: Compensated absences payable | G15: 119478
C17: Total Liabilities | G17: =SUM(G13:G15) -> 329738
A19: NET ASSETS
B20: Net investment in capital assets | G20: 11719166
B21: Restricted | G21: 5837212
B22: Unrestricted | G22: 2293722
B24: Total Net Assets | G24: =SUM(G20:G22) -> 19850100
B26: Total Liabilities and Net Assets | G26: =SUM(G17+G24) -> 20179838

Sheet Cameron
C1: Cameron Parish 2013 Statement of Net Assets
C2: Issued: December 31, 2013
G4: Governmental Activities
A5: ASSETS
B6: Cash | G6: 28095654
B7: Receivables, net | G7: 19930829
B8: Inventory, at cost | G8: 1839555
B9: Other | G9: 85154
B10: Capital assets, net of accumulated depreciation | G10: 111753810
B12: Total Assets | G12: =SUM(G6:G10) -> 161705002
A14: LIABILITIES
B15: Accounts, salaries, and other payables | G15: 4610520
B16: Due to other agencies | G16: 3695066
B17: Unearned revenue | G17: 17231
B18: Interest payable | G18: 104867
B19: Long-term liabilities:
C20: Due within one year | G20: 1892917
C21: Due after one year | G21: 5190396
C23: Total Liabilities | G23: =SUM(G15:G21) -> 15510997
A25: NET ASSETS
B26: Invested in capital assets, net of related debt | G26: 104565630
B27: Net position - restricted for:
C28: Judicial | G28: 6377
C29: Debt service | G29: 1468574
C30: Tourism development | G30: 35404
C31: Inventories | G31: 1839555
C32: Prepaid expenses | G32: 64152
B33: Net position - unrestricted | G33: 38214313
B35: Total Net Assets | G35: =SUM(G26:G33) -> 146194005
B37: Total Liabilities and Net Assets | G37: =SUM(G23+G35) -> 161705002

Sheet Catahoula
D1: Catahoula Parish 2013 Statement of Net Assets
D2: Issued: December 31, 2013
H4: Primary Government
H5: Governmental Activities | I5: Component Units
A6: ASSETS
C7: Cash and cash equivalents | H7: 1908979 | I7: 131356
C8: Cash restricted for debt service | H8: 26325
C9: Receivables | H9: 1411486 | I9: 14280
C10: Other assets | H10: 81766
C11: Capital assets, net of accumulated depreciation | H11: 5862816 | I11: 88616
C13: Total Assets | H13: =SUM(H7:H11) -> 9291372 | I13: =SUM(I7:I11) -> 234252
A15: LIABILITIES
C16: Accounts, salaries, and other payables | H16: 551794 | I16: 490
C17: Compensated absences | H17: 27615
C18: Certificates of indebtedness due within one year | H18: 120000
C19: Certificates of indebtedness due in more than one | H19: 51000
D21: Total Liabilities | H21: =SUM(H16:H19) -> 750409 | I21: =SUM(I16:I19) -> 490
A23: DEFERRED INFLOWS
C24: Grant revenues pending | H24: 14777
A26: NET ASSETS
B27: Net investment in capital assets | H27: 5862816 | I27: 88616
B28: Unrestricted net position | H28: 2663370 | I28: 145146
C30: Total Net Assets | H30: =SUM(H27:H28) -> 8526186 | I30: =SUM(I27:I28) -> 233762
C32: Total Liabilities and Net Assets | H32: =SUM(H21+H30+H24) -> 9291372 | I32: =SUM(I30+I21) -> 234252

Sheet Claiborne
C1: Claiborne Parish 2013 Statement of Net Assets
C2: Issued: December 31, 2013
G4: Governmental Activities
A5: ASSETS
B6: Cash and cash equivalents | G6: 7547110
B7: Investments | G7: 28082
B8: Receivables | G8: 3215328
B9: Deferred charges | G9: 113163
B10: Capital assets, net of accumulated depreciation | G10: 7059807
B12: Total Assets | G12: =SUM(G6:G10) -> 17963490
A14: LIABILITIES
B15: Accounts, salaries, and other payables | G15: 643570
B16: Due to other agencies | G16: 16368
B17: Deferred revenue | G17: 15626
B18: Compensated absences payable | G18: 50773
B19: Bonds payable within one year | G19: 155000
B20: Bonds payable in more than one year | G20: 1700000
C22: Total Liabilities | G22: =SUM(G15:G20) -> 2581337
A24: NET ASSETS
B25: Net investment in capital assets | G25: 5048392
B26: Restricted for:
C27: General government | G27: 804147
C28: General government - judicial | G28: 1473326
C29: Public works | G29: 876596
C30: Public safety | G30: 256431
C31: Health and welfare | G31: 253852
C32: Culture and recreation | G32: 995881
B33: Unrestricted | G33: 5673528
B35: Total Net Assets | G35: =SUM(G25:G33) -> 15382153
B37: Total Liabilities and Net Assets | G37: =SUM(G22+G35) -> 17963490

Sheet Concordia
C1: Concordia Parish 2013 Statement of Net Assets
C2: Issued: December 31, 2013
G4: Governmental Activities
A5: ASSETS
B6: Cash | G6: 5653482
B7: Cash - restricted | G7: 2396243
B8: Receivables | G8: 2125063
B9: Accrued interest | G9: 2658
B10: Capital assets (net) | G10: 10920531
B12: Total Assets | G12: =SUM(G6:G10) -> 21097977
A14: LIABILITIES
B15: Current liabilities:
C16: Accounts payable | G16: 102093
C17: Interest payable | G17: 277708
C18: Long-term liabilities due in one year | G18: 395818
B19: Noncurrent liabilities:
C20: Long-term liabilities due in more than one year | G20: 9404258
C22: Total Liabilities | G22: =SUM(G15:G20) -> 10179877
A24: NET ASSETS
B25: Invested in capital assets, net of related debt | G25: 1120455
B26: Restricted for:
C27: Debt service | G27: 2396243
C28: Special revenue projects | G28: 4394633
B29: Unrestricted | G29: 3006769
B31: Total Net Assets | G31: =SUM(G25:G29) -> 10918100
B33: Total Liabilities and Net Assets | G33: =SUM(G22+G31) -> 21097977

Sheet DeSoto
D1: DeSoto Parish 2013 Statement of Net Assets
D2: Issued: December 31, 2013
H4: Primary Government
H5: Governmental Activities | I5: Business-Type Activities | J5: Total
A6: ASSETS
C7: Cash and cash equivalents | H7: 9790825 | I7: 265 | J7: =SUM(H7:I7) -> 9791090
C8: Investments | H8: 19901346 | J8: =SUM(H8:I8) -> 19901346
C9: Receivables (net of allowance for uncollectibles) | H9: 13582980 | I9: 4072 | J9: =SUM(H9:I9) -> 13587052
C10: Due from other governments | H10: 2650 | J10: =SUM(H10:I10) -> 2650
C11: Inventory | H11: 40185 | J11: =SUM(H11:I11) -> 40185
C12: Capital assets, net | H12: 75371606 | I12: 10175 | J12: =SUM(H12:I12) -> 75381781
C14: Total Assets | H14: =SUM(H7:H12) -> 118689592 | I14: =SUM(I7:I12) -> 14512 | J14: =SUM(J7:J12) -> 118704104
A16: LIABILITIES
C17: Accounts payable | H17: 1173758 | I17: 2331 | J17: =SUM(H17:I17) -> 1176089
C18: Deposit balances | H18: 1100 | I18: 270 | J18: =SUM(H18:I18) -> 1370
C19: Advance from grantors | H19: 67825 | J19: =SUM(H19:I19) -> 67825
C20: Due to other governments | H20: 260166 | J20: =SUM(H20:I20) -> 260166
C21: Landfill post closure liability | H21: 2165606 | J21: =SUM(H21:I21) -> 2165606
C22: Compensated absences | H22: 284258 | J22: =SUM(H22:I22) -> 284258
C23: Other postemployment benefit obligation | H23: 2466192 | J23: =SUM(H23:I23) -> 2466192
C24: Long-term liabilities:
D25: Due within one year | H25: 5641 | J25: =SUM(H25:I25) -> 5641
D26: Due in more than one year | H26: 5280 | J26: =SUM(H26:I26) -> 5280
D28: Total Liabilities | H28: =SUM(H17:H26) -> 6429826 | I28: =SUM(I17:I26) -> 2601 | J28: =SUM(J17:J26) -> 6432427
A30: NET ASSETS
B31: Net investment in capital assets | H31: 75360685 | I31: 10175 | J31: =SUM(H31:I31) -> 75370860
B32: Restricted for:
C33: Airport | H33: 7402456 | J33: =SUM(H33:I33) -> 7402456
C34: District court | H34: 98450 | J34: =SUM(H34:I34) -> 98450
C35: Public safety | H35: 4730847 | J35: =SUM(H35:I35) -> 4730847
C36: Roads | H36: 4233180 | J36: =SUM(H36) -> 4233180
C37: Sanitation | H37: 12418900 | J37: =SUM(H37) -> 12418900
C38: Health and welfare | H38: 6995 | J38: =SUM(H38) -> 6995
C39: Witness and juror fees | H39: 394991 | J39: =SUM(H39:I39) -> 394991
B40: Unrestricted | H40: 7613262 | I40: 1736 | J40: =SUM(H40:I40) -> 7614998
C42: Total Net Assets | H42: =SUM(H31:H40) -> 112259766 | I42: =SUM(I31:I40) -> 11911 | J42: =SUM(J31:J40) -> 112271677
C44: Total Liabilities and Net Assets | H44: =SUM(H42+H28) -> 118689592 | I44: =SUM(I42+I28) -> 14512 | J44: =SUM(J42+J28) -> 118704104

Sheet East Baton Rouge
D1: East Baton Rouge Parish 2013 Statement of Net Assets
D2: Issued: December 31, 2013
H4: Primary Government
H5: Governmental Activities | I5: Business-Type Activities | J5: Total | K5: Component Unit
A6: ASSETS
B7: Current Assets
C8: Cash and cash equivalents (note 3) | H8: 201411313 | I8: 117820392 | J8: =SUM(H8:I8) -> 319231705 | K8: 25523322
C9: Investments (note 3) | H9: 180338007 | I9: 121601048 | J9: =SUM(H9:I9) -> 301939055
C10: Receivables--net (note 13) | H10: 51943230 | I10: 16302378 | J10: =SUM(H10:I10) -> 68245608 | K10: 15586464
C11: Due from other governments (note 11) | H11: 83097626 | I11: 5285858 | J11: =SUM(H11:I11) -> 88383484 | K11: 1552267
C12: Prepaid items | H12: 767695 | I12: 209424 | J12: =SUM(H12:I12) -> 977119 | K12: 531507
C13: Loans receivable | H13: 3530623 | J13: =SUM(H13:I13) -> 3530623 | K13: 1243278
C14: Inventory | H14: 846296 | I14: 51347 | J14: =SUM(H14:I14) -> 897643 | K14: 3020853
C15: Net pension asset | K15: 1590755
C16: Other assets | K16: 599504
C17: Restricted assets:
D18: Cash and cash equivalents (note 3) | I18: 171497464 | J18: =SUM(H18:I18) -> 171497464 | K18: 12012409
D19: Investments (note 3) | I19: 215767910 | J19: =SUM(H19:I19) -> 215767910
D20: Receivables--net (note 13) | I20: 328901 | J20: =SUM(H20:I20) -> 328901
D21: Prepaid items | I21: 434949 | J21: =SUM(H21:I21) -> 434949
C22: Investment in joint venture (note 19) | I22: 1973958 | J22: =SUM(H22:I22) -> 1973958
C23: Capital assets:
D24: Non-depreciable | H24: 193385057 | I24: 254999935 | J24: =SUM(H24:I24) -> 448384992
D25: Depreciable, net | H25: 666566380 | I25: 1405099819 | J25: =SUM(H25:I25) -> 2071666199 | K25: 110619580
C27: Total Assets | H27: =SUM(H8:H25) -> 1381886227 | I27: =SUM(I8:I25) -> 2311373383 | J27: =SUM(J8:J25) -> 3693259610 | K27: =SUM(K8:K25) -> 172279939
A29: Deferred Outflows of Resources
B30: Deferred amount on refunding | H30: 6298894 | I30: 3831563 | J30: =SUM(H30:I30) -> 10130457 | K30: 0
B31: Deferred outflows on derivative instruments | H31: 10609916 | I31: 41015560 | J31: =SUM(H31:I31) -> 51625476 | K31: 0
C33: Total deferred outflows of resources | H33: =SUM(H30:H31) -> 16908810 | I33: =SUM(I30:I31) -> 44847123 | J33: =SUM(J30:J31) -> 61755933 | K33: =SUM(K30:K31) -> 0
A35: LIABILITIES
C36: Accounts payable and other current liabilities | H36: 37439384 | I36: 50703777 | J36: =SUM(H36:I36) -> 88143161 | K36: 1930897
C37: Due to other governments | H37: 7390530 | J37: =SUM(H37:I37) -> 7390530 | K37: 375598
C38: Accrued payables | H38: 15541911 | I38: 26034074 | J38: =SUM(H38:I38) -> 41575985 | K38: 1345157
C39: Unearned revenue | H39: 1709094 | I39: 1224069 | J39: =SUM(H39:I39) -> 2933163
C40: Deposits and escrow accounts | H40: 22503554 | J40: 22503554
C41: Other liabilities | K41: 420865
C42: Noncurrent liabilities (note 10): | J42: =SUM(H42:I42) -> 0
D43: Due within one year | H43: 33495310 | I43: 18764052 | J43: =SUM(H43:I43) -> 52259362 | K43: 3270518
D44: Due in more than one year | H44: 665555682 | I44: 1333967445 | J44: =SUM(H44:I44) -> 1999523127 | K44: 117232768
D46: Total Liabilities | H46: =SUM(H36:H44) -> 783635465 | I46: =SUM(I36:I44) -> 1430693417 | J46: =SUM(J36:J44) -> 2214328882 | K46: =SUM(K36:K44) -> 124575803
A48: Deferred Inflows of Reources
B49: Resources received before the requirements | H49: 526276 | I49: 0 | J49: =SUM(H49:I49) -> 526276 | K49: 0
A51: NET ASSETS
B52: Net investment in capital assets | H52: 626659126 | I52: 704171906 | J52: =SUM(H52:I52) -> 1330831032 | K52: 14980551
B53: Restricted for (note 14):
C54: Capital projects | H54: 87023236 | I54: 9649394 | J54: =SUM(H54:I54) -> 96672630
C55: Debt service | H55: 8693142 | I55: 51268170 | J55: =SUM(H55:I55) -> 59961312 | K55: 12282495
C56: Passenger facility charges | I56: 391611 | J56: =SUM(H56:I56) -> 391611
C57: External legal constraints | H57: 102785974 | I57: 10000000 | J57: =SUM(H57:I57) -> 112785974 | K57: 8946251
B58: Unrestricted | H58: -210528182 | I58: 150046008 | J58: =SUM(H58:I58) -> -60482174 | K58: 11494839
C60: Total Net Assets | H60: =SUM(H52:H58) -> 614633296 | I60: =SUM(I52:I58) -> 925527089 | J60: =SUM(J52:J58) -> 1540160385 | K60: =SUM(K51:K58) -> 47704136
C62: Total Liabilities and Net Assets | H62: =SUM(H46+H60+H49) -> 1398795037 | I62: =SUM(I46+I60+I49) -> 2356220506 | J62: =SUM(J46+J60+J49) -> 3755015543 | K62: =SUM(K46+K60+K49) -> 172279939

Sheet East Carroll
D1: East Carroll Parish 2013 Statement of Net Assets
D2: Issued: December 31, 2013
H4: Primary Government
H5: Governmental Activities | I5: Business-Type Activities | J5: Total
A6: ASSETS
C7: Cash and cash equivalents | H7: 2754931 | I7: 15702 | J7: =SUM(H7:I7) -> 2770633
C8: Investments | H8: 836856 | J8: =SUM(H8:I8) -> 836856
C9: Receivables | H9: 2244765 | J9: =SUM(H9:I9) -> 2244765
C10: Prepaid items | I10: 3090 | J10: =SUM(H10:I10) -> 3090
C11: Cash and cash equivalents - restricted | I11: 15218 | J11: =SUM(H11:I11) -> 15218
C12: Capital assets not being depreciated | H12: 637429 | J12: =SUM(H12:I12) -> 637429
C13: Capital assets, net of accumulated depreciation | H13: 4917326 | J13: =SUM(H13:I13) -> 4917326
C15: Total Assets | H15: =SUM(H7:H13) -> 11391307 | I15: =SUM(I7:I13) -> 34010 | J15: =SUM(J7:J13) -> 11425317
A17: LIABILITIES
C18: Accounts payable | H18: 218903 | I18: 5776 | J18: =SUM(H18:I18) -> 224679
C19: Interest payable | H19: 5987 | J19: =SUM(H19:I19) -> 5987
C20: Unearned revenue | I20: 151 | J20: =SUM(H20:I20) -> 151
C21: Long-term liabilities:
D22: Due within one year | H22: 120776 | I22: 744 | J22: =SUM(H22:I22) -> 121520
D23: Due in more than one year | H23: 423316 | J23: =SUM(H23:I23) -> 423316
D25: Total Liabilities | H25: =SUM(H18:H23) -> 768982 | I25: =SUM(I18:I23) -> 6671 | J25: =SUM(J18:J23) -> 775653
A27: NET ASSETS
B28: Net investment in capital assets | H28: 5017234 | J28: =SUM(H28:I28) -> 5017234
B29: Restricted for:
C30: Debt service | H30: 96497 | J30: =SUM(H30:I30) -> 96497
C31: Road maintenance | H31: 1440460 | J31: =SUM(H31:I31) -> 1440460
C32: Garbage | H32: 791427 | J32: =SUM(H32:I32) -> 791427
C33: Library | H33: 590967 | J33: =SUM(H33:I33) -> 590967
C34: Drainage | H34: 795219 | J34: =SUM(H34:I34) -> 795219
C35: Airport hangar | H35: 3057 | J35: =SUM(H35:I35) -> 3057
C36: Rural fire protection | H36: 380303 | J36: =SUM(H36:I36) -> 380303
C37: LSU/SU Extension | H37: 181990 | J37: =SUM(H37:I37) -> 181990
C38: Health unit | H38: 512372 | J38: =SUM(H38:I38) -> 512372
C39: Housing assistance payments | I39: 15218 | J39: =SUM(H39:I39) -> 15218
B40: Unrestricted | H40: 812799 | I40: 12121 | J40: =SUM(H40:I40) -> 824920
C42: Total Net Assets | H42: =SUM(H28:H40) -> 10622325 | I42: =SUM(I28:I40) -> 27339 | J42: =SUM(J28:J40) -> 10649664
C44: Total Liabilities and Net Assets | H44: =SUM(H42+H25) -> 11391307 | I44: =SUM(I42+I25) -> 34010 | J44: =SUM(J42+J25) -> 11425317

Sheet East Feliciana
C1: East Feliciana Parish 2013 Statement of Net Assets
C2: Issued: December 31, 2013
G4: Governmental Activities
A5: ASSETS
B6: Cash and cash equivalents | G6: 5513411.8
B7: Receivables, net | G7: 838202.1
B8: Due from other funds | G8: 1597760
B9: Due from other governmental agencies | G9: 122932.96
B10: Capital assets, net | G10: 8313076.6
B12: Total Assets | G12: =SUM(G6:G10) -> 16385383
A14: LIABILITIES
B15: Accounts payable | G15: 235942.02
B16: Due to other funds | G16: 1452400.9
B17: Due to other governmental agencies | G17: 12350.44
B18: Notes payable | G18: 16548.42
B19: Compensated absences | G19: 13428
C21: Total Liabilities | G21: =SUM(G15:G19) -> 1730669.8
A23: NET ASSETS
B24: Net investment in capital assets | G24: 8313076.6
B25: Restricted for:
C26: Health unit operations/maintenance | G26: 532497.89
C27: Homeland security | G27: 49454.42
C28: Solid waste management | G28: 3333393
B29: Unrestricted | G29: 2426291.7
B31: Total Net Assets | G31: =SUM(G24:G29) -> 14654714
B33: Total Liabilities and Net Assets | G33: =G31+G21 -> 16385383

Sheet Evangeline
D1: Evangeline Parish 2013 Statement of Net Assets
D2: Issued: December 31, 2013
H4: Primary Government | K4: Component Unit
H5: Governmental Activities | I5: Business-Type Activities | J5: Total | K5: Criminal Court Fund
A6: ASSETS
C7: Cash and interest-bearing deposits | H7: 9772120 | I7: 100123 | J7: =SUM(H7:I7) -> 9872243
C8: Receivables, net | H8: 5534711 | I8: 14143 | J8: =SUM(H8:I8) -> 5548854 | K8: 84972
C9: Due from other governmental units | H9: 372502 | J9: =SUM(H9:I9) -> 372502 | K9: 6141
C10: Other assets | H10: 20960 | J10: =SUM(H10:I10) -> 20960
C11: Restricted assets:
D12: Cash and interest-bearing deposits | I12: 20831 | J12: =SUM(I12) -> 20831
D13: Investments | H13: 28970121 | J13: =SUM(H13:I13) -> 28970121
C14: Capital assets, net | H14: 24663497 | I14: 291100 | J14: =SUM(H14:I14) -> 24954597
C16: Total Assets | H16: =SUM(H7:H14) -> 69333911 | I16: =SUM(I7:I14) -> 426197 | J16: =SUM(J7:J14) -> 69760108 | K16: =SUM(K7:K14) -> 91113
A18: LIABILITIES
C19: Cash overdraft | H19: 44286 | J19: =SUM(H19:I19) -> 44286 | K19: 112041
C20: Accounts and other payables | H20: 453124 | I20: 1476 | J20: =SUM(H20:I20) -> 454600 | K20: 1159
C21: Accrued interest | H21: 94056 | J21: =SUM(H21:I21) -> 94056
C22: Performance bonds payable | H22: 300318 | J22: =SUM(H22:I22) -> 300318
C23: Unearned revenue | H23: 69456 | I23: 1175 | J23: =SUM(H23:I23) -> 70631
C24: Noncurrent liabilities:
D25: Portion due within one year:
E26: Compensated absences payable | H26: 8669 | J26: =SUM(H26:I26) -> 8669
E27: Capital lease payable | H27: 27459 | J27: =SUM(H27:I27) -> 27459
E28: Bonds and certificates payable | H28: 222000 | I28: 1819 | J28: =SUM(H28:I28) -> 223819
D29: Portion due after one year:
E30: Sewer deposits payable | H30: 10182 | I30: 11191 | J30: =SUM(H30:I30) -> 21373
E31: Compensated absences payable | H31: 52810 | J31: =SUM(H31:I31) -> 52810
E32: Capital lease payable | H32: 2338 | J32: =SUM(H32:I32) -> 2338
E33: Bonds and certificates payable | H33: 31902009 | I33: 59732 | J33: =SUM(H33:I33) -> 31961741
D35: Total Liabilities | H35: =SUM(H19:H33) -> 33186707 | I35: =SUM(I19:I33) -> 75393 | J35: =SUM(J19:J33) -> 33262100 | K35: =SUM(K19:K33) -> 113200
A37: DEFERRED INFLOWS OF RESOURCES
C38: Unearned rent | H38: 271333 | J38: =SUM(H38:I38) -> 271333
A40: NET ASSETS
B41: Net investment in capital assets | H41: 22524204 | I41: 231368 | J41: =SUM(H41:I41) -> 22755572
B42: Restricted for debt service | H42: 3177 | I42: 7821 | J42: =SUM(H42:I42) -> 10998
B43: Restricted for housing purposes | I43: 9853 | J43: =SUM(H43:I43) -> 9853
B44: Unrestricted (deficit) | H44: 13348490 | I44: 101762 | J44: =SUM(H44:I44) -> 13450252 | K44: -22086
C46: Total Net Assets | H46: =SUM(H41:H44) -> 35875871 | I46: =SUM(I41:I44) -> 350804 | J46: =SUM(J41:J44) -> 36226675 | K46: =SUM(K40:K44) -> -22086
C48: Total Liabilities and Net Assets | H48: =SUM(H46+H35+H38) -> 69333911 | I48: =SUM(I46+I35+I38) -> 426197 | J48: =SUM(J46+J35+J38) -> 69760108 | K48: =SUM(K46+K35+K38) -> 91114

Sheet Franklin
C1: Franklin Parish 2013 Statement of Net Assets
C2: Issued: December 31, 2013
G4: Governmental Activities
A5: ASSETS
B6: Cash and cash equivalents | G6: 7269664
B7: Receivables | G7: 3659846
B8: Prepaid assets | G8: 4140
B9: Capital assets (net) | G9: 17836416
B11: Total Assets | G11: =SUM(G6:G9) -> 28770066
A13: LIABILITIES
B14: Accounts payable | G14: 382154
B15: Payroll withholding payable | G15: 66963
B16: Compensated absences payable | G16: 131420
B17: Capital leases payable | G17: 49970
B18: Due to others (damage deposit) | G18: 20000
B19: Net OPEB obligation | G19: 1337359
C21: Total Liabilities | G21: =SUM(G14:G19) -> 1987866
A23: NET ASSETS
B24: Invested in capital assets, net of related debt | G24: 17786447
B25: Unrestricted | G25: 8995753
B27: Total Net Assets | G27: =SUM(G24:G25) -> 26782200
B29: Total Liabilities and Net Assets | G29: =SUM(G21+G27) -> 28770066

Sheet Grant
D1: Grant Parish 2013 Statement of Net Assets
D2: Issued: December 31, 2013
H4: Primary Government
H5: Governmental Activities | I5: Business-Type Activities | J5: Total
A6: ASSETS
C7: Cash and cash equivalents | H7: 1681553 | I7: 363999 | J7: =SUM(H7:I7) -> 2045552
C8: Receivables (net) | H8: 1486129 | I8: 105407 | J8: =SUM(H8:I8) -> 1591536
C9: Capital assets:
D10: Non depreciable capital assets
E11: Construction in progress | H11: 37900 | J11: =SUM(H11:I11) -> 37900
E12: Land | H12: 203250 | J12: =SUM(H12:I12) -> 203250
D13: Depreciable capital assets, net | H13: 5842328 | I13: 357194 | J13: =SUM(H13:I13) -> 6199522
C15: Total Assets | H15: =SUM(H7:H13) -> 9251160 | I15: =SUM(I7:I13) -> 826600 | J15: =SUM(J7:J13) -> 10077760
A17: LIABILITIES
C18: Accounts and other payables | H18: 379081 | I18: 33092 | J18: =SUM(H18:I18) -> 412173
C19: Deposits due others | I19: 76433 | J19: =SUM(H19:I19) -> 76433
C20: Unearned revenues | H20: 2266 | J20: =SUM(H20:I20) -> 2266
C21: Long-term liabilities:
D22: Compensated absences | H22: 42221 | I22: 9025 | J22: =SUM(H22:I22) -> 51246
D23: Notes payable:
E24: Due within one year | H24: 92877 | J24: =SUM(H24:I24) -> 92877
E25: Due in more than one year | H25: 339716 | J25: =SUM(H25:I25) -> 339716
D27: Total Liabilities | H27: =SUM(H18:H25) -> 856161 | I27: =SUM(I18:I25) -> 118550 | J27: =SUM(J18:J25) -> 974711
A29: NET ASSETS
B30: Invested in capital assets, net of related debt | H30: 5650885 | I30: 357194 | J30: =SUM(H30:I30) -> 6008079
B31: Restricted:
C32: Maintenance | H32: 1893524 | J32: =SUM(H32:I32) -> 1893524
C33: Judicial | H33: 24781 | J33: =SUM(H33:I33) -> 24781
C34: Construction | H34: 51625 | J34: =SUM(H34:I34) -> 51625
B35: Unrestricted | H35: 774184 | I35: 350856 | J35: =SUM(H35:I35) -> 1125040
C37: Total Net Assets | H37: =SUM(H30:H35) -> 8394999 | I37: =SUM(I30:I35) -> 708050 | J37: =SUM(J30:J35) -> 9103049
C39: Total Liabilities and Net Assets | H39: =SUM(H37+H27) -> 9251160 | I39: =SUM(I37+I27) -> 826600 | J39: =SUM(J37+J27) -> 10077760

Sheet Iberia
D1: Iberia Parish 2013 Statement of Net Assets
D2: Issued: December 31, 2013
H4: Primary Government
H5: Governmental Activities | I5: Component Units
A6: ASSETS
C7: Cash and interest-bearing deposits | H7: 39934830 | I7: 39091186
C8: Investments | H8: 83378
C9: Receivables, net | H9: 8030264 | I9: 10729454
C10: Advance to component unit | H10: 1416411
C11: Due from other governmental agencies | H11: 5793561 | I11: 925334
C12: Due from primary government | I12: 627437
C13: Inventories | I13: 1951088
C14: Prepaid items | I14: 667027
C15: Investments in joint ventures | I15: 375146
C16: Restricted assets | I16: 3633711
C17: Capital assets:
D18: Non-depreciable | H18: 5456279 | I18: 13538519
D19: Depreciable, net | H19: 90480984 | I19: 60219171
C21: Total Assets | H21: =SUM(H7:H19) -> 151195707 | I21: =SUM(I7:I19) -> 131758073
A23: LIABILITIES
C24: Accounts payable | H24: 1802114 | I24: 3237190
C25: Accrued expenses | H25: 181539 | I25: 6909924
C26: Contracts and retainage payable | H26: 604712 | I26: 732472
C27: Due to other governmental agencies | H27: 337184 | I27: 91132
C28: Due to component unit | H28: 627437
C29: Advance from primary government | I29: 1416411
C30: Advances from grantors and others | H30: 171235 | I30: 110549
C31: Deposits | I31: 270125
C32: Accrued interest payable | H32: 42018 | I32: 126013
C33: Long-term liabilities:
D34: Other post employment benefits payable | H34: 3453813 | I34: 1514778
D35: Due within one year | H35: 1464872 | I35: 3107445
D36: Due in more than one year | H36: 9078674 | I36: 32542923
D38: Total Liabilities | H38: =SUM(H24:H36) -> 17763598 | I38: =SUM(I24:I36) -> 50058962
A40: NET ASSETS
B41: Net investment in capital assets | H41: 86345332 | I41: 52359053
B42: Restricted | H42: 564816 | I42: 12300232
B43: Unrestricted | H43: 46521961 | I43: 17039826
C45: Total Net Assets | H45: =SUM(H41:H43) -> 133432109 | I45: =SUM(I41:I43) -> 81699111
C47: Total Liabilities and Net Assets | H47: =SUM(H38+H45) -> 151195707 | I47: =SUM(I45+I38) -> 131758073

Sheet Iberville
D1: Iberville Parish 2013 Statement of Net Assets
D2: Issued: December 31, 2013
H4: Primary Government | K4: Total Component Units
H5: Governmental Activities | I5: Business-Type Activities | J5: Total | K5: Governmental Activities | L5: Business-type Activities
A6: ASSETS
B7: Current Assets
C8: Cash and cash equivalents | H8: 16410571 | I8: 1795376 | J8: =SUM(H8:I8) -> 18205947 | K8: 1177559 | L8: 712715
C9: Receivables (net of allowance for uncollectibles) | H9: 9074534 | I9: 995840 | J9: =SUM(H9:I9) -> 10070374 | K9: 3439297 | L9: 202002
C10: Inventories | I10: 132465 | J10: =SUM(H10:I10) -> 132465
C11: Prepaid items | H11: 870703 | J11: =SUM(H11:I11) -> 870703 | L11: 14931
C12: Other assets | H12: 100000 | I12: 348456 | J12: =SUM(H12:I12) -> 448456 | K12: 103972 | L12: 260524
C13: Restricted assets
D14: Cash and cash equivalents | I14: 882151 | J14: =SUM(H14:I14) -> 882151 | L14: 767572
C15: Capital assets (net of accumulated depreciation)
D16: Land | H16: 2975825 | I16: 193511 | J16: =SUM(H16:I16) -> 3169336 | K16: 435740
D17: Building and system | H17: 31725027 | I17: 10071429 | J17: =SUM(H17:I17) -> 41796456 | K17: 999067 | L17: 3405591
D18: Improvemetns other than building | H18: 55243002 | J18: =SUM(H18:I18) -> 55243002 | K18: 331118 | L18: 1757047
D19: Machinery and equipment | H19: 4023678 | I19: 154513 | J19: =SUM(H19:I19) -> 4178191 | K19: 368125 | L19: 1277720
D20: Construction in progress | H20: 6218861 | I20: 156733 | J20: =SUM(H20:I20) -> 6375594
C22: Total Assets | H22: =SUM(H8:H20) -> 126642201 | I22: =SUM(I8:I20) -> 14730474 | J22: =SUM(J8:J20) -> 141372675 | K22: =SUM(K8:K20) -> 6854878 | L22: =SUM(L8:L20) -> 8398102
A24: LIABILITIES
C25: Accounts payable and other current liabilities | H25: 2043820 | I25: 520051 | J25: =SUM(H25:I25) -> 2563871 | K25: 28218 | L25: 74793
C26: Matured bonds and interest payable | J26: =SUM(H26:I26) -> 0
C27: Accrued interest payable | J27: =SUM(H27:I27) -> 0
C28: Bank overdraft liability | J28: =SUM(H28:I28) -> 0
C29: Other payables | H29: 795376 | J29: =SUM(H29:I29) -> 795376 | K29: 159045
C30: Liabilities payable from restricted assets | I30: 279573 | J30: =SUM(H30:I30) -> 279573 | L30: 122661
C31: Noncurrent liabilities:
D32: Other post employment benefits | H32: 485401 | J32: =SUM(H32:I32) -> 485401 | K32: 69779
D33: Due in one year | H33: 1091504 | I33: 55000 | J33: =SUM(H33:I33) -> 1146504 | K33: 9000 | L33: 73441
D34: Due in more than one year | H34: 17258488 | I34: 545000 | J34: =SUM(H34:I34) -> 17803488 | K34: 320458 | L34: 3337547
D36: Total Liabilities | H36: =SUM(H25:H34) -> 21674589 | I36: =SUM(I25:I34) -> 1399624 | J36: =SUM(J25:J34) -> 23074213 | K36: =SUM(K25:K34) -> 586500 | L36: =SUM(L25:L34) -> 3608442
A38: Deferred Inflows (Outflows)
B39: Prepaid rental fees | H39: 0 | I39: 0 | J39: 0 | K39: 12809 | L39: 0
D41: Total deferred inflows (outflows) | H41: 0 | I41: 0 | J41: 0 | K41: 12809 | L41: 0
A43: NET ASSETS
B44: Invested in capital assets, net of related debt | H44: 84078829 | I44: 10031185 | J44: =SUM(H44:I44) -> 94110014 | K44: 2066050 | L44: 3064555
B45: Restricted for:
C46: Public building maintenance | H46: 1087400 | J46: =SUM(H46:I46) -> 1087400
C47: Drainage | H47: 2465926 | J47: =SUM(H47:I47) -> 2465926
C48: Solid waste | H48: 2886771 | J48: =SUM(H48:I48) -> 2886771
C49: Fire protection | H49: 2522779 | J49: =SUM(H49:I49) -> 2522779
C50: Emergency services | H50: 704838 | J50: =SUM(H50:I50) -> 704838
C51: Debt service | H51: 2368629 | J51: =SUM(H51:I51) -> 2368629 | L51: 604787
C52: Other | H52: 5259184 | I52: 545000 | J52: =SUM(H52:I52) -> 5804184
B53: Unrestricted | H53: 3593255 | I53: 2754666 | J53: =SUM(H53:I53) -> 6347921 | K53: 4189519 | L53: 1120318
C55: Total Net Assets | H55: =SUM(H44:H53) -> 104967611 | I55: =SUM(I44:I53) -> 13330851 | J55: =SUM(J44:J53) -> 118298462 | K55: =SUM(K44:K53) -> 6255569 | L55: =SUM(L43:L53) -> 4789660
C57: Total Liabilities and Net Assets | H57: =SUM(H36+H55) -> 126642200 | I57: =SUM(I36+I55) -> 14730475 | J57: =SUM(J36+J55) -> 141372675 | K57: =SUM(K36+K55) -> 6842069 | L57: =SUM(L36+L55) -> 8398102

Sheet Jackson
C1: Jackson Parish 2013 Statement of Net Assets
C2: Issued: December 31, 2013
G4: Governmental Activities
A5: ASSETS
B6: Cash and cash equivalents | G6: 9622291
B7: Receivables | G7: 4755981
B8: Prepaid items | G8: 70256
B9: Capital assets:
C10: Land and construction in progress | G10: 1117140
C11: Capital assets, net of depreciation | G11: 15282488
B13: Total Assets | G13: =SUM(G6:G11) -> 30848156
A15: LIABILITIES
B16: Accounts, salaries, and other payables | G16: 342065
B17: Security deposits | G17: 31249
B18: Long-term liabilities:
C19: Due within one year | G19: 139468
C20: Due in more than one year | G20: 443412
C22: Total Liabilities | G22: =SUM(G16:G20) -> 956194
A24: NET ASSETS
B25: Net investment in capital assets | G25: 16399628
B26: Restricted for:
C27: Road maintenance (Road, Sales tax and asphalt funds) | G27: 4726132
C28: Waste management | G28: 1518466
C29: Library | G29: 3226859
C30: Health unit | G30: 152363
C31: Tourism | G31: 45549
C32: Landfill closure | G32: 547090
C33: Industrial district | G33: 252644
C34: Grant funds | G34: 19871
C35: Grand jury and witness fees | G35: 13023
B36: Unrestricted | G36: 2990337
B38: Total Net Assets | G38: =SUM(G25:G36) -> 29891962
B40: Total Liabilities and Net Assets | G40: =SUM(G22+G38) -> 30848156

Sheet Jefferson Davis
C1: Jefferson Davis Parish 2013 Statement of Net Assets
C2: Issued: December 31, 2013
G4: Governmental Activities
A5: ASSETS
B6: Cash and cash equivalents | G6: 17705770
B7: Investments | G7: 2101032
B8: Receivables | G8: 799744
B9: Prepaid items | G9: 68433
B10: Restricted cash and cash equivalents | G10: 2695412
B11: Capital assets (net) | G11: 33564914
B13: Total Assets | G13: =SUM(G6:G11) -> 56935305
A15: DEFERRED OUTFLOWS OF RESOURCES
B16: Deferred bond issuance costs | G16: 84323
A18: LIABILITIES
B19: Accounts, salaries, and other payables | G19: 827133
B20: Contracts payable | G20: 31096
B21: Deposits due others | G21: 368500
B22: Other liabilities | G22: 140
B23: Accrued interest payable | G23: 301928
B24: Liability for other post-employment benefits | G24: 1732554
B25: Current portion of bonds payable | G25: 1000000
B26: Current portion of capital leases payable | G26: 112761
B27: Capital leases payable | G27: 645690
B28: Bonds payable | G28: 15670000
C30: Total Liabilities | G30: =SUM(G19:G28) -> 20689802
A32: DEFERRED INFLOWS OF RESOURCES
B33: Deferred revenues | G33: 46979
A35: NET ASSETS
B36: Net investment in capital assets | G36: 15843535
B37: Restricted for:
C38: Public safety | G38: 3901978
C39: Public works | G39: 7087706
C40: Health and welfare | G40: 366708
C41: Debt service | G41: 2652177
C42: Capital projects | G42: 2477
C43: Other general government | G43: 1251900
B44: Unrestricted | G44: 5176366
B46: Total Net Assets | G46: =SUM(G36:G44) -> 36282847
B48: Total Liabilities and Net Assets | G48: =SUM(G30+G46+G33) -> 57019628

Sheet Jefferson
D1: Jefferson Parish 2013 Statement of Net Assets
D2: Issued: December 31, 2013
G3: (amounts in thousands)
H5: Primary Government
H6: Governmental Activities | I6: Business-Type Activities | J6: Total | K6: Component Unit
A7: ASSETS
B8: Current Assets
C9: Cash and cash equivalents | H9: 18642000 | I9: 4829000 | J9: =SUM(H9:I9) -> 23471000 | K9: 26503000
C10: Investments | H10: 75588000 | J10: =SUM(H10:I10) -> 75588000 | K10: 87829000
C11: Share of pooled assets | H11: 470672000 | I11: 20780000 | J11: =SUM(H11:I11) -> 491452000
C12: Receivables, net of allowances for
D13: estimated uncollectibles:
D14: Interest | H14: 107000 | J14: =SUM(H14:I14) -> 107000 | K14: 298000
D15: Ad valorem tax | H15: 176257000 | I15: 9065000 | J15: =SUM(H15:I15) -> 185322000
D16: Accounts | H16: 5215000 | I16: 6071000 | J16: =SUM(H16:I16) -> 11286000 | K16: 82451000
D17: Notes | K17: 6587000
D18: Mortgage loans
D19: Intergovernmental | H19: 65745000 | I19: 28000 | J19: =SUM(H19:I19) -> 65773000 | K19: 1578000
D20: Other | K20: 10645000
C21: Inventories | H21: 3077000 | I21: 8250000 | J21: =SUM(H21:I21) -> 11327000 | K21: 15636000
C22: Prepaid items | K22: 19270000
C23: Restricted assets:
D24: Cash and cash equivalents | I24: 82000 | J24: =SUM(I24) -> 82000
D25: Investments | I25: 15681000 | J25: =SUM(H25:I25) -> 15681000 | K25: 247889000
D26: Share of pooled assets | I26: 44315000 | J26: =SUM(H26:I26) -> 44315000
D27: Receivables | I27: 5227000 | J27: =SUM(H27:I27) -> 5227000
C29: Total Current Assets | H29: =SUM(H9:H27) -> 815303000 | I29: =SUM(I9:I27) -> 114328000 | J29: =SUM(J9:J27) -> 929631000 | K29: =SUM(K9:K27) -> 498686000
B31: Noncurrent Assets
C32: Restricted assets:
D33: Deposits and other assets | H33: 7938000 | J33: =SUM(H33:I33) -> 7938000 | K33: 28679000
C34: Mortgage loans receivable | K34: 70850000
C35: Capital assets not being depreciated | H35: 243181000 | I35: 16703000 | J35: =SUM(H35:I35) -> 259884000
C36: Capital assets being depreciated, net | H36: 930821000 | I36: 529954000 | J36: =SUM(H36:I36) -> 1460775000 | K36: 378862000
C38: Total Noncurrent Assets | H38: =SUM(H31:H36) -> 1181940000 | I38: =SUM(I31:I36) -> 546657000 | J38: =SUM(J31:J36) -> 1728597000 | K38: =SUM(K31:K36) -> 478391000
C40: Total Assets | H40: =SUM(H38+H29) -> 1997243000 | I40: =SUM(I38+I29) -> 660985000 | J40: =SUM(J29+J38) -> 2658228000 | K40: =SUM(K29+K38) -> 977077000
B42: Deferred outflows of resources
C43: Deferred charges on bond issuance costs | H43: 7537000 | J43: =SUM(H43:I43) -> 7537000
C45: Total Deferred Outflows of Resources | H45: =H43 -> 7537000 | I45: =I43 -> 0 | J45: =J43 -> 7537000 | K45: =K43 -> 0
A47: LIABILITIES
B48: Current liabilities
C49: Accounts and contracts payable | H49: 37457000 | I49: 186000 | J49: =SUM(H49:I49) -> 37643000 | K49: 28756000
C50: Claims and judgments payable | H50: 5615000 | J50: =SUM(H50:I50) -> 5615000
C51: Intergovernmental payable | H51: 2189000 | J51: =SUM(H51:I51) -> 2189000
C52: Current portion of long term debt | H52: 31102000 | I52: 66000 | J52: =SUM(H52:I52) -> 31168000 | K52: 8729000
C53: Deposits | H53: 81000 | J53: =SUM(H53:I53) -> 81000
C54: Accrued salaries payable | H54: 5241000 | J54: =SUM(H54:I54) -> 5241000
C55: Accrued interest payable | H55: 1519000 | J55: =SUM(H55:I55) -> 1519000 | K55: 1980000
C56: Other payables and accruals | H56: 4036000 | I56: 4211000 | J56: =SUM(H56:I56) -> 8247000 | K56: 46532000
C57: Unearned revenue | H57: 180070000 | I57: 9074000 | J57: =SUM(H57:I57) -> 189144000
C58: Payable from restricted assets:
D59: Accounts payable | I59: 2860000 | J59: =SUM(H59:I59) -> 2860000
D60: Retainage interset payable | I60: 305000 | J60: =SUM(H60:I60) -> 305000
D61: Accrued interest payable | J61: =SUM(H61:I61) -> 0 | K61: 8706000
D62: Other payables | J62: =SUM(H62:I62) -> 0
D63: Unearned revenue | I63: 2525000 | J63: =SUM(H63:I63) -> 2525000
D65: Total Current Liabilities | H65: =SUM(H49:H63) -> 267310000 | I65: =SUM(I49:I63) -> 19227000 | J65: =SUM(J49:J63) -> 286537000 | K65: =SUM(K49:K63) -> 94703000
B67: Noncurrent liabilities
C68: Customers' deposits | I68: 8827000 | J68: =SUM(H68:I68) -> 8827000
C69: Due in more than one year | H69: 463060000 | I69: 4723000 | J69: =SUM(H69:I69) -> 467783000 | K69: 404975000
D71: Total Noncurrent Liabilities | H71: =SUM(H67:H69) -> 463060000 | I71: =SUM(I67:I69) -> 13550000 | J71: =SUM(J67:J69) -> 476610000 | K71: =SUM(K67:K69) -> 404975000
D73: Total Liabilities | H73: =SUM(H65+H71) -> 730370000 | I73: =SUM(I71+I65) -> 32777000 | J73: =SUM(J71+J65) -> 763147000 | K73: =SUM(K65+K71) -> 499678000
A75: NET ASSETS
B76: Invested in capital assets, net of related debt | H76: 800435000 | I76: 546657000 | J76: =SUM(H76:I76) -> 1347092000 | K76: 89244000
B77: Restricted for:
C78: Judges annuitles | H78: 1681000 | J78: =SUM(H78:I78) -> 1681000
C79: General government | H79: 33000 | J79: =SUM(H79:I79) -> 33000
C80: Public safety | H80: 30618000 | J80: =SUM(H80:I80) -> 30618000
C81: Public works | H81: 34836000 | J81: =SUM(H81) -> 34836000
C82: Transit | H82: 20674000 | J82: =SUM(H82) -> 20674000
C83: Health and welfare | H83: 6280000 | J83: =SUM(H83) -> 6280000
C84: Culture and recreation | H84: 38765000 | J84: =SUM(H84) -> 38765000
C85: Economic development | H85: 3693000 | J85: =SUM(H85) -> 3693000
C86: Urban redevelopment and housing | H86: 285000 | J86: =SUM(H86) -> 285000 | K86: 11655000
C87: Construction | H87: 240214000 | I87: 45280000 | J87: =SUM(H87:I87) -> 285494000
C88: Debt service | I88: 38000 | J88: =SUM(H88:I88) -> 38000 | K88: 104830000
C89: Claims and judgments payable | H89: 3599000 | J89: =SUM(H89:I89) -> 3599000
B90: Unrestricted | H90: 93297000 | I90: 36233000 | J90: =SUM(H90:I90) -> 129530000 | K90: 271670000
C92: Total Net Assets | H92: =SUM(H76:H90) -> 1274410000 | I92: =SUM(I76:I90) -> 628208000 | J92: =SUM(J76:J90) -> 1902618000 | K92: =SUM(K75:K90) -> 477399000
C94: Total Liabilities and Net Assets | H94: =SUM(H73+H92) -> 2004780000 | I94: =SUM(I73+I92) -> 660985000 | J94: =SUM(J73+J92) -> 2665765000 | K94: =SUM(K73+K92) -> 977077000

Sheet LaSalle
C1: LaSalle Parish 2013 Statement of Net Assets
C2: Issued: December 31, 2013
G4: Governmental Activities
A5: ASSETS
B6: Cash and cash equivalents | G6: 2504699
B7: Receivables | G7: 3366905
B8: Prepaid lease payments | G8: 7476
B9: Capital assets (net) | G9: 5846162
B11: Total Assets | G11: =SUM(G6:G9) -> 11725242
A13: LIABILITIES
B14: Cash overdraft | G14: 216358
B15: Accounts payable | G15: 275032
B16: Payroll payable | G16: 37855
B17: Net OPEB obligations | G17: 69188
B18: Long term liabilities:
C19: Due within one year | G19: 221535
C20: Due in more than one year | G20: 125749
C22: Total Liabilities | G22: =SUM(G14:G20) -> 945717
A24: NET ASSETS
B25: Invested in capital assets, net of related debt | G25: 5498878
B26: Unrestricted | G26: 5280647
B28: Total Net Assets | G28: =SUM(G25:G26) -> 10779525
B30: Total Liabilities and Net Assets | G30: =SUM(G22+G28) -> 11725242

Sheet Lafayette
D1: Lafayete Parish 2013 Statement of Net Assets
D2: Issued: December 31, 2013
H4: Primary Government
H5: Governmental Activities | I5: Business-Type Activities | J5: Total | K5: Component Unit
A6: ASSETS
B7: Current Assets
C8: Cash and interest-bearing deposits | H8: 7721845 | I8: 2848461 | J8: =SUM(H8:I8) -> 10570306 | K8: 50132926
C9: Investments | H9: 278852022 | I9: 16027117 | J9: =SUM(H9:I9) -> 294879139 | K9: 16338139
C10: Accounts receivable, net | H10: 2270885 | I10: 27658362 | J10: =SUM(H10:I10) -> 29929247 | K10: 2002495
C11: Loans receivable, net | H11: 2140411 | J11: =SUM(H11:I11) -> 2140411 | K11: 6171947
C12: Taxes receivable | J12: =SUM(H12:I12) -> 0 | K12: 1371542
C13: Assessments receivable | H13: 273120 | J13: =SUM(H13:I13) -> 273120
C14: Accrued interest receivable | H14: 310013 | I14: 1099 | J14: =SUM(H14:I14) -> 311112 | K14: 93598
C15: Internal balances | H15: 3559213 | I15: -3559213 | J15: =SUM(H15:I15) -> 0
C16: Due from primary government | J16: =SUM(H16:I16) -> 0 | K16: 73188
C17: Due from component units | H17: 177735 | I17: 1879 | J17: =SUM(H17:I17) -> 179614
C18: Due from other governmental agencies | H18: 18499918 | I18: 3456198 | J18: =SUM(H18:I18) -> 21956116 | K18: 7986272
C19: Other receivables | J19: =SUM(H19:I19) -> 0 | K19: 15000
C20: Inventories, net | H20: 419825 | I20: 31932260 | J20: =SUM(H20:I20) -> 32352085 | K20: 218586
C21: Prepaid items | H21: 149592 | I21: 293411 | J21: =SUM(H21:I21) -> 443003 | K21: 378702
C22: Other assets | K22: 1346182
C23: Restricted assets:
D24: Cash | I24: 8101700 | J24: =SUM(H24:I24) -> 8101700 | K24: 3981944
D25: Investments | I25: 209339409 | J25: 209339409 | K25: 20708601
D26: Receivables | I26: 111938 | J26: =SUM(H26:I26) -> 111938 | K26: 44820
C27: Unamortized bond issuance costs | H27: 4415993 | I27: 5108695 | J27: =SUM(H27:I27) -> 9524688
C28: Unamortized start-up costs | I28: 1960661 | J28: =SUM(H28:I28) -> 1960661
C29: Capital assets:
D30: Non-depreciable | H30: 70197995 | I30: 66232170 | J30: =SUM(H30:I30) -> 136430165 | K30: 29146560
D31: Depreciable,net | H31: 517241758 | I31: 662632316 | J31: =SUM(H31:I31) -> 1179874074 | K31: 90812166
C33: Total Assets | H33: =SUM(H8:H31) -> 906230325 | I33: =SUM(I8:I31) -> 1032146463 | J33: =SUM(J8:J31) -> 1938376788 | K33: =SUM(K8:K31) -> 230822668
A35: LIABILITIES
C36: Cash overdraft | I36: 2167552 | J36: =SUM(H36:I36) -> 2167552 | K36: 173447
C37: Accounts payable | H37: 3505182 | I37: 6433320 | J37: =SUM(H37:I37) -> 9938502 | K37: 4651833
C38: Accrued liabilities | H38: 4204230 | I38: 1831756 | J38: =SUM(H38:I38) -> 6035986 | K38: 834353
C39: Contracts payable | H39: 2352712 | I39: 4514145 | J39: =SUM(H39:I39) -> 6866857
C40: Retainage payable | H40: 2067414 | I40: 1452778 | J40: =SUM(H40:I40) -> 3520192
C41: Other payables | H41: 444275 | J41: =SUM(H41:I41) -> 444275
C42: Due to primary government | J42: =SUM(H42:I42) -> 0 | K42: 179614
C43: Due to component units | H43: 73188 | J43: =SUM(H43:I43) -> 73188
C44: Due to other governmental agencies | H44: 714973 | J44: =SUM(H44:I44) -> 714973 | K44: 4507
C45: Unearned revenue | H45: 281108 | I45: 2989 | J45: =SUM(H45:I45) -> 284097 | K45: 2513461
C46: Accrued interest payable | H46: 1916210 | I46: 2150966 | J46: =SUM(H46:I46) -> 4067176 | K46: 159675
C47: Customer deposits | I47: 8151514 | J47: =SUM(H47:I47) -> 8151514 | K47: 101171
C48: Long-term liabilities:
D49: Portion due or payable within one year | H49: 34417905 | I49: 5045582 | J49: =SUM(H49:I49) -> 39463487 | K49: 7960162
D50: Portion due or payable after one year | H50: 409431497 | I50: 494865322 | J50: =SUM(H50:I50) -> 904296819 | K50: 22626084
D52: Total Liabilities | H52: =SUM(H37:H50) -> 459408694 | I52: =SUM(I36:I50) -> 526615924 | J52: =SUM(J36:J50) -> 986024618 | K52: =SUM(K36:K50) -> 39204307
A54: NET ASSETS
B55: Invested in capital assets, net of related debt | H55: 304942786 | I55: 306572079 | J55: =SUM(H55:I55) -> 611514865 | K55: 111883759
B56: Restricted for:
C57: Capital projects | H57: 74069893 | J57: =SUM(H57:I57) -> 74069893 | K57: 2337789
C58: Debt service | H58: 45756145 | I58: 124301456 | J58: =SUM(H58:I58) -> 170057601 | K58: 4929977
C59: Other | H59: 50174981 | J59: =SUM(H59:I59) -> 50174981 | K59: 596720
B60: Unrestricted (deficit) | H60: -28122174 | I60: 74657004 | J60: =SUM(H60:I60) -> 46534830 | K60: 71870116
C62: Total Net Assets | H62: =SUM(H55:H60) -> 446821631 | I62: =SUM(I55:I60) -> 505530539 | J62: =SUM(J55:J60) -> 952352170 | K62: =SUM(K54:K60) -> 191618361
C64: Total Liabilities and Net Assets | H64: =SUM(H52+H62) -> 906230325 | I64: =SUM(I62+I52) -> 1032146463 | J64: =SUM(J62+J52) -> 1938376788 | K64: =SUM(K62+K52) -> 230822668

Sheet Lafourche
D1: Lafourche Parish 2013 Statement of Net Assets
D2: Issued: December 31, 2013
H4: Primary Government | K4: Component Unit
H5: Governmental Activities | I5: Business-Type Activities | J5: Total | K5: Total
A6: ASSETS
C7: Cash | H7: 28390862 | J7: =SUM(H7:I7) -> 28390862 | K7: 198057510
C8: Investments | H8: 19417222 | J8: =SUM(H8:I8) -> 19417222 | K8: 24203089
C9: Receivables | H9: 2513853 | I9: 17430 | J9: =SUM(H9:I9) -> 2531283 | K9: 36021414
C10: Due from other governmental units | H10: 32644660 | J10: =SUM(H10:I10) -> 32644660
C11: Prepaids and other assets | H11: 1525426 | J11: =SUM(H11:I11) -> 1525426 | K11: 21575554
C12: Capital assets:
D13: Non-depreciable | H13: 25100579 | J13: =SUM(H13:I13) -> 25100579 | K13: 29927075
D14: Depreciable | H14: 57951906 | I14: 3062776 | J14: =SUM(H14:I14) -> 61014682 | K14: 198267967
C16: Total Assets | H16: =SUM(H7:H14) -> 167544508 | I16: =SUM(I7:I14) -> 3080206 | J16: =SUM(J7:J14) -> 170624714 | K16: =SUM(K7:K14) -> 508052609
B18: Deferred outflows of resources
C19: Deferred charge on refunding | H19: 1077879 | J19: =SUM(H19:I19) -> 1077879
C21: Total Deferred Outflows of Resources | H21: =H19 -> 1077879 | I21: =I19 -> 0 | J21: =J19 -> 1077879 | K21: =K19 -> 0
A23: LIABILITIES
C24: Accounts payable and accrued expenses | H24: 7236302 | I24: 16352 | J24: =SUM(H24:I24) -> 7252654 | K24: 18038291
C25: Other current liabilities | H25: 517734 | J25: =SUM(H25:I25) -> 517734 | K25: 5286633
C26: Accrued interest payable | H26: 664933 | J26: =SUM(H26:I26) -> 664933
C27: Due to other governmental units | H27: 383924 | I27: 199494 | J27: =SUM(H27:I27) -> 583418
C28: Long-term liabilities | J28: =SUM(H28:I28) -> 0
D29: Due within one year | H29: 8630887 | J29: =SUM(H29:I29) -> 8630887 | K29: 4017837
D30: Due in more than one year | H30: 46541145 | J30: =SUM(H30:I30) -> 46541145 | K30: 26224316
D32: Total Liabilities | H32: =SUM(H24:H30) -> 63974925 | I32: =SUM(I24:I30) -> 215846 | J32: =SUM(J24:J30) -> 64190771 | K32: =SUM(K24:K30) -> 53567077
A34: NET ASSETS
B35: Net invested in capital assets | H35: 34851386 | I35: 3062776 | J35: =SUM(H35:I35) -> 37914162 | K35: 199214122
B36: Restricted for:
C37: Capital projects | H37: 31251705 | J37: =SUM(H37:I37) -> 31251705 | K37: 1653013
C38: Debt service | H38: 6243097 | J38: =SUM(H38:I38) -> 6243097 | K38: 3694956
B39: Unrestricted (deficit) | H39: 32301274 | I39: -198416 | J39: =SUM(H39:I39) -> 32102858 | K39: 249923441
C41: Total Net Assets | H41: =SUM(H35:H39) -> 104647462 | I41: =SUM(I35:I39) -> 2864360 | J41: =SUM(J35:J39) -> 107511822 | K41: =SUM(K34:K39) -> 454485532
C43: Total Liabilities and Net Assets | H43: =SUM(H41+H32) -> 168622387 | I43: =SUM(I32+I41) -> 3080206 | J43: =SUM(J32+J41) -> 171702593 | K43: =SUM(K41+K32) -> 508052609

Sheet Lincoln
C1: Lincoln Parish 2013 Statement of Net Assets
C2: Issued: December 31, 2013
G4: Governmental Activities
A5: ASSETS
B6: Cash | G6: 9270701
B7: Investments | G7: 22426630
B8: Accounts receivable | G8: 7709169
B9: Due from other entities | G9: 236078
B10: Inventory | G10: 11582
B11: Capital assets:
C12: Non-Depreciable | G12: 1775786
C13: Depreciable | G13: 22094399
B15: Total Assets | G15: =SUM(G6:G13) -> 63524345
A17: DEFERRED OUTFLOWS OF RESOURCES
B18: Prepaid expenses | G18: 3008
A20: LIABILITIES
B21: Accounts payable | G21: 1372481
B22: Due to other entities | G22: 1330002
B23: Noncurrent liabilities:
C24: Due within one year:
D25: Bonds payable | G25: 466000
C26: Due in more than one year:
D27: Compensated absences | G27: 114162
D28: Bonds payable | G28: 3476000
C29: Unfunded postretirement:
D30: Benefit plan obligations | G30: 1605571
C32: Total Liabilities | G32: =SUM(G21:G30) -> 8364216
A34: NET ASSETS
B35: Net investment in capital assets | G35: 23870185
B36: Restricted for:
C37: Capital projects | G37: 1998577
C38: Debt service | G38: 990393
B39: Unrestricted | G39: 28303982
B41: Total Net Assets | G41: =SUM(G35:G39) -> 55163137
B43: Total Liabilities and Net Assets | G43: =SUM(G32+G41) -> 63527353

Sheet Livingston
D1: Livingston Parish 2013 Statement of Net Assets
D2: Issued: December 31, 2013
H4: Primary Government
H5: Governmental Activities | I5: Business-Type Activities | J5: Total
A6: ASSETS
B7: Current Assets
C8: Cash and cash equivalents | H8: 5509530 | I8: 325932 | J8: =SUM(H8:I8) -> 5835462
C9: Investments | H9: 3407261 | J9: =SUM(H9:I9) -> 3407261
C10: Receivables, Net of Allowance | H10: 1643857 | I10: 125158 | J10: =SUM(H10:I10) -> 1769015
C11: Inventory | H11: 186604 | J11: =SUM(H11:I11) -> 186604
C12: Internal balances | H12: 222383 | I12: -222383 | J12: =SUM(H12:I12) -> 0
C13: Due from other governments | H13: 12320275 | J13: =SUM(H13:I13) -> 12320275
C14: Due from component unit | H14: 2945 | J14: =SUM(H14:I14) -> 2945
C15: Unamortized bond insurance premiums | H15: 653977 | J15: =SUM(H15:I15) -> 653977
C16: Prepaid items | H16: 266580 | I16: 670 | J16: =SUM(H16:I16) -> 267250
C17: Restricted assets
D18: Cash | H18: 6871428 | I18: 78945 | J18: =SUM(H18:I18) -> 6950373
D19: Investments | H19: 8630079 | J19: =SUM(H19:I19) -> 8630079
C20: Capital assets
D21: Non-depreciable | H21: 20955526 | I21: 190726 | J21: =SUM(H21:I21) -> 21146252
D22: Depreciable capital assets, net | H22: 122717002 | I22: 8106754 | J22: =SUM(H22:I22) -> 130823756
C24: Total Assets | H24: =SUM(H8:H22) -> 183387447 | I24: =SUM(I8:I22) -> 8605802 | J24: =SUM(J8:J22) -> 191993249
B26: Deferred Outflows of Resources
C27: Deferred Amount on Refunding of Debt | H27: 377331 | J27: =SUM(H27:I27) -> 377331
E29: Total Assets and Deferred Outflows | H29: =SUM(H24+H27) -> 183764778 | I29: =SUM(I24+I27) -> 8605802 | J29: =SUM(J24+J27) -> 192370580
A31: LIABILITIES
C32: Accounts payable and accrued expenses | H32: 5537668 | I32: 149695 | J32: =SUM(H32:I32) -> 5687363
C33: Overdraft Payable | H33: 1092566 | J33: =SUM(H33:I33) -> 1092566
C34: Due to other governments | H34: 574768 | J34: =SUM(H34:I34) -> 574768
C35: Unearned revenues | H35: 19700 | J35: =SUM(H35:I35) -> 19700
C36: Accrued bond interest payable | H36: 1284931 | I36: 2881 | J36: =SUM(H36:I36) -> 1287812
C37: Non-current liabilities
E38: Due within one year | H38: 6216751 | I38: 84949 | J38: =SUM(H38:I38) -> 6301700
E39: Due in more than one year | H39: 80849877 | I39: 2493066 | J39: =SUM(H39:I39) -> 83342943
D41: Total Liabilities | H41: =SUM(H32:H39) -> 95576261 | I41: =SUM(I32:I39) -> 2730591 | J41: =SUM(J32:J39) -> 98306852
A43: NET ASSETS
B44: Invested in capital assets, net of related debt | H44: 63010299 | I44: 5719966 | J44: =SUM(H44:I44) -> 68730265
B45: Restricted for:
C46: Construction | H46: 7492916 | J46: =SUM(H46:I46) -> 7492916
C47: Criminal Court | H47: 54995 | J47: =SUM(H47:I47) -> 54995
C48: Debt Service | H48: 8821586 | J48: =SUM(H48:I48) -> 8821586
C49: Grant | H49: 92784 | J49: =SUM(H49:I49) -> 92784
B50: Unrestricted | H50: 8715937 | I50: 155245 | J50: =SUM(H50:I50) -> 8871182
C52: Total Net Assets | H52: =SUM(H44:H50) -> 88188517 | I52: =SUM(I44:I50) -> 5875211 | J52: =SUM(J43:J50) -> 94063728
C54: Total Liabilities and Net Assets | H54: =SUM(H41+H52) -> 183764778 | I54: =SUM(I52+I41) -> 8605802 | J54: =SUM(J52+J41) -> 192370580

Sheet Madison
C1: Madison Parish 2013 Statement of Net Assets
C2: Issued: December 31, 2013
G4: Governmental Activities
A5: ASSETS
B6: Cash and cash equivalents | G6: 4448930
B7: Investments | G7: 2949665
B8: Receivables (net) | G8: 5726410
B9: Capital assets, net | G9: 8177367
B11: Total Assets | G11: =SUM(G6:G9) -> 21302372
A13: LIABILITIES
B14: Accounts, salaries and other payables | G14: 272870
B15: Long-term liabilities:
C16: Due within one year | G16: 39058
C17: Due in more than one year | G17: 514428
C19: Total Liabilities | G19: =SUM(G14:G17) -> 826356
A21: NET ASSETS
B22: Invested in capital assets, net of related debt | G22: 8055870
B23: Restricted for:
C24: Library | G24: 1314818
C25: Garbage collection | G25: 1553590
C26: Health unit | G26: 1004915
C27: Drainage and roads | G27: 1771399
C28: Courthouse and jail | G28: 5024280
C29: Other special revenue funds | G29: 1307046
B30: Unrestricted | G30: 444098
B32: Total Net Assets | G32: =SUM(G22:G30) -> 20476016
B34: Total Liabilities and Net Assets | G34: =SUM(G19+G32) -> 21302372

Sheet Morehouse
C1: Morehouse Parish 2013 Statement of Net Assets
C2: Issued: December 31, 2013
G4: Governmental Activities
A5: ASSETS
B6: Cash | G6: 3855174
B7: Investments | G7: 525000
B8: Receivables | G8: 2339602
B9: Capital assets:
C10: Land | G10: 778626
C11: Other capital assets, net of depreciation | G11: 12865795
B13: Total Assets | G13: =SUM(G6:G11) -> 20364197
A15: LIABILITIES
B16: Bank overdrafts | G16: 2067087
B17: Accounts payable | G17: 253492
B18: Payroll accruals and wothholdings | G18: 27496
B19: Long-term liabilities:
C20: Due within one year | G20: 34542
C22: Total Liabilities | G22: =SUM(G16:G20) -> 2382617
A24: Deferred Inflows of Resources
B25: Property Taxes | G25: 2110568
A27: NET ASSETS
B28: Invested in capital assets | G28: 13644421
B29: Restricted for special revenue | G29: 4215876
B30: Unrestricted | G30: -1989285
B32: Total Net Assets | G32: =SUM(G28:G30) -> 15871012
B34: Total Liabilities and Net Assets | G34: =SUM(G22+G32+G25) -> 20364197

Sheet Natchitoches
D1: Natchitoches Parish 2013 Statement of Net Assets
D2: Issued: December 31, 2013
H4: Governmental Activities
A5: ASSETS
B6: Current Assets
C7: Cash and cash equivalents | H7: 6692314
C8: Revenue receivables | H8: 6580976
C10: Total Current Assets | H10: =SUM(H7:H8) -> 13273290
B12: Non-current Assets:
C13: Capital assets, net of accumulated depreciation | H13: 10706052
C15: Total Non-current Assets | H15: =SUM(H13) -> 10706052
C17: Total Assets | H17: =SUM(H10+H15) -> 23979342
A19: LIABILITIES
B20: Current Liabilities:
C21: Cash overdraft | H21: 27017
C22: Accounts payable | H22: 623794
C23: Accrued payroll | H23: 402461
C24: Due to other governments | H24: 894223
D26: Total Current Liabilities | H26: =SUM(H21:H24) -> 1947495
B28: Long-term Liabilities:
C29: Accrued compensated absences | H29: 142189
D31: Total Non-current Liabilities | H31: =SUM(H29:H29) -> 142189
D33: Total Liabilities | H33: =SUM(H26+H31) -> 2089684
A35: NET ASSETS
B36: Net investment in capital assets | H36: 10706052
B37: Unrestricted | H37: 11183606
C39: Total Net Assets | H39: =SUM(H36:H37) -> 21889658
C41: Total Liabilities and Net Assets | H41: =SUM(H33+H39) -> 23979342

Sheet Orleans
D1: Orleans Parish 2013 Statement of Net Assets
D2: Issued: December 31, 2013
H4: Primary Government
H5: Governmental Activities | I5: Component Unit
A6: ASSETS
C7: Cash and cash equivalents | H7: 62125000 | I7: 116617000
C8: Investments | H8: 165644000 | I8: 68472000
C9: Receivables (net of allowance for uncollectibles):
D10: Taxes | H10: 31443000 | I10: 8390000
D11: Accounts | H11: 10841000 | I11: 26138000
D12: Interest | I12: 28000
D13: Grantee loans | H13: 1517000 | I13: 12432000
D14: Other | I14: 21467000
C15: Due from component units | H15: 19627000
C16: Due from other governments | H16: 53213000 | I16: 2674000
C17: Other assets | H17: 24000 | I17: 36304000
C18: Restricted cash and investments | I18: 199268000
C19: Capital assets (net of accumulated depreciation) | H19: 1550110000 | I19: 2945985000
C21: Total Assets | H21: =SUM(H7:H19) -> 1894544000 | I21: =SUM(I7:I19) -> 3437775000
A23: Deferred Outflows of Resources
B24: Deferred loss on bond refunding | H24: 7241 | I24: 20654
C26: Total deferred outflows of resources | H26: =H24 -> 7241 | I26: =I24 -> 20654
A28: LIABILITIES
C29: Accounts payable | H29: 84953000 | I29: 57297000
C30: Retainage payable | H30: 3728000 | I30: 6548000
C31: Accrued expenses | H31: 1001000 | I31: 29846000
C32: Taxes payable | H32: 5422000
C33: Accrued Interest Payable | H33: 6218000 | I33: 13653000
C34: Due to component units | H34: 59000
C35: Due to other governments | H35: 10217000 | I35: 31650000
C36: Unearned revenue | H36: 2744000
C37: Liabilities payable from restricted assets | I37: 17460000
C38: Long-term liabilities due within one year | H38: 163403000 | I38: 44880000
C39: Long-term liabilities due in more than one year | H39: 1431852000 | I39: 810323000
D41: Total Liabilities | H41: =SUM(H29:H39) -> 1709597000 | I41: =SUM(I29:I39) -> 1011657000
A43: Deferred Inflows of Resources
B44: Unavailable Revenue | H44: 7386 | I44: 2031
C46: Total deferred inflows of resources | H46: =H44 -> 7386 | I46: =I44 -> 2031
A48: NET ASSETS
B49: Net investment in capital assets | H49: 894662000 | I49: 2358587000
B50: Restricted for debt service | H50: 77759000 | I50: 80009000
B51: Restricted for capital improvement | H51: 35445000 | I51: 50009000
B52: Restricted for operating reserve | I52: 16030000
B53: Unrestricted (deficit) | H53: -823064000 | I53: -59894000
C55: Total Net Assets | H55: =SUM(H49:H53) -> 184802000 | I55: =SUM(I48:I53) -> 2444741000
C57: Total Liabilities and Net Assets | H57: =SUM(H41+H55+H46) -> 1894406386 | I57: =SUM(I41+I55+I46) -> 3456400031

Sheet Ouachita
C1: Ouachita Parish 2013 Statement of Net Assets
D2: Issued: December 31, 2013
F4: Primary Government
F5: Governmental Activities | G5: Business-Type Activities | H5: Total
A6: ASSETS
B7: Cash and cash equivalents | F7: 42454537 | G7: 157585 | H7: =SUM(F7:G7) -> 42612122
B8: Investments, at market value | F8: 12027474 | H8: =SUM(F8:G8) -> 12027474
B9: Receivables:
C10: Ad valorem taxes | F10: 31569922 | H10: =SUM(F10:G10) -> 31569922
C11: Sales taxes | F11: 3017501 | H11: =SUM(F11:G11) -> 3017501
C12: Special assessments | F12: 198068 | H12: =SUM(F12:G12) -> 198068
C13: Trade receivables | F13: 900245 | G13: 30574 | H13: =SUM(F13:G13) -> 930819
C14: Other | G14: 15309 | H14: =SUM(F14:G14) -> 15309
B15: Due from other governmental | F15: 4118714 | G15: 2193 | H15: =SUM(F15:G15) -> 4120907
B16: Internal balances | F16: 106520 | G16: -106520 | H16: =SUM(F16:G16) -> 0
B17: Prepaid expenses | F17: 315747 | H17: =SUM(F17:G17) -> 315747
B18: Inventories | F18: 610322 | H18: =SUM(F18:G18) -> 610322
B19: Capital assets, net | F19: 181359356 | G19: 2574363 | H19: =SUM(F19:G19) -> 183933719
C21: Total Assets | F21: =SUM(F7:F19) -> 276678406 | G21: =SUM(G7:G19) -> 2673504 | H21: =SUM(H7:H19) -> 279351910
A23: LIABILITIES
B24: Accounts payable and accrued expenses | F24: 5273831 | G24: 51035 | H24: =SUM(F24:G24) -> 5324866
B25: Unearned revenues | F25: 1295186 | H25: =SUM(F25:G25) -> 1295186
B26: Deposits held | F26: 201234 | H26: =SUM(F26:G26) -> 201234
B27: Long term payables:
C28: Due within one year | F28: 1956292 | G28: 24000 | H28: =SUM(F28:G28) -> 1980292
C29: Due in more than one year | F29: 5916082 | G29: 401000 | H29: =SUM(F29:G29) -> 6317082
B30: Other noncurrent liabilities | G30: 3662 | H30: =SUM(F30:G30) -> 3662
D32: Total Liabilities | F32: =SUM(F24:F30) -> 14642625 | G32: =SUM(G24:G30) -> 479697 | H32: =SUM(H24:H30) -> 15122322
A34: NET ASSETS
B35: Net investment in capital assets | F35: 181359356 | G35: 2149363 | H35: =SUM(F35:G35) -> 183508719
B36: Restricted for:
C37: Public works | F37: 5229069 | H37: =SUM(F37:G37) -> 5229069
C38: Public safety | F38: 40084163 | H38: =SUM(F38:G38) -> 40084163
C39: Health and welfare | F39: 5540067 | H39: =SUM(F39:G39) -> 5540067
C40: Culture and recreation | F40: 9670569 | H40: =SUM(F40:G40) -> 9670569
C41: Economic development | F41: 755593 | H41: =SUM(F41:G41) -> 755593
C42: Judicial | F42: 1442907 | H42: =SUM(F42:G42) -> 1442907
C43: Debt service | F43: 58523 | G43: 93446 | H43: =SUM(F43:G43) -> 151969
C44: Capital improvements | F44: 7377501 | H44: =SUM(F44:G44) -> 7377501
C45: Insurance claims | F45: 6919183 | H45: =SUM(F45:G45) -> 6919183
B46: Unrestricted | F46: 3598850 | G46: -49002 | H46: =SUM(F46:G46) -> 3549848
C48: Total Net Assets | F48: =SUM(F35:F46) -> 262035781 | G48: =SUM(G35:G46) -> 2193807 | H48: =SUM(H34:H46) -> 264229588
C50: Total Liabilities and Net Assets | F50: =SUM(F32+F48) -> 276678406 | G50: =SUM(G48+G32) -> 2673504 | H50: =SUM(H48+H32) -> 279351910

Sheet Plaquemines
D1: Plaquemines Parish 2013 Statement of Net Assets
D2: Issued: December 31, 2013
H4: Governmental Activities | I4: Business-Type Activities | J4: Total
A5: ASSETS
B6: Current Assets
C7: Cash and cash equivalents | H7: 132705600 | I7: 304223 | J7: =SUM(H7:I7) -> 133009823
C8: Investments | H8: 4998456 | J8: =SUM(H8:I8) -> 4998456
C9: Receivables (net of allowaces for uncollectibles) | H9: 91095902 | I9: 4952675 | J9: =SUM(H9:I9) -> 96048577
C10: Internal balances | H10: 60000 | I10: -60000 | J10: =SUM(H10:I10) -> 0
C11: Prepaid items | H11: 904373 | I11: 3435 | J11: =SUM(H11:I11) -> 907808
C13: Total Current Assets | H13: =SUM(H7:H11) -> 229764331 | I13: =SUM(I7:I12) -> 5200333 | J13: =SUM(J7:J11) -> 234964664
B15: Non-current Assets:
C16: Internal balances | H16: 2073727 | I16: -2073727 | J16: =SUM(H16:I16) -> 0
C17: Capital assets, net of accumulated depreciation | H17: 298451667 | I17: 59770882 | J17: =SUM(H17:I17) -> 358222549
C18: Capital assets not being depreciated | H18: 139378928 | I18: 31053463 | J18: =SUM(H18:I18) -> 170432391
C20: Total Non-current Assets | H20: =SUM(H15:H18) -> 439904322 | I20: =SUM(I15:I18) -> 88750618 | J20: =SUM(J15:J18) -> 528654940
C22: Total Assets | H22: =SUM(H13+H20) -> 669668653 | I22: =SUM(I13+I20) -> 93950951 | J22: =SUM(J13+J20) -> 763619604
A24: LIABILITIES
B25: Current Liabilities:
C26: Cash overdraft | I26: 4120246 | J26: =SUM(H26:I26) -> 4120246
C27: Accounts, salaries and other payables | H27: 19335807 | I27: 886074 | J27: =SUM(H27:I27) -> 20221881
C28: Bonds payable | H28: 3965000 | J28: =SUM(H28:I28) -> 3965000
C29: Capital leases payable | H29: 33932 | J29: =SUM(H29:I29) -> 33932
C30: Unearned revenues | H30: 6684526 | J30: =SUM(H30:I30) -> 6684526
C31: Accrued interest payable | H31: 3432235 | J31: =SUM(H31:I31) -> 3432235
C32: Compensated absences payable | H32: 1134856 | I32: 29245 | J32: =SUM(H32:I32) -> 1164101
C33: Deposits due others | H33: 52325 | I33: 407643 | J33: =SUM(H33:I33) -> 459968
C34: Other | H34: 1105011 | I34: 127040 | J34: =SUM(H34:I34) -> 1232051
D36: Total Current Liabilities | H36: =SUM(H27:H34) -> 35743692 | I36: =SUM(I26:I34) -> 5570248 | J36: =SUM(J26:J34) -> 41313940
B38: Non-current Liabilities
C39: Litigation and other contingencies | H39: 4591376 | J39: =SUM(H39:I39) -> 4591376
C40: Capital leases payable | H40: 58290 | J40: =SUM(H40:I40) -> 58290
C41: Notes payable-long term | H41: 8900000 | J41: =SUM(H41:I41) -> 8900000
C42: Bonds payable-long term | H42: 121195000 | J42: =SUM(H42:I42) -> 121195000
C43: Other post-employment benefits payable | H43: 18671611 | I43: 677457 | J43: =SUM(H43:I43) -> 19349068
D45: Total Non-current Liabilities | H45: =SUM(H39:H43) -> 153416277 | I45: =SUM(I39:I43) -> 677457 | J45: =SUM(J39:J43) -> 154093734
D47: Total Liabilities | H47: =SUM(H36+H45) -> 189159969 | I47: =SUM(I45+I36) -> 6247705 | J47: =SUM(J36+J45) -> 195407674
A49: NET ASSETS
B50: Invested in capital assets, net of related debt | H50: 312670595 | I50: 90824345 | J50: =SUM(H50:I50) -> 403494940
B51: Restricted | H51: 108839363 | J51: =SUM(H51:I51) -> 108839363
B52: Unrestricted (deficit) | H52: 58998726 | I52: -3121099 | J52: =SUM(H52:I52) -> 55877627
C54: Total Net Assets | H54: =SUM(H50:H52) -> 480508684 | I54: =SUM(I50:I52) -> 87703246 | J54: =SUM(J49:J52) -> 568211930
C56: Total Liabilities and Net Assets | H56: =SUM(H47+H54) -> 669668653 | I56: =SUM(I54+I47) -> 93950951 | J56: =SUM(J54+J47) -> 763619604

Sheet Pointe Coupee
C1: Pointe Coupee Parish 2013 Statement of Net Assets
D2: Issued: December 31, 2013
F4: Primary Government | I4: Component Units
F5: Governmental Activities | G5: Business-Type Activities | H5: Total | I5: Governmental Activities | J5: Business-Type Activities
A6: ASSETS
B7: Cash and cash equivalents | F7: 2478409 | G7: 92267 | H7: =SUM(F7:G7) -> 2570676 | I7: 3892288 | J7: 4577798
B8: Investments | F8: 702328 | H8: =SUM(F8:G8) -> 702328 | I8: 10190976 | J8: 15134224
B9: Accounts receivable, net | F9: 3448430 | G9: 807584 | H9: =SUM(F9:G9) -> 4256014 | I9: 3415485 | J9: 3584469
B10: Due from other governments | F10: 679093 | G10: 49378 | H10: =SUM(F10:G10) -> 728471 | I10: 308283 | J10: 291941
B11: Due from fiduciary funds | F11: 135860 | H11: =SUM(F11:G11) -> 135860
B12: Internal balances | F12: -982000 | G12: 966000 | H12: =SUM(F12:G12) -> -16000 | J12: 16000
B13: Prepaid items | F13: 62357 | G13: 1136 | H13: =SUM(F13:G13) -> 63493 | I13: 77928 | J13: 695521
B14: Other assets | F14: 9008 | G14: 11617 | H14: =SUM(F14:G14) -> 20625 | I14: 31650 | J14: 2595
B15: Capital assets: | H15: =SUM(F15:G15) -> 0
C16: Non-depreciable | F16: 3554457 | G16: 45233 | H16: =SUM(F16:G16) -> 3599690 | I16: 630268 | J16: 5712933
C17: Depreciable, net | F17: 13600295 | G17: 2117538 | H17: =SUM(F17:G17) -> 15717833 | I17: 13308143 | J17: 23147380
C19: Total Assets | F19: =SUM(F7:F17) -> 23688237 | G19: =SUM(G7:G17) -> 4090753 | H19: =SUM(H7:H17) -> 27778990 | I19: =SUM(I7:I17) -> 31855021 | J19: =SUM(J7:J17) -> 53162861
A21: LIABILITIES
B22: Accounts payable and accrued liabilities | F22: 1495978 | G22: 649805 | H22: =SUM(F22:G22) -> 2145783 | I22: 1680390 | J22: 4035532
B23: Due to other governments | F23: 421610 | H23: =SUM(F23:G23) -> 421610 | I23: 8308
B24: Customer meter deposits | G24: 765232 | H24: =SUM(F24:G24) -> 765232 | J24: 301550
B25: Long term payables: | H25: =SUM(F25:G25) -> 0
C26: Due within one year | F26: 429289 | G26: 104924 | H26: =SUM(F26:G26) -> 534213 | I26: 425347 | J26: 190002
C27: Due in more than one year | F27: 7837889 | G27: 550161 | H27: =SUM(F27:G27) -> 8388050 | I27: 1610718 | J27: 6339016
D29: Total Liabilities | F29: =SUM(F22:F27) -> 10184766 | G29: =SUM(G22:G27) -> 2070122 | H29: =SUM(H22:H27) -> 12254888 | I29: =SUM(I22:I27) -> 3724763 | J29: =SUM(J22:J27) -> 10866100
A31: Deferred Inflows of Resources
B32: Grants received in advance | F32: 2473 | G32: 0 | H32: =SUM(F32:G32) -> 2473 | I32: 979528 | J32: 0
A34: NET ASSETS
B35: Invested in capital assets, net of related debt | F35: 8887574 | G35: 1507686 | H35: =SUM(F35:G35) -> 10395260 | I35: 11897324 | J35: 21833078
B36: Restricted for:
C37: Road construction and maintenance | F37: 439483 | H37: =SUM(F37:G37) -> 439483
C38: Debt service | F38: 1551372 | G38: 35491 | H38: =SUM(F38:G38) -> 1586863 | J38: 394078
C39: Other purposes | F39: 159340 | H39: =SUM(F39:G39) -> 159340 | I39: 643298
B40: Unrestricted | F40: 2463229 | G40: 477454 | H40: =SUM(F40:G40) -> 2940683 | I40: 14610108 | J40: 20069605
C42: Total Net Assets | F42: =SUM(F35:F40) -> 13500998 | G42: =SUM(G35:G40) -> 2020631 | H42: =SUM(H34:H40) -> 15521629 | I42: =SUM(I35:I40) -> 27150730 | J42: =SUM(J35:J40) -> 42296761
C44: Total Liabilities and Net Assets | F44: =SUM(F29+F42+F32) -> 23688237 | G44: =SUM(G29+G42+G32) -> 4090753 | H44: =SUM(H29+H42+H32) -> 27778990 | I44: =SUM(I29+I42+I32) -> 31855021 | J44: =SUM(J29+J42+J32) -> 53162861

Sheet Rapides
D1: Rapides Parish 2013 Statement of Net Assets
D2: Issued: December 31, 2013
H4: Primary Government
H5: 2013 | I5: 2012
A6: ASSETS
C7: Cash and cash equivalents | H7: 50024032 | I7: 25937860
C8: Receivables | H8: 22585071 | I8: 18491555
C9: Other assets | H9: 492 | I9: 13514
C10: Capital assets (net of accumulated depreciation):
D11: Nondepreciable:
E12: Land | H12: 1689373 | I12: 1694373
E13: Construction in progress | H13: 1375268 | I13: 1141822
D14: Depreciable:
E15: Buildings and improvements | H15: 10856728 | I15: 10366723
E16: Furniture, equipment, and other | H16: 7063409 | I16: 7429862
E17: Infrastructure | H17: 30119389 | I17: 32243929
C19: Total Assets | H19: =SUM(H7:H17) -> 123713762 | I19: =SUM(I7:I17) -> 97319638
A21: LIABILITIES
C22: Accounts, salaries, and other payables | H22: 1276458 | I22: 618828
C23: Deferred revenues | H23: 1693311 | I23: 412472
C24: Interest payable | H24: 1097664 | I24: 66424
C25: Long-term liabilities:
D26: Due within one year | H26: 1649430 | I26: 1526095
D27: Due in more than one year | H27: 48762251 | I27: 21238906
D29: Total Liabilities | H29: =SUM(H22:H27) -> 54479114 | I29: =SUM(I22:I27) -> 23862725
A31: NET ASSETS
B32: Invested in capital assets, net of related debt | H32: 24889814 | I32: 50532341
B33: Restricted for debt service | H33: 2945708 | I33: 41385
B34: Unrestricted | H34: 41399125 | I34: 22883185
C36: Total Net Assets | H36: =SUM(H32:H34) -> 69234647 | I36: =SUM(I31:I34) -> 73456911
C38: Total Liabilities and Net Assets | H38: =SUM(H29+H36) -> 123713761 | I38: =SUM(I36+I29) -> 97319636

Sheet Red River
D1: Red River Parish 2013 Statement of Net Assets
D2: Issued: December 31, 2013
H4: Governmental Activities | I4: Business-Type Activities | J4: Total
A5: ASSETS
B6: Current Assets
C7: Cash and cash equivalents | H7: 14939159 | I7: 27597 | J7: =SUM(H7:I7) -> 14966756
C8: Investments | H8: 15927098 | J8: =SUM(H8:I8) -> 15927098
C9: Receivables | H9: 4231862 | I9: 3052 | J9: =SUM(H9:I9) -> 4234914
C10: Prepaid expense | H10: 20301 | J10: =SUM(H10:I10) -> 20301
C12: Total Current Assets | H12: =SUM(H7:H10) -> 35118420 | I12: =SUM(I7:I11) -> 30649 | J12: =SUM(J7:J10) -> 35149069
B14: Non-current Assets:
C15: Capital assets, net of accumulated depreciation | H15: 14236061 | I15: 354991 | J15: =SUM(H15:I15) -> 14591052
C17: Total Non-current Assets | H17: =SUM(H14:H15) -> 14236061 | I17: =SUM(I14:I15) -> 354991 | J17: =SUM(J14:J15) -> 14591052
C19: Total Assets | H19: =SUM(H12+H17) -> 49354481 | I19: =SUM(I12+I17) -> 385640 | J19: =SUM(J12+J17) -> 49740121
A21: LIABILITIES
B22: Current Liabilities:
C23: Compensated absences payable | H23: 25335 | J23: =SUM(H23:I23) -> 25335
C24: Current portion of long-term debt | H24: 236000 | J24: =SUM(H24:I24) -> 236000
C25: Accounts payable and accrued liabilities | H25: 382459 | I25: 5021 | J25: =SUM(H25:I25) -> 387480
C26: Interest payable | H26: 6510 | J26: =SUM(H26:I26) -> 6510
D28: Total Current Liabilities | H28: =SUM(H23:H26) -> 650304 | I28: =SUM(I23:I26) -> 5021 | J28: =SUM(J23:J26) -> 655325
B30: Non-current Liabilities
C31: Compensated absences payable, net of current portion | H31: 51438 | J31: =SUM(H31:I31) -> 51438
C32: Long-term debt, net of current portion | H32: 734000 | J32: =SUM(H32:I32) -> 734000
C33: Other post-employment benefits payable | H33: 109950 | J33: =SUM(H33:I33) -> 109950
D35: Total Non-current Liabilities | H35: =SUM(H31:H33) -> 895388 | I35: =SUM(I31:I33) -> 0 | J35: =SUM(J31:J33) -> 895388
D37: Total Liabilities | H37: =SUM(H28+H35) -> 1545692 | I37: =SUM(I35+I28) -> 5021 | J37: =SUM(J28+J35) -> 1550713
A39: NET ASSETS
B40: Net investment in capital assets | H40: 13266061 | I40: 354991 | J40: =SUM(H40:I40) -> 13621052
B41: Restricted for:
C42: Ambulance services | H42: 1958751 | J42: =SUM(H42:I42) -> 1958751
C43: Dedicated property taxes for library services and construction | H43: 9595343 | J43: =SUM(H43:I43) -> 9595343
B44: Unrestricted | H44: 22988634 | I44: 25628 | J44: =SUM(H44:I44) -> 23014262
C46: Total Net Assets | H46: =SUM(H40:H44) -> 47808789 | I46: =SUM(I40:I44) -> 380619 | J46: =SUM(J39:J44) -> 48189408
C48: Total Liabilities and Net Assets | H48: =SUM(H37+H46) -> 49354481 | I48: =SUM(I46+I37) -> 385640 | J48: =SUM(J46+J37) -> 49740121

Sheet Richland
C1: Richland Parish 2013 Statement of Net Assets
C2: Issued: December 31, 2013
G4: Governmental Activities
A5: ASSETS
B6: Cash | G6: 7877011
B7: Receivables | G7: 2803917
B8: Capital assets:
C9: Land | G9: 300273
C10: Other capital assets, net of depreciation | G10: 2137747
B12: Total Assets | G12: =SUM(G6:G10) -> 13118948
A14: LIABILITIES
B15: Accounts payable | G15: 219835
B16: Payroll accruals and wothholding | G16: 94972
C18: Total Liabilities | G18: =SUM(G15:G16) -> 314807
A20: DEFERRED INFLOWS OF RESOURCES
B21: Property taxes | G21: 2680349
A23: NET ASSETS
B24: Invested in capital assets | G24: 2438020
B25: Restricted for special revenue | G25: 6161125
B26: Unrestricted | G26: 1524647
B28: Total Net Assets | G28: =SUM(G24:G26) -> 10123792
B30: Total Liabilities and Net Assets | G30: =SUM(G18+G28+G21) -> 13118948

Sheet Sabine
D1: Sabine Parish 2013 Statement of Net Assets
D2: Issued: December 31, 2013
H5: 2013 | I5: 2012
A6: ASSETS
C7: Cash and cash equivalents | H7: 8931765 | I7: 10539101
C8: Receivables | H8: 3916001 | I8: 3153470
C9: Capital assets (net of accumulated depreciation):
E10: Land | H10: 639576 | I10: 595253
E11: Construction in progress | H11: 540422
E12: Buildings and improvements | H12: 1720235 | I12: 1647721
E13: Machinery and equipment | H13: 3069475 | I13: 2926989
E14: Furniture, equipment, and other | H14: 15328 | I14: 19296
E15: Infrastructure:
F16: Roads | H16: 1849947 | I16: 2976835
F17: Road right-of-way | H17: 991177 | I17: 987759
F18: Bridges | H18: 3769263 | I18: 3463123
C20: Total Assets | H20: =SUM(H7:H18) -> 25443189 | I20: =SUM(I7:I18) -> 26309547
A22: LIABILITIES
C23: Accounts, salaries, and other payables | H23: 752592 | I23: 822300
C24: Interest payable | H24: 12512 | I24: 14942
C25: Long-term liabilities:
D26: Due within one year | H26: 372094 | I26: 280194
D27: Due in more than one year | H27: 910569 | I27: 657951
D29: Total Liabilities | H29: =SUM(H23:H27) -> 2047767 | I29: =SUM(I23:I27) -> 1775387
A31: NET ASSETS
B32: Invested in capital assets, net of related debt | H32: 11935674 | I32: 11978775
B33: Unrestricted | H33: 11459748 | I33: 12555384
C35: Total Net Assets | H35: =SUM(H32:H33) -> 23395422 | I35: =SUM(I31:I33) -> 24534159
C37: Total Liabilities and Net Assets | H37: =SUM(H29+H35) -> 25443189 | I37: =SUM(I35+I29) -> 26309546

Sheet St. Bernard
C1: St. Bernard Parish 2013 Statement of Net Assets
D2: Issued: December 31, 2013
F4: Primary Government
F5: Governmental Activities | G5: Business-Type Activities | H5: Total
A6: ASSETS
B7: Cash and cash equivalents | F7: 33550215 | G7: 4748123 | H7: =SUM(F7:G7) -> 38298338
B8: Investments | F8: 864327 | H8: =SUM(F8:G8) -> 864327
B9: Investments--land held for sale | F9: 5326500 | H9: =SUM(F9:G9) -> 5326500
B10: Receivables (net of allowance for uncollectibles) | H10: =SUM(F10:G10) -> 0
C11: Sales and use taxes | F11: 2306121 | H11: =SUM(F11:G11) -> 2306121
C12: Ad valorem taxes | F12: 12263645 | H12: =SUM(F12:G12) -> 12263645
C13: Cable franchise fees | F13: 99097 | H13: =SUM(F13:G13) -> 99097
C14: Customer | G14: 150423 | H14: =SUM(F14:G14) -> 150423
C15: Intergovernmental | F15: 18006253 | H15: =SUM(F15:G15) -> 18006253
C16: Other | F16: 1690983 | G16: 4 | H16: =SUM(F16:G16) -> 1690987
B17: Unbilled charges | G17: 345364 | H17: =SUM(F17:G17) -> 345364
B18: Internal balances | F18: -2721617 | G18: 2721617 | H18: =SUM(F18:G18) -> 0
B19: Prepaids | F19: 202937 | G19: 78429 | H19: =SUM(F19:G19) -> 281366
B20: Inventory | G20: 367950 | H20: =SUM(F20:G20) -> 367950
B21: Restricted assets--cash and cash equivalents | G21: 12806176 | H21: =SUM(F21:G21) -> 12806176
B22: Restricted assets--receivables | G22: 576528 | H22: =SUM(F22:G22) -> 576528
B23: Other assets | F23: 9714 | G23: 744000 | H23: =SUM(F23:G23) -> 753714
B24: Capital assets, net of depreciation | F24: 386140491 | G24: 204966155 | H24: =SUM(F24:G24) -> 591106646
C26: Total Assets | F26: =SUM(F7:F24) -> 457738666 | G26: =SUM(G7:G24) -> 227504769 | H26: =SUM(H7:H24) -> 685243435
A28: LIABILITIES
B29: Accounts payable and accrued liabilities | F29: 16376944 | G29: 492771 | H29: =SUM(F29:G29) -> 16869715
B30: Claims payable | F30: 4121020 | G30: 587474 | H30: =SUM(F30:G30) -> 4708494
B31: Retainage payable | F31: 8050192 | H31: =SUM(F31:G31) -> 8050192
B32: Salaries and payroll deductions payable | F32: 1658955 | G32: 118593 | H32: =SUM(F32:G32) -> 1777548
B33: Payable from restricted assets | G33: 1220560 | H33: =SUM(F33:G33) -> 1220560
B34: Accrued interest payable | F34: 526421 | G34: 157703 | H34: =SUM(F34:G34) -> 684124
B35: Unearned revenue | G35: 338023 | H35: =SUM(F35:G35) -> 338023
B36: Certificates of indebtedness | F36: 9356000 | H36: =SUM(F36:G36) -> 9356000
B37: Long term payables:
C38: Due within one year | F38: 1870020 | G38: 3108455 | H38: =SUM(F38:G38) -> 4978475
C39: Due in more than one year | F39: 37379219 | G39: 4463880 | H39: =SUM(F39:G39) -> 41843099
D41: Total Liabilities | F41: =SUM(F29:F39) -> 79338771 | G41: =SUM(G29:G39) -> 10487459 | H41: =SUM(H29:H39) -> 89826230
A43: NET ASSETS
B44: Invested in capital assets, net of related debt | F44: 350256061 | G44: 204966155 | H44: =SUM(F44:G44) -> 555222216
B45: Restricted for:
C46: Capital projects | F46: 452609 | H46: =SUM(F46:G46) -> 452609
C47: Debt service | F47: 1232224 | G47: 353165 | H47: =SUM(F47:G47) -> 1585389
C48: Other purposes | F48: 7785544 | G48: 503968 | H48: =SUM(F48:G48) -> 8289512
B49: Unrestricted | F49: 18673457 | G49: 11194022 | H49: =SUM(F49:G49) -> 29867479
C51: Total Net Assets | F51: =SUM(F44:F49) -> 378399895 | G51: =SUM(G44:G49) -> 217017310 | H51: =SUM(H43:H49) -> 595417205
C53: Total Liabilities and Net Assets | F53: =SUM(F41+F51) -> 457738666 | G53: =SUM(G51+G41) -> 227504769 | H53: =SUM(H51+H41) -> 685243435

Sheet St. Charles
D1: St. Charles Parish 2013 Statement of Net Assets
D2: Issued: December 31, 2013
H4: Primary Government
H5: Governmental Activities | I5: Business-Type Activities | J5: Total | K5: Component Units
A6: ASSETS
C7: Cash and cash equivalents | H7: 3477479 | I7: 170148 | J7: =SUM(H7:I7) -> 3647627 | K7: 180688
C8: Investments | H8: 86002362 | I8: 1051238 | J8: =SUM(H8:I8) -> 87053600 | K8: 7251309
C9: Receivables, net | H9: 29876291 | I9: 2923747 | J9: =SUM(H9:I9) -> 32800038 | K9: 12199202
C10: Due from component units | H10: 40 | J10: =SUM(H10:I10) -> 40
C11: Due from other governments | H11: 3220427 | I11: 109118 | J11: =SUM(H11:I11) -> 3329545 | K11: 15949
C12: Due from primary government | J12: =SUM(H12:I12) -> 0 | K12: 85495
C13: Inventory | I13: 467658 | J13: =SUM(H13:I13) -> 467658 | K13: 1323914
C14: Prepaid fees | H14: 560135 | I14: 38918 | J14: =SUM(H14:I14) -> 599053 | K14: 1387809
C15: Other assets | H15: 4343 | I15: 182 | J15: =SUM(H15:I15) -> 4525 | K15: 1167218
C16: Restricted assets
D17: Cash and cash equivalents | I17: 25471 | J17: =SUM(H17:I17) -> 25471 | K17: 5911014
D18: Investments | I18: 7997735 | J18: =SUM(H18:I18) -> 7997735
C19: Capital assets, net
D20: Land | H20: 10141106 | I20: 824777 | J20: =SUM(H20:I20) -> 10965883 | K20: 876676
D21: Infrastructure | H21: 59749009 | J21: =SUM(H21:I21) -> 59749009
D22: Plant and equipment | H22: 74316961 | I22: 128248435 | J22: =SUM(H22:I22) -> 202565396 | K22: 32133420
D23: Construction in progress | H23: 50057093 | I23: 5726853 | J23: =SUM(H23:I23) -> 55783946 | K23: 332123
C25: Total Assets | H25: =SUM(H7:H23) -> 317405246 | I25: =SUM(I7:I23) -> 147584280 | J25: =SUM(J7:J23) -> 464989526 | K25: =SUM(K7:K23) -> 62864817
A27: LIABILITIES
C28: Cash overdrafts | J28: =SUM(H28:I28) -> 0 | K28: 372206
C29: Accounts payable and other current liabilities | H29: 6550411 | I29: 1128204 | J29: =SUM(H29:I29) -> 7678615 | K29: 3284364
C30: Internal balances | H30: 35744 | I30: -35744 | J30: =SUM(H30:I30) -> 0
C31: Due to component units | H31: 85495 | J31: =SUM(H31:I31) -> 85495
C32: Due to other governments | H32: 370046 | J32: =SUM(H32:I32) -> 370046
C33: Due to primary government | K33: 40
C34: Interest payable | H34: 124402 | J34: =SUM(H34:I34) -> 124402
C35: Other liabilities and accruals | H35: 1224892 | I35: 223224 | J35: =SUM(H35:I35) -> 1448116 | K35: 2914079
C36: Liabilities payable from restricted assets | I36: 1466890 | J36: =SUM(H36:I36) -> 1466890
C37: Non-current liabilities | J37: =SUM(H37:I37) -> 0
D38: Amounts due within one year | H38: 2625000 | I38: 1563000 | J38: =SUM(H38:I38) -> 4188000 | K38: 3738280
D39: Amounts due beyond one year | H39: 29848009 | I39: 29629890 | J39: =SUM(H39:I39) -> 59477899 | K39: 45395315
D40: Multi-employer Pension Liability | K40: 4079418
D41: Other non-current liabilities | J41: =SUM(H41:I41) -> 0 | K41: 17452
D43: Total Liabilities | H43: =SUM(H28:H41) -> 40863999 | I43: =SUM(I28:I41) -> 33975464 | J43: =SUM(J28:J41) -> 74839463 | K43: =SUM(K28:K41) -> 59801154
A45: Deferred Inflows of Resources
B46: Advances | H46: 25111217 | I46: 0 | J46: =SUM(H46:I46) -> 25111217 | K46: 5262456
D48: Total deferred inflows of resources | H48: =H46 -> 25111217 | I48: =I46 -> 0 | J48: =J46 -> 25111217 | K48: =K46 -> 5262456
A50: NET ASSETS
B51: Invested in capital assets, net of related debt | H51: 175989169 | I51: 103607176 | J51: =SUM(H51:I51) -> 279596345 | K51: -161595
B52: Restricted for: | J52: =SUM(H52:I52) -> 0
C53: Maintenance/operations | H53: 32432876 | J53: =SUM(H53:I53) -> 32432876
C54: Debt service | H54: 4474558 | I54: 2857886 | J54: =SUM(H54:I54) -> 7332444
C55: Capital projects | H55: 2573931 | I55: 6366278 | J55: =SUM(H55:I55) -> 8940209 | K55: 58185
C56: Road lighting | H56: 984893 | J56: =SUM(H56:I56) -> 984893
C57: Other purposes | H57: 2638212 | J57: =SUM(H57:I57) -> 2638212
B58: Unrestricted | H58: 32336391 | I58: 777476 | J58: =SUM(H58:I58) -> 33113867 | K58: -2095383
C60: Total Net Assets | H60: =SUM(H51:H58) -> 251430030 | I60: =SUM(I51:I58) -> 113608816 | J60: =SUM(J51:J58) -> 365038846 | K60: =SUM(K50:K58) -> -2198793
C62: Total Liabilities and Net Assets | H62: =SUM(H60+H43+H48) -> 317405246 | I62: =SUM(I43+I60) -> 147584280 | J62: =SUM(J43+J60) -> 439878309 | K62: =SUM(K60+K43) -> 57602361

Sheet St. Helena
D1: St. Helena Parish 2013 Statement of Net Assets
D2: Issued: December 31, 2013
H4: Primary Government | I4: Component Units
H5: Governmental Activities | I5: St. Helena Parish Hospital Serv Dist 1 & Subsidiary | J5: Water Works Dist No. 2 of St. Helena Parish | K5: Other Component Units | L5: Total Component Units
A6: ASSETS
B7: Current Assets:
C8: Cash and cash equivalents | H8: 6030167 | I8: 2241455 | J8: 531342 | K8: 317975 | L8: =SUM(I8:K8) -> 3090772
C9: Investments | H9: 980608 | L9: =SUM(I9:K9) -> 0
C10: Receivables, net | H10: 2218238 | I10: 2721872 | J10: 162562 | K10: 335331 | L10: =SUM(I10:K10) -> 3219765
C11: Due from component units | L11: =SUM(I11:K11) -> 0
C12: Inventory | I12: 348823 | J12: 29079 | L12: =SUM(I12:K12) -> 377902
C13: Prepaid insurance and other assets | H13: 110731 | I13: 83620 | J13: 5736 | K13: 6241 | L13: =SUM(I13:K13) -> 95597
B14: Total current assets | H14: =SUM(H8:H13) -> 9339744 | I14: =SUM(I8:I13) -> 5395770 | J14: =SUM(J8:J13) -> 728719 | K14: =SUM(K8:K13) -> 659547 | L14: =SUM(L8:L13) -> 6784036
B16: Restricted assets:
C17: Restricted cash and cash equivalents | H17: 420892 | I17: 278293 | J17: 533179 | L17: =SUM(I17:K17) -> 811472
B18: Total restricted assets | H18: =SUM(H17) -> 420892 | I18: =SUM(I17) -> 278293 | J18: =SUM(J17) -> 533179 | K18: =SUM(K17) -> 0 | L18: =SUM(L17) -> 811472
B20: Long term assets:
C21: Investments
B22: Total long term assets
B24: Capital assets:
C25: Land | H25: 227865 | L25: =SUM(I25:K25) -> 0
C26: Capital assets, net | H26: 12311341 | I26: 6506375 | J26: 5981938 | K26: 762324 | L26: =SUM(I26:K26) -> 13250637
B27: Total capital assets | H27: =SUM(H25:H26) -> 12539206 | I27: =SUM(I25:I26) -> 6506375 | J27: =SUM(J25:J26) -> 5981938 | K27: =SUM(K25:K26) -> 762324 | L27: =SUM(L25:L26) -> 13250637
C29: Total Assets | H29: =H27+H22+H18+H14 -> 22299842 | I29: =I27+I22+I18+I14 -> 12180438 | J29: =J27+J22+J18+J14 -> 7243836 | K29: =K27+K22+K18+K14 -> 1421871 | L29: =L27+L22+L18+L14 -> 20846145
A31: LIABILITIES
B32: Current liabilities:
C33: Accounts payable | H33: 407278 | I33: 1654799 | J33: 222736 | K33: 10528 | L33: =SUM(I33:K33) -> 1888063
C34: Other accrued payables | H34: 60238 | K34: 11693 | L34: =SUM(I34:K34) -> 11693
C35: Interim financing | J35: 2005871 | L35: =SUM(I35:K35) -> 2005871
C36: Accrued interest on long term indebtedness | H36: 15768 | J36: 43497 | K36: 2728 | L36: =SUM(I36:K36) -> 46225
C37: Customer deposits | J37: 88025 | L37: =SUM(I37:K37) -> 88025
C38: Current portion of long term indebtedness
D39: Bonds payable | H39: 287718 | I39: 774714 | J39: 57583 | K39: 25000 | L39: =SUM(I39:K39) -> 857297
D40: Capital leases | H40: 71465 | L40: =SUM(I40:K40) -> 0
B41: Total current liabilities: | H41: =SUM(H33:H40) -> 842467 | I41: =SUM(I33:I40) -> 2429513 | J41: =SUM(J33:J40) -> 2417712 | K41: =SUM(K33:K40) -> 49949 | L41: =SUM(L33:L40) -> 4897174
B43: Long term liabilities:
C44: Bonds payable | H44: 793199 | I44: 4480601 | J44: 886583 | K44: 200000 | L44: =SUM(I44:K44) -> 5567184
C45: Capital leases | H45: 230754 | L45: =SUM(I45:K45) -> 0
C46: Compensated absences payable | H46: 186139 | L46: =SUM(I46:K46) -> 0
C47: Unifunded net other post employment benefit obligations | H47: 850540 | L47: =SUM(I47:K47) -> 0
B48: Total long term liabilities | H48: =SUM(H44:H47) -> 2060632 | I48: =SUM(I44:I47) -> 4480601 | J48: =SUM(J44:J47) -> 886583 | K48: =SUM(K44:K47) -> 200000 | L48: =SUM(L44:L47) -> 5567184
D50: Total Liabilities | H50: =H41+H48 -> 2903099 | I50: =I41+I48 -> 6910114 | J50: =J41+J48 -> 3304295 | K50: =K41+K48 -> 249949 | L50: =L41+L48 -> 10464358
A52: NET ASSETS
B53: Net investment in capital assets | H53: 11140302 | I53: 2966022 | J53: 3031901 | K53: 534596 | L53: =SUM(I53:K53) -> 6532519
B54: Restricted for: | L54: =SUM(I54:K54) -> 0
C55: Debt service | H55: 32795 | J55: 279101 | K55: 54097 | L55: =SUM(I55:K55) -> 333198
C56: Capital projects | H56: 321481 | L56: =SUM(I56:K56) -> 0
C57: Other purposes | H57: 7761624 | L57: =SUM(I57:K57) -> 0
B58: Unrestricted | H58: 140541 | I58: 2304302 | J58: 628539 | K58: 583229 | L58: =SUM(I58:K58) -> 3516070
C60: Total Net Assets | H60: =SUM(H53:H58) -> 19396743 | I60: =SUM(I53:I58) -> 5270324 | J60: =SUM(J53:J58) -> 3939541 | K60: =SUM(K53:K58) -> 1171922 | L60: =SUM(L52:L58) -> 10381787
C62: Total Liabilities and Net Assets | H62: =SUM(H60+H50) -> 22299842 | I62: =SUM(I50+I60) -> 12180438 | J62: =SUM(J50+J60) -> 7243836 | K62: =SUM(K50+K60) -> 1421871 | L62: =SUM(L60+L50) -> 20846145

Sheet St. James
C1: St. James Parish 2013 Statement of Net Assets
C2: Issued: December 31, 2013
G4: Primary Government | J4: Component Unit
G5: Governmental Activities | H5: Business-Type Activities | I5: Total | J5: St. James Parish Hospital
A6: ASSETS
B7: Cash and cash equivalents | G7: 21299609 | H7: 7093238 | I7: =SUM(G7:H7) -> 28392847 | J7: 8236245
B8: Investments | G8: 10986073 | I8: =SUM(G8:H8) -> 10986073
B9: Receivables (net of allowance for uncollectibles) | G9: 20348518 | H9: 1487343 | I9: =SUM(G9:H9) -> 21835861 | J9: 3556709
B10: Notes receivable:
C11: Due within one year | G11: 481000 | I11: =SUM(G11:H11) -> 481000
C12: Due in more than one year | G12: 1590000 | I12: =SUM(G12:H12) -> 1590000
B13: Internal balance | G13: 43987 | H13: -43987 | I13: =SUM(G13:H13) -> 0
B14: Inventories | G14: 35049 | H14: 294560 | I14: =SUM(G14:H14) -> 329609 | J14: 334518
B15: Prepaid items | G15: 160909 | H15: 36471 | I15: =SUM(G15:H15) -> 197380 | J15: 731135
B16: Restricted assets
C17: Cash and cash equivalents | H17: 491249 | I17: =SUM(G17:H17) -> 491249
C18: Held by trustee for debt service | J18: 1272606
C19: Internally designated for capital acquisition | J19: 8553171
B20: Capital assets (net of accumulated depreciation) | G20: 56279384 | H20: 14520264 | I20: =SUM(G20:H20) -> 70799648 | J20: 22549068
B21: Other assets, net | H21: 245 | I21: =SUM(G21:H21) -> 245
B23: Total Assets | G23: =SUM(G7:G20) -> 111224529 | H23: =SUM(H7:H21) -> 23879383 | I23: =SUM(I7:I21) -> 135103912 | J23: =SUM(J7:J21) -> 45233452
A25: LIABILITIES
B26: Accounts payable and accrued expenses | G26: 3254897 | H26: 412534 | I26: =SUM(G26:H26) -> 3667431 | J26: 570191
B27: Contractual settlements | I27: =SUM(G27:H27) -> 0 | J27: 870161
B28: Other liabilities | G28: 73989 | I28: =SUM(G28:H28) -> 73989
B29: Other payables
B30: Accrued expenses | G30: 1331822 | H30: 131837 | I30: =SUM(G30:H30) -> 1463659 | J30: 2852138
B31: Liabilities payable from restricted assets | H31: 466696 | I31: =SUM(G31:H31) -> 466696
B32: Long-term liabilities:
D33: Due within one year | G33: 1465822 | H33: 55654 | I33: =SUM(G33:H33) -> 1521476 | J33: 242644
D34: Due in more than one year | G34: 9397585 | H34: 413108 | I34: =SUM(G34:H34) -> 9810693 | J34: 15467065
C36: Total Liabilities | G36: =SUM(G26:G34) -> 15524115 | H36: =SUM(H26:H34) -> 1479829 | I36: =SUM(I26:I34) -> 17003944 | J36: =SUM(J26:J34) -> 20002199
A38: NET ASSETS
B39: Net invested in capital assets | G39: 50197934 | H39: 14520264 | I39: =SUM(G39:H39) -> 64718198 | J39: 6839359
B40: Restricted for:
C41: General government | G41: 6378749 | I41: =SUM(G41:H41) -> 6378749
C42: Culture and recreation | G42: 4707191 | I42: =SUM(G42:H42) -> 4707191
C43: Debt service | G43: 1801474 | I43: =SUM(G43:H43) -> 1801474 | J43: 1272606
C44: Capital projects | G44: 1107620 | I44: =SUM(G44:H44) -> 1107620
C45: Health and welfare | G45: 5272994 | I45: =SUM(G45:H45) -> 5272994
C46: Highways and streets | G46: 4277291 | I46: =SUM(G46:H46) -> 4277291
C47: Public safety | G47: 11784280 | I47: =SUM(G47:H47) -> 11784280
C48: Sanitation | G48: 3501473 | I48: =SUM(G48:H48) -> 3501473
C49: Group health insurance claims | G49: 2050925 | I49: =SUM(G49:H49) -> 2050925
B50: Unrestricted | G50: 4620483 | H50: 7879290 | I50: =SUM(G50:H50) -> 12499773 | J50: 17119288
B52: Total Net Assets | G52: =SUM(G39:G50) -> 95700414 | H52: =SUM(H39:H50) -> 22399554 | I52: =SUM(I39:I50) -> 118099968 | J52: =SUM(J39:J50) -> 25231253
B54: Total Liabilities and Net Assets | G54: =G36+G52 -> 111224529 | H54: =H36+H52 -> 23879383 | I54: =I36+I52 -> 135103912 | J54: =J36+J52 -> 45233452

Sheet St John the Baptist
C1: St. John the Baptist Parish 2013 Statement of Net Assets
C2: Issued: December 31, 2013
G4: Primary Government | J4: Component Unit
G5: Governmental Activities | H5: Business-Type Activities | I5: Total | J5: Library
A6: ASSETS
B7: Cash and cash equivalents | G7: 58246102 | H7: 2662147 | I7: =SUM(G7:H7) -> 60908249 | J7: 3644502
B8: Inventory, at cost | H8: 363526 | I8: =SUM(G8:H8) -> 363526
B9: Receivables (net of allowances)
C10: Accounts | G10: 1444935 | H10: 2536807 | I10: =SUM(G10:H10) -> 3981742
C11: Ad valorem taxes | G11: 11902039 | I11: =SUM(G11:H11) -> 11902039 | J11: 4344320
C12: Sales and use taxes | G12: 3481479 | I12: =SUM(G12:H12) -> 3481479
C13: Other | G13: 315907 | I13: =SUM(G13:H13) -> 315907 | J13: 63067
B14: Due from other governments | G14: 782043 | H14: 301586 | I14: =SUM(G14:H14) -> 1083629
B15: Prepaid items | G15: 137860 | H15: 116002 | I15: =SUM(G15:H15) -> 253862
B16: Restricted assets | H16: 1229264 | I16: =SUM(G16:H16) -> 1229264
B17: Internal balances | G17: 402344 | H17: -402344 | I17: =SUM(G17:H17) -> 0
B18: Capital assets not being depreciated | G18: 8723315 | H18: 2031419 | I18: =SUM(G18:H18) -> 10754734 | J18: 40000
B19: Capital assets being depreciated
C20: (net of accumulated depreciation) | G20: 68660908 | H20: 126935340 | I20: =SUM(G20:H20) -> 195596248 | J20: 5351171
B22: Total Assets | G22: =SUM(G7:G20) -> 154096932 | H22: =SUM(H7:H20) -> 135773747 | I22: =SUM(I7:I20) -> 289870679 | J22: =SUM(J7:J20) -> 13443060
A24: LIABILITIES
B25: Accounts, salaries, and other payables | G25: 3755988 | H25: 2759562 | I25: =SUM(G25:H25) -> 6515550 | J25: 28851
B26: Contracts payable | G26: 78792 | I26: =SUM(G26:H26) -> 78792
B27: Due to other governments | G27: 53604 | I27: =SUM(G27:H27) -> 53604
B28: Deposits due others | H28: 1302904 | I28: =SUM(G28:H28) -> 1302904
B29: Other liabilities | H29: 161659 | I29: =SUM(G29:H29) -> 161659 | J29: 185724
B30: Interest payable | G30: 698968 | H30: 9661 | I30: =SUM(G30:H30) -> 708629
B31: Noncurrent liabilities: | I31: =SUM(G31:H31) -> 0
C32: Due within one yeear | G32: 6203877 | H32: 261000 | I32: =SUM(G32:H32) -> 6464877
C33: Due in more than one year | G33: 69298429 | H33: 4367478 | I33: =SUM(G33:H33) -> 73665907 | J33: 962113
C35: Total Liabilities | G35: =SUM(G25:G33) -> 80089658 | H35: =SUM(H25:H33) -> 8862264 | I35: =SUM(I25:I33) -> 88951922 | J35: =SUM(J25:J33) -> 1176688
A37: NET ASSETS
B38: Net investment in capital assets | G38: 10633141 | H38: 124338281 | I38: =SUM(G38:H38) -> 134971422 | J38: 5391171
B39: Restricted for:
C40: Special revenue | G40: 34178846 | I40: =SUM(G40:H40) -> 34178846
C41: Debt service | G41: 13956797 | H41: 420000 | I41: =SUM(G41:H41) -> 14376797
C42: Capital projects | G42: 8420546 | I42: =SUM(G42:H42) -> 8420546
C43: Customer deposits | H43: 73640 | I43: =SUM(G43:H43) -> 73640
C44: Endowment | J44: 5000
B45: Unrestricted | G45: 6817944 | H45: 2079562 | I45: =SUM(G45:H45) -> 8897506 | J45: 6870201
B47: Total Net Assets | G47: =SUM(G38:G45) -> 74007274 | H47: =SUM(H38:H45) -> 126911483 | I47: =SUM(I38:I45) -> 200918757 | J47: =SUM(J37:J45) -> 12266372
B49: Total Liabilities and Net Assets | G49: =SUM(G35+G47) -> 154096932 | H49: =SUM(H47+H35) -> 135773747 | I49: =SUM(I47+I35) -> 289870679 | J49: =SUM(J47+J35) -> 13443060

Sheet St. Landry
D1: St. Landry Parish 2013 Statement of Net Assets
D2: Issued: December 31, 2013
H4: Governmental Activities | I4: Component Units | J4: Total
A5: ASSETS
B6: Current Assets
C7: Cash and interest-bearing deposits | H7: 1555264 | I7: 1373535 | J7: =SUM(H7:I7) -> 2928799
C8: Receivables, net | H8: 5692205 | I8: 542188 | J8: =SUM(H8:I8) -> 6234393
C9: Prepaid expenditures | H9: 42458 | J9: =SUM(H9:I9) -> 42458
C10: Due from agency funds | H10: 290254 | J10: =SUM(H10:I10) -> 290254
C11: Due from component units | H11: 4357 | J11: =SUM(H11:I11) -> 4357
C12: Due from other governments | H12: 20051 | J12: =SUM(H12:I12) -> 20051
C13: Due from primary government | I13: 6389 | J13: =SUM(H13:I13) -> 6389
C15: Total Current Assets | H15: =SUM(H7:H13) -> 7604589 | I15: =SUM(I7:I13) -> 1922112 | J15: =SUM(J7:J13) -> 9526701
B17: Noncurrent assets
C18: Capital assets, net | H18: 9506315 | I18: 2833181 | J18: =SUM(H18:I18) -> 12339496
C20: Total Assets | H20: =SUM(H15:H19) -> 17110904 | I20: =SUM(I15:I18) -> 4755293 | J20: =SUM(J15:J18) -> 21866197
A22: LIABILITIES
B23: Current
C24: Accounts payable | H24: 2100083 | I24: 190379 | J24: =SUM(H24:I24) -> 2290462
C25: Accrued expenses | H25: 214419 | J25: =SUM(H25:I25) -> 214419
C26: Bonds payable | H26: 58000 | I26: 80000 | J26: =SUM(H26:I26) -> 138000
C27: Accrued interest | H27: 3082 | I27: 21916 | J27: =SUM(H27:I27) -> 24998
C28: Deferred revenue | H28: 4737 | J28: =SUM(H28:I28) -> 4737
C29: Compensated absences | H29: 121245 | I29: 8538 | J29: =SUM(H29:I29) -> 129783
C30: Due to agency funds | H30: 95000 | J30: =SUM(H30:I30) -> 95000
C31: Due to component units | H31: 6389 | J31: =SUM(H31:I31) -> 6389
C32: Due primary government | I32: 4357 | J32: =SUM(H32:I32) -> 4357
D34: Total Current Liabilities | H34: =SUM(H24:H32) -> 2602955 | I34: =SUM(I23:I32) -> 305190 | J34: =SUM(J24:J32) -> 2908145
B36: Noncurrent
C37: Claims payable | H37: 171605 | J37: =SUM(H37:I37) -> 171605
C38: Bonds payable | H38: 60000 | I38: 1180000 | J38: =SUM(H38:I38) -> 1240000
D40: Total Noncurrent Liabilities | H40: =SUM(H36:H38) -> 231605 | I40: =SUM(I37:I38) -> 1180000 | J40: =SUM(J37:J38) -> 1411605
D42: Total Liabilities | H42: =SUM(H34+H40) -> 2834560 | I42: =SUM(I34+I40) -> 1485190 | J42: =SUM(J34+J40) -> 4319750
A44: NET ASSETS
B45: Invested in capital assets, net of related debt | H45: 9506315 | I45: 1573181 | J45: =SUM(H45:I45) -> 11079496
B46: Restricted for debt service | H46: 42458 | J46: =SUM(H46:I46) -> 42458
B47: Restricted- other | H47: 663515 | J47: =SUM(H47:I47) -> 663515
B48: Unrestricted | H48: 4064056 | I48: 1696922 | J48: =SUM(H48:I48) -> 5760978
C50: Total Net Assets | H50: =SUM(H45:H48) -> 14276344 | I50: =SUM(I45:I48) -> 3270103 | J50: =SUM(J44:J48) -> 17546447
C52: Total Liabilities and Net Assets | H52: =SUM(H42+H50) -> 17110904 | I52: =SUM(I50+I42) -> 4755293 | J52: =SUM(J50+J42) -> 21866197

Sheet St. Martin
D1: St. Martin Parish 2013 Statement of Net Assets
D2: Issued: December 31, 2013
H4: Governmental Activities | I4: Business-Type Activities | J4: Total
A5: ASSETS
C6: Cash and interest bearing deposits | H6: 23148572 | J6: =SUM(H6:I6) -> 23148572
C7: Receivables | H7: 11004695 | I7: 368645 | J7: =SUM(H7:I7) -> 11373340
C8: Internal balances | H8: 204890 | J8: =SUM(H8:I8) -> 204890
C9: Due from other governments | H9: 183431 | J9: =SUM(H9:I9) -> 183431
C10: Capital assets:
D11: Non-depreciable | H11: 10938131 | J11: =SUM(H11:I11) -> 10938131
D12: Depreciable (net) | H12: 59422704 | J12: =SUM(H12:I12) -> 59422704
C14: Total Assets | H14: =SUM(H6:H12) -> 104902423 | I14: =SUM(I6:I12) -> 368645 | J14: =SUM(J6:J12) -> 105271068
A16: LIABILITIES
C17: Accounts payable | H17: 76361 | I17: 209728 | J17: =SUM(H17:I17) -> 286089
C18: Internal balances | I18: 204890 | J18: =SUM(H18:I18) -> 204890
C19: Accrued interest payable | H19: 231068 | J19: =SUM(H19:I19) -> 231068
C20: Due to other governments | H20: 93304 | J20: =SUM(H20:I20) -> 93304
C21: Other liabilities | H21: 308916 | I21: 2293 | J21: =SUM(H21:I21) -> 311209
C22: Long-term liabilities:
D23: Bonds payable, due within one year | H23: 1781000 | J23: =SUM(H23:I23) -> 1781000
D24: Bonds payable, due in more than one year | H24: 22494000 | J24: =SUM(H24:I24) -> 22494000
D25: Capital leases payable, due within one year | H25: 193138 | J25: =SUM(H25:I25) -> 193138
D26: Capital leases payable, due in more than one year | H26: 150518 | J26: =SUM(H26:I26) -> 150518
D27: OPEB liability-due in more than one year | H27: 5646858 | J27: =SUM(H27:I27) -> 5646858
D28: Compensated absences payable | H28: 410568 | J28: =SUM(H28:I28) -> 410568
D30: Total Liabilities | H30: =SUM(H17:H28) -> 31385731 | I30: =SUM(I17:I28) -> 416911 | J30: =SUM(J17:J28) -> 31802642
A32: NET ASSETS
B33: Net investment in capital assets | H33: 45511111 | J33: =SUM(H33:I33) -> 45511111
B34: Restricted for:
C35: Debt service | H35: 4608471 | J35: =SUM(H35:I35) -> 4608471
C36: Other purposes | H36: 24603290 | I36: 30996 | J36: =SUM(H36:I36) -> 24634286
B37: Unrestricted (deficit) | H37: -1893420 | I37: -79262 | J37: =SUM(H37:I37) -> -1972682
C39: Total Net Assets | H39: =SUM(H33:H37) -> 72829452 | I39: =SUM(I33:I37) -> -48266 | J39: =SUM(J32:J37) -> 72781186
C41: Total Liabilities and Net Assets | H41: =SUM(H30+H39) -> 104215183 | I41: =SUM(I39+I30) -> 368645 | J41: =SUM(J39+J30) -> 104583828

Sheet St. Mary
D1: St. Mary Parish 2013 Statement of Net Assets
D2: Issued: December 31, 2013
H4: Primary Government
H5: Governmental Activities | I5: Business-type Activities | J5: Total
A6: ASSETS
B7: Current Assets
C8: Cash and cash equivalents | H8: 4392344 | I8: 230569 | J8: =SUM(H8:I8) -> 4622913
C9: Investments | H9: 14775501 | I9: 1996024 | J9: =SUM(H9:I9) -> 16771525
C10: Receivables (net of allowances for uncollectibles) | H10: 1166958 | I10: 515375 | J10: =SUM(H10:I10) -> 1682333
C11: Due from component units | H11: 1975880 | J11: =SUM(H11:I11) -> 1975880
C12: Due from other governments | H12: 10764256 | I12: 101291 | J12: =SUM(H12:I12) -> 10865547
C13: Other assets | H13: 4220 | J13: =SUM(H13:I13) -> 4220
C14: Internal balances | H14: -8111173 | I14: 8111173 | J14: =SUM(H14:I14) -> 0
C16: Total Current Assets | H16: =SUM(H8:H14) -> 24967986 | I16: =SUM(I8:I14) -> 10954432 | J16: =SUM(J8:J14) -> 35922418
B18: Noncurrent Assets
C19: Restricted cash | I19: 2279994 | J19: =SUM(H19:I19) -> 2279994
C20: Restricted investments | I20: 829958 | J20: =SUM(H20:I20) -> 829958
J21: =SUM(H21:I21) -> 0
C22: Total restricted assets | I22: =SUM(I19:I20) -> 3109952 | J22: =SUM(J19:J20) -> 3109952
B24: Capital assets
C25: Land and improvements | H25: 1870876 | I25: 3802599 | J25: =SUM(H25:I25) -> 5673475
C26: Buildings, net of accumulated depreciation | H26: 10520454 | I26: 152238 | J26: =SUM(H26:I26) -> 10672692
C27: Improvements other than buildings, net of | J27: =SUM(H27:I27) -> 0
D28: accumulated depreciation | H28: 13744984 | I28: 14748782 | J28: =SUM(H28:I28) -> 28493766
C29: Equipment and furniture, net of accumulated | J29: =SUM(H29:I29) -> 0
D30: depreciation | H30: 2023025 | I30: 2065040 | J30: =SUM(H30:I30) -> 4088065
C31: Infrastructure, net of accumulated depreciation | H31: 78560660 | J31: =SUM(H31:I31) -> 78560660
C32: Construction in progress | H32: 1887343 | I32: 314569 | J32: =SUM(H32:I32) -> 2201912
C34: Total Noncurrent Assets | H34: =SUM(H25:H32) -> 108607342 | I34: =SUM(I25:I32) -> 21083228 | J34: =SUM(J25:J32) -> 129690570
C36: Total Assets | H36: =SUM(H34+H22+H16) -> 133575328 | I36: =SUM(I34+I22+I16) -> 35147612 | J36: =SUM(J34+J22+J16) -> 168722940
A38: Gain on refunding | I38: 245000 | J38: =I38 -> 245000
C39: Total deferred outflows of resources
C41: Total assets and deferred outflows of resources | H41: =H36 -> 133575328 | I41: =SUM(I36:I38) -> 35392612 | J41: =SUM(J36:J38) -> 168967940
A43: LIABILITIES
B44: Current liabilities
C45: Accounts payable | H45: 1093698 | I45: 327975 | J45: =SUM(H45:I45) -> 1421673
C46: Retainage payable | H46: 159540 | I46: 10932 | J46: =SUM(H46:I46) -> 170472
C47: Accrued liabilities | H47: 428191 | J47: =SUM(H47:I47) -> 428191
C48: Due to other governments | H48: 663469 | J48: =SUM(H48:I48) -> 663469
C49: Accrued interest payable | H49: 273245 | J49: =SUM(H49:I49) -> 273245
C50: Current portion of long-term debt | H50: 2624000 | I50: 715000 | J50: =SUM(H50:I50) -> 3339000
D52: Total Current Liabilities | H52: =SUM(H45:H50) -> 5242143 | I52: =SUM(I44:I50) -> 1053907 | J52: =SUM(J45:J50) -> 6296050
B54: Noncurrent liabilities
C55: Other post-employment benefits | H55: 5880700 | I55: 867600 | J55: =SUM(H55:I55) -> 6748300
C56: Compensated absences | H56: 165000 | J56: =SUM(H56:I56) -> 165000
C57: Noncurent portion of long-term debt | H57: 22254694 | I57: 12891980 | J57: =SUM(H57:I57) -> 35146674
C58: Landfill closure costs and post-closure care costs | I58: 3728000 | J58: =SUM(H58:I58) -> 3728000
D60: Total Noncurrent Liabilities | H60: =SUM(H54:H58) -> 28300394 | I60: =SUM(I54:I58) -> 17487580 | J60: =SUM(J54:J58) -> 45787974
D62: Total Liabilities | H62: =SUM(H52+H60) -> 33542537 | I62: =SUM(I60+I52) -> 18541487 | J62: =SUM(J52+J60) -> 52084024
A64: NET ASSETS
B65: Investment in capital assets | H65: 83404108 | I65: 7476248 | J65: =SUM(H65:I65) -> 90880356
B66: Restricted for:
C67: Debt service | H67: 2327076 | I67: 788182 | J67: =SUM(H67:I67) -> 3115258
C68: Other Purposes | H68: 14118675 | I68: -1554648 | J68: =SUM(H68:I68) -> 12564027
B69: Unrestricted | H69: 182932 | I69: 10141343 | J69: =SUM(H69:I69) -> 10324275
C71: Total Net Assets | H71: =SUM(H65:H69) -> 100032791 | I71: =SUM(I65:I69) -> 16851125 | J71: =SUM(J65:J69) -> 116883916
C73: Total Liabilities and Net Assets | H73: =SUM(H62+H71) -> 133575328 | I73: =SUM(I71+I62) -> 35392612 | J73: =SUM(J62+J71) -> 168967940

Sheet St. Tammany
D1: St.Tammany Parish 2013 Statement of Net Assets
D2: Issued: December 31, 2013
H4: Primary Government
H5: Governmental Activities | I5: Business-type Activities | J5: Total | K5: Component Units | L5: Total
A6: ASSETS
C7: Cash and cash equivalents | H7: 33410917 | I7: 1487270 | J7: =SUM(H7:I7) -> 34898187 | K7: 30579366 | L7: =SUM(J7:K7) -> 65477553
C8: Investments | H8: 147136813 | I8: 9165500 | J8: =SUM(H8:I8) -> 156302313 | K8: 17696642 | L8: =SUM(J8:K8) -> 173998955
C9: Receivables (net of allowances for uncollectibles) | H9: 49934017 | I9: 849148 | J9: =SUM(H9:I9) -> 50783165 | K9: 59452937 | L9: =SUM(J9:K9) -> 110236102
C10: Due from primary government/component units | H10: 24006 | J10: =SUM(H10:I10) -> 24006 | K10: 8639997 | L10: =SUM(J10:K10) -> 8664003
C11: Inventory | J11: =SUM(H11:I11) -> 0 | K11: 2274324 | L11: =SUM(J11:K11) -> 2274324
C12: Prepaid items | H12: 87540 | J12: =SUM(H12:I12) -> 87540 | K12: 570291 | L12: =SUM(J12:K12) -> 657831
C13: Restricted assets | H13: 9765448 | I13: 4196582 | J13: =SUM(H13:I13) -> 13962030 | K13: 4149109 | L13: =SUM(J13:K13) -> 18111139
C14: Other assets | H14: 2120 | I14: 13159 | J14: =SUM(H14:I14) -> 15279 | K14: 22974 | L14: =SUM(J14:K14) -> 38253
C15: Capital assets: | J15: =SUM(H15:I15) -> 0 | L15: =SUM(J15:K15) -> 0
D16: Land. improvements and construction in progress | H16: 105108197 | I16: 1167018 | J16: =SUM(H16:I16) -> 106275215 | K16: 11307617 | L16: =SUM(J16:K16) -> 117582832
D17: Other capital assets, net of depreciation | H17: 308418347 | I17: 39486517 | J17: =SUM(H17:I17) -> 347904864 | K17: 80491864 | L17: =SUM(J17:K17) -> 428396728
C19: Total Assets | H19: =SUM(H7:H17) -> 653887405 | I19: =SUM(I7:I17) -> 56365194 | J19: =SUM(J7:J17) -> 710252599 | K19: =SUM(K7:K17) -> 215185121 | L19: =SUM(L7:L17) -> 925437720
B21: Deferred outflows of resources
C22: Deferred charges on refunding | H22: 5106064 | J22: =SUM(H22:I22) -> 5106064 | K22: 296771 | L22: =SUM(J22:K22) -> 5402835
C24: Total Deferred Outflows of Resources | H24: =SUM(H21:H22) -> 5106064 | I24: =SUM(I22) -> 0 | J24: =SUM(J22) -> 5106064 | K24: =SUM(K22) -> 296771 | L24: =SUM(L22) -> 5402835
A26: LIABILITIES
C27: Accounts, salaries, and other payables | H27: 19836750 | I27: 675938 | J27: =SUM(H27:I27) -> 20512688 | K27: 3549524 | L27: =SUM(J27:K27) -> 24062212
C28: Payable from restricted assets | J28: =SUM(H28:I28) -> 0 | K28: 128082 | L28: =SUM(J28:K28) -> 128082
C29: Due to primary government/component units | H29: 8555724 | J29: =SUM(H29:I29) -> 8555724 | K29: 108279 | L29: =SUM(J29:K29) -> 8664003
C30: Unearned revenues | H30: 3491906 | J30: =SUM(H30:I30) -> 3491906 | K30: 734354 | L30: =SUM(J30:K30) -> 4226260
C31: Other liabilities | H31: 2319255 | I31: 1163951 | J31: =SUM(H31:I31) -> 3483206 | K31: 111663 | L31: =SUM(J31:K31) -> 3594869
C32: Interest payable | H32: 634737 | I32: 826945 | J32: =SUM(H32:I32) -> 1461682 | K32: 471123 | L32: =SUM(J32:K32) -> 1932805
C33: Non-current liabilities: | L33: =SUM(J33:K33) -> 0
D34: Due within one year | H34: 9708024 | I34: 710000 | J34: =SUM(H34:I34) -> 10418024 | K34: 4760420 | L34: =SUM(J34:K34) -> 15178444
D35: Due in more than one year | H35: 97673633 | I35: 41425586 | J35: =SUM(H35:I35) -> 139099219 | K35: 31502713 | L35: =SUM(J35:K35) -> 170601932
D37: Total Liabilities | H37: =SUM(H27:H35) -> 142220029 | I37: =SUM(I27:I35) -> 44802420 | J37: =SUM(J27:J35) -> 187022449 | K37: =SUM(K27:K35) -> 41366158 | L37: =SUM(L27:L35) -> 228388607
A39: NET ASSETS
B40: Net investment in capital assets | H40: 337361295 | I40: -1482051 | J40: =SUM(H40:I40) -> 335879244 | K40: 60872039 | L40: =SUM(J40:K40) -> 396751283
B41: Restricted for: | J41: =SUM(H41:I41) -> 0 | L41: =SUM(J41:K41) -> 0
C42: Capital projects | H42: 8167272 | I42: 457268 | J42: =SUM(H42:I42) -> 8624540 | K42: 3002091 | L42: =SUM(J42:K42) -> 11626631
C43: Culture and recreation | H43: 199753 | J43: =SUM(H43:I43) -> 199753 | L43: =SUM(J43:K43) -> 199753
C44: Debt service | H44: 9765448 | I44: 3739314 | J44: =SUM(H44:I44) -> 13504762 | K44: 4640487 | L44: =SUM(J44:K44) -> 18145249
C45: Economic development | H45: 256520 | J45: =SUM(H45:I45) -> 256520 | L45: =SUM(J45:K45) -> 256520
C46: Health and welfare | H46: 9096739 | J46: =SUM(H46:I46) -> 9096739 | L46: =SUM(J46:K46) -> 9096739
C47: Judicial | H47: 10019657 | J47: =SUM(H47:I47) -> 10019657 | L47: =SUM(J47:K47) -> 10019657
C48: Lighting districts | H48: 4769924 | J48: =SUM(H48:I48) -> 4769924 | L48: =SUM(J48:K48) -> 4769924
C49: Public safety | H49: 12086291 | J49: =SUM(H49:I49) -> 12086291 | L49: =SUM(J49:K49) -> 12086291
C50: Roads, bridges and drainage | H50: 88774950 | J50: =SUM(H50:I50) -> 88774950 | L50: =SUM(J50:K50) -> 88774950
C51: Transit | H51: 726746 | J51: =SUM(H51:I51) -> 726746 | L51: =SUM(J51:K51) -> 726746
B52: Unrestricted | H52: 35548845 | I52: 8848243 | J52: =SUM(H52:I52) -> 44397088 | K52: 105601117 | L52: =SUM(J52:K52) -> 149998205
C54: Total Net Assets | H54: =SUM(H40:H52) -> 516773440 | I54: =SUM(I40:I52) -> 11562774 | J54: =SUM(J40:J52) -> 528336214 | K54: =SUM(K40:K52) -> 174115734 | L54: =SUM(L40:L52) -> 702451948
C56: Total Liabilities and Net Assets | H56: =SUM(H37+H54) -> 658993469 | I56: =SUM(I37+I54) -> 56365194 | J56: =SUM(J37+J54) -> 715358663 | K56: =SUM(K37+K54) -> 215481892 | L56: =SUM(L37+L54) -> 930840555

Sheet Tangipahoa
D1: Tangipahoa Parish 2013 Statement of Net Assets
D2: Issued: December 31, 2013
H4: Primary Government | I4: Component Units
H5: Governmental Activities | I5: Governmental Activities
A6: ASSETS
C7: Cash and cash equivalents | H7: 17398202 | I7: 5455651
C8: Investment in certificates of deposit | I8: 1405848
C9: Receivebles, net | H9: 8935241 | I9: 5924672
C10: Due from other governments | H10: 42692
C11: Restricted assets- cash | H11: 898211 | I11: 3784
C12: Prepaid insurance | I12: 59520
C13: Capital assets (net) | H13: 178240431 | I13: 9545067
C15: Total Assets | H15: =SUM(H7:H13) -> 205514777 | I15: =SUM(I7:I13) -> 22394542
A17: LIABILITIES
C18: Cash overdraft | H18: 515
C19: Accounts, salaries, and other payables | H19: 4186126 | I19: 397478
C20: Due to other governments | H20: 383324 | I20: 71532
C21: Due to volunteer fire departments | I21: 1427112
C22: Noncuurent liabilities:
D23: Due within one year | H23: 90000 | I23: 280408
D24: Due in more than one year | H24: 8104902 | I24: 1196363
D25: Postemployment healthcare benefits payable | H25: 1567398
D27: Total Liabilities | H27: =SUM(H18:H25) -> 14332265 | I27: =SUM(I18:I25) -> 3372893
A29: Deferred inflow of resources
C30: Hazard Mitigation Funds | H30: 53394
C32: Total Deferred inflow of resources | H32: =SUM(H30:H30) -> 53394 | I32: =SUM(I30:I30) -> 0
A34: NET ASSETS
B35: Invested in capital assets, net of related debt | H35: 175665431 | I35: 8303477
B36: Restricted for:
C37: Capital projects | H37: 239065
C38: Debt service | H38: 354764 | I38: 3784
C39: Other purposes | H39: 746958 | I39: 10714688
B40: Unrestricted | H40: 14122900
C42: Total Net Assets | H42: =SUM(H35:H40) -> 191129118 | I42: =SUM(I35:I40) -> 19021949
C44: Total Liabilities and Net Assets | H44: =SUM(H42+H27+H32) -> 205514777 | I44: =SUM(I42+I27+I32) -> 22394842

Sheet Tensas
C1: Tensas Parish 2013 Statement of Net Assets
C2: Issued: December 31, 2013
G4: Governmental Activities
A5: ASSETS
B6: Cash and cash equivalents | G6: 2313344
B7: Receivables | G7: 763109
B8: Amounts held by trustee for landfill closure
C9: and post-closure care costs | G9: 944665
B10: Restricted assets | G10: 29094
B11: Capital assets, net | G11: 8567911
B13: Total Assets | G13: =SUM(G6:G11) -> 12618123
A15: LIABILITIES
B16: Accounts, salaries, and other payables | G16: 156049
B17: Intergovernmental payables | G17: 54048
B18: Long-term liabilities:
C19: Due within one year | G19: 39882
C20: Due in more than one year | G20: 1255223
C22: Total Liabilities | G22: =SUM(G16:G20) -> 1505202
A24: NET ASSETS
B25: Invested in capital assets, net of related debt | G25: 7414340
B26: Restricted for:
C27: Debt service | G27: 29094
C28: Landfill closure | G28: 944665
B29: Unrestricted | G29: 2724822
B31: Total Net Assets | G31: =SUM(G25:G29) -> 11112921
B33: Total Liabilities and Net Assets | G33: =SUM(G22+G31) -> 12618123

Sheet Terrebonne
D1: Terrebonne Parish 2013 Statement of Net Assets
D2: Issued: December 31, 2013
H4: Primary Government
H5: Governmental Activities | I5: Business-Type Activities | J5: Total | K5: Component Unit
A6: ASSETS
C7: Cash and cash equivalents | H7: 25560944 | I7: 19476492 | J7: =SUM(H7:I7) -> 45037436 | K7: 71367610
C8: Investments | H8: 91704922 | I8: 25186798 | J8: =SUM(H8:I8) -> 116891720 | K8: 190895040
C9: Receivables | H9: 9293551 | I9: 9902100 | J9: =SUM(H9:I9) -> 19195651 | K9: 41102618
C10: Internal balances | H10: 4475677 | I10: -4475677 | J10: =SUM(H10:I10) -> 0
C11: Due from other governments | H11: 69924659 | I11: 10561703 | J11: =SUM(H11:I11) -> 80486362 | K11: 22383791
C12: Due from component units | H12: 28642 | J12: =SUM(H12:I12) -> 28642
C13: Due from primary government | K13: 2438
C14: Inventories | H14: 2019531 | I14: 19722 | J14: =SUM(H14:I14) -> 2039253 | K14: 4217818
C15: Other assets | H15: 1346260 | I15: 1938576 | J15: =SUM(H15:I15) -> 3284836 | K15: 10993935
C16: Restricted assets:
D17: Cash and cash equivalents | H17: 205485 | I17: 3491836 | J17: =SUM(H17:I17) -> 3697321 | K17: 24569845
D18: Investments | I18: 2288502 | J18: =SUM(I18) -> 2288502
D19: Receivables | I19: 50641 | J19: =SUM(I19) -> 50641
D20: Due from other governments | I20: 602975 | J20: =SUM(I20) -> 602975
C21: Investment in joint venture | I21: 1103465 | J21: =SUM(I21) -> 1103465
C22: Capital assets: | J22: =SUM(H22:I22) -> 0
D23: Non-depreciable | H23: 49093810 | I23: 15668393 | J23: =SUM(H23:I23) -> 64762203 | K23: 49448854
D24: Depreciable, net | H24: 248631957 | I24: 135434728 | J24: =SUM(H24:I24) -> 384066685 | K24: 592717622
C26: Total Assets | H26: =SUM(H7:H24) -> 502285438 | I26: =SUM(I7:I24) -> 221250254 | J26: =SUM(J7:J24) -> 723535692 | K26: =SUM(K7:K24) -> 1007699571
A28: Deferred Outflows of Resources | H28: 132278 | J28: =SUM(H28:I28) -> 132278 | K28: 383427
A30: LIABILITIES
C31: Accounts payable and other current liabilities | H31: 22525998 | I31: 7214755 | J31: =SUM(H31:I31) -> 29740753 | K31: 34872706
C32: Accrued interest payable | H32: 1439333 | J32: =SUM(H32:I32) -> 1439333
C33: Due to other governments | H33: 7589076 | I33: 550233 | J33: =SUM(H33:I33) -> 8139309 | K33: 887373
C34: Due to component units | H34: 2438 | J34: =SUM(H34:I34) -> 2438
C35: Due to primary government | K35: 28642
C36: Grant Advancements | H36: 1149808 | J36: =SUM(H36:I36) -> 1149808
C37: Liabilities payable from restricted assets | H37: 135065 | I37: 1624702 | J37: =SUM(H37:I37) -> 1759767
C38: Noncurrent liabilities: | J38: =SUM(H38:I38) -> 0
D39: Due within one year | H39: 6196610 | I39: 1236088 | J39: =SUM(H39:I39) -> 7432698 | K39: 6131660
D40: Due in more than one year | H40: 119817673 | I40: 16790963 | J40: =SUM(H40:I40) -> 136608636 | K40: 115711002
D42: Total Liabilities | H42: =SUM(H31:H40) -> 158856001 | I42: =SUM(I31:I40) -> 27416741 | J42: =SUM(J31:J40) -> 186272742 | K42: =SUM(K31:K40) -> 157631383
A44: Deferred Inflows of Resources | H44: 27193917 | I44: 9974005 | J44: =SUM(H44:I44) -> 37167922 | K44: 26961437
A46: NET ASSETS
B47: Invested in capital assets, net of related debt | H47: 236913363 | I47: 137504660 | J47: =SUM(H47:I47) -> 374418023 | K47: 540431339
B48: Restricted for: | J48: =SUM(H48:I48) -> 0
C49: General governments | H49: 226735 | J49: =SUM(H49:I49) -> 226735
C50: Streets and drainage | H50: 11405690 | J50: =SUM(H50) -> 11405690
C51: Capital projects | H51: 27192190 | J51: =SUM(H51) -> 27192190 | K51: 7820662
C52: Debt service | H52: 15506186 | I52: 3186302 | J52: =SUM(H52:I52) -> 18692488 | K52: 10630866
C53: Health and welfare | H53: 5177929 | J53: =SUM(H53) -> 5177929
C54: Economic development and assistance | H54: 740952 | J54: =SUM(H54) -> 740952
C55: Urban redevelopment and assistance | H55: 2424405 | J55: =SUM(H55) -> 2424405
C56: Utilities | I56: 28247764 | J56: =SUM(I56) -> 28247764
C57: Sewerage | I57: 1886064 | J57: =SUM(I57) -> 1886064
C58: Sanitation | I58: 13147447 | J58: =SUM(I58) -> 13147447
C59: Other purposes | K59: 5115491
B60: Unrestricted (deficit) | H60: 16780348 | I60: -112729 | J60: =SUM(H60:I60) -> 16667619 | K60: 259491820
C62: Total Net Assets | H62: =SUM(H47:H60) -> 316367798 | I62: =SUM(I47:I60) -> 183859508 | J62: =SUM(J47:J60) -> 500227306 | K62: =SUM(K46:K60) -> 823490178
C64: Total Liabilities and Net Assets | H64: =SUM(H62+H42+H44) -> 502417716 | I64: =SUM(I62+I42+I44) -> 221250254 | J64: =SUM(J62+J42+J44) -> 723667970 | K64: =SUM(K62+K42+K44) -> 1008082998

Sheet Union
C1: Union Parish 2013 Statement of Net Assets
C2: Issued: December 31, 2013
G4: Governmental Activities
A5: ASSETS
B6: Cash and cash equivalents | G6: 7110474
B7: Investments | G7: 7240283
B8: Receivables | G8: 4749704
B9: Capital assets, net of accumulated depreciation | G9: 12207847
B11: Total Assets | G11: =SUM(G6:G9) -> 31308308
A13: LIABILITIES
B14: Cash overdraft | G14: 987165
B15: Accounts, salaries and other payables | G15: 1373845
B16: Deposits due others | G16: 260018
B17: Compensated absences | G17: 219368
B18: Certificates of indebtedness due within one year | G18: 174000
B19: Certificates of indebtedness due in more than one year | G19: 180000
B20: Public building revenue bonds due within one year | G20: 18000
B21: Public building revenue bonds due in more than one year | G21: 235000
B22: Net OPEB obligation | G22: 1012903
B23: Landfill closure/postclosure care | G23: 6907020
C25: Total Liabilities | G25: =SUM(G14:G23) -> 11367319
G26: \
A27: DEFERRED INFLOWS
B28: Grant revenues pending | G28: 14194
A30: NET ASSETS
B31: Net investment in capital assets | G31: 11600847
B32: Restricted for landfill closure/postclosure care | G32: 4765799
B33: Unrestricted | G33: 3560149
B35: Total Net Assets | G35: =SUM(G31:G33) -> 19926795
B37: Total Liabilities and Net Assets | G37: =SUM(G25+G35+G28) -> 31308308

Sheet Vermillion
D1: Vermillion Parish 2013 Statement of Net Assets
D2: Issued: December 31, 2013
H4: Primary Government | I4: Component Units
H5: Governmental Activities | I5: Criminal Court Fund | J5: Tourist Commission
A6: ASSETS
C7: Cash and interest-bearing deposits | H7: 53128318 | I7: 60326 | J7: 205047
C8: Receivables, net | H8: 381262 | J8: 100
C9: Due from component unit | H9: 630
C10: Due from other governmental units | H10: 8635042 | I10: 186781 | J10: 60361
C11: Prepaid expenses | H11: 56444
C12: Capital assets, net | H12: 82500254
C14: Total Assets | H14: =SUM(H7:H12) -> 144701950 | I14: =SUM(I7:I12) -> 247107 | J14: =SUM(J7:J12) -> 265508
A16: LIABILITIES
C17: Accounts and other payables | H17: 1215562 | I17: 28729 | J17: 21343
C18: Contracts payable | H18: 818573
C19: Retainage payable | H19: 151097
C20: Due to primary government | I20: 630
C21: Due to other governments | H21: 58759
C22: Accrued interest payable | H22: 31076
C23: Long-term liabilities:
D24: Due within one year | H24: 365000
D25: Due in more than one year | H25: 5463515
D27: Total Liabilities | H27: =SUM(H17:H25) -> 8103582 | I27: =SUM(I17:I25) -> 29359 | J27: =SUM(J17:J25) -> 21343
A29: DEFERRED INFLOWS OF RESOURCES
C30: Deferred revenue | H30: 948391
A32: NET ASSETS
B33: Net investment in capital assets | H33: 80370929
B34: Restricted for:
C35: Debt service | H35: 1615102
C36: Other purposes | H36: 36016375
B37: Unrestricted | H37: 17647571 | I37: 217748 | J37: 244165
C39: Total Net Assets | H39: =SUM(H33:H37) -> 135649977 | I39: =SUM(I33:I37) -> 217748 | J39: =SUM(J32:J37) -> 244165
C41: Total Liabilities and Net Assets | H41: =SUM(H27+H39+H30) -> 144701950 | I41: =SUM(I27+I39+I30) -> 247107 | J41: =SUM(J27+J39+J30) -> 265508

Sheet Vernon
D1: Vernon Parish 2013 Statement of Net Assets
D2: Issued: December 31, 2013
H5: 2013 | I5: 2012
A6: ASSETS
C7: Cash and cash equivalents | H7: 23897070 | I7: 23444012
C8: Investments, at fair market value | H8: 1246021 | I8: 1243260
C9: Receivebles | H9: 6132255 | I9: 5819491
C10: Other | H10: 21627
C11: Capital assets (net of accumulated depreciation):
D12: Land | H12: 1695977 | I12: 1675227
D13: Buildings and improvements | H13: 6348922 | I13: 6507783
D14: Furniture and equipment | H14: 8930284 | I14: 8408447
D15: Infrastructure | H15: 27802037 | I15: 27562146
D16: Library book collection | H16: 544834 | I16: 509728
C18: Total Assets | H18: =SUM(H7:H16) -> 76619027 | I18: =SUM(I7:I16) -> 75170094
A20: LIABILITIES
C21: Accounts, salaries, and other payables | H21: 831526 | I21: 755784
C22: Deferred revenue | H22: 110008 | I22: 2230
C23: Interest payable | H23: 382172 | I23: 388877
C24: Long-term liabilities:
D25: Due within one year | H25: 812070 | I25: 698388
D26: Due in more than one year | H26: 19678827 | I26: 17831812
D28: Total Liabilities | H28: =SUM(H21:H26) -> 21814603 | I28: =SUM(I21:I26) -> 19677091
A30: NET ASSETS
B31: Invested in capital assets, net of related debt | H31: 35813460 | I31: 35183499
B32: Restricted for:
C33: Debt service | H33: 749979 | I33: 797878
C34: Employee benefits | H34: 2213890 | I34: 2285219
B35: Unrestricted | H35: 16036096 | I35: 17226407
C37: Total Net Assets | H37: =SUM(H31:H35) -> 54813425 | I37: =SUM(I31:I35) -> 55493003
C39: Total Liabilities and Net Assets | H39: =SUM(H37+H28) -> 76628028 | I39: =SUM(I37+I28) -> 75170094

Sheet Washington
D1: Washington Parish 2013 Statement of Net Assets
D2: Issued: December 31, 2013
H4: Primary Government
H5: Governmental Activities | I5: Business-Type Activities | J5: Total
A6: ASSETS
C7: Cash | H7: 1269386 | I7: 110817 | J7: =SUM(H7:I7) -> 1380203
C8: Investments | H8: 2545233 | J8: =SUM(H8:I8) -> 2545233
C9: Receivables | H9: 5095177 | J9: =SUM(H9:I9) -> 5095177
C10: FEMA receivable | H10: 230025 | J10: =SUM(H10) -> 230025
C11: Prepaids | J11: =SUM(H11) -> 0
C12: Due from other funds
C13: Notes receivable
C14: Due from other funds
C15: Due from other governments | H15: 352460 | J15: =SUM(H15:I15) -> 352460
C16: Equity in Choctaw Road Landfill | H16: 1467434 | J16: =SUM(H16) -> 1467434
C17: Restricted other assets | H17: 873296 | J17: =SUM(H17) -> 873296
C18: Capital assets (net)
D19: Land | H19: 2564278 | J19: =SUM(H19) -> 2564278
D20: Construction in progress | H20: 1713828 | J20: =SUM(H20) -> 1713828
D21: Other capital assets, net of depreciation | H21: 33965136 | J21: =SUM(H21) -> 33965136
C23: Total Assets | H23: =SUM(H7:H21) -> 50076253 | I23: =SUM(I7:I21) -> 110817 | J23: =SUM(J7:J21) -> 50187070
A25: LIABILITIES
C26: Accounts payable | H26: 877732 | J26: =SUM(H26:I26) -> 877732
C27: Advanced revenue | H27: 342731 | J27: =SUM(H27:I27) -> 342731
C28: Due to other governments | H28: 910200 | J28: =SUM(H28:I28) -> 910200
C29: Due from other funds | J29: =SUM(H29:I29) -> 0
C30: OPEB liability | H30: 644340 | J30: =SUM(H30:I30) -> 644340
C31: Long-term liabilities: | J31: =SUM(H31:I31) -> 0
D32: Portion due within one year | H32: 1480893 | J32: =SUM(H32:I32) -> 1480893
D33: Portion due in more than one year | H33: 4425000 | J33: =SUM(H33:I33) -> 4425000
D35: Total Liabilities | H35: =SUM(H26:H33) -> 8680896 | I35: =SUM(I26:I33) -> 0 | J35: =SUM(J26:J33) -> 8680896
A37: NET ASSETS
B38: Invested in capital assets, net of related debt | H38: 33325933 | J38: =SUM(H38:I38) -> 33325933
B39: Restricted for:
C40: Capital projects | H40: 458165 | J40: =SUM(H40:I40) -> 458165
C41: Health and welfare | H41: 683997 | J41: =SUM(H41:I41) -> 683997
C42: Solid waste disposal | H42: 1477902 | J42: =SUM(H42:I42) -> 1477902
C43: Debt service | H43: 1249213 | J43: =SUM(H43:I43) -> 1249213
C44: Highways and bridges | H44: 2094708 | J44: =SUM(H44:I44) -> 2094708
C45: Other purposes | H45: 1777349 | J45: =SUM(H45:I45) -> 1777349
B46: Unrestricted | H46: 908364 | I46: 192351 | J46: =SUM(H46:I46) -> 1100715
C48: Total Net Assets | H48: =SUM(H38:H46) -> 41975631 | I48: =SUM(I38:I46) -> 192351 | J48: =SUM(J37:J46) -> 42167982
C50: Total Liabilities and Net Assets | H50: =SUM(H48+H35) -> 50656527 | I50: =SUM(I48+I35) -> 192351 | J50: =SUM(J48+J35) -> 50848878

Sheet Webster
D1: Webster Parish 2013 Statement of Net Assets
D2: Issued: December 31, 2013
H4: Primary Government
H5: Governmental Activities | I5: Component Units
A6: ASSETS
C7: Cash and cash equivalents | H7: 5380498 | I7: 688883
C8: Investments | H8: 2611059 | I8: 528783
C9: Receivables | H9: 5361318 | I9: 427061
C10: Prepaid items | H10: 287208 | I10: 80122
C11: Inventory | I11: 4614
C12: Capital assets not being depreciated | H12: 1212782
C13: Capital assets, net of accumulated depreciation | H13: 10318696 | I13: 1528182
C15: Total Assets | H15: =SUM(H7:H13) -> 25171561 | I15: =SUM(I7:I13) -> 3257645
A17: LIABILITIES
C18: Accounts payable vendors | H18: 132395 | I18: 210769
C19: Accrued payroll liabilities | H19: 190467 | I19: 14158
C20: Escrow payable | I20: 12304
C21: Interest payable | H21: 10777
C22: Unearned revenue | H22: 11805
C23: Due to other governments | H23: 163911
C24: Taxes paid under protest | H24: 45919
C25: Long-term liabilities:
D26: Due within one year | H26: 641574 | I26: 70118
D27: Due in more than one year | H27: 1134777 | I27: 5736
D29: Total Liabilities | H29: =SUM(H18:H27) -> 2331625 | I29: =SUM(I18:I27) -> 313085
A31: NET ASSETS
B32: Net investment in capital assets | H32: 10763259 | I32: 1528182
B33: Restricted for:
C34: Debt service | H34: 232039
C35: Solid waste collection, road and jail | H35: 586032
C36: Library | H36: 4108287
C37: Solid waste | H37: 908028
C38: Road | H38: 1953746
C39: Courthouse and health unit | H39: 1354909
C40: DA salaries and benefits | H40: 128
C41: Criminal court | H41: 42365
C42: Court reporter | H42: 9358
C43: Grants | I43: 59782
B44: Unrestricted | H44: 2881785 | I44: 1356596
C46: Total Net Assets | H46: =SUM(H32:H44) -> 22839936 | I46: =SUM(I31:I44) -> 2944560
C48: Total Liabilities and Net Assets | H48: =SUM(H46+H29) -> 25171561 | I48: =SUM(I46+I29) -> 3257645

Sheet West Baton Rouge
C1: West Baton Rouge Parish 2013 Statement of Net Assets
C2: Issued: December 31, 2013
G4: Primary Government
G5: Governmental Activities
A6: ASSETS
B7: Cash and cash equivalents | G7: 8020772
B8: Investments | G8: 15962223
B9: Investments - restricted | G9: 324000
B10: Taxes receivable | G10: 7542652
B11: Restricted cash | G11: 384902
B12: Due from other governments | G12: 1673400
B13: Other receivables | G13: 783
B14: Capital assets:
C15: Non-Depreciable | G15: 3020829
C16: Depreciable | G16: 58144234
B18: Total Assets | G18: =SUM(G7:G16) -> 95073795
A20: LIABILITIES
B21: Accounts payable | G21: 557345
B22: Noncurrent liabilities:
C23: Due in one year | G23: 582760
C24: Due in more than one year | G24: 7829726
C26: Total Liabilities | G26: =SUM(G21:G24) -> 8969831
A28: DEFERRED INFLOWS OF RESOURCES
B29: Grant advances | G29: 349264
B30: Unavailable revenue - property taxes | G30: 8579559
C31: Total deferred inflows of resources | G31: =SUM(G29:G30) -> 8928823
A33: NET ASSETS
B34: Net investment in capital assets | G34: 57048940
B35: Restricted for:
C36: Debt service | G36: 592082
C37: Poydras endowment | G37: 113570
B38: Unrestricted | G38: 19420549
B40: Total Net Assets | G40: =SUM(G34:G38) -> 77175141
B42: Total Liabilities and Net Assets | G42: =SUM(G26+G40+G31) -> 95073795

Sheet West Carroll
D1: West Carroll Parish 2013 Statement of Net Assets
D2: Issued: December 31, 2013
H4: Primary Government
H5: Governmental Activities
A6: ASSETS
C7: Cash and cash equivalents | H7: 5432216
C8: Receivables | H8: 1464515
C9: Deposits held in trust | H9: 696655
C10: Capital assets, net of accumulated depreciation | H10: 14017269
C12: Total Assets | H12: =SUM(H7:H10) -> 21610655
A14: LIABILITIES
C15: Cash overdraft | H15: 25846
C16: Accounts, salaries and other payables | H16: 157412
C17: Compensated absences | H17: 94228
C18: Certificates of indebtedness due within one year | H18: 14133
C19: Certificates of indebtedness due in more than one | H19: 98938
C20: Landfill closure/post closure care | H20: 1889469
D22: Total Liabilities | H22: =SUM(H15:H20) -> 2280026
A24: DEFERRED INFLOWS
C25: Protested taxes held pending settlement | H25: 184752
A27: NET ASSETS
B28: Net investment in capital assets | H28: 13904198
B29: Restricted for:
C30: Public works | H30: 4371977
C31: Health and welfare | H31: 556008
C32: Landfill closure/postclosure | H32: 696694
B33: Unrestricted | H33: -383000
C35: Total Net Assets | H35: =SUM(H28:H33) -> 19145877
C37: Total Liabilities and Net Assets | H37: =SUM(H35+H22+H25) -> 21610655

Sheet West Feliciana
D1: West Feliciana Parish 2013 Statement of Net Assets
D2: Issued: December 31, 2013
H4: Primary Government | K4: Component Unit
H5: Governmental Activities | I5: Business-Type Activities | J5: Total | K5: Business-type Activities
A6: ASSETS
C7: Cash and cash equivalents | H7: 1074501 | I7: 374956 | J7: =SUM(H7:I7) -> 1449457 | K7: 4300293
C8: Certificates of deposit | K8: 3457256
C9: Investments | H9: 9608297 | I9: 319727 | J9: =SUM(H9:I9) -> 9928024
C10: Taxes receivable | H10: 4589683 | I10: 166 | J10: =SUM(H10:I10) -> 4589849 | K10: 648734
C11: Due from other governments | H11: 69407 | I11: 419244 | J11: =SUM(H11:I11) -> 488651
C12: Accounts receivable (net) | H12: 19836 | I12: 82236 | J12: =SUM(H12:I12) -> 102072 | K12: 3587253
C13: Inventory | J13: =SUM(H13:I13) -> 0 | K13: 451569
C14: Prepaid expenses | H14: 79627 | I14: 17298 | J14: =SUM(H14:I14) -> 96925 | K14: 247700
C15: Restricted assets: | J15: =SUM(H15:I15) -> 0
D16: Cash and cash equivalents | H16: 38072 | I16: 236583 | J16: =SUM(H16:I16) -> 274655 | K16: 2576977
D17: Certificates of deposit | J17: =SUM(H17:I17) -> 0 | K17: 2305933
D18: Investments | H18: 2725899 | I18: 205276 | J18: =SUM(H18:I18) -> 2931175 | K18: 5657008
C19: Capital assets:
D20: Land and construction in progress | H20: 2583702 | J20: =SUM(H20:I20) -> 2583702
D21: Depreciable capital assets, net | H21: 14046921 | I21: 9978173 | J21: =SUM(H21:I21) -> 24025094 | K21: 6747983
C23: Total Assets | H23: =SUM(H7:H21) -> 34835945 | I23: =SUM(I7:I21) -> 11633659 | J23: =SUM(J7:J21) -> 46469604 | K23: =SUM(K7:K21) -> 29980706
A25: LIABILITIES
C26: Accounts payable | H26: 392446 | I26: 547575 | J26: =SUM(H26:I26) -> 940021 | K26: 420225
C27: Accrued expenses and other liabilities | H27: 132641 | I27: 19454 | J27: =SUM(H27:I27) -> 152095 | K27: 676807
C28: Cash overdraft | H28: 872793 | I28: 139415 | J28: =SUM(H28:I28) -> 1012208
C29: Customer deposits | I29: 155183 | J29: =SUM(H29:I29) -> 155183
C30: Internal balances | H30: 66749 | I30: -66749
C31: Long-term liablilities:
D32: Due within one year | H32: 224006 | I32: 104291 | J32: =SUM(H32:I32) -> 328297
D33: Due beyond one year | H33: 3703091 | I33: 2999206 | J33: =SUM(H33:I33) -> 6702297
D35: Total Liabilities | H35: =SUM(H26:H33) -> 5391726 | I35: =SUM(I26:I33) -> 3898375 | J35: =SUM(J26:J33) -> 9290101 | K35: =SUM(K26:K33) -> 1097032
A37: NET ASSETS
B38: Net investment in capital assets | H38: 13041623 | I38: 6925652 | J38: =SUM(H38:I38) -> 19967275 | K38: 6747983
B39: Restricted for:
C40: Debt service | H40: 482237 | I40: 205276 | J40: =SUM(H40:I40) -> 687513
C41: Capital improvements | H41: 5480909 | I41: 81400 | J41: =SUM(H41:I41) -> 5562309 | K41: 10539918
C42: Health unit | H42: 1238791 | J42: =SUM(H42:I42) -> 1238791
C43: Recreation | H43: 393451 | J43: =SUM(H43:I43) -> 393451
C44: Other | H44: 151557 | J44: =SUM(H44:I44) -> 151557
B45: Unrestricted (deficit) | H45: 8655651 | I45: 522956 | J45: =SUM(H45:I45) -> 9178607 | K45: 11595773
C47: Total Net Assets | H47: =SUM(H38:H45) -> 29444219 | I47: =SUM(I38:I45) -> 7735284 | J47: =SUM(J38:J45) -> 37179503 | K47: =SUM(K37:K45) -> 28883674
C49: Total Liabilities and Net Assets | H49: =SUM(H47+H35) -> 34835945 | I49: =SUM(I47+I35) -> 11633659 | J49: =SUM(J47+J35) -> 46469604 | K49: =SUM(K47+K35) -> 29980706

Sheet Winn
D1: Winn Parish 2013 Statement of Net Assets
D2: Issued: December 31, 2013
H5: 2013 | I5: 2012
A6: ASSETS
C7: Cash and cash equivalents | H7: 4118802 | I7: 5537124
C8: Receivebles | H8: 2234175 | I8: 2483756
C9: Capital assets (net of accumulated depreciation):
D10: Nondepreciable:
E11: Land | H11: 223675 | I11: 223675
E12: Construction in progress | H12: 1298815
D13: Depreciable:
E14: Buildings and improvements | H14: 698972 | I14: 724553
E15: Furniture, equipment, and other | H15: 639557 | I15: 807860
E16: Infrastructure - roads | H16: 737271 | I16: 757751
C18: Total Assets | H18: =SUM(H7:H16) -> 9951267 | I18: =SUM(I7:I16) -> 10534719
A20: LIABILITIES
C21: Accounts, salaries, and other payables | H21: 82711 | I21: 551603
C22: Deferred revenues | H22: 32101
C23: Interest payable | H23: 42979 | I23: 48779
C24: Long-term liabilities:
D25: Due within one year | H25: 220000 | I25: 205000
D26: Due in more than one year | H26: 2010000 | I26: 2230000
D28: Total Liabilities | H28: =SUM(H21:H26) -> 2387791 | I28: =SUM(I21:I26) -> 3035382
A30: NET ASSETS
B31: Net investment in capital assets | H31: 3598291 | I31: 2513838
B32: Unrestricted | H32: 3965187 | I32: 4985497
C34: Total Net Assets | H34: =SUM(H31:H32) -> 7563478 | I34: =SUM(I31:I32) -> 7499335
C36: Total Liabilities and Net Assets | H36: =SUM(H34+H28) -> 9951269 | I36: =SUM(I34+I28) -> 10534717

Sheet Cross Sectional
A1: 2013-SONA
C2: Assets: | N2: Liabilities: | S2: Non-Current/Long-Term Liabilities:
A3: Denotes Error Found in Statement | C3: Cash | D3: Investments | E3: Receivables | F3: Capital Assets | G3: Transfers | H3: Other Assets | I3: Total Assets (Sum) | J3: Accuracy | K3: Accuracy | L3: Deferred Outflows | M3: Accounts Payable | N3: Compensated Absences Payable | O3: Bonds Payable Due within 1 Year | P3: Bonds Payable Due after 1 Year | Q3: Government Transfers | R3: Payable within 1 Year | S3: Payable after 1 Year | T3: Other Liabilities | U3: Total Liabilities (Sum) | V3: Accuracy | W3: Accuracy | Y3: Deferred Inflows
A4: Parish's Statement Not Available | X4: PARISH
B5: County
B6: Acadia | C6: =CSG!C6+CSB!C6 -> 6387055 | D6: =CSG!D6+CSB!D6 -> 7359136 | E6: =CSG!E6+CSB!E6 -> 520283 | F6: =CSG!F6+CSB!F6 -> 54470286 | G6: =CSG!G6+CSB!G6 -> 6707822 | H6: =CSG!H6+CSB!H6 -> 0 | I6: =SUM(C6:H6) -> 75444582 | J6: =IF(I6=K6, "ok", "check") -> ok | K6: =Acadia!H19 -> 75444582 | L6: =Acadia!H22 -> 40499 | M6: =CSG!M6+CSB!M6 -> 1235703 | N6: =CSG!N6+CSB!N6 -> 371210 | O6: =CSG!O6+CSB!O6 -> 1531435 | P6: =CSG!P6+CSB!P6 -> 12775783 | Q6: =CSG!Q6+CSB!Q6 -> 0 | R6: =CSG!R6+CSB!R6 -> 0 | S6: =CSG!S6+CSB!S6 -> 0 | T6: =CSG!T6+CSB!T6 -> 6919970 | U6: =SUM(M6:T6) -> 22834101 | V6: =IF(U6=W6, "ok", "check") -> ok | W6: =Acadia!H40 -> 22834101 | Y6: =Acadia!H43 -> 29556
B7: Allen | C7: =CSG!C7+CSB!C7 -> 4518521 | D7: =CSG!D7+CSB!D7 -> 0 | E7: =CSG!E7+CSB!E7 -> 2958638 | F7: =CSG!F7+CSB!F7 -> 24665755 | G7: =CSG!G7+CSB!G7 -> 549380 | H7: =CSG!H7+CSB!H7 -> 29719 | I7: =SUM(C7:H7) -> 32722013 | J7: =IF(I7=K7, "ok", "check") -> ok | K7: =Allen!G13 -> 32722013 | M7: =CSG!M7+CSB!M7 -> 487946 | N7: =CSG!N7+CSB!N7 -> 37649 | O7: =CSG!O7+CSB!O7 -> 33000 | P7: =CSG!P7+CSB!P7 -> 155000 | Q7: =CSG!Q7+CSB!Q7 -> 0 | R7: =CSG!R7+CSB!R7 -> 0 | S7: =CSG!S7+CSB!S7 -> 989571 | T7: =CSG!T7+CSB!T7 -> 134467 | U7: =SUM(M7:T7) -> 1837633 | V7: =IF(U7=W7, "ok", "check") -> ok | W7: =Allen!G24 -> 1837633
B8: Ascension | C8: =CSG!C8+CSB!C8 -> 46091237 | D8: =CSG!D8+CSB!D8 -> 97818553 | E8: =CSG!E8+CSB!E8 -> 31963150 | F8: =CSG!F8+CSB!F8 -> 220457798 | G8: =CSG!G8+CSB!G8 -> 5125945 | H8: =CSG!H8+CSB!H8 -> 1164472 | I8: =SUM(C8:H8) -> 402621155 | J8: =IF(I8=K8, "ok", "check") -> ok | K8: =Ascension!K21 -> 402621155 | L8: =Ascension!I24 -> 294404 | M8: =CSG!M8+CSB!M8 -> 7744502 | N8: =CSG!N8+CSB!N8 -> 0 | O8: =CSG!O8+CSB!O8 -> 235409 | P8: =CSG!P8+CSB!P8 -> 667416 | Q8: =CSG!Q8+CSB!Q8 -> 838595 | R8: =CSG!R8+CSB!R8 -> 4335000 | S8: =CSG!S8+CSB!S8 -> 80612569 | T8: =CSG!T8+CSB!T8 -> 4561445 | U8: =SUM(M8:T8) -> 98994936 | V8: =IF(U8=W8, "ok", "check") -> ok | W8: =Ascension!K42 -> 98994936 | Y8: =Ascension!I45 -> 629856
B9: Assumption | C9: =CSG!C9+CSB!C9 -> 3793804 | D9: =CSG!D9+CSB!D9 -> 13855799 | E9: =CSG!E9+CSB!E9 -> 5121670 | F9: =CSG!F9+CSB!F9 -> 43733131 | G9: =CSG!G9+CSB!G9 -> 0 | H9: =CSG!H9+CSB!H9 -> 27165 | I9: =SUM(C9:H9) -> 66531569 | J9: =IF(I9=K9, "ok", "check") -> ok | K9: =Assumption!H13 -> 66531569 | M9: =CSG!M9+CSB!M9 -> 1477018 | N9: =CSG!N9+CSB!N9 -> 0 | O9: =CSG!O9+CSB!O9 -> 0 | P9: =CSG!P9+CSB!P9 -> 0 | Q9: =CSG!Q9+CSB!Q9 -> 0 | R9: =CSG!R9+CSB!R9 -> 0 | S9: =CSG!S9+CSB!S9 -> 0 | T9: =CSG!T9+CSB!T9 -> 456599 | U9: =SUM(M9:T9) -> 1933617 | V9: =IF(U9=W9, "ok", "check") -> ok | W9: =Assumption!H25 -> 1933617
B10: Avoyelles | C10: =CSG!C10+CSB!C10 -> 7808079 | D10: =CSG!D10+CSB!D10 -> 0 | E10: =CSG!E10+CSB!E10 -> 2186064 | F10: =CSG!F10+CSB!F10 -> 3564386 | G10: =CSG!G10+CSB!G10 -> 454661 | H10: =CSG!H10+CSB!H10 -> 1772656 | I10: =SUM(C10:H10) -> 15785846 | J10: =IF(I10=K10, "ok", "check") -> ok | K10: =Avoyelles!H20 -> 15785846 | M10: =CSG!M10+CSB!M10 -> 588143 | N10: =CSG!N10+CSB!N10 -> 98082 | O10: =CSG!O10+CSB!O10 -> 0 | P10: =CSG!P10+CSB!P10 -> 0 | Q10: =CSG!Q10+CSB!Q10 -> 37903 | R10: =CSG!R10+CSB!R10 -> 0 | S10: =CSG!S10+CSB!S10 -> 0 | T10: =CSG!T10+CSB!T10 -> 36260 | U10: =SUM(M10:T10) -> 760388 | V10: =IF(U10=W10, "ok", "check") -> ok | W10: =Avoyelles!H36 -> 760388
B11: Beauregard | C11: =CSG!C11+CSB!C11 -> 14858366 | D11: =CSG!D11+CSB!D11 -> 0 | E11: =CSG!E11+CSB!E11 -> 6484761 | F11: =CSG!F11+CSB!F11 -> 31507158 | G11: =CSG!G11+CSB!G11 -> 0 | H11: =CSG!H11+CSB!H11 -> 313803 | I11: =SUM(C11:H11) -> 53164088 | J11: =IF(I11=K11, "ok", "check") -> ok | K11: =Beauregard!G16 -> 53164088 | M11: =CSG!M11+CSB!M11 -> 874849 | N11: =CSG!N11+CSB!N11 -> 0 | O11: =CSG!O11+CSB!O11 -> 0 | P11: =CSG!P11+CSB!P11 -> 0 | Q11: =CSG!Q11+CSB!Q11 -> 0 | R11: =CSG!R11+CSB!R11 -> 1760644 | S11: =CSG!S11+CSB!S11 -> 2722875 | T11: =CSG!T11+CSB!T11 -> 0 | U11: =SUM(M11:T11) -> 5358368 | V11: =IF(U11=W11, "ok", "check") -> ok | W11: =Beauregard!G25 -> 5358368
B12: Bienville | C12: =CSG!C12+CSB!C12 -> 17224341 | D12: =CSG!D12+CSB!D12 -> 0 | E12: =CSG!E12+CSB!E12 -> 5448406 | F12: =CSG!F12+CSB!F12 -> 22814176 | G12: =CSG!G12+CSB!G12 -> 0 | H12: =CSG!H12+CSB!H12 -> 0 | I12: =SUM(C12:H12) -> 45486923 | J12: =IF(I12=K12, "ok", "check") -> ok | K12: =Bienville!G10 -> 45486923 | M12: =CSG!M12+CSB!M12 -> 413411 | N12: =CSG!N12+CSB!N12 -> 81369 | O12: =CSG!O12+CSB!O12 -> 10820000 | P12: =CSG!P12+CSB!P12 -> 0 | Q12: =CSG!Q12+CSB!Q12 -> 0 | R12: =CSG!R12+CSB!R12 -> 0 | S12: =CSG!S12+CSB!S12 -> 0 | T12: =CSG!T12+CSB!T12 -> 1596929 | U12: =SUM(M12:T12) -> 12911709 | V12: =IF(U12=W12, "ok", "check") -> ok | W12: =Bienville!G22 -> 12911709
B13: Bossier | C13: =CSG!C13+CSB!C13 -> 42994403 | D13: =CSG!D13+CSB!D13 -> 0 | E13: =CSG!E13+CSB!E13 -> 18083724 | F13: =CSG!F13+CSB!F13 -> 291765612 | G13: =CSG!G13+CSB!G13 -> 0 | H13: =CSG!H13+CSB!H13 -> 1003971 | I13: =SUM(C13:H13) -> 353847710 | J13: =IF(I13=K13, "ok", "check") -> ok | K13: =Bossier!J17 -> 353847710 | M13: =CSG!M13+CSB!M13 -> 3316221 | N13: =CSG!N13+CSB!N13 -> 0 | O13: =CSG!O13+CSB!O13 -> 0 | P13: =CSG!P13+CSB!P13 -> 0 | Q13: =CSG!Q13+CSB!Q13 -> 0 | R13: =CSG!R13+CSB!R13 -> 4678377 | S13: =CSG!S13+CSB!S13 -> 60913668 | T13: =CSG!T13+CSB!T13 -> 91817 | U13: =SUM(M13:T13) -> 69000083 | V13: =IF(U13=W13, "ok", "check") -> ok | W13: =Bossier!J33 -> 69000083
B14: Caddo | C14: =CSG!C14+CSB!C14 -> 16689898 | D14: =CSG!D14+CSB!D14 -> 117520729 | E14: =CSG!E14+CSB!E14 -> 57370497 | F14: =CSG!F14+CSB!F14 -> 210268925 | G14: =CSG!G14+CSB!G14 -> 2164467 | H14: =CSG!H14+CSB!H14 -> 194590 | I14: =SUM(C14:H14) -> 404209106 | J14: =IF(I14=K14, "ok", "check") -> ok | K14: =Caddo!H18 -> 404209106 | M14: =CSG!M14+CSB!M14 -> 5714023 | N14: =CSG!N14+CSB!N14 -> 0 | O14: =CSG!O14+CSB!O14 -> 0 | P14: =CSG!P14+CSB!P14 -> 0 | Q14: =CSG!Q14+CSB!Q14 -> 1414351 | R14: =CSG!R14+CSB!R14 -> 2989243 | S14: =CSG!S14+CSB!S14 -> 40233745 | T14: =CSG!T14+CSB!T14 -> 82995 | U14: =SUM(M14:T14) -> 50434357 | V14: =IF(U14=W14, "ok", "check") -> ok | W14: =Caddo!H38 -> 50434357
B15: Calcasieu | C15: =CSG!C15+CSB!C15 -> 61703595 | D15: =CSG!D15+CSB!D15 -> 194289481 | E15: =CSG!E15+CSB!E15 -> 60776704 | F15: =CSG!F15+CSB!F15 -> 519690704 | G15: =CSG!G15+CSB!G15 -> 222898 | H15: =CSG!H15+CSB!H15 -> 1347131 | I15: =SUM(C15:H15) -> 838030513 | J15: =IF(I15=K15, "ok", "check") -> ok | K15: =Calcasieu!J27 -> 838030513 | M15: =CSG!M15+CSB!M15 -> 12179257 | N15: =CSG!N15+CSB!N15 -> 0 | O15: =CSG!O15+CSB!O15 -> 0 | P15: =CSG!P15+CSB!P15 -> 0 | Q15: =CSG!Q15+CSB!Q15 -> 458224 | R15: =CSG!R15+CSB!R15 -> 2888680 | S15: =CSG!S15+CSB!S15 -> 6898289 | T15: =CSG!T15+CSB!T15 -> 1634115 | U15: =SUM(M15:T15) -> 24058565 | V15: =IF(U15=W15, "ok", "check") -> ok | W15: =Calcasieu!J44 -> 24058565 | Y15: =Calcasieu!H47 -> 47202105
B16: Caldwell | C16: =CSG!C16+CSB!C16 -> 6482087 | D16: =CSG!D16+CSB!D16 -> 0 | E16: =CSG!E16+CSB!E16 -> 1978585 | F16: =CSG!F16+CSB!F16 -> 11719166 | G16: =CSG!G16+CSB!G16 -> 0 | H16: =CSG!H16+CSB!H16 -> 0 | I16: =SUM(C16:H16) -> 20179838 | J16: =IF(I16=K16, "ok", "check") -> ok | K16: =Caldwell!G10 -> 20179838 | M16: =CSG!M16+CSB!M16 -> 152562 | N16: =CSG!N16+CSB!N16 -> 119478 | O16: =CSG!O16+CSB!O16 -> 0 | P16: =CSG!P16+CSB!P16 -> 0 | Q16: =CSG!Q16+CSB!Q16 -> 57698 | R16: =CSG!R16+CSB!R16 -> 0 | S16: =CSG!S16+CSB!S16 -> 0 | T16: =CSG!T16+CSB!T16 -> 0 | U16: =SUM(M16:T16) -> 329738 | V16: =IF(U16=W16, "ok", "check") -> ok | W16: =Caldwell!G17 -> 329738
B17: Cameron | C17: =CSG!C17+CSB!C17 -> 28095654 | D17: =CSG!D17+CSB!D17 -> 0 | E17: =CSG!E17+CSB!E17 -> 19930829 | F17: =CSG!F17+CSB!F17 -> 111753810 | G17: =CSG!G17+CSB!G17 -> 0 | H17: =CSG!H17+CSB!H17 -> 1924709 | I17: =SUM(C17:H17) -> 161705002 | J17: =IF(I17=K17, "ok", "check") -> ok | K17: =Cameron!G12 -> 161705002 | M17: =CSG!M17+CSB!M17 -> 4715387 | N17: =CSG!N17+CSB!N17 -> 0 | O17: =CSG!O17+CSB!O17 -> 0 | P17: =CSG!P17+CSB!P17 -> 0 | Q17: =CSG!Q17+CSB!Q17 -> 3695066 | R17: =CSG!R17+CSB!R17 -> 1892917 | S17: =CSG!S17+CSB!S17 -> 5190396 | T17: =CSG!T17+CSB!T17 -> 17231 | U17: =SUM(M17:T17) -> 15510997 | V17: =IF(U17=W17, "ok", "check") -> ok | W17: =Cameron!G23 -> 15510997
B18: Catahoula | C18: =CSG!C18+CSB!C18 -> 1935304 | D18: =CSG!D18+CSB!D18 -> 0 | E18: =CSG!E18+CSB!E18 -> 1411486 | F18: =CSG!F18+CSB!F18 -> 5862816 | G18: =CSG!G18+CSB!G18 -> 0 | H18: =CSG!H18+CSB!H18 -> 81766 | I18: =SUM(C18:H18) -> 9291372 | J18: =IF(I18=K18, "ok", "check") -> ok | K18: =Catahoula!H13 -> 9291372 | M18: =CSG!M18+CSB!M18 -> 551794 | N18: =CSG!N18+CSB!N18 -> 27615 | O18: =CSG!O18+CSB!O18 -> 0 | P18: =CSG!P18+CSB!P18 -> 0 | Q18: =CSG!Q18+CSB!Q18 -> 0 | R18: =CSG!R18+CSB!R18 -> 120000 | S18: =CSG!S18+CSB!S18 -> 51000 | T18: =CSG!T18+CSB!T18 -> 0 | U18: =SUM(M18:T18) -> 750409 | V18: =IF(U18=W18, "ok", "check") -> ok | W18: =Catahoula!H21 -> 750409 | Y18: =Catahoula!H24 -> 14777
B19: Claiborne | C19: =CSG!C19+CSB!C19 -> 7547110 | D19: =CSG!D19+CSB!D19 -> 28082 | E19: =CSG!E19+CSB!E19 -> 3215328 | F19: =CSG!F19+CSB!F19 -> 7059807 | G19: =CSG!G19+CSB!G19 -> 0 | H19: =CSG!H19+CSB!H19 -> 113163 | I19: =SUM(C19:H19) -> 17963490 | J19: =IF(I19=K19, "ok", "check") -> ok | K19: =Claiborne!G12 -> 17963490 | M19: =CSG!M19+CSB!M19 -> 643570 | N19: =CSG!N19+CSB!N19 -> 50773 | O19: =CSG!O19+CSB!O19 -> 0 | P19: =CSG!P19+CSB!P19 -> 0 | Q19: =CSG!Q19+CSB!Q19 -> 16368 | R19: =CSG!R19+CSB!R19 -> 155000 | S19: =CSG!S19+CSB!S19 -> 1700000 | T19: =CSG!T19+CSB!T19 -> 15626 | U19: =SUM(M19:T19) -> 2581337 | V19: =IF(U19=W19, "ok", "check") -> ok | W19: =Claiborne!G22 -> 2581337
B20: Concordia | C20: =CSG!C20+CSB!C20 -> 8049725 | D20: =CSG!D20+CSB!D20 -> 0 | E20: =CSG!E20+CSB!E20 -> 2125063 | F20: =CSG!F20+CSB!F20 -> 10920531 | G20: =CSG!G20+CSB!G20 -> 0 | H20: =CSG!H20+CSB!H20 -> 2658 | I20: =SUM(C20:H20) -> 21097977 | J20: =IF(I20=K20, "ok", "check") -> ok | K20: =Concordia!G12 -> 21097977 | M20: =CSG!M20+CSB!M20 -> 379801 | N20: =CSG!N20+CSB!N20 -> 0 | O20: =CSG!O20+CSB!O20 -> 0 | P20: =CSG!P20+CSB!P20 -> 0 | Q20: =CSG!Q20+CSB!Q20 -> 0 | R20: =CSG!R20+CSB!R20 -> 395818 | S20: =CSG!S20+CSB!S20 -> 9404258 | T20: =CSG!T20+CSB!T20 -> 0 | U20: =SUM(M20:T20) -> 10179877 | V20: =IF(U20=W20, "ok", "check") -> ok | W20: =Concordia!G22 -> 10179877
B21: DeSoto | C21: =CSG!C21+CSB!C21 -> 9791090 | D21: =CSG!D21+CSB!D21 -> 19901346 | E21: =CSG!E21+CSB!E21 -> 13587052 | F21: =CSG!F21+CSB!F21 -> 75381781 | G21: =CSG!G21+CSB!G21 -> 2650 | H21: =CSG!H21+CSB!H21 -> 40185 | I21: =SUM(C21:H21) -> 118704104 | J21: =IF(I21=K21, "ok", "check") -> ok | K21: =DeSoto!J14 -> 118704104 | M21: =CSG!M21+CSB!M21 -> 1176089 | N21: =CSG!N21+CSB!N21 -> 284258 | O21: =CSG!O21+CSB!O21 -> 0 | P21: =CSG!P21+CSB!P21 -> 0 | Q21: =CSG!Q21+CSB!Q21 -> 260166 | R21: =CSG!R21+CSB!R21 -> 5641 | S21: =CSG!S21+CSB!S21 -> 5280 | T21: =CSG!T21+CSB!T21 -> 4700993 | U21: =SUM(M21:T21) -> 6432427 | V21: =IF(U21=W21, "ok", "check") -> ok | W21: =DeSoto!J28 -> 6432427
B22: East Baton Rouge | C22: =CSG!C22+CSB!C22 -> 490729169 | D22: =CSG!D22+CSB!D22 -> 519680923 | E22: =CSG!E22+CSB!E22 -> 72105132 | F22: =CSG!F22+CSB!F22 -> 2520051191 | G22: =CSG!G22+CSB!G22 -> 88383484 | H22: =CSG!H22+CSB!H22 -> 2309711 | I22: =SUM(C22:H22) -> 3693259610 | J22: =IF(I22=K22, "ok", "check") -> ok | K22: ='East Baton Rouge'!J27 -> 3693259610 | L22: ='East Baton Rouge'!H30+'East Baton Rouge'!H31 -> 16908810 | M22: =CSG!M22+CSB!M22 -> 88143161 | N22: =CSG!N22+CSB!N22 -> 0 | O22: =CSG!O22+CSB!O22 -> 0 | P22: =CSG!P22+CSB!P22 -> 0 | Q22: =CSG!Q22+CSB!Q22 -> 7390530 | R22: =CSG!R22+CSB!R22 -> 52259362 | S22: =CSG!S22+CSB!S22 -> 1999523127 | T22: =CSG!T22+CSB!T22 -> 67012702 | U22: =SUM(M22:T22) -> 2214328882 | V22: =IF(U22=W22, "ok", "check") -> ok | W22: ='East Baton Rouge'!J46 -> 2214328882 | Y22: ='East Baton Rouge'!H49 -> 526276
B23: East Carroll | C23: =CSG!C23+CSB!C23 -> 2785851 | D23: =CSG!D23+CSB!D23 -> 836856 | E23: =CSG!E23+CSB!E23 -> 2244765 | F23: =CSG!F23+CSB!F23 -> 5554755 | G23: =CSG!G23+CSB!G23 -> 0 | H23: =CSG!H23+CSB!H23 -> 3090 | I23: =SUM(C23:H23) -> 11425317 | J23: =IF(I23=K23, "ok", "check") -> ok | K23: ='East Carroll'!J15 -> 11425317 | M23: =CSG!M23+CSB!M23 -> 230666 | N23: =CSG!N23+CSB!N23 -> 0 | O23: =CSG!O23+CSB!O23 -> 0 | P23: =CSG!P23+CSB!P23 -> 0 | Q23: =CSG!Q23+CSB!Q23 -> 0 | R23: =CSG!R23+CSB!R23 -> 121520 | S23: =CSG!S23+CSB!S23 -> 423316 | T23: =CSG!T23+CSB!T23 -> 151 | U23: =SUM(M23:T23) -> 775653 | V23: =IF(U23=W23, "ok", "check") -> ok | W23: ='East Carroll'!J25 -> 775653
B24: East Feliciana | C24: =CSG!C24+CSB!C24 -> 5513411.8 | D24: =CSG!D24+CSB!D24 -> 0 | E24: =CSG!E24+CSB!E24 -> 838202.1 | F24: =CSG!F24+CSB!F24 -> 8313076.6 | G24: =CSG!G24+CSB!G24 -> 1720693 | H24: =CSG!H24+CSB!H24 -> 0 | I24: =SUM(C24:H24) -> 16385383 | J24: =IF(I24=K24, "ok", "check") -> ok | K24: ='East Feliciana'!G12 -> 16385383 | M24: =CSG!M24+CSB!M24 -> 252490.44 | N24: =CSG!N24+CSB!N24 -> 13428 | O24: =CSG!O24+CSB!O24 -> 0 | P24: =CSG!P24+CSB!P24 -> 0 | Q24: =CSG!Q24+CSB!Q24 -> 1464751.4 | R24: =CSG!R24+CSB!R24 -> 0 | S24: =CSG!S24+CSB!S24 -> 0 | T24: =CSG!T24+CSB!T24 -> 0 | U24: =SUM(M24:T24) -> 1730669.8 | V24: =IF(U24=W24, "ok", "check") -> ok | W24: ='East Feliciana'!G21 -> 1730669.8
B25: Evangeline | C25: =CSG!C25+CSB!C25 -> 9893074 | D25: =CSG!D25+CSB!D25 -> 28970121 | E25: =CSG!E25+CSB!E25 -> 5548854 | F25: =CSG!F25+CSB!F25 -> 24954597 | G25: =CSG!G25+CSB!G25 -> 372502 | H25: =CSG!H25+CSB!H25 -> 20960 | I25: =SUM(C25:H25) -> 69760108 | J25: =IF(I25=K25, "ok", "check") -> ok | K25: =Evangeline!J16 -> 69760108 | M25: =CSG!M25+CSB!M25 -> 848974 | N25: =CSG!N25+CSB!N25 -> 61479 | O25: =CSG!O25+CSB!O25 -> 223819 | P25: =CSG!P25+CSB!P25 -> 31961741 | Q25: =CSG!Q25+CSB!Q25 -> 0 | R25: =CSG!R25+CSB!R25 -> 27459 | S25: =CSG!S25+CSB!S25 -> 23711 | T25: =CSG!T25+CSB!T25 -> 114917 | U25: =SUM(M25:T25) -> 33262100 | V25: =IF(U25=W25, "ok", "check") -> ok | W25: =Evangeline!J35 -> 33262100 | Y25: =Evangeline!H38 -> 271333
B26: Franklin | C26: =CSG!C26+CSB!C26 -> 7269664 | D26: =CSG!D26+CSB!D26 -> 0 | E26: =CSG!E26+CSB!E26 -> 3659846 | F26: =CSG!F26+CSB!F26 -> 17836416 | G26: =CSG!G26+CSB!G26 -> 0 | H26: =CSG!H26+CSB!H26 -> 4140 | I26: =SUM(C26:H26) -> 28770066 | J26: =IF(I26=K26, "ok", "check") -> ok | K26: =Franklin!G11 -> 28770066 | M26: =CSG!M26+CSB!M26 -> 499087 | N26: =CSG!N26+CSB!N26 -> 131420 | O26: =CSG!O26+CSB!O26 -> 0 | P26: =CSG!P26+CSB!P26 -> 0 | Q26: =CSG!Q26+CSB!Q26 -> 20000 | R26: =CSG!R26+CSB!R26 -> 0 | S26: =CSG!S26+CSB!S26 -> 0 | T26: =CSG!T26+CSB!T26 -> 1337359 | U26: =SUM(M26:T26) -> 1987866 | V26: =IF(U26=W26, "ok", "check") -> ok | W26: =Franklin!G21 -> 1987866
B27: Grant | C27: =CSG!C27+CSB!C27 -> 2045552 | D27: =CSG!D27+CSB!D27 -> 0 | E27: =CSG!E27+CSB!E27 -> 1591536 | F27: =CSG!F27+CSB!F27 -> 6440672 | G27: =CSG!G27+CSB!G27 -> 0 | H27: =CSG!H27+CSB!H27 -> 0 | I27: =SUM(C27:H27) -> 10077760 | J27: =IF(I27=K27, "ok", "check") -> ok | K27: =Grant!J15 -> 10077760 | M27: =CSG!M27+CSB!M27 -> 412173 | N27: =CSG!N27+CSB!N27 -> 51246 | O27: =CSG!O27+CSB!O27 -> 0 | P27: =CSG!P27+CSB!P27 -> 0 | Q27: =CSG!Q27+CSB!Q27 -> 0 | R27: =CSG!R27+CSB!R27 -> 92877 | S27: =CSG!S27+CSB!S27 -> 339716 | T27: =CSG!T27+CSB!T27 -> 78699 | U27: =SUM(M27:T27) -> 974711 | V27: =IF(U27=W27, "ok", "check") -> ok | W27: =Grant!J27 -> 974711
B28: Iberia | C28: =CSG!C28+CSB!C28 -> 39934830 | D28: =CSG!D28+CSB!D28 -> 83378 | E28: =CSG!E28+CSB!E28 -> 8030264 | F28: =CSG!F28+CSB!F28 -> 95937263 | G28: =CSG!G28+CSB!G28 -> 5793561 | H28: =CSG!H28+CSB!H28 -> 1416411 | I28: =SUM(C28:H28) -> 151195707 | J28: =IF(I28=K28, "ok", "check") -> ok | K28: =Iberia!H21 -> 151195707 | M28: =CSG!M28+CSB!M28 -> 2630383 | N28: =CSG!N28+CSB!N28 -> 0 | O28: =CSG!O28+CSB!O28 -> 0 | P28: =CSG!P28+CSB!P28 -> 0 | Q28: =CSG!Q28+CSB!Q28 -> 964621 | R28: =CSG!R28+CSB!R28 -> 1464872 | S28: =CSG!S28+CSB!S28 -> 9078674 | T28: =CSG!T28+CSB!T28 -> 3625048 | U28: =SUM(M28:T28) -> 17763598 | V28: =IF(U28=W28, "ok", "check") -> ok | W28: =Iberia!H38 -> 17763598
B29: Iberville | C29: =CSG!C29+CSB!C29 -> 19088098 | D29: =CSG!D29+CSB!D29 -> 0 | E29: =CSG!E29+CSB!E29 -> 10070374 | F29: =CSG!F29+CSB!F29 -> 110762579 | G29: =CSG!G29+CSB!G29 -> 0 | H29: =CSG!H29+CSB!H29 -> 1451624 | I29: =SUM(C29:H29) -> 141372675 | J29: =IF(I29=K29, "ok", "check") -> ok | K29: =Iberville!J22 -> 141372675 | M29: =CSG!M29+CSB!M29 -> 3638820 | N29: =CSG!N29+CSB!N29 -> 0 | O29: =CSG!O29+CSB!O29 -> 0 | P29: =CSG!P29+CSB!P29 -> 0 | Q29: =CSG!Q29+CSB!Q29 -> 0 | R29: =CSG!R29+CSB!R29 -> 1146504 | S29: =CSG!S29+CSB!S29 -> 17803488 | T29: =CSG!T29+CSB!T29 -> 485401 | U29: =SUM(M29:T29) -> 23074213 | V29: =IF(U29=W29, "ok", "check") -> ok | W29: =Iberville!J36 -> 23074213
B30: Jackson | C30: =CSG!C30+CSB!C30 -> 9622291 | D30: =CSG!D30+CSB!D30 -> 0 | E30: =CSG!E30+CSB!E30 -> 4755981 | F30: =CSG!F30+CSB!F30 -> 16399628 | G30: =CSG!G30+CSB!G30 -> 0 | H30: =CSG!H30+CSB!H30 -> 70256 | I30: =SUM(C30:H30) -> 30848156 | J30: =IF(I30=K30, "ok", "check") -> ok | K30: =Jackson!G13 -> 30848156 | M30: =CSG!M30+CSB!M30 -> 342065 | N30: =CSG!N30+CSB!N30 -> 0 | O30: =CSG!O30+CSB!O30 -> 0 | P30: =CSG!P30+CSB!P30 -> 0 | Q30: =CSG!Q30+CSB!Q30 -> 0 | R30: =CSG!R30+CSB!R30 -> 139468 | S30: =CSG!S30+CSB!S30 -> 443412 | T30: =CSG!T30+CSB!T30 -> 31249 | U30: =SUM(M30:T30) -> 956194 | V30: =IF(U30=W30, "ok", "check") -> ok | W30: =Jackson!G22 -> 956194
B31: Jefferson | C31: =CSG!C31+CSB!C31 -> 23553000 | D31: =CSG!D31+CSB!D31 -> 91269000 | E31: =CSG!E31+CSB!E31 -> 267715000 | F31: =CSG!F31+CSB!F31 -> 1720659000 | G31: =CSG!G31+CSB!G31 -> 0 | H31: =CSG!H31+CSB!H31 -> 555032000 | I31: =SUM(C31:H31) -> 2658228000 | J31: =IF(I31=K31, "ok", "check") -> ok | K31: =Jefferson!J40 -> 2658228000 | L31: =Jefferson!H43 -> 7537000 | M31: =CSG!M31+CSB!M31 -> 63619000 | N31: =CSG!N31+CSB!N31 -> 0 | O31: =CSG!O31+CSB!O31 -> 0 | P31: =CSG!P31+CSB!P31 -> 0 | Q31: =CSG!Q31+CSB!Q31 -> 81000 | R31: =CSG!R31+CSB!R31 -> 31168000 | S31: =CSG!S31+CSB!S31 -> 467783000 | T31: =CSG!T31+CSB!T31 -> 200496000 | U31: =SUM(M31:T31) -> 763147000 | V31: =IF(U31=W31, "ok", "check") -> ok | W31: =Jefferson!J73 -> 763147000
B32: Jefferson Davis | C32: =CSG!C32+CSB!C32 -> 20401182 | D32: =CSG!D32+CSB!D32 -> 2101032 | E32: =CSG!E32+CSB!E32 -> 799744 | F32: =CSG!F32+CSB!F32 -> 33564914 | G32: =CSG!G32+CSB!G32 -> 0 | H32: =CSG!H32+CSB!H32 -> 68433 | I32: =SUM(C32:H32) -> 56935305 | J32: =IF(I32=K32, "ok", "check") -> ok | K32: ='Jefferson Davis'!G13 -> 56935305 | L32: ='Jefferson Davis'!G16 -> 84323 | M32: =CSG!M32+CSB!M32 -> 1918608 | N32: =CSG!N32+CSB!N32 -> 0 | O32: =CSG!O32+CSB!O32 -> 1000000 | P32: =CSG!P32+CSB!P32 -> 15670000 | Q32: =CSG!Q32+CSB!Q32 -> 368500 | R32: =CSG!R32+CSB!R32 -> 0 | S32: =CSG!S32+CSB!S32 -> 0 | T32: =CSG!T32+CSB!T32 -> 1732694 | U32: =SUM(M32:T32) -> 20689802 | V32: =IF(U32=W32, "ok", "check") -> ok | W32: ='Jefferson Davis'!G30 -> 20689802 | Y32: ='Jefferson Davis'!G33 -> 46979
B33: Lafayette | C33: =CSG!C33+CSB!C33 -> 18672006 | D33: =CSG!D33+CSB!D33 -> 504218548 | E33: =CSG!E33+CSB!E33 -> 32765828 | F33: =CSG!F33+CSB!F33 -> 1316304239 | G33: =CSG!G33+CSB!G33 -> 22135730 | H33: =CSG!H33+CSB!H33 -> 44280437 | I33: =SUM(C33:H33) -> 1938376788 | J33: =IF(I33=K33, "ok", "check") -> ok | K33: =Lafayette!J33 -> 1938376788 | M33: =CSG!M33+CSB!M33 -> 24837002 | N33: =CSG!N33+CSB!N33 -> 0 | O33: =CSG!O33+CSB!O33 -> 0 | P33: =CSG!P33+CSB!P33 -> 0 | Q33: =CSG!Q33+CSB!Q33 -> 788161 | R33: =CSG!R33+CSB!R33 -> 39463487 | S33: =CSG!S33+CSB!S33 -> 904296819 | T33: =CSG!T33+CSB!T33 -> 16639149 | U33: =SUM(M33:T33) -> 986024618 | V33: =IF(U33=W33, "ok", "check") -> ok | W33: =Lafayette!J52 -> 986024618
B34: Lafourche | C34: =CSG!C34+CSB!C34 -> 28390862 | D34: =CSG!D34+CSB!D34 -> 19417222 | E34: =CSG!E34+CSB!E34 -> 2531283 | F34: =CSG!F34+CSB!F34 -> 86115261 | G34: =CSG!G34+CSB!G34 -> 32644660 | H34: =CSG!H34+CSB!H34 -> 1525426 | I34: =SUM(C34:H34) -> 170624714 | J34: =IF(I34=K34, "ok", "check") -> ok | K34: =Lafourche!J16 -> 170624714 | L34: =Lafourche!H19 -> 1077879 | M34: =CSG!M34+CSB!M34 -> 7917587 | N34: =CSG!N34+CSB!N34 -> 0 | O34: =CSG!O34+CSB!O34 -> 0 | P34: =CSG!P34+CSB!P34 -> 0 | Q34: =CSG!Q34+CSB!Q34 -> 583418 | R34: =CSG!R34+CSB!R34 -> 8630887 | S34: =CSG!S34+CSB!S34 -> 46541145 | T34: =CSG!T34+CSB!T34 -> 517734 | U34: =SUM(M34:T34) -> 64190771 | V34: =IF(U34=W34, "ok", "check") -> ok | W34: =Lafourche!J32 -> 64190771
B35: LaSalle | C35: =CSG!C35+CSB!C35 -> 2504699 | D35: =CSG!D35+CSB!D35 -> 0 | E35: =CSG!E35+CSB!E35 -> 3366905 | F35: =CSG!F35+CSB!F35 -> 5846162 | G35: =CSG!G35+CSB!G35 -> 0 | H35: =CSG!H35+CSB!H35 -> 7476 | I35: =SUM(C35:H35) -> 11725242 | J35: =IF(I35=K35, "ok", "check") -> ok | K35: =LaSalle!G11 -> 11725242 | M35: =CSG!M35+CSB!M35 -> 312887 | N35: =CSG!N35+CSB!N35 -> 0 | O35: =CSG!O35+CSB!O35 -> 0 | P35: =CSG!P35+CSB!P35 -> 0 | Q35: =CSG!Q35+CSB!Q35 -> 0 | R35: =CSG!R35+CSB!R35 -> 221535 | S35: =CSG!S35+CSB!S35 -> 125749 | T35: =CSG!T35+CSB!T35 -> 285546 | U35: =SUM(M35:T35) -> 945717 | V35: =IF(U35=W35, "ok", "check") -> ok | W35: =LaSalle!G22 -> 945717
B36: Lincoln | C36: =CSG!C36+CSB!C36 -> 9270701 | D36: =CSG!D36+CSB!D36 -> 22426630 | E36: =CSG!E36+CSB!E36 -> 7709169 | F36: =CSG!F36+CSB!F36 -> 23870185 | G36: =CSG!G36+CSB!G36 -> 236078 | H36: =CSG!H36+CSB!H36 -> 11582 | I36: =SUM(C36:H36) -> 63524345 | J36: =IF(I36=K36, "ok", "check") -> ok | K36: =Lincoln!G15 -> 63524345 | L36: =Lincoln!G18 -> 3008 | M36: =CSG!M36+CSB!M36 -> 1372481 | N36: =CSG!N36+CSB!N36 -> 114162 | O36: =CSG!O36+CSB!O36 -> 466000 | P36: =CSG!P36+CSB!P36 -> 3476000 | Q36: =CSG!Q36+CSB!Q36 -> 1330002 | R36: =CSG!R36+CSB!R36 -> 0 | S36: =CSG!S36+CSB!S36 -> 0 | T36: =CSG!T36+CSB!T36 -> 1605571 | U36: =SUM(M36:T36) -> 8364216 | V36: =IF(U36=W36, "ok", "check") -> ok | W36: =Lincoln!G32 -> 8364216
B37: Livingston | C37: =CSG!C37+CSB!C37 -> 12785835 | D37: =CSG!D37+CSB!D37 -> 12037340 | E37: =CSG!E37+CSB!E37 -> 1769015 | F37: =CSG!F37+CSB!F37 -> 151970008 | G37: =CSG!G37+CSB!G37 -> 12323220 | H37: =CSG!H37+CSB!H37 -> 1107831 | I37: =SUM(C37:H37) -> 191993249 | J37: =IF(I37=K37, "ok", "check") -> ok | K37: =Livingston!J24 -> 191993249 | L37: =Livingston!H27 -> 377331 | M37: =CSG!M37+CSB!M37 -> 6975175 | N37: =CSG!N37+CSB!N37 -> 0 | O37: =CSG!O37+CSB!O37 -> 0 | P37: =CSG!P37+CSB!P37 -> 0 | Q37: =CSG!Q37+CSB!Q37 -> 574768 | R37: =CSG!R37+CSB!R37 -> 6301700 | S37: =CSG!S37+CSB!S37 -> 83342943 | T37: =CSG!T37+CSB!T37 -> 1112266 | U37: =SUM(M37:T37) -> 98306852 | V37: =IF(U37=W37, "ok", "check") -> ok | W37: =Livingston!J41 -> 98306852
B38: Madison | C38: =CSG!C38+CSB!C38 -> 4448930 | D38: =CSG!D38+CSB!D38 -> 2949665 | E38: =CSG!E38+CSB!E38 -> 5726410 | F38: =CSG!F38+CSB!F38 -> 8177367 | G38: =CSG!G38+CSB!G38 -> 0 | H38: =CSG!H38+CSB!H38 -> 0 | I38: =SUM(C38:H38) -> 21302372 | J38: =IF(I38=K38, "ok", "check") -> ok | K38: =Madison!G11 -> 21302372 | M38: =CSG!M38+CSB!M38 -> 272870 | N38: =CSG!N38+CSB!N38 -> 0 | O38: =CSG!O38+CSB!O38 -> 0 | P38: =CSG!P38+CSB!P38 -> 0 | Q38: =CSG!Q38+CSB!Q38 -> 0 | R38: =CSG!R38+CSB!R38 -> 39058 | S38: =CSG!S38+CSB!S38 -> 514428 | T38: =CSG!T38+CSB!T38 -> 0 | U38: =SUM(M38:T38) -> 826356 | V38: =IF(U38=W38, "ok", "check") -> ok | W38: =Madison!G19 -> 826356
B39: Morehouse | C39: =CSG!C39+CSB!C39 -> 3855174 | D39: =CSG!D39+CSB!D39 -> 525000 | E39: =CSG!E39+CSB!E39 -> 2339602 | F39: =CSG!F39+CSB!F39 -> 13644421 | G39: =CSG!G39+CSB!G39 -> 0 | H39: =CSG!H39+CSB!H39 -> 0 | I39: =SUM(C39:H39) -> 20364197 | J39: =IF(I39=K39, "ok", "check") -> ok | K39: =Morehouse!G13 -> 20364197 | M39: =CSG!M39+CSB!M39 -> 280988 | N39: =CSG!N39+CSB!N39 -> 0 | O39: =CSG!O39+CSB!O39 -> 0 | P39: =CSG!P39+CSB!P39 -> 0 | Q39: =CSG!Q39+CSB!Q39 -> 0 | R39: =CSG!R39+CSB!R39 -> 34542 | S39: =CSG!S39+CSB!S39 -> 0 | T39: =CSG!T39+CSB!T39 -> 2067087 | U39: =SUM(M39:T39) -> 2382617 | V39: =IF(U39=W39, "ok", "check") -> ok | W39: =Morehouse!G22 -> 2382617 | Y39: =Morehouse!G25 -> 2110568
B40: Natchitoches | C40: =CSG!C40+CSB!C40 -> 6692314 | D40: =CSG!D40+CSB!D40 -> 0 | E40: =CSG!E40+CSB!E40 -> 6580976 | F40: =CSG!F40+CSB!F40 -> 10706052 | G40: =CSG!G40+CSB!G40 -> 0 | H40: =CSG!H40+CSB!H40 -> 0 | I40: =SUM(C40:H40) -> 23979342 | J40: =IF(I40=K40, "ok", "check") -> ok | K40: =Natchitoches!H17 -> 23979342 | M40: =CSG!M40+CSB!M40 -> 1026255 | N40: =CSG!N40+CSB!N40 -> 142189 | O40: =CSG!O40+CSB!O40 -> 0 | P40: =CSG!P40+CSB!P40 -> 0 | Q40: =CSG!Q40+CSB!Q40 -> 894223 | R40: =CSG!R40+CSB!R40 -> 0 | S40: =CSG!S40+CSB!S40 -> 0 | T40: =CSG!T40+CSB!T40 -> 27017 | U40: =SUM(M40:T40) -> 2089684 | V40: =IF(U40=W40, "ok", "check") -> ok | W40: =Natchitoches!H33 -> 2089684
B41: Orleans | C41: =CSG!C41+CSB!C41 -> 62125000 | D41: =CSG!D41+CSB!D41 -> 165644000 | E41: =CSG!E41+CSB!E41 -> 43801000 | F41: =CSG!F41+CSB!F41 -> 1550110000 | G41: =CSG!G41+CSB!G41 -> 72840000 | H41: =CSG!H41+CSB!H41 -> 24000 | I41: =SUM(C41:H41) -> 1894544000 | J41: =IF(I41=K41, "ok", "check") -> ok | K41: =Orleans!H21 -> 1894544000 | L41: =Orleans!H24 -> 7241 | M41: =CSG!M41+CSB!M41 -> 100321000 | N41: =CSG!N41+CSB!N41 -> 0 | O41: =CSG!O41+CSB!O41 -> 0 | P41: =CSG!P41+CSB!P41 -> 0 | Q41: =CSG!Q41+CSB!Q41 -> 10276000 | R41: =CSG!R41+CSB!R41 -> 163403000 | S41: =CSG!S41+CSB!S41 -> 1431852000 | T41: =CSG!T41+CSB!T41 -> 3745000 | U41: =SUM(M41:T41) -> 1709597000 | V41: =IF(U41=W41, "ok", "check") -> ok | W41: =Orleans!H41 -> 1709597000 | Y41: =Orleans!H44 -> 7386
B42: Ouachita | C42: =CSG!C42+CSB!C42 -> 42612122 | D42: =CSG!D42+CSB!D42 -> 12027474 | E42: =CSG!E42+CSB!E42 -> 35731619 | F42: =CSG!F42+CSB!F42 -> 183933719 | G42: =CSG!G42+CSB!G42 -> 4120907 | H42: =CSG!H42+CSB!H42 -> 926069 | I42: =SUM(C42:H42) -> 279351910 | J42: =IF(I42=K42, "ok", "check") -> ok | K42: =Ouachita!H21 -> 279351910 | M42: =CSG!M42+CSB!M42 -> 5324866 | N42: =CSG!N42+CSB!N42 -> 0 | O42: =CSG!O42+CSB!O42 -> 0 | P42: =CSG!P42+CSB!P42 -> 0 | Q42: =CSG!Q42+CSB!Q42 -> 0 | R42: =CSG!R42+CSB!R42 -> 1980292 | S42: =CSG!S42+CSB!S42 -> 6317082 | T42: =CSG!T42+CSB!T42 -> 1500082 | U42: =SUM(M42:T42) -> 15122322 | V42: =IF(U42=W42, "ok", "check") -> ok | W42: =Ouachita!H32 -> 15122322
B43: Plaquemines | C43: =CSG!C43+CSB!C43 -> 133009823 | D43: =CSG!D43+CSB!D43 -> 4998456 | E43: =CSG!E43+CSB!E43 -> 96048577 | F43: =CSG!F43+CSB!F43 -> 528654940 | G43: =CSG!G43+CSB!G43 -> 0 | H43: =CSG!H43+CSB!H43 -> 907808 | I43: =SUM(C43:H43) -> 763619604 | J43: =IF(I43=K43, "ok", "check") -> ok | K43: =Plaquemines!J22 -> 763619604 | M43: =CSG!M43+CSB!M43 -> 43095406 | N43: =CSG!N43+CSB!N43 -> 1164101 | O43: =CSG!O43+CSB!O43 -> 3965000 | P43: =CSG!P43+CSB!P43 -> 130095000 | Q43: =CSG!Q43+CSB!Q43 -> 459968 | R43: =CSG!R43+CSB!R43 -> 0 | S43: =CSG!S43+CSB!S43 -> 0 | T43: =CSG!T43+CSB!T43 -> 16628199 | U43: =SUM(M43:T43) -> 195407674 | V43: =IF(U43=W43, "ok", "check") -> ok | W43: =Plaquemines!J47 -> 195407674
B44: Point Coupee | C44: =CSG!C44+CSB!C44 -> 2570676 | D44: =CSG!D44+CSB!D44 -> 702328 | E44: =CSG!E44+CSB!E44 -> 4256014 | F44: =CSG!F44+CSB!F44 -> 19317523 | G44: =CSG!G44+CSB!G44 -> 864331 | H44: =CSG!H44+CSB!H44 -> 68118 | I44: =SUM(C44:H44) -> 27778990 | J44: =IF(I44=K44, "ok", "check") -> ok | K44: ='Pointe Coupee'!H19 -> 27778990 | M44: =CSG!M44+CSB!M44 -> 2145783 | N44: =CSG!N44+CSB!N44 -> 0 | O44: =CSG!O44+CSB!O44 -> 0 | P44: =CSG!P44+CSB!P44 -> 0 | Q44: =CSG!Q44+CSB!Q44 -> 421610 | R44: =CSG!R44+CSB!R44 -> 534213 | S44: =CSG!S44+CSB!S44 -> 8388050 | T44: =CSG!T44+CSB!T44 -> 765232 | U44: =SUM(M44:T44) -> 12254888 | V44: =IF(U44=W44, "ok", "check") -> ok | W44: ='Pointe Coupee'!H29 -> 12254888 | Y44: ='Pointe Coupee'!F32 -> 2473
B45: Rapides | C45: =CSG!C45+CSB!C45 -> 50024032 | D45: =CSG!D45+CSB!D45 -> 0 | E45: =CSG!E45+CSB!E45 -> 22585071 | F45: =CSG!F45+CSB!F45 -> 51104167 | G45: =CSG!G45+CSB!G45 -> 0 | H45: =CSG!H45+CSB!H45 -> 492 | I45: =SUM(C45:H45) -> 123713762 | J45: =IF(I45=K45, "ok", "check") -> ok | K45: =Rapides!H19 -> 123713762 | M45: =CSG!M45+CSB!M45 -> 2374122 | N45: =CSG!N45+CSB!N45 -> 0 | O45: =CSG!O45+CSB!O45 -> 0 | P45: =CSG!P45+CSB!P45 -> 0 | Q45: =CSG!Q45+CSB!Q45 -> 0 | R45: =CSG!R45+CSB!R45 -> 1649430 | S45: =CSG!S45+CSB!S45 -> 48762251 | T45: =CSG!T45+CSB!T45 -> 1693311 | U45: =SUM(M45:T45) -> 54479114 | V45: =IF(U45=W45, "ok", "check") -> ok | W45: =Rapides!H29 -> 54479114
B46: Red River | C46: =CSG!C46+CSB!C46 -> 14966756 | D46: =CSG!D46+CSB!D46 -> 15927098 | E46: =CSG!E46+CSB!E46 -> 4234914 | F46: =CSG!F46+CSB!F46 -> 14591052 | G46: =CSG!G46+CSB!G46 -> 0 | H46: =CSG!H46+CSB!H46 -> 20301 | I46: =SUM(C46:H46) -> 49740121 | J46: =IF(I46=K46, "ok", "check") -> ok | K46: ='Red River'!J19 -> 49740121 | M46: =CSG!M46+CSB!M46 -> 503940 | N46: =CSG!N46+CSB!N46 -> 76773 | O46: =CSG!O46+CSB!O46 -> 0 | P46: =CSG!P46+CSB!P46 -> 0 | Q46: =CSG!Q46+CSB!Q46 -> 0 | R46: =CSG!R46+CSB!R46 -> 0 | S46: =CSG!S46+CSB!S46 -> 0 | T46: =CSG!T46+CSB!T46 -> 970000 | U46: =SUM(M46:T46) -> 1550713 | V46: =IF(U46=W46, "ok", "check") -> ok | W46: ='Red River'!J37 -> 1550713
B47: Richland | C47: =CSG!C47+CSB!C47 -> 7877011 | D47: =CSG!D47+CSB!D47 -> 0 | E47: =CSG!E47+CSB!E47 -> 2803917 | F47: =CSG!F47+CSB!F47 -> 2438020 | G47: =CSG!G47+CSB!G47 -> 0 | H47: =CSG!H47+CSB!H47 -> 0 | I47: =SUM(C47:H47) -> 13118948 | J47: =IF(I47=K47, "ok", "check") -> ok | K47: =Richland!G12 -> 13118948 | M47: =CSG!M47+CSB!M47 -> 314807 | N47: =CSG!N47+CSB!N47 -> 0 | O47: =CSG!O47+CSB!O47 -> 0 | P47: =CSG!P47+CSB!P47 -> 0 | Q47: =CSG!Q47+CSB!Q47 -> 0 | R47: =CSG!R47+CSB!R47 -> 0 | S47: =CSG!S47+CSB!S47 -> 0 | T47: =CSG!T47+CSB!T47 -> 0 | U47: =SUM(M47:T47) -> 314807 | V47: =IF(U47=W47, "ok", "check") -> ok | W47: =Richland!G18 -> 314807 | Y47: =Richland!G21 -> 2680349
B48: Sabine | C48: =CSG!C48+CSB!C48 -> 8931765 | D48: =CSG!D48+CSB!D48 -> 0 | E48: =CSG!E48+CSB!E48 -> 3916001 | F48: =CSG!F48+CSB!F48 -> 12595423 | G48: =CSG!G48+CSB!G48 -> 0 | H48: =CSG!H48+CSB!H48 -> 0 | I48: =SUM(C48:H48) -> 25443189 | J48: =IF(I48=K48, "ok", "check") -> ok | K48: =Sabine!H20 -> 25443189 | M48: =CSG!M48+CSB!M48 -> 765104 | N48: =CSG!N48+CSB!N48 -> 0 | O48: =CSG!O48+CSB!O48 -> 0 | P48: =CSG!P48+CSB!P48 -> 0 | Q48: =CSG!Q48+CSB!Q48 -> 0 | R48: =CSG!R48+CSB!R48 -> 372094 | S48: =CSG!S48+CSB!S48 -> 910569 | T48: =CSG!T48+CSB!T48 -> 0 | U48: =SUM(M48:T48) -> 2047767 | V48: =IF(U48=W48, "ok", "check") -> ok | W48: =Sabine!H29 -> 2047767
B49: St Bernard | C49: =CSG!C49+CSB!C49 -> 51104514 | D49: =CSG!D49+CSB!D49 -> 6190827 | E49: =CSG!E49+CSB!E49 -> 35093054 | F49: =CSG!F49+CSB!F49 -> 591106646 | G49: =CSG!G49+CSB!G49 -> 0 | H49: =CSG!H49+CSB!H49 -> 1748394 | I49: =SUM(C49:H49) -> 685243435 | J49: =IF(I49=K49, "ok", "check") -> ok | K49: ='St. Bernard'!H26 -> 685243435 | M49: =CSG!M49+CSB!M49 -> 33310633 | N49: =CSG!N49+CSB!N49 -> 0 | O49: =CSG!O49+CSB!O49 -> 0 | P49: =CSG!P49+CSB!P49 -> 0 | Q49: =CSG!Q49+CSB!Q49 -> 0 | R49: =CSG!R49+CSB!R49 -> 4978475 | S49: =CSG!S49+CSB!S49 -> 41843099 | T49: =CSG!T49+CSB!T49 -> 9694023 | U49: =SUM(M49:T49) -> 89826230 | V49: =IF(U49=W49, "ok", "check") -> ok | W49: ='St. Bernard'!H41 -> 89826230
B50: St Charles | C50: =CSG!C50+CSB!C50 -> 3673098 | D50: =CSG!D50+CSB!D50 -> 95051335 | E50: =CSG!E50+CSB!E50 -> 32800038 | F50: =CSG!F50+CSB!F50 -> 329064234 | G50: =CSG!G50+CSB!G50 -> 3329585 | H50: =CSG!H50+CSB!H50 -> 1071236 | I50: =SUM(C50:H50) -> 464989526 | J50: =IF(I50=K50, "ok", "check") -> ok | K50: ='St. Charles'!J25 -> 464989526 | M50: =CSG!M50+CSB!M50 -> 7803017 | N50: =CSG!N50+CSB!N50 -> 0 | O50: =CSG!O50+CSB!O50 -> 0 | P50: =CSG!P50+CSB!P50 -> 0 | Q50: =CSG!Q50+CSB!Q50 -> 455541 | R50: =CSG!R50+CSB!R50 -> 4188000 | S50: =CSG!S50+CSB!S50 -> 59477899 | T50: =CSG!T50+CSB!T50 -> 2915006 | U50: =SUM(M50:T50) -> 74839463 | V50: =IF(U50=W50, "ok", "check") -> ok | W50: ='St. Charles'!J43 -> 74839463 | Y50: ='St. Charles'!H46 -> 25111217
B51: St Helena | C51: =CSG!C51+CSB!C51 -> 6451059 | D51: =CSG!D51+CSB!D51 -> 980608 | E51: =CSG!E51+CSB!E51 -> 2218238 | F51: =CSG!F51+CSB!F51 -> 12539206 | G51: =CSG!G51+CSB!G51 -> 0 | H51: =CSG!H51+CSB!H51 -> 110731 | I51: =SUM(C51:H51) -> 22299842 | J51: =IF(I51=K51, "ok", "check") -> ok | K51: ='St. Helena'!H29 -> 22299842 | M51: =CSG!M51+CSB!M51 -> 698270 | N51: =CSG!N51+CSB!N51 -> 186139 | O51: =CSG!O51+CSB!O51 -> 287718 | P51: =CSG!P51+CSB!P51 -> 793199 | Q51: =CSG!Q51+CSB!Q51 -> 0 | R51: =CSG!R51+CSB!R51 -> 0 | S51: =CSG!S51+CSB!S51 -> 0 | T51: =CSG!T51+CSB!T51 -> 937773 | U51: =SUM(M51:T51) -> 2903099 | V51: =IF(U51=W51, "ok", "check") -> ok | W51: ='St. Helena'!H50 -> 2903099
B52: St. James | C52: =CSG!C52+CSB!C52 -> 28884096 | D52: =CSG!D52+CSB!D52 -> 10986073 | E52: =CSG!E52+CSB!E52 -> 21835861 | F52: =CSG!F52+CSB!F52 -> 70799648 | G52: =CSG!G52+CSB!G52 -> 2071000 | H52: =CSG!H52+CSB!H52 -> 527234 | I52: =SUM(C52:H52) -> 135103912 | J52: =IF(I52=K52, "ok", "check") -> ok | K52: ='St. James'!I23 -> 135103912 | M52: =CSG!M52+CSB!M52 -> 3667431 | N52: =CSG!N52+CSB!N52 -> 0 | O52: =CSG!O52+CSB!O52 -> 0 | P52: =CSG!P52+CSB!P52 -> 0 | Q52: =CSG!Q52+CSB!Q52 -> 0 | R52: =CSG!R52+CSB!R52 -> 1521476 | S52: =CSG!S52+CSB!S52 -> 9810693 | T52: =CSG!T52+CSB!T52 -> 2004344 | U52: =SUM(M52:T52) -> 17003944 | V52: =IF(U52=W52, "ok", "check") -> ok | W52: ='St. James'!I36 -> 17003944
B53: St. John the Baptist | C53: =CSG!C53+CSB!C53 -> 60908249 | D53: =CSG!D53+CSB!D53 -> 363526 | E53: =CSG!E53+CSB!E53 -> 19681167 | F53: =CSG!F53+CSB!F53 -> 206350982 | G53: =CSG!G53+CSB!G53 -> 1083629 | H53: =CSG!H53+CSB!H53 -> 1483126 | I53: =SUM(C53:H53) -> 289870679 | J53: =IF(I53=K53, "ok", "check") -> ok | K53: ='St John the Baptist'!I22 -> 289870679 | M53: =CSG!M53+CSB!M53 -> 7293310 | N53: =CSG!N53+CSB!N53 -> 0 | O53: =CSG!O53+CSB!O53 -> 0 | P53: =CSG!P53+CSB!P53 -> 0 | Q53: =CSG!Q53+CSB!Q53 -> 1356508 | R53: =CSG!R53+CSB!R53 -> 6464877 | S53: =CSG!S53+CSB!S53 -> 73665907 | T53: =CSG!T53+CSB!T53 -> 171320 | U53: =SUM(M53:T53) -> 88951922 | V53: =IF(U53=W53, "ok", "check") -> ok | W53: ='St John the Baptist'!I35 -> 88951922
B54: St. Landry | C54: =CSG!C54+CSB!C54 -> 1555264 | D54: =CSG!D54+CSB!D54 -> 0 | E54: =CSG!E54+CSB!E54 -> 5692205 | F54: =CSG!F54+CSB!F54 -> 9506315 | G54: =CSG!G54+CSB!G54 -> 314662 | H54: =CSG!H54+CSB!H54 -> 42458 | I54: =SUM(C54:H54) -> 17110904 | J54: =IF(I54=K54, "ok", "check") -> ok | K54: ='St. Landry'!H20 -> 17110904 | M54: =CSG!M54+CSB!M54 -> 2271688 | N54: =CSG!N54+CSB!N54 -> 121245 | O54: =CSG!O54+CSB!O54 -> 58000 | P54: =CSG!P54+CSB!P54 -> 60000 | Q54: =CSG!Q54+CSB!Q54 -> 101389 | R54: =CSG!R54+CSB!R54 -> 0 | S54: =CSG!S54+CSB!S54 -> 0 | T54: =CSG!T54+CSB!T54 -> 222238 | U54: =SUM(M54:T54) -> 2834560 | V54: =IF(U54=W54, "ok", "check") -> ok | W54: ='St. Landry'!H42 -> 2834560
B55: St. Martin | C55: =CSG!C55+CSB!C55 -> 23148572 | D55: =CSG!D55+CSB!D55 -> 0 | E55: =CSG!E55+CSB!E55 -> 11373340 | F55: =CSG!F55+CSB!F55 -> 70360835 | G55: =CSG!G55+CSB!G55 -> 183431 | H55: =CSG!H55+CSB!H55 -> 204890 | I55: =SUM(C55:H55) -> 105271068 | J55: =IF(I55=K55, "ok", "check") -> ok | K55: ='St. Martin'!J14 -> 105271068 | M55: =CSG!M55+CSB!M55 -> 517157 | N55: =CSG!N55+CSB!N55 -> 410568 | O55: =CSG!O55+CSB!O55 -> 1781000 | P55: =CSG!P55+CSB!P55 -> 22494000 | Q55: =CSG!Q55+CSB!Q55 -> 93304 | R55: =CSG!R55+CSB!R55 -> 193138 | S55: =CSG!S55+CSB!S55 -> 150518 | T55: =CSG!T55+CSB!T55 -> 6162957 | U55: =SUM(M55:T55) -> 31802642 | V55: =IF(U55=W55, "ok", "check") -> ok | W55: ='St. Martin'!J30 -> 31802642
B56: St. Mary | C56: =CSG!C56+CSB!C56 -> 6902907 | D56: =CSG!D56+CSB!D56 -> 17601483 | E56: =CSG!E56+CSB!E56 -> 1682333 | F56: =CSG!F56+CSB!F56 -> 129690570 | G56: =CSG!G56+CSB!G56 -> 12841427 | H56: =CSG!H56+CSB!H56 -> 4220 | I56: =SUM(C56:H56) -> 168722940 | J56: =IF(I56=K56, "ok", "check") -> ok | K56: ='St. Mary'!J36 -> 168722940 | M56: =CSG!M56+CSB!M56 -> 1865390 | N56: =CSG!N56+CSB!N56 -> 165000 | O56: =CSG!O56+CSB!O56 -> 0 | P56: =CSG!P56+CSB!P56 -> 0 | Q56: =CSG!Q56+CSB!Q56 -> 663469 | R56: =CSG!R56+CSB!R56 -> 0 | S56: =CSG!S56+CSB!S56 -> 0 | T56: =CSG!T56+CSB!T56 -> 49390165 | U56: =SUM(M56:T56) -> 52084024 | V56: =IF(U56=W56, "ok", "check") -> ok | W56: ='St. Mary'!J62 -> 52084024
B57: St. Tammany | C57: =CSG!C57+CSB!C57 -> 34898187 | D57: =CSG!D57+CSB!D57 -> 156302313 | E57: =CSG!E57+CSB!E57 -> 50783165 | F57: =CSG!F57+CSB!F57 -> 454180079 | G57: =CSG!G57+CSB!G57 -> 24006 | H57: =CSG!H57+CSB!H57 -> 14064849 | I57: =SUM(C57:H57) -> 710252599 | J57: =IF(I57=K57, "ok", "check") -> ok | K57: ='St. Tammany'!J19 -> 710252599 | L57: ='St. Tammany'!H24 -> 5106064 | M57: =CSG!M57+CSB!M57 -> 21974370 | N57: =CSG!N57+CSB!N57 -> 0 | O57: =CSG!O57+CSB!O57 -> 0 | P57: =CSG!P57+CSB!P57 -> 0 | Q57: =CSG!Q57+CSB!Q57 -> 8555724 | R57: =CSG!R57+CSB!R57 -> 10418024 | S57: =CSG!S57+CSB!S57 -> 139099219 | T57: =CSG!T57+CSB!T57 -> 6975112 | U57: =SUM(M57:T57) -> 187022449 | V57: =IF(U57=W57, "ok", "check") -> ok | W57: ='St. Tammany'!J37 -> 187022449
B58: Tangipahoa | C58: =CSG!C58+CSB!C58 -> 17398202 | D58: =CSG!D58+CSB!D58 -> 0 | E58: =CSG!E58+CSB!E58 -> 8935241 | F58: =CSG!F58+CSB!F58 -> 178240431 | G58: =CSG!G58+CSB!G58 -> 42692 | H58: =CSG!H58+CSB!H58 -> 898211 | I58: =SUM(C58:H58) -> 205514777 | J58: =IF(I58=K58, "ok", "check") -> ok | K58: =Tangipahoa!H15 -> 205514777 | M58: =CSG!M58+CSB!M58 -> 4186126 | N58: =CSG!N58+CSB!N58 -> 0 | O58: =CSG!O58+CSB!O58 -> 0 | P58: =CSG!P58+CSB!P58 -> 0 | Q58: =CSG!Q58+CSB!Q58 -> 383324 | R58: =CSG!R58+CSB!R58 -> 90000 | S58: =CSG!S58+CSB!S58 -> 8104902 | T58: =CSG!T58+CSB!T58 -> 1567913 | U58: =SUM(M58:T58) -> 14332265 | V58: =IF(U58=W58, "ok", "check") -> ok | W58: =Tangipahoa!H27 -> 14332265 | Y58: =Tangipahoa!H32 -> 53394
B59: Tensas | C59: =CSG!C59+CSB!C59 -> 2313344 | D59: =CSG!D59+CSB!D59 -> 0 | E59: =CSG!E59+CSB!E59 -> 763109 | F59: =CSG!F59+CSB!F59 -> 8567911 | G59: =CSG!G59+CSB!G59 -> 0 | H59: =CSG!H59+CSB!H59 -> 973759 | I59: =SUM(C59:H59) -> 12618123 | J59: =IF(I59=K59, "ok", "check") -> ok | K59: =Tensas!G13 -> 12618123 | M59: =CSG!M59+CSB!M59 -> 156049 | N59: =CSG!N59+CSB!N59 -> 0 | O59: =CSG!O59+CSB!O59 -> 0 | P59: =CSG!P59+CSB!P59 -> 0 | Q59: =CSG!Q59+CSB!Q59 -> 54048 | R59: =CSG!R59+CSB!R59 -> 39882 | S59: =CSG!S59+CSB!S59 -> 1255223 | T59: =CSG!T59+CSB!T59 -> 0 | U59: =SUM(M59:T59) -> 1505202 | V59: =IF(U59=W59, "ok", "check") -> ok | W59: =Tensas!G22 -> 1505202
B60: Terrebonne | C60: =CSG!C60+CSB!C60 -> 48734757 | D60: =CSG!D60+CSB!D60 -> 120283687 | E60: =CSG!E60+CSB!E60 -> 19246292 | F60: =CSG!F60+CSB!F60 -> 448828888 | G60: =CSG!G60+CSB!G60 -> 81117979 | H60: =CSG!H60+CSB!H60 -> 5324089 | I60: =SUM(C60:H60) -> 723535692 | J60: =IF(I60=K60, "ok", "check") -> ok | K60: =Terrebonne!J26 -> 723535692 | L60: =Terrebonne!H28 -> 132278 | M60: =CSG!M60+CSB!M60 -> 32939853 | N60: =CSG!N60+CSB!N60 -> 0 | O60: =CSG!O60+CSB!O60 -> 0 | P60: =CSG!P60+CSB!P60 -> 0 | Q60: =CSG!Q60+CSB!Q60 -> 9291555 | R60: =CSG!R60+CSB!R60 -> 7432698 | S60: =CSG!S60+CSB!S60 -> 136608636 | T60: =CSG!T60+CSB!T60 -> 0 | U60: =SUM(M60:T60) -> 186272742 | V60: =IF(U60=W60, "ok", "check") -> ok | W60: =Terrebonne!J42 -> 186272742 | Y60: =Terrebonne!H44 -> 27193917
B61: Union | C61: =CSG!C61+CSB!C61 -> 7110474 | D61: =CSG!D61+CSB!D61 -> 7240283 | E61: =CSG!E61+CSB!E61 -> 4749704 | F61: =CSG!F61+CSB!F61 -> 12207847 | G61: =CSG!G61+CSB!G61 -> 0 | H61: =CSG!H61+CSB!H61 -> 0 | I61: =SUM(C61:H61) -> 31308308 | J61: =IF(I61=K61, "ok", "check") -> ok | K61: =Union!G11 -> 31308308 | M61: =CSG!M61+CSB!M61 -> 1373845 | N61: =CSG!N61+CSB!N61 -> 219368 | O61: =CSG!O61+CSB!O61 -> 18000 | P61: =CSG!P61+CSB!P61 -> 235000 | Q61: =CSG!Q61+CSB!Q61 -> 260018 | R61: =CSG!R61+CSB!R61 -> 174000 | S61: =CSG!S61+CSB!S61 -> 180000 | T61: =CSG!T61+CSB!T61 -> 8907088 | U61: =SUM(M61:T61) -> 11367319 | V61: =IF(U61=W61, "ok", "check") -> ok | W61: =Union!G25 -> 11367319 | Y61: =Union!G28 -> 14194
B62: Vermillion | C62: =CSG!C62+CSB!C62 -> 53128318 | D62: =CSG!D62+CSB!D62 -> 0 | E62: =CSG!E62+CSB!E62 -> 381262 | F62: =CSG!F62+CSB!F62 -> 82500254 | G62: =CSG!G62+CSB!G62 -> 8635672 | H62: =CSG!H62+CSB!H62 -> 56444 | I62: =SUM(C62:H62) -> 144701950 | J62: =IF(I62=K62, "ok", "check") -> ok | K62: =Vermillion!H14 -> 144701950 | M62: =CSG!M62+CSB!M62 -> 2216308 | N62: =CSG!N62+CSB!N62 -> 0 | O62: =CSG!O62+CSB!O62 -> 0 | P62: =CSG!P62+CSB!P62 -> 0 | Q62: =CSG!Q62+CSB!Q62 -> 58759 | R62: =CSG!R62+CSB!R62 -> 365000 | S62: =CSG!S62+CSB!S62 -> 5463515 | T62: =CSG!T62+CSB!T62 -> 0 | U62: =SUM(M62:T62) -> 8103582 | V62: =IF(U62=W62, "ok", "check") -> ok | W62: =Vermillion!H27 -> 8103582 | Y62: =Vermillion!H30 -> 948391
B63: Vernon | C63: =CSG!C63+CSB!C63 -> 23897070 | D63: =CSG!D63+CSB!D63 -> 1246021 | E63: =CSG!E63+CSB!E63 -> 6132255 | F63: =CSG!F63+CSB!F63 -> 45322054 | G63: =CSG!G63+CSB!G63 -> 0 | H63: =CSG!H63+CSB!H63 -> 21627 | I63: =SUM(C63:H63) -> 76619027 | J63: =IF(I63=K63, "ok", "check") -> ok | K63: =Vernon!H18 -> 76619027 | M63: =CSG!M63+CSB!M63 -> 1213698 | N63: =CSG!N63+CSB!N63 -> 0 | O63: =CSG!O63+CSB!O63 -> 0 | P63: =CSG!P63+CSB!P63 -> 0 | Q63: =CSG!Q63+CSB!Q63 -> 0 | R63: =CSG!R63+CSB!R63 -> 812070 | S63: =CSG!S63+CSB!S63 -> 19678827 | T63: =CSG!T63+CSB!T63 -> 110008 | U63: =SUM(M63:T63) -> 21814603 | V63: =IF(U63=W63, "ok", "check") -> ok | W63: =Vernon!H28 -> 21814603
B64: Washington | C64: =CSG!C64+CSB!C64 -> 1380203 | D64: =CSG!D64+CSB!D64 -> 2545233 | E64: =CSG!E64+CSB!E64 -> 5325202 | F64: =CSG!F64+CSB!F64 -> 38243242 | G64: =CSG!G64+CSB!G64 -> 352460 | H64: =CSG!H64+CSB!H64 -> 2340730 | I64: =SUM(C64:H64) -> 50187070 | J64: =IF(I64=K64, "ok", "check") -> ok | K64: =Washington!J23 -> 50187070 | M64: =CSG!M64+CSB!M64 -> 877732 | N64: =CSG!N64+CSB!N64 -> 0 | O64: =CSG!O64+CSB!O64 -> 0 | P64: =CSG!P64+CSB!P64 -> 0 | Q64: =CSG!Q64+CSB!Q64 -> 910200 | R64: =CSG!R64+CSB!R64 -> 1480893 | S64: =CSG!S64+CSB!S64 -> 4425000 | T64: =CSG!T64+CSB!T64 -> 987071 | U64: =SUM(M64:T64) -> 8680896 | V64: =IF(U64=W64, "ok", "check") -> ok | W64: =Washington!H35 -> 8680896
B65: Webster | C65: =CSG!C65+CSB!C65 -> 5380498 | D65: =CSG!D65+CSB!D65 -> 2611059 | E65: =CSG!E65+CSB!E65 -> 5361318 | F65: =CSG!F65+CSB!F65 -> 11531478 | G65: =CSG!G65+CSB!G65 -> 0 | H65: =CSG!H65+CSB!H65 -> 287208 | I65: =SUM(C65:H65) -> 25171561 | J65: =IF(I65=K65, "ok", "check") -> ok | K65: =Webster!H15 -> 25171561 | M65: =CSG!M65+CSB!M65 -> 333639 | N65: =CSG!N65+CSB!N65 -> 0 | O65: =CSG!O65+CSB!O65 -> 0 | P65: =CSG!P65+CSB!P65 -> 0 | Q65: =CSG!Q65+CSB!Q65 -> 163911 | R65: =CSG!R65+CSB!R65 -> 641574 | S65: =CSG!S65+CSB!S65 -> 1134777 | T65: =CSG!T65+CSB!T65 -> 57724 | U65: =SUM(M65:T65) -> 2331625 | V65: =IF(U65=W65, "ok", "check") -> ok | W65: =Webster!H29 -> 2331625
B66: West Baton Rouge | C66: =CSG!C66+CSB!C66 -> 8405674 | D66: =CSG!D66+CSB!D66 -> 16286223 | E66: =CSG!E66+CSB!E66 -> 7543435 | F66: =CSG!F66+CSB!F66 -> 61165063 | G66: =CSG!G66+CSB!G66 -> 1673400 | H66: =CSG!H66+CSB!H66 -> 0 | I66: =SUM(C66:H66) -> 95073795 | J66: =IF(I66=K66, "ok", "check") -> ok | K66: ='West Baton Rouge'!G18 -> 95073795 | M66: =CSG!M66+CSB!M66 -> 557345 | N66: =CSG!N66+CSB!N66 -> 0 | O66: =CSG!O66+CSB!O66 -> 0 | P66: =CSG!P66+CSB!P66 -> 0 | Q66: =CSG!Q66+CSB!Q66 -> 0 | R66: =CSG!R66+CSB!R66 -> 582760 | S66: =CSG!S66+CSB!S66 -> 7829726 | T66: =CSG!T66+CSB!T66 -> 0 | U66: =SUM(M66:T66) -> 8969831 | V66: =IF(U66=W66, "ok", "check") -> ok | W66: ='West Baton Rouge'!G26 -> 8969831 | Y66: ='West Baton Rouge'!G31 -> 8928823
B67: West Carroll | C67: =CSG!C67+CSB!C67 -> 5432216 | D67: =CSG!D67+CSB!D67 -> 0 | E67: =CSG!E67+CSB!E67 -> 1464515 | F67: =CSG!F67+CSB!F67 -> 14017269 | G67: =CSG!G67+CSB!G67 -> 0 | H67: =CSG!H67+CSB!H67 -> 696655 | I67: =SUM(C67:H67) -> 21610655 | J67: =IF(I67=K67, "ok", "check") -> ok | K67: ='West Carroll'!H12 -> 21610655 | M67: =CSG!M67+CSB!M67 -> 157412 | N67: =CSG!N67+CSB!N67 -> 94228 | O67: =CSG!O67+CSB!O67 -> 0 | P67: =CSG!P67+CSB!P67 -> 0 | Q67: =CSG!Q67+CSB!Q67 -> 0 | R67: =CSG!R67+CSB!R67 -> 14133 | S67: =CSG!S67+CSB!S67 -> 98938 | T67: =CSG!T67+CSB!T67 -> 1915315 | U67: =SUM(M67:T67) -> 2280026 | V67: =IF(U67=W67, "ok", "check") -> ok | W67: ='West Carroll'!H22 -> 2280026 | Y67: ='West Carroll'!H25 -> 184752
B68: West Feliciana | C68: =CSG!C68+CSB!C68 -> 1724112 | D68: =CSG!D68+CSB!D68 -> 12859199 | E68: =CSG!E68+CSB!E68 -> 4691921 | F68: =CSG!F68+CSB!F68 -> 26608796 | G68: =CSG!G68+CSB!G68 -> 488651 | H68: =CSG!H68+CSB!H68 -> 96925 | I68: =SUM(C68:H68) -> 46469604 | J68: =IF(I68=K68, "ok", "check") -> ok | K68: ='West Feliciana'!J23 -> 46469604 | M68: =CSG!M68+CSB!M68 -> 940021 | N68: =CSG!N68+CSB!N68 -> 0 | O68: =CSG!O68+CSB!O68 -> 0 | P68: =CSG!P68+CSB!P68 -> 0 | Q68: =CSG!Q68+CSB!Q68 -> 0 | R68: =CSG!R68+CSB!R68 -> 328297 | S68: =CSG!S68+CSB!S68 -> 6702297 | T68: =CSG!T68+CSB!T68 -> 1319486 | U68: =SUM(M68:T68) -> 9290101 | V68: =IF(U68=W68, "ok", "check") -> ok | W68: ='West Feliciana'!J35 -> 9290101
B69: Winn | C69: =CSG!C69+CSB!C69 -> 4118802 | D69: =CSG!D69+CSB!D69 -> 0 | E69: =CSG!E69+CSB!E69 -> 2234175 | F69: =CSG!F69+CSB!F69 -> 3598290 | G69: =CSG!G69+CSB!G69 -> 0 | H69: =CSG!H69+CSB!H69 -> 0 | I69: =SUM(C69:H69) -> 9951267 | J69: =IF(I69=K69, "ok", "check") -> ok | K69: =Winn!H18 -> 9951267 | M69: =CSG!M69+CSB!M69 -> 125690 | N69: =CSG!N69+CSB!N69 -> 0 | O69: =CSG!O69+CSB!O69 -> 0 | P69: =CSG!P69+CSB!P69 -> 0 | Q69: =CSG!Q69+CSB!Q69 -> 0 | R69: =CSG!R69+CSB!R69 -> 220000 | S69: =CSG!S69+CSB!S69 -> 2010000 | T69: =CSG!T69+CSB!T69 -> 32101 | U69: =SUM(M69:T69) -> 2387791 | V69: =IF(U69=W69, "ok", "check") -> ok | W69: =Winn!H28 -> 2387791
B71: Totals | C71: =SUM(C8:C8) -> 46091237 | D71: =SUM(D8:D8) -> 97818553 | E71: =SUM(E8:E8) -> 31963150 | F71: =SUM(F8:F8) -> 220457798 | G71: =SUM(G8:G8) -> 5125945 | H71: =SUM(H8:H8) -> 1164472 | I71: =SUM(I6:I69) -> 1.9165871e+10 | J71: =IF(I71=K71, "ok", "check") -> ok | K71: =SUM(K6:K70) -> 1.9165871e+10 | M71: =SUM(M8:M8) -> 7744502 | N71: =SUM(N8:N8) -> 0 | O71: =SUM(O8:O8) -> 235409 | P71: =SUM(P8:P8) -> 667416 | Q71: =SUM(Q8:Q8) -> 838595 | R71: =SUM(R8:R8) -> 4335000 | S71: =SUM(S8:S8) -> 80612569 | T71: =SUM(T8:T8) -> 4561445 | U71: =SUM(U6:U69) -> 7.3811087e+09 | V71: =IF(U71=W71, "ok", "check") -> ok | W71: =SUM(W6:W70) -> 7.3811087e+09 | X71: =SUM(#REF!) -> #REF!

Sheet CSG
A1: 2013-SONA
C2: Assets: | N2: Liabilities: | S2: Non-Current/Long-Term Liabilities: | AA2: Net Assets:
