Workbook

Sheet Acadia
D1: ACADIA PARISH POLICE JURY
D2: Capital Assets
D3: For the Year Ended December 31, 2013
I5: Beginning Balance | J5: Increases | K5: Decreases | L5: Ending Balance | M5: Cross Sectional
A7: Primary Government
A8: Government Activities:
A9: Capital assets, not being depreciated:
B10: Land | I10: 1172249 | J10: 210643 | K10: -53884 | L10: =SUM(I10:K10) -> 1329008 | M10: =SUM(L10) -> 1329008
B11: Construction in progress | I11: 3168467 | J11: 9240635 | K11: -2161157 | L11: =SUM(I11:K11) -> 10247945 | M11: =SUM(L11) -> 10247945
C12: Total assets not being depreciated | I12: =SUM(I10:I11) -> 4340716 | J12: =SUM(J10:J11) -> 9451278 | K12: =SUM(K10:K11) -> -2215041 | L12: =SUM(L10:L11) -> 11576953
A14: Capital assets being depreciated:
B15: Buildings and improvements | I15: 22193080 | J15: 2231588 | K15: 0 | L15: =SUM(I15:K15) -> 24424668
B16: Machinery and equipment | I16: 11766135 | J16: 261410 | K16: 0 | L16: =SUM(I16:K16) -> 12027545
B17: Improvements, other than buildings | I17: 748499 | J17: 16078 | L17: =SUM(I17:K17) -> 764577
B18: Infrastructure | I18: 36944045 | J18: 926083 | K18: -68500 | L18: =SUM(I18:K18) -> 37801628
C19: Total capital assets being depreciated | I19: =SUM(I15:I18) -> 71651759 | J19: =SUM(J15:J18) -> 3435159 | K19: =SUM(K15:K18) -> -68500 | L19: =SUM(L15:L18) -> 75018418
A21: Less accumulated depreciation for:
B22: Buildings and improvements | I22: -5958982 | J22: -771222 | K22: 0 | L22: =SUM(I22:K22) -> -6730204 | M22: =SUM(L22,L15) -> 17694464
B23: Machinery and equipment | I23: -5627631 | J23: -946670 | K23: 0 | L23: =SUM(I23:K23) -> -6574301 | M23: =SUM(L23,L16) -> 5453244
B24: Improvements, other than buildings | I24: -396486 | J24: -8734 | L24: =SUM(I24:K24) -> -405220 | M24: =SUM(L24,L17) -> 359357
B25: Infrastructure | I25: -17105170 | J25: -1378690 | K25: 68500 | L25: =SUM(I25:K25) -> -18415360 | M25: =SUM(L25,L18) -> 19386268
C26: Total accumulated depreciation | I26: =SUM(I22:I25) -> -29088269 | J26: =SUM(J22:J25) -> -3105316 | K26: =SUM(K22:K25) -> 68500 | L26: =SUM(L22:L25) -> -32125085
B27: Total capital assets being depreciated, net | I27: =I26+I19 -> 42563490 | J27: =J26+J19 -> 329843 | K27: =K26+K19 -> 0 | L27: =L26+L19 -> 42893333
B28: Governmental activities capital assets, net | I28: =I12+I27 -> 46904206 | J28: =J12+J27 -> 9781121 | K28: =K12+K27 -> -2215041 | L28: =L12+L27 -> 54470286 | M28: =SUM(M22:M25,M10:M11) -> 54470286

Sheet Allen
D1: ALLEN PARISH POLICE JURY
D2: Capital Assets
D3: For the Year Ended December 31, 2013
G5: Beginning Balance | H5: Increases | I5: Decreases | J5: Ending Balance | K5: Cross Sectional
A7: Governmental Activities:
B8: Capital assets, not being depreciated:
C9: Construction in progress | G9: 273169 | I9: -273169 | J9: =SUM(G9:I9) -> 0 | K9: =SUM(J9) -> 0
C10: Land | G10: 572300 | J10: =SUM(G10:I10) -> 572300 | K10: =SUM(J10) -> 572300
D12: Total capital assets, not being depreciated | G12: =SUM(G8:G11) -> 845469 | H12: =SUM(H8:H11) -> 0 | I12: =SUM(I8:I11) -> -273169 | J12: =SUM(J8:J11) -> 572300
A14: Capital assets being depreciated:
B15: Buildings | G15: 4488374 | H15: 58965 | I15: 0 | J15: =SUM(G15:I15) -> 4547339
B16: Improvements other than buildings | G16: 5851280 | H16: 1775 | J16: =SUM(G16:I16) -> 5853055
B17: Furniture and fixtures | G17: 405550 | H17: 3899 | I17: -19416 | J17: =SUM(G17:I17) -> 390033
B18: Vehicles | G18: 804226 | H18: 55832 | I18: -40609 | J18: =SUM(G18:I18) -> 819449
B19: Machinery and equipment | G19: 4520910 | H19: 306084 | I19: -1572772 | J19: =SUM(G19:I19) -> 3254222
B20: Infrastructure | G20: 28219912 | I20: 0 | J20: =SUM(G20:I20) -> 28219912
D22: Total capital assets being depreciated | G22: =SUM(G15:G21) -> 44290252 | H22: =SUM(H15:H21) -> 426555 | I22: =SUM(I15:I21) -> -1632797 | J22: =SUM(J15:J20) -> 43084010
A24: Less accumulated depreciation for:
B25: Buildings | G25: 1686529 | H25: 100580 | I25: 0 | J25: =SUM(G25:I25) -> 1787109 | K25: =J15-J25 -> 2760230
B26: Improvements other than buildings | G26: 1980497 | H26: 200716 | J26: =SUM(G26:I26) -> 2181213 | K26: =J16-J26 -> 3671842
B27: Furniture and fixtures | G27: 297147 | H27: 27444 | I27: -12961 | J27: =SUM(G27:I27) -> 311630 | K27: =J17-J27 -> 78403
B28: Vehicles | G28: 613540 | H28: 46028 | I28: -40609 | J28: =SUM(G28:I28) -> 618959 | K28: =J18-J28 -> 200490
B29: Machinery and equipment | G29: 2893539 | H29: 209343 | I29: -872988 | J29: =SUM(G29:I29) -> 2229894 | K29: =J19-J29 -> 1024328
B30: Infrastructure | G30: 11277335 | H30: 584415 | I30: 0 | J30: =SUM(G30:I30) -> 11861750 | K30: =J20-J30 -> 16358162
D32: Total accumulated depreciation | G32: =SUM(G25:G31) -> 18748587 | H32: =SUM(H25:H31) -> 1168526 | I32: =SUM(I25:I31) -> -926558 | J32: =SUM(J25:J31) -> 18990555
B34: Total capital assets being depreciated, net | G34: =G22-G32 -> 25541665 | H34: =H22-H32 -> -741971 | I34: =I22-I32 -> -706239 | J34: =J22-J32 -> 24093455
B36: Governmental activities capital assets, net | G36: =G34+G12 -> 26387134 | H36: =H34+H12 -> -741971 | I36: =I34+I12 -> -979408 | J36: =J34+J12 -> 24665755 | K36: =SUM(K25:K30,K9:K10) -> 24665755

Sheet Ascension
D1: ASCENSION PARISH POLICE JURY
D2: Capital Assets
D3: For the Year Ended December 31, 2013
I5: Beginning Balance | J5: Increases | K5: Decreases | L5: Ending Balance | M5: Cross Sectional
A7: Governmental Activities:
B8: Capital assets, not being depreciated:
C9: Land | I9: 16585 | J9: 728 | K9: 0 | L9: =SUM(I9:K9) -> 17313 | M9: =SUM(L9) -> 17313
C10: Construction in progress | I10: 32839 | J10: 23212 | K10: -264 | L10: =SUM(I10:K10) -> 55787 | M10: =SUM(L10) -> 55787
D12: Total capital assets, not being depreciated | I12: =SUM(I8:I11) -> 49424 | J12: =SUM(J8:J11) -> 23940 | K12: =SUM(K8:K11) -> -264 | L12: =SUM(L8:L11) -> 73100
A14: Capital assets being depreciated:
B15: Buildings | I15: 62442 | J15: 256 | K15: 0 | L15: =SUM(I15:K15) -> 62698
B16: Vehicles | I16: 13147 | J16: 544 | K16: -529 | L16: =SUM(I16:K16) -> 13162
B17: Equipment | I17: 12549 | J17: 840 | K17: -1303 | L17: =SUM(I17:K17) -> 12086
B18: Furniture and fixtures | I18: 1100 | J18: 32 | K18: -5 | L18: =SUM(I18:K18) -> 1127
B19: Library materials | I19: 2882 | J19: 417 | K19: -507 | L19: =SUM(I19:K19) -> 2792
B20: Infrastructure | I20: 210670 | J20: 5615 | K20: 0 | L20: =SUM(I20:K20) -> 216285
D22: Total capital assets being depreciated | I22: =SUM(I15:I21) -> 302790 | J22: =SUM(J15:J21) -> 7704 | K22: =SUM(K15:K21) -> -2344 | L22: =SUM(L15:L20) -> 308150
A24: Less accumulated depreciation for:
B25: Buildings | I25: -19199 | J25: -1697 | K25: 0 | L25: =SUM(I25:K25) -> -20896 | M25: =SUM(L25,L15) -> 41802
B26: Vehicles | I26: -8800 | J26: -697 | K26: 510 | L26: =SUM(I26:K26) -> -8987 | M26: =SUM(L26,L16) -> 4175
B27: Equipment | I27: -9796 | J27: -935 | K27: 1322 | L27: =SUM(I27:K27) -> -9409 | M27: =SUM(L27,L17) -> 2677
B28: Furniture and fixtures | I28: -568 | J28: -82 | K28: 5 | L28: =SUM(I28:K28) -> -645 | M28: =SUM(L28,L18) -> 482
B29: Library materials | I29: -1774 | J29: -558 | K29: 507 | L29: =SUM(I29:K29) -> -1825 | M29: =SUM(L29,L19) -> 967
B30: Infrastructure | I30: -119227 | J30: -10696 | K30: 0 | L30: =SUM(I30:K30) -> -129923 | M30: =SUM(L30,L20) -> 86362
D32: Total accumulated depreciation | I32: =SUM(I25:I31) -> -159364 | J32: =SUM(J25:J31) -> -14665 | K32: =SUM(K25:K31) -> 2344 | L32: =SUM(L25:L31) -> -171685
B34: Total capital assets being depreciated, net | I34: =I22+I32 -> 143426 | J34: =J22+J32 -> -6961 | K34: =K22+K32 -> 0 | L34: =L22+L32 -> 136465
B36: Governmental activities capital assets, net | I36: =I32+I22+I12 -> 192850 | J36: =J32+J22+J12 -> 16979 | K36: =K32+K22+K12 -> -264 | L36: =L32+L22+L12 -> 209565 | M36: =SUM(M25:M30,M9:M10) -> 209565
I39: Beginning Balance | J39: Increases | K39: Decreases | L39: Ending Balance
A40: Business-Type Activities:
B41: Capital assets, not being depreciated:
C42: Land | I42: 670 | J42: 0 | K42: 0 | L42: =SUM(I42:K42) -> 670 | M42: =SUM(L42) -> 670
C43: Construction in progress | I43: 98 | J43: 173 | K43: 0 | L43: =SUM(I43:K43) -> 271 | M43: =SUM(L43) -> 271
D45: Total capital assets, not being depreciated | I45: =SUM(I41:I44) -> 768 | J45: =SUM(J41:J44) -> 173 | K45: =SUM(K41:K44) -> 0 | L45: =SUM(L41:L44) -> 941
B47: Capital assets, depreciable:
C48: Sewer systems | I48: 5911 | J48: 0 | K48: 0 | L48: =SUM(I48:K48) -> 5911
C49: Water systems | I49: 766 | J49: 9 | K49: 0 | L49: =SUM(I49:K49) -> 775
C50: Lamar Dixon Expo Center | I50: 7127 | J50: 171 | K50: 0 | L50: =SUM(I50:K50) -> 7298
D52: Total capital assets, depreciable | I52: =SUM(I47:I50) -> 13804 | J52: =SUM(J47:J50) -> 180 | K52: =SUM(K47:K50) -> 0 | L52: =SUM(L47:L50) -> 13984
B54: Less accumulated depreciation for:
C55: Sewer systems | I55: -1793 | J55: -302 | L55: =SUM(I55:K55) -> -2095 | M55: =SUM(L55,L48) -> 3816
C56: Water systems | I56: -386 | J56: -16 | L56: =SUM(I56:K56) -> -402 | M56: =SUM(L56,L49) -> 373
C57: Lamar Dixon Expo Center | I57: -1118 | J57: -417 | L57: =SUM(I57:K57) -> -1535 | M57: =SUM(L57,L50) -> 5763
D59: Total accumulated depreciation | I59: =SUM(I55:I57) -> -3297 | J59: =SUM(J55:J57) -> -735 | K59: =SUM(K55:K57) -> 0 | L59: =SUM(L55:L57) -> -4032
D61: Total capital assets, depreciable, net | I61: =I52+I59 -> 10507 | J61: =J52+J59 -> -555 | K61: =K52+K59 -> 0 | L61: =L52+L59 -> 9952
D63: Business-type activities capital assets, net | I63: =I61+I45 -> 11275 | J63: =J61+J45 -> -382 | K63: =K61+K45 -> 0 | L63: =L61+L45 -> 10893 | M63: =SUM(M55:M57,M42:M43) -> 10893

Sheet Assumption
D1: ASSUMPTION PARISH POLICE JURY
D2: Capital Assets
D3: For the Year Ended December 31, 2013
H6: Balance 12/31/2012 | I6: 2013 Additions | J6: 2013 Deletions | K6: 2013 Reclassifications | L6: Balance 12/31/2013 | M6: Cross Sectional
N7: Net Depreciation
C8: Land | H8: 2210258 | I8: 3123 | J8: 0 | K8: 0 | L8: =SUM(H8:K8) -> 2213381 | M8: =SUM(L8) -> 2213381 | N8: =SUM(H8:K8) -> 2213381 | O8: Depreciation
C9: Buildings | H9: 11414215 | I9: 723095 | J9: 0 | K9: 11579849 | L9: =SUM(H9:K9) -> 23717159 | M9: =L9 -> 23717159 | N9: =M9-O9 -> 16396346 | O9: =(M9/P9)*M17 -> 7320812.6 | P9: =SUM(M9:M13) -> 59351210 | Q9: Total capital assets being depreeciated
C10: Improvements other than buildings | H10: 9600524 | I10: 112916 | J10: 133 | K10: 1971576 | L10: =+H10+I10-J10+K10 -> 11684883 | M10: =L10 -> 11684883 | N10: =M10-O10 -> 8078091.9 | O10: =(M10/P9)*M17 -> 3606791.1
C11: Roads | H11: 14256123 | I11: 930212 | J11: 0 | K11: 923067 | L11: =SUM(H11:K11) -> 16109402 | M11: =L11 -> 16109402 | N11: =M11-O11 -> 11136888 | O11: =(M11/P9)*M17 -> 4972514.4
C12: Bridges | H12: 588844 | I12: 0 | J12: 0 | K12: 0 | L12: =SUM(H12:K12) -> 588844 | M12: =L12 -> 588844 | N12: =M12-O12 -> 407084.6 | O12: =(M12/P9)*M17 -> 181759.4
C13: Equipment & other | H13: 6669216 | I13: 576282 | J13: 129654 | K13: 135078 | L13: =+H13+I13-J13+K13 -> 7250922 | M13: =L13 -> 7250922 | N13: =M13-O13 -> 5012768.5 | O13: =(M13/P9)*M17 -> 2238153.5
C14: Construction in progress | H14: 12616148 | I14: 2481993 | J14: 0 | K14: -14609570 | L14: =SUM(H14:K14) -> 488571 | M14: =SUM(L14) -> 488571 | N14: =SUM(H14:K14) -> 488571
H15: =SUM(H8:H14) -> 57355328 | I15: =SUM(I8:I14) -> 4827621 | J15: =SUM(J8:J14) -> 129787 | K15: =SUM(K8:K14) -> 0 | L15: =SUM(L8:L14) -> 62053162 | O15: =SUM(O9:O13) -> 18320031
C17: Accumulated Depreciation | H17: 16038335 | I17: 2334670 | J17: 52974 | K17: 0 | L17: =+H17+I17-J17 -> 18320031 | M17: =SUM(L17) -> 18320031
C19: Capital Assets, Net Depreciation | H19: =H15-H17 -> 41316993 | I19: =I15-J17 -> 4774647 | J19: =J15-J17 -> 76813 | K19: =K15+K17 -> 0 | L19: =L15-L17 -> 43733131 | M19: =SUM(M8:M14)-M17 -> 43733131 | N19: =SUM(N8:N16) -> 43733131

Sheet Avoyelles
D1: AVOYELLES PARISH POLICE JURY
D2: Capital Assets
D3: For the Year Ended December 31, 2013
G5: Beginning Balance | H5: Increases | I5: Decreases | J5: Ending Balance | K5: Cross Sectional
A7: Governmental Activities:
B8: Capital assets, not being depreciated:
C9: Land | G9: 584787 | J9: =SUM(G9:I9) -> 584787 | K9: =SUM(J9) -> 584787
C10: Construction in progress | G10: 492818 | H10: 590251 | J10: =SUM(G10:I10) -> 1083069 | K10: =SUM(J10) -> 1083069
D12: Total capital assets, not being depreciated | G12: =SUM(G8:G11) -> 1077605 | H12: =SUM(H8:H11) -> 590251 | I12: =SUM(I8:I11) -> 0 | J12: =SUM(J8:J11) -> 1667856
A14: Capital assets being depreciated:
B15: Buildings and improvements | G15: 4168006 | H15: 9090 | I15: 0 | J15: =SUM(G15:I15) -> 4177096
B16: Equipment, furniture and fixtures | G16: 567578 | H16: 2899 | J16: =SUM(G16:I16) -> 570477
B17: Infrastructure | G17: 25000 | H17: 50128 | J17: =SUM(G17:I17) -> 75128
B18: Heavy equipment | G18: 3177605 | H18: 67404 | I18: 0 | J18: =SUM(G18:I18) -> 3245009
D20: Total capital assets being depreciated | G20: =SUM(G15:G19) -> 7938189 | H20: =SUM(H15:H18) -> 129521 | I20: =SUM(I15:I19) -> 0 | J20: =SUM(J15:J18) -> 8067710
A22: Less accumulated depreciation for:
B23: Buildings and improvements | G23: 1292488 | H23: 155643 | I23: 0 | J23: =SUM(G23:I23) -> 1448131 | K23: =J15-J23 -> 2728965
B24: Equipment, furniture and fixtures | G24: 456935 | H24: 33747 | J24: =SUM(G24:I24) -> 490682 | K24: =J16-J24 -> 79795
B25: Infrastructure | H25: 31327 | J25: =SUM(G25:I25) -> 31327 | K25: =J17-J25 -> 43801
B26: Heavy equipment | G26: 2377326 | H26: 155858 | I26: 0 | J26: =SUM(G26:I26) -> 2533184 | K26: =J18-J26 -> 711825
D28: Total accumulated depreciation | G28: =SUM(G23:G27) -> 4126749 | H28: =SUM(H23:H27) -> 376575 | I28: =SUM(I23:I27) -> 0 | J28: =SUM(J23:J27) -> 4503324
B30: Total capital assets being depreciated, net | G30: =G20-G28 -> 3811440 | H30: =H20-H28 -> -247054 | I30: =I20-I28 -> 0 | J30: =J20-J28 -> 3564386
B32: Governmental activities capital assets, net | G32: =G30+G12 -> 4889045 | H32: =H30+H12 -> 343197 | I32: =I30+I12 -> 0 | J32: =J30+J12 -> 5232242 | K32: =SUM(K23:K26,K9:K10) -> 5232242

Sheet Beauregard
D1: BEAUREGARD PARISH POLICE JURY
D2: Capital Assets
D3: For the Year Ended December 31, 2013
I5: Beginning Balance | J5: Additions | K5: Deletions | L5: Transfers | M5: Ending Balance | N5: Cross Sectional
A7: Primary Government
A8: Government Activities:
A9: Capital assets, not being depreciated:
B10: Land | I10: 786565 | J10: 20170 | M10: =SUM(I10:L10) -> 806735 | N10: =SUM(M10) -> 806735
B11: Construction in progress | I11: 539166 | J11: 790379 | L11: -539166 | M11: =SUM(I11:L11) -> 790379 | N11: =SUM(M11) -> 790379
C12: Total assets not being depreciated | I12: =SUM(I10:I11) -> 1325731 | J12: =SUM(J10:J11) -> 810549 | K12: =SUM(K10:K11) -> 0 | L12: =SUM(L10:L11) -> -539166 | M12: =SUM(M10:M11) -> 1597114
A14: Capital assets being depreciated:
B15: Buildings and improvements | I15: 16309487 | J15: 960000 | L15: 539166 | M15: =SUM(I15:L15) -> 17808653
B16: Infrastructure | I16: 43048502 | J16: 55622 | K16: -4218 | M16: =SUM(I16:L16) -> 43099906
B17: Furniture and equipment | I17: 11649469 | J17: 709008 | K17: -548344 | M17: =SUM(I17:L17) -> 11810133
C18: Total capital assets being depreciated | I18: =SUM(I15:I17) -> 71007458 | J18: =SUM(J15:J17) -> 1724630 | K18: =SUM(K15:K17) -> -552562 | L18: =SUM(L15:L17) -> 539166 | M18: =SUM(M15:M17) -> 72718692
A20: Less accumulated depreciation for:
B21: Buildings and improvements | I21: -7438986 | J21: -438673 | M21: =SUM(I21:L21) -> -7877659 | N21: =SUM(M21,M15) -> 9930994
B22: Infrastructure | I22: -26036207 | J22: -1078870 | K22: 4218 | M22: =SUM(I22:L22) -> -27110859 | N22: =SUM(M22,M16) -> 15989047
B23: Furniture and equipment | I23: -7538686 | J23: -777266 | K23: 495822 | L23: 0 | M23: =SUM(I23:L23) -> -7820130 | N23: =M17+M23 -> 3990003
C24: Total accumulated depreciation | I24: =SUM(I21:I23) -> -41013879 | J24: =SUM(J21:J23) -> -2294809 | K24: =SUM(K21:K23) -> 500040 | L24: =SUM(L21:L23) -> 0 | M24: =SUM(M21:M23) -> -42808648
B25: Total capital assets being depreciated, net | I25: =I24+I18 -> 29993579 | J25: =J24+J18 -> -570179 | K25: =K24+K18 -> -52522 | L25: =L24+L18 -> 539166 | M25: =M24+M18 -> 29910044
B26: Governmental activities capital assets, net | I26: =I12+I25 -> 31319310 | J26: =J12+J25 -> 240370 | K26: =K12+K25 -> -52522 | L26: =L12+L25 -> 0 | M26: =M12+M25 -> 31507158 | N26: =SUM(N21:N23,N10:N11) -> 31507158

Sheet Bienville
D1: BIENVILLE PARISH POLICE JURY
D2: Capital Assets
D3: For the Year Ended December 31, 2013
G5: Beginning Balance | H5: Increases | I5: Decreases | J5: Ending Balance | K5: Cross Sectional
A7: Governmental Activities:
B8: Capital assets, not being depreciated:
C9: Land | G9: 660250 | J9: =SUM(G9:I9) -> 660250 | K9: =SUM(J9) -> 660250
C10: Construction in progress | G10: 10196359 | H10: 1837952 | I10: -12034311 | J10: =SUM(G10:I10) -> 0 | K10: =SUM(J10) -> 0
D12: Total capital assets, not being depreciated | G12: =SUM(G8:G11) -> 10856609 | H12: =SUM(H8:H11) -> 1837952 | I12: =SUM(I8:I11) -> -12034311 | J12: =SUM(J8:J11) -> 660250
A14: Capital assets being depreciated:
B15: Infrastructure:
C16: Roads | G16: 19856904 | H16: 1167236 | J16: =SUM(G16:I16) -> 21024140
C17: Bridges | G17: 1973698 | H17: 564000 | J17: =SUM(G17:I17) -> 2537698
B18: Buildings and improvements | G18: 4817522 | H18: 12034311 | I18: 0 | J18: =SUM(G18:I18) -> 16851833
B19: Office furniture and equipment | G19: 22519 | H19: 519145 | J19: =SUM(G19:I19) -> 541664
B20: Heavy equipment | G20: 1545021 | H20: 45541 | I20: -12566 | J20: =SUM(G20:I20) -> 1577996
B21: Vehicles | G21: 1219091 | H21: 314967 | I21: -139288 | J21: =SUM(G21:I21) -> 1394770
B22: Miscellaneous equipment | G22: 523698 | I22: -8960 | J22: =SUM(G22:I22) -> 514738
D24: Total capital assets being depreciated | G24: =SUM(G16:G22) -> 29958453 | H24: =SUM(H16:H22) -> 14645200 | I24: =SUM(I16:I22) -> -160814 | J24: =SUM(J16:J22) -> 44442839
A26: Less accumulated depreciation for:
B27: Infrastructure:
C28: Roads | G28: -14811392 | H28: -874354 | J28: =SUM(G28:I28) -> -15685746 | K28: =J16+J28 -> 5338394
C29: Bridges | G29: -1279334 | H29: -39480 | J29: =SUM(G29:I29) -> -1318814 | K29: =J17+J29 -> 1218884
B30: Buildings and improvements | G30: -2565179 | H30: -365514 | I30: 0 | J30: =SUM(G30:I30) -> -2930693 | K30: =J18+J30 -> 13921140
B31: Office furniture and equipment | G31: -22189 | H31: -104159 | J31: =SUM(G31:I31) -> -126348 | K31: =J19+J31 -> 415316
B32: Heavy equipment | G32: -1091356 | H32: -71214 | I32: 12566 | J32: =SUM(G32:I32) -> -1150004 | K32: =J20+J32 -> 427992
B33: Vehicles | G33: -749219 | H33: -99765 | I33: 139058 | J33: =SUM(G33:I33) -> -709926 | K33: =J21+J33 -> 684844
B34: Miscellaneous equipment | G34: -352897 | H34: -23155 | I34: 8670 | J34: =SUM(G34:I34) -> -367382 | K34: =J22+J34 -> 147356
D36: Total accumulated depreciation | G36: =SUM(G28:G34) -> -20871566 | H36: =SUM(H28:H34) -> -1577641 | I36: =SUM(I28:I34) -> 160294 | J36: =SUM(J28:J34) -> -22288913
B38: Total capital assets being depreciated, net | G38: =G36+G24 -> 9086887 | H38: =H36+H24 -> 13067559 | I38: =I36+I24 -> -520 | J38: =J36+J24 -> 22153926
B40: Governmental activities capital assets, net | G40: =G38+G12 -> 19943496 | H40: =H38+H12 -> 14905511 | I40: =I38+I12 -> -12034831 | J40: =J38+J12 -> 22814176 | K40: =SUM(K9:K34) -> 22814176

Sheet Bossier
D1: BOSSIER PARISH POLICE JURY
D2: Capital Assets
D3: For the Year Ended December 31, 2013
I5: Beginning Balance | J5: Transfers | K5: Additions | L5: Deletions | M5: Ending Balance | N5: Cross Sectional
A7: Primary Government
A8: Government Activities:
A9: Capital assets, not being depreciated:
B10: Land | I10: 11633324 | J10: 0 | K10: 573760 | M10: =SUM(I10:L10) -> 12207084 | N10: =SUM(M10) -> 12207084
B11: Construction in progress | I11: 11307751 | J11: -7862502 | K11: 2597030 | M11: =SUM(I11:L11) -> 6042279 | N11: =SUM(M11) -> 6042279
C12: Total assets not being depreciated | I12: =SUM(I10:I11) -> 22941075 | J12: =SUM(J10:J11) -> -7862502 | K12: =SUM(K10:K11) -> 3170790 | L12: =SUM(L10:L11) -> 0 | M12: =SUM(M10:M11) -> 18249363
A14: Capital assets being depreciated:
B15: Buildings and improvements | I15: 107381194 | J15: 262706 | K15: 416159 | M15: =SUM(I15:L15) -> 108060059
B16: Infrastructure | I16: 201825504 | J16: 7599796 | K16: 10826090 | M16: =SUM(I16:L16) -> 220251390
B17: Furniture, equipment and vehicles | I17: 10240517 | K17: 613900 | L17: -278841 | M17: =SUM(I17:L17) -> 10575576
B18: Library books and information material | I18: 4156868 | K18: 474808 | M18: =SUM(I18:L18) -> 4631676
C19: Total capital assets being depreciated | I19: =SUM(I15:I18) -> 323604083 | J19: =SUM(J15:J18) -> 7862502 | K19: =SUM(K15:K18) -> 12330957 | L19: =SUM(L15:L18) -> -278841 | M19: =SUM(M15:M18) -> 343518701
A21: Less accumulated depreciation for:
B22: Buildings and improvements | I22: -21419002 | K22: -2606481 | L22: 0 | M22: =SUM(I22:L22) -> -24025483 | N22: =SUM(M22,M15) -> 84034576
B23: Infrastructure | I23: -41327651 | K23: -5376036 | L23: 0 | M23: =SUM(I23:L23) -> -46703687 | N23: =SUM(M23,M16) -> 173547703
B24: Furniture, equipment and vehicles | I24: -5797114 | K24: -685150 | L24: 273741 | M24: =SUM(I24:L24) -> -6208523 | N24: =SUM(M24,M17) -> 4367053
B25: Library books and information material | I25: -3163340 | K25: -363564 | L25: 0 | M25: =SUM(I25:L25) -> -3526904 | N25: =M18+M25 -> 1104772
C26: Total accumulated depreciation | I26: =SUM(I22:I25) -> -71707107 | J26: =SUM(J22:J25) -> 0 | K26: =SUM(K22:K25) -> -9031231 | L26: =SUM(L22:L25) -> 273741 | M26: =SUM(M22:M25) -> -80464597
B27: Total capital assets being depreciated, net | I27: =I26+I19 -> 251896976 | J27: =J26+J19 -> 7862502 | K27: =K26+K19 -> 3299726 | L27: =L26+L19 -> -5100 | M27: =M26+M19 -> 263054104
B28: Governmental activities capital assets, net | I28: =I12+I27 -> 274838051 | J28: =J12+J27 -> 0 | K28: =K12+K27 -> 6470516 | L28: =L12+L27 -> -5100 | M28: =M12+M27 -> 281303467 | N28: =SUM(N22:N25,N10:N11) -> 281303467
I31: Beginning Balance | J31: Transfers | K31: Additions | L31: Deletions | M31: Ending Balance
A33: Business-type Activities:
A34: Capital assets not being depreciated:
B35: Land | I35: 1261868 | J35: 0 | K35: 39910 | L35: 0 | M35: =SUM(I35:L35) -> 1301778 | N35: =SUM(M35) -> 1301778
B36: Goodwill | I36: 1226000 | M36: =SUM(I36:L36) -> 1226000 | N36: =M36 -> 1226000
B37: Construction in progress | I37: 2371730 | K37: 908068 | M37: =SUM(I37:L37) -> 3279798 | N37: =SUM(M37) -> 3279798
C38: Total assets not being depreciated | I38: =SUM(I35:I37) -> 4859598 | J38: =SUM(J35:J37) -> 0 | K38: =SUM(K35:K37) -> 947978 | L38: =SUM(L35:L37) -> 0 | M38: =SUM(M35:M37) -> 5807576
A40: Capital assets being depreciated:
B41: Furniture, equipment and vehicles | I41: 23293000 | J41: 0 | K41: 0 | L41: 0 | M41: =SUM(I41:L41) -> 23293000
B42: Buildings and improvements | I42: 11488000 | J42: 939000 | K42: -93000 | L42: 0 | M42: =SUM(I42:L42) -> 12334000
C43: Total capital assets being depreciated | I43: =SUM(I41:I42) -> 34781000 | J43: =SUM(J41:J42) -> 939000 | K43: =SUM(K41:K42) -> -93000 | L43: =SUM(L41:L42) -> 0 | M43: =SUM(M41:M42) -> 35627000
A45: Less accumulated depreciation for:
B46: Furniture, equipment and vehicles | I46: -9558000 | J46: -434000 | K46: 0 | L46: 0 | M46: =SUM(I46:L46) -> -9992000 | N46: =SUM(M46,M41) -> 13301000
B47: Buildings and improvements | I47: -8378000 | J47: -1186000 | K47: 93000 | L47: 0 | M47: =SUM(I47:L47) -> -9471000 | N47: =SUM(M47,M42) -> 2863000
C48: Total accumulated depreciation | I48: =SUM(I46:I47) -> -17936000 | J48: =SUM(J46:J47) -> -1620000 | K48: =SUM(K46:K47) -> 93000 | L48: =SUM(L46:L47) -> 0 | M48: =SUM(M46:M47) -> -19463000
B49: Total capital assets being depreciated, net | I49: =SUM(I48,I43) -> 16845000 | J49: =SUM(J48,J43) -> -681000 | K49: =SUM(K48,K43) -> 0 | L49: =SUM(L48,L43) -> 0 | M49: =SUM(M48,M43) -> 16164000
B50: Business-type activities capital assets, net | I50: =I38+I49 -> 21704598 | J50: =J38+J49 -> -681000 | K50: =K38+K49 -> 947978 | L50: =L38+L49 -> 0 | M50: =M38+M49 -> 21971576 | N50: =SUM(N46:N47,N35:N37) -> 21971576

Sheet Caddo
D1: CADDO PARISH POLICE JURY
D2: Capital Assets
D3: For the Year Ended December 31, 2013
I5: Beginning Balance | J5: Prior Period Adjustment | K5: Additions | L5: Deletions | M5: Ending Balance | N5: Cross Sectional
A7: Primary Government
A8: Government Activities:
A9: Capital assets, not being depreciated:
B10: Land and land improvements | I10: 14587873 | J10: -10612 | K10: 8410 | L10: -7262 | M10: =SUM(I10:L10) -> 14578409 | N10: =SUM(M10) -> 14578409
B11: Construction in progress - Infrastructure | I11: 1490456 | K11: 3926421 | L11: -5206264 | M11: =SUM(I11:L11) -> 210613 | N11: =M11 -> 210613
B12: Construction in progress | I12: 11194813 | K12: 3654638 | L12: -1077180 | M12: =SUM(I12:L12) -> 13772271 | N12: =SUM(M12) -> 13772271
C13: Total assets not being depreciated | I13: =SUM(I10:I12) -> 27273142 | J13: =SUM(J10:J12) -> -10612 | K13: =SUM(K10:K12) -> 7589469 | L13: =SUM(L10:L12) -> -6290706 | M13: =SUM(M10:M12) -> 28561293
A15: Capital assets being depreciated:
B16: Buildings and structures | I16: 89670371 | K16: 209580 | L16: -14742 | M16: =SUM(I16:L16) -> 89865209
B17: Equipment and vehicles | I17: 36255276 | K17: 3680568 | L17: -1631252 | M17: =SUM(I17:L17) -> 38304592
B18: Infrastructure | I18: 377842136 | J18: -875719 | K18: 10230871 | L18: -555242 | M18: =SUM(I18:L18) -> 386642046
C19: Total capital assets being depreciated | I19: =SUM(I16:I18) -> 503767783 | J19: =SUM(J16:J18) -> -875719 | K19: =SUM(K16:K18) -> 14121019 | L19: =SUM(L16:L18) -> -2201236 | M19: =SUM(M16:M18) -> 514811847
A21: Less accumulated depreciation for:
B22: Buildings and structures | I22: -34803394 | K22: -2184659 | L22: 12531 | M22: =SUM(I22:L22) -> -36975522 | N22: =SUM(M22,M16) -> 52889687
B23: Equipment and vehicles | I23: -25304064 | K23: -2765310 | L23: 1616376 | M23: =SUM(I23:L23) -> -26452998 | N23: =SUM(M23,M17) -> 11851594
B24: Infrastructure | I24: -257070930 | J24: -1495833 | K24: -11108932 | L24: 0 | M24: =SUM(I24:L24) -> -269675695 | N24: =M18+M24 -> 116966351
C25: Total accumulated depreciation | I25: =SUM(I22:I24) -> -317178388 | J25: =SUM(J22:J24) -> -1495833 | K25: =SUM(K22:K24) -> -16058901 | L25: =SUM(L22:L24) -> 1628907 | M25: =SUM(M22:M24) -> -333104215
B26: Total capital assets being depreciated, net | I26: =I25+I19 -> 186589395 | J26: =J25+J19 -> -2371552 | K26: =K25+K19 -> -1937882 | L26: =L25+L19 -> -572329 | M26: =M25+M19 -> 181707632
B27: Governmental activities capital assets, net | I27: =I13+I26 -> 213862537 | J27: =J13+J26 -> -2382164 | K27: =K13+K26 -> 5651587 | L27: =L13+L26 -> -6863035 | M27: =M13+M26 -> 210268925 | N27: =SUM(N22:N24,N10:N12) -> 210268925

Sheet Calcasieu
D1: CALCASIEU PARISH POLICE JURY
D2: Capital Assets
D3: For the Year Ended December 31, 2013
I5: Balance 1/1/2013 | J5: Additions | K5: Deletions | L5: Balance 12/31/2013 | M5: Cross Sectional
A7: Governmental Activities:
B8: Capital assets, not being depreciated:
C9: Land and right-of-ways | I9: 16832923 | J9: 711623 | L9: =SUM(I9:K9) -> 17544546 | M9: =SUM(L9) -> 17544546
C10: Construction in progress | I10: 23845079 | J10: 12115481 | K10: -19108040 | L10: =SUM(I10:K10) -> 16852520 | M10: =SUM(L10) -> 16852520
C11: Roads | I11: 382296012 | J11: 1021270 | L11: =SUM(I11:K11) -> 383317282 | M11: =SUM(L11) -> 383317282
D12: Total capital assets, not being depreciated | I12: =SUM(I8:I11) -> 422974014 | J12: =SUM(J8:J11) -> 13848374 | K12: =SUM(K8:K11) -> -19108040 | L12: =SUM(L8:L11) -> 417714348
A14: Capital assets being depreciated:
B15: Buildings and improvements | I15: 122300990 | J15: 5892103 | K15: -411314 | L15: =SUM(I15:K15) -> 127781779
B16: Machinery and equipment | I16: 30856097 | J16: 4406050 | K16: -2193615 | L16: =SUM(I16:K16) -> 33068532
B17: Bridges | I17: 11887348 | L17: =SUM(I17:K17) -> 11887348
D18: Total capital assets being depreciated | I18: =SUM(I15:I17) -> 165044435 | J18: =SUM(J15:J17) -> 10298153 | K18: =SUM(K15:K17) -> -2604929 | L18: =SUM(L15:L17) -> 172737659
A20: Less accumulated depreciation for:
B21: Buildings and improvements | I21: -51800073 | J21: -3362407 | K21: 59555 | L21: =SUM(I21:K21) -> -55102925 | M21: =SUM(L21,L15) -> 72678854
B22: Machinery and equipment | I22: -20158778 | J22: -2976760 | K22: 2182803 | L22: =SUM(I22:K22) -> -20952735 | M22: =SUM(L22,L16) -> 12115797
B23: Bridges | I23: -3689827 | J23: -263075 | L23: =SUM(I23:K23) -> -3952902 | M23: =SUM(L23,L17) -> 7934446
D24: Total accumulated depreciation | I24: =SUM(I21:I23) -> -75648678 | J24: =SUM(J21:J23) -> -6602242 | K24: =SUM(K21:K23) -> 2242358 | L24: =SUM(L21:L23) -> -80008562
B25: Total capital assets being depreciated, net | I25: =I18+I24 -> 89395757 | J25: =J18+J24 -> 3695911 | K25: =K18+K24 -> -362571 | L25: =L18+L24 -> 92729097
B26: Total governmental activities capital assets, net | I26: =I24+I18+I12 -> 512369771 | J26: =J24+J18+J12 -> 17544285 | K26: =K24+K18+K12 -> -19470611 | L26: =L24+L18+L12 -> 510443445 | M26: =SUM(M21:M23,M9:M11) -> 510443445
I29: Balance 1/1/2013 | J29: Decreases | K29: Adjustments | L29: Balance 12/31/2013
A30: Business-Type Activities:
B31: Capital assets, not being depreciated:
C32: Land and right-of-ways | I32: 227920 | L32: =SUM(I32:K32) -> 227920 | M32: =SUM(L32) -> 227920
C33: Construction in progress | I33: 91303 | J33: 904198 | K33: -276681 | L33: =SUM(I33:K33) -> 718820 | M33: =SUM(L33) -> 718820
D34: Total capital assets, not being depreciated | I34: =SUM(I31:I33) -> 319223 | J34: =SUM(J31:J33) -> 904198 | K34: =SUM(K31:K33) -> -276681 | L34: =SUM(L31:L33) -> 946740
A36: Capital assets being depreciated:
B37: Non-Building improvements | I37: 10043068 | J37: 175351 | L37: =SUM(I37:K37) -> 10218419
B38: Building and improvements | I38: 100350 | J38: 3043 | L38: =SUM(I38:K38) -> 103393
B39: Infrastructure | I39: 3016772 | J39: 103515 | L39: =SUM(I39:K39) -> 3120287
B40: Machinery and equipment | I40: 512284 | J40: 5667 | K40: -274386 | L40: =SUM(I40:K40) -> 243565
D41: Total capital assets being depreciated | I41: =SUM(I37:I40) -> 13672474 | J41: =SUM(J37:J40) -> 287576 | K41: =SUM(K37:K40) -> -274386 | L41: =SUM(L37:L40) -> 13685664
A43: Less accumulated depreciation for:
B44: Non-Building improvements | I44: -3057985 | J44: -279601 | L44: =SUM(I44:K44) -> -3337586 | M44: =SUM(L44,L37) -> 6880833
B45: Building and improvements | I45: -81008 | J45: -2065 | L45: =SUM(I45:K45) -> -83073 | M45: =SUM(L45,L38) -> 20320
B46: Infrastructure | I46: -1634374 | J46: -125269 | L46: =SUM(I46:K46) -> -1759643 | M46: =SUM(L46,L39) -> 1360644
B47: Machinery and equipment | I47: -467117 | J47: -12112 | K47: 274386 | L47: =SUM(I47:K47) -> -204843 | M47: =SUM(L47,L40) -> 38722
D48: Total accumulated depreciation | I48: =SUM(I44:I47) -> -5240484 | J48: =SUM(J44:J47) -> -419047 | K48: =SUM(K44:K47) -> 274386 | L48: =SUM(L44:L47) -> -5385145
B49: Total capital assets being depreciated, net | I49: =I41+I48 -> 8431990 | J49: =J41+J48 -> -131471 | K49: =K41+K48 -> 0 | L49: =L41+L48 -> 8300519
B50: Total business-type activities capital assets, net | I50: =I48+I41+I34 -> 8751213 | J50: =J48+J41+J34 -> 772727 | K50: =K48+K41+K34 -> -276681 | L50: =SUM(I50:K50) -> 9247259 | M50: =SUM(M44:M47,M32:M32,M33) -> 9247259

Sheet Caldwell
D1: CALDWELL PARISH POLICE JURY
D2: Capital Assets
D3: For the Year Ended December 31, 2013
G5: Beginning Balance | H5: Increases | I5: Decreases | J5: Ending Balance | K5: Cross Sectional
A7: Governmental Activities:
B8: Capital assets, not being depreciated:
C9: Land | G9: 420095 | J9: =SUM(G9:I9) -> 420095 | K9: =SUM(J9) -> 420095
C10: Construction in progress | G10: 7412928 | H10: 519426 | J10: =SUM(G10:I10) -> 7932354 | K10: =SUM(J10) -> 7932354
D12: Total capital assets, not being depreciated | G12: =SUM(G8:G11) -> 7833023 | H12: =SUM(H8:H11) -> 519426 | I12: =SUM(I8:I11) -> 0 | J12: =SUM(J8:J11) -> 8352449
A14: Capital assets being depreciated: | N14: =Caldwell!K30 -> 935
B15: Infrastructure:
C16: Roads | G16: 47897858 | J16: =SUM(G16:I16) -> 47897858
C17: Bridges | G17: 642997 | J17: =SUM(G17:I17) -> 642997
B18: Buildings and improvements | G18: 2914289 | H18: 63454 | I18: 0 | J18: =SUM(G18:I18) -> 2977743
B19: Land improvements | G19: 716214 | J19: =SUM(G19:I19) -> 716214
B20: Heavy equipment | G20: 1348353 | H20: 111861 | J20: =SUM(G20:I20) -> 1460214
B21: Vehicles | G21: 1158700 | H21: 28527 | J21: =SUM(G21:I21) -> 1187227
B22: Public works equipment | G22: 283107 | H22: 2599 | J22: =SUM(G22:I22) -> 285706
B23: Office furniture and equipment | G23: 577716 | J23: =SUM(G23:I23) -> 577716
D25: Total capital assets being depreciated | G25: =SUM(G16:G23) -> 55539234 | H25: =SUM(H16:H23) -> 206441 | I25: =SUM(I16:I23) -> 0 | J25: =SUM(J16:J23) -> 55745675
A27: Less accumulated depreciation for:
B28: Infrastructure:
C29: Roads | G29: -46001271 | H29: -149992 | J29: =SUM(G29:I29) -> -46151263 | K29: =J16+J29 -> 1746595
C30: Bridges | G30: -642014 | H30: -48 | J30: =SUM(G30:I30) -> -642062 | K30: =J17+J30 -> 935
B31: Buildings and improvements | G31: -2585383 | H31: -16226 | I31: 0 | J31: =SUM(G31:I31) -> -2601609 | K31: =J18+J31 -> 376134
B32: Land improvements | G32: -155374 | H32: -30960 | J32: =SUM(G32:I32) -> -186334 | K32: =J19+J32 -> 529880
B33: Heavy equipment | G33: -1122896 | H33: -46857 | J33: =SUM(G33:I33) -> -1169753 | K33: =J20+J33 -> 290461
B34: Vehicles | G34: -1008367 | H34: -65499 | J34: =SUM(G34:I34) -> -1073866 | K34: =J21+J34 -> 113361
B35: Public works equipment | G35: -80043 | H35: -25467 | J35: =SUM(G35:I35) -> -105510 | K35: =J22+J35 -> 180196
B36: Office furniture and equipment | G36: -413330 | H36: -35231 | J36: =SUM(G36:I36) -> -448561 | K36: =J23+J36 -> 129155
D38: Total accumulated depreciation | G38: =SUM(G29:G36) -> -52008678 | H38: =SUM(H29:H36) -> -370280 | I38: =SUM(I29:I36) -> 0 | J38: =SUM(J29:J36) -> -52378958
B40: Total capital assets being depreciated, net | G40: =G38+G25 -> 3530556 | H40: =H38+H25 -> -163839 | I40: =I38+I25 -> 0 | J40: =J38+J25 -> 3366717
B42: Governmental activities capital assets, net | G42: =G40+G12 -> 11363579 | H42: =H40+H12 -> 355587 | I42: =I40+I12 -> 0 | J42: =J40+J12 -> 11719166 | K42: =SUM(K9:K36) -> 11719166

Sheet Cameron
D1: CAMERON PARISH POLICE JURY
D2: Capital Assets
D3: For the Year Ended December 31, 2013
G5: Beginning Balance | H5: Increases | I5: Decreases | J5: Ending Balance | K5: Cross Sectional
C7: Land | G7: 1381390 | J7: =SUM(G7:I7) -> 1381390 | K7: =J7 -> 1381390
C8: Construction in progress | G8: 9198240 | H8: 15405895 | I8: -3808770 | J8: =SUM(G8:I8) -> 20795365 | K8: =J8 -> 20795365 | M8: Depreciation
B9: Buildings and improvements | G9: 35278285 | H9: 158249 | I9: 0 | J9: =SUM(G9:I9) -> 35436534 | K9: =J9-M9 -> 29213490 | L9: =J9/M14 -> 0.32612693 | M9: =J16*L9 -> 6223044.2
B10: Books and videos | G10: 702647 | J10: =SUM(G10:I10) -> 702647 | K10: =J10-M10 -> 579254.48 | L10: =J10/M14 -> 0.0064665497 | M10: =J16*L10 -> 123392.52
B11: Equipment and furniture | G11: 17493034 | H11: 1214585 | I11: -563297 | J11: =SUM(G11:I11) -> 18144322 | K11: =J11-M11 -> 14957980 | L11: =J11/M14 -> 0.1669845 | M11: =J16*L11 -> 3186342
B12: Infrastructure | G12: 50724694 | H12: 3650521 | I12: 0 | J12: =SUM(G12:I12) -> 54375215 | K12: =J12-M12 -> 44826331 | L12: =J12/M14 -> 0.50042202 | M12: =J16*L12 -> 9548884.3
M13: Total capital assets being depreciated
D14: Total capital assets being depreciated | G14: =SUM(G7:G12) -> 114778290 | H14: =SUM(H7:H12) -> 20429250 | I14: =SUM(I7:I12) -> -4372067 | J14: =SUM(J7:J12) -> 130835473 | L14: =SUM(L9:L12) -> 1 | M14: =+J9+J10+J11++J12 -> 108658718
A16: Less accumulated depreciation | G16: 15476036 | H16: 4168924 | I16: -563297 | J16: =SUM(G16:I16) -> 19081663
B18: Total capital assets being depreciated, net | G18: =G14-G16 -> 99302254 | H18: =H14-H16 -> 16260326 | I18: =I14-I16 -> -3808770 | J18: =J14-J16 -> 111753810 | K18: =SUM(K7:K12) -> 111753810

Sheet Catahoula
D1: CATAHOULA PARISH POLICE JURY
D2: Capital Assets
D3: For the Year Ended December 31, 2013
I5: Beginning Balance | J5: Increases | K5: Decreases | L5: Ending Balance | M5: Cross Sectional
A7: Governmental Activities:
B8: Capital assets, not being depreciated:
C9: Land | I9: 112200 | K9: 0 | L9: =SUM(I9:K9) -> 112200 | M9: =SUM(L9) -> 112200
C10: Construction in progress | L10: =SUM(I10:K10) -> 0 | M10: =SUM(L10) -> 0
D12: Total capital assets, not being depreciated | I12: =SUM(I8:I11) -> 112200 | J12: =SUM(J8:J11) -> 0 | K12: =SUM(K8:K11) -> 0 | L12: =SUM(L8:L11) -> 112200
A14: Capital assets being depreciated:
B15: Infrastructure - roads and bridges | I15: 11318548 | J15: 70926 | L15: =SUM(I15:K15) -> 11389474
B16: Buildings | I16: 2983414 | K16: 0 | L16: =SUM(I16:K16) -> 2983414
B17: Improvements | I17: 1558229 | L17: =SUM(I17:K17) -> 1558229
B18: Equipment | I18: 1464919 | J18: 87117 | K18: -80450 | L18: =SUM(I18:K18) -> 1471586
B19: Heavy equipment | I19: 892178 | J19: 33895 | L19: =SUM(I19:K19) -> 926073
B20: Vehicles | I20: 441923 | J20: 108476 | L20: =SUM(I20:K20) -> 550399
B21: Books and periodicals | I21: 669345 | J21: 38586 | K21: -17046 | L21: =SUM(I21:K21) -> 690885
D23: Total capital assets being depreciated | I23: =SUM(I15:I21) -> 19328556 | J23: =SUM(J15:J21) -> 339000 | K23: =SUM(K15:K21) -> -97496 | L23: =SUM(L15:L21) -> 19570060
A25: Less accumulated depreciation for:
B26: Infrastructure - roads and bridges | I26: 8256786 | J26: 111334 | L26: =SUM(I26:K26) -> 8368120 | M26: =L15-L26 -> 3021354
B27: Buildings | I27: 2531257 | J27: 22306 | K27: 0 | L27: =SUM(I27:K27) -> 2553563 | M27: =L16-L27 -> 429851
B28: Improvements | I28: 149509 | J28: 64696 | K28: -80450 | L28: =SUM(I28:K28) -> 133755 | M28: =L17-L28 -> 1424474
B29: Equipment | I29: 1140465 | J29: 80953 | L29: =SUM(I29:K29) -> 1221418 | M29: =L18-L29 -> 250168
B30: Heavy equipment | I30: 574687 | J30: 55392 | L30: =SUM(I30:K30) -> 630079 | M30: =L19-L30 -> 295994
B31: Vehicles | I31: 253712 | J31: 46489 | L31: =SUM(I31:K31) -> 300201 | M31: =L20-L31 -> 250198
B32: Books and periodicals | I32: 601853 | J32: 27501 | K32: -17046 | L32: =SUM(I32:K32) -> 612308 | M32: =L21-L32 -> 78577
D34: Total accumulated depreciation | I34: =SUM(I26:I32) -> 13508269 | J34: =SUM(J26:J32) -> 408671 | K34: =SUM(K26:K32) -> -97496 | L34: =SUM(L26:L32) -> 13819444
B36: Total capital assets being depreciated, net | I36: =I23-I34 -> 5820287 | J36: =J23-J34 -> -69671 | K36: =K23-K34 -> 0 | L36: =L23-L34 -> 5750616
B38: Governmental activities capital assets, net | I38: =I36+I12 -> 5932487 | J38: =J36+J12 -> -69671 | K38: =K36+K12 -> 0 | L38: =L36+L12 -> 5862816 | M38: =SUM(M9:M32,) -> 5862816
I41: Beginning Balance | J41: Increases | K41: Decreases | L41: Ending Balance
A42: Business-Type Activities:
B43: Capital assets, not being depreciated:
C44: Land | J44: 0 | K44: 0 | L44: =SUM(I44:K44) -> 0 | M44: =SUM(L44) -> 0
C45: Construction in progress | K45: 0 | L45: =SUM(I45:K45) -> 0 | M45: =SUM(L45) -> 0
D47: Total capital assets, not being depreciated | I47: =SUM(I43:I46) -> 0 | J47: =SUM(J43:J46) -> 0 | K47: =SUM(K43:K46) -> 0 | L47: =SUM(L43:L46) -> 0
B49: Capital assets, depreciable:
C50: Buildings and improvements | I50: 88375 | K50: 0 | L50: =SUM(I50:K50) -> 88375
C51: Office furniture and equipment | I51: 74150 | K51: 0 | L51: =SUM(I51:K51) -> 74150
D53: Total capital assets, depreciable | I53: =SUM(I49:I51) -> 162525 | J53: =SUM(J49:J51) -> 0 | K53: =SUM(K49:K51) -> 0 | L53: =SUM(L49:L51) -> 162525
B55: Less accumulated depreciation for:
C56: Buildings and improvements | I56: 24855 | J56: 2209 | L56: =SUM(I56:K56) -> 27064 | M56: =L50-L56 -> 61311
C57: Office furniture and equipment | I57: 43568 | J57: 3277 | L57: =SUM(I57:K57) -> 46845 | M57: =L51-L57 -> 27305
D59: Total accumulated depreciation | I59: =SUM(I56:I57) -> 68423 | J59: =SUM(J56:J57) -> 5486 | K59: =SUM(K56:K57) -> 0 | L59: =SUM(L56:L57) -> 73909
D61: Total capital assets, depreciable, net | I61: =I53-I59 -> 94102 | J61: =J53-J59 -> -5486 | K61: =K53+K59 -> 0 | L61: =L53-L59 -> 88616
D63: Business-type activities capital assets, net | I63: =I61+I47 -> 94102 | J63: =J61+J47 -> -5486 | K63: =K61+K47 -> 0 | L63: =L61+L47 -> 88616 | M63: =SUM(M56:M57,M44:M45) -> 88616

Sheet Claiborne
D1: CLAIBORNE PARISH POLICE JURY
D2: Capital Assets
D3: For the Year Ended December 31, 2013
G5: Beginning Balance | H5: Adjustments | I5: Additions | J5: Deletions | K5: Ending Balance | L5: Cross Sectional
A7: Governmental Activities:
B8: Capital assets, not being depreciated:
C9: Land:
D10: Police jury | G10: 49900 | K10: =SUM(G10:J10) -> 49900 | L10: =SUM(K10) -> 49900
D11: Library | H11: 3580 | K11: =SUM(G11:J11) -> 3580 | L11: =SUM(K11) -> 3580
D12: Office of community services | G12: 30000 | K12: =SUM(G12:J12) -> 30000 | L12: =SUM(K12) -> 30000
D13: Adjudicated property | G13: 15360 | K13: =SUM(G13:J13) -> 15360 | L13: =SUM(K13) -> 15360
C14: Construction in progress | G14: 235496 | H14: -3580 | I14: 2109471 | K14: =SUM(G14:J14) -> 2341387 | L14: =SUM(K14) -> 2341387
D16: Total capital assets, not being depreciated | G16: =SUM(G10:G14) -> 330756 | H16: =SUM(H10:H14) -> 0 | I16: =SUM(I10:I14) -> 2109471 | J16: =SUM(J10:J14) -> 0 | K16: =SUM(K10:K14) -> 2440227
A18: Capital assets being depreciated: | O18: =Caldwell!K30 -> 935
B19: Infrastructure:
C20: Roads | G20: 15517189 | K20: =SUM(G20:J20) -> 15517189
C21: Bridges | G21: 1912668 | K21: =SUM(G21:J21) -> 1912668
B22: Land improvements | G22: 15995 | I22: 0 | K22: =SUM(G22:J22) -> 15995
B23: Buildings and improvements | G23: 2549623 | K23: =SUM(G23:J23) -> 2549623
B24: Public works heavy equipment | G24: 2705883 | I24: 225117 | J24: -81315 | K24: =SUM(G24:J24) -> 2849685
B25: Public works other equipment | G25: 82575 | K25: =SUM(G25:J25) -> 82575
B26: Vehicles | G26: 201599 | I26: 46198 | J26: -15350 | K26: =SUM(G26:J26) -> 232447
B27: Office furniture and equipment | G27: 249691 | K27: =SUM(G27:J27) -> 249691
B28: Office of emergency preparedness and homeland security:
C29: Vehicles | G29: 45517 | K29: =SUM(G29:J29) -> 45517
C30: Office furniture and equipment | G30: 50506 | K30: =SUM(G30:J30) -> 50506
C31: Buildings and improvements | G31: 13205 | K31: =SUM(G31:J31) -> 13205
B32: Office of community services:
C33: Land improvements | G33: 7800 | K33: =SUM(G33:J33) -> 7800
C34: Buildings and improvements | G34: 62156 | K34: =SUM(G34:J34) -> 62156
C35: Vehicles | G35: 430873 | I35: 44620 | J35: -22530 | K35: =SUM(G35:J35) -> 452963
C36: Office furniture and equipment | G36: 116327 | K36: =SUM(G36:J36) -> 116327
B37: Library:
C38: Buildings and improvements | G38: 797365 | J38: -6999 | K38: =SUM(G38:J38) -> 790366
C39: Vehicle | G39: 49901 | K39: =SUM(G39:J39) -> 49901
C40: Furniture and equipment | G40: 91746 | I40: 37009 | J40: -32601 | K40: =SUM(G40:J40) -> 96154
C41: Books and videos | G41: 771167 | I41: 29537 | J41: -40881 | K41: =SUM(G41:J41) -> 759823
D43: Total capital assets being depreciated | G43: =SUM(G20:G41) -> 25671786 | H43: =SUM(H20:H41) -> 0 | I43: =SUM(I20:I41) -> 382481 | J43: =SUM(J20:J41) -> -199676 | K43: =SUM(K20:K41) -> 25854591
A45: Less accumulated depreciation for:
B46: Infrastructure:
C47: Roads | G47: 14338755 | I47: 37255 | K47: =SUM(G47:J47) -> 14376010 | L47: =K20-K47 -> 1141179
C48: Bridges | G48: 1171761 | I48: 42692 | K48: =SUM(G48:J48) -> 1214453 | L48: =K21-K48 -> 698215
B49: Land improvements | G49: 13263 | I49: 800 | K49: =SUM(G49:J49) -> 14063 | L49: =K22-K49 -> 1932
B50: Buildings and improvements | G50: 1624627 | I50: 57209 | K50: =SUM(G50:J50) -> 1681836 | L50: =K23-K50 -> 867787
B51: Public works heavy equipment | G51: 1647131 | I51: 170514 | J51: -73432 | K51: =SUM(G51:J51) -> 1744213 | L51: =K24-K51 -> 1105472
B52: Public works other equipment | G52: 55031 | I52: 3200 | K52: =SUM(G52:J52) -> 58231 | L52: =K25-K52 -> 24344
B53: Vehicles | G53: 84438 | I53: 26068 | J53: -9722 | K53: =SUM(G53:J53) -> 100784 | L53: =K26-K53 -> 131663
B54: Office furniture and equipment | G54: 61005 | I54: 23913 | K54: =SUM(G54:J54) -> 84918 | L54: =K27-K54 -> 164773
B55: Office of emergency preparedness and homeland security: | L55: =K28-K55 -> 0
C56: Vehicles | G56: 41137 | H56: -2983 | I56: 5522 | K56: =SUM(G56:J56) -> 43676 | L56: =K29-K56 -> 1841
C57: Office furniture and equipment | G57: 35545 | H57: 130 | I57: 9833 | K57: =SUM(G57:J57) -> 45508 | L57: =K30-K57 -> 4998
C58: Buildings and improvements | G58: 2365 | I58: 660 | K58: =SUM(G58:J58) -> 3025 | L58: =K31-K58 -> 10180
B59: Office of community services: | L59: =K32-K59 -> 0
C60: Land improvements | G60: 8255 | H60: -455 | K60: =SUM(G60:J60) -> 7800 | L60: =K33-K60 -> 0
C61: Buildings and improvements | G61: 42647 | I61: 2072 | K61: =SUM(G61:J61) -> 44719 | L61: =K34-K61 -> 17437
C62: Vehicles | G62: 381138 | I62: 29991 | J62: -22530 | K62: =SUM(G62:J62) -> 388599 | L62: =K35-K62 -> 64364
C63: Office furniture and equipment | G63: 107136 | H63: -450 | K63: =SUM(G63:J63) -> 106686 | L63: =K36-K63 -> 9641
B64: Library: | L64: =K37-K64 -> 0
C65: Buildings and improvements | G65: 439585 | I65: 21587 | J65: -1575 | K65: =SUM(G65:J65) -> 459597 | L65: =K38-K65 -> 330769
C66: Vehicles | G66: 49901 | K66: =SUM(G66:J66) -> 49901 | L66: =K39-K66 -> 0
C67: Furniture and equipment | G67: 73379 | I67: 7182 | J67: -29392 | K67: =SUM(G67:J67) -> 51169 | L67: =K40-K67 -> 44985
C68: Books and videos | G68: 734660 | H68: -7657 | I68: 73701 | J68: -40881 | K68: =SUM(G68:J68) -> 759823 | L68: =K41-K68 -> 0
D70: Total accumulated depreciation | G70: =SUM(G47:G68) -> 20911759 | H70: =SUM(H47:H68) -> -11415 | I70: =SUM(I47:I68) -> 512199 | K70: =SUM(K47:K68) -> 21235011
B72: Total capital assets being depreciated, net | G72: =G43-G70 -> 4760027 | H72: =H43-H70 -> 11415 | I72: =I43-I70 -> -129718 | J72: =J43-J70 -> -199676 | K72: =K43-K70 -> 4619580
B74: Governmental activities capital assets, net | G74: =G72+G16 -> 5090783 | H74: =H72+H16 -> 11415 | I74: =I72+I16 -> 1979753 | K74: =K72+K16 -> 7059807 | L74: =SUM(L10:L68) -> 7059807

Sheet Concordia
D1: CONCORDIA PARISH POLICE JURY
D2: Capital Assets
D3: For the Year Ended December 31, 2013
G5: Balance at January 1, 2013 | H5: Reclassification | I5: Additions | J5: Retirements | K5: Balance December 12, 2013 | L5: Cross Sectional
A7: Governmental Activities:
B8: Land - nondepreciable | G8: 7038 | K8: =SUM(G8:J8) -> 7038 | L8: =K8 -> 7038
B9: Depreciable assets: | N9: % of Depreciable Assets | O9: Accumulated Depreciation
C10: Buildings | G10: 5522117 | H10: 23394 | I10: 383639 | K10: =SUM(G10:J10) -> 5929150 | N10: =K10/K16 -> 0.26803184 | O10: =K24*N10 -> -3003986.4
C11: Furniture and fixtures | G11: 441519 | K11: =SUM(G11:J11) -> 441519 | N11: =K11/K16 -> 0.01995921 | O11: =K24*N11 -> -223694.3
C12: Machinery and equipment | G12: 2416110 | I12: 89142 | K12: =SUM(G12:J12) -> 2505252 | N12: =K12/K16 -> 0.11325187 | O12: =K24*N12 -> -1269278.6
C13: Transportation equipment | G13: 1028979 | I13: 20708 | K13: =SUM(G13:J13) -> 1049687 | N13: =K13/K16 -> 0.047451918 | O13: =K24*N13 -> -531820.83
C14: Roads and bridges | G14: 12195458 | K14: =SUM(G14:J14) -> 12195458 | N14: =K14/K16 -> 0.55130517 | O14: =K24*N14 -> -6178792.9
C15: Construction in progress | G15: 23394 | H15: -23394 | K15: =SUM(G15:J15) -> 0 | N15: =K15/K27 -> 0
D16: Subtotal | G16: =SUM(G10:G15) -> 21627577 | H16: =SUM(H10:H15) -> 0 | I16: =SUM(I10:I15) -> 493489 | J16: =SUM(J10:J15) -> 0 | K16: =SUM(K10:K15) -> 22121066 | N16: =SUM(N10:N15) -> 1 | O16: =SUM(O10:O15) -> -11207573
C18: Buildings | K18: -3003986 | L18: =SUM(K10+K18) -> 2925164
C19: Furniture and fixtures | K19: -223694 | L19: =SUM(K11+K19) -> 217825
C20: Machinery and equipment | K20: -1269279 | L20: =SUM(K12+K20) -> 1235973
C21: Transportation equipment | K21: -531821 | L21: =SUM(K13+K21) -> 517866
C22: Roads and bridges | K22: -6178793 | L22: =SUM(K14+K22) -> 6016665
C23: Construction in progress | L23: =SUM(K15+K23) -> 0
D24: Less accumulated depreciation | G24: -10330886 | I24: -876687 | K24: =SUM(G24:J24) -> -11207573
C26: Net Police Jury fixed
D27: assets | G27: 11303729 | I27: -383198 | K27: =SUM(G27:J27) -> 10920531 | O27: =SUM(K8:K15)+K24 -> 10920531
C29: Total governmental activities capital assets, net | G29: =G16+G8+G24 -> 11303729 | H29: =H16+H8+H24 -> 0 | I29: =I16+I8+I24 -> -383198 | J29: =J16+J8+J24 -> 0 | K29: =K16+K8+K24 -> 10920531 | L29: =SUM(L8:L23) -> 10920531

Sheet DeSoto
D1: DESOTO PARISH POLICE JURY
D2: Capital Assets
D3: For the Year Ended December 31, 2013
I5: Balance 1/1/2013 | J5: Additions | K5: Deletions | L5: Balance 12/31/2013 | M5: Cross Sectional
A7: Governmental Activities:
B8: Capital assets, not being depreciated:
C9: Land | I9: 1980743 | J9: 20000 | K9: -20800 | L9: =SUM(I9:K9) -> 1979943 | M9: =SUM(L9) -> 1979943
C10: Construction in progress | I10: 2046951 | J10: 359254 | K10: -1907311 | L10: =SUM(I10:K10) -> 498894 | M10: =SUM(L10) -> 498894
D11: Total capital assets, not being depreciated | I11: =SUM(I8:I10) -> 4027694 | J11: =SUM(J8:J10) -> 379254 | K11: =SUM(K8:K10) -> -1928111 | L11: =SUM(L8:L10) -> 2478837
A13: Capital assets being depreciated:
B14: Buildings and improvements | I14: 26639391 | J14: 456368 | K14: -13331 | L14: =SUM(I14:K14) -> 27082428
B15: Land improvements - structures | I15: 2785535 | J15: 2407392 | L15: =SUM(I15:K15) -> 5192927
B16: Furniture and equipment | I16: 11864930 | J16: 566744 | K16: -40169 | L16: =SUM(I16:K16) -> 12391505
B17: Infrastructure | I17: 217009407 | J17: 1774323 | L17: =SUM(I17:J17) -> 218783730
D18: Total capital assets being depreciated | I18: =SUM(I14:I17) -> 258299263 | J18: =SUM(J14:J17) -> 5204827 | K18: =SUM(K14:K17) -> -53500 | L18: =SUM(L14:L17) -> 263450590
A20: Less accumulated depreciation for:
B21: Buildings and improvements | I21: 11112067 | J21: 663638 | K21: -7943 | L21: =SUM(I21:K21) -> 11767762 | M21: =L14-L21 -> 15314666
B22: Land improvements - structures | I22: 158146 | J22: 187507 | L22: =SUM(I22:K22) -> 345653 | M22: =L15-L22 -> 4847274
B23: Furniture and equipment | I23: 6830433 | J23: 1068469 | K23: -14175 | L23: =SUM(I23:K23) -> 7884727 | M23: =L16-L23 -> 4506778
B24: Infrastructure | I24: 168627234 | J24: 1932445 | L24: =SUM(I24:K24) -> 170559679 | M24: =L17-L24 -> 48224051
D25: Total accumulated depreciation | I25: =SUM(I21:I24) -> 186727880 | J25: =SUM(J21:J24) -> 3852059 | K25: =SUM(K21:K24) -> -22118 | L25: =SUM(L21:L24) -> 190557821
B26: Total capital assets being depreciated, net | I26: =I18-I25 -> 71571383 | J26: =J18-J25 -> 1352768 | K26: =K18-K25 -> -31382 | L26: =L18-L25 -> 72892769
B27: Total governmental activities capital assets, net | I27: =I26+I11 -> 75599077 | J27: =J26+J11 -> 1732022 | K27: =K26+K11 -> -1959493 | L27: =L26+L11 -> 75371606 | M27: =SUM(M21:M24,M9:M10) -> 75371606
I30: Balance 1/1/2013 | J30: Decreases | K30: Adjustments | L30: Balance 12/31/2013
A31: Business-Type Activities:
B32: Capital assets, not being depreciated:
C33: Land | I33: 10175 | L33: =SUM(I33:K33) -> 10175 | M33: =SUM(L33) -> 10175
D34: Total capital assets, not being depreciated | I34: =SUM(I32:I33) -> 10175 | J34: =SUM(J32:J33) -> 0 | K34: =SUM(K32:K33) -> 0 | L34: =SUM(L32:L33) -> 10175
A36: Capital assets being depreciated:
B37: Sewer system | I37: 373375 | L37: =SUM(I37:K37) -> 373375
B38: Treatment plant | I38: 101180 | K38: 0 | L38: =SUM(I38:K38) -> 101180
D39: Total capital assets being depreciated | I39: =SUM(I37:I38) -> 474555 | J39: =SUM(J37:J38) -> 0 | K39: =SUM(K37:K38) -> 0 | L39: =SUM(L37:L38) -> 474555
A41: Less accumulated depreciation for:
B42: Sewer system | I42: 373375 | L42: =SUM(I42:K42) -> 373375 | M42: =L37-L42 -> 0
B43: Treatment plant | I43: 101180 | L43: =SUM(I43:K43) -> 101180 | M43: =L38-L43 -> 0
D44: Total accumulated depreciation | I44: =SUM(I42:I43) -> 474555 | J44: =SUM(J42:J43) -> 0 | K44: =SUM(K42:K43) -> 0 | L44: =SUM(L42:L43) -> 474555
B45: Total capital assets being depreciated, net | I45: =I39-I44 -> 0 | J45: =J39+J44 -> 0 | K45: =K39+K44 -> 0 | L45: =L39-L44 -> 0
B46: Total business-type activities capital assets, net | I46: =I45+I34 -> 10175 | J46: =J45+J34 -> 0 | K46: =K45+K34 -> 0 | L46: =L45+L34 -> 10175 | M46: =SUM(M33:M43) -> 10175

Sheet East Baton Rouge
D1: EAST BATON ROUGE PARISH POLICE JURY
D2: Capital Assets
D3: For the Year Ended December 31, 2013
I5: Balance 1/1/2013 | J5: Transfers | K5: Additions | L5: Deletions | M5: Balance 12/31/2013 | N5: Cross Sectional
A7: Governmental Activities:
B8: Capital assets, not being depreciated:
C9: Land and right-of-way | I9: 11006200 | K9: 627124 | M9: =SUM(I9:K9) -> 11633324 | N9: =SUM(M9) -> 11633324
C10: Construction work in progress | I10: 9026422 | J10: -5977507 | K10: 8258836 | M10: =SUM(I10:K10) -> 11307751 | N10: =SUM(M10) -> 11307751
D11: Total capital assets, not being depreciated | I11: =SUM(I8:I10) -> 20032622 | J11: =SUM(J8:J10) -> -5977507 | K11: =SUM(K8:K10) -> 8885960 | M11: =SUM(M8:M10) -> 22941075
A13: Capital assets being depreciated:
B14: Buildings | I14: 107230589 | K14: 150605 | M14: =SUM(I14:K14) -> 107381194
B15: Improvements (other than buildings) and infrastructure | I15: 174611343 | J15: 5977507 | K15: 21236654 | M15: =SUM(I15:K15) -> 201825504
B16: Equipment and equipment under lease | I16: 3739203 | K16: 417665 | M16: =SUM(I16:K16) -> 4156868
D17: Total capital assets being depreciated | I17: =SUM(I14:I16) -> 285581135 | J17: =SUM(J14:J16) -> 5977507 | K17: =SUM(K14:K16) -> 21804924 | L17: =SUM(L14:L16) -> 0 | M17: =SUM(M14:M16) -> 313363566
A19: Less accumulated depreciation for:
B20: Buildings | I20: -18839429 | K20: -2579573 | M20: =SUM(I20:L20) -> -21419002 | N20: =SUM(M20,M14) -> 85962192
B21: Improvements (other than buildings) and infrastructure | I21: -36641632 | K21: -4686019 | M21: =SUM(I21:L21) -> -41327651 | N21: =SUM(M21,M15) -> 160497853
B22: Equipment and equipment under lease | I22: -2800310 | K22: -363030 | M22: =SUM(I22:L22) -> -3163340 | N22: =SUM(M22,M16) -> 993528
D23: Total accumulated depreciation | I23: =SUM(I20:I22) -> -58281371 | J23: =SUM(J20:J22) -> 0 | K23: =SUM(K20:K22) -> -7628622 | L23: =SUM(L20:L22) -> 0 | M23: =SUM(M20:M22) -> -65909993
B24: Total capital assets being depreciated, net | I24: =I17+I23 -> 227299764 | J24: =J17+J23 -> 5977507 | K24: =K17+K23 -> 14176302 | L24: =L17+L23 -> 0 | M24: =M17+M23 -> 247453573
B25: Total governmental activities capital assets, net | I25: =I23+I17+I11 -> 247332386 | J25: =J23+J17+J11 -> 0 | K25: =K23+K17+K11 -> 23062262 | L25: =L23+L17+L11 -> 0 | M25: =SUM(I25:L25) -> 270394648 | N25: =SUM(N20:N22,N9:N10) -> 270394648
I28: Balance 1/1/2013 | J28: Increases | K28: Decreases | L28: Adjustments | M28: Balance 12/31/2013
A29: Business-Type Activities:
B30: Capital assets, not being depreciated:
C31: Land and right-of-way | I31: 77556445 | J31: 4035196 | K31: -549917 | L31: -220441 | M31: =SUM(I31:L31) -> 80821283 | N31: =SUM(M31) -> 80821283
C32: Noise mitigation | I32: 57876615 | J32: 0 | K32: 0 | L32: 228103 | M32: =SUM(I32:L32) -> 58104718 | N32: =SUM(M32) -> 58104718
C33: Construction work in progress | I33: 211622261 | J33: 55345105 | K33: -371895 | L33: -150521537 | M33: =SUM(I33:L33) -> 116073934 | N33: =SUM(M33) -> 116073934
D34: Total capital assets, not being depreciated | I34: =SUM(I30:I33) -> 347055321 | J34: =SUM(J30:J33) -> 59380301 | K34: =SUM(K30:K33) -> -921812 | L34: =SUM(L30:L33) -> -150513875 | M34: =SUM(M30:M33) -> 254999935
A36: Capital assets being depreciated:
B37: Buildings | I37: 220610624 | J37: 4659163 | K37: 0 | L37: 9553872 | M37: =SUM(I37:L37) -> 234823659
B38: Improvements (other than buildings) and infrastructure | I38: 1536676864 | J38: 219826258 | K38: -10280399 | L38: 141207173 | M38: =SUM(I38:L38) -> 1887429896
B39: Equipment | I39: 11467460 | J39: 164403 | K39: -1055546 | L39: 0 | M39: =SUM(I39:L39) -> 10576317
D40: Total capital assets being depreciated | I40: =SUM(I37:I39) -> 1768754948 | J40: =SUM(J37:J39) -> 224649824 | K40: =SUM(K37:K39) -> -11335945 | L40: =SUM(L37:L39) -> 150761045 | M40: =SUM(M37:M39) -> 2132829872
A42: Less accumulated depreciation for:
B43: Buildings | I43: -100195132 | J43: -8368419 | K43: 0 | M43: =SUM(I43:L43) -> -108563551 | N43: =SUM(M43,M37) -> 126260108
B44: Improvements (other than buildings) and infrastructure | I44: -562556664 | J44: -56150837 | K44: 9252036 | M44: =SUM(I44:L44) -> -609455465 | N44: =SUM(M44,M38) -> 1277974431
B45: Equipment | I45: -10424064 | J45: -338853 | K45: 1051880 | M45: =SUM(I45:L45) -> -9711037 | N45: =SUM(M45,M39) -> 865280
D46: Total accumulated depreciation | I46: =SUM(I43:I45) -> -673175860 | J46: =SUM(J43:J45) -> -64858109 | K46: =SUM(K43:K45) -> 10303916 | L46: =SUM(L43:L45) -> 0 | M46: =SUM(M43:M45) -> -727730053
B47: Total capital assets being depreciated, net | I47: =I40+I46 -> 1095579088 | J47: =J40+J46 -> 159791715 | K47: =K40+K46 -> -1032029 | L47: =L40+L46 -> 150761045 | M47: =M40+M46 -> 1405099819
B48: Total business-type activities capital assets, net | I48: =I46+I40+I34 -> 1442634409 | J48: =J46+J40+J34 -> 219172016 | K48: =K46+K40+K34 -> -1953841 | L48: =L46+L40+L34 -> 247170 | M48: =SUM(I48:L48) -> 1660099754 | N48: =SUM(N43:N45,N31:N32,N33) -> 1660099754

Sheet East Carroll
D1: EAST CARROLL PARISH POLICE JURY
D2: Capital Assets
D3: For the Year Ended December 31, 2013
G5: Beginning Balance | H5: Additions | I5: Deletions | J5: Ending Balance | K5: Cross Sectional
A7: Governmental Activities:
B8: Capital assets, not being depreciated:
C9: Land | G9: 274665 | J9: =SUM(G9:I9) -> 274665 | K9: =SUM(J9) -> 274665
C10: Airport land | G10: 101000 | J10: =SUM(G10:I10) -> 101000 | K10: =SUM(J10) -> 101000
C11: Construction in progress | G11: 353730 | H11: 291155 | I11: -383121 | J11: =SUM(G11:I11) -> 261764 | K11: =SUM(J11) -> 261764
D12: Total capital assets, not being depreciated | G12: =SUM(G9:G11) -> 729395 | H12: =SUM(H9:H11) -> 291155 | I12: =SUM(I9:I11) -> -383121 | J12: =SUM(J9:J11) -> 637429
A14: Capital assets being depreciated: | N14: =Caldwell!K30 -> 935
B15: Buildings | G15: 2630747 | H15: 16081 | J15: =SUM(G15:I15) -> 2646828
B16: Office equipment | G16: 432022 | H16: 11948 | I16: 16888 | J16: =SUM(G16:I16) -> 460858
B17: Furniture and fixtures | G17: 105179 | H17: 14372 | J17: =SUM(G17:I17) -> 119551
B18: Construction equipment | G18: 1533590 | H18: 193895 | J18: =SUM(G18:I18) -> 1727485
B19: Vehicles | G19: 2292724 | H19: 106700 | J19: =SUM(G19:I19) -> 2399424
B20: Books, periodicals and law books | G20: 342548 | J20: =SUM(G20:I20) -> 342548
B21: Infrastructure:
C22: Airport hangars | G22: 25000 | J22: =SUM(G22:I22) -> 25000
C23: Airport runway | G23: 763626 | H23: 367040 | J23: =SUM(G23:I23) -> 1130666
C24: Road right-of-way | G24: 558234 | J24: =SUM(G24:I24) -> 558234 | K24: =J24 -> 558234
C25: Road surface | G25: 9140845 | J25: =SUM(G25:I25) -> 9140845
C26: Bridges | G26: 1759091 | J26: =SUM(G26:I26) -> 1759091
D27: Total capital assets being depreciated | G27: =SUM(G15:G26) -> 19583606 | H27: =SUM(H15:H26) -> 710036 | I27: =SUM(I15:I26) -> 16888 | J27: =SUM(J15:J26) -> 20310530
A29: Less accumulated depreciation:
B30: Buildings | G30: 1535390 | H30: 51129 | J30: =SUM(G30:I30) -> 1586519 | K30: =J15-J30 -> 1060309
B31: Office equipment | G31: 338093 | H31: 28604 | I31: -16888 | J31: =SUM(G31:I31) -> 349809 | K31: =J16-J31 -> 111049
B32: Furniture and fixtures | G32: 78239 | H32: 5834 | J32: =SUM(G32:I32) -> 84073 | K32: =J17-J32 -> 35478
B33: Construction equipment | G33: 1097614 | H33: 102043 | J33: =SUM(G33:I33) -> 1199657 | K33: =J18-J33 -> 527828
B34: Vehicles | G34: 1874824 | H34: 94659 | J34: =SUM(G34:I34) -> 1969483 | K34: =J19-J34 -> 429941
B35: Books, periodicals and law books | G35: 339855 | H35: 1795 | J35: =SUM(G35:I35) -> 341650 | K35: =J20-J35 -> 898
B36: Infrastructure:
C37: Airport hangars | G37: 23438 | H37: 625 | J37: =SUM(G37:I37) -> 24063 | K37: =J22-J37 -> 937
C38: Airport runway | G38: 181361 | H38: 23679 | J38: =SUM(G38:I38) -> 205040 | K38: =J23-J38 -> 925626
C39: Road surface | G39: 8397342 | H39: 35595 | J39: =SUM(G39:I39) -> 8432937 | K39: =J25-J39 -> 707908
C40: Bridges | G40: 1137577 | H40: 28620 | J40: =SUM(G40:I40) -> 1166197 | K40: =J26-J40 -> 592894
D42: Total accumulated depreciation | G42: =SUM(G30:G40) -> 15003733 | H42: =SUM(H30:H40) -> 372583 | J42: =SUM(J30:J40) -> 15359428
B44: Total capital assets being depreciated, net | G44: =G27-G42 -> 4579873 | H44: =H27-H42 -> 337453 | I44: =I27-I42 -> 16888 | J44: =J27-J42 -> 4951102
B46: Governmental activities capital assets, net | G46: =G44+G12 -> 5309268 | H46: =H44+H12 -> 628608 | J46: =J44+J12 -> 5588531 | K46: =SUM(K9:K40) -> 5588531

Sheet East Feliciana
D1: EAST FELICIANA PARISH POLICE JURY
D2: Capital Assets
D3: For the Year Ended December 31, 2013
I5: Beginning Balance | J5: Additions | K5: Deletions | L5: Ending Balance | M5: Cross Sectional
A7: Governmental Activities:
B8: Capital assets, not being depreciated:
C9: Land | I9: 259230 | L9: =SUM(I9:K9) -> 259230 | M9: =SUM(L9) -> 259230
D10: Total capital assets, not being depreciated | I10: =SUM(I8:I9) -> 259230 | J10: =SUM(J8:J9) -> 0 | K10: =SUM(K8:K9) -> 0 | L10: =SUM(L8:L9) -> 259230
A12: Capital assets being depreciated:
B13: Buildings | I13: 9627258.6 | L13: =SUM(I13:K13) -> 9627258.6
B14: Less: accumulated depreciation | I14: 4164529.8 | J14: 196840.7 | L14: =SUM(I14:J14) -> 4361370.5
D15: Net Buildings | I15: =I13-I14 -> 5462728.8 | J15: =J13-J14 -> -196840.7 | K15: =K13-K14 -> 0 | L15: =L13-L14 -> 5265888.1 | M15: =L13-L14 -> 5265888.1
B17: Equipment/Vehicles | I17: 3677798.9 | J17: 592096.43 | K17: -87400 | L17: =SUM(I17:K17) -> 4182495.3
B18: Less: accumulated depreciation | I18: 2273761.5 | J18: 164978.49 | K18: -87400 | L18: =SUM(I18:K18) -> 2351340
D19: Net Equipment/vehicles | I19: =I17-I18 -> 1404037.3 | J19: =J17-J18 -> 427117.94 | K19: =K17-K18 -> 0 | L19: =L17-L18 -> 1831155.3 | M19: =L17-L18 -> 1831155.3
B21: Streets/Bridges | I21: 1342103.2 | L21: =SUM(I21:K21) -> 1342103.2
B22: Less: accumulated depreciation | I22: 313695.63 | J22: 71604.32 | L22: =SUM(I22:K22) -> 385299.95
D23: Net Furniture and fixtures | I23: =I21-I22 -> 1028407.5 | J23: =J21-J22 -> -71604.32 | K23: =K21-K22 -> 0 | L23: =L21-L22 -> 956803.22 | M23: =L21-L22 -> 956803.22
B24: Capital assets, being depreciated, net | I24: =I23+I19+I15 -> 7895173.7 | J24: =J23+J19+J15 -> 158672.92 | K24: =K23+K19+K15 -> 0 | L24: =L23+L19+L15 -> 8053846.6
B25: Capital assets, net | I25: =I24+I10 -> 8154403.7 | J25: =J24+J10 -> 158672.92 | K25: =K24+K10 -> 0 | L25: =L24+L10 -> 8313076.6 | M25: =SUM(M9:M23) -> 8313076.6

Sheet Evangeline
D1: EVANGELINE PARISH POLICE JURY
D2: Capital Assets
D3: For the Year Ended December 31, 2013
I5: Beginning Balance | J5: Increases | K5: Decreases | L5: Ending Balance | M5: Cross Sectional
A7: Primary Government
A8: Government Activities:
A9: Capital assets, not being depreciated:
B10: Land | I10: 876298 | J10: 0 | K10: 0 | L10: =SUM(I10:K10) -> 876298 | M10: =SUM(L10) -> 876298
B11: Construction in progress | I11: 818496 | J11: 2647442 | K11: -1614513 | L11: =SUM(I11:K11) -> 1851425 | M11: =SUM(L11) -> 1851425
C12: Total assets not being depreciated | I12: =SUM(I10:I11) -> 1694794 | J12: =SUM(J10:J11) -> 2647442 | K12: =SUM(K10:K11) -> -1614513 | L12: =SUM(L10:L11) -> 2727723
A14: Capital assets being depreciated:
B15: Buildings and improvements | I15: 11360591 | J15: 197254 | K15: 0 | L15: =SUM(I15:K15) -> 11557845
B16: Infrastructure | I16: 19003541 | J16: 3376445 | K16: 0 | L16: =SUM(I16:K16) -> 22379986
B17: Vehicles | I17: 660291 | J17: 43985 | L17: =SUM(I17:K17) -> 704276
B18: Equipment, furniture and fixtures | I18: 5279409 | J18: 1204581 | K18: -100700 | L18: =SUM(I18:K18) -> 6383290
C19: Total capital assets being depreciated | I19: =SUM(I15:I18) -> 36303832 | J19: =SUM(J15:J18) -> 4822265 | K19: =SUM(K15:K18) -> -100700 | L19: =SUM(L15:L18) -> 41025397
A20: Less accumulated depreciation:
B21: Buildings | I21: 4177812 | J21: 303449 | K21: 0 | L21: =SUM(I21:K21) -> 4481261 | M21: =L15-L21 -> 7076584
B22: Infrastructure | I22: 9096921 | J22: 959297 | K22: 0 | L22: =SUM(I22:K22) -> 10056218 | M22: =L16-L22 -> 12323768
B23: Vehicles | I23: 520294 | J23: 58794 | L23: =SUM(I23:K23) -> 579088 | M23: =L17-L23 -> 125188
B24: Equipment, furniture and fixtures | I24: 3666099 | J24: 406557 | K24: -99600 | L24: =SUM(I24:K24) -> 3973056 | M24: =L18-L24 -> 2410234
C25: Total accumulated depreciation | I25: =SUM(I21:I24) -> 17461126 | J25: =SUM(J21:J24) -> 1728097 | K25: =SUM(K21:K24) -> -99600 | L25: =SUM(L21:L24) -> 19089623
B26: Total capital assets being depreciated, net | I26: =I19-I25 -> 18842706 | J26: =J19-J25 -> 3094168 | K26: =K19-K25 -> -1100 | L26: =L19-L25 -> 21935774
B27: Governmental activities capital assets, net | I27: =I12+I26 -> 20537500 | J27: =J12+J26 -> 5741610 | K27: =K12+K26 -> -1615613 | L27: =L12+L26 -> 24663497 | M27: =SUM(M21:M24,M10:M11) -> 24663497
I30: Beginning Balance | J30: Increases | K30: Decreases | L30: Ending Balance
A32: Business-type Activities:
A33: Capital assets being depreciated:
B34: Sewer system | I34: 828812 | J34: 0 | K34: 0 | L34: =SUM(I34:K34) -> 828812
B35: Equipment, furniture and fixtures | I35: 18209 | J35: 1560 | L35: =SUM(I35:K35) -> 19769
C36: Total capital assets being depreciated | I36: =SUM(I34:I35) -> 847021 | J36: =SUM(J34:J35) -> 1560 | K36: =SUM(K34:K35) -> 0 | L36: =SUM(L34:L35) -> 848581
B38: Less accumulated depreciation | I38: 528442 | J38: 29039 | K38: 0 | L38: =SUM(I38:K38) -> 557481 | M38: =L36-L38 -> 291100
B39: Total capital assets being depreciated, net | I39: =I36-I38 -> 318579 | J39: =J36-J38 -> -27479 | K39: =K36-K38 -> 0 | L39: =L36-L38 -> 291100
B40: Business-type activities capital assets, net | I40: =I39 -> 318579 | J40: =J39 -> -27479 | K40: =K39 -> 0 | L40: =L39 -> 291100 | M40: =SUM(M34:M38) -> 291100

Sheet Franklin
D1: EVANGELINE PARISH POLICE JURY
D2: Capital Assets
D3: For the Year Ended December 31, 2013
G5: Beginning Balance | H5: Additions | I5: Deletions | J5: Ending Balance | K5: Cross Sectional
A7: Police Jury:
B8: Capital assets, not being depreciated:
C9: Land | G9: 390416 | J9: =SUM(G9:I9) -> 390416 | K9: =SUM(J9) -> 390416
C10: Construction in progress | G10: 311170 | H10: 375222 | J10: =SUM(G10:I10) -> 686392 | K10: =SUM(J10) -> 686392
C11: Assets under capital lease | G11: 96829 | J11: =SUM(G11:I11) -> 96829 | K11: =SUM(J11) -> 96829
D12: Total capital assets, not being depreciated | G12: =SUM(G9:G11) -> 798415 | H12: =SUM(H9:H11) -> 375222 | I12: =SUM(I9:I11) -> 0 | J12: =SUM(J9:J11) -> 1173637
A14: Capital assets being depreciated: | N14: =Caldwell!K30 -> 935
B15: Infrastructure - roads | G15: 86784323 | H15: 335893 | J15: =SUM(G15:I15) -> 87120216
B16: Infrastructure - bridges | G16: 3366140 | J16: =SUM(G16:I16) -> 3366140
B17: Buildings and improvements | G17: 4765535 | H17: 7000 | J17: =SUM(G17:I17) -> 4772535
B18: Improvements other than buildings | G18: 2593516 | J18: =SUM(G18:I18) -> 2593516
B19: Office furniture and equipment | G19: 60459 | J19: =SUM(G19:I19) -> 60459
B20: Heavy equipment | G20: 1729613 | H20: 131034 | I20: -402630 | J20: =SUM(G20:I20) -> 1458017
B21: Other equipment | G21: 400559 | H21: 6430 | I21: -5850 | J21: =SUM(G21:I21) -> 401139
B22: Vehicles | G22: 1208005 | I22: -7735 | J22: =SUM(G22:I22) -> 1200270
D23: Total capital assets being depreciated | G23: =SUM(G15:G22) -> 100908150 | H23: =SUM(H15:H22) -> 480357 | I23: =SUM(I15:I22) -> -416215 | J23: =SUM(J15:J22) -> 100972292
A25: Less accumulated depreciation for:
B26: Infrastructure - roads | G26: -74418357 | H26: -738290 | J26: =SUM(G26:I26) -> -75156647 | K26: =J15+J26 -> 11963569
B27: Infrastructure - bridges | G27: -1573675 | H27: -48964 | J27: =SUM(G27:I27) -> -1622639 | K27: =J16+J27 -> 1743501
B28: Buildings and improvements | G28: -3337791 | H28: -119343 | J28: =SUM(G28:I28) -> -3457134 | K28: =J17+J28 -> 1315401
B29: Improvements other than buildings | G29: -1558271 | H29: -111001 | J29: =SUM(G29:I29) -> -1669272 | K29: =J18+J29 -> 924244
B30: Office furniture and equipment | G30: -58535 | H30: -480 | J30: =SUM(G30:I30) -> -59015 | K30: =J19+J30 -> 1444
B31: Heavy equipment | G31: -990767 | H31: -108647 | I31: 207194 | J31: =SUM(G31:I31) -> -892220 | K31: =J20+J31 -> 565797
B32: Other equipment | G32: -345648 | H32: -14622 | I32: 5850 | J32: =SUM(G32:I32) -> -354420 | K32: =J21+J32 -> 46719
B33: Vehicles | G33: -1041791 | H33: -64110 | I33: 7735 | J33: =SUM(G33:I33) -> -1098166 | K33: =J22+J33 -> 102104
D34: Total accumulated depreciation | G34: =SUM(G26:G33) -> -83324835 | H34: =SUM(H26:H33) -> -1205457 | I34: =SUM(I26:I33) -> 220779 | J34: =SUM(J26:J33) -> -84309513
B36: Total capital assets being depreciated, net | G36: =G23+G34 -> 17583315 | H36: =H23+H34 -> -725100 | I36: =I23+I34 -> -195436 | J36: =J23+J34 -> 16662779
B38: Governmental activities capital assets, net | G38: =G36+G12 -> 18381730 | H38: =H36+H12 -> -349878 | I38: =I36+I12 -> -195436 | J38: =J36+J12 -> 17836416 | K38: =SUM(K9:K33) -> 17836416

Sheet Grant
D1: GRANT PARISH POLICE JURY
D2: Capital Assets
D3: For the Year Ended December 31, 2013
I5: Beginning Balance | J5: Increases | K5: Decreases | L5: Ending Balance | M5: Cross Sectional
A7: Primary Government
A8: Government Activities:
A9: Capital assets, not being depreciated:
B10: Construction in progress | I10: 196164 | J10: 37900 | K10: -196164 | L10: =SUM(I10:K10) -> 37900 | M10: =L10 -> 37900
B11: Land | I11: 202250 | J11: 1000 | L11: =SUM(I11:K11) -> 203250 | M11: =L11 -> 203250
C12: Total assets not being depreciated | I12: =SUM(I10:I11) -> 398414 | J12: =SUM(J10:J11) -> 38900 | K12: =SUM(K10:K11) -> -196164 | L12: =SUM(L10:L11) -> 241150
A14: Capital assets being depreciated: | O14: % of Total CAs | P14: Depreciation | Q14: Capital Assets, Net
B15: Buildings and improvements | I15: 2641293 | K15: 0 | L15: =SUM(I15:K15) -> 2641293 | M15: =L15+P15 -> 1562053.7 | O15: =L15/L19 -> 0.26736836 | P15: =O15*L21 -> -1079239.3 | Q15: =+L15+P15 -> 1562053.7
B16: Furniture, fixtures and equipment | I16: 2360030 | J16: 345929 | K16: -130513 | L16: =SUM(I16:K16) -> 2575446 | M16: =L16+P16 -> 1523111.9 | O16: =L16/L19 -> 0.26070291 | P16: =O16*L21 -> -1052334.1 | Q16: =+L16+P16 -> 1523111.9
B17: Infrastructure | I17: 4013990 | J17: 438478 | L17: =SUM(I17:K17) -> 4452468 | M17: =L17+P17 -> 2633177.7 | O17: =L17/L19 -> 0.45070693 | P17: =O17*L21 -> -1819290.3 | Q17: =+L17+P17 -> 2633177.7
B18: Solid waste station | I18: 209647 | L18: =SUM(I18:K18) -> 209647 | M18: =L18+P18 -> 123984.68 | O18: =L18/L19 -> 0.021221794 | P18: =O18*L21 -> -85662.321 | Q18: =+L18+P18 -> 123984.68
C19: Total capital assets being depreciated | I19: =SUM(I15:I18) -> 9224960 | J19: =SUM(J15:J18) -> 784407 | K19: =SUM(K15:K18) -> -130513 | L19: =SUM(L15:L18) -> 9878854 | O19: =SUM(O15:O18) -> 1 | P19: =SUM(P15:P18) -> -4036526 | Q19: =+L19+P19 -> 5842328
Q20: Total CAs, Net
B21: Accumulated depreciation | I21: -3831555 | J21: -335484 | K21: 130513 | L21: =SUM(I21:K21) -> -4036526 | Q21: =+L12+Q19 -> 6083478
B22: Total capital assets being depreciated, net | I22: =I19+I21 -> 5393405 | J22: =J19+J21 -> 448923 | K22: =K19+K21 -> 0 | L22: =L19+L21 -> 5842328
B23: Governmental activities capital assets, net | I23: =I12+I22 -> 5791819 | J23: =J12+J22 -> 487823 | K23: =K12+K22 -> -196164 | L23: =L12+L22 -> 6083478 | M23: =SUM(M10:M18) -> 6083478
I26: Beginning Balance | J26: Increases | K26: Decreases | L26: Ending Balance
A28: Business-type Activities:
A29: Capital assets being depreciated: | O29: % of Total CAs | P29: Depreciation | Q29: Capital Assets, Net
B30: Distribution system | I30: 1245902 | J30: 0 | K30: 0 | L30: =SUM(I30:K30) -> 1245902 | M30: =L30+P30 -> 299292.05 | O30: =L30/L33 -> 0.83789775 | P30: =O30*L35 -> -946609.95 | Q30: =+L30+P30 -> 299292.05
B31: Buildings | I31: 7878 | L31: =SUM(I31:K31) -> 7878 | M31: =L31+P31 -> 1892.4625 | O31: =L31/L33 -> 0.0052981362 | P31: =O31*L35 -> -5985.5375 | Q31: =+L31+P31 -> 1892.4625
B32: Equipment | I32: 228865 | J32: 4293 | L32: =SUM(I32:K32) -> 233158 | M32: =L32+P32 -> 56009.49 | O32: =L32/L33 -> 0.15680412 | P32: =O32*L35 -> -177148.51 | Q32: =+L32+P32 -> 56009.49
C33: Total capital assets being depreciated | I33: =SUM(I30:I32) -> 1482645 | J33: =SUM(J30:J32) -> 4293 | K33: =SUM(K30:K32) -> 0 | L33: =SUM(L30:L32) -> 1486938 | O33: =SUM(O29:O32) -> 1 | P33: =SUM(P30:P32) -> -1129744 | Q33: =+L33+P33 -> 357194 | R33: Total CAs, Net
B35: Accumulated depreciation | I35: -1093271 | J35: -36473 | K35: 0 | L35: =SUM(I35:K35) -> -1129744
B36: Total capital assets being depreciated, net | I36: =I35+I33 -> 389374 | J36: =J35+J33 -> -32180 | K36: =K35+K33 -> 0 | L36: =L35+L33 -> 357194
B37: Business-type activities capital assets, net | I37: =I36 -> 389374 | J37: =J36 -> -32180 | K37: =K36 -> 0 | L37: =L36 -> 357194 | M37: =SUM(M30:M32) -> 357194

Sheet Iberia
D1: IBERIA PARISH POLICE JURY
D2: Capital Assets
D3: For the Year Ended December 31, 2013
G5: Beginning Balance | H5: Additions | I5: Deletions | J5: Ending Balance | K5: Cross Sectional
A7: Police Jury:
B8: Capital assets, not being depreciated:
C9: Land | G9: 2466687 | J9: =SUM(G9:I9) -> 2466687 | K9: =SUM(J9) -> 2466687
C10: Construction in progress | G10: 1680267 | H10: 3657657 | I10: -2348332 | J10: =SUM(G10:I10) -> 2989592 | K10: =SUM(J10) -> 2989592
D11: Total capital assets, not being depreciated | G11: =SUM(G9:G10) -> 4146954 | H11: =SUM(H9:H10) -> 3657657 | I11: =SUM(I9:I10) -> -2348332 | J11: =SUM(J9:J10) -> 5456279
A13: Capital assets being depreciated: | N13: =Caldwell!K30 -> 935
B14: Land improvements | G14: 10470 | J14: =SUM(G14:I14) -> 10470
B15: Buildings and improvements | G15: 30906429 | H15: 1002394 | J15: =SUM(G15:I15) -> 31908823
B16: Furniture and equipment | G16: 8666144 | H16: 1426818 | J16: =SUM(G16:I16) -> 10092962
B17: Infrastructure | G17: 120711529 | H17: 2187960 | J17: =SUM(G17:I17) -> 122899489
D18: Total capital assets being depreciated | G18: =SUM(G14:G17) -> 160294572 | H18: =SUM(H14:H17) -> 4617172 | I18: =SUM(I14:I17) -> 0 | J18: =SUM(J14:J17) -> 164911744
A20: Less accumulated depreciation for:
B21: Land improvements | G21: 6850 | H21: 524 | J21: =SUM(G21:I21) -> 7374 | K21: =J14-J21 -> 3096
B22: Buildings and improvements | G22: 16537907 | H22: 671569 | J22: =SUM(G22:I22) -> 17209476 | K22: =J15-J22 -> 14699347
B23: Furniture and equipment | G23: 5981376 | H23: 594345 | J23: =SUM(G23:I23) -> 6575721 | K23: =J16-J23 -> 3517241
B24: Infrastructure | G24: 47625240 | H24: 3012949 | J24: =SUM(G24:I24) -> 50638189 | K24: =J17-J24 -> 72261300
D25: Total accumulated depreciation | G25: =SUM(G21:G24) -> 70151373 | H25: =SUM(H21:H24) -> 4279387 | I25: =SUM(I21:I24) -> 0 | J25: =SUM(J21:J24) -> 74430760
B27: Total capital assets being depreciated, net | G27: =G18-G25 -> 90143199 | H27: =H18-H25 -> 337785 | I27: =I18-I25 -> 0 | J27: =J18-J25 -> 90480984
B29: Governmental activities capital assets, net | G29: =G27+G11 -> 94290153 | H29: =H27+H11 -> 3995442 | I29: =I27+I11 -> -2348332 | J29: =J27+J11 -> 95937263 | K29: =SUM(K9:K24) -> 95937263

Sheet Iberville
D1: IBERVILLE PARISH POLICE JURY
D2: Capital Assets
D3: For the Year Ended December 31, 2013
C5: Primary Government - Governmental Activities:
E6: Land | F6: Construction in Progress | G6: Buildings and Improvement | H6: Infrastructure | I6: Furniture and Equipment | J6: Total
C7: Cost at December 31, 2012 | E7: 2975825 | F7: 1088045 | G7: 39668784 | H7: 79445129 | I7: 27946409 | J7: =SUM(E7:I7) -> 151124192 | K7: =E10 -> 2975825
D8: Additions | E8: 0 | F8: 5130816 | G8: 533136 | H8: 2089142 | I8: 954391 | J8: =SUM(E8:I8) -> 8707485 | K8: =F10 -> 6218861
D9: Deletions | E9: 0 | F9: 0 | G9: 0 | H9: 0 | I9: -46461 | J9: =SUM(E9:I9) -> -46461
C10: Cost at December 31, 2013 | E10: =SUM(E7:E9) -> 2975825 | F10: =SUM(F7:F9) -> 6218861 | G10: =SUM(G7:G9) -> 40201920 | H10: =SUM(H7:H9) -> 81534271 | I10: =SUM(I7:I9) -> 28854339 | J10: =SUM(E10:I10) -> 159785216
B12: Depreciation:
C13: Accumulated Depreciation at December 31, 2012 | E13: 0 | F13: 0 | G13: -7488940 | H13: -24522162 | I13: -23795945 | J13: =SUM(E13:I13) -> -55807047 | K13: =G10+G16 -> 31725027
D14: Additions | E14: 0 | F14: 0 | G14: -987953 | H14: -1769107 | I14: -1081177 | J14: =SUM(E14:I14) -> -3838237 | K14: =H10+H16 -> 55243002
D15: Deletions | E15: 0 | F15: 0 | G15: 0 | H15: 0 | I15: 46461 | J15: =SUM(E15:I15) -> 46461 | K15: =I10+I16 -> 4023678
C16: Accumulated Depreciation at December 31, 2013 | E16: =SUM(E13:E15) -> 0 | F16: =SUM(F13:F15) -> 0 | G16: =SUM(G13:G15) -> -8476893 | H16: =SUM(H13:H15) -> -26291269 | I16: =SUM(I13:I15) -> -24830661 | J16: =SUM(J13:J15) -> -59598823
C18: Capital Assets net of Accumulated Depreciation at December 31, 2013 | E18: =SUM(E16,E10) -> 2975825 | F18: =SUM(F16,F10) -> 6218861 | G18: =SUM(G16,G10) -> 31725027 | H18: =SUM(H16,H10) -> 55243002 | I18: =SUM(I16,I10) -> 4023678 | J18: =SUM(J16,J10) -> 100186393 | K18: =SUM(K7:K15) -> 100186393
C21: Primary Government - Business Type Activities:
E22: Land | F22: Construction in Progress | G22: Buildings and Improvement | H22: Equipment | I22: Total
C23: Cost at December 31, 2012 | E23: 193511 | F23: 40151 | G23: 18891560 | H23: 1007203 | I23: =SUM(E23:H23) -> 20132425 | J23: =E27 -> 193511
D24: Additions | E24: 0 | F24: 116582 | G24: 232017 | H24: 71106 | I24: =SUM(E24:H24) -> 419705 | J24: =F27 -> 156733
D25: Transfer | E25: 0 | F25: 0 | G25: -75959 | H25: -7666 | I25: =SUM(E25:H25) -> -83625
D26: Deletions | E26: 0 | F26: 0 | G26: 0 | H26: 0 | I26: =SUM(E26:H26) -> 0
C27: Cost at December 31, 2013 | E27: =SUM(E23:E26) -> 193511 | F27: =SUM(F23:F26) -> 156733 | G27: =SUM(G23:G26) -> 19047618 | H27: =SUM(H23:H26) -> 1070643 | I27: =SUM(I23:I26) -> 20468505
B29: Depreciation:
C30: Accumulated Depreciation at December 31, 2012 | E30: 0 | F30: 0 | G30: -8509184 | H30: -866246 | I30: =SUM(E30:H30) -> -9375430 | J30: =G27+G34 -> 10071429
D31: Additions | E31: 0 | F31: 0 | G31: -542964 | H31: -57550 | I31: =SUM(E31:H31) -> -600514 | J31: =H27+H34 -> 154513
D32: Transfer | E32: 0 | F32: 0 | G32: 0 | H32: 0 | I32: =SUM(E32:H32) -> 0
D33: Deletions | E33: 0 | F33: 0 | G33: 75959 | H33: 7666 | I33: =SUM(E33:H33) -> 83625
C34: Accumulated Depreciation at December 31, 2013 | E34: =SUM(E30:E33) -> 0 | F34: =SUM(F30:F33) -> 0 | G34: =SUM(G30:G33) -> -8976189 | H34: =SUM(H30:H33) -> -916130 | I34: =SUM(I30:I33) -> -9892319
C36: Capital Assets net of Accumulated Depreciation at December 31, 2013 | E36: =SUM(E34,E27) -> 193511 | F36: =SUM(F34,F27) -> 156733 | G36: =SUM(G34,G27) -> 10071429 | H36: =SUM(H34,H27) -> 154513 | I36: =SUM(I34,I27) -> 10576186 | J36: =SUM(J23:J34) -> 10576186
C38: Component Unit - Business Type Actitivites
E39: Distribution System | F39: Plant | G39: Construction in Progress | H39: Equipment | I39: Total
C40: Cost at December 31, 2012 | E40: 3234179 | F40: 3252606 | G40: 1294627 | H40: 2365159 | I40: =SUM(E40:H40) -> 10146571
D41: Additions | E41: 35533 | F41: 1429631 | G41: 0 | H41: 60766 | I41: =SUM(E41:H41) -> 1525930
D42: Deletions | E42: 0 | F42: 0 | G42: -1294627 | H42: 0 | I42: =SUM(E42:H42) -> -1294627
C43: Cost at December 31, 2013 | E43: =SUM(E40:E42) -> 3269712 | F43: =SUM(F40:F42) -> 4682237 | G43: =SUM(G40:G42) -> 0 | H43: =SUM(H40:H42) -> 2425925 | I43: =SUM(I40:I42) -> 10377874
B45: Depreciation:
C46: Accumulated Depreciation at December 31, 2012 | E46: -1432859 | F46: -1211594 | G46: 0 | H46: -1044257 | I46: =SUM(E46:H46) -> -3688710
D47: Additions | E47: -79806 | F47: -65052 | G47: 0 | H47: -103948 | I47: =SUM(E47:H47) -> -248806
D48: Deletions | E48: 0 | F48: 0 | G48: 0 | H48: 0 | I48: =SUM(E48:H48) -> 0
C49: Accumulated Depreciation at December 31, 2013 | E49: =SUM(E46:E48) -> -1512665 | F49: =SUM(F46:F48) -> -1276646 | G49: =SUM(G46:G48) -> 0 | H49: =SUM(H46:H48) -> -1148205 | I49: =SUM(I46:I48) -> -3937516
C51: Capital Assets net of Accumulated Depreciation at December 31, 2013 | E51: =SUM(E49,E43) -> 1757047 | F51: =SUM(F49,F43) -> 3405591 | G51: =SUM(G49,G43) -> 0 | H51: =SUM(H49,H43) -> 1277720 | I51: =SUM(I49,I43) -> 6440358
C53: Component Unit Governmental Actitivites
E54: Land | F54: Construction in Progress | G54: Building and Improvements | H54: Furniture and Equipment | I54: Books and Periodicals | J54: Recreational Facilities | K54: Total
C55: Cost at December 31, 2012 | E55: 435740 | F55: 467485 | G55: 1958343 | H55: 2823818 | I55: 1914980 | J55: 2934710 | K55: =SUM(E55:J55) -> 10535076
D56: Additions | E56: 0 | F56: 0 | G56: 164208 | H56: 142880 | I56: 126313 | J56: 8306 | K56: =SUM(E56:J56) -> 441707
D57: Deletions | E57: 0 | F57: -467485 | G57: 467485 | H57: -73128 | I57: 0 | J57: 0 | K57: =SUM(E57:J57) -> -73128
C58: Cost at December 31, 2013 | E58: =SUM(E55:E57) -> 435740 | F58: =SUM(F55:F57) -> 0 | G58: =SUM(G55:G57) -> 2590036 | H58: =SUM(H55:H57) -> 2893570 | I58: =SUM(I55:I57) -> 2041293 | J58: =SUM(J55:J57) -> 2943016 | K58: =SUM(E58:J58) -> 10903655
K59: =SUM(E59:J59) -> 0
B60: Depreciation: | K60: =SUM(E60:J60) -> 0
C61: Accumulated Depreciation at December 31, 2012 | E61: 0 | F61: 0 | G61: -1527627 | H61: -2755365 | I61: -1685370 | J61: -2579288 | K61: =SUM(E61:J61) -> -8547650
D62: Additions | E62: 0 | F62: 0 | G62: -63342 | H62: -58220 | I62: -140911 | J62: -32610 | K62: =SUM(E62:J62) -> -295083
D63: Deletions | E63: 0 | F63: 0 | G63: 0 | H63: 73128 | I63: 0 | J63: 0 | K63: =SUM(E63:J63) -> 73128
C64: Accumulated Depreciation at December 31, 2013 | E64: =SUM(E61:E63) -> 0 | F64: =SUM(F61:F63) -> 0 | G64: =SUM(G61:G63) -> -1590969 | H64: =SUM(H61:H63) -> -2740457 | I64: =SUM(I61:I63) -> -1826281 | J64: =SUM(J61:J63) -> -2611898 | K64: =SUM(E64:J64) -> -8769605
K65: =SUM(E65:J65) -> 0
C66: Capital Assets net of Accumulated Depreciation at December 31, 2013 | E66: =SUM(E64,E58) -> 435740 | F66: =SUM(F64,F58) -> 0 | G66: =SUM(G64,G58) -> 999067 | H66: =SUM(H64,H58) -> 153113 | I66: =SUM(I64,I58) -> 215012 | J66: =SUM(J64,J58) -> 331118 | K66: =SUM(K64,K58) -> 2134050

Sheet Jackson
D1: JACKSON PARISH POLICE JURY
D2: Capital Assets
D3: For the Year Ended December 31, 2013
G5: Beginning Balance | H5: Additions | I5: Deletions | J5: Ending Balance | K5: Cross Sectional
A7: Police Jury:
B8: Capital assets, not being depreciated:
C9: Land | G9: 388962 | H9: 38600 | J9: =SUM(G9:I9) -> 427562 | K9: =SUM(J9) -> 427562
C10: Construction in progress | G10: 406981 | H10: 779309 | I10: -496712 | J10: =SUM(G10:I10) -> 689578 | K10: =SUM(J10) -> 689578
D11: Total capital assets, not being depreciated | G11: =SUM(G9:G10) -> 795943 | H11: =SUM(H9:H10) -> 817909 | I11: =SUM(I9:I10) -> -496712 | J11: =SUM(J9:J10) -> 1117140
A13: Capital assets being depreciated: | N13: =Caldwell!K30 -> 935
B14: Buildings and improvements | G14: 6999747 | H14: 482867 | J14: =SUM(G14:I14) -> 7482614
B15: Vehicles | G15: 2212472 | H15: 58818 | J15: =SUM(G15:I15) -> 2271290
B16: Equipment/Machinery/Furniture | G16: 3761823 | H16: 402604 | I16: -158951 | J16: =SUM(G16:I16) -> 4005476
B17: Infrastructure/Roads | G17: 16292434 | H17: 1430035 | J17: =SUM(G17:I17) -> 17722469
D18: Total capital assets being depreciated | G18: =SUM(G14:G17) -> 29266476 | H18: =SUM(H14:H17) -> 2374324 | I18: =SUM(I14:I17) -> -158951 | J18: =SUM(J14:J17) -> 31481849
A20: Less accumulated depreciation for:
B21: Buildings and improvements | G21: 2324134 | H21: 204936 | J21: =SUM(G21:I21) -> 2529070 | K21: =J14-J21 -> 4953544
B22: Vehicles | G22: 1540554 | H22: 118703 | J22: =SUM(G22:I22) -> 1659257 | K22: =J15-J22 -> 612033
B23: Equipment/Machinery/Furniture | G23: 1715524 | H23: 449375 | I23: -158951 | J23: =SUM(G23:I23) -> 2005948 | K23: =J16-J23 -> 1999528
B24: Infrastructure/Roads | G24: 8358533 | H24: 1646553 | J24: =SUM(G24:I24) -> 10005086 | K24: =J17-J24 -> 7717383
D25: Total accumulated depreciation | G25: =SUM(G21:G24) -> 13938745 | H25: =SUM(H21:H24) -> 2419567 | I25: =SUM(I21:I24) -> -158951 | J25: =SUM(J21:J24) -> 16199361
B27: Total capital assets being depreciated, net | G27: =G18-G25 -> 15327731 | H27: =H18-H25 -> -45243 | I27: =I18-I25 -> 0 | J27: =J18-J25 -> 15282488
B29: Governmental activities capital assets, net | G29: =G27+G11 -> 16123674 | H29: =H27+H11 -> 772666 | I29: =I27+I11 -> -496712 | J29: =J27+J11 -> 16399628 | K29: =SUM(K9:K24) -> 16399628

Sheet Jefferson Davis
C1: JEFFERSON DAVIS PARISH POLICE JURY
C2: Capital Assets
C3: For the Year Ended December 31, 2013
F6: Balance 12/31/12 | G6: Additions | H6: Deletions & Adjustments | I6: Transfers | J6: Balance 12/31/13 | K6: Cross Sectional
A7: Governmental Activities:
B8: Capital assets, not being depreciated:
B9: Land | F9: 436905 | G9: 88800 | J9: =SUM(F9:I9) -> 525705 | K9: =SUM(J9) -> 525705
B10: Construction in progress | F10: 595916 | G10: 45312 | I10: -553221 | J10: =SUM(F10:I10) -> 88007 | K10: =SUM(J10) -> 88007
C11: Capital Assets Non-depreciable | F11: =SUM(F9:F10) -> 1032821 | G11: =SUM(G9:G10) -> 134112 | H11: =SUM(H9:H10) -> 0 | I11: =SUM(I9:I10) -> -553221 | J11: =SUM(J9:J10) -> 613712
B13: Capital assets being depreciated:
B14: Buildings and improvements | F14: 12583050 | G14: 70989 | J14: =SUM(F14:I14) -> 12654039
B15: Vehicles | F15: 4976735 | G15: 61475 | H15: -133557 | I15: 553221 | J15: =SUM(F15:I15) -> 5457874
B16: Maintenance and equipment | F16: 2272472 | G16: 90556 | H16: -133885 | J16: =SUM(F16:I16) -> 2229143
B17: Machinery and equipment | F17: 1556951 | G17: 78036 | H17: -15710 | J17: =SUM(F17:I17) -> 1619277
B18: Office furniture and equipment | F18: 336986 | G18: 1949 | J18: =SUM(F18:I18) -> 338935
B19: Sewer and sewer improvements | F19: 318782 | J19: =SUM(F19:I19) -> 318782
B20: Infrastructure | F20: 22176351 | G20: 1726216 | J20: =SUM(F20:I20) -> 23902567
C21: Total Capital Assets--Depreciable | F21: =SUM(F14:F20) -> 44221327 | G21: =SUM(G14:G20) -> 2029221 | H21: =SUM(H14:H20) -> -283152 | I21: =SUM(I14:I20) -> 553221 | J21: =SUM(J14:J20) -> 46520617
A23: Accumulated Depreciation
B24: Buildings and improvements | F24: 3625848 | G24: 399175 | J24: =SUM(F24:I24) -> 4025023 | K24: =J14-J24 -> 8629016
B25: Vehicles | F25: 2536409 | G25: 333535 | H25: -64555 | J25: =SUM(F25:I25) -> 2805389 | K25: =J15-J25 -> 2652485
B26: Maintenance equipment | F26: 1190339 | G26: 141505 | H26: -85755 | J26: =SUM(F26:I26) -> 1246089 | K26: =J16-J26 -> 983054
B27: Machinery and equipment | F27: 1196002 | G27: 93920 | H27: -15710 | J27: =SUM(F27:I27) -> 1274212 | K27: =J17-J27 -> 345065
B28: Office furniture and equipment | F28: 242074 | G28: 26534 | J28: =SUM(F28:I28) -> 268608 | K28: =J18-J28 -> 70327
B29: Sewer and sewer improvements | F29: 63658 | G29: 7970 | J29: =SUM(F29:I29) -> 71628 | K29: =J19-J29 -> 247154
B30: Infrastructure | F30: 3099207 | G30: 779259 | J30: =SUM(F30:I30) -> 3878466 | K30: =J20-J30 -> 20024101
C31: Total accumulated depreciation | F31: =SUM(F24:F30) -> 11953537 | G31: =SUM(G24:G30) -> 1781898 | H31: =SUM(H24:H30) -> -166020 | I31: =SUM(I24:I30) -> 0 | J31: =SUM(J24:J30) -> 13569415
C32: Net Depreciable Capital Assets | F32: =F21-F31 -> 32267790 | G32: =G21-G31 -> 247323 | H32: =H21-H31 -> -117132 | I32: =I21-I31 -> 553221 | J32: =J21-J31 -> 32951202
C34: Net Capital Assets | F34: =F32+F11 -> 33300611 | G34: =G32+G11 -> 381435 | H34: =H32+H11 -> -117132 | I34: =I32+I11 -> 0 | J34: =J32+J11 -> 33564914 | K34: =SUM(K24:K30,K9:K10) -> 33564914

Sheet Jefferson
D1: JEFFERSON PARISH POLICE JURY
D2: Capital Assets
D3: For the Year Ended December 31, 2013
G4: (amounts in thousands)
I6: Beginning Balance | J6: Increases | K6: Decreases | L6: Completed Construction | M6: Transfers (To) From Other Funds | N6: Ending Balance | O6: Cross Sectional
A8: Primary Government
A9: Government Activities:
A10: Capital assets, not being depreciated:
B11: Land and land improvements | I11: 59236000 | J11: 0 | K11: 0 | L11: 5038000 | M11: 0 | N11: =SUM(I11:M11) -> 64274000 | O11: =SUM(N11) -> 64274000
B12: Construction in progress | I12: 162686000 | J12: 111186000 | K12: 0 | L12: -86196000 | M12: -8769000 | N12: =SUM(I12:M12) -> 178907000 | O12: =SUM(N12) -> 178907000
C13: Total assets not being depreciated | I13: =SUM(I11:I12) -> 221922000 | J13: =SUM(J11:J12) -> 111186000 | K13: =SUM(K11:K12) -> 0 | L13: =SUM(L11:L12) -> -81158000 | M13: =SUM(M11:M12) -> -8769000 | N13: =SUM(N11:N12) -> 243181000
A15: Capital assets being depreciated:
B16: Buildings | I16: 378812000 | J16: 0 | K16: 0 | L16: 2176000 | M16: 0 | N16: =SUM(I16:M16) -> 380988000
B17: Improvements other than buildings | I17: 179678000 | J17: 0 | K17: 0 | L17: 7884000 | M17: 0 | N17: =SUM(I17:M17) -> 187562000
B18: Vehicles | I18: 57275000 | J18: 4466000 | K18: -4349000 | L18: 0 | M18: 1200000 | N18: =SUM(I18:M18) -> 58592000
B19: Machinery and equipment | I19: 250521000 | J19: 1361000 | K19: -2201000 | L19: 91000 | M19: 88000 | N19: =SUM(I19:M19) -> 249860000
B20: Infrastructure | I20: 2924471000 | J20: 0 | K20: 0 | L20: 71007000 | M20: 0 | N20: =SUM(I20:M20) -> 2995478000
C21: Total capital assets being depreciated | I21: =SUM(I16:I20) -> 3790757000 | J21: =SUM(J16:J20) -> 5827000 | K21: =SUM(K16:K20) -> -6550000 | L21: =SUM(L16:L20) -> 81158000 | M21: =SUM(M16:M20) -> 1288000 | N21: =SUM(N16:N20) -> 3872480000
A22: Less accumulated depreciation for:
B23: Buildings | I23: -159176000 | J23: -10016000 | K23: 0 | L23: 0 | M23: 0 | N23: =SUM(I23:M23) -> -169192000 | O23: =SUM(N23,N16) -> 211796000
B24: Improvements other than buildings | I24: -69203000 | J24: -7387000 | K24: 0 | L24: 0 | M24: 0 | N24: =SUM(I24:M24) -> -76590000 | O24: =SUM(N24,N17) -> 110972000
B25: Vehicles | I25: -41672000 | J25: -5652000 | K25: 4254000 | L25: 0 | M25: -1183000 | N25: =SUM(I25:M25) -> -44253000 | O25: =SUM(N25,N18) -> 14339000
B26: Machinery and equipment | I26: -202856000 | J26: -3932000 | K26: 2111000 | L26: 0 | M26: -73000 | N26: =SUM(I26:M26) -> -204750000 | O26: =SUM(N26,N19) -> 45110000
B27: Infrastructure | I27: -2420867000 | J27: -26007000 | K27: 0 | L27: 0 | M27: 0 | N27: =SUM(I27:M27) -> -2446874000 | O27: =SUM(N27,N20) -> 548604000
C28: Total accumulated depreciation | I28: =SUM(I23:I27) -> -2893774000 | J28: =SUM(J23:J27) -> -52994000 | K28: =SUM(K23:K27) -> 6365000 | L28: =SUM(L23:L27) -> 0 | M28: =SUM(M23:M27) -> -1256000 | N28: =SUM(N23:N27) -> -2941659000
B29: Total capital assets being depreciated, net | I29: =I21-I28 -> 6684531000 | J29: =J21-J28 -> 58821000 | K29: =K21-K28 -> -12915000 | L29: =L21-L28 -> 81158000 | M29: =M21-M28 -> 2544000 | N29: =SUM(N28,N21) -> 930821000
B30: Governmental activities capital assets, net | I30: =I13+I29 -> 6906453000 | J30: =J13+J29 -> 170007000 | K30: =K13+K29 -> -12915000 | L30: =L13+L29 -> 0 | M30: =M13+M29 -> -6225000 | N30: =N13+N29 -> 1174002000 | O30: =SUM(O23:O27,O11:O12) -> 1174002000
I33: Beginning Balance | J33: Increases | K33: Decreases | L33: Completed Construction | M33: Transfers (To) From Other Funds | N33: Ending Balance
A35: Business-type Activities:
A36: Capital assets not being depreciated:
B37: Land and land improvements | I37: 13591000 | J37: 0 | K37: 0 | L37: 0 | M37: 0 | N37: =SUM(I37:M37) -> 13591000 | O37: =SUM(N37) -> 13591000
B38: Construction in progress | I38: 5768000 | J38: 13409000 | K38: 0 | L38: -16065000 | M38: 0 | N38: =SUM(I38:M38) -> 3112000 | O38: =SUM(N38) -> 3112000
C39: Total assets not being depreciated | I39: =SUM(I37:I38) -> 19359000 | J39: =SUM(J37:J38) -> 13409000 | K39: =SUM(K37:K38) -> 0 | L39: =SUM(L37:L38) -> -16065000 | M39: =SUM(M37:M38) -> 0 | N39: =SUM(N37:N38) -> 16703000
A41: Capital assets being depreciated:
B42: Buildings | I42: 23293000 | J42: 0 | K42: 0 | L42: 0 | M42: 0 | N42: =SUM(I42:M42) -> 23293000
B43: Collection and distribution systems | I43: 609135000 | J43: 0 | K43: 0 | L43: 16065000 | M43: 3462000 | N43: =SUM(I43:M43) -> 628662000
B44: Plants | I44: 260269000 | J44: 0 | K44: 0 | L44: 0 | M44: 0 | N44: =SUM(I44:M44) -> 260269000
B45: Improvements other than buildings | I45: 10449000 | J45: 0 | K45: 0 | L45: 0 | M45: 5307000 | N45: =SUM(I45:M45) -> 15756000
B46: Machinery and equipment | I46: 8847000 | J46: 28000 | K46: -38000 | L46: 0 | M46: -58000 | N46: =SUM(I46:M46) -> 8779000
B47: Vehicles | I47: 11488000 | J47: 939000 | K47: -93000 | L47: 0 | M47: -688000 | N47: =SUM(I47:M47) -> 11646000
C48: Total capital assets being depreciated | I48: =SUM(I42:I47) -> 923481000 | J48: =SUM(J42:J47) -> 967000 | K48: =SUM(K42:K47) -> -131000 | L48: =SUM(L42:L47) -> 16065000 | M48: =SUM(M42:M47) -> 8023000 | N48: =SUM(N42:N47) -> 948405000
A49: Less accumulated depreciation for:
B50: Buildings | I50: -9558000 | J50: -434000 | K50: 0 | L50: 0 | M50: 0 | N50: =SUM(I50:M50) -> -9992000 | O50: =SUM(N50,N42) -> 13301000
B51: Collection and distribution systems | I51: -257879000 | J51: -13984000 | K51: 0 | L51: 0 | M51: 0 | N51: =SUM(I51:M51) -> -271863000 | O51: =SUM(N51,N43) -> 356799000
B52: Plants | I52: -109585000 | J52: -5845000 | K52: 0 | L52: 0 | M52: 0 | N52: =SUM(I52:M52) -> -115430000 | O52: =SUM(N52,N44) -> 144839000
B53: Improvements other than buildings | I53: -4322000 | J53: -512000 | K53: 0 | L53: 0 | M53: 0 | N53: =SUM(I53:M53) -> -4834000 | O53: =SUM(N53,N45) -> 10922000
B54: Machinery and equipment | I54: -7779000 | J54: -351000 | K54: 38000 | L54: 0 | M54: 76000 | N54: =SUM(I54:M54) -> -8016000 | O54: =SUM(N54,N46) -> 763000
B55: Vehicles | I55: -8378000 | J55: -1186000 | K55: 93000 | L55: 0 | M55: 1155000 | N55: =SUM(I55:M55) -> -8316000 | O55: =SUM(N55,N47) -> 3330000
C56: Total accumulated depreciation | I56: =SUM(I50:I55) -> -397501000 | J56: =SUM(J50:J55) -> -22312000 | K56: =SUM(K50:K55) -> 131000 | L56: =SUM(L50:L55) -> 0 | M56: =SUM(M50:M55) -> 1231000 | N56: =SUM(N50:N55) -> -418451000
B57: Total capital assets being depreciated, net | I57: =SUM(I56,I48) -> 525980000 | J57: =SUM(J56,J48) -> -21345000 | K57: =SUM(K56,K48) -> 0 | L57: =SUM(L56,L48) -> 16065000 | M57: =SUM(M56,M48) -> 9254000 | N57: =SUM(N56,N48) -> 529954000
B58: Business-type activities capital assets, net | I58: =I39+I57 -> 545339000 | J58: =J39+J57 -> -7936000 | K58: =K39+K57 -> 0 | L58: =L39+L57 -> 0 | M58: =M39+M57 -> 9254000 | N58: =N39+N57 -> 546657000 | O58: =SUM(O50:O55,O37:O38) -> 546657000

Sheet LaSalle
D1: LASALLE PARISH POLICE JURY
D2: Capital Assets
D3: For the Year Ended December 31, 2013
I5: Beginning Balance | J5: Increases | K5: Decreases | L5: Ending Balance | M5: Cross Sectional
A7: Police Jury:
A8: Government Activities:
A9: Capital assets, not being depreciated:
B10: Land | I10: 477208 | J10: 0 | K10: 0 | L10: =SUM(I10:K10) -> 477208 | M10: =SUM(L10) -> 477208
C11: Total assets not being depreciated | I11: =SUM(I10:I10) -> 477208 | J11: =SUM(J10:J10) -> 0 | K11: =SUM(K10:K10) -> 0 | L11: =SUM(L10:L10) -> 477208
A13: Capital assets being depreciated:
B14: Infrastrucure - roads and bridges | I14: 76971471 | J14: 271974 | K14: 0 | L14: =SUM(I14:K14) -> 77243445
B15: Buildings and improvements | I15: 1971980 | J15: 426774 | K15: -10925 | L15: =SUM(I15:K15) -> 2387829
B16: Office furniture and equipment | I16: 324575 | J16: 25610 | K16: -2900 | L16: =SUM(I16:K16) -> 347285
B17: Heavy equipment | I17: 2650998 | J17: 336679 | K17: -630604 | L17: =SUM(I17:K17) -> 2357073
B18: Other equipment | I18: 285625 | J18: 6000 | K18: -190377 | L18: =SUM(I18:K18) -> 101248
B19: Vehicles | I19: 302197 | J19: 0 | K19: -5000 | L19: =SUM(I19:K19) -> 297197
C20: Total capital assets being depreciated | I20: =SUM(I14:I19) -> 82506846 | J20: =SUM(J14:J19) -> 1067037 | K20: =SUM(K14:K19) -> -839806 | L20: =SUM(L14:L19) -> 82734077
B22: Governmental activities capital assets, net | I22: =I20+I11 -> 82984054 | J22: =J20+J11 -> 1067037 | K22: =K20+K11 -> -839806 | L22: =L20+L11 -> 83211285
I25: Beginning Balance | J25: Increases | K25: Decreases | L25: Ending Balance
A26: Library:
A27: Capital assets not being depreciated:
B28: Land | I28: 23810 | J28: 0 | K28: 0 | L28: =SUM(I28:K28) -> 23810 | M28: =SUM(L28) -> 23810
B29: Construction in progress | I29: 136855 | J29: 517483 | K29: -654338 | L29: =SUM(I29:K29) -> 0 | M29: =SUM(L29) -> 0
C30: Total assets not being depreciated | I30: =SUM(I28:I29) -> 160665 | J30: =SUM(J28:J29) -> 517483 | K30: =SUM(K28:K29) -> -654338 | L30: =SUM(L28:L29) -> 23810
A32: Capital assets being depreciated:
B33: Books | I33: 494242 | J33: 41577 | K33: -21581 | L33: =SUM(I33:K33) -> 514238 | M33: =L33 -> 514238
B34: Vehicles | I34: 44382 | J34: 0 | K34: 0 | L34: =SUM(I34:K34) -> 44382 | M34: =L34 -> 44382
B35: Buildings | I35: 308405 | J35: 548474 | K35: -43313 | L35: =SUM(I35:K35) -> 813566 | M35: =L35 -> 813566
B36: Furniture | I36: 51106 | J36: 96056 | K36: -11900 | L36: =SUM(I36:K36) -> 135262 | M36: =L36 -> 135262
B37: Equipment | I37: 59378 | J37: 11302 | K37: -5609 | L37: =SUM(I37:K37) -> 65071 | M37: =L37 -> 65071
C38: Total library assets being depreciated | I38: =SUM(I33:I37) -> 957513 | J38: =SUM(J33:J37) -> 697409 | K38: =SUM(K33:K37) -> -82403 | L38: =SUM(L33:L37) -> 1572519
A39: Less accumulated depreciation for:
B40: Infrastructure - roads and bridges | I40: -74406368 | J40: -138318 | K40: 0 | L40: =SUM(I40:K40) -> -74544686 | M40: =L14+L40 -> 2698759
B41: Buildings and improvements | I41: -1487424 | J41: -65811 | K41: 50720 | L41: =SUM(I41:K41) -> -1502515 | M41: =L15+L41 -> 885314
B42: Office furniture and equipment | I42: -411694 | J42: -31802 | K42: 200225 | L42: =SUM(I42:K42) -> -243271 | M42: =L16+L42 -> 104014
B43: Heavy equipment | I43: -2318606 | J43: -75248 | K43: 498870 | L43: =SUM(I43:K43) -> -1894984 | M43: =L17+L43 -> 462089
B44: Other equipment | I44: -222123 | J44: -17363 | K44: 8506 | L44: =SUM(I44:K44) -> -230980 | M44: =L18+L44 -> -129732
B45: Vehicles | I45: -136532 | J45: -47250 | K45: 5000 | L45: =SUM(I45:K45) -> -178782 | M45: =L19+L45 -> 118415
B46: Books | I46: -355058 | J46: -32757 | K46: 21581 | L46: =SUM(I46:K46) -> -366234 | M46: =L46 -> -366234
C47: Total accumulated depreciation | I47: =SUM(I40:I46) -> -79337805 | J47: =SUM(J40:J46) -> -408549 | K47: =SUM(K40:K46) -> 784902 | L47: =SUM(L40:L46) -> -78961452
B48: Total capital assets being depreciated, net | I48: =I47+I38+I20 -> 4126554 | J48: =J47+J38+J20 -> 1355897 | K48: =K47+K38+K20 -> -137307 | L48: =L47+L38+L20 -> 5345144
B50: Business-type activities capital assets, net | I50: =I48+I30+I11 -> 4764427 | J50: =J48+J30+J11 -> 1873380 | K50: =K48+K30+K11 -> -791645 | L50: =L48+L30+L11 -> 5846162 | M50: =SUM(M10:M46) -> 5846162

Sheet Cross Sectional
B1: Louisiana Counties
B2: 2013 Capital Assets, Net of Accumulated Depreciation | O2: Governmental Activities | AE2: Business-Type Activities | AH2: Grand Total
B3: Governmental Activities | O3: Capital Assets | R3: Business-Type Activities | AE3: Capital Assets | AH3: (Governmental + Business)
B4: Land | C4: Construction in progress | D4: Other non-depreciable | E4: Buildings and improvements | F4: Improvements other than buildings | G4: Machinery and equipment | H4: Other depreciable | I4: Books and periodicals | J4: Furniture and fixtures | K4: Vehicles | L4: Bridges | M4: Leased Property Under Capital Leases | N4: Infrastructure | O4: Total (Net) | P4: Check | Q4: Okay? | R4: Land | S4: Construction in progress | T4: Other non-depreciable | U4: Buildings and improvements | V4: Improvements other than buildings | W4: Machinery and equipment | X4: Other depreciable | Y4: Books and periodicals | Z4: Furniture and fixtures | AA4: Vehicles | AB4: Bridges | AC4: Leased Property Under Capital Leases | AD4: Infrastructure | AE4: Total (Net) | AF4: Check | AG4: Okay? | AI4: Check | AJ4: Okay?
A5: Acadia | B5: =Acadia!M10 -> 1329008 | C5: =Acadia!M11 -> 10247945 | D5: 0 | E5: =Acadia!M22 -> 17694464 | F5: =Acadia!M24 -> 359357 | G5: =Acadia!M23 -> 5453244 | H5: 0 | I5: 0 | J5: 0 | K5: 0 | L5: 0 | M5: 0 | N5: =Acadia!M25 -> 19386268 | O5: =Acadia!M28 -> 54470286 | P5: =SUM(B5:N5) -> 54470286 | Q5: =IF(O5="","Blank",IF(O5=P5,"Yes","No")) -> Yes | AF5: =SUM(R5:AD5) -> 0 | AG5: =IF(AE5="","Blank",IF(AE5=AF5,"Yes","No")) -> Blank | AH5: =Acadia!M28 -> 54470286 | AI5: =O5+AE5 -> 54470286 | AJ5: =IF(AH5="","Blank",IF(AH5=AI5,"Yes","No")) -> Yes
A6: Allen | B6: =Allen!K10 -> 572300 | C6: 0 | D6: 0 | E6: =Allen!K25 -> 2760230 | F6: =Allen!K26 -> 3671842 | G6: =Allen!K29 -> 1024328 | H6: 0 | I6: 0 | J6: =Allen!K27 -> 78403 | K6: =Allen!K28 -> 200490 | L6: 0 | M6: 0 | N6: =Allen!K30 -> 16358162 | O6: =Allen!K36 -> 24665755 | P6: =SUM(B6:N6) -> 24665755 | Q6: =IF(O6="","Blank",IF(O6=P6,"Yes","No")) -> Yes | AF6: =SUM(R6:AD6) -> 0 | AG6: =IF(AE6="","Blank",IF(AE6=AF6,"Yes","No")) -> Blank | AH6: =Allen!K36 -> 24665755 | AI6: =O6+AE6 -> 24665755 | AJ6: =IF(AH6="","Blank",IF(AH6=AI6,"Yes","No")) -> Yes
A7: Ascension | B7: =Ascension!M9 -> 17313 | C7: =Ascension!M10 -> 55787 | D7: 0 | E7: =Ascension!M25 -> 41802 | F7: 0 | G7: =Ascension!M27 -> 2677 | H7: 0 | I7: =Ascension!M29 -> 967 | J7: =Ascension!M28 -> 482 | K7: =Ascension!M26 -> 4175 | L7: 0 | M7: 0 | N7: =Ascension!M30 -> 86362 | O7: =Ascension!M36 -> 209565 | P7: =SUM(B7:N7) -> 209565 | Q7: =IF(O7="","Blank",IF(O7=P7,"Yes","No")) -> Yes | R7: =Ascension!M42 -> 670 | S7: =Ascension!M43 -> 271 | T7: 0 | U7: 0 | V7: 0 | W7: 0 | X7: =Ascension!M57 -> 5763 | Y7: 0 | Z7: 0 | AA7: 0 | AB7: 0 | AC7: 0 | AD7: =Ascension!M55+Ascension!M56 -> 4189 | AE7: =Ascension!M63 -> 10893 | AF7: =SUM(R7:AD7) -> 10893 | AG7: =IF(AE7="","Blank",IF(AE7=AF7,"Yes","No")) -> Yes | AH7: =Ascension!M63+Ascension!M36 -> 220458 | AI7: =O7+AE7 -> 220458 | AJ7: =IF(AH7="","Blank",IF(AH7=AI7,"Yes","No")) -> Yes
A8: Assumption | B8: =Assumption!N8 -> 2213381 | C8: 0 | D8: 0 | E8: =Assumption!N9 -> 16396346 | F8: =Assumption!N10 -> 8078091.9 | G8: =Assumption!N13 -> 5012768.5 | H8: =Assumption!N14 -> 488571 | I8: 0 | J8: 0 | K8: 0 | L8: =Assumption!N12 -> 407084.6 | M8: 0 | N8: =Assumption!N11 -> 11136888 | O8: =Assumption!N19 -> 43733131 | P8: =SUM(B8:N8) -> 43733131 | Q8: =IF(O8="","Blank",IF(O8=P8,"Yes","No")) -> Yes | AF8: =SUM(R8:AD8) -> 0 | AG8: =IF(AE8="","Blank",IF(AE8=AF8,"Yes","No")) -> Blank | AH8: =Assumption!N19 -> 43733131 | AI8: =O8+AE8 -> 43733131 | AJ8: =IF(AH8="","Blank",IF(AH8=AI8,"Yes","No")) -> Yes
A9: Avoyelles | B9: =Avoyelles!K9 -> 584787 | C9: =Avoyelles!K10 -> 1083069 | D9: 0 | E9: =Avoyelles!K23 -> 2728965 | F9: 0 | G9: =Avoyelles!K24+Avoyelles!K26 -> 791620 | H9: 0 | I9: 0 | J9: 0 | K9: 0 | L9: 0 | M9: 0 | N9: =Avoyelles!K25 -> 43801 | O9: =Avoyelles!K32 -> 5232242 | P9: =SUM(B9:N9) -> 5232242 | Q9: =IF(O9="","Blank",IF(O9=P9,"Yes","No")) -> Yes | AF9: =SUM(R9:AD9) -> 0 | AG9: =IF(AE9="","Blank",IF(AE9=AF9,"Yes","No")) -> Blank | AH9: =Avoyelles!K32 -> 5232242 | AI9: =O9+AE9 -> 5232242 | AJ9: =IF(AH9="","Blank",IF(AH9=AI9,"Yes","No")) -> Yes
A10: Beauregard | B10: =Beauregard!N10 -> 806735 | C10: =Beauregard!N11 -> 790379 | D10: 0 | E10: =Beauregard!N21 -> 9930994 | F10: 0 | G10: =Assumption!N15 -> 0 | H10: =Assumption!N16 -> 0 | I10: 0 | J10: =Beauregard!N23 -> 3990003 | K10: 0 | L10: 0 | M10: 0 | N10: =Beauregard!N22 -> 15989047 | O10: =Beauregard!N26 -> 31507158 | P10: =SUM(B10:N10) -> 31507158 | Q10: =IF(O10="","Blank",IF(O10=P10,"Yes","No")) -> Yes | AF10: =SUM(R10:AD10) -> 0 | AG10: =IF(AE10="","Blank",IF(AE10=AF10,"Yes","No")) -> Blank | AH10: =Beauregard!M26 -> 31507158 | AI10: =O10+AE10 -> 31507158 | AJ10: =IF(AH10="","Blank",IF(AH10=AI10,"Yes","No")) -> Yes
A11: Bienville | B11: =Bienville!K9 -> 660250 | C11: =Iberville!K6 -> 0 | D11: 0 | E11: =Bienville!K30 -> 13921140 | F11: 0 | G11: =Bienville!K32+Bienville!K34 -> 575348 | H11: 0 | I11: 0 | J11: =Bienville!K31 -> 415316 | K11: =Bienville!K33 -> 684844 | L11: 0 | M11: 0 | N11: =Bienville!K28+Bienville!K29 -> 6557278 | O11: =Bienville!K40 -> 22814176 | P11: =SUM(B11:N11) -> 22814176 | Q11: =IF(O11="","Blank",IF(O11=P11,"Yes","No")) -> Yes | AF11: =SUM(R11:AD11) -> 0 | AG11: =IF(AE11="","Blank",IF(AE11=AF11,"Yes","No")) -> Blank | AH11: =Bienville!K40 -> 22814176 | AI11: =O11+AE11 -> 22814176 | AJ11: =IF(AH11="","Blank",IF(AH11=AI11,"Yes","No")) -> Yes
A12: Bossier | B12: =Bossier!N10 -> 12207084 | C12: =Bossier!N11 -> 6042279 | D12: 0 | E12: =Bossier!N22 -> 84034576 | F12: =Lafayette!K18 -> 0 | G12: 0 | H12: =Lafayette!K21 -> 0 | I12: =Bossier!N25 -> 1104772 | J12: =Bossier!N24 -> 4367053 | K12: =Lafayette!K20 -> 0 | L12: 0 | M12: 0 | N12: =Bossier!N23 -> 173547703 | O12: =Bossier!N28 -> 281303467 | P12: =SUM(B12:N12) -> 281303467 | Q12: =IF(O12="","Blank",IF(O12=P12,"Yes","No")) -> Yes | R12: =Bossier!N35 -> 1301778 | S12: =Bossier!N37 -> 3279798 | T12: =Bossier!N36 -> 1226000 | U12: =Bossier!N47 -> 2863000 | V12: 0 | W12: 0 | X12: 0 | Y12: 0 | Z12: =Bossier!N46 -> 13301000 | AA12: 0 | AB12: 0 | AC12: 0 | AD12: =Lafayette!K43+Lafayette!K44+Lafayette!K45 -> 0 | AE12: =Bossier!N50 -> 21971576 | AF12: =SUM(R12:AD12) -> 21971576 | AG12: =IF(AE12="","Blank",IF(AE12=AF12,"Yes","No")) -> Yes | AH12: =Bossier!M28+Bossier!M50 -> 303275043 | AI12: =O12+AE12 -> 303275043 | AJ12: =IF(AH12="","Blank",IF(AH12=AI12,"Yes","No")) -> Yes
A13: Caddo | B13: =Caddo!N10 -> 14578409 | C13: =Caddo!N11+Caddo!N12 -> 13982884 | D13: 0 | E13: =Caddo!N22 -> 52889687 | F13: =Jefferson!O21 -> 0 | G13: =Caddo!N23 -> 11851594 | H13: 0 | I13: 0 | J13: 0 | K13: =Jefferson!O22 -> 0 | L13: 0 | M13: 0 | N13: =Caddo!N24 -> 116966351 | O13: =Caddo!N27 -> 210268925 | P13: =SUM(B13:N13) -> 210268925 | Q13: =IF(O13="","Blank",IF(O13=P13,"Yes","No")) -> Yes | AF13: =SUM(R13:AD13) -> 0 | AG13: =IF(AE13="","Blank",IF(AE13=AF13,"Yes","No")) -> Blank | AH13: =Caddo!M27 -> 210268925 | AI13: =O13+AE13 -> 210268925 | AJ13: =IF(AH13="","Blank",IF(AH13=AI13,"Yes","No")) -> Yes
A14: Calcasieu | B14: =Calcasieu!M9 -> 17544546 | C14: =Calcasieu!M10 -> 16852520 | D14: =Calcasieu!M11 -> 383317282 | E14: =Calcasieu!M21 -> 72678854 | F14: =Jefferson!O21 -> 0 | G14: =Calcasieu!M22 -> 12115797 | H14: 0 | I14: 0 | J14: 0 | K14: =Jefferson!O22 -> 0 | L14: =Calcasieu!M23 -> 7934446 | M14: 0 | N14: 0 | O14: =Calcasieu!M26 -> 510443445 | P14: =SUM(B14:N14) -> 510443445 | Q14: =IF(O14="","Blank",IF(O14=P14,"Yes","No")) -> Yes | R14: =Calcasieu!M32 -> 227920 | S14: =Calcasieu!M33 -> 718820 | T14: 0 | U14: =Calcasieu!M45 -> 20320 | V14: =Calcasieu!M44 -> 6880833 | W14: =Calcasieu!M47 -> 38722 | X14: 0 | Y14: 0 | Z14: 0 | AA14: 0 | AB14: 0 | AC14: 0 | AD14: =Calcasieu!M46 -> 1360644 | AE14: =Calcasieu!M50 -> 9247259 | AF14: =SUM(R14:AD14) -> 9247259 | AG14: =IF(AE14="","Blank",IF(AE14=AF14,"Yes","No")) -> Yes | AH14: =Calcasieu!L50+Calcasieu!L26 -> 519690704 | AI14: =O14+AE14 -> 519690704 | AJ14: =IF(AH14="","Blank",IF(AH14=AI14,"Yes","No")) -> Yes
A15: Caldwell | B15: =Caldwell!K9 -> 420095 | C15: =Caldwell!K10 -> 7932354 | D15: 0 | E15: =Caldwell!K31 -> 376134 | F15: =Caldwell!K32 -> 529880 | G15: =Caldwell!K33+Caldwell!K35 -> 470657 | H15: 0 | I15: 0 | J15: =Caldwell!K36 -> 129155 | K15: =Caldwell!K34 -> 113361 | L15: 0 | M15: 0 | N15: =Caldwell!K29+Caldwell!K30 -> 1747530 | O15: =Caldwell!K42 -> 11719166 | P15: =SUM(B15:N15) -> 11719166 | Q15: =IF(O15="","Blank",IF(O15=P15,"Yes","No")) -> Yes | AF15: =SUM(R15:AD15) -> 0 | AG15: =IF(AE15="","Blank",IF(AE15=AF15,"Yes","No")) -> Blank | AH15: =Caldwell!J42 -> 11719166 | AI15: =O15+AE15 -> 11719166 | AJ15: =IF(AH15="","Blank",IF(AH15=AI15,"Yes","No")) -> Yes
A16: Cameron | B16: =Cameron!K7 -> 1381390 | C16: =Cameron!K8 -> 20795365 | D16: 0 | E16: =Cameron!K9 -> 29213490 | F16: 0 | G16: =Cameron!K11 -> 14957980 | H16: 0 | I16: =Cameron!K10 -> 579254.48 | J16: 0 | K16: 0 | L16: 0 | M16: 0 | N16: =Cameron!K12 -> 44826331 | O16: =Cameron!K18 -> 111753810 | P16: =SUM(B16:N16) -> 111753810 | Q16: =IF(O16="","Blank",IF(O16=P16,"Yes","No")) -> Yes | AF16: =SUM(R16:AD16) -> 0 | AG16: =IF(AE16="","Blank",IF(AE16=AF16,"Yes","No")) -> Blank | AH16: =Cameron!J18 -> 111753810 | AI16: =O16+AE16 -> 111753810 | AJ16: =IF(AH16="","Blank",IF(AH16=AI16,"Yes","No")) -> Yes
A17: Catahoula | B17: =Catahoula!M9 -> 112200 | C17: =Iberville!K6 -> 0 | D17: 0 | E17: =Catahoula!M27+Catahoula!M28 -> 1854325 | F17: 0 | G17: =Catahoula!M30+Catahoula!M29 -> 546162 | H17: 0 | I17: =Catahoula!M32 -> 78577 | J17: 0 | K17: =Catahoula!M31 -> 250198 | L17: 0 | M17: 0 | N17: =Catahoula!M26 -> 3021354 | O17: =Catahoula!M38 -> 5862816 | P17: =SUM(B17:N17) -> 5862816 | Q17: =IF(O17="","Blank",IF(O17=P17,"Yes","No")) -> Yes | R17: =Iberville!J21 -> 0 | S17: =Iberville!J22 -> 0 | T17: 0 | U17: =Catahoula!M56 -> 61311 | V17: 0 | W17: =Iberville!J29 -> 0 | X17: 0 | Y17: 0 | Z17: =Catahoula!M57 -> 27305 | AA17: 0 | AB17: 0 | AC17: 0 | AD17: 0 | AE17: =Catahoula!M63 -> 88616 | AF17: =SUM(R17:AD17) -> 88616 | AG17: =IF(AE17="","Blank",IF(AE17=AF17,"Yes","No")) -> Yes | AH17: =Catahoula!L63+Catahoula!L38 -> 5951432 | AI17: =O17+AE17 -> 5951432 | AJ17: =IF(AH17="","Blank",IF(AH17=AI17,"Yes","No")) -> Yes
A18: Claiborne | B18: =Claiborne!L10+Claiborne!L11+Claiborne!L12+Claiborne!L13 -> 98840 | C18: =Claiborne!L14 -> 2341387 | D18: 0 | E18: =Claiborne!L50 -> 867787 | F18: =Claiborne!L49 -> 1932 | G18: =Claiborne!L51+Claiborne!L52 -> 1129816 | H18: =Claiborne!L56+Claiborne!L57+Claiborne!L58+Claiborne!L60+Claiborne!L61+Claiborne!L62+Claiborne!L63 -> 108461 | I18: =Claiborne!L65+Claiborne!L66+Claiborne!L67+Claiborne!L68 -> 375754 | J18: =Claiborne!L54 -> 164773 | K18: =Claiborne!L53 -> 131663 | L18: 0 | M18: 0 | N18: =Claiborne!L47+Claiborne!L48 -> 1839394 | O18: =Claiborne!L74 -> 7059807 | P18: =SUM(B18:N18) -> 7059807 | Q18: =IF(O18="","Blank",IF(O18=P18,"Yes","No")) -> Yes | R18: 0 | S18: 0 | T18: 0 | U18: 0 | V18: 0 | W18: 0 | X18: 0 | Y18: 0 | Z18: 0 | AA18: 0 | AB18: 0 | AC18: 0 | AD18: 0 | AF18: =SUM(R18:AD18) -> 0 | AG18: =IF(AE18="","Blank",IF(AE18=AF18,"Yes","No")) -> Blank | AH18: =Claiborne!K74 -> 7059807 | AI18: =O18+AE18 -> 7059807 | AJ18: =IF(AH18="","Blank",IF(AH18=AI18,"Yes","No")) -> Yes
A19: Concordia | B19: =Concordia!L8 -> 7038 | C19: 0 | D19: 0 | E19: =Concordia!L18 -> 2925164 | F19: 0 | G19: =Concordia!L20+Concordia!L21 -> 1753839 | H19: =Concordia!L24 -> 0 | I19: 0 | J19: =Concordia!L19 -> 217825 | K19: 0 | L19: =Concordia!L22 -> 6016665 | M19: 0 | N19: 0 | O19: =Concordia!L29 -> 10920531 | P19: =SUM(B19:N19) -> 10920531 | Q19: =IF(O19="","Blank",IF(O19=P19,"Yes","No")) -> Yes | R19: 0 | S19: 0 | T19: 0 | U19: 0 | V19: 0 | W19: 0 | X19: 0 | Y19: 0 | Z19: 0 | AA19: 0 | AB19: 0 | AC19: 0 | AD19: 0 | AF19: =SUM(R19:AD19) -> 0 | AG19: =IF(AE19="","Blank",IF(AE19=AF19,"Yes","No")) -> Blank | AH19: =Concordia!L29 -> 10920531 | AI19: =O19+AE19 -> 10920531 | AJ19: =IF(AH19="","Blank",IF(AH19=AI19,"Yes","No")) -> Yes
A20: DeSoto | B20: =DeSoto!M9 -> 1979943 | C20: =DeSoto!M10 -> 498894 | D20: 0 | E20: =DeSoto!M21 -> 15314666 | F20: =DeSoto!M22 -> 4847274 | G20: 0 | H20: 0 | I20: 0 | J20: =DeSoto!M23 -> 4506778 | K20: =Jefferson!O22 -> 0 | L20: 0 | M20: 0 | N20: =DeSoto!M24 -> 48224051 | O20: =DeSoto!M27 -> 75371606 | P20: =SUM(B20:N20) -> 75371606 | Q20: =IF(O20="","Blank",IF(O20=P20,"Yes","No")) -> Yes | R20: =DeSoto!M33 -> 10175 | S20: =Jefferson!O35 -> 0 | T20: 0 | U20: =Jefferson!O47 -> 0 | V20: 0 | W20: 0 | X20: 0 | Y20: 0 | Z20: 0 | AA20: 0 | AB20: 0 | AC20: 0 | AD20: =Jefferson!O48+Jefferson!O49 -> 0 | AE20: =DeSoto!M46 -> 10175 | AF20: =SUM(R20:AD20) -> 10175 | AG20: =IF(AE20="","Blank",IF(AE20=AF20,"Yes","No")) -> Yes | AH20: =DeSoto!L46+DeSoto!L27 -> 75381781 | AI20: =O20+AE20 -> 75381781 | AJ20: =IF(AH20="","Blank",IF(AH20=AI20,"Yes","No")) -> Yes
A21: East Baton Rouge | B21: ='East Baton Rouge'!N9 -> 11633324 | C21: ='East Baton Rouge'!N10 -> 11307751 | D21: 0 | E21: ='East Baton Rouge'!N20 -> 85962192 | F21: ='East Baton Rouge'!N21 -> 160497853 | G21: ='East Baton Rouge'!N22 -> 993528 | H21: 0 | I21: 0 | J21: 0 | K21: 0 | L21: 0 | M21: 0 | N21: 0 | O21: ='East Baton Rouge'!N25 -> 270394648 | P21: =SUM(B21:N21) -> 270394648 | Q21: =IF(O21="","Blank",IF(O21=P21,"Yes","No")) -> Yes | R21: ='East Baton Rouge'!N31 -> 80821283 | S21: ='East Baton Rouge'!N33 -> 116073934 | T21: ='East Baton Rouge'!N32 -> 58104718 | U21: ='East Baton Rouge'!N43 -> 126260108 | V21: ='East Baton Rouge'!N44 -> 1277974431 | W21: ='East Baton Rouge'!N45 -> 865280 | X21: 0 | Y21: 0 | Z21: 0 | AA21: 0 | AB21: 0 | AC21: 0 | AD21: 0 | AE21: ='East Baton Rouge'!N48 -> 1660099754 | AF21: =SUM(R21:AD21) -> 1660099754 | AG21: =IF(AE21="","Blank",IF(AE21=AF21,"Yes","No")) -> Yes | AH21: ='East Baton Rouge'!N48+'East Baton Rouge'!N25 -> 1930494402 | AI21: =O21+AE21 -> 1930494402 | AJ21: =IF(AH21="","Blank",IF(AH21=AI21,"Yes","No")) -> Yes
A22: East Carroll | B22: ='East Carroll'!K9+'East Carroll'!K10 -> 375665 | C22: ='East Carroll'!K11 -> 261764 | D22: 0 | E22: ='East Carroll'!K30 -> 1060309 | F22: =Lafayette!K19 -> 0 | G22: ='East Carroll'!K31+'East Carroll'!K33 -> 638877 | H22: 0 | I22: ='East Carroll'!K35 -> 898 | J22: ='East Carroll'!K32 -> 35478 | K22: ='East Carroll'!K34 -> 429941 | L22: 0 | M22: 0 | N22: ='East Carroll'!K37+'East Carroll'!K38+'East Carroll'!K39+'East Carroll'!K40+'East Carroll'!K24 -> 2785599 | O22: ='East Carroll'!K46 -> 5588531 | P22: =SUM(B22:N22) -> 5588531 | Q22: =IF(O22="","Blank",IF(O22=P22,"Yes","No")) -> Yes | R22: =Lafayette!K30 -> 0 | S22: =Lafayette!K31 -> 0 | T22: 0 | U22: =Lafayette!K43 -> 0 | V22: 0 | W22: 0 | X22: 0 | Y22: 0 | Z22: 0 | AA22: 0 | AB22: 0 | AC22: 0 | AD22: 0 | AF22: =SUM(R22:AD22) -> 0 | AG22: =IF(AE22="","Blank",IF(AE22=AF22,"Yes","No")) -> Blank | AH22: ='East Carroll'!J46 -> 5588531 | AI22: =O22+AE22 -> 5588531 | AJ22: =IF(AH22="","Blank",IF(AH22=AI22,"Yes","No")) -> Yes
A23: East Feliciana | B23: ='East Feliciana'!M9 -> 259230 | C23: 0 | D23: 0 | E23: ='East Feliciana'!M15 -> 5265888.1 | F23: 0 | G23: ='East Feliciana'!M19 -> 1831155.3 | H23: 0 | I23: 0 | J23: 0 | K23: 0 | L23: 0 | M23: 0 | N23: ='East Feliciana'!M23 -> 956803.22 | O23: ='East Feliciana'!M25 -> 8313076.6 | P23: =SUM(B23:N23) -> 8313076.6 | Q23: =IF(O23="","Blank",IF(O23=P23,"Yes","No")) -> Yes | AF23: =SUM(R23:AE23) -> 0 | AG23: =IF(AE23="","Blank",IF(AE23=AF23,"Yes","No")) -> Blank | AH23: ='East Feliciana'!L25 -> 8313076.6 | AI23: =O23+AE23 -> 8313076.6 | AJ23: =IF(AH23="","Blank",IF(AH23=AI23,"Yes","No")) -> Yes
A24: Evangeline | B24: =Evangeline!M10 -> 876298 | C24: =Evangeline!M11 -> 1851425 | D24: 0 | E24: =Evangeline!M21 -> 7076584 | F24: 0 | G24: =Evangeline!M24 -> 2410234 | H24: =Livingston!M17 -> 0 | I24: 0 | J24: 0 | K24: =Evangeline!M23 -> 125188 | L24: 0 | M24: 0 | N24: =Evangeline!M22 -> 12323768 | O24: =Evangeline!M27 -> 24663497 | P24: =SUM(B24:N24) -> 24663497 | Q24: =IF(O24="","Blank",IF(O24=P24,"Yes","No")) -> Yes | R24: 0 | S24: =Livingston!M30 -> 0 | T24: 0 | U24: 0 | V24: 0 | W24: 0 | X24: 0 | Y24: 0 | Z24: 0 | AA24: 0 | AB24: 0 | AC24: 0 | AD24: =Evangeline!M38 -> 291100 | AE24: =Evangeline!M40 -> 291100 | AF24: =SUM(R24:AD24) -> 291100 | AG24: =IF(AE24="","Blank",IF(AE24=AF24,"Yes","No")) -> Yes | AH24: =Evangeline!L40+Evangeline!L27 -> 24954597 | AI24: =O24+AE24 -> 24954597 | AJ24: =IF(AH24="","Blank",IF(AH24=AI24,"Yes","No")) -> Yes
A25: Franklin | B25: =Franklin!K9 -> 390416 | C25: =Franklin!K10 -> 686392 | D25: =Franklin!K11 -> 96829 | E25: =Franklin!K28 -> 1315401 | F25: =Franklin!K29 -> 924244 | G25: =Franklin!K31+Franklin!K32 -> 612516 | H25: 0 | I25: 0 | J25: =Franklin!K30 -> 1444 | K25: =Franklin!K33 -> 102104 | L25: 0 | M25: 0 | N25: =Franklin!K26+Franklin!K27 -> 13707070 | O25: =Franklin!K38 -> 17836416 | P25: =SUM(B25:N25) -> 17836416 | Q25: =IF(O25="","Blank",IF(O25=P25,"Yes","No")) -> Yes | R25: 0 | S25: 0 | T25: 0 | U25: 0 | V25: 0 | W25: 0 | X25: 0 | Y25: 0 | Z25: 0 | AA25: 0 | AB25: 0 | AC25: 0 | AD25: 0 | AF25: =SUM(R25:AE25) -> 0 | AG25: =IF(AE25="","Blank",IF(AE25=AF25,"Yes","No")) -> Blank | AH25: =Franklin!J38 -> 17836416 | AI25: =O25+AE25 -> 17836416 | AJ25: =IF(AH25="","Blank",IF(AH25=AI25,"Yes","No")) -> Yes
A26: Grant | B26: =Grant!M11 -> 203250 | C26: =Grant!M10 -> 37900 | D26: 0 | E26: =Grant!M15 -> 1562053.7 | F26: 0 | G26: 0 | H26: 0 | I26: 0 | J26: =Grant!M16 -> 1523111.9 | K26: 0 | L26: 0 | M26: 0 | N26: =Grant!M17+Grant!M18 -> 2757162.4 | O26: =Grant!M23 -> 6083478 | P26: =SUM(B26:N26) -> 6083478 | Q26: =IF(O26="","Blank",IF(O26=P26,"Yes","No")) -> Yes | R26: 0 | S26: 0 | T26: 0 | U26: =Grant!M31 -> 1892.4625 | V26: 0 | W26: =Grant!M32 -> 56009.49 | X26: 0 | Y26: 0 | Z26: 0 | AA26: 0 | AB26: 0 | AC26: 0 | AD26: =Grant!M30 -> 299292.05 | AE26: =Grant!M37 -> 357194 | AF26: =SUM(R26:AD26) -> 357194 | AG26: =IF(AE26="","Blank",IF(AE26=AF26,"Yes","No")) -> Yes | AH26: =Grant!L37+Grant!L23 -> 6440672 | AI26: =O26+AE26 -> 6440672 | AJ26: =IF(AH26="","Blank",IF(AH26=AI26,"Yes","No")) -> Yes
A27: Iberia | B27: =Iberia!K9 -> 2466687 | C27: =Iberia!K10 -> 2989592 | D27: 0 | E27: =Iberia!K22 -> 14699347 | F27: =Iberia!K21 -> 3096 | G27: =Morehouse!N9 -> 0 | H27: 0 | I27: 0 | J27: =Iberia!K23 -> 3517241 | K27: 0 | L27: 0 | M27: 0 | N27: =Iberia!K24 -> 72261300 | O27: =Iberia!K29 -> 95937263 | P27: =SUM(B27:N27) -> 95937263 | Q27: =IF(O27="","Blank",IF(O27=P27,"Yes","No")) -> Yes | R27: 0 | S27: 0 | T27: 0 | U27: 0 | V27: 0 | W27: 0 | X27: 0 | Y27: 0 | Z27: 0 | AA27: 0 | AB27: 0 | AC27: 0 | AD27: 0 | AF27: =SUM(R27:AE27) -> 0 | AG27: =IF(AE27="","Blank",IF(AE27=AF27,"Yes","No")) -> Blank | AH27: =Iberia!J29 -> 95937263 | AI27: =O27+AE27 -> 95937263 | AJ27: =IF(AH27="","Blank",IF(AH27=AI27,"Yes","No")) -> Yes
A28: Iberville | B28: =Iberville!K7 -> 2975825 | C28: =Iberville!K8 -> 6218861 | D28: 0 | E28: =Iberville!K13 -> 31725027 | F28: 0 | G28: =Iberville!K15 -> 4023678 | H28: 0 | I28: 0 | J28: 0 | K28: 0 | L28: 0 | M28: 0 | N28: =Iberville!K14 -> 55243002 | O28: =Iberville!K18 -> 100186393 | P28: =SUM(B28:N28) -> 100186393 | Q28: =IF(O28="","Blank",IF(O28=P28,"Yes","No")) -> Yes | R28: =Iberville!J23 -> 193511 | S28: =Iberville!J24 -> 156733 | T28: 0 | U28: =Iberville!J30 -> 10071429 | V28: 0 | W28: =Iberville!J31 -> 154513 | X28: 0 | Y28: 0 | Z28: 0 | AA28: 0 | AB28: 0 | AC28: 0 | AD28: 0 | AE28: =Iberville!J36 -> 10576186 | AF28: =SUM(R28:AD28) -> 10576186 | AG28: =IF(AE28="","Blank",IF(AE28=AF28,"Yes","No")) -> Yes | AH28: =Iberville!K18+Iberville!J36 -> 110762579 | AI28: =O28+AE28 -> 110762579 | AJ28: =IF(AH28="","Blank",IF(AH28=AI28,"Yes","No")) -> Yes
A29: Jackson | B29: =Jackson!K9 -> 427562 | C29: =Jackson!K10 -> 689578 | D29: 0 | E29: =Jackson!K21 -> 4953544 | F29: 0 | G29: =Jackson!K23 -> 1999528 | H29: =Livingston!M18 -> 0 | I29: 0 | J29: 0 | K29: =Jackson!K22 -> 612033 | L29: 0 | M29: 0 | N29: =Jackson!K24 -> 7717383 | O29: =Jackson!K29 -> 16399628 | P29: =SUM(B29:N29) -> 16399628 | Q29: =IF(O29="","Blank",IF(O29=P29,"Yes","No")) -> Yes | R29: =Livingston!M30 -> 0 | S29: =Livingston!M31 -> 0 | T29: 0 | U29: 0 | V29: 0 | W29: 0 | X29: 0 | Y29: 0 | Z29: 0 | AA29: 0 | AB29: 0 | AC29: 0 | AD29: =Livingston!M37 -> 0 | AF29: =SUM(R29:AD29) -> 0 | AG29: =IF(AE29="","Blank",IF(AE29=AF29,"Yes","No")) -> Blank | AH29: =Jackson!K29 -> 16399628 | AI29: =O29+AE29 -> 16399628 | AJ29: =IF(AH29="","Blank",IF(AH29=AI29,"Yes","No")) -> Yes
A30: Jefferson | B30: =Jefferson!O11 -> 64274000 | C30: =Jefferson!O12 -> 178907000 | D30: 0 | E30: =Jefferson!O23 -> 211796000 | F30: =Jefferson!O24 -> 110972000 | G30: =Jefferson!O26 -> 45110000 | H30: 0 | I30: 0 | J30: 0 | K30: =Jefferson!O25 -> 14339000 | L30: 0 | M30: 0 | N30: =Jefferson!O27 -> 548604000 | O30: =Jefferson!O30 -> 1174002000 | P30: =SUM(B30:N30) -> 1174002000 | Q30: =IF(O30="","Blank",IF(O30=P30,"Yes","No")) -> Yes | R30: =Jefferson!O37 -> 13591000 | S30: =Jefferson!O38 -> 3112000 | T30: 0 | U30: =Jefferson!O50 -> 13301000 | V30: =Jefferson!O53 -> 10922000 | W30: =Jefferson!O54 -> 763000 | X30: 0 | Y30: 0 | Z30: 0 | AA30: =Jefferson!O55 -> 3330000 | AB30: 0 | AC30: 0 | AD30: =Jefferson!O51+Jefferson!O52 -> 501638000 | AE30: =Jefferson!O58 -> 546657000 | AF30: =SUM(R30:AD30) -> 546657000 | AG30: =IF(AE30="","Blank",IF(AE30=AF30,"Yes","No")) -> Yes | AH30: =Jefferson!O30+Jefferson!O58 -> 1720659000 | AI30: =O30+AE30 -> 1720659000 | AJ30: =IF(AH30="","Blank",IF(AH30=AI30,"Yes","No")) -> Yes
A31: Jefferson Davis | B31: ='Jefferson Davis'!K9 -> 525705 | C31: ='Jefferson Davis'!K10 -> 88007 | D31: 0 | E31: ='Jefferson Davis'!K24 -> 8629016 | F31: 0 | G31: ='Jefferson Davis'!K26+'Jefferson Davis'!K27 -> 1328119 | H31: =Orleans!N18 -> 0 | I31: 0 | J31: ='Jefferson Davis'!K28 -> 70327 | K31: ='Jefferson Davis'!K25 -> 2652485 | L31: 0 | M31: 0 | N31: ='Jefferson Davis'!K29+'Jefferson Davis'!K30 -> 20271255 | O31: ='Jefferson Davis'!K34 -> 33564914 | P31: =SUM(B31:N31) -> 33564914 | Q31: =IF(O31="","Blank",IF(O31=P31,"Yes","No")) -> Yes | R31: 0 | S31: 0 | T31: 0 | U31: 0 | V31: 0 | W31: 0 | X31: 0 | Y31: 0 | Z31: 0 | AA31: 0 | AB31: 0 | AC31: 0 | AD31: 0 | AF31: =SUM(R31:AD31) -> 0 | AG31: =IF(AE31="","Blank",IF(AE31=AF31,"Yes","No")) -> Blank | AH31: ='Jefferson Davis'!K34 -> 33564914 | AI31: =O31+AE31 -> 33564914 | AJ31: =IF(AH31="","Blank",IF(AH31=AI31,"Yes","No")) -> Yes
A32: Lafayette | B32: =Lafayette!K10 -> 38517490 | C32: =Lafayette!K11 -> 31680505 | D32: 0 | E32: =Lafayette!K23 -> 255344012 | F32: =Lafayette!K22 -> 7439174 | G32: 0 | H32: =Lafayette!K25 -> 58611671 | I32: 0 | J32: 0 | K32: =Lafayette!K24 -> 85328518 | L32: 0 | M32: 0 | N32: =Lafayette!K26 -> 931529137 | O32: =Lafayette!K28 -> 1408450507 | P32: =SUM(B32:N32) -> 1408450507 | Q32: =IF(O32="","Blank",IF(O32=P32,"Yes","No")) -> Yes | R32: =Lafayette!K33 -> 21168445 | S32: =Lafayette!K34 -> 45063725 | T32: 0 | U32: =Lafayette!K46 -> 228117 | V32: 0 | W32: =Lafayette!K51 -> 14444193 | X32: =Lafayette!K50 -> 85009057 | Y32: 0 | Z32: 0 | AA32: 0 | AB32: 0 | AC32: 0 | AD32: =Lafayette!K47+Lafayette!K48+Lafayette!K49 -> 562950949 | AE32: =Lafayette!K53 -> 728864486 | AF32: =SUM(R32:AD32) -> 728864486 | AG32: =IF(AE32="","Blank",IF(AE32=AF32,"Yes","No")) -> Yes | AH32: =Lafayette!K28+Lafayette!K53 -> 2137314993 | AI32: =O32+AE32 -> 2137314993 | AJ32: =IF(AH32="","Blank",IF(AH32=AI32,"Yes","No")) -> Yes
A33: LaFourche | B33: =LaFourche!J8 -> 1315603 | C33: =LaFourche!J9 -> 23784977 | D33: 0 | E33: =LaFourche!J22 -> 24429538 | F33: =LaFourche!J24 -> 1269667 | G33: =LaFourche!J26 -> 3325327 | H33: 0 | I33: 0 | J33: 0 | K33: =LaFourche!J27 -> 3332367 | L33: 0 | M33: 0 | N33: =LaFourche!J23+LaFourche!J25 -> 25595009 | O33: =LaFourche!J30 -> 83052488 | P33: =SUM(B33:N33) -> 83052488 | Q33: =IF(O33="","Blank",IF(O33=P33,"Yes","No")) -> Yes | R33: 0 | S33: 0 | T33: 0 | U33: 0 | V33: 0 | W33: 0 | X33: 0 | Y33: 0 | Z33: 0 | AA33: 0 | AB33: 0 | AC33: 0 | AD33: 0 | AF33: =SUM(R33:AD33) -> 0 | AG33: =IF(AE33="","Blank",IF(AE33=AF33,"Yes","No")) -> Blank | AH33: =LaFourche!J30 -> 83052488 | AI33: =O33+AE33 -> 83052488 | AJ33: =IF(AH33="","Blank",IF(AH33=AI33,"Yes","No")) -> Yes
A34: LaSalle | B34: =LaSalle!M10+LaSalle!M28 -> 501018 | C34: =LaSalle!M29 -> 0 | D34: 0 | E34: =LaSalle!M35+LaSalle!M41 -> 1698880 | F34: =Plaquemines!M16 -> 0 | G34: =LaSalle!M44+LaSalle!M43+LaSalle!M37 -> 397428 | H34: 0 | I34: =LaSalle!M46+LaSalle!M33 -> 148004 | J34: =LaSalle!M42+LaSalle!M36 -> 239276 | K34: =LaSalle!M34+LaSalle!M45 -> 162797 | L34: 0 | M34: 0 | N34: =LaSalle!M40 -> 2698759 | O34: =LaSalle!M50 -> 5846162 | P34: =SUM(B34:N34) -> 5846162 | Q34: =IF(O34="","Blank",IF(O34=P34,"Yes","No")) -> Yes | R34: =Plaquemines!M27 -> 0 | S34: 0 | T34: 0 | U34: =Plaquemines!M39 -> 0 | V34: =Plaquemines!M40 -> 0 | W34: 0 | X34: 0 | Y34: 0 | Z34: 0 | AA34: 0 | AB34: 0 | AC34: 0 | AD34: =Plaquemines!M35 -> 0 | AF34: =SUM(R34:AD34) -> 0 | AG34: =IF(AE34="","Blank",IF(AE34=AF34,"Yes","No")) -> Blank | AH34: =LaSalle!M50 -> 5846162 | AI34: =O34+AE34 -> 5846162 | AJ34: =IF(AH34="","Blank",IF(AH34=AI34,"Yes","No")) -> Yes
A35: Lincoln | B35: =Lincoln!M9 -> 1775786 | C35: 0 | D35: 0 | E35: =Lincoln!M22+Lincoln!M24 -> 11922226 | F35: =Plaquemines!M18 -> 0 | G35: =Lincoln!M27 -> 1796224 | H35: 0 | I35: 0 | J35: =Lincoln!M26 -> 315178 | K35: =Lincoln!M25 -> 531373 | L35: 0 | M35: 0 | N35: =Lincoln!M23 -> 7529398 | O35: =Lincoln!M30 -> 23870185 | P35: =SUM(B35:N35) -> 23870185 | Q35: =IF(O35="","Blank",IF(O35=P35,"Yes","No")) -> Yes | R35: =Plaquemines!M29 -> 0 | S35: =Plaquemines!M30 -> 0 | T35: 0 | U35: 0 | V35: =Plaquemines!M42 -> 0 | W35: =Plaquemines!M43 -> 0 | X35: 0 | Y35: 0 | Z35: 0 | AA35: 0 | AB35: 0 | AC35: 0 | AD35: =Plaquemines!M37 -> 0 | AF35: =SUM(R35:AD35) -> 0 | AG35: =IF(AE35="","Blank",IF(AE35=AF35,"Yes","No")) -> Blank | AH35: =Lincoln!M30 -> 23870185 | AI35: =O35+AE35 -> 23870185 | AJ35: =IF(AH35="","Blank",IF(AH35=AI35,"Yes","No")) -> Yes
A36: Livingston | B36: =Livingston!M9 -> 5844429 | C36: =Livingston!M10 -> 15111097 | D36: 0 | E36: =Livingston!M21 -> 45429948 | F36: 0 | G36: =Livingston!M23 -> 1538945 | H36: =Livingston!M22 -> 3452060 | I36: 0 | J36: =Livingston!M26 -> -17870 | K36: 0 | L36: 0 | M36: 0 | N36: =Livingston!M25+Livingston!M24 -> 72313919 | O36: =Livingston!M29 -> 143672528 | P36: =SUM(B36:N36) -> 143672528 | Q36: =IF(O36="","Blank",IF(O36=P36,"Yes","No")) -> Yes | R36: =Livingston!M34 -> 13243 | S36: =Livingston!M35 -> 177483 | T36: 0 | U36: 0 | V36: 0 | W36: 0 | X36: 0 | Y36: 0 | Z36: 0 | AA36: 0 | AB36: 0 | AC36: 0 | AD36: =Livingston!M41 -> 8106754 | AE36: =Livingston!M44 -> 8297480 | AF36: =SUM(R36:AD36) -> 8297480 | AG36: =IF(AE36="","Blank",IF(AE36=AF36,"Yes","No")) -> Yes | AH36: =Livingston!M44+Livingston!M29 -> 151970008 | AI36: =O36+AE36 -> 151970008 | AJ36: =IF(AH36="","Blank",IF(AH36=AI36,"Yes","No")) -> Yes
A37: Madison | B37: =Madison!M9 -> 188750 | C37: 0 | D37: =Madison!M10 -> 3771405 | E37: =Madison!M20 -> 1572206 | F37: 0 | G37: ='Pointe Coupee'!M18 -> 0 | H37: =Madison!M14 -> 1509539 | I37: =Madison!M22 -> 109434 | J37: =Madison!M21 -> 1026033 | K37: 0 | L37: 0 | M37: 0 | N37: ='Pointe Coupee'!M19 -> 0 | O37: =Madison!M25 -> 8177367 | P37: =SUM(B37:N37) -> 8177367 | Q37: =IF(O37="","Blank",IF(O37=P37,"Yes","No")) -> Yes | R37: ='Pointe Coupee'!M28 -> 0 | S37: 0 | T37: 0 | U37: 0 | V37: 0 | W37: 0 | X37: 0 | Y37: 0 | Z37: 0 | AA37: 0 | AB37: 0 | AC37: 0 | AD37: 0 | AF37: =SUM(R37:AD37) -> 0 | AG37: =IF(AE37="","Blank",IF(AE37=AF37,"Yes","No")) -> Blank | AH37: =Madison!M25 -> 8177367 | AI37: =O37+AE37 -> 8177367 | AJ37: =IF(AH37="","Blank",IF(AH37=AI37,"Yes","No")) -> Yes
A38: Morehouse | B38: =Morehouse!N8 -> 778626 | C38: 0 | D38: 0 | E38: =Morehouse!N14 -> 11986527 | G38: =Morehouse!N15 -> 879268 | H38: 0 | I38: 0 | J38: 0 | K38: 0 | L38: 0 | M38: 0 | N38: 0 | O38: =Morehouse!N19 -> 13644421 | P38: =SUM(B38:N38) -> 13644421 | Q38: =IF(O38="","Blank",IF(O38=P38,"Yes","No")) -> Yes | R38: 0 | S38: 0 | T38: 0 | U38: 0 | V38: 0 | W38: 0 | X38: 0 | Y38: 0 | Z38: 0 | AA38: 0 | AB38: 0 | AC38: 0 | AD38: 0 | AF38: =SUM(R38:AE38) -> 0 | AG38: =IF(AE38="","Blank",IF(AE38=AF38,"Yes","No")) -> Blank | AH38: =Morehouse!N19 -> 13644421 | AI38: =O38+AE38 -> 13644421 | AJ38: =IF(AH38="","Blank",IF(AH38=AI38,"Yes","No")) -> Yes
A39: Natchitoches | B39: =Natchitoches!M9+Natchitoches!M120 -> 471485 | C39: =Natchitoches!M108 -> 29054 | D39: 0 | E39: =Natchitoches!M17+Natchitoches!M54+Natchitoches!M80+Natchitoches!M130 -> 2102193 | F39: 0 | G39: =Natchitoches!M18+Natchitoches!M19+Natchitoches!M55+Natchitoches!M56+Natchitoches!M67+Natchitoches!M82+Natchitoches!M81+Natchitoches!M113+Natchitoches!M131+Natchitoches!M132 -> 521785 | H39: 0 | I39: =Natchitoches!M115 -> 337451 | J39: 0 | K39: =Natchitoches!M20+Natchitoches!M57+Natchitoches!M68+Natchitoches!M83+Natchitoches!M101+Natchitoches!M114+Natchitoches!M133 -> 404192 | L39: =Natchitoches!M134 -> 6711927 | M39: 0 | N39: =Natchitoches!M135 -> 127966 | O39: =Natchitoches!M140 -> 10706053 | P39: =SUM(B39:N39) -> 10706053 | Q39: =IF(O39="","Blank",IF(O39=P39,"Yes","No")) -> Yes | R39: ='Pointe Coupee'!M29 -> 0 | S39: 0 | T39: 0 | U39: 0 | V39: 0 | W39: 0 | X39: 0 | Y39: 0 | Z39: 0 | AA39: 0 | AB39: 0 | AC39: 0 | AD39: ='Pointe Coupee'!M33 -> 0 | AF39: =SUM(R39:AD39) -> 0 | AG39: =IF(AE39="","Blank",IF(AE39=AF39,"Yes","No")) -> Blank | AH39: =Natchitoches!M140 -> 10706053 | AI39: =O39+AE39 -> 10706053 | AJ39: =IF(AH39="","Blank",IF(AH39=AI39,"Yes","No")) -> Yes
A40: Orleans | B40: =Orleans!N9 -> 94474000 | C40: =Orleans!N10 -> 447135000 | D40: 0 | E40: =Orleans!N22 -> 254036000 | F40: 0 | G40: =Orleans!N23 -> 19119000 | H40: =Orleans!N24 -> 10310000 | I40: 0 | J40: 0 | K40: 0 | L40: 0 | M40: 0 | N40: =Orleans!N21 -> 725036000 | O40: =Orleans!N27 -> 1550110000 | P40: =SUM(B40:N40) -> 1550110000 | Q40: =IF(O40="","Blank",IF(O40=P40,"Yes","No")) -> Yes | R40: 0 | S40: 0 | T40: 0 | U40: 0 | V40: 0 | W40: 0 | X40: 0 | Y40: 0 | Z40: 0 | AA40: 0 | AB40: 0 | AC40: 0 | AD40: 0 | AF40: =SUM(R40:AD40) -> 0 | AG40: =IF(AE40="","Blank",IF(AE40=AF40,"Yes","No")) -> Blank | AH40: =Orleans!N27 -> 1550110000 | AI40: =O40+AE40 -> 1550110000 | AJ40: =IF(AH40="","Blank",IF(AH40=AI40,"Yes","No")) -> Yes
A41: Ouachita | B41: =Ouachita!M9 -> 8970022 | C41: =Ouachita!M10 -> 10039664 | D41: 0 | E41: =Ouachita!M24 -> 37393923 | F41: 0 | G41: =Morehouse!N18 -> 0 | H41: 0 | I41: =Ouachita!M26 -> 1524273 | J41: =Ouachita!M25 -> 10285677 | K41: 0 | L41: 0 | M41: 0 | N41: =Ouachita!M28+Ouachita!M29+Ouachita!M30 -> 113145796 | O41: =Ouachita!M33 -> 181359355 | P41: =SUM(B41:N41) -> 181359355 | Q41: =IF(O41="","Blank",IF(O41=P41,"Yes","No")) -> Yes | R41: 0 | S41: 0 | T41: 0 | U41: 0 | V41: 0 | W41: 0 | X41: 0 | Y41: 0 | Z41: 0 | AA41: 0 | AB41: 0 | AC41: 0 | AD41: 0 | AF41: =SUM(R41:AE41) -> 0 | AG41: =IF(AE41="","Blank",IF(AE41=AF41,"Yes","No")) -> Blank | AH41: =Ouachita!L33 -> 181359355 | AI41: =O41+AE41 -> 181359355 | AJ41: =IF(AH41="","Blank",IF(AH41=AI41,"Yes","No")) -> Yes
A42: Plaquemines | B42: =Plaquemines!M8 -> 13511734 | C42: =Plaquemines!M9+Plaquemines!M10 -> 125867194 | D42: 0 | E42: =Plaquemines!M21 -> 129982363 | F42: =Plaquemines!M22 -> 68326186 | G42: =Plaquemines!M23 -> 21643821 | H42: 0 | I42: 0 | J42: 0 | K42: 0 | L42: 0 | M42: 0 | N42: =Plaquemines!M24 -> 78499297 | O42: =Plaquemines!M28 -> 437830595 | P42: =SUM(B42:N42) -> 437830595 | Q42: =IF(O42="","Blank",IF(O42=P42,"Yes","No")) -> Yes | R42: =Plaquemines!M33 -> 52000 | S42: =Plaquemines!M34 -> 31001463 | T42: 0 | U42: =Plaquemines!M45 -> 13167508 | V42: =Plaquemines!M46 -> 39913135 | W42: =Plaquemines!M47 -> 1019380 | X42: 0 | Y42: 0 | Z42: 0 | AA42: 0 | AB42: 0 | AC42: 0 | AD42: =Plaquemines!M41 -> 5670859 | AE42: =Plaquemines!M52 -> 90824345 | AF42: =SUM(R42:AD42) -> 90824345 | AG42: =IF(AE42="","Blank",IF(AE42=AF42,"Yes","No")) -> Yes | AH42: =Plaquemines!M28+Plaquemines!M52 -> 528654940 | AI42: =O42+AE42 -> 528654940 | AJ42: =IF(AH42="","Blank",IF(AH42=AI42,"Yes","No")) -> Yes
A43: Pointe Coupee | B43: ='Pointe Coupee'!M8 -> 841274 | C43: ='Pointe Coupee'!M9 -> 2713183 | D43: 0 | E43: ='Pointe Coupee'!M20 -> 4906692 | F43: 0 | G43: ='Pointe Coupee'!M22 -> 337679 | H43: 0 | I43: ='Pointe Coupee'!M21 -> 508875 | J43: 0 | K43: 0 | L43: 0 | M43: 0 | N43: ='Pointe Coupee'!M23 -> 7847049 | O43: ='Pointe Coupee'!M27 -> 17154752 | P43: =SUM(B43:N43) -> 17154752 | Q43: =IF(O43="","Blank",IF(O43=P43,"Yes","No")) -> Yes | R43: ='Pointe Coupee'!M32 -> 45233 | S43: 0 | T43: 0 | U43: 0 | V43: 0 | W43: 0 | X43: 0 | Y43: 0 | Z43: 0 | AA43: 0 | AB43: 0 | AC43: 0 | AD43: ='Pointe Coupee'!M36 -> 2117538 | AE43: ='Pointe Coupee'!M40 -> 2162771 | AF43: =SUM(R43:AD43) -> 2162771 | AG43: =IF(AE43="","Blank",IF(AE43=AF43,"Yes","No")) -> Yes | AH43: ='Pointe Coupee'!M27+'Pointe Coupee'!M40 -> 19317523 | AI43: =O43+AE43 -> 19317523 | AJ43: =IF(AH43="","Blank",IF(AH43=AI43,"Yes","No")) -> Yes
A44: Rapides | B44: =Rapides!K7 -> 1689373 | C44: =Rapides!K8 -> 1375268 | D44: 0 | E44: =Rapides!K13 -> 10856728 | F44: ='St. James'!M18 -> 0 | G44: ='St. James'!M19 -> 0 | H44: 0 | I44: 0 | J44: =Rapides!K14 -> 7063408 | K44: ='St. James'!M20 -> 0 | L44: 0 | M44: 0 | N44: =Rapides!K15 -> 30119389 | O44: =Rapides!K18 -> 51104166 | P44: =SUM(B44:N44) -> 51104166 | Q44: =IF(O44="","Blank",IF(O44=P44,"Yes","No")) -> Yes | R44: ='St. James'!M29 -> 0 | S44: ='St. James'!M30 -> 0 | T44: 0 | U44: ='St. James'!M42 -> 0 | V44: 0 | W44: 0 | X44: 0 | Y44: 0 | Z44: ='St. James'!M45 -> 0 | AA44: 0 | AB44: 0 | AC44: 0 | AD44: ='St. James'!M43+'St. James'!M44 -> 0 | AF44: =SUM(R44:AD44) -> 0 | AG44: =IF(AE44="","Blank",IF(AE44=AF44,"Yes","No")) -> Blank | AH44: =Rapides!J18 -> 51104166 | AI44: =O44+AE44 -> 51104166 | AJ44: =IF(AH44="","Blank",IF(AH44=AI44,"Yes","No")) -> Yes
A45: Red River | B45: ='Red River'!M8 -> 301537 | C45: ='Red River'!M9 -> 1874046 | D45: 0 | E45: ='Red River'!M14 -> 2628041 | F45: ='St. James'!M18 -> 0 | G45: ='St. James'!M19 -> 0 | H45: 0 | I45: ='Red River'!M26 -> 73621 | J45: ='Red River'!M22 -> 1281860 | K45: ='St. James'!M20 -> 0 | L45: 0 | M45: 0 | N45: ='Red River'!M18 -> 8076956 | O45: ='Red River'!M31 -> 14236061 | P45: =SUM(B45:N45) -> 14236061 | Q45: =IF(O45="","Blank",IF(O45=P45,"Yes","No")) -> Yes | R45: ='St. James'!M29 -> 0 | S45: ='St. James'!M30 -> 0 | T45: 0 | U45: ='St. James'!M42 -> 0 | V45: 0 | W45: 0 | X45: 0 | Y45: 0 | Z45: ='St. James'!M45 -> 0 | AA45: 0 | AB45: 0 | AC45: 0 | AD45: ='St. James'!M43+'St. James'!M44 -> 0 | AF45: =SUM(R45:AD45) -> 0 | AG45: =IF(AE45="","Blank",IF(AE45=AF45,"Yes","No")) -> Blank | AH45: ='Red River'!L31 -> 14236061 | AI45: =O45+AE45 -> 14236061 | AJ45: =IF(AH45="","Blank",IF(AH45=AI45,"Yes","No")) -> Yes
A46: Richland | B46: =Richland!M9 -> 300273 | C46: 0 | D46: ='St. Charles'!N6 -> 0 | E46: =Richland!M18 -> 1569503 | F46: ='St. Charles'!N19 -> 0 | G46: =Richland!M19 -> 568244 | H46: 0 | I46: 0 | J46: 0 | K46: 0 | L46: 0 | M46: 0 | N46: 0 | O46: =Richland!M23 -> 2438020 | P46: =SUM(B46:N46) -> 2438020 | Q46: =IF(O46="","Blank",IF(O46=P46,"Yes","No")) -> Yes | R46: ='St. Charles'!N30 -> 0 | S46: ='St. Charles'!N31 -> 0 | T46: 0 | U46: ='St. Charles'!N40 -> 0 | V46: 0 | W46: ='St. Charles'!N41 -> 0 | X46: 0 | Y46: 0 | Z46: 0 | AA46: 0 | AB46: 0 | AC46: 0 | AD46: 0 | AF46: =SUM(R46:AD46) -> 0 | AG46: =IF(AE46="","Blank",IF(AE46=AF46,"Yes","No")) -> Blank | AH46: =Richland!L23 -> 2438020 | AI46: =O46+AE46 -> 2438020 | AJ46: =IF(AH46="","Blank",IF(AH46=AI46,"Yes","No")) -> Yes
A47: Sabine | B47: =Sabine!M9 -> 639576 | C47: =Sabine!M10 -> 540422 | D47: 0 | E47: =Sabine!M21 -> 1720235 | F47: 0 | G47: =Sabine!M22 -> 3069476 | H47: 0 | I47: 0 | J47: =Sabine!M23 -> 15328 | K47: 0 | L47: 0 | M47: 0 | N47: =Sabine!M24 -> 6610386 | O47: =Sabine!M28 -> 12595423 | P47: =SUM(B47:N47) -> 12595423 | Q47: =IF(O47="","Blank",IF(O47=P47,"Yes","No")) -> Yes | R47: 0 | S47: 0 | T47: 0 | U47: 0 | V47: 0 | W47: 0 | X47: 0 | Y47: 0 | Z47: 0 | AA47: 0 | AB47: 0 | AC47: 0 | AD47: 0 | AF47: =SUM(R47:AD47) -> 0 | AG47: =IF(AE47="","Blank",IF(AE47=AF47,"Yes","No")) -> Blank | AH47: =Sabine!M28 -> 12595423 | AI47: =O47+AE47 -> 12595423 | AJ47: =IF(AH47="","Blank",IF(AH47=AI47,"Yes","No")) -> Yes
A48: St. Bernard | B48: ='St. Bernard'!N8 -> 19245801 | C48: ='St. Bernard'!N9 -> 23876204 | D48: 0 | E48: ='St. Bernard'!N14 -> 1.1238689e+08 | F48: ='St. Bernard'!N13 -> 17474.677 | G48: ='St. Bernard'!N16 -> 15365044 | H48: 0 | I48: 0 | J48: ='St. Bernard'!N15 -> 330940.93 | K48: 0 | L48: ='St. Bernard'!N18 -> 1181349.5 | M48: 0 | N48: ='St. Bernard'!N17 -> 2.1373678e+08 | O48: ='St. Bernard'!N22 -> 3.8614049e+08 | P48: =SUM(B48:N48) -> 386140491 | Q48: =IF(O48="","Blank",IF(O48=P48,"Yes","No")) -> Yes | R48: ='St. Bernard'!N27 -> 221036 | S48: ='St. Bernard'!N28 -> 50611062 | T48: 0 | U48: ='St. Bernard'!N32 -> 43285819 | V48: 0 | W48: ='St. Bernard'!N34 -> 944154.48 | X48: 0 | Y48: 0 | Z48: ='St. Bernard'!N33 -> 21353.963 | AA48: 0 | AB48: 0 | AC48: 0 | AD48: ='St. Bernard'!N35 -> 1.0988273e+08 | AE48: ='St. Bernard'!N39 -> 204966155 | AF48: =SUM(R48:AD48) -> 204966155 | AG48: =IF(AE48="","Blank",IF(AE48=AF48,"Yes","No")) -> Yes | AH48: ='St. Bernard'!M39+'St. Bernard'!M22 -> 591106646 | AI48: =O48+AE48 -> 591106646 | AJ48: =IF(AH48="","Blank",IF(AH48=AI48,"Yes","No")) -> Yes
A49: St. Charles | B49: ='St. Charles'!N7 -> 10141106 | C49: ='St. Charles'!N9 -> 50057093 | D49: ='St. Charles'!N8 -> 14855447 | E49: ='St. Charles'!N20 -> 20280744 | F49: ='St. Charles'!N21 -> 44140924 | G49: ='St. Charles'!N22 -> 9895293 | H49: 0 | I49: 0 | J49: 0 | K49: 0 | L49: 0 | M49: 0 | N49: ='St. Charles'!N23 -> 44893562 | O49: ='St. Charles'!N28 -> 194264169 | P49: =SUM(B49:N49) -> 194264169 | Q49: =IF(O49="","Blank",IF(O49=P49,"Yes","No")) -> Yes | R49: ='St. Charles'!N32 -> 824777 | S49: ='St. Charles'!N33 -> 5726853 | T49: 0 | U49: ='St. Charles'!N42 -> 126209531 | V49: 0 | W49: ='St. Charles'!N43 -> 2038904 | X49: 0 | Y49: 0 | Z49: 0 | AA49: 0 | AB49: 0 | AC49: 0 | AD49: 0 | AE49: ='St. Charles'!N48 -> 134800065 | AF49: =SUM(R49:AD49) -> 134800065 | AG49: =IF(AE49="","Blank",IF(AE49=AF49,"Yes","No")) -> Yes | AH49: ='St. Charles'!N28+'St. Charles'!N48 -> 329064234 | AI49: =O49+AE49 -> 329064234 | AJ49: =IF(AH49="","Blank",IF(AH49=AI49,"Yes","No")) -> Yes
A50: St. Helena | B50: ='St. Helena'!N9 -> 227865 | C50: ='St. Helena'!N10 -> 1476353 | D50: 0 | E50: ='St. Helena'!N20 -> 2494097 | F50: 0 | G50: ='St. Helena'!N21 -> 2558875 | H50: 0 | I50: 0 | J50: 0 | K50: 0 | L50: 0 | M50: 0 | N50: ='St. Helena'!N22 -> 5782016 | O50: ='St. Helena'!N26 -> 12539206 | P50: =SUM(B50:N50) -> 12539206 | Q50: =IF(O50="","Blank",IF(O50=P50,"Yes","No")) -> Yes | R50: 0 | S50: 0 | T50: 0 | U50: 0 | V50: 0 | W50: 0 | X50: 0 | Y50: 0 | Z50: 0 | AA50: 0 | AB50: 0 | AC50: 0 | AD50: 0 | AF50: =SUM(R50:AD50) -> 0 | AG50: =IF(AE50="","Blank",IF(AE50=AF50,"Yes","No")) -> Blank | AH50: ='St. Helena'!N26 -> 12539206 | AI50: =O50+AE50 -> 12539206 | AJ50: =IF(AH50="","Blank",IF(AH50=AI50,"Yes","No")) -> Yes
A51: St. James | B51: ='St. James'!M8 -> 17858242 | C51: ='St. James'!M9 -> 1874609 | D51: 0 | E51: ='St. James'!M21 -> 14480256 | F51: ='St. James'!M22 -> 3238805 | G51: ='St. James'!M23 -> 6067699 | H51: 0 | I51: 0 | J51: 0 | K51: ='St. James'!M24 -> 73884 | L51: 0 | M51: 0 | N51: ='St. James'!M25 -> 12685889 | O51: ='St. James'!M28 -> 56279384 | P51: =SUM(B51:N51) -> 56279384 | Q51: =IF(O51="","Blank",IF(O51=P51,"Yes","No")) -> Yes | R51: ='St. James'!M33 -> 1040000 | S51: ='St. James'!M34 -> 23713 | T51: 0 | U51: ='St. James'!M46 -> 1415647 | V51: 0 | W51: ='St. James'!M50 -> 140519 | X51: 0 | Y51: 0 | Z51: ='St. James'!M49 -> 12192 | AA51: 0 | AB51: 0 | AC51: 0 | AD51: ='St. James'!M47+'St. James'!M48 -> 11888193 | AE51: ='St. James'!M53 -> 14520264 | AF51: =SUM(R51:AD51) -> 14520264 | AG51: =IF(AE51="","Blank",IF(AE51=AF51,"Yes","No")) -> Yes | AH51: ='St. James'!M28+'St. James'!M53 -> 70799648 | AI51: =O51+AE51 -> 70799648 | AJ51: =IF(AH51="","Blank",IF(AH51=AI51,"Yes","No")) -> Yes
A52: St. John the Baptist | B52: ='St. John the Baptist'!M8 -> 3976254 | C52: ='St. John the Baptist'!M9 -> 4747061 | D52: 0 | E52: ='St. John the Baptist'!M21 -> 24484784 | F52: 0 | G52: 0 | H52: 0 | I52: 0 | J52: ='St. John the Baptist'!M24 -> 2170865 | K52: ='St. John the Baptist'!M25 -> 2289874 | L52: 0 | M52: 0 | N52: ='St. John the Baptist'!M22+'St. John the Baptist'!M23 -> 39715385 | O52: ='St. John the Baptist'!M28 -> 77384223 | P52: =SUM(B52:N52) -> 77384223 | Q52: =IF(O52="","Blank",IF(O52=P52,"Yes","No")) -> Yes | R52: ='St. John the Baptist'!M33 -> 1678616 | S52: ='St. John the Baptist'!M34 -> 352803 | T52: 0 | U52: ='St. John the Baptist'!M45 -> 12089368 | V52: 0 | W52: 0 | X52: 0 | Y52: 0 | Z52: ='St. John the Baptist'!M47 -> 3040136 | AA52: ='St. John the Baptist'!M48 -> 352017 | AB52: 0 | AC52: 0 | AD52: ='St. John the Baptist'!M46 -> 111453819 | AE52: ='St. John the Baptist'!M51 -> 128966759 | AF52: =SUM(R52:AD52) -> 128966759 | AG52: =IF(AE52="","Blank",IF(AE52=AF52,"Yes","No")) -> Yes | AH52: ='St. John the Baptist'!M28+'St. John the Baptist'!M51 -> 206350982 | AI52: =O52+AE52 -> 206350982 | AJ52: =IF(AH52="","Blank",IF(AH52=AI52,"Yes","No")) -> Yes
A53: St. Landry | B53: ='St. Landry'!M8 -> 499243 | C53: 0 | D53: 0 | E53: ='St. Landry'!M17 -> 3917630 | F53: ='St. Landry'!M20 -> 3543986 | G53: ='St. Landry'!M19 -> 1305861 | H53: 0 | I53: 0 | J53: 0 | K53: ='St. Landry'!M18 -> 239595 | L53: 0 | M53: 0 | N53: 0 | O53: ='St. Landry'!M23 -> 9506315 | P53: =SUM(B53:N53) -> 9506315 | Q53: =IF(O53="","Blank",IF(O53=P53,"Yes","No")) -> Yes | R53: 0 | S53: 0 | T53: 0 | U53: 0 | V53: 0 | W53: 0 | X53: 0 | Y53: 0 | Z53: 0 | AA53: 0 | AB53: 0 | AC53: 0 | AD53: 0 | AF53: =SUM(R53:AD53) -> 0 | AG53: =IF(AE53="","Blank",IF(AE53=AF53,"Yes","No")) -> Blank | AH53: ='St. Landry'!M23 -> 9506315 | AI53: =O53+AE53 -> 9506315 | AJ53: =IF(AH53="","Blank",IF(AH53=AI53,"Yes","No")) -> Yes
A54: St. Martin | B54: ='St. Martin'!M9 -> 1515115 | C54: ='St. Martin'!M10 -> 9423016 | D54: =Tangipahoa!M7 -> 0 | E54: ='St. Martin'!M21 -> 23307165 | F54: ='St. Martin'!M23 -> 1105624 | G54: ='St. Martin'!M22 -> 5506413 | H54: 0 | I54: 0 | J54: 0 | K54: 0 | L54: 0 | M54: 0 | N54: ='St. Martin'!M24 -> 29503502 | O54: ='St. Martin'!M28 -> 70360835 | P54: =SUM(B54:N54) -> 70360835 | Q54: =IF(O54="","Blank",IF(O54=P54,"Yes","No")) -> Yes | R54: 0 | S54: 0 | T54: 0 | U54: 0 | V54: 0 | W54: 0 | X54: 0 | Y54: 0 | Z54: 0 | AA54: 0 | AB54: 0 | AC54: 0 | AD54: 0 | AF54: =SUM(R54:AD54) -> 0 | AG54: =IF(AE54="","Blank",IF(AE54=AF54,"Yes","No")) -> Blank | AH54: ='St. Martin'!L28 -> 70360835 | AI54: =O54+AE54 -> 70360835 | AJ54: =IF(AH54="","Blank",IF(AH54=AI54,"Yes","No")) -> Yes
A55: St. Mary | B55: ='St. Mary'!M9 -> 1870876 | C55: ='St. Mary'!M10 -> 1887343 | D55: 0 | E55: ='St. Mary'!M22+'St. Mary'!M24 -> 24265438 | F55: 0 | G55: ='St. Mary'!M23 -> 2023025 | H55: 0 | I55: 0 | J55: 0 | K55: 0 | L55: 0 | M55: 0 | N55: ='St. Mary'!M21 -> 78560660 | O55: ='St. Mary'!M27 -> 108607342 | P55: =SUM(B55:N55) -> 108607342 | Q55: =IF(O55="","Blank",IF(O55=P55,"Yes","No")) -> Yes | R55: ='St. Mary'!M33+'St. Mary'!M34 -> 3802599 | S55: ='St. Mary'!M32 -> 314569 | T55: 0 | U55: ='St. Mary'!M44+'St. Mary'!M46 -> 14901020 | V55: 0 | W55: ='St. Mary'!M45 -> 2065040 | X55: 0 | Y55: 0 | Z55: 0 | AA55: 0 | AB55: 0 | AC55: 0 | AD55: 0 | AE55: ='St. Mary'!M49 -> 21083228 | AF55: =SUM(R55:AD55) -> 21083228 | AG55: =IF(AE55="","Blank",IF(AE55=AF55,"Yes","No")) -> Yes | AH55: ='St. Mary'!M49+'St. Mary'!M27 -> 129690570 | AI55: =O55+AE55 -> 129690570 | AJ55: =IF(AH55="","Blank",IF(AH55=AI55,"Yes","No")) -> Yes
A56: St. Tammany | B56: ='St. Tammany'!O7+'St. Tammany'!O8 -> 48413710 | C56: ='St. Tammany'!O9 -> 218211 | D56: ='St. Tammany'!O11+'St. Tammany'!O12+'St. Tammany'!O13 -> 54757659 | E56: ='St. Tammany'!O29+'St. Tammany'!O30 -> 77524186 | F56: ='St. Tammany'!O28 -> 3177109 | G56: ='St. Tammany'!O33+'St. Tammany'!O34 -> 7391788 | H56: 0 | I56: 0 | J56: 0 | K56: ='St. Tammany'!O32 -> 447854 | L56: 0 | M56: 0 | N56: ='St. Tammany'!O31+'St. Tammany'!O36+'St. Tammany'!O37 -> 198738116 | O56: ='St. Tammany'!O40 -> 390668633 | P56: =SUM(B56:N56) -> 390668633 | Q56: =IF(O56="","Blank",IF(O56=P56,"Yes","No")) -> Yes | R56: ='St. Tammany'!O44 -> 575567 | S56: ='St. Tammany'!O45 -> 591451 | T56: 0 | U56: ='St. Tammany'!O59 -> 11191 | V56: ='St. Tammany'!O58 -> 41693 | W56: ='St. Tammany'!O61+'St. Tammany'!O62 -> 231740 | X56: 0 | Y56: 0 | Z56: 0 | AA56: ='St. Tammany'!O60 -> 260098 | AB56: 0 | AC56: 0 | AD56: ='St. Tammany'!O64+'St. Tammany'!O65 -> 38941795 | AE56: ='St. Tammany'!O68 -> 40653535 | AF56: =SUM(R56:AD56) -> 40653535 | AG56: =IF(AE56="","Blank",IF(AE56=AF56,"Yes","No")) -> Yes | AH56: ='St. Tammany'!O40+'St. Tammany'!O68 -> 431322168 | AI56: =O56+AE56 -> 431322168 | AJ56: =IF(AH56="","Blank",IF(AH56=AI56,"Yes","No")) -> Yes
A57: Tangipahoa | B57: =Tangipahoa!M9 -> 2938462 | C57: =Tangipahoa!M11 -> 9985749 | D57: =Tangipahoa!M10 -> 70869285 | E57: =Tangipahoa!M21 -> 28177803 | F57: 0 | G57: =Tangipahoa!M23 -> 6391220 | H57: 0 | I57: 0 | J57: 0 | K57: 0 | L57: 0 | M57: 0 | N57: =Tangipahoa!M22 -> 59877912 | O57: =Tangipahoa!M27 -> 178240431 | P57: =SUM(B57:N57) -> 178240431 | Q57: =IF(O57="","Blank",IF(O57=P57,"Yes","No")) -> Yes | R57: 0 | S57: 0 | T57: 0 | U57: 0 | V57: 0 | W57: 0 | X57: 0 | Y57: 0 | Z57: 0 | AA57: 0 | AB57: 0 | AC57: 0 | AD57: 0 | AF57: =SUM(R57:AD57) -> 0 | AG57: =IF(AE57="","Blank",IF(AE57=AF57,"Yes","No")) -> Blank | AH57: =Tangipahoa!M27 -> 178240431 | AI57: =O57+AE57 -> 178240431 | AJ57: =IF(AH57="","Blank",IF(AH57=AI57,"Yes","No")) -> Yes
A58: Tensas | B58: =Tensas!M8 -> 743698 | C58: =Rapides!K22 -> 0 | D58: 0 | E58: =Tensas!M17 -> 6945698 | F58: ='St. James'!M32 -> 0 | G58: 0 | H58: 0 | I58: 0 | J58: =Tensas!M18 -> 878515 | K58: 0 | L58: 0 | M58: 0 | N58: =Rapides!K29 -> 0 | O58: =Tensas!M22 -> 8567911 | P58: =SUM(B58:N58) -> 8567911 | Q58: =IF(O58="","Blank",IF(O58=P58,"Yes","No")) -> Yes | R58: ='St. James'!M43 -> 0 | S58: ='St. James'!M44 -> 0 | T58: 0 | U58: ='St. James'!M56 -> 0 | V58: 0 | W58: 0 | X58: 0 | Y58: 0 | Z58: ='St. James'!M59 -> 0 | AA58: 0 | AB58: 0 | AC58: 0 | AD58: ='St. James'!M57+'St. James'!M58 -> 0 | AF58: =SUM(R58:AD58) -> 0 | AG58: =IF(AE58="","Blank",IF(AE58=AF58,"Yes","No")) -> Blank | AH58: =Tensas!L22 -> 8567911 | AI58: =O58+AE58 -> 8567911 | AJ58: =IF(AH58="","Blank",IF(AH58=AI58,"Yes","No")) -> Yes
A59: Terrebonne | B59: =Terrebonne!N7 -> 4988188 | C59: =Terrebonne!N8 -> 44105622 | D59: 0 | E59: =Terrebonne!N16 -> 28429056 | F59: 0 | G59: =Terrebonne!N17 -> 20694379 | H59: 0 | I59: 0 | J59: 0 | K59: 0 | L59: 0 | M59: 0 | N59: =Terrebonne!N18 -> 199508522 | O59: =Terrebonne!N21 -> 297725767 | P59: =SUM(B59:N59) -> 297725767 | Q59: =IF(O59="","Blank",IF(O59=P59,"Yes","No")) -> Yes | R59: =Terrebonne!N26 -> 3767923 | S59: =Terrebonne!N27 -> 11900470 | T59: 0 | U59: =Terrebonne!N42 -> 11395744 | V59: 0 | W59: =Terrebonne!N43 -> 3092446 | X59: 0 | Y59: 0 | Z59: 0 | AA59: 0 | AB59: 0 | AC59: 0 | AD59: =Terrebonne!N38+Terrebonne!N39+Terrebonne!N40+Terrebonne!N41 -> 120946538 | AE59: =Terrebonne!N46 -> 151103121 | AF59: =SUM(R59:AD59) -> 151103121 | AG59: =IF(AE59="","Blank",IF(AE59=AF59,"Yes","No")) -> Yes | AH59: =Terrebonne!N21+Terrebonne!N46 -> 448828888 | AI59: =O59+AE59 -> 448828888 | AJ59: =IF(AH59="","Blank",IF(AH59=AI59,"Yes","No")) -> Yes
A60: Union | B60: =Union!M9 -> 760833 | C60: =Union!M10 -> 1119052 | D60: 0 | E60: =Union!M30 -> 5246518 | F60: =Union!M29+Union!M31+Union!M32 -> 2635808 | G60: =Union!M33 -> 1957093 | H60: 0 | I60: =Union!M37+Union!M38+Union!M39+Union!M40 -> 223496 | J60: =Union!M35 -> 40376 | K60: =Union!M34 -> 224671 | L60: 0 | M60: 0 | N60: ='St. Mary'!M26 -> 0 | O60: =Union!M44 -> 12207847 | P60: =SUM(B60:N60) -> 12207847 | Q60: =IF(O60="","Blank",IF(O60=P60,"Yes","No")) -> Yes | R60: ='St. Mary'!M38+'St. Mary'!M39 -> 0 | S60: ='St. Mary'!M37 -> 0 | T60: 0 | U60: 0 | V60: 0 | W60: ='St. Mary'!M50 -> 0 | X60: 0 | Y60: 0 | Z60: 0 | AA60: 0 | AB60: 0 | AC60: 0 | AD60: 0 | AF60: =SUM(R60:AD60) -> 0 | AG60: =IF(AE60="","Blank",IF(AE60=AF60,"Yes","No")) -> Blank | AH60: =Union!L44 -> 12207847 | AI60: =O60+AE60 -> 12207847 | AJ60: =IF(AH60="","Blank",IF(AH60=AI60,"Yes","No")) -> Yes
A61: Vermillion | B61: =Vermillion!M9 -> 1893204 | C61: =Vermillion!M10 -> 3747744 | D61: 0 | E61: =Vermillion!M24 -> 9431363 | F61: ='St. James'!M35 -> 0 | G61: 0 | H61: 0 | I61: 0 | J61: =Vermillion!M25 -> 5567795 | K61: 0 | L61: 0 | M61: 0 | N61: =Vermillion!M27+Vermillion!M28 -> 61860148 | O61: =Vermillion!M32 -> 82500254 | P61: =SUM(B61:N61) -> 82500254 | Q61: =IF(O61="","Blank",IF(O61=P61,"Yes","No")) -> Yes | R61: 0 | S61: 0 | T61: 0 | U61: ='St. James'!M59 -> 0 | V61: 0 | W61: 0 | X61: 0 | Y61: 0 | Z61: ='St. James'!M62 -> 0 | AA61: 0 | AB61: 0 | AC61: 0 | AD61: ='St. James'!M60+'St. James'!M61 -> 0 | AF61: =SUM(R61:AD61) -> 0 | AG61: =IF(AE61="","Blank",IF(AE61=AF61,"Yes","No")) -> Blank | AH61: =Vermillion!L32 -> 82500254 | AI61: =O61+AE61 -> 82500254 | AJ61: =IF(AH61="","Blank",IF(AH61=AI61,"Yes","No")) -> Yes
A62: Vernon | B62: =Vernon!K7 -> 1695977 | C62: =Terrebonne!N11 -> 0 | D62: 0 | E62: =Vernon!K10 -> 6348922 | F62: 0 | G62: =Vernon!K11 -> 8930284 | H62: 0 | I62: =Vernon!K13 -> 544834 | J62: 0 | K62: 0 | L62: 0 | M62: 0 | N62: =Vernon!K12 -> 27802037 | O62: =Vernon!K14 -> 45322054 | P62: =SUM(B62:N62) -> 45322054 | Q62: =IF(O62="","Blank",IF(O62=P62,"Yes","No")) -> Yes | R62: =Terrebonne!N29 -> 0 | S62: =Terrebonne!N30 -> 0 | T62: 0 | U62: =Terrebonne!N45 -> 0 | V62: 0 | W62: 0 | X62: 0 | Y62: 0 | Z62: 0 | AA62: 0 | AB62: 0 | AC62: 0 | AD62: 0 | AF62: =SUM(R62:AD62) -> 0 | AG62: =IF(AE62="","Blank",IF(AE62=AF62,"Yes","No")) -> Blank | AH62: =Vernon!J14 -> 45322054 | AI62: =O62+AE62 -> 45322054 | AJ62: =IF(AH62="","Blank",IF(AH62=AI62,"Yes","No")) -> Yes
A63: Washington | B63: =Washington!M8 -> 2560211 | C63: =Washington!M9 -> 217385 | D63: =Tangipahoa!M12 -> 0 | E63: =Washington!M21 -> 6349642 | F63: 0 | G63: =Washington!M22 -> 1395236 | H63: 0 | I63: =Washington!M23 -> 1975 | J63: 0 | K63: 0 | L63: =Washington!M26 -> 16098602 | M63: 0 | N63: =Washington!M24+Washington!M25 -> 12527874 | O63: =Washington!M29 -> 39150925 | P63: =SUM(B63:N63) -> 39150925 | Q63: =IF(O63="","Blank",IF(O63=P63,"Yes","No")) -> Yes | R63: 0 | S63: 0 | T63: 0 | U63: 0 | V63: 0 | W63: 0 | X63: 0 | Y63: 0 | Z63: 0 | AA63: 0 | AB63: 0 | AC63: 0 | AD63: 0 | AF63: =SUM(R63:AD63) -> 0 | AG63: =IF(AE63="","Blank",IF(AE63=AF63,"Yes","No")) -> Blank | AH63: =Washington!M29 -> 39150925 | AI63: =O63+AE63 -> 39150925 | AJ63: =IF(AH63="","Blank",IF(AH63=AI63,"Yes","No")) -> Yes
A64: Webster | B64: =Webster!M9 -> 1212782 | C64: ='St. Tammany'!O17 -> 0 | D64: ='St. Tammany'!O19+'St. Tammany'!O20+'St. Tammany'!O21 -> 0 | E64: =Webster!M21 -> 6892714 | F64: 0 | G64: ='St. Tammany'!O42+'St. Tammany'!O43 -> 0 | H64: 0 | I64: =Webster!M24 -> 740705 | J64: =Webster!M23 -> 923225 | K64: 0 | L64: 0 | M64: 0 | N64: =Webster!M22 -> 1762052 | O64: =Webster!M28 -> 11531478 | P64: =SUM(B64:N64) -> 11531478 | Q64: =IF(O64="","Blank",IF(O64=P64,"Yes","No")) -> Yes | R64: ='St. Tammany'!O52 -> 0 | S64: ='St. Tammany'!O53 -> 0 | T64: 0 | U64: ='St. Tammany'!O67 -> 0 | V64: ='St. Tammany'!O66 -> 0 | W64: 0 | X64: 0 | Y64: 0 | Z64: 0 | AA64: 0 | AB64: 0 | AC64: 0 | AD64: ='St. Tammany'!O72+'St. Tammany'!O73 -> 0 | AF64: =SUM(R64:AD64) -> 0 | AG64: =IF(AE64="","Blank",IF(AE64=AF64,"Yes","No")) -> Blank | AH64: =Webster!L28 -> 11531478 | AI64: =O64+AE64 -> 11531478 | AJ64: =IF(AH64="","Blank",IF(AH64=AI64,"Yes","No")) -> Yes
A65: West Baton Rouge | B65: ='West Baton Rouge'!M9 -> 1760826 | C65: ='West Baton Rouge'!M10 -> 1260003 | D65: 0 | E65: ='West Baton Rouge'!M20 -> 25337975 | F65: 0 | G65: ='West Baton Rouge'!M21 -> 3363008 | H65: 0 | I65: =Vernon!K16 -> 0 | J65: 0 | K65: 0 | L65: 0 | M65: 0 | N65: ='West Baton Rouge'!M22 -> 29443251 | O65: ='West Baton Rouge'!M26 -> 61165063 | P65: =SUM(B65:N65) -> 61165063 | Q65: =IF(O65="","Blank",IF(O65=P65,"Yes","No")) -> Yes | R65: =Terrebonne!N32 -> 0 | S65: =Terrebonne!N33 -> 0 | T65: 0 | U65: =Terrebonne!N48 -> 0 | V65: 0 | W65: 0 | X65: 0 | Y65: 0 | Z65: 0 | AA65: 0 | AB65: 0 | AC65: 0 | AD65: 0 | AF65: =SUM(R65:AD65) -> 0 | AG65: =IF(AE65="","Blank",IF(AE65=AF65,"Yes","No")) -> Blank | AH65: ='West Baton Rouge'!L26 -> 61165063 | AI65: =O65+AE65 -> 61165063 | AJ65: =IF(AH65="","Blank",IF(AH65=AI65,"Yes","No")) -> Yes
A66: West Carroll | B66: ='West Carroll'!M9 -> 936927 | C66: ='West Carroll'!M11 -> 24000 | D66: ='West Carroll'!M10 -> 89589 | E66: ='West Carroll'!M30 -> 3264952 | F66: ='West Carroll'!M31 -> 1978893 | G66: ='West Carroll'!M34+'West Carroll'!M33 -> 657197 | H66: 0 | I66: 0 | J66: ='West Carroll'!M32 -> 13339 | K66: ='West Carroll'!M35 -> 155568 | L66: 0 | M66: 0 | N66: ='West Carroll'!M28+'West Carroll'!M29 -> 6896805 | O66: ='West Carroll'!M39 -> 14017270 | P66: =SUM(B66:N66) -> 14017270 | Q66: =IF(O66="","Blank",IF(O66=P66,"Yes","No")) -> Yes | R66: 0 | S66: 0 | T66: 0 | U66: 0 | V66: 0 | W66: 0 | X66: 0 | Y66: 0 | Z66: 0 | AA66: 0 | AB66: 0 | AC66: 0 | AD66: 0 | AF66: =SUM(R66:AD66) -> 0 | AG66: =IF(AE66="","Blank",IF(AE66=AF66,"Yes","No")) -> Blank | AH66: ='West Carroll'!L39 -> 14017270 | AI66: =O66+AE66 -> 14017270 | AJ66: =IF(AH66="","Blank",IF(AH66=AI66,"Yes","No")) -> Yes
A67: West Feliciana | B67: ='West Feliciana'!N7 -> 1388267 | C67: ='West Feliciana'!N8 -> 1195435 | D67: 0 | E67: ='West Feliciana'!N19 -> 10232299 | F67: 0 | G67: ='West Feliciana'!N20 -> 446329 | H67: 0 | I67: ='West Feliciana'!N22 -> 72081 | J67: ='West Feliciana'!N21 -> 9399 | K67: ='West Feliciana'!N24 -> 124354 | L67: 0 | M67: 0 | N67: ='West Feliciana'!N23 -> 3162459 | O67: ='West Feliciana'!N27 -> 16630623 | P67: =SUM(B67:N67) -> 16630623 | Q67: =IF(O67="","Blank",IF(O67=P67,"Yes","No")) -> Yes | R67: 0 | S67: 0 | T67: 0 | U67: 0 | V67: 0 | W67: ='West Feliciana'!N42 -> 120849 | X67: 0 | Y67: 0 | Z67: 0 | AA67: ='West Feliciana'!N43 -> 16683 | AB67: 0 | AC67: 0 | AD67: ='West Feliciana'!N41 -> 9840641 | AE67: ='West Feliciana'!N46 -> 9978173 | AF67: =SUM(R67:AD67) -> 9978173 | AG67: =IF(AE67="","Blank",IF(AE67=AF67,"Yes","No")) -> Yes | AH67: ='West Feliciana'!M46+'West Feliciana'!M27 -> 26608796 | AI67: =O67+AE67 -> 26608796 | AJ67: =IF(AH67="","Blank",IF(AH67=AI67,"Yes","No")) -> Yes
A68: Winn | B68: =Winn!M8 -> 223675 | C68: =Winn!M14 -> 1298815 | D68: 0 | E68: =Winn!M21 -> 698972 | F68: 0 | G68: =Winn!M22 -> 421743 | H68: 0 | I68: =Winn!M25 -> 151415 | J68: =Winn!M24 -> 2335 | K68: =Winn!M23 -> 64062 | L68: 0 | M68: 0 | N68: =Winn!M27 -> 737271 | O68: =Winn!M30 -> 3598288 | P68: =SUM(B68:N68) -> 3598288 | Q68: =IF(O68="","Blank",IF(O68=P68,"Yes","No")) -> Yes | R68: =Terrebonne!N34 -> 0 | S68: =Terrebonne!N35 -> 0 | T68: 0 | U68: =Terrebonne!N50 -> 0 | V68: 0 | W68: 0 | X68: 0 | Y68: 0 | Z68: 0 | AA68: 0 | AB68: 0 | AC68: 0 | AD68: 0 | AF68: =SUM(R68:AD68) -> 0 | AG68: =IF(AE68="","Blank",IF(AE68=AF68,"Yes","No")) -> Blank | AH68: =Winn!L30 -> 3598288 | AI68: =O68+AE68 -> 3598288 | AJ68: =IF(AH68="","Blank",IF(AH68=AI68,"Yes","No")) -> Yes

Sheet Lafayette
D1: LAFAYETTE PARISH POLICE JURY
D2: Capital Assets
D3: For the Year Ended October 31, 2013
G7: Balance 11/01/12 | H7: Additions | I7: Deletions | J7: Balance 10/31/13 | K7: Cross Sectional
A8: Governmental Activities:
B9: Capital assets not being depreciated:
C10: Land | G10: 38247443 | H10: 270047 | I10: 0 | J10: =SUM(G10:I10) -> 38517490 | K10: =SUM(J10) -> 38517490
C11: Construction in progress | G11: 30874317 | H11: 24104541 | I11: -23298353 | J11: =SUM(G11:I11) -> 31680505 | K11: =SUM(J11) -> 31680505
B13: Other capital assets:
C14: Land improvements | G14: 6231119 | H14: 420400 | I14: 0 | J14: =SUM(G14:I14) -> 6651519
C15: Buildings and improvements | G15: 170879001 | H15: 3479264 | I15: -144842 | J15: =SUM(G15:I15) -> 174213423
C16: Vehicles | G16: 52110662 | H16: 3916443 | I16: -3172775 | J16: =SUM(G16:I16) -> 52854330
C17: Movables | G17: 32874173 | H17: 2550187 | I17: -223889 | J17: =SUM(G17:I17) -> 35200471
C18: Infrastructure | G18: 637794887 | H18: 21032505 | J18: =SUM(G18:I18) -> 658827392
D19: Totals | G19: =SUM(G10:G18) -> 969011602 | H19: =SUM(H10:H18) -> 55773387 | I19: =SUM(I10:I18) -> -26839859 | J19: =SUM(J10:J18) -> 997945130
B21: Less accumulated depreciation for:
C22: Land improvements | G22: 532297 | H22: 255358 | I22: 0 | J22: =SUM(G22:I22) -> 787655 | K22: =SUM(J22,J14) -> 7439174
C23: Buildings and improvements | G23: 77542860 | H23: 3656837 | I23: -69108 | J23: =SUM(G23:I23) -> 81130589 | K23: =SUM(J23,J15) -> 255344012
C24: Vehicles | G24: 31665948 | H24: 3720756 | I24: -2912516 | J24: =SUM(G24:I24) -> 32474188 | K24: =SUM(J24,J16) -> 85328518
C25: Movables | G25: 20971467 | H25: 2626892 | I25: -187159 | J25: =SUM(G25:I25) -> 23411200 | K25: =SUM(J25,J17) -> 58611671
C26: Infrastructure | G26: 255697323 | H26: 17004422 | I26: 0 | J26: =SUM(G26:I26) -> 272701745 | K26: =SUM(J26,J18) -> 931529137
D27: Total accumulated depreciation | G27: =SUM(G22:G26) -> 386409895 | H27: =SUM(H22:H26) -> 27264265 | I27: =SUM(I22:I26) -> -3168783 | J27: =SUM(J22:J26) -> 410505377
C28: Governmental activities capital assets, net | G28: =G19-G27 -> 582601707 | H28: =H19-H27 -> 28509122 | I28: =I19-I27 -> -23671076 | J28: =J19-J27 -> 587439753 | K28: =SUM(K22:K26,K10:K11) -> 1408450507
G30: Balance 11/01/12 | H30: Additions | I30: Deletions | J30: Balance 10/31/13
A31: Business-type activities:
B32: Capital assets not being depreciated:
C33: Land | G33: 19176349 | H33: 1992096 | J33: =SUM(G33:I33) -> 21168445 | K33: =SUM(J33) -> 21168445
C34: Construction in progress | G34: 29319113 | H34: 67194534 | I34: -51449922 | J34: =SUM(G34:I34) -> 45063725 | K34: =SUM(J34) -> 45063725
B36: Other capital assets:
C37: Buildings and improvements | G37: 3150901 | H37: 8748 | I37: 0 | J37: =SUM(G37:I37) -> 3159649
C38: Electric plant | G38: 690950504 | H38: 16553604 | I38: -1559172 | J38: =SUM(G38:I38) -> 705944936
C39: Water plant | G39: 139367051 | H39: 8928495 | I39: -138638 | J39: =SUM(G39:I39) -> 148156908
C40: Sewer plant | G40: 203212854 | H40: 16126165 | I40: -476165 | J40: =SUM(G40:I40) -> 218862854
C41: Fiber optics | G41: 118857347 | H41: 8105492 | I41: -157092 | J41: =SUM(G41:I41) -> 126805747
C42: Equipment | G42: 18593375 | H42: 106066 | I42: -163872 | J42: =SUM(G42:I42) -> 18535569
D43: Totals | G43: =SUM(G33:G42) -> 1222627494 | H43: =SUM(H33:H42) -> 119015200 | I43: =SUM(I33:I42) -> -53944861 | J43: =SUM(J33:J42) -> 1287697833
B45: Less accumulated depreciation for:
C46: Buildings and improvements | G46: -2923274 | H46: -8258 | I46: 0 | J46: =SUM(G46:I46) -> -2931532 | K46: =SUM(J46,J37) -> 228117
C47: Electric plant | G47: -375023592 | H47: -16419727 | I47: 1307307 | J47: =SUM(G47:I47) -> -390136012 | K47: =SUM(J47,J38) -> 315808924
C48: Water plant | G48: -50756707 | H48: -3704634 | I48: 127299 | J48: =SUM(G48:I48) -> -54334042 | K48: =SUM(J48,J39) -> 93822866
C49: Sewer plant | G49: -61676614 | H49: -4328760 | I49: 461679 | J49: =SUM(G49:I49) -> -65543695 | K49: =SUM(J49,J40) -> 153319159
C50: Fiber optics | G50: -30571005 | H50: -11244478 | I50: 18793 | J50: =SUM(G50:I50) -> -41796690 | K50: =SUM(J50,J41) -> 85009057
C51: Equipment | G51: -3509018 | H51: -613487 | I51: 31129 | J51: =SUM(G51:I51) -> -4091376 | K51: =SUM(J51,J42) -> 14444193
D52: Total accumulated depreciation | G52: =SUM(G46:G51) -> -524460210 | H52: =SUM(H46:H51) -> -36319344 | I52: =SUM(I46:I51) -> 1946207 | J52: =SUM(J46:J51) -> -558833347
C53: Business-type activities capital assets, net | G53: =SUM(G52,G43) -> 698167284 | H53: =SUM(H52,H43) -> 82695856 | I53: =SUM(I52,I43) -> -51998654 | J53: =SUM(J52,J43) -> 728864486 | K53: =SUM(K47:K51,K46,K33:K34) -> 728864486

Sheet LaFourche
C1: LAFOURCHE PARISH POLICE JURY
C2: Capital Assets
C3: For the Year Ended December 31, 2013
F6: Balance 12/31/12 | G6: Additions | H6: Deletions & Adjustments | I6: Balance 12/31/13 | J6: Cross Sectional
A7: Cost of Capital Assets
B8: Land | F8: 1486401 | H8: -170798 | I8: =SUM(F8:H8) -> 1315603 | J8: =SUM(I8) -> 1315603
B9: Construction in progress | F9: 15114930 | G9: 18321399 | H9: -9651352 | I9: =SUM(F9:H9) -> 23784977 | J9: =SUM(I9) -> 23784977
C10: Capital Assets Non-depreciable | F10: =SUM(F8:F9) -> 16601331 | G10: =SUM(G8:G9) -> 18321399 | H10: =SUM(H8:H9) -> -9822150 | I10: 25100579
B12: Buildings | F12: 33585886 | G12: 4643130 | H12: -6931425 | I12: =SUM(F12:H12) -> 31297591
B13: Infrastructure | F13: 106610769 | G13: 1095451 | I13: =SUM(F13:H13) -> 107706220
B14: Drainage & Other Improvements | F14: 2464790 | G14: 96103 | H14: 60000 | I14: =SUM(F14:H14) -> 2620893
B15: Pumps & Sewerage | F15: 32610612 | G15: 4687965 | I15: =SUM(F15:H15) -> 37298577
B16: Equipments & Furniture | F16: 7411059 | G16: 847266 | H16: -748151 | I16: =SUM(F16:H16) -> 7510174
B17: Vehicles & Equipment | F17: 8558656 | G17: 1289116 | H17: -40605 | I17: =SUM(F17:H17) -> 9807167
C18: Total Capital Assets--Depreciable | F18: =SUM(F12:F17) -> 191241772 | G18: =SUM(G12:G17) -> 12659031 | H18: =SUM(H12:H17) -> -7660181 | I18: 196240621
C19: Total Cost of Capital Assets | F19: =F10+F18 -> 207843103 | G19: =G10+G18 -> 30980430 | H19: =H10+H18 -> -17482331 | I19: =I10+I18 -> 221341200
A21: Accumulated Depreciation
B22: Buildings | F22: -7238270 | G22: -715358 | H22: 1085575 | I22: =SUM(F22:H22) -> -6868053 | J22: =SUM(I22,I12) -> 24429538
B23: Infrastructure | F23: -84296255 | G23: -5251751 | I23: =SUM(F23:H23) -> -89548006 | J23: =SUM(I23,I13) -> 18158214
B24: Drainage & Other Improvements | F24: -1169104 | G24: -178122 | H24: -4000 | I24: =SUM(F24:H24) -> -1351226 | J24: =SUM(I24,I14) -> 1269667
B25: Pumps & Sewerage | F25: -29012407 | G25: -849375 | I25: =SUM(F25:H25) -> -29861782 | J25: =SUM(I25,I15) -> 7436795
B26: Equipment & Furniture | F26: -4409408 | G26: -1127484 | H26: 1352045 | I26: =SUM(F26:H26) -> -4184847 | J26: =SUM(I26,I16) -> 3325327
B27: Vehicles & Equipment | F27: -6045301 | G27: -569415 | H27: 139916 | I27: =SUM(F27:H27) -> -6474800 | J27: =SUM(I27,I17) -> 3332367
C28: Total accumulated depreciation | F28: =SUM(F22:F27) -> -132170745 | G28: =SUM(G22:G27) -> -8691505 | H28: =SUM(H22:H27) -> 2573536 | I28: -138288715
C29: Net Depreciable Capital Assets | F29: =F18+F28 -> 59071027 | G29: =G18+G28 -> 3967526 | H29: -5086645 | I29: =I18+I28 -> 57951906
C30: Net Capital Assets | F30: 75672358 | I30: 83052485 | J30: =SUM(J22:J27,J8:J9) -> 83052488

Sheet Lincoln
D1: LINCOLN PARISH POLICE JURY
D2: Capital Assets
D3: For the Year Ended December 31, 2013
I5: Balance January 1, 2013 | L5: Balance December 31, 2013 | M5: Cross Sectional
J6: Increases | K6: Decreases
A7: Governmental Activities
A8: Nondepreciable capital assets:
B9: Land | I9: 1775786 | L9: =SUM(I9:K9) -> 1775786 | M9: =SUM(L9) -> 1775786
B10: Infrastructure - CIP
B11: Construction in progress | L11: =SUM(I11:K11) -> 0 | M11: =SUM(L11) -> 0
C12: Total Capital assets not being depreciated | I12: =SUM(I9:I11) -> 1775786 | J12: =SUM(J9:J11) -> 0 | K12: =SUM(K9:K11) -> 0 | L12: =SUM(L9:L11) -> 1775786
A13: Depreciable capital assets
B14: Buildings | I14: 13459488 | L14: =SUM(I14:K14) -> 13459488
B15: Infrastructure | I15: 26022018 | L15: =SUM(I15:K15) -> 26022018
B16: Improvements | I16: 6845204 | L16: =SUM(I16:K16) -> 6845204
B17: Vehicles | I17: 1733825 | J17: 10000 | K17: -125692 | L17: =SUM(I17:K17) -> 1618133
B18: Furniture and Fixtures | I18: 1394667 | K18: -13073 | L18: =SUM(I18:K18) -> 1381594
B19: Machinery and Equipment | I19: 4195355 | J19: 471822 | K19: -291151 | L19: =SUM(I19:K19) -> 4376026
C20: Total depreciable capital assets | I20: =SUM(I14:I19) -> 53650557 | J20: =SUM(J14:J19) -> 481822 | K20: =SUM(K14:K19) -> -429916 | L20: =SUM(L14:L19) -> 53702463
A21: Less accumulated depreciation for:
B22: Buildings | I22: -4696075 | J22: -141454 | L22: =SUM(I22:K22) -> -4837529 | M22: =SUM(L22,L14) -> 8621959
B23: Infrastructure | I23: -18164949 | J23: -327671 | L23: =SUM(I23:K23) -> -18492620 | M23: =SUM(L23,L15) -> 7529398
B24: Improvements | I24: -3158795 | J24: -386142 | L24: =SUM(I24:K24) -> -3544937 | M24: =SUM(L24,L16) -> 3300267
B25: Vehicles | I25: -1126804 | J25: -65483 | K25: 105527 | L25: =SUM(I25:K25) -> -1086760 | M25: =SUM(L25,L17) -> 531373
B26: Furniture and Fixtures | I26: -1015388 | J26: -58316 | K26: 7288 | L26: =SUM(I26:K26) -> -1066416 | M26: =SUM(L26,L18) -> 315178
B27: Machinery and Equipment | I27: -2379461 | J27: -359190 | K27: 158849 | L27: =SUM(I27:K27) -> -2579802 | M27: =SUM(L27,L19) -> 1796224
C28: Total accumulated depreciation | I28: =SUM(I22:I27) -> -30541472 | J28: =SUM(J22:J27) -> -1338256 | K28: =SUM(K22:K27) -> 271664 | L28: =SUM(L22:L27) -> -31608064
B29: Total depreciable capital assets, net | I29: =I28+I20 -> 23109085 | J29: =J28+J20 -> -856434 | K29: =K28+K20 -> -158252 | L29: =L28+L20 -> 22094399
B30: Capital Assets, net | I30: =I12+I29 -> 24884871 | J30: =J12+J29 -> -856434 | K30: =K12+K29 -> -158252 | L30: =L12+L29 -> 23870185 | M30: =SUM(M22:M27,M9:M11) -> 23870185

Sheet Livingston
D1: LIVINGSTON PARISH POLICE JURY
D2: Capital Assets
D3: For the Year Ended December 31, 2013
I5: Balance January 1, 2013 | L5: Balance December 31, 2013 | M5: Cross Sectional
J6: Increases | K6: Decreases
A7: Governmental Activities
A8: Nondepreciable capital assets:
B9: Land | I9: 5844429 | L9: =SUM(I9:K9) -> 5844429 | M9: =SUM(L9) -> 5844429
B10: Construction in progress | I10: 7416561 | J10: 12652731 | K10: -4958195 | L10: =SUM(I10:K10) -> 15111097 | M10: =SUM(L10) -> 15111097
C11: Total Capital assets not being depreciated | I11: =SUM(I9:I10) -> 13260990 | J11: =SUM(J9:J10) -> 12652731 | K11: =SUM(K9:K10) -> -4958195 | L11: =SUM(L9:L10) -> 20955526
A12: Depreciable capital assets
B13: Buildings | I13: 53096695 | J13: 1717022 | L13: =SUM(I13:K13) -> 54813717
B14: Recreational Facilities | I14: 3758232 | L14: =SUM(I14:K14) -> 3758232
B15: Machinery and Equipment | I15: 6290267 | J15: 477952 | K15: -529226 | L15: =SUM(I15:K15) -> 6238993
B16: Sewer System | I16: 2126234 | L16: =SUM(I16:K16) -> 2126234
B17: Infrastructure | I17: 143108015 | J17: 3254528 | L17: =SUM(I17:K17) -> 146362543
B18: Furniture and Fixtures | I18: 250660 | L18: =SUM(I18:K18) -> 250660
C19: Total depreciable capital assets | I19: =SUM(I13:I18) -> 208630103 | J19: =SUM(J13:J18) -> 5449502 | K19: =SUM(K13:K18) -> -529226 | L19: =SUM(L13:L18) -> 213550379
A20: Less accumulated depreciation for:
B21: Infrastructure | I21: -7991608 | J21: -1392161 | L21: =SUM(I21:K21) -> -9383769 | M21: =SUM(L21,L13) -> 45429948
B22: Recreational Facilities | I22: -164423 | J22: -141749 | L22: =SUM(I22:K22) -> -306172 | M22: =SUM(L22,L14) -> 3452060
B23: Machinery and Equipment | I23: -4559562 | J23: -561739 | K23: 421253 | L23: =SUM(I23:K23) -> -4700048 | M23: =SUM(L23,L15) -> 1538945
B24: Sewer System | I24: -99937 | J24: -9081199 | L24: =SUM(I24:K24) -> -9181136 | M24: =SUM(L24,L16) -> -7054902
B25: Infrastructure | I25: -66964782 | J25: -28940 | L25: =SUM(I25:K25) -> -66993722 | M25: =SUM(L25,L17) -> 79368821
B26: Furniture and Fixtures | I26: -174574 | J26: -93956 | L26: =SUM(I26:K26) -> -268530 | M26: =SUM(L26,L18) -> -17870
C27: Total accumulated depreciation | I27: =SUM(I21:I26) -> -79954886 | J27: =SUM(J21:J26) -> -11299744 | K27: =SUM(K21:K26) -> 421253 | L27: =SUM(L21:L26) -> -90833377
B28: Total depreciable capital assets, net | I28: 128675217 | J28: -5850242 | K28: -107973 | L28: =SUM(I28:K28) -> 122717002
B29: Capital Assets, net | I29: =I11+I28 -> 141936207 | J29: =J11+J28 -> 6802489 | K29: =K11+K28 -> -5066168 | L29: =L11+L28 -> 143672528 | M29: =SUM(M21:M26,M9:M10) -> 143672528
A32: Business-Type activities
A33: Nondepreciable capital assets:
B34: Land | I34: 13243 | L34: =SUM(I34:K34) -> 13243 | M34: =SUM(L34) -> 13243
B35: Construction in progress | I35: 223862 | J35: 629643 | K35: -676022 | L35: =SUM(I35:K35) -> 177483 | M35: =SUM(L35) -> 177483
C36: Total Capital assets not being depreciated | I36: =SUM(I34:I35) -> 237105 | J36: =SUM(J34:J35) -> 629643 | K36: =SUM(K34:K35) -> -676022 | L36: =SUM(L34:L35) -> 190726
A37: Depreciable capital assets
B38: Utility system | I38: 9261411 | J38: 684247 | L38: =SUM(I38:K38) -> 9945658
C39: Total depreciable capital assets | I39: =SUM(I38:I38) -> 9261411 | J39: =SUM(J38:J38) -> 684247 | K39: =SUM(K38:K38) -> 0 | L39: =SUM(L38:L38) -> 9945658
A40: Less accumulated depreciation for:
B41: Utility System | I41: -1558758 | J41: -280146 | L41: =SUM(I41:K41) -> -1838904 | M41: =SUM(L41,L38) -> 8106754
C42: Total accumulated depreciation | I42: =SUM(I41:I41) -> -1558758 | J42: =SUM(J41:J41) -> -280146 | K42: =SUM(K41:K41) -> 0 | L42: =SUM(L41:L41) -> -1838904
B43: Total depreciable capital assets, net | I43: 7702653 | J43: 404101 | K43: =K39-K42 -> 0 | L43: =SUM(I43:K43) -> 8106754
B44: Capital Assets, net | I44: =I36+I43 -> 7939758 | J44: =J36+J43 -> 1033744 | K44: =K36+K43 -> -676022 | L44: =L36+L43 -> 8297480 | M44: =SUM(M41,M34:M35) -> 8297480

Sheet Madison
D1: MADISON PARISH POLICE JURY
D2: Capital Assets
D3: For the Year Ended December 31, 2013
I5: Balance January 1, 2013 | L5: Balance December 31, 2013 | M5: Cross Sectional
J6: Increases | K6: Decreases
A7: Governmental Activities
A8: Nondepreciable capital assets:
B9: Land | I9: 188750 | L9: =SUM(I9:K9) -> 188750 | M9: =SUM(L9) -> 188750
B10: Quebec road | I10: 3771405 | L10: =SUM(I10:K10) -> 3771405 | M10: =L10 -> 3771405
B11: Construction in progress - health unit | I11: 98884 | J11: 1410655 | K11: -1509539 | L11: =SUM(I11:K11) -> 0 | M11: =SUM(L11) -> 0
C12: Total Capital assets not being depreciated | I12: =SUM(I9:I11) -> 4059039 | J12: =SUM(J9:J11) -> 1410655 | K12: =SUM(K9:K11) -> -1509539 | L12: =SUM(L9:L11) -> 3960155
A13: Depreciable capital assets
B14: Health unit | J14: 1509539 | L14: =SUM(I14:K14) -> 1509539 | M14: =L14 -> 1509539
B15: Buildings and improvements | I15: 5553844 | J15: 435581 | L15: =SUM(I15:K15) -> 5989425
B16: Furniture and equipment | I16: 3096559 | J16: 373155 | K16: -84149 | L16: =SUM(I16:K16) -> 3385565
B17: Books and periodicals | I17: 440791 | J17: 51067 | K17: -5708 | L17: =SUM(I17:K17) -> 486150
C18: Total depreciable capital assets | I18: =SUM(I14:I17) -> 9091194 | J18: =SUM(J14:J17) -> 2369342 | K18: =SUM(K14:K17) -> -89857 | L18: =SUM(L14:L17) -> 11370679
A19: Less accumulated depreciation for:
B20: Buildings and improvements | I20: 4332904 | J20: 84315 | L20: =SUM(I20:K20) -> 4417219 | M20: =L15-L20 -> 1572206
B21: Furniture and equipment | I21: 2209465 | J21: 209399 | K21: -59332 | L21: =SUM(I21:K21) -> 2359532 | M21: =L16-L21 -> 1026033
B22: Books and periodicals | I22: 333809 | J22: 48615 | K22: -5708 | L22: =SUM(I22:K22) -> 376716 | M22: =L17-L22 -> 109434
C23: Total accumulated depreciation | I23: =SUM(I20:I22) -> 6876178 | J23: =SUM(J20:J22) -> 342329 | K23: =SUM(K20:K22) -> -65040 | L23: =SUM(L20:L22) -> 7153467
B24: Total depreciable capital assets, net | I24: =I18-I23 -> 2215016 | J24: =J18-J23 -> 2027013 | K24: =K18-K23 -> -24817 | L24: =L18-L23 -> 4217212
B25: Capital Assets, net | I25: =I12+I24 -> 6274055 | J25: =J12+J24 -> 3437668 | K25: =K12+K24 -> -1534356 | L25: =L12+L24 -> 8177367 | M25: =SUM(M14:M22,M9:M11) -> 8177367

Sheet Morehouse
D1: MOREHOUSE PARISH POLICE JURY
D2: Capital Assets
D3: For the Year Ended December 31, 2013
I5: Balance 1/1/2013 | J5: Additions | K5: Deletions | L5: Prior Period Adjustment | M5: Balance 12/31/2013
A7: Capital assets, not being depreciated
B8: Land | I8: 783626 | K8: -5000 | M8: =SUM(I8:L8) -> 778626 | N8: =M8 -> 778626
A9: Capital assets being depreciated
B10: Buildings and improvements | I10: 16405517 | J10: 183124 | K10: -10356 | L10: 22341 | M10: =SUM(I10:L10) -> 16600626
B11: Machinery and equipment | I11: 3379690 | J11: 29913 | L11: -322458 | M11: =SUM(I11:L11) -> 3087145
B12: Total capital assets, being depreciated | I12: =SUM(I10:I11) -> 19785207 | J12: =SUM(J10:J11) -> 213037 | K12: =SUM(K10:K11) -> -10356 | L12: =SUM(L10:L11) -> -300117 | M12: =SUM(M10:M11) -> 19687771
A13: Less accumulated depreciation for:
B14: Buildings and improvements | I14: 4217857 | J14: 406598 | K14: -10356 | M14: =SUM(I14:L14) -> 4614099 | N14: =M10-M14 -> 11986527
B15: Machinery and equipment | I15: 2234911 | J15: 299015 | L15: -326049 | M15: =SUM(I15:L15) -> 2207877 | N15: =M11-M15 -> 879268
B16: Total accumulated depreciation | I16: =SUM(I14:I15) -> 6452768 | J16: =SUM(J14:J15) -> 705613 | K16: =SUM(K14:K15) -> -10356 | L16: =SUM(L14:L15) -> -326049 | M16: =SUM(I16:L16) -> 6821976
B17: Total capital asseys being depreciated, net | I17: 13332439 | J17: -492576 | L17: 25932 | M17: =SUM(I17:L17) -> 12865795
D19: Total capital assets | I19: =I17+I8 -> 14116065 | J19: =J17+J8 -> -492576 | K19: =K17+K8 -> -5000 | L19: =L17+L8 -> 25932 | M19: =M17+M8 -> 13644421 | N19: =SUM(N8:N15) -> 13644421

Sheet Natchitoches
D1: NATCHITOCHES PARISH POLICE JURY
D2: Capital Assets
D3: For the Year Ended December 31, 2013
I5: Balance January 1, 2013 | L5: Balance December 31, 2013 | M5: Cross Sectional
J6: Increases | K6: Decreases
A7: General Fund:
A8: Capital assets:
B9: Land | I9: 423873 | K9: -500 | L9: =SUM(I9:K9) -> 423373 | M9: =SUM(L9) -> 423373
B10: Building | I10: 4973966 | L10: =SUM(I10:K10) -> 4973966
B11: Office equipment | I11: 244564 | K11: -30911 | L11: =SUM(I11:K11) -> 213653
B12: Other equipment | I12: 87409 | K12: -29254 | L12: =SUM(I12:K12) -> 58155
B13: Vehicles | I13: 230923 | L13: =SUM(I13:K13) -> 230923
C14: Total assets | I14: =SUM(I9:I13) -> 5960735 | J14: =SUM(J9:J13) -> 0 | K14: =SUM(K9:K13) -> -60665 | L14: =SUM(L9:L13) -> 5900070
A16: Accumulated depreciation:
B17: Building | I17: 3273123 | J17: 90340 | L17: =SUM(I17:K17) -> 3363463 | M17: =L10-L17 -> 1610503
B18: Office equipment | I18: 241276 | J18: 1181 | K18: -30911 | L18: =SUM(I18:K18) -> 211546 | M18: =L11-L18 -> 2107
B19: Other equipment | I19: 73211 | J19: 3124 | K19: -29136 | L19: =SUM(I19:K19) -> 47199 | M19: =L12-L19 -> 10956
B20: Vehicles | I20: 228214 | J20: 2707 | L20: =SUM(I20:K20) -> 230921 | M20: =L13-L20 -> 2
C21: Total accumulated depreciation | I21: =SUM(I17:I20) -> 3815824 | J21: =SUM(J17:J20) -> 97352 | K21: =SUM(K17:K20) -> -60047 | L21: =SUM(L17:L20) -> 3853129
A23: Civil defense:
A24: Capital assets:
B25: Office equipment | I25: 38504 | L25: =SUM(I25:K25) -> 38504
B26: Other equipment | I26: 18265 | L26: =SUM(I26:K26) -> 18265
C27: Total assets | I27: =SUM(I25:I26) -> 56769 | J27: =SUM(J25:J26) -> 0 | K27: =SUM(K25:K26) -> 0 | L27: =SUM(L25:L26) -> 56769
A29: Accumulated depreciation:
B30: Office equipment | I30: 38504 | L30: =SUM(I30:K30) -> 38504 | M30: =L25-L30 -> 0
B31: Other equipment | I31: 18265 | L31: =SUM(I31:K31) -> 18265 | M31: =L26-L31 -> 0
C32: Total accumulated depreciation | I32: =SUM(I30:I31) -> 56769 | J32: =SUM(J30:J31) -> 0 | K32: =SUM(K30:K31) -> 0 | L32: =SUM(L30:L31) -> 56769
A34: Criminal Court/DA:
A35: Capital assets:
B36: Office equipment | I36: 50880 | K36: -12300 | L36: =SUM(I36:K36) -> 38580
B37: Other equipment | I37: 39733 | K37: -3169 | L37: =SUM(I37:K37) -> 36564
C38: Total assets | I38: =SUM(I36:I37) -> 90613 | J38: =SUM(J36:J37) -> 0 | K38: =SUM(K36:K37) -> -15469 | L38: =SUM(L36:L37) -> 75144
A40: Accumulated depreciation:
B41: Office equipment | I41: 50880 | K41: -12300 | L41: =SUM(I41:K41) -> 38580 | M41: =L36-L41 -> 0
B42: Other equipment | I42: 39733 | K42: -3169 | L42: =SUM(I42:K42) -> 36564 | M42: =L37-L42 -> 0
C43: Total accumulated depreciation | I43: =SUM(I42:I42) -> 39733 | J43: =SUM(J42:J42) -> 0 | K43: =SUM(K42:K42) -> -3169 | L43: =SUM(L42:L42) -> 36564
A45: Health Unit:
A46: Capital assets:
B47: Building | I47: 846415 | L47: =SUM(I47:K47) -> 846415
B48: Office equipment | I48: 57750 | K48: -1396 | L48: =SUM(I48:K48) -> 56354
B49: Other equipment | I49: 71086 | J49: 1349 | K49: -6590 | L49: =SUM(I49:K49) -> 65845
B50: Vehicles | I50: 214790 | L50: =SUM(I50:K50) -> 214790
C51: Total assets | I51: =SUM(I47:I50) -> 1190041 | J51: =SUM(J47:J50) -> 1349 | K51: =SUM(K47:K50) -> -7986 | L51: =SUM(L47:L50) -> 1183404
A53: Accumulated depreciation:
B54: Building | I54: 527899 | J54: 21160 | L54: =SUM(I54:K54) -> 549059 | M54: =L47-L54 -> 297356
B55: Office equipment | I55: 49611 | J55: 2921 | K55: -1396 | L55: =SUM(I55:K55) -> 51136 | M55: =L48-L55 -> 5218
B56: Other equipment | I56: 62006 | J56: 6055 | K56: -6590 | L56: =SUM(I56:K56) -> 61471 | M56: =L49-L56 -> 4374
B57: Vehicles | I57: 111247 | J57: 24463 | L57: =SUM(I57:K57) -> 135710 | M57: =L50-L57 -> 79080
C58: Total accumulated depreciation | I58: =SUM(I57:I57) -> 111247 | J58: =SUM(J57:J57) -> 24463 | K58: =SUM(K57:K57) -> 0 | L58: =SUM(L57:L57) -> 135710
A60: Government building:
A61: Capital assets:
B62: Other equipment | I62: 42178 | J62: 1995 | K62: -3692 | L62: =SUM(I62:K62) -> 40481
B63: Vehicles | I63: 12993 | L63: =SUM(I63:K63) -> 12993
C64: Total assets | I64: =SUM(I62:I63) -> 55171 | J64: =SUM(J62:J63) -> 1995 | K64: =SUM(K62:K63) -> -3692 | L64: =SUM(L62:L63) -> 53474
A66: Accumulated depreciation:
B67: Other equipment | I67: 18114 | J67: 3526 | K67: -3221 | L67: =SUM(I67:K67) -> 18419 | M67: =L62-L67 -> 22062
B68: Vehicles | I68: 12213 | J68: 260 | L68: =SUM(I68:K68) -> 12473 | M68: =L63-L68 -> 520
C69: Total accumulated depreciation | I69: =SUM(I67:I68) -> 30327 | J69: =SUM(J67:J68) -> 3786 | K69: =SUM(K67:K68) -> -3221 | L69: =SUM(L67:L68) -> 30892
A71: Head start:
A72: Capital assets:
B73: Building | I73: 140390 | K73: -4542 | L73: =SUM(I73:K73) -> 135848
B74: Office equipment | I74: 180889 | J74: 2354 | K74: -21856 | L74: =SUM(I74:K74) -> 161387
B75: Other equipment | I75: 376125 | J75: 8056 | K75: -27674 | L75: =SUM(I75:K75) -> 356507
B76: Vehicles | I76: 181279 | L76: =SUM(I76:K76) -> 181279
C77: Total assets | I77: =SUM(I73:I76) -> 878683 | J77: =SUM(J73:J76) -> 10410 | K77: =SUM(K73:K76) -> -54072 | L77: =SUM(L73:L76) -> 835021
A79: Accumulated depreciation:
B80: Building | I80: 115411 | J80: 5471 | K80: -3267 | L80: =SUM(I80:K80) -> 117615 | M80: =L73-L80 -> 18233
B81: Office equipment | I81: 179337 | J81: 1367 | K81: -21856 | L81: =SUM(I81:K81) -> 158848 | M81: =L74-L81 -> 2539
B82: Other equipment | I82: 248459 | J82: 24588 | K82: -25114 | L82: =SUM(I82:K82) -> 247933 | M82: =L75-L82 -> 108574
B83: Vehicles | I83: 181279 | L83: =SUM(I83:K83) -> 181279 | M83: =L76-L83 -> 0
C84: Total accumulated depreciation | I84: =SUM(I80:I83) -> 724486 | J84: =SUM(J80:J83) -> 31426 | K84: =SUM(K80:K83) -> -50237 | L84: =SUM(L80:L83) -> 705675
A86: LIHEAP:
A87: Capital assets:
B88: Office equipment | I88: 4256 | L88: =SUM(I88:K88) -> 4256
C89: Total assets | I89: =SUM(I88:I88) -> 4256 | J89: =SUM(J88:J88) -> 0 | K89: =SUM(K88:K88) -> 0 | L89: =SUM(L88:L88) -> 4256
A91: Accumulated depreciation:
B92: Office equipment | I92: 4256 | L92: =SUM(I92:K92) -> 4256 | M92: =L88-L92 -> 0
C93: Total accumulated depreciation | I93: =I92 -> 4256 | J93: =J92 -> 0 | K93: =K92 -> 0 | L93: =L92 -> 4256
A95: Rural transit:
A96: Capital assets:
B97: Vehicles | I97: 15425 | L97: =SUM(I97:K97) -> 15425
C98: Total assets | I98: =SUM(I97:I97) -> 15425 | J98: =SUM(J97:J97) -> 0 | K98: =SUM(K97:K97) -> 0 | L98: =SUM(L97:L97) -> 15425
A100: Accumulated depreciation:
B101: Vehicles | I101: 15425 | L101: =SUM(I101:K101) -> 15425 | M101: =L97-L101 -> 0
C102: Total accumulated depreciation | I102: =I101 -> 15425 | J102: =J101 -> 0 | K102: =K101 -> 0 | L102: =L101 -> 15425
A104: Library:
A105: Capital assets:
B106: Office equipment | I106: 715130 | J106: 3525 | K106: -96462 | L106: =SUM(I106:K106) -> 622193
B107: Vehicles | I107: 20730 | L107: =SUM(I107:K107) -> 20730
B108: CIP | J108: 29054 | L108: =SUM(I108:K108) -> 29054 | M108: =L108 -> 29054
B109: Books, recordings, etc. | I109: 1915009 | J109: 154146 | K109: -153315 | L109: =SUM(I109:K109) -> 1915840
C110: Total assets | I110: =SUM(I106:I109) -> 2650869 | J110: =SUM(J106:J109) -> 186725 | K110: =SUM(K106:K109) -> -249777 | L110: =SUM(L106:L109) -> 2587817
A112: Accumulated depreciation:
B113: Office equipment | I113: 561213 | J113: 34373 | K113: -94727 | L113: =SUM(I113:K113) -> 500859 | M113: =L106-L113 -> 121334
B114: Vehicles | I114: 4146 | J114: 4146 | L114: =SUM(I114:K114) -> 8292 | M114: =L107-L114 -> 12438
B115: Books, recordings, etc. | I115: 1567112 | J115: 164592 | K115: -153315 | L115: =SUM(I115:K115) -> 1578389 | M115: =L109-L115 -> 337451
C116: Total accumulated depreciation | I116: =SUM(I115:I115) -> 1567112 | J116: =SUM(J115:J115) -> 164592 | K116: =SUM(K115:K115) -> -153315 | L116: =SUM(L115:L115) -> 1578389
A118: Road maintenance:
A119: Capital assets:
...

Sheet Orleans
D1: ORLEANS PARISH POLICE JURY
D2: Capital Assets
D3: For the Year Ended December 31, 2013
I5: Balance January 1, 2013 | J5: Additions | K5: Deletions and adjustments | L5: Transfers | M5: Balance December 31, 2013 | N5: Cross Sectional
A7: Governmental Activities:
A8: Capital assets, not being depreciated
B9: Land | I9: 94474000 | M9: =SUM(I9:L9) -> 94474000 | N9: =M9 -> 94474000
B10: Construction in progress | I10: 347632000 | J10: 143696000 | L10: -44193000 | M10: =SUM(I10:L10) -> 447135000 | N10: =M10 -> 447135000
C11: Total capital assets not being depreciated | I11: =SUM(I9:I10) -> 442106000 | J11: =SUM(J9:J10) -> 143696000 | K11: =SUM(K9:K10) -> 0 | L11: =SUM(L9:L10) -> -44193000 | M11: =SUM(M9:M10) -> 541609000
A13: Capital assets being depreciated
B14: Infrastructure | I14: 2469541000 | J14: 11251000 | K14: -217000 | M14: =SUM(I14:L14) -> 2480575000
B15: Buildings and Improvements | I15: 333798000 | J15: 32955000 | K15: -564000 | M15: =SUM(I15:L15) -> 366189000
B16: Equipment and vehicles | I16: 97002000 | J16: 9238000 | K16: -1167000 | M16: =SUM(I16:L16) -> 105073000
B17: Other | I17: 41072000 | K17: -580000 | M17: =SUM(I17:L17) -> 40492000
C18: Total capital assets being depreciated | I18: =SUM(I14:I17) -> 2941413000 | J18: =SUM(J14:J17) -> 53444000 | K18: =SUM(K14:K17) -> -2528000 | L18: =SUM(L14:L17) -> 0 | M18: =SUM(M14:M17) -> 2992329000
A20: Less accumulated depreciation for:
B21: Infrastructure | I21: 1697429000 | J21: 58233000 | K21: -123000 | M21: =SUM(I21:L21) -> 1755539000 | N21: =M14-M21 -> 725036000
B22: Buildings and improvements | I22: 102449000 | J22: 9925000 | K22: -221000 | M22: =SUM(I22:L22) -> 112153000 | N22: =M15-M22 -> 254036000
B23: Equipment and vehicles | I23: 80217000 | J23: 6800000 | K23: -1063000 | M23: =SUM(I23:L23) -> 85954000 | N23: =M16-M23 -> 19119000
B24: Other | I24: 29133000 | J24: 1387000 | K24: -338000 | M24: =SUM(I24:L24) -> 30182000 | N24: =M17-M24 -> 10310000
C25: Total accumulated depreciation | I25: =SUM(I21:I24) -> 1909228000 | J25: =SUM(J21:J24) -> 76345000 | K25: =SUM(K21:K24) -> -1745000 | L25: =SUM(L21:L24) -> 0 | M25: =SUM(M21:M24) -> 1983828000
B26: Total capital assets being depreciated, net | I26: =I18-I25 -> 1032185000 | J26: =J18-J25 -> -22901000 | K26: =K18-K25 -> -783000 | L26: =L18-L25 -> 0 | M26: =M18-M25 -> 1008501000
B27: Total | I27: =I26+I11 -> 1474291000 | J27: =J26+J11 -> 120795000 | K27: =K26+K11 -> -783000 | L27: =L26+L11 -> -44193000 | M27: =M26+M11 -> 1550110000 | N27: =SUM(N9:N24) -> 1550110000

Sheet Ouachita
D1: OUACHITA PARISH POLICE JURY
D2: Capital Assets
D3: For the Year Ended December 31, 2013
I5: Balance January 1, 2013 | L5: Balance December 31, 2013 | M5: Cross Sectional
J6: Additions and Transfers | K6: Deletions and Transfers
A7: Governmental Activities
A8: Nondepreciable capital assets:
B9: Land | I9: 9045433 | K9: -75411 | L9: =SUM(I9:K9) -> 8970022 | M9: =SUM(L9) -> 8970022
B10: Construction in progress | I10: 9599699 | J10: 3681222 | K10: -3241257 | L10: =SUM(I10:K10) -> 10039664 | M10: =SUM(L10) -> 10039664
C11: Total Capital assets not being depreciated | I11: =SUM(I9:I10) -> 18645132 | J11: =SUM(J9:J10) -> 3681222 | K11: =SUM(K9:K10) -> -3316668 | L11: =SUM(L9:L10) -> 19009686
A13: Depreciable capital assets
B14: Buildings | I14: 57087679 | J14: 1142912 | K14: -5000 | L14: =SUM(I14:K14) -> 58225591
B15: Furniture, fixtures and equipment | I15: 29680408 | J15: 2988190 | K15: -471898 | L15: =SUM(I15:K15) -> 32196700
B16: Books | I16: 4820701 | J16: 510570 | K16: -566894 | L16: =SUM(I16:K16) -> 4764377
B17: Infrastructure:
C18: Roads | I18: 251520541 | J18: 3494100 | L18: =SUM(I18:K18) -> 255014641
C19: Bridges | I19: 6541105 | L19: =SUM(I19:K19) -> 6541105
C20: Drainage | I20: 486426 | J20: 1570702 | L20: =SUM(I20:K20) -> 2057128
C21: Total depreciable capital assets | I21: =SUM(I14:I20) -> 350136860 | J21: =SUM(J14:J20) -> 9706474 | K21: =SUM(K14:K20) -> -1043792 | L21: =SUM(L14:L20) -> 358799542
A23: Less accumulated depreciation for:
B24: Buildings | I24: 19376338 | J24: 1460143 | K24: -4813 | L24: =SUM(I24:K24) -> 20831668 | M24: =L14-L24 -> 37393923
B25: Furniture, fixtures and equipment | I25: 20756178 | J25: 1747394 | K25: -592549 | L25: =SUM(I25:K25) -> 21911023 | M25: =L15-L25 -> 10285677
B26: Books | I26: 3350625 | J26: 475514 | K26: -586035 | L26: =SUM(I26:K26) -> 3240104 | M26: =L16-L26 -> 1524273
B27: Infrastructure:
C28: Roads | I28: 141294061 | J28: 6342223 | L28: =SUM(I28:K28) -> 147636284 | M28: =L18-L28 -> 107378357
C29: Bridges | I29: 2528945 | J29: 87214 | L29: =SUM(I29:K29) -> 2616159 | M29: =L19-L29 -> 3924946
C30: Drainage | I30: 176099 | J30: 38536 | L30: =SUM(I30:K30) -> 214635 | M30: =L20-L30 -> 1842493
C31: Total accumulated depreciation | I31: =SUM(I24:I30) -> 187482246 | J31: =SUM(J24:J30) -> 10151024 | K31: =SUM(K24:K30) -> -1183397 | L31: =SUM(L24:L30) -> 196449873
B32: Total depreciable capital assets, net | I32: =I21-I31 -> 162654614 | J32: =J21-J31 -> -444550 | K32: =K21-K31 -> 139605 | L32: =L21-L31 -> 162349669
B33: Governmental activities capital assets, net | I33: =I32+I11 -> 181299746 | J33: =J11+J32 -> 3236672 | K33: =K11+K32 -> -3177063 | L33: =L11+L32 -> 181359355 | M33: =SUM(M24:M30,M9:M10) -> 181359355
I35: Beginning capital assets were adjusted by $259,155 to reflect land that had been
I36: previously omitted.

Sheet Plaquemines
D1: PLAQUEMINES PARISH POLICE JURY
D2: Capital Assets
D3: For the Year Ended December 31, 2013
I5: Beginning Balance | J5: Additions | K5: Deductions | L5: Ending Balance | M5: Cross Sectional
A6: Governmental-Type Activities:
A7: Capital assets, not being depreciated:
B8: Land | I8: 13474494 | J8: 74480 | K8: -37240 | L8: =SUM(I8:K8) -> 13511734 | M8: =L8 -> 13511734
B9: Construction in progress | I9: 77505097 | J9: 38297976 | K9: -16269983 | L9: =SUM(I9:K9) -> 99533090 | M9: =L9 -> 99533090
B10: Construction in progress-FEMA Projects | I10: 94405561 | J10: 24009425 | K10: -92080882 | L10: =SUM(I10:K10) -> 26334104 | M10: =L10 -> 26334104
C11: Total capital assets not being depreciated | I11: =SUM(I8:I10) -> 185385152 | J11: =SUM(J8:J10) -> 62381881 | K11: =SUM(K8:K10) -> -108388105 | L11: =SUM(L8:L10) -> 139378928
A13: Capital assets, being depreciated:
B14: Buildings and improvements | I14: 126882545 | J14: 45832337 | K14: -12622519 | L14: =SUM(I14:K14) -> 160092363
B15: Improvements other than buildings | I15: 47596529 | J15: 27777487 | K15: -106267 | L15: =SUM(I15:K15) -> 75267749
B16: Machinery and Equipment | I16: 39949857 | J16: 3543273 | K16: -2822191 | L16: =SUM(I16:K16) -> 40670939
B17: Infrastructure | I17: 198758838 | J17: 44443734 | L17: =SUM(I17:K17) -> 243202572
C18: Total capital assets being depreciated | I18: =SUM(I14:I17) -> 413187769 | J18: =SUM(J14:J17) -> 121596831 | K18: =SUM(K14:K17) -> -15550977 | L18: =SUM(L14:L17) -> 519233623
A20: Less accumulated depreciation for
B21: Buildings and improvements | I21: -34996107 | J21: -3650874 | K21: 8536981 | L21: =SUM(I21:K21) -> -30110000 | M21: =L14+L21 -> 129982363
B22: Improvements other than buildings | I22: -5105893 | J22: -1880622 | K22: 44952 | L22: =SUM(I22:K22) -> -6941563 | M22: =L15+L22 -> 68326186
B23: Machinery and Equipment | I23: -18404573 | J23: -2180166 | K23: 1557621 | L23: =SUM(I23:K23) -> -19027118 | M23: =L16+L23 -> 21643821
B24: Infrastructure | I24: -159482181 | J24: -5221094 | L24: =SUM(I24:K24) -> -164703275 | M24: =L17+L24 -> 78499297
C25: Total accumulated depreciation | I25: =SUM(I21:I24) -> -217988754 | J25: =SUM(J21:J24) -> -12932756 | K25: =SUM(K21:K24) -> 10139554 | L25: =SUM(L21:L24) -> -220781956
A27: Total Capital Assets, being depreciated | I27: =I18+I25 -> 195199015 | J27: =J18+J25 -> 108664075 | K27: =K18+K25 -> -5411423 | L27: =L18+L25 -> 298451667
A28: Governmental Activities, net | I28: =I11+I27 -> 380584167 | J28: =J11+J27 -> 171045956 | K28: =K11+K27 -> -113799528 | L28: =L11+L27 -> 437830595 | M28: =SUM(M8:M25) -> 437830595
A31: Business-Type Activities:
A32: Capital assets, not being depreciated:
B33: Land | I33: 52000 | L33: =SUM(I33:K33) -> 52000 | M33: =L33 -> 52000
B34: Construction in Progress | I34: 62293781 | J34: 17257931 | K34: -48550249 | L34: =SUM(I34:K34) -> 31001463 | M34: =L34 -> 31001463
A35: Total capital assets not being depreciated | I35: =SUM(I33:I34) -> 62345781 | J35: =SUM(J33:J34) -> 17257931 | K35: =SUM(K33:K34) -> -48550249 | L35: =SUM(L33:L34) -> 31053463
A37: Capital assets being depreciated
B38: Buildings and Improvements | I38: 23953449 | K38: -1117926 | L38: =SUM(I38:K38) -> 22835523
B39: Improvements other than buildings | I39: 66916238 | J39: 17551344 | K39: -27737 | L39: =SUM(I39:K39) -> 84439845
B40: Machinery and Equipment | I40: 3290382 | J40: 69397 | K40: -28535 | L40: =SUM(I40:K40) -> 3331244
B41: Infrastructure | J41: 5670859 | L41: =SUM(I41:K41) -> 5670859 | M41: =L41 -> 5670859
C42: Total capital assets being depreciated | I42: =SUM(I38:I41) -> 94160069 | J42: =SUM(J38:J41) -> 23291600 | K42: =SUM(K38:K41) -> -1174198 | L42: =SUM(L38:L41) -> 116277471
A44: Less accumulated depreciation for
B45: Buildings and Improvements | I45: -9942625 | J45: -521939 | K45: 796549 | L45: =SUM(I45:K45) -> -9668015 | M45: =L38+L45 -> 13167508
B46: Improvements other than buildings | I46: -41918718 | J46: -2631245 | K46: 23253 | L46: =SUM(I46:K46) -> -44526710 | M46: =L39+L46 -> 39913135
B47: Machinery and Equipment | I47: -2176731 | J47: -147672 | K47: 12539 | L47: =SUM(I47:K47) -> -2311864 | M47: =L40+L47 -> 1019380
C48: Total accumulated depreciation | I48: =SUM(I45:I47) -> -54038074 | J48: =SUM(J45:J47) -> -3300856 | K48: =SUM(K45:K47) -> 832341 | L48: =SUM(L45:L47) -> -56506589
A50: Total capital assets being depreciated, net | I50: =I42+I48 -> 40121995 | J50: =J42+J48 -> 19990744 | K50: =K42+K48 -> -341857 | L50: =L42+L48 -> 59770882
A52: Business-type activities, net | I52: =I35+I50 -> 102467776 | J52: =J35+J50 -> 37248675 | K52: =K35+K50 -> -48892106 | L52: =L35+L50 -> 90824345 | M52: =SUM(M33:M50) -> 90824345

Sheet Pointe Coupee
D1: POINTE COUPEE PARISH POLICE JURY
D2: Capital Assets
D3: For the Year Ended December 31, 2013
I5: Beginning Balance | J5: Additions | K5: Deductions | L5: Ending Balance | M5: Cross Sectional
A6: Governmental-Type Activities:
A7: Capital assets, not being depreciated:
B8: Land | I8: 814274 | J8: 27000 | K8: 0 | L8: =SUM(I8:K8) -> 841274 | M8: =L8 -> 841274
B9: Construction in progress | I9: 417905 | J9: 2605606 | K9: -310328 | L9: =SUM(I9:K9) -> 2713183 | M9: =L9 -> 2713183
C10: Total capital assets not being depreciated | I10: =SUM(I8:I9) -> 1232179 | J10: =SUM(J8:J9) -> 2632606 | K10: =SUM(K8:K9) -> -310328 | L10: =SUM(L8:L9) -> 3554457
A12: Capital assets, being depreciated:
B13: Buildings and improvements | I13: 7653718 | J13: 1263395 | K13: 0 | L13: =SUM(I13:K13) -> 8917113
B14: Library collection | I14: 2703004 | J14: 134836 | K14: -5344 | L14: =SUM(I14:K14) -> 2832496
B15: Equipment, furnishings, and vehicles | I15: 7140870 | J15: 106061 | K15: -221948 | L15: =SUM(I15:K15) -> 7024983
B16: Infrastructure | I16: 7737691 | J16: 2823091 | L16: =SUM(I16:K16) -> 10560782
C17: Total capital assets being depreciated | I17: =SUM(I13:I16) -> 25235283 | J17: =SUM(J13:J16) -> 4327383 | K17: =SUM(K13:K16) -> -227292 | L17: =SUM(L13:L16) -> 29335374
A19: Less accumulated depreciation for
B20: Buildings and improvements | I20: -3830446 | J20: -179975 | K20: 0 | L20: =SUM(I20:K20) -> -4010421 | M20: =L13+L20 -> 4906692
B21: Library collection | I21: -2195617 | J21: -133348 | K21: 5344 | L21: =SUM(I21:K21) -> -2323621 | M21: =L14+L21 -> 508875
B22: Equipment, furnishings, and vehicles | I22: -6740859 | J22: -167185 | K22: 220740 | L22: =SUM(I22:K22) -> -6687304 | M22: =L15+L22 -> 337679
B23: Infrastructure | I23: -2259387 | J23: -454346 | L23: =SUM(I23:K23) -> -2713733 | M23: =L16+L23 -> 7847049
C24: Total accumulated depreciation | I24: =SUM(I20:I23) -> -15026309 | J24: =SUM(J20:J23) -> -934854 | K24: =SUM(K20:K23) -> 226084 | L24: =SUM(L20:L23) -> -15735079
A26: Total Capital Assets, being depreciated | I26: =I17+I24 -> 10208974 | J26: =J17+J24 -> 3392529 | K26: =K17+K24 -> -1208 | L26: =L17+L24 -> 13600295
A27: Governmental Activities, net | I27: =I10+I26 -> 11441153 | J27: =J10+J26 -> 6025135 | K27: =K10+K26 -> -311536 | L27: =L10+L26 -> 17154752 | M27: =SUM(M8:M25) -> 17154752
A30: Business-Type Activities:
A31: Capital assets, not being depreciated:
B32: Land | I32: 45233 | L32: =SUM(I32:K32) -> 45233 | M32: =L32 -> 45233
A34: Capital assets being depreciated
B35: Utility systems and related equipment | I35: 7675462 | J35: 99645 | K35: -14676 | L35: =SUM(I35:K35) -> 7760431
B36: Less accumulated depreciation | I36: -5449377 | J36: -208192 | K36: 14676 | L36: =SUM(I36:K36) -> -5642893 | M36: =L35+L36 -> 2117538
A38: Total capital assets being depreciated, net | I38: =SUM(I35:I36) -> 2226085 | J38: =SUM(J35:J36) -> -108547 | K38: =SUM(K35:K36) -> 0 | L38: =SUM(L35:L36) -> 2117538
A40: Business-type activities, net | I40: =SUM(I38,I32) -> 2271318 | J40: =SUM(J38,J32) -> -108547 | K40: =SUM(K38,K32) -> 0 | L40: =SUM(L38,L32) -> 2162771 | M40: =SUM(M32:M38) -> 2162771

Sheet Rapides
D1: RAPIDES PARISH POLICE JURY
D2: Capital Assets
D3: For the Year Ended December 31, 2013
C5: Primary Government - Governmental Activities:
E6: Land | F6: Construction in Progress | G6: Buildings and Improvements | H6: Furniture and Equipment | I6: Infrastructure | J6: Total
C7: Beginning balance | E7: 1694373 | F7: 1141822 | G7: 24932313 | H7: 21621818 | I7: 346650575 | J7: =SUM(E7:I7) -> 396040901 | K7: =E10 -> 1689373
D8: Additions | E8: 20000 | F8: 233446 | G8: 1184584 | H8: 912397 | I8: 3797316 | J8: =SUM(E8:I8) -> 6147743 | K8: =F10 -> 1375268
D9: Deletions | E9: -25000 | F9: 0 | G9: 0 | H9: -457012 | I9: -3674382 | J9: =SUM(E9:I9) -> -4156394
C10: Ending balance | E10: =SUM(E7:E9) -> 1689373 | F10: =SUM(F7:F9) -> 1375268 | G10: =SUM(G7:G9) -> 26116897 | H10: =SUM(H7:H9) -> 22077203 | I10: =SUM(I7:I9) -> 346773509 | J10: =SUM(E10:I10) -> 398032250
B12: Accumulated depreciation:
C13: Beginning balance | E13: 0 | F13: 0 | G13: -14565590 | H13: -14191957 | I13: -314406646 | J13: =SUM(E13:I13) -> -343164193 | K13: =G10+G16 -> 10856728
D14: Additions | E14: 0 | F14: 0 | G14: -694579 | H14: -1252291 | I14: -2027980 | J14: =SUM(E14:I14) -> -3974850 | K14: =H10+H16 -> 7063408
D15: Deletions | E15: 0 | F15: 0 | G15: 0 | H15: 430453 | I15: -219494 | J15: =SUM(E15:I15) -> 210959 | K15: =I10+I16 -> 30119389
C16: Ending balance | E16: =SUM(E13:E15) -> 0 | F16: =SUM(F13:F15) -> 0 | G16: =SUM(G13:G15) -> -15260169 | H16: =SUM(H13:H15) -> -15013795 | I16: =SUM(I13:I15) -> -316654120 | J16: =SUM(J13:J15) -> -346928084
C18: Ending balance, net | E18: =SUM(E16,E10) -> 1689373 | F18: =SUM(F16,F10) -> 1375268 | G18: =SUM(G16,G10) -> 10856728 | H18: =SUM(H16,H10) -> 7063408 | I18: =SUM(I16,I10) -> 30119389 | J18: =SUM(J16,J10) -> 51104166 | K18: =SUM(K7:K15) -> 51104166

Sheet Red River
D1: RED RIVER PARISH POLICE JURY
D2: Capital Assets
D3: For the Year Ended December 31, 2013
I5: Beginning Balance | J5: Additions | K5: Deductions | L5: Ending Balance | M5: Cross Sectional
A6: Governmental-Type Activities:
A7: Capital assets, not being depreciated:
B8: Land | I8: 301537 | K8: 0 | L8: =SUM(I8:K8) -> 301537 | M8: =L8 -> 301537
B9: Construction in progress | I9: 1668511 | J9: 1243828 | K9: -1038293 | L9: =SUM(I9:K9) -> 1874046 | M9: =L9 -> 1874046
C10: Total capital assets not being depreciated | I10: =SUM(I8:I9) -> 1970048 | J10: =SUM(J8:J9) -> 1243828 | K10: =SUM(K8:K9) -> -1038293 | L10: =SUM(L8:L9) -> 2175583
A12: Capital assets, being depreciated:
B13: Buildings and building improvements | I13: 7023025 | J13: 1348056 | K13: 0 | L13: =SUM(I13:K13) -> 8371081
B14: Less accumulated depreciation | I14: -5466742 | J14: -276298 | L14: =SUM(I14:K14) -> -5743040 | M14: =L13+L14 -> 2628041
C15: Total buildings and building improvements | I15: =SUM(I13:I14) -> 1556283 | J15: =SUM(J13:J14) -> 1071758 | K15: =SUM(K13:K14) -> 0 | L15: =SUM(L13:L14) -> 2628041
B17: Streets, parking lots and other improvements | I17: 7120627 | J17: 2454254 | K17: 0 | L17: =SUM(I17:K17) -> 9574881
B18: Less accumulated depreciation | I18: -765410 | J18: -732515 | L18: =SUM(I18:K18) -> -1497925 | M18: =L17+L18 -> 8076956
C19: Total streets, parking lots and other improvements | I19: =SUM(I17:I18) -> 6355217 | J19: =SUM(J17:J18) -> 1721739 | K19: =SUM(K17:K18) -> 0 | L19: =SUM(L17:L18) -> 8076956
B21: Furniture, equipment, and vehicles | I21: 3445213 | J21: 146562 | L21: =SUM(I21:K21) -> 3591775
B22: Less accumulated depreciation | I22: -1753361 | J22: -556554 | L22: =SUM(I22:K22) -> -2309915 | M22: =L21+L22 -> 1281860
C23: Total furniture, equipment, and vehicles | I23: =SUM(I21:I22) -> 1691852 | J23: =SUM(J21:J22) -> -409992 | K23: =SUM(K21:K22) -> 0 | L23: =SUM(L21:L22) -> 1281860
B25: Library books and information materials | I25: 189572 | J25: 9167 | L25: =SUM(I25:K25) -> 198739
B26: Less accumulated depreciation | I26: -107760 | J26: -17358 | L26: =SUM(I26:K26) -> -125118 | M26: =L25+L26 -> 73621
C27: Total library books and information materials | I27: =SUM(I25:I26) -> 81812 | J27: =SUM(J25:J26) -> -8191 | K27: =SUM(K25:K26) -> 0 | L27: =SUM(L25:L26) -> 73621
A29: Total capital assets being depreciated | I29: =I27+I23+I19+I15 -> 9685164 | J29: =J27+J23+J19+J15 -> 2375314 | K29: =K27+K23+K19+K15 -> 0 | L29: =L27+L23+L19+L15 -> 12060478 | N29: The difference between the numbers here and the unmbers was reported to have been a typo by Tommy Naquin with Postlewaithe & Netterville (225-408-4710) on 03/04/2015.
A31: Governmental activities total capital assets, net | I31: =I29+I10 -> 11655212 | J31: =J29+J10 -> 3619142 | K31: =K29+K10 -> -1038293 | L31: =L29+L10 -> 14236061 | M31: =SUM(M8:M29) -> 14236061

Sheet Richland
D1: RICHLAND PARISH POLICE JURY
D2: Capital Assets
D3: For the Year Ended December 31, 2013
I5: Beginning Balance | J5: Increases | K5: Decreases | L5: Ending Balance | M5: Cross Sectional
A6: Primary Government
A7: Governmental-Type Activities:
A8: Capital assets, not being depreciated:
B9: Land | I9: 300273 | L9: =SUM(I9:K9) -> 300273 | M9: =L9 -> 300273
C10: Total assets not being depreciated | I10: =SUM(I9:I9) -> 300273 | J10: =SUM(J9:J9) -> 0 | K10: =SUM(K9:K9) -> 0 | L10: =SUM(L9:L9) -> 300273
A12: Capital assets, being depreciated:
B13: Buildings and improvements | I13: 2854206 | J13: 103205 | L13: =SUM(I13:K13) -> 2957411
B14: Machinery and equipment | I14: 3807568 | J14: 96526 | K14: -42257 | L14: =SUM(I14:K14) -> 3861837
C15: Total capital assets being depreciated | I15: =SUM(I13:I14) -> 6661774 | J15: =SUM(J13:J14) -> 199731 | K15: =SUM(K13:K14) -> -42257 | L15: =SUM(L13:L14) -> 6819248
A17: Less accumulated depreciation for
B18: Buildings and improvements | I18: 1327874 | J18: 60034 | L18: =SUM(I18:K18) -> 1387908 | M18: =L13-L18 -> 1569503
B19: Machinery and Equipment | I19: 3113462 | J19: 222388 | K19: -42257 | L19: =SUM(I19:K19) -> 3293593 | M19: =L14-L19 -> 568244
C20: Total accumulated depreciation | I20: =SUM(I18:I19) -> 4441336 | J20: =SUM(J18:J19) -> 282422 | K20: =SUM(K18:K19) -> -42257 | L20: =SUM(L18:L19) -> 4681501
A22: Total Capital Assets, being depreciated | I22: =I15-I20 -> 2220438 | J22: =J15-J20 -> -82691 | K22: =K15-K20 -> 0 | L22: =L15-L20 -> 2137747
A23: Governmental activities capital assets, net | I23: =I10+I22 -> 2520711 | J23: =J10+J22 -> -82691 | K23: =K10+K22 -> 0 | L23: =L10+L22 -> 2438020 | M23: =SUM(M9:M21) -> 2438020

Sheet Sabine
D1: SABINE PARISH POLICE JURY
D2: Capital Assets
D3: For the Year Ended December 31, 2013
I5: Beginning Balance | J5: Increases | K5: Decreases | L5: Ending Balance | M5: Cross Sectional
A6: Primary Government
A7: Governmental-Type Activities:
A8: Capital assets, not being depreciated:
B9: Land | I9: 595253 | J9: 44323 | L9: =SUM(I9:K9) -> 639576 | M9: =L9 -> 639576
B10: Construction in progress | J10: 540422 | L10: =SUM(I10:K10) -> 540422 | M10: =L10 -> 540422
C11: Total assets not being depreciated | I11: =SUM(I9:I10) -> 595253 | J11: =SUM(J9:J10) -> 584745 | K11: =SUM(K9:K10) -> 0 | L11: =SUM(L9:L10) -> 1179998
A13: Capital assets, being depreciated:
B14: Buildings | I14: 2673696 | J14: 119672 | L14: =SUM(I14:K14) -> 2793368
B15: Machinery and equipment | I15: 5553828 | J15: 521943 | K15: -104821 | L15: =SUM(I15:K15) -> 5970950
B16: Furniture and fixtures | I16: 91182 | J16: 46328 | K16: -45488 | L16: =SUM(I16:K16) -> 92022
B17: Infrastructure | I17: 65673651 | J17: 510195 | K17: -44301 | L17: =SUM(I17:K17) -> 66139545
C18: Total capital assets being depreciated | I18: =SUM(I14:I17) -> 73992357 | J18: =SUM(J14:J17) -> 1198138 | K18: =SUM(K14:K17) -> -194610 | L18: =SUM(L14:L17) -> 74995885
A20: Less accumulated depreciation for
B21: Buildings | I21: 1025976 | J21: 47157 | L21: =SUM(I21:K21) -> 1073133 | M21: =L14-L21 -> 1720235
B22: Machinery and Equipment | I22: 2626838 | J22: 326273 | K22: -51637 | L22: =SUM(I22:K22) -> 2901474 | M22: =L15-L22 -> 3069476
B23: Furniture and fixtures | I23: 71886 | J23: 4808 | L23: =SUM(I23:K23) -> 76694 | M23: =L16-L23 -> 15328
