Workbook

Sheet Acadia
C1: Acadia Parish 2014 Statement of Net Assets
D2: Issued: December 31, 2014
H4: Primary Government | I4: Component Units
A5: ASSETS
B6: Cash | H6: 8972007 | I6: 37066
B7: Investments | H7: 7896569
B8: Taxes receivable | H8: 497168
B9: Special assessments receivable | H9: 18188
B10: Other receivables | H10: 56204
B11: Due from other governmental entities | H11: 6041763 | I11: 33659
B12: Due from component units | H12: 20249
B13: Capital assets:
C14: Non-depreciable | H14: 1945511
C15: Depreciable, net | H15: 51047200
C17: Total Assets | H17: =SUM(H6:H15) -> 76494859 | I17: =SUM(I6:I15) -> 70725
A19: Deferred Outflows of Resources
B20: Deferred loss on refunding | H20: 24822
C22: Total assets and deferred outflows of resources | H22: =H17+H20 -> 76519681 | I22: =I17+I20 -> 70725
A24: Liabilities
B25: Accounts payable | H25: 871484 | I25: 10260
B26: Retainage payable | H26: 7879
B27: Accured liabilites and other payables | H27: 606926
B28: Unearned revenues | H28: 45000
B29: Accrued interest payable | H29: 69355
B30: Due to primary government | I30: 20249
B31: Long-term liabilities
C32: Portion due or payable within one year-
D33: Bonds payable | H33: 1542435
D34: Compensated absences | H34: 187122
C35: Portion due or payable after one year-
D36: Bonds payable | H36: 11233348
D37: Compensated absences | H37: 187122
D38: Landfill closure and postclosure care
E39: costs liability | H39: 7158993
D42: Total Liabilities | H42: =SUM(H25:H39) -> 21909664 | I42: =SUM(I25:I39) -> 30509
A44: Deferred Outflows of Resources
B45: Unavailable revenue- special assessments | H45: 18188
A48: NET ASSETS
B49: Investment in capital assets | H49: 40241750
B50: Restricted for:
C51: Debt service | H51: 1588110
C52: Capital projects | H52: 1246437
C53: Other purposes | H53: 6809787
B54: Unrestricted net position | H54: 4705745 | I54: 40216
C56: Total Net Assets | H56: =SUM(H49:H54) -> 54591829 | I56: =SUM(I49:I54) -> 40216
C58: Total Liabilities and Net Assets | H58: =H56+H42 -> 76501493 | I58: =SUM(I56+I42) -> 70725

Sheet Allen
C1: Allen Parish 2014 Statement of Net Assets
C2: Issued: December 31, 2014
G4: Governmental Activities
A5: ASSETS
B6: Cash and cash equivalents | G6: 14858366
B7: Receivables | G7: 6484761
B8: Due from other governments | G8: 313803
B9: Inventory
B10: Prepaid assets | G10: 806735
B11: Capital assets, net of accumulated depreciation | G11: 9930994
B13: Total Assets | G13: =SUM(G6:G11) -> 32394659
A15: LIABILITIES
B16: Accounts payable | G16: 626637
B17: Accrued interest payable | G17: 1476
B18: Unearned revenue | G18: 48703
B19: Bonds payable - due within one year | G19: 62000
B20: Compensated absences payable - due
C21: within one year | G21: 26940
B22: OPEB obligations - due in more
C23: than one year | G23: 1149691
B24: Bonds payable - due in more than one year | G24: 148000
C26: Total Liabilities | G26: =SUM(G16:G24) -> 2063447
A28: NET ASSETS
B29: Invested in capital assets, net of related debt | G29: 27191700
B30: Restricted for:
C31: Inventory | G31: 313803
C32: Equipment purchases | G32: 324072
C33: Public safety | G33: 1810976
C34: Public works | G34: 6392675
C35: Health and welfare | G35: 2463098
C36: Culture and recreation | G36: 607692
C37: Sanitation | G37: 3275003
C38: Other general government | G38: 136917
C39: Capital projects | G39: 1275201
C40: Debt service | G40: 166216
B41: Unrestricted | G41: 3848367
B43: Total Net Assets | G43: =SUM(G29:G41) -> 47805720
B45: Total Liabilities and Net Assets | G45: =SUM(G26+G43) -> 49869167

Sheet Ascension
D1: Ascension Parish 2014 Statement of Net Assets
D2: Issued: December 31, 2014
I4: Primary Government | L4: Component Unit
I5: Governmental Activities | J5: Business-type Activities | K5: Total | L5: Governmental Activities | M5: Business-type Activities
A6: ASSETS
B7: Current Assets
C8: Cash and cash equivalents | I8: 42404828 | J8: 3686409 | K8: =SUM(I8:J8) -> 46091237 | L8: 30169983 | M8: 457571
C9: Investments | I9: 93691087 | J9: 4127466 | K9: =SUM(I9:J9) -> 97818553 | L9: 4943491 | M9: 9681370
C10: Accounts receivable, net | I10: 31751994 | J10: 211156 | K10: =SUM(I10:J10) -> 31963150 | L10: 3767692 | M10: 1153256
C11: Due from other governments | I11: 5021470 | J11: 104475 | K11: =SUM(I11:J11) -> 5125945 | L11: 1125619
C12: Internal balances | I12: 5 | J12: -5 | K12: =SUM(I12:J12) -> 0
C13: Prepaid assets | I13: 1008407 | J13: 281 | K13: =SUM(I13:J13) -> 1008688 | L13: 173484
C14: Inventory | J14: 22147 | K14: =SUM(I14:J14) -> 22147 | M14: 240233
C15: Restricted assets | J15: 36464 | K15: =SUM(I15:J15) -> 36464 | L15: 709316 | M15: 548502
C16: Other assets | I16: 97173 | K16: =SUM(I16:J16) -> 97173 | L16: 6681 | M16: 116241
C17: Capital assets:
E18: Nondepreciable | I18: 73100022 | J18: 941205 | K18: =SUM(I18:J18) -> 74041227 | L18: 1945991 | M18: 110902
E19: Depreciable, net | I19: 136464488 | J19: 9952083 | K19: =SUM(I19:J19) -> 146416571 | L19: 11921812 | M19: 11753708
C21: Total Assets | I21: =SUM(I8:I19) -> 383539474 | J21: =SUM(J8:J19) -> 19081681 | K21: =SUM(K8:K19) -> 402621155 | L21: =SUM(L8:L19) -> 54764069 | M21: =SUM(M7:M19) -> 24061783
A23: Deferred Outflows of Resources
B24: Deferred loss on refunding bonds, net | I24: 294404 | J24: 0 | K24: =SUM(I24:J24) -> 294404 | L24: 0 | M24: 0
C26: Total assets and deferred outflows of resources | I26: =SUM(I24+I21) -> 383833878 | J26: =J21 -> 19081681 | K26: =K24+K21 -> 402915559 | L26: =L21 -> 54764069 | M26: =M21 -> 24061783
A28: LIABILITIES
C29: Accounts payable and accrued liabilities | I29: 3198900 | J29: 565558 | K29: =SUM(I29:J29) -> 3764458 | L29: 3210186 | M29: 352605
C30: Contracts payable | I30: 3980044 | K30: =SUM(I30:J30) -> 3980044
C31: Due to other goevernments | I31: 269707 | K31: =SUM(I31:J31) -> 269707 | L31: 1136146
C32: Accrued payroll | I32: 540668 | J32: 28220 | K32: =SUM(I32:J32) -> 568888
C33: Customer deposits | J33: 36464 | K33: =SUM(I33:J33) -> 36464 | M33: 43501
C34: Sales tax rebate reserve | I34: 4524981 | K34: =SUM(I34:J34) -> 4524981
C35: Claims reserve | K35: =SUM(I35:J35) -> 0
D36: Due within one year | I36: 235409 | K36: =SUM(I36:J36) -> 235409
D37: Due in more than one year | I37: 667416 | K37: =SUM(I37:J37) -> 667416
C38: Long-term payable | K38: =SUM(I38:J38) -> 0
D39: Due within one year | I39: 4335000 | K39: =SUM(I39:J39) -> 4335000 | L39: 551031 | M39: 176485
D40: Due in more than one year | I40: 80612569 | K40: =SUM(I40:J40) -> 80612569 | L40: 6694058 | M40: 4766994
D42: Total Liabilities | I42: =SUM(I29:I40) -> 98364694 | J42: =SUM(J29:J40) -> 630242 | K42: =SUM(K29:K40) -> 98994936 | L42: =SUM(L29:L40) -> 11591421 | M42: =SUM(M29:M40) -> 5339585
A44: Deferred Inflows of Resources
B45: Grant Advances | I45: 629856 | J45: 0 | K45: =SUM(I45:J45) -> 629856 | L45: 0 | M45: 0
B46: Unearned Revenue | I46: 0 | J46: 18770 | K46: =SUM(I46:J46) -> 18770 | L46: 0 | M46: 0
D48: Total deferred inflows of resources | I48: =SUM(I45:I46) -> 629856 | J48: =SUM(J45:J46) -> 18770 | K48: =SUM(K45:K46) -> 648626 | L48: 0 | M48: 0
A50: NET POSITION
B51: Net investment in capital assets | I51: 127427898 | J51: 10893288 | K51: =SUM(I51:J51) -> 138321186 | L51: 12884726 | M51: 6921131
B52: Restricted for:
C53: Capital Projects | I53: 55001484 | K53: =SUM(I53:J53) -> 55001484
C54: External legal constraints | I54: 77707027 | K54: =SUM(I54:J54) -> 77707027
C55: Debt service | I55: 2519611 | K55: =SUM(I55:J55) -> 2519611 | M55: 505001
C56: Other Purposes | L56: 2627035
B57: Unrestricted | I57: 22183308 | J57: 7539381 | K57: =SUM(I57:J57) -> 29722689 | L57: 27660887 | M57: 11296066
C59: Total Net Position | I59: =SUM(I51:I57) -> 284839328 | J59: =SUM(J51:J57) -> 18432669 | K59: =SUM(K51:K57) -> 303271997 | L59: =SUM(L51:L57) -> 43172648 | M59: =SUM(M51:M57) -> 18722198
C61: Total Liabilities, deferred inflows of resources, and Net Assets | I61: =SUM(I42+I59) -> 383204022 | J61: =SUM(J59+J42+J48) -> 19081681 | K61: =SUM(K42+K59+K48) -> 402915559 | L61: =SUM(L59+L42) -> 54764069 | M61: =SUM(M59+M42) -> 24061783

Sheet Assumption
D1: Assumption Parish 2014 Statement of Net Assets
D2: Issued: December 31, 2014
H4: Primary Government | I4: Component Units
A5: ASSETS
B6: Current Assets
C7: Cash and cash equivalents | H7: 2824757 | I7: 1215826
C8: Investments | H8: 18123491 | I8: 3932994
C9: Receivables | H9: 5769470 | I9: 1510860
C10: Other assets | I10: 260463
C11: Restricted investments | I11: 3899610
C12: Net investment in capital assets | H12: 42293964 | I12: 15878625
C14: Total Assets | H14: =SUM(H7:H12) -> 69011682 | I14: =SUM(I7:I12) -> 26698378
A16: LIABILITIES AND NET POSITION
B17: Liabilities
C18: Accounts payable | H18: 554277 | I18: 704225
C19: Salaries payable | H19: 129885 | I19: 11722
C20: Compensated absences payable | H20: 163079 | I20: 29149
C21: Other post-employment benefits payable | H21: 868870 | I21: 888799
C22: Other liabilities | H22: 422634 | I22: 335861
C23: Long-term liabilities:
D24: Due within one year | I24: 510000
D25: Due in more than one year | I25: 4800000
D27: Total Liabilities | H27: =SUM(H18:H25) -> 2138745 | I27: =SUM(I18:I25) -> 7279756
A29: NET ASSETS
B30: Invested in capital assets, net of related debt | H30: 42293964 | I30: 10568623
B31: Restricted for revenue bond debt service and contingencies | I31: 3899380
B32: Unrestricted | H32: 24582973 | I32: 4950619
C34: Total Net Assets | H34: =SUM(H30:H32) -> 66876937 | I34: =SUM(I29:I32) -> 19418622
C36: Total Liabilities and Net Assets | H36: =SUM(H27+H34) -> 69015682 | I36: =SUM(I27+I34) -> 26698378

Sheet Avoyelles
D1: Avoyelles Parish 2014 Statement of Net Assets
D2: Issued: December 31, 2014
H4: Primary Government
A5: ASSETS
B6: Current Assets
C7: Cash and interest-bearing deposits | H7: 9443859
C8: Receivables, net | H8: 56433
C9: Due from other governmental units | H9: 2631894
C10: Prepaid items | H10: 148720
C12: Total Current Assets | H12: =SUM(H7:H10) -> 12280906
B14: Non-current Assets:
C15: Land and construction in progress | H15: 590548
C16: Capital assets, net | H16: 4599312
C18: Total Non-current Assets | H18: =SUM(H14:H16) -> 5189860
C20: Total Assets | H20: =SUM(H12+H18) -> 17470766
A22: LIABILITIES
B23: Current Liabilities:
C24: Accounts, salaries and other payables | H24: 712402
C25: Unearned revenue | H25: 36260
D27: Total Current Liabilities | H27: =SUM(H24:H25) -> 748662
B29: Non-current Liabilities
C30: Compensated absences payable | H30: 99940
D32: Total Liabilities | H32: =H30+H27 -> 848602
A34: NET ASSETS
B35: Net investment in capital assets | H35: 5189860
B36: Unrestricted | H36: 11432304
C38: Total Net Assets | H38: =SUM(H35:H36) -> 16622164
C40: Total Liabilities and Net Assets | H40: =H38+H32 -> 17470766

Sheet Beauregard
C1: Beauregard Parish 2014 Statement of Net Assets
C2: Issued: December 31, 2014
G4: Governmental Activities
A5: ASSETS
B6: Cash and cash equivalents | G6: 17545772
B7: Receivables | G7: 6974145
B8: Inventory | G8: 204510
B9: Capital assets (net of accumulated depreciation):
C10: Land | G10: 688379
C11: Buildings and improvements | G11: 9185546
C12: Furniture and equipment | G12: 4096339
C13: Infrastructure | G13: 15391434
C14: Construction in progress | G14: 2175228
B16: Total Assets | G16: =SUM(G6:G14) -> 56261353
A18: LIABILITIES
B19: Accounts, salaries, and other payables | G19: 1028338
B20: Interest payable | G20: 25763
B21: Long-term liabilities:
C22: Due within one year | G22: 553200
C23: Due in more than one year | G23: 4845000
C25: Total Liabilities | G25: =SUM(G19:G23) -> 6452301
A27: NET ASSETS
B28: Invested in capital assets, net of related debt | G28: 26350226
B29: Restricted for:
C30: Inventory | G30: 204510
C31: Equipment purchases | G31: 306908
C32: Public safety | G32: 1932609
C33: Public works | G33: 6543000
C34: Health and welfare | G34: 2551297
C35: Culture and recreation | G35: 536904
C36: Sanitation | G36: 4491195
C37: Other general government | G37: 151475
C38: Capital projects | G38: 3820546
C39: Debt service | G39: 149912
B40: Unrestricted | G40: 2770770
B42: Total Net Assets | G42: =SUM(G28:G40) -> 49809352
B44: Total Liabilities and Net Assets | G44: =SUM(G25+G42) -> 56261653

Sheet Bienville
C1: Bienville Parish 2014 Statement of Net Assets
C2: Issued: December 31, 2014
G4: Governmental Activities
A5: ASSETS
B6: Cash and cash equivalents | G6: 17166902
B7: Receivables | G7: 5274448
B8: Capital assets, net | G8: 22504607
B10: Total Assets | G10: =SUM(G6:G8) -> 44945957
A12: LIABILITIES
B13: Accounts payable | G13: 210615
B14: Wages and related payable | G14: 30252
B15: Interest payable | G15: 136529
B16: Bonds payable | G16: 10365000
B17: Premium on bonds | G17: 274509
B18: Deferred revenues | G18: 70000
B19: Compensated absences payable | G19: 80615
B20: Other post-employment benefits | G20: 1751911
C22: Total Liabilities | G22: =SUM(G13:G20) -> 12919431
A24: NET ASSETS
B25: Invested in capital assets, net of related debt | G25: 12139607
B26: Unrestricted | G26: 19886919
B28: Total Net Assets | G28: =SUM(G25:G26) -> 32026526
B30: Total Liabilities and Net Assets | G30: =SUM(G22+G28) -> 44945957

Sheet Bossier
D1: Bossier Parish 2014 Statement of Net Assets
D2: Issued: December 31, 2014
H5: Governmental Activities | I5: Business-Type Activities | J5: Total
A6: ASSETS
C7: Cash and cash equivalents | H7: 40504142 | I7: 258697 | J7: =SUM(H7:I7) -> 40762839
C8: Restricted cash | H8: 4879227 | I8: 1081529 | J8: =SUM(H8:I8) -> 5960756
C9: Investments | H9: 170335 | J9: =SUM(H9:I9) -> 170335
C10: Receivables | H10: 23074512 | I10: 224210 | J10: =SUM(H10:I10) -> 23298722
C11: Prepaid expenses | H11: 922606 | I11: 38252 | J11: =SUM(H11:I11) -> 960858
C12: Capital assets, net:
D13: Non-depreciable | H13: 19244357 | I13: 16269418 | J13: =SUM(H13:I13) -> 35513775
D14: Depreciable (net) | H14: 265881743 | I14: 4609925 | J14: =SUM(H14:I14) -> 270491668
C15: Internal balances | H15: 8243332 | I15: -8243332 | J15: =SUM(H15:I15) -> 0
C17: Total Assets | H17: =SUM(H7:H15) -> 362920254 | I17: =SUM(I7:I15) -> 14238699 | J17: =SUM(J7:J15) -> 377158953
A19: LIABILITIES
B20: Current
C21: Accounts payable and accrued expenses | H21: 5670884 | I21: 316283 | J21: =SUM(H21:I21) -> 5987167
C22: Payable from restricted assets:
D23: Customer deposits | I23: 112887 | J23: =SUM(H23:I23) -> 112887
B24: Noncurrent liabilities
C25: Due within one year | H25: 4998865 | I25: 80000 | J25: =SUM(H25:I25) -> 5078865
C26: Due in more than one year | H26: 56933777 | I26: 1662385 | J26: =SUM(H26:I26) -> 58596162
D28: Total Liabilities | H28: =SUM(H21+H23+H25+H26) -> 67603526 | I28: =SUM(I21+I23+I25+I26) -> 2171555 | J28: =SUM(J21+J23+J25+J26) -> 69775081
A30: Deferred Inflows of Resouces
C31: Unavailable revenue- property taxes | H31: 15065078 | J31: =SUM(H31:I31) -> 15065078
A33: NET ASSETS
B34: Net investment in capital assets | H34: 234828358 | I34: 10893626 | J34: =SUM(H34:I34) -> 245721984
B35: Restricted for:
C36: Capital projects | H36: 10572534 | J36: =SUM(H36:I36) -> 10572534
C37: Public works | H37: 1299267 | J37: =SUM(H37:I37) -> 1299267
C38: Public safety | H38: 1000587 | J38: =SUM(H38:I38) -> 1000587
C39: Economic development | H39: 110911 | J39: =SUM(H39) -> 110911
C40: Culture and recreation | H40: 5359731 | J40: =SUM(H40) -> 5359731
C41: Debt service | H41: 3470999 | J41: =SUM(H41) -> 3470999
C42: Health and welfare | H42: 2174851 | J42: =SUM(H42) -> 2174851
C43: Sewer operations | H43: 360910 | J43: =SUM(H43:I43) -> 360910
B44: Unrestricted | H44: 21073502 | I44: 1173518 | J44: =SUM(H44:I44) -> 22247020
C46: Total Net Assets | H46: =SUM(H34:H44) -> 280251650 | I46: =SUM(I34:I44) -> 12067144 | J46: =SUM(J34:J44) -> 292318794
C48: Total Liabilities and Net Assets | H48: =SUM(H46+H31+H28) -> 362920254 | I48: =SUM(I46+I31+I28) -> 14238699 | J48: =SUM(J46+J31+J28) -> 377158953

Sheet Caddo
D1: Caddo Parish 2014 Statement of Net Assets
D2: Issued: December 31, 2014
H5: Primary government | I5: Component Units
A6: ASSETS
C7: Cash and cash equivalents | H7: 15950171 | I7: 13698250
C8: Investments | H8: 119354639 | I8: 5477656
C9: Receivables, net | H9: 56915285 | I9: 15284875
C10: Due from other governments | H10: 3504844 | I10: 847274
C11: Due from primary government | I11: 571302
C12: Inventories | H12: 97808 | I12: 364398
C13: Other assets | H13: 116149 | I13: 9975946
C14: Capital assets:
D15: Land and construction in progress | H15: 20514314 | I15: 7473191
D16: Other capital assets, net of depreciation | H16: 183428797 | I16: 35403414
C18: Total Assets | H18: =SUM(H7:H16) -> 399882007 | I18: =SUM(I7:I16) -> 89096306
A20: DEFERRED OUTFLOWS OF RESOURCES
C21: Deferred loss on refunding bonds, net | H21: 146667 | I21: 151285
E23: Total assets and deferred outlfows of resources | H23: =H21+H18 -> 400028674 | I23: =I21+I18 -> 89247591
A25: LIABILITIES
C26: Accounts payable | H26: 2890397 | I26: 3145936
C27: Accrued liabilities | H27: 918576 | I27: 1171920
C28: Accrued interest payable | H28: 489926 | I28: 29614
C29: Retainage payable | H29: 353334
C30: Accrued insurance claims payable | H30: 641458 | I30: 414000
C31: Due to component units | H31: 520956
C32: Due to other governmental agencies | H32: 118146 | I32: 368089
C33: Unearned revenue | H33: 35478 | I33: 49709
C34: Noncurrent liabilities:
D35: Due within one year | H35: 3114529 | I35: 3334350
D36: Due in more than one year | H36: 40226768 | I36: 28163537
D38: Total Liabilities | H38: =SUM(H26:H36) -> 49309568 | I38: =SUM(I26:I36) -> 36677155
A40: Deferred inflows of Resources
C41: Unavailable revenue- property taxes and assessments- service charges | I41: 1787930
D43: Total liabilities and deferred inflows of resources | H43: =SUM(H41+H38) -> 49309568 | I43: =SUM(I41+I38) -> 38465085
A44: NET ASSETS
B45: Net investment in capital assets | H45: 172306406 | I45: 24635594
B46: Restricted for:
C47: Criminal justice | H47: 14884859
C48: Health and welfare | H48: 4844635
C49: Highways, streets and drainage | H49: 31807558
C50: Building facilities | H50: 9088900
C51: Sanitation | H51: 22312030
C52: Culture and recreation | H52: 24743537
C53: Economic development | H53: 926745 | I53: 7175000
C54: Debt service | H54: 2981838 | I54: 2029696
C55: Capital outlay | I55: 2220180
B56: Unrestricted | H56: 66822598 | I56: 14722036
C58: Total Net Assets | H58: =SUM(H45:H56) -> 350719106 | I58: =SUM(I45:I56) -> 50782506
C60: Total Liabilities and Net Assets | H60: =SUM(H38+H58) -> 400028674 | I60: =SUM(I58+I38) -> 87459661

Sheet Caldwell
C1: Caldwell Parish 2014 Statement of Net Assets
C2: Issued: December 31, 2014
G4: Governmental Activities
A5: ASSETS
B6: Cash and cash equivalents | G6: 7860568
B7: Receivables | G7: 1821397
B8: Capital assets, net of accumulated depreciation | G8: 14109112
B10: Total Assets | G10: =SUM(G6:G8) -> 23791077
A12: LIABILITIES
B13: Accounts, salaries, and other payables | G13: 244089
B14: Due to other agencies | G14: 57698
B15: Compensated absences payable | G15: 119522
C17: Total Liabilities | G17: =SUM(G13:G15) -> 421309
A19: NET ASSETS
B20: Net investment in capital assets | G20: 14109112
B21: Restricted | G21: 6856564
B22: Unrestricted | G22: 2404092
B24: Total Net Assets | G24: =SUM(G20:G22) -> 23369768
B26: Total Liabilities and Net Assets | G26: =SUM(G17+G24) -> 23791077

Sheet Catahoula
D1: Catahoula Parish 2014 Statement of Net Assets
D2: Issued: December 31, 2014
I4: Component Units
H5: Governmental Activities | I5: Fire District No. 1 Maintenance
A6: ASSETS
C7: Cash and cash equivalents | H7: 2290596 | I7: 104637
C8: Cash restricted for debt service | H8: 26325
C9: Cash restricted for capital project
C10: Receivables | H10: 1411486 | I10: 14594
C11: Other assets | H11: 81766
C12: Capital assets, net of accumulated depreciation | H12: 5862816 | I12: 88616
C14: Total Assets | H14: =SUM(H7:H12) -> 9672989 | I14: =SUM(I7:I12) -> 207847
A16: LIABILITIES
C17: Accounts, salaries, and other payables | H17: 144719 | I17: 526
C18: Compensated absences | H18: 32033
C19: Certificates of indebtedness due within one year | H19: 104000
C20: Certificates of indebtedness due in more than one | H20: 272000
D22: Total Liabilities | H22: =SUM(H17:H20) -> 552752 | I22: =SUM(I17:I20) -> 526
A24: DEFERRED INFLOWS
C25: Grant revenues pending | H25: 14777
A27: NET ASSETS
B28: Net investment in capital assets | H28: 5750215 | I28: 88616
B29: Unrestricted net position | H29: 3220628 | I29: 118705
C31: Total Net Assets | H31: =SUM(H28:H29) -> 8970843 | I31: =SUM(I28:I29) -> 207321
C33: Total Liabilities and Net Assets | H33: =SUM(H22+H31+H25) -> 9538372 | I33: =SUM(I31+I22) -> 207847

Sheet Calcasieu
D1: Calcasieu Parish 2014 Statement of Net Assets
D2: Issued: December 31, 2014
H4: Primary Government
H5: Governmental Activities | I5: Business-Type Activities | J5: Total | K5: Component Unit
A6: ASSETS
C7: Cash and cash equivalents | H7: 58437555 | I7: 313815 | J7: =SUM(H7:I7) -> 58751370 | K7: 43640254
C8: Investments | H8: 208827036 | I8: 971149 | J8: =SUM(H8:I8) -> 209798185 | K8: 48040669
C9: Receivables (net of allowance for uncollectibles) | H9: 54814781 | I9: 458456 | J9: =SUM(H9:I9) -> 55273237 | K9: 64038752
C10: Intergovernmental receivable | H10: 2785381 | J10: =SUM(H10:I10) -> 2785381 | K10: 1774669
C11: Due from component units | H11: 27125 | I11: 52541 | J11: =SUM(H11:I11) -> 79666
C12: Due from primary government | J12: =SUM(H12:I12) -> 0 | K12: 58216
C13: Loan receivable | H13: 33189 | J13: =SUM(H13:I13) -> 33189
C14: Prepaid items | H14: 236100 | I14: 20099 | J14: =SUM(H14:I14) -> 256199 | K14: 1756410
C15: Inventory | H15: 1175401 | J15: =SUM(H15:I15) -> 1175401 | K15: 1940603
C16: Other assets | I16: 320 | J16: =SUM(H16:I16) -> 320 | K16: 222243
C17: Restricted assets:
D18: Cash and cash equivalents | I18: 11173 | J18: =SUM(H18:I18) -> 11173 | K18: 5437563
D19: Investments | I19: 222206 | J19: =SUM(H19:I19) -> 222206 | K19: 7040297
D20: Receivables - net | I20: 189350 | J20: =SUM(H20:I20) -> 189350 | K20: 3013281
C21: Capital assets:
D22: Non-depreciable | H22: 420818629 | I22: 252770 | J22: =SUM(H22:I22) -> 421071399 | K22: 38320566
D23: Depreciable, net | H23: 97989562 | I23: 8819750 | J23: =SUM(H23:I23) -> 106809312 | K23: 210376526
C25: Total Assets | H25: =SUM(H7:H23) -> 845144759 | I25: =SUM(I7:I23) -> 11311629 | J25: =SUM(J7:J23) -> 856456388 | K25: =SUM(K7:K23) -> 425660049
A27: DEFERRED OUTFLOWS OF RESOURCES
C28: Deferred amount on refunding | K28: 65281
A30: LIABILITIES
C31: Accounts payable and other accrued liabilities | H31: 7910576 | I31: 103090 | J31: =SUM(H31:I31) -> 8013666 | K31: 10957145
C32: Intergovernmental payable | H32: 3573549 | J32: =SUM(H32:I32) -> 3573549 | K32: 1128353
C33: Due to primary government | J33: =SUM(H33:I33) -> 0 | K33: 79666
C34: Due to component units | H34: 58216 | J34: =SUM(H34:I34) -> 58216
C35: Unearned revenue | H35: 1089097 | J35: =SUM(H35:I35) -> 1089097 | K35: 105362
C36: Other liabilities | H36: 371818 | J36: =SUM(H36:I36) -> 371818 | K36: 326547
C37: Liabilities payable from restricted assets | I37: 122470 | J37: =SUM(H37:I37) -> 122470 | K37: 791128
C38: Noncurrent liabilities:
D39: Due within one year | H39: 2707932 | I39: 41626 | J39: =SUM(H39:I39) -> 2749558 | K39: 8459117
D40: Due in more than one year | H40: 7467672 | I40: 274460 | J40: =SUM(H40:I40) -> 7742132 | K40: 50270434
D42: Total Liabilities | H42: =SUM(H31:H40) -> 23178860 | I42: =SUM(I31:I40) -> 541646 | J42: =SUM(J31:J40) -> 23720506 | K42: =SUM(K31:K40) -> 72117752
A44: DEFERRED INFLOWS OF RESOURCES
C45: Property taxes levied for the next fiscal year | H45: 47096091 | J45: =SUM(H45:I45) -> 47096091 | K45: 21173199
A47: NET ASSETS
B48: Net investment in capital assets | H48: 518808191 | I48: 8756434 | J48: =SUM(H48:I48) -> 527564625 | K48: 215742765
B49: Restricted for:
C50: Debt service | I50: 305212 | J50: =SUM(H50:I50) -> 305212 | K50: 3170314
C51: External legal constraints | H51: 111932288 | J51: =SUM(H51:I51) -> 111932288
C52: Capital improvement projects | H52: 66075687 | J52: =SUM(H52:I52) -> 66075687 | K52: 1880666
B53: Unrestricted | H53: 78053642 | I53: 1708337 | J53: 79761979 | K53: 111640634
C55: Total Net Assets | H55: =SUM(H48:H53) -> 774869808 | I55: =SUM(I48:I53) -> 10769983 | J55: =SUM(J48:J53) -> 785639791 | K55: =SUM(K48:K53) -> 332434379
C57: Total Liabilities and Net Assets | H57: =SUM(H42+H55+H45) -> 845144759 | I57: =SUM(I42+I55+I45) -> 11311629 | J57: =SUM(J42+J55+J45) -> 856456388 | K57: =SUM(K42+K55+K45) -> 425725330

Sheet Cameron
C1: Cameron Parish 2014 Statement of Net Assets
C2: Issued: December 31, 2014
G4: Governmental Activities
A5: ASSETS
B6: Cash | G6: 28467308
B7: Receivables, net | G7: 16614795
B8: Inventory, at cost | G8: 1822766
B9: Other | G9: 146710
B10: Capital assets, net of accumulated depreciation | G10: 123967765
B12: Total Assets | G12: =SUM(G6:G10) -> 171019344
A14: LIABILITIES
B15: Accounts, salaries, and other payables | G15: 3869415
B16: Due to other agencies | G16: 2623074
B17: Unearned revenue | G17: 17231
B18: Interest payable | G18: 72342
B19: Long-term liabilities:
C20: Due within one year | G20: 1420448
C21: Due after one year | G21: 4202746
C23: Total Liabilities | G23: =SUM(G15:G21) -> 12205256
A25: DEFERRED INFLOWS OF RESOURCES
A27: NET ASSETS
B28: Net investment in capital assets | G28: 118625621
B29: Net position - restricted for:
C30: Judicial | G30: 58817
C31: Debt service | G31: 999067
C32: Tourism development | G32: 39983
C33: Inventories | G33: 1822766
C34: Prepaid expenses | G34: 146710
B35: Net position - unrestricted | G35: 37121124
B37: Total Net Assets | G37: =SUM(G28:G35) -> 158814088
B39: Total Liabilities and Net Assets | G39: =SUM(G23+G37) -> 171019344

Sheet Claiborne
C1: Claiborne Parish 2014 Statement of Net Assets
C2: Issued: December 31, 2014
G4: Governmental Activities
A5: ASSETS
B6: Cash and cash equivalents | G6: 6269126
B7: Investments | G7: 797211
B8: Receivables | G8: 3084505
B9: Due from other agencies | G9: 22416
B10: Deferred charges | G10: 107283
B11: Capital assets, net of accumulated depreciation | G11: 8219499
B13: Total Assets | G13: =SUM(G6:G11) -> 18500040
A15: LIABILITIES
B16: Accounts, salaries, and other payables | G16: 446867
B17: Due to other agencies | G17: 14025
B18: Deferred revenue | G18: 15626
B19: Compensated absences payable | G19: 57248
B20: Bonds payable within one year | G20: 155000
B21: Bonds payable in more than one year | G21: 1545000
C23: Total Liabilities | G23: =SUM(G16:G21) -> 2233766
A25: NET ASSETS
B26: Net investment in capital assets | G26: 6362770
B27: Restricted for:
C28: General government | G28: 471359
C29: General government - judicial | G29: 165209
C30: Public works | G30: 2721807
C31: Public safety | G31: 273907
C32: Health and welfare | G32: 257550
C33: Culture and recreation | G33: 1394279
B34: Unrestricted | G34: 4619394
B36: Total Net Assets | G36: =SUM(G26:G34) -> 16266275
B38: Total Liabilities and Net Assets | G38: =SUM(G23+G36) -> 18500041

Sheet Concodria
C1: Concordia Parish 2014 Statement of Net Assets
C2: Issued: December 31, 2014
G4: Governmental Activities
A5: ASSETS
B6: Current Assets
B7: Cash and cash equivalents | G7: 7138217
B8: Cash and cash equivalents - restricted | G8: 2563431
B9: Acounts Receivable | G9: 167238
B10: Ad valorem taxes receivable, net | G10: 1599471
B11: Sales and use taxes receivable | G11: 257934
B12: Severance taxes receivable | G12: 143713
B14: Total Assets | G14: =SUM(G7:G12) -> 11870004
B16: Capital Assets
B17: Proptery and equipment, net | G17: 10215629
G18: =SUM(G14+G17) -> 22085633
A20: LIABILITIES
B21: Current liabilities:
C22: Accounts payable | G22: 175950
C23: Interest payable | G23: 237717
C24: Accured payroll and benefits | G24: 83974
C25: Sales tax bonds- due within one year | G25: 390767
G26: =SUM(G22:G25) -> 888408
B28: Noncurrent liabilities:
C29: Sales tax bonds | G29: 9013491
C31: Total Liabilities | G31: =SUM(G29+G26) -> 9901899
A33: NET ASSETS
B34: Net investment in capital assets | G34: 1120455
B35: Restricted for:
C36: Debt service | G36: 2643431
C37: Special projects | G37: 5376698
B38: Unrestricted | G38: 3043150
B40: Total Net Assets | G40: =SUM(G34:G38) -> 12183734
B42: Total Liabilities and Net Assets | G42: =SUM(G31+G40) -> 22085633

Sheet DeSoto
D1: DeSoto Parish 2014 Statement of Net Assets
D2: Issued: December 31, 2014
H4: Primary Government
H5: Governmental Activities | I5: Business-Type Activities | J5: Total
A6: ASSETS
C7: Cash and cash equivalents | H7: 13162797 | I7: 228 | J7: =SUM(H7:I7) -> 13163025
C8: Investments | H8: 20355526 | J8: =SUM(H8:I8) -> 20355526
C9: Receivables (net of allowance for uncollectibles) | H9: 13659168 | I9: 3256 | J9: =SUM(H9:I9) -> 13662424
C10: Inventory | H10: 38185 | J10: =SUM(H10:I10) -> 38185
C11: Capital assets, net | H11: 73781725 | I11: 10175 | J11: =SUM(H11:I11) -> 73791900
C13: Total Assets | H13: =SUM(H7:H11) -> 120997401 | I13: =SUM(I7:I11) -> 13659 | J13: =SUM(J7:J11) -> 121011060
A15: LIABILITIES
C16: Accounts payable | H16: 1106355 | I16: 1500 | J16: =SUM(H16:I16) -> 1107855
C17: Master Bank Overdrafts | H17: 55314 | J17: =SUM(H17:I17) -> 55314
C18: Deposit balances | H18: 1800 | I18: 270 | J18: =SUM(H18:I18) -> 2070
C19: Advance from grantors | H19: 22885 | J19: =SUM(H19:I19) -> 22885
C20: Due to other governments | H20: 207897 | J20: =SUM(H20:I20) -> 207897
C21: Landfill post closure liability | H21: 2298127 | J21: =SUM(H21:I21) -> 2298127
C22: Compensated absences | H22: 307960 | J22: =SUM(H22:I22) -> 307960
C23: Other postemployment benefit obligation | H23: 2932408 | J23: =SUM(H23:I23) -> 2932408
C24: Long-term liabilities:
D25: Due within one year | H25: 5326 | J25: =SUM(H25:I25) -> 5326
D26: Due in more than one year | H26: 450 | J26: =SUM(H26:I26) -> 450
D28: Total Liabilities | H28: =SUM(H16:H26) -> 6938522 | I28: =SUM(I16:I26) -> 1770 | J28: =SUM(J16:J26) -> 6940292
A30: NET ASSETS
B31: Net investment in capital assets | H31: 73775949 | I31: 10175 | J31: =SUM(H31:I31) -> 73786124
B32: Restricted for Debt Service | H32: 5776 | J32: =SUM(H32:I32) -> 5776
B33: Unrestricted | H33: 40277154 | I33: 1714 | J33: =SUM(H33:I33) -> 40278868
C35: Total Net Assets | H35: =SUM(H31:H33) -> 114058879 | I35: =SUM(I31:I33) -> 11889 | J35: =SUM(J31:J33) -> 114070768
C37: Total Liabilities and Net Assets | H37: =SUM(H35+H28) -> 120997401 | I37: =SUM(I35+I28) -> 13659 | J37: =SUM(J35+J28) -> 121011060

Sheet East Baton Rouge
D1: East Baton Rouge Parish 2014 Statement of Net Assets
D2: Issued: December 31, 2014
H4: Primary Government
H5: Governmental Activities | I5: Business-Type Activities | J5: Total | K5: Component Unit
A6: ASSETS
B7: Current Assets
C8: Cash and cash equivalents (note 3) | H8: 192939199 | I8: 88246830 | J8: =SUM(H8:I8) -> 281186029 | K8: 20082173
C9: Investments (note 3) | H9: 188791227 | I9: 98538697 | J9: =SUM(H9:I9) -> 287329924
C10: Receivables--net (note 13) | H10: 53255487 | I10: 16172998 | J10: =SUM(H10:I10) -> 69428485 | K10: 17183849
C11: Due from other governments (note 11) | H11: 84764697 | I11: 5304530 | J11: =SUM(H11:I11) -> 90069227 | K11: 2446711
C12: Prepaid items | H12: 681554 | I12: 255888 | J12: =SUM(H12:I12) -> 937442 | K12: 172487
C13: Loans receivable | H13: 3614676 | J13: =SUM(H13:I13) -> 3614676 | K13: 1719373
C14: Inventory | H14: 833178 | I14: 118566 | J14: =SUM(H14:I14) -> 951744 | K14: 5335339
C15: Net pension asset | K15: 456737
C16: Other assets
C17: Restricted assets:
D18: Cash and cash equivalents (note 3) | I18: 215032849 | J18: =SUM(H18:I18) -> 215032849 | K18: 11958469
D19: Investments (note 3) | I19: 277525563 | J19: =SUM(H19:I19) -> 277525563
D20: Receivables--net (note 13) | I20: 280765 | J20: =SUM(H20:I20) -> 280765
D21: Prepaid items | I21: 6637 | J21: =SUM(H21:I21) -> 6637
C22: Capital assets:
D23: Non-depreciable | H23: 208882220 | I23: 264648985 | J23: =SUM(H23:I23) -> 473531205 | K23: 350523
D24: Depreciable, net | H24: 669766158 | I24: 1515753639 | J24: =SUM(H24:I24) -> 2185519797 | K24: 109555466
C26: Total Assets | H26: =SUM(H8:H24) -> 1403528396 | I26: =SUM(I8:I24) -> 2481885947 | J26: =SUM(J8:J24) -> 3885414343 | K26: =SUM(K8:K24) -> 169261127
A28: Deferred Outflows of Resources
B29: Deferred amount on refunding | H29: 5548137 | I29: 42943956 | J29: =SUM(H29:I29) -> 48492093 | K29: 0
B30: Deferred outflows on derivative instruments | H30: 15294792 | I30: 87643226 | J30: =SUM(H30:I30) -> 102938018 | K30: 0
B31: Deferred outflow for pension | K31: 239993
C33: Total deferred outflows of resources | H33: =SUM(H29:H31) -> 20842929 | I33: =SUM(I29:I31) -> 130587182 | J33: =SUM(J29:J31) -> 151430111 | K33: =SUM(K29:K31) -> 239993
A35: LIABILITIES
C36: Accounts payable and other current liabilities | H36: 43709310 | I36: 54839795 | J36: =SUM(H36:I36) -> 98549105 | K36: 2603986
C37: Due to other governments | H37: 7697870 | J37: =SUM(H37:I37) -> 7697870 | K37: 189696
C38: Accrued payables | H38: 16640784 | I38: 23230251 | J38: =SUM(H38:I38) -> 39871035 | K38: 2738092
C39: Unearned revenue | H39: 1063162 | I39: 1321484 | J39: =SUM(H39:I39) -> 2384646
C40: Deposits and escrow accounts | H40: 18143567 | J40: =SUM(H40:I40) -> 18143567
C41: Other liabilities | K41: 67022
C42: Noncurrent liabilities (note 10):
D43: Due within one year | H43: 30338476 | I43: 14982026 | J43: =SUM(H43:I43) -> 45320502 | K43: 3321919
D44: Due in more than one year | H44: 698794643 | I44: 1634951737 | J44: =SUM(H44:I44) -> 2333746380 | K44: 118067670
D46: Total Liabilities | H46: =SUM(H36:H44) -> 816387812 | I46: =SUM(I36:I44) -> 1729325293 | J46: =SUM(J36:J44) -> 2545713105 | K46: =SUM(K36:K44) -> 126988385
A48: Deferred Inflows of Reources
B49: Resources received before the requirements | H49: 351292 | I49: 0 | J49: =SUM(H49:I49) -> 351292 | K49: 0
A51: NET ASSETS
B52: Net investment in capital assets | H52: 650424770 | I52: 668570688 | J52: =SUM(H52:I52) -> 1318995458 | K52: 16536348
B53: Restricted for (note 14):
C54: Capital projects | H54: 81679016 | I54: 8873538 | J54: =SUM(H54:I54) -> 90552554
C55: Debt service | H55: 8949390 | I55: 73175963 | J55: =SUM(H55:I55) -> 82125353 | K55: 12116805
C56: Passenger facility charges | I56: 389690 | J56: =SUM(H56:I56) -> 389690
C57: External legal constraints | H57: 105284345 | I57: 78050000 | J57: =SUM(H57:I57) -> 183334345 | K57: 7294843
B58: Unrestricted | H58: -238705300 | I58: 54087957 | J58: =SUM(H58:I58) -> -184617343 | K58: 6564739
C60: Total Net Assets | H60: =SUM(H52:H58) -> 607632221 | I60: =SUM(I52:I58) -> 883147836 | J60: =SUM(J52:J58) -> 1490780057 | K60: =SUM(K51:K58) -> 42512735
C62: Total Liabilities and Net Assets | H62: =SUM(H46+H60+H49) -> 1424371325 | I62: =SUM(I46+I60+I49) -> 2612473129 | J62: =SUM(J46+J60+J49) -> 4036844454 | K62: =SUM(K46+K60+K49) -> 169501120

Sheet East Carroll
D1: East Carroll Parish 2014 Statement of Net Assets
D2: Issued: December 31, 2014
H4: Primary Government
H5: Governmental Activities | I5: Business-Type Activities | J5: Total
A6: ASSETS
C7: Cash and cash equivalents | H7: 2275206 | I7: 21246 | J7: =SUM(H7:I7) -> 2296452
C8: Investments | H8: 773667 | J8: =SUM(H8:I8) -> 773667
C9: Receivables | H9: 2551513 | I9: 997 | J9: =SUM(H9:I9) -> 2552510
C10: Prepaid items | I10: 1903 | J10: =SUM(H10:I10) -> 1903
C11: Cash and cash equivalents - restricted | I11: 9119 | J11: =SUM(H11:I11) -> 9119
C12: Capital assets not being depreciated | H12: 2573398 | J12: =SUM(H12:I12) -> 2573398
C13: Capital assets, net of accumulated depreciation | H13: 3785585 | J13: =SUM(H13:I13) -> 3785585
C15: Total Assets | H15: =SUM(H7:H13) -> 11959369 | I15: =SUM(I7:I13) -> 33265 | J15: =SUM(J7:J13) -> 11992634
A17: LIABILITIES
C18: Accounts payable | H18: 207657 | I18: 676 | J18: =SUM(H18:I18) -> 208333
C19: Interest payable | H19: 5987 | J19: =SUM(H19:I19) -> 5987
C20: Long-term liabilities:
D21: Due within one year | H21: 154753 | I21: 275 | J21: =SUM(H21:I21) -> 155028
D22: Due in more than one year | H22: 457009 | J22: =SUM(H22:I22) -> 457009
D24: Total Liabilities | H24: =SUM(H18:H22) -> 825406 | I24: =SUM(I18:I22) -> 951 | J24: =SUM(J18:J22) -> 826357
A26: NET ASSETS
B27: Net investment in capital assets | H27: 5755524 | J27: =SUM(H27:I27) -> 5755524
B28: Restricted for:
C29: Debt service | H29: 95165 | J29: =SUM(H29:I29) -> 95165
C30: Road maintenance | H30: 1372893 | J30: =SUM(H30:I30) -> 1372893
C31: Garbage | H31: 537606 | J31: =SUM(H31:I31) -> 537606
C32: Library | H32: 618729 | J32: =SUM(H32:I32) -> 618729
C33: Drainage | H33: 681845 | J33: =SUM(H33:I33) -> 681845
C34: Rural fire protection | H34: 425053 | J34: =SUM(H34:I34) -> 425053
C35: LSU/SU Extension | H35: 200984 | J35: =SUM(H35:I35) -> 200984
C36: Health unit | H36: 604006 | J36: =SUM(H36:I36) -> 604006
C37: Criminal Court | H37: 28298 | J37: =SUM(H37:I37) -> 28298
C38: Housing assistance payments | I38: 9119 | J38: =SUM(H38:I38) -> 9119
B39: Unrestricted | H39: 813860 | I39: 23195 | J39: =SUM(H39:I39) -> 837055
C41: Total Net Assets | H41: =SUM(H27:H39) -> 11133963 | I41: =SUM(I27:I39) -> 32314 | J41: =SUM(J27:J39) -> 11166277
C43: Total Liabilities and Net Assets | H43: =SUM(H41+H24) -> 11959369 | I43: =SUM(I41+I24) -> 33265 | J43: =SUM(J41+J24) -> 11992634

Sheet East Feliciana
C1: East Feliciana Parish 2014 Statement of Net Assets
C2: Issued: December 31, 2014
G4: Governmental Activities
A5: ASSETS
B6: Cash and cash equivalents | G6: 5002609.6
B7: Receivables, net | G7: 1124824.8
B8: Due from other funds | G8: 1831042.5
B9: Due from other governmental agencies | G9: 91971.96
B10: Capital assets, net | G10: 12861749
B12: Total Assets | G12: =SUM(G6:G10) -> 20912198
A14: DEFERRED OUTFLOWS OF RESOURCES
A17: LIABILITIES
B18: Accounts payable | G18: 735676.08
B19: Due to other funds | G19: 1464267.6
B20: Due to other governmental agencies | G20: 2729.05
B21: Compensated absences | G21: 13428
C23: Total Liabilities | G23: =SUM(G18:G21) -> 2216100.7
A25: DEFERRED OUTFLOWS OF RESOURCES
A28: NET ASSETS
B29: Net investment in capital assets | G29: 12861749
B30: Restricted for:
C31: Health unit operations/maintenance | G31: 872066
C32: Homeland security/emergency preparedness | G32: 47484.38
C33: Solid waste management | G33: 3938014
B34: Unrestricted | G34: 976786.83
B36: Total Net Assets | G36: =SUM(G29:G34) -> 18696100
B38: Total Liabilities and Net Assets | G38: =G36+G23 -> 20912201

Sheet Evangeline
D1: Evangeline Parish 2014 Statement of Net Assets
D2: Issued: December 31, 2014
H4: Primary Government
H5: Governmental Activities | I5: Business-Type Activities | J5: Total
A6: ASSETS
C7: Cash and interest-bearing deposits | H7: 11515168 | I7: 85541 | J7: =SUM(H7:I7) -> 11600709
C8: Receivables, net | H8: 12345 | I8: 18998 | J8: =SUM(H8:I8) -> 31343
C9: Due from other governmental units | H9: 6225622 | J9: =SUM(H9:I9) -> 6225622
C10: Other assets | H10: 5000 | J10: =SUM(H10:I10) -> 5000
C11: Restricted assets:
D12: Cash and interest-bearing deposits | I12: 20844 | J12: =SUM(I12) -> 20844
D13: Investments | H13: 28105054 | J13: =SUM(H13:I13) -> 28105054
C14: Capital assets, net | H14: 25647365 | I14: 261965 | J14: =SUM(H14:I14) -> 25909330
C16: Total Assets | H16: =SUM(H7:H14) -> 71510554 | I16: =SUM(I7:I14) -> 387348 | J16: =SUM(J7:J14) -> 71897902
A18: LIABILITIES
C19: Cash overdraft | H19: 7145 | J19: =SUM(H19:I19) -> 7145
C20: Accounts and other payables | H20: 2809470 | I20: 10998 | J20: =SUM(H20:I20) -> 2820468
C21: Accrued interest | H21: 114296 | J21: =SUM(H21:I21) -> 114296
C22: Performance bonds payable | H22: 307818 | J22: =SUM(H22:I22) -> 307818
C23: Unearned revenue | H23: 329789 | I23: 1438 | J23: =SUM(H23:I23) -> 331227
C24: Noncurrent liabilities:
D25: Portion due within one year:
E26: Compensated absences payable | H26: 2955 | J26: =SUM(H26:I26) -> 2955
E27: Capital lease payable | H27: 2338 | J27: =SUM(H27:I27) -> 2338
E28: Bonds and certificates payable | H28: 234000 | I28: 1916 | J28: =SUM(H28:I28) -> 235916
D29: Portion due after one year:
E30: Sewer deposits payable | H30: 11062 | I30: 11700 | J30: =SUM(H30:I30) -> 22762
E31: Compensated absences payable | H31: 68625 | J31: =SUM(H31:I31) -> 68625
E32: Bonds and certificates payable | H32: 31605866 | I32: 57806 | J32: =SUM(H32:I32) -> 31663672
D34: Total Liabilities | H34: =SUM(H19:H32) -> 35493364 | I34: =SUM(I19:I32) -> 83858 | J34: =SUM(J19:J32) -> 35577222
A36: NET ASSETS
B37: Net investment in capital assets | H37: 22677823 | I37: 204159 | J37: =SUM(H37:I37) -> 22881982
B38: Restricted for debt service | H38: 126351 | I38: 7228 | J38: =SUM(H38:I38) -> 133579
B39: Unrestricted | H39: 13213016 | I39: 92103 | J39: =SUM(H39:I39) -> 13305119
C41: Total Net Assets | H41: =SUM(H37:H39) -> 36017190 | I41: =SUM(I37:I39) -> 303490 | J41: =SUM(J37:J39) -> 36320680
C43: Total Liabilities and Net Assets | H43: =SUM(H41+H34) -> 71510554 | I43: =SUM(I41+I34) -> 387348 | J43: =SUM(J41+J34) -> 71897902

Sheet Franklin
C1: Franklin Parish 2014 Statement of Net Assets
C2: Issued: December 31, 2014
G4: Governmental Activities
A5: ASSETS
B6: Cash and cash equivalents | G6: 8560372
B7: Receivables | G7: 3796748
B8: Capital assets (net) | G8: 18743780
B10: Total Assets | G10: =SUM(G6:G8) -> 31100900
A12: LIABILITIES
B13: Accounts payable | G13: 497630
B14: Payroll withholding payable | G14: 67733
B15: Compensated absences payable | G15: 103567
B16: Capital leases payable | G16: 70000
B17: Due to others (damage deposit) | G17: 132000
B18: Net OPEB obligation | G18: 1433906
C20: Total Liabilities | G20: =SUM(G13:G18) -> 2304836
A22: NET ASSETS
B23: Invested in capital assets, net of related debt | G23: 18541780
B24: Unrestricted | G24: 10254284
B26: Total Net Assets | G26: =SUM(G23:G24) -> 28796064
B28: Total Liabilities and Net Assets | G28: =SUM(G20+G26) -> 31100900

Sheet Grant
D1: Grant Parish 2014 Statement of Net Assets
D2: Issued: December 31, 2014
H4: Primary Government
H5: Governmental Activities | I5: Business-Type Activities | J5: Total
A6: ASSETS
C7: Cash and cash equivalents | H7: 1797180 | I7: 466152 | J7: =SUM(H7:I7) -> 2263332
C8: Receivables (net) | H8: 1472672 | I8: 88420 | J8: =SUM(H8:I8) -> 1561092
C9: Capital assets:
D10: Non depreciable capital assets
E11: Construction in progress | H11: 60410 | J11: =SUM(H11:I11) -> 60410
E12: Land | H12: 203250 | J12: =SUM(H12:I12) -> 203250
D13: Depreciable capital assets, net | H13: 5577373 | I13: 349237 | J13: =SUM(H13:I13) -> 5926610
C15: Total Assets | H15: =SUM(H7:H13) -> 9110885 | I15: =SUM(I7:I13) -> 903809 | J15: =SUM(J7:J13) -> 10014694
A17: LIABILITIES
C18: Accounts and other payables | H18: 527147 | I18: 41378 | J18: =SUM(H18:I18) -> 568525
C19: Deposits due others | I19: 77981 | J19: =SUM(H19:I19) -> 77981
C20: Unearned revenues | H20: 17112 | J20: =SUM(H20:I20) -> 17112
C21: Long-term liabilities:
D22: Compensated absences | H22: 44833 | I22: 9609 | J22: =SUM(H22:I22) -> 54442
D23: Notes payable:
E24: Due within one year | H24: 95211 | J24: =SUM(H24:I24) -> 95211
E25: Due in more than one year | H25: 247461 | J25: =SUM(H25:I25) -> 247461
D27: Total Liabilities | H27: 931764 | I27: =SUM(I18:I25) -> 128968 | J27: =SUM(J18:J25) -> 1060732
A29: NET ASSETS
B30: Invested in capital assets, net of related debt | H30: 5498361 | I30: 349237 | J30: =SUM(H30:I30) -> 5847598
B31: Restricted:
C32: Maintenance | H32: 1839813 | J32: =SUM(H32:I32) -> 1839813
C33: Judicial | H33: 25525 | J33: =SUM(H33:I33) -> 25525
C34: Construction | H34: 51676 | J34: =SUM(H34:I34) -> 51676
B35: Unrestricted | H35: 763746 | I35: 425604 | J35: =SUM(H35:I35) -> 1189350
C37: Total Net Assets | H37: =SUM(H30:H35) -> 8179121 | I37: =SUM(I30:I35) -> 774841 | J37: =SUM(J30:J35) -> 8953962
C39: Total Liabilities and Net Assets | H39: =SUM(H37+H27) -> 9110885 | I39: =SUM(I37+I27) -> 903809 | J39: =SUM(J37+J27) -> 10014694

Sheet Iberia
D1: Iberia Parish 2014 Statement of Net Assets
D2: Issued: December 31, 2014
H4: Primary Government
H5: Governmental Activities | I5: Component Units
A6: ASSETS
C7: Cash and interest-bearing deposits | H7: 41860020 | I7: 50012752
C8: Investments | H8: 72229
C9: Receivables, net | H9: 8148320 | I9: 10661648
C10: Advance to component unit | H10: 1813645
C11: Due from other governmental agencies | H11: 3826329 | I11: 1109307
C12: Due from primary government | I12: 699043
C13: Inventories | I13: 1829268
C14: Prepaid items | I14: 690228
C15: Investments in joint ventures | I15: 343738
C16: Restricted assets | I16: 3604141
C17: Capital assets:
D18: Non-depreciable | H18: 7506786 | I18: 10114835
D19: Depreciable, net | H19: 86713962 | I19: 67336603
C21: Total Assets | H21: =SUM(H7:H19) -> 149941291 | I21: =SUM(I7:I19) -> 146401563
A23: DEFERRED OUTFLOWS OF RESOURCES
B24: Prepaid bond insurance
A26: LIABILITIES
C27: Accounts payable | H27: 970975 | I27: 2757772
C28: Accrued expenses | H28: 221930 | I28: 7088119
C29: Contracts and retainage payable | H29: 567425 | I29: 520118
C30: Due to other governmental agencies | H30: 361954 | I30: 204273
C31: Due to component unit | H31: 699043
C32: Advance from primary government | I32: 1813645
C33: Advances from grantors and others | H33: 126545 | I33: 92170
C34: Deposits | I34: 329200
C35: Accrued interest payable | H35: 38674 | I35: 238123
C36: Long-term liabilities:
D37: Other post employment benefits payable | H37: 4495880 | I37: 1872648
D38: Due within one year | H38: 1680344 | I38: 3633893
D39: Due in more than one year | H39: 8169937 | I39: 41369087
D41: Total Liabilities | H41: =SUM(H27:H39) -> 17332707 | I41: =SUM(I27:I39) -> 59919048
A43: NET ASSETS
B44: Net investment in capital assets | H44: 83346072 | I44: 55003983
B45: Restricted
C46: Nonexpendable | H46: 68863
C47: Capital projects | H47: 397649
C48: Debt Service | H48: 651511
C49: Tax dedications | H49: 27356660 | I49: 5615183
C50: Other | H50: 48874 | I50: 8253788
B51: Unrestricted | H51: 20738955 | I51: 17694690
C53: Total Net Assets | H53: =SUM(H44:H51) -> 132608584 | I53: =SUM(I44:I51) -> 86567644
C55: Total Liabilities and Net Assets | H55: =SUM(H41+H53) -> 149941291 | I55: =SUM(I53+I41) -> 146486692

Sheet Iberville
D1: Iberville Parish 2014 Statement of Net Assets
D2: Issued: December 31, 2014
H4: Primary Government | K4: Total Component Units
H5: Governmental Activities | I5: Business-Type Activities | J5: Total | K5: Governmental Activities | L5: Business-type Activities
A6: ASSETS
B7: Current Assets
C8: Cash and cash equivalents | H8: 23827413 | I8: 2675951 | J8: =SUM(H8:I8) -> 26503364 | K8: 1886128 | L8: 631857
C9: Receivables (net of allowance for uncollectibles) | H9: 10119866 | I9: 1016909 | J9: =SUM(H9:I9) -> 11136775 | K9: 3523868 | L9: 194625
C10: Inventories | I10: 135857 | J10: =SUM(H10:I10) -> 135857
C11: Prepaid items | H11: 560586 | J11: =SUM(H11:I11) -> 560586 | L11: 15379
C12: Other assets | H12: 48880 | I12: 336524 | J12: =SUM(H12:I12) -> 385404 | K12: 103379 | L12: 35161
C13: Restricted assets
D14: Cash and cash equivalents | H14: 100000 | I14: 542690 | J14: =SUM(H14:I14) -> 642690 | L14: 728625
C15: Capital assets (net of accumulated depreciation)
D16: Land | H16: 3105380 | I16: 193511 | J16: =SUM(H16:I16) -> 3298891 | K16: 435740
D17: Building and system | H17: 30995324 | I17: 9708202 | J17: =SUM(H17:I17) -> 40703526 | K17: 934316 | L17: 1718008
D18: Improvemetns other than building | H18: 55191369 | J18: =SUM(H18:I18) -> 55191369 | K18: 409009 | L18: 3304798
D19: Machinery and equipment | H19: 3776825 | I19: 336997 | J19: =SUM(H19:I19) -> 4113822 | K19: 378370 | L19: 1283032
D20: Construction in progress | H20: 22208945 | I20: 687059 | J20: =SUM(H20:I20) -> 22896004
C22: Total Assets | H22: =SUM(H8:H20) -> 149934588 | I22: =SUM(I8:I20) -> 15633700 | J22: =SUM(J8:J20) -> 165568288 | K22: =SUM(K8:K20) -> 7670810 | L22: =SUM(L8:L20) -> 7911485
A24: LIABILITIES
C25: Accounts payable and other current liabilities | H25: 2819108 | I25: 523848 | J25: =SUM(H25:I25) -> 3342956 | K25: 110341 | L25: 68945
C26: Matured bonds and interest payable | J26: =SUM(H26:I26) -> 0
C27: Accrued interest payable | J27: =SUM(H27:I27) -> 0
C28: Bank overdraft liability | J28: =SUM(H28:I28) -> 0
C29: Other payables | H29: 1220993 | J29: =SUM(H29:I29) -> 1220993 | K29: 204216
C30: Liabilities payable from restricted assets | I30: 291777 | J30: =SUM(H30:I30) -> 291777 | L30: 217963
C31: Noncurrent liabilities:
D32: Other post employment benefits | H32: 535622 | J32: =SUM(H32:I32) -> 535622 | K32: 79851
D33: Due in one year | H33: 1104609 | I33: 55000 | J33: =SUM(H33:I33) -> 1159609 | K33: 9000
D34: Due in more than one year | H34: 16076384 | I34: 490000 | J34: =SUM(H34:I34) -> 16566384 | K34: 297042 | L34: 3260174
D36: Total Liabilities | H36: =SUM(H25:H34) -> 21756716 | I36: =SUM(I25:I34) -> 1360625 | J36: =SUM(J25:J34) -> 23117341 | K36: =SUM(K25:K34) -> 700450 | L36: =SUM(L25:L34) -> 3547082
A38: NET ASSETS
B39: Invested in capital assets, net of related debt | H39: 97712719 | I39: 10380769 | J39: =SUM(H39:I39) -> 108093488 | K39: 2121508 | L39: 2986823
B40: Restricted for:
C41: Public building maintenance | H41: 2046146 | J41: =SUM(H41:I41) -> 2046146
C42: Drainage | H42: 3209288 | J42: =SUM(H42:I42) -> 3209288
C43: Solid waste | H43: 3474754 | J43: =SUM(H43:I43) -> 3474754
C44: Fire protection | H44: 3015608 | J44: =SUM(H44:I44) -> 3015608
C45: Emergency services | H45: 579675 | J45: =SUM(H45:I45) -> 579675
C46: Debt service | H46: 2396427 | J46: =SUM(H46:I46) -> 2396427 | L46: 470390
C47: Road Improvements | H47: 4253042 | J47: =SUM(H47:I47) -> 4253042
C48: Other | H48: 6848730 | I48: 247661 | J48: =SUM(H48:I48) -> 7096391
B49: Unrestricted | H49: 4641483 | I49: 3644645 | J49: =SUM(H49:I49) -> 8286128 | K49: 4848852 | L49: 907190
C51: Total Net Assets | H51: =SUM(H39:H49) -> 128177872 | I51: =SUM(I39:I49) -> 14273075 | J51: =SUM(J39:J49) -> 142450947 | K51: =SUM(K39:K49) -> 6970360 | L51: =SUM(L38:L49) -> 4364403
C53: Total Liabilities and Net Assets | H53: =SUM(H36+H51) -> 149934588 | I53: =SUM(I36+I51) -> 15633700 | J53: =SUM(J36+J51) -> 165568288 | K53: =SUM(K36+K51) -> 7670810 | L53: =SUM(L36+L51) -> 7911485

Sheet Jackson 
C1: Jackson Parish 2014 Statement of Net Assets
C2: Issued: December 31, 2014
G4: Governmental Activities
A5: ASSETS
B6: Cash and cash equivalents | G6: 9298920
B7: Receivables | G7: 4981192
B8: Prepaid items | G8: 75502
B9: Capital assets:
C10: Land and construction in progress | G10: 459821
C11: Capital assets, net of depreciation | G11: 15991533
B13: Total Assets | G13: =SUM(G6:G11) -> 30806968
A15: LIABILITIES
B16: Accounts, salaries, and other payables | G16: 310576
B17: Security deposits | G17: 30799
B18: Long-term liabilities:
C19: Due within one year | G19: 110115
C20: Due in more than one year | G20: 491865
C22: Total Liabilities | G22: =SUM(G16:G20) -> 943355
A24: NET ASSETS
B25: Net investment in capital assets | G25: 16451354
B26: Restricted for:
C27: Road maintenance (Road, Sales tax and asphalt funds) | G27: 5981278
C28: Waste management | G28: 1368834
C29: Library | G29: 1955864
C30: Health unit | G30: 232347
C31: Tourism | G31: 58802
C32: Landfill closure | G32: 551480
C33: Grant funds | G33: 31741
C34: Grand jury and witness fees | G34: 10559
B35: Unrestricted | G35: 3188354
B37: Total Net Assets | G37: =SUM(G25:G35) -> 29830613
B39: Total Liabilities and Net Assets | G39: =SUM(G22+G37) -> 30773968

Sheet Jefferson Davis
C1: Jefferson Davis Parish 2014 Statement of Net Assets
C2: Issued: December 31, 2014
G4: Governmental Activities
A5: ASSETS
B6: Cash and cash equivalents | G6: 19914802
B7: Investments | G7: 2112204
B8: Receivables | G8: 1464881
B9: Prepaid items | G9: 78534
B10: Restricted cash and cash equivalents | G10: 2707659
B11: Capital assets (net) | G11: 33983534
B13: Total Assets | G13: =SUM(G6:G11) -> 60261614
A15: DEFERRED OUTFLOWS OF RESOURCES
B16: Deferred bond issuance costs | G16: 71146
A18: LIABILITIES
B19: Accounts, salaries, and other payables | G19: 619781
B20: Contracts payable | G20: 161303
B21: Deposits due others | G21: 550500
B22: Other liabilities | G22: 140
B23: Accrued interest payable | G23: 282268
B24: Liability for other post-employment benefits | G24: 2078060
B25: Current portion of bonds payable | G25: 956000
B26: Current portion of capital leases payable | G26: 141267
B27: Capital leases payable | G27: 784193
B28: Bonds payable | G28: 14714000
C30: Total Liabilities | G30: =SUM(G19:G28) -> 20287512
A32: DEFERRED INFLOWS OF RESOURCES
B33: Deferred revenues | G33: 509597
A35: NET ASSETS
B36: Net investment in capital assets | G36: 17105806
B37: Restricted for:
C38: Public safety | G38: 4888543
C39: Public works | G39: 8158420
C40: Health and welfare | G40: 376920
C41: Debt service | G41: 2657652
C42: Other general government | G42: 1340505
B43: Unrestricted | G43: 5007805
B45: Total Net Assets | G45: =SUM(G36:G43) -> 39535651
B47: Total Liabilities and Net Assets | G47: =SUM(G30+G45+G33) -> 60332760

Sheet Jefferson
D1: Jefferson Parish 2014 Statement of Net Assets
D2: Issued: December 31, 2014
G3: (amounts in thousands)
H5: Primary Government
H6: Governmental Activities | I6: Business-Type Activities | J6: Total | K6: Component Unit
A7: ASSETS
B8: Current Assets
C9: Cash and cash equivalents | H9: 4986 | I9: 2624 | J9: =SUM(H9:I9) -> 7610 | K9: 22493
C10: Investments | H10: 73761 | J10: =SUM(H10:I10) -> 73761 | K10: 94049
C11: Share of pooled assets | H11: 503630 | I11: 18337 | J11: =SUM(H11:I11) -> 521967
C12: Receivables, net of allowances for
D13: estimated uncollectibles:
D14: Interest | H14: 51 | J14: =SUM(H14:I14) -> 51 | K14: 202
D15: Ad valorem tax | H15: 196362 | I15: 9233 | J15: =SUM(H15:I15) -> 205595
D16: Accounts | H16: 5362 | I16: 6026 | J16: =SUM(H16:I16) -> 11388 | K16: 88844
D17: Notes | K17: 7991
D18: Mortgage loans
D19: Intergovernmental | H19: 62965 | I19: 13 | J19: =SUM(H19:I19) -> 62978 | K19: 1607
D20: Other | K20: 11541
C21: Inventories | H21: 3423 | I21: 7883 | J21: =SUM(H21:I21) -> 11306 | K21: 16484
C22: Prepaid items | K22: 19821
C23: Restricted assets:
D24: Cash and cash equivalents | I24: 2275 | J24: =SUM(I24) -> 2275
D25: Investments | I25: 15687 | J25: =SUM(H25:I25) -> 15687 | K25: 206184
D26: Share of pooled assets | I26: 50475 | J26: =SUM(H26:I26) -> 50475
D27: Receivables | I27: 13495 | J27: =SUM(H27:I27) -> 13495
C29: Total Current Assets | H29: =SUM(H9:H27) -> 850540 | I29: =SUM(I9:I27) -> 126048 | J29: =SUM(J9:J27) -> 976588 | K29: =SUM(K9:K27) -> 469216
B31: Noncurrent Assets
C32: Restricted assets:
D33: Deposits and other assets | H33: 8427 | J33: =SUM(H33:I33) -> 8427 | K33: 26025
C34: Mortgage loans receivable | J34: =SUM(H34:I34) -> 0 | K34: 48456
C35: Capital assets not being depreciated | H35: 233702 | I35: 19347 | J35: =SUM(H35:I35) -> 253049
C36: Capital assets being depreciated, net | H36: 992761 | I36: 527411 | J36: =SUM(H36:I36) -> 1520172 | K36: 379084
C38: Total Noncurrent Assets | H38: =SUM(H31:H36) -> 1234890 | I38: =SUM(I31:I36) -> 546758 | J38: =SUM(J31:J36) -> 1781648 | K38: =SUM(K31:K36) -> 453565
C40: Total Assets | H40: =SUM(H38+H29) -> 2085430 | I40: =SUM(I38+I29) -> 672806 | J40: =SUM(J29+J38) -> 2758236 | K40: =SUM(K29+K38) -> 922781
B42: Deferred outflows of resources
C43: Deferred charges on bond issuance costs | H43: 8143 | J43: =SUM(H43:I43) -> 8143
C45: Total Deferred Outflows of Resources | H45: =H43 -> 8143 | I45: =I43 -> 0 | J45: =J43 -> 8143 | K45: =K43 -> 0
A47: LIABILITIES
B48: Current liabilities
C49: Accounts and contracts payable | H49: 27719 | I49: 481 | J49: =SUM(H49:I49) -> 28200 | K49: 30493
C50: Claims and judgments payable | H50: 5994 | J50: =SUM(H50:I50) -> 5994
C51: Intergovernmental payable | H51: 2397 | J51: =SUM(H51:I51) -> 2397
C52: Current portion of long term debt | H52: 31521 | I52: 1114 | J52: =SUM(H52:I52) -> 32635 | K52: 8458
C53: Deposits | H53: 56 | J53: =SUM(H53:I53) -> 56
C54: Accrued salaries payable | H54: 1383 | J54: =SUM(H54:I54) -> 1383
C55: Accrued interest payable | H55: 1357 | J55: =SUM(H55:I55) -> 1357 | K55: 2138
C56: Other payables and accruals | H56: 6019 | I56: 4634 | J56: =SUM(H56:I56) -> 10653 | K56: 44017
C57: Unearned revenue | H57: 198684 | I57: 9245 | J57: =SUM(H57:I57) -> 207929 | K57: 13
C58: Payable from restricted assets:
D59: Accounts payable | I59: 867 | J59: =SUM(H59:I59) -> 867
D60: Retainage payable | I60: 507 | J60: =SUM(H60:I60) -> 507
D61: Accrued interest payable | J61: =SUM(H61:I61) -> 0 | K61: 8621
D62: Other payables | J62: =SUM(H62:I62) -> 0
D63: Unearned revenue | I63: 11028 | J63: =SUM(H63:I63) -> 11028
D65: Total Current Liabilities | H65: =SUM(H49:H63) -> 275130 | I65: =SUM(I49:I63) -> 27876 | J65: =SUM(J49:J63) -> 303006 | K65: =SUM(K49:K63) -> 93740
B67: Noncurrent liabilities
C68: Customers' deposits | I68: 9081 | J68: =SUM(H68:I68) -> 9081
C69: Due in more than one year | H69: 433561 | I69: 8957 | J69: =SUM(H69:I69) -> 442518 | K69: 376980
D71: Total Noncurrent Liabilities | H71: =SUM(H67:H69) -> 433561 | I71: =SUM(I68:I69) -> 18038 | J71: =SUM(J67:J69) -> 451599 | K71: =SUM(K67:K69) -> 376980
D73: Total Liabilities | H73: =SUM(H65+H71) -> 708691 | I73: =SUM(I71+I65) -> 45914 | J73: =SUM(J71+J65) -> 754605 | K73: =SUM(K65+K71) -> 470720
A75: NET ASSETS
B76: Net investment in capital assets | H76: 877954 | I76: 536687 | J76: =SUM(H76:I76) -> 1414641 | K76: 90261
B77: Restricted for:
C78: Judges annuitles | H78: 1861 | J78: =SUM(H78:I78) -> 1861
C79: General government | H79: 1470 | J79: =SUM(H79:I79) -> 1470
C80: Public safety | H80: 40348 | J80: =SUM(H80:I80) -> 40348
C81: Public works | H81: 37967 | J81: =SUM(H81) -> 37967
C82: Transit | H82: 21529 | J82: =SUM(H82) -> 21529
C83: Health and welfare | H83: 6120 | J83: =SUM(H83) -> 6120
C84: Culture and recreation | H84: 52795 | J84: =SUM(H84) -> 52795
C85: Economic development | H85: 4021 | J85: =SUM(H85) -> 4021
C86: Urban redevelopment and housing | H86: 1464 | J86: =SUM(H86) -> 1464 | K86: 11654
C87: Construction | H87: 226518 | I87: 51997 | J87: =SUM(H87:I87) -> 278515
C88: Debt service | I88: 138 | J88: =SUM(H88:I88) -> 138 | K88: 86808
C89: Claims and judgments payable | H89: 4898 | J89: =SUM(H89:I89) -> 4898
C90: Pension benefits | H90: 528 | J90: 528
B91: Unrestricted | H91: 107409 | I91: 38070 | J91: =SUM(H91:I91) -> 145479 | K91: 263338
C93: Total Net Assets | H93: =SUM(H76:H91) -> 1384882 | I93: =SUM(I76:I91) -> 626892 | J93: =SUM(J76:J91) -> 2011774 | K93: =SUM(K75:K91) -> 452061
C95: Total Liabilities and Net Assets | H95: =SUM(H73+H93) -> 2093573 | I95: =SUM(I73+I93) -> 672806 | J95: =SUM(J73+J93) -> 2766379 | K95: =SUM(K73+K93) -> 922781

Sheet Lafayette
D1: Lafayete Parish 2014 Statement of Net Assets
D2: Issued: December 31, 2014
H4: Primary Government
H5: Governmental Activities | I5: Business-Type Activities | J5: Total | K5: Component Unit
A6: ASSETS
C7: Cash and interest-bearing deposits | H7: 7721845 | I7: 2848461 | J7: =SUM(H7:I7) -> 10570306 | K7: 50132926
C8: Investments | H8: 278852022 | I8: 16027117 | J8: =SUM(H8:I8) -> 294879139 | K8: 16338139
C9: Receivables, net | H9: 2270885 | I9: 27658362 | J9: =SUM(H9:I9) -> 29929247 | K9: 2002495
C10: Internal balances | H10: 3559213 | I10: -3559213 | J10: =SUM(H10:I10) -> 0
C11: Due from primary government | J11: =SUM(H11:I11) -> 0 | K11: 73188
C12: Due from component units | H12: 177735 | I12: 1879 | J12: =SUM(H12:I12) -> 179614
C13: Due from other governmental agencies | H13: 18499918 | I13: 3456198 | J13: =SUM(H13:I13) -> 21956116 | K13: 7986272
C14: Inventories, net | H14: 419825 | I14: 31932260 | J14: =SUM(H14:I14) -> 32352085 | K14: 218586
C15: Prepaid items | H15: 149592 | I15: 293411 | J15: =SUM(H15:I15) -> 443003 | K15: 378702
C16: Other assets | K16: 1346182
C17: Restricted assets:
D18: Cash | I18: 8101700 | J18: =SUM(H18:I18) -> 8101700 | K18: 3981944
D19: Investments | I19: 209339409 | J19: 209339409 | K19: 20708601
D20: Receivables | I20: 111938 | J20: =SUM(H20:I20) -> 111938 | K20: 44820
C21: Unamortized start-up costs | I21: 1960661 | J21: =SUM(H21:I21) -> 1960661
C22: Capital assets:
D23: Non-depreciable | H23: 70197995 | I23: 66232170 | J23: =SUM(H23:I23) -> 136430165 | K23: 29146560
D24: Depreciable,net | H24: 517241758 | I24: 662632316 | J24: =SUM(H24:I24) -> 1179874074 | K24: 90812166
C26: Total Assets | H26: =SUM(H7:H24) -> 899090788 | I26: =SUM(I7:I24) -> 1027036669 | J26: =SUM(J7:J24) -> 1926127457 | K26: =SUM(K7:K24) -> 223170581
A28: DEFERRED OUTFLOWS OF RESOURCES
B29: Deferred loss on bond refunding | H29: 10285862 | I29: 11427508 | J29: =SUM(H29:I29) -> 21713370 | K29: 24771
A31: LIABILITIES
C32: Accounts and other payables | H32: 3505182 | I32: 6433320 | J32: =SUM(H32:I32) -> 9938502 | K32: 4651833
C33: Due to primary government | J33: =SUM(H33:I33) -> 0 | K33: 179614
C34: Due to component units | H34: 73188 | J34: =SUM(H34:I34) -> 73188
C35: Due to other governmental agencies | H35: 714973 | J35: =SUM(H35:I35) -> 714973 | K35: 4507
C36: Unearned revenue | H36: 281108 | I36: 2989 | J36: =SUM(H36:I36) -> 284097 | K36: 2513461
C37: Customer deposits | I37: 8151514 | J37: =SUM(H37:I37) -> 8151514 | K37: 101171
C38: Long-term liabilities:
D39: Portion due or payable within one year | H39: 34417905 | I39: 5045582 | J39: =SUM(H39:I39) -> 39463487 | K39: 7960162
D40: Portion due or payable after one year | H40: 409431497 | I40: 494865322 | J40: =SUM(H40:I40) -> 904296819 | K40: 22626084
D42: Total Liabilities | H42: =SUM(H32:H40) -> 448423853 | I42: =SUM(I32:I40) -> 514498727 | J42: =SUM(J32:J40) -> 962922580 | K42: =SUM(K32:K40) -> 38036832
A44: DEFERRED INFLOWS OF RESOURCES
A45: Property taxes | K45: 2008404
A47: NET ASSETS
B48: Net investment in capital assets | H48: 311019205 | I48: 311982121 | J48: =SUM(H48:I48) -> 623001326 | K48: 118654045
B49: Restricted for: | J49: =SUM(H49:I49) -> 0
C50: Capital projects | H50: 82813637 | J50: =SUM(H50:I50) -> 82813637 | K50: 4476066
C51: Debt service | H51: 46408778 | I51: 133086432 | J51: =SUM(H51:I51) -> 179495210 | K51: 4385366
C52: Other | H52: 45252830 | J52: =SUM(H52:I52) -> 45252830 | K52: 620855
B53: Unrestricted (deficit) | H53: -10964684 | I53: 77912897 | J53: =SUM(H53:I53) -> 66948213 | K53: 72656539
C55: Total Net Assets | H55: =SUM(H48:H53) -> 474529766 | I55: =SUM(I48:I53) -> 522981450 | J55: =SUM(J48:J53) -> 997511216 | K55: =SUM(K47:K53) -> 200792871
C57: Total Liabilities and Net Assets | H57: =SUM(H42+H55) -> 922953619 | I57: =SUM(I55+I42) -> 1037480177 | J57: =SUM(J55+J42) -> 1960433796 | K57: =SUM(K55+K42) -> 238829703

Sheet Lafourche
D1: Lafourche Parish 2014 Statement of Net Assets
D2: Issued: December 31, 2014
H4: Primary Government | K4: Component Unit
H5: Governmental Activities | I5: Business-Type Activities | J5: Total | K5: Total
A6: ASSETS
C7: Cash | H7: 20213397 | J7: =SUM(H7:I7) -> 20213397 | K7: 213552743
C8: Investments | H8: 22534040 | J8: =SUM(H8:I8) -> 22534040 | K8: 21165841
C9: Receivables | H9: 2766041 | I9: 18174 | J9: =SUM(H9:I9) -> 2784215 | K9: 36339765
C10: Due from other governmental units | H10: 30663568 | J10: =SUM(H10:I10) -> 30663568
C11: Prepaids and other assets | H11: 2779853 | J11: =SUM(H11:I11) -> 2779853 | K11: 20080601
C12: Capital assets:
D13: Non-depreciable | H13: 39812853 | J13: =SUM(H13:I13) -> 39812853 | K13: 29927075
D14: Depreciable | H14: 56399643 | I14: 2762073 | J14: =SUM(H14:I14) -> 59161716 | K14: 211712535
C16: Total Assets | H16: =SUM(H7:H14) -> 175169395 | I16: =SUM(I7:I14) -> 2780247 | J16: =SUM(J7:J14) -> 177949642 | K16: =SUM(K7:K14) -> 532778560
B18: Deferred outflows of resources
C19: Deferred charge on refunding | H19: 998036 | J19: =SUM(H19:I19) -> 998036
C21: Total Deferred Outflows of Resources | H21: =H19 -> 998036 | I21: =I19 -> 0 | J21: =J19 -> 998036 | K21: =K19 -> 0
A23: LIABILITIES
C24: Accounts payable and accrued expenses | H24: 5646947 | I24: 27127 | J24: =SUM(H24:I24) -> 5674074 | K24: 18113211
C25: Other current liabilities | H25: 468146 | J25: =SUM(H25:I25) -> 468146 | K25: 4632620
C26: Accrued interest payable | H26: 595935 | J26: =SUM(H26:I26) -> 595935
C27: Due to other governmental units | H27: 933144 | I27: 211687 | J27: =SUM(H27:I27) -> 1144831
C28: Long-term liabilities | J28: =SUM(H28:I28) -> 0
D29: Due within one year | H29: 2495013 | J29: =SUM(H29:I29) -> 2495013 | K29: 2854918
D30: Due in more than one year | H30: 43892757 | J30: =SUM(H30:I30) -> 43892757 | K30: 26120342
D32: Total Liabilities | H32: =SUM(H24:H30) -> 54031942 | I32: =SUM(I24:I30) -> 238814 | J32: =SUM(J24:J30) -> 54270756 | K32: =SUM(K24:K30) -> 51721091
A34: NET ASSETS
B35: Net invested in capital assets | H35: 40588502 | I35: 2762073 | J35: =SUM(H35:I35) -> 43350575 | K35: 215082552
B36: Restricted for:
C37: Capital projects | H37: 12449084 | J37: =SUM(H37:I37) -> 12449084 | K37: 4158197
C38: Debt service | H38: 6338397 | J38: =SUM(H38:I38) -> 6338397 | K38: 3622326
B39: Unrestricted (deficit) | H39: 62759506 | I39: -220640 | J39: =SUM(H39:I39) -> 62538866 | K39: 258194394
C41: Total Net Assets | H41: =SUM(H35:H39) -> 122135489 | I41: =SUM(I35:I39) -> 2541433 | J41: =SUM(J35:J39) -> 124676922 | K41: =SUM(K34:K39) -> 481057469
C43: Total Liabilities and Net Assets | H43: =SUM(H41+H32) -> 176167431 | I43: =SUM(I32+I41) -> 2780247 | J43: =SUM(J32+J41) -> 178947678 | K43: =SUM(K41+K32) -> 532778560

Sheet LaSalle
C1: LaSalle Parish 2014 Statement of Net Assets
C2: Issued: December 31, 2014
G4: Governmental Activities
A5: ASSETS
B6: Cash and cash equivalents | G6: 2562628
B7: Receivables | G7: 4667182
B8: Prepaid lease payments | G8: 12440
B9: Capital assets (net) | G9: 7095343
B11: Total Assets | G11: =SUM(G6:G9) -> 14337593
A13: LIABILITIES
B14: Cash overdraft | G14: 733382
B15: Accounts payable | G15: 1157501
B16: Payroll payable | G16: 49332
B17: Net OPEB obligations | G17: 88421
B18: Long term liabilities:
C19: Due within one year | G19: 113744
C20: Due in more than one year | G20: 300699
C22: Total Liabilities | G22: =SUM(G14:G20) -> 2443079
A24: NET ASSETS
B25: Invested in capital assets, net of related debt | G25: 6680900
B26: Unrestricted | G26: 5213614
B28: Total Net Assets | G28: =SUM(G25:G26) -> 11894514
B30: Total Liabilities and Net Assets | G30: =SUM(G22+G28) -> 14337593

Sheet Lincoln
C1: Lincoln Parish 2014 Statement of Net Assets
C2: Issued: December 31, 2014
G4: Governmental Activities
A5: ASSETS
B6: Cash | G6: 9467885
B7: Investments | G7: 22471496
B8: Accounts receivable | G8: 7666006
B9: Due from other entities | G9: 813998
B10: Inventory | G10: 11582
B11: Capital assets:
C12: Non-Depreciable | G12: 1775786
C13: Depreciable | G13: 21184623
B15: Total Assets | G15: =SUM(G6:G13) -> 63391376
A17: DEFERRED OUTFLOWS OF RESOURCES
B18: Prepaid expenses | G18: 7819
A20: LIABILITIES
B21: Accounts payable | G21: 1255073
B22: Due to other entities | G22: 720960
B23: Noncurrent liabilities:
C24: Due within one year:
D25: Bonds payable | G25: 487000
C26: Due in more than one year:
D27: Compensated absences | G27: 107370
D28: Bonds payable | G28: 2989000
C29: Unfunded postretirement:
D30: Benefit plan obligations | G30: 1677068
C32: Total Liabilities | G32: =SUM(G21:G30) -> 7236471
A34: NET ASSETS
B35: Net investment in capital assets | G35: 22960409
B36: Restricted for:
C37: Capital projects | G37: 1987642
C38: Debt service | G38: 1022397
B39: Unrestricted | G39: 30192276
B41: Total Net Assets | G41: =SUM(G35:G39) -> 56162724
B43: Total Liabilities and Net Assets | G43: =SUM(G32+G41) -> 63399195

Sheet Livingston
D1: Livingston Parish 2014 Statement of Net Assets
D2: Issued: December 31, 2014
H4: Governmental Activities | I4: Business-Type Activities | J4: Total
A5: ASSETS
C6: Cash and cash equivalents | H6: 9725487 | I6: 270166 | J6: =SUM(H6:I6) -> 9995653
C7: Investments | H7: 3408123 | J7: =SUM(H7:I7) -> 3408123
C8: Receivables, Net of Allowance | H8: 913933 | I8: 12935 | J8: =SUM(H8:I8) -> 926868
C9: Inventory | H9: 227265 | J9: =SUM(H9:I9) -> 227265
C10: Internal balances | H10: 22383 | I10: -22383 | J10: =SUM(H10:I10) -> 0
C11: Due from other governments | H11: 11547592 | J11: =SUM(H11:I11) -> 11547592
C12: Due from component unit | H12: 1116951 | J12: =SUM(H12:I12) -> 1116951
C13: Unamortized bond insurance premiums | H13: 348050 | J13: =SUM(H13:I13) -> 348050
C14: Prepaid items | H14: 440288 | I14: 670 | J14: =SUM(H14:I14) -> 440958
C15: Restricted assets
D16: Cash | H16: 8774594 | I16: 92481 | J16: =SUM(H16:I16) -> 8867075
C17: Capital assets
D18: Non-depreciable | H18: 11551218 | I18: 64362 | J18: =SUM(H18:I18) -> 11615580
D19: Depreciable-net | H19: 131785254 | I19: 7811640 | J19: =SUM(H19:I19) -> 139596894
C21: Total Assets | H21: =SUM(H6:H19) -> 179861138 | I21: =SUM(I6:I19) -> 8229871 | J21: =SUM(J6:J19) -> 188091009
B23: Deferred Outflows of Resources
C24: Deferred Amount on Refunding of Debt | H24: 4057845 | J24: =SUM(H24:I24) -> 4057845
E26: Total Assets and Deferred Outflows | H26: =SUM(H24) -> 4057845 | I26: =SUM(I24) -> 0 | J26: =SUM(J24) -> 4057845
A28: LIABILITIES
C29: Accounts payable and accrued expenses | H29: 3799345 | I29: 23046 | J29: =SUM(H29:I29) -> 3822391
C30: Due to other governments | H30: 503302 | J30: =SUM(H30:I30) -> 503302
C31: Due to component Units | H31: 136508 | J31: =SUM(H31:I31) -> 136508
C32: Unearned revenues | H32: 19700 | J32: =SUM(H32:I32) -> 19700
C33: Accrued bond interest payable | H33: 1069109 | I33: 2546 | J33: =SUM(H33:I33) -> 1071655
C34: Non-current liabilities
E35: Due within one year | H35: 6948051 | I35: 92489 | J35: =SUM(H35:I35) -> 7040540
E36: Due in more than one year | H36: 79109380 | I36: 2401440 | J36: =SUM(H36:I36) -> 81510820
D38: Total Liabilities | H38: =SUM(H29:H36) -> 91585395 | I38: =SUM(I29:I36) -> 2519521 | J38: =SUM(J29:J36) -> 94104916
A40: NET ASSETS
B41: Net investment in capital assets | H41: 57658796 | I41: 5383440 | J41: =SUM(H41:I41) -> 63042236
B42: Restricted for:
C43: Construction | H43: 2452531 | J43: =SUM(H43:I43) -> 2452531
C44: Criminal Court | H44: 91894 | J44: =SUM(H44:I44) -> 91894
C45: Debt Service | H45: 8524255 | J45: =SUM(H45:I45) -> 8524255
C46: Grant | H46: 90364 | J46: =SUM(H46:I46) -> 90364
B47: Unrestricted | H47: 22515748 | I47: 326910 | J47: =SUM(H47:I47) -> 22842658
C49: Total Net Position | H49: =SUM(H41:H47) -> 91333588 | I49: =SUM(I41:I47) -> 5710350 | J49: =SUM(J40:J47) -> 97043938
C51: Total Liabilities and Net Assets | H51: =H49+H38 -> 182918983 | I51: =I49+I38 -> 8229871 | J51: =J49+J38 -> 191148854

Sheet Madison
C1: Madison Parish 2014 Statement of Net Assets
C2: Issued: December 31, 2014
G3: Primary Government
G4: Governmental Activities
A5: ASSETS
B6: Cash and cash equivalents | G6: 6060133
B7: Investments | G7: 2972442
B8: Receivables (net) | G8: 5117727
B9: Capital assets, net | G9: 8087139
B11: Total Assets | G11: =SUM(G6:G9) -> 22237441
A13: LIABILITIES
B14: Accounts, salaries and other payables | G14: 263534
B15: Long-term liabilities:
C16: Due within one year | G16: 36567
C17: Due in more than one year | G17: 536212
C19: Total Liabilities | G19: =SUM(G14:G17) -> 836313
A21: NET ASSETS
B22: Invested in capital assets, net of related debt | G22: 8004701
B23: Restricted for:
C24: Library | G24: 1374366
C25: Garbage collection | G25: 1373412
C26: Health unit | G26: 1223132
C27: Drainage and roads | G27: 1782562
C28: Courthouse and jail | G28: 5802905
C29: Other special revenue funds | G29: 1713590
B30: Unrestricted | G30: 126460
B32: Total Net Position | G32: =SUM(G22:G30) -> 21401128
B34: Total Liabilities and Net Assets | G34: =G32+G19 -> 22237441

Sheet Morehouse
C1: Morehouse Parish 2014 Statement of Net Assets
C2: Issued: December 31, 2014
G4: Governmental Activities
A5: ASSETS
B6: Cash | G6: 4184992
B7: Investments | G7: 540000
B8: Receivables | G8: 2375399
B9: Capital assets:
C10: Land | G10: 778626
C11: Other capital assets, net of depreciation | G11: 12615791
B13: Total Assets | G13: =SUM(G6:G11) -> 20494808
A15: LIABILITIES
B16: Bank overdrafts | G16: 2120878
B17: Accounts payable | G17: 250637
B18: Payroll accruals and wothholdings | G18: 27645
B19: Long-term liabilities:
C20: Due within one year | G20: 37425
C22: Total Liabilities | G22: =SUM(G16:G20) -> 2436585
A24: Deferred Inflows of Resources
B25: Property Taxes | G25: 2092447
A27: NET POSITION
B28: Invested in capital assets | G28: 13394417
B29: Restricted for special revenue | G29: 4444717
B30: Unrestricted (deficit) | G30: -1873358
B32: Total Net Position | G32: =SUM(G28:G30) -> 15965776
B34: Total Liabilities and Net Assets | G34: =G32+G22 -> 18402361

Sheet Natchitoches (2)
D1: Natchitoches Parish 2014 Statement of Net Assets
D2: Issued: December 31, 2014
H4: Governmental Activities
A5: ASSETS
B6: Current Assets
C7: Cash and cash equivalents | H7: 7337945
C8: Revenue receivables | H8: 6092207
C10: Total Assets | H10: =SUM(H7:H8) -> 13430152
B13: Noncurrent Assets
C14: Capital assets | H14: 10548209
C16: Total Assets | H16: =H14+H10 -> 23978361
A18: LIABILITIES
B19: Current Liabilities-
C20: Cash Overdraft | H20: 10015
C21: Accounts payable | H21: 564289
C22: Accrued payroll | H22: 75976
C23: Due to Other Governments | H23: 834223
D25: Total Current Liabilities | H25: =SUM(H19:H23) -> 1484503
B27: Long-term Liabilities;
C28: Accrued Compensated Absences | H28: 134639
C29: Other Post-Employment Benefit Obligation | H29: 653106
D31: Total Long-term Liabilities | H31: =SUM(H28:H29) -> 787745
E33: Total Liabilities | H33: =H31+H25 -> 2272248
A35: NET POSITION
B36: Net investment in capital assets | H36: 10548209
B37: Unrestricted | H37: 11157904
C39: Total Net Position | H39: =SUM(H36:H37) -> 21706113
C41: Total Liabilities and Net Assets | H41: =H39+H25 -> 23190616

Sheet Natchitoches
D1: Natchitoches Parish 2014 Statement of Net Assets
D2: Issued: December 31, 2014
H4: Governmental Activities | I4: Business-Type Activities | J4: Total
A5: ASSETS
B6: Current Assets
C7: Cash and cash equivalents | H7: 28619219 | I7: 4396086 | J7: =SUM(H7:I7) -> 33015305
C8: Revenue receivables | H8: 2081947 | I8: 4072402 | J8: =SUM(H8:I8) -> 6154349
C9: Other Receivables | J9: =SUM(H9:I9) -> 0
C10: Inventories at Cost | H10: 28871 | I10: 1374428 | J10: =SUM(H10:I10) -> 1403299
C11: Prepaid Expenses | H11: 10990 | I11: 84948 | J11: =SUM(H11:I11) -> 95938
C12: Restricted Assets | J12: =SUM(H12:I12) -> 0
D13: Cash & Cash Equivalents | J13: =SUM(H13:I13) -> 0
C14: Capital assets- | J14: =SUM(H14:I14) -> 0
D15: Land | H15: 7633862 | I15: 758408 | J15: =SUM(H15:I15) -> 8392270
D16: Buildings | H16: 16656061 | I16: 1899439 | J16: =SUM(H16:I16) -> 18555500
D17: Machinery & Equipment | H17: 2743172 | I17: 10140956 | J17: =SUM(H17:I17) -> 12884128
D18: Vehicles | H18: 5516668 | I18: 1493423 | J18: =SUM(H18:I18) -> 7010091
D19: Other assets | H19: 905568 | I19: 310366 | J19: =SUM(H19:I19) -> 1215934
D20: Streets | H20: 92561315 | J20: =SUM(H20:I20) -> 92561315
D21: Other Infrastructure | H21: 11191156 | J21: =SUM(H21:I21) -> 11191156
D22: Construction in Progress | H22: 1688203 | J22: =SUM(H22:I22) -> 1688203
D23: Utility Plant & System | J23: =SUM(H23:I23) -> 0
D24: Accumulated Depreciation | H24: -102602577 | J24: =SUM(H24:I24) -> -102602577
C26: Total Assets | H26: =SUM(H7:H24) -> 67034455 | I26: =SUM(I7:I24) -> 24530456 | J26: =SUM(J7:J24) -> 91564911
A28: LIABILITIES
C29: Cash overdraft | H29: 1234953 | J29: =SUM(H29:I29) -> 1234953
C30: Accounts payable | H30: 776327 | I30: 1866255 | J30: =SUM(H30:I30) -> 2642582
C31: Accrued payroll | H31: 216533 | I31: 69861 | J31: =SUM(H31:I31) -> 286394
C32: Accured Expenses | H32: 1066501 | I32: 18527 | J32: =SUM(H32:I32) -> 1085028
C33: Payable from Restriced Assets-
D34: Bond Principal | I34: 1185000 | J34: =SUM(H34:I34) -> 1185000
D35: Customer's Deposits | I35: 828561 | J35: =SUM(H35:I35) -> 828561
C36: Long-term Debt- | J36: =SUM(H36:I36) -> 0
D37: Due Within One year | H37: 408096 | J37: =SUM(H37:I37) -> 408096
D38: Due in More than One Year | H38: 3883262 | J38: =SUM(H38:I38) -> 3883262
C39: Net OPEB Obligation | H39: 647980 | I39: 193531 | J39: =SUM(H39:I39) -> 841511
C40: Accured Employee Vacations | H40: 2056016 | I40: 560912 | J40: =SUM(H40:I40) -> 2616928
J41: =SUM(H41:I41) -> 0
D42: Total Current Liabilities | H42: =SUM(H29:H40) -> 10289668 | I42: =SUM(I29:I40) -> 4722647 | J42: =SUM(J29:J40) -> 15012315
A44: NET POSITION
B45: Net investment in capital assets | H45: 32002070 | I45: 41908967 | J45: =SUM(H45:I45) -> 73911037
B46: Restricted for Debt Service | H46: 4291358 | I46: 1185000 | J46: =SUM(H46:I46) -> 5476358
B47: Unrestricted | H47: 20451359 | I47: 27117378 | J47: =SUM(H47:I47) -> 47568737
C49: Total Net Position | H49: =SUM(H45:H47) -> 56744787 | I49: =SUM(I45:I47) -> 70211345 | J49: =SUM(J45:J47) -> 126956132
C51: Total Liabilities and Net Assets | H51: =H49+H42 -> 67034455 | I51: =I49+I42 -> 74933992 | J51: =J49+J42 -> 141968447

Sheet Orleans
D1: Orleans Parish 2014 Statement of Net Assets
D2: Issued: December 31, 2014
H4: Primary Government
H5: Governmental Activities | I5: Component Unit
A6: ASSETS
C7: Cash and cash equivalents | H7: 91036 | I7: 121383
C8: Investments | H8: 190025 | I8: 58245
C9: Receivables (net of allowance for uncollectibles):
D10: Taxes | H10: 32593 | I10: 8660
D11: Accounts | H11: 14605 | I11: 31297
D12: Interest | I12: 42
D13: Grantee loans | H13: 658 | I13: 44246
D14: Other | I14: 12020
C15: Due from component units | H15: 14890
C16: Due from other governments | H16: 56538 | I16: 2743
C17: Other assets | H17: 15 | I17: 40181
C18: Restricted cash and investments | I18: 304698
C19: Capital assets (net of accumulated depreciation) | H19: 1595680 | I19: 3207656
C21: Total Assets | H21: =SUM(H7:H19) -> 1996040 | I21: =SUM(I7:I19) -> 3831171
A23: Deferred Outflows of Resources
B24: Deferred loss on bond refunding | H24: 6435 | I24: 22601
C25: Total deferred outflows of resources | H25: =H24 -> 6435 | I25: =I24 -> 22601
A27: LIABILITIES
C28: Accounts payable | H28: 76891 | I28: 58988
C29: Retainage payable | H29: 3658 | I29: 7946
C30: Accrued expenses | H30: 676 | I30: 36352
C31: Taxes payable | H31: 6337
C32: Accrued Interest Payable | H32: 6654 | I32: 14016
C33: Due to component units | H33: 7146
C34: Due to other governments | H34: 12557 | I34: 31722
C35: Liabilities payable from restricted assets | I35: 18844
C36: Long-term liabilities due within one year | H36: 104932 | I36: 51651
C37: Long-term liabilities due in more than one year | H37: 1481068 | I37: 996165
D39: Total Liabilities | H39: =SUM(H28:H37) -> 1699919 | I39: =SUM(I28:I37) -> 1215684
A41: Deferred Inflows of Resources
B42: Unavailable Revenue | H42: 6687 | I42: 4890
C43: Total deferred inflows of resources | H43: =H42 -> 6687 | I43: =I42 -> 4890
A45: NET POSITION
B46: Net investment in capital assets | H46: 936247 | I46: 2482767
B47: Restricted for debt service | H47: 73516 | I47: 79715
B48: Restricted for capital improvement | H48: 51081 | I48: 127076
B49: Restricted for operating reserve | I49: 15479
B50: Unrestricted (deficit) | H50: -764975 | I50: -71839
C52: Total Net Position | H52: =SUM(H46:H50) -> 295869 | I52: =SUM(I45:I50) -> 2633198
C54: Total Liabilities and Net Assets | H54: =H52+H39 -> 1995788 | I54: =I52+I39 -> 3848882

Sheet Ouachita 
C1: Ouachita Parish 2014 Statement of Net Assets
D2: Issued: December 31, 2014
F5: Governmental Activities | G5: Business-Type Activities | H5: Total
A6: ASSETS
B7: Cash and cash equivalents | F7: 37300264 | G7: 78223 | H7: =SUM(F7:G7) -> 37378487
B8: Investments, at market value | F8: 25766100 | H8: =SUM(F8:G8) -> 25766100
B9: Receivables:
C10: Ad valorem taxes | F10: 32242138 | H10: =SUM(F10:G10) -> 32242138
C11: Sales taxes | F11: 2660019 | H11: =SUM(F11:G11) -> 2660019
C12: Special assessments | F12: 162436 | H12: =SUM(F12:G12) -> 162436
C13: Trade receivables | F13: 979346 | G13: 24586 | H13: =SUM(F13:G13) -> 1003932
C14: Other | G14: 15380 | H14: =SUM(F14:G14) -> 15380
B15: Due from other governmental | F15: 3664640 | G15: 2181 | H15: =SUM(F15:G15) -> 3666821
B16: Internal balances | F16: 84661 | G16: -84661 | H16: =SUM(F16:G16) -> 0
B17: Prepaid expenses | F17: 326720 | H17: =SUM(F17:G17) -> 326720
B18: Inventories | F18: 539675 | H18: =SUM(F18:G18) -> 539675
B19: Restricted assets-cash | G19: 58502 | H19: =SUM(F19:G19) -> 58502
B20: Capital assets, net | F20: 180966576 | G20: 2570352 | H20: =SUM(F20:G20) -> 183536928
C22: Total Assets | F22: =SUM(F7:F20) -> 284692575 | G22: =SUM(G7:G20) -> 2664563 | H22: =SUM(H7:H20) -> 287357138
A24: LIABILITIES
B25: Accounts payable and accrued expenses | F25: 6536200 | G25: 24093 | H25: =SUM(F25:G25) -> 6560293
B26: Unearned revenues | F26: 1019255 | H26: =SUM(F26:G26) -> 1019255
B27: Deposits held | F27: 235293 | H27: =SUM(F27:G27) -> 235293
B28: Long-term liabilities
C29: Due within one year | F29: 1421391 | G29: 25000 | H29: =SUM(F29:G29) -> 1446391
C30: Due in more than one year | F30: 7731868 | G30: 376000 | H30: =SUM(F30:G30) -> 8107868
B31: Other noncurrent liabilities | G31: 2556 | H31: =SUM(F31:G31) -> 2556
D33: Total Liabilities | F33: =SUM(F25:F31) -> 16944007 | G33: =SUM(G25:G31) -> 427649 | H33: =SUM(H25:H31) -> 17371656
A35: NET POSITION
B36: Net investment in capital assets | F36: 180966576 | G36: 2169352 | H36: =SUM(F36:G36) -> 183135928
B37: Restricted for:
C38: Public works | F38: 7023933 | H38: =SUM(F38:G38) -> 7023933
C39: Public safety | F39: 43191674 | H39: =SUM(F39:G39) -> 43191674
C40: Health and welfare | F40: 5112412 | H40: =SUM(F40:G40) -> 5112412
C41: Culture and recreation | F41: 11189533 | H41: =SUM(F41:G41) -> 11189533
C42: Economic development | F42: 743934 | H42: =SUM(F42:G42) -> 743934
C43: Judicial | F43: 1480125 | H43: =SUM(F43:G43) -> 1480125
C44: Debt service | F44: 96037 | G44: 58502 | H44: =SUM(F44:G44) -> 154539
C45: Capital improvements | F45: 8066222 | H45: =SUM(F45:G45) -> 8066222
C46: Insurance claims | F46: 6073825 | H46: =SUM(F46:G46) -> 6073825
B47: Unrestricted | F47: 3804300 | G47: 9060 | H47: =SUM(F47:G47) -> 3813360
C49: Total Net Position | F49: =SUM(F36:F47) -> 267748571 | G49: =SUM(G36:G47) -> 2236914 | H49: =SUM(H35:H47) -> 269985485
C51: Total Liabilities and Net Assets | F51: =F49+F33 -> 284692578 | G51: =G49+G33 -> 2664563 | H51: =H49+H33 -> 287357141

Sheet Plaquemines
D1: Plaquemines Parish 2014 Statement of Net Assets
D2: Issued: December 31, 2014
H4: Governmental Activities | I4: Business-Type Activities | J4: Total
A5: ASSETS
B6: Current Assets
C7: Cash and cash equivalents | H7: 113364903 | I7: 266738 | J7: =SUM(H7:I7) -> 113631641
C8: Investments | H8: 4716345 | J8: =SUM(H8:I8) -> 4716345
C9: Receivables (net of allowaces for uncollectibles) | H9: 71277195 | I9: 4353695 | J9: =SUM(H9:I9) -> 75630890
C10: Internal balances | J10: =SUM(H10:I10) -> 0
C11: Prepaid items | H11: 1640560 | I11: 4104 | J11: =SUM(H11:I11) -> 1644664
C13: Total Current Assets | H13: =SUM(H7:H11) -> 190999003 | I13: =SUM(I7:I12) -> 4624537 | J13: =SUM(J7:J11) -> 195623540
B15: Non-current Assets:
C16: Internal balances | H16: 2073727 | I16: -2073727 | J16: =SUM(H16:I16) -> 0
C17: Capital assets, net of accumulated depreciation | H17: 312070406 | I17: 75746403 | J17: =SUM(H17:I17) -> 387816809
C18: Capital assets not being depreciated | H18: 160855080 | I18: 27764347 | J18: =SUM(H18:I18) -> 188619427
C20: Total Non-current Assets | H20: =SUM(H15:H18) -> 474999213 | I20: =SUM(I15:I18) -> 101437023 | J20: =SUM(J15:J18) -> 576436236
C22: Total Assets | H22: =SUM(H13+H20) -> 665998216 | I22: =SUM(I13+I20) -> 106061560 | J22: =SUM(J13+J20) -> 772059776
A24: LIABILITIES
B25: Current Liabilities:
C26: Cash overdraft | I26: 5444208 | J26: =SUM(H26:I26) -> 5444208
C27: Accounts, salaries and other payables | H27: 11081312 | I27: 220782 | J27: =SUM(H27:I27) -> 11302094
C28: Bonds payable | H28: 3725000 | J28: =SUM(H28:I28) -> 3725000
C29: Capital leases payable | H29: 29467 | J29: =SUM(H29:I29) -> 29467
C30: Unearned revenues | H30: 4944703 | J30: =SUM(H30:I30) -> 4944703
C31: Accrued interest payable | H31: 2340925 | J31: =SUM(H31:I31) -> 2340925
C32: Compensated absences payable | H32: 1091878 | I32: 34115 | J32: =SUM(H32:I32) -> 1125993
C33: Deposits due others | H33: 33275 | J33: =SUM(H33:I33) -> 33275
C34: Other | H34: 733000 | I34: 414888 | J34: =SUM(H34:I34) -> 1147888
D36: Total Current Liabilities | H36: =SUM(H27:H34) -> 23979560 | I36: =SUM(I26:I34) -> 6113993 | J36: =SUM(J26:J34) -> 30093553
B38: Non-current Liabilities
C39: Litigation and other contingencies | H39: 3964423 | J39: =SUM(H39:I39) -> 3964423
C40: Capital leases payable | H40: 78073 | J40: =SUM(H40:I40) -> 78073
C41: Notes payable-long term | H41: 2989446 | J41: =SUM(H41:I41) -> 2989446
C42: Bonds payable-long term | H42: 117680000 | J42: =SUM(H42:I42) -> 117680000
C43: Other post-employment benefits payable | H43: 21448731 | I43: 766302 | J43: =SUM(H43:I43) -> 22215033
D45: Total Non-current Liabilities | H45: =SUM(H39:H43) -> 146160673 | I45: =SUM(I39:I43) -> 766302 | J45: =SUM(J39:J43) -> 146926975
D47: Total Liabilities | H47: =SUM(H36+H45) -> 170140233 | I47: =SUM(I45+I36) -> 6880295 | J47: =SUM(J36+J45) -> 177020528
A49: NET POSITION
B50: Invested in capital assets | H50: 351520486 | I50: 103510750 | J50: =SUM(H50:I50) -> 455031236
B51: Restricted | H51: 96356871 | J51: =SUM(H51:I51) -> 96356871
B52: Unrestricted (deficit) | H52: 47980626 | I52: -4329485 | J52: =SUM(H52:I52) -> 43651141
C54: Total Net Position | H54: =SUM(H50:H52) -> 495857983 | I54: =SUM(I50:I52) -> 99181265 | J54: =SUM(J49:J52) -> 595039248
C56: Total Liabilities and Net Position | H56: =SUM(H47+H54) -> 665998216 | I56: =SUM(I54+I47) -> 106061560 | J56: =SUM(J54+J47) -> 772059776

Sheet Pointe Couppe
C1: Pointe Coupee Parish 2014 Statement of Net Assets
D2: Issued: December 31, 2014
F4: Primary Government | I4: Component Units
F5: Governmental Activities | G5: Business-Type Activities | H5: Total | I5: Governmental Activities | J5: Business-Type Activities | K5: Total
A6: ASSETS
B7: Cash and cash equivalents | F7: 2279603 | G7: 792371 | H7: =SUM(F7:G7) -> 3071974 | I7: 4429806 | J7: 5067971 | K7: =SUM(I7:J7) -> 9497777
B8: Investments | F8: 706925 | H8: =SUM(F8:G8) -> 706925 | I8: 11314015 | J8: 14679094 | K8: =SUM(I8:J8) -> 25993109
B9: Accounts receivable, net | F9: 3308824 | G9: 690527 | H9: =SUM(F9:G9) -> 3999351 | I9: 3645141 | J9: 3434763 | K9: =SUM(I9:J9) -> 7079904
B10: Due from other governments | F10: 700786 | G10: 56040 | H10: =SUM(F10:G10) -> 756826 | I10: 339567 | J10: 152189 | K10: =SUM(I10:J10) -> 491756
B11: Due from fiduciary funds | F11: 239026 | H11: =SUM(F11:G11) -> 239026 | K11: =SUM(I11:J11) -> 0
B12: Internal balances | F12: 62650 | G12: -62650 | H12: =SUM(F12:G12) -> 0 | K12: =SUM(I12:J12) -> 0
B13: Prepaid items | F13: 90147 | G13: 1136 | H13: =SUM(F13:G13) -> 91283 | I13: 133931 | J13: 678255 | K13: =SUM(I13:J13) -> 812186
B14: Other assets | F14: 13366 | G14: 15966 | H14: =SUM(F14:G14) -> 29332 | I14: 28127 | J14: 540 | K14: =SUM(I14:J14) -> 28667
B15: Capital assets: | H15: =SUM(F15:G15) -> 0 | K15: =SUM(I15:J15) -> 0
C16: Non-depreciable | F16: 1460171 | G16: 45233 | H16: =SUM(F16:G16) -> 1505404 | I16: 1313808 | J16: 5248953 | K16: =SUM(I16:J16) -> 6562761
C17: Depreciable, net | F17: 15541863 | G17: 2061224 | H17: =SUM(F17:G17) -> 17603087 | I17: 12908626 | J17: 23988537 | K17: =SUM(I17:J17) -> 36897163
C19: Total Assets | F19: =SUM(F7:F17) -> 24403361 | G19: =SUM(G7:G17) -> 3599847 | H19: =SUM(H7:H17) -> 28003208 | I19: =SUM(I7:I17) -> 34113021 | J19: =SUM(J7:J17) -> 53250302 | K19: =SUM(I19:J20) -> 87363323
A21: LIABILITIES
B22: Accounts payable and accrued liabilities | F22: 1058577 | G22: 319400 | H22: =SUM(F22:G22) -> 1377977 | I22: 706987 | J22: 2102604 | K22: =SUM(I22:J22) -> 2809591
B23: Due to other governments | F23: 476736 | H23: =SUM(F23:G23) -> 476736 | I23: 8849 | J23: 177350 | K23: =SUM(I23:J23) -> 186199
B24: Customer meter deposits | G24: 780178 | H24: =SUM(F24:G24) -> 780178 | J24: 310443 | K24: =SUM(I24:J24) -> 310443
B25: Long term payables: | H25: =SUM(F25:G25) -> 0 | K25: =SUM(I25:J25) -> 0
C26: Due within one year | F26: 443736 | G26: 93220 | H26: 536956 | I26: 465764 | J26: 228729 | K26: =SUM(I26:J26) -> 694493
C27: Due in more than one year | F27: 7635201 | G27: 456941 | H27: =SUM(F27:G27) -> 8092142 | I27: 3897020 | J27: 7146607 | K27: =SUM(I27:J27) -> 11043627
D29: Total Liabilities | F29: =SUM(F22:F27) -> 9614250 | G29: =SUM(G22:G27) -> 1649739 | H29: =SUM(H22:H27) -> 11263989 | I29: =SUM(I22:I27) -> 5078620 | J29: =SUM(J22:J27) -> 9965733 | K29: =SUM(I29:J29) -> 15044353
A31: Deferred Inflows of Resources
B32: Ad calorem received in advance | G32: 0 | H32: =SUM(F32:G32) -> 0 | I32: 1038523 | J32: 0 | K32: =SUM(I32:J32) -> 1038523
A34: NET ASSETS
B35: Invested in capital assets, net of related debt | F35: 8923097 | G35: 1556296 | H35: =SUM(F35:G35) -> 10479393 | I35: 11607710 | J35: 21563440 | K35: =SUM(I35:J35) -> 33171150
B36: Restricted for:
C37: Road construction and maintenance | F37: 613294 | H37: =SUM(F37:G37) -> 613294 | K37: =SUM(I37:J37) -> 0
C38: Debt service | F38: 2196694 | G38: 35563 | H38: =SUM(F38:G38) -> 2232257 | I38: 155773 | J38: 443025 | K38: =SUM(I38:J38) -> 598798
C39: Other purposes | H39: =SUM(F39:G39) -> 0 | I39: 721976 | K39: =SUM(I39:J39) -> 721976
B40: Unrestricted | F40: 3056026 | G40: 358249 | H40: =SUM(F40:G40) -> 3414275 | I40: 15510419 | J40: 21278104 | K40: =SUM(I40:J40) -> 36788523
C42: Total Net Assets | F42: =SUM(F35:F40) -> 14789111 | G42: =SUM(G35:G40) -> 1950108 | H42: =SUM(H34:H40) -> 16739219 | I42: =SUM(I35:I40) -> 27995878 | J42: =SUM(J35:J40) -> 43284569 | K42: =SUM(I42:J42) -> 71280447
C44: Total Liabilities and Net Assets | F44: =SUM(F29+F42+F32) -> 24403361 | G44: =SUM(G29+G42+G32) -> 3599847 | H44: =SUM(H29+H42+H32) -> 28003208 | I44: =SUM(I29+I42+I32) -> 34113021 | J44: =SUM(J29+J42+J32) -> 53250302 | K44: =SUM(I44:J44) -> 87363323

Sheet Rapides
D1: Rapides Parish 2014 Statement of Net Assets
D2: Issued: December 31, 2014
H5: 2014 | I5: 2013
A6: ASSETS
C7: Cash and cash equivalents | H7: 51085465 | I7: 50024032
C8: Receivables | H8: 22832720 | I8: 22585071
C9: Other assets | H9: 516 | I9: 492
C10: Capital assets (net of accumulated depreciation):
D11: Nondepreciable:
E12: Land | H12: 1991998 | I12: 1689373
E13: Construction in progress | H13: 4503009 | I13: 1375268
D14: Depreciable:
E15: Buildings and improvements | H15: 10023028 | I15: 10856728
E16: Furniture, equipment, and other | H16: 8034400 | I16: 7063409
E17: Infrastructure | H17: 29558510 | I17: 30119389
C19: Total Assets | H19: =SUM(H7:H17) -> 128029646 | I19: =SUM(I7:I17) -> 123713762
A21: LIABILITIES
C22: Accounts, salaries, and other payables | H22: 916265 | I22: 1276458
C23: Deferred revenues | H23: 632212 | I23: 1693311
C24: Interest payable | H24: 881344 | I24: 1097664
C25: Long-term liabilities:
D26: Due within one year | H26: 1660074 | I26: 1649430
D27: Due in more than one year | H27: 53531400 | I27: 48762251
D29: Total Liabilities | H29: =SUM(H22:H27) -> 57621295 | I29: =SUM(I22:I27) -> 54479114
A31: NET ASSETS
B32: Invested in capital assets, net of related debt | H32: 26878874 | I32: 24889814
B33: Restricted for debt service | H33: 3296487 | I33: 2945708
B34: Unrestricted | H34: 40232989 | I34: 41399125
C36: Total Net Position | H36: =SUM(H32:H34) -> 70408350 | I36: =SUM(I31:I34) -> 69234647
C38: Total Liabilities and Net Assets | H38: =H36+H29 -> 128029645 | I38: =I36+I29 -> 123713761

Sheet Red River
D1: Red River Parish 2014 Statement of Net Assets
D2: Issued: December 31, 2014
H4: Governmental Activities | I4: Business-Type Activities | J4: Total
A5: ASSETS
B6: Current Assets
C7: Cash and cash equivalents | H7: 12519211 | I7: 100126 | J7: =SUM(H7:I7) -> 12619337
C8: Investments | H8: 19054888 | J8: =SUM(H8:I8) -> 19054888
C9: Receivables | H9: 4424485 | I9: 3082 | J9: =SUM(H9:I9) -> 4427567
C10: Prepaid expense | H10: 18353 | J10: =SUM(H10:I10) -> 18353
C12: Total Current Assets | H12: =SUM(H7:H10) -> 36016937 | I12: =SUM(I7:I11) -> 103208 | J12: =SUM(J7:J10) -> 36120145
B14: Non-current Assets:
C15: Capital assets, net of accumulated depreciation | H15: 15298294 | I15: 262880 | J15: 15561174
C17: Total Assets | H17: =SUM(H12+H15) -> 51315231 | I17: =SUM(I12+I15) -> 366088 | J17: =SUM(J12+J15) -> 51681319
A19: LIABILITIES
B20: Current Liabilities:
C21: Accounts payable and accured liabilities | H21: 723013 | I21: 1738 | J21: =SUM(H21:I21) -> 724751
C22: Compensated absences payable | H22: 52750 | J22: =SUM(H22:I22) -> 52750
D24: Total Current Liabilities | H24: =SUM(H21:H22) -> 775763 | I24: =SUM(I21:I22) -> 1738 | J24: =SUM(J21:J22) -> 777501
B26: Non-current Liabilities
C27: Compensated absences payable, net of current portion | H27: 17758 | J27: =SUM(H27:I27) -> 17758
C28: Other post-employment benefits payable | H28: 139351 | J28: =SUM(H28:I28) -> 139351
D30: Total Non-current Liabilities | H30: =SUM(H27:H28) -> 157109 | I30: =SUM(I27:I28) -> 0 | J30: =SUM(J27:J28) -> 157109
D32: Total Liabilities | H32: =SUM(H24+H30) -> 932872 | I32: =SUM(I30+I24) -> 1738 | J32: =SUM(J24+J30) -> 934610
A34: DEFERRED INFLOWS OF RESOURCES
A36: NET POSITION
B37: Net investment in capital assets | H37: 15298294 | I37: 262880 | J37: =SUM(H37:I37) -> 15561174
B38: Restricted for:
C39: Sales tax dedicated for the maintenance of ambulances and the costs to provide services | H39: 7062267 | J39: =SUM(H39:I39) -> 7062267
C40: Dedicated property taxes for library services and construction | H40: 3829412 | J40: =SUM(H40:I40) -> 3829412
C41: Dedicated property taxes for health unit services and construction | H41: 1961059 | J41: =SUM(H41:I41) -> 1961059
C42: External legal constraints | H42: 481881 | J42: =SUM(H42:I42) -> 481881
B43: Unrestricted | H43: 21749446 | I43: 101470 | J43: =SUM(H43:I43) -> 21850916
C45: Total Net Assets | H45: =SUM(H37:H43) -> 50382359 | I45: =SUM(I37:I43) -> 364350 | J45: =SUM(J37:J43) -> 50746709
C47: Total Liabilities and Net Assets | H47: =SUM(H32+H45) -> 51315231 | I47: =SUM(I45+I32) -> 366088 | J47: =SUM(J45+J32) -> 51681319

Sheet Richland
C1: Richland Parish 2014 Statement of Net Assets
C2: Issued: December 31, 2014
G4: Governmental Activities
A5: ASSETS
B6: Cash | G6: 8156413
B7: Receivables | G7: 2837396
B8: Capital assets:
C9: Land | G9: 300273
C10: Other capital assets, net of depreciation | G10: 2325795
B12: Total Assets | G12: =SUM(G6:G10) -> 13619877
A14: LIABILITIES
B15: Accounts payable | G15: 391719
B16: Payroll accruals and wothholding | G16: 62400
C18: Total Liabilities | G18: =SUM(G15:G16) -> 454119
A20: DEFERRED INFLOWS OF RESOURCES
B21: Property taxes | G21: 2667511
A23: NET POSITION
B24: Invested in capital assets | G24: 2626068
B25: Restricted for special revenue | G25: 6125046
B26: Unrestricted | G26: 1747133
B28: Total Net Position | G28: =SUM(G24:G26) -> 10498247
B30: Total Liabilities and Net Assets | G30: =G28+G18 -> 10952366

Sheet Sabine
D1: Sabine Parish 2014 Statement of Net Assets
D2: Issued: December 31, 2014
H5: 2014 | I5: 2013
A6: ASSETS
C7: Cash and cash equivalents | H7: 9360736 | I7: 8931765
C8: Receivables | H8: 3889321 | I8: 3916001
C9: Capital assets (net of accumulated depreciation):
E10: Land | H10: 639576 | I10: 639576
E11: Construction in progress | H11: 2281793 | I11: 540422
E12: Buildings and improvements | H12: 2199290 | I12: 1720235
E13: Machinery and equipment | H13: 2943475 | I13: 3069475
E14: Furniture, equipment, and other | H14: 12573 | I14: 15328
E15: Infrastructure:
F16: Roads | H16: 1123833 | I16: 1849947
F17: Road right-of-way | H17: 995977 | I17: 991177
F18: Bridges | H18: 3681027 | I18: 3769263
C20: Total Assets | H20: =SUM(H7:H18) -> 27127601 | I20: =SUM(I7:I18) -> 25443189
A22: LIABILITIES
C23: Accounts, salaries, and other payables | H23: 477050 | I23: 752592
C24: Interest payable | H24: 6775 | I24: 12512
C25: Long-term liabilities:
D26: Due within one year | H26: 351017 | I26: 372094
D27: Due in more than one year | H27: 952478 | I27: 910569
D29: Total Liabilities | H29: =SUM(H23:H27) -> 1787320 | I29: =SUM(I23:I27) -> 2047767
A31: NET POSITION
B32: Invested in capital assets, net of related debt | H32: 13520414 | I32: 11935674
B33: Unrestricted | H33: 11819867 | I33: 11459748
C35: Total Net Position | H35: =SUM(H32:H33) -> 25340281 | I35: =SUM(I31:I33) -> 23395422
C37: Total Liabilities and Net Assets | H37: =H35+H29 -> 27127601 | I37: =I35+I29 -> 25443189

Sheet St. Bernard
C1: St. Bernard Parish 2014 Statement of Net Assets
D2: Issued: December 31, 2014
F5: Governmental Activities | G5: Business-Type Activities | H5: Total
A6: ASSETS
B7: Cash and cash equivalents | F7: 35522122 | G7: 4274873 | H7: =SUM(F7:G7) -> 39796995
B8: Investments | F8: 1065661 | H8: =SUM(F8:G8) -> 1065661
B9: Investments--land held for sale | F9: 4229000 | H9: =SUM(F9:G9) -> 4229000
B10: Receivables | H10: =SUM(F10:G10) -> 0
C11: Sales and use taxes | F11: 2629527 | G11: 657382 | H11: =SUM(F11:G11) -> 3286909
C12: Property taxes | F12: 13179754 | H12: =SUM(F12:G12) -> 13179754
C13: Cable franchise fees | F13: 92741 | H13: =SUM(F13:G13) -> 92741
C14: Customer | G14: 304054 | H14: =SUM(F14:G14) -> 304054
C15: Intergovernmental | F15: 22465426 | H15: =SUM(F15:G15) -> 22465426
C16: Other | F16: 1047399 | G16: 11006 | H16: =SUM(F16:G16) -> 1058405
B17: Unbilled charges | G17: 581796 | H17: =SUM(F17:G17) -> 581796
B18: Internal balances | F18: -3031265 | G18: 3031265 | H18: =SUM(F18:G18) -> 0
B19: Prepaids | F19: 214304 | G19: 89375 | H19: =SUM(F19:G19) -> 303679
B20: Inventory | G20: 317247 | H20: =SUM(F20:G20) -> 317247
B21: Restricted assets--cash and cash equivalents | G21: 8718644 | H21: =SUM(F21:G21) -> 8718644
B22: Loan and interest receivable | G22: 780000 | H22: =SUM(F22:G22) -> 780000
B23: Capital assets
C24: Land, improvements and construction in progess | F24: 36755816 | G24: 55140066 | H24: =SUM(F24:G24) -> 91895882
C25: Other capital assets, net of depreciation | F25: 348102094 | G25: 162342663 | H25: =SUM(F25:G25) -> 510444757
C27: Total Assets | F27: =SUM(F7:F25) -> 462272579 | G27: =SUM(G7:G25) -> 236248371 | H27: =SUM(H7:H25) -> 698520950
A29: LIABILITIES
B30: Accounts payable | F30: 19365175 | G30: 183135 | H30: =SUM(F30:G30) -> 19548310
B31: Claims payable | F31: 2113560 | G31: 542214 | H31: =SUM(F31:G31) -> 2655774
B32: Retainage payable | F32: 5463276 | H32: =SUM(F32:G32) -> 5463276
B33: Salaries and payroll deductions payable | F33: 1836737 | G33: 258326 | H33: =SUM(F33:G33) -> 2095063
B34: Customer deposits | G34: 1218437 | H34: =SUM(F34:G34) -> 1218437
B35: Accrued interest payable | F35: 435330 | G35: 160937 | H35: =SUM(F35:G35) -> 596267
B36: Advance collections | F36: 69188 | G36: 84879 | H36: =SUM(F36:G36) -> 154067
B37: Certificates of indebtedness | F37: 6760932 | H37: =SUM(F37:G37) -> 6760932
B38: Long term non-cuttent liabilities
C39: Due within one year | F39: 3915948 | G39: 855624 | H39: =SUM(F39:G39) -> 4771572
C40: Due in more than one year | F40: 37500615 | G40: 3656282 | H40: =SUM(F40:G40) -> 41156897
D42: Total Liabilities | F42: =SUM(F30:F40) -> 77460761 | G42: =SUM(G30:G40) -> 6959834 | H42: =SUM(H30:H40) -> 84420595
A44: NET ASSETS
B45: Invested in capital assets | F45: 347417372 | G45: 213189989 | H45: =SUM(F45:G45) -> 560607361
B46: Restricted for: | H46: =SUM(F46:G46) -> 0
C47: Capital projects | F47: 989788 | G47: 4715133 | H47: =SUM(F47:G47) -> 5704921
C48: Debt service | F48: 3497452 | G48: 2816068 | H48: =SUM(F48:G48) -> 6313520
C49: Federal programs | F49: 5370629 | H49: =SUM(F49:G49) -> 5370629
C50: Public safety | F50: 3586724 | H50: =SUM(F50:G50) -> 3586724
C51: Other purposes | F51: 2493118 | G51: 2 | H51: =SUM(F51:G51) -> 2493120
B52: Unrestricted | F52: 21456735 | G52: 8567345 | H52: =SUM(F52:G52) -> 30024080
C54: Total Net Assets | F54: =SUM(F45:F52) -> 384811818 | G54: =SUM(G45:G52) -> 229288537 | H54: =SUM(H44:H52) -> 614100355
C56: Total Liabilities and Net Assets | F56: =F54+F42 -> 462272579 | G56: =G54+G42 -> 236248371 | H56: =H54+H42 -> 698520950

Sheet St. Charles
D1: St. Charles Parish 2014 Statement of Net Assets
D2: Issued: December 31, 2014
H4: Primary Government
H5: Governmental Activities | I5: Business-Type Activities | J5: Total | K5: Component Units
A6: ASSETS
C7: Cash and cash equivalents | H7: 1704337 | I7: 112900 | J7: =SUM(H7:I7) -> 1817237 | K7: 134377
C8: Investments | H8: 91136263 | I8: 1483658 | J8: =SUM(H8:I8) -> 92619921 | K8: 8408106
C9: Receivables, net | H9: 29690795 | I9: 3203924 | J9: =SUM(H9:I9) -> 32894719 | K9: 13038573
C10: Due from other governments | H10: 4581936 | I10: 485838 | J10: =SUM(H10:I10) -> 5067774 | K10: 17148
C11: Due from primary government | J11: =SUM(H11:I11) -> 0 | K11: 6057
C12: Inventory | I12: 433829 | J12: =SUM(H12:I12) -> 433829 | K12: 1212929
C13: Prepaid fees | H13: 469726 | I13: 34771 | J13: =SUM(H13:I13) -> 504497 | K13: 506602
C14: Other assets | H14: 4270 | I14: 182 | J14: =SUM(H14:I14) -> 4452 | K14: 1733587
C15: Restricted assets | J15: =SUM(H15:I15) -> 0
D16: Cash and cash equivalents | I16: 87535 | J16: =SUM(H16:I16) -> 87535 | K16: 2657898
D17: Investments | I17: 6576622 | J17: =SUM(H17:I17) -> 6576622
C18: Capital assets, net | J18: =SUM(H18:I18) -> 0
D19: Land | H19: 10484811 | I19: 824777 | J19: =SUM(H19:I19) -> 11309588 | K19: 1590676
D20: Infrastructure | H20: 57582536 | J20: =SUM(H20:I20) -> 57582536
D21: Plant and equipment | H21: 95364805 | I21: 128195765 | J21: =SUM(H21:I21) -> 223560570 | K21: 29333127
D22: Construction in progress | H22: 34185224 | I22: 3944738 | J22: =SUM(H22:I22) -> 38129962 | K22: 7062725
C24: Total Assets | H24: =SUM(H7:H22) -> 325204703 | I24: =SUM(I7:I22) -> 145384539 | J24: =SUM(J7:J22) -> 470589242 | K24: =SUM(K7:K22) -> 65701805
A26: LIABILITIES
C27: Cash overdrafts | J27: =SUM(H27:I27) -> 0 | K27: 310998
C28: Accounts payable and other current liabilities | H28: 5459673 | I28: 1213267 | J28: =SUM(H28:I28) -> 6672940 | K28: 6443974
C29: Internal balances | H29: -608059 | I29: 608059 | J29: =SUM(H29:I29) -> 0
C30: Due to component units | H30: 6057 | J30: =SUM(H30:I30) -> 6057
C31: Due to other governments | H31: 254389 | J31: =SUM(H31:I31) -> 254389
C32: Interest payable | H32: 92047 | J32: =SUM(H32:I32) -> 92047
C33: Other liabilities and accruals | H33: 1039075 | I33: 270428 | J33: =SUM(H33:I33) -> 1309503 | K33: 3176757
C34: Liabilities payable from restricted assets | I34: 1521940 | J34: =SUM(H34:I34) -> 1521940
C35: Non-current liabilities | J35: =SUM(H35:I35) -> 0
D36: Amounts due within one year | H36: 3125000 | I36: 1616000 | J36: =SUM(H36:I36) -> 4741000 | K36: 3752843
D37: Amounts due beyond one year | H37: 27310425 | I37: 28549219 | J37: =SUM(H37:I37) -> 55859644 | K37: 47385158
D38: Multi-employer Pension Liability | K38: 4100757
D39: Other non-current liabilities | J39: =SUM(H39:I39) -> 0 | K39: 17452
D41: Total Liabilities | H41: =SUM(H27:H39) -> 36678607 | I41: =SUM(I27:I39) -> 33778913 | J41: =SUM(J27:J39) -> 70457520 | K41: =SUM(K27:K39) -> 65187939
A43: Deferred Inflows of Resources
B44: Advances | H44: 25868468 | I44: 0 | J44: =SUM(H44:I44) -> 25868468 | K44: 5521842
D45: Total deferred inflows of resources | H45: =H44 -> 25868468 | I45: =I44 -> 0 | J45: =J44 -> 25868468 | K45: =K44 -> 5521842
A47: NET ASSETS
B48: Invested in capital assets | H48: 181967376 | I48: 102800061 | J48: =SUM(H48:I48) -> 284767437 | K48: -2831576
B49: Restricted for: | J49: =SUM(H49:I49) -> 0
C50: Maintenance/operations | H50: 25773560 | J50: =SUM(H50:I50) -> 25773560
C51: Debt service | H51: 4848261 | I51: 2865761 | J51: =SUM(H51:I51) -> 7714022
C52: Capital projects | H52: 1280366 | I52: 6365219 | J52: =SUM(H52:I52) -> 7645585 | K52: 265722
C53: Special Revenues | H53: 11752537 | J53: =SUM(H53:I53) -> 11752537
B54: Unrestricted | H54: 37035528 | I54: -425415 | J54: =SUM(H54:I54) -> 36610113 | K54: -2442122
C56: Total Net Assets | H56: =SUM(H48:H54) -> 262657628 | I56: =SUM(I48:I54) -> 111605626 | J56: =SUM(J48:J54) -> 374263254 | K56: =SUM(K47:K54) -> -5007976
C58: Total Liabilities and Net Assets | H58: =H56+H41 -> 299336235 | I58: =I56+I41 -> 145384539 | J58: =J56+J41 -> 444720774 | K58: =K56+K41 -> 60179963

Sheet St. Helena 
D1: St. Helena Parish 2014 Statement of Net Assets
D2: Issued: December 31, 2014
H3: Primary Government | I3: Discretely Presented Component Units
H4: Governmental Activities | I4: St. Helena Parish Hospital Serv Dist 1 & Subsidiary | J4: Water Works Dist No. 2 of St. Helena Parish | K4: Other Component Units | L4: Total Component Units
A5: ASSETS
B6: Current Assets:
C7: Cash and cash equivalents | H7: 4446922 | I7: 1574249 | J7: 734710 | K7: 198201 | L7: =SUM(I7:K7) -> 2507160
C8: Investments | H8: 986526 | K8: 20100 | L8: =SUM(I8:K8) -> 20100
C9: Receivables, net | H9: 2817120 | I9: 3395889 | J9: 136063 | K9: 358452 | L9: =SUM(I9:K9) -> 3890404
C10: Due from component units | L10: =SUM(I10:K10) -> 0
C11: Inventory | I11: 361993 | J11: 42724 | L11: =SUM(I11:K11) -> 404717
C12: Prepaid insurance and other assets | H12: 99350 | I12: 87961 | J12: 6377 | K12: 7055 | L12: =SUM(I12:K12) -> 101393
B13: Total current assets | H13: =SUM(H7:H12) -> 8349918 | I13: =SUM(I7:I12) -> 5420092 | J13: =SUM(J7:J12) -> 919874 | K13: =SUM(K7:K12) -> 583808 | L13: =SUM(L7:L12) -> 6923774
B15: Restricted assets:
C16: Restricted cash and cash equivalents | H16: 431850 | I16: 387473 | J16: 563911 | L16: =SUM(I16:K16) -> 951384
B17: Total restricted assets | H17: =SUM(H16) -> 431850 | I17: =SUM(I16) -> 387473 | J17: =SUM(J16) -> 563911 | K17: =SUM(K16) -> 0 | L17: =SUM(L16) -> 951384
B19: Long term assets:
C20: Investments
B21: Total long term assets
B23: Capital assets:
C24: Land | H24: 235036 | J24: 47631 | L24: =SUM(I24:K24) -> 47631
C25: Capital assets, net | H25: 17632429 | I25: 6219874 | J25: 6138340 | K25: 900259 | L25: =SUM(I25:K25) -> 13258473
B26: Total capital assets | H26: =SUM(H24:H25) -> 17867465 | I26: =SUM(I24:I25) -> 6219874 | J26: =SUM(J24:J25) -> 6185971 | K26: =SUM(K24:K25) -> 900259 | L26: =SUM(L24:L25) -> 13306104
C28: Total Assets | H28: =SUM(H13+H17+H21+H26) -> 26649233 | I28: =I26+I21+I17+I13 -> 12027439 | J28: =J26+J21+J17+J13 -> 7669756 | K28: =K26+K21+K17+K13 -> 1484067 | L28: =L26+L21+L17+L13 -> 21181262
A30: LIABILITIES
B31: Current liabilities:
C32: Accounts payable | H32: 914891 | I32: 569271 | J32: 26385 | K32: 7706 | L32: =SUM(I32:K32) -> 603362
C33: Other accrued payables | H33: 62229 | I33: 486822 | J33: 177586 | K33: 8985 | L33: =SUM(I33:K33) -> 673393
C34: Accrued interest on long term indebtedness | H34: 31378 | J34: 90769 | K34: 3582 | L34: =SUM(I34:K34) -> 94351
C35: Customer deposits | J35: 90455 | L35: =SUM(I35:K35) -> 90455
C36: Current portion of long term indebtedness
D37: Bonds payable | H37: 428726 | I37: 399830 | J37: 97879 | K37: 31036 | L37: =SUM(I37:K37) -> 528745
D38: Capital leases | H38: 134903 | I38: 51138 | L38: =SUM(I38:K38) -> 51138
B39: Total current liabilities: | H39: =SUM(H32:H38) -> 1572127 | I39: =SUM(I32:I38) -> 1507061 | J39: =SUM(J32:J38) -> 483074 | K39: =SUM(K32:K38) -> 51309 | L39: =SUM(L32:L38) -> 2041444
B41: Long term liabilities:
C42: Bonds payable | H42: 1865000 | I42: 3975896 | J42: 3100906 | K42: 202827 | L42: =SUM(I42:K42) -> 7279629
C43: Capital leases | H43: 261857 | I43: 149859 | L43: =SUM(I43:K43) -> 149859
C44: Compensated absences payable | H44: 308432 | L44: =SUM(I44:K44) -> 0
C45: Unfunded net other post employment benefit obligations | H45: 1070146 | L45: =SUM(I45:K45) -> 0
B46: Total long term liabilities | H46: =SUM(H42:H45) -> 3505435 | I46: =SUM(I42:I45) -> 4125755 | J46: =SUM(J42:J45) -> 3100906 | K46: =SUM(K42:K45) -> 202827 | L46: =SUM(L42:L45) -> 7429488
D48: Total Liabilities | H48: =H39+H46 -> 5077562 | I48: =I39+I46 -> 5632816 | J48: =J39+J46 -> 3583980 | K48: =K39+K46 -> 254136 | L48: =L39+L46 -> 9470932
A50: NET ASSETS
B51: Net investment in capital assets | H51: 15145601 | I51: 2896404 | J51: 2987186 | K51: 662814 | L51: =SUM(I51:K51) -> 6546404
B52: Restricted for: | L52: =SUM(I52:K52) -> 0
C53: Debt service | H53: 41273 | J53: 272937 | K53: 54163 | L53: =SUM(I53:K53) -> 327100
C54: Capital projects | H54: 261754 | L54: =SUM(I54:K54) -> 0
C55: Other purposes | H55: 6851274 | L55: =SUM(I55:K55) -> 0
B56: Unrestricted | H56: -728231 | I56: 3498219 | J56: 825653 | K56: 512954 | L56: =SUM(I56:K56) -> 4836826
C58: Total Net Assets | H58: =SUM(H51:H56) -> 21571671 | I58: =SUM(I51:I56) -> 6394623 | J58: =SUM(J51:J56) -> 4085776 | K58: =SUM(K51:K56) -> 1229931 | L58: =SUM(L50:L56) -> 11710330
C60: Total Liabilities and Net Assets | H60: =SUM(H58+H48) -> 26649233 | I60: =SUM(I48+I58) -> 12027439 | J60: =SUM(J48+J58) -> 7669756 | K60: =SUM(K48+K58) -> 1484067 | L60: =SUM(L58+L48) -> 21181262

Sheet St. James
C1: St. James Parish 2014 Statement of Net Assets
C2: Issued: December 31, 2014
G4: Primary Government | J4: Component Unit
G5: Governmental Activities | H5: Business-Type Activities | I5: Total | J5: St. James Parish Hospital
A6: ASSETS
B7: Cash and cash equivalents | G7: 22660670 | H7: 6548899 | I7: =SUM(G7:H7) -> 29209569 | J7: 8648856
B8: Investments | G8: 10808344 | H8: 2003210 | I8: =SUM(G8:H8) -> 12811554
B9: Receivables (net of allowance for uncollectibles) | G9: 23579733 | H9: 1196672 | I9: =SUM(G9:H9) -> 24776405 | J9: 3558537
B10: Notes receivable:
C11: Due within one year | G11: 510000 | I11: =SUM(G11:H11) -> 510000
C12: Due in more than one year | G12: 1080000 | I12: =SUM(G12:H12) -> 1080000
C13: Estimated third-party payor settlements | J13: 101683
B14: Internal balance | G14: -12842 | H14: 12842 | I14: =SUM(G14:H14) -> 0
B15: Inventories | G15: 34391 | H15: 261482 | I15: =SUM(G15:H15) -> 295873 | J15: 357106
B16: Prepaid items | G16: 254465 | H16: 9591 | I16: =SUM(G16:H16) -> 264056
B17: Restricted assets
C18: Cash and cash equivalents | H18: 503398 | I18: =SUM(G18:H18) -> 503398
C19: Held by trustee for debt service | J19: 1391528
C20: Internally designated for capital acquisition | J20: 8474392
B21: Capital assets (net of accumulated depreciation) | G21: 63127363 | H21: 13136113 | I21: =SUM(G21:H21) -> 76263476 | J21: 21560281
B22: Other assets, net | H22: 245 | I22: =SUM(G22:H22) -> 245 | J22: 574989
B24: Total Assets | G24: =SUM(G7:G21) -> 122042124 | H24: =SUM(H7:H22) -> 23672452 | I24: =SUM(I7:I22) -> 145714576 | J24: =SUM(J7:J22) -> 44667372
A25: DEFERRED OUTFLOWS OF RESOURCES
C26: Deferred charge on refunding | G26: 163636 | I26: =SUM(G26:H26) -> 163636
A28: LIABILITIES
B29: Accounts payable and other current liabilities | G29: 4907605 | H29: 317658 | I29: =SUM(G29:H29) -> 5225263 | J29: 798354
B30: Other liabilities | G30: 125909 | I30: =SUM(G30:H30) -> 125909
B31: Accrued expenses | G31: 1285071 | H31: 141115 | I31: =SUM(G31:H31) -> 1426186 | J31: 886061
B32: Liabilities payable from restricted assets | H32: 478845 | I32: =SUM(G32:H32) -> 478845
B33: Long-term liabilities: | I33: =SUM(G33:H33) -> 0
D34: Due within one year | G34: 1538866 | H34: 57287 | I34: =SUM(G34:H34) -> 1596153 | J34: 766538
D35: Due in more than one year | G35: 9012522 | H35: 433809 | I35: =SUM(G35:H35) -> 9446331 | J35: 16281099
C37: Total Liabilities | G37: =SUM(G29:G35) -> 16869973 | H37: =SUM(H29:H35) -> 1428714 | I37: =SUM(I29:I35) -> 18298687 | J37: =SUM(J29:J35) -> 18732052
A39: NET ASSETS
B40: Net invested in capital assets | G40: 57285911 | H40: 13136113 | I40: =SUM(G40:H40) -> 70422024 | J40: 6093216
B41: Restricted for:
C42: General government | G42: 7253937 | I42: =SUM(G42:H42) -> 7253937
C43: Culture and recreation | G43: 5033120 | I43: =SUM(G43:H43) -> 5033120
C44: Debt service | G44: 1705826 | I44: =SUM(G44:H44) -> 1705826 | J44: 1391528
C45: Capital projects | G45: 1059444 | I45: =SUM(G45:H45) -> 1059444
C46: Health and welfare | G46: 6024835 | I46: =SUM(G46:H46) -> 6024835
C47: Highways and streets | G47: 4924452 | I47: =SUM(G47:H47) -> 4924452
C48: Public safety | G48: 13110874 | I48: =SUM(G48:H48) -> 13110874
C49: Sanitation | G49: 2942312 | I49: =SUM(G49:H49) -> 2942312
C50: Group health insurance claims | G50: 1316468 | I50: =SUM(G50:H50) -> 1316468
B51: Unrestricted | G51: 4678608 | H51: 9107625 | I51: =SUM(G51:H51) -> 13786233 | J51: 18450576
B53: Total Net Assets | G53: =SUM(G40:G52) -> 105335787 | H53: =SUM(H40:H51) -> 22243738 | I53: =SUM(I39:I51) -> 127579525 | J53: =SUM(J39:J51) -> 25935320
B55: Total Liabilities and Net Assets | G55: =G53+G37 -> 122205760 | H55: =H53+H37 -> 23672452 | I55: =I53+I37 -> 145878212 | J55: =J53+J37 -> 44667372

Sheet St. John the Baptist
C1: St. John the Baptist Parish 2014 Statement of Net Assets
C2: Issued: December 31, 2014
G4: Primary Government | J4: Component Unit
G5: Governmental Activities | H5: Business-Type Activities | I5: Total | J5: Library
A6: ASSETS
B7: Cash and cash equivalents | G7: 68703620 | H7: 1206480 | I7: =SUM(G7:H7) -> 69910100 | J7: 5144173
B8: Inventory, at cost | H8: 434054 | I8: =SUM(G8:H8) -> 434054
B9: Receivables (net of allowances) | I9: =SUM(G9:H9) -> 0
C10: Accounts | G10: 331747 | H10: 2634157 | I10: =SUM(G10:H10) -> 2965904
C11: Ad valorem taxes | G11: 11498456 | I11: =SUM(G11:H11) -> 11498456 | J11: 4237599
C12: Sales and use taxes | G12: 3377260 | I12: =SUM(G12:H12) -> 3377260
C13: Other | G13: 172605 | I13: =SUM(G13:H13) -> 172605 | J13: 61625
B14: Due from other governments | G14: 3096282 | H14: 300632 | I14: =SUM(G14:H14) -> 3396914
B15: Prepaid items | G15: 150582 | H15: 99504 | I15: =SUM(G15:H15) -> 250086
B16: Restricted assets | H16: 1170454 | I16: =SUM(G16:H16) -> 1170454
B17: Internal balances | G17: 1200568 | H17: -1200568 | I17: =SUM(G17:H17) -> 0
B18: Capital assets not being depreciated | G18: 15682406 | H18: 3166345 | I18: =SUM(G18:H18) -> 18848751
B19: Capital assets being depreciated | I19: =SUM(G19:H19) -> 0
C20: (net of accumulated depreciation) | G20: 70495237 | H20: 124516843 | I20: =SUM(G20:H20) -> 195012080 | J20: 5249777
B22: Total Assets | G22: =SUM(G7:G20) -> 174708763 | H22: =SUM(H7:H20) -> 132327901 | I22: =SUM(I7:I20) -> 307036664 | J22: =SUM(J7:J20) -> 14693174
A24: LIABILITIES
B25: Accounts, salaries, and other payables | G25: 4076912 | H25: 2570268 | I25: =SUM(G25:H25) -> 6647180 | J25: 29679
B26: Contracts payable | G26: 942369 | I26: =SUM(G26:H26) -> 942369
B27: Due to other governments | G27: 21935 | I27: =SUM(G27:H27) -> 21935
B28: Deposits due others | H28: 1285479 | I28: =SUM(G28:H28) -> 1285479
B29: Other liabilities | H29: 119313 | I29: =SUM(G29:H29) -> 119313 | J29: 180159
B30: Interest payable | G30: 526136 | H30: 9661 | I30: =SUM(G30:H30) -> 535797
B31: Noncurrent liabilities: | I31: =SUM(G31:H31) -> 0
C32: Due within one yeear | G32: 5187032 | H32: 279000 | I32: =SUM(G32:H32) -> 5466032
C33: Due in more than one year | G33: 84501977 | H33: 4575868 | I33: =SUM(G33:H33) -> 89077845 | J33: 1084720
C35: Total Liabilities | G35: =SUM(G25:G33) -> 95256361 | H35: =SUM(H25:H33) -> 8839589 | I35: =SUM(I25:I33) -> 104095950 | J35: =SUM(J25:J33) -> 1294558
A37: NET ASSETS
B38: Net investment in capital assets | G38: 6020921 | H38: 122828320 | I38: =SUM(G38:H38) -> 128849241 | J38: 5249777
B39: Restricted for:
C40: Special revenue | G40: 29172521 | I40: =SUM(G40:H40) -> 29172521
C41: Debt service | G41: 14744069 | H41: 421500 | I41: 15165569
C42: Capital projects | I42: =SUM(G42:H42) -> 0
C43: Customer deposits | H43: 115025 | I43: =SUM(G43:H43) -> 115025
C44: Endowment | J44: 5000
B45: Unrestricted | G45: 29514891 | H45: 123467 | I45: =SUM(G45:H45) -> 29638358 | J45: 8143839
B47: Total Net Assets | G47: =SUM(G38:G45) -> 79452402 | H47: =SUM(H38:H45) -> 123488312 | I47: =SUM(I38:I45) -> 202940714 | J47: =SUM(J37:J45) -> 13398616
B49: Total Liabilities and Net Assets | G49: =G47+G35 -> 174708763 | H49: =H47+H35 -> 132327901 | I49: =I47+I35 -> 307036664 | J49: =J47+J35 -> 14693174

Sheet St. Landry
D1: St. Landry Parish 2014 Statement of Net Assets
D2: Issued: December 31, 2014
H4: Governmental Activities | I4: Component Units | J4: Total
A5: ASSETS
B6: Current Assets
C7: Cash and interest-bearing deposits | H7: 1580783 | I7: 1423374 | J7: =SUM(H7:I7) -> 3004157
C8: Receivables, net | H8: 6405899 | I8: 596201 | J8: =SUM(H8:I8) -> 7002100
C9: Prepaid expenditures | H9: 239518 | J9: =SUM(H9:I9) -> 239518
C10: Due from agency funds | H10: 285099 | J10: =SUM(H10:I10) -> 285099
C11: Due from component units | H11: 4555 | J11: =SUM(H11:I11) -> 4555
C12: Due from other governments | H12: 140373 | J12: =SUM(H12:I12) -> 140373
C13: Due from primary government | I13: 6389 | J13: =SUM(H13:I13) -> 6389
C15: Total Current Assets | H15: =SUM(H7:H13) -> 8656227 | I15: =SUM(I7:I13) -> 2025964 | J15: =SUM(J7:J13) -> 10682191
B17: Noncurrent assets
C18: Cash and cash equivalents- restricted | H18: 3232030 | J18: =SUM(H18:I18) -> 3232030
C19: Investments-restricted | H19: 56180653 | J19: =SUM(H19:I19) -> 56180653
C20: Capital assets, net | H20: 18081147 | I20: 2747842 | J20: =SUM(H20:I20) -> 20828989
C22: Total Assets | H22: =SUM(H15:H21) -> 86150057 | I22: =SUM(I15:I20) -> 4773806 | J22: =SUM(J15:J20) -> 90923863
A24: LIABILITIES
B25: Current
C26: Bank overdrafts | H26: 19011 | J26: =SUM(H26:I26) -> 19011
C27: Accounts payable | H27: 4339697 | I27: 158043 | J27: =SUM(H27:I27) -> 4497740
C28: Accrued expenses | H28: 360414 | I28: 1870 | J28: =SUM(H28:I28) -> 362284
C29: Accrued interest | H29: 96612 | I29: 20725 | J29: =SUM(H29:I29) -> 117337
C30: Bonds payable | H30: 3074167 | I30: 85000 | J30: =SUM(H30:I30) -> 3159167
C31: Unearned revenue | H31: 4387 | J31: =SUM(H31:I31) -> 4387
C32: Unamortized premium | H32: 109951 | J32: =SUM(H32:I32) -> 109951
C33: Compensated absences | H33: 141666 | I33: 8744 | J33: =SUM(H33:I33) -> 150410
C34: Due to agency funds | H34: 95000 | J34: =SUM(H34:I34) -> 95000
C35: Due to component units | H35: 6389 | J35: =SUM(H35:I35) -> 6389
C36: Due primary government | I36: 4555 | J36: =SUM(H36:I36) -> 4555
D38: Total Current Liabilities | H38: =SUM(H26:H35) -> 8247294 | I38: =SUM(I25:I36) -> 278937 | J38: =SUM(J26:J36) -> 8526231
B40: Noncurrent
C41: Claims payable | H41: 171605 | J41: =SUM(H41:I41) -> 171605
C42: Bonds payable | H42: 58619667 | I42: 1090000 | J42: =SUM(H42:I42) -> 59709667
C43: Unamortized premium | H43: 1429368 | J43: =SUM(H43:I43) -> 1429368
D45: Total Noncurrent Liabilities | H45: =SUM(H41:H43) -> 60220640 | I45: =SUM(I41:I42) -> 1090000 | J45: =SUM(J41:J43) -> 61310640
D47: Total Liabilities | H47: =SUM(H38+H45) -> 68467934 | I47: =SUM(I38+I45) -> 1368937 | J47: =SUM(J38+J45) -> 69836871
A49: NET ASSETS
B50: Net investment in capital assets | H50: 9000399 | I50: 1572842 | J50: =SUM(H50:I50) -> 10573241
B51: Restricted for debt service | H51: 33991 | J51: =SUM(H51:I51) -> 33991
B52: Restricted- roads | H52: 2611823 | J52: =SUM(H52:I52) -> 2611823
B53: Restricted-other | H53: 3490783 | J53: =SUM(H53:I53) -> 3490783
B54: Unrestricted | H54: 2545127 | I54: 1832027 | J54: =SUM(H54:I54) -> 4377154
C56: Total Net Assets | H56: =SUM(H50:H54) -> 17682123 | I56: =SUM(I50:I54) -> 3404869 | J56: =SUM(J49:J54) -> 21086992
C58: Total Liabilities and Net Assets | H58: =H56+H47 -> 86150057 | I58: =I56+I47 -> 4773806 | J58: =J56+J47 -> 90923863

Sheet St. Martin
D1: St. Martin Parish 2014 Statement of Net Assets
D2: Issued: December 31, 2014
H3: Primary Government
H4: Governmental Activities | I4: Business-Type Activities | J4: Total
A5: ASSETS
C6: Cash and interest bearing deposits | H6: 26425600 | J6: =SUM(H6:I6) -> 26425600
C7: Receivables | H7: 12465808 | I7: 385862 | J7: =SUM(H7:I7) -> 12851670
C8: Internal balances | H8: 232915 | J8: =SUM(H8:I8) -> 232915
C9: Due from other governments | H9: 138381 | J9: =SUM(H9:I9) -> 138381
C10: Capital assets:
D11: Non-depreciable | H11: 2773258 | J11: =SUM(H11:I11) -> 2773258
D12: Depreciable (net) | H12: 67960731 | J12: =SUM(H12:I12) -> 67960731
C14: Total Assets | H14: =SUM(H6:H12) -> 109996693 | I14: =SUM(I6:I12) -> 385862 | J14: =SUM(J6:J12) -> 110382555
A16: LIABILITIES
C17: Accounts payable | H17: 1134563 | I17: 207713 | J17: =SUM(H17:I17) -> 1342276
C18: Internal balances | I18: 232915 | J18: =SUM(H18:I18) -> 232915
C19: Accrued interest payable | H19: 253588 | J19: =SUM(H19:I19) -> 253588
C20: Unearned revenues | H20: 24101 | J20: =SUM(H20:I20) -> 24101
C21: Due to other governments | H21: 89704 | J21: =SUM(H21:I21) -> 89704
C22: Other liabilities | H22: 273547 | I22: 2354 | J22: =SUM(H22:I22) -> 275901
C23: Long-term liabilities:
D24: Bonds payable, due within one year | H24: 1894000 | J24: =SUM(H24:I24) -> 1894000
D25: Bonds payable, due in more than one year | H25: 21010000 | J25: =SUM(H25:I25) -> 21010000
D26: Capital leases payable, due within one year | H26: 188692 | J26: =SUM(H26:I26) -> 188692
D27: Capital leases payable, due in more than one year | H27: 502130 | J27: =SUM(H27:I27) -> 502130
D28: OPEB liability-due in more than one year | H28: 6691300 | J28: =SUM(H28:I28) -> 6691300
D29: Compensated absences payable | H29: 465766 | J29: =SUM(H29:I29) -> 465766
D31: Total Liabilities | H31: =SUM(H17:H29) -> 32527391 | I31: =SUM(I17:I29) -> 442982 | J31: =SUM(J17:J29) -> 32970373
A33: NET ASSETS
B34: Net investment in capital assets | H34: 46885579 | J34: =SUM(H34:I34) -> 46885579
B35: Restricted for:
C36: Debt service | H36: 5555223 | J36: =SUM(H36:I36) -> 5555223
C37: Other purposes | H37: 26112175 | I37: 30142 | J37: =SUM(H37:I37) -> 26142317
B38: Unrestricted (deficit) | H38: -1083675 | I38: -87262 | J38: =SUM(H38:I38) -> -1170937
C40: Total Net Assets | H40: =SUM(H34:H38) -> 77469302 | I40: =SUM(I34:I38) -> -57120 | J40: =SUM(J33:J38) -> 77412182
C42: Total Liabilities and Net Assets | H42: =H40+H31 -> 109996693 | I42: =I40+I31 -> 385862 | J42: =J40+J31 -> 110382555

Sheet St. Mary
D1: St. Mary Parish 2014 Statement of Net Assets
D2: Issued: December 31, 2013
H4: Primary Government
H5: Governmental Activities | I5: Business-type Activities | J5: Total
A6: ASSETS
B7: Current Assets
C8: Cash and cash equivalents | H8: 3457312 | I8: 1191322 | J8: =SUM(H8:I8) -> 4648634
C9: Investments | H9: 13074756 | I9: 1987532 | J9: =SUM(H9:I9) -> 15062288
C10: Receivables (net of allowances for uncollectibles) | H10: 892554 | I10: 569047 | J10: =SUM(H10:I10) -> 1461601
C11: Due from component units | H11: 2498938 | I11: 1898 | J11: =SUM(H11:I11) -> 2500836
C12: Due from other governments | H12: 11214501 | I12: 101291 | J12: =SUM(H12:I12) -> 11315792
C13: Other assets | H13: 71914 | J13: =SUM(H13:I13) -> 71914
C14: Internal balances | H14: -6864574 | I14: 6864574 | J14: =SUM(H14:I14) -> 0
C16: Total Current Assets | H16: =SUM(H8:H14) -> 24345401 | I16: =SUM(I8:I14) -> 10715664 | J16: =SUM(J8:J14) -> 35061065
B18: Noncurrent Assets
C19: Restricted cash | I19: 2712351 | J19: =SUM(H19:I19) -> 2712351
C20: Restricted investments | I20: 844081 | J20: =SUM(H20:I20) -> 844081
J21: =SUM(H21:I21) -> 0
C22: Total restricted assets | I22: =SUM(I19:I20) -> 3556432 | J22: =SUM(J19:J20) -> 3556432
B24: Capital assets
C25: Land and improvements | H25: 1870876 | I25: 3802599 | J25: =SUM(H25:I25) -> 5673475
C26: Buildings, net of accumulated depreciation | H26: 10048231 | I26: 142950 | J26: =SUM(H26:I26) -> 10191181
C27: Improvements other than buildings, net of | J27: =SUM(H27:I27) -> 0
D28: accumulated depreciation | H28: 15030277 | I28: 15393907 | J28: =SUM(H28:I28) -> 30424184
C29: Equipment and furniture, net of accumulated | J29: =SUM(H29:I29) -> 0
D30: depreciation | H30: 2210150 | I30: 1944417 | J30: =SUM(H30:I30) -> 4154567
C31: Infrastructure, net of accumulated depreciation | H31: 75560523 | J31: =SUM(H31:I31) -> 75560523
C32: Construction in progress | H32: 2899550 | I32: 50068 | J32: =SUM(H32:I32) -> 2949618
C34: Total Noncurrent Assets | H34: =SUM(H25:H32) -> 107619607 | I34: =SUM(I25:I32) -> 21333941 | J34: =SUM(J25:J32) -> 128953548
C36: Total Assets | H36: =SUM(H34+H22+H16) -> 131965008 | I36: =SUM(I34+I22+I16) -> 35606037 | J36: =SUM(J34+J22+J16) -> 167571045
A38: Gain on refunding | I38: 220000 | J38: =I38 -> 220000
C39: Total deferred outflows of resources
C41: Total assets and deferred outflows of resources | H41: =H36 -> 131965008 | I41: =SUM(I36:I38) -> 35826037 | J41: =SUM(J36:J38) -> 167791045
A43: LIABILITIES
B44: Current liabilities
C45: Accounts payable | H45: 1474397 | I45: 602961 | J45: =SUM(H45:I45) -> 2077358
C46: Contracts payable | H46: 1236225 | J46: =SUM(H46:I46) -> 1236225
C47: Retainage payable | H47: 241045 | I47: 7690 | J47: =SUM(H47:I47) -> 248735
C48: Accrued liabilities | H48: 540085 | J48: =SUM(H48:I48) -> 540085
C49: Due to component units | H49: 100000 | J49: =SUM(H49:I49) -> 100000
C50: Due to other governments | H50: 104452 | J50: =SUM(H50:I50) -> 104452
C51: Accrued interest payable | H51: 193963 | J51: =SUM(H51:I51) -> 193963
C52: Current portion of long-term debt | H52: 2626000 | I52: 730000 | J52: =SUM(H52:I52) -> 3356000
D54: Total Current Liabilities | H54: =SUM(H45:H52) -> 6516167 | I54: =SUM(I45:I52) -> 1340651 | J54: =SUM(J45:J52) -> 7856818
B56: Noncurrent liabilities
C57: Other post-employment benefits | H57: 6753900 | I57: 1032600 | J57: =SUM(H57:I57) -> 7786500
C58: Compensated absences | H58: 198000 | J58: =SUM(H58:I58) -> 198000
C59: Long term debt | H59: 18236000 | I59: 12161980 | J59: =SUM(H59:I59) -> 30397980
C60: Landfill closure costs and post-closure care costs | I60: 3876000 | J60: =SUM(H60:I60) -> 3876000
D62: Total Noncurrent Liabilities | H62: =SUM(H56:H60) -> 25187900 | I62: =SUM(I56:I60) -> 17070580 | J62: =SUM(J56:J60) -> 42258480
D64: Total Liabilities | H64: =SUM(H54+H62) -> 31704067 | I64: =SUM(I54+I62) -> 18411231 | J64: =SUM(J54+J62) -> 50115298
A66: NET ASSETS
B67: Investment in capital assets | H67: 86318562 | I67: 8441961 | J67: =SUM(H67:I67) -> 94760523
B68: Restricted for:
C69: Debt service | H69: 2391405 | I69: 938140 | J69: =SUM(H69:I69) -> 3329545
C70: Other Purposes | H70: 10717283 | I70: -1301326 | J70: =SUM(H70:I70) -> 9415957
B71: Unrestricted | H71: 833691 | I71: 9336031 | J71: =SUM(H71:I71) -> 10169722
C73: Total Net Assets | H73: =SUM(H67:H71) -> 100260941 | I73: =SUM(I67:I71) -> 17414806 | J73: =SUM(J67:J71) -> 117675747
C75: Total Liabilities and Net Assets | H75: =SUM(H64+H73) -> 131965008 | I75: =SUM(I64+I73) -> 35826037 | J75: =SUM(J64+J73) -> 167791045

Sheet St. Tammany
D1: St.Tammany Parish 2014 Statement of Net Assets
D2: Issued: December 31, 2014
H4: Primary Government
H5: Governmental Activities | I5: Business-type Activities | J5: Total | K5: Component Units | L5: Total
A6: ASSETS
C7: Cash and cash equivalents | H7: 32231916 | I7: 1640973 | J7: =SUM(H7:I7) -> 33872889 | K7: 33507195 | L7: =SUM(J7:K7) -> 67380084
C8: Investments | H8: 139982794 | I8: 10921541 | J8: =SUM(H8:I8) -> 150904335 | K8: 17101546 | L8: =SUM(J8:K8) -> 168005881
C9: Receivables (net of allowances for uncollectibles) | H9: 52368483 | I9: 896138 | J9: =SUM(H9:I9) -> 53264621 | K9: 63546893 | L9: =SUM(J9:K9) -> 116811514
C10: Due from primary government/component units | H10: 360844 | J10: 360844 | K10: 8926010 | L10: =SUM(J10:K10) -> 9286854
C11: Inventory | J11: =SUM(H11:I11) -> 0 | K11: 2240748 | L11: =SUM(J11:K11) -> 2240748
C12: Prepaid items | H12: 241027 | J12: =SUM(H12:I12) -> 241027 | K12: 863953 | L12: =SUM(J12:K12) -> 1104980
C13: Restricted assets | H13: 19014325 | I13: 4335875 | J13: =SUM(H13:I13) -> 23350200 | K13: 3324852 | L13: =SUM(J13:K13) -> 26675052
C14: Other assets | H14: 2120 | I14: 13159 | J14: =SUM(H14:I14) -> 15279 | K14: 179150 | L14: =SUM(J14:K14) -> 194429
C15: Capital assets: | J15: =SUM(H15:I15) -> 0 | L15: =SUM(J15:K15) -> 0
D16: Land. improvements and construction in progress | H16: 117032131 | I16: 1704839 | J16: =SUM(H16:I16) -> 118736970 | K16: 12895127 | L16: =SUM(J16:K16) -> 131632097
D17: Other capital assets, net of depreciation | H17: 314057724 | I17: 37370127 | J17: =SUM(H17:I17) -> 351427851 | K17: 82748732 | L17: =SUM(J17:K17) -> 434176583
C19: Total Assets | H19: =SUM(H7:H17) -> 675291364 | I19: =SUM(I7:I17) -> 56882652 | J19: =SUM(J7:J17) -> 732174016 | K19: =SUM(K7:K17) -> 225334206 | L19: =SUM(L7:L17) -> 957508222
B21: Deferred outflows of resources
C22: Deferred charges on refunding | H22: 4730418 | J22: =SUM(H22) -> 4730418 | K22: 206138 | L22: =SUM(J22:K22) -> 4936556
C24: Total Deferred Outflows of Resources | H24: =SUM(H21:H22) -> 4730418 | I24: =SUM(I22) -> 0 | J24: =SUM(J22) -> 4730418 | K24: =SUM(K22) -> 206138 | L24: =SUM(L22) -> 4936556
A26: LIABILITIES
C27: Accounts, salaries, and other payables | H27: 22029341 | I27: 830397 | J27: =SUM(H27:I27) -> 22859738 | K27: 4220526 | L27: =SUM(J27:K27) -> 27080264
C28: Payable from restricted assets | J28: =SUM(H28:I28) -> 0 | K28: 134355 | L28: =SUM(J28:K28) -> 134355
C29: Due to primary government/component units | H29: 8842090 | J29: =SUM(H29:I29) -> 8842090 | K29: 444764 | L29: =SUM(J29:K29) -> 9286854
C30: Unearned revenues | H30: 3300100 | J30: =SUM(H30:I30) -> 3300100 | K30: 361213 | L30: =SUM(J30:K30) -> 3661313
C31: Other liabilities | H31: 1999849 | I31: 1320805 | J31: =SUM(H31:I31) -> 3320654 | K31: 46108 | L31: =SUM(J31:K31) -> 3366762
C32: Interest payable | H32: 565788 | I32: 821487 | J32: =SUM(H32:I32) -> 1387275 | K32: 555632 | L32: =SUM(J32:K32) -> 1942907
C33: Non-current liabilities: | J33: =SUM(H33:I33) -> 0 | L33: =SUM(J33:K33) -> 0
D34: Due within one year | H34: 8387911 | I34: 725000 | J34: =SUM(H34:I34) -> 9112911 | K34: 6941025 | L34: =SUM(J34:K34) -> 16053936
D35: Due in more than one year | H35: 92368011 | I35: 40700586 | J35: =SUM(H35:I35) -> 133068597 | K35: 37265919 | L35: =SUM(J35:K35) -> 170334516
D37: Total Liabilities | H37: =SUM(H27:H35) -> 137493090 | I37: =SUM(I27:I35) -> 44398275 | J37: =SUM(J27:J35) -> 181891365 | K37: =SUM(K27:K35) -> 49969542 | L37: =SUM(L27:L35) -> 231860907
A39: NET ASSETS
B40: Net investment in capital assets | H40: 361538436 | I40: -2350620 | J40: =SUM(H40:I40) -> 359187816 | K40: 63776877 | L40: =SUM(J40:K40) -> 422964693
B41: Restricted for: | J41: =SUM(H41:I41) -> 0 | L41: =SUM(J41:K41) -> 0
C42: Capital projects | H42: 9340801 | I42: 595421 | J42: =SUM(H42:I42) -> 9936222 | L42: =SUM(J42:K42) -> 9936222
C43: Culture and recreation | H43: 136976 | J43: =SUM(H43:I43) -> 136976 | L43: =SUM(J43:K43) -> 136976
C44: Debt service | H44: 10013794 | I44: 3740454 | J44: =SUM(H44:I44) -> 13754248 | K44: 4226517 | L44: =SUM(J44:K44) -> 17980765
C45: Economic development | H45: 275109 | J45: =SUM(H45:I45) -> 275109 | L45: =SUM(J45:K45) -> 275109
C46: Health and welfare | H46: 9241870 | J46: =SUM(H46:I46) -> 9241870 | L46: =SUM(J46:K46) -> 9241870
C47: Judicial | H47: 11104623 | J47: =SUM(H47:I47) -> 11104623 | L47: =SUM(J47:K47) -> 11104623
C48: Lighting districts | H48: 4799157 | J48: =SUM(H48:I48) -> 4799157 | L48: =SUM(J48:K48) -> 4799157
C49: Public safety | H49: 13229758 | J49: =SUM(H49:I49) -> 13229758 | L49: =SUM(J49:K49) -> 13229758
C50: Roads, bridges and drainage | H50: 86811013 | J50: =SUM(H50:I50) -> 86811013 | L50: =SUM(J50:K50) -> 86811013
C51: Transit | H51: 550762 | J51: =SUM(H51:I51) -> 550762 | L51: =SUM(J51:K51) -> 550762
B52: Unrestricted | H52: 35486393 | I52: 10499122 | J52: =SUM(H52:I52) -> 45985515 | K52: 107567408 | L52: =SUM(J52:K52) -> 153552923
C54: Total Net Assets | H54: =SUM(H40:H52) -> 542528692 | I54: =SUM(I40:I52) -> 12484377 | J54: =SUM(J40:J52) -> 555013069 | K54: =SUM(K40:K52) -> 175570802 | L54: =SUM(L40:L52) -> 730583871
C56: Total Liabilities and Net Assets | H56: =H54+H37 -> 680021782 | I56: =I54+I37 -> 56882652 | J56: =J54+J37 -> 736904434 | K56: =K54+K37 -> 225540344 | L56: =L54+L37 -> 962444778

Sheet Tangipahoa
D1: Tangipahoa Parish 2014 Statement of Net Assets
D2: Issued: December 31, 2014
H4: Primary Government | I4: Component Units
H5: Governmental Activities | I5: Governmental Activities
A6: ASSETS
C7: Cash and cash equivalents | H7: 16117497 | I7: 5648133
C8: Investment in certificates of deposit | I8: 557878
C9: Receivebles, net | H9: 9874591 | I9: 6019116
C10: Due from other governments | H10: 414377
C11: Restricted assets- cash | H11: 1037478
C12: Prepaid insurance | I12: 80437
C13: Capital assets (net) | H13: 180628136 | I13: 9626485
C15: Total Assets | H15: =SUM(H7:H13) -> 208072079 | I15: =SUM(I7:I13) -> 21932049
A17: LIABILITIES
C18: Accounts, salaries, and other payables | H18: 2735360 | I18: 489468
C19: Due to other governments | H19: 444765 | I19: 71532
C20: Due to volunteer fire departments | I20: 945892
C21: Noncuurent liabilities:
D22: Due within one year | H22: 105000 | I22: 257842
D23: Due in more than one year | H23: 8239663 | I23: 310926
D24: Postemployment healthcare benefits payable | H24: 1722972
D26: Total Liabilities | H26: =SUM(H18:H24) -> 13247760 | I26: =SUM(I18:I24) -> 2075660
A28: Deferred inflow of resources
C29: Grant funds | H29: 150368
C31: Total Deferred inflow of resources | H31: =SUM(H29:H29) -> 150368 | I31: =SUM(I29:I29) -> 0
A33: NET ASSETS
B34: Net investment in capital assets | H34: 178143136 | I34: 9084091
B35: Restricted for:
C36: Capital projects
C37: Debt service | H37: 295989
C38: Other purposes | H38: 943497 | I38: 10772298
B39: Unrestricted | H39: 15291329
C41: Total Net Assets | H41: =SUM(H34:H39) -> 194673951 | I41: =SUM(I34:I39) -> 19856389
C43: Total Liabilities and Net Assets | H43: =H41+H26 -> 207921711 | I43: =I41+I26 -> 21932049

Sheet Terrebonne
D1: Terrebonne Parish 2014 Statement of Net Assets
D2: Issued: December 31, 2014
H4: Primary Government
H5: Governmental Activities | I5: Business-Type Activities | J5: Total | K5: Component Unit
A6: ASSETS
C7: Cash and cash equivalents | H7: 87216255 | I7: 28796008 | J7: =SUM(H7:I7) -> 116012263 | K7: 134054012
C8: Investments | H8: 48447943 | I8: 21664299 | J8: =SUM(H8:I8) -> 70112242 | K8: 226707770
C9: Receivables | H9: 13832027 | I9: 7344315 | J9: =SUM(H9:I9) -> 21176342 | K9: 50495267
C10: Internal balances | H10: 1041619 | I10: -1041619 | J10: =SUM(H10:I10) -> 0
C11: Due from other governments | H11: 54874043 | I11: 10343680 | J11: =SUM(H11:I11) -> 65217723 | K11: 21022390
C12: Due from component units | H12: 121923 | J12: =SUM(H12:I12) -> 121923 | K12: 34
C13: Inventories | H13: 1886935 | I13: 18941 | J13: =SUM(H13:I13) -> 1905876 | K13: 4682060
C14: Other assets | H14: 1500885 | I14: 2622271 | J14: =SUM(H14:I14) -> 4123156 | K14: 9278249
C15: Restricted assets:
D16: Cash and cash equivalents | H16: 293490 | I16: 1629233 | J16: =SUM(H16:I16) -> 1922723 | K16: 22793875
D17: Investments | I17: 950853 | J17: =SUM(I17) -> 950853
D18: Receivables | I18: 1551 | J18: =SUM(I18) -> 1551
C19: Investment in joint venture | I19: 847732 | J19: =SUM(I19) -> 847732
C20: Capital assets: | J20: =SUM(H20:I20) -> 0
D21: Non-depreciable | H21: 63841872 | I21: 6478790 | J21: =SUM(H21:I21) -> 70320662 | K21: 43007403
D22: Depreciable, net | H22: 257999620 | I22: 146155878 | J22: =SUM(H22:I22) -> 404155498 | K22: 624144836
C24: Total Assets | H24: =SUM(H7:H22) -> 531056612 | I24: =SUM(I7:I22) -> 225811932 | J24: =SUM(J7:J22) -> 756868544 | K24: =SUM(K7:K22) -> 1136185896
A26: Deferred Outflows of Resources | H26: 87484 | J26: =SUM(H26:I26) -> 87484 | K26: 486142
A28: LIABILITIES
C29: Accounts payable and other current liabilities | H29: 18519832 | I29: 5427692 | J29: =SUM(H29:I29) -> 23947524 | K29: 50411666
C30: Accrued interest payable | H30: 1385524 | J30: =SUM(H30:I30) -> 1385524
C31: Due to other governments | H31: 1761268 | I31: 174177 | J31: =SUM(H31:I31) -> 1935445 | K31: 798744
C32: Due to component units | H32: 34 | J32: =SUM(H32:I32) -> 34 | K32: 121923
C33: Unavailable revenue | H33: 28200172 | I33: 10422956 | J33: =SUM(H33:I33) -> 38623128 | K33: 21706491
C34: Grant Advancements | H34: 8922173 | J34: =SUM(H34:I34) -> 8922173
C35: Liabilities payable from restricted assets | H35: 133229 | I35: 1093033 | J35: =SUM(H35:I35) -> 1226262
C36: Noncurrent liabilities: | J36: =SUM(H36:I36) -> 0
D37: Due within one year | H37: 6514089 | I37: 1347278 | J37: =SUM(H37:I37) -> 7861367 | K37: 7329868
D38: Due in more than one year | H38: 119868844 | I38: 16975400 | J38: =SUM(H38:I38) -> 136844244 | K38: 204421295
D40: Total Liabilities | H40: =SUM(H29:H38) -> 185305165 | I40: =SUM(I29:I38) -> 35440536 | J40: =SUM(J29:J38) -> 220745701 | K40: =SUM(K29:K38) -> 284789987
A42: Deferred Inflows of Resources | J42: =SUM(H42:I42) -> 0 | K42: 99902
A44: NET ASSETS
B45: Invested in capital assets | H45: 260584619 | I45: 138795447 | J45: =SUM(H45:I45) -> 399380066 | K45: 552430144
B46: Restricted for: | J46: =SUM(H46:I46) -> 0
C47: General governments | H47: 205697 | J47: =SUM(H47:I47) -> 205697
C48: Streets and drainage | H48: 12786358 | J48: =SUM(H48) -> 12786358
C49: Capital projects | H49: 24128226 | J49: =SUM(H49) -> 24128226 | K49: 13233633
C50: Debt service | H50: 15959753 | J50: =SUM(H50:I50) -> 15959753 | K50: 13478781
C51: Health and welfare | H51: 5501375 | J51: =SUM(H51) -> 5501375
C52: Economic development and assistance | H52: 550091 | J52: =SUM(H52) -> 550091
C53: Urban redevelopment and assistance | H53: 2350740 | J53: =SUM(H53) -> 2350740
C54: Culture and recreation | H54: 3594039 | J54: =SUM(H54) -> 3594039
C55: Utilities | I55: 33819486 | J55: =SUM(I55) -> 33819486
C56: Sewerage | I56: 362749 | J56: =SUM(I56) -> 362749
C57: Sanitation | I57: 17610966 | J57: =SUM(I57) -> 17610966
C58: Other purposes | K58: 6259410
B59: Unrestricted | H59: 20178033 | I59: -217252 | J59: =SUM(H59:I59) -> 19960781 | K59: 266380181
C61: Total Net Assets | H61: =SUM(H45:H59) -> 345838931 | I61: =SUM(I45:I59) -> 190371396 | J61: =SUM(J45:J59) -> 536210327 | K61: =SUM(K44:K59) -> 851782149
C63: Total Liabilities and Net Assets | H63: =H61+H40 -> 531144096 | I63: =I61+I40 -> 225811932 | J63: =J61+J40 -> 756956028 | K63: =K61+K40 -> 1136572136

Sheet Tensas
C1: Tensas Parish 2014 Statement of Net Assets
C2: Issued: December 31, 2014
G4: Governmental Activities
A5: ASSETS
B6: Cash and cash equivalents | G6: 1972756
B7: Receivables | G7: 1413886
B8: Amounts held by trustee for landfill closure
C9: and post-closure care costs | G9: 980324
B10: Restricted assets | G10: 24008
B11: Capital assets, net | G11: 8654948
B13: Total Assets | G13: =SUM(G6:G11) -> 13045922
A15: LIABILITIES
B16: Accounts, salaries, and other payables | G16: 186567
B17: Intergovernmental payables | G17: 52119
B18: Long-term liabilities:
C19: Due within one year | G19: 66912
C20: Due in more than one year | G20: 1429057
C22: Total Liabilities | G22: =SUM(G16:G20) -> 1734655
A24: NET ASSETS
B25: Invested in capital assets, net of related debt | G25: 7158979
B26: Restricted for:
C27: Debt service | G27: 24008
C28: Landfill closure | G28: 980324
B29: Unrestricted | G29: 3147956
B31: Total Net Assets | G31: =SUM(G25:G29) -> 11311267
B33: Total Liabilities and Net Assets | G33: =G31+G22 -> 13045922

Sheet Union
C1: Union Parish 2014 Statement of Net Assets
C2: Issued: December 31, 2014
G4: Governmental Activities
A5: ASSETS
B6: Cash and cash equivalents | G6: 6259472
B7: Investments | G7: 7413268
B8: Receivables | G8: 4642781
B9: Capital assets, net of accumulated depreciation | G9: 12227890
B11: Total Assets | G11: =SUM(G6:G9) -> 30543411
A13: LIABILITIES
B14: Cash overdraft | G14: 1158594
B15: Accounts, salaries and other payables | G15: 911561
B16: Deposits due others | G16: 30838
B17: Compensated absences | G17: 355020
B18: Certificates of indebtedness due within one year | G18: 222837
B19: Certificates of indebtedness due in more than one year | G19: 180000
B20: Public building revenue bonds due within one year | G20: 18000
B21: Public building revenue bonds due in more than one year | G21: 217000
B22: Net OPEB obligation | G22: 1246380
B23: Landfill closure/postclosure care | G23: 6065277
C25: Total Liabilities | G25: =SUM(G14:G23) -> 10405507
A27: DEFERRED INFLOWS
B28: Grant revenues pending | G28: 14194
A30: NET ASSETS
B31: Net investment in capital assets | G31: 11812890
B32: Restricted for landfill closure/postclosure care | G32: 5000081
B33: Unrestricted | G33: 3310739
B35: Total Net Assets | G35: =SUM(G31:G33) -> 20123710
B37: Total Liabilities and Net Assets | G37: =G35+G25 -> 30529217

Sheet Vermilion
D1: Vermillion Parish 2014 Statement of Net Assets
D2: Issued: December 31, 2014
H4: Primary Government | I4: Component Units
H5: Governmental Activities | I5: Criminal Court Fund | J5: Tourist Commission
A6: ASSETS
C7: Cash and interest-bearing deposits | H7: 59064295 | I7: 52661 | J7: 233378
C8: Receivables, net | H8: 577792 | J8: 100
C9: Due from component unit | H9: 630
C10: Due from other governmental units | H10: 10124905 | I10: 185109 | J10: 10594
C11: Prepaid expenses | H11: 25907
C12: Capital assets, net | H12: 81804386
C14: Total Assets | H14: =SUM(H7:H12) -> 151597915 | I14: =SUM(I7:I12) -> 237770 | J14: =SUM(J7:J12) -> 244072
A16: LIABILITIES
C17: Accounts and other payables | H17: 3272834 | I17: 30738 | J17: 18898
C18: Contracts payable | H18: 631824
C19: Retainage payable | H19: 123311
C20: Due to primary government | I20: 630
C21: Accrued interest payable | H21: 26561
C22: Long-term liabilities:
D23: Other post employment benefits payable | H23: 1497605
D24: Due within one year | H24: 375000
D25: Due in more than one year | H25: 3355287
D27: Total Liabilities | H27: =SUM(H17:H25) -> 9282422 | I27: =SUM(I17:I25) -> 31368 | J27: =SUM(J17:J25) -> 18898
A29: DEFERRED INFLOWS OF RESOURCES
C30: Deferred revenue | H30: 1086595
A32: NET ASSETS
B33: Net investment in capital assets | H33: 80040061
B34: Restricted for:
C35: Debt service | H35: 1503470
C36: Other purposes | H36: 39450794
B37: Unrestricted | H37: 20234573 | I37: 206402 | J37: 225174
C39: Total Net Assets | H39: =SUM(H33:H37) -> 141228898 | I39: =SUM(I33:I37) -> 206402 | J39: =SUM(J32:J37) -> 225174
C41: Total Liabilities and Net Assets | H41: =H39+H27 -> 150511320 | I41: =I39+I27 -> 237770 | J41: =J39+J27 -> 244072

Sheet Vernon
D1: Vernon Parish 2014 Statement of Net Assets
D2: Issued: December 31, 2014
H5: 2014 | I5: 2013
A6: ASSETS
C7: Cash and cash equivalents | H7: 17372780 | I7: 23897070
C8: Investments, at fair market value | H8: 1246151 | I8: 1246021
C9: Receivebles | H9: 6948566 | I9: 6132255
C10: Other | H10: 39589 | I10: 21627
C11: Capital assets (net of accumulated depreciation):
D12: Land | H12: 1695977 | I12: 1695977
D13: Construction in progress | H13: 7715076
D14: Buildings and improvements | H14: 6171031 | I14: 6348922
D15: Furniture and equipment | H15: 8673574 | I15: 8930284
D16: Infrastructure | H16: 28172702 | I16: 27802037
D17: Library book collection | H17: 587324 | I17: 544834
C19: Total Assets | H19: =SUM(H7:H17) -> 78622770 | I19: =SUM(I7:I17) -> 76619027
A21: LIABILITIES
C22: Accounts, salaries, and other payables | H22: 937890 | I22: 831526
C23: Deferred revenue | H23: 44879 | I23: 110008
C24: Interest payable | H24: 392394 | I24: 382172
C25: Long-term liabilities:
D26: Due within one year | H26: 899766 | I26: 812070
D27: Due in more than one year | H27: 23278107 | I27: 19678827
D29: Total Liabilities | H29: =SUM(H22:H27) -> 25553036 | I29: =SUM(I22:I27) -> 21814603
A31: NET ASSETS
B32: Invested in capital assets, net of related debt | H32: 43245853 | I32: 35813460
B33: Restricted for:
C34: Debt service | H34: 705876 | I34: 740979
C35: Employee benefits | H35: 2427545 | I35: 2213890
B36: Unrestricted | H36: 6690459 | I36: 16036096
C38: Total Net Assets | H38: =SUM(H32:H36) -> 53069733 | I38: =SUM(I32:I36) -> 54804425
C40: Total Liabilities and Net Assets | H40: =H38+H29 -> 78622769 | I40: =I38+I29 -> 76619028

Sheet Washington
D1: Washington Parish 2014 Statement of Net Assets
D2: Issued: December 31, 2014
H4: Primary Government
H5: Governmental Activities | I5: Business-Type Activities | J5: Total
A6: ASSETS
C7: Cash | H7: 3332126 | I7: 150244 | J7: =SUM(H7:I7) -> 3482370
C8: Investments | H8: 2571647 | J8: =SUM(H8:I8) -> 2571647
C9: Receivables | H9: 5357310 | J9: =SUM(H9:I9) -> 5357310
C10: FEMA receivable | H10: 47409 | J10: =SUM(H10) -> 47409
C11: Notes receivable | I11: 46014 | J11: =SUM(H11:I11) -> 46014
C12: Due from other governments | H12: 175037 | J12: =SUM(H12:I12) -> 175037
C13: Equity in Choctaw Road Landfill | H13: 1499388 | J13: =SUM(H13) -> 1499388
C14: Restricted other assets | H14: 943283 | J14: =SUM(H14) -> 943283
C15: Capital assets
D16: Land | H16: 2535169 | J16: =SUM(H16) -> 2535169
D17: Construction in progress | H17: 458085 | J17: =SUM(H17) -> 458085
D18: Other capital assets, net of depreciation | H18: 36107028 | J18: =SUM(H18) -> 36107028
C20: Total Assets | H20: =SUM(H7:H18) -> 53026482 | I20: =SUM(I7:I18) -> 196258 | J20: =SUM(J7:J18) -> 53222740
A22: LIABILITIES
C23: Accounts payable | H23: 809043 | J23: =SUM(H23:I23) -> 809043
C24: Advanced revenue | H24: 861203 | J24: =SUM(H24:I24) -> 861203
C25: Due to FEMA | H25: 272389 | J25: =SUM(H25) -> 272389
C26: Due to other governments | H26: 620471 | J26: =SUM(H26:I26) -> 620471
C27: OPEB liability | H27: 721543 | J27: =SUM(H27:I27) -> 721543
C28: Long-term liabilities: | J28: =SUM(H28:I28) -> 0
D29: Portion due within one year | H29: 1529830 | J29: =SUM(H29:I29) -> 1529830
D30: Portion due in more than one year | H30: 3010000 | J30: =SUM(H30:I30) -> 3010000
D32: Total Liabilities | H32: =SUM(H23:H30) -> 7824479 | I32: =SUM(I23:I30) -> 0 | J32: =SUM(J23:J30) -> 7824479
A34: NET ASSETS
B35: Net invested in capital assets | H35: 34644356 | J35: =SUM(H35:I35) -> 34644356
B36: Restricted for:
C37: Capital projects | H37: 943395 | J37: =SUM(H37:I37) -> 943395
C38: Health and welfare | H38: 815825 | J38: =SUM(H38:I38) -> 815825
C39: Solid waste disposal | H39: 1629015 | J39: =SUM(H39:I39) -> 1629015
C40: Debt service | H40: 1305675 | J40: =SUM(H40:I40) -> 1305675
C41: Highways and bridges | H41: 2852781 | J41: =SUM(H41:I41) -> 2852781
C42: Other purposes | H42: 1622228 | J42: =SUM(H42:I42) -> 1622228
B43: Unrestricted | H43: 1388728 | I43: 196258 | J43: =SUM(H43:I43) -> 1584986
C45: Total Net Assets | H45: =SUM(H35:H43) -> 45202003 | I45: =SUM(I35:I43) -> 196258 | J45: =SUM(J34:J43) -> 45398261
C47: Total Liabilities and Net Assets | H47: =H45+H32 -> 53026482 | I47: =I45+I32 -> 196258 | J47: =J45+J32 -> 53222740

Sheet Webster
D1: Webster Parish 2014 Statement of Net Assets
D2: Issued: December 31, 2014
H4: Primary Government
H5: Governmental Activities | I5: Component Units
A6: ASSETS
C7: Cash and cash equivalents | H7: 4804541 | I7: 626768
C8: Investments | H8: 6021598 | I8: 428146
C9: Receivables | H9: 5707961 | I9: 430293
C10: Prepaid items | H10: 274135 | I10: 51717
C11: Inventory | I11: 4625
C12: Capital assets not being depreciated | H12: 1306517 | I12: 5000
C13: Capital assets, net of accumulated depreciation | H13: 10447733 | I13: 1443045
C15: Total Assets | H15: =SUM(H7:H13) -> 28562485 | I15: =SUM(I7:I13) -> 2989594
A17: LIABILITIES
C18: Accounts payable vendors | H18: 212666 | I18: 198518
C19: Accrued payroll liabilities | H19: 196948 | I19: 97731
C20: Escrow payable | I20: 13243
C21: Interest payable | H21: 14546
C22: Unearned revenue | H22: 10746
C23: Due to other governments | H23: 159042
C24: Taxes paid under protest | H24: 45919
C25: Long-term liabilities:
D26: Due within one year | H26: 402128 | I26: 79479
D27: Due in more than one year | H27: 3321167 | I27: 1813
D29: Total Liabilities | H29: =SUM(H18:H27) -> 4363162 | I29: =SUM(I18:I27) -> 390784
A31: NET ASSETS
B32: Net investment in capital assets | H32: 11457377 | I32: 1448045
B33: Restricted for:
C34: Debt service | H34: 7047
C35: Solid waste collection, road and jail | H35: 1086018
C36: Library | H36: 4384794
C37: Solid waste | H37: 1290263
C38: Road | H38: 2100687
C39: Courthouse and health unit | H39: 1457559
C40: DA salaries and benefits | H40: 10196
C41: Criminal court | H41: 24530
C42: Court reporter | H42: 847
C43: Grants | I43: 59775
B44: Unrestricted | H44: 2380005 | I44: 1090990
C46: Total Net Assets | H46: =SUM(H32:H44) -> 24199323 | I46: =SUM(I31:I44) -> 2598810
C48: Total Liabilities and Net Assets | H48: =H46+H29 -> 28562485 | I48: =I46+I29 -> 2989594

Sheet West Baton Rouge
C1: West Baton Rouge Parish 2014 Statement of Net Assets
C2: Issued: December 31, 2014
G4: Primary Government
G5: Governmental Activities
A6: ASSETS
B7: Cash and cash equivalents | G7: 8081632
B8: Investments | G8: 20199785
B9: Investments - restricted | G9: 108000
B10: Taxes receivable | G10: 7587764
B11: Restricted cash | G11: 481248
B12: Due from other governments | G12: 1744108
B13: Other receivables | G13: 783
B14: Capital assets:
C15: Non-Depreciable | G15: 2849307
C16: Depreciable | G16: 58902360
B18: Total Assets | G18: =SUM(G7:G16) -> 99954987
A20: LIABILITIES
B21: Accounts payable | G21: 496221
B22: Noncurrent liabilities:
C23: Due in one year | G23: 408750
C24: Due in more than one year | G24: 8665014
C26: Total Liabilities | G26: =SUM(G21:G24) -> 9569985
A28: DEFERRED INFLOWS OF RESOURCES
B29: Grant advances | G29: 364274
B30: Unavailable revenue - property taxes | G30: 8692665
C31: Total deferred inflows of resources | G31: =SUM(G29:G30) -> 9056939
A33: NET ASSETS
B34: Net investment in capital assets | G34: 57589285
B35: Restricted for:
C36: Debt service | G36: 614686
C37: Poydras endowment | G37: 113570
B38: Unrestricted | G38: 23010522
B40: Total Net Assets | G40: =SUM(G34:G38) -> 81328063
B42: Total Liabilities and Net Assets | G42: =G40+G26 -> 90898048

Sheet West Carroll
D1: West Carroll Parish 2014 Statement of Net Assets
D2: Issued: December 31, 2014
H4: Primary Government
H5: Governmental Activities
A6: ASSETS
C7: Cash and cash equivalents | H7: 6004251
C8: Receivables | H8: 1318697
C9: Deposits held in trust | H9: 784477
C10: Capital assets, net of accumulated depreciation | H10: 14156782
C12: Total Assets | H12: =SUM(H7:H10) -> 22264207
A14: LIABILITIES
C15: Cash overdraft | H15: 105667
C16: Accounts, salaries and other payables | H16: 220827
C17: Compensated absences | H17: 98075
C18: Certificates of indebtedness due within one year | H18: 14133
C19: Certificates of indebtedness due in more than one | H19: 84805
C20: Landfill closure/post closure care | H20: 2442440
D22: Total Liabilities | H22: =SUM(H15:H20) -> 2965947
A24: DEFERRED INFLOWS
C25: Protested taxes held pending settlement | H25: 180365
A27: NET ASSETS
B28: Net investment in capital assets | H28: 14057844
B29: Restricted for:
C30: Public works | H30: 4905031
C31: Health and welfare | H31: 531372
C32: Landfill closure/postclosure | H32: 784477
B33: Unrestricted | H33: -1160829
C35: Total Net Assets | H35: =SUM(H28:H33) -> 19117895
C37: Total Liabilities and Net Assets | H37: =H35+H22 -> 22083842

Sheet West Feliciana
D1: West Feliciana Parish 2014 Statement of Net Assets
D2: Issued: June 30, 2014
H4: Primary Government | K4: Component Unit
H5: Governmental Activities | I5: Business-Type Activities | J5: Total | K5: Business-type Activities
A6: ASSETS
C7: Cash and cash equivalents | H7: 1126360 | I7: 468720 | J7: =SUM(H7:I7) -> 1595080 | K7: 4300293
C8: Certificates of deposit | J8: =SUM(H8:I8) -> 0 | K8: 3457256
C9: Investments | H9: 12529200 | I9: 278554 | J9: =SUM(H9:I9) -> 12807754
C10: Taxes receivable | H10: 227502 | J10: =SUM(H10:I10) -> 227502 | K10: 648734
C11: Due from other governments | H11: 53694 | J11: =SUM(H11:I11) -> 53694
C12: Accouns receivable (net) | H12: 72728 | I12: 109887 | J12: =SUM(H12:I12) -> 182615 | K12: 3587253
C13: Inventory | J13: =SUM(H13:I13) -> 0 | K13: 451569
C14: Prepaid expenses | H14: 157071 | I14: 24487 | J14: =SUM(H14:I14) -> 181558 | K14: 247700
C15: Restricted assets: | J15: =SUM(H15:I15) -> 0
D16: Cash and cash equivalents | H16: 5429 | I16: 153927 | J16: =SUM(H16:I16) -> 159356 | K16: 2576977
D17: Certificates of deposit | J17: =SUM(H17:I17) -> 0 | K17: 2305933
D18: Investments | H18: 1315208 | I18: 214895 | J18: =SUM(H18:I18) -> 1530103 | K18: 5657008
C19: Investment in joint venture | J19: =SUM(H19:I19) -> 0
C20: Capital assets: | J20: =SUM(H20:I20) -> 0
D21: Land and construction in progress | H21: 3920330 | J21: =SUM(H21:I21) -> 3920330
D22: Depreciable, net | H22: 13769845 | I22: 9805673 | J22: =SUM(H22:I22) -> 23575518 | K22: 6747983
C24: Total Assets | H24: =SUM(H7:H22) -> 33177367 | I24: =SUM(I7:I22) -> 11056143 | J24: =SUM(J7:J22) -> 44233510 | K24: =SUM(K7:K22) -> 29980706
A27: LIABILITIES
C28: Accounts payable | H28: 553589 | I28: 18343 | J28: =SUM(H28:I28) -> 571932 | K28: 420225
C29: Accrued expenses and other liabilities | H29: 138263 | I29: 25833 | J29: =SUM(H29:I29) -> 164096 | K29: 676807
C30: Cash overdraft | H30: 1316732 | I30: 141470 | J30: =SUM(H30:I30) -> 1458202
C31: Customer deposits | I31: 153927 | J31: =SUM(H31:I31) -> 153927
C32: Internal balances | H32: 71608 | I32: -71608 | J32: =SUM(H32:I32) -> 0
C33: Noncurrent liabilities: | J33: =SUM(H33:I33) -> 0
D34: Due within one year | H34: 219053 | I34: 101470 | J34: =SUM(H34:I34) -> 320523
D35: Due in more than one year | H35: 3585937 | I35: 2977915 | J35: =SUM(H35:I35) -> 6563852
D37: Total Liabilities | H37: =SUM(H28:H35) -> 5885182 | I37: =SUM(I28:I35) -> 3347350 | J37: =SUM(J28:J35) -> 9232532 | K37: =SUM(K28:K35) -> 1097032
A40: NET ASSETS
B41: Net investment in capital assets | H41: 14221175 | I41: 6781838 | J41: =SUM(H41:I41) -> 21003013 | K41: 6747983
B42: Restricted for: | J42: =SUM(H42:I42) -> 0
C43: Debt service | H43: 319825 | I43: 368822 | J43: =SUM(H43:I43) -> 688647
C44: Capital improvements | H44: 3168668 | J44: =SUM(H44) -> 3168668 | K44: 10539918
C45: Health unit | H45: 1132963 | J45: =SUM(H45) -> 1132963
C46: Recreation | H46: 290409 | J46: =SUM(H46:I46) -> 290409
C47: Library | H47: 1207214 | J47: =SUM(H47) -> 1207214
C48: Other | H48: 365174 | J48: =SUM(H48) -> 365174
B49: Unrestricted | H49: 6586757 | I49: 558133 | J49: =SUM(H49:I49) -> 7144890 | K49: 11595773
C51: Total Net Assets | H51: =SUM(H41:H49) -> 27292185 | I51: =SUM(I41:I49) -> 7708793 | J51: =SUM(J41:J49) -> 35000978 | K51: =SUM(K40:K49) -> 28883674
C53: Total Liabilities and Net Assets | H53: =H51+H37 -> 33177367 | I53: =I51+I37 -> 11056143 | J53: =J51+J37 -> 44233510 | K53: =K51+K37 -> 29980706

Sheet Winn
D1: Winn Parish 2014 Statement of Net Assets
D2: Issued: December 31, 2014
H5: 2014 | I5: 2013
A6: ASSETS
C7: Cash and cash equivalents | H7: 1954725 | I7: 4118802
C8: Receivebles | H8: 2232420 | I8: 2234175
C9: Capital assets (net of accumulated depreciation):
D10: Nondepreciable:
E11: Land | H11: 223675 | I11: 223675
E12: Construction in progress | I12: 1298815
D13: Depreciable:
E14: Buildings and improvements | H14: 3516302 | I14: 698972
E15: Furniture, equipment, and other | H15: 624965 | I15: 639557
E16: Infrastructure - roads and bridges | H16: 1529469 | I16: 737271
C18: Total Assets | H18: =SUM(H7:H16) -> 10081556 | I18: =SUM(I7:I16) -> 9951267
A20: LIABILITIES
C21: Accounts, salaries, and other payables | H21: 232973 | I21: 82711
C22: Interest payable | H22: 38485 | I22: 42979
C23: Long-term liabilities:
D24: Due within one year | H24: 225000 | I24: 220000
D25: Due in more than one year | H25: 1785000 | I25: 2010000
D27: Total Liabilities | H27: =SUM(H21:H25) -> 2281458 | I27: =SUM(I21:I25) -> 2355690
C28: Deferred inflows- deferred revenues | H28: 13144 | I28: 32101
A30: NET ASSETS
B31: Net investment in capital assets | H31: 3884412 | I31: 3598291
B32: Unrestricted | H32: 3902544 | I32: 3965187
C34: Total Net Assets | H34: =SUM(H31:H32) -> 7786956 | I34: =SUM(I31:I32) -> 7563478
C36: Total Liabilities and Net Assets | H36: =H34+H27 -> 10068414 | I36: =I34+I27 -> 9919168

Sheet CSG
A1: 2014-SONA
C2: Assets: | N2: Liabilities: | S2: Non-Current/Long-Term Liabilities: | AA2: Net Assets:
A3: Denotes Error Found in Statement | C3: Cash | D3: Investments | E3: Receivables | F3: Capital Assets | G3: Transfers | H3: Other Assets | I3: Total Assets (Sum) | J3: Accuracy | K3: Accuracy | M3: Accounts Payable | N3: Compensated Absences Payable | O3: Bonds Payable Due within 1 Year | P3: Bonds Payable Due after 1 Year | Q3: Government Transfers | R3: Payable within 1 Year | S3: Payable after 1 Year | T3: Other Liabilities | U3: Total Liabilities (Sum) | V3: Accuracy | W3: Accuracy | Z3: Invested in Capital Assets, Net of Related Debt | AA3: Restricted Assets | AB3: Unrestricted Assets | AC3: Total Net Assets (Sum) | AD3: Total Liabilites and Net Assets (Sum) | AE3: Accuracy | AF3: Accuracy
A4: Parish's Statement Not Available | L4: Deferred Outflows of Resources | X4: PARISH | Y4: Deferred Inflows of Resources
B5: County | L5: PARISH | Y5: PARISH
B6: Acadia | C6: =Acadia!H6 -> 8972007 | D6: =Acadia!H7 -> 7896569 | E6: =Acadia!H8+Acadia!H9+Acadia!H10 -> 571560 | F6: =Acadia!H14+Acadia!H15 -> 52992711 | G6: =Acadia!H11+Acadia!H12 -> 6062012 | I6: =SUM(C6:H6) -> 76494859 | J6: =IF(I6=K6, "ok", "check") -> ok | K6: =Acadia!H17 -> 76494859 | M6: =Acadia!H25+Acadia!H26+Acadia!H27+Acadia!H29 -> 1555644 | N6: =Acadia!H34+Acadia!H37 -> 374244 | O6: =Acadia!H33 -> 1542435 | P6: =Acadia!H36 -> 11233348 | T6: =Acadia!H28+Acadia!H39 -> 7203993 | U6: =SUM(M6:T6) -> 21909664 | V6: =IF(U6=W6, "ok", "check") -> ok | W6: =Acadia!H42 -> 21909664 | Z6: =Acadia!H49 -> 40241750 | AA6: =Acadia!H51+Acadia!H52+Acadia!H53 -> 9644334 | AB6: =Acadia!H54 -> 4705745 | AC6: =SUM(Z6:AB6) -> 54591829 | AD6: =SUM(AC6,U6) -> 76501493 | AE6: =IF(AD6=AF6, "ok", "check") -> ok | AF6: =Acadia!H58 -> 76501493
B7: Allen | C7: =Allen!G6 -> 14858366 | E7: =Allen!G7 -> 6484761 | F7: =Allen!G10+Allen!G11 -> 10737729 | H7: =Allen!G8 -> 313803 | I7: =SUM(C7:H7) -> 32394659 | J7: =IF(I7=K7, "ok", "check") -> ok | K7: =Allen!G13 -> 32394659 | M7: =Allen!G16+Allen!G17 -> 628113 | O7: =Allen!G19+Allen!G21 -> 88940 | P7: =Allen!G23+Allen!G24 -> 1297691 | T7: =Allen!G18 -> 48703 | U7: =SUM(M7:T7) -> 2063447 | V7: =IF(U7=W7, "ok", "check") -> ok | W7: =Allen!G26 -> 2063447 | Z7: =Allen!G29 -> 27191700 | AA7: =Allen!G31+Allen!G32+Allen!G33+Allen!G34+Allen!G35+Allen!G36+Allen!G37+Allen!G38+Allen!G39+Allen!G40 -> 16765653 | AB7: =Allen!G41 -> 3848367 | AC7: =SUM(Z7:AB7) -> 47805720 | AD7: =SUM(AC7,U7) -> 49869167 | AE7: =IF(AD7=AF7, "ok", "check") -> ok | AF7: =Allen!G45 -> 49869167
B8: Ascension | C8: =Ascension!I8 -> 42404828 | D8: =Ascension!I9 -> 93691087 | E8: =Ascension!I10 -> 31751994 | F8: =Ascension!I18+Ascension!I19 -> 209564510 | G8: =Ascension!I11 -> 5021470 | H8: =Ascension!I12+Ascension!I13+Ascension!I16 -> 1105585 | I8: =SUM(C8:H8) -> 383539474 | J8: =IF(I8=K8, "ok", "check") -> ok | K8: =Ascension!I21 -> 383539474 | L8: =Ascension!I24 -> 294404 | M8: =Ascension!I29+Ascension!I30 -> 7178944 | O8: =Ascension!I36 -> 235409 | P8: =Ascension!I37 -> 667416 | Q8: =Ascension!I31 -> 269707 | R8: =Ascension!I39 -> 4335000 | S8: =Ascension!I40 -> 80612569 | T8: =Ascension!I32+Ascension!I34 -> 5065649 | U8: =SUM(M8:T8) -> 98364694 | V8: =IF(U8=W8, "ok", "check") -> ok | W8: =Ascension!I42 -> 98364694 | Y8: =Ascension!I48 -> 629856 | Z8: =Ascension!I51 -> 127427898 | AA8: =Ascension!I53+Ascension!I54+Ascension!I55 -> 135228122 | AB8: =Ascension!I57 -> 22183308 | AC8: =SUM(Z8:AB8) -> 284839328 | AD8: =SUM(AC8,U8) -> 383204022 | AE8: =IF(AD8=AF8, "ok", "check") -> ok | AF8: =Ascension!I61 -> 383204022
B9: Assumption | C9: =Assumption!H7 -> 2824757 | D9: =Assumption!H8+Assumption!H12 -> 60417455 | E9: =Assumption!H9 -> 5769470 | I9: =SUM(C9:H9) -> 69011682 | J9: =IF(I9=K9, "ok", "check") -> ok | K9: =Assumption!H14 -> 69011682 | M9: =Assumption!H18+Assumption!H19+Assumption!H21 -> 1553032 | T9: =Assumption!H20+Assumption!H22 -> 585713 | U9: =SUM(M9:T9) -> 2138745 | V9: =IF(U9=W9, "ok", "check") -> ok | W9: =Assumption!H27 -> 2138745 | Z9: =Assumption!H30 -> 42293964 | AB9: =Assumption!H32 -> 24582973 | AC9: =SUM(Z9:AB9) -> 66876937 | AD9: =SUM(AC9,U9) -> 69015682 | AE9: =IF(AD9=AF9, "ok", "check") -> ok | AF9: =Assumption!H36 -> 69015682
B10: Avoyelles | C10: =Avoyelles!H7 -> 9443859 | E10: =Avoyelles!H8 -> 56433 | F10: =Avoyelles!H16 -> 4599312 | G10: =Avoyelles!H9 -> 2631894 | H10: =Avoyelles!H10+Avoyelles!H15 -> 739268 | I10: =SUM(C10:H10) -> 17470766 | J10: =IF(I10=K10, "ok", "check") -> ok | K10: =Avoyelles!H20 -> 17470766 | M10: =Avoyelles!H24 -> 712402 | N10: =Avoyelles!H30 -> 99940 | T10: =Avoyelles!H25 -> 36260 | U10: =SUM(M10:T10) -> 848602 | V10: =IF(U10=W10, "ok", "check") -> ok | W10: =Avoyelles!H32 -> 848602 | Z10: =Avoyelles!H35 -> 5189860 | AB10: =Avoyelles!H36 -> 11432304 | AC10: =SUM(Z10:AB10) -> 16622164 | AD10: =SUM(AC10,U10) -> 17470766 | AE10: =IF(AD10=AF10, "ok", "check") -> ok | AF10: =Avoyelles!H40 -> 17470766
B11: Beauregard | C11: =Beauregard!G6 -> 17545772 | E11: =Beauregard!G7 -> 6974145 | F11: =Beauregard!G10+Beauregard!G11+Beauregard!G12+Beauregard!G13+Beauregard!G14 -> 31536926 | H11: =Beauregard!G8 -> 204510 | I11: =SUM(C11:H11) -> 56261353 | J11: =IF(I11=K11, "ok", "check") -> ok | K11: =Beauregard!G16 -> 56261353 | M11: =Beauregard!G19+Beauregard!G20 -> 1054101 | R11: =Beauregard!G22 -> 553200 | S11: =Beauregard!G23 -> 4845000 | U11: =SUM(M11:T11) -> 6452301 | V11: =IF(U11=W11, "ok", "check") -> ok | W11: =Beauregard!G25 -> 6452301 | Z11: =Beauregard!G28 -> 26350226 | AA11: =Beauregard!G30+Beauregard!G31+Beauregard!G32+Beauregard!G33+Beauregard!G34+Beauregard!G35+Beauregard!G36+Beauregard!G37+Beauregard!G38+Beauregard!G39 -> 20688356 | AB11: =Beauregard!G40 -> 2770770 | AC11: =SUM(Z11:AB11) -> 49809352 | AD11: =SUM(AC11,U11,Y11) -> 56261653 | AE11: =IF(AD11=AF11, "ok", "check") -> ok | AF11: =Beauregard!G44 -> 56261653
B12: Bienville | C12: =Bienville!G6 -> 17166902 | E12: =Bienville!G7 -> 5274448 | F12: =Bienville!G8 -> 22504607 | I12: =SUM(C12:H12) -> 44945957 | J12: =IF(I12=K12, "ok", "check") -> ok | K12: =Bienville!G10 -> 44945957 | M12: =Bienville!G13+Bienville!G14+Bienville!G15 -> 377396 | N12: =Bienville!G19 -> 80615 | O12: =Bienville!G16 -> 10365000 | T12: =Bienville!G17+Bienville!G18+Bienville!G20 -> 2096420 | U12: =SUM(M12:T12) -> 12919431 | V12: =IF(U12=W12, "ok", "check") -> ok | W12: =Bienville!G22 -> 12919431 | Z12: =Bienville!G25 -> 12139607 | AB12: =Bienville!G26 -> 19886919 | AC12: =SUM(Z12:AB12) -> 32026526 | AD12: =SUM(AC12,U12,Y12) -> 44945957 | AE12: =IF(AD12=AF12, "ok", "check") -> ok | AF12: =Bienville!G30 -> 44945957
B13: Bossier | C13: =Bossier!H7+Bossier!H8 -> 45383369 | D13: =Bossier!H9 -> 170335 | E13: =Bossier!H10 -> 23074512 | F13: =Bossier!H13+Bossier!H14 -> 285126100 | H13: =Bossier!H11+Bossier!H15 -> 9165938 | I13: =SUM(C13:H13) -> 362920254 | J13: =IF(I13=K13, "ok", "check") -> ok | K13: =Bossier!H17 -> 362920254 | M13: =Bossier!H21 -> 5670884 | R13: =Bossier!H25 -> 4998865 | S13: =Bossier!H26 -> 56933777 | U13: =SUM(M13:T13) -> 67603526 | V13: =IF(U13=W13, "ok", "check") -> ok | W13: =Bossier!H28 -> 67603526 | Y13: =Bossier!H31 -> 15065078 | Z13: =Bossier!H34 -> 234828358 | AA13: =Bossier!H36+Bossier!H37+Bossier!H38+Bossier!H39+Bossier!H40+Bossier!H41+Bossier!H42+Bossier!H43 -> 24349790 | AB13: =Bossier!H44 -> 21073502 | AC13: =SUM(Z13:AB13) -> 280251650 | AD13: =SUM(AC13,U13,Y13) -> 362920254 | AE13: =IF(AD13=AF13, "ok", "check") -> ok | AF13: =Bossier!H48 -> 362920254
B14: Caddo | C14: =Caddo!H7 -> 15950171 | D14: =Caddo!H8 -> 119354639 | E14: =Caddo!H9 -> 56915285 | F14: =Caddo!H15+Caddo!H16 -> 203943111 | G14: =Caddo!H10 -> 3504844 | H14: =Caddo!H12+Caddo!H13 -> 213957 | I14: =SUM(C14:H14) -> 399882007 | J14: =IF(I14=K14, "ok", "check") -> ok | K14: =Caddo!H18 -> 399882007 | L14: =Caddo!H23 -> 400028674 | M14: =Caddo!H26+Caddo!H27+Caddo!H28+Caddo!H29+Caddo!H30 -> 5293691 | Q14: =Caddo!H31+Caddo!H32 -> 639102 | R14: =Caddo!H35 -> 3114529 | S14: =Caddo!H36 -> 40226768 | T14: =Caddo!H33 -> 35478 | U14: =SUM(M14:T14) -> 49309568 | V14: =IF(U14=W14, "ok", "check") -> ok | W14: =Caddo!H38 -> 49309568 | Y14: =Caddo!H41 -> 0 | Z14: =Caddo!H45 -> 172306406 | AA14: =Caddo!H47+Caddo!H48+Caddo!H49+Caddo!H50+Caddo!H51+Caddo!H52+Caddo!H53+Caddo!H54 -> 111590102 | AB14: =Caddo!H56 -> 66822598 | AC14: =SUM(Z14:AB14) -> 350719106 | AD14: =SUM(AC14,U14,Y14) -> 400028674 | AE14: =IF(AD14=AF14, "ok", "check") -> ok | AF14: =Caddo!H60 -> 400028674
B15: Calcasieu | C15: =Calcasieu!H7 -> 58437555 | D15: =Calcasieu!H8 -> 208827036 | E15: =Calcasieu!H9+Calcasieu!H10+Calcasieu!H13 -> 57633351 | F15: =Calcasieu!H22+Calcasieu!H23 -> 518808191 | G15: =Calcasieu!H11 -> 27125 | H15: =Calcasieu!H14+Calcasieu!H15 -> 1411501 | I15: =SUM(C15:H15) -> 845144759 | J15: =IF(I15=K15, "ok", "check") -> ok | K15: =Calcasieu!H25 -> 845144759 | L15: =Calcasieu!H28 -> 0 | M15: =Calcasieu!H31+Calcasieu!H32 -> 11484125 | Q15: =Calcasieu!H34 -> 58216 | R15: =Calcasieu!H39 -> 2707932 | S15: =Calcasieu!H40 -> 7467672 | T15: =Calcasieu!H35+Calcasieu!H36 -> 1460915 | U15: =SUM(M15:T15) -> 23178860 | V15: =IF(U15=W15, "ok", "check") -> ok | W15: =Calcasieu!H42 -> 23178860 | Y15: =Calcasieu!H45 -> 47096091 | Z15: =Calcasieu!H48 -> 518808191 | AA15: =Calcasieu!H51+Calcasieu!H52 -> 178007975 | AB15: =Calcasieu!H53 -> 78053642 | AC15: =SUM(Z15:AB15) -> 774869808 | AD15: =SUM(AC15,U15,Y15) -> 845144759 | AE15: =IF(AD15=AF15, "ok", "check") -> ok | AF15: =Calcasieu!H57 -> 845144759
B16: Caldwell | C16: =Caldwell!G6 -> 7860568 | E16: =Caldwell!G7 -> 1821397 | F16: =Caldwell!G8 -> 14109112 | I16: =SUM(C16:H16) -> 23791077 | J16: =IF(I16=K16, "ok", "check") -> ok | K16: =Caldwell!G10 -> 23791077 | M16: =Caldwell!G13 -> 244089 | N16: =Caldwell!G15 -> 119522 | Q16: =Caldwell!G14 -> 57698 | U16: =SUM(M16:T16) -> 421309 | V16: =IF(U16=W16, "ok", "check") -> ok | W16: =Caldwell!G17 -> 421309 | Z16: =Caldwell!G20 -> 14109112 | AA16: =Caldwell!G21 -> 6856564 | AB16: =Caldwell!G22 -> 2404092 | AC16: =SUM(Z16:AB16) -> 23369768 | AD16: =SUM(AC16,U16,Y16) -> 23791077 | AE16: =IF(AD16=AF16, "ok", "check") -> ok | AF16: =Caldwell!G26 -> 23791077
B17: Cameron | C17: =Cameron!G6 -> 28467308 | D17: =Cameron!G7 -> 16614795 | F17: =Cameron!G10 -> 123967765 | H17: =Cameron!G8+Cameron!G9 -> 1969476 | I17: =SUM(C17:H17) -> 171019344 | J17: =IF(I17=K17, "ok", "check") -> ok | K17: =Cameron!G12 -> 171019344 | M17: =Cameron!G15+Cameron!G18 -> 3941757 | Q17: =Cameron!G16 -> 2623074 | R17: =Cameron!G20 -> 1420448 | S17: =Cameron!G21 -> 4202746 | T17: =Cameron!G17 -> 17231 | U17: =SUM(M17:T17) -> 12205256 | V17: =IF(U17=W17, "ok", "check") -> ok | W17: =Cameron!G23 -> 12205256 | Y17: =Cameron!G25 -> 0 | Z17: =Cameron!G28 -> 118625621 | AA17: =Cameron!G30+Cameron!G31+Cameron!G32+Cameron!G33+Cameron!G34 -> 3067343 | AB17: =Cameron!G35 -> 37121124 | AC17: =SUM(Z17:AB17) -> 158814088 | AD17: =SUM(AC17,U17,Y17) -> 171019344 | AE17: =IF(AD17=AF17, "ok", "check") -> ok | AF17: =Cameron!G39 -> 171019344
B18: Catahoula | C18: =Catahoula!H7+Catahoula!H8 -> 2316921 | E18: =Catahoula!H10 -> 1411486 | F18: =Catahoula!H12 -> 5862816 | H18: =Catahoula!H11 -> 81766 | I18: =SUM(C18:H18) -> 9672989 | J18: =IF(I18=K18, "ok", "check") -> ok | K18: =Catahoula!H14 -> 9672989 | M18: =Catahoula!H17 -> 144719 | N18: =Catahoula!H18 -> 32033 | R18: =Catahoula!H19 -> 104000 | S18: =Catahoula!H20 -> 272000 | U18: =SUM(M18:T18) -> 552752 | V18: =IF(U18=W18, "ok", "check") -> ok | W18: =Catahoula!H22 -> 552752 | Y18: =Catahoula!H25 -> 14777 | Z18: =Catahoula!H28 -> 5750215 | AB18: =Catahoula!H29 -> 3220628 | AC18: =SUM(Z18:AB18) -> 8970843 | AD18: =SUM(AC18,U18,Y18) -> 9538372 | AE18: =IF(AD18=AF18, "ok", "check") -> ok | AF18: =Catahoula!H33 -> 9538372
B19: Claiborne | C19: =Claiborne!G6 -> 6269126 | D19: =Claiborne!G7 -> 797211 | E19: =Claiborne!G8 -> 3084505 | F19: =Claiborne!G11 -> 8219499 | H19: =Claiborne!G9+Claiborne!G10 -> 129699 | I19: =SUM(C19:H19) -> 18500040 | J19: =IF(I19=K19, "ok", "check") -> ok | K19: =Claiborne!G13 -> 18500040 | L19: ='[1]East Baton Rouge'!C33+'[1]East Baton Rouge'!C34 -> #REF! | M19: =Claiborne!G16 -> 446867 | N19: =Claiborne!G19 -> 57248 | Q19: =Claiborne!G17 -> 14025 | R19: =Claiborne!G20 -> 155000 | S19: =Claiborne!G21 -> 1545000 | T19: =Claiborne!G18 -> 15626 | U19: =SUM(M19:T19) -> 2233766 | V19: =IF(U19=W19, "ok", "check") -> ok | W19: =Claiborne!G23 -> 2233766 | Z19: =Claiborne!G26 -> 6362770 | AA19: =Claiborne!G28+Claiborne!G29+Claiborne!G30+Claiborne!G31+Claiborne!G32+Claiborne!G33 -> 5284111 | AB19: =Claiborne!G34 -> 4619394 | AC19: =SUM(Z19:AB19) -> 16266275 | AD19: =SUM(AC19,U19,Y19) -> 18500041 | AE19: =IF(AD19=AF19, "ok", "check") -> ok | AF19: =Claiborne!G38 -> 18500041
B20: Concordia | C20: =Concodria!G7+Concodria!G8 -> 9701648 | E20: =Concodria!G9+Concodria!G10+Concodria!G11+Concodria!G12 -> 2168356 | I20: =SUM(C20:H20) -> 11870004 | J20: =IF(I20=K20, "ok", "check") -> ok | K20: =Concodria!G14 -> 11870004 | M20: =Concodria!G22+Concodria!G23 -> 413667 | R20: =Concodria!G25 -> 390767 | S20: =Concodria!G29 -> 9013491 | T20: =Concodria!G24 -> 83974 | U20: =SUM(M20:T20) -> 9901899 | V20: =IF(U20=W20, "ok", "check") -> ok | W20: =Concodria!G31 -> 9901899 | Z20: =Concodria!G34 -> 1120455 | AA20: =Concodria!G36+Concodria!G37 -> 8020129 | AB20: =Concodria!G38 -> 3043150 | AC20: =SUM(Z20:AB20) -> 12183734 | AD20: =SUM(AC20,U20,Y20) -> 22085633 | AE20: =IF(AD20=AF20, "ok", "check") -> ok | AF20: =Concodria!G42 -> 22085633
B21: DeSoto | C21: =DeSoto!H7 -> 13162797 | D21: =DeSoto!H8 -> 20355526 | E21: =DeSoto!H9 -> 13659168 | F21: =DeSoto!H11 -> 73781725 | H21: =DeSoto!H10 -> 38185 | I21: =SUM(C21:H21) -> 120997401 | J21: =IF(I21=K21, "ok", "check") -> ok | K21: =DeSoto!H13 -> 120997401 | M21: =DeSoto!H16 -> 1106355 | N21: =DeSoto!H22 -> 307960 | Q21: =DeSoto!H20 -> 207897 | R21: =DeSoto!H25 -> 5326 | S21: =DeSoto!H26 -> 450 | T21: =DeSoto!H17+DeSoto!H18+DeSoto!H19+DeSoto!H21+DeSoto!H23 -> 5310534 | U21: =SUM(M21:T21) -> 6938522 | V21: =IF(U21=W21, "ok", "check") -> ok | W21: =DeSoto!H28 -> 6938522 | Z21: =DeSoto!H31 -> 73775949 | AA21: =DeSoto!H32 -> 5776 | AB21: =DeSoto!H33 -> 40277154 | AC21: =SUM(Z21:AB21) -> 114058879 | AD21: =SUM(AC21,U21,Y21) -> 120997401 | AE21: =IF(AD21=AF21, "ok", "check") -> ok | AF21: =DeSoto!H37 -> 120997401
B22: East Baton Rouge | C22: ='East Baton Rouge'!H8 -> 192939199 | D22: ='East Baton Rouge'!H9 -> 188791227 | E22: ='East Baton Rouge'!H10+'East Baton Rouge'!H13 -> 56870163 | F22: ='East Baton Rouge'!H23+'East Baton Rouge'!H24 -> 878648378 | G22: ='East Baton Rouge'!H11 -> 84764697 | H22: ='East Baton Rouge'!H12+'East Baton Rouge'!H14 -> 1514732 | I22: =SUM(C22:H22) -> 1403528396 | J22: =IF(I22=K22, "ok", "check") -> ok | K22: ='East Baton Rouge'!H26 -> 1403528396 | L22: ='East Baton Rouge'!H33 -> 20842929 | M22: ='East Baton Rouge'!H36 -> 43709310 | Q22: ='East Baton Rouge'!H37 -> 7697870 | R22: ='East Baton Rouge'!H43 -> 30338476 | S22: ='East Baton Rouge'!H44 -> 698794643 | T22: ='East Baton Rouge'!H38+'East Baton Rouge'!H39+'East Baton Rouge'!H40 -> 35847513 | U22: =SUM(M22:T22) -> 816387812 | V22: =IF(U22=W22, "ok", "check") -> ok | W22: ='East Baton Rouge'!H46 -> 816387812 | Y22: ='East Baton Rouge'!H49 -> 351292 | Z22: ='East Baton Rouge'!H52 -> 650424770 | AA22: ='East Baton Rouge'!H54+'East Baton Rouge'!H55+'East Baton Rouge'!H57 -> 195912751 | AB22: ='East Baton Rouge'!H58 -> -238705300 | AC22: =SUM(Z22:AB22) -> 607632221 | AD22: =SUM(AC22,U22,Y22) -> 1424371325 | AE22: =IF(AD22=AF22, "ok", "check") -> ok | AF22: ='East Baton Rouge'!H62 -> 1424371325
B23: East Carroll | C23: ='East Carroll'!H7 -> 2275206 | D23: ='East Carroll'!H8 -> 773667 | E23: ='East Carroll'!H9 -> 2551513 | F23: ='East Carroll'!H12+'East Carroll'!H13 -> 6358983 | I23: =SUM(C23:H23) -> 11959369 | J23: =IF(I23=K23, "ok", "check") -> ok | K23: ='East Carroll'!H15 -> 11959369 | M23: ='East Carroll'!H18+'East Carroll'!H19 -> 213644 | R23: ='East Carroll'!H21 -> 154753 | S23: ='East Carroll'!H22 -> 457009 | U23: =SUM(M23:T23) -> 825406 | V23: =IF(U23=W23, "ok", "check") -> ok | W23: ='East Carroll'!H24 -> 825406 | Z23: ='East Carroll'!H27 -> 5755524 | AA23: ='East Carroll'!H29+'East Carroll'!H30+'East Carroll'!H31+'East Carroll'!H32+'East Carroll'!H33+'East Carroll'!H34+'East Carroll'!H35+'East Carroll'!H36+'East Carroll'!H37 -> 4564579 | AB23: ='East Carroll'!H39 -> 813860 | AC23: =SUM(Z23:AB23) -> 11133963 | AD23: =SUM(AC23,U23,Y23) -> 11959369 | AE23: =IF(AD23=AF23, "ok", "check") -> ok | AF23: ='East Carroll'!H43 -> 11959369
B24: East Feliciana | C24: ='East Feliciana'!G6 -> 5002609.6 | E24: ='East Feliciana'!G7 -> 1124824.8 | F24: ='East Feliciana'!G10 -> 12861749 | G24: ='East Feliciana'!G8+'East Feliciana'!G9 -> 1923014.5 | I24: =SUM(C24:H24) -> 20912198 | J24: =IF(I24=K24, "ok", "check") -> ok | K24: ='East Feliciana'!G12 -> 20912198 | L24: ='East Feliciana'!G15 -> 0 | M24: ='East Feliciana'!G18 -> 735676.08 | N24: ='East Feliciana'!G21 -> 13428 | Q24: ='East Feliciana'!G19+'East Feliciana'!G20 -> 1466996.6 | U24: =SUM(M24:T24) -> 2216100.7 | V24: =IF(U24=W24, "ok", "check") -> ok | W24: ='East Feliciana'!G23 -> 2216100.7 | Z24: ='East Feliciana'!G29 -> 12861749 | AA24: ='East Feliciana'!G31+'East Feliciana'!G32+'East Feliciana'!G33 -> 4857564.4 | AB24: ='East Feliciana'!G34 -> 976786.83 | AC24: =SUM(Z24:AB24) -> 18696100 | AD24: =SUM(AC24,U24,Y24) -> 20912201 | AE24: =IF(AD24=AF24, "ok", "check") -> ok | AF24: ='East Feliciana'!G38 -> 20912201
B25: Evangeline | C25: =Evangeline!H7 -> 11515168 | D25: =Evangeline!H13 -> 28105054 | E25: =Evangeline!H8 -> 12345 | F25: =Evangeline!H14 -> 25647365 | G25: =Evangeline!H9 -> 6225622 | H25: =Evangeline!H10 -> 5000 | I25: =SUM(C25:H25) -> 71510554 | J25: =IF(I25=K25, "ok", "check") -> ok | K25: =Evangeline!H16 -> 71510554 | M25: =Evangeline!H20+Evangeline!H21+Evangeline!H22 -> 3231584 | N25: =Evangeline!H26+Evangeline!H31 -> 71580 | O25: =Evangeline!H28 -> 234000 | P25: =Evangeline!H32 -> 31605866 | R25: =Evangeline!H27 -> 2338 | S25: =Evangeline!H30 -> 11062 | T25: =Evangeline!H19+Evangeline!H23 -> 336934 | U25: =SUM(M25:T25) -> 35493364 | V25: =IF(U25=W25, "ok", "check") -> ok | W25: =Evangeline!H34 -> 35493364 | Z25: =Evangeline!H37 -> 22677823 | AA25: =Evangeline!H38 -> 126351 | AB25: =Evangeline!H39 -> 13213016 | AC25: =SUM(Z25:AB25) -> 36017190 | AD25: =SUM(AC25,U25,Y25) -> 71510554 | AE25: =IF(AD25=AF25, "ok", "check") -> ok | AF25: =Evangeline!H43 -> 71510554
B26: Franklin | C26: =Franklin!G6 -> 8560372 | E26: =Franklin!G7 -> 3796748 | F26: =Franklin!G8 -> 18743780 | I26: =SUM(C26:H26) -> 31100900 | J26: =IF(I26=K26, "ok", "check") -> ok | K26: =Franklin!G10 -> 31100900 | M26: =Franklin!G13+Franklin!G14+Franklin!G16 -> 635363 | N26: =Franklin!G15 -> 103567 | Q26: =Franklin!G17 -> 132000 | T26: =Franklin!G18 -> 1433906 | U26: =SUM(M26:T26) -> 2304836 | V26: =IF(U26=W26, "ok", "check") -> ok | W26: =Franklin!G20 -> 2304836 | Z26: =Franklin!G23 -> 18541780 | AB26: =Franklin!G24 -> 10254284 | AC26: =SUM(Z26:AB26) -> 28796064 | AD26: =SUM(AC26,U26,Y26) -> 31100900 | AE26: =IF(AD26=AF26, "ok", "check") -> ok | AF26: =Franklin!G28 -> 31100900
B27: Grant | C27: =Grant!H7 -> 1797180 | E27: =Grant!H8 -> 1472672 | F27: =Grant!H11+Grant!H12+Grant!H13 -> 5841033 | I27: =SUM(C27:H27) -> 9110885 | J27: =IF(I27=K27, "ok", "check") -> ok | K27: =Grant!H15 -> 9110885 | M27: =Grant!H18 -> 527147 | N27: =Grant!H22 -> 44833 | R27: =Grant!H24 -> 95211 | S27: =Grant!H25 -> 247461 | T27: =Grant!H20 -> 17112 | U27: =SUM(M27:T27) -> 931764 | V27: =IF(U27=W27, "ok", "check") -> ok | W27: =Grant!H27 -> 931764 | Z27: =Grant!H30 -> 5498361 | AA27: =Grant!H32+Grant!H33+Grant!H34 -> 1917014 | AB27: =Grant!H35 -> 763746 | AC27: =SUM(Z27:AB27) -> 8179121 | AD27: =SUM(AC27,U27,Y27) -> 9110885 | AE27: =IF(AD27=AF27, "ok", "check") -> ok | AF27: =Grant!H39 -> 9110885
B28: Iberia | C28: =Iberia!H7 -> 41860020 | D28: =Iberia!H8 -> 72229 | E28: =Iberia!H9 -> 8148320 | F28: =Iberia!H18+Iberia!H19 -> 94220748 | G28: =Iberia!H11 -> 3826329 | H28: =Iberia!H10 -> 1813645 | I28: =SUM(C28:H28) -> 149941291 | J28: =IF(I28=K28, "ok", "check") -> ok | K28: =Iberia!H21:H21 -> 149941291 | M28: =Iberia!H27+Iberia!H28+Iberia!H29+Iberia!H35 -> 1799004 | Q28: =Iberia!H30+Iberia!H31 -> 1060997 | R28: =Iberia!H38 -> 1680344 | S28: =Iberia!H39 -> 8169937 | T28: =Iberia!H33+Iberia!H37 -> 4622425 | U28: =SUM(M28:T28) -> 17332707 | V28: =IF(U28=W28, "ok", "check") -> ok | W28: =Iberia!H41 -> 17332707 | Z28: =Iberia!H44 -> 83346072 | AA28: =Iberia!H46+Iberia!H47+Iberia!H48+Iberia!H49+Iberia!H50 -> 28523557 | AB28: =Iberia!H51 -> 20738955 | AC28: =SUM(Z28:AB28) -> 132608584 | AD28: =SUM(AC28,U28,Y28) -> 149941291 | AE28: =IF(AD28=AF28, "ok", "check") -> ok | AF28: =Iberia!H55 -> 149941291
B29: Iberville | C29: =Iberville!H8+Iberville!H14 -> 23927413 | E29: =Iberville!H9 -> 10119866 | F29: =Iberville!H16+Iberville!H17+Iberville!H18+Iberville!H19+Iberville!H20 -> 115277843 | H29: =Iberville!H11+Iberville!H12 -> 609466 | I29: =SUM(C29:H29) -> 149934588 | J29: =IF(I29=K29, "ok", "check") -> ok | K29: =Iberville!H22 -> 149934588 | M29: =Iberville!H25+Iberville!H29 -> 4040101 | R29: =Iberville!H33 -> 1104609 | S29: =Iberville!H34 -> 16076384 | T29: =Iberville!H32 -> 535622 | U29: =SUM(M29:T29) -> 21756716 | V29: =IF(U29=W29, "ok", "check") -> ok | W29: =Iberville!H36 -> 21756716 | Z29: =Iberville!H39 -> 97712719 | AA29: =Iberville!H41+Iberville!H42+Iberville!H43+Iberville!H44+Iberville!H45+Iberville!H46+Iberville!H47+Iberville!H48 -> 25823670 | AB29: =Iberville!H49 -> 4641483 | AC29: =SUM(Z29:AB29) -> 128177872 | AD29: =SUM(AC29,U29,Y29) -> 149934588 | AE29: =IF(AD29=AF29, "ok", "check") -> ok | AF29: =Iberville!H53 -> 149934588
B30: Jackson | C30: ='Jackson '!G6 -> 9298920 | E30: ='Jackson '!G7 -> 4981192 | F30: ='Jackson '!G10+'Jackson '!G11 -> 16451354 | H30: ='Jackson '!G8 -> 75502 | I30: =SUM(C30:H30) -> 30806968 | J30: =IF(I30=K30, "ok", "check") -> ok | K30: ='Jackson '!G13 -> 30806968 | M30: ='Jackson '!G16 -> 310576 | R30: ='Jackson '!G19 -> 110115 | S30: ='Jackson '!G20 -> 491865 | T30: ='Jackson '!G17 -> 30799 | U30: =SUM(M30:T30) -> 943355 | V30: =IF(U30=W30, "ok", "check") -> ok | W30: ='Jackson '!G22 -> 943355 | Z30: ='Jackson '!G25 -> 16451354 | AA30: ='Jackson '!G27+'Jackson '!G28+'Jackson '!G29+'Jackson '!G30+'Jackson '!G31+'Jackson '!G32+'Jackson '!G33+'Jackson '!G34 -> 10190905 | AB30: ='Jackson '!G35 -> 3188354 | AC30: =SUM(Z30:AB30) -> 29830613 | AD30: =SUM(AC30,U30,Y30) -> 30773968 | AE30: =IF(AD30=AF30, "ok", "check") -> ok | AF30: ='Jackson '!G39 -> 30773968
B31: Jefferson | C31: =Jefferson!H9 -> 4986 | D31: =Jefferson!H10 -> 73761 | E31: =Jefferson!H14+Jefferson!H15+Jefferson!H16+Jefferson!H19 -> 264740 | F31: =Jefferson!H35+Jefferson!H36 -> 1226463 | H31: =Jefferson!H11+Jefferson!H21+Jefferson!H33 -> 515480 | I31: =SUM(C31:H31) -> 2085430 | J31: =IF(I31=K31, "ok", "check") -> ok | K31: =Jefferson!H40 -> 2085430 | L31: =Jefferson!H45 -> 8143 | M31: =Jefferson!H49+Jefferson!H50+Jefferson!H51+Jefferson!H54+Jefferson!H55+Jefferson!H56 -> 44869 | R31: =Jefferson!H52 -> 31521 | S31: =Jefferson!H69 -> 433561 | T31: =Jefferson!H53+Jefferson!H57 -> 198740 | U31: =SUM(M31:T31) -> 708691 | V31: =IF(U31=W31, "ok", "check") -> ok | W31: =Jefferson!H73 -> 708691 | Z31: =Jefferson!H76 -> 877954 | AA31: =Jefferson!H78+Jefferson!H79+Jefferson!H80+Jefferson!H81+Jefferson!H82+Jefferson!H83+Jefferson!H84+Jefferson!H85+Jefferson!H86+Jefferson!H87+Jefferson!H89+Jefferson!H90 -> 399519 | AB31: =Jefferson!H91 -> 107409 | AC31: =SUM(Z31:AB31) -> 1384882 | AD31: =SUM(AC31,U31,Y31) -> 2093573 | AE31: =IF(AD31=AF31, "ok", "check") -> ok | AF31: =Jefferson!H95 -> 2093573
B32: Jefferson Davis | C32: ='Jefferson Davis'!G6+'Jefferson Davis'!G10 -> 22622461 | D32: ='Jefferson Davis'!G7 -> 2112204 | E32: ='Jefferson Davis'!G8 -> 1464881 | F32: ='Jefferson Davis'!G11 -> 33983534 | H32: ='Jefferson Davis'!G9 -> 78534 | I32: =SUM(C32:H32) -> 60261614 | J32: =IF(I32=K32, "ok", "check") -> ok | K32: ='Jefferson Davis'!G13 -> 60261614 | L32: ='Jefferson Davis'!G16 -> 71146 | M32: ='Jefferson Davis'!G19+'Jefferson Davis'!G20+'Jefferson Davis'!G23+'Jefferson Davis'!G26+'Jefferson Davis'!G27 -> 1988812 | O32: ='Jefferson Davis'!G25 -> 956000 | P32: ='Jefferson Davis'!G28 -> 14714000 | Q32: ='Jefferson Davis'!G21 -> 550500 | T32: ='Jefferson Davis'!G22+'Jefferson Davis'!G24 -> 2078200 | U32: =SUM(M32:T32) -> 20287512 | V32: =IF(U32=W32, "ok", "check") -> ok | W32: ='Jefferson Davis'!G30 -> 20287512 | Y32: ='Jefferson Davis'!G33 -> 509597 | Z32: ='Jefferson Davis'!G36 -> 17105806 | AA32: ='Jefferson Davis'!G38+'Jefferson Davis'!G39+'Jefferson Davis'!G40+'Jefferson Davis'!G41+'Jefferson Davis'!G42 -> 17422040 | AB32: ='Jefferson Davis'!G43 -> 5007805 | AC32: =SUM(Z32:AB32) -> 39535651 | AD32: =SUM(AC32,U32,Y32) -> 60332760 | AE32: =IF(AD32=AF32, "ok", "check") -> ok | AF32: ='Jefferson Davis'!G47 -> 60332760
B33: Lafayette | C33: =Lafayette!H7 -> 7721845 | D33: =Lafayette!H8 -> 278852022 | E33: =Lafayette!H9 -> 2270885 | F33: =Lafayette!H23+Lafayette!H24 -> 587439753 | G33: =Lafayette!H12+Lafayette!H13 -> 18677653 | H33: =Lafayette!H10+Lafayette!H14+Lafayette!H15 -> 4128630 | I33: =SUM(C33:H33) -> 899090788 | J33: =IF(I33=K33, "ok", "check") -> ok | K33: =Lafayette!H26 -> 899090788 | L33: =Lafayette!H29 -> 10285862 | M33: =Lafayette!H32 -> 3505182 | Q33: =Lafayette!H34+Lafayette!H35 -> 788161 | R33: =Lafayette!H39 -> 34417905 | S33: =Lafayette!H40 -> 409431497 | T33: =Lafayette!H36 -> 281108 | U33: =SUM(M33:T33) -> 448423853 | V33: =IF(U33=W33, "ok", "check") -> ok | W33: =Lafayette!H42 -> 448423853 | Z33: =Lafayette!H48 -> 311019205 | AA33: =Lafayette!H50+Lafayette!H51+Lafayette!H52 -> 174475245 | AB33: =Lafayette!H53 -> -10964684 | AC33: =SUM(Z33:AB33) -> 474529766 | AD33: =SUM(AC33,U33,Y33) -> 922953619 | AE33: =IF(AD33=AF33, "ok", "check") -> ok | AF33: =Lafayette!H57 -> 922953619
B34: Lafourche | C34: =Lafourche!H7 -> 20213397 | D34: =Lafourche!H8 -> 22534040 | E34: =Lafourche!H9 -> 2766041 | F34: =Lafourche!H13+Lafourche!H14 -> 96212496 | G34: =Lafourche!H10 -> 30663568 | H34: =Lafourche!H11 -> 2779853 | I34: =SUM(C34:H34) -> 175169395 | J34: =IF(I34=K34, "ok", "check") -> ok | K34: =Lafourche!H16 -> 175169395 | L34: =Lafourche!H21 -> 998036 | M34: =Lafourche!H24+Lafourche!H26 -> 6242882 | Q34: =Lafourche!H27 -> 933144 | R34: =Lafourche!H29 -> 2495013 | S34: =Lafourche!H30 -> 43892757 | T34: =Lafourche!H25 -> 468146 | U34: =SUM(M34:T34) -> 54031942 | V34: =IF(U34=W34, "ok", "check") -> ok | W34: =Lafourche!H32 -> 54031942 | Z34: =Lafourche!H35 -> 40588502 | AA34: =Lafourche!H37+Lafourche!H38 -> 18787481 | AB34: =Lafourche!H39 -> 62759506 | AC34: =SUM(Z34:AB34) -> 122135489 | AD34: =SUM(AC34,U34) -> 176167431 | AE34: =IF(AD34=AF34, "ok", "check") -> ok | AF34: =Lafourche!H43 -> 176167431
B35: LaSalle | C35: =LaSalle!G6 -> 2562628 | E35: =LaSalle!G7 -> 4667182 | F35: =LaSalle!G9 -> 7095343 | H35: =LaSalle!G8 -> 12440 | I35: =SUM(C35:H35) -> 14337593 | J35: =IF(I35=K35, "ok", "check") -> ok | K35: =LaSalle!G11 -> 14337593 | M35: =LaSalle!G15+LaSalle!G16 -> 1206833 | R35: =LaSalle!G19 -> 113744 | S35: =LaSalle!G20 -> 300699 | T35: =LaSalle!G14+LaSalle!G17 -> 821803 | U35: =SUM(M35:T35) -> 2443079 | V35: =IF(U35=W35, "ok", "check") -> ok | W35: =LaSalle!G22 -> 2443079 | Z35: =LaSalle!G25 -> 6680900 | AB35: =LaSalle!G26 -> 5213614 | AC35: =SUM(Z35:AB35) -> 11894514 | AD35: =SUM(AC35,U35,Y35) -> 14337593 | AE35: =IF(AD35=AF35, "ok", "check") -> ok | AF35: =LaSalle!G30 -> 14337593
B36: Lincoln | C36: =Lincoln!G6 -> 9467885 | D36: =Lincoln!G7 -> 22471496 | E36: =Lincoln!G8 -> 7666006 | F36: =Lincoln!G12+Lincoln!G13 -> 22960409 | G36: =Lincoln!G9 -> 813998 | H36: =Lincoln!G10 -> 11582 | I36: =SUM(C36:H36) -> 63391376 | J36: =IF(I36=K36, "ok", "check") -> ok | K36: =Lincoln!G15 -> 63391376 | L36: =Lincoln!G18 -> 7819 | M36: =Lincoln!G21 -> 1255073 | N36: =Lincoln!G27 -> 107370 | O36: =Lincoln!G25 -> 487000 | P36: =Lincoln!G28 -> 2989000 | Q36: =Lincoln!G22 -> 720960 | T36: =Lincoln!G30 -> 1677068 | U36: =SUM(M36:T36) -> 7236471 | V36: =IF(U36=W36, "ok", "check") -> ok | W36: =Lincoln!G32 -> 7236471 | Z36: =Lincoln!G35 -> 22960409 | AA36: =Lincoln!G37+Lincoln!G38 -> 3010039 | AB36: =Lincoln!G39 -> 30192276 | AC36: =SUM(Z36:AB36) -> 56162724 | AD36: =SUM(AC36,U36) -> 63399195 | AE36: =IF(AD36=AF36, "ok", "check") -> ok | AF36: =Lincoln!G43 -> 63399195
B37: Livingston | C37: =Livingston!H6+Livingston!H16 -> 18500081 | D37: =Livingston!H7 -> 3408123 | E37: =Livingston!H8 -> 913933 | F37: =Livingston!H18+Livingston!H19 -> 143336472 | G37: =Livingston!H11+Livingston!H12 -> 12664543 | H37: =Livingston!H9+Livingston!H10+Livingston!H13+Livingston!H14 -> 1037986 | I37: =SUM(C37:H37) -> 179861138 | J37: =IF(I37=K37, "ok", "check") -> ok | K37: =Livingston!H21 -> 179861138 | L37: =Livingston!H26 -> 4057845 | M37: =Livingston!H29+Livingston!H33 -> 4868454 | Q37: =Livingston!H30+Livingston!H31 -> 639810 | R37: =Livingston!H35 -> 6948051 | S37: =Livingston!H36 -> 79109380 | T37: =Livingston!H32 -> 19700 | U37: =SUM(M37:T37) -> 91585395 | V37: =IF(U37=W37, "ok", "check") -> ok | W37: =Livingston!H38 -> 91585395 | Z37: =Livingston!H41 -> 57658796 | AA37: =Livingston!H43+Livingston!H44+Livingston!H45+Livingston!H46 -> 11159044 | AB37: =Livingston!H47 -> 22515748 | AC37: =SUM(Z37:AB37) -> 91333588 | AD37: =SUM(AC37,U37) -> 182918983 | AE37: =IF(AD37=AF37, "ok", "check") -> ok | AF37: =Livingston!H51 -> 182918983
B38: Madison | C38: =Madison!G6 -> 6060133 | D38: =Madison!G7 -> 2972442 | E38: =Madison!G8 -> 5117727 | F38: =Madison!G9 -> 8087139 | I38: =SUM(C38:H38) -> 22237441 | J38: =IF(I38=K38, "ok", "check") -> ok | K38: =Madison!G11 -> 22237441 | M38: =Madison!G14 -> 263534 | R38: =Madison!G16 -> 36567 | S38: =Madison!G17 -> 536212 | T38: =Madison!G1 -> 0 | U38: =SUM(M38:T38) -> 836313 | V38: =IF(U38=W38, "ok", "check") -> ok | W38: =Madison!G19 -> 836313 | Z38: =Madison!G22 -> 8004701 | AA38: =Madison!G24+Madison!G25+Madison!G26+Madison!G27+Madison!G28+Madison!G29 -> 13269967 | AB38: =Madison!G30 -> 126460 | AC38: =SUM(Z38:AB38) -> 21401128 | AD38: =SUM(AC38,U38) -> 22237441 | AE38: =IF(AD38=AF38, "ok", "check") -> ok | AF38: =Madison!G34 -> 22237441
B39: Morehouse | C39: =Morehouse!G6 -> 4184992 | D39: =Morehouse!G7 -> 540000 | E39: =Morehouse!G8 -> 2375399 | F39: =Morehouse!G10+Morehouse!G11 -> 13394417 | I39: =SUM(C39:H39) -> 20494808 | J39: =IF(I39=K39, "ok", "check") -> ok | K39: =Morehouse!G13 -> 20494808 | M39: =Morehouse!G17+Morehouse!G18 -> 278282 | R39: =Morehouse!G20 -> 37425 | T39: =Morehouse!G16 -> 2120878 | U39: =SUM(M39:T39) -> 2436585 | V39: =IF(U39=W39, "ok", "check") -> ok | W39: =Morehouse!G22 -> 2436585 | Y39: =Morehouse!G25 -> 2092447 | Z39: =Morehouse!G28 -> 13394417 | AA39: =Morehouse!G29 -> 4444717 | AB39: =Morehouse!G30 -> -1873358 | AC39: =SUM(Z39:AB39) -> 15965776 | AD39: =SUM(AC39,U39) -> 18402361 | AE39: =IF(AD39=AF39, "ok", "check") -> ok | AF39: =Morehouse!G34 -> 18402361
B40: Natchitoches | C40: =Natchitoches!H7 -> 28619219 | E40: =Natchitoches!H8 -> 2081947 | F40: =Natchitoches!H15+Natchitoches!H16+Natchitoches!H17+Natchitoches!H18+Natchitoches!H19+Natchitoches!H20+Natchitoches!H21+Natchitoches!H22+Natchitoches!H24 -> 36293428 | H40: =Natchitoches!H10+Natchitoches!H11 -> 39861 | I40: =SUM(C40:H40) -> 67034455 | J40: =IF(I40=K40, "ok", "check") -> ok | K40: =Natchitoches!H26 -> 67034455 | M40: =Natchitoches!H30+Natchitoches!H31+Natchitoches!H32 -> 2059361 | R40: =Natchitoches!H37 -> 408096 | S40: =Natchitoches!H38 -> 3883262 | T40: =Natchitoches!H29+Natchitoches!H39+Natchitoches!H40 -> 3938949 | U40: =SUM(M40:T40) -> 10289668 | V40: =IF(U40=W40, "ok", "check") -> ok | W40: =Natchitoches!H42 -> 10289668 | Z40: =Natchitoches!H45 -> 32002070 | AA40: =Natchitoches!H46 -> 4291358 | AB40: =Natchitoches!H47 -> 20451359 | AC40: =SUM(Z40:AB40) -> 56744787 | AD40: =SUM(AC40,U40) -> 67034455 | AE40: =IF(AD40=AF40, "ok", "check") -> ok | AF40: =Natchitoches!H51 -> 67034455
B41: Orleans | C41: =Orleans!H7 -> 91036 | D41: =Orleans!H8 -> 190025 | E41: =Orleans!H10+Orleans!H11+Orleans!H13 -> 47856 | F41: =Orleans!H19 -> 1595680 | G41: =Orleans!H15+Orleans!H16 -> 71428 | H41: =Orleans!H17 -> 15 | I41: =SUM(C41:H41) -> 1996040 | J41: =IF(I41=K41, "ok", "check") -> ok | K41: =Orleans!H21 -> 1996040 | L41: =Orleans!H25 -> 6435 | M41: =Orleans!H28+Orleans!H29+Orleans!H31+Orleans!H32 -> 93540 | Q41: =Orleans!H33+Orleans!H34 -> 19703 | R41: =Orleans!H36 -> 104932 | S41: =Orleans!H37 -> 1481068 | T41: =Orleans!H30 -> 676 | U41: =SUM(M41:T41) -> 1699919 | V41: =IF(U41=W41, "ok", "check") -> ok | W41: =Orleans!H39 -> 1699919 | Y41: =Orleans!H43 -> 6687 | Z41: =Orleans!H46 -> 936247 | AA41: =Orleans!H47+Orleans!H48 -> 124597 | AB41: =Orleans!H50 -> -764975 | AC41: =SUM(Z41:AB41) -> 295869 | AD41: =SUM(AC41,U41) -> 1995788 | AE41: =IF(AD41=AF41, "ok", "check") -> ok | AF41: =Orleans!H54 -> 1995788
B42: Ouachita | C42: ='Ouachita '!F7 -> 37300264 | D42: ='Ouachita '!F8 -> 25766100 | E42: ='Ouachita '!F10+'Ouachita '!F11+'Ouachita '!F12+'Ouachita '!F13 -> 36043939 | F42: ='Ouachita '!F20 -> 180966576 | G42: ='Ouachita '!F15 -> 3664640 | H42: ='Ouachita '!F16+'Ouachita '!F17+'Ouachita '!F18 -> 951056 | I42: =SUM(C42:H42) -> 284692575 | J42: =IF(I42=K42, "ok", "check") -> ok | K42: ='Ouachita '!F22 -> 284692575 | M42: ='Ouachita '!F25 -> 6536200 | R42: ='Ouachita '!F29 -> 1421391 | S42: ='Ouachita '!F30 -> 7731868 | T42: ='Ouachita '!F26+'Ouachita '!F27 -> 1254548 | U42: =SUM(M42:T42) -> 16944007 | V42: =IF(U42=W42, "ok", "check") -> ok | W42: ='Ouachita '!F33 -> 16944007 | Z42: ='Ouachita '!F36 -> 180966576 | AA42: ='Ouachita '!F38+'Ouachita '!F39+'Ouachita '!F40+'Ouachita '!F41+'Ouachita '!F42+'Ouachita '!F43+'Ouachita '!F44+'Ouachita '!F45+'Ouachita '!F46 -> 82977695 | AB42: ='Ouachita '!F47 -> 3804300 | AC42: =SUM(Z42:AB42) -> 267748571 | AD42: =SUM(AC42,U42) -> 284692578 | AE42: =IF(AD42=AF42, "ok", "check") -> ok | AF42: ='Ouachita '!F51 -> 284692578
B43: Plaquemines | C43: =Plaquemines!H7 -> 113364903 | D43: =Plaquemines!H8 -> 4716345 | E43: =Plaquemines!H9 -> 71277195 | F43: =Plaquemines!H17+Plaquemines!H18 -> 472925486 | H43: =Plaquemines!H11+Plaquemines!H16 -> 3714287 | I43: =SUM(C43:H43) -> 665998216 | J43: =IF(I43=K43, "ok", "check") -> ok | K43: =Plaquemines!H22 -> 665998216 | M43: =Plaquemines!H27+Plaquemines!H29+Plaquemines!H31+Plaquemines!H40+Plaquemines!H43 -> 34978508 | N43: =Plaquemines!H32 -> 1091878 | O43: =Plaquemines!H28 -> 3725000 | P43: =Plaquemines!H41+Plaquemines!H42 -> 120669446 | Q43: =Plaquemines!H33 -> 33275 | T43: =Plaquemines!H30+Plaquemines!H34+Plaquemines!H39 -> 9642126 | U43: =SUM(M43:T43) -> 170140233 | V43: =IF(U43=W43, "ok", "check") -> ok | W43: =Plaquemines!H47 -> 170140233 | Z43: =Plaquemines!H50 -> 351520486 | AA43: =Plaquemines!H51 -> 96356871 | AB43: =Plaquemines!H52 -> 47980626 | AC43: =SUM(Z43:AB43) -> 495857983 | AD43: =SUM(AC43,U43) -> 665998216 | AE43: =IF(AD43=AF43, "ok", "check") -> ok | AF43: =Plaquemines!H56 -> 665998216
B44: Point Coupee | C44: ='Pointe Couppe'!F7 -> 2279603 | D44: ='Pointe Couppe'!F8 -> 706925 | E44: ='Pointe Couppe'!F9 -> 3308824 | F44: ='Pointe Couppe'!F16+'Pointe Couppe'!F17 -> 17002034 | G44: ='Pointe Couppe'!F10+'Pointe Couppe'!F11 -> 939812 | H44: ='Pointe Couppe'!F12+'Pointe Couppe'!F13+'Pointe Couppe'!F14 -> 166163 | I44: =SUM(C44:H44) -> 24403361 | J44: =IF(I44=K44, "ok", "check") -> ok | K44: ='Pointe Couppe'!F19 -> 24403361 | M44: ='Pointe Couppe'!F22 -> 1058577 | Q44: ='Pointe Couppe'!F23 -> 476736 | R44: ='Pointe Couppe'!F26 -> 443736 | S44: ='Pointe Couppe'!F27 -> 7635201 | U44: =SUM(M44:T44) -> 9614250 | V44: =IF(U44=W44, "ok", "check") -> ok | W44: ='Pointe Couppe'!F29:F29 -> 9614250 | Z44: ='Pointe Couppe'!F35 -> 8923097 | AA44: ='Pointe Couppe'!F37+'Pointe Couppe'!F38 -> 2809988 | AB44: ='Pointe Couppe'!F40 -> 3056026 | AC44: =SUM(Z44:AB44) -> 14789111 | AD44: =SUM(AC44,U44) -> 24403361 | AE44: =IF(AD44=AF44, "ok", "check") -> ok | AF44: ='Pointe Couppe'!F44 -> 24403361
B45: Rapides | C45: =Rapides!H7 -> 51085465 | E45: =Rapides!H8 -> 22832720 | F45: =Rapides!H12+Rapides!H13+Rapides!H15+Rapides!H16+Rapides!H17 -> 54110945 | H45: =Rapides!H9 -> 516 | I45: =SUM(C45:H45) -> 128029646 | J45: =IF(I45=K45, "ok", "check") -> ok | K45: =Rapides!H19 -> 128029646 | M45: =Rapides!H22+Rapides!H24 -> 1797609 | R45: =Rapides!H26 -> 1660074 | S45: =Rapides!H27 -> 53531400 | T45: =Rapides!H23 -> 632212 | U45: =SUM(M45:T45) -> 57621295 | V45: =IF(U45=W45, "ok", "check") -> ok | W45: =Rapides!H29 -> 57621295 | Z45: =Rapides!H32 -> 26878874 | AA45: =Rapides!H33 -> 3296487 | AB45: =Rapides!H34 -> 40232989 | AC45: =SUM(Z45:AB45) -> 70408350 | AD45: =SUM(AC45,U45) -> 128029645 | AE45: =IF(AD45=AF45, "ok", "check") -> ok | AF45: =Rapides!H38 -> 128029645
B46: Red River | C46: ='Red River'!H7 -> 12519211 | D46: ='Red River'!H8 -> 19054888 | E46: ='Red River'!H9 -> 4424485 | F46: ='Red River'!H15 -> 15298294 | H46: ='Red River'!H10 -> 18353 | I46: =SUM(C46:H46) -> 51315231 | J46: =IF(I46=K46, "ok", "check") -> ok | K46: ='Red River'!H17 -> 51315231 | L46: ='[1]St. Bernard'!C32 -> #REF! | M46: ='Red River'!H21+'Red River'!H28 -> 862364 | N46: ='Red River'!H22+'Red River'!H27 -> 70508 | U46: =SUM(M46:T46) -> 932872 | V46: =IF(U46=W46, "ok", "check") -> ok | W46: ='Red River'!H32 -> 932872 | Y46: ='[1]St. Bernard'!P32 -> 21051265 | Z46: ='Red River'!H37 -> 15298294 | AA46: ='Red River'!H39+'Red River'!H40+'Red River'!H41+'Red River'!H42 -> 13334619 | AB46: ='Red River'!H43 -> 21749446 | AC46: =SUM(Z46:AB46) -> 50382359 | AD46: =SUM(AC46,U46) -> 51315231 | AE46: =IF(AD46=AF46, "ok", "check") -> ok | AF46: ='Red River'!H47 -> 51315231
B47: Richland | C47: =Richland!G6 -> 8156413 | E47: =Richland!G7 -> 2837396 | F47: =Richland!G9+Richland!G10 -> 2626068 | I47: =SUM(C47:H47) -> 13619877 | J47: =IF(I47=K47, "ok", "check") -> ok | K47: =Richland!G12 -> 13619877 | L47: ='[1]St. Charles'!C33 -> #REF! | M47: =Richland!G15+Richland!G16 -> 454119 | U47: =SUM(M47:T47) -> 454119 | V47: =IF(U47=W47, "ok", "check") -> ok | W47: =Richland!G18 -> 454119 | Y47: =Richland!G21 -> 2667511 | Z47: =Richland!G24 -> 2626068 | AA47: =Richland!G25 -> 6125046 | AB47: =Richland!G26 -> 1747133 | AC47: =SUM(Z47:AB47) -> 10498247 | AD47: =SUM(AC47,U47) -> 10952366 | AE47: =IF(AD47=AF47, "ok", "check") -> ok | AF47: =Richland!G30 -> 10952366
B48: Sabine | C48: =Sabine!H7 -> 9360736 | E48: =Sabine!H8 -> 3889321 | F48: =Sabine!H10+Sabine!H11+Sabine!H12+Sabine!H13+Sabine!H14+Sabine!H16+Sabine!H17+Sabine!H18 -> 13877544 | I48: =SUM(C48:H48) -> 27127601 | J48: =IF(I48=K48, "ok", "check") -> ok | K48: =Sabine!H20 -> 27127601 | M48: =Sabine!H23+Sabine!H24 -> 483825 | R48: =Sabine!H26 -> 351017 | S48: =Sabine!H27 -> 952478 | U48: =SUM(M48:T48) -> 1787320 | V48: =IF(U48=W48, "ok", "check") -> ok | W48: =Sabine!H29 -> 1787320 | Z48: =Sabine!H32 -> 13520414 | AB48: =Sabine!H33 -> 11819867 | AC48: =SUM(Z48:AB48) -> 25340281 | AD48: =SUM(AC48,U48) -> 27127601 | AE48: =IF(AD48=AF48, "ok", "check") -> ok | AF48: =Sabine!H37 -> 27127601
B49: St Bernard | C49: ='St. Bernard'!F7 -> 35522122 | D49: ='St. Bernard'!F8+'St. Bernard'!F9 -> 5294661 | E49: ='St. Bernard'!F11+'St. Bernard'!F12+'St. Bernard'!F13+'St. Bernard'!F15+'St. Bernard'!F16 -> 39414847 | F49: ='St. Bernard'!F24+'St. Bernard'!F25 -> 384857910 | H49: ='St. Bernard'!F18+'St. Bernard'!F19 -> -2816961 | I49: =SUM(C49:H49) -> 462272579 | J49: =IF(I49=K49, "ok", "check") -> ok | K49: ='St. Bernard'!F27 -> 462272579 | M49: ='St. Bernard'!F30+'St. Bernard'!F31+'St. Bernard'!F32+'St. Bernard'!F33+'St. Bernard'!F35 -> 29214078 | R49: ='St. Bernard'!F39 -> 3915948 | S49: ='St. Bernard'!F40 -> 37500615 | T49: ='St. Bernard'!F36+'St. Bernard'!F37 -> 6830120 | U49: =SUM(M49:T49) -> 77460761 | V49: =IF(U49=W49, "ok", "check") -> ok | W49: ='St. Bernard'!F42 -> 77460761 | Z49: ='St. Bernard'!F45 -> 347417372 | AA49: ='St. Bernard'!F47+'St. Bernard'!F48+'St. Bernard'!F49+'St. Bernard'!F50+'St. Bernard'!F51 -> 15937711 | AB49: ='St. Bernard'!F52 -> 21456735 | AC49: =SUM(Z49:AB49) -> 384811818 | AD49: =SUM(AC49,U49) -> 462272579 | AE49: =IF(AD49=AF49, "ok", "check") -> ok | AF49: ='St. Bernard'!F56 -> 462272579
B50: St Charles | C50: ='St. Charles'!H7 -> 1704337 | D50: ='St. Charles'!H8 -> 91136263 | E50: ='St. Charles'!H9 -> 29690795 | F50: ='St. Charles'!H19+'St. Charles'!H20+'St. Charles'!H21+'St. Charles'!H22 -> 197617376 | G50: ='St. Charles'!H10 -> 4581936 | H50: ='St. Charles'!H13+'St. Charles'!H14 -> 473996 | I50: =SUM(C50:H50) -> 325204703 | J50: =IF(I50=K50, "ok", "check") -> ok | K50: ='St. Charles'!H24 -> 325204703 | M50: ='St. Charles'!H28+'St. Charles'!H32 -> 5551720 | Q50: ='St. Charles'!H30+'St. Charles'!H31 -> 260446 | R50: ='St. Charles'!H36 -> 3125000 | S50: ='St. Charles'!H37 -> 27310425 | T50: ='St. Charles'!H29+'St. Charles'!H33 -> 431016 | U50: =SUM(M50:T50) -> 36678607 | V50: =IF(U50=W50, "ok", "check") -> ok | W50: ='St. Charles'!H41 -> 36678607 | Y50: ='St. Charles'!H45 -> 25868468 | Z50: ='St. Charles'!H48 -> 181967376 | AA50: ='St. Charles'!H50+'St. Charles'!H51+'St. Charles'!H52+'St. Charles'!H53 -> 43654724 | AB50: ='St. Charles'!H54 -> 37035528 | AC50: =SUM(Z50:AB50) -> 262657628 | AD50: =SUM(AC50,U50) -> 299336235 | AE50: =IF(AD50=AF50, "ok", "check") -> ok | AF50: ='St. Charles'!H58 -> 299336235
B51: St Helena | C51: ='St. Helena '!H7+'St. Helena '!H16 -> 4878772 | D51: ='St. Helena '!H8 -> 986526 | E51: ='St. Helena '!H9 -> 2817120 | F51: ='St. Helena '!H24+'St. Helena '!H25 -> 17867465 | H51: ='St. Helena '!H12 -> 99350 | I51: =SUM(C51:H51) -> 26649233 | J51: =IF(I51=K51, "ok", "check") -> ok | K51: ='St. Helena '!H28 -> 26649233 | M51: ='St. Helena '!H32+'St. Helena '!H33+'St. Helena '!H43 -> 1238977 | N51: ='St. Helena '!H44 -> 308432 | O51: ='St. Helena '!H37 -> 428726 | P51: ='St. Helena '!H42 -> 1865000 | T51: ='St. Helena '!H34+'St. Helena '!H38+'St. Helena '!H45 -> 1236427 | U51: =SUM(M51:T51) -> 5077562 | V51: =IF(U51=W51, "ok", "check") -> ok | W51: ='St. Helena '!H48 -> 5077562 | Z51: ='St. Helena '!H51 -> 15145601 | AA51: ='St. Helena '!H53+'St. Helena '!H54+'St. Helena '!H55 -> 7154301 | AB51: ='St. Helena '!H56 -> -728231 | AC51: =SUM(Z51:AB51) -> 21571671 | AD51: =SUM(AC51,U51) -> 26649233 | AE51: =IF(AD51=AF51, "ok", "check") -> ok | AF51: ='St. Helena '!H60 -> 26649233
B52: St. James | C52: ='St. James'!G7 -> 22660670 | D52: ='St. James'!G8 -> 10808344 | E52: ='St. James'!G9 -> 23579733 | F52: ='St. James'!G21 -> 63127363 | G52: ='St. James'!G11+'St. James'!G12 -> 1590000 | H52: ='St. James'!G14+'St. James'!G15+'St. James'!G16 -> 276014 | I52: =SUM(C52:H52) -> 122042124 | J52: =IF(I52=K52, "ok", "check") -> ok | K52: ='St. James'!G24 -> 122042124 | L52: ='St. James'!G26 -> 163636 | M52: ='St. James'!G29 -> 4907605 | R52: ='St. James'!G34 -> 1538866 | S52: ='St. James'!G35 -> 9012522 | T52: ='St. James'!G30+'St. James'!G31 -> 1410980 | U52: =SUM(M52:T52) -> 16869973 | V52: =IF(U52=W52, "ok", "check") -> ok | W52: ='St. James'!G37 -> 16869973 | Z52: ='St. James'!G40 -> 57285911 | AA52: ='St. James'!G42+'St. James'!G43+'St. James'!G44+'St. James'!G45+'St. James'!G46+'St. James'!G47+'St. James'!G48+'St. James'!G49+'St. James'!G50 -> 43371268 | AB52: ='St. James'!G51 -> 4678608 | AC52: =SUM(Z52:AB52) -> 105335787 | AD52: =SUM(AC52,U52) -> 122205760 | AE52: =IF(AD52=AF52, "ok", "check") -> ok | AF52: ='St. James'!G55 -> 122205760
B53: St. John the Baptist | C53: ='St. John the Baptist'!G7 -> 68703620 | E53: ='St. John the Baptist'!G10+'St. John the Baptist'!G11+'St. John the Baptist'!G12+'St. John the Baptist'!G13 -> 15380068 | F53: ='St. John the Baptist'!G18+'St. John the Baptist'!G20 -> 86177643 | G53: ='St. John the Baptist'!G14 -> 3096282 | H53: ='St. John the Baptist'!G15+'St. John the Baptist'!G17 -> 1351150 | I53: =SUM(C53:H53) -> 174708763 | J53: =IF(I53=K53, "ok", "check") -> ok | K53: ='St. John the Baptist'!G22 -> 174708763 | M53: ='St. John the Baptist'!G25+'St. John the Baptist'!G30 -> 4603048 | Q53: ='St. John the Baptist'!G27 -> 21935 | R53: ='St. John the Baptist'!G32 -> 5187032 | S53: ='St. John the Baptist'!G33 -> 84501977 | T53: ='St. John the Baptist'!G26 -> 942369 | U53: =SUM(M53:T53) -> 95256361 | V53: =IF(U53=W53, "ok", "check") -> ok | W53: ='St. John the Baptist'!G35 -> 95256361 | Z53: ='St. John the Baptist'!G38 -> 6020921 | AA53: ='St. John the Baptist'!G40+'St. John the Baptist'!G41 -> 43916590 | AB53: ='St. John the Baptist'!G45 -> 29514891 | AC53: =SUM(Z53:AB53) -> 79452402 | AD53: =SUM(AC53,U53) -> 174708763 | AE53: =IF(AD53=AF53, "ok", "check") -> ok | AF53: ='St. John the Baptist'!G49 -> 174708763
