Workbook

Sheet Acadia
D1: Acadia Combined Balance Sheet
D2: Issued: December 31, 2015
K4: General Fund | L4: Parish Road Fund | M4: Sales Tax Fund | N4: 1% Sales Tax District No. 2 Fund | O4: Other Governmental Funds | P4: Total Governmental Funds
A5: Assets:
B6: Cash | K6: 594846 | L6: 1442181 | M6: 1777092 | N6: 349485 | O6: 5031940 | P6: =SUM(K6:O6) -> 9195544
B7: Investments | K7: 627565 | L7: 12742 | M7: 4074584 | N7: 137018 | O7: 3087127 | P7: =SUM(K7:O7) -> 7939036
B8: Tax Receivable | K8: 1827046 | L8: 1117278 | M8: 1457991 | N8: 477857 | O8: 1662324 | P8: =SUM(K8:O8) -> 6542496
B9: Special assessments receivable | O9: 16996 | P9: =SUM(K9:O9) -> 16996
B10: Other receivables | K10: 8444 | O10: 1650 | P10: =SUM(K10:O10) -> 10094
B11: Due from other governmental entities, net of allowance
C12: for doubtful accounts | K12: 359090 | L12: 45485 | M12: 21150 | O12: 124735 | P12: =SUM(K12:O12) -> 550460
B13: Due from other funds | K13: 95052 | P13: =SUM(K13:O13) -> 95052
B14: Due from component units | K14: 20177 | P14: =SUM(K14:O14) -> 20177
E16: Total assets: | K16: =SUM(K6:K14) -> 3532220 | L16: =SUM(L6:L14) -> 2617686 | M16: =SUM(M6:M14) -> 7330817 | N16: =SUM(N6:N14) -> 964360 | O16: =SUM(O6:O14) -> 9924772 | P16: =SUM(K16:O16) -> 24369855
A18: LIABILITIES AND FUND BALANCES
B19: Liabilities:
C20: Accounts payable | K20: 661040 | L20: 16126 | M20: 385236 | N20: 6349 | O20: 249209 | P20: =SUM(K20:O20) -> 1317960
C21: Retainage payable | P21: =SUM(K21:O21) -> 0
C22: Accrued liabilities and other payables | K22: 519374 | L22: 41289 | M22: 12218 | O22: 55052 | P22: =SUM(K22:O22) -> 627933
C23: Unearned revenue | L23: 46000 | P23: =SUM(K23:O23) -> 46000
C24: Due to other funds | L24: 42381 | M24: 36357 | O24: 16314 | P24: =SUM(K24:O24) -> 95052
E26: Total liabilities: | K26: =SUM(K20:K24) -> 1180414 | L26: =SUM(L20:L24) -> 145796 | M26: =SUM(M20:M24) -> 433811 | N26: =SUM(N20:N24) -> 6349 | O26: =SUM(O20:O24) -> 320575 | P26: =SUM(P20:P24) -> 2086945
A28: DEFERRED INFLOWS OF RESOURCES
C29: Unavailable revenue- special assessments | O29: 16997 | P29: =SUM(K29:O29) -> 16997
E31: Total deferred inflows of resources | K31: =SUM(K29:K29) -> 0 | L31: =SUM(L29:L29) -> 0 | M31: =SUM(M29:M29) -> 0 | N31: =SUM(N29:N29) -> 0 | O31: =SUM(O29:O29) -> 16997 | P31: =SUM(P29:P29) -> 16997
B33: Fund Balances
C34: Restricted for:
D35: Property tax dedication for council on aging | K35: 482052 | P35: =SUM(K35:O35) -> 482052
D36: Property tax and sales tax dedication for
E37: constructing and maintaining solid
E38: waste, facilities, roads and bridges | L38: 2471890 | M38: 6897006 | N38: 958011 | P38: =SUM(K38:O38) -> 10326907
D39: Debt retirement | O39: 1669655 | P39: =SUM(K39:O39) -> 1669655
D40: Mosquito control | O40: 2126616 | P40: =SUM(K40:O40) -> 2126616
D41: Cooperative extension operation and maintenance | O41: 1667432 | P41: =SUM(K41:O41) -> 1667432
D42: Road maintenance and construction | O42: 1129541 | P42: =SUM(K42:O42) -> 1129541
C43: Committed to:
D44: Health unit operation and maintenance | O44: 1707620 | P44: =SUM(K44:O44) -> 1707620
D45: Rice Arena operation and maintenance | O45: 1061885 | P45: =SUM(K45:O45) -> 1061885
C46: Assigned: | P46: =SUM(K46:O46) -> 0
D47: Capital projects | O47: 1916 | P47: =SUM(K47:O47) -> 1916
D48: Economic development | P48: =SUM(K48:O48) -> 0
D49: Airport | O49: 183628 | P49: =SUM(K49:O49) -> 183628
D50: Other | O50: 38907 | P50: =SUM(K50:O50) -> 38907
C51: Unassigned | K51: 1869754 | P51: =SUM(K51:O51) -> 1869754
E53: Total fund balances: | K53: =SUM(K34:K51) -> 2351806 | L53: =SUM(L34:L51) -> 2471890 | M53: =SUM(M34:M51) -> 6897006 | N53: =SUM(N34:N51) -> 958011 | O53: =SUM(O34:O51) -> 9587200 | P53: =SUM(P34:P51) -> 22265913
E55: Total liabilities and fund balances: | K55: =SUM(K53,K26,K31) -> 3532220 | L55: =SUM(L53,L26,L31) -> 2617686 | M55: =SUM(M53,M26,M31) -> 7330817 | N55: =SUM(N53,N26,N31) -> 964360 | O55: =SUM(O53,O26,O31) -> 9924772 | P55: =SUM(P53,P26,P31) -> 24369855

Sheet Allen
D1: Allen Combined Balance Sheet
D2: Issued: December 31, 2015
K5: General | L5: Solid Waste Fund | M5: Road District #2 Mtc. Fund | N5: Road District #3 Mtc. Fund | O5: Library Capital Projects Fund | P5: North Drainage Capital Projects Fund | Q5: Nonmajor Governmental Funds | R5: Total Governmental Funds
A6: Assets:
B7: Cash | K7: 132295 | L7: 477668 | M7: 469617 | N7: 864081 | O7: 493056 | Q7: 1632845 | R7: =SUM(K7:Q7) -> 4069562
B8: Receivables | K8: 234323 | M8: 596200 | N8: 630435 | Q8: 1372153 | R8: =SUM(K8:Q8) -> 2833111
B9: Due from other governments | K9: 280033 | L9: 135294 | P9: 268581 | Q9: 78487 | R9: =SUM(K9:Q9) -> 762395
B10: Inventory | Q10: 45179 | R10: =SUM(K10:Q10) -> 45179
B11: Prepaid assets | K11: 4443 | Q11: 2989 | R11: =SUM(K11:Q11) -> 7432
E13: Total Assets: | K13: =SUM(K7:K11) -> 651094 | L13: =SUM(L7:L11) -> 612962 | M13: =SUM(M7:M11) -> 1065817 | N13: =SUM(N7:N11) -> 1494516 | O13: =SUM(O7:O11) -> 493056 | P13: =SUM(P7:P11) -> 268581 | Q13: =SUM(Q7:Q11) -> 3131653 | R13: =SUM(R7:R11) -> 7717679
A15: LIABILITIES AND FUND BALANCES
B16: Liabilities:
C17: Accounts payable | K17: 43891 | L17: 132980 | M17: 48187 | N17: 58319 | O17: 102505 | P17: 268581 | Q17: 170096 | R17: =SUM(K17:Q17) -> 824559
C18: Unearned revenue | Q18: 48703 | R18: =SUM(K18:Q18) -> 48703
E20: Total liabilities: | K20: =SUM(K17:K18) -> 43891 | L20: =SUM(L17:L18) -> 132980 | M20: =SUM(M17:M18) -> 48187 | N20: =SUM(N17:N18) -> 58319 | O20: =SUM(O17:O18) -> 102505 | P20: =SUM(P17:P18) -> 268581 | Q20: =SUM(Q17:Q18) -> 218799 | R20: =SUM(R17:R18) -> 873262
A22: DEFERRED INFLOWS OF RESROUCES
C23: Unavailable revenue | K23: 29082 | M23: 50116 | N23: 59851 | Q23: 206210 | R23: =SUM(K23:Q23) -> 345259
E25: Total deferred inflows of resources | K25: =SUM(K23:K23) -> 29082 | L25: =SUM(L23:L23) -> 0 | M25: =SUM(M23:M23) -> 50116 | N25: =SUM(N23:N23) -> 59851 | O25: =SUM(O23:O23) -> 0 | P25: =SUM(P23:P23) -> 0 | Q25: =SUM(Q23:Q23) -> 206210 | R25: =SUM(R23:R23) -> 345259
B27: Fund Balances
C28: Nonspendable - prepaids | K28: 4443 | Q28: 2989 | R28: =SUM(K28:Q28) -> 7432
C29: Nonspendable- inventroy | Q29: 45179 | R29: =SUM(K29:Q29) -> 45179
C30: Restricted:
D31: Judicial | Q31: 611041 | R31: =SUM(K31:Q31) -> 611041
D32: Other general government | Q32: 634469 | R32: =SUM(K32:Q32) -> 634469
D33: Public works | M33: 967514 | N33: 1376346 | Q33: 1157545 | R33: =SUM(K33:Q33) -> 3501405
D34: Economic development | L34: 479982 | R34: =SUM(K34:Q34) -> 479982
D35: Sanitation | O35: 390551 | R35: =SUM(K35:Q35) -> 390551
D36: Capital projects | Q36: 53723 | R36: =SUM(K36:Q36) -> 53723
D37: Debt service | R37: =SUM(K37:Q37) -> 0
C38: Committed: | R38: =SUM(K38:Q38) -> 0
D39: Other general government | R39: =SUM(K39:Q39) -> 0
C40: Assigned: | R40: =SUM(K40:Q40) -> 0
D41: Other general government | R41: =SUM(K41:Q41) -> 0
D42: Public works | R42: =SUM(K42:Q42) -> 0
C43: Negative unassigned | R43: =SUM(K43:Q43) -> 0
C44: Unassigned | K44: 573678 | Q44: 201698 | R44: =SUM(K44:Q44) -> 775376
E46: Total fund balance: | K46: =SUM(K28:K44) -> 578121 | L46: =SUM(L28:L44) -> 479982 | M46: =SUM(M28:M44) -> 967514 | N46: =SUM(N28:N44) -> 1376346 | O46: =SUM(O28:O44) -> 390551 | P46: =SUM(P28:P44) -> 0 | Q46: =SUM(Q28:Q44) -> 2706644 | R46: =SUM(R28:R44) -> 6499158
E48: Total liabilities, deffered inflows of resources and fund balances: | K48: =K46+K25+K20 -> 651094 | L48: =L46+L25+L20 -> 612962 | M48: =M46+M25+M20 -> 1065817 | N48: =N46+N25+N20 -> 1494516 | O48: =O46+O25+O20 -> 493056 | P48: =P46+P25+P20 -> 268581 | Q48: =Q46+Q25+Q20 -> 3131653 | R48: =R46+R25+R20 -> 7717679

Sheet Ascension
D1: Ascension Combined Balance Sheet
D2: Issued: December 31, 2015
K4: General Fund | L4: East Ascension Drainage | M4: Road Project | N4: East Ascension Drainage Project | O4: Nonmajor Governmental Funds | P4: Total Governmental Funds
A5: Assets:
B6: Cash and cash equivalents | K6: 5648893 | L6: 5955781 | M6: 3389546 | N6: 2002929 | O6: 14260482 | P6: =SUM(K6:O6) -> 31257631
B7: Investments | K7: 28724249 | L7: 28865877 | M7: 16841615 | N7: 26025996 | O7: 30077557 | P7: =SUM(K7:O7) -> 130535294
B8: Accounts receivable, net
C9: Ad valorem taxes | K9: 4324287 | L9: 5376980 | O9: 20255720 | P9: =SUM(K9:O9) -> 29956987
C10: Sales and use taxes | K10: 3556195 | L10: 1122416 | P10: =SUM(K10:O10) -> 4678611
C11: Other | K11: 597421 | L11: 86292 | M11: 46714 | N11: 27604 | O11: 325909 | P11: =SUM(K11:O11) -> 1083940
B12: Due from other governments
C13: LA - State revenue sharing | K13: 89772 | L13: 156822 | O13: 642656 | P13: =SUM(K13:O13) -> 889250
C14: LA -Severence | K14: 21378 | P14: =SUM(K14:O14) -> 21378
C15: LA - Beer and Parish Transportation | K15: 18569 | P15: =SUM(K15:O15) -> 18569
C16: Grants | K16: 1096579 | L16: 244823 | M16: 52620 | O16: 3016465 | P16: =SUM(K16:O16) -> 4410487
B17: Due from other funds | K17: 10 | L17: 117437 | M17: 653664 | O17: 1067499 | P17: =SUM(K17:O17) -> 1838610
B18: Prepaid and other assets | K18: 500 | O18: 94092 | P18: =SUM(K18:O18) -> 94592
E20: Total assets: | K20: =SUM(K6:K18) -> 44077853 | L20: =SUM(L6:L18) -> 41926428 | M20: =SUM(M6:M18) -> 20984159 | N20: =SUM(N6:N18) -> 28056529 | O20: =SUM(O6:O18) -> 69740380 | P20: =SUM(P6:P18) -> 204785349
A22: LIABILITIES, DEFERRED INFLOWS OF RESOURCES, AND FUND BALANCE
B23: Liabilities:
C24: Accounts payable | K24: 591306 | L24: 298191 | O24: 637675 | P24: =SUM(K24:O24) -> 1527172
C25: Contracts payable | K25: 40170 | L25: 146229 | M25: 1403928 | N25: 1304357 | O25: 2212013 | P25: =SUM(K25:O25) -> 5106697
C26: Accrued payroll | K26: 276060 | L26: 97188 | O26: 302062 | P26: =SUM(K26:O26) -> 675310
C27: Deductions from ad valorem taxes: | P27: =SUM(K27:O27) -> 0
D28: Contribution to retirement system | K28: 142818 | L28: 177439 | O28: 670974 | P28: =SUM(K28:O28) -> 991231
C29: Due to other funds | K29: 1838600 | O29: 5 | P29: =SUM(K29:O29) -> 1838605
C30: Due to other governments | K30: 2500 | L30: 269707 | O30: 200000 | P30: =SUM(K30:O30) -> 472207
C31: Sales tax rebate escrow | K31: 4759700 | P31: =SUM(K31:O31) -> 4759700
C32: Unearned revenue | O32: 414404 | P32: =SUM(K32:O32) -> 414404
E34: Total liabilities: | K34: =SUM(K24:K32) -> 7651154 | L34: =SUM(L24:L32) -> 988754 | M34: =SUM(M24:M32) -> 1403928 | N34: =SUM(N24:N32) -> 1304357 | O34: =SUM(O24:O32) -> 4437133 | P34: =SUM(P24:P32) -> 15785326
A36: DEFERRED INFLOWS OF RESOURCES
B37: Unavailable revenue | K37: 209419 | L37: 304 | M37: 52620 | O37: 1489747 | P37: =SUM(K37:O37) -> 1752090
E39: Total deferred inflows: | K39: =SUM(K37:K37) -> 209419 | L39: =SUM(L37:L37) -> 304 | M39: =SUM(M37:M37) -> 52620 | N39: =SUM(N37:N37) -> 0 | O39: =SUM(O37:O37) -> 1489747 | P39: =SUM(P37:P37) -> 1752090
B41: Fund Balances:
C42: Nonspendable: | O42: 94092 | P42: =SUM(K42:O42) -> 94092
C43: Restricted for:
D44: Construction of capital assets | M44: 2986717 | N44: 26752172 | O44: 9535502 | P44: =SUM(K44:O44) -> 39274391
D45: Debt service | O45: 2528147 | P45: =SUM(K45:O45) -> 2528147
D46: Fire protection | O46: 19779144 | P46: =SUM(K46:O46) -> 19779144
D47: Drainage maintenance | L47: 36090453 | O47: 1534322 | P47: =SUM(K47:O47) -> 37624775
D48: Health and mental health services | O48: 3697885 | P48: =SUM(K48:O48) -> 3697885
D49: Law enforcement | O49: 39454 | P49: =SUM(K49:O49) -> 39454
D50: Road lighting | O50: 2135226 | P50: =SUM(K50:O50) -> 2135226
D51: Juvenile detention | K51: 1654557 | P51: =SUM(K51:O51) -> 1654557
D52: Hazard mitigation | O52: 1342493 | P52: =SUM(K52:O52) -> 1342493
D53: Other purposes | K53: 311600 | O53: 1754707 | P53: =SUM(K53:O53) -> 2066307
C54: Committed for:
D55: Construction of capital assets | M55: 16540894 | O55: 4003347 | P55: =SUM(K55:O55) -> 20544241
D56: Culture and recreation | K56: 4094479 | P56: =SUM(K56:O56) -> 4094479
D57: Drainage maintenance | L57: 4846917 | O57: 130619 | P57: =SUM(K57:O57) -> 4977536
D58: Health and mental health services | O58: 5320424 | P58: =SUM(K58:O58) -> 5320424
D59: Law enforcement | K59: 592760 | P59: =SUM(K59:O59) -> 592760
D60: Road lighting | O60: 460671 | P60: =SUM(K60:O60) -> 460671
D61: Culture and recreation | O61: 10638691 | P61: =SUM(K61:O61) -> 10638691
D62: Other purposes | K62: 162189 | O62: 882665 | P62: =SUM(K62:O62) -> 1044854
C63: Unassigned | K63: 29401695 | P63: =SUM(K63:O63) -> 29401695
E65: Total fund balance: | K65: =SUM(K42:K63) -> 36217280 | L65: =SUM(L42:L63) -> 40937370 | M65: =SUM(M42:M63) -> 19527611 | N65: =SUM(N42:N63) -> 26752172 | O65: =SUM(O42:O63) -> 63877389 | P65: =SUM(P42:P63) -> 187311822
E67: Total liabilities. Deferred inflows of resources, and fund balances: | K67: =K65+K39+K34 -> 44077853 | L67: =L65+L39+L34 -> 41926428 | M67: =M65+M39+M34 -> 20984159 | N67: =N65+N39+N34 -> 28056529 | O67: =O65+O39+O34 -> 69804269 | P67: =P65+P39+P34 -> 204849238

Sheet Assumption
D1: Assumption Combined Balance Sheet
D2: Issued: December 31, 2015
K4: General Fund | L4: Sales and Use Tax | M4: Solid Waste | N4: Section Eight Housing | O4: Community Development Block Grant | P4: LCDBG Disaster Recovery Program | Q4: Road Improvement Tax Fund | R4: Other Non-major Governmental Funds | S4: Total Governmental Funds
A5: Assets:
B6: Cash and cash equivalents | K6: 3105425 | L6: 236494 | M6: 136686 | N6: 12532 | Q6: 135336 | R6: 1429195 | S6: =SUM(K6:R6) -> 5055668
B7: Investments | K7: 3327782 | L7: 1765594 | M7: 1015459 | Q7: 1030309 | R7: 7584524 | S7: =SUM(K7:R7) -> 14723668
B8: Receivables | K8: 1007456 | L8: 250245 | M8: 185991 | N8: 594 | O8: 729295 | P8: 733546 | Q8: 80858 | R8: 3002965 | S8: =SUM(K8:R8) -> 5990950
B9: Due from other funds | K9: 633553 | R9: 14012 | S9: =SUM(K9:R9) -> 647565
B10: Other assets | P10: 135412 | R10: 3623 | S10: =SUM(K10:R10) -> 139035
E12: Total assets: | K12: =SUM(K6:K10) -> 8074216 | L12: =SUM(L6:L10) -> 2252333 | M12: =SUM(M6:M10) -> 1338136 | N12: =SUM(N6:N10) -> 13126 | P12: =SUM(P6:P10) -> 868958 | S12: =SUM(S6:S10) -> 26556886
A14: LIABILITIES AND FUND BALANCES
B15: Liabilities:
C16: Accounts payable | K16: 63575 | L16: 14599 | M16: 206 | N16: 66 | O16: 138919 | P16: 725072 | R16: 734997 | S16: =SUM(K16:R16) -> 1677434
C17: Salaries payable | K17: 5640 | L17: 6338 | R17: 32402 | S17: =SUM(K17:R17) -> 44380
C18: Due to other funds | K18: 4612 | L18: 2996 | O18: 590376 | P18: 8474 | R18: 41107 | S18: =SUM(K18:R18) -> 647565
C19: Other liabilities | K19: 240044 | L19: 14320 | P19: 135412 | Q19: 101898 | R19: 216217 | S19: =SUM(K19:R19) -> 707891
E21: Total liabilities: | K21: =SUM(K16:K19) -> 313871 | L21: =SUM(L16:L19) -> 38253 | M21: =SUM(M16:M19) -> 206 | N21: =SUM(N16:N19) -> 66 | O21: =SUM(O16:O19) -> 729295 | P21: =SUM(P16:P19) -> 868958 | Q21: =SUM(Q16:Q19) -> 101898 | R21: =SUM(R16:R19) -> 1024723 | S21: =SUM(S16:S19) -> 3077270
B23: Fund Balances
C24: Restricted | L24: 2214080 | N24: 23 | Q24: 1144605 | R24: 10133638 | S24: =SUM(K24:R24) -> 13492346
C25: Assigned | K25: 40645 | M25: 1337930 | N25: 13037 | R25: 875958 | S25: =SUM(K25:R25) -> 2267570
C26: Unassigned | K26: 7719700 | S26: =SUM(K26:R26) -> 7719700
E28: Total fund balance: | K28: =SUM(K24:K26) -> 7760345 | L28: =SUM(L24:L26) -> 2214080 | M28: =SUM(M24:M26) -> 1337930 | N28: =SUM(N24:N26) -> 13060 | O28: =SUM(O24:O26) -> 0 | P28: =SUM(P24:P26) -> 0 | Q28: =SUM(Q24:Q26) -> 1144605 | R28: =SUM(R24:R26) -> 11009596 | S28: =SUM(S24:S26) -> 23479616
E30: Total liabilities and fund balances: | K30: =SUM(K28,K21) -> 8074216 | L30: =SUM(L28,L21) -> 2252333 | M30: =SUM(M28,M21) -> 1338136 | N30: =SUM(N28,N21) -> 13126 | O30: =SUM(O28,O21) -> 729295 | P30: =SUM(P28,P21) -> 868958 | Q30: =SUM(Q28,Q21) -> 1246503 | R30: =SUM(R28,R21) -> 12034319 | S30: =SUM(S28,S21) -> 26556886

Sheet Avoyelles
D1: Avoyelles Combined Balance Sheet
D2: Issued: December 31, 2015
K4: General | L4: Road & Bridge | M4: Solid Waste | N4: Drainage | O4: Health Unit | P4: Library | Q4: Section 8 | R4: LCDBG Ike Gustav | S4: Other Governmental Funds | T4: Total Governmental Funds
A5: Assets:
B6: Cash and interest-bearing deposits | K6: 855612 | L6: 1028184 | M6: 4191293 | N6: 621908 | O6: 2058472 | P6: 1272452 | Q6: 213029 | R6: 319 | S6: 280938 | T6: =SUM(K6:S6) -> 10522207
B7: Receivables, net | K7: 18000 | Q7: 6998 | S7: 8791 | T7: =SUM(K7:S7) -> 33789
B8: Due from other governmental units | K8: 406664 | L8: 131384 | M8: 284617 | N8: 410957 | O8: 469734 | P8: 727864 | R8: 140655 | S8: 4054 | T8: =SUM(K8:S8) -> 2575929
B9: Due from other funds | S9: 3376 | T9: =SUM(K9:S9) -> 3376
B10: Prepaid items | K10: 15525 | L10: 20690 | M10: 22959 | N10: 17285 | O10: 8719 | P10: 19924 | Q10: 60 | S10: 3668 | T10: =SUM(K10:S10) -> 108830
E12: Total Assets: | K12: =SUM(K6:K10) -> 1295801 | L12: =SUM(L6:L10) -> 1180258 | M12: =SUM(M6:M10) -> 4498869 | N12: =SUM(N6:N10) -> 1050150 | O12: =SUM(O6:O10) -> 2536925 | P12: =SUM(P6:P10) -> 2020240 | Q12: =SUM(Q6:Q10) -> 220087 | R12: =SUM(R6:R10) -> 140974 | ... T12: =SUM(T6:T10) -> 13244131
A14: LIABILITIES, DEFERRED INFLOWS OF RESOURCES AND FUND BALANCES
B16: Liabilities:
C17: Accounts, salaries, and other payables | K17: 124365 | L17: 110779 | M17: 188005 | N17: 23002 | O17: 22806 | P17: 56159 | Q17: 2798 | R17: 140655 | S17: 20568 | T17: =SUM(K17:S17) -> 689137
C18: Unearned revenue | Q18: 36260 | T18: =SUM(K18:S18) -> 36260
C19: Due to other funds | K19: 1546 | S19: 1830 | T19: =SUM(K19:S19) -> 3376
C20: Due to other governments | K20: 59537 | L20: 6467 | T20: =SUM(K20:S20) -> 66004
E22: Total liabilities: | K22: =SUM(K17:K20) -> 185448 | L22: =SUM(L17:L20) -> 117246 | M22: =SUM(M17:M20) -> 188005 | N22: =SUM(N17:N21) -> 23002 | O22: =SUM(O17:O20) -> 22806 | P22: =SUM(P17:P20) -> 56159 | Q22: =SUM(Q17:Q20) -> 39058 | R22: =SUM(R17:R20) -> 140655 | S22: =SUM(S17:S20) -> 22398 | T22: =SUM(T17:T20) -> 794777
A24: DEFERRED INFLOWS OF RESOURCES
C25: Unavailable revenue | K25: 43264 | N25: 70453 | O25: 80648 | P25: 124787 | T25: =SUM(K25:S25) -> 319152
B27: Fund Balances
C28: Nonspendable | K28: 15525 | L28: 20690 | M28: 22959 | N28: 17285 | O28: 8719 | P28: 19924 | Q28: 60 | S28: 3668 | T28: =SUM(K28:S28) -> 108830
C29: Restricted | T29: =SUM(K29:S29) -> 0
D30: Public safety | S30: 7063 | T30: =SUM(K30:S30) -> 7063
D31: Public works | L31: 1042322 | M31: 4287905 | N31: 939410 | R31: 319 | S31: 74541 | T31: =SUM(K31:S31) -> 6344497
D32: Health and welfare | O32: 2424752 | Q32: 180969 | T32: =SUM(K32:S32) -> 2605721
D33: Culture and recreation | P33: 1819370 | T33: =SUM(K33:S33) -> 1819370
D34: Economic development | S34: 204739 | T34: =SUM(K34:S34) -> 204739
C35: Unassigned (deficit) | K35: 1051564 | S35: -11582 | T35: =SUM(K35:S35) -> 1039982
E37: Total fund balance: | K37: =SUM(K28:K36) -> 1067089 | L37: =SUM(L28:L35) -> 1063012 | M37: =SUM(M28:M35) -> 4310864 | N37: =SUM(N28:N35) -> 956695 | O37: =SUM(O28:O35) -> 2433471 | P37: =SUM(P28:P35) -> 1839294 | Q37: =SUM(Q28:Q35) -> 181029 | R37: =SUM(R28:R35) -> 319 | S37: =SUM(S28:S35) -> 278429 | T37: =SUM(T28:T35) -> 12130202
E39: Total liabilities and fund balances: | K39: =SUM(K37+K25+K22) -> 1295801 | L39: =SUM(L37+L25+L22) -> 1180258 | M39: =SUM(M37+M25+M22) -> 4498869 | N39: =SUM(N37+N25+N22) -> 1050150 | O39: =SUM(O37+O25+O22) -> 2536925 | P39: =SUM(P37+P25+P22) -> 2020240 | Q39: =SUM(Q37+Q25+Q22) -> 220087 | R39: =SUM(R37+R25+R22) -> 140974 | ... T39: =SUM(T37+T25+T22) -> 13244131

Sheet Beauregard
D1: Beauregard Combined Balance Sheet
D2: Issued: December 31, 2015
K4: General Fund | L4: Parishwide Road Special Revenue | M4: Road District No. 6 Special Revenue | N4: Sales Tax District No. 1 Special Revenue | O4: Health Unit Special Revenue | P4: South Beau. Rec. Dist. No. 2 Special Revenue | Q4: Courthouse Sales Tax Special Revenue | R4: Courthouse Renovation Capital Project | S4: Nonmajor Governmental Funds | T4: Total Governmental Funds
A5: Assets:
B6: Equity in pooled cash | K6: 145177 | L6: 1569627 | M6: 393160 | N6: 4774356 | O6: 2121897 | Q6: 2634695 | R6: 9164133 | S6: 4717507 | T6: =SUM(K6:S6) -> 25520552
B7: Receivables | K7: 1222735 | L7: 36204 | M7: 968633 | N7: 428863 | O7: 515610 | P7: 531092 | Q7: 129309 | S7: 2593006 | T7: =SUM(K7:S7) -> 6425452
B8: Interfund receivable | K8: 107332 | L8: 11404 | T8: =SUM(K8:S8) -> 118736
B9: Inventory | M9: 54053 | S9: 280629 | T9: =SUM(K9:S9) -> 334682
B10: Prepaid iterms | K10: 226353 | T10: =SUM(K10:S10) -> 226353
E12: Total assets: | K12: =SUM(K6:K10) -> 1701597 | L12: =SUM(L6:L10) -> 1617235 | M12: =SUM(M6:M10) -> 1415846 | N12: =SUM(N6:N10) -> 5203219 | O12: =SUM(O6:O10) -> 2637507 | P12: =SUM(P6:P10) -> 531092 | Q12: =SUM(Q6:Q10) -> 2764004 | R12: =SUM(R6:R10) -> 9164133 | ... T12: =SUM(T6:T10) -> 32625775
A14: LIABILITIES
B15: Liabilities:
C16: Accounts payable | K16: 273323 | L16: 29583 | M16: 20059 | N16: 128239 | O16: 535 | P16: 67905 | Q16: 3671 | R16: 472197 | S16: 103737 | T16: =SUM(K16:S16) -> 1099249
C17: Contracts payable | M17: 77583 | R17: 153725 | T17: =SUM(K17:S17) -> 231308
C18: Payroll liabilities | K18: 201087 | T18: =SUM(K18:S18) -> 201087
C19: Interfund payable | P19: 92033 | S19: 26703 | T19: =SUM(K19:S19) -> 118736
E21: Total liabilities: | K21: =SUM(K16:K19) -> 474410 | L21: =SUM(L16:L19) -> 29583 | M21: =SUM(M16:M19) -> 97642 | N21: =SUM(N16:N19) -> 128239 | O21: =SUM(O16:O19) -> 535 | P21: =SUM(P16:P19) -> 159938 | Q21: =SUM(Q16:Q19) -> 3671 | R21: =SUM(R16:R19) -> 625922 | ... T21: =SUM(T16:T19) -> 1650380
A23: DEFERRED INFLOWS OF RESOURCES
B24: Unavailable revenue | K24: 117403 | M24: 57515 | O24: 60331 | P24: 28866 | S24: 165109 | T24: =SUM(K24:S24) -> 429224
C25: Total deferred inflows of resources | K25: =K24 -> 117403 | L25: =L24 -> 0 | M25: =M24 -> 57515 | N25: =N24 -> 0 | O25: =O24 -> 60331 | P25: =P24 -> 28866 | Q25: =Q24 -> 0 | R25: =R24 -> 0 | ... T25: =T24 -> 429224
B27: Fund Balances:
C28: Nonspendable - inventory | M28: 54053 | S28: 280629 | T28: =SUM(K28:S28) -> 334682
C29: Restricted:
D30: Purchases of equipment | L30: 744819 | T30: =SUM(K30:S30) -> 744819
D31: Public safety | S31: 1932609 | T31: =SUM(K31:S31) -> 1932609
D32: Public works | L32: 842833 | M32: 1206636 | S32: 3806866 | T32: =SUM(K32:S32) -> 5856335
D33: Health and welfare | O33: 2576641 | T33: =SUM(K33:S33) -> 2576641
D34: Culture and recreation | P34: 342288 | S34: 523629 | T34: =SUM(K34:S34) -> 865917
D35: Sanitation | N35: 5074980 | T35: =SUM(K35:S35) -> 5074980
D36: Other general government | S36: 325299 | T36: =SUM(K36:S36) -> 325299
D37: Capital projects | Q37: 2760333 | R37: 8538211 | S37: 260228 | T37: =SUM(K37:S37) -> 11558772
D38: Debt service | S38: 166333 | T38: =SUM(K38:S38) -> 166333
C39: Unassigned | K39: 1109784 | T39: =SUM(K39:S39) -> 1109784
E41: Total fund balance: | K41: =SUM(K28:K39) -> 1109784 | L41: =SUM(L28:L39) -> 1587652 | M41: =SUM(M28:M39) -> 1260689 | N41: =SUM(N28:N39) -> 5074980 | O41: =SUM(O28:O39) -> 2576641 | P41: =SUM(P28:P39) -> 342288 | Q41: =SUM(Q28:Q39) -> 2760333 | R41: =SUM(R28:R39) -> 8538211 | ... T41: =SUM(T28:T39) -> 30546171
E43: Total liabilities, deferred inflows of resources, and fund balances: | K43: =K41+K24+K21 -> 1701597 | L43: =L41+L24+L21 -> 1617235 | M43: =M41+M24+M21 -> 1415846 | N43: =N41+N24+N21 -> 5203219 | O43: =O41+O24+O21 -> 2637507 | P43: =P41+P24+P21 -> 531092 | Q43: =Q41+Q24+Q21 -> 2764004 | R43: =R41+R24+R21 -> 9164133 | ... T43: =T41+T24+T21 -> 32625775

Sheet Bienville
D1: Bienville Combined Balance Sheet
D2: Issued: December 31, 2015
K4: General Fund | L4: Road Maintenance | M4: Solid Waste | N4: Debt Service Fund | O4: Other Governmental Funds | P4: Total
A5: Assets:
B6: Cash and cash equivalents | K6: 4817035 | L6: 6752352 | M6: 3759965 | N6: 1249258 | O6: 279881 | P6: =SUM(K6:O6) -> 16858491
B7: Receivables | K7: 1762003 | L7: 1885884 | M7: 79106 | N7: 920773 | O7: 6836 | P7: =SUM(K7:O7) -> 4654602
E9: Total assets: | K9: =SUM(K6:K7) -> 6579038 | L9: =SUM(L6:L7) -> 8638236 | M9: =SUM(M6:M7) -> 3839071 | N9: =SUM(N6:N7) -> 2170031 | O9: =SUM(O6:O7) -> 286717 | P9: =SUM(P6:P7) -> 21513093
A11: LIABILITIES AND FUND BALANCES
B12: Liabilities:
C13: Accounts payable | K13: 92298 | L13: 25688 | M13: 97995 | O13: 600 | P13: =SUM(K13:O13) -> 216581
C14: Salaries and related payable | K14: 9398 | L14: 24128 | P14: =SUM(K14:O14) -> 33526
C15: Deferred revenues | K15: 70000 | P15: =SUM(K15:O15) -> 70000
E17: Total liabilities: | K17: =SUM(K13:K15) -> 171696 | L17: =SUM(L13:L15) -> 49816 | M17: =SUM(M13:M15) -> 97995 | N17: =SUM(N13:N15) -> 0 | O17: =SUM(O13:O15) -> 600 | P17: =SUM(P13:P15) -> 320107
B19: Fund Balances
C20: Non spendable | O20: 16 | P20: =SUM(K20:O20) -> 16
C21: Restricted | P21: =SUM(K21:O21) -> 0
D22: Other general government | O22: 175730 | P22: =SUM(K22:O22) -> 175730
D23: Public works | L23: 8558420 | M23: 3741076 | O23: 14471 | P23: =SUM(K23:O23) -> 12313967
D24: Health and welfare | O24: 57002 | P24: =SUM(K24:O24) -> 57002
D25: Economic development | O25: 36521 | P25: =SUM(K25:O25) -> 36521
C26: Assigned | N26: 2170031 | O26: 2377 | P26: =SUM(K26:O26) -> 2172408
C27: Unassigned | K27: 6407342 | P27: =SUM(K27:O27) -> 6407342
E29: Total fund balance: | K29: =SUM(K21:K27) -> 6407342 | L29: =SUM(L21:L27) -> 8558420 | M29: =SUM(M21:M27) -> 3741076 | N29: =SUM(N21:N27) -> 2170031 | O29: =SUM(O20:O27) -> 286117 | P29: =SUM(P20:P27) -> 21162986
E31: Total liabilities and fund balances: | K31: =SUM(K29,K17) -> 6579038 | L31: =SUM(L29,L17) -> 8608236 | M31: =SUM(M29,M17) -> 3839071 | N31: =SUM(N29,N17) -> 2170031 | O31: =SUM(O29,O17) -> 286717 | P31: =SUM(P29,P17) -> 21483093

Sheet Bossier
D1: Bossier Combined Balance Sheet
D2: Issued: December 31, 2015
K5: General | L5: HIghway | M5: Library | N5: Capital Improvement | O5: Corrections | P5: LCDA Sewer Construction | Q5: LCDA Sinking Fund | R5: Other Governmental Funds | S5: Total Governmental Funds
A6: Assets:
B7: Cash and cash equivalents | K7: 3995100 | L7: 4321821 | M7: 12346953 | N7: 8439777 | O7: 3069476 | P7: 210716 | Q7: 229 | R7: 9358163 | S7: =SUM(K7:R7) -> 41742235
B8: Investments | N8: 1470000 | R8: 1055000 | S8: =SUM(K8:R8) -> 2525000
B9: Receivables | K9: 2766939 | L9: 3234515 | M9: 7025554 | N9: 972382 | O9: 2832702 | R9: 1578845 | S9: =SUM(K9:R9) -> 18410937
B10: Restricted cash | P10: 2540249 | Q10: 115116 | R10: 1722767 | S10: =SUM(K10:R10) -> 4378132
B11: Restricted investment | Q11: 11092426 | S11: =SUM(K11:R11) -> 11092426
B12: Due from other funds | K12: 76015 | R12: 6373 | S12: =SUM(K12:R12) -> 82388
B13: Advance to waterworks/sewer district | P13: 8176744 | S13: =SUM(K13:R13) -> 8176744
E15: Total Assets: | K15: =SUM(K7:K13) -> 6838054 | L15: =SUM(L7:L13) -> 7556336 | M15: =SUM(M7:M13) -> 19372507 | N15: =SUM(N7:N13) -> 10882159 | O15: =SUM(O7:O13) -> 5902178 | P15: =SUM(P7:P13) -> 10927709 | Q15: =SUM(Q7:Q13) -> 11207771 | R15: =SUM(R7:R13) -> 13721148 | S15: =SUM(S7:S13) -> 86407862
A17: LIABILITIES, DEFERRED INFLOWS OF RESOURCES, AND FUND BALANCES
B18: Liabilities:
C19: Accounts payable | K19: 313294 | L19: 594891 | M19: 451210 | N19: 394648 | O19: 283180 | R19: 473789 | S19: =SUM(K19:R19) -> 2511012
C20: Due to other funds | L20: 55782 | N20: 11300 | R20: 15306 | S20: =SUM(K20:R20) -> 82388
E22: Total liabilities: | K22: =SUM(K19:K20) -> 313294 | L22: =SUM(L19:L20) -> 650673 | M22: =SUM(M19:M20) -> 451210 | N22: =SUM(N19:N20) -> 405948 | O22: =SUM(O19:O20) -> 283180 | P22: =SUM(P19:P20) -> 0 | Q22: =SUM(Q19:Q20) -> 0 | R22: =SUM(R19:R20) -> 489095 | S22: =SUM(S19:S20) -> 2593400
A24: DEFERRED INFLOWS OF RESROUCES
B25: Unavailable revenue
C26: Property taxes | K26: 1936976 | L26: 1966410 | M26: 7405923 | O26: 2934970 | R26: 812023 | S26: =SUM(K26:R26) -> 15056302
C27: Other | K27: 13218 | L27: 177171 | M27: 6609 | R27: 35073 | S27: =SUM(K27:R27) -> 232071
E29: Total deferred inflows of resources | K29: =SUM(K25:K27) -> 1950194 | L29: =SUM(L25:L27) -> 2143581 | M29: =SUM(M25:M27) -> 7412532 | N29: =SUM(N25:N27) -> 0 | O29: =SUM(O25:O27) -> 2934970 | P29: =SUM(P25:P27) -> 0 | Q29: =SUM(Q25:Q27) -> 0 | R29: =SUM(R25:R27) -> 847096 | S29: =SUM(S25:S27) -> 15288373
B31: Fund Balances
C32: Nonspendable | P32: 8176744 | S32: =SUM(K32:R32) -> 8176744
C33: Restricted | M33: 9460640 | N33: 10324362 | O33: 944556 | P33: 2750965 | Q33: 11207771 | R33: 4401935 | S33: =SUM(K33:R33) -> 39090229
C34: Assigned | K34: 1570876 | L34: 4762082 | M34: 2048125 | N34: 151849 | O34: 1739472 | R34: 7983022 | S34: =SUM(K34:R34) -> 18255426
C35: Unassigned | K35: 3003690 | S35: =SUM(K35:R35) -> 3003690
E37: Total fund balance: | K37: =SUM(K32:K35) -> 4574566 | L37: =SUM(L32:L35) -> 4762082 | M37: =SUM(M32:M35) -> 11508765 | N37: =SUM(N32:N35) -> 10476211 | O37: =SUM(O32:O35) -> 2684028 | P37: =SUM(P32:P35) -> 10927709 | Q37: =SUM(Q32:Q35) -> 11207771 | R37: =SUM(R32:R35) -> 12384957 | S37: =SUM(S32:S35) -> 68526089
E39: Total liabilities, deffered inflows of resources and fund balances: | K39: =SUM(K22+K29+K37) -> 6838054 | L39: =SUM(L22+L29+L37) -> 7556336 | M39: =SUM(M22+M29+M37) -> 19372507 | N39: =SUM(N22+N29+N37) -> 10882159 | O39: =SUM(O22+O29+O37) -> 5902178 | P39: =SUM(P22+P29+P37) -> 10927709 | Q39: =SUM(Q22+Q29+Q37) -> 11207771 | R39: =SUM(R22+R29+R37) -> 13721148 | S39: =SUM(S22+S29+S37) -> 86407862

Sheet Caddo
D1: Caddo Combined Balance Sheet
D2: Issued: December 31, 2015
K4: General Fund | L4: Detention Facilities Fund | M4: Solid Waste Disposal Fund | N4: Public Works Fund | O4: Head Start Fund | P4: Biomedical Fund | Q4: Capital Outlay Fund | R4: Criminal Justice Fund | S4: Other Governmental Funds | T4: Total Governmental Funds
A5: Assets:
B6: Cash and cash equivalents | K6: 2165963 | L6: 31620 | M6: 1001500 | N6: 684819 | Q6: 623277 | S6: 168362 | T6: =SUM(K6:S6) -> 4675541
B7: Investments | K7: 43345664 | L7: 667041 | M7: 20981526 | N7: 14336882 | Q7: 13060286 | S7: 24471578 | T7: =SUM(K7:S7) -> 116862977
B8: Receivables, net:
C9: Ad valorem taxes | K9: 6502121 | L9: 8255761 | N9: 6453859 | P9: 2737122 | R9: 5027031 | S9: 14267311 | T9: =SUM(K9:S9) -> 43243205
C10: Paving assessments | N10: 151647 | T10: =SUM(K10:S10) -> 151647
C11: Other | K11: 9693 | L11: 247 | M11: 6556 | S11: 174972 | T11: =SUM(K11:S11) -> 191468
C12: Accrued interest | K12: 139030 | L12: 2030 | M12: 64285 | N12: 43949 | Q12: 40007 | S12: 74978 | T12: =SUM(K12:S12) -> 364279
B13: Due from other funds | K13: 1202730 | L13: 60455 | M13: 545051 | N13: 428333 | Q13: 400320 | S13: 1283979 | T13: =SUM(K13:S13) -> 3920868
B14: Due from other governments | K14: 194831 | L14: 159204 | M14: 280350 | N14: 934684 | P14: 45356 | R14: 81957 | S14: 578176 | T14: =SUM(K14:S14) -> 2274558
B15: Inventories | N15: 115369 | T15: =SUM(K15:S15) -> 115369
B16: Other assets | N16: 19512 | T16: =SUM(K16:S16) -> 19512
E18: Total assets: | K18: =SUM(K6:K16) -> 53560032 | L18: =SUM(L6:L16) -> 9176358 | M18: =SUM(M6:M16) -> 22879268 | N18: =SUM(N6:N16) -> 23169054 | O18: =SUM(O6:O16) -> 0 | P18: =SUM(P6:P16) -> 2782478 | Q18: =SUM(Q6:Q16) -> 14123890 | R18: =SUM(R6:R16) -> 5108988 | ... T18: =SUM(T6:T16) -> 171819424
A20: LIABILITIES AND FUND BALANCES
B21: Liabilities:
C22: Accounts payable | K22: 53144 | L22: 89303 | M22: 167196 | N22: 368299 | P22: 659281 | Q22: 1225550 | S22: 411239 | T22: =SUM(K22:S22) -> 2974012
C23: Accrued liabilities | K23: 32433 | L23: 8945 | M23: 16978 | N23: 47058 | S23: 117586 | T23: =SUM(K23:S23) -> 223000
C24: Retainage payable | Q24: 405543 | T24: =SUM(K24:S24) -> 405543
C25: Due to other funds | P25: 1519906 | R25: 2732500 | T25: =SUM(K25:S25) -> 4252406
C26: Unearned revenue | K26: 34465 | T26: =SUM(K26:S26) -> 34465
C27: Due to component units | L27: 893500 | T27: =SUM(K27:S27) -> 893500
C28: Due to other governments | K28: 15014 | M28: 3460 | N28: 7822 | R28: 161984 | S28: 94680 | T28: =SUM(K28:S28) -> 282960
E30: Total liabilities: | K30: =SUM(K22:K28) -> 135056 | L30: =SUM(L22:L28) -> 991748 | M30: =SUM(M22:M28) -> 187634 | N30: =SUM(N22:N28) -> 423179 | O30: =SUM(O22:O28) -> 0 | P30: =SUM(P22:P28) -> 2179187 | Q30: =SUM(Q22:Q28) -> 1631093 | R30: =SUM(R22:R28) -> 2894484 | ... T30: =SUM(T22:T28) -> 9065886
A32: DEFERRED INFLOWS OF RESOURCES
B33: Unavailable revenue - property taxes | K33: 47879 | L33: 62643 | N33: 39798 | P33: 10584 | R33: 22127 | S33: 84863 | T33: =SUM(K33:S33) -> 267894
B34: Unavailable revenue - special assessments | N34: 56265 | T34: =SUM(K34:S34) -> 56265
E36: Total deferred inflows: | K36: =SUM(K33:K34) -> 47879 | L36: =SUM(L33:L34) -> 62643 | M36: =SUM(M33:M34) -> 0 | N36: =SUM(N33:N34) -> 96063 | O36: =SUM(O33:O34) -> 0 | P36: =SUM(P33:P34) -> 10584 | Q36: =SUM(Q33:Q34) -> 0 | R36: =SUM(R33:R34) -> 22127 | ... T36: =SUM(T33:T34) -> 324159
B38: Fund Balances:
C39: Restricted for:
D40: Criminal justice | L40: 7419892 | R40: 2164345 | S40: 4115816 | T40: =SUM(K40:S40) -> 13700053
D41: Health and welfare | S41: 4598423 | T41: =SUM(K41:S41) -> 4598423
D42: Highways, streets and drainage | N42: 17760128 | T42: =SUM(K42:S42) -> 17760128
D43: Building facilities | S43: 8149857 | T43: =SUM(K43:S43) -> 8149857
D44: Sanitation | M44: 21151391 | T44: =SUM(K44:S44) -> 21151391
D45: Culture and recreation | S45: 3114732 | T45: =SUM(K45:S45) -> 3114732
D46: Economic development | P46: 213504 | T46: =SUM(K46:S46) -> 213504
D47: Debt service | S47: 3161513 | T47: =SUM(K47:S47) -> 3161513
D48: Capital projects | Q48: 12492797 | S48: 7164738 | T48: =SUM(K48:S48) -> 19657535
C49: Committed to:
D50: Contingencies | K50: 37568272 | T50: =SUM(K50:S50) -> 37568272
D51: Economic development | S51: 1498895 | T51: =SUM(K51:S51) -> 1498895
D52: Subsequent year's expenditures | K52: 1765245 | L52: 702075 | M52: 1540243 | N52: 4889684 | P52: 379203 | R52: 28032 | S52: 1635601 | T52: =SUM(K52:S52) -> 10940083
C53: Assigned to:
D54: Special services | S54: 7871413 | T54: =SUM(K54:S54) -> 7871413
D55: Future claims | K55: 600000 | T55: =SUM(K55:S55) -> 600000
C56: Unassigned | K56: 15443580 | T56: =SUM(K56:S56) -> 15443580
E58: Total fund balance: | K58: =SUM(K39:K56) -> 55377097 | L58: =SUM(L39:L56) -> 8121967 | M58: =SUM(M39:M56) -> 22691634 | N58: =SUM(N39:N56) -> 22649812 | O58: =SUM(O39:O56) -> 0 | P58: =SUM(P39:P56) -> 592707 | Q58: =SUM(Q39:Q56) -> 12492797 | R58: =SUM(R39:R56) -> 2192377 | ... T58: =SUM(T39:T56) -> 165429379
E60: Total liabilities. Deferred inflows, and fund balances: | K60: =K58+K36+K30 -> 55560032 | L60: =L58+L36+L30 -> 9176358 | M60: =M58+M36+M30 -> 22879268 | N60: =N58+N36+N30 -> 23169054 | O60: =O58+O36+O30 -> 0 | P60: =P58+P36+P30 -> 2782478 | Q60: =Q58+Q36+Q30 -> 14123890 | R60: =R58+R36+R30 -> 5108988 | ... T60: =T58+T36+T30 -> 174819424

Sheet Calcasieu
D1: Calcasieu Combined Balance Sheet
D2: Issued: December 31, 2015
K4: General Fund | L4: Public Works Operating Fund | M4: Office of Juvenille Justice Services Fund | N4: Calcasieu Parish Library Fund | O4: Road Capital Improvement Fund | P4: Nonmajor Governmental Funds | Q4: Total Governmental Funds
A5: Assets:
B6: Cash and Cash Equivalents | K6: 10931817 | L6: 4523372 | M6: 1232339 | N6: 1126793 | O6: 21177168 | P6: 7630364 | Q6: =SUM(K6:P6) -> 46621853
B7: Investments | K7: 56198681 | L7: 23764364 | M7: 6771928 | N7: 6183676 | O7: 117512490 | P7: 37003077 | Q7: =SUM(K7:P7) -> 247434216
B8: Receivable (net of allowance for uncollectibles):
C9: Property taxes | K9: 12319577 | M9: 6271772 | N9: 10372119 | O9: 6296084 | P9: 14249394 | Q9: =SUM(K9:P9) -> 49508946
C10: Sales taxes | L10: 1454093 | O10: 3180894 | P10: 566667 | Q10: =SUM(K10:P10) -> 5201654
C11: Franchise taxes | K11: 315760 | Q11: =SUM(K11:P11) -> 315760
B12: Interest receivable | K12: 98232 | L12: 39585 | M12: 12418 | N12: 11939 | O12: 193032 | P12: 64767 | Q12: =SUM(K12:P12) -> 419973
B13: Other receivables | K13: 3858732 | L13: 50000 | M13: 20587 | N13: 29 | O13: 2000000 | P13: 28047 | Q13: =SUM(K13:P13) -> 5957395
B14: Intergovernmental receivable | K14: 395131 | L14: 3780 | M14: 242578 | O14: 120780 | P14: 1952057 | Q14: =SUM(K14:P14) -> 2714326
B15: Due from other funds | K15: 524717 | L15: 9305 | P15: 74639 | Q15: =SUM(K15:P15) -> 608661
B16: Loans receivable | K16: 25764 | Q16: =SUM(K16:P16) -> 25764
B17: Prepaid items | K17: 1226 | L17: 575 | M17: 31675 | N17: 465 | P17: 278562 | Q17: =SUM(K17:P17) -> 312503
B18: Inventory | L18: 695170 | P18: 302877 | Q18: =SUM(K18:P18) -> 998047
E20: Total assets: | K20: =SUM(K6:K18) -> 84669637 | L20: =SUM(L6:L18) -> 30540244 | M20: =SUM(M6:M18) -> 14583297 | N20: =SUM(N6:N18) -> 17695021 | O20: =SUM(O6:O18) -> 150480448 | P20: =SUM(P6:P18) -> 62150451 | Q20: =SUM(Q6:Q18) -> 360119098
A22: LIABILITIES AND FUND BALANCES
B23: Liabilities:
C24: Accounts payable | K24: 1653550 | L24: 371543 | M24: 88725 | N24: 195730 | O24: 818981 | P24: 2621682 | Q24: =SUM(K24:P24) -> 5750211
C25: Accrued liabilities | K25: 351520 | L25: 261852 | M25: 132532 | N25: 162727 | P25: 135832 | Q25: =SUM(K25:P25) -> 1044463
C26: Intergovernmental payable | K26: 20000 | P26: 43080 | Q26: =SUM(K26:P26) -> 63080
C27: Due to other funds | K27: 92794 | M27: 4009 | O27: 4897 | P27: 527756 | Q27: =SUM(K27:P27) -> 629456
C28: Due to component units | K28: 12963 | L28: 13228 | P28: 34655 | Q28: =SUM(K28:P28) -> 60846
C29: Unearned revenue | K29: 157739 | O29: 2071450 | P29: 1152908 | Q29: =SUM(K29:P29) -> 3382097
C30: Retainage payable | O30: 248052 | P30: 366741 | Q30: =SUM(K30:P30) -> 614793
C31: Other liabilities | K31: 89099 | L31: 1770 | P31: 81668 | Q31: =SUM(K31:P31) -> 172537
C32: Enterprize zone rebate liability | L32: 314038 | Q32: =SUM(K32:P32) -> 314038
E34: Total liabilities: | K34: =SUM(K24:K31) -> 2377665 | L34: =SUM(L24:L32) -> 962431 | M34: =SUM(M24:M32) -> 225266 | N34: =SUM(N24:N31) -> 358457 | O34: =SUM(O24:O31) -> 3143380 | P34: =SUM(P24:P31) -> 4964322 | Q34: =SUM(Q24:Q32) -> 12031521
A36: DEFERRED INFLOWS OF RESOURCES
C37: Property taxes levied for the next fiscal year | K37: 12373150 | M37: 6314426 | N37: 10442515 | O37: 6345696 | P37: 14343941 | Q37: =SUM(K37:P37) -> 49819728
C38: Unavailable revenue | L38: 105934 | O38: 132844 | Q38: =SUM(K38:P38) -> 238778
E40: Total deferred inflows of resources | K40: =SUM(K37:K38) -> 12373150 | L40: =SUM(L37:L38) -> 105934 | M40: =SUM(M37:M38) -> 6314426 | N40: =SUM(N37:N38) -> 10442515 | O40: =SUM(O37:O38) -> 6478540 | P40: =SUM(P37:P38) -> 14343941 | Q40: =SUM(Q37:Q38) -> 50058506
B42: Fund Balances
C43: Nonspendable:
D44: Prepaid items | K44: 1226 | L44: 575 | M44: 31675 | N44: 465 | P44: 278562 | Q44: =SUM(K44:P44) -> 312503
D45: Inventories | L45: 695170 | P45: 302877 | Q45: =SUM(K45:P45) -> 998047
D46: Loans receivable | K46: 25764 | Q46: =SUM(K46:P46) -> 25764
C47: Restricted:
D48: Public works operations | L48: 28776134 | Q48: =SUM(K48:P48) -> 28776134
D49: Juvenile justice operations | M49: 8011930 | Q49: =SUM(K49:P49) -> 8011930
D50: Library purposes | N50: 6893584 | Q50: =SUM(K50:P50) -> 6893584
D51: Roads and infrastructure | O51: 140858528 | Q51: =SUM(K51:P51) -> 140858528
D52: Other restrictions | P52: 29344902 | Q52: =SUM(K52:P52) -> 29344902
C53: Assigned:
D54: Animal services | K54: 94602 | P54: 0 | Q54: =SUM(K54:P54) -> 94602
D55: Parks operations | K55: 1355829 | Q55: =SUM(K55:P55) -> 1355829
D56: Training center operations | K56: 548733 | Q56: =SUM(K56:P56) -> 548733
D57: Future capital needs | K57: 19264835 | P57: 12918446 | Q57: =SUM(K57:P57) -> 32183281
D58: Matching funds for capital grants | K58: 10500000 | Q58: =SUM(K58:P58) -> 10500000
D59: Major infrastructure | K59: 3500000 | Q59: =SUM(K59:P59) -> 3500000
D60: Cooperative endeavor agreements | K60: 2157523 | Q60: =SUM(K60:P60) -> 2157523
C61: Unassigned | K61: 32470310 | P61: -2599 | Q61: =SUM(K61:P61) -> 32467711
E63: Total fund balances: | K63: =SUM(K44:K61) -> 69918822 | L63: =SUM(L44:L61) -> 29471879 | M63: =SUM(M44:M61) -> 8043605 | N63: =SUM(N44:N61) -> 6894049 | O63: =SUM(O44:O61) -> 140858528 | P63: =SUM(P44:P61) -> 42842188 | Q63: =SUM(Q44:Q61) -> 298029071
E65: Total liabilities and fund balances: | K65: =SUM(K63,K34,K40) -> 84669637 | L65: =SUM(L63,L34,L40) -> 30540244 | M65: =SUM(M63,M34,M40) -> 14583297 | N65: =SUM(N63,N34,N40) -> 17695021 | O65: =SUM(O63,O34,O40) -> 150480448 | P65: =SUM(P63,P34,P40) -> 62150451 | Q65: =SUM(Q63,Q34,Q40) -> 360119098

Sheet Caldwell
D1: Caldwell Combined Balance Sheet
D2: Issued: December 31, 2015
K4: General Fund | L4: Road Maintenance | M4: Recreation | N4: Solid Waste | O4: Blacktop Road | P4: Bayou Dechere Resevoir | Q4: LCDBG | R4: Other Governmental Funds | S4: Total Governmental Funds
A5: Assets:
B6: Cash and Cash Equivalents | K6: 1192998 | L6: 561744 | M6: 794466 | N6: 1010200 | O6: 2077705 | P6: 97678 | Q6: 40 | R6: 1665610 | S6: =SUM(K6:R6) -> 7400441
B7: Investments | K7: 366187 | L7: 515816 | M7: 308950 | N7: 109632 | S7: =SUM(K7:R7) -> 1300585
B8: Due from other funds | K8: 2700 | L8: 25652 | R8: 36402 | S8: =SUM(K8:R8) -> 64754
E10: Total assets: | K10: =SUM(K6:K8) -> 1561885 | L10: =SUM(L6:L8) -> 1103212 | M10: =SUM(M6:M8) -> 1103416 | N10: =SUM(N6:N8) -> 1119832 | O10: =SUM(O6:O8) -> 2077705 | P10: =SUM(P6:P8) -> 97678 | Q10: =SUM(Q6:Q8) -> 40 | R10: =SUM(R6:R8) -> 1702012 | S10: =SUM(S6:S8) -> 8765780
A12: LIABILITIES AND FUND BALANCES
B13: Liabilities:
C14: Accounts payable | K14: 13881 | L14: 31237 | M14: 19448 | N14: 45919 | O14: 260584 | R14: 29588 | S14: =SUM(K14:R14) -> 400657
C15: Saleries and related payables | K15: 10661 | L15: 15263 | M15: 2241 | R15: 7980 | S15: =SUM(K15:R15) -> 36145
C16: Due to other agencies | K16: 57698 | S16: =SUM(K16:R16) -> 57698
C17: Due to other funds | K17: 62054 | L17: 2700 | S17: =SUM(K17:R17) -> 64754
E19: Total liabilities: | K19: =SUM(K14:K17) -> 144294 | L19: =SUM(L14:L17) -> 49200 | M19: =SUM(M14:M17) -> 21689 | N19: =SUM(N14:N17) -> 45919 | O19: =SUM(O14:O17) -> 260584 | P19: =SUM(P14:P17) -> 0 | Q19: =SUM(Q14:Q17) -> 0 | R19: =SUM(R14:R17) -> 37568 | S19: =SUM(S14:S17) -> 559254
B21: Fund Balances
C22: Unassigned | K22: 1417591 | S22: =SUM(K22:P22) -> 1417591
C23: Restricted | L23: 1054012 | M23: 1081727 | N23: 1073913 | O23: 1817121 | P23: 97678 | Q23: 40 | R23: 2266638 | S23: =SUM(K23:R23) -> 7391129
E25: Total fund balances: | K25: =SUM(K22:K23) -> 1417591 | L25: =SUM(L22:L23) -> 1054012 | M25: =SUM(M22:M23) -> 1081727 | N25: =SUM(N22:N23) -> 1073913 | O25: =SUM(O22:O23) -> 1817121 | P25: =SUM(P22:P23) -> 97678 | Q25: =SUM(Q22:Q23) -> 40 | R25: =SUM(R22:R23) -> 2266638 | S25: =SUM(S22:S23) -> 8808720
E27: Total liabilities and fund balances: | K27: =SUM(K25+K19) -> 1561885 | L27: =SUM(L25+L19) -> 1103212 | M27: =SUM(M25+M19) -> 1103416 | N27: =SUM(N25+N19) -> 1119832 | O27: =SUM(O25+O19) -> 2077705 | P27: =SUM(P25+P19) -> 97678 | Q27: =SUM(Q25+Q19) -> 40 | R27: =SUM(R25+R19) -> 2304206 | S27: =SUM(S25+S19) -> 9367974

Sheet Cameron
D1: Cameron Combined Balance Sheet
D2: Issued: December 31, 2015
K4: General Fund | L4: Road & Bridge Maintenance | M4: Long-Term Community Recovery | N4: Library | O4: Non-Major | P4: Total
A5: Assets:
B6: Cash | K6: 11043177 | L6: 401 | M6: 100 | N6: 1271296 | O6: 4260526 | P6: =SUM(K6:O6) -> 16575500
B7: Investments | K7: 2209031 | N7: 2113254 | O7: 7155345 | P7: =SUM(K7:O7) -> 11477630
B8: Receivables, net | K8: 7299605 | L8: 1815429 | M8: 566609 | N8: 954049 | O8: 3282928 | P8: =SUM(K8:O8) -> 13918620
B9: Inventory, at cost | K9: 1793767 | L9: 64283 | P9: =SUM(K9:O9) -> 1858050
B10: Other | K10: 72523 | L10: 48633 | N10: 51933 | O10: 24180 | P10: =SUM(K10:O10) -> 197269
B11: Interfund receivables | K11: 2366061 | L11: 234428 | N11: 842246 | O11: 1798954 | P11: =SUM(K11:O11) -> 5241689
A13: DEFERRED OUTFLOWS OF RESOURCES
E15: Total assets and deferred outflows of resources: | K15: =SUM(K6:K11) -> 24784164 | L15: =SUM(L6:L11) -> 2163174 | M15: =SUM(M6:M11) -> 566709 | N15: =SUM(N6:N11) -> 5232778 | O15: =SUM(O6:O11) -> 16521933 | P15: =SUM(P6:P11) -> 49268758
A17: LIABILITIES AND FUND BALANCES
B18: Liabilities:
C19: Accounts, salaries, and other payables | K19: 1171350 | L19: 39535 | M19: 562446 | N19: 68069 | O19: 157859 | P19: =SUM(K19:O19) -> 1999259
C20: Due to other agencies | K20: 2551196 | P20: =SUM(K20:O20) -> 2551196
C21: Unearned revenue | K21: 7413 | M21: 9818 | P21: =SUM(K21:O21) -> 17231
C22: Interfund payables | K22: 2871381 | M22: 66214 | O22: 2304094 | P22: =SUM(K22:O22) -> 5241689
E24: Total liabilities: | K24: =SUM(K19:K22) -> 6601340 | L24: =SUM(L19:L22) -> 39535 | M24: =SUM(M19:M22) -> 638478 | O24: =SUM(O19:O22) -> 2461953 | P24: =SUM(P19:P22) -> 9809375
A26: DEFERRED INFLOWS OF RESOURCES | K26: 1793767 | P26: =SUM(K26:O26) -> 1793767
E28: Total deferred inflows of resources | K28: =SUM(K26) -> 1793767 | L28: =SUM(L26) -> 0 | M28: =SUM(M26) -> 0 | N28: =SUM(N26) -> 0 | O28: =SUM(O26) -> 0 | P28: =SUM(P26) -> 1793767
B30: Fund Balances
C31: Nonspendable:
D32: Inventories | K32: 1793767 | L32: 64283 | N32: 51933 | P32: =SUM(K32:O32) -> 1909983
D33: Prepaid expenses | K33: 72523 | L33: 48633 | O33: 24180 | P33: =SUM(K33:O33) -> 145336
C34: Restricted:
D35: Judicial | O35: 48266 | P35: =SUM(K35:O35) -> 48266
D36: Debt service | O36: 646986 | P36: =SUM(K36:O36) -> 646986
D37: Tourism development | O37: 44880 | P37: =SUM(K37:O37) -> 44880
C38: Commited to:
D39: Infrastructure maintenance | L39: 2010723 | P39: =SUM(K39:O39) -> 2010723
D40: Culture and recreation | N40: 5089637 | P40: =SUM(K40:O40) -> 5089637
D41: Public safety | O41: 4611317 | P41: =SUM(K41:O41) -> 4611317
D42: Judicial | O42: 3430605 | P42: =SUM(K42:O42) -> 3430605
D43: Health and welfare | O43: 5101344 | P43: =SUM(K43:O43) -> 5101344
D44: Other purposes | K44: 343354 | P44: =SUM(K44:O44) -> 343354
C45: Assigned:
D46: Judicial | O46: 11057 | P46: =SUM(K46:O46) -> 11057
D47: Health and welfare | O47: 24648 | P47: =SUM(K47:O47) -> 24648
D48: Public safety | O48: 116697 | P48: =SUM(K48:O48) -> 116697
D49: Othercapital projects | M49: -71769 | P49: =SUM(K49:O49) -> -71769
C50: Unassigned | K50: 14179413 | N50: 23139 | P50: =SUM(K50:O50) -> 14202552
E52: Total fund balances: | K52: =SUM(K32:K50) -> 16389057 | L52: =SUM(L32:L50) -> 2123639 | M52: =SUM(M32:M50) -> -71769 | O52: =SUM(O32:O50) -> 14059980 | P52: =SUM(P32:P50) -> 37665616
E54: Total liabilities and fund balances: | K54: =SUM(K24+K28+K52) -> 24784164 | L54: =SUM(L24+L28+L52) -> 2163174 | M54: =SUM(M24+M28+M52) -> 566709 | N54: =SUM(N24+N28+N52) -> 0 | O54: =SUM(O24+O28+O52) -> 16521933 | P54: =SUM(P24+P28+P52) -> 49268758

Sheet Catahoula
D1: Catahoula Combined Balance Sheet
D2: Issued: December 31, 2015
K5: General | L5: Road and Bridge | M5: Hard Surfacing | N5: Sanitation | O5: Library | P5: Heatlh Unit | Q5: Courthouse Roof Rehabilitation | R5: Other Governmental Funds | S5: Total Governmental Funds
A6: Assets:
B7: Cash and cash equivalents | K7: 643284 | L7: 93544 | M7: 230590 | N7: 394127 | O7: 281429 | P7: 384230 | R7: 119023 | S7: =SUM(K7:R7) -> 2146227
B8: Cash restricted for debt service | R8: 27472 | S8: =SUM(K8:R8) -> 27472
B9: Cash restricted for capital project | Q9: 38193 | S9: =SUM(K9:R9) -> 38193
B10: Receivables | K10: 728877 | L10: 70383 | M10: 53608 | N10: 33505 | O10: 328111 | P10: 81893 | Q10: 120994 | R10: 69763 | S10: =SUM(K10:R10) -> 1487134
B11: Other assets | K11: 34157 | L11: 16870 | M11: 25655 | P11: 2858 | R11: 3786 | S11: =SUM(K11:R11) -> 83326
E13: Total Assets: | K13: =SUM(K7:K11) -> 1406318 | L13: =SUM(L7:L11) -> 180797 | M13: =SUM(M7:M11) -> 309853 | N13: =SUM(N7:N11) -> 427632 | O13: =SUM(O7:O11) -> 609540 | P13: =SUM(P7:P11) -> 468981 | Q13: =SUM(Q7:Q11) -> 159187 | R13: =SUM(R7:R11) -> 220044 | S13: =SUM(K13:R13) -> 3782352
A15: LIABILITIES, DEFERRED INFLOWS OF RESOURCES, AND FUND BALANCES
B16: Liabilities:
C17: Accounts payable | K17: 275889 | L17: 16405 | M17: 16403 | N17: 53004 | O17: 19547 | P17: 3719 | Q17: 252509 | R17: 3732 | S17: =SUM(K17:R17) -> 641208
C18: Salaries and related payables | K18: 3126 | L18: 5334 | M18: 4695 | R18: 2042 | S18: =SUM(K18:R18) -> 15197
E20: Total liabilities: | K20: =SUM(K17:K18) -> 279015 | L20: =SUM(L17:L18) -> 21739 | M20: =SUM(M17:M18) -> 21098 | N20: =SUM(N17:N18) -> 53004 | O20: =SUM(O17:O18) -> 19547 | P20: =SUM(P17:P18) -> 3719 | R20: =SUM(R17:R18) -> 5774 | S20: =SUM(S17:S18) -> 656405
A22: DEFERRED INFLOWS OF RESROUCES
B23: Ad valorem taxes and state revenue sharing - unavailable | K23: 39308 | O23: 30472 | P23: 7618 | R23: 18659 | S23: =SUM(K23:R23) -> 96057
E25: Total deferred inflows of resources | K25: =SUM(K23:K23) -> 39308 | L25: =SUM(L23:L23) -> 0 | M25: =SUM(M23:M23) -> 0 | N25: =SUM(N23:N23) -> 0 | O25: =SUM(O23:O23) -> 30472 | P25: =SUM(P23:P23) -> 7618 | R25: =SUM(R23:R23) -> 18659 | S25: =SUM(S23:S23) -> 96057
B27: Fund Balances
C28: Restricted | L28: 159058 | M28: 288755 | N28: 374628 | O28: 559521 | P28: 457644 | R28: 195611 | S28: =SUM(K28:R28) -> 2035217
C29: Unassigned | K29: 1087995 | Q29: -93322 | S29: =SUM(K29:R29) -> 994673
E31: Total fund balance: | K31: =SUM(K28:K29) -> 1087995 | L31: =SUM(L28:L29) -> 159058 | M31: =SUM(M28:M29) -> 288755 | N31: =SUM(N28:N29) -> 374628 | O31: =SUM(O28:O29) -> 559521 | P31: =SUM(P28:P29) -> 457644 | R31: =SUM(R28:R29) -> 195611 | S31: =SUM(S28:S29) -> 3029890
E33: Total liabilities, deffered inflows of resources and fund balances: | K33: =K20+K25+K31 -> 1406318 | L33: =L20+L25+L31 -> 180797 | M33: =M20+M25+M31 -> 309853 | N33: =N20+N25+N31 -> 427632 | O33: =O20+O25+O31 -> 609540 | P33: =P20+P25+P31 -> 468981 | R33: =R20+R25+R31 -> 220044 | S33: =S20+S25+S31 -> 3782352

Sheet Claiborne
D1: Claiborne Combined Balance Sheet
D2: Issued: December 31, 2015
K5: General | L5: Parish Road | M5: Library Maintenance | N5: Sales Tax | O5: Criminal Court | P5: Section 8 | Q5: Other Governmental Funds | R5: Total Governmental Funds
A6: Assets:
B7: Cash and cash equivalents | K7: 3626950 | L7: 91142 | M7: 756727 | N7: 955910 | O7: 76321 | P7: 60565 | Q7: 1213056 | R7: =SUM(K7:Q7) -> 6780671
B8: Investments | K8: 434153 | L8: 3042 | M8: 6252 | N8: 344316 | Q8: 5781 | R8: =SUM(K8:Q8) -> 793544
B9: Receivables | K9: 657929 | L9: 1065213 | M9: 744284 | N9: 57637 | Q9: 713435 | R9: =SUM(K9:Q9) -> 3238498
B10: Due from other funds | K10: 1094 | R10: =SUM(K10:Q10) -> 1094
B11: Due from other agencies | K11: 26079 | R11: =SUM(K11:Q11) -> 26079
B12: Deferred charges | K12: 106117 | R12: =SUM(K12:Q12) -> 106117
E14: Total Assets: | K14: =SUM(K7:K12) -> 4852322 | L14: =SUM(L7:L12) -> 1159397 | M14: =SUM(M7:M12) -> 1507263 | N14: =SUM(N7:N12) -> 1357863 | O14: =SUM(O7:O12) -> 76321 | P14: =SUM(P7:P12) -> 60565 | Q14: =SUM(Q7:Q12) -> 1932272 | R14: =SUM(R7:R12) -> 10946003
A16: LIABILITIES, DEFERRED INFLOWS OF RESOURCES, AND FUND BALANCES
B17: Liabilities:
C18: Accounts, salaries and other payables | K18: 210775 | L18: 148647 | M18: 56521 | N18: 55004 | O18: 24911 | Q18: 51778 | R18: =SUM(K18:Q18) -> 547636
C19: Due to other funds | L19: 538 | M19: 456 | Q19: 100 | R19: =SUM(K19:Q19) -> 1094
C20: Due to other agencies | P20: 14025 | R20: =SUM(K20:Q20) -> 14025
E22: Total liabilities: | K22: =SUM(K18:K20) -> 210775 | L22: =SUM(L18:L20) -> 149185 | M22: =SUM(M18:M20) -> 56977 | N22: =SUM(N18:N20) -> 55004 | O22: =SUM(O18:O20) -> 24911 | P22: =SUM(P18:P20) -> 14025 | Q22: =SUM(Q18:Q20) -> 51878 | R22: =SUM(R18:R20) -> 562755
A24: DEFERRED INFLOWS OF RESROUCES
B25: Unavailable ad valorem tax revenue | K25: 43701 | L25: 86001 | M25: 55024 | P25: 15626 | Q25: 57089 | R25: =SUM(K25:Q25) -> 257441
E27: Total deferred inflows of resources | K27: =SUM(K25:K25) -> 43701 | L27: =SUM(L25:L25) -> 86001 | M27: =SUM(M25:M25) -> 55024 | N27: =SUM(N25:N25) -> 0 | O27: =SUM(O25:O25) -> 0 | P27: =SUM(P25:P25) -> 15626 | Q27: =SUM(Q25:Q25) -> 57089 | R27: =SUM(R25:R25) -> 257441
B29: Fund Balances
C30: Restricted fund balances | K30: 369605 | L30: 924211 | M30: 1395262 | N30: 1302859 | O30: 51410 | P30: 30914 | Q30: 1823305 | R30: =SUM(K30:Q30) -> 5897566
C31: Unassigned fund balances | K31: 4228241 | R31: =SUM(K31:Q31) -> 4228241
E33: Total fund balance: | K33: =SUM(K30:K31) -> 4597846 | L33: =SUM(L30:L31) -> 924211 | M33: =SUM(M30:M31) -> 1395262 | N33: =SUM(N30:N31) -> 1302859 | O33: =SUM(O30:O31) -> 51410 | P33: =SUM(P30:P31) -> 30914 | Q33: =SUM(Q30:Q31) -> 1823305 | R33: =SUM(R30:R31) -> 10125807
E35: Total liabilities, deffered inflows of resources and fund balances: | K35: =SUM(K22+K27+K33) -> 4852322 | L35: =SUM(L22+L27+L33) -> 1159397 | M35: =SUM(M22+M27+M33) -> 1507263 | N35: =SUM(N22+N27+N33) -> 1357863 | O35: =SUM(O22+O27+O33) -> 76321 | P35: =SUM(P22+P27+P33) -> 60565 | Q35: =SUM(Q22+Q27+Q33) -> 1932272 | R35: =SUM(R22+R27+R33) -> 10946003

Sheet Concordia
D1: Concordia Combined Balance Sheet
D2: Issued: December 31, 2015
M4: Major Funds
K5: General Fund | L5: Drainage Fund | M5: Sales Tax Fund | N5: Road Debt Service Fund | O5: Highway Maintenance Fund | P5: Nonmajor Governmental Funds | Q5: Total
A6: Assets:
B7: Cash and cash equivalents | K7: 3045095 | L7: 1247237 | M7: 2053953 | O7: 552356 | P7: 997776 | Q7: =SUM(K7:P7) -> 7896417
B8: Cash and cash equivalents - restricted | N8: 2542427 | Q8: =SUM(K8:P8) -> 2542427
B9: Accounts recievable | K9: 48252 | L9: 25193 | O9: 39804 | P9: 16718 | Q9: =SUM(K9:P9) -> 129967
B10: Ad valorem taxes receivable, net | K10: 252973 | L10: 1114404 | P10: 201711 | Q10: =SUM(K10:P10) -> 1569088
B11: Sales and use taxes recievable | M11: 167250 | Q11: =SUM(K11:P11) -> 167250
B12: Severancetaxes receivable | K12: 183685 | Q12: =SUM(K12:P12) -> 183685
B13: Due from other funds | K13: 90748 | L13: 9300 | N13: 72000 | O13: 28000 | P13: 49529 | Q13: =SUM(K13:P13) -> 249577
E15: Total Assets: | K15: =SUM(K7:K13) -> 3620753 | L15: =SUM(L7:L13) -> 2396134 | M15: =SUM(M7:M13) -> 2221203 | N15: =SUM(N7:N13) -> 2614427 | O15: =SUM(O7:O13) -> 620160 | P15: =SUM(P7:P13) -> 1265734 | Q15: =SUM(Q7:Q13) -> 12738411
A17: LIABILITIES
C18: Accounts payable | K18: 31115 | L18: 1009 | M18: 26599 | O18: 9547 | P18: 148708 | Q18: =SUM(K18:P18) -> 216978
C19: Accrued payroll and benefits | K19: 45503 | L19: 25436 | O19: 14205 | P19: 7181 | Q19: =SUM(K19:P19) -> 92325
C20: Due to other funds | K20: 3729 | M20: 245848 | Q20: =SUM(K20:P20) -> 249577
E22: Total liabilities: | K22: =SUM(K18:K20) -> 80347 | L22: =SUM(L18:L20) -> 26445 | M22: =SUM(M18:M20) -> 272447 | N22: =SUM(N18:N20) -> 0 | O22: =SUM(O18:O20) -> 23752 | P22: =SUM(P18:P20) -> 155889 | Q22: =SUM(Q18:Q20) -> 558880
A24: DEFERRED INFLOWS OF RESROUCES
B25: Unavailable ad valorem taxes | K25: 12924 | L25: 56933 | P25: 10305 | Q25: =SUM(K25:P25) -> 80162
E27: Total deferred inflows of resources | K27: =SUM(K25:K25) -> 12924 | L27: =SUM(L25:L25) -> 56933 | M27: =SUM(M25:M25) -> 0 | N27: =SUM(N25:N25) -> 0 | O27: =SUM(O25:O25) -> 0 | P27: =SUM(P25:P25) -> 10305 | Q27: =SUM(Q25:Q25) -> 80162
A29: Fund Balances
C30: Restricted | L30: 2312756 | M30: 1948756 | N30: 2614427 | O30: 596408 | P30: 1019664 | Q30: =SUM(K30:P30) -> 8492011
C31: Unassigned | K31: 3527482 | P31: 79876 | Q31: =SUM(K31:P31) -> 3607358
E33: Total fund balance: | K33: =SUM(K30:K31) -> 3527482 | L33: =SUM(L30:L31) -> 2312756 | M33: =SUM(M30:M31) -> 1948756 | N33: =SUM(N30:N31) -> 2614427 | O33: =SUM(O30:O31) -> 596408 | P33: =SUM(P30:P31) -> 1099540 | Q33: =SUM(Q30:Q31) -> 12099369
E35: Total liabilities, deffered inflows of resources and fund balances: | K35: =SUM(K22+K27+K33) -> 3620753 | L35: =SUM(L22+L27+L33) -> 2396134 | M35: =SUM(M22+M27+M33) -> 2221203 | N35: =SUM(N22+N27+N33) -> 2614427 | O35: =SUM(O22+O27+O33) -> 620160 | P35: =SUM(P22+P27+P33) -> 1265734 | Q35: =SUM(Q22+Q27+Q33) -> 12738411

Sheet DeSoto
D1: DeSoto Combined Balance Sheet
D2: Issued: December 31, 2015
K4: General Fund | L4: Solid Waste Fund | M4: Road Fund | N4: Airport Fund | O4: Jail Fund | P4: Sales Tax | Q4: Other Governmental Funds | R4: Total Governmental Funds
A5: Assets:
B6: Cash and Cash Equivalents | K6: 2168096 | L6: 562724 | M6: 111109 | N6: 145874 | O6: 4729998 | P6: 3000 | Q6: 774183 | R6: =SUM(K6:Q6) -> 8494984
B7: Investments | K7: 7150213 | L7: 6744260 | M7: 10706 | N7: 6947617 | R7: =SUM(K7:Q7) -> 20852796
B8: Revenue Receivables | K8: 4095689 | L8: 4234560 | M8: 4052326 | N8: 121379 | O8: 379 | P8: 629370 | Q8: 77453 | R8: =SUM(K8:Q8) -> 13211156
B9: Inventory | N9: 26264 | R9: =SUM(K9:Q9) -> 26264
B10: Due from Other Funds | K10: 103000 | L10: 92584 | M10: 360118 | O10: 61722 | R10: =SUM(K10:Q10) -> 617424
B11: Noncurrent Receivable | M11: 42000 | R11: =SUM(K11:Q11) -> 42000
E13: Total assets: | K13: =SUM(K6:K11) -> 13516998 | L13: =SUM(L6:L11) -> 11634128 | M13: =SUM(M6:M11) -> 4576259 | N13: =SUM(N6:N11) -> 7241134 | O13: =SUM(O6:O11) -> 4792099 | P13: =SUM(P6:P11) -> 632370 | Q13: =SUM(Q6:Q11) -> 851636 | R13: =SUM(R6:R11) -> 43244624
A15: LIABILITIES AND FUND BALANCES
B16: Liabilities:
C17: Accounts payable | K17: 389042 | L17: 386303 | M17: 377047 | N17: 11112 | O17: 26107 | P17: 12147 | Q17: 156789 | R17: =SUM(K17:Q17) -> 1358547
C18: Due to other funds | K18: 22496 | L18: 29011 | P18: 465917 | Q18: 100000 | R18: =SUM(K18:Q18) -> 617424
C19: Master bank Overdrafts | N19: 50957 | R19: =SUM(K19:Q19) -> 50957
C20: Due to other governments | P20: 154306 | R20: =SUM(K20:Q20) -> 154306
C21: Advance from grantors | Q21: 18938 | R21: =SUM(K21:Q21) -> 18938
C22: Deposits | K22: 300 | R22: =SUM(K22:Q22) -> 300
E24: Total liabilities: | K24: =SUM(K17:K22) -> 411838 | L24: =SUM(L17:L22) -> 415314 | M24: =SUM(M17:M22) -> 377047 | N24: =SUM(N17:N22) -> 62069 | O24: =SUM(O17:O22) -> 26107 | P24: =SUM(P17:P22) -> 632370 | Q24: =SUM(Q17:Q22) -> 275727 | R24: =SUM(R17:R22) -> 2200472
A26: DEFERRED INFLOWS OF RESOURCES
C27: Unavailable Property Taxes | K27: 321345 | L27: 285935 | M27: 268405 | R27: =SUM(K27:Q27) -> 875685
E29: Total deferred inflows of resources | K29: =SUM(K27:K27) -> 321345 | L29: =SUM(L27:L27) -> 285935 | M29: =SUM(M27:M27) -> 268405 | N29: =SUM(N27:N27) -> 0 | O29: =SUM(O27:O27) -> 0 | P29: =SUM(P27:P27) -> 0 | Q29: =SUM(Q27:Q27) -> 0 | R29: =SUM(R27:R27) -> 875685
B31: Fund Balances
C32: Nonspendable:
D33: Inventory | N33: 26264 | R33: =SUM(K33:Q33) -> 26264
C34: Restricted: | R34: =SUM(K34:Q34) -> 0
D35: Airport | N35: 7152801 | R35: =SUM(K35:Q35) -> 7152801
D36: Judicial | Q36: 487 | R36: =SUM(K36:Q36) -> 487
D37: Public Safety | O37: 4765992 | R37: =SUM(K37:Q37) -> 4765992
D38: Roads | M38: 3930807 | R38: =SUM(K38:Q38) -> 3930807
D39: Sanitation | L39: 10932879 | R39: =SUM(K39:Q39) -> 10932879
D40: Health & Welfare | Q40: 72684 | R40: =SUM(K40:Q40) -> 72684
D41: Witness & Juror Fees | Q41: 422295 | R41: =SUM(K41:Q41) -> 422295
C42: Assigned: | R42: =SUM(K42:Q42) -> 0
D43: Animal Control | Q43: 80443 | R43: =SUM(K43:Q43) -> 80443
C44: Unassigned | K44: 12783815 | R44: =SUM(K44:Q44) -> 12783815
E46: Total fund balances: | K46: =SUM(K33:K44) -> 12783815 | L46: =SUM(L33:L44) -> 10932879 | M46: =SUM(M33:M44) -> 3930807 | N46: =SUM(N33:N44) -> 7179065 | O46: =SUM(O33:O44) -> 4765992 | P46: =SUM(P33:P44) -> 0 | Q46: =SUM(Q33:Q44) -> 575909 | R46: =SUM(R33:R44) -> 40168467
E48: Total liabilities and fund balances: | K48: =SUM(K46,K24,K29) -> 13516998 | L48: =SUM(L46,L24,L29) -> 11634128 | M48: =SUM(M46,M24,M29) -> 4576259 | N48: =SUM(N46,N24,N29) -> 7241134 | O48: =SUM(O46,O24,O29) -> 4792099 | P48: =SUM(P46,P24,P29) -> 632370 | Q48: =SUM(Q46,Q24,Q29) -> 851636 | R48: =SUM(R46,R24,R29) -> 43244624

Sheet East Baton Rouge
D1: East Baton Rouge Combined Balance Sheet
D2: Issued: December 31, 2015
K5: General Fund | L5: Library Board of Control | M5: Grants | N5: Capital Projects | O5: Other Governmental Funds | P5: Total Governmental Funds
A6: Assets:
B7: Cash and cash equivalents (note 3) | K7: 29552975 | L7: 28706421 | M7: 3722634 | N7: 55732890 | O7: 41188097 | P7: =SUM(K7:O7) -> 158903017
B8: Investments (note 3) | K8: 40811250 | L8: 39642201 | M8: 5140781 | N8: 76046568 | O8: 40142167 | P8: =SUM(K8:O8) -> 201782967
B9: Property taxes receivable - net (note 4) | K9: 6227741 | L9: 8851423 | O9: 7173814 | P9: =SUM(K9:O9) -> 22252978
B10: Gross receipts business taxes receivable | K10: 4106161 | P10: =SUM(K10:O10) -> 4106161
B11: Sales taxes receivable | K11: 17539310 | N11: 2595295 | O11: 1652437 | P11: =SUM(K11:O11) -> 21787042
B12: Interest and penalties receivable on taxes | K12: 98251 | P12: =SUM(K12:O12) -> 98251
B13: Accounts receivable - net (note 13) | K13: 1609221 | L13: 718 | M13: 2642 | N13: 60870 | O13: 2271963 | P13: =SUM(K13:O13) -> 3945414
B14: Accrued interest receivable | K14: 80788 | L14: 57925 | M14: 6593 | N14: 102824 | O14: 47178 | P14: =SUM(K14:O14) -> 295308
B15: Due from other funds (Note 11) | K15: 9472834 | N15: 37818068 | P15: =SUM(K15:O15) -> 47290902
B16: Due from other governments (Note 11) | K16: 20961465 | L16: 31408708 | M16: 6202760 | N16: 1828373 | O16: 23092159 | P16: =SUM(K16:O16) -> 83493465
B17: Loans receivable | M17: 4115590 | P17: =SUM(K17:O17) -> 4115590
B18: Inventory | K18: 656653 | P18: =SUM(K18:O18) -> 656653
E20: Total Assets: | K20: =SUM(K7:K18) -> 131116649 | L20: =SUM(L7:L18) -> 108667396 | M20: =SUM(M7:M18) -> 19191000 | N20: =SUM(N7:N18) -> 174184888 | O20: =SUM(O7:O18) -> 115567815 | P20: =SUM(P7:P18) -> 548727748
A22: LIABILITIES, DEFERRED INFLOWS OF RESOURCES, AND FUND BALANCES
B23: Liabilities:
C24: Accounts and contracts payable | K24: 13921373 | L24: 1745687 | M24: 3690951 | N24: 4433058 | O24: 2545180 | P24: =SUM(K24:O24) -> 26336249
C25: Due to other funds (Note 11) | L25: 27796921 | O25: 18075097 | P25: =SUM(K25:O25) -> 45872018
C26: Due to other governments | K26: 167662 | O26: 322767 | P26: =SUM(K26:O26) -> 490429
C27: Accrued payables | K27: 2914916 | L27: 298014 | M27: 218814 | N27: 4094 | O27: 475835 | P27: =SUM(K27:O27) -> 3911673
C28: Unearned revenue | M28: 697022 | N28: 398579 | P28: =SUM(K28:O28) -> 1095601
C29: Deposits and escrow accounts | K29: 11142962 | M29: 337129 | P29: =SUM(K29:O29) -> 11480091
E31: Total liabilities: | K31: =SUM(K24:K29) -> 28146913 | L31: =SUM(L24:L30) -> 29840622 | M31: =SUM(M24:M30) -> 4943916 | N31: =SUM(N24:N30) -> 4835731 | O31: =SUM(O24:O30) -> 21418879 | P31: =SUM(P24:P30) -> 89186061
A33: DEFERRED INFLOWS OF RESROUCES
B34: Unavailable revenue- property taxes | K34: 552818 | L34: 726595 | O34: 675093 | P34: =SUM(K34:O34) -> 1954506
B35: Unavailable revenue- revenue sharing | K35: 613417 | O35: 71042 | P35: =SUM(K35:O35) -> 684459
B36: Resources recieved before time requirements | M36: 668996 | P36: =SUM(K36:O36) -> 668996
E38: Total deferred inflows of resources | K38: =SUM(K34:K36) -> 1166235 | L38: =SUM(L34:L36) -> 726595 | M38: =SUM(M34:M36) -> 668996 | N38: =SUM(N34:N36) -> 0 | O38: =SUM(O34:O36) -> 746135 | P38: =SUM(P34:P36) -> 3307961
B40: Fund Balances
C41: Nonspendable | K41: 656653 | P41: =SUM(K41:O41) -> 656653
C42: Restricted | K42: 517487 | L42: 78100179 | M42: 13578088 | N42: 145151310 | O42: 84686576 | P42: =SUM(K42:O42) -> 322033640
C43: Committed | K43: 59144527 | N43: 24197847 | O43: 8716225 | P43: =SUM(K43:O43) -> 92058599
C44: Assigned | K44: 28346341 | P44: =SUM(K44:O44) -> 28346341
C45: Unassigned | K45: 13138493 | P45: =SUM(K45:O45) -> 13138493
E47: Total fund balance: | K47: =SUM(K41:K45) -> 101803501 | L47: =SUM(L41:L45) -> 78100179 | M47: =SUM(M41:M45) -> 13578088 | N47: =SUM(N41:N45) -> 169349157 | O47: =SUM(O41:O45) -> 93402801 | P47: =SUM(P41:P45) -> 456233726
E49: Total liabilities, deffered inflows of resources and fund balances: | K49: =SUM(K31+K38+K47) -> 131116649 | L49: =SUM(L31+L38+L47) -> 108667396 | M49: =SUM(M31+M38+M47) -> 19191000 | N49: =SUM(N31+N38+N47) -> 174184888 | O49: =SUM(O31+O38+O47) -> 115567815 | P49: =SUM(P31+P38+P47) -> 548727748

Sheet East Carroll
D1: East Carroll Combined Balance Sheet
D2: Issued: December 31, 2015
K4: General | L4: Road Maintenance and Construction | M4: Garbage District No. 1 | N4: Library | O4: Drainage Maintenance | P4: Health Unit | Q4: Criminal Court | R4: Nonmajor Governmental | S4: Total
A5: Assets:
B6: Cash and Cash Equivalents | K6: 173636 | L6: 701013 | M6: 4545 | N6: 136346 | O6: 25091 | P6: 494493 | Q6: 1000 | R6: 459622 | S6: =SUM(K6:R6) -> 1995746
B7: Investments | L7: 191686 | M7: 154475 | N7: 211637 | O7: 61709 | P7: 28789 | R7: 70731 | S7: =SUM(K7:R7) -> 719027
B8: Receivables | K8: 643711 | L8: 499843 | M8: 393954 | N8: 334222 | O8: 545162 | P8: 192728 | Q8: 11723 | R8: 286022 | S8: =SUM(K8:R8) -> 2907365
E10: Total assets: | K10: =SUM(K6:K8) -> 817347 | L10: =SUM(L6:L8) -> 1392542 | M10: =SUM(M6:M8) -> 552974 | N10: =SUM(N6:N8) -> 682205 | O10: =SUM(O6:O8) -> 631962 | P10: =SUM(P6:P8) -> 716010 | Q10: =SUM(Q6:Q8) -> 12723 | R10: =SUM(R6:R8) -> 816375 | S10: =SUM(K10:R10) -> 5622138
A12: LIABILITIES, DEFERRED INFLOWS OF RESOURCES, AND FUND BALANCES
B13: Liabilities:
C14: Accounts payable | K14: 88432 | L14: 18098 | M14: 4978 | P14: 21 | Q14: 41 | R14: 109 | S14: =SUM(K14:R14) -> 111679
E16: Total liabilities: | K16: =SUM(K14:K14) -> 88432 | L16: =SUM(L14:L14) -> 18098 | M16: =SUM(M14:M14) -> 4978 | N16: =SUM(N14:N14) -> 0 | O16: =SUM(O14:O14) -> 0 | P16: =SUM(P14:P14) -> 21 | R16: =SUM(R14:R14) -> 109 | S16: =SUM(S14:S14) -> 111679
A18: Deferred Inflows of Resources
B19: Unavailable revenue- property taxes | K19: 34053 | L19: 30733 | M19: 36771 | N19: 30658 | O19: 30733 | P19: 17679 | R19: 26573 | S19: =SUM(K19:R19) -> 207200
E21: Total deferred inflows of resources | K21: =SUM(K17:K19) -> 34053 | L21: =SUM(L17:L19) -> 30733 | M21: =SUM(M17:M19) -> 36771 | N21: =SUM(N17:N19) -> 30658 | O21: =SUM(O17:O19) -> 30733 | P21: =SUM(P17:P19) -> 17679 | R21: =SUM(R17:R19) -> 26573 | S21: =SUM(S17:S19) -> 207200 | T21: =SUM(T17:T19) -> 0 | U21: =SUM(U17:U19) -> 0 | V21: =SUM(V17:V19) -> 0 | W21: =SUM(W17:W19) -> 0 | X21: =SUM(X17:X19) -> 0 | Y21: =SUM(Y17:Y19) -> 0 | ... AA21: =SUM(AA17:AA19) -> 0
A23: Fund Balances
C24: Restricted | L24: 1343711 | M24: 511225 | N24: 651547 | O24: 601229 | P24: 698310 | Q24: 12682 | R24: 789693 | S24: =SUM(K24:R24) -> 4608397
C25: Unassigned | K25: 694862 | S25: =SUM(K25:R25) -> 694862
E27: Total fund balance: | K27: =SUM(K24:K25) -> 694862 | L27: =SUM(L24:L25) -> 1343711 | M27: =SUM(M24:M25) -> 511225 | N27: =SUM(N24:N25) -> 651547 | O27: =SUM(O24:O25) -> 601229 | P27: =SUM(P24:P25) -> 698310 | R27: =SUM(R24:R25) -> 789693 | S27: =SUM(S24:S25) -> 5303259
E29: Total liabilities, deferred inflows of resources, and fund balances: | K29: =SUM(K27+K21+K16) -> 817347 | L29: =SUM(L27+L21+L16) -> 1392542 | M29: =SUM(M27+M21+M16) -> 552974 | N29: =SUM(N27+N21+N16) -> 682205 | O29: =SUM(O27+O21+O16) -> 631962 | P29: =SUM(P27+P21+P16) -> 716010 | R29: =SUM(R27+R21+R16) -> 816375 | S29: =SUM(S27+S21+S16) -> 5622138

Sheet East Feliciana
D1: East Feliciana Combined Balance Sheet
D2: Issued: December 31, 2015
K4: General Fund | L4: Roads and Bridges | M4: Solid Waste | N4: Other Governmental Funds | O4: Total Governmental Funds
A5: Assets:
B6: Cash and cash equivalents | K6: 425147 | L6: 1035134 | M6: 2918765 | N6: 198560 | O6: =SUM(K6:N6) -> 4577606
B7: Receivables | O7: =SUM(K7:N7) -> 0
C8: Accounts | N8: 7527 | O8: =SUM(K8:N8) -> 7527
C9: Taxes | K9: 456441 | M9: 223835 | N9: 513248 | O9: =SUM(K9:N9) -> 1193524
B10: Due from other funds | K10: 347329 | L10: 354614 | M10: 1175000 | N10: 12566 | O10: =SUM(K10:N10) -> 1889509
B11: Due from other govt units | K11: 25340 | L11: 44918 | O11: =SUM(K11:N11) -> 70258
E13: Total assets: | K13: =SUM(K6:K11) -> 1254257 | L13: =SUM(L6:L11) -> 1434666 | M13: =SUM(M6:M11) -> 4317600 | N13: =SUM(N6:N11) -> 731901 | O13: =SUM(O6:O11) -> 7738424
A15: LIABILITIES AND FUND BALANCES
B16: Liabilities:
C17: Accounts payable | K17: 2831 | M17: 95386 | O17: =SUM(K17:N17) -> 98217
C18: Due to other funds | K18: 18686 | L18: 1175000 | M18: 16779 | N18: 206713 | O18: =SUM(K18:N18) -> 1417178
C19: Due to other govt agencies | O19: =SUM(K19:N19) -> 0
E21: Total liabilities: | K21: =SUM(K17:K19) -> 21517 | L21: =SUM(L17:L19) -> 1175000 | M21: =SUM(M17:M19) -> 112165 | N21: =SUM(N17:N19) -> 206713 | O21: =SUM(O17:O19) -> 1515395
A23: Deferred inflows of resources:
B24: Unavailable revenue | K24: 122435 | N24: 176283 | O24: =SUM(K24:N24) -> 298718
O25: =SUM(K25:N25) -> 0
A26: Fund Balances (Deficit): | O26: =SUM(K26:N26) -> 0
C27: Restricted for: | O27: =SUM(K27:N27) -> 0
D28: Health unit oper/maintenance | N28: 522291 | O28: =SUM(K28:N28) -> 522291
D29: Homeland security | K29: 30194 | O29: =SUM(K29:N29) -> 30194
D30: Solid waste management | M30: 4205435 | O30: =SUM(K30:N30) -> 4205435
C31: Committed to: | O31: =SUM(K31:N31) -> 0
D32: Debt service | O32: =SUM(K32:N32) -> 0
D33: Road improvements | L33: 259666 | O33: =SUM(K33:N33) -> 259666
D34: Coroner/court operations | N34: -173386 | O34: =SUM(K34:N34) -> -173386
D35: Claims and judgements | O35: =SUM(K35:N35) -> 0
C36: Unassigned | K36: 1080111 | O36: =SUM(K36:N36) -> 1080111
E38: Total fund balance: | K38: =SUM(K28:K36) -> 1110305 | L38: =SUM(L28:L36) -> 259666 | M38: =SUM(M28:M36) -> 4205435 | N38: =SUM(N28:N36) -> 348905 | O38: =SUM(O28:O36) -> 5924311
E40: Total liabilities, deferred inflows of resources, and fund balances: | K40: =SUM(K38+K24+K21) -> 1254257 | L40: =SUM(L38+L24+L21) -> 1434666 | M40: =SUM(M38+M24+M21) -> 4317600 | N40: =SUM(N38+N24+N21) -> 731901 | O40: =SUM(O38+O24+O21) -> 7738424

Sheet Evangeline
D1: Evangeline Combined Balance Sheet
D2: Issued: December 31, 2015
K4: General | L4: Special Grant | M4: Road District Maintenance | N4: Public Library Maintenance | O4: 2% Sales Tax District #1 Capital Projects | P4: Other Governmental Funds | Q4: Total
A5: Assets:
B6: Cash and interest-bearing deposits | K6: 836113 | L6: 121402 | M6: 2014366 | N6: 1906042 | O6: 1855968 | P6: 3242657 | Q6: =SUM(K6:P6) -> 9976548
B7: Receivables, net | K7: 3936 | P7: 3227 | Q7: =SUM(K7:P7) -> 7163
B8: Due from other funds | K8: 143522 | M8: 15590 | Q8: =SUM(K8:P8) -> 159112
B9: Due from other governmental units | K9: 939549 | L9: 282304 | M9: 2579526 | N9: 1255276 | P9: 1019049 | Q9: =SUM(K9:P9) -> 6075704
B10: Other assets | K10: 41456 | P10: 5000 | Q10: =SUM(K10:P10) -> 46456
B11: Restricted assets: | Q11: =SUM(K11:P11) -> 0
C12: Investments | O12: 6973557 | P12: 224863 | Q12: =SUM(K12:P12) -> 7198420
E14: Total assets: | K14: =SUM(K6:K12) -> 1964576 | L14: =SUM(L6:L12) -> 403706 | M14: =SUM(M6:M12) -> 4609482 | N14: =SUM(N6:N12) -> 3161318 | O14: =SUM(O6:O12) -> 8829525 | P14: =SUM(P6:P12) -> 4494796 | Q14: =SUM(Q6:Q12) -> 23463403
A16: LIABILITIES, DEFERRED INFLOWS OF RESOURCES, AND FUND BALANCES
B17: Liabilities:
C18: Accounts, salaries, and other payables | K18: 231625 | L18: 243976 | M18: 36872 | O18: 2256216 | P18: 53983 | Q18: =SUM(K18:P18) -> 2822672
C19: Unearned revenue | P19: 249333 | Q19: =SUM(K19:P19) -> 249333
C20: Due to other funds | K20: 15590 | L20: 105213 | M20: 9365 | O20: 8805 | P20: 20139 | Q20: =SUM(K20:P20) -> 159112
C21: Performance bonds payable | K21: 300318 | Q21: =SUM(K21:P21) -> 300318
C22: Deposits payable | P22: 12297 | Q22: =SUM(K22:P22) -> 12297
E24: Total liabilities: | K24: =SUM(K18:K22) -> 547533 | L24: =SUM(L18:L22) -> 349189 | M24: =SUM(M18:M22) -> 46237 | N24: =SUM(N18:N22) -> 0 | O24: =SUM(O18:O22) -> 2265021 | P24: =SUM(P18:P22) -> 335752 | Q24: =SUM(Q18:Q22) -> 3543732
A27: Fund Balances
C28: Restricted-
D29: Debt service | P29: 240618 | Q29: =SUM(K29:P29) -> 240618
D30: Public works | O30: 6564504 | Q30: =SUM(K30:P30) -> 6564504
C31: Assigned-
D32: Judicial | P32: 22488 | Q32: =SUM(K32:P32) -> 22488
D33: Public works | L33: 54517 | M33: 4563245 | P33: 2340889 | Q33: =SUM(K33:P33) -> 6958651
D34: Health and welfare | P34: 1666674 | Q34: =SUM(K34:P34) -> 1666674
D35: Culture and recreation | N35: 3161318 | P35: 15 | Q35: =SUM(K35:P35) -> 3161333
D36: Drainage improvements | P36: 42734 | Q36: =SUM(K36:P36) -> 42734
C37: Unassigned (deficit) | K37: 1417043 | P37: -154374 | Q37: =SUM(K37:P37) -> 1262669
E39: Total fund balance: | K39: =SUM(K28:K37) -> 1417043 | L39: =SUM(L28:L37) -> 54517 | M39: =SUM(M28:M37) -> 4563245 | N39: =SUM(N28:N37) -> 3161318 | O39: =SUM(O28:O37) -> 6564504 | P39: =SUM(P28:P37) -> 4159044 | Q39: =SUM(Q28:Q37) -> 19919671
E41: Total liabilities, deferred inflows of resources, and fund balances: | K41: =SUM(K39+K24) -> 1964576 | L41: =SUM(L39+L24) -> 403706 | M41: =SUM(M39+M24) -> 4609482 | N41: =SUM(N39+N24) -> 3161318 | O41: =SUM(O39+O24) -> 8829525 | P41: =SUM(P39+P24) -> 4494796 | Q41: =SUM(Q39+Q24) -> 23463403

Sheet Franklin
D1: Franklin Combined Balance Sheet
D2: Issued: December 31, 2015
K4: General | L4: Road and Bridge | M4: Drainage Maintenance | N4: Parish Equipment | O4: Sales Tax | P4: IKE GUSTAV | Q4: Other Governmental Funds | R4: Total
A5: Assets:
B6: Cash and Cash Equivalents | K6: 536782 | L6: 3284176 | M6: 544303 | N6: 860062 | O6: 1677801 | P6: 687 | Q6: 2938314 | R6: =SUM(K6:Q6) -> 9842125
B7: Receivables | K7: 353306 | L7: 228677 | M7: 965387 | N7: 701785 | O7: 91222 | P7: 5904 | Q7: 1218749 | R7: =SUM(K7:Q7) -> 3565030
B8: Due from other funds | K8: 83513 | O8: 30000 | R8: =SUM(K8:Q8) -> 113513
E10: Total assets: | K10: =SUM(K6:K8) -> 973601 | L10: =SUM(L6:L8) -> 3512853 | M10: =SUM(M6:M8) -> 1509690 | N10: =SUM(N6:N8) -> 1561847 | O10: =SUM(O6:O8) -> 1799023 | P10: =SUM(P6:P8) -> 6591 | Q10: =SUM(Q6:Q8) -> 4157063 | R10: =SUM(R6:R8) -> 13520668
A12: LIABILITIES, DEFERRED INFLOWS OF RESOURCES, AND FUND BALANCES
B13: Liabilities:
C14: Accounts payable | K14: 83779 | L14: 86890 | M14: 37320 | N14: 27205 | O14: 103765 | P14: 5904 | Q14: 65861 | R14: =SUM(K14:Q14) -> 410724
C15: Payroll withholdings payable | K15: 73784 | R15: =SUM(K15:Q15) -> 73784
C16: Due to other funds | K16: 30000 | O16: 50498 | Q16: 33015 | R16: =SUM(K16:Q16) -> 113513
E18: Total liabilities: | K18: =SUM(K14:K15) -> 157563 | L18: =SUM(L14:L15) -> 86890 | M18: =SUM(M14:M15) -> 37320 | N18: =SUM(N14:N15) -> 27205 | O18: =SUM(O14:O16) -> 154263 | P18: =SUM(P14:P16) -> 5904 | Q18: =SUM(Q14:Q16) -> 98876 | R18: =SUM(R14:R16) -> 598021
A20: Fund Equity - Fund Balances
C21: Restricted
D22: Other General Government | Q22: 1095564 | R22: =SUM(K22:Q22) -> 1095564
D23: Health and Welfare | Q23: 686197 | R23: =SUM(K23:Q23) -> 686197
D24: Culture and recreation | Q24: 8627 | R24: =SUM(K24:Q24) -> 8627
D25: Public safety | Q25: 607289 | R25: =SUM(K25:Q25) -> 607289
D26: Public works | L26: 3425963 | M26: 1472370 | N26: 1534642 | O26: 1644760 | Q26: 945409 | R26: =SUM(K26:Q26) -> 9023144
D27: Economic development | Q27: 213275 | R27: =SUM(K27:Q27) -> 213275
D28: Committed | Q28: 31581 | R28: =SUM(K28:Q28) -> 31581
C29: Assigned | P29: 687 | Q29: 470245 | R29: =SUM(K29:Q29) -> 470932
C30: Unassigned | K30: 786038 | R30: =SUM(K30:Q30) -> 786038
E32: Total fund balance: | K32: =SUM(K21:K30) -> 786038 | L32: =SUM(L21:L30) -> 3425963 | M32: =SUM(M21:M30) -> 1472370 | N32: =SUM(N21:N30) -> 1534642 | O32: =SUM(O21:O30) -> 1644760 | P32: =SUM(P21:P30) -> 687 | Q32: =SUM(Q21:Q30) -> 4058187 | R32: =SUM(R21:R30) -> 12922647
E34: Total liabilities, deferred inflows of resources, and fund balances: | K34: =SUM(K32+K18) -> 943601 | L34: =SUM(L32+L18) -> 3512853 | M34: =SUM(M32+M18) -> 1509690 | N34: =SUM(N32+N18) -> 1561847 | O34: =SUM(O32+O18) -> 1799023 | P34: =SUM(P32+P18) -> 6591 | Q34: =SUM(Q32+Q18) -> 4157063 | R34: =SUM(R32+R18) -> 13520668

Sheet Grant
D1: Grant Parish Combined Balance Sheet
D2: Issued: December 31, 2015
K4: General Fund | L4: Parish Road Maintenance | M4: Sales Tax Fund | N4: Head Start | O4: Courthouse and Jail Maintenance | P4: Old Bank Building | Q4: Other Governmental Funds | R4: Total Governmental Funds
A5: Assets:
B6: Cash and Cash Equivalents | K6: 269651 | L6: 254727 | M6: 369430 | N6: 74993 | O6: 96049 | P6: 5115 | Q6: 537594 | R6: =SUM(K6:Q6) -> 1607559
B7: Receivables (net) | K7: 386040 | L7: 418451 | M7: 212538 | O7: 144546 | P7: 155706 | Q7: 159243 | R7: =SUM(K7:Q7) -> 1476524
B8: Interfund Receivables | K8: 138964 | L8: 43350 | M8: 3016 | O8: 479 | Q8: 5000 | R8: =SUM(K8:Q8) -> 190809
E10: Total assets: | K10: =SUM(K6:K8) -> 794655 | L10: =SUM(L6:L8) -> 716528 | N10: =SUM(N6:N8) -> 74993 | O10: =SUM(O6:O8) -> 241074 | P10: =SUM(P6:P8) -> 160821 | Q10: =SUM(Q6:Q8) -> 701837 | R10: =SUM(R6:R8) -> 3274892
A12: LIABILITIES AND FUND BALANCES
B13: Liabilities:
C14: Accounts payable | K14: 145485 | L14: 57822 | M14: 55273 | N14: 74993 | O14: 10967 | P14: 127473 | Q14: 9248 | R14: =SUM(K14:Q14) -> 481261
C15: Retainage Payable | P15: 32870 | R15: =SUM(K15:Q15) -> 32870
C16: Interfund Payables | K16: 5000 | L16: 2259 | M16: 68735 | O16: 71106 | P16: 576 | Q16: 43133 | R16: =SUM(K16:Q16) -> 190809
E18: Total liabilities: | K18: =SUM(K14:K16) -> 150485 | L18: =SUM(L14:L16) -> 60081 | M18: =SUM(M14:M16) -> 124008 | N18: =SUM(N14:N16) -> 74993 | O18: =SUM(O14:O16) -> 82073 | P18: =SUM(P14:P16) -> 160919 | Q18: =SUM(Q14:Q16) -> 52381 | R18: =SUM(R14:R16) -> 704940
B20: Fund Balances
C21: Restricted:
D22: Maintenance | L22: 656447 | M22: 460976 | O22: 159001 | Q22: 456549 | R22: =SUM(K22:Q22) -> 1732973
D23: Judicial | Q23: 30664 | R23: =SUM(K23:Q23) -> 30664
D24: Construction | Q24: 51728 | R24: =SUM(K24:Q24) -> 51728
C25: Committed To:
D26: Maintenance | Q26: 18877 | R26: =SUM(K26:Q26) -> 18877
D27: Construction | Q27: 711 | R27: =SUM(K27:Q27) -> 711
D28: Litter Abatement | Q28: 605 | R28: =SUM(K28:Q28) -> 605
D29: General Purposes | Q29: 96566 | R29: =SUM(K29:Q29) -> 96566
C30: Unassigned | K30: 644170 | P30: -98 | Q30: -6244 | R30: =SUM(K30:Q30) -> 637828
E32: Total fund balances: | K32: =SUM(K21:K30) -> 644170 | L32: =SUM(L21:L30) -> 656447 | N32: =SUM(N21:N30) -> 0 | O32: =SUM(O21:O30) -> 159001 | P32: =SUM(P21:P30) -> -98 | Q32: =SUM(Q21:Q30) -> 649456 | R32: =SUM(R21:R30) -> 2569952
E34: Total liabilities and fund balances: | K34: =SUM(K18+K32) -> 794655 | L34: =SUM(L18+L32) -> 716528 | N34: =SUM(N18+N32) -> 74993 | O34: =SUM(O18+O32) -> 241074 | P34: =SUM(P18+P32) -> 160821 | Q34: =SUM(Q18+Q32) -> 701837 | R34: =SUM(R18+R32) -> 3274892

Sheet Iberia
D1: Iberia Combined Balance Sheet
D2: Issued: December 31, 2015
K4: General | L4: Public Library | M4: Sales Tax | N4: Public Buildings Maintenance | O4: Paarish Wide Drainage Maintenance | P4: Royalty | Q4: Mosquito Control/ Drainage Program | R4: Other Governmental Funds | S4: Total
A5: Assets:
B6: Cash and interest-bearing deposits | K6: 477849 | L6: 6254632 | M6: 6599235 | N6: 3524048 | O6: 4343977 | P6: 12450767 | R6: 11485828 | S6: =SUM(K6:R6) -> 45136336
B7: Investments | L7: 63081 | S7: =SUM(K7:R7) -> 63081
B8: Receivables, net | K8: 1117621 | L8: 1946277 | N8: 2024759 | O8: 1322648 | R8: 1105518 | S8: =SUM(K8:R8) -> 7516823
B9: Due from other funds | K9: 315598 | L9: 41450 | N9: 353762 | O9: 95392 | P9: 99879 | R9: 319735 | S9: =SUM(K9:R9) -> 1225816
B10: Advance to component unit | K10: 1816356 | P10: 104710 | S10: =SUM(K10:R10) -> 1921066
B11: Due from other governmental agencies | K11: 325245 | L11: 79330 | M11: 170656 | N11: 56730 | O11: 42557 | P11: 1221637 | Q11: 228677 | R11: 507439 | S11: =SUM(K11:R11) -> 2632271
E13: Total assets: | K13: =SUM(K6:K11) -> 4052669 | L13: =SUM(L6:L11) -> 8384770 | M13: =SUM(M6:M11) -> 6769891 | N13: =SUM(N6:N11) -> 5959299 | O13: =SUM(O6:O11) -> 5804574 | P13: =SUM(P6:P11) -> 13876993 | Q13: =SUM(Q6:Q11) -> 228677 | R13: =SUM(R6:R11) -> 13418520 | S13: =SUM(S6:S11) -> 58495393
A15: LIABILITIES, DEFERRED INFLOWS OF RESOURCES, AND FUND BALANCES
B16: Liabilities:
C17: Accounts payable | K17: 289116 | L17: 34632 | M17: 217387 | N17: 59125 | O17: 116373 | P17: 207287 | R17: 379422 | S17: =SUM(K17:R17) -> 1303342
C18: Accrued expenses | K18: 86449 | L18: 35448 | M18: 2923 | N18: 7201 | O18: 28420 | P18: 9341 | R18: 63537 | S18: =SUM(K18:R18) -> 233319
C19: Contracts payable | P19: 607134 | R19: 20000 | S19: =SUM(K19:R19) -> 627134
C20: Retainage payable | P20: 191636 | R20: 41359 | S20: =SUM(K20:R20) -> 232995
C21: Due to other funds | K21: 580743 | L21: 12816 | M21: 31205 | N21: 18314 | O21: 115524 | P21: 125696 | R21: 692901 | S21: =SUM(K21:R21) -> 1577199
C22: Due to other governmental agencies | K22: 53111 | L22: 96284 | N22: 99942 | O22: 65421 | R22: 49811 | S22: =SUM(K22:R22) -> 364569
C23: Due to component units | K23: 32643 | P23: 3993 | Q23: 228677 | R23: 30991 | S23: =SUM(K23:R23) -> 296304
C24: Unearned revenue | K24: 6540 | S24: =SUM(K24:R24) -> 6540
C25: Advances from grantors and assessments | R25: 83410 | S25: =SUM(K25:R25) -> 83410
E27: Total liabilities: | K27: =SUM(K17:K25) -> 1048602 | L27: =SUM(L17:L25) -> 179180 | M27: =SUM(M17:M25) -> 251515 | N27: =SUM(N17:N25) -> 184582 | O27: =SUM(O17:O25) -> 325738 | P27: =SUM(P17:P25) -> 1145087 | Q27: =SUM(Q17:Q25) -> 228677 | R27: =SUM(R17:R25) -> 1361431 | S27: =SUM(S17:S25) -> 4724812
A30: Fund Balances
C31: Nonspendable | R31: 68863 | S31: =SUM(K31:R31) -> 68863
C32: Restricted | L32: 8205590 | M32: 6518376 | N32: 5774717 | O32: 5478836 | R32: 4058523 | S32: =SUM(K32:R32) -> 30036042
C33: Committed | K33: 515153 | R33: 5129318 | S33: =SUM(K33:R33) -> 5644471
C34: Assigned | K34: 870023 | P34: 12731906 | R34: 2800385 | S34: =SUM(K34:R34) -> 16402314
C35: Unassigned | K35: 1618891 | S35: =SUM(K35:R35) -> 1618891
E37: Total fund balance: | K37: =SUM(K31:K35) -> 3004067 | L37: =SUM(L31:L35) -> 8205590 | M37: =SUM(M31:M35) -> 6518376 | N37: =SUM(N31:N35) -> 5774717 | O37: =SUM(O31:O35) -> 5478836 | P37: =SUM(P31:P35) -> 12731906 | Q37: =SUM(Q31:Q35) -> 0 | R37: =SUM(R31:R35) -> 12057089 | S37: =SUM(S31:S35) -> 53770581
E39: Total liabilities, deferred inflows of resources, and fund balances: | K39: =SUM(K37+K27) -> 4052669 | L39: =SUM(L37+L27) -> 8384770 | M39: =SUM(M37+M27) -> 6769891 | N39: =SUM(N37+N27) -> 5959299 | O39: =SUM(O37+O27) -> 5804574 | P39: =SUM(P37+P27) -> 13876993 | Q39: =SUM(Q37+Q27) -> 228677 | R39: =SUM(R37+R27) -> 13418520 | S39: =SUM(S37+S27) -> 58495393

Sheet Iberville
D1: Iberville Combined Balance Sheet
D2: Issued: December 31, 2015
K4: General | L4: Drainage Maintenance | M4: Public Building Maintenance | N4: Sales Tax Roads | O4: Solid Waste | P4: Iberville Parish Medical Complex CDBG | Q4: Louisiana Recovery Authority | R4: Capital Improvement | S4: WD 3 Line Extension Project DHH | T4: Other Governmental Funds | U4: Total Governmental Funds
A5: Assets:
B6: Cash and cash equivalents | K6: 3957437 | L6: 1299609 | M6: 862543 | N6: 5296856 | O6: 4126561 | P6: 118618 | Q6: 94204 | R6: 4713101 | T6: 9844351 | U6: =SUM(K6:T6) -> 30313280
B7: Receivables (net of allowance for uncollectible) | K7: 2338133 | L7: 2790879 | M7: 1654589 | N7: 335205 | O7: 273195 | P7: 384930 | Q7: 260213 | R7: 163069 | S7: 13703 | T7: 892940 | U7: =SUM(K7:T7) -> 9106856
B8: Prepaid items | K8: 1418 | M8: 29 | N8: 3750 | O8: 25 | U8: =SUM(K8:T8) -> 5222
B9: Due From Other Funds | U9: =SUM(K9:T9) -> 0
B10: Cash - restricted | K10: 100000 | U10: =SUM(K10:T10) -> 100000
B11: Other assets | S11: 1217182 | T11: 704 | U11: =SUM(K11:T11) -> 1217886
E13: Total assets: | K13: =SUM(K6:K11) -> 6396988 | L13: =SUM(L6:L11) -> 4090488 | M13: =SUM(M6:M11) -> 2517161 | N13: =SUM(N6:N11) -> 5635811 | O13: =SUM(O6:O11) -> 4399781 | P13: =SUM(P6:P11) -> 503548 | Q13: =SUM(Q6:Q11) -> 354417 | R13: =SUM(R6:R11) -> 4876170 | T13: =SUM(T6:T11) -> 10737995 | U13: =SUM(U6:U11) -> 40743244
A15: LIABILITIES, DEFERRED INFLOWS OF RESOURCES, AND FUND BALANCES
B16: Liabilities:
C17: Accounts payable | K17: 252394 | L17: 10985 | M17: 111538 | N17: 78428 | O17: 259986 | Q17: 229923 | R17: 1007678 | S17: 1217182 | T17: 258839 | U17: =SUM(K17:T17) -> 3426953
C18: Due to other funds | U18: =SUM(K18:T18) -> 0
C19: Other payables | K19: 385986 | L19: 150006 | M19: 95529 | N19: 46600 | O19: 8019 | P19: 2312 | Q19: 25640 | R19: 45496 | S19: 13703 | T19: 112669 | U19: =SUM(K19:T19) -> 885960
E21: Total liabilities: | K21: =SUM(K17:K19) -> 638380 | L21: =SUM(L17:L19) -> 160991 | M21: =SUM(M17:M19) -> 207067 | N21: =SUM(N17:N19) -> 125028 | O21: =SUM(O17:O19) -> 268005 | P21: =SUM(P17:P19) -> 2312 | Q21: =SUM(Q17:Q19) -> 255563 | R21: =SUM(R17:R19) -> 1053174 | ... T21: =SUM(T17:T19) -> 371508 | U21: =SUM(K21:T21) -> 4312913
A24: Fund Balances
C25: Non Spendable | K25: 1418 | M25: 29 | N25: 3750 | O25: 25 | T25: 704 | U25: =SUM(K25:T25) -> 5926
C26: Restricted | K26: 125809 | L26: 3929497 | M26: 2310065 | N26: 5507033 | O26: 4131751 | P26: 501236 | Q26: 98854 | R26: 3822996 | T26: 7806040 | U26: =SUM(K26:T26) -> 28233281
C27: Committed | T27: 2559743 | U27: =SUM(K27:T27) -> 2559743
C28: Assigned | U28: =SUM(K28:T28) -> 0
C29: Unassigned | K29: 5631381 | U29: =SUM(K29:T29) -> 5631381
E31: Total fund balance: | K31: =SUM(K25:K29) -> 5758608 | L31: =SUM(L25:L29) -> 3929497 | M31: =SUM(M25:M29) -> 2310094 | N31: =SUM(N25:N29) -> 5510783 | O31: =SUM(O25:O29) -> 4131776 | P31: =SUM(P25:P29) -> 501236 | Q31: =SUM(Q25:Q29) -> 98854 | R31: =SUM(R25:R29) -> 3822996 | T31: =SUM(T25:T29) -> 10366487 | U31: =SUM(U25:U29) -> 36430331
E33: Total liabilities, deferred inflows of resources, and fund balances: | K33: =SUM(K31+K21) -> 6396988 | L33: =SUM(L31+L21) -> 4090488 | M33: =SUM(M31+M21) -> 2517161 | N33: =SUM(N31+N21) -> 5635811 | O33: =SUM(O31+O21) -> 4399781 | P33: =SUM(P31+P21) -> 503548 | Q33: =SUM(Q31+Q21) -> 354417 | R33: =SUM(R31+R21) -> 4876170 | T33: =SUM(T31+T21) -> 10737995 | U33: =SUM(U31+U21) -> 40743244

Sheet Jackson
D1: Jackson Combined Balance Sheet
D2: Issued: December 31, 2015
K4: General | L4: Road Fund | M4: Solid Waste | N4: Library | O4: Asphalt Fund | P4: Nonmajor Governmental | Q4: Total
A5: Assets:
B6: Cash and Cash Equivalents | K6: 2421598 | L6: 2551690 | M6: 869733 | N6: 920009 | O6: 1858288 | P6: 2094230 | Q6: =SUM(K6:P6) -> 10715548
B7: Receivables | K7: 1328287 | L7: 1148265 | M7: 348376 | N7: 1562072 | O7: 1006606 | P7: 315162 | Q7: =SUM(K7:P7) -> 5708768
B8: Prepaid Items | K8: 3206 | N8: 40313 | Q8: =SUM(K8:P8) -> 43519
E10: Total assets: | K10: =SUM(K6:K8) -> 3753091 | L10: =SUM(L6:L8) -> 3699955 | M10: =SUM(M6:M8) -> 1218109 | N10: =SUM(N6:N8) -> 2522394 | O10: =SUM(O6:O8) -> 2864894 | P10: =SUM(P6:P8) -> 2409392 | Q10: =SUM(Q6:Q8) -> 16467835
A12: LIABILITIES AND FUND BALANCES
B13: Liabilities:
C14: Accounts, salaries and other payables | K14: 116865 | L14: 287957 | M14: 59872 | N14: 12805 | O14: 9636 | P14: 4566 | Q14: =SUM(K14:P14) -> 491701
C15: Sequrity deposits | K15: 4635 | L15: 20686 | Q15: =SUM(K15:P15) -> 25321
E17: Total liabilities: | K17: =SUM(K14:K15) -> 121500 | L17: =SUM(L14:L15) -> 308643 | M17: =SUM(M14:M15) -> 59872 | N17: =SUM(N14:N15) -> 12805 | O17: =SUM(O14:O15) -> 9636 | P17: =SUM(P14:P15) -> 4566 | Q17: =SUM(Q14:Q15) -> 517022
A19: DEFERRED INFLOWS OF RESOURCES
C20: Unavailable revenue-property taxes | K20: 59927 | L20: 64400 | N20: 55971 | O20: 92187 | P20: 9877 | Q20: =SUM(K20:P20) -> 282362
E22: Total deferred inflows of resources | K22: =SUM(K20:K20) -> 59927 | L22: =SUM(L20:L20) -> 64400 | M22: =SUM(M20:M20) -> 0 | N22: =SUM(N20:N20) -> 55971 | O22: =SUM(O20:O20) -> 92187 | P22: =SUM(P20:P20) -> 9877 | Q22: =SUM(Q20:Q20) -> 282362
B24: Fund Balances
C25: Nonspendable - prepaid items | K25: 3206 | N25: 40313 | Q25: =SUM(K25:P25) -> 43519
C26: Restricted | K26: 50577 | L26: 3326912 | M26: 1158237 | N26: 2413305 | O26: 2763071 | P26: 2371144 | Q26: =SUM(K26:P26) -> 12083246
C27: Committed | K27: 772941 | P27: 23805 | Q27: =SUM(K27:P27) -> 796746
C28: Unassigned | K28: 2744940 | Q28: =SUM(K28:P28) -> 2744940
E30: Total fund balances: | K30: =SUM(K25:K28) -> 3571664 | L30: =SUM(L25:L28) -> 3326912 | M30: =SUM(M25:M28) -> 1158237 | N30: =SUM(N25:N28) -> 2453618 | O30: =SUM(O25:O28) -> 2763071 | P30: =SUM(P25:P28) -> 2394949 | Q30: =SUM(Q25:Q28) -> 15668451
E32: Total liabilities and fund balances: | K32: =SUM(K30,K17,K22) -> 3753091 | L32: =SUM(L30,L17,L22) -> 3699955 | M32: =SUM(M30,M17,M22) -> 1218109 | N32: =SUM(N30,N17,N22) -> 2522394 | O32: =SUM(O30,O17,O22) -> 2864894 | P32: =SUM(P30,P17,P22) -> 2409392 | Q32: =SUM(Q30,Q17,Q22) -> 16467835

Sheet Jefferson Davis
D1: Jefferson Combined Balance Sheet
D2: Issued: December 31, 2015
K4: General Fund | L4: Road Sales Tax No. 1 Sales Tax Fund | M4: Criminal Court Fund | N4: Section 8 Housing Fund | O4: Regional Consolidated Jail Maintenance Tax | P4: Road Sales Tax No. 1 Sinking Fund | Q4: Other Governmental Funds | R4: Total Governmental Funds
A5: Assets:
B6: Cash and Cash Equivalents | K6: 6210691 | L6: 6191050 | M6: 3006 | N6: 10634 | O6: 2988298 | Q6: 6891569 | R6: =SUM(K6:Q6) -> 22295248
B7: Investments | K7: 679905 | Q7: 1438858 | R7: =SUM(K7:Q7) -> 2118763
B8: Receivables | K8: 444599 | L8: 437930 | M8: 121325 | O8: 375652 | Q8: 195478 | R8: =SUM(K8:Q8) -> 1574984
B9: Due from Other Funds | K9: 361806 | Q9: 1321 | R9: =SUM(K9:Q9) -> 363127
B10: Restricted cash and cash equivalents | L10: 1552823 | P10: 1097263 | Q10: 28367 | R10: =SUM(K10:Q10) -> 2678453
E12: Total assets: | K12: =SUM(K6:K10) -> 7697001 | L12: =SUM(L6:L10) -> 8181803 | M12: =SUM(M6:M10) -> 124331 | N12: =SUM(N6:N10) -> 10634 | P12: =SUM(P6:P10) -> 1097263 | Q12: =SUM(Q6:Q10) -> 8555593 | R12: =SUM(R6:R10) -> 29030575
A14: LIABILITIES AND FUND BALANCES
B15: Liabilities:
C16: Accounts, salaries, and other payables | K16: 185582 | L16: 69814 | M16: 151438 | N16: 153 | Q16: 420540 | R16: =SUM(K16:Q16) -> 827527
C17: Contracts payable | Q17: 43790 | R17: =SUM(K17:Q17) -> 43790
C18: Deposits to others | K18: 567800 | R18: =SUM(K18:Q18) -> 567800
C19: Due to other funds | Q19: 363127 | R19: =SUM(K19:Q19) -> 363127
E21: Total liabilities: | K21: =SUM(K16:K19) -> 753382 | L21: =SUM(L16:L19) -> 69814 | M21: =SUM(M16:M19) -> 151438 | N21: =SUM(N16:N19) -> 153 | P21: =SUM(P16:P19) -> 0 | Q21: =SUM(Q16:Q19) -> 827457 | R21: =SUM(R16:R19) -> 1802244
A23: DEFERRED INFLOWS OF RESOURCES
C24: Deferred revenues | K24: 50755 | Q24: 126909 | R24: =SUM(K24:Q24) -> 177664
E26: Total deferred inflows of resources | K26: =SUM(K24:K24) -> 50755 | L26: =SUM(L24:L24) -> 0 | M26: =SUM(M24:M24) -> 0 | N26: =SUM(N24:N24) -> 0 | P26: =SUM(P24:P24) -> 0 | Q26: =SUM(Q24:Q24) -> 126909 | R26: =SUM(R24:R24) -> 177664
B28: Fund Balances
C29: Restricted:
D30: Public safety | O30: 3363950 | Q30: 3988540 | R30: =SUM(K30:Q30) -> 7352490
D31: Public works | L31: 6559166 | Q31: 2218118 | R31: =SUM(K31:Q31) -> 8777284
D32: Health and welfare | N32: 10481 | Q32: 396963 | R32: =SUM(K32:Q32) -> 407444
D33: Debt service | L33: 1552823 | P33: 1097263 | Q33: 25414 | R33: =SUM(K33:Q33) -> 2675500
D34: Other general government | Q34: 1503341 | R34: =SUM(K34:Q34) -> 1503341
C35: Assigned:
D36: Jail capital project | K36: 538003 | R36: =SUM(K36:Q36) -> 538003
C37: Unassigned | K37: 6354861 | M37: -27107 | Q37: -531149 | R37: =SUM(K37:Q37) -> 5796605
E39: Total fund balances: | K39: =SUM(K29:K37) -> 6892864 | L39: =SUM(L29:L37) -> 8111989 | M39: =SUM(M29:M37) -> -27107 | N39: =SUM(N29:N37) -> 10481 | P39: =SUM(P29:P37) -> 1097263 | Q39: =SUM(Q29:Q37) -> 7601227 | R39: =SUM(R29:R37) -> 27050667
E41: Total liabilities and fund balances: | K41: =SUM(K39,K21,K26) -> 7697001 | L41: =SUM(L39,L21,L26) -> 8181803 | M41: =SUM(M39,M21,M26) -> 124331 | N41: =SUM(N39,N21,N26) -> 10634 | P41: =SUM(P39,P21,P26) -> 1097263 | Q41: =SUM(Q39,Q21,Q26) -> 8555593 | R41: =SUM(R39,R21,R26) -> 29030575

Sheet Jefferson
D1: Jefferson Combined Balance Sheet
D2: Issued: December 31, 2015
K5: General Fund | L5: Federal and State Grants | M5: East Bank Consolidated Fire Dictrict | N5: Library | O5: Drainage and Pump Station Capital | P5: Road & Street Capital Improvements | Q5: Other Governmental Funds | R5: Total Governmental Funds
A6: Assets:
B7: Cash and cash equivalents | K7: 12 | O7: 690 | Q7: 4492 | R7: =SUM(K7:Q7) -> 5194
B8: Investments | O8: 18758 | P8: 15768 | Q8: 6707 | R8: =SUM(K8:Q8) -> 41233
B9: Share of pooled assets | K9: 17952 | L9: 2935 | M9: 16128 | N9: 32781 | O9: 116907 | P9: 81578 | Q9: 257650 | R9: =SUM(K9:Q9) -> 525931
B10: Receivables, net of allowances for estimated uncollectibles | R10: =SUM(K10:Q10) -> 0
C11: Intrerest | O11: 89 | P11: 25 | Q11: 12 | R11: =SUM(K11:Q11) -> 126
C12: Ad valorem tax | K12: 4169 | M12: 38929 | N12: 21167 | O12: 15966 | Q12: 120272 | R12: =SUM(K12:Q12) -> 200503
C13: Accounts | K13: 1033 | L13: 1 | M13: 1 | Q13: 4653 | R13: =SUM(K13:Q13) -> 5688
C14: Intergovernmental | K14: 16860 | L14: 15101 | M14: 35 | N14: 37 | O14: 4941 | P14: 341 | Q14: 24690 | R14: =SUM(K14:Q14) -> 62005
B15: Inventories | Q15: 2089 | R15: =SUM(K15:Q15) -> 2089
B16: Deposits and other assets | K16: 856 | R16: =SUM(K16:Q16) -> 856
E18: Total Assets: | K18: =SUM(K7:K16) -> 40882 | L18: =SUM(L7:L16) -> 18037 | M18: =SUM(M7:M16) -> 55093 | N18: =SUM(N7:N16) -> 53985 | O18: =SUM(O7:O16) -> 157351 | P18: =SUM(P7:P16) -> 97712 | Q18: =SUM(Q7:Q16) -> 420565 | R18: =SUM(R7:R16) -> 843625
A20: LIABILITIES, DEFERRED INFLOWS OF RESOURCES, AND FUND BALANCES
B21: Liabilities:
C22: Accounts and contracts payable | K22: 2257 | L22: 2426 | M22: 101 | N22: 185 | O22: 4424 | P22: 10914 | Q22: 11091 | R22: =SUM(K22:Q22) -> 31398
C23: Intergovernmental payable | K23: 25 | L23: 167 | Q23: 1986 | R23: =SUM(K23:Q23) -> 2178
C24: Due to other governments | L24: 7899 | Q24: 1072 | R24: =SUM(K24:Q24) -> 8971
C25: Deposits | K25: 72 | R25: =SUM(K25:Q25) -> 72
C26: Other payables and accruals | K26: 6249 | R26: =SUM(K26:Q26) -> 6249
E28: Total liabilities: | K28: =SUM(K22:K26) -> 8603 | L28: =SUM(L22:L26) -> 10492 | M28: =SUM(M22:M26) -> 101 | N28: =SUM(N22:N26) -> 185 | O28: =SUM(O22:O26) -> 4424 | P28: =SUM(P22:P26) -> 10914 | Q28: =SUM(Q22:Q26) -> 14149 | R28: =SUM(R22:R26) -> 48868
A30: DEFERRED INFLOWS OF RESROUCES
B31: Unavailable revenue- property taxes | K31: 4180 | M31: 39061 | N31: 21220 | O31: 16006 | Q31: 122600 | R31: =SUM(K31:Q31) -> 203067
E33: Total deferred inflows of resources | K33: =SUM(K31:K31) -> 4180 | L33: =SUM(L31:L31) -> 0 | M33: =SUM(M31:M31) -> 39061 | N33: =SUM(N31:N31) -> 21220 | O33: =SUM(O31:O31) -> 16006 | P33: =SUM(P31:P31) -> 0 | Q33: =SUM(Q31:Q31) -> 122600 | R33: =SUM(R31:R31) -> 203067
B35: Fund Balances
C36: Nonspendable | Q36: 2089 | R36: =SUM(K36:Q36) -> 2089
C37: Restricted | K37: 1683 | L37: 7545 | M37: 15931 | N37: 32580 | O37: 136919 | P37: 86798 | Q37: 190521 | R37: =SUM(K37:Q37) -> 471977
C38: Committed | K38: 11460 | Q38: 91206 | R38: =SUM(K38:Q38) -> 102666
C39: Assigned | R39: =SUM(K39:Q39) -> 0
C40: Unassigned | K40: 14956 | R40: =SUM(K40:Q40) -> 14956
E42: Total fund balance: | K42: =SUM(K36:K40) -> 28099 | L42: =SUM(L36:L40) -> 7545 | M42: =SUM(M36:M40) -> 15931 | N42: =SUM(N36:N40) -> 32580 | O42: =SUM(O36:O40) -> 136919 | P42: =SUM(P36:P40) -> 86798 | Q42: =SUM(Q36:Q40) -> 283816 | R42: =SUM(R36:R40) -> 591688
E44: Total liabilities, deffered inflows of resources and fund balances: | K44: =SUM(K28+K33+K42) -> 40882 | L44: =SUM(L28+L33+L42) -> 18037 | M44: =SUM(M28+M33+M42) -> 55093 | N44: =SUM(N28+N33+N42) -> 53985 | O44: =SUM(O28+O33+O42) -> 157349 | P44: =SUM(P28+P33+P42) -> 97712 | Q44: =SUM(Q28+Q33+Q42) -> 420565 | R44: =SUM(R28+R33+R42) -> 843623

Sheet Lafayette
D1: Lafayette Combined Balance Sheet
D2: Issued: October 31, 2015
K4: General | L4: Sales Tax Capital Improvements | M4: Other Governmental Funds | N4: Total Governmental Funds
A5: Assets:
B6: Cash | K6: 2387209 | L6: 3111488 | M6: 12968007 | N6: =SUM(K6:M6) -> 18466704
B7: Investments | K7: 36563839 | L7: 36839001 | M7: 182742506 | N7: =SUM(K7:M7) -> 256145346
B8: Accounts receivable, net | K8: 1349629 | L8: 51544 | M8: 775499 | N8: =SUM(K8:M8) -> 2176672
B9: Loans receivable | M9: 2577503 | N9: =SUM(K9:M9) -> 2577503
B10: Allowance for uncollectible loans | M10: -59979 | N10: =SUM(K10:M10) -> -59979
B11: Assessments receivable | M11: 143880 | N11: =SUM(K11:M11) -> 143880
B12: Accrued interest receivable | K12: 35254 | L12: 35464 | M12: 268870 | N12: =SUM(K12:M12) -> 339588
B13: Due from other funds | K13: 3191072 | L13: 5603076 | M13: 3906770 | N13: =SUM(K13:M13) -> 12700918
B14: Due from other governmental agencies | K14: 868435 | M14: 11742590 | N14: =SUM(K14:M14) -> 12611025
B15: Inventories, at cost | L15: 219311 | M15: 36694 | N15: =SUM(K15:M15) -> 256005
B16: Prepaid items | K16: 1652 | M16: 15162 | N16: =SUM(K16:M16) -> 16814
B17: Property held for resale | K17: 775000 | N17: =SUM(K17:M17) -> 775000
E19: Total assets: | K19: =SUM(K6:K17) -> 45172090 | L19: =SUM(L6:L16) -> 45859884 | M19: =SUM(M6:M18) -> 215117502 | N19: =SUM(N6:N17) -> 306149476
A21: LIABILITIES AND FUND BALANCES
B22: Liabilities:
C23: Cash overdraft | M23: 2965886 | N23: =SUM(K23:M23) -> 2965886
C24: Accounts payable | K24: 671416 | L24: 741636 | M24: 1729718 | N24: =SUM(K24:M24) -> 3142770
C25: Accrued salaries and benefits | K25: 926003 | L25: 41644 | M25: 475497 | N25: =SUM(K25:M25) -> 1443144
C26: Contracts payable | L26: 730774 | M26: 1854032 | N26: =SUM(K26:M26) -> 2584806
C27: Retainage payable | L27: 643281 | M27: 759507 | N27: =SUM(K27:M27) -> 1402788
C28: Other payables | K28: 295789 | M28: 146355 | N28: =SUM(K28:M28) -> 442144
C29: Due to other funds | K29: 344041 | L29: 1310414 | M29: 9918774 | N29: =SUM(K29:M29) -> 11573229
C30: Due to component units | K30: 92392 | N30: =SUM(K30:M30) -> 92392
C31: Due to other governmental agencies | M31: 262270 | N31: =SUM(K31:M31) -> 262270
C32: Unearned revenue | K32: 2411 | L32: 64005 | M32: 144007 | N32: =SUM(K32:M32) -> 210423
E34: Total liabilities: | K34: =SUM(K23:K32) -> 2332052 | L34: =SUM(L23:L32) -> 3531754 | M34: =SUM(M23:M32) -> 18256046 | N34: =SUM(N23:N32) -> 24119852
B36: Fund Balances
C37: Nonspendable -
D38: Inventories | L38: 219311 | M38: 36694 | N38: =SUM(K38:M38) -> 256005
D39: Prepaid items | K39: 1652 | M39: 15162 | N39: =SUM(K39:M39) -> 16814
C40: Restricted - | N40: =SUM(K40:M40) -> 0
D41: Capital expenditures | L41: 33380899 | M41: 94992348 | N41: =SUM(K41:M41) -> 128373247
D42: Debt service | M42: 45027523 | N42: =SUM(K42:M42) -> 45027523
D43: Operations and maintenance | M43: 49316239 | N43: =SUM(K43:M43) -> 49316239
D44: Purpose of grantors and donors | M44: 4882793 | N44: =SUM(K44:M44) -> 4882793
C45: Committed -
D46: Incomplete projects | K46: 670452 | M46: 26723 | N46: =SUM(K46:M46) -> 697175
C47: Assigned - | N47: =SUM(K47:M47) -> 0
D48: Subsequent year's expenditures | K48: 2774438 | L48: 8727920 | M48: 2563974 | N48: =SUM(K48:M48) -> 14066332
C49: Unassigned | K49: 39393496 | N49: =SUM(K49:M49) -> 39393496
E51: Total fund balance: | K51: =SUM(K38:K49) -> 42840038 | L51: =SUM(L38:L49) -> 42328130 | M51: =SUM(M38:M49) -> 196861456 | N51: =SUM(N37:N49) -> 282029624
E53: Total liabilities and fund balances: | K53: =SUM(K51,K34) -> 45172090 | L53: =SUM(L34,L51) -> 45859884 | M53: =SUM(M34,M51) -> 215117502 | N53: =SUM(N34,N51) -> 306149476

Sheet Lafourche
D1: Lafourche Combined Balance Sheet
D2: Issued: December 31, 2015
O4: Major Funds
K5: General | L5: Solid Waste | M5: Board of Health | N5: Library Commission | O5: BP Oil Spill Fund | P5: Capital Projects | Q5: Non-Major Funds | R5: Total
A6: Assets:
B7: Cash and cash equivalents | K7: 2493094 | N7: 861297 | O7: 6125197 | Q7: 8161260 | R7: =SUM(K7:Q7) -> 17640848
B8: Investments | K8: 28364 | L8: 1595639 | M8: 110030 | N8: 7967465 | Q8: 17205246 | R8: =SUM(K8:Q8) -> 26906744
B9: Receivables | K9: 468148 | N9: 2 | O9: 1975 | Q9: 942293 | R9: =SUM(K9:Q9) -> 1412418
B10: Due from other governmental units | K10: 5646979 | L10: 1516971 | M10: 708560 | N10: 5762420 | Q10: 20063784 | R10: =SUM(K10:Q10) -> 33698714
B11: Due from other funds | K11: 9218015 | M11: 581224 | O11: 4999 | P11: 2257300 | Q11: 7163970 | R11: =SUM(K11:Q11) -> 19225508
B12: Other current assets | Q12: 1035138 | R12: =SUM(K12:Q12) -> 1035138
B13: Prepaid assets | K13: 955831 | R13: =SUM(K13:Q13) -> 955831
E15: Total Assets: | K15: =SUM(K7:K13) -> 18810431 | L15: =SUM(L7:L13) -> 3112610 | M15: =SUM(M7:M13) -> 1399814 | N15: =SUM(N7:N13) -> 14591184 | O15: =SUM(O7:O13) -> 6132171 | P15: =SUM(P7:P13) -> 2257300 | Q15: =SUM(Q7:Q13) -> 54571691 | R15: =SUM(R7:R13) -> 100875201
A17: LIABILITIES AND FUND BALANCES
B18: Liabilities:
C19: Accounts payable and accrued expenses | K19: 742412 | L19: 637824 | M19: 3509 | N19: 46255 | P19: 2211472 | Q19: 1573952 | R19: =SUM(K19:Q19) -> 5215424
C20: Contracts and retainages payable | K20: 36225 | P20: 111078 | Q20: 42345 | R20: =SUM(K20:Q20) -> 189648
C21: Salaries and benefits payable | K21: 196073 | L21: 6137 | M21: 11399 | N21: 113185 | Q21: 331272 | R21: =SUM(K21:Q21) -> 658066
C22: Due to other funds | K22: 13293086 | L22: 202 | N22: 35790 | Q22: 6393257 | R22: =SUM(K22:Q22) -> 19722335
C23: Due to other governmental units | M23: 1006500 | Q23: 20557 | R23: =SUM(K23:Q23) -> 1027057
C24: Other current liabilities | K24: 4414 | Q24: 635207 | R24: =SUM(K24:Q24) -> 639621
E26: Total liabilities: | K26: =SUM(K19:K24) -> 14272210 | L26: =SUM(L19:L24) -> 644163 | N26: =SUM(N19:N24) -> 195230 | O26: =SUM(O19:O24) -> 0 | P26: =SUM(P19:P24) -> 2322550 | Q26: =SUM(Q19:Q24) -> 8996590 | R26: =SUM(R19:R24) -> 27452151
B28: Fund Balances
C29: Non-spendable for prepaid assets | K29: 955831 | R29: =SUM(K29:Q29) -> 955831
C30: Restricted:
D31: Capital projects | K31: 1820407 | N31: 433269 | Q31: 8770639 | R31: =SUM(K31:Q31) -> 11024315
D32: Judicial programs | Q32: 3842210 | R32: =SUM(K32:Q32) -> 3842210
D33: Federal and state grant programs | O33: 6132171 | Q33: 563984 | R33: =SUM(K33:Q33) -> 6696155
D34: Debt service | Q34: 5955009 | R34: =SUM(K34:Q34) -> 5955009
C35: Commited:
D36: Public safety | M36: 378406 | Q36: 234259 | R36: =SUM(K36:Q36) -> 612665
D37: Public works | L37: 2468447 | Q37: 22441149 | R37: =SUM(K37:Q37) -> 24909596
D38: Culture and recreation | N38: 13962685 | Q38: 1837319 | R38: =SUM(K38:Q38) -> 15800004
D39: Health and community services | Q39: 1906379 | R39: =SUM(K39:Q39) -> 1906379
C40: Unassigned | K40: 1761983 | P40: -65250 | Q40: 24153 | R40: =SUM(K40:Q40) -> 1720886
E42: Total fund balance: | K42: =SUM(K29:K41) -> 4538221 | L42: =SUM(L29:L40) -> 2468447 | M42: =SUM(M29:M40) -> 378406 | N42: =SUM(N29:N40) -> 14395954 | O42: =SUM(O29:O40) -> 6132171 | P42: =SUM(P29:P40) -> -65250 | Q42: =SUM(Q29:Q40) -> 45575101 | R42: =SUM(R29:R40) -> 73423050
E44: Total liabilities and fund balances: | K44: =SUM(K42,K26) -> 18810431 | L44: =SUM(L26,L42) -> 3112610 | M44: =SUM(M26,M42) -> 378406 | N44: =SUM(N26,N42) -> 14591184 | O44: =SUM(O26,O42) -> 6132171 | P44: =SUM(P26,P42) -> 2257300 | Q44: =SUM(Q26,Q42) -> 54571691 | R44: =SUM(R26,R42) -> 100875201

Sheet LaSalle
D1: LaSalle Combined Balance Sheet
D2: Issued: December 31, 2015
K4: General Fund | L4: Road and Bridge | M4: Courthouse Maintenance | N4: Garbage District | O4: Library | P4: Criminal Court | Q4: Other Governmental Funds | R4: Total Governmental Funds
A5: Assets:
B6: Cash and equivalents | K6: 222061 | L6: 38941 | M6: 43859 | N6: 145331 | O6: 1427925 | Q6: 832535 | R6: =SUM(K6:Q6) -> 2710652
B7: Prepaid lease payments | L7: 4283 | N7: 3783 | Q7: 1785 | R7: =SUM(K7:Q7) -> 9851
B8: Receivables | K8: 372247 | L8: 584719 | M8: 454170 | N8: 562899 | O8: 533568 | P8: 5683 | Q8: 568104 | R8: =SUM(K8:Q8) -> 3081390
E10: Total assets: | K10: =SUM(K6:K8) -> 594308 | L10: =SUM(L6:L8) -> 627943 | M10: =SUM(M6:M8) -> 498029 | N10: =SUM(N6:N8) -> 712013 | O10: =SUM(O6:O8) -> 1961493 | P10: =SUM(P6:P8) -> 5683 | Q10: =SUM(Q6:Q8) -> 1402424 | R10: =SUM(R6:R8) -> 5801893
A12: LIABILITIES AND FUND BALANCES
B13: Liabilities:
C14: Cash overdraft | P14: 166079 | R14: =SUM(K14:Q14) -> 166079
C15: Accounts payable | K15: 209298 | L15: 33278 | M15: 34166 | N15: 55245 | O15: 37977 | P15: 14475 | Q15: 50079 | R15: =SUM(K15:Q15) -> 434518
C16: Salaries and related payable | K16: 20745 | L16: 7837 | M16: 1254 | N16: 2121 | O16: 3442 | P16: 3987 | Q16: 526 | R16: =SUM(K16:Q16) -> 39912
E18: Total liabilities: | K18: =SUM(K14:K16) -> 230043 | L18: =SUM(L14:L16) -> 41115 | M18: =SUM(M14:M16) -> 35420 | N18: =SUM(N14:N16) -> 57366 | O18: =SUM(O14:O16) -> 41419 | P18: =SUM(P14:P16) -> 184541 | Q18: =SUM(Q14:Q16) -> 50605 | R18: =SUM(R14:R16) -> 640509
B20: Fund Balances:
C21: Nonspendable | Q21: 1785 | R21: =SUM(K21:Q21) -> 1785
C22: Restricted:
D23: Other general government | M23: 462609 | P23: -178858 | R23: =SUM(K23:Q23) -> 283751
D24: Public works | L24: 586828 | N24: 654647 | Q24: 1045271 | R24: =SUM(K24:Q24) -> 2286746
D25: Health and welfare | Q25: 220260 | R25: =SUM(K25:Q25) -> 220260
D26: Culture and recreation | O26: 1920074 | R26: =SUM(K26:Q26) -> 1920074
C27: Committed | Q27: 84503 | R27: =SUM(K27:Q27) -> 84503
C28: Unassigned | K28: 364265 | R28: =SUM(K28:Q28) -> 364265
E30: Total Fund Equity- fund balances (deficit) | K30: =SUM(K21:K28) -> 364265 | L30: =SUM(L21:L28) -> 586828 | M30: =SUM(M21:M28) -> 462609 | N30: =SUM(N21:N28) -> 654647 | O30: =SUM(O21:O28) -> 1920074 | P30: =SUM(P21:P28) -> -178858 | Q30: =SUM(Q21:Q28) -> 1351819 | R30: =SUM(R21:R28) -> 5161384
E32: Total liabilities and fund balances: | K32: =K30+K18 -> 594308 | L32: =L30+L18 -> 627943 | M32: =M30+M18 -> 498029 | N32: =N30+N18 -> 712013 | O32: =O30+O18 -> 1961493 | P32: =P30+P18 -> 5683 | Q32: =Q30+Q18 -> 1402424 | R32: =R30+R18 -> 5801893

Sheet Lincoln
D1: Lincoln Combined Balance Sheet
D2: Issued: December 31, 2015
K4: General Fund | L4: Road Construction Fund | M4: Road Maintenance Fund | N4: Library Fund | O4: Solid Waste Disposal Fund | P4: Solid Waste Disposal Equipment Reserve Fund | Q4: Hospital Proceeds Fund | R4: Nonmajor Governmental Funds | S4: Total Governmental Funds
A5: Assets:
B6: Cash and cash equivalents | K6: 1513461 | L6: 2226051 | M6: 1898122 | N6: 276750 | P6: 129057 | Q6: 450805 | R6: 6183346 | S6: =SUM(K6:R6) -> 12677592
B7: Investments | K7: 2075344 | L7: 544826 | M7: 1025040 | N7: 2446566 | P7: 3007391 | Q7: 9966830 | R7: 3069977 | S7: =SUM(K7:R7) -> 22135974
B8: Receivables | K8: 1279234 | L8: 1792774 | M8: 1789202 | N8: 1977024 | O8: 983413 | P8: 1932 | R8: 821117 | S8: =SUM(K8:R8) -> 8644696
B9: Due from other funds | K9: 491604 | L9: 4714 | M9: 4709 | O9: 4327 | R9: 1541553 | S9: =SUM(K9:R9) -> 2046907
B10: Due from other entities | K10: 297704 | L10: 191 | M10: 34 | R10: 35857 | S10: =SUM(K10:R10) -> 333786
B11: Inventory | L11: 11582 | S11: =SUM(K11:N11) -> 11582
E13: Total Assets: | K13: =SUM(K6:K11) -> 5657347 | L13: =SUM(L6:L11) -> 4580138 | M13: =SUM(M6:M11) -> 4717107 | N13: =SUM(N6:N11) -> 4700340 | O13: =SUM(O6:O11) -> 987740 | P13: =SUM(P6:P11) -> 3138380 | Q13: =SUM(Q6:Q11) -> 10417635 | R13: =SUM(R6:R11) -> 11651850 | S13: =SUM(S6:S11) -> 45850537
A15: LIABILITIES AND FUND BALANCES
B16: Liabilities:
C17: Cash overdraft | O17: 328053 | R17: 166467 | S17: =SUM(K17:R17) -> 494520
C18: Accounts payable | K18: 174453 | L18: 64976 | M18: 460208 | N18: 105632 | O18: 673802 | Q18: 2500 | R18: 206129 | S18: =SUM(K18:R18) -> 1687700
C19: Salaries and related payables | K19: 134316 | S19: =SUM(K19:R19) -> 134316
C20: Due to other agencies | K20: 520475 | R20: 283022 | S20: =SUM(K20:R20) -> 803497
C21: Due to other funds | K21: 1115881 | P21: 336880 | Q21: 417635 | R21: 176511 | S21: =SUM(K21:R21) -> 2046907
E23: Total liabilities: | K23: =SUM(K17:K21) -> 1945125 | L23: =SUM(L17:L21) -> 64976 | M23: =SUM(M17:M21) -> 460208 | N23: =SUM(N17:N21) -> 105632 | O23: =SUM(O17:O21) -> 1001855 | P23: =SUM(P17:P21) -> 336880 | Q23: =SUM(Q17:Q21) -> 420135 | R23: =SUM(R17:R21) -> 832129 | S23: =SUM(S17:S21) -> 5166940
B25: Fund Balances
C26: Nonspendable | L26: 11582 | S26: =SUM(K26:R26) -> 11582
C27: Restricted | R27: 540866 | S27: =SUM(K27:R27) -> 540866
C28: Assigned | L28: 4503580 | M28: 4256899 | N28: 4594708 | P28: 2801500 | Q28: 9997500 | R28: 10278855 | S28: =SUM(K28:R28) -> 36433042
C29: Unassigned | K29: 3712222 | O29: -14115 | S29: =SUM(K29:R29) -> 3698107
E31: Total fund equity | K31: =SUM(K26:K30) -> 3712222 | L31: =SUM(L26:L29) -> 4515162 | M31: =SUM(M26:M29) -> 4256899 | N31: =SUM(N26:N29) -> 4594708 | O31: =SUM(O26:O29) -> -14115 | P31: =SUM(P26:P29) -> 2801500 | Q31: =SUM(Q26:Q29) -> 9997500 | R31: =SUM(R26:R29) -> 10819721 | S31: =SUM(S25:S29) -> 40683597
E33: Total liabilities and fund equity | K33: =K31+K23 -> 5657347 | L33: =L31+L23 -> 4580138 | M33: =M31+M23 -> 4717107 | N33: =N31+N23 -> 4700340 | O33: =O31+O23 -> 987740 | P33: =P31+P23 -> 3138380 | Q33: =Q31+Q23 -> 10417635 | R33: =R31+R23 -> 11651850 | S33: =S31+S23 -> 45850537

Sheet Livingston
D1: Livingston Combined Balance Sheet
D2: Issued: December 31, 2015
K4: Major Funds
K5: General Fund | L5: Health Unit Fund | M5: Jail Sales Tax Fund | N5: Road Fund | O5: Road 06 Debt Service Fund | P5: Other Governemntal Funds | Q5: Total Governmental Funds
A6: Assets:
B7: Cash and cash equivalents | K7: 53486 | L7: 2827050 | N7: 4649898 | P7: 3416796 | Q7: =SUM(K7:P7) -> 10947230
B8: Pooled Cash in Other Funds | K8: 3206017 | Q8: =SUM(K8:P8) -> 3206017
B9: Investments | K9: 71276 | L9: 3069876 | N9: 268927 | Q9: =SUM(K9:P9) -> 3410079
B10: Receivables, net of allowance | K10: 522803 | L10: 70 | M10: 3317 | N10: 364 | P10: 488782 | Q10: =SUM(K10:P10) -> 1015336
B11: Restricted assets:
C12: Cash | K12: 97896 | O12: 3405391 | P12: 3311766 | Q12: =SUM(K12:P12) -> 6815053
B13: Inventory | M13: 15947 | N13: 215812 | Q13: =SUM(K13:P13) -> 231759
B14: Due from component units | P14: 116846 | Q14: =SUM(K14:P14) -> 116846
B15: Due from other funds | K15: 4026470 | N15: 1388509 | Q15: =SUM(K15:P15) -> 5414979
B16: Due from other governments | K16: 1467200 | L16: 1001405 | M16: 760671 | N16: 4739168 | P16: 3612117 | Q16: =SUM(K16:P16) -> 11580561
B17: Advance to jail sales tax fund | K17: 3431708 | L17: 300000 | Q17: =SUM(K17:P17) -> 3731708
E19: Total Assets: | K19: =SUM(K7:K17) -> 12876856 | L19: =SUM(L7:L17) -> 7198401 | M19: =SUM(M7:M17) -> 779935 | N19: =SUM(N7:N17) -> 11262678 | O19: =SUM(O7:O17) -> 3405391 | P19: =SUM(P7:P17) -> 10946307 | Q19: =SUM(Q7:Q17) -> 46469568
A21: LIABILITIES AND FUND BALANCES
B22: Liabilities:
C23: Accounts payables | K23: 301132 | L23: 20943 | M23: 213007 | N23: 474302 | P23: 1209273 | Q23: =SUM(K23:P23) -> 2218657
C24: Deficit in Pooled Cash | M24: 2064910 | P24: 1141107 | Q24: =SUM(K24:P24) -> 3206017
C25: Accrued expenses payable | K25: 237941 | L25: 45536 | M25: 36493 | N25: 238487 | P25: 19542 | Q25: =SUM(K25:P25) -> 577999
C26: Due to component units | P26: 142562 | Q26: =SUM(K26:P26) -> 142562
C27: Due to other governments | K27: 255886 | L27: 47467 | M27: 60856 | N27: 125407 | P27: 620664 | Q27: =SUM(K27:P27) -> 1110280
C28: Due to other funds | K28: 837948 | L28: 227549 | M28: 2624842 | N28: 1303434 | P28: 398823 | Q28: =SUM(K28:P28) -> 5392596
C29: Unearned revenue | K29: 19700 | Q29: =SUM(K29:P29) -> 19700
C30: Advances from other funds | M30: 3731708 | Q30: =SUM(K30:P30) -> 3731708
E32: Total liabilities: | K32: =SUM(K23:K30) -> 1652607 | L32: =SUM(L23:L30) -> 341495 | M32: =SUM(M23:M30) -> 8731816 | N32: =SUM(N23:N30) -> 2141630 | O32: =SUM(O23:O30) -> 0 | P32: =SUM(P23:P30) -> 3531971 | Q32: =SUM(Q23:Q30) -> 16399519
B34: Fund Balances
C35: Non-spendable:
D36: Inventory | M36: 15947 | N36: 215812 | Q36: =SUM(K36:P36) -> 231759
D37: Advances | K37: 3431708 | L37: 300000 | Q37: =SUM(K37:P37) -> 3731708
C38: Restricted for:
D39: Construction | P39: 945547 | Q39: =SUM(K39:P39) -> 945547
D40: Criminal court | P40: 36532 | Q40: =SUM(K40:P40) -> 36532
D41: Criminal court witness | P41: 42800 | Q41: =SUM(K41:P41) -> 42800
D42: Debt service | O42: 3405391 | P42: 4292485 | Q42: =SUM(K42:P42) -> 7697876
D43: Grant expenditures | K43: 97896 | Q43: =SUM(K43:P43) -> 97896
C44: Commited to:
D45: Construction | N45: 467590 | Q45: =SUM(K45:P45) -> 467590
D46: State grant programs | N46: 448367 | Q46: =SUM(K46:P46) -> 448367
D47: Federal grant programs | K47: 22500 | Q47: =SUM(K47:P47) -> 22500
D48: Other purposes | K48: 15233 | Q48: =SUM(K48:P48) -> 15233
C49: Assigned to:
D50: Bingo | P50: 7140 | Q50: =SUM(K50:P50) -> 7140
D51: Court fees | P51: 1840571 | Q51: =SUM(K51:P51) -> 1840571
D52: Health unit | L52: 6556906 | Q52: =SUM(K52:P52) -> 6556906
D53: Road | N53: 7989279 | Q53: =SUM(K53:P53) -> 7989279
D54: Other purposes | K54: 248113 | P54: 153844 | Q54: =SUM(K54:P54) -> 401957
C55: Unassigned | K55: 7408799 | M55: -7967828 | P55: 95417 | Q55: =SUM(K55:P55) -> -463612
E57: Total fund balances (Deficits): | K57: =SUM(K35:K56) -> 11224249 | L57: =SUM(L36:L55) -> 6856906 | M57: =SUM(M35:M55) -> -7951881 | N57: =SUM(N36:N55) -> 9121048 | O57: =SUM(O36:O55) -> 3405391 | P57: =SUM(P36:P55) -> 7414336 | Q57: =SUM(Q36:Q55) -> 30070049
E59: Total liabilities and fund balances (Deficits): | K59: =SUM(K57,K32) -> 12876856 | L59: =SUM(L32,L57) -> 7198401 | M59: =SUM(M32,M57) -> 779935 | N59: =SUM(N32,N57) -> 11262678 | O59: =SUM(O32,O57) -> 3405391 | P59: =SUM(P32,P57) -> 10946307 | Q59: =SUM(Q32,Q57) -> 46469568

Sheet Madison
D1: Madison Combined Balance Sheet
D2: Issued: December 31, 2015
K5: General Fund | L5: Library | M5: Garbage Maintenance | N5: Health Unit | O5: Public Works | P5: Courthouse and Jail | Q5: E-911 | R5: Other Governmental Funds | S5: Total
A6: Assets:
B7: Cash and cash equivalents | K7: 173630 | L7: 619289 | M7: 834855 | N7: 1093174 | O7: 29909 | P7: 2833723 | Q7: 226147 | R7: 385311 | S7: =SUM(K7:R7) -> 6196038
B8: Investments | L8: 321097 | P8: 2055945 | Q8: 676590 | S8: =SUM(K8:R8) -> 3053632
B9: Receivables | K9: 626868 | L9: 557576 | M9: 519937 | N9: 274027 | O9: 1762330 | P9: 1448431 | Q9: 329681 | R9: 40144 | S9: =SUM(K9:R9) -> 5558994
B10: Interfund receivables | K10: 387487 | M10: 411006 | N10: 40 | P10: 235315 | S10: =SUM(K10:R10) -> 1033848
E12: Total Assets: | K12: =SUM(K7:K10) -> 1187985 | L12: =SUM(L7:L10) -> 1497962 | M12: =SUM(M7:M10) -> 1765798 | N12: =SUM(N7:N10) -> 1367241 | O12: =SUM(O7:O10) -> 1792239 | P12: =SUM(P7:P10) -> 6573414 | Q12: =SUM(Q7:Q10) -> 1232418 | R12: =SUM(R7:R10) -> 425455 | S12: =SUM(S7:S10) -> 15842512
A14: LIABILITIES AND FUND BALANCES
B15: Liabilities: | S15: =SUM(K15:R15) -> 0
C16: Accounts, salaries and other payables | K16: 239938 | L16: 19879 | M16: 4086 | N16: 599 | O16: 35729 | P16: 54082 | R16: 51823 | S16: =SUM(K16:R16) -> 406136
C17: Interfund payables | K17: 234582 | O17: 411006 | R17: 388260 | S17: =SUM(K17:R17) -> 1033848
E19: Total liabilities: | K19: =SUM(K16:K17) -> 474520 | L19: =SUM(L16:L17) -> 19879 | M19: =SUM(M16:M17) -> 4086 | N19: =SUM(N16:N17) -> 599 | O19: =SUM(O16:O17) -> 446735 | P19: =SUM(P16:P17) -> 54082 | Q19: =SUM(Q16:Q17) -> 0 | R19: =SUM(R16:R17) -> 440083 | S19: =SUM(S16:S17) -> 1439984
B21: Fund Balances
C22: Restricted | L22: 1478083 | M22: 1761712 | N22: 1366642 | O22: 1345504 | P22: 6519332 | Q22: 1232418 | R22: -14628 | S22: =SUM(K22:R22) -> 13689063
C23: Unassigned | K23: 713465 | S23: =SUM(K23:R23) -> 713465
E25: Total fund balances: | K25: =SUM(K22:K24) -> 713465 | L25: =SUM(L22:L23) -> 1478083 | M25: =SUM(M22:M23) -> 1761712 | N25: =SUM(N22:N23) -> 1366642 | O25: =SUM(O22:O23) -> 1345504 | P25: =SUM(P22:P23) -> 6519332 | Q25: =SUM(Q22:Q23) -> 1232418 | R25: =SUM(R22:R23) -> -14628 | S25: =SUM(S22:S23) -> 14402528
E27: Total liabilities and fund balances: | K27: =K25+K19 -> 1187985 | L27: =L25+L19 -> 1497962 | M27: =M25+M19 -> 1765798 | N27: =N25+N19 -> 1367241 | O27: =O25+O19 -> 1792239 | P27: =P25+P19 -> 6573414 | Q27: =Q25+Q19 -> 1232418 | R27: =R25+R19 -> 425455 | S27: =S25+S19 -> 15842512

Sheet Morehouse
D1: Morehouse Combined Balance Sheet
D2: Issued: December 31, 2015
K5: General | L5: Road Maintenance | M5: Drainage Maintenance | N5: Building Maintenance | O5: Solid Waste | P5: Health Unit | Q5: Criminal Court | R5: Other Governmental Funds | S5: Total Governmental Funds
A6: Assets:
B7: Cash | L7: 797336 | M7: 1200524 | O7: 1640237 | P7: 726746 | R7: 314477 | S7: =SUM(K7:R7) -> 4679320
B8: Investments | K8: 25000 | L8: 100000 | M8: 375000 | P8: 25000 | R8: 15000 | S8: =SUM(K8:R8) -> 540000
B9: Receivables | K9: 616047 | L9: 799851 | M9: 353297 | N9: 224444 | P9: 138551 | Q9: 8749 | R9: 82022 | S9: =SUM(K9:R9) -> 2222961
B10: Due from other Funds | M10: 1962 | O10: 9402 | S10: =SUM(K10:R10) -> 11364
E12: Total Assets: | K12: =SUM(K7:K10) -> 641047 | L12: =SUM(L7:L10) -> 1697187 | M12: =SUM(M7:M10) -> 1930783 | N12: =SUM(N7:N10) -> 224444 | O12: =SUM(O7:O10) -> 1649639 | P12: =SUM(P7:P10) -> 890297 | Q12: =SUM(Q7:Q10) -> 8749 | R12: =SUM(R7:R10) -> 411499 | S12: =SUM(S7:S10) -> 7453645
A14: LIABILITIES
C15: Bank overdraft | K15: 1516047 | N15: 296672 | Q15: 377155 | S15: =SUM(K15:R15) -> 2189874
C16: Accounts payable | K16: 135161 | L16: 22652 | M16: 1572 | N16: 14781 | O16: 4846 | P16: 393 | Q16: 352 | R16: 3943 | S16: =SUM(K16:R16) -> 183700
C17: Payroll accruals and withholdings | K17: 40297 | Q17: 5818 | S17: =SUM(K17:R17) -> 46115
C18: Due to other funds | K18: 9402 | L18: 1962 | S18: =SUM(K18:R18) -> 11364
E20: Total liabilities: | K20: =SUM(K15:K18) -> 1700907 | L20: =SUM(L15:L18) -> 24614 | M20: =SUM(M15:M18) -> 1572 | N20: =SUM(N15:N18) -> 311453 | O20: =SUM(O15:O18) -> 4846 | P20: =SUM(P15:P18) -> 393 | Q20: =SUM(Q15:Q18) -> 383325 | R20: =SUM(R15:R18) -> 3943 | S20: =SUM(S15:S18) -> 2431053
A22: DEFERRED INFLOWS OF RESOURCES
C23: Property taxes | K23: 524600 | L23: 773100 | M23: 353304 | N23: 224448 | P23: 138553 | R23: 78976 | S23: =SUM(K23:R23) -> 2092981
B25: Fund Balances
C26: Restricted for special revenue | L26: 899473 | M26: 1575907 | O26: 1644793 | P26: 751351 | R26: 328580 | S26: =SUM(K26:R26) -> 5200104
C27: Unassigned for special revenue (deficit) | N27: -311457 | Q27: -374576 | S27: =SUM(K27:R27) -> -686033
C28: Unassigned (deficit) | K28: -1584460 | S28: =SUM(K28:R28) -> -1584460
E30: Total fund balance: | K30: =SUM(K26:K29) -> -1584460 | L30: =SUM(L26:L28) -> 899473 | M30: =SUM(M26:M28) -> 1575907 | N30: =SUM(N26:N28) -> -311457 | O30: =SUM(O26:O28) -> 1644793 | P30: =SUM(P26:P28) -> 751351 | Q30: =SUM(Q26:Q28) -> -374576 | R30: =SUM(R26:R28) -> 328580 | S30: =SUM(S26:S28) -> 2929611
E32: Total liabilities, deferred inflows of resources, and fund balances: | K32: =K30+K23+K20 -> 641047 | L32: =L30+L23+L20 -> 1697187 | M32: =M30+M23+M20 -> 1930783 | N32: =N30+N23+N20 -> 224444 | O32: =O30+O23+O20 -> 1649639 | P32: =P30+P23+P20 -> 890297 | Q32: =Q30+Q23+Q20 -> 8749 | R32: =R30+R23+R20 -> 411499 | S32: =S30+S23+S20 -> 7453645

Sheet Natchitoches
D1: Natchitoches Combined Balance Sheet
D2: Issued: May 31, 2015
N4: Major Funds
K5: General Fund | L5: Road Maintenance Fund | M5: Sales Tax Fund | N5: Parish Library Fund | O5: Disposal Solid Waste | P5: Governmental Building Fund | Q5: Head Start Fund | R5: Nonmajor Funds | S5: Total Governmental Funds
A6: Assets:
B7: Cash and cash equivalents | K7: 822299 | L7: 896589 | M7: 1503822 | N7: 1601596 | O7: 363265 | P7: 1457572 | Q7: 113419 | R7: 1564919 | S7: =SUM(K7:R7) -> 8323481
B8: Revenue receivables | K8: 948256 | L8: 1157580 | M8: 286173 | N8: 1923182 | O8: 3668 | P8: 7834188 | R8: 913562 | S8: =SUM(K8:R8) -> 13066609
B9: Due from other Funds | R9: 5595 | S9: =SUM(K9:R9) -> 5595
E11: Total Assets: | K11: =SUM(K7:K9) -> 1770555 | L11: =SUM(L7:L9) -> 2054169 | M11: =SUM(M7:M9) -> 1789995 | N11: =SUM(N7:N9) -> 3524778 | O11: =SUM(O7:O9) -> 366933 | P11: =SUM(P7:P9) -> 9291760 | Q11: =SUM(Q7:Q9) -> 113419 | R11: =SUM(R7:R9) -> 2484076 | S11: =SUM(S7:S9) -> 21395685
A13: LIABILITIES
C14: Cash overdraft | R14: 5846 | S14: =SUM(K14:R14) -> 5846
C15: Accounts payable | K15: 342905 | L15: 98496 | N15: 119223 | O15: 124430 | P15: 12271 | R15: 33937 | S15: =SUM(K15:R15) -> 731262
C16: Accrued Payroll | L16: 7761 | N16: 2263 | O16: 7164 | P16: 1507 | Q16: 4441 | R16: 11243 | S16: =SUM(K16:R16) -> 34379
C17: Due to other governments | R17: 774223 | S17: =SUM(K17:R17) -> 774223
C18: Due to other funds | R18: 5595 | S18: =SUM(K18:R18) -> 5595
E20: Total liabilities: | K20: =SUM(K14:K18) -> 342905 | L20: =SUM(L14:L18) -> 106257 | M20: =SUM(M14:M18) -> 0 | N20: =SUM(N14:N18) -> 121486 | O20: =SUM(O14:O18) -> 131594 | P20: =SUM(P14:P18) -> 13778 | Q20: =SUM(Q14:Q18) -> 4441 | R20: =SUM(R14:R18) -> 830844 | S20: =SUM(S14:S18) -> 1551305
B22: Fund Balances
C23: Fund Balances- | S23: =SUM(K23:R23) -> 0
D24: Restricted | L24: 1947912 | M24: 1789995 | N24: 3403292 | O24: 235339 | P24: 2227212 | Q24: 108978 | R24: 2310225 | S24: =SUM(K24:R24) -> 12022953
D25: Unassigned | K25: 1427650 | R25: -656993 | S25: =SUM(K25:R25) -> 770657
E27: Total fund balance: | K27: =SUM(K23:K25) -> 1427650 | L27: =SUM(L23:L25) -> 1947912 | M27: =SUM(M23:M25) -> 1789995 | N27: =SUM(N23:N25) -> 3403292 | O27: =SUM(O23:O25) -> 235339 | P27: =SUM(P23:P25) -> 2227212 | Q27: =SUM(Q23:Q25) -> 108978 | R27: =SUM(R23:R25) -> 1653232 | S27: =SUM(S23:S25) -> 12793610
E29: Total liabilities and fund balances: | K29: =K27+K20 -> 1770555 | L29: =L27+L20 -> 2054169 | M29: =M27+M20 -> 1789995 | N29: =N27+N20 -> 3524778 | O29: =O27+O20 -> 366933 | P29: =P27+P20 -> 2240990 | Q29: =Q27+Q20 -> 113419 | R29: =R27+R20 -> 2484076 | S29: =S27+S20 -> 14344915

Sheet Orleans
D1: Orleans Combined Balance Sheet
D2: Issued: December 31, 2015
I3: (amounts in thousands)
K5: General Fund | L5: HUD | M5: Federal UDAG | N5: FEMA | O5: Debt Service | P5: Capital Projects | Q5: Louisiana Office of Community Development | R5: Nonmajor Governmental | S5: Total Governmental Funds
A6: Assets:
B7: Cash and cash equivalents | K7: 54520 | M7: 12097 | O7: 303 | P7: 24314 | Q7: 49 | R7: 40199 | S7: =SUM(K7:R7) -> 131482
B8: Investments | K8: 768 | O8: 76351 | P8: 141071 | R8: 8918 | S8: =SUM(K8:R8) -> 227108
B9: Receivables (net of allowance for uncollectibles): | S9: =SUM(K9:R9) -> 0
C10: Sales taxes | K10: 18319 | S10: =SUM(K10:R10) -> 18319
C11: Property taxes | K11: 2195 | O11: 1118 | R11: 160 | S11: =SUM(K11:R11) -> 3473
C12: Franchise taxes | K12: 6662 | S12: =SUM(K12:R12) -> 6662
C13: Accounts | K13: 13342 | L13: 170 | P13: 6 | R13: 1927 | S13: =SUM(K13:R13) -> 15445
C14: Grantee loans | M14: 542 | S14: =SUM(K14:R14) -> 542
B15: Due from other funds | K15: 19790 | L15: 261 | N15: 3935 | Q15: 101 | R15: 1 | S15: =SUM(K15:R15) -> 24088
B16: Due from other governments | K16: 2188 | L16: 4716 | N16: 6230 | P16: 19019 | Q16: 2891 | R16: 4805 | S16: =SUM(K16:R16) -> 39849
B17: Due from component units | K17: 1413 | P17: 9792 | S17: =SUM(K17:R17) -> 11205
B18: Advances to other funds | K18: 2 | S18: =SUM(K18:R18) -> 2
B19: Other assets | K19: 3 | N19: 26 | R19: 228 | S19: =SUM(K19:R19) -> 257
E21: Total Assets: | K21: =SUM(K7:K20) -> 119202 | L21: =SUM(L7:L19) -> 5147 | M21: =SUM(M7:M19) -> 12639 | N21: =SUM(N7:N19) -> 10191 | O21: =SUM(O7:O19) -> 77772 | P21: =SUM(P7:P19) -> 194202 | Q21: =SUM(Q7:Q19) -> 3041 | R21: =SUM(R7:R19) -> 56238 | S21: =SUM(S7:S19) -> 478432
A23: LIABILITIES
C24: Accounts payable | K24: 37398 | L24: 4086 | M24: 471 | N24: 14625 | P24: 28565 | Q24: 8525 | R24: 6720 | S24: =SUM(K24:R24) -> 100390
C25: Retainages payable | P25: 3483 | S25: =SUM(K25:R25) -> 3483
C26: Accrued expenses | L26: 149 | M26: 4 | N26: 235 | Q26: 121 | R26: 284 | S26: =SUM(K26:R26) -> 793
C27: Due to other funds | K27: 1 | L27: 6786 | N27: 8913 | P27: 3935 | Q27: 3198 | R27: 1255 | S27: =SUM(K27:R27) -> 24088
C28: Due to other governments | K28: 1185 | L28: 17 | R28: 688 | S28: =SUM(K28:R28) -> 1890
C29: Due to component units | K29: 44 | P29: 172 | S29: =SUM(K29:R29) -> 216
C30: Advances from other funds | R30: 2 | S30: =SUM(K30:R30) -> 2
E32: Total liabilities: | K32: =SUM(K24:K30) -> 38628 | L32: =SUM(L24:L30) -> 11038 | M32: =SUM(M24:M29) -> 475 | N32: =SUM(N24:N30) -> 23773 | O32: =SUM(O24:O30) -> 0 | P32: =SUM(P24:P31) -> 36155 | Q32: =SUM(Q24:Q30) -> 11844 | R32: =SUM(R24:R30) -> 8949 | S32: =SUM(S24:S30) -> 130862
A34: DEFERRED INFLOWS OF RESOURCES
C35: Unavailable revenue | K35: 5001 | L35: 2529 | N35: 557 | O35: 2502 | P35: 19951 | Q35: 1131 | R35: 3095 | S35: =SUM(K35:R35) -> 34766
E37: Total deferred inflows of resources: | K37: =SUM(K35) -> 5001 | L37: =SUM(L35) -> 2529 | M37: =SUM(M35) -> 0 | N37: =SUM(N35) -> 557 | O37: =SUM(O35) -> 2502 | P37: =SUM(P35) -> 19951 | Q37: =SUM(Q35) -> 1131 | R37: =SUM(R35) -> 3095 | S37: =SUM(S35) -> 34766
B39: Fund Balances
C40: Nonspendable | M40: 542 | R40: 1094 | S40: =SUM(K40:R40) -> 1636
C41: Restricted | K41: 250 | L41: 535 | M41: 11622 | O41: 75270 | P41: 38167 | R41: 13649 | S41: =SUM(K41:R41) -> 139493
C42: Committed | K42: 2080 | P42: 99929 | R42: 33291 | S42: =SUM(K42:R42) -> 135300
C43: Assigned | K43: 38196 | R43: 308 | S43: =SUM(K43:R43) -> 38504
C44: Unassigned | K44: 35047 | L44: -8955 | N44: -14139 | Q44: -9934 | R44: -4148 | S44: =SUM(K44:R44) -> -2129
E46: Total fund balance: | K46: =SUM(K40:K45) -> 75573 | L46: =SUM(L41:L44) -> -8420 | M46: =SUM(M40:M44) -> 12164 | N46: =SUM(N41:N44) -> -14139 | O46: =SUM(O40:O44) -> 75270 | P46: =SUM(P40:P44) -> 138096 | Q46: =SUM(Q40:Q44) -> -9934 | R46: =SUM(R40:R44) -> 44194 | S46: =SUM(S39:S44) -> 312804
E48: Total liabilities,deferred inflows of resources, and fund balances: | K48: =SUM(K46+K32+K37) -> 119202 | L48: =SUM(L46+L32+L37) -> 5147 | M48: =SUM(M46+M32+M37) -> 12639 | N48: =SUM(N46+N32+N37) -> 10191 | O48: =SUM(O46+O32+O37) -> 77772 | P48: =SUM(P46+P32+P37) -> 194202 | Q48: =SUM(Q46+Q32+Q37) -> 3041 | R48: =SUM(R46+R32+R37) -> 56238 | S48: =SUM(S46+S32+S37) -> 478432

Sheet Ouachita
D1: Ouachita Combined Balance Sheet
D2: Issued: December 31, 2015
K3: Major Funds | Q3: Aggregate remaining funds
N4: Special Revenue Funds
K5: General Fund 001 | L5: Public Works Fund 102 | M5: Fire Department Fund 104 | N5: Public Library Fund 105 | O5: Correctional Center Fund 110 | P5: Urban System Fund 132 | Q5: Other Governemntal Funds | R5: Total
A6: Assets:
B7: Cash and cash equivalents | K7: 5154347 | L7: 5275474 | M7: 6680989 | N7: 2725167 | O7: 5056771 | P7: 193285 | Q7: 18694885 | R7: =SUM(K7:Q7) -> 43780918
B8: Investments | K8: 1248000 | L8: 1000000 | M8: 4000000 | N8: 2000000 | O8: 1000000 | Q8: 7000000 | R8: =SUM(K8:Q8) -> 16248000
B9: Receivables:
C10: Ad valorem taxes | K10: 2931644 | M10: 9199172 | N10: 7000422 | O10: 8621724 | Q10: 4488983 | R10: =SUM(K10:Q10) -> 32241945
C11: Sales taxes | L11: 1266766 | M11: 1268864 | R11: =SUM(K11:Q11) -> 2535630
C12: Special assessments | L12: 7050 | Q12: 178067 | R12: =SUM(K12:Q12) -> 185117
C13: Other receivables | K13: 460968 | L13: 49615 | M13: 5049 | N13: 2771 | O13: 82625 | Q13: 378518 | R13: =SUM(K13:Q13) -> 979546
B14: Due from other funds | K14: 612708 | Q14: 13902 | R14: =SUM(K14:Q14) -> 626610
B15: Due from other governments | K15: 433488 | L15: 55880 | M15: 780980 | N15: 116587 | O15: 461077 | P15: 1401159 | Q15: 2187508 | R15: =SUM(K15:Q15) -> 5436679
B16: Prepaid expenses and other assets | K16: 45 | N16: 200 | Q16: 334066 | R16: =SUM(K16:Q16) -> 334311
B17: Inventories | K17: 2341 | L17: 201168 | O17: 98634 | Q17: 266402 | R17: =SUM(K17:Q17) -> 568545
E19: Total Assets: | K19: =SUM(K7:K17) -> 10843541 | L19: =SUM(L7:L17) -> 7855953 | M19: =SUM(M7:M17) -> 21935054 | N19: =SUM(N7:N17) -> 11845147 | O19: =SUM(O7:O17) -> 15320831 | P19: =SUM(P7:P17) -> 1594444 | Q19: =SUM(Q7:Q17) -> 33542331 | R19: =SUM(R7:R17) -> 102937301
A21: LIABILITIES AND FUND EQUITY
B22: Liabilities:
C23: Accounts payable and accrued expenses | K23: 925141 | L23: 475149 | M23: 1126259 | N23: 396593 | O23: 875876 | P23: 1451613 | Q23: 1523198 | R23: =SUM(K23:Q23) -> 6773829
C24: Due to other funds | K24: 13901 | Q24: 557136 | R24: =SUM(K24:Q24) -> 571037
C25: Unearned revenues | K25: 343438 | L25: 27555 | Q25: 67631 | R25: =SUM(K25:Q25) -> 438624
C26: Deposits held | K26: 2970 | L26: 225504 | O26: 1399 | Q26: 12700 | R26: =SUM(K26:Q26) -> 242573
E28: Total liabilities: | K28: =SUM(K23:K26) -> 1285450 | L28: =SUM(L23:L26) -> 728208 | M28: =SUM(M23:M26) -> 1126259 | N28: =SUM(N23:N26) -> 396593 | O28: =SUM(O23:O26) -> 877275 | P28: =SUM(P23:P26) -> 1451613 | Q28: =SUM(Q23:Q26) -> 2160665 | R28: =SUM(R23:R26) -> 8026063
B30: Fund Equity
C31: Fund balances
C32: Non-spendable:
D33: Prepaid expenses and other assets | K33: 45 | N33: 200 | Q33: 334066 | R33: =SUM(K33:Q33) -> 334311
D34: Inventories | K34: 2341 | L34: 201168 | O34: 98634 | Q34: 266402 | R34: =SUM(K34:Q34) -> 568545
C35: Spendable:
D36: Restricted | L36: 6926577 | M36: 20808795 | N36: 11448354 | O36: 14344922 | P36: 142831 | Q36: 20323618 | R36: =SUM(K36:Q36) -> 73995097
D37: Committed | K37: 4375647 | Q37: 10457580 | R37: =SUM(K37:Q37) -> 14833227
D38: Unassigned | K38: 5180058 | R38: =SUM(K38:Q38) -> 5180058
E40: Total fund balance: | K40: =SUM(K32:K39) -> 9558091 | L40: =SUM(L33:L38) -> 7127745 | M40: =SUM(M33:M38) -> 20808795 | N40: =SUM(N33:N38) -> 11448554 | O40: =SUM(O33:O38) -> 14443556 | P40: =SUM(P33:P38) -> 142831 | Q40: =SUM(Q33:Q38) -> 31381666 | R40: =SUM(R33:R38) -> 94911238
E42: Total liabilities and fund equity: | K42: =SUM(K40,K28) -> 10843541 | L42: =SUM(L28,L40) -> 7855953 | M42: =SUM(M28,M40) -> 21935054 | N42: =SUM(N28,N40) -> 11845147 | O42: =SUM(O28,O40) -> 15320831 | P42: =SUM(P28,P40) -> 1594444 | Q42: =SUM(Q28,Q40) -> 33542331 | R42: =SUM(R28,R40) -> 102937301

Sheet Plaquemines
D1: Plaquemines Combined Balance Sheet
D2: Issued: December 31, 2015
K5: General Fund | L5: FEMA Management | M5: Series 2012 A Coastal Restorations | N5: Series 2012 B Courthouse | O5: Other Governmental Funds | P5: Total Governmental Funds
A6: Assets:
B7: Cash and cash equivalents | K7: 8952201 | M7: 42803900 | N7: 23603161 | O7: 31208628 | P7: =SUM(K7:O7) -> 106567890
B8: Investments | K8: 1497 | O8: 1606 | P8: =SUM(K8:O8) -> 3103
B9: Receivables (net of allowances for uncollectibles) | K9: 11209554 | L9: 39236353 | O9: 15048067 | P9: =SUM(K9:O9) -> 65493974
B10: Due from other funds | K10: 24266587 | N10: 4000 | O10: 167005 | P10: =SUM(K10:O10) -> 24437592
B11: Prepaid items | K11: 1199944 | P11: =SUM(K11:O11) -> 1199944
B12: Interfund loan | K12: 2073727 | P12: =SUM(K12:N12) -> 2073727
E14: Total Assets: | K14: =SUM(K7:K12) -> 47703510 | L14: =SUM(L7:L12) -> 39236353 | M14: =SUM(M7:M12) -> 42803900 | N14: =SUM(N7:N12) -> 23607161 | O14: =SUM(O7:O12) -> 46425306 | P14: =SUM(P7:P12) -> 199776230
A16: LIABILITIES AND FUND BALANCES
B17: Liabilities:
C18: Accounts, salaries and other payables | K18: 3541344 | L18: 3326407 | M18: 150791 | N18: 317429 | O18: 6265711 | P18: =SUM(K18:O18) -> 13601682
C19: Compensated absences payable | K19: 695854 | O19: 389838 | P19: =SUM(K19:O19) -> 1085692
C20: Unearned revenues | L20: 11382905 | P20: =SUM(K20:O20) -> 11382905
C21: Deposits due others | K21: 35075 | O21: 255 | P21: =SUM(K21:O21) -> 35330
C22: Due to other funds | K22: 106828 | L22: 20566129 | M22: 25872 | N22: 4000 | O22: 3734763 | P22: =SUM(K22:O22) -> 24437592
C23: Other | K23: 581953 | O23: 381686 | P23: =SUM(K23:O23) -> 963639
E25: Total liabilities: | K25: =SUM(K18:K23) -> 4961054 | L25: =SUM(L18:L23) -> 35275441 | M25: =SUM(M18:M24) -> 176663 | N25: =SUM(N18:N23) -> 321429 | O25: =SUM(O18:O23) -> 10772253 | P25: =SUM(P18:P23) -> 51506840
A27: DEFERRED INFLOWS OF RESROUCES
C28: Deferred revenues | K28: 3806309 | O28: 14702469 | P28: =SUM(K28:O28) -> 18508778
B30: Fund Balances
C31: Non Spendable | K31: 3270464 | P31: =SUM(K31:O31) -> 3270464
C32: Restricted | K32: 2161809 | L32: 3960912 | M32: 42627237 | N32: 23285732 | O32: 27860563 | P32: =SUM(K32:O32) -> 99896253
C33: Committed | K33: 28403308 | P33: =SUM(K33:O33) -> 28403308
C34: Assigned | K34: 919993 | O34: 3075 | P34: =SUM(K34:O34) -> 923068
C35: Unassigned (Deficit) | K35: 4180573 | O35: -6913054 | P35: =SUM(K35:O35) -> -2732481
E37: Total fund balance: | K37: =SUM(K31:K35) -> 38936147 | L37: =SUM(L31:L35) -> 3960912 | M37: =SUM(M31:M35) -> 42627237 | N37: =SUM(N31:N35) -> 23285732 | O37: =SUM(O31:O35) -> 20950584 | P37: =SUM(P31:P35) -> 129760612
E39: Total liabilities and fund balances: | K39: =SUM(K37,K25,K28) -> 47703510 | L39: =SUM(L37,L25,L28) -> 39236353 | M39: =SUM(M37,M25,M28) -> 42803900 | N39: =SUM(N37,N25,N28) -> 23607161 | O39: =SUM(O37,O25,O28) -> 46425306 | P39: =SUM(P37,P25,P28) -> 199776230

Sheet Pointe Couppe 
D1: Pointe Coupee Combined Balance Sheet
D2: Issued: December 31, 2015
K4: General | L4: Parishwide drainage | M4: Roads and Bridges | N4: Pointe Coupee Library | O4: Detention Center | P4: Road Construction | Q4: Debt Service Road Improvement | R4: Other Governmental Funds | S4: Total Governmental Funds
A5: Assets:
B6: Cash and cash equivalents | K6: 14821 | L6: 94268 | M6: 2800 | N6: 2492877 | O6: 1871 | P6: 554475 | Q6: 61260 | R6: 94108 | S6: =SUM(K6:R6) -> 3316480
B7: Investments | N7: 141853 | S7: =SUM(K7:R7) -> 141853
B8: Accounts receivable, net | K8: 1459366 | L8: 98323 | N8: 1657405 | O8: 20169 | Q8: 168074 | R8: 63868 | S8: =SUM(K8:R8) -> 3467205
B9: Due from other governments | K9: 343340 | L9: 213305 | M9: 24079 | Q9: 1411 | R9: 15488 | S9: =SUM(K9:R9) -> 597623
B10: Due from other funds | K10: 1908524 | P10: 891000 | Q10: 1700000 | R10: 290000 | S10: =SUM(K10:R10) -> 4789524
B11: Prepaid items | K11: 110525 | S11: =SUM(K11:R11) -> 110525
B12: Other assets | K12: 14213 | L12: 709 | R12: 615 | S12: =SUM(K12:R12) -> 15537
E14: Total Assets: | K14: =SUM(K6:K12) -> 3850789 | L14: =SUM(L6:L12) -> 406605 | M14: =SUM(M6:M12) -> 26879 | N14: =SUM(N6:N12) -> 4292135 | O14: =SUM(O6:O12) -> 22040 | P14: =SUM(P6:P12) -> 1445475 | Q14: =SUM(Q6:Q12) -> 1930745 | R14: =SUM(R6:R12) -> 464079 | S14: =SUM(S6:S12) -> 12438747
A16: LIABILITIES, DEFERRED INFLOWS OF RESOURCES AND FUND BALANCES
B17: Liabilities:
C18: Accounts payable and accrued expenses | K18: 344002 | L18: 248692 | M18: 18101 | N18: 140389 | O18: 17031 | P18: 950383 | R18: 31612 | S18: =SUM(K18:R18) -> 1750210
C19: Due to other governments | K19: 519937 | S19: =SUM(K19:R19) -> 519937
C20: Due to other funds | K20: 2881000 | L20: 142000 | M20: 5000 | O20: 781000 | R20: 36000 | S20: =SUM(K20:R20) -> 3845000
E22: Total liabilities: | K22: =SUM(K18:K20) -> 3744939 | L22: =SUM(L18:L20) -> 390692 | M22: =SUM(M18:M20) -> 23101 | N22: =SUM(N18:N21) -> 140389 | O22: =SUM(O18:O20) -> 798031 | P22: =SUM(P18:P20) -> 950383 | Q22: =SUM(Q18:Q20) -> 0 | R22: =SUM(R18:R20) -> 67612 | S22: =SUM(S18:S20) -> 6115147
A24: DEFERRED INFLOWS OF RESROUCES
C25: Unavailable revenues | K25: 22863 | S25: =SUM(K25:R25) -> 22863
B27: Fund Balances
C28: Nonspendable | K28: 110525 | S28: =SUM(K28:R28) -> 110525
C29: Restricted | N29: 4151746 | P29: 495092 | Q29: 1930745 | S29: =SUM(K29:R29) -> 6577583
C30: Committed | L30: 15913 | M30: 3778 | R30: 396467 | S30: =SUM(K30:R30) -> 416158
C31: Assigned
C32: Unassigned | K32: -27538 | O32: -775991 | S32: =SUM(K32:R32) -> -803529
E34: Total fund balance: | K34: =SUM(K28:K33) -> 82987 | L34: =SUM(L28:L33) -> 15913 | M34: =SUM(M28:M33) -> 3778 | N34: =SUM(N28:N33) -> 4151746 | O34: =SUM(O28:O33) -> -775991 | P34: =SUM(P28:P33) -> 495092 | Q34: =SUM(Q28:Q33) -> 1930745 | R34: =SUM(R28:R33) -> 396467 | S34: =SUM(S28:S33) -> 6300737
E36: Total liabilities and fund balances: | K36: =SUM(K34,K22,K25) -> 3850789 | L36: =SUM(L34,L22,L25) -> 406605 | M36: =SUM(M34,M22,M25) -> 26879 | N36: =SUM(N34,N22,N25) -> 4292135 | O36: =SUM(O34,O22,O25) -> 22040 | P36: =SUM(P34,P22,P25) -> 1445475 | Q36: =SUM(Q34,Q22,Q25) -> 1930745 | R36: =SUM(R34,R22,R25) -> 464079 | S36: =SUM(S34,S22,S25) -> 12438747

Sheet Rapides
D1: Rapides Combined Balance Sheet
D2: Issued: December 31, 2015
K5: General Fund | L5: Road and Bridge Fund | M5: Fire Protection District No. 2 Fund | N5: Other Governmental Funds | O5: 2015 Total Governmental Funds | P5: 2014 Total Governmental Funds
A6: Assets:
B7: Cash and cash equivalents | K7: 1909591 | L7: 1560163 | M7: 4361195 | N7: 35216501 | O7: 43047450 | P7: 51085465
B8: Receivables | K8: 2609074 | L8: 386242 | M8: 4751553 | N8: 14992118 | O8: =SUM(K8:N8) -> 22738987 | P8: 22832720
B9: Interfund receivables | K9: 312290 | N9: 3529 | O9: =SUM(K9:N9) -> 315819 | P9: 128739
B10: Other | O10: =SUM(K10:N10) -> 0 | P10: 516
E12: Total Assets: | K12: =SUM(K7:K10) -> 4830955 | L12: =SUM(L7:L9) -> 1946405 | M12: =SUM(M7:M9) -> 9112748 | N12: =SUM(N7:N10) -> 50212148 | O12: =SUM(O7:O9) -> 66102256 | P12: =SUM(P7:P10) -> 74047440
A14: LIABILITIES AND FUND BALANCES
B15: Liabilities:
C16: Accounts payable | K16: 91830 | L16: 60900 | M16: 29787 | N16: 483563 | O16: =SUM(K16:N16) -> 666080 | P16: 916265
C17: Interfund payables | K17: 208472 | N17: 107346 | O17: =SUM(K17:N17) -> 315818 | P17: 128740
C18: Deferred revenues | N18: 715461 | O18: =SUM(K18:N18) -> 715461 | P18: 632212
E20: Total liabilities: | K20: =SUM(K16:K18) -> 300302 | L20: =SUM(L16:L18) -> 60900 | M20: =SUM(M16:M18) -> 29787 | N20: =SUM(N16:N18) -> 1306370 | O20: =SUM(O16:O18) -> 1697359 | P20: =SUM(P16:P18) -> 1677217
B22: Fund Balances
C23: Reserved for:
D24: Judicial | N24: 228410 | O24: =SUM(K24:N24) -> 228410 | P24: 178151
D25: Other general government | N25: 78449 | O25: =SUM(K25:N25) -> 78449 | P25: 179091
D26: Public safety | K26: 216077 | M26: 9082961 | N26: 12757016 | O26: =SUM(K26:N26) -> 22056054 | P26: 21061886
D27: Public works | L27: 1885505 | N27: 16319049 | O27: 18204553 | P27: 17126733
D28: Health and welfare | N28: 3891517 | O28: =SUM(K28:N28) -> 3891517 | P28: 4102147
D29: Culture and recreation | N29: 12104730 | O29: =SUM(K29:N29) -> 12104730 | P29: 21484034
D30: Debt service | N30: 3526607 | O30: =SUM(K30:N30) -> 3526607 | P30: 3296487
D31: Employee benefits | K31: 1094516 | O31: =SUM(K31:N31) -> 1094516 | P31: 1266984
C32: Unassigned | K32: 3220060 | O32: =SUM(K32:N32) -> 3220060 | P32: 3674712
E34: Total fund balance: | K34: =SUM(K23:K32) -> 4530653 | L34: =SUM(L23:L32) -> 1885505 | M34: =SUM(M23:M32) -> 9082961 | N34: =SUM(N23:N32) -> 48905778 | O34: =SUM(O23:O32) -> 64404896 | P34: =SUM(P23:P33) -> 72370225
E36: Total liabilities and fund balances: | K36: =SUM(K34,K20) -> 4830955 | L36: =SUM(L20,L34) -> 1946405 | M36: =SUM(M20,M34) -> 9112748 | N36: =SUM(N20,N34) -> 50212148 | O36: =SUM(O20,O34) -> 66102255 | P36: =SUM(P20+P34) -> 74047442

Sheet Red River
D1: Red River Combined Balance Sheet
D2: Issued: December 31, 2015
K4: General Fund | L4: Sales Tax Fund | M4: Ambulance Service Fund | N4: Library Fund | O4: Unit 1 Road Fund | P4: Public Facilities Maintenance Fund | Q4: Other non-major Governmental Funda | R4: Total
A5: Assets:
B6: Cash | K6: 4544578 | L6: 3784134 | M6: 1488364 | N6: 2742348 | O6: 1201866 | P6: 1596157 | Q6: 2353954 | R6: =SUM(K6:Q6) -> 17711401
B7: Investments | K7: 2497396 | L7: 5540008 | M7: 6755315 | N7: 650878 | Q7: 240629 | R7: =SUM(K7:Q7) -> 15684226
B8: Receivables | K8: 923493 | L8: 259477 | M8: 185685 | N8: 1641190 | O8: 10908 | P8: 706737 | Q8: 958053 | R8: =SUM(K8:Q8) -> 4685543
B9: Due from other funds | K9: 3221 | R9: =SUM(K9:Q9) -> 3221
B10: Prepaid expenses | K10: 11785 | M10: 5326 | P10: 3128 | R10: =SUM(K10:P10) -> 20239
E12: Total Assets: | K12: =SUM(K6:K10) -> 7980473 | L12: =SUM(L6:L10) -> 9583619 | M12: =SUM(M6:M10) -> 8434690 | N12: =SUM(N6:N10) -> 5034416 | O12: =SUM(O6:O10) -> 1212774 | P12: =SUM(P6:P10) -> 2306022 | Q12: =SUM(Q6:Q10) -> 3552636 | R12: =SUM(R6:R10) -> 38104630
A14: DEFERRED OUTLFLOWS OF RESOURCES
E16: Total Assets and deferred outflows | K16: =SUM(K12) -> 7980473 | L16: =SUM(L12) -> 9583619 | M16: =SUM(M12) -> 8434690 | N16: =SUM(N12) -> 5034416 | O16: =SUM(O12) -> 1212774 | P16: =SUM(P12) -> 2306022 | Q16: =SUM(Q12) -> 3552636 | R16: =SUM(R12) -> 38104630
A19: LIABILITIES
C20: Accounts payable and accrued expenses | K20: 167431 | M20: 24519 | N20: 66781 | O20: 360933 | P20: 123477 | Q20: 38910 | R20: =SUM(K20:Q20) -> 782051
C21: Due to other funds | Q21: 3221 | R21: =SUM(K21:Q21) -> 3221
E23: Total liabilities: | K23: =SUM(K21:K21) -> 0 | L23: =SUM(L21:L21) -> 0 | M23: =SUM(M21:M21) -> 0 | N23: =SUM(N21:N21) -> 0 | O23: =SUM(O21:O21) -> 0 | P23: =SUM(P21:P21) -> 0 | Q23: =SUM(Q21:Q21) -> 3221 | R23: =SUM(R20:R21) -> 785272
A25: DEFERRED INFLOWS OF RESOURCES | K25: 45666 | N25: 93482 | P25: 40143 | Q25: 26669 | R25: =SUM(K25:Q25) -> 205960
B27: Fund Balances
C28: Nonspendable:
D29: Prepaid expenses | K29: 11785 | M29: 5326 | P29: 3128 | R29: =SUM(K29:P29) -> 20239
C30: Spendable:
C31: Restricted:
D32: Dedicated property taxes | N32: 4874153 | Q32: 2292400 | R32: =SUM(K32:Q32) -> 7166553
D33: Dedicated sales taxes | M33: 5744400 | R33: =SUM(K33:Q33) -> 5744400
D34: Court fees for juror and witness compensation | Q34: 200499 | R34: =SUM(K34:Q34) -> 200499
D35: Federal and state grant programs | Q35: 455932 | R35: =SUM(K35:Q35) -> 455932
C36: Committed:
D37: Criminal court costs | Q37: 95314 | R37: =SUM(K37:Q37) -> 95314
D38: Ambulance services | M38: 2660445 | R38: =SUM(K38:Q38) -> 2660445
D39: Road maintenance and improvements | O39: 851841 | Q39: 336634 | R39: =SUM(K39:Q39) -> 1188475
D40: Public facilities maintenance | P40: 2139274 | R40: =SUM(K40:Q40) -> 2139274
D41: Buildings and infrastructure | L41: 9583619 | R41: =SUM(K41:Q41) -> 9583619
D42: Tourism | Q42: 103057 | R42: =SUM(K42:Q42) -> 103057
C43: Unassigned | K43: 7755591 | R43: =SUM(K43:Q43) -> 7755591
E45: Total fund balance: | K45: =SUM(K29:K44) -> 7767376 | L45: =SUM(L29:L43) -> 9583619 | M45: =SUM(M29:M43) -> 8410171 | N45: =SUM(N29:N43) -> 4874153 | O45: =SUM(O29:O43) -> 851841 | P45: =SUM(P29:P43) -> 2142402 | Q45: =SUM(Q29:Q43) -> 3483836 | R45: =SUM(R29:R43) -> 37113398
E47: Total liabilities, deferred inflows, and fund balances: | K47: =K45+K25+K23 -> 7813042 | L47: =L45+L25+L23 -> 9583619 | M47: =M45+M25+M23 -> 8410171 | N47: =N45+N25+N23 -> 4967635 | O47: =O45+O25+O23 -> 851841 | P47: =P45+P25+P23 -> 2182545 | Q47: =Q45+Q25+Q23 -> 3513726 | R47: =R45+R25+R23 -> 38104630

Sheet Richland
D1: Richland Combined Balance Sheet
D2: Issued: December 31, 2015
K5: General | L5: Capital Projects | M5: Road Maintenance | N5: Drainage Maintenance | O5: Library | P5: Other Governmental Funds | Q5: Total Governmental Funds
A6: ASSETS
B7: Cash | K7: 1890719 | M7: 675597 | N7: 1298649 | O7: 3595569 | P7: 706100 | Q7: =SUM(K7:P7) -> 8166634
B8: Receivables | K8: 1175915 | L8: 6578 | M8: 21885 | O8: 1354736 | P8: 239210 | Q8: =SUM(K8:P8) -> 2798324
E10: Total Assets: | K10: =SUM(K7:K8) -> 3066634 | L10: =SUM(L7:L8) -> 6578 | M10: =SUM(M7:M8) -> 697482 | N10: =SUM(N7:N8) -> 1298649 | O10: =SUM(O7:O8) -> 4950305 | P10: =SUM(P7:P8) -> 945310 | Q10: =SUM(Q7:Q8) -> 10964958
A12: LIABILITIES
C13: Accounts payable | K13: 30184 | L13: 6578 | M13: 155276 | N13: 16845 | O13: 17914 | P13: 23586 | Q13: =SUM(K13:P13) -> 250383
C14: Payroll accruals and withholdings | K14: 61306 | Q14: =SUM(K14:P14) -> 61306
E16: Total liabilities: | K16: =SUM(K13:K14) -> 91490 | L16: =SUM(L13:L14) -> 6578 | M16: =SUM(M13:M14) -> 155276 | N16: =SUM(N13:N15) -> 16845 | O16: =SUM(O13:O14) -> 17914 | P16: =SUM(P13:P14) -> 23586 | Q16: =SUM(Q13:Q14) -> 311689
A18: DEFERRED INFLOWS OF RESROUCES
C19: Property taxes | K19: 1108210 | O19: 1354736 | P19: 237638 | Q19: =SUM(K19:P19) -> 2700584
B21: Fund Balance
C22: Restricted for special revenue | M22: 542206 | N22: 1281804 | O22: 3577655 | P22: 684086 | Q22: =SUM(K22:P22) -> 6085751
C23: Unassigned (deficit) | K23: 1866934 | Q23: =SUM(K23:P23) -> 1866934
E25: Total fund balances: | K25: =SUM(K22:K24) -> 1866934 | L25: =SUM(L22:L23) -> 0 | M25: =SUM(M22:M23) -> 542206 | N25: =SUM(N22:N23) -> 1281804 | O25: =SUM(O22:O23) -> 3577655 | P25: =SUM(P22:P23) -> 684086 | Q25: =SUM(Q22:Q23) -> 7952685
E27: Total liabilities, deferred inflows of resources, and fund balances: | K27: =SUM(K25,K16,K19) -> 3066634 | L27: =SUM(L25,L16,L19) -> 6578 | M27: =SUM(M25,M16,M19) -> 697482 | N27: =SUM(N25,N16,N19) -> 1298649 | O27: =SUM(O25,O16,O19) -> 4950305 | P27: =SUM(P25,P16,P19) -> 945310 | Q27: =SUM(Q25,Q16,Q19) -> 10964958

Sheet Sabine
D1: Sabine Combined Balance Sheet
D2: Issued: December 31, 2015
S4: Total
K5: General Fund | L5: Transportation Fund | M5: Sales Tax Fund | N5: Criminal Court Fund | O5: Road District Fund No.17 | P5: Road District Fund No.18 | Q5: Health Unit Fund | R5: Other Governmental Funds | S5: 2015 | T5: 2014
A6: Assets:
B7: Cash and cash equivalents | K7: 5759098 | L7: 597391 | M7: 544129 | O7: 42280 | P7: 84196 | Q7: 1811737 | R7: 1427255 | S7: =SUM(K7:R7) -> 10266086 | T7: 9360736
B8: Receivables | K8: 1047889 | L8: 26158 | M8: 21685 | N8: 11211 | O8: 327848 | P8: 152680 | Q8: 175491 | R8: 1883838 | S8: =SUM(K8:R8) -> 3646800 | T8: 3889321
B9: Interfund receivable | K9: 81433 | S9: =SUM(K9:R9) -> 81433 | T9: 53535
E11: Total Assets: | K11: =SUM(K7:K9) -> 6888420 | L11: =SUM(L7:L9) -> 623549 | M11: =SUM(M7:M9) -> 565814 | N11: =SUM(N7:N9) -> 11211 | O11: =SUM(O7:O9) -> 370128 | P11: =SUM(P7:P9) -> 236876 | Q11: =SUM(Q7:Q9) -> 1987228 | R11: =SUM(R7:R9) -> 3311093 | ... T11: =SUM(T7:T9) -> 13303592
A13: Liabilities
C14: Accounts, salaries, and other payables | K14: 60994 | L14: 12260 | M14: 41336 | N14: 28614 | O14: 22729 | P14: 13435 | Q14: 6572 | R14: 203130 | S14: =SUM(K14:R14) -> 389070 | T14: 477050
C15: Interfund payables | N15: 31302 | R15: 50131 | S15: =SUM(K15:R15) -> 81433 | T15: 53535
E17: Total liabilities: | K17: =SUM(K14:K15) -> 60994 | L17: =SUM(L14:L15) -> 12260 | M17: =SUM(M14:M15) -> 41336 | N17: =SUM(N14:N15) -> 59916 | O17: =SUM(O14:O15) -> 22729 | P17: =SUM(P14:P15) -> 13435 | Q17: =SUM(Q14:Q15) -> 6572 | R17: =SUM(R14:R15) -> 253261 | ... T17: =SUM(T14:T15) -> 530585
A19: Fund Balances
C20: Restricted for maintenance and operation | L20: 611289 | M20: 524478 | N20: -48704 | O20: 347398 | P20: 223442 | Q20: 1980656 | R20: 3107538 | S20: =SUM(K20:R20) -> 6746097 | T20: 7002730
C21: Unassigned | K21: 6827425 | R21: -49706 | S21: =SUM(K21:R21) -> 6777719 | T21: 5770277
E23: Total fund balances: | K23: =SUM(K20:K21) -> 6827425 | L23: =SUM(L20:L21) -> 611289 | M23: =SUM(M20:M21) -> 524478 | N23: =SUM(N20:N21) -> -48704 | O23: =SUM(O20:O21) -> 347398 | P23: =SUM(P20:P21) -> 223442 | Q23: =SUM(Q20:Q21) -> 1980656 | R23: =SUM(R20:R21) -> 3057832 | S23: =SUM(S20:S22) -> 13523816 | T23: =SUM(T20:T22) -> 12773007
E25: Total liabilities and fund balances | K25: =SUM(K17+K23) -> 6888419 | L25: =SUM(L17+L23) -> 623549 | M25: =SUM(M17+M23) -> 565814 | N25: =SUM(N17+N23) -> 11212 | O25: =SUM(O17+O23) -> 370127 | P25: =SUM(P17+P23) -> 236877 | Q25: =SUM(Q17+Q23) -> 1987228 | R25: =SUM(R17+R23) -> 3311093 | ... T25: =SUM(T17+T23) -> 13303592

Sheet St. Bernard
D1: St. Bernard Combined Balance Sheet
D2: Issued: December 31, 2015
M4: Special Revenue Funds
K5: General Fund | L5: Hazard Mitigation Grant Program | M5: Disaster Recovery Fund | N5: Consolidated Fire Protection District No. 1-2 | O5: Non-Major Governmental Funds | P5: Total
A6: Assets:
B7: Cash and cash equivalents | K7: 9448931 | L7: 5866225 | M7: 4920930 | N7: 626745 | O7: 14733094 | P7: =SUM(K7:O7) -> 35595925
B8: Investments - land held for sale | K8: 3650500 | P8: =SUM(K8:O8) -> 3650500
B9: Receivables: | P9: =SUM(K9:O9) -> 0
C10: Sales and use taxes | K10: 1632582 | O10: 545374 | P10: =SUM(K10:O10) -> 2177956
C11: Property taxes | K11: 853113 | N11: 8527076 | O11: 3425920 | P11: =SUM(K11:O11) -> 12806109
C12: Cable franchise fees | K12: 123670 | P12: =SUM(K12:O12) -> 123670
C13: Intergovernmental | K13: 2911489 | L13: 3814259 | M13: 14987892 | N13: 8798 | O13: 3424000 | P13: =SUM(K13:O13) -> 25146438
C14: Other | K14: 355611 | N14: 800 | O14: 433295 | P14: =SUM(K14:O14) -> 789706
B15: Due from other funds | K15: 6068350 | L15: 475000 | M15: 12450962 | O15: 3123788 | P15: =SUM(K15:O15) -> 22118100 | Q15: Number wrong on file
B16: Prepaid | K16: 109215 | N16: 21887 | O16: 112122 | P16: =SUM(K16:O16) -> 243224
E18: Total Assets: | K18: =SUM(K7:K16) -> 25153461 | L18: =SUM(L7:L16) -> 10155484 | M18: =SUM(M7:M16) -> 32359784 | N18: =SUM(N7:N16) -> 9185306 | O18: =SUM(O7:O16) -> 25797593 | P18: =SUM(P7:P16) -> 102651628
A20: LIABILITIES AND FUND BALANCES
C21: Accounts payable | K21: 3612256 | L21: 1226983 | M21: 8290609 | N21: 325543 | O21: 4007538 | P21: =SUM(K21:O21) -> 17462929
C22: Retainage payable | K22: 21091 | M22: 1910685 | O22: 502682 | P22: =SUM(K22:O22) -> 2434458
C23: Salaries and payroll deductions payable | K23: 287740 | L23: 10618 | N23: 539220 | O23: 229888 | P23: =SUM(K23:O23) -> 1067466
C24: Due to other funds | K24: 6346958 | L24: 662370 | M24: 12721220 | N24: 3354755 | O24: 4573910 | P24: =SUM(K24:O24) -> 27659213
C25: Advance collections | K25: 69188 | P25: =SUM(K25:O25) -> 69188
C26: Short-term certificates of indebtedness | K26: 771048 | N26: 1444614 | P26: =SUM(K26:O26) -> 2215662
E28: Total liabilities: | K28: =SUM(K21:K26) -> 11108281 | L28: =SUM(L21:L26) -> 1899971 | M28: =SUM(M21:M26) -> 22922514 | N28: =SUM(N21:N26) -> 5664132 | O28: =SUM(O21:O26) -> 9314018 | P28: =SUM(P21:P26) -> 50908916
A30: Deferred inflows of resources
B31: Unavailable revenues | K31: 3788526 | L31: 8255513 | M31: 11400045 | N31: 108518 | O31: 2822941 | P31: =SUM(K31:O31) -> 26375543
E32: Total deferred inflows of resources | P32: =SUM(P31) -> 26375543
B34: Fund Balances
C35: Nonspendable
D36: Prepaid items | K36: 109215 | N36: 21887 | O36: 112122 | P36: =SUM(K36:O36) -> 243224
C37: Restricted
D38: Mortgage refunding | K38: 91185 | P38: =SUM(K38:O38) -> 91185
D39: Debt service | O39: 3561965 | P39: =SUM(K39:O39) -> 3561965
D40: Federal programs | K40: 3658868 | O40: 2156863 | P40: =SUM(K40:O40) -> 5815731
D41: Council on aging | O41: 332098 | P41: =SUM(K41:O41) -> 332098
D42: Road lighting | O42: 124127 | P42: =SUM(K42:O42) -> 124127
D43: Health | O43: 818972 | P43: =SUM(K43:O43) -> 818972
D44: Communication | O44: 558059 | P44: =SUM(K44:O44) -> 558059
D45: Garbage | O45: 262616 | P45: =SUM(K45:O45) -> 262616
D46: Court operations | O46: 15819 | P46: =SUM(K46:O46) -> 15819
D47: Public safety | N47: 3099269 | P47: =SUM(K47:O47) -> 3099269
D48: Capital outlay | O48: 313966 | P48: =SUM(K48:O48) -> 313966
D49: BP oil spill | K49: 242815 | P49: =SUM(K49:O49) -> 242815
C50: Commited
D51: Capital outlay | O51: 956564 | P51: =SUM(K51:O51) -> 956564
C52: Assigned
D53: Coastal Restoration | K53: 5421492 | P53: =SUM(K53:O53) -> 5421492
D54: Capital outlay | N54: 291500 | O54: 294025 | P54: =SUM(K54:O54) -> 585525
D55: Recovery | O55: 5778189 | P55: =SUM(K55:O55) -> 5778189
C56: Unassigned | K56: 733079 | M56: -1962775 | O56: -1584751 | P56: =SUM(K56:O56) -> -2814447
E58: Total fund balance: | K58: =SUM(K36:K56) -> 10256654 | L58: =SUM(L37:L56) -> 0 | M58: =SUM(M37:M56) -> -1962775 | N58: =SUM(N36:N56) -> 3412656 | O58: =SUM(O36:O56) -> 13700634 | P58: =SUM(P36:P57) -> 25407169
E60: Total liabilities, deferred inflows and fund balances: | K60: =SUM(K58,K28,K31) -> 25153461 | L60: =SUM(L58,L28,L31) -> 10155484 | M60: =SUM(M58,M28,M31) -> 32359784 | N60: =SUM(N58,N28,N31) -> 9185306 | O60: =SUM(O58,O28,O31) -> 25837593 | P60: =SUM(P58,P28,P31) -> 102691628

Sheet St. Charles
D1: St. Charles Combined Balance Sheet
D2: Issued: December 31, 2015
K5: General Fund | L5: Road & Drainage Maintenance & Operation | M5: Flood Protection | N5: Sewer General Obligation Sinking | O5: Nonmajor Governmental Funds | P5: Total Governmental Funds
A6: Assets:
B7: Cash and Cash equivalents | K7: 1124023 | L7: 515257 | N7: 320 | O7: 27032 | P7: =SUM(K7:O7) -> 1666632
B8: Investments | K8: 36694669 | L8: 30870991 | N8: 4057276 | O8: 9146417 | P8: =SUM(K8:O8) -> 80769353
B9: Receivables, net
C10: Ad valorem taxes | K10: 3862375 | L10: 7237380 | M10: 4873650 | N10: 2680515 | O10: 7417140 | P10: =SUM(K10:O10) -> 26071060
C11: Sales taxes | K11: 1338062 | L11: 1529211 | P11: =SUM(K11:O11) -> 2867273
C12: Accounts | K12: 427 | P12: =SUM(K12:O12) -> 427
C13: Other | K13: 405486 | L13: 80287 | O13: 35357 | P13: =SUM(K13:O13) -> 521130
B14: Due from other funds | K14: 6925 | L14: 50636 | M14: 3569261 | O14: 1951716 | P14: =SUM(K14:O14) -> 5578538
B15: Due from other governments | K15: 868931 | L15: 2906022 | O15: 1668340 | P15: =SUM(K15:O15) -> 5443293
B16: Prepaid fees | K16: 449093 | L16: 1200 | O16: 24654 | P16: =SUM(K16:O16) -> 474947
B17: Other assets | K17: 2095 | L17: 1125 | O17: 1050 | P17: =SUM(K17:O17) -> 4270
E19: Total Assets: | K19: =SUM(K7:K17) -> 44752086 | L19: =SUM(L7:L17) -> 43192109 | M19: =SUM(M7:M17) -> 8442911 | N19: =SUM(N7:N17) -> 6738111 | O19: =SUM(O7:O17) -> 20271706 | P19: =SUM(P7:P17) -> 123396923
A21: LIABILITIES AND FUND BALANCES
B22: Liabilities:
D23: Accounts payable | K23: 2260493 | L23: 1967067 | O23: 1203528 | P23: =SUM(K23:O23) -> 5431088
D24: Contracts payable | L24: 267309 | O24: 55919 | P24: =SUM(K24:O24) -> 323228
D25: Due to other funds | K25: 1920861 | L25: 30814 | O25: 3626863 | P25: =SUM(K25:O25) -> 5578538
D26: Due to component units | O26: 3829 | P26: =SUM(K26:O26) -> 3829
D27: Due to other governments | K27: 105297 | L27: 109925 | O27: 269729 | P27: =SUM(K27:O27) -> 484951
D28: Other liabilities | K28: 693821 | L28: 313694 | O28: 136675 | P28: =SUM(K28:O28) -> 1144190
E30: Total liabilities: | K30: =SUM(K23:K28) -> 4980472 | L30: =SUM(L23:L28) -> 2688809 | M30: =SUM(M23:M28) -> 0 | N30: =SUM(N23:N28) -> 0 | O30: =SUM(O23:O28) -> 5296543 | P30: =SUM(P23:P28) -> 12965824
A32: DEFERRED INFLOWS OF RESOURCES
D33: Advances | K33: 4018537 | L33: 7282527 | M33: 4873650 | N33: 2680515 | O33: 7421978 | P33: =SUM(K33:O33) -> 26277207
D34: Unavailable revenues | L34: 1524067 | P34: =SUM(K34:O34) -> 1524067
E36: Total deferred inflows of resources: | K36: =SUM(K33:K34) -> 4018537 | L36: =SUM(L33:L34) -> 8806594 | M36: =SUM(M33:M34) -> 4873650 | N36: =SUM(N33:N34) -> 2680515 | O36: =SUM(O33:O34) -> 7421978 | P36: =SUM(P33:P34) -> 27801274
B38: Fund Balances
C39: Nonspendable | K39: 449093 | L39: 1200 | O39: 24654 | P39: =SUM(K39:O39) -> 474947
C40: Restricted | K40: 718977 | L40: 28679452 | M40: 3569261 | N40: 4057596 | O40: 5317012 | P40: =SUM(K40:O40) -> 42342298
C41: Commited | K41: 12381828 | L41: 3016054 | O41: 2191497 | P41: =SUM(K41:O41) -> 17589379
C42: Assigned | K42: 27758632 | O42: 22377 | P42: =SUM(K42:O42) -> 27781009
C43: Unassigned | K43: -2555453 | O43: -2355 | P43: =SUM(K43:O43) -> -2557808
E45: Total fund balances: | K45: =SUM(K39:K43) -> 38753077 | L45: =SUM(L39:L43) -> 31696706 | M45: =SUM(M39:M43) -> 3569261 | N45: =SUM(N39:N43) -> 4057596 | O45: =SUM(O39:O43) -> 7553185 | P45: =SUM(P39:P43) -> 85629825
E47: Total liabilities and fund balances: | K47: =SUM(K45,K30,K36) -> 47752086 | L47: =SUM(L45,L30,L36) -> 43192109 | M47: =SUM(M45,M30,M36) -> 8442911 | N47: =SUM(N45,N30,N36) -> 6738111 | O47: =SUM(O45,O30,O36) -> 20271706 | P47: =SUM(P45,P30,P36) -> 126396923

Sheet St. Helena
D1: St. Helena Combined Balance Sheet
D2: Issued: December 31, 2015
L4: Major Funds | Q4: Nonmajor Funds
K5: General Fund | L5: Road Building & Maintenance Fund | M5: Solid Waste Fund | N5: Sales Tax Fund | O5: LGAP Grants fund | P5: Courthouse Project Fund | Q5: Other Governmental Funds | R5: Total Governmental Funds
A6: Assets:
B7: Cash and equivalents | K7: 118204 | L7: 2417350 | M7: 52288 | N7: 901302 | Q7: 2642325 | R7: =SUM(K7:Q7) -> 6131469
B8: Investments | Q8: 154282 | R8: =SUM(K8:Q8) -> 154282
B9: Receivables, net | K9: 397130 | L9: 575401 | M9: 54258 | N9: 54258 | O9: 8444 | P9: 48831 | Q9: 1372129 | R9: =SUM(K9:Q9) -> 2510451
B10: Due from other funds | K10: 79351 | R10: =SUM(K10:Q10) -> 79351
B11: Restricted cash | O11: 1 | P11: 1 | Q11: 393910 | R11: =SUM(K11:Q11) -> 393912
E13: Total assets: | K13: =SUM(K7:K12) -> 594685 | L13: =SUM(L7:L12) -> 2992751 | M13: =SUM(M7:M12) -> 106546 | N13: =SUM(N7:N12) -> 955560 | O13: =SUM(O7:O12) -> 8445 | P13: =SUM(P7:P12) -> 48832 | Q13: =SUM(Q7:Q12) -> 4562646 | R13: =SUM(R7:R11) -> 9269465
A15: LIABILITIES AND FUND BALANCES
B16: Liabilities:
C17: Accounts payable | K17: 73272 | L17: 201844 | M17: 255 | O17: 55550 | P17: 49471 | Q17: 67318 | R17: =SUM(K17:Q17) -> 447710
C18: Other accrued liabilities | K18: 3944 | L18: 16783 | Q18: 42606 | R18: =SUM(K18:Q18) -> 63333
C19: Due to other funds | O19: 17536 | P19: 33422 | Q19: 28393 | R19: =SUM(K19:Q19) -> 79351
E21: Total liabilities: | K21: =SUM(K17:K19) -> 77216 | L21: =SUM(L17:L19) -> 218627 | M21: =SUM(M17:M19) -> 255 | N21: =SUM(N17:N19) -> 0 | O21: =SUM(O17:O19) -> 73086 | P21: =SUM(P17:P19) -> 82893 | Q21: =SUM(Q17:Q19) -> 138317 | R21: =SUM(R17:R19) -> 590394
B23: Fund Balances
C24: Restricted | L24: 2774124 | M24: 106291 | N24: 955560 | Q24: 4440992 | R24: =SUM(K24:Q24) -> 8276967
C25: Unassigned | K25: 517469 | O25: -64641 | P25: -34061 | Q25: -16663 | R25: =SUM(K25:Q25) -> 402104
E27: Total fund balance (deficit): | K27: =SUM(K24:K25) -> 517469 | L27: =SUM(L24:L25) -> 2774124 | M27: =SUM(M24:M25) -> 106291 | N27: =SUM(N24:N25) -> 955560 | O27: =SUM(O24:O25) -> -64641 | Q27: =SUM(Q24:Q25) -> 4424329 | R27: =SUM(R24:R25) -> 8679071
E29: Total liabilities and fund balances: | K29: =SUM(K27,K21) -> 594685 | L29: =SUM(L21,L27) -> 2992751 | M29: =SUM(M21,M27) -> 106546 | N29: =SUM(N21+N27) -> 955560 | O29: =SUM(O21+O27) -> 8445 | Q29: =SUM(Q21,Q27) -> 4562646 | R29: =SUM(R21,R27) -> 9269465

Sheet St. James
D1: St. James Combined Balance Sheet
D2: Issued: December 31, 2015
K5: General | L5: Courthouse, Jail, and Public Buildings Maintenance | M5: Parishwide Drainage Maintenance | N5: Road & Bridge Maintenance | O5: CDBG Disaster Recovery Projects | P5: Nonmajor Governmental Funds | Q5: Total Governmental Funds
A6: Assets:
B7: Cash and cash equivalents | K7: 3680718 | L7: 1303863 | M7: 1384104 | N7: 460409 | O7: 7132 | P7: 10364231 | Q7: =SUM(K7:P7) -> 17200457
B8: Investments | K8: 2709554 | L8: 3243105 | M8: 3011572 | N8: 1206783 | P8: 8708487 | Q8: =SUM(K8:P8) -> 18879501
B9: Receivables (net of allowances for uncollectibles) | K9: 4968364 | L9: 2989445 | M9: 1653686 | N9: 2851738 | O9: 1595979 | P9: 7319333 | Q9: =SUM(K9:P9) -> 21378545
B10: Due from other funds | K10: 67784 | L10: 1142369 | M10: 122 | P10: 752480 | Q10: =SUM(K10:P10) -> 1962755
B11: Prepaid items | P11: 16476 | Q11: =SUM(K11:P11) -> 16476
B12: Inventory | K12: 36691 | Q12: =SUM(K12:P12) -> 36691
E14: Total Assets: | K14: =SUM(K7:K12) -> 11463111 | L14: =SUM(L7:L10) -> 8678782 | M14: =SUM(M7:M10) -> 6049484 | N14: =SUM(N7:N10) -> 4518930 | O14: =SUM(O7:O10) -> 1603111 | P14: =SUM(P7:P11) -> 27161007 | Q14: =SUM(Q7:Q12) -> 59474425
A16: LIABILITIES AND FUND BALANCES
B17: Liabilities:
C18: Accounts payable | K18: 969681 | L18: 199205 | M18: 151122 | N18: 119888 | O18: 602747 | P18: 1173622 | Q18: =SUM(K18:P18) -> 3216265
C19: Payroll deductions and withholdings payable | K19: 553993 | L19: 12163 | M19: 8512 | N19: 22760 | P19: 38263 | Q19: =SUM(K19:P19) -> 635691
C20: Due to other funds | K20: 32316 | N20: 472147 | O20: 1282172 | P20: 250589 | Q20: =SUM(K20:P20) -> 2037224
C21: Accrued expenses | K21: 59386 | L21: 12036 | M21: 5298 | N21: 20900 | P21: 68507 | Q21: =SUM(K21:P21) -> 166127
C22: Other liabilities | P22: 61456 | Q22: =SUM(K22:P22) -> 61456
E24: Total liabilities: | K24: =SUM(K18:K22) -> 1615376 | L24: =SUM(L18:L22) -> 223404 | M24: =SUM(M18:M22) -> 164932 | N24: =SUM(N18:N22) -> 635695 | O24: =SUM(O18:O22) -> 1884919 | P24: =SUM(P18:P22) -> 1592437 | Q24: =SUM(Q18:Q22) -> 6116763
B26: Fund Balances
C27: Nonspendable -prepaid items and Inventory | K27: 36691 | P27: 16476 | Q27: =SUM(K27:P27) -> 53167
C28: Restricted for
D29: Culture and recreation | P29: 7043866 | Q29: =SUM(K29:P29) -> 7043866
D30: Debt service | P30: 1529209 | Q30: =SUM(K30:P30) -> 1529209
D31: Capital projects | P31: 898744 | Q31: =SUM(K31:P31) -> 898744
D32: Health and welfare | K32: 5685398 | P32: 1572203 | Q32: =SUM(K32:P32) -> 7257601
D33: Highways and streets | N33: 3913778 | P33: 1543151 | Q33: =SUM(K33:P33) -> 5456929
D34: Public safety | M34: 5884552 | P34: 8921467 | Q34: =SUM(K34:P34) -> 14806019
D35: Sanitation | P35: 3305887 | Q35: =SUM(K35:P35) -> 3305887
D36: General government | L36: 8455378 | Q36: =SUM(K36:P36) -> 8455378
D37: Other purposes | P37: 5904 | Q37: =SUM(K37:P37) -> 5904
C38: Commited for
D39: Judicial | P39: 656497 | Q39: =SUM(K39:P39) -> 656497
D40: Highways and streets | P40: 45618 | Q40: =SUM(K40:P40) -> 45618
D41: Public transportation | P41: 69572 | Q41: =SUM(K41:P41) -> 69572
C42: Assigned for
D43: Health and welfare | P43: 20843 | Q43: =SUM(K43:P43) -> 20843
D44: Other purposes | P44: 44295 | Q44: =SUM(K44:P44) -> 44295
C45: Unassigned | K45: 4125646 | O45: -281808 | P45: -105162 | Q45: =SUM(K45:P45) -> 3738676
E47: Total fund balance: | K47: =SUM(K27:K45) -> 9847735 | L47: =SUM(L28:L45) -> 8455378 | M47: =SUM(M28:M45) -> 5884552 | N47: =SUM(N28:N45) -> 3913778 | O47: =SUM(O28:O45) -> -281808 | P47: =SUM(P27:P45) -> 25568570 | Q47: =SUM(Q27:Q46) -> 53388205
E49: Total liabilities and fund balances: | K49: =SUM(K47,K24) -> 11463111 | L49: =SUM(L24,L47) -> 8678782 | M49: =SUM(M24,M47) -> 6049484 | N49: =SUM(N24,N47) -> 4549473 | O49: =SUM(O24,O47) -> 1603111 | P49: =SUM(P47+P24) -> 27161007 | Q49: =SUM(Q24+Q47) -> 59504968

Sheet St. John the Baptist
D1: St. John the Baptist Combined Balance Sheet
D2: Issued: December 31, 2015
K4: General | L4: Sales Tax District | M4: Roads and Bridges | N4: 1992 General Obligation Sinking | O4: 2010 Sewer Construction Bond | P4: 2014 General Obligation Bond | Q4: Fire Services | R4: Issac Hurricane CDBG | S4: Non-Major Governmental Funds | T4: Total Governmental Funds
A5: Assets:
B6: Cash and cash equivalents | K6: 666991 | L6: 3993201 | M6: 1488984 | N6: 6315091 | O6: 12024796 | P6: 12318607 | Q6: 5482645 | S6: 31081121 | T6: =SUM(K6:S6) -> 73371436
B7: Receivables (net of allowances for uncollectible) | T7: =SUM(K7:S7) -> 0
C8: Accounts | K8: 130358 | Q8: 29789 | S8: 258042 | T8: =SUM(K8:S8) -> 418189
C9: Ad valorem taxes | K9: 2139726 | N9: 5254722 | S9: 4548120 | T9: =SUM(K9:S9) -> 11942568
C10: Sales and use taxes | K10: 15648 | L10: 1787890 | M10: 709863 | Q10: 946485 | S10: 709863 | T10: =SUM(K10:S10) -> 4169749
C11: Other | K11: 254 | M11: 85313 | S11: 108731 | T11: =SUM(K11:S11) -> 194298
B12: Due from other funds | K12: 781583 | L12: 2029607 | M12: 1422032 | O12: 331178 | Q12: 159697 | S12: 887970 | T12: =SUM(K12:S12) -> 5612067
B13: Due from other governments | K13: 49319 | M13: 52890 | P13: 521559 | Q13: 3528 | R13: 1743463 | S13: 1611485 | T13: =SUM(K13:S13) -> 3982244
B14: Prepaid items | K14: 49838 | M14: 71466 | S14: 351054 | T14: =SUM(K14:S14) -> 472358
E16: Total assets: | K16: =SUM(K6:K14) -> 3833717 | L16: =SUM(L6:L14) -> 7810698 | M16: =SUM(M6:M14) -> 3830548 | N16: =SUM(N6:N14) -> 11569813 | O16: =SUM(O6:O14) -> 12355974 | P16: =SUM(P6) -> 12318607 | Q16: =SUM(Q6) -> 5482645 | R16: =SUM(R6) -> 0 | S16: =SUM(S6:S15) -> 39556386 | T16: =SUM(T6:T14) -> 100162909
A18: LIABILITIES AND FUND BALANCES
B19: Liabilities:
C20: Accounts, salaries and other payables | K20: 933731 | M20: 898767 | O20: 204879 | P20: 776827 | Q20: 218013 | R20: 205178 | S20: 1463277 | T20: =SUM(K20:S20) -> 4700672
C21: Contracts payable | M21: 51219 | O21: 129908 | P21: 106978 | R21: 1350129 | S21: 396593 | T21: =SUM(K21:S21) -> 2034827
C22: Due to other funds | K22: 656236 | L22: 100000 | M22: 32262 | P22: 1437 | Q22: 63217 | R22: 167534 | S22: 1774480 | T22: =SUM(K22:S22) -> 2795166
C23: Other liabilities | S23: 33935 | T23: =SUM(K23:S23) -> 33935
E25: Total liabilities: | K25: =SUM(K20:K23) -> 1589967 | L25: =SUM(L20:L22) -> 100000 | M25: =SUM(M20:M22) -> 982248 | N25: =SUM(N20:N22) -> 0 | O25: =SUM(O20:O22) -> 334787 | P25: =SUM(P20:P23) -> 885242 | Q25: =SUM(Q20:Q23) -> 281230 | R25: =SUM(R20:R23) -> 1722841 | S25: =SUM(S20:S23) -> 3668285 | T25: =SUM(T20:T23) -> 9564600
A27: DEFERRED INFLOWS OF RESOURCES
C28: Unavailable revenue | K28: 40223 | M28: 15034 | P28: 521559 | R28: 1464310 | S28: 975108 | T28: =SUM(K28:S28) -> 3016234
E30: Total deferred inflows of resources: | K30: =K28 -> 40223 | L30: =SUM(L28) -> 0 | M30: =SUM(M28) -> 15034 | N30: =SUM(N28) -> 0 | O30: =SUM(O28) -> 0 | S30: =SUM(S28) -> 975108 | T30: =SUM(T28) -> 3016234
B32: Fund Balances
C33: Non-spendable | K33: 49838 | M33: 71466 | S33: 351054 | T33: =SUM(K33:S33) -> 472358
C34: Restricted | L34: 7710698 | M34: 2761800 | N34: 11569813 | S34: 15736235 | T34: =SUM(K34:S34) -> 37778546
C35: Committed | O35: 12021187 | P35: 11433365 | Q35: 6340914 | R35: -1443688 | S35: 18825704 | T35: =SUM(K35:S35) -> 47177482
C36: Unassigned | K36: 2153689 | T36: =SUM(K36:S36) -> 2153689
E38: Total fund balance: | K38: =SUM(K33:K36) -> 2203527 | L38: =SUM(L33:L36) -> 7710698 | M38: =SUM(M33:M36) -> 2833266 | N38: =SUM(N33:N36) -> 11569813 | O38: =SUM(O33:O36) -> 12021187 | P38: =SUM(P33:P36) -> 11433365 | Q38: =SUM(Q33:Q36) -> 6340914 | R38: =SUM(R33:R36) -> -1443688 | ... T38: =SUM(T33:T36) -> 87582075
E40: Total liabilities, deferred inflows, and fund balances: | K40: =SUM(K38,K25,K30) -> 3833717 | L40: =SUM(L38,L25,L30) -> 7810698 | M40: =SUM(M38,M25,M30) -> 3830548 | N40: =SUM(N38,N25,N30) -> 11569813 | O40: =SUM(O38,O25,O30) -> 12355974 | P40: =SUM(P25+P30+P38) -> 12318607 | Q40: =SUM(Q25+Q30+Q38) -> 6622144 | R40: =SUM(R25+R30+R38) -> 279153 | S40: =SUM(S38,S25,S30) -> 39556386 | T40: =SUM(T38,T25,T30) -> 100162909

Sheet St. Landry
D1: St. Landry Combined Balance Sheet
D2: Issued: December 31, 2015
K4: General Fund | L4: Road and Bridge Maintenance Fund | M4: Health Unit Maintenance Fund | N4: Airport Maintenance Fund | O4: LCDBG Disaster Recovery Fund | P4: Road District 1 Sales Tax | Q4: Road District 1 Construction | R4: Road District 1 Sinking Fund | S4: Other Governmental Funds | T4: Total Governmental Funds
A5: Assets:
B6: Cash and interest-bearing deposits | K6: 191320 | L6: 69740 | M6: 17398 | N6: 3771 | O6: 3617 | S6: 653527 | T6: =SUM(K6:S6) -> 939373
B7: Cash and cash equivalents, restricted | P7: 792691 | Q7: 2045141 | R7: 14 | T7: =SUM(K7:S7) -> 2837846
B8: Receivables | K8: 2519392 | L8: 147308 | M8: 1382396 | N8: 20832 | O8: 125432 | P8: 589459 | S8: 1601523 | T8: =SUM(K8:S8) -> 6386342
B9: Prepaid items | K9: 25877 | L9: 15967 | M9: 4190 | N9: 796 | Q9: 213038 | T9: =SUM(K9:S9) -> 259868
B10: Investments, restricted | Q10: 28604186 | T10: =SUM(K10:S10) -> 28604186
B11: Due from other funds | K11: 562732 | L11: 104 | M11: 15425 | O11: 4910 | P11: 130000 | S11: 293864 | T11: =SUM(K11:S11) -> 1007035
B12: Due from agency funds | K12: 42602 | L12: 251331 | N12: 6854 | T12: =SUM(K12:S12) -> 300787
B13: Due from component units | K13: 12272 | T13: =SUM(K13:S13) -> 12272
B14: Due from other governments | K14: 120589 | L14: 9346 | T14: =SUM(K14:S14) -> 129935
E16: Total assets: | K16: =SUM(K6:K14) -> 3474784 | L16: =SUM(L6:L14) -> 493796 | M16: =SUM(M6:M14) -> 1419409 | N16: =SUM(N6:N14) -> 32253 | O16: =SUM(O6:O14) -> 133959 | P16: =SUM(P6:P14) -> 1512150 | Q16: =SUM(Q6:Q14) -> 30862365 | R16: =SUM(R6:R14) -> 14 | S16: =SUM(S6:S15) -> 2548914 | T16: =SUM(T6:T14) -> 40477644
A18: LIABILITIES AND FUND BALANCES
B19: Liabilities:
C20: Accounts payable | K20: 414771 | M20: 46026 | N20: 78296 | O20: 125432 | P20: 3426 | Q20: 4194363 | S20: 247936 | T20: =SUM(K20:S20) -> 5110250
C21: Accrued penalties and interest | N21: 6091 | T21: =SUM(K21:S21) -> 6091
C22: Accrued expenditures | K22: 411873 | N22: 13018 | T22: =SUM(K22:S22) -> 424891
C23: Unearned revenue | K23: 1300 | N23: 4037 | T23: =SUM(K23:S23) -> 5337
C24: Due to agency funds | K24: 106926 | T24: =SUM(K24:S24) -> 106926
C25: Due to other funds | K25: 123540 | L25: 291178 | M25: 241022 | N25: 82542 | S25: 268753 | T25: =SUM(K25:S25) -> 1007035
C26: Due to component units | K26: 6389 | T26: =SUM(K26:S26) -> 6389
E28: Total liabilities: | K28: =SUM(K20:K26) -> 1064799 | L28: =SUM(L20:L26) -> 291178 | M28: =SUM(M20:M26) -> 287048 | N28: =SUM(N20:N26) -> 183984 | O28: =SUM(O20:O26) -> 125432 | P28: =SUM(P20:P26) -> 3426 | Q28: =SUM(Q20:Q26) -> 4194363 | R28: =SUM(R20:R26) -> 0 | ... T28: =SUM(T20:T26) -> 6666919
A30: DEFERRED INFLOWS OF RESOURCES
K31: 57604 | M31: 39307 | S31: 52517 | T31: =SUM(K31:S31) -> 149428
E33: Total deferred inflows of resources: | K33: =K31 -> 57604 | L33: =SUM(L31) -> 0 | M33: =SUM(M31) -> 39307 | N33: =SUM(N31) -> 0 | O33: =SUM(O31) -> 0 | S33: =SUM(S31) -> 52517 | T33: =SUM(T31) -> 149428
C35: Restricted for:
C36: Nonspendable:
D37: Prepaids | K37: 25877 | L37: 15967 | M37: 4190 | Q37: 213038 | T37: =SUM(K37:S37) -> 259072
C38: Restricted for:
D39: Other general government | S39: 21718 | T39: =SUM(K39:S39) -> 21718
D40: Public works | S40: 1521987 | T40: =SUM(K40:S40) -> 1521987
D41: Prisoner expense and jury witness | K41: 247612 | T41: =SUM(K41:S41) -> 247612
D42: Judicial expenses | K42: 29192 | T42: =SUM(K42:S42) -> 29192
D43: Public safety | S43: 474354 | T43: =SUM(K43:S43) -> 474354
D44: Health and welfare | M44: 1088864 | T44: =SUM(K44:S44) -> 1088864
D45: Parish road construction | P45: 1508724 | Q45: 26454964 | T45: =SUM(K45:S45) -> 27963688
D46: Debt service | R46: 14 | S46: 30690 | T46: =SUM(K46:S46) -> 30704
C47: Committed to: | T47: =SUM(K47:S47) -> 0
D48: General contingencies | K48: 167363 | T48: =SUM(K48:S48) -> 167363
C49: Assigned to | T49: =SUM(K49:S49) -> 0
D50: Public works | K50: 198751 | T50: =SUM(K50:S50) -> 198751
D51: Public safety | K51: 75788 | T51: =SUM(K51:S51) -> 75788
C52: Unassigned | K52: 1607798 | L52: 186651 | N52: -151731 | O52: 8527 | S52: -69041 | T52: =SUM(K52:S52) -> 1582204
E54: Total fund balance: | K54: =SUM(K37:K52) -> 2352381 | L54: =SUM(L37:L52) -> 202618 | M54: =SUM(M37:M52) -> 1093054 | N54: =SUM(N37:N52) -> -151731 | O54: =SUM(O37:O52) -> 8527 | P54: =SUM(P37:P52) -> 1508724 | Q54: =SUM(Q37:Q52) -> 26668002 | R54: =SUM(R37:R52) -> 14 | ... T54: =SUM(T37:T52) -> 33661297
E56: Total liabilities and fund balances: | K56: =SUM(K28+K33+K54) -> 3474784 | L56: =SUM(L28+L33+L54) -> 493796 | M56: =SUM(M28+M33+M54) -> 1419409 | N56: =SUM(N28+N33+N54) -> 32253 | O56: =SUM(O28+O33+O54) -> 133959 | P56: =SUM(P28+P33+P54) -> 1512150 | Q56: =SUM(Q28+Q33+Q54) -> 30862365 | R56: =SUM(R28+R33+R54) -> 14 | ... T56: =SUM(T28+T33+T54) -> 40477644

Sheet St. Martin
D1: St. Martin Combined Balance Sheet
D2: Issued: December 31, 2015
K5: General Fund | L5: District #1 Sales Tax Revenue Fund | M5: District #2 Sales Tax Revenue Fund | N5: Public Works Fund | O5: Parishwide Bond Sinking Fund | P5: Road Construction Fund | Q5: Capital Outlay Fund | R5: Nonmajor Governmental Funds | S5: Total Governmental Funds
A6: Assets:
B7: Cash and cash equivalents | K7: 4829757 | L7: 12201682 | M7: 10873707 | O7: 135954 | P7: 576710 | R7: 1043508 | S7: =SUM(K7:R7) -> 29661318
B8: Receivables | K8: 931074 | L8: 434626 | N8: 5010534 | O8: 1496317 | R8: 4493713 | S8: =SUM(K8:R8) -> 12366264
B9: Due from other governmental entities | K9: 78022 | L9: 244764 | M9: 108266 | S9: =SUM(K9:R9) -> 431052
B10: Due from other funds | N10: 6576474 | O10: 4827657 | R10: 8873911 | S10: =SUM(K10:R10) -> 20278042
E12: Total Assets: | K12: =SUM(K7:K10) -> 5838853 | L12: =SUM(L7:L10) -> 12881072 | M12: =SUM(M7:M10) -> 10981973 | N12: =SUM(N7:N10) -> 11587008 | O12: =SUM(O7:O10) -> 6459928 | P12: =SUM(P7:P10) -> 576710 | Q12: =SUM(Q7:Q10) -> 0 | R12: =SUM(R7:R10) -> 14411132 | S12: =SUM(S7:S10) -> 62736676
A14: LIABILITIES, DEFERRED INFLOWS OF RESOURCES, AND FUND BALANCES
B15: Liabilities:
C16: Accounts payable | K16: 149347 | L16: 7100 | M16: 12659 | N16: 58346 | Q16: 74013 | R16: 346280 | S16: =SUM(K16:R16) -> 647745
C17: Accrued liabilities | K17: 31534 | M17: 670 | N17: 45672 | R17: 51319 | S17: =SUM(K17:R17) -> 129195
C18: Unearned revenues | M18: 28084 | S18: =SUM(K18:R18) -> 28084
C19: Due to other funds | K19: 2253184 | L19: 4160415 | M19: 5167579 | P19: 3378375 | Q19: 1541805 | R19: 3428338 | S19: =SUM(K19:R19) -> 19929696
C20: Due to other governmental entities | R20: 89704 | S20: =SUM(K20:R20) -> 89704
C21: Other liabilities | K21: 133007 | S21: =SUM(K21:R21) -> 133007
E23: Total liabilities: | K23: =SUM(K16:K21) -> 2567072 | L23: =SUM(L16:L21) -> 4167515 | M23: =SUM(M16:M21) -> 5208992 | N23: =SUM(N16:N21) -> 104018 | O23: =SUM(O16:O21) -> 0 | P23: =SUM(P16:P21) -> 3378375 | Q23: =SUM(Q16:Q21) -> 1615818 | R23: =SUM(R16:R21) -> 3915641 | S23: =SUM(S16:S21) -> 20957431
A25: DEFERRED INFLOWS OF RESOURCES:
C26: Unavailable revenues | S26: =SUM(K26:R26) -> 0
B28: Fund Balances:
C29: Restricted for:
D30: Sales tax dedications | L30: 8713557 | M30: 5772981 | S30: =SUM(K30:R30) -> 14486538
D31: Other general government | R31: 60432 | S31: =SUM(K31:R31) -> 60432
D32: Public works | N32: 11482990 | R32: 609684 | S32: =SUM(K32:R32) -> 12092674
D33: Public safety | R33: 3650014 | S33: =SUM(K33:R33) -> 3650014
D34: Culture and recreation | R34: 390218 | S34: =SUM(K34:R34) -> 390218
D35: Economic development | R35: 1721262 | S35: =SUM(K35:R35) -> 1721262
D36: Health and welfare | R36: 586402 | S36: =SUM(K36:R36) -> 586402
D37: Debt service | O37: 6459928 | R37: 143322 | S37: =SUM(K37:R37) -> 6603250
D38: Capital outlay | S38: =SUM(K38:R38) -> 0
C39: Commited to:
D40: Other general government | R40: 342048 | S40: =SUM(K40:R40) -> 342048
D41: Public works | R41: 286686 | S41: =SUM(K41:R41) -> 286686
D42: Public safety | S42: =SUM(K42:R42) -> 0
D43: Economic development | R43: 190298 | S43: =SUM(K43:R43) -> 190298
D44: Health and welfare | R44: 43500 | S44: =SUM(K44:R44) -> 43500
C45: Assigned to: | S45: =SUM(K45:R45) -> 0
D46: Economic development | R46: 1626778 | S46: =SUM(K46:R46) -> 1626778
D47: Debt service | R47: 19794 | S47: =SUM(K47:R47) -> 19794
C48: Unassigned | K48: 3271781 | P48: -2801665 | Q48: -1615818 | R48: 825053 | S48: =SUM(K48:R48) -> -320649
E50: Total fund balance: | K50: =SUM(K29:K48) -> 3271781 | L50: =SUM(L29:L48) -> 8713557 | M50: =SUM(M29:M48) -> 5772981 | N50: =SUM(N29:N48) -> 11482990 | O50: =SUM(O29:O48) -> 6459928 | P50: =SUM(P29:P48) -> -2801665 | Q50: =SUM(Q29:Q48) -> -1615818 | R50: =SUM(R29:R48) -> 10495491 | S50: =SUM(S29:S48) -> 41779245
E52: Total liabilities and fund balances: | K52: =SUM(K23+K50) -> 5838853 | L52: =SUM(L50,L23,L26) -> 12881072 | M52: =SUM(M50,M23,M26) -> 10981973 | N52: =SUM(N50,N23,N26) -> 11587008 | O52: =SUM(O50,O23,O26) -> 6459928 | P52: =SUM(P50,P23,P26) -> 576710 | Q52: =SUM(Q50,Q23,Q26) -> 0 | R52: =SUM(R50,R23,R26) -> 14411132 | S52: =SUM(S50,S23,S26) -> 62736676

Sheet St. Mary
D1: St. Mary Combined Balance Sheet
D2: Issued: December 31, 2015
K5: General Fund | L5: Road Construction & Maintenance Fund | M5: Sanitation Fund | N5: Capital Improvement Fund | O5: CDBG Recovery Fund | P5: Combined Sewer Construction Fund | Q5: Other Governmental Funds | R5: Total Governmental Funds
A6: Assets:
B7: Cash and cash equivalents | L7: 123 | O7: 235 | P7: 1 | Q7: 1706201 | R7: =SUM(K7:Q7) -> 1706560
B8: Investments | L8: 2710814 | M8: 1307498 | N8: 1502859 | P8: 2581509 | Q8: 2497135 | R8: =SUM(K8:Q8) -> 10599815
B9: Receivables (net, where applicable of
C10: allowances for uncollectibles) | K10: 449501 | L10: 107999 | M10: 203765 | Q10: 133851 | R10: =SUM(K10:Q10) -> 895116
B11: Due from component units | K11: 1601018 | M11: 41357 | P11: 641246 | R11: =SUM(K11:Q11) -> 2283621
B12: Due from other governments | K12: 3050405 | L12: 1049937 | M12: 476265 | N12: 1148176 | O12: 1000696 | Q12: 1362352 | R12: =SUM(K12:Q12) -> 8087831
B13: Due from other funds | L13: 137 | R13: =SUM(K13:Q13) -> 137
B14: Advances to other funds | Q14: 3566818 | R14: =SUM(K14:Q14) -> 3566818
B15: Other assets | Q15: 4220 | R15: =SUM(K15:Q15) -> 4220
E17: Total Assets: | K17: =SUM(K7:K15) -> 5100924 | L17: =SUM(L7:L15) -> 3869010 | M17: =SUM(M7:M15) -> 2028885 | N17: =SUM(N7:N15) -> 2651035 | O17: =SUM(O7:O15) -> 1000931 | P17: =SUM(P7:P15) -> 3222756 | Q17: =SUM(Q7:Q15) -> 9270577 | R17: =SUM(R7:R15) -> 27144118
A19: LIABILITIES
C20: Accounts payable | K20: 343181 | L20: 157410 | M20: 188218 | P20: 407 | Q20: 262047 | R20: =SUM(K20:Q20) -> 951263
C21: Contracts payable | N21: 659864 | O21: 729580 | R21: =SUM(K21:Q21) -> 1389444
C22: Retainage payable | L22: 21657 | N22: 218738 | O22: 271116 | Q22: 4113 | R22: =SUM(K22:Q22) -> 515624
C23: Accrued liabilities | K23: 130516 | L23: 61155 | M23: 2337 | Q23: 47186 | R23: =SUM(K23:Q23) -> 241194
C24: Due to other governmental units | Q24: 456210 | R24: =SUM(K24:Q24) -> 456210
C25: Due to other funds | K25: 1319 | Q25: 50 | R25: =SUM(K25:Q25) -> 1369
C26: Advance from other funds | K26: 1456609 | L26: 1639875 | M26: 1006727 | N26: 1375772 | P26: 2279203 | Q26: 732903 | R26: =SUM(K26:Q26) -> 8491089
E28: Total liabilities: | K28: =SUM(K20:K26) -> 1931625 | L28: =SUM(L20:L26) -> 1880097 | M28: =SUM(M20:M26) -> 1197282 | N28: =SUM(N20:N26) -> 2254374 | O28: =SUM(O20:O26) -> 1000696 | P28: =SUM(P20:P26) -> 2279610 | Q28: =SUM(Q20:Q26) -> 1502509 | R28: =SUM(R20:R26) -> 12046193
B30: Fund Balances (deficit)
C31: Nonspendable- non-current receivables | K31: 1600000 | L31: 1049937 | P31: 589137 | R31: =SUM(K31:Q31) -> 3239074
C32: Restricted for:
D33: Use in specific geographic areas | Q33: 1620084 | R33: =SUM(K33:Q33) -> 1620084
D34: Debt service | Q34: 3473635 | R34: =SUM(K34:Q34) -> 3473635
C35: Assigned for:
D36: General government | Q36: 254884 | R36: =SUM(K36:Q36) -> 254884
D37: Public safety | Q37: 65518 | R37: =SUM(K37:Q37) -> 65518
D38: Public works | L38: 938976 | Q38: 151548 | R38: =SUM(K38:Q38) -> 1090524
D39: Culture and recreation | Q39: 291186 | R39: =SUM(K39:Q39) -> 291186
D40: Health and welfare | Q40: 179735 | R40: =SUM(K40:Q40) -> 179735
D41: Urban redevelopment and housing | Q41: 14591 | R41: =SUM(K41:Q41) -> 14591
D42: Debt service | Q42: 1125980 | R42: =SUM(K42:Q42) -> 1125980
D43: Sanitation | M43: 831603 | R43: =SUM(K43:Q43) -> 831603
D44: Capital projects | N44: 396661 | O44: 235 | R44: =SUM(K44:Q44) -> 396896
C45: Unassigned | K45: 1569299 | P45: 354009 | Q45: 590907 | R45: =SUM(K45:Q45) -> 2514215
E47: Total fund balance: | K47: =SUM(K31:K45) -> 3169299 | L47: =SUM(L31:L45) -> 1988913 | M47: =SUM(M31:M45) -> 831603 | N47: =SUM(N31:N45) -> 396661 | O47: =SUM(O31:O45) -> 235 | P47: =SUM(P31:P45) -> 943146 | Q47: =SUM(Q31:Q45) -> 7768068 | R47: =SUM(R31:R45) -> 15097925
E49: Total liabilities and fund balances: | K49: =SUM(K47+K28) -> 5100924 | L49: =SUM(L47,L28,) -> 3869010 | M49: =SUM(M47,M28,) -> 2028885 | N49: =SUM(N47,N28,) -> 2651035 | O49: =SUM(O47,O28,) -> 1000931 | P49: =SUM(P47,P28,) -> 3222756 | Q49: =SUM(Q47+Q28) -> 9270577 | R49: =SUM(R47+R28) -> 27144118

Sheet St. Tammany
D1: St.Tammany Combined Balance Sheet
D2: Issued: December 31, 2015
K4: Major Funds
K5: 010, 012 General Fund | L5: 013 St. Tammany Parish Library | M5: 015 Public Works | N5: 300 Capital Improvements - General | O5: Total Non-Major Governmental Funds | P5: Total Governmental Funds
A6: Assets:
B7: Cash and Cash equivalents | K7: 1862081 | M7: 2578307 | N7: 1826250 | O7: 37046383 | P7: =SUM(K7:O7) -> 43313021
B8: Investments | K8: 10817767 | M8: 11426140 | N8: 27136140 | O8: 69505358 | P8: =SUM(K8:O8) -> 118885405
B9: Receivables, net of allowances for uncollectibles:
C10: Ad valorem/parcel fees | K10: 4414686 | L10: 10774947 | O10: 17802930 | P10: =SUM(K10:O10) -> 32992563
C11: Sales and use tax | M11: 8453729 | O11: 4394242 | P11: =SUM(K11:O11) -> 12847971
C12: Other recievables | K12: 1608151 | L12: 162885 | M12: 899823 | N12: 267885 | O12: 6882748 | P12: =SUM(K12:O12) -> 9821492
B13: Due from other funds | O13: 976212 | P13: =SUM(K13:O13) -> 976212
B14: Due from component units | K14: 46305 | O14: 85102 | P14: =SUM(K14:O14) -> 131407
B15: Prepaid items | K15: 101628 | M15: 2487 | O15: 4775 | P15: =SUM(K15:O15) -> 108890
B16: Restricted assets | O16: 10149191 | P16: =SUM(K16:O16) -> 10149191
B17: Other assets | K17: 15456 | M17: 500 | P17: =SUM(K17:O17) -> 15956
E19: Total Assets: | K19: =SUM(K7:K17) -> 18866074 | L19: =SUM(L7:L17) -> 10937832 | M19: =SUM(M7:M17) -> 23360986 | N19: =SUM(N7:N17) -> 29230275 | O19: =SUM(O7:O17) -> 146846941 | P19: =SUM(P7:P17) -> 229242108
A21: LIABILITIES
B22: Liabilities:
C23: Accounts, salaries, and other payables | K23: 2999800 | L23: 361886 | M23: 1536528 | N23: 459393 | O23: 14008244 | P23: =SUM(K23:O23) -> 19365851
C24: Due to other funds | L24: 976212 | O24: 1319571 | P24: =SUM(K24:O24) -> 2295783
C25: Due to component units | L25: 9410851 | P25: =SUM(K25:O25) -> 9410851
C26: Unearned revenue | K26: 53050 | M26: 69787 | O26: 4219896 | P26: =SUM(K26:O26) -> 4342733
C27: Other liabilities | K27: 1953655 | L27: 1032 | M27: 28500 | N27: 112843 | O27: 301253 | P27: =SUM(K27:O27) -> 2397283
E29: Total liabilities: | K29: =SUM(K23:K27) -> 5006505 | L29: =SUM(L23:L27) -> 10749981 | M29: =SUM(M23:M27) -> 1634815 | N29: =SUM(N23:N27) -> 572236 | O29: =SUM(O23:O27) -> 19848964 | P29: =SUM(P23:P27) -> 37812501
A31: DEFERRED INFLOWS OF RESOURCES
B32: Unavailable revenue-ad valorem/parcel fees | K32: 38464 | L32: 106408 | O32: 198798 | P32: =SUM(K32:O32) -> 343670
B33: Unavailable revenue-state revenue sharing | K33: 91209 | L33: 81443 | O33: 80543 | P33: =SUM(K33:O33) -> 253195
E35: Total deferred inflows of resources | K35: =SUM(K32:K33) -> 129673 | L35: =SUM(L32:L33) -> 187851 | M35: =SUM(M32:M33) -> 0 | N35: =SUM(N32:N33) -> 0 | O35: =SUM(O32:O33) -> 279341 | P35: =SUM(P32:P33) -> 596865
B38: Fund Balances
C39: Nonspendable, prepaid items | K39: 101628 | M39: 2487 | O39: 4775 | P39: =SUM(K39:O39) -> 108890
C40: Restricted | M40: 20935414 | N40: 28658039 | O40: 101812659 | P40: =SUM(K40:O40) -> 151406112
C41: Commited | M41: 788270 | O41: 24946202 | P41: =SUM(K41:O41) -> 25734472
C42: Unassigned | K42: 13628268 | P42: =SUM(K42:O42) -> 13628268
E44: Total fund balances: | K44: =SUM(K39:K42) -> 13729896 | L44: =SUM(L39:L42) -> 0 | M44: =SUM(M39:M42) -> 21726171 | N44: =SUM(N39:N42) -> 28658039 | O44: =SUM(O39:O42) -> 126763636 | P44: =SUM(P39:P42) -> 190877742
E46: Total liabilities, deferred inflows of resouces, and fund balances: | K46: =SUM(K29+K35+K44) -> 18866074 | L46: =SUM(L29+L35+L44) -> 10937832 | M46: =SUM(M29+M35+M44) -> 23360986 | N46: =SUM(N29+N35+N44) -> 29230275 | O46: =SUM(O29+O35+O44) -> 146891941 | P46: =SUM(P29+P35+P44) -> 229287108

Sheet Tangipahoa
D1: Tangipahoa Combined Balance Sheet
D2: Issued: December 31, 2015
K5: General Fund | L5: Road and Bridge Funds | M5: Garbage District No. 1 | N5: Health Unit | O5: Hazard Mitigation | P5: Other Governmental Funds | Q5: Total Governmental Funds
A6: Assets:
B7: Cash and Cash equivalents | K7: 195733 | L7: 10197868 | M7: 4612715 | N7: 445622 | O7: 17 | P7: 3270231 | Q7: =SUM(K7:P7) -> 18722186
B8: Receivables, net | K8: 2144043 | L8: 1408651 | M8: 3301847 | N8: 2311202 | O8: 447336 | P8: 826993 | Q8: =SUM(K8:P8) -> 10440072
B9: Due from other governments | K9: 330751 | Q9: =SUM(K9:P9) -> 330751
B10: Due from other funds | K10: 402530 | N10: 300000 | Q10: =SUM(K10:P10) -> 702530
B11: Restricted assets - cash | K11: 677606 | L11: 103410 | M11: 183148 | N11: 24506 | P11: 10619 | Q11: =SUM(K11:P11) -> 999289
E13: Total Assets: | K13: =SUM(K7:K11) -> 3750663 | L13: =SUM(L7:L11) -> 11709929 | M13: =SUM(M7:M11) -> 8097710 | N13: =SUM(N7:N11) -> 3081330 | O13: =SUM(O7:O11) -> 447353 | P13: =SUM(P7:P11) -> 4107843 | Q13: =SUM(Q7:Q11) -> 31194828
A15: LIABILITIES
C16: Accounts, salaries, and other payables | K16: 725391 | L16: 1139117 | M16: 302069 | N16: 198520 | O16: 258081 | P16: 157129 | Q16: =SUM(K16:P16) -> 2780307
C17: Due to other governments | K17: 49775 | M17: 109411 | P17: 280519 | Q17: =SUM(K17:P17) -> 439705
C18: Due to other funds | K18: 300000 | O18: 266000 | P18: 136530 | Q18: =SUM(K18:P18) -> 702530
E20: Total liabilities: | K20: =SUM(K16:K18) -> 1075166 | L20: =SUM(L16:L18) -> 1139117 | M20: =SUM(M16:M17) -> 411480 | N20: =SUM(N16:N19) -> 198520 | O20: =SUM(O16:O18) -> 524081 | P20: =SUM(P16:P18) -> 574178 | Q20: =SUM(Q16:Q18) -> 3922542
A22: Deferred Inflow of Resources
B23: Grant Funds | K23: 7500 | L23: 0 | M23: 0 | N23: 0 | Q23: =SUM(K23:O23) -> 7500
E25: Total Deferred inflow of Resources | K25: =SUM(K23) -> 7500 | L25: =SUM(L23) -> 0 | M25: =SUM(M23) -> 0 | N25: =SUM(N23) -> 0 | O25: =SUM(O23) -> 0 | P25: =SUM(P23) -> 0 | Q25: =SUM(Q23) -> 7500
B27: Fund Balances
C28: Restricted | K28: 123120 | L28: 10467402 | M28: 7655863 | N28: 2858304 | P28: 3414556 | Q28: =SUM(K28:P28) -> 24519245
C29: Commited | K29: 578712 | P29: 55297 | Q29: =SUM(K29:P29) -> 634009
C30: Assigned | K30: 98894 | L30: 103410 | M30: 30367 | N30: 24506 | P30: 67630 | Q30: =SUM(K30:P30) -> 324807
C31: Unassigned | K31: 1867271 | O31: -76728 | P31: -3818 | Q31: =SUM(K31:P31) -> 1786725
E33: Total fund balances | K33: =SUM(K28:K31) -> 2667997 | L33: =SUM(L28:L31) -> 10570812 | M33: =SUM(M28:M31) -> 7686230 | N33: =SUM(N28:N31) -> 2882810 | O33: =SUM(O28:O31) -> -76728 | P33: =SUM(P28:P31) -> 3533665 | Q33: =SUM(Q28:Q31) -> 27264786
E35: Total liabilities, Deferred inflow of Resources, | K35: =SUM(K33,K20,K25) -> 3750663 | L35: =SUM(L33,L20,L25) -> 11709929 | M35: =SUM(M33,M20,M25) -> 8097710 | N35: =SUM(N33,N20,N25) -> 3081330 | O35: =SUM(O20+O25+O33) -> 447353 | P35: =SUM(P20+P25+P33) -> 4107843 | Q35: =SUM(Q33,Q20,Q25) -> 31194828
F36: and fund balances:

Sheet Tensas
D1: Tensas Combined Balance Sheet
D2: Issued: December 31, 2015
J5: General Fund | K5: Road Fund | L5: Ambulance Fund | M5: Health Unit Fund | N5: Waste Collection Fund | O5: Landfill Site Fund | P5: Fire Protection Fund | Q5: Other Governmental Funds | R5: Total
A6: Assets:
B7: Cash and cash equivalents | J7: 244987 | K7: 117555 | L7: 4853 | M7: 531065 | N7: 11491 | O7: 20 | P7: 19553 | Q7: 830166 | R7: =SUM(J7:Q7) -> 1759690
B8: Receivables | J8: 554248 | K8: 32447 | M8: 139551 | N8: 97368 | P8: 8112 | Q8: 262332 | R8: =SUM(J8:Q8) -> 1094058
B9: Amounts held by trustee for landfill closure and post-closure care costs | L9: 35137 | O9: 989776 | R9: =SUM(J9:Q9) -> 1024913
B10: Restricted assets | Q10: 21705 | R10: =SUM(J10:Q10) -> 21705
B11: Due from other funds | K11: 25353 | L11: 27456 | N11: 16897 | P11: 6338 | Q11: 12676 | R11: =SUM(J11:Q11) -> 88720
E13: Total assets: | J13: =SUM(J7:J11) -> 799235 | K13: =SUM(K7:K11) -> 175355 | L13: =SUM(L7:L11) -> 67446 | M13: =SUM(M7:M11) -> 670616 | N13: =SUM(N7:N11) -> 125756 | O13: =SUM(O7:O11) -> 989796 | P13: =SUM(P7:P11) -> 34003 | Q13: =SUM(Q7:Q11) -> 1126879 | R13: =SUM(R7:R11) -> 3989086
A15: LIABILITIES AND FUND BALANCES
B16: Liabilities:
C17: Accounts, salaries, and other payables | J17: 178274 | K17: 80815 | L17: 33684 | M17: 4079 | N17: 46551 | Q17: 52763 | R17: =SUM(J17:Q17) -> 396166
C18: Intergovernmental payables | P18: 47165 | R18: =SUM(J18:Q18) -> 47165
E20: Total liabilities: | J20: =SUM(J17:J18) -> 178274 | K20: =SUM(K17:K18) -> 80815 | L20: =SUM(L17:L18) -> 33684 | M20: =SUM(M17:M18) -> 4079 | N20: =SUM(N17:N18) -> 46551 | O20: =SUM(O17:O18) -> 0 | P20: =SUM(P17:P18) -> 47165 | Q20: =SUM(Q17:Q18) -> 52763 | R20: =SUM(R17:R18) -> 443331
A22: Fund Balances (deficit)
C23: Restricted for:
D24: Debt service | Q24: 21705 | R24: =SUM(J24:Q24) -> 21705
D25: Landfill closure | O25: 989796 | R25: =SUM(J25:Q25) -> 989796
C26: Committed for:
D27: Special revenue projects | K27: 94540 | L27: 33762 | M27: 666537 | N27: 79205 | P27: -13162 | Q27: 1052411 | R27: =SUM(J27:Q27) -> 1913293
C28: Unassigned, reported in:
D29: General | J29: 620961 | R29: =SUM(J29:Q29) -> 620961
E31: Total fund balances: | J31: =SUM(J26:J29) -> 620961 | K31: =SUM(K26:K29) -> 94540 | L31: =SUM(L26:L29) -> 33762 | M31: =SUM(M26:M29) -> 666537 | N31: =SUM(N26:N29) -> 79205 | O31: =SUM(O24:O29) -> 989796 | P31: =SUM(P24:P29) -> -13162 | Q31: =SUM(Q24:Q29) -> 1074116 | R31: =SUM(R24:R29) -> 3545755
E33: Total liabilities and fund balances: | J33: =SUM(J31+J20) -> 799235 | K33: =SUM(K31+K20) -> 175355 | L33: =SUM(L31+L20) -> 67446 | M33: =SUM(M31+M20) -> 670616 | N33: =SUM(N31+N20) -> 125756 | O33: =SUM(O31+O20) -> 989796 | P33: =SUM(P31+P20) -> 34003 | Q33: =SUM(Q31+Q20) -> 1126879 | R33: =SUM(R31+R20) -> 3989086

Sheet Terrebonne
D1: Terrebonne Combined Balance Sheet
D2: Issued: December 31, 2015
K5: General Fund | L5: Public Safety Fund | M5: Grant Fund | N5: Road and Bridge Maintenance Fund | O5: Drainage Maintenance Fund | P5: Terrebonne Levee & Conservation District Fund | Q5: Capital Projects Fund | R5: Other Governmental Funds | S5: Total Governmental Funds
A6: Assets:
B7: Cash and cash equivalents | K7: 17082949 | L7: 4471640 | M7: 4464161 | N7: 2401967 | O7: 6518808 | P7: 2417234 | Q7: 38975190 | R7: 11691320 | S7: =SUM(K7:R7) -> 88023269
B8: Investments | K8: 1910404 | M8: 1064287 | N8: 249145 | P8: 10230870 | Q8: 20905077 | R8: 16561405 | S8: =SUM(K8:R8) -> 50921188
B9: Receivables (net, where applicable of | S9: =SUM(K9:R9) -> 0
C10: allowances for uncollectibles)
C11: Taxes | K11: 303432 | L11: 590220 | N11: 490 | O11: 822420 | S11: =SUM(K11:R11) -> 1716562
C12: Accounts | K12: 483707 | L12: 20419 | M12: 132124 | O12: 2977 | S12: =SUM(K12:R12) -> 639227
C13: Other | M13: 323 | S13: =SUM(K13:R13) -> 323
C14: Economic loans | M14: 11256833 | N14: 1410 | O14: 148627 | Q14: 5772838 | R14: 3761733 | S14: =SUM(K14:R14) -> 20941441
B15: Due from other funds | K15: 23372169 | L15: 583 | M15: 231591 | N15: 1080392 | O15: 7200456 | P15: 980896 | Q15: 8917601 | R15: 12326344 | S15: =SUM(K15:R15) -> 54110032
B16: Due from other governmental units | K16: 5196465 | L16: 4966595 | M16: 4786597 | S16: =SUM(K16:R16) -> 14949657
B17: Due from component units | K17: 3316 | S17: =SUM(K17:R17) -> 3316
B18: Inventories | M18: 7755 | S18: =SUM(K18:R18) -> 7755
B19: Other assets | K19: 3145 | M19: 650 | S19: =SUM(K19:R19) -> 3795
B20: Restricted assets: | S20: =SUM(K20:R20) -> 0
C21: Cash and cash equivalents | K21: 68415 | M21: 184143 | S21: =SUM(K21:R21) -> 252558
E23: Total Assets: | K23: =SUM(K7:K21) -> 48424002 | L23: =SUM(L7:L21) -> 10049457 | M23: =SUM(M7:M21) -> 22128464 | N23: =SUM(N7:N21) -> 3733404 | O23: =SUM(O7:O21) -> 14693288 | P23: =SUM(P7:P21) -> 13629000 | Q23: =SUM(Q7:Q21) -> 74570706 | R23: =SUM(R7:R21) -> 44340802 | S23: =SUM(S7:S21) -> 231569123
A25: LIABILITIES
C26: Accounts payable and accrued expenditures | K26: 843637 | L26: 349035 | M26: 1150074 | N26: 415376 | O26: 609397 | Q26: 3620884 | R26: 1190266 | S26: =SUM(K26:R26) -> 8178669
C27: Liability for work completed on contracts | K27: 1446 | M27: 3200 | O27: 26291 | Q27: 2102620 | R27: 5000 | S27: =SUM(K27:R27) -> 2138557
C28: Grant advances | M28: 11699515 | S28: =SUM(K28:R28) -> 11699515
C29: Due to other funds | K29: 30057166 | L29: 1121463 | M29: 3466664 | N29: 374681 | O29: 1613146 | P29: 4529 | Q29: 3019057 | R29: 4262545 | S29: =SUM(K29:R29) -> 43919251
C30: Due to other governmental units | K30: 578766 | L30: 213668 | M30: 126059 | N30: 19984 | O30: 27472 | Q30: 57490 | R30: 176424 | S30: =SUM(K30:R30) -> 1199863
C31: Due to component units | Q31: 1500000 | S31: =SUM(K31:R31) -> 1500000
C32: Payable from restricted assets: | S32: =SUM(K32:R32) -> 0
D33: Tenents' escrow accounts | M33: 93029 | S33: =SUM(K33:R33) -> 93029
E35: Total liabilities: | K35: =SUM(K26:K33) -> 31481015 | L35: =SUM(L26:L33) -> 1684166 | M35: =SUM(M26:M33) -> 16538541 | N35: =SUM(N26:N33) -> 810041 | O35: =SUM(O26:O33) -> 2276306 | P35: =SUM(P26:P33) -> 4529 | Q35: =SUM(Q26:Q33) -> 10300051 | R35: =SUM(R26:R33) -> 5634235 | S35: =SUM(S26:S33) -> 68728884
A37: Deferred Inflow of Resources
K38: 2537296 | L38: 4414759 | M38: 65421 | N38: 0 | O38: 6800823 | R38: 12938294 | S38: 26756593
E40: Total Deferred inflow of Resources | K40: =SUM(K38) -> 2537296 | L40: =SUM(L38) -> 4414759 | M40: =SUM(M38) -> 65421 | N40: =SUM(N38) -> 0 | O40: =SUM(O38) -> 6800823 | P40: =SUM(P38) -> 0 | Q40: =SUM(Q38) -> 0 | R40: =SUM(R38) -> 12938294 | S40: =SUM(S38) -> 26756593
B42: Fund Balances (deficit)
C43: Nonspendables:
D44: Inventories | M44: 7755 | S44: =SUM(K44:R44) -> 7755
C45: Restricted for:
D46: Dedicated emergency | K46: 2500000 | S46: =SUM(K46:R46) -> 2500000
D47: Broadmoor trees | K47: 68415 | S47: =SUM(K47:R47) -> 68415
D48: Grants | M48: 4051866 | S48: =SUM(K48:R48) -> 4051866
D49: Capital projects | Q49: 13174010 | S49: =SUM(K49:R49) -> 13174010
D50: Drainage | O50: 302292 | S50: =SUM(K50:R50) -> 302292
D51: Levee and conservation | P51: 13624471 | S51: =SUM(K51:R51) -> 13624471
D52: Debt service | R52: 14453091 | S52: =SUM(K52:R52) -> 14453091
D53: Other special purposes | R53: 11691954 | S53: =SUM(K53:R53) -> 11691954
C54: Commited for:
D55: Capital projects | Q55: 22093979 | S55: =SUM(K55:R55) -> 22093979
D56: Other special purposes | R56: 95948 | S56: =SUM(K56:R56) -> 95948
C57: Assigned for:
D58: Subsequent year's expenditures | K58: 1233088 | S58: =SUM(K58:R58) -> 1233088
D59: Dedicated emergency | K59: 187392 | S59: =SUM(K59:R59) -> 187392
D60: Non-district recreation | K60: 230824 | S60: =SUM(K60:R60) -> 230824
D61: Parish prisoners | K61: 226361 | S61: =SUM(K61:R61) -> 226361
D62: City marshall | K62: 299794 | S62: =SUM(K62:R62) -> 299794
D63: Coastal restoration | K63: 73759 | S63: =SUM(K63:R63) -> 73759
D64: Public safety | L64: 3950532 | S64: =SUM(K64:R64) -> 3950532
D65: Capital projects | Q65: 29002666 | S65: =SUM(K65:R65) -> 29002666
D66: Grants | M66: 1464881 | S66: =SUM(K66:R66) -> 1464881
D67: Road and bridge | N67: 2923403 | S67: =SUM(K67:R67) -> 2923403
D68: Drainage | O68: 5313867 | S68: =SUM(K68:R68) -> 5313867
D69: Other special purposes | R69: 1162957 | S69: =SUM(K69:R69) -> 1162957
C70: Unassigned | K70: 9586058 | S70: =SUM(K70:R70) -> 9586058
E72: Total fund balance: | K72: =SUM(K44:K70) -> 14405691 | L72: =SUM(L44:L70) -> 3950532 | M72: =SUM(M44:M70) -> 5524502 | N72: =SUM(N44:N70) -> 2923403 | O72: =SUM(O44:O70) -> 5616159 | P72: =SUM(P44:P70) -> 13624471 | Q72: =SUM(Q44:Q70) -> 64270655 | R72: =SUM(R44:R70) -> 27403950 | S72: =SUM(S44:S70) -> 137719363
E74: Total liabilities and fund balances: | K74: =SUM(K72+K40+K35) -> 48424002 | L74: =SUM(L72+L40+L35) -> 10049457 | M74: =SUM(M72+M40+M35) -> 22128464 | N74: =SUM(N72+N40+N35) -> 3733444 | O74: =SUM(O72+O40+O35) -> 14693288 | P74: =SUM(P72+P40+P35) -> 13629000 | Q74: =SUM(Q72+Q40+Q35) -> 74570706 | R74: =SUM(R72+R40+R35) -> 45976479 | S74: =SUM(S72+S40+S35) -> 233204840

Sheet Union
D1: Union Combined Balance Sheet
D2: Issued: December 31, 2015
K4: General | L4: Road Maintenance | M4: Road Construction | N4: Sales Tax Landfill | O4: Detention Center | P4: Other Governmental Funds | Q4: Total Governmental Funds
A5: Assets:
B6: Cash and cash equivalents | K6: 853141 | L6: 375037 | M6: 1253408 | N6: 3435114 | O6: 500 | P6: 1994931 | Q6: =SUM(K6:P6) -> 7912131
B7: Investments | K7: 499573 | L7: 152478 | M7: 291236 | N7: 6046797 | O7: 38021 | P7: 585036 | Q7: =SUM(K7:P7) -> 7613141
B8: Receivables | K8: 962474 | L8: 1035750 | M8: 850592 | N8: 440908 | O8: 157772 | P8: 604924 | Q8: =SUM(K8:P8) -> 4052420
E10: Total assets: | K10: =SUM(K6:K8) -> 2315188 | L10: =SUM(L6:L8) -> 1563265 | M10: =SUM(M6:M8) -> 2395236 | N10: =SUM(N6:N8) -> 9922819 | O10: =SUM(O6:O8) -> 196293 | P10: =SUM(P6:P8) -> 3184891 | Q10: =SUM(Q6:Q8) -> 19577692
A12: LIABILITIES, DEFERRED INFLOWS AND FUND EQUITY
B13: Liabilities:
C14: Cash overdraft | O14: 947080 | Q14: =SUM(K14:P14) -> 947080
C15: Accounts payable | K15: 217894 | L15: 53279 | M15: 27811 | N15: 11052 | O15: 87736 | P15: 87488 | Q15: =SUM(K15:P15) -> 485260
C16: Salaries and related payables | K16: 128420 | L16: 19742 | N16: 12810 | P16: 23233 | Q16: =SUM(K16:P16) -> 184205
C17: Deposits due others | L17: 385020 | Q17: =SUM(K17:P17) -> 385020
E19: Total liabilities: | K19: =SUM(K14:K17) -> 346314 | L19: =SUM(L14:L17) -> 458041 | M19: =SUM(M14:M17) -> 27811 | N19: =SUM(N14:N17) -> 23862 | O19: =SUM(O14:O17) -> 1034816 | P19: =SUM(P14:P17) -> 110721 | Q19: =SUM(Q14:Q17) -> 2001565
A21: Deferred Inflows:
B22: Grant revenues pending | P22: 14194 | Q22: =SUM(K22:P22) -> 14194
B24: Fund equity- fund balances
C25: Restricted | K25: 708019 | L25: 1105224 | M25: 2367425 | N25: 9898957 | O25: -838523 | P25: 3059976 | Q25: =SUM(K25:P25) -> 16301078
C26: Unassigned | K26: 1260855 | Q26: =SUM(K26:P26) -> 1260855
E28: Total fund equity- fund balances: | K28: =SUM(K25:K26) -> 1968874 | L28: =SUM(L25:L26) -> 1105224 | M28: =SUM(M25:M26) -> 2367425 | N28: =SUM(N25:N26) -> 9898957 | O28: =SUM(O25:O26) -> -838523 | P28: =SUM(P25:P26) -> 3059976 | Q28: =SUM(Q25:Q26) -> 17561933
E30: Total liabilities, deferred inflows, and fund equity: | K30: =K28+K22+K19 -> 2315188 | L30: =L28+L22+L19 -> 1563265 | M30: =M28+M22+M19 -> 2395236 | N30: =N28+N22+N19 -> 9922819 | O30: =O28+O22+O19 -> 196293 | P30: =P28+P22+P19 -> 3184891 | Q30: =Q28+Q22+Q19 -> 19577692

Sheet Vermillion
D1: Vermillion Combined Balance Sheet
D2: Issued: December 31, 2013 | E2: Issued December 31, 2015
K5: General | L5: 1976 Sales Tax Fund | M5: 1978 Sales Tax Fund | N5: 1994 Sales Tax Fund | O5: Royalty Road Fund | P5: Parishwide Public Improvement Maintenance Fund | Q5: Project Account Fund | R5: Other Governmental Funds | S5: Total (Memorandum Only)
A6: Assets:
B7: Cash and interest-bearing deposits | K7: 1105751 | L7: 9278922 | M7: 11945070 | N7: 15461701 | O7: 10541846 | P7: 178461 | Q7: 42636 | R7: 8555534 | S7: =SUM(K7:R7) -> 57109921
B8: Accounts receivable | N8: 37318 | R8: 79082 | S8: =SUM(K8:R8) -> 116400
B9: Ad valorem tax receivable, net | K9: 101892 | P9: 86222 | R9: 283294 | S9: =SUM(K9:R9) -> 471408
B10: Accrued interest receivable | L10: 6911 | M10: 10228 | N10: 14722 | O10: 7419 | R10: 1149 | S10: =SUM(K10:R10) -> 40429
B11: Due from other funds | K11: 680283 | M11: 18841 | O11: 89609 | P11: 41301 | S11: =SUM(K11:R11) -> 830034
B12: Due from component unit | K12: 111 | O12: 519 | S12: =SUM(K12:R12) -> 630
B13: Due from other governmental units | K13: 1217510 | L13: 601768 | M13: 601768 | N13: 605717 | O13: 156590 | P13: 1072188 | Q13: 32446 | R13: 3048200 | S13: =SUM(K13:R13) -> 7336187
B14: Other receivables | K14: 48628 | S14: =SUM(K14:R14) -> 48628
B15: Prepaid expenses | L15: 1345 | N15: 5516 | O15: 10776 | P15: 12419 | R15: 502 | S15: =SUM(K15:R15) -> 30558
E17: Total Assets: | K17: =SUM(K7:K15) -> 3154175 | L17: =SUM(L7:L15) -> 9888946 | M17: =SUM(M7:M15) -> 12575907 | N17: =SUM(N7:N15) -> 16124974 | O17: =SUM(O7:O15) -> 10806759 | P17: =SUM(P7:P15) -> 1390591 | Q17: =SUM(Q7:Q15) -> 75082 | R17: =SUM(R7:R15) -> 11967761 | S17: =SUM(S7:S15) -> 65984195
A19: LIABILITIES, DEFERRED INFLOWS OF RESOURCES, AND FUND BALANCES
B20: Liabilities:
C21: Accounts payable | K21: 137429 | L21: 50374 | M21: 4840 | N21: 277872 | O21: 16429 | P21: 65694 | Q21: 5330 | R21: 116404 | S21: =SUM(K21:R21) -> 674372
C22: Contracts payable | L22: 20776 | O22: 31265 | Q22: 3000 | R22: 185987 | S22: =SUM(K22:R22) -> 241028
C23: Retainage payable | O23: 3474 | Q23: 32446 | R23: 57740 | S23: =SUM(K23:R23) -> 93660
C24: Accrued liabilities | K24: 9889 | L24: 4549 | M24: 1788 | N24: 20415 | P24: 30056 | R24: 33109 | S24: =SUM(K24:R24) -> 99806
C25: Due to other funds | K25: 121369 | L25: 3499 | M25: 852 | N25: 67787 | P25: 37299 | Q25: 500287 | R25: 98941 | S25: =SUM(K25:R25) -> 830034
C26: Other liabilities | K26: 220899 | S26: =SUM(K26:R26) -> 220899
E28: Total liabilities: | K28: =SUM(K21:K26) -> 489586 | L28: =SUM(L21:L26) -> 79198 | M28: =SUM(M21:M26) -> 7480 | N28: =SUM(N21:N26) -> 366074 | O28: =SUM(O21:O26) -> 51168 | P28: =SUM(P21:P26) -> 133049 | Q28: =SUM(Q21:Q26) -> 541063 | R28: =SUM(R21:R26) -> 492181 | S28: =SUM(S21:S26) -> 2159799 | T28: =SUM(T18:T25) -> 0 | U28: =SUM(U18:U25) -> 0 | V28: =SUM(V18:V26) -> 0
A30: DEFERRED INFLOWS OF RESROUCES
C31: Deferred revenue | K31: 246995 | N31: 13271 | P31: 98375 | Q31: 40742 | R31: 319862 | S31: =SUM(K31:R31) -> 719245
B33: Fund Balances
C34: Nonspendable | L34: 1345 | N34: 5516 | O34: 10776 | P34: 12419 | R34: 502 | S34: =SUM(K34:R34) -> 30558
C35: Restricted | L35: 9808403 | M35: 12568427 | N35: 15740113 | O35: 10744815 | P35: 1146748 | R35: 11155216 | S35: =SUM(K35:R35) -> 61163722
C36: Assigned | K36: 52783 | S36: =SUM(K36:R36) -> 52783
C37: Unassigned | K37: 2364811 | Q37: -506723 | S37: =SUM(K37:R37) -> 1858088
E39: Total fund balances: | K39: =SUM(K34:K37) -> 2417594 | L39: =SUM(L34:L37) -> 9809748 | M39: =SUM(M34:M37) -> 12568427 | N39: =SUM(N34:N37) -> 15745629 | O39: =SUM(O34:O37) -> 10755591 | P39: =SUM(P34:P37) -> 1159167 | Q39: =SUM(Q34:Q37) -> -506723 | R39: =SUM(R34:R37) -> 11155718 | S39: =SUM(S34:S37) -> 63105151 | T39: =SUM(T20:T37) -> 0 | U39: =SUM(U20:U37) -> 0 | V39: =SUM(V20:V37) -> 0
E41: Total liabilities, deferred inflows of resources, and fund balances: | K41: =SUM(K39+K31+K28) -> 3154175 | L41: =SUM(L39+L28) -> 9888946 | M41: =SUM(M39+M28) -> 12575907 | N41: =SUM(N39+N28+N31) -> 16124974 | O41: =SUM(O39+O31+O28) -> 10806759 | P41: =SUM(P39+P28+P31) -> 1390591 | Q41: =SUM(Q39+Q28+Q31) -> 75082 | R41: =SUM(R39+R28+R31) -> 11967761 | S41: =SUM(S39+S31+S28) -> 65984195

Sheet Vernon
D1: Vernon Combined Balance Sheet
D2: Issued: December 31, 2015
