Workbook

Sheet Acadia
D1: Acadia Parish 2015 Statement of Net Assets
D2: Issued: December 31, 2015
H4: Primary Government
H5: Governmental Activities | I5: Component Unit
A6: ASSETS
B7: Current Assets
C8: Cash and cash equivalents | H8: 9195544 | I8: 79400
C9: Investments | H9: 7939036
C10: Taxes receivable | H10: 6542496
C11: Special assessments receivable | H11: 16996
C12: Other receivables | H12: 10094
C13: Due from other governmental entities | H13: 550460
C14: Due from component units | H14: 20177
C15: Capital assets:
D16: Non-depreciable | H16: 1704568
D17: Depreciable, net | H17: 50254249
C19: Total Assets | H19: =SUM(H8:H17) -> 76233620 | I19: =SUM(I8:I17) -> 79400
A21: DEFERRED OUTFLOWS OF RESOURCES
C22: Deferred loss on refunding | H22: 9122
C23: Pension related | H23: 656278 | I23: 105698
D24: Total deferred outflows | H24: =SUM(H22:H23) -> 665400 | I24: =SUM(I22:I23) -> 105698
A27: LIABILITIES
C28: Accounts payable | H28: 1295353 | I28: 9083
C29: Retainage payable
C30: Accrued liabilities and other payables | H30: 650540
C31: Unearned revenue | H31: 62997
C32: Accrued interest payable | H32: 57734
C33: Due to primary government | I33: 20177
C34: Long-term liabilities:
D35: Portion due or payable within one year:
E36: Bonds payable | H36: 1587435
E37: Compensated absences | H37: 176145
D38: Portion due or payable after one year:
E39: Bonds payable | H39: 9865913
E40: Compensated absences | H40: 158899
E41: Net pension liability | H41: 411100 | I41: 23082
E42: Landfill closure and postclosure care costs liability | H42: 5054233
D44: Total Liabilities | H44: =SUM(H28:H42) -> 19320349 | I44: =SUM(I28:I42) -> 52342
A46: DEFERRED INFLOWS OF RESOURCES
C47: Pension related | H47: 178983 | I47: 19678
D48: Total deferred inflows | H48: =H47 -> 178983 | I48: =I47 -> 19678
A50: NET ASSETS
B51: Net investment in capital assets | H51: 40505469
B52: Restricted for:
C53: Debt service | H53: 1669655
C54: Capital projects | H54: 11456448
C55: Other purposes | H55: 4276100
B56: Unrestricted | H56: -507984 | I56: 113078
C58: Total Net Assets | H58: =SUM(H51:H56) -> 57399688 | I58: =SUM(I50:I56) -> 113078
C60: Total Liabilities and Net Assets | H60: =H58+H47+H44 -> 76899020 | I60: =I58+I47+I44 -> 185098

Sheet Allen
C1: Allen Parish 2015 Statement of Net Assets
C2: Issued: December 31, 2015
G4: Governmental Activities
A5: ASSETS
B6: Cash | G6: 4069562
B7: Receivables | G7: 2833111
B8: Due from other governments | G8: 762395
B9: Inventory | G9: 45179
B10: Prepaid assets | G10: 7432
B11: Capital assets, net of accumulated depreciation | G11: 23777069
B13: Total Assets | G13: =SUM(G6:G11) -> 31494748
A15: DEFERRED OUTFLOWS OF RESOURCES RELATED TO PENSIONS | G15: 276783
B16: Total assets and deferred outflows | G16: =SUM(G15+G13) -> 31771531
A18: LIABILITIES
B19: Accounts payable | G19: 824559
B20: Accrued interest payable | G20: 5628
B21: Unearned revenue | G21: 48703
B22: Bonds payable - due within one year | G22: 254000
B23: Compensated absences payable-
C24: due within one year | G24: 29759
B25: OPEB obligations - due in more
C26: than one year | G26: 1311282
B27: Pension liability- due in more than one year | G27: 54246
B28: Bonds payable - due in more than one year | G28: 1394000
C30: Total Liabilities | G30: =SUM(G19:G28) -> 3922177
A32: DEFERRED INFLOWS OF RESOURCES RELATED TO PENSIONS | G32: 24855
A34: NET ASSETS
B35: Net Investmend in capital assets | G35: 22129069
B36: Restricted for:
C37: Inventory | G37: 45179
C38: Judicial | G38: 611041
C39: Other general government | G39: 634469
C40: Public works | G40: 3501405
C41: Sanitation | G41: 479982
C42: Capital projects | G42: 390551
C43: Debt service | G43: 53723
B44: Unrestricted | G44: -20920
B46: Total Net Assets | G46: =SUM(G35:G44) -> 27824499
B48: Total Liabilities, deferred inflows, and Net Assets | G48: =SUM(G30+G46+G32) -> 31771531

Sheet Ascension
D1: Ascension Parish 2015 Statement of Net Assets
D2: Issued: December 31, 2015
I4: Primary Government | L4: Component Unit
I5: Governmental Activities | J5: Business-type Activities | K5: Total | L5: Governmental Activities | M5: Business-type Activities
A6: ASSETS
B7: Current Assets
C8: Cash and cash equivalents | I8: 32250738 | J8: 3967892 | K8: =SUM(I8:J8) -> 36218630 | L8: 32916630 | M8: 1196210
C9: Investments | I9: 135507608 | J9: 10561966 | K9: =SUM(I9:J9) -> 146069574 | L9: 5694111 | M9: 14060003
C10: Accounts receivable, net | I10: 35732327 | J10: 257762 | K10: =SUM(I10:J10) -> 35990089 | L10: 4072629 | M10: 1536049
C11: Due from other governments | I11: 5417238 | J11: 51244 | K11: =SUM(I11:J11) -> 5468482 | L11: 2280280
C12: Internal balances | I12: 5 | J12: -5 | K12: =SUM(I12:J12) -> 0
C13: Prepaid and other assets | I13: 251833 | J13: 250281 | K13: =SUM(I13:J13) -> 502114 | L13: 207600 | M13: 146137
C14: Inventory | J14: 25935 | K14: 25935 | M14: 206469
C15: Restricted assets | J15: 37019 | K15: =SUM(I15:J15) -> 37019 | L15: 718443 | M15: 597235
C16: Capital assets:
D17: Nondepreciable | I17: 46116046 | J17: 1655313 | K17: =SUM(I17:J17) -> 47771359 | L17: 3500494 | M17: 110902
D18: Depreciable, net | I18: 181199117 | J18: 9634710 | K18: =SUM(I18:J18) -> 190833827 | L18: 12535508 | M18: 11104401
C20: Total Assets | I20: =SUM(I8:I18) -> 436474912 | J20: =SUM(J8:J18) -> 26442117 | K20: =SUM(K8:K18) -> 462917029 | L20: =SUM(L8:L18) -> 61925695 | M20: =SUM(M7:M18) -> 28957406
A22: Deferred Outflows of Resources
B23: Pension liability | I23: 3835629 | J23: 75110 | K23: =SUM(I23:J23) -> 3910739 | L23: 4763789 | M23: 27020
B24: Deferred loss on debt refunding | I24: 6506451 | J24: 0 | K24: 6506451 | L24: 0 | M24: 0
C26: Total deferred outflows of resources | I26: =SUM(I23:I24) -> 10342080 | J26: =SUM(J23:J24) -> 75110 | K26: =SUM(K23:K24) -> 10417190 | L26: =SUM(L23:L24) -> 4763789 | M26: =SUM(M23:M24) -> 27020
C28: Total assets and deferred outflows of resources | I28: =I26+I20 -> 446816992 | J28: =J26+J20 -> 26517227 | K28: =K26+K20 -> 473334219 | L28: =L26+L20 -> 66689484 | M28: =M26+M20 -> 28984426
A30: LIABILITIES
C31: Accounts payable and accrued liabilities | I31: 3140132 | J31: 733139 | K31: =SUM(I31:J31) -> 3873271 | L31: 2037934 | M31: 606412
C32: Contracts payable | I32: 5106697 | K32: =SUM(I32:J32) -> 5106697
C33: Due to other governments | I33: 472207 | K33: =SUM(I33:J33) -> 472207 | L33: 934476
C34: Accrued payroll | I34: 736585 | J34: 31614 | K34: =SUM(I34:J34) -> 768199
C35: Customer deposits | J35: 37019 | K35: =SUM(I35:J35) -> 37019 | M35: 45946
C36: Sales tax rebate reserve | I36: 4759700 | K36: =SUM(I36:J36) -> 4759700
C37: Unearned revenue | I37: 414404 | J37: 42364 | K37: =SUM(I37:J37) -> 456768
C38: Claims reserve | K38: =SUM(I38:J38) -> 0
D39: Due within one year | I39: 354297 | K39: =SUM(I39:J39) -> 354297
D40: Due in more than one year | I40: 904237 | K40: =SUM(I40:J40) -> 904237
C41: Long-term payable | K41: =SUM(I41:J41) -> 0
D42: Due within one year | I42: 5546774 | K42: =SUM(I42:J42) -> 5546774 | L42: 601691 | M42: 182363
D43: Due within more than one year | I43: 77209825 | K43: =SUM(I43:J43) -> 77209825 | L43: 2680740 | M43: 4394107
D44: Other post-employment benefits | I44: 659115 | K44: =SUM(I44:J44) -> 659115 | L44: 7147074
D45: Net pension liability | I45: 3360215 | J45: 1607 | K45: =SUM(I45:J45) -> 3361822 | L45: 14902076 | M45: 578
D47: Total Liabilities | I47: =SUM(I31:I45) -> 102664188 | J47: =SUM(J31:J45) -> 845743 | K47: =SUM(K31:K45) -> 103509931 | L47: =SUM(L31:L45) -> 28303991 | M47: =SUM(M31:M45) -> 5229406
A49: Deferred Inflows of Resources
B50: Pension liability | I50: 864558 | J50: 15572 | K50: =SUM(I50:J50) -> 880130 | L50: 7535323 | M50: 5602
D52: Total deferred inflows of resources | I52: =SUM(I50:I50) -> 864558 | J52: =SUM(J50:J50) -> 15572 | K52: =SUM(K50:K50) -> 880130 | L52: =SUM(L50:L50) -> 7535323 | M52: =SUM(M50:M50) -> 5602
A54: NET POSITION
B55: Net investment in capital assets | I55: 129059066 | J55: 11290023 | K55: =SUM(I55:J55) -> 140349089 | L55: 15240788 | M55: 6638833
B56: Restricted for:
C57: Capital Projects | I57: 39274391 | K57: =SUM(I57:J57) -> 39274391
C58: Public works | I58: 42672416 | K58: =SUM(I58:J58) -> 42672416
C59: Public safety | I59: 25429449 | K59: =SUM(I59:J59) -> 25429449
C60: Health and welfare | I60: 10773016 | K60: =SUM(I60:J60) -> 10773016
C61: Culture and recreation | I61: 10732783 | K61: =SUM(I61:J61) -> 10732783
C62: Debt service | I62: 2891744 | K62: =SUM(I62:J62) -> 2891744 | M62: 551289
C63: Other Purposes | I63: 922119 | K63: =SUM(I63:J63) -> 922119 | L63: 3080526
B64: Unrestricted | I64: 81533262 | J64: 14365889 | K64: =SUM(I64:J64) -> 95899151 | L64: 12528604 | M64: 16559296
C66: Total Net Position | I66: =SUM(I55:I64) -> 343288246 | J66: =SUM(J55:J64) -> 25655912 | K66: =SUM(K55:K64) -> 368944158 | L66: =SUM(L55:L64) -> 30849918 | M66: =SUM(M55:M64) -> 23749418
C68: Total Liabilities, deferred inflows of resources, and Net Assets | I68: =SUM(I47+I66+I52) -> 446816992 | J68: =SUM(J47+J66+J52) -> 26517227 | K68: =SUM(K47+K66+K52) -> 473334219 | L68: =SUM(L47+L66+L52) -> 66689232 | M68: =SUM(M47+M66+M52) -> 28984426

Sheet Assumption
D1: Assumption Parish 2015 Statement of Net Assets
D2: Issued: December 31, 2015
H4: Primary Government | I4: Component Units
A5: ASSETS
B6: Current Assets
C7: Cash and cash equivalents | H7: 5055668 | I7: 2111958
C8: Investments | H8: 14723668 | I8: 4748511
C9: Receivables | H9: 5990950 | I9: 1476612
C10: Other assets | H10: 139035 | I10: 252635
C11: Restricted investments | I11: 3417634
C12: Net investment in capital assets | H12: 44674146 | I12: 16188968
C14: Total Assets | H14: =SUM(H7:H12) -> 70583467 | I14: =SUM(I7:I12) -> 28196318
A16: DEFERRED OUTFLOWS OF RESOURCES
B17: Pension related | H17: 546760 | I17: 473091
C18: TOTAL DEFERRED OUTFLOWS OF RESOURCES | H18: =H17 -> 546760 | I18: =I17 -> 473091
A20: LIABILITIES AND NET POSITION
B21: Liabilities
C22: Accounts payable | H22: 1677434 | I22: 87422
C23: Salaries payable | H23: 44380 | I23: 16770
C24: Compensated absences payable | H24: 165805 | I24: 29149
C25: Other post-employment benefits payable | H25: 1072694 | I25: 1854099
C26: Other liabilities | H26: 707891 | I26: 336749
C27: Long-term liabilities:
D28: Due within one year | I28: 530000
D29: Due in more than one year | I29: 4270000
D30: Net pension liability | H30: 137545 | I30: 993483
D32: Total Liabilities | H32: =SUM(H22:H30) -> 3805749 | I32: =SUM(I22:I30) -> 8117672
A34: DEFERRED INFLOWS OF RESOURCES
B35: Pension related | H35: 70848 | I35: 315637
D36: TOTAL DEFERRED INFLOWS OF RESOURCES | H36: =H35 -> 70848 | I36: =I35 -> 315637
A38: NET ASSETS
B39: Invested in capital assets, net of related debt | H39: 44674146 | I39: 11388968
B40: Restricted for revenue bond debt service and contingencies | I40: 3417553
B41: Unrestricted | H41: 22579484 | I41: 5429579
C43: Total Net Assets | H43: =SUM(H39:H41) -> 67253630 | I43: =SUM(I38:I41) -> 20236100
C45: Total Liabilities and Net Assets | H45: =SUM(H32+H43+H36) -> 71130227 | I45: =SUM(I32+I43+I36) -> 28669409

Sheet Avoyelles
D1: Avoyelles Parish 2015 Statement of Net Assets
D2: Issued: December 31, 2015
H4: Primary Government
A5: ASSETS
B6: Current Assets
C7: Cash and interest-bearing deposits | H7: 10522207
C8: Receivables, net | H8: 33789
C9: Due from other governmental units | H9: 2575929
C10: Prepaid items | H10: 108830
C11: Land and contruction in progress | H11: 1775946
C12: Capital assets, net | H12: 4318512
C14: Total Assets | H14: =SUM(H7:H12) -> 19335213
B16: Deferred outflows of resources related to pensions | H16: 192033
A18: LIABILITIES
C19: Accounts, salaries and other payables | H19: 689137
C20: Unearned revenue | H20: 36260
C21: Due to other governmental units | H21: 66004
C22: Long-term liabilities:
D23: Portion due within one year | H23: 30149
D24: Portion due after one year | H24: 64772
C25: Net pension liability | H25: 79068
D27: Total Liabilities | H27: =SUM(H19:H25) -> 965390
B29: Deferred inflows of resources related to pensions | H29: 51851
A31: NET ASSETS
B32: Net investment in capital assets | H32: 6094458
B33: Unrestricted | H33: 12415547
C35: Total Net Assets | H35: =SUM(H32:H33) -> 18510005
C37: Total Liabilities and Net Assets | H37: =H35+H27 -> 19475395

Sheet Beauregard
C1: Beauregard Parish 2015 Statement of Net Assets
C2: Issued: December 31, 2015
G4: Governmental Activities
A5: ASSETS
B6: Cash and cash equivalents | G6: 25520552
B7: Receivables | G7: 6425452
B8: Inventory | G8: 334682
B9: Prepaid expenses | G9: 226353
B10: Capital assets (net of accumulated depreciation):
C11: Land | G11: 698779
C12: Buildings and improvements | G12: 11668437
C13: Furniture and equipment | G13: 3697372
C14: Infrastructure | G14: 14276186
C15: Construction in progress | G15: 5640233
B17: Total Assets | G17: =SUM(G6:G15) -> 68488046
A19: Deferred Outflows of Resources
B20: Pension-related deferrals | G20: 587818
A22: LIABILITIES
B23: Accounts, salaries, and other payables | G23: 1531644
B24: Interest payable | G24: 33384
B25: Net pension liability | G25: 148204
B26: Long-term liabilities:
C27: Due within one year | G27: 1256668
C28: Due in more than one year | G28: 13691999
C30: Total Liabilities | G30: =SUM(G23:G28) -> 16661899
A32: Deferred Inflows of Resources
B33: Pension-related deferrals | G33: 99372
A35: NET ASSETS
B36: Invested in capital assets, net of related debt | G36: 21141007
B37: Restricted for:
C38: Inventory | G38: 334682
C39: Equipment purchases | G39: 744819
C40: Public safety | G40: 1932609
C41: Public works | G41: 5856335
C42: Health and welfare | G42: 2576641
C43: Culture and recreation | G43: 865917
C44: Sanitation | G44: 5074980
C45: Other general government | G45: 325299
C46: Capital projects | G46: 11558772
C47: Debt service | G47: 166333
B48: Unrestricted | G48: 1737199
B50: Total Net Assets | G50: =SUM(G36:G48) -> 52314593
B52: Total Liabilities and Net Assets | G52: =SUM(G30+G50) -> 68976492

Sheet Bienville
C1: Bienville Parish 2015 Statement of Net Assets
C2: Issued: December 31, 2015
G4: Governmental Activities
A5: ASSETS
B6: Cash and cash equivalents | G6: 16858491
B7: Receivables | G7: 4654602
B8: Capital assets, net | G8: 22261869
B10: Total Assets | G10: =SUM(G6:G8) -> 43774962
A12: Deferred Outflow of Resources
B13: Pension related | G13: 134448
B14: Total Assets and Deferred Outflow of Resources | G14: =G13 -> 134448
A16: LIABILITIES
B17: Accounts payable | G17: 216581
B18: Wages and related payable | G18: 33526
B19: Interest payable | G19: 130263
B20: Bonds payable | G20: 9895000
B21: Premium on bonds | G21: 259109
B22: Deferred revenues | G22: 70000
B23: Compensated absences payable | G23: 87473
B24: Net pensioni liability | G24: 186811
B25: Net OPEB obligation | G25: 1756770
C27: Total Liabilities | G27: =SUM(G17:G25) -> 12635533
A29: Deferred Inflows of Resources
B30: Pension related | G30: 46967
A32: NET ASSETS
B33: Invested in capital assets, net of related debt | G33: 12366869
B34: Unrestricted | G34: 18860041
B36: Total Net Assets | G36: =SUM(G33:G34) -> 31226910
B38: Total Liabilities and Net Assets | G38: =SUM(G27+G36+G30) -> 43909410

Sheet Bossier
D1: Bossier Parish 2015 Statement of Net Assets
D2: Issued: December 31, 2015
H5: Governmental Activities | I5: Business-Type Activities | J5: Total
A6: ASSETS
C7: Cash and cash equivalents | H7: 41742235 | J7: =SUM(H7:I7) -> 41742235
C8: Restricted cash | H8: 4378132 | I8: 1257137 | J8: =SUM(H8:I8) -> 5635269
C9: Investments | H9: 2525000 | J9: =SUM(H9:I9) -> 2525000
C10: Restricted Investments | H10: 11092426 | J10: =SUM(H10:I10) -> 11092426
C11: Receivables | H11: 18410937 | I11: 308664 | J11: =SUM(H11:I11) -> 18719601
C12: Prepaid expenses | H12: 922640 | I12: 116888 | J12: =SUM(H12:I12) -> 1039528
C13: Capital assets, net: | J13: =SUM(H13:I13) -> 0
D14: Non-depreciable | H14: 21139166 | I14: 36078080 | J14: =SUM(H14:I14) -> 57217246
D15: Depreciable (net) | H15: 266323459 | I15: 4557975 | J15: =SUM(H15:I15) -> 270881434
C16: Internal balances | H16: 8176744 | I16: -8176744 | J16: =SUM(H16:I16) -> 0
C18: Total Assets | H18: =SUM(H7:H16) -> 374710739 | I18: =SUM(I7:I16) -> 34142000 | J18: =SUM(J7:J16) -> 408852739
A20: Deferred Outflows of Resources
C21: Pension related | H21: 2017962 | I21: 62411 | J21: =SUM(H21:I21) -> 2080373
A23: LIABILITIES
B24: Current
C25: Accounts payable and accrued expenses | H25: 3040969 | I25: 1147352 | J25: =SUM(H25:I25) -> 4188321
C26: Payable from restricted assets:
D27: Customer deposits | I27: 125647 | J27: =SUM(H27:I27) -> 125647
B28: Noncurrent liabilities
C29: Due within one year | H29: 4779068 | I29: 492000 | J29: 5271068
C30: Due in more than one year | H30: 65724929 | I30: 17765150 | J30: =SUM(H30:I30) -> 83490079
D32: Total Liabilities | H32: =SUM(H25+H27+H29+H30) -> 73544966 | I32: =SUM(I25+I27+I29+I30) -> 19530149 | J32: =SUM(J25+J27+J29+J30) -> 93075115
A34: Deferred Inflows of Resouces
C35: Unavailable revenue
E36: Property taxes | H36: 15056302 | J36: =SUM(H36:I36) -> 15056302
D37: Pension related | H37: 173586 | I37: 5369 | J37: =SUM(H37:I37) -> 178955
C38: Total Deferred Inflows of Resources | H38: =SUM(H36:H37) -> 15229888 | I38: =SUM(I36:I37) -> 5369 | J38: =SUM(H38:I38) -> 15235257
A40: NET ASSETS
B41: Net investment in capital assets | H41: 241133940 | I41: 14213969 | J41: =SUM(H41:I41) -> 255347909
B42: Restricted for:
C43: Capital projects | H43: 10311163 | J43: =SUM(H43:I43) -> 10311163
C44: Public works | H44: 743268 | J44: =SUM(H44:I44) -> 743268
C45: Public safety | H45: 1228154 | J45: =SUM(H45:I45) -> 1228154
C46: Economic development | H46: 37213 | J46: =SUM(H46) -> 37213
C47: Culture and recreation | H47: 6758072 | J47: =SUM(H47) -> 6758072
C48: Debt service | H48: 1722767 | J48: =SUM(H48) -> 1722767
C49: Health and welfare | H49: 2300039 | J49: =SUM(H49) -> 2300039
C50: Sewer operations | H50: 508358 | J50: =SUM(H50:I50) -> 508358
B51: Unrestricted | H51: 23210873 | I51: 454924 | J51: =SUM(H51:I51) -> 23665797
C53: Total Net Assets | H53: =SUM(H41:H51) -> 287953847 | I53: =SUM(I41:I51) -> 14668893 | J53: =SUM(J41:J51) -> 302622740
C55: Total Liabilities and Net Assets | H55: =SUM(H53+H32+H38) -> 376728701 | I55: =SUM(I53+I32+I38) -> 34204411 | J55: =SUM(J53+J32+J38) -> 410933112

Sheet Caddo
D1: Caddo Parish 2015 Statement of Net Assets
D2: Issued: December 31, 2015
H5: Primary government | I5: Component Units
A6: ASSETS
C7: Cash and cash equivalents | H7: 5950999 | I7: 15245486
C8: Investments | H8: 124633857 | I8: 5095867
C9: Receivables, net | H9: 44347039 | I9: 16115808
C10: Due from other governments | H10: 2274558 | I10: 817834
C11: Due from primary government | I11: 692410
C12: Inventories | H12: 115369 | I12: 450463
C13: Other assets | H13: 19512 | I13: 9942089
C14: Capital assets:
D15: Land and construction in progress | H15: 9700709 | I15: 1603135
D16: Other capital assets, net of depreciation | H16: 151921031 | I16: 50887863
C18: Total Assets | H18: =SUM(H7:H16) -> 338963074 | I18: =SUM(I7:I16) -> 100850955
A20: DEFERRED OUTFLOWS OF RESOURCES
C21: Deferred outflows related to pensions | H21: 3279211 | I21: 6079574
C22: Deferred loss on refunding bonds, net | H22: 73334 | I22: 139786
E24: Total assets and deferred outlfows of resources | H24: =H21+H18 -> 342242285 | I24: =I21+I18 -> 106930529
A26: LIABILITIES
C27: Accounts payable | H27: 2998886 | I27: 4389663
C28: Accrued liabilities | H28: 223000 | I28: 1523876
C29: Accrued interest payable | H29: 453794 | I29: 19447
C30: Retainage payable | H30: 405543
C31: Accrued insurance claims payable | H31: 1214564 | I31: 334504
C32: Due to component units | H32: 893500
C33: Due to other governmental agencies | H33: 282960 | I33: 113287
C34: Unearned revenue | H34: 34466 | I34: 53585
C35: Noncurrent liabilities:
D36: Due within one year | H36: 3181419 | I36: 3595406
D37: Due in more than one year | H37: 34939843 | I37: 25755110
C38: Net pension liability | H38: 622014 | I38: 20794724
C39: Net other post-employment benefit obligation | H39: 4436978 | I39: 12583599
D41: Total Liabilities | H41: =SUM(H27:H39) -> 49686967 | I41: =SUM(I27:I39) -> 69163201
A43: Deferred inflows of Resources
C44: Unavailable revenue- property taxes and assessments- service charges | I44: 2156050
C45: Deferred gain on refunding bonds, net | H45: 190000
C46: Deferred inflows related to pensions | H46: 300293 | I46: 7176874
D48: Total deferred inflows of resources | H48: =SUM(H44:H46) -> 490293 | I48: =SUM(I44:I46) -> 9332924
A50: NET ASSETS
B51: Net investment in capital assets | H51: 135822820 | I51: 25973741
B52: Restricted for:
C53: Criminal justice | H53: 15647979
C54: Health and welfare | H54: 5061413
C55: Highways, streets and drainage | H55: 30895016
C56: Building facilities | H56: 10254430
C57: Sanitation | H57: 23026737
C58: Culture and recreation | H58: 3893020
C59: Economic development | H59: 603291 | I59: 6875000
C60: Debt service | H60: 3176805 | I60: 1904900
C61: Capital outlay | I61: 2289574
B62: Unrestricted | H62: 63756848 | I62: -8469025
C64: Total Net Assets | H64: =SUM(H51:H62) -> 292138359 | I64: =SUM(I51:I62) -> 28574190
C66: Total Liabilities and Net Assets | H66: =SUM(H41+H64+H48) -> 342315619 | I66: =SUM(I41+I64+I48) -> 107070315

Sheet Calcasieu
D1: Calcasieu Parish 2015 Statement of Net Assets
D2: Issued: December 31, 2015
H4: Primary Government
H5: Governmental Activities | I5: Business-Type Activities | J5: Total | K5: Component Unit
A6: ASSETS
C7: Cash and cash equivalents | H7: 47833925 | I7: 323060 | J7: =SUM(H7:I7) -> 48156985 | K7: 43385785
C8: Investments | H8: 254012189 | I8: 1534237 | J8: =SUM(H8:I8) -> 255546426 | K8: 50541626
C9: Receivables (net of allowance for uncollectibles) | H9: 62053802 | I9: 550844 | J9: =SUM(H9:I9) -> 62604646 | K9: 79442776
C10: Intergovernmental receivable | H10: 2771729 | I10: 33551 | J10: =SUM(H10:I10) -> 2805280 | K10: 1283024
C11: Internal balances | H11: 4408 | I11: -4408 | J11: =SUM(H11:I11) -> 0
C12: Due from primary government | J12: =SUM(H12:I12) -> 0 | K12: 60846
C13: Loan receivable | H13: 25764 | J13: =SUM(H13:I13) -> 25764
C14: Prepaid items | H14: 488700 | I14: 26741 | J14: =SUM(H14:I14) -> 515441 | K14: 2012295
C15: Inventory | H15: 998047 | J15: =SUM(H15:I15) -> 998047 | K15: 1939692
C16: Other assets | I16: 320 | J16: =SUM(H16:I16) -> 320 | K16: 1041703
C17: Restricted assets: | J17: =SUM(H17:I17) -> 0
D18: Cash and cash equivalents | I18: 11882 | J18: =SUM(H18:I18) -> 11882 | K18: 4435646
D19: Investments | I19: 288173 | J19: =SUM(H19:I19) -> 288173 | K19: 7590803
D20: Receivables - net | I20: 153051 | J20: =SUM(H20:I20) -> 153051 | K20: 2713172
C21: Capital assets: | J21: =SUM(H21:I21) -> 0
D22: Non-depreciable | H22: 427965041 | I22: 227920 | J22: =SUM(H22:I22) -> 428192961 | K22: 42292522
D23: Depreciable, net | H23: 102872425 | I23: 9680095 | J23: =SUM(H23:I23) -> 112552520 | K23: 215355582
C25: Total Assets | H25: =SUM(H7:H23) -> 899026030 | I25: =SUM(I7:I23) -> 12825466 | J25: =SUM(J7:J23) -> 911851496 | K25: =SUM(K7:K23) -> 452095472
A27: DEFERRED OUTFLOWS OF RESOURCES
C28: Deferred amount on refunding | J28: =SUM(H28:I28) -> 0 | K28: 59374
C29: Deferred outflows- other | J29: =SUM(H29:I29) -> 0 | K29: 10668000
C30: Pension related deferred inflows of resources | H30: 5963331 | J30: =SUM(H30:I30) -> 5963331 | K30: 10209540
C31: Total deferred inflows of resouces | H31: =SUM(H28:H30) -> 5963331 | I31: =SUM(I28:I30) -> 0 | J31: =SUM(J28:J30) -> 5963331 | K31: =SUM(K28:K30) -> 20936914
A33: LIABILITIES
C34: Accounts payable and other accrued liabilities | H34: 8118541 | I34: 188157 | J34: =SUM(H34:I34) -> 8306698 | K34: 11455655
C35: Intergovernmental payable | H35: 4132661 | J35: =SUM(H35:I35) -> 4132661 | K35: 10064354
C36: Due to component units | H36: 60846 | J36: =SUM(H36:I36) -> 60846
C37: Unearned revenue | H37: 3382097 | J37: =SUM(H37:I37) -> 3382097 | K37: 1600562
C38: Other liabilities | H38: 172537 | J38: =SUM(H38:I38) -> 172537 | K38: 327849
C39: Liabilities payable from restricted assets | I39: 169443 | J39: =SUM(H39:I39) -> 169443 | K39: 894726
C40: Noncurrent liabilities: | J40: =SUM(H40:I40) -> 0
D41: Due within one year | H41: 2926865 | I41: 42456 | J41: =SUM(H41:I41) -> 2969321 | K41: 10956289
D42: Due in more than one year | H42: 9767208 | I42: 232004 | J42: =SUM(H42:I42) -> 9999212 | K42: 62595999
D44: Total Liabilities | H44: =SUM(H34:H42) -> 28560755 | I44: =SUM(I34:I42) -> 632060 | J44: =SUM(J34:J42) -> 29192815 | K44: =SUM(K34:K42) -> 97895434
A46: DEFERRED INFLOWS OF RESOURCES
C47: Property taxes levied for the next fiscal year | H47: 49819728 | J47: =SUM(H47:I47) -> 49819728 | K47: 23589626
C48: Deffered inflows- other | H48: 238778 | J48: =SUM(H48:I48) -> 238778
C49: Pension related deferred inflows of resources | H49: 549550 | J49: =SUM(H49:I49) -> 549550 | K49: 1362378
D50: Total deferred inflows of resources | H50: =SUM(H47:H49) -> 50608056 | I50: =SUM(I47:I49) -> 0 | J50: =SUM(J47:J49) -> 50608056 | K50: =SUM(K47:K49) -> 24952004
A53: NET ASSETS
B54: Net investment in capital assets | H54: 530837466 | I54: 9633555 | J54: =SUM(H54:I54) -> 540471021 | K54: 217056007
B55: Restricted for:
C56: Debt service | I56: 287228 | J56: =SUM(H56:I56) -> 287228 | K56: 2496680
C57: External legal constraints | H57: 122479766 | J57: =SUM(H57:I57) -> 122479766
C58: Capital improvement projects | H58: 86351450 | J58: =SUM(H58:I58) -> 86351450 | K58: 5438246
B59: Unrestricted | H59: 86151868 | I59: 2272623 | J59: =SUM(H59:I59) -> 88424491 | K59: 125194015
C61: Total Net Assets | H61: =SUM(H54:H59) -> 825820550 | I61: =SUM(I54:I59) -> 12193406 | J61: =SUM(J54:J59) -> 838013956 | K61: =SUM(K54:K59) -> 350184948
C63: Total Liabilities and Net Assets | H63: =SUM(H44+H61+H50) -> 904989361 | I63: =SUM(I44+I61+I50) -> 12825466 | J63: =SUM(J44+J61+J50) -> 917814827 | K63: =SUM(K44+K61+K50) -> 473032386

Sheet Caldwell
C1: Caldwell Parish 2015 Statement of Net Assets
C2: Issued: December 31, 2015
G4: Governmental Activities
A5: ASSETS
B6: Cash and cash equivalents | G6: 7400441
B7: Receivables | G7: 1902779
B8: Capital assets, net of accumulated depreciation | G8: 16886347
B10: Total Assets | G10: =SUM(G6:G8) -> 26189567
A12: DEFERRED OUTFLOWS
B13: Pension related | G13: 85830
A15: LIABILITIES
B16: Cash overdraft
B17: Accounts, salaries, and other payables | G17: 436806
B18: Due to other agencies | G18: 57698
B19: Compensated absences payable | G19: 102079
B20: Net pension liability | G20: 86662
C22: Total Liabilities | G22: =SUM(G17:G20) -> 683245
A24: DEFERRED INFLOWS
B25: Pension related | G25: 35166
A27: NET ASSETS
B28: Net investment in capital assets | G28: 16886347
B29: Restricted | G29: 8172641
B30: Unrestricted | G30: 497998
B32: Total Net Assets | G32: =SUM(G28:G30) -> 25556986
B34: Total Liabilities and Net Assets | G34: =SUM(G22+G32+G25) -> 26275397

Sheet Catahoula
D1: Catahoula Parish 2015 Statement of Net Assets
D2: Issued: December 31, 2015
I4: Component Units
H5: Governmental Activities | I5: Fire District No. 1 Maintenance
A6: ASSETS
C7: Cash and cash equivalents | H7: 2146227 | I7: 116852
C8: Cash restricted for debt service | H8: 27472
C9: Cash restricted for capital project | H9: 38193
C10: Receivables | H10: 1487134 | I10: 14895
C11: Other assets | H11: 83326
C12: Capital assets, net of accumulated depreciation | H12: 6900530 | I12: 92646
C14: Total Assets | H14: =SUM(H7:H12) -> 10682882 | I14: =SUM(I7:I12) -> 224393
A16: DEFERRED OUTFLOWS
B17: Deferred outflows- pension related | H17: 54981
A19: LIABILITIES
C20: Accounts, salaries, and other payables | H20: 656405 | I20: 522
C21: Compensated absences | H21: 36269
C22: Certificates of indebtedness due within one year | H22: 107000
C23: Certificates of indebtedness due in more than one | H23: 165000
C24: Net pension liability | H24: 26562
D26: Total Liabilities | H26: =SUM(H20:H24) -> 991236 | I26: =SUM(I20:I24) -> 522
A28: DEFERRED INFLOWS
C29: Deferred inflows- pension related | H29: 12106
C30: Grant revenues pending | H30: 14776
D31: Total deferred inflows | H31: =SUM(H29:H30) -> 26882 | I31: =SUM(I29:I30) -> 0
A33: NET ASSETS
B34: Net investment in capital assets | H34: 6900530 | I34: 92646
B35: Restricted net position | H35: 2035217 | I35: 131225
B36: Unrestricted net position | H36: 783998
C38: Total Net Assets | H38: =SUM(H34:H36) -> 9719745 | I38: =SUM(I34:I36) -> 223871
C40: Total Liabilities and Net Assets | H40: =SUM(H26+H38+H31) -> 10737863 | I40: =SUM(I26+I38+I31) -> 224393

Sheet Cameron
C1: Cameron Parish 2015 Statement of Net Assets
C2: Issued: December 31, 2015
G4: Governmental Activities
A5: ASSETS
B6: Cash | G6: 16575500
B7: Investments | G7: 11477630
B8: Receivables, net | G8: 13918620
B9: Inventory, at cost | G9: 1858050
B10: Other | G10: 197269
B11: Capital assets, net of accumulated depreciation | G11: 123784927
B13: Total Assets | G13: =SUM(G6:G11) -> 167811996
A15: DEFERRED OUTFLOWS OF RESOURCES | G15: 1016716
A17: LIABILITIES
B18: Accounts, salaries, and other payables | G18: 1999259
B19: Due to other agencies | G19: 2551196
B20: Unearned revenue | G20: 17231
B21: Interest payable | G21: 22491
B22: Long-term liabilities:
C23: Due within one year | G23: 1183863
C24: Due after one year | G24: 3075083
C26: Total Liabilities | G26: =SUM(G18:G24) -> 8849123
A28: DEFERRED INFLOWS OF RESOURCES | G28: 1986478
A30: NET ASSETS
B31: Net investment in capital assets | G31: 121538091
B32: Net position - restricted for:
C33: Judicial | G33: 48266
C34: Debt service | G34: 646986
C35: Tourism development | G35: 44880
C36: Inventories | G36: 1909983
C37: Prepaid expenses | G37: 145336
B38: Net position - unrestricted | G38: 33659569
B40: Total Net Assets | G40: =SUM(G31:G38) -> 157993111
B42: Total Liabilities and Net Assets | G42: =SUM(G26+G40+G28) -> 168828712

Sheet Claiborne
C1: Claiborne Parish 2015 Statement of Net Assets
C2: Issued: December 31, 2015
G4: Governmental Activities
A5: ASSETS
B6: Cash and cash equivalents | G6: 6780670
B7: Investments | G7: 793544
B8: Receivables | G8: 3238498
B9: Due from other agencies | G9: 26080
B10: Deferred charges | G10: 106117
B11: Capital assets, net of accumulated depreciation | G11: 8351695
B13: Total Assets | G13: =SUM(G6:G11) -> 19296604
A15: DEFERRED OUTFLOWS
B16: Deferred outflow- pension related | G16: 129494
A18: LIABILITIES
B19: Accounts, salaries, and other payables | G19: 547636
B20: Due to other agencies | G20: 14025
B21: Deferred revenue | G21: 15626
B22: Compensated absences payable | G22: 70564
B23: Bonds payable within one year | G23: 155000
B24: Bonds payable in more than one year | G24: 1390000
B25: Net pension liability | G25: 87240
C27: Total Liabilities | G27: =SUM(G19:G25) -> 2280091
A29: DEFERRED INFLOWS
B30: Deferred inflows- pension related | G30: 33504
A32: NET ASSETS
B33: Net investment in capital assets | G33: 6806695
B34: Restricted for:
C35: General government | G35: 587824
C36: General government - judicial | G36: 162333
C37: Public works | G37: 2871650
C38: Public safety | G38: 266061
C39: Health and welfare | G39: 244831
C40: Culture and recreation | G40: 1395262
B41: Unrestricted | G41: 4777847
B43: Total Net Assets | G43: =SUM(G33:G41) -> 17112503
B45: Total Liabilities and Net Assets | G45: =SUM(G27+G43+G30) -> 19426098

Sheet Concodria
C1: Concordia Parish 2015 Statement of Net Assets
C2: Issued: December 31, 2015
G4: Governmental Activities
A5: ASSETS
B6: Current Assets
B7: Cash and cash equivalents | G7: 8008253
B8: Cash and cash equivalents - restricted | G8: 2542427
B9: Acounts Receivable | G9: 131838
B10: Ad valorem taxes receivable, net | G10: 1569088
B11: Sales and use taxes receivable | G11: 167250
B12: Severance taxes receivable | G12: 183685
B14: Total Assets | G14: =SUM(G7:G12) -> 12602541
B16: Capital Assets
B17: Proptery and equipment, net | G17: 10080096
G18: =SUM(G14+G17) -> 22682637
B20: Deferred Outflows of Resources
B21: Deferred outflows of pension resources | G21: 234703
G22: =G21+G18 -> 22917340
A24: LIABILITIES, DEFERRED INFLOWS OF RESOURCES, AND NET POSITION
B25: Current liabilities:
C26: Accounts payable | G26: 216980
C27: Accured payroll and benefits | G27: 92325
C28: Interest payable | G28: 217504
C29: Sales tax bonds- due within one year | G29: 413369
G30: =SUM(G26:G29) -> 940178
B32: Noncurrent liabilities:
C33: General obligation bonds | G33: 8419519
C34: Net pension liability | G34: 76459
G35: =SUM(G33:G34) -> 8495978
C37: Total Liabilities | G37: =G35+G30 -> 9436156
A39: Deferred Inflows of Resources
B40: Deferred inflows related to pensions | G40: 34846
A42: NET ASSETS
B43: Net investment in capital assets | G43: 1247208
B44: Restricted for:
C45: Debt service | G45: 3206009
C46: Special projects | G46: 5041759
B47: Unrestricted | G47: 3951362
B49: Total Net Assets | G49: =SUM(G43:G47) -> 13446338
B51: Total Liabilities and Net Assets | G51: =SUM(G37+G49+G40) -> 22917340

Sheet DeSoto
D1: DeSoto Parish 2015 Statement of Net Assets
D2: Issued: December 31, 2015
H4: Primary Government
H5: Governmental Activities | I5: Business-Type Activities | J5: Total
A6: ASSETS
C7: Cash and cash equivalents | H7: 8494984 | I7: 36131 | J7: =SUM(H7:I7) -> 8531115
C8: Investments | H8: 20852796 | J8: =SUM(H8:I8) -> 20852796
C9: Receivables (net of allowance for uncollectibles) | H9: 13253156 | I9: 2154 | J9: =SUM(H9:I9) -> 13255310
C10: Inventory | H10: 26264 | J10: =SUM(H10:I10) -> 26264
C11: Capital assets, net | H11: 76265772 | I11: 21965 | J11: =SUM(H11:I11) -> 76287737
C13: Total Assets | H13: =SUM(H7:H11) -> 118892972 | I13: =SUM(I7:I11) -> 60250 | J13: =SUM(J7:J11) -> 118953222
A15: Deferred Outflows of Resources | H15: 594521 | J15: =SUM(H15:I15) -> 594521
A18: LIABILITIES
C19: Accounts payable | H19: 1358547 | I19: 1538 | J19: =SUM(H19:I19) -> 1360085
C20: Master Bank Overdrafts | H20: 50957 | J20: =SUM(H20:I20) -> 50957
C21: Deposit balances | H21: 300 | I21: 270 | J21: =SUM(H21:I21) -> 570
C22: Advance from grantors | H22: 18938 | J22: =SUM(H22:I22) -> 18938
C23: Due to other governments | H23: 154306 | J23: =SUM(H23:I23) -> 154306
C24: Landfill post closure liability | H24: 2402514 | J24: =SUM(H24:I24) -> 2402514
C25: Compensated absences | H25: 323506 | J25: =SUM(H25:I25) -> 323506
C26: Other postemployment benefit obligation | H26: 3391372 | J26: =SUM(H26:I26) -> 3391372
C27: Net pension liability | H27: 76675 | J27: =SUM(H27:I27) -> 76675
C28: Long-term liabilities:
D29: Due within one year | H29: 449 | J29: =SUM(H29:I29) -> 449
D31: Total Liabilities | H31: =SUM(H19:H29) -> 7777564 | I31: =SUM(I19:I29) -> 1808 | J31: =SUM(J19:J29) -> 7779372
A33: Deferred Inflows of Resources | H33: 165486 | J33: =SUM(H33:I33) -> 165486
A35: NET ASSETS
B36: Net investment in capital assets | H36: 76265323 | I36: 21965 | J36: =SUM(H36:I36) -> 76287288
B37: Restricted for Debt Service | H37: 449 | J37: =SUM(H37:I37) -> 449
B38: Unrestricted | H38: 35278671 | I38: 36477 | J38: =SUM(H38:I38) -> 35315148
C40: Total Net Assets | H40: =SUM(H36:H38) -> 111544443 | I40: =SUM(I36:I38) -> 58442 | J40: =SUM(J36:J38) -> 111602885
C42: Total Liabilities and Net Assets | H42: =SUM(H40+H31) -> 119322007 | I42: =SUM(I40+I31) -> 60250 | J42: =SUM(J40+J31) -> 119382257

Sheet East Baton Rouge
D1: East Baton Rouge Parish 2015 Statement of Net Assets
D2: Issued: December 31, 2015
H4: Primary Government
H5: Governmental Activities | I5: Business-Type Activities | J5: Total | K5: Component Unit
A6: ASSETS
B7: Current Assets
C8: Cash and cash equivalents (note 3) | H8: 166127175 | I8: 79289820 | J8: =SUM(H8:I8) -> 245416995 | K8: 16982146
C9: Investments (note 3) | H9: 211759186 | I9: 118482692 | J9: =SUM(H9:I9) -> 330241878
C10: Receivables--net (note 13) | H10: 52535997 | I10: 16288427 | J10: =SUM(H10:I10) -> 68824424 | K10: 16655099
C11: Due from other governments (note 11) | H11: 84333564 | I11: 2817878 | J11: =SUM(H11:I11) -> 87151442 | K11: 1994449
C12: Prepaid items | H12: 383370 | I12: 207466 | J12: =SUM(H12:I12) -> 590836 | K12: 79566
C13: Loans receivable | H13: 4115590 | J13: =SUM(H13:I13) -> 4115590 | K13: 2138660
C14: Inventory | H14: 896044 | I14: 93352 | J14: =SUM(H14:I14) -> 989396 | K14: 5295059
C15: Other assets | K15: 404912
C16: Restricted assets:
D17: Cash and cash equivalents (note 3) | I17: 135635134 | J17: =SUM(H17:I17) -> 135635134 | K17: 13552638
D18: Investments (note 3) | I18: 232187796 | J18: =SUM(H18:I18) -> 232187796
D19: Receivables--net (note 13) | I19: 423264 | J19: =SUM(H19:I19) -> 423264
D20: Prepaid items | I20: 5880 | J20: =SUM(H20:I20) -> 5880
C21: Capital assets:
D22: Non-depreciable | H22: 198991410 | I22: 349628460 | J22: =SUM(H22:I22) -> 548619870
D23: Depreciable, net | H23: 692284458 | I23: 1530952497 | J23: =SUM(H23:I23) -> 2223236955 | K23: 105830990
C25: Total Assets | H25: =SUM(H8:H23) -> 1411426794 | I25: =SUM(I8:I23) -> 2466012666 | J25: =SUM(J8:J23) -> 3877439460 | K25: =SUM(K8:K23) -> 162933519
A27: Deferred Outflows of Resources
B28: Deferred amount on refunding | H28: 14606047 | I28: 39737972 | J28: =SUM(H28:I28) -> 54344019 | K28: 0
B29: Deferred outflows on derivative instruments | H29: 14755836 | I29: 92452209 | J29: =SUM(H29:I29) -> 107208045 | K29: 0
B30: Deferred outflow for pension | H30: 66874233 | I30: 5853183 | J30: =SUM(H30:I30) -> 72727416 | K30: 9366140
C32: Total deferred outflows of resources | H32: =SUM(H28:H30) -> 96236116 | I32: =SUM(I28:I30) -> 138043364 | J32: =SUM(J28:J30) -> 234279480 | K32: =SUM(K28:K30) -> 9366140
A34: LIABILITIES
C35: Accounts payable and other current liabilities | H35: 27771571 | I35: 50174496 | J35: =SUM(H35:I35) -> 77946067 | K35: 2709410
C36: Internal balances (Note 11) | H36: -1418884 | I36: 1418884
C37: Due to other governments | H37: 490429 | J37: =SUM(H37:I37) -> 490429 | K37: 189168
C38: Accrued payables | H38: 9680296 | I38: 28401015 | J38: =SUM(H38:I38) -> 38081311 | K38: 1490511
C39: Unearned revenue | H39: 1095601 | I39: 1767570 | J39: =SUM(H39:I39) -> 2863171
C40: Deposits and escrow accounts | H40: 1095601 | I40: 1767570 | J40: 11480091
C41: Other liabilities | H41: 11480091 | K41: 59366
C42: Noncurrent liabilities (note 10):
D43: Due within one year | H43: 35509330 | I43: 14070175 | J43: =SUM(H43:I43) -> 49579505 | K43: 3611296
D44: Due in more than one year | H44: 1236678992 | I44: 1683809809 | J44: =SUM(H44:I44) -> 2920488801 | K44: 154960366
D46: Total Liabilities | H46: =SUM(H35:H44) -> 1322383027 | I46: =SUM(I35:I44) -> 1781409519 | J46: =SUM(H46:I46) -> 3103792546 | K46: =SUM(K35:K44) -> 163020117
A48: Deferred Inflows of Reources
B49: Resources received before the requirements | H49: 668996 | J49: =SUM(H49:I49) -> 668996 | K49: 0
B50: Deferred inflow for pensions | H50: 7458464 | I50: 566897 | J50: =SUM(H50:I50) -> 8025361 | K50: 6207313
D51: Total deferred inflows of resources | H51: =SUM(H49:H50) -> 8127460 | I51: =SUM(I49:I50) -> 566897 | J51: =SUM(J49:J50) -> 8694357 | K51: =SUM(K49:K50) -> 6207313
A53: NET ASSETS
B54: Net investment in capital assets | H54: 665194789 | I54: 652390880 | J54: =SUM(H54:I54) -> 1317585669 | K54: 14842088
B55: Restricted for (note 14):
C56: Capital projects | H56: 78237843 | I56: 8306503 | J56: =SUM(H56:I56) -> 86544346
C57: Debt service | H57: 9169416 | I57: 57375662 | J57: =SUM(H57:I57) -> 66545078 | K57: 10322023
C58: Passenger facility charges | I58: 440848 | J58: =SUM(H58:I58) -> 440848
C59: External legal constraints | H59: 78661575 | I59: 70000000 | J59: =SUM(H59:I59) -> 148661575 | K59: 4024483
B60: Unrestricted | H60: -650015599 | I60: 35333291 | J60: =SUM(H60:I60) -> -614682308 | K60: -26116368
C62: Total Net Assets | H62: =SUM(H54:H60) -> 181248024 | I62: =SUM(I54:I60) -> 823847184 | J62: =SUM(J54:J60) -> 1005095208 | K62: =SUM(K53:K60) -> 3072226
C64: Total Liabilities and Net Assets | H64: =SUM(H46+H62+H51) -> 1511758511 | I64: =SUM(I46+I62+I51) -> 2605823600 | J64: =SUM(J46+J62+J51) -> 4117582111 | K64: =SUM(K46+K62+K51) -> 172299656

Sheet East Carroll
D1: East Carroll Parish 2015 Statement of Net Assets
D2: Issued: December 31, 2015
H4: Primary Government
H5: Governmental Activities | I5: Business-Type Activities | J5: Total
A6: ASSETS
C7: Cash and cash equivalents | H7: 1995746 | I7: 35311 | J7: =SUM(H7:I7) -> 2031057
C8: Investments | H8: 719027 | J8: =SUM(H8:I8) -> 719027
C9: Receivables | H9: 2907365 | I9: 2197 | J9: =SUM(H9:I9) -> 2909562
C10: Prepaid items | I10: 1189 | J10: =SUM(H10:I10) -> 1189
C11: Cash and cash equivalents - restricted | I11: 10050 | J11: =SUM(H11:I11) -> 10050
C12: Capital assets not being depreciated | H12: 695896 | J12: =SUM(H12:I12) -> 695896
C13: Capital assets, net of accumulated depreciation | H13: 5462550 | J13: =SUM(H13:I13) -> 5462550
C15: Total Assets | H15: =SUM(H7:H13) -> 11780584 | I15: =SUM(I7:I13) -> 48747 | J15: =SUM(J7:J13) -> 11829331
A17: DEFERRED OUTFLOWS OF RESOURCES
B18: Deferred outflows related to pensions | H18: 287208 | I18: 6937 | J18: =SUM(H18:I18) -> 294145
C19: TOTAL DEFERRED OUTFLOWS OF RESOURCES | H19: =SUM(H18) -> 287208 | I19: =SUM(I18) -> 6937 | J19: =SUM(H19:I19) -> 294145
A21: LIABILITIES
C22: Accounts payable | H22: 111679 | I22: 339 | J22: =SUM(H22:I22) -> 112018
C23: Interest payable | H23: 5987 | J23: =SUM(H23:I23) -> 5987
C24: Long-term liabilities:
D25: Due within one year | H25: 213975 | I25: 489 | J25: =SUM(H25:I25) -> 214464
D26: Due in more than one year | H26: 310647 | I26: 1431 | J26: =SUM(H26:I26) -> 312078
D28: Total Liabilities | H28: =SUM(H22:H26) -> 642288 | I28: =SUM(I22:I26) -> 2259 | J28: =SUM(J22:J26) -> 644547
A30: DEFERRED INFLOWS OF RESOURCES
B31: Deferred outflows related to pensions | H31: 39401 | I31: 952 | J31: =SUM(H31:I31) -> 40353
D32: TOTAL DEFERRED INFLOWS OF RESOURCES | H32: =H31 -> 39401 | I32: =I31 -> 952 | J32: =SUM(H32:I32) -> 40353
A34: NET ASSETS
B35: Net investment in capital assets | H35: 5701437 | J35: =SUM(H35:I35) -> 5701437
B36: Restricted for:
C37: Road maintenance | H37: 1374444 | J37: =SUM(H37:I37) -> 1374444
C38: Garbage | H38: 547996 | J38: =SUM(H38:I38) -> 547996
C39: Library | H39: 682205 | J39: =SUM(H39:I39) -> 682205
C40: Drainage | H40: 631962 | J40: =SUM(H40:I40) -> 631962
C41: Health unit | H41: 715989 | J41: =SUM(H41:I41) -> 715989
C42: Criminal Court | H42: 12682 | J42: =SUM(H42:I42) -> 12682
C43: Debt service | H43: 97837 | J43: =SUM(H43:I43) -> 97837
C44: Rural Fire Protection | H44: 490894 | J44: =SUM(H44:I44) -> 490894
C45: LSU/SU Extension | H45: 221548 | J45: =SUM(H45:I45) -> 221548
C46: Housing Assistance Payments | I46: 10050 | J46: =SUM(H46:I46) -> 10050
B47: Unrestricted | H47: 909109 | I47: 42423 | J47: =SUM(H47:I47) -> 951532
C49: Total Net Assets | H49: =SUM(H35:H47) -> 11386103 | I49: =SUM(I35:I47) -> 52473 | J49: =SUM(J35:J47) -> 11438576
C51: Total Liabilities and Net Assets | H51: =SUM(H49+H28+H32) -> 12067792 | I51: =SUM(I49+I28+I32) -> 55684 | J51: =SUM(J49+J28+J32) -> 12123476

Sheet East Feliciana
C1: East Feliciana Parish 2015 Statement of Net Assets
C2: Issued: December 31, 2015
G4: Governmental Activities
A5: ASSETS
B6: Cash and cash equivalents | G6: 4577606
B7: Receivables, net | G7: 1201051
B8: Due from other funds | G8: 1889509
B9: Due from other governmental agencies | G9: 70258
B10: Capital assets, net | G10: 14087861
B12: Total Assets | G12: =SUM(G6:G10) -> 21826285
A14: DEFERRED OUTFLOWS OF RESOURCES
B15: Pensions | G15: 132270
B16: Total Deferred Outflows of Resources | G16: =G15 -> 132270
A18: LIABILITIES
B19: Accounts payable | G19: 98217
B20: Due to other funds | G20: 1417178
B21: Due to other governmental agencies
B22: Net pension liability | G22: 66241
B23: Compensated absences | G23: 8736
C25: Total Liabilities | G25: =SUM(G19:G23) -> 1590372
A27: DEFERRED OUTFLOWS OF RESOURCES
B28: Pensions | G28: 23363
B29: Total Deferred Outflows of Resources | G29: =G28 -> 23363
A31: NET ASSETS
B32: Net investment in capital assets | G32: 14087861
B33: Restricted for:
C34: Health unit operations/maintenance | G34: 698574
C35: Homeland security/emergency preparedness | G35: 30194
C36: Solid waste management | G36: 4205435
B37: Unrestricted | G37: 1322756
B39: Total Net Assets | G39: =SUM(G32:G37) -> 20344820
B41: Total Liabilities and Net Assets | G41: =G39+G25+G29 -> 21958555

Sheet Evangeline
D1: Evangeline Parish 2015 Statement of Net Assets
D2: Issued: December 31, 2015
H4: Primary Government
H5: Governmental Activities | I5: Business-Type Activities | J5: Total
A6: ASSETS
C7: Cash and interest-bearing deposits | H7: 9976548 | I7: 120763 | J7: =SUM(H7:I7) -> 10097311
C8: Receivables, net | H8: 7163 | I8: 13593 | J8: =SUM(H8:I8) -> 20756
C9: Due from other governmental units | H9: 6075704 | J9: =SUM(H9:I9) -> 6075704
C10: Other assets | H10: 46456 | J10: =SUM(H10:I10) -> 46456
C11: Restricted assets:
D12: Cash and interest-bearing deposits | I12: 20858 | J12: =SUM(I12) -> 20858
D13: Investments | H13: 7198420 | J13: =SUM(H13:I13) -> 7198420
C14: Capital assets, net | H14: 47031804 | I14: 233558 | J14: =SUM(H14:I14) -> 47265362
C16: Total Assets | H16: =SUM(H7:H14) -> 70336095 | I16: =SUM(I7:I14) -> 388772 | J16: =SUM(J7:J14) -> 70724867
A18: Deferred outflows of resources | H18: 560010 | I18: 3029 | J18: =SUM(H18:I18) -> 563039
A21: LIABILITIES
C22: Accounts and other payables | H22: 2822672 | I22: 795 | J22: =SUM(H22:I22) -> 2823467
C23: Accrued interest | H23: 96408 | J23: =SUM(H23:I23) -> 96408
C24: Unearned revenue | H24: 300318 | J24: =SUM(H24:I24) -> 300318
C25: Performance bonds payable | H25: 249333 | I25: 1065 | J25: =SUM(H25:I25) -> 250398
C26: Unearned revenue | H26: 12297 | I26: 12349 | J26: =SUM(H26:I26) -> 24646
C27: Deposits payable | J27: =SUM(H27:I27) -> 0
C28: Long-term liabilities: | J28: =SUM(H28:I28) -> 0
D29: Portion due within one year | H29: 1889000 | I29: 1926 | J29: =SUM(H29:I29) -> 1890926
D30: Portion due after one year | H30: 28115103 | I30: 55870 | J30: =SUM(H30:I30) -> 28170973
C31: Net pension liability | H31: 214778 | I31: 563 | J31: =SUM(H31:I31) -> 215341
D33: Total Liabilities | H33: =SUM(H22:H31) -> 33699909 | I33: =SUM(I22:I31) -> 72568 | J33: =SUM(J22:J31) -> 33772477
A35: Deferred inflows of resources | H35: 82697 | I35: 307 | J35: =SUM(H35:I35) -> 83004
A37: NET ASSETS
B38: Net investment in capital assets | H38: 24827361 | I38: 177688 | J38: =SUM(H38:I38) -> 25005049
B39: Restricted for debt service | H39: 144210 | I39: 6583 | J39: =SUM(H39:I39) -> 150793
B40: Unrestricted | H40: 12141928 | I40: 134655 | J40: =SUM(H40:I40) -> 12276583
C42: Total Net Assets | H42: =SUM(H38:H40) -> 37113499 | I42: =SUM(I38:I40) -> 318926 | J42: =SUM(J38:J40) -> 37432425
C44: Total Liabilities and Net Assets | H44: =SUM(H42+H33) -> 70813408 | I44: =SUM(I42+I33) -> 391494 | J44: =SUM(J42+J33) -> 71204902

Sheet Franklin
C1: Franklin Parish 2015 Statement of Net Assets
C2: Issued: December 31, 2015
G4: Governmental Activities
A5: ASSETS
B6: Cash and cash equivalents | G6: 9845125
B7: Receivables | G7: 3565030
B8: Capital assets (net) | G8: 19315782
B10: Total Assets | G10: =SUM(G6:G8) -> 32725937
A12: DEFERRED OUTFLOWS OF RESOURCES
B13: Pension related | G13: 114200
B14: Total assests and deferred outflow of resources | G14: =G13+G10 -> 32840137
A16: LIABILITIES
B17: Accounts payable | G17: 410724
B18: Payroll withholding payable | G18: 73784
B19: Compensated absences payable | G19: 97918
B20: Capital leases payable | G20: 42662
B21: Long-term liabilities:
C22: Due within one year | G22: 31000
C23: Due in more than one year | G23: 72000
B24: Net pension liability | G24: 72472
B25: Net OPEB obligation | G25: 1566426
C27: Total Liabilities | G27: =SUM(G17:G25) -> 2366986
A29: DEFERRED INFLOWS OF RESOURCES
B30: Pension related | G30: 28927
A32: NET ASSETS
B33: Invested in capital assets, net of related debt | G33: 19170120
B34: Unrestricted | G34: 11271104
B36: Total Net Assets | G36: =SUM(G33:G34) -> 30441224
B38: Total Liabilities, Deferred inflows of Resources, and Net Assets | G38: =SUM(G27+G36+G30) -> 32837137

Sheet Grant
D1: Grant Parish 2015 Statement of Net Assets
D2: Issued: December 31, 2015
H4: Primary Government
H5: Governmental Activities | I5: Business-Type Activities | J5: Total
A6: ASSETS
C7: Cash and cash equivalents | H7: 1607559 | I7: 448494 | J7: =SUM(H7:I7) -> 2056053
C8: Receivables (net) | H8: 1476524 | I8: 52934 | J8: =SUM(H8:I8) -> 1529458
C9: Capital assets:
D10: Non depreciable capital assets
E11: Construction in progress | H11: 410009 | I11: 20000 | J11: =SUM(H11:I11) -> 430009
E12: Land | H12: 203250 | J12: =SUM(H12:I12) -> 203250
D13: Depreciable capital assets, net | H13: 5503118 | I13: 312597 | J13: =SUM(H13:I13) -> 5815715
C15: Total Assets | H15: =SUM(H7:H13) -> 9200460 | I15: =SUM(I7:I13) -> 834025 | J15: =SUM(J7:J13) -> 10034485
C17: DEFERRED OUTFLOWS | H17: 327152 | I17: 39770 | J17: =SUM(H17:I17) -> 366922
A19: LIABILITIES
C20: Accounts and other payables | H20: 481261 | I20: 22337 | J20: =SUM(H20:I20) -> 503598
C21: Retainage Payable | H21: 32870 | J21: =SUM(H21:I21) -> 32870
C22: Deposits due others | I22: 79146 | J22: =SUM(H22:I22) -> 79146
C23: Unearned revenues | J23: =SUM(H23:I23) -> 0
C24: Long-term liabilities: | J24: =SUM(H24:I24) -> 0
D25: Compensated absences | H25: 48059 | I25: 12224 | J25: =SUM(H25:I25) -> 60283
D26: Notes payable: | J26: =SUM(H26:I26) -> 0
E27: Due within one year | H27: 97605 | J27: =SUM(H27:I27) -> 97605
E28: Due in more than one year | H28: 149857 | J28: =SUM(H28:I28) -> 149857
D29: Aggregate Net Pension Liability | H29: 95921 | I29: 7854 | J29: =SUM(H29:I29) -> 103775
D31: Total Liabilities | H31: =SUM(H20:H29) -> 905573 | I31: =SUM(I20:I29) -> 121561 | J31: =SUM(J20:J29) -> 1027134
C33: DEFERRED INFLOWS | H33: 101227 | I33: 3497 | J33: =SUM(H33:I33) -> 104724
A35: NET ASSETS
B36: Invested in capital assets, net of related debt | H36: 5836045 | I36: 332597 | J36: =SUM(H36:I36) -> 6168642
B37: Restricted:
C38: Maintenance | H38: 1732973 | J38: =SUM(H38:I38) -> 1732973
C39: Judicial | H39: 30664 | J39: =SUM(H39:I39) -> 30664
C40: Construction | H40: 51728 | J40: =SUM(H40:I40) -> 51728
B41: Unrestricted | H41: 869402 | I41: 416140 | J41: =SUM(H41:I41) -> 1285542
C43: Total Net Assets | H43: =SUM(H36:H41) -> 8520812 | I43: =SUM(I36:I41) -> 748737 | J43: =SUM(J36:J41) -> 9269549
C45: Total Liabilities and Net Assets | H45: =SUM(H43+H31+H33) -> 9527612 | I45: =SUM(I43+I31+I33) -> 873795 | J45: =SUM(J43+J31+J33) -> 10401407

Sheet Iberia
D1: Iberia Parish 2015 Statement of Net Assets
D2: Issued: December 31, 2015
H4: Primary Government
H5: Governmental Activities | I5: Component Units
A6: ASSETS
C7: Cash and interest-bearing deposits | H7: 46860646 | I7: 41977434
C8: Investments | H8: 63081
C9: Receivables, net | H9: 7717579 | I9: 10093684
C10: Advance to component unit | H10: 1989685
C11: Due from other governmental agencies | H11: 3219065 | I11: 813304
C12: Due from primary government | I12: 614357
C13: Inventories | I13: 1727422
C14: Prepaid items | I14: 707184
C15: Goodwill | I15: 282536
C16: Investments in joint ventures | I16: 501439
C17: Restricted assets | I17: 3890720
C18: Capital assets:
D19: Non-depreciable | H19: 8523433 | I19: 13973493
D20: Depreciable, net | H20: 85605502 | I20: 67696703
C22: Total Assets | H22: =SUM(H7:H20) -> 153978991 | I22: =SUM(I7:I20) -> 142278276
A24: DEFERRED OUTFLOWS OF RESOURCES
B25: Pension related | H25: 1266943 | I25: 5503380
B26: Prepaid bond insurance | I26: 80687
C27: Total deferred outflows of resources | H27: =SUM(H25:H26) -> 1266943 | I27: =SUM(I25:I26) -> 5584067
A29: LIABILITIES
C30: Accounts payable | H30: 1304798 | I30: 2567682
C31: Accrued expenses | H31: 233319 | I31: 6224024
C32: Contracts and retainage payable | H32: 860129 | I32: 1227829
C33: Due to other governmental agencies | H33: 364569 | I33: 234180
C34: Due to component unit | H34: 614357
C35: Advance from primary government | I35: 1989685
C36: Advances from grantors and others | H36: 89950 | I36: 66735
C37: Deposits | I37: 371027
C38: Accrued interest payable | H38: 23641 | I38: 221554
C39: Long-term liabilities:
D40: Tenant deposits | I40: 12311
D41: Other post employment benefits payable | H41: 5571987 | I41: 2214306
D42: Net pension liability | H42: 245699 | I42: 3734210
D43: Due within one year | H43: 1825318 | I43: 3726878
D44: Due in more than one year | H44: 13093322 | I44: 37757138
D46: Total Liabilities | H46: =SUM(H30:H44) -> 24227089 | I46: =SUM(I30:I44) -> 60347559
A48: DEFERRED INFLOWS OF RESOURCES
B49: Pension related | H49: 109223 | I49: 734436
A51: NET ASSETS
B52: Net investment in capital assets | H52: 80033586 | I52: 56080744
B53: Restricted
C54: Nonexpendable | H54: 68863
C55: Capital projects | H55: 189936
C56: Debt Service | H56: 286475
C57: Tax dedications | H57: 29531203 | I57: 2873733
C58: Other | H58: 28428 | I58: 8959449
B59: Unrestricted | H59: 20771131 | I59: 18866422
C61: Total Net Assets | H61: =SUM(H52:H59) -> 130909622 | I61: =SUM(I52:I59) -> 86780348
C63: Total Liabilities and Net Assets | H63: =SUM(H46+H61+H49) -> 155245934 | I63: =SUM(I46+I61+I49) -> 147862343

Sheet Iberville
D1: Iberville Parish 2015 Statement of Net Assets
D2: Issued: December 31, 2015
H4: Primary Government | K4: Total Component Units
H5: Governmental Activities | I5: Business-Type Activities | J5: Total | K5: Governmental Activities | L5: Business-type Activities
A6: ASSETS
B7: Current Assets
C8: Cash and cash equivalents | H8: 30313280 | I8: 3497391 | J8: =SUM(H8:I8) -> 33810671 | K8: 1884797 | L8: 546127
C9: Investments | J9: =SUM(H9:I9) -> 0 | K9: 299697
C10: Receivables (net of allowance for uncollectibles) | H10: 9106856 | I10: 705101 | J10: =SUM(H10:I10) -> 9811957 | K10: 3893015 | L10: 193352
C11: Inventories | I11: 177220 | J11: =SUM(H11:I11) -> 177220
C12: Prepaid items | H12: 5222 | J12: =SUM(H12:I12) -> 5222 | L12: 15379
C13: Other assets | H13: 1217886 | I13: 62274 | J13: =SUM(H13:I13) -> 1280160 | K13: 38380 | L13: 35137
C14: Restricted assets
D15: Cash and cash equivalents | H15: 100000 | I15: 303573 | J15: =SUM(H15:I15) -> 403573 | L15: 750238
C16: Capital assets (net of accumulated depreciation)
D17: Land | H17: 3232380 | I17: 193511 | J17: =SUM(H17:I17) -> 3425891 | K17: 435740
D18: Building and system | H18: 52248412 | I18: 10523122 | J18: =SUM(H18:I18) -> 62771534 | K18: 869565 | L18: 1722119
D19: Improvemetns other than building | H19: 54880429 | J19: =SUM(H19:I19) -> 54880429 | K19: 484925 | L19: 3204005
D20: Machinery and equipment | H20: 6118075 | I20: 486014 | J20: =SUM(H20:I20) -> 6604089 | K20: 433565 | L20: 1150084
D21: Construction in progress | H21: 1222654 | J21: =SUM(H21:I21) -> 1222654 | K21: 220857 | L21: 73167
C23: Total Assets | H23: =SUM(H8:H21) -> 158445194 | I23: =SUM(I8:I21) -> 15948206 | J23: =SUM(J8:J21) -> 174393400 | K23: =SUM(K8:K21) -> 8560541 | L23: =SUM(L8:L21) -> 7689608
A25: DEFERRED OUTFLOWS OF RESOURCES
B26: Pension | H26: 1111407 | I26: 209614 | J26: =SUM(H26:I26) -> 1321021 | K26: 308042
A28: LIABILITIES
C29: Accounts payable and other current liabilities | H29: 3426953 | I29: 517330 | J29: =SUM(H29:I29) -> 3944283 | L29: 71599
C30: Matured bonds and interest payable | J30: =SUM(H30:I30) -> 0
C31: Accrued interest payable | J31: =SUM(H31:I31) -> 0
C32: Bank overdraft liability | J32: =SUM(H32:I32) -> 0
C33: Other payables | H33: 885850 | I33: 3348 | J33: =SUM(H33:I33) -> 889198 | K33: 282113
C34: Liabilities payable from restricted assets | I34: 300298 | J34: =SUM(H34:I34) -> 300298 | K34: 189454 | L34: 124376
C35: Noncurrent liabilities: | J35: =SUM(H35:I35) -> 0
D36: Pension | H36: 204798 | I36: 38625 | J36: =SUM(H36:I36) -> 243423 | K36: 57273
D37: Other post employment benefits | H37: 585479 | J37: =SUM(H37:I37) -> 585479 | K37: 89936
D38: Due in one year | H38: 1415089 | I38: 55000 | J38: =SUM(H38:I38) -> 1470089 | L38: 97891
D39: Due in more than one year | H39: 18163086 | I39: 435000 | J39: =SUM(H39:I39) -> 18598086 | K39: 312344 | L39: 3160978
D41: Total Liabilities | H41: =SUM(H29:H39) -> 24681255 | I41: =SUM(I29:I39) -> 1349601 | J41: =SUM(J29:J39) -> 26030856 | K41: =SUM(K29:K39) -> 931120 | L41: =SUM(L29:L39) -> 3454844
A43: DEFERRED INFLOWS OF RESOURCES
B44: Pension | H44: 97127 | I44: 18318 | J44: =SUM(H44:I44) -> 115445 | K44: 27415
A46: NET ASSETS
B47: Net Investment in Capital Assets | H47: 99077563 | I47: 10712647 | J47: =SUM(H47:I47) -> 109790210 | K47: 2444652 | L47: 3023534
B48: Restricted, related to
C49: Public building maintenance | H49: 2310065 | J49: =SUM(H49:I49) -> 2310065
C50: Drainage | H50: 3929497 | J50: =SUM(H50:I50) -> 3929497
C51: Solid waste | H51: 4131751 | J51: =SUM(H51:I51) -> 4131751
C52: Fire protection | H52: 3032689 | J52: =SUM(H52:I52) -> 3032689
C53: Emergency services | H53: 1210889 | J53: =SUM(H53:I53) -> 1210889
C54: Debt service | H54: 2723809 | J54: =SUM(H54:I54) -> 2723809 | L54: 527971
C55: Road Improvements | H55: 5507033 | J55: =SUM(H55:I55) -> 5507033
C56: Other | H56: 906025 | J56: =SUM(H56:I56) -> 906025
B57: Unrestricted | H57: 11948898 | I57: 4077254 | J57: =SUM(H57:I57) -> 16026152 | K57: 5465396 | L57: 683259
C59: Total Net Assets | H59: =SUM(H47:H57) -> 134778219 | I59: =SUM(I47:I57) -> 14789901 | J59: =SUM(J47:J57) -> 149568120 | K59: =SUM(K47:K57) -> 7910048 | L59: =SUM(L46:L57) -> 4234764
C61: Total Liabilities and Net Assets | H61: =SUM(H41+H59+H44) -> 159556601 | I61: =SUM(I41+I59+I44) -> 16157820 | J61: =SUM(J41+J59+J44) -> 175714421 | K61: =SUM(K41+K59+K44) -> 8868583 | L61: =SUM(L41+L59+L44) -> 7689608

Sheet Jackson 
C1: Jackson Parish 2015 Statement of Net Assets
C2: Issued: December 31, 2015
G4: Governmental Activities
A5: ASSETS
B6: Cash and cash equivalents | G6: 10715548
B7: Receivables | G7: 5708768
B8: Prepaid items | G8: 43519
B9: Capital assets:
C10: Land and construction in progress | G10: 433912
C11: Capital assets, net of depreciation | G11: 16798841
B13: Total Assets | G13: =SUM(G6:G11) -> 33700588
A15: DEFERRED OUTFLOWS OF RESOURCES
B16: Deferred outflows related to pensions | G16: 425617
B17: TOTAL DEFERRED OUTFLOWS OF RESOURCES | G17: =G16 -> 425617
A19: LIABILITIES
B20: Accounts, salaries, and other payables | G20: 491701
B21: Security deposits | G21: 25321
B22: Long-term liabilities:
C23: Due within one year | G23: 372241
C24: Due in more than one year | G24: 3340963
C26: Total Liabilities | G26: =SUM(G20:G24) -> 4230226
A28: DEFERRED INFLOWS OF RESOURCES
B29: Deferred outflows related to pensions | G29: 64691
B30: TOTAL DEFERRED OUTFLOWS OF RESOURCES | G30: =G29 -> 64691
A32: NET ASSETS
B33: Net investment in capital assets | G33: 14791909
B34: Restricted for:
C35: Road maintenance (Road, Sales tax and asphalt funds) | G35: 6733177
C36: Waste management | G36: 1158237
C37: Library | G37: 2469276
C38: Health unit | G38: 286867
C39: Tourism | G39: 50860
C40: Landfill closure | G40: 555594
C41: Pavillion/Riding Arena | G41: 251024
C42: Grant funds | G42: 35419
C43: Grand jury and witness fees | G43: 15158
C44: Debt service | G44: 190913
B45: Unrestricted | G45: 3292854
B47: Total Net Assets | G47: =SUM(G33:G45) -> 29831288
B49: Total Liabilities and Net Assets | G49: =SUM(G26+G47+G30) -> 34126205

Sheet Jefferson
D1: Jefferson Parish 2015 Statement of Net Assets
D2: Issued: December 31, 2015
G3: (amounts in thousands)
H5: Primary Government
H6: Governmental Activities | I6: Business-Type Activities | J6: Total | K6: Component Unit
A7: ASSETS
B8: Current Assets
C9: Cash and cash equivalents | H9: 5540 | I9: 4796 | J9: =SUM(H9:I9) -> 10336 | K9: 15882
C10: Investments | H10: 73132 | J10: =SUM(H10:I10) -> 73132 | K10: 90512
C11: Share of pooled assets | H11: 558920 | I11: 15040 | J11: =SUM(H11:I11) -> 573960
C12: Receivables, net of allowances for
D13: estimated uncollectibles:
D14: Interest | H14: 214 | J14: =SUM(H14:I14) -> 214 | K14: 180
D15: Ad valorem tax | H15: 200503 | I15: 9211 | J15: =SUM(H15:I15) -> 209714
D16: Accounts | H16: 5688 | I16: 5439 | J16: =SUM(H16:I16) -> 11127 | K16: 51143
D17: Notes | K17: 7625
D18: Mortgage loans
D19: Intergovernmental | H19: 62084 | I19: 21 | J19: =SUM(H19:I19) -> 62105 | K19: 58
D20: Other | J20: =SUM(H20:I20) -> 0 | K20: 6239
C21: Inventories | H21: 3414 | I21: 7786 | J21: =SUM(H21:I21) -> 11200 | K21: 10061
C22: Prepaid items | I22: 398 | J22: =SUM(H22:I22) -> 398 | K22: 7818
C23: Restricted assets: | J23: =SUM(H23:I23) -> 0
D24: Cash and cash equivalents | I24: 27743 | J24: =SUM(H24:I24) -> 27743 | K24: 10881
D25: Investments | I25: 106509 | J25: =SUM(H25:I25) -> 106509 | K25: 83923
D26: Share of pooled assets | I26: 57307 | J26: =SUM(H26:I26) -> 57307
D27: Receivables | I27: 13488 | J27: =SUM(H27:I27) -> 13488
C29: Total Current Assets | H29: =SUM(H9:H27) -> 909495 | I29: =SUM(I9:I27) -> 247738 | J29: =SUM(J9:J27) -> 1157233 | K29: =SUM(K9:K27) -> 284322
B31: Noncurrent Assets
C32: Restricted assets:
D33: Deposits and other assets | H33: 7817 | J33: =SUM(H33:I33) -> 7817 | K33: 7698
C34: Mortgage loans receivable | J34: =SUM(H34:I34) -> 0 | K34: 40572
C35: Capital assets not being depreciated | H35: 202984 | I35: 50606 | J35: =SUM(H35:I35) -> 253590
C36: Capital assets being depreciated, net | H36: 1112858 | I36: 639120 | J36: =SUM(H36:I36) -> 1751978 | K36: 221050
C38: Total Noncurrent Assets | H38: =SUM(H31:H36) -> 1323659 | I38: =SUM(I31:I36) -> 689726 | J38: =SUM(J31:J36) -> 2013385 | K38: =SUM(K31:K36) -> 269320
C40: Total Assets | H40: =SUM(H38+H29) -> 2233154 | I40: =SUM(I38+I29) -> 937464 | J40: =SUM(J29+J38) -> 3170618 | K40: =SUM(K29+K38) -> 553642
B42: Deferred outflows of resources
C43: Deferred charges on debt refunding | H43: 9616 | J43: =SUM(H43:I43) -> 9616
C44: Deferred charges acquisition costs | I44: 3362 | J44: =SUM(H44:I44) -> 3362
C45: Pension-relate deferred outflows | H45: 35056 | I45: 8197 | J45: =SUM(H45:I45) -> 43253 | K45: 4090
C47: Total Deferred Outflows of Resources | H47: =SUM(H43:H45) -> 44672 | I47: =SUM(I43:I45) -> 11559 | J47: =SUM(J43:J45) -> 56231 | K47: =SUM(K43:K45) -> 4090
A49: LIABILITIES
B50: Current liabilities
C51: Accounts and contracts payable | H51: 32009 | I51: 785 | J51: =SUM(H51:I51) -> 32794 | K51: 14268
C52: Claims and judgments payable | H52: 5994 | J52: =SUM(H52:I52) -> 5994
C53: Intergovernmental payable | H53: 2180 | I53: 1193 | J53: =SUM(H53:I53) -> 3373
C54: Current portion of long term debt | H54: 34211 | I54: 2251 | J54: =SUM(H54:I54) -> 36462
C55: Deposits | H55: 72 | J55: =SUM(H55:I55) -> 72
C56: Accrued salaries payable | H56: 1919 | I56: 3198 | J56: =SUM(H56:I56) -> 5117
C57: Accrued interest payable | H57: 1357 | J57: =SUM(H57:I57) -> 1357 | K57: 2325
C58: Other payables and accruals | H58: 6249 | I58: 3122 | J58: =SUM(H58:I58) -> 9371 | K58: 31515
C59: Unearned revenue | H59: 203067 | I59: 9236 | J59: =SUM(H59:I59) -> 212303
C60: Advanced lease and other payments from CEA | I60: 4467 | J60: =SUM(H60:I60) -> 4467
C61: Payable from restricted assets: | J61: =SUM(H61:I61) -> 0
D62: Accounts payable | I62: 1405 | J62: =SUM(H62:I62) -> 1405
D63: Retainage payable | I63: 257 | J63: =SUM(H63:I63) -> 257
D64: Accrued interest payable | J64: =SUM(H64:I64) -> 0 | K64: 4657
D65: Current portion of long term debt | J65: =SUM(H65:I65) -> 0 | K65: 4246
D66: Unearned revenue | I66: 11034 | J66: =SUM(H66:I66) -> 11034
D68: Total Current Liabilities | H68: =SUM(H51:H66) -> 287058 | I68: =SUM(I51:I66) -> 36948 | J68: =SUM(J51:J66) -> 324006 | K68: =SUM(K51:K66) -> 57011
B70: Noncurrent liabilities
C71: Net pension liability | H71: 51302 | I71: 61921 | J71: =SUM(H71:I71) -> 113223 | K71: 32992
C72: Other long term liabilities | I72: 6321 | J72: =SUM(H72:I72) -> 6321
C73: Customers' deposits | I73: 9337 | J73: =SUM(H73:I73) -> 9337
C74: Advanced lease and other payments from CEA | I74: 194422 | J74: =SUM(H74:I74) -> 194422
C75: Due in more than one year | H75: 413686 | I75: 14700 | J75: =SUM(H75:I75) -> 428386 | K75: 213342
D77: Total Noncurrent Liabilities | H77: =SUM(H70:H75) -> 464988 | I77: =SUM(I70:I75) -> 286701 | J77: =SUM(J70:J75) -> 751689 | K77: =SUM(K70:K75) -> 246334
D79: Total Liabilities | H79: =SUM(H68+H77) -> 752046 | I79: =SUM(I77+I68) -> 323649 | J79: =SUM(J77+J68) -> 1075695 | K79: =SUM(K68+K77) -> 303345
B81: Deferred outflows of resources
C82: Pension-related deferred inflows of resources | H82: 4096 | I82: 399 | J82: =SUM(H82:I82) -> 4495 | K82: 117
A84: NET ASSETS
B85: Net investment in capital assets | H85: 991422 | I85: 674982 | J85: =SUM(H85:I85) -> 1666404 | K85: 63515
B86: Restricted for:
C87: Judges annuitles | H87: 1683 | J87: =SUM(H87:I87) -> 1683
C88: General government | H88: 1237 | J88: =SUM(H88:I88) -> 1237
C89: Public safety | H89: 50112 | J89: =SUM(H89:I89) -> 50112
C90: Public works | H90: 36097 | J90: =SUM(H90:I90) -> 36097
C91: Transit | H91: 22867 | J91: =SUM(H91:I91) -> 22867
C92: Health and welfare | H92: 9138 | I92: 20000 | J92: =SUM(H92:I92) -> 29138
C93: Culture and recreation | H93: 88153 | J93: =SUM(H93:I93) -> 88153
C94: Economic development | H94: 4366 | J94: =SUM(H94:I94) -> 4366
C95: Urban redevelopment and housing | H95: 2278 | J95: =SUM(H95:I95) -> 2278 | K95: 15138
C96: Construction | H96: 223717 | I96: 58952 | J96: =SUM(H96:I96) -> 282669
C97: Debt service | I97: 127 | J97: =SUM(H97:I97) -> 127 | K97: 51082
C98: Claims and judgments payable | H98: 3643 | J98: =SUM(H98:I98) -> 3643
B99: Unrestricted | H99: 86971 | I99: -129086 | J99: =SUM(H99:I99) -> -42115 | K99: 124535
C101: Total Net Assets | H101: =SUM(H85:H99) -> 1521684 | I101: =SUM(I85:I99) -> 624975 | J101: =SUM(J85:J99) -> 2146659 | K101: =SUM(K84:K99) -> 254270
C103: Total Liabilities and Net Assets | H103: =SUM(H79+H101+H82) -> 2277826 | I103: =SUM(I79+I101+I82) -> 949023 | J103: =SUM(J79+J101+J82) -> 3226849 | K103: =SUM(K79+K101+K82) -> 557732

Sheet Jefferson Davis
C1: Jefferson Davis Parish 2015 Statement of Net Assets
C2: Issued: December 31, 2015
G4: Governmental Activities
A5: ASSETS
B6: Cash and cash equivalents | G6: 22295246
B7: Investments | G7: 2118764
B8: Receivables | G8: 2190018
B9: Prepaid items | G9: 79428
B10: Restricted cash and cash equivalents | G10: 2678453
B11: Capital assets (net) | G11: 34263814
B13: Total Assets | G13: =SUM(G6:G11) -> 63625723
A15: DEFERRED OUTFLOWS OF RESOURCES
B16: Pension related deferrals | G16: 327109
B17: Deferred bond issuance costs | G17: 57099
B18: TOTAL DEFERRED OUTFLOWS OF RESOURCES | G18: =SUM(G16:G17) -> 384208
A20: LIABILITIES
B21: Accounts, salaries, and other payables | G21: 827526
B22: Contracts payable | G22: 43790
B23: Deposits due others | G23: 567800
B24: Accrued interest payable | G24: 262428
B25: Liability for other post-employment benefits | G25: 2453168
B26: Current portion of bonds payable | G26: 984000
B27: Current portion of capital leases payable | G27: 144783
B28: Capital leases payable | G28: 639410
B29: Bonds payable | G29: 13730000
B30: Net pension liability | G30: 273215
C32: Total Liabilities | G32: =SUM(G21:G30) -> 19926120
A34: DEFERRED INFLOWS OF RESOURCES
B35: Pension related deferrals | G35: 78329
B36: Deferred revenues | G36: 177663
B37: TOTAL DEFERRED INFLOWS OF RESOURCES | G37: =SUM(G35:G36) -> 255992
A39: NET ASSETS
B40: Net investment in capital assets | G40: 18503193
B41: Restricted for:
C42: Public safety | G42: 7352490
C43: Public works | G43: 8777284
C44: Health and welfare | G44: 407444
C45: Debt service | G45: 2675500
C46: Other general government | G46: 1503341
B47: Unrestricted | G47: 4608567
B49: Total Net Assets | G49: =SUM(G40:G47) -> 43827819
B51: Total Liabilities and Net Assets | G51: =SUM(G32+G49+G37) -> 64009931

Sheet Lafayette
D1: Lafayete Parish 2015 Statement of Net Assets
D2: Issued: December 31, 2015
H4: Primary Government
H5: Governmental Activities | I5: Business-Type Activities | J5: Total | K5: Component Unit
A6: ASSETS
C7: Cash and interest-bearing deposits | H7: 16641210 | I7: 5283189 | J7: =SUM(H7:I7) -> 21924399 | K7: 52538532
C8: Investments | H8: 271226470 | I8: 28061815 | J8: =SUM(H8:I8) -> 299288285 | K8: 18134974
C9: Receivables, net | H9: 5368379 | I9: 23844975 | J9: =SUM(H9:I9) -> 29213354 | K9: 9343950
C10: Internal balances | H10: 1545353 | I10: -1545353 | J10: =SUM(H10:I10) -> 0
C11: Due from primary government | J11: =SUM(H11:I11) -> 0 | K11: 92392
C12: Due from other governmental agencies | H12: 19498802 | I12: 2460768 | J12: =SUM(H12:I12) -> 21959570 | K12: 4672050
C13: Inventories, net | H13: 479070 | I13: 19979155 | J13: =SUM(H13:I13) -> 20458225 | K13: 226786
C14: Prepaid items | H14: 311348 | I14: 603948 | J14: =SUM(H14:I14) -> 915296 | K14: 460338
C15: Other assets | H15: 775000 | J15: =SUM(H15:I15) -> 775000 | K15: 2339940
C16: Restricted assets: | J16: =SUM(H16:I16) -> 0
D17: Cash | I17: 4557261 | J17: =SUM(H17:I17) -> 4557261 | K17: 3590811
D18: Investments | I18: 158334857 | J18: =SUM(H18:I18) -> 158334857 | K18: 12248459
D19: Receivables | I19: 156557 | J19: =SUM(H19:I19) -> 156557 | K19: 24899
C20: Unamortized start-up costs | I20: 1753603 | J20: =SUM(H20:I20) -> 1753603
C21: Capital assets: | J21: =SUM(H21:I21) -> 0
D22: Non-depreciable | H22: 69787539 | I22: 103348893 | J22: =SUM(H22:I22) -> 173136432 | K22: 21843992
D23: Depreciable,net | H23: 529713470 | I23: 668422936 | J23: =SUM(H23:I23) -> 1198136406 | K23: 103294800
C25: Total Assets | H25: =SUM(H7:H23) -> 915346641 | I25: =SUM(I7:I23) -> 1015262604 | J25: =SUM(J7:J23) -> 1930609245 | K25: =SUM(K7:K23) -> 228811923
A27: DEFERRED OUTFLOWS OF RESOURCES
B28: Deferred loss on bond refunding | H28: 8782907 | I28: 16251537 | J28: =SUM(H28:I28) -> 25034444 | K28: 21454
B29: Deferred outflows related to pensions | H29: 28818871 | I29: 10704356 | J29: =SUM(H29:I29) -> 39523227 | K29: 1313649
C30: Total deferred outflows of resources | H30: =SUM(H28:H29) -> 37601778 | I30: =SUM(I28:I29) -> 26955893 | J30: =SUM(J28:J29) -> 64557671 | K30: =SUM(K28:K29) -> 1335103
A33: LIABILITIES
C34: Accounts and other payables | H34: 11527783 | I34: 9718935 | J34: =SUM(H34:I34) -> 21246718 | K34: 1997015
C35: Due to component units | H35: 92392 | J35: =SUM(H35:I35) -> 92392
C36: Due to other governmental agencies | H36: 262270 | J36: =SUM(H36:I36) -> 262270 | K36: 10939
C37: Unearned revenue | H37: 210423 | I37: 10621 | J37: =SUM(H37:I37) -> 221044 | K37: 1676684
C38: Customer deposits | I38: 8700206 | J38: =SUM(H38:I38) -> 8700206 | K38: 233936
C39: Long-term liabilities:
D40: Portion due or payable within one year | H40: 33728815 | I40: 2363943 | J40: =SUM(H40:I40) -> 36092758 | K40: 3203565
D41: Portion due or payable after one year | H41: 368165568 | I41: 472682900 | J41: =SUM(H41:I41) -> 840848468 | K41: 16264846
C42: Other post-employment benefits | H42: 3280148 | J42: =SUM(H42:I42) -> 3280148 | K42: 12820
C43: Net pension liability | H43: 105952178 | I43: 28220360 | J43: =SUM(H43:I43) -> 134172538 | K43: 3791169
D45: Total Liabilities | H45: =SUM(H34:H43) -> 523219577 | I45: =SUM(I34:I43) -> 521696965 | J45: =SUM(J34:J43) -> 1044916542 | K45: =SUM(K34:K43) -> 27190974
A47: DEFERRED INFLOWS OF RESOURCES
A48: Property taxes | K48: 1931828
A49: Deferred inflows related to pensions | H49: 5264024 | I49: 1444333 | J49: =SUM(H49:I49) -> 6708357 | K49: 569700
D50: Total deferred inflows of resources | H50: =SUM(H48:H49) -> 5264024 | I50: =SUM(I48:I49) -> 1444333 | J50: =SUM(J48:J49) -> 6708357 | K50: =SUM(K48:K49) -> 2501528
A53: NET ASSETS
B54: Net investment in capital assets | H54: 323368785 | I54: 318155755 | J54: =SUM(H54:I54) -> 641524540 | K54: 118304299
B55: Restricted for: | J55: =SUM(H55:I55) -> 0
C56: Capital projects | H56: 81566002 | J56: =SUM(H56:I56) -> 81566002 | K56: 4480744
C57: Debt service | H57: 45839088 | I57: 143872510 | J57: =SUM(H57:I57) -> 189711598 | K57: 3502224
C58: Other | H58: 54623926 | J58: =SUM(H58:I58) -> 54623926 | K58: 589961
B59: Unrestricted (deficit) | H59: -80932983 | I59: 57048934 | J59: =SUM(H59:I59) -> -23884049 | K59: 73577296
C61: Total Net Assets | H61: =SUM(H54:H59) -> 424464818 | I61: =SUM(I54:I59) -> 519077199 | J61: =SUM(J54:J59) -> 943542017 | K61: =SUM(K53:K59) -> 200454524
C63: Total Liabilities and Net Assets | H63: =SUM(H45+H61+H50) -> 952948419 | I63: =SUM(I45+I61+I50) -> 1042218497 | J63: =SUM(J45+J61+J50) -> 1995166916 | K63: =SUM(K45+K61+K50) -> 230147026

Sheet Lafourche
D1: Lafourche Parish 2015 Statement of Net Assets
D2: Issued: December 31, 2015
H4: Primary Government | K4: Component Unit
H5: Governmental Activities | I5: Business-Type Activities | J5: Total | K5: Total
A6: ASSETS
C7: Cash | H7: 17684263 | J7: =SUM(H7:I7) -> 17684263 | K7: 194871525
C8: Investments | H8: 27443994 | J8: =SUM(H8:I8) -> 27443994 | K8: 21272286
C9: Receivables | H9: 1414026 | I9: 15905 | J9: =SUM(H9:I9) -> 1429931 | K9: 42193102
C10: Due from other governmental units | H10: 33698714 | J10: =SUM(H10:I10) -> 33698714
C11: Prepaids and other assets | H11: 2261412 | J11: =SUM(H11:I11) -> 2261412 | K11: 9542611
C12: Capital assets: | K12: 1401858
D13: Non-depreciable | H13: 15216799 | J13: =SUM(H13:I13) -> 15216799 | K13: 29927075
D14: Depreciable | H14: 86570530 | I14: 2477397 | J14: =SUM(H14:I14) -> 89047927 | K14: 251936313
C16: Total Assets | H16: =SUM(H7:H14) -> 184289738 | I16: =SUM(I7:I14) -> 2493302 | J16: =SUM(J7:J14) -> 186783040 | K16: =SUM(K7:K14) -> 551144770
B18: Deferred outflows of resources
C19: Deferred charge on refunding | H19: 918193 | J19: =SUM(H19:I19) -> 918193
C20: Deferred outflows- pension contributions | H20: 5797 | J20: =SUM(H20:I20) -> 5797 | K20: 905123
C21: Deferred outflows- pension other | H21: 15475 | J21: =SUM(H21:I21) -> 15475
C23: Total Deferred Outflows of Resources | H23: =SUM(H19:H21) -> 939465 | I23: =SUM(I19:I21) -> 0 | J23: =SUM(J19:J21) -> 939465 | K23: =SUM(K19:K21) -> 905123
A25: LIABILITIES
C26: Accounts payable and accrued expenses | H26: 6254898 | I26: 14914 | J26: =SUM(H26:I26) -> 6269812 | K26: 21813201
C27: Other current liabilities | H27: 639621 | J27: =SUM(H27:I27) -> 639621 | K27: 2460428
C28: Accrued interest payable | H28: 938561 | J28: =SUM(H28:I28) -> 938561
C29: Due to other governmental units | H29: 1027057 | I29: 231793 | J29: =SUM(H29:I29) -> 1258850
C30: Long-term liabilities | J30: =SUM(H30:I30) -> 0
D31: Due within one year | H31: 3981003 | J31: =SUM(H31:I31) -> 3981003 | K31: 3040602
D32: Due in more than one year | H32: 42264212 | J32: =SUM(H32:I32) -> 42264212 | K32: 24361165
D34: Total Liabilities | H34: =SUM(H26:H32) -> 55105352 | I34: =SUM(I26:I32) -> 246707 | J34: =SUM(J26:J32) -> 55352059 | K34: =SUM(K26:K32) -> 51675396
B36: Deferred outflows of resources
C37: Deferred inflows of resources- pension | H37: 17130 | J37: =SUM(H37:I37) -> 17130 | K37: 3734963
A39: NET ASSETS
B40: Net invested in capital assets | H40: 65174839 | I40: 2477397 | J40: =SUM(H40:I40) -> 67652236 | K40: 258318924
B41: Restricted for:
C42: Capital projects | H42: 19568786 | J42: =SUM(H42:I42) -> 19568786 | K42: 1079044
C43: Debt service | H43: 5955009 | J43: =SUM(H43:I43) -> 5955009 | K43: 3708544
B44: Unrestricted (deficit) | H44: 39408087 | I44: -230802 | J44: =SUM(H44:I44) -> 39177285 | K44: 233541202
C46: Total Net Assets | H46: =SUM(H40:H44) -> 130106721 | I46: =SUM(I40:I44) -> 2246595 | J46: =SUM(J40:J44) -> 132353316 | K46: =SUM(K39:K44) -> 496647714
C48: Total Liabilities and Net Assets | H48: =SUM(H46+H34+H37) -> 185229203 | I48: =SUM(I46+I34+I37) -> 2493302 | J48: =SUM(J46+J34+J37) -> 187722505 | K48: =SUM(K46+K34+K37) -> 552058073

Sheet LaSalle
C1: LaSalle Parish 2015 Statement of Net Assets
C2: Issued: December 31, 2015
G4: Governmental Activities
A5: ASSETS
B6: Cash and cash equivalents | G6: 2710652
B7: Receivables | G7: 3081390
B8: Prepaid lease payments | G8: 9851
B9: Capital assets (net) | G9: 8452909
B11: Total Assets | G11: =SUM(G6:G9) -> 14254802
A13: DEFERRED OUTFLOW OF RESOURCES
B14: Pension related | G14: 121997
G15: =G14 -> 121997
B16: TOTAL ASSETS AND DEFERRED OUTFLOW OF RESOURCES | G16: =G15+G11 -> 14376799
A18: LIABILITIES
B19: Cash overdraft | G19: 166079
B20: Accounts payable | G20: 434518
B21: Payroll payable | G21: 39912
B22: Net pension liability | G22: 151069
B23: Net OPEB obligations | G23: 107621
B24: Long term liabilities:
C25: Due within one year | G25: 231322
C26: Due in more than one year | G26: 69377
C28: Total Liabilities | G28: =SUM(G19:G26) -> 1199898
A30: DEFERRED INFLOW OF RESOURCES
B31: Pension related | G31: 34818
A33: NET ASSETS
B34: Invested in capital assets, net of related debt | G34: 8152210
B35: Unrestricted | G35: 4989473
B37: Total Net Assets | G37: =SUM(G34:G35) -> 13141683
B39: Total Liabilities and Net Assets | G39: =SUM(G28+G37+G31) -> 14376399

Sheet Lincoln
C1: Lincoln Parish 2015 Statement of Net Assets
C2: Issued: December 31, 2015
G4: Governmental Activities
A5: ASSETS
B6: Cash and cash equivalents | G6: 12183072
B7: Investments | G7: 22135974
B8: Receivables | G8: 8644696
B9: Due from other governments | G9: 333786
B10: Inventory | G10: 11582
B11: Capital assets, net of accumulated depreciated | G11: 22658045
B13: Total Assets | G13: =SUM(G6:G11) -> 65967155
A15: DEFERRED OUTFLOWS OF RESOURCES
B16: Pension related | G16: 333795
A18: LIABILITIES
B19: Accounts payable | G19: 1687700
B20: Salaries and related payables | G20: 134316
B21: Due to other agencies | G21: 803497
B22: Compensated absences due within one year | G22: 128050
B23: Bonds payable due within one year | G23: 508000
B24: Bonds payable due in more than one | G24: 2481000
B25: Net OPEB obligation | G25: 1738938
B26: Net pension liability | G26: 161049
C28: Total Liabilities | G28: =SUM(G19:G26) -> 7642550
A30: DEFERRED INFLOWS OF RESOURCES
B31: Pension related | G31: 72700
A33: NET ASSETS
B34: Net investment in capital assets | G34: 19669045
B35: Restricted net position | G35: 3648216
B36: Unrestricted net position | G36: 35268439
B38: Total Net Assets | G38: =SUM(G34:G36) -> 58585700
B40: Total Liabilities and Net Assets | G40: =SUM(G28+G38+G31) -> 66300950

Sheet Livingston
D1: Livingston Parish 2015 Statement of Net Assets
D2: Issued: December 31, 2015
H4: Governmental Activities | I4: Business-Type Activities | J4: Total
A5: ASSETS
C6: Cash and cash equivalents | H6: 10951230 | I6: 424438 | J6: =SUM(H6:I6) -> 11375668
C7: Investments | H7: 3410079 | J7: =SUM(H7:I7) -> 3410079
C8: Receivables, Net of Allowance | H8: 1015336 | I8: 12935 | J8: =SUM(H8:I8) -> 1028271
C9: Inventory | H9: 231759 | J9: =SUM(H9:I9) -> 231759
C10: Internal balances | H10: 22383 | I10: -22383 | J10: =SUM(H10:I10) -> 0
C11: Due from other governments | H11: 12808896 | I11: 2231 | J11: =SUM(H11:I11) -> 12811127
C12: Due from component unit | H12: 116846 | J12: =SUM(H12:I12) -> 116846
C13: Unamortized bond insurance premiums | H13: 313827 | J13: =SUM(H13:I13) -> 313827
C14: Prepaid items | H14: 329158 | I14: 670 | J14: =SUM(H14:I14) -> 329828
C15: Restricted assets
D16: Cash | H16: 6811053 | I16: 106017 | J16: =SUM(H16:I16) -> 6917070
C17: Capital assets
D18: Non-depreciable | H18: 10491236 | I18: 13243 | J18: =SUM(H18:I18) -> 10504479
D19: Depreciable-net | H19: 124998336 | I19: 7037753 | J19: =SUM(H19:I19) -> 132036089
C21: Total Assets | H21: =SUM(H6:H19) -> 171500139 | I21: =SUM(I6:I19) -> 7574904 | J21: =SUM(J6:J19) -> 179075043
B23: Deferred Outflows of Resources
C24: Deferred Amount on Refunding of Debt | H24: 4129145 | J24: =SUM(H24:I24) -> 4129145
C25: Deferred Charges- Pensions | H25: 734791 | J25: =SUM(H25:I25) -> 734791
E27: Total Deferred Outflows of Resources | H27: =SUM(H24:H25) -> 4863936 | I27: =SUM(I24:I25) -> 0 | J27: =SUM(J24:J25) -> 4863936
A29: LIABILITIES
C30: Accounts payable and accrued expenses | H30: 2796656 | I30: 28848 | J30: =SUM(H30:I30) -> 2825504
C31: Due to other governments | H31: 1110280 | J31: =SUM(H31:I31) -> 1110280
C32: Due to component Units | H32: 142562 | J32: =SUM(H32:I32) -> 142562
C33: Unearned revenues | H33: 19700 | J33: =SUM(H33:I33) -> 19700
C34: Accrued bond interest payable | H34: 935076 | I34: 1338 | J34: =SUM(H34:I34) -> 936414
C35: Non-current liabilities
E36: Due within one year | H36: 7473612 | I36: 94408 | J36: =SUM(H36:I36) -> 7568020
E37: Due in more than one year | H37: 71567604 | I37: 2306910 | J37: =SUM(H37:I37) -> 73874514
D39: Total Liabilities | H39: =SUM(H30:H37) -> 84045490 | I39: =SUM(I30:I37) -> 2431504 | J39: =SUM(J30:J37) -> 86476994
B41: Deferred Inflows of Resources
C42: Deferred Charges- Pensions | H42: 117051 | J42: =SUM(H42:I42) -> 117051
D43: Total Deferred Inflows of Resources | H43: =H42 -> 117051 | I43: =I42 -> 0 | J43: =J42 -> 117051
A45: NET ASSETS
B46: Net investment in capital assets | H46: 56844478 | I46: 4650923 | J46: =SUM(H46:I46) -> 61495401
B47: Restricted for:
C48: Construction | H48: 945547 | J48: =SUM(H48:I48) -> 945547
C49: Criminal Court | H49: 79332 | J49: =SUM(H49:I49) -> 79332
C50: Debt Service | H50: 7697876 | J50: =SUM(H50:I50) -> 7697876
C51: Grant | H51: 97896 | J51: =SUM(H51:I51) -> 97896
B52: Unrestricted | H52: 26536405 | I52: 492477 | J52: =SUM(H52:I52) -> 27028882
C54: Total Net Position | H54: =SUM(H46:H52) -> 92201534 | I54: =SUM(I46:I52) -> 5143400 | J54: =SUM(J45:J52) -> 97344934
C56: Total Liabilities and Net Assets | H56: =H54+H39+H43 -> 176364075 | I56: =I54+I39+I43 -> 7574904 | J56: =J54+J39+J43 -> 183938979

Sheet Madison
C1: Madison Parish 2015 Statement of Net Assets
C2: Issued: December 31, 2015
G3: Primary Government
G4: Governmental Activities
A5: ASSETS
B6: Cash and cash equivalents | G6: 6196038
B7: Investments | G7: 3053632
B8: Receivables (net) | G8: 5831186
B9: Capital assets, net | G9: 7751890
B11: Total Assets | G11: =SUM(G6:G9) -> 22832746
A13: Deferred Outflows of Resources | G13: 639383
A15: LIABILITIES
B16: Accounts, salaries and other payables | G16: 406136
B17: Long-term liabilities:
C18: Due within one year | G18: 45871
C19: Due in more than one year | G19: 665717
C21: Total Liabilities | G21: =SUM(G16:G19) -> 1117724
A23: Deferred Inflows of Resources | G23: 41890
A25: NET ASSETS
B26: Invested in capital assets, net of related debt | G26: 7706019
B27: Restricted for:
C28: Library | G28: 1506597
C29: Garbage collection | G29: 1374297
C30: Health unit | G30: 1380616
C31: Drainage and roads | G31: 1845896
C32: Courthouse and jail | G32: 6358091
C33: Other special revenue funds | G33: 1621741
C34: Other purposes | G34: 597493
B35: Unrestricted | G35: -78235
B37: Total Net Position | G37: =SUM(G26:G35) -> 22312515
B39: Total Liabilities and Net Assets | G39: =G37+G21+G23 -> 23472129

Sheet Morehouse
C1: Morehouse Parish 2015 Statement of Net Assets
C2: Issued: December 31, 2015
G4: Governmental Activities
A5: ASSETS
B6: Cash | G6: 4679320
B7: Investments | G7: 540000
B8: Receivables | G8: 2222961
B9: Capital assets:
C10: Land | G10: 778626
C11: Other capital assets, net of depreciation | G11: 12196276
B13: Total Assets | G13: =SUM(G6:G11) -> 20417183
A15: DEFERRED OUTFLOWS OF RESOURCES
B16: Resources related to pension | G16: 235036
A18: LIABILITIES
B19: Bank overdrafts | G19: 2189874
B20: Accounts payable | G20: 183700
B21: Payroll accruals and wothholdings | G21: 46115
B22: Long-term liabilities:
C23: Due within one year | G23: 38154
B24: Net pension | G24: 44944
C26: Total Liabilities | G26: =SUM(G19:G24) -> 2502787
A28: Deferred Inflows of Resources
B29: Property Taxes | G29: 2092981
B30: Resources related to pensions | G30: 20444
C31: Total deferred inflows of resources | G31: =SUM(G29:G30) -> 2113425
A33: NET POSITION
B34: Net Invested in capital assets | G34: 12974902
B35: Restricted for special revenue | G35: 5216951
B36: Unrestricted (deficit) | G36: -2158846
B38: Total Net Position | G38: =SUM(G34:G36) -> 16033007
B40: Total Liabilities and Net Assets | G40: =G38+G26+G31 -> 20649219

Sheet Natchitoches
D1: Natchitoches Parish 2015 Statement of Net Assets
D2: Issued: December 31, 2015
H4: Governmental Activities
A5: ASSETS
B6: Current Assets
C7: Cash and cash equivalents | H7: 8323481
C8: Revenue receivables | H8: 6015839
C9: Total Current Assets | H9: =SUM(H7:H8) -> 14339320
B10: Noncurrent Assets-
C11: Capital Assets (net of accumulated depreciation) | H11: 10781636
C13: Total Assets | H13: =H11+H9 -> 25120956
A15: Deferred Outflows of Resources | H15: 961781
A17: LIABILITIES
B18: Current Liabilities-
C19: Cash overdraft | H19: 5846
C20: Accounts payable | H20: 731262
C21: Accrued payroll | H21: 34379
C22: Due to other governments | H22: 774223
D23: Total Current Liabilities
C24: Long-term Debt-
D25: Accrued Compensated Absences | H25: 143222
D26: OPEB Payable | H26: 1311775
D27: Net Pension Liability | H27: 251910
D29: Total Long-term Liabilities | H29: =SUM(H25:H27) -> 1706907
D31: Total Liabilities | H31: =SUM(H19:H27) -> 3252617
A33: Deferred Inflows of Resources | H33: 162622
A35: NET POSITION
B36: Net investment in capital assets | H36: 10781636
B37: Unrestricted | H37: 11885862
C39: Total Net Position | H39: =SUM(H36:H37) -> 22667498
C41: Total Liabilities and Net Assets | H41: =H39+H33+H31 -> 26082737

Sheet Orleans
D1: Orleans Parish 2015 Statement of Net Assets
D2: Issued: December 31, 2015
H4: Primary Government
H5: Governmental Activities | I5: Component Unit
A6: ASSETS
C7: Cash and cash equivalents | H7: 131482 | I7: 161433
C8: Investments | H8: 227108 | I8: 68663
C9: Receivables (net of allowance for uncollectibles):
D10: Taxes | H10: 28454 | I10: 8486
D11: Accounts | H11: 15445 | I11: 33874
D12: Interest | I12: 56
D13: Grantee loans | H13: 542 | I13: 52808
D14: Other | I14: 4651
C15: Due from component units | H15: 11205
C16: Due from other governments | H16: 39849 | I16: 3467
C17: Other assets | H17: 257 | I17: 46320
C18: Restricted cash and investments | I18: 1052497
C19: Capital assets (net of accumulated depreciation) | H19: 1611132 | I19: 3444536
C21: Total Assets | H21: =SUM(H7:H19) -> 2065474 | I21: =SUM(I7:I19) -> 4876791
A23: Deferred Outflows of Resources
B24: Deferred amounts related to net position liability | H24: 214249 | I24: 23880
B25: Deferred loss on bond refunding | H25: 4679 | I25: 19889
C27: Total deferred outflows of resources | H27: =SUM(H24:H25) -> 218928 | I27: =SUM(I24:I25) -> 43769
A29: LIABILITIES
C30: Accounts payable | H30: 96508 | I30: 60842
C31: Retainage payable | H31: 3483 | I31: 8320
C32: Accrued expenses | H32: 793 | I32: 34075
C33: Taxes payable | H33: 8098
C34: Accrued Interest Payable | H34: 7267 | I34: 26940
C35: Due to component units | H35: 216
C36: Due to other governments | H36: 1890 | I36: 29444
C37: Liabilities payable from restricted assets | I37: 7720
C38: Long-term liabilities due within one year | H38: 109620 | I38: 48456
C39: Long-term liabilities due in more than one year | H39: 2304860 | I39: 1932028
D41: Total Liabilities | H41: =SUM(H30:H39) -> 2532735 | I41: =SUM(I30:I39) -> 2147825
A43: Deferred Inflows of Resources
B44: Deferred amounts related to net position liability | H44: 34976 | I44: 25263
B45: Deferred loss on bond refunding | H45: 1581
B46: Unavailable Revenue | H46: 9295 | I46: 5575
C48: Total deferred inflows of resources | H48: =SUM(H44:H46) -> 45852 | I48: =SUM(I44:I46) -> 30838
A50: NET POSITION
B51: Net investment in capital assets | H51: 933606 | I51: 2342335
B52: Restricted for debt service | H52: 38167 | I52: 131455
B53: Restricted for capital improvement | H53: 75270 | I53: 366441
B54: Restricted for operating reserve | I54: 15800
B55: Unrestricted (deficit) | H55: -1341228 | I55: -115134
C57: Total Net Position | H57: =SUM(H51:H55) -> -294185 | I57: =SUM(I50:I55) -> 2740897
C59: Total Liabilities and Net Assets | H59: =H57+H41+H48 -> 2284402 | I59: =I57+I41+I48 -> 4919560

Sheet Ouachita 
C1: Ouachita Parish 2015 Statement of Net Assets
D2: Issued: December 31, 2015
F5: Governmental Activities | G5: Business-Type Activities | H5: Total
A6: ASSETS
B7: Cash and cash equivalents | F7: 48840225 | G7: 129021 | H7: =SUM(F7:G7) -> 48969246
B8: Investments, at market value | F8: 18766100 | H8: =SUM(F8:G8) -> 18766100
B9: Receivables:
C10: Ad valorem taxes | F10: 32241945 | H10: =SUM(F10:G10) -> 32241945
C11: Sales taxes | F11: 2535630 | H11: =SUM(F11:G11) -> 2535630
C12: Special assessments | F12: 185117 | H12: =SUM(F12:G12) -> 185117
C13: Trade receivables | F13: 979992 | G13: 2372 | H13: =SUM(F13:G13) -> 982364
C14: Other | G14: 29634 | H14: =SUM(F14:G14) -> 29634
B15: Due from other governmental | F15: 5436679 | G15: 1890 | H15: =SUM(F15:G15) -> 5438569
B16: Internal balances | F16: 55570 | G16: -55571 | H16: =SUM(F16:G16) -> -1
B17: Prepaid expenses | F17: 550021 | H17: =SUM(F17:G17) -> 550021
B18: Inventories | F18: 568545 | H18: =SUM(F18:G18) -> 568545
B19: Restricted assets-cash | G19: 58502 | H19: =SUM(F19:G19) -> 58502
B20: Capital assets, net | F20: 183839139 | G20: 2399612 | H20: =SUM(F20:G20) -> 186238751
C22: Total Assets | F22: =SUM(F7:F20) -> 293998963 | G22: =SUM(G7:G20) -> 2565460 | H22: =SUM(H7:H20) -> 296564423
A24: Deferred Outflows of Resources
B25: Deferred charges on pensions | F25: 7023044 | H25: =SUM(F25:G25) -> 7023044
C27: Total deferred outflows of resources | F27: =F25 -> 7023044 | G27: =G25 -> 0 | H27: =H25 -> 7023044
A29: LIABILITIES
B30: Accounts payable and accrued expenses | F30: 6805903 | G30: 7802 | H30: =SUM(F30:G30) -> 6813705
B31: Unearned revenues | F31: 438624 | H31: =SUM(F31:G31) -> 438624
B32: Deposits held | F32: 243741 | H32: =SUM(F32:G32) -> 243741
B33: Long-term liabilities
C34: Due within one year | F34: 1749976 | G34: 25000 | H34: =SUM(F34:G34) -> 1774976
C35: Due in more than one year | F35: 29887275 | G35: 351000 | H35: =SUM(F35:G35) -> 30238275
B36: Other noncurrent liabilities | G36: 2400 | H36: =SUM(F36:G36) -> 2400
D38: Total Liabilities | F38: =SUM(F30:F36) -> 39125519 | G38: =SUM(G30:G36) -> 386202 | H38: =SUM(H30:H36) -> 39511721
A40: Deferred Inflows of Resources
B41: Deferred charges on pensions | F41: 758244 | H41: 4679
C43: Total deferred inflows of resources | F43: =F41 -> 758244 | G43: =G41 -> 0 | H43: =H41 -> 4679
A45: NET POSITION
B46: Net investment in capital assets | F46: 183839139 | G46: 2023612 | H46: =SUM(F46:G46) -> 185862751
B47: Restricted for:
C48: Public works | F48: 8362775 | H48: =SUM(F48:G48) -> 8362775
C49: Public safety | F49: 46259909 | H49: =SUM(F49:G49) -> 46259909
C50: Health and welfare | F50: 4261788 | H50: =SUM(F50:G50) -> 4261788
C51: Culture and recreation | F51: 11448354 | H51: =SUM(F51:G51) -> 11448354
C52: Economic development | F52: 948427 | H52: =SUM(F52:G52) -> 948427
C53: Judicial | F53: 1559222 | H53: =SUM(F53:G53) -> 1559222
C54: Debt service | F54: 98410 | G54: 58502 | H54: =SUM(F54:G54) -> 156912
C55: Capital improvements | F55: 1056212 | H55: =SUM(F55:G55) -> 1056212
C56: Insurance claims | F56: 5064371 | H56: =SUM(F56:G56) -> 5064371
B57: Unrestricted | F57: -1760362 | G57: 97144 | H57: =SUM(F57:G57) -> -1663218
C59: Total Net Position | F59: =SUM(F46:F57) -> 261138245 | G59: =SUM(G46:G57) -> 2179258 | H59: =SUM(H45:H57) -> 263317503
C61: Total Liabilities and Net Assets | F61: =F59+F38 -> 300263764 | G61: =G59+G38 -> 2565460 | H61: =H59+H38 -> 302829224

Sheet Plaquemines
D1: Plaquemines Parish 2015 Statement of Net Assets
D2: Issued: December 31, 2015
H4: Governmental Activities | I4: Business-Type Activities | J4: Total
A5: ASSETS
B6: Current Assets
C7: Cash and cash equivalents | H7: 106567890 | I7: 330318 | J7: =SUM(H7:I7) -> 106898208
C8: Investments | H8: 3103 | J8: =SUM(H8:I8) -> 3103
C9: Receivables (net of allowaces for uncollectibles) | H9: 65493974 | I9: 4920337 | J9: =SUM(H9:I9) -> 70414311
C10: Prepaid items | H10: 1199944 | I10: 6562 | J10: =SUM(H10:I10) -> 1206506
C12: Total Current Assets | H12: =SUM(H7:H10) -> 173264911 | I12: =SUM(I7:I10) -> 5257217 | J12: =SUM(J7:J10) -> 178522128
B14: Non-current Assets:
C15: Internal balances | H15: 2073727 | I15: -2073727 | J15: =SUM(H15:I15) -> 0
C16: Capital assets, net of accumulated depreciation | H16: 329099468 | I16: 79152492 | J16: =SUM(H16:I16) -> 408251960
C17: Capital assets not being depreciated | H17: 135058617 | I17: 26036945 | J17: =SUM(H17:I17) -> 161095562
C19: Total Non-current Assets | H19: =SUM(H14:H17) -> 466231812 | I19: =SUM(I14:I17) -> 103115710 | J19: =SUM(J14:J17) -> 569347522
C21: Total Assets | H21: =SUM(H12+H19) -> 639496723 | I21: =SUM(I12+I19) -> 108372927 | J21: =SUM(J12+J19) -> 747869650
A23: Deferred Outflows of Resources:
B24: Deferred outflows related to net pension liability | H24: 7317000 | I24: 163693 | J24: =SUM(H24:I24) -> 7480693
C25: Total Assets and Deferred Outflows of Resources | H25: =H24+H21 -> 646813723 | I25: =I24+I21 -> 108536620 | J25: =J24+J21 -> 755350343
A27: LIABILITIES
B28: Current Liabilities:
C29: Cash overdraft | I29: 4933197 | J29: =SUM(H29:I29) -> 4933197
C30: Accounts, salaries and other payables | H30: 13601682 | I30: 723370 | J30: =SUM(H30:I30) -> 14325052
C31: Bonds payable | H31: 3895000 | J31: =SUM(H31:I31) -> 3895000
C32: Capital leases payable | H32: 49724 | J32: =SUM(H32:I32) -> 49724
C33: Unearned revenues | H33: 11382905 | J33: =SUM(H33:I33) -> 11382905
C34: Accrued interest payable | H34: 1531476 | J34: =SUM(H34:I34) -> 1531476
C35: Compensated absences payable | H35: 1085692 | I35: 40681 | J35: =SUM(H35:I35) -> 1126373
C36: Deposits due others | H36: 35330 | I36: 429470 | J36: =SUM(H36:I36) -> 464800
C37: Other | H37: 963639 | I37: 130128 | J37: =SUM(H37:I37) -> 1093767
D39: Total Current Liabilities | H39: =SUM(H29:H37) -> 32545448 | I39: =SUM(I29:I37) -> 6256846 | J39: =SUM(J29:J37) -> 38802294
B41: Non-current Liabilities
C42: Litigation and other contingencies | H42: 4526860 | J42: =SUM(H42:I42) -> 4526860
C43: Capital leases payable | H43: 126286 | J43: =SUM(H43:I43) -> 126286
C44: Notes payable-long term | H44: 2989446 | J44: =SUM(H44:I44) -> 2989446
C45: Bonds payable-long term | H45: 114902122 | J45: =SUM(H45:I45) -> 114902122
C46: Other post-employment benefits payable | H46: 24017610 | I46: 869565 | J46: =SUM(H46:I46) -> 24887175
C47: Net pension liability | H47: 9876324 | I47: 32996 | J47: =SUM(H47:I47) -> 9909320
D49: Total Non-current Liabilities | H49: =SUM(H42:H47) -> 156438648 | I49: =SUM(I42:I47) -> 902561 | J49: =SUM(J42:J47) -> 157341209
D51: Total Liabilities | H51: =SUM(H39+H49) -> 188984096 | I51: =SUM(I49+I39) -> 7159407 | J51: =SUM(J39+J49) -> 196143503
A53: Deferred Inflows of Resources:
B54: Deferred inflows related to net pension liability | H54: 1009468 | I54: 14817 | J54: =SUM(H54:I54) -> 1024285
C55: Total Assets and Deferred Outflows of Resources | H55: =H54+H50 -> 1009468 | I55: =I54+I50 -> 14817 | J55: =J54+J50 -> 1024285
A57: NET POSITION
B58: Invested in capital assets | H58: 345913086 | I58: 105189437 | J58: =SUM(H58:I58) -> 451102523
B59: Restricted | H59: 83817891 | J59: =SUM(H59:I59) -> 83817891
B60: Unrestricted (deficit) | H60: 27089182 | I60: -3827041 | J60: =SUM(H60:I60) -> 23262141
C62: Total Net Position | H62: =SUM(H58:H60) -> 456820159 | I62: =SUM(I58:I60) -> 101362396 | J62: =SUM(J57:J60) -> 558182555
C64: Total Liabilities, Deferred Inflows of Resources, and Net Position | H64: =SUM(H51+H62+H55) -> 646813723 | I64: =SUM(I51+I62+I55) -> 108536620 | J64: =SUM(J51+J62+J55) -> 755350343

Sheet Pointe Couppe
C1: Pointe Coupee Parish 2015 Statement of Net Assets
D2: Issued: December 31, 2015
F4: Primary Government | I4: Component Units
F5: Governmental Activities | G5: Business-Type Activities | H5: Total | I5: Business-Type Activities
A6: ASSETS
B7: Cash and cash equivalents | F7: 3316480 | G7: 1183805 | H7: =SUM(F7:G7) -> 4500285 | I7: 197148
B8: Investments | F8: 141853 | H8: =SUM(F8:G8) -> 141853 | I8: 181195
B9: Accounts receivable, net | F9: 3467205 | G9: 510331 | H9: =SUM(F9:G9) -> 3977536 | I9: 170359
B10: Due from other governments | F10: 597623 | G10: 26465 | H10: =SUM(F10:G10) -> 624088 | I10: 117188
B11: Due from fiduciary funds | F11: 126524 | H11: =SUM(F11:G11) -> 126524
B12: Internal balances | F12: 818000 | G12: -818000 | H12: =SUM(F12:G12) -> 0
B13: Prepaid items | F13: 110525 | G13: 1136 | H13: =SUM(F13:G13) -> 111661 | I13: 5350
B14: Other assets | F14: 15537 | G14: 24921 | H14: =SUM(F14:G14) -> 40458 | I14: 519
B15: Capital assets: | H15: =SUM(F15:G15) -> 0
C16: Non-depreciable | F16: 4044749 | G16: 236768 | H16: =SUM(F16:G16) -> 4281517 | I16: 81400
C17: Depreciable, net | F17: 15190315 | G17: 2083978 | H17: =SUM(F17:G17) -> 17274293 | I17: 4616543
C19: Total Assets | F19: =SUM(F7:F17) -> 27828811 | G19: =SUM(G7:G17) -> 3249404 | H19: =SUM(H7:H17) -> 31078215 | I19: =SUM(I7:I17) -> 5369702
A21: LIABILITIES
B22: Accounts payable and accrued liabilities | F22: 1805749 | G22: 200793 | H22: =SUM(F22:G22) -> 2006542 | I22: 89944
B23: Due to other governments | F23: 519937 | H23: =SUM(F23:G23) -> 519937 | I23: 220000
B24: Customer meter deposits | G24: 803565 | H24: =SUM(F24:G24) -> 803565
B25: Long term payables: | H25: =SUM(F25:G25) -> 0
C26: Due within one year | F26: 495471 | G26: 98061 | H26: =SUM(F26:G26) -> 593532 | I26: 62741
C27: Due in more than one year | F27: 5664157 | G27: 358880 | H27: =SUM(F27:G27) -> 6023037 | I27: 1408611
C28: Other post-employment benefits | F28: 2004255 | H28: =SUM(F28:G28) -> 2004255
C29: Net pension liability | F29: 152946 | G29: 21307 | H29: =SUM(F29:G29) -> 174253
D31: Total Liabilities | F31: =SUM(F22:F29) -> 10642515 | G31: =SUM(G22:G29) -> 1482606 | H31: =SUM(H22:H29) -> 12125121 | I31: =SUM(I22:I29) -> 1781296
A33: Deferred Inflows of Resources
B34: Pension liability | F34: 61852 | G34: 9639 | H34: =SUM(F34:G34) -> 71491 | I34: 0
C35: Total deferred inflows of resources | F35: =F34 -> 61852 | G35: =G34 -> 9639 | H35: =H34 -> 71491 | I35: =I34 -> 0
C37: Total liabilities and deferred inflows of resources | F37: =F35+F31 -> 10704367 | G37: =G35+G31 -> 1492245 | H37: =H35+H31 -> 12196612 | I37: =I35+I31 -> 1781296
A39: NET ASSETS
B40: Invested in capital assets, net of related debt | F40: 13322085 | G40: 1863805 | H40: =SUM(F40:G40) -> 15185890 | I40: 3226591
B41: Restricted for:
C42: Library operations | F42: 4151746 | H42: =SUM(F42:G42) -> 4151746
C43: Road construction and maintenance | F43: 495092 | H43: =SUM(F43:G43) -> 495092
C44: Debt service | F44: 1930745 | G44: 35563 | H44: =SUM(F44:G44) -> 1966308 | I44: 80745
B45: Unrestricted | F45: -2231273 | G45: -33436 | H45: =SUM(F45:G45) -> -2264709 | I45: 281070
C47: Total Net Assets | F47: =SUM(F40:F45) -> 17668395 | G47: =SUM(G40:G45) -> 1865932 | H47: =SUM(H40:H45) -> 19534327 | I47: =SUM(I40:I45) -> 3588406
C49: Total Liabilities, deferred inflows of resources, and Net Assets | F49: =SUM(F31+F47+F34) -> 28372762 | G49: =SUM(G31+G47+G34) -> 3358177 | H49: =SUM(H31+H47+H34) -> 31730939 | I49: =SUM(I31+I47+I34) -> 5369702

Sheet Rapides
D1: Rapides Parish 2015 Statement of Net Assets
D2: Issued: December 31, 2015
H5: 2015 | I5: 2014
A6: ASSETS
C7: Cash and cash equivalents | H7: 43047450 | I7: 51085465
C8: Receivables | H8: 22738987 | I8: 22832720
C9: Other assets | I9: 516
C10: Capital assets (net of accumulated depreciation):
D11: Nondepreciable:
E12: Land | H12: 3125048 | I12: 1091998
E13: Construction in progress | H13: 12342066 | I13: 4503009
D14: Depreciable:
E15: Buildings and improvements | H15: 9922928 | I15: 10023028
E16: Furniture, equipment, and other | H16: 7374755 | I16: 8034400
E17: Infrastructure | H17: 31353451 | I17: 29558510
D18: Deferred outflows related to pensions | H18: 4009397
C20: Total Assets | H20: =SUM(H7:H18) -> 133914082 | I20: =SUM(I7:I18) -> 127129646
A22: LIABILITIES
C23: Accounts, salaries, and other payables | H23: 666080 | I23: 916265
C24: Deferred revenues | H24: 715461 | I24: 632212
C25: Interest payable | H25: 843394 | I25: 881344
C26: Long-term liabilities:
D27: Due within one year | H27: 1701962 | I27: 1660074.2
D28: Due in more than one year | H28: 62946023 | I28: 59740213
C29: Deferred inflows related to pensions | H29: 1103597
D31: Total Liabilities | H31: =SUM(H23:H29) -> 67976517 | I31: =SUM(I23:I29) -> 63830108
A33: NET ASSETS
B34: Invested in capital assets, net of related debt | H34: 38384558 | I34: 26878874
B35: Restricted for debt service | H35: 3526607 | I35: 3296486
B36: Unrestricted | H36: 24026401 | I36: 34024176
C38: Total Net Position | H38: =SUM(H34:H36) -> 65937566 | I38: =SUM(I33:I36) -> 64199536
C40: Total Liabilities and Net Assets | H40: =H38+H31 -> 133914083 | I40: =I38+I31 -> 1.2802964e+08

Sheet Red River
D1: Red River Parish 2015 Statement of Net Assets
D2: Issued: December 31, 2015
H4: Governmental Activities | I4: Business-Type Activities | J4: Total
A5: ASSETS
B6: Current Assets
C7: Cash and cash equivalents | H7: 17711401 | I7: 93641 | J7: =SUM(H7:I7) -> 17805042
C8: Investments | H8: 15684226 | J8: =SUM(H8:I8) -> 15684226
C9: Receivables | H9: 4685543 | I9: 807 | J9: =SUM(H9:I9) -> 4686350
C10: Prepaid expense | H10: 20239 | J10: =SUM(H10:I10) -> 20239
C12: Total Current Assets | H12: =SUM(H7:H10) -> 38101409 | I12: =SUM(I7:I10) -> 94448 | J12: =SUM(J7:J10) -> 38195857
B14: Non-current Assets:
C15: Capital assets, net of accumulated depreciation | H15: 16044475 | I15: 205220 | J15: =SUM(H15:I15) -> 16249695
C17: Total Assets | H17: =SUM(H12+H15) -> 54145884 | I17: =SUM(I12+I15) -> 299668 | J17: =SUM(J12+J15) -> 54445552
A19: DEFERRED OUTFLOWS OF RESOURCES | H19: 384360 | J19: =SUM(H19:I19) -> 384360
A21: LIABILITIES
B22: Current Liabilities:
C23: Accounts payable and accured liabilities | H23: 782052 | I23: 3934 | J23: =SUM(H23:I23) -> 785986
C24: Compensated absences payable | H24: 47794 | J24: =SUM(H24:I24) -> 47794
D26: Total Current Liabilities | H26: =SUM(H23:H24) -> 829846 | I26: =SUM(I23:I24) -> 3934 | J26: =SUM(J23:J24) -> 833780
B28: Non-current Liabilities
C29: Compensated absences payable, net of current portion | H29: 17061 | J29: =SUM(H29:I29) -> 17061
C30: Net pension liability | H30: 115212 | J30: =SUM(H30:I30) -> 115212
C31: Other post-employment benefits payable | H31: 177785 | J31: =SUM(H31:I31) -> 177785
D33: Total Non-current Liabilities | H33: =SUM(H29:H31) -> 310058 | I33: =SUM(I29:I31) -> 0 | J33: =SUM(J29:J31) -> 310058
D35: Total Liabilities | H35: =SUM(H26+H33) -> 1139904 | I35: =SUM(I26+I33) -> 3934 | J35: =SUM(J26+J33) -> 1143838
A37: DEFERRED INFLOWS OF RESOURCES | H37: 64801 | J37: =SUM(H37:I37) -> 64801
A39: NET POSITION
B40: Net investment in capital assets | H40: 16044475 | I40: 205220 | J40: =SUM(H40:I40) -> 16249695
B41: Restricted for:
C42: Sales tax dedicated for the maintenance of ambulances, | J42: =SUM(H42:I42) -> 0
D43: the costs to provide services, and tourism | H43: 5744400
C44: Dedicated property taxes for library services | H44: 4874153 | J44: =SUM(H44:I44) -> 4874153
C45: Dedicated property taxes for health unit services and construction | H45: 2292400 | J45: =SUM(H45:I45) -> 2292400
C46: External legal constraints for juror and witness compensation | H46: 200499 | J46: =SUM(H46:I46) -> 200499
C47: External legal contraints for federal and sate grant programs | H47: 455932 | J47: =SUM(H47:I47) -> 455932
B48: Unrestricted | H48: 23713680 | I48: 90514 | J48: =SUM(H48:I48) -> 23804194
C50: Total Net Assets | H50: =SUM(H40:H48) -> 53325539 | I50: =SUM(I40:I48) -> 295734 | J50: =SUM(J40:J48) -> 47876873
C52: Total Liabilities and Net Assets | H52: =SUM(H35+H50+H37) -> 54530244 | I52: =SUM(I35+I50+I37) -> 299668 | J52: =SUM(J35+J50+J37) -> 49085512

Sheet Richland
C1: Richland Parish 2015 Statement of Net Assets
C2: Issued: December 31, 2015
G4: Governmental Activities
A5: ASSETS
B6: Cash | G6: 8166634
B7: Receivables | G7: 2798324
B8: Capital assets:
C9: Land | G9: 300273
C10: Other capital assets, net of depreciation | G10: 2270299
B12: Total Assets | G12: =SUM(G6:G10) -> 13535530
A14: DEFERRED OUTFLOWS OF RESOURCES
B15: Resources related to pension | G15: 463319
A17: LIABILITIES
B18: Accounts payable | G18: 250383
B19: Payroll accruals and wothholding | G19: 61306
B20: Net pension | G20: 84471
C22: Total Liabilities | G22: =SUM(G18:G20) -> 396160
A24: DEFERRED INFLOWS OF RESOURCES
B25: Property taxes | G25: 2700584
B26: Resources related to pensions | G26: 37551
C27: Total deferred inflows of resources | G27: =SUM(G25:G26) -> 2738135
A29: NET POSITION
B30: Net investment in capital assets | G30: 2570572
B31: Restricted for special revenue | G31: 6385675
B32: Unrestricted | G32: 1908307
B34: Total Net Position | G34: =SUM(G30:G32) -> 10864554
B36: Total Liabilities and Net Assets | G36: =G34+G22+G27 -> 13998849

Sheet Sabine
D1: Sabine Parish 2015 Statement of Net Assets
D2: Issued: December 31, 2015
H5: 2015 | I5: 2014
A6: ASSETS
C7: Cash and cash equivalents | H7: 10266086 | I7: 9360736
C8: Receivables | H8: 3646800 | I8: 3889321
C9: Capital assets (net of accumulated depreciation):
E10: Land | H10: 639576 | I10: 639576
E11: Construction in progress | I11: 2281793
E12: Buildings and improvements | H12: 2129702 | I12: 2199290
E13: Machinery and equipment | H13: 2983878 | I13: 2943475
E14: Furniture, equipment, and other | H14: 21081 | I14: 12573
E15: Infrastructure:
F16: Roads | H16: 3372200 | I16: 1123833
F17: Road right-of-way | H17: 995977 | I17: 995977
F18: Bridges | H18: 3592792 | I18: 3681027
C19: Deferred outflows related to pensions | H19: 356746
C21: Total Assets | H21: =SUM(H7:H19) -> 28004838 | I21: =SUM(I7:I19) -> 27127601
A23: LIABILITIES
C24: Accounts, salaries, and other payables | H24: 389069 | I24: 477050
C25: Interest payable | H25: 927 | I25: 6775
C26: Long-term liabilities:
D27: Due within one year | H27: 122083 | I27: 351017
D28: Due in more than one year | H28: 1275594 | I28: 1010869
C29: Deferred inflows related to pensions | H29: 48002
D31: Total Liabilities | H31: =SUM(H24:H29) -> 1835675 | I31: =SUM(I24:I29) -> 1845711
A33: NET POSITION
B34: Invested in capital assets, net of related debt | H34: 13686433 | I34: 13520414
B35: Unrestricted | H35: 12482731 | I35: 11761476
C37: Total Net Position | H37: =SUM(H34:H35) -> 26169164 | I37: =SUM(I33:I35) -> 25281890
C39: Total Liabilities and Net Assets | H39: =H37+H31 -> 28004839 | I39: =I37+I31 -> 27127601

Sheet St. Bernard
C1: St. Bernard Parish 2015 Statement of Net Assets
D2: Issued: December 31, 2015
F5: Governmental Activities | G5: Business-Type Activities | H5: Total
A6: ASSETS
B7: Cash and cash equivalents | F7: 36775410 | G7: 6883481 | H7: =SUM(F7:G7) -> 43658891
B8: Investments | F8: 1068813 | H8: =SUM(F8:G8) -> 1068813
B9: Investments--land held for sale | F9: 3650500 | H9: =SUM(F9:G9) -> 3650500
B10: Receivables | H10: =SUM(F10:G10) -> 0
C11: Sales and use taxes | F11: 2177956 | G11: 545374 | H11: =SUM(F11:G11) -> 2723330
C12: Property taxes | F12: 12806109 | H12: =SUM(F12:G12) -> 12806109
C13: Cable franchise fees | F13: 123670 | H13: =SUM(F13:G13) -> 123670
C14: Customer | G14: 1010725 | H14: =SUM(F14:G14) -> 1010725
C15: Intergovernmental | F15: 21146438 | H15: =SUM(F15:G15) -> 21146438
C16: Other | F16: 790300 | G16: 15236 | H16: =SUM(F16:G16) -> 805536
B17: Unbilled charges | G17: 674500 | H17: =SUM(F17:G17) -> 674500
B18: Internal balances | F18: -4467781 | G18: 4467781 | H18: =SUM(F18:G18) -> 0
B19: Prepaid expidentures | F19: 251411 | G19: 126239 | H19: =SUM(F19:G19) -> 377650
B20: Inventory | G20: 336677 | H20: =SUM(F20:G20) -> 336677
B21: Restricted assets--cash and cash equivalents | G21: 59215577 | H21: =SUM(F21:G21) -> 59215577
B22: Loan and interest receivable | G22: 816000 | H22: =SUM(F22:G22) -> 816000
B23: Capital assets
C24: Land, improvements and construction in progess | F24: 54653576 | G24: 59767224 | H24: =SUM(F24:G24) -> 114420800
C25: Other capital assets, net of depreciation | F25: 336472221 | G25: 147240903 | H25: =SUM(F25:G25) -> 483713124
C27: Total Assets | F27: =SUM(F7:F25) -> 465448623 | G27: =SUM(G7:G25) -> 281099717 | H27: =SUM(H7:H25) -> 746548340
A29: DEFERRED OUTFLOWS OF RESOURCES
B30: Deferred outflows on pension obligation | F30: 4542971 | G30: 488361 | H30: =SUM(F30:G30) -> 5031332
C31: Total deferred outflows of resources | F31: =F30 -> 4542971 | G31: =G30 -> 488361 | H31: =H30 -> 5031332
A33: LIABILITIES
B34: Accounts payable | F34: 17765212 | G34: 1586052 | H34: =SUM(F34:G34) -> 19351264
B35: Claims payable | F35: 2443606 | G35: 527050 | H35: =SUM(F35:G35) -> 2970656
B36: Retainage payable | F36: 2434458 | H36: =SUM(F36:G36) -> 2434458
B37: Salaries and payroll deductions payable | F37: 1350447 | G37: 143647 | H37: =SUM(F37:G37) -> 1494094
B38: Customer deposits | G38: 1269903 | H38: =SUM(F38:G38) -> 1269903
B39: Accrued interest payable | F39: 420197 | G39: 134642 | H39: =SUM(F39:G39) -> 554839
B40: Advance collections | F40: 69188 | G40: 151913 | H40: =SUM(F40:G40) -> 221101
B41: Certificates of indebtedness | F41: 2215662 | H41: =SUM(F41:G41) -> 2215662
B42: Long term non-cuttent liabilities
C43: Due within one year | F43: 4044111 | G43: 1132511 | H43: =SUM(F43:G43) -> 5176622
C44: Due in more than one year | F44: 48685849 | G44: 3449383 | H44: =SUM(F44:G44) -> 52135232
D46: Total Liabilities | F46: =SUM(F34:F44) -> 79428730 | G46: =SUM(G34:G44) -> 8395101 | H46: =SUM(H34:H44) -> 87823831
A48: DEFERRED INFLOWS OF RESOURCES
B49: Deferred outflows on pension obligation | F49: 1282878 | G49: 100945 | H49: =SUM(F49:G49) -> 1383823
C50: Total deferred inflows of resources | F50: =F49 -> 1282878 | G50: =G49 -> 100945 | H50: =H49 -> 1383823
A52: NET ASSETS
B53: Invested in capital assets | F53: 357038864 | G53: 196619074 | H53: =SUM(F53:G53) -> 553657938
B54: Restricted for: | H54: =SUM(F54:G54) -> 0
C55: Capital projects | F55: 313966 | G55: 2888617 | H55: =SUM(F55:G55) -> 3202583
C56: Debt service | F56: 3561965 | G56: 2462903 | H56: =SUM(F56:G56) -> 6024868
C57: Federal programs | F57: 5815731 | H57: =SUM(F57:G57) -> 5815731
C58: Public safety | F58: 3099269 | H58: =SUM(F58:G58) -> 3099269
C59: Other purposes | F59: 2445691 | G59: 4 | H59: =SUM(F59:G59) -> 2445695
B60: Unrestricted | F60: 21004500 | G60: 17827434 | H60: =SUM(F60:G60) -> 38831934
C62: Total Net Assets | F62: =SUM(F53:F60) -> 393279986 | G62: =SUM(G53:G60) -> 219798032 | H62: =SUM(H52:H60) -> 613078018
C64: Total Liabilities and Net Assets | F64: =F62+F46+F50 -> 473991594 | G64: =G62+G46+G50 -> 228294078 | H64: =H62+H46+H50 -> 702285672

Sheet St. Charles
D1: St. Charles Parish 2015 Statement of Net Assets
D2: Issued: December 31, 2015
H4: Primary Government
H5: Governmental Activities | I5: Business-Type Activities | J5: Total | K5: Component Units
A6: ASSETS
C7: Cash and cash equivalents | H7: 1666632 | I7: 293475 | J7: =SUM(H7:I7) -> 1960107 | K7: 7895309
C8: Investments | H8: 83769353 | I8: 684440 | J8: =SUM(H8:I8) -> 84453793 | K8: 9327615
C9: Receivables, net | H9: 29459890 | I9: 3506013 | J9: =SUM(H9:I9) -> 32965903 | K9: 13060701
C10: Due from other governments | H10: 5113293 | I10: 116328 | J10: 5559621 | K10: 17963
C11: Due from primary government | J11: =SUM(H11:I11) -> 0 | K11: 3829
C12: Inventory | I12: 485187 | J12: =SUM(H12:I12) -> 485187 | K12: 1249209
C13: Prepaid fees | H13: 474947 | I13: 44262 | J13: =SUM(H13:I13) -> 519209 | K13: 141326
C14: Other assets | H14: 4270 | I14: 182 | J14: =SUM(H14:I14) -> 4452 | K14: 1737582
C15: Restricted assets | J15: =SUM(H15:I15) -> 0
D16: Cash and cash equivalents | I16: 40375 | J16: =SUM(H16:I16) -> 40375 | K16: 6060202
D17: Investments | I17: 6887998 | J17: =SUM(H17:I17) -> 6887998
C18: Capital assets, net | J18: =SUM(H18:I18) -> 0
D19: Land | H19: 10669811 | I19: 824777 | J19: =SUM(H19:I19) -> 11494588 | K19: 1586680
D20: Infrastructure | H20: 55386536 | J20: =SUM(H20:I20) -> 55386536
D21: Plant and equipment | H21: 98272578 | I21: 125671345 | J21: =SUM(H21:I21) -> 223943923 | K21: 30507506
D22: Construction in progress | H22: 51853809 | I22: 2642348 | J22: =SUM(H22:I22) -> 54496157 | K22: 11413600
C24: Total Assets | H24: =SUM(H7:H22) -> 336671119 | I24: =SUM(I7:I22) -> 141196730 | J24: =SUM(H24:I24) -> 477867849 | K24: =SUM(K7:K22) -> 83001522
A26: Deferred Outflows of Resources
B27: Deferred Inflows- Pension | H27: 6025080 | I27: 2541799 | J27: =SUM(H27:I27) -> 8566879 | K27: 755462
D29: Total deferred inflows of resources | H29: =H27 -> 6025080 | I29: =I27 -> 2541799 | J29: =J27 -> 8566879 | K29: =K27 -> 755462
A31: LIABILITIES
C32: Accounts payable and other current liabilities | H32: 5754316 | I32: 900665 | J32: =SUM(H32:I32) -> 6654981 | K32: 1725557
C33: Due to component units | H33: 3829 | J33: =SUM(H33:I33) -> 3829
C34: Due to other governments | H34: 484951 | J34: =SUM(H34:I34) -> 484951
C35: Interest payable | H35: 96493 | J35: =SUM(H35:I35) -> 96493
C36: Other liabilities and accruals | H36: 1144190 | I36: 305331 | J36: =SUM(H36:I36) -> 1449521 | K36: 10430882
C37: Liabilities payable from restricted assets | I37: 1598190 | J37: =SUM(H37:I37) -> 1598190
C38: Non-current liabilities | J38: =SUM(H38:I38) -> 0
D39: Amounts due within one year | H39: 4004000 | I39: 1248000 | J39: =SUM(H39:I39) -> 5252000 | K39: 4019613
D40: Amounts due beyond one year | H40: 23758074 | I40: 25820842 | J40: =SUM(H40:I40) -> 49578916 | K40: 62625233
D41: Net Pension Liability | H41: 819755 | I41: 298639 | J41: =SUM(H41:I41) -> 1118394 | K41: 88760
D42: Multi-employer Pension Liability | K42: 3716687
D43: Other non-current liabilities | J43: =SUM(H43:I43) -> 0 | K43: 17452
D45: Total Liabilities | H45: =SUM(H32:H43) -> 36065608 | I45: =SUM(I32:I43) -> 30171667 | J45: =SUM(J32:J43) -> 66237275 | K45: =SUM(K32:K43) -> 82624184
A47: Deferred Inflows of Resources
B48: Advances | H48: 26277207 | J48: =SUM(H48:I48) -> 26277207 | K48: 5487598
B49: Deferred Inflows- Pension | H49: 492597 | I49: 134136 | J49: =SUM(H49:I49) -> 626733 | K49: 39867
B50: Gain on Bond Refunding | H50: 1227798 | I50: 4432193 | J50: =SUM(H50:I50) -> 5659991
D52: Total deferred inflows of resources | H52: =SUM(H48:H50) -> 27997602 | I52: =SUM(I48:I50) -> 4566329 | J52: =SUM(J48:J50) -> 32563931 | K52: =SUM(K48:K50) -> 5527465
A54: NET ASSETS
B55: Invested in capital assets | H55: 203387734 | I55: 102069628 | J55: =SUM(H55:I55) -> 305457362 | K55: -17087188
B56: Restricted for: | J56: =SUM(H56:I56) -> 0
C57: Maintenance/operations | H57: 21557419 | J57: =SUM(H57:I57) -> 21557419
C58: Debt service | H58: 4716112 | I58: 2471579 | J58: =SUM(H58:I58) -> 7187691
C59: Capital projects | H59: 8024372 | I59: 7418328 | J59: =SUM(H59:I59) -> 15442700 | K59: 140449
C60: Special Revenues | J60: =SUM(H60:I60) -> 0
D61: Maintanence/Operations | H61: 8044395 | J61: =SUM(H61:I61) -> 8044395
B62: Unrestricted | H62: 33232957 | I62: -2959002 | J62: =SUM(H62:I62) -> 30273955 | K62: 12552074
C64: Total Net Assets | H64: =SUM(H55:H62) -> 278962989 | I64: =SUM(I55:I62) -> 109000533 | J64: =SUM(J55:J62) -> 387963522 | K64: =SUM(K54:K62) -> -4394665
C66: Total Liabilities and Net Assets | H66: =H64+H45+H52 -> 343026199 | I66: =I64+I45+I52 -> 143738529 | J66: =J64+J45+J52 -> 486764728 | K66: =K64+K45+K52 -> 83756984

Sheet St. Helena 
D1: St. Helena Parish 2015 Statement of Net Assets
D2: Issued: December 31, 2015
H3: Primary Government | I3: Discretely Presented Component Units
H4: Governmental Activities | I4: St. Helena Parish Hospital Serv Dist 1 & Subsidiary | J4: Water Works Dist No. 2 of St. Helena Parish | K4: Other Component Units | L4: Total Component Units
A5: ASSETS
B6: Current Assets:
C7: Cash and cash equivalents | H7: 5723972 | I7: 1278648 | J7: 877015 | K7: 449184 | L7: =SUM(I7:K7) -> 2604847
C8: Investments | H8: 561779 | K8: 20180 | L8: =SUM(I8:K8) -> 20180
C9: Receivables, net | H9: 2510451 | I9: 3797489 | J9: 127929 | K9: 351631 | L9: =SUM(I9:K9) -> 4277049
C10: Due from component units | L10: =SUM(I10:K10) -> 0
C11: Inventory | I11: 369128 | J11: 47487 | L11: =SUM(I11:K11) -> 416615
C12: Prepaid insurance and other assets | H12: 107473 | I12: 19061 | J12: 5614 | K12: 7243 | L12: =SUM(I12:K12) -> 31918
B13: Total current assets | H13: =SUM(H7:H12) -> 8903675 | I13: =SUM(I7:I12) -> 5464326 | J13: =SUM(J7:J12) -> 1058045 | K13: =SUM(K7:K12) -> 828238 | L13: =SUM(L7:L12) -> 7350609
B15: Restricted assets:
C16: Restricted cash and cash equivalents | H16: 393912 | I16: 711595 | J16: 790541 | L16: =SUM(I16:K16) -> 1502136
B17: Total restricted assets | H17: =SUM(H16) -> 393912 | I17: =SUM(I16) -> 711595 | J17: =SUM(J16) -> 790541 | K17: =SUM(K16) -> 0 | L17: =SUM(L16) -> 1502136
B19: Long term assets:
C20: Investments
B21: Total long term assets
B23: Capital assets:
C24: Land | H24: 242736 | J24: 47631 | L24: =SUM(I24:K24) -> 47631
C25: Capital assets, net | H25: 17553409 | I25: 5755516 | J25: 7318285 | K25: 864754 | L25: =SUM(I25:K25) -> 13938555
B27: Total capital assets | H27: =SUM(H24:H25) -> 17796145 | I27: =SUM(I24:I25) -> 5755516 | J27: =SUM(J24:J25) -> 7365916 | K27: =SUM(K24:K25) -> 864754 | L27: =SUM(L24:L25) -> 13986186
C29: Total Assets | H29: =SUM(H13+H17+H21+H27) -> 27093732 | I29: =I27+I21+I17+I13 -> 11931437 | J29: =J27+J21+J17+J13 -> 9214502 | K29: =K27+K21+K17+K13 -> 1692992 | L29: =L27+L21+L17+L13 -> 22838931
A31: DEFERRED OUTFLOWS OF RESOURCES
B32: Pension related | H32: 289712
C33: Total Deferred Outflows of Resources | H33: =H32 -> 289712 | I33: =I32 -> 0 | J33: =J32 -> 0 | K33: =K32 -> 0 | L33: =L32 -> 0
A35: LIABILITIES
B36: Current liabilities:
C37: Accounts payable | H37: 447710 | I37: 1061127 | J37: 102879 | K37: 9810 | L37: =SUM(I37:K37) -> 1173816
C38: Other accrued payables | H38: 63333 | J38: 354497 | K38: 8816 | L38: =SUM(I38:K38) -> 363313
C39: Interim Financing | J39: 498000
C40: Accrued interest on long term indebtedness | H40: 17955 | J40: 23833 | K40: 4093 | L40: =SUM(I40:K40) -> 27926
C41: Customer deposits | J41: 92855 | L41: =SUM(I41:K41) -> 92855
C42: Current portion of long term indebtedness
D43: Bonds payable | H43: 346000 | I43: 487967 | J43: 95700 | K43: 44384 | L43: =SUM(I43:K43) -> 628051
D44: Capital leases | H44: 168310 | L44: =SUM(I44:K44) -> 0
B45: Total current liabilities: | H45: =SUM(H37:H44) -> 1043308 | I45: =SUM(I37:I44) -> 1549094 | J45: =SUM(J37:J44) -> 1167764 | K45: =SUM(K37:K44) -> 67103 | L45: =SUM(L37:L44) -> 2285961
B47: Long term liabilities:
C48: Bonds payable | H48: 1519000 | I48: 3714519 | J48: 3358678 | K48: 308444 | L48: =SUM(I48:K48) -> 7381641
C49: Capital leases | H49: 243047 | L49: =SUM(I49:K49) -> 0
C50: Compensated absences payable | H50: 290570 | L50: =SUM(I50:K50) -> 0
C51: Unfunded net other post employment benefit obligations | H51: 1434057 | L51: =SUM(I51:K51) -> 0
C52: Net pension liability | H52: 94328
B53: Total long term liabilities | H53: =SUM(H48:H52) -> 3581002 | I53: =SUM(I48:I52) -> 3714519 | J53: =SUM(J48:J52) -> 3358678 | K53: =SUM(K48:K52) -> 308444 | L53: =SUM(L48:L52) -> 7381641
D55: Total Liabilities | H55: =H45+H53 -> 4624310 | I55: =I45+I53 -> 5263613 | J55: =J45+J53 -> 4526442 | K55: =K45+K53 -> 375547 | L55: =L45+L53 -> 9667602
A57: DEFERRED INFLOWS OF RESOURCES
B58: Pension related | H58: 54780
C59: Total Deferred Inflows of Resources | H59: =H58 -> 54780 | I59: =I58 -> 0 | J59: =J58 -> 0 | K59: =K58 -> 0 | L59: =L58 -> 0
A61: NET ASSETS
B62: Net investment in capital assets | H62: 15501833 | I62: 2674831 | J62: 3413538 | K62: 507833 | L62: =SUM(I62:K62) -> 6596202
B63: Restricted for: | L63: =SUM(I63:K63) -> 0
C64: Debt service | H64: 5297 | I64: 711595 | K64: 42441 | L64: =SUM(I64:K64) -> 754036
C65: Capital projects | H65: 348077 | L65: =SUM(I65:K65) -> 0
C66: Other purposes | H66: 7808226 | J66: 290281 | L66: =SUM(I66:K66) -> 290281
B67: Unrestricted | H67: -959079 | I67: 3281398 | J67: 984241 | K67: 767171 | L67: =SUM(I67:K67) -> 5032810
C69: Total Net Assets | H69: =SUM(H62:H67) -> 22704354 | I69: =SUM(I62:I67) -> 6667824 | J69: =SUM(J62:J67) -> 4688060 | K69: =SUM(K62:K67) -> 1317445 | L69: =SUM(L61:L67) -> 12673329
C71: Total Liabilities and Net Assets | H71: =SUM(H69+H55+H59) -> 27383444 | I71: =SUM(I55+I69) -> 11931437 | J71: =SUM(J55+J69) -> 9214502 | K71: =SUM(K55+K69) -> 1692992 | L71: =SUM(L69+L55) -> 22340931

Sheet St. James
C1: St. James Parish 2015 Statement of Net Assets
C2: Issued: December 31, 2015
G4: Primary Government | J4: Component Unit
G5: Governmental Activities | H5: Business-Type Activities | I5: Total | J5: St. James Parish Hospital
A6: ASSETS
B7: Cash and cash equivalents | G7: 19112401 | H7: 6002490 | I7: =SUM(G7:H7) -> 25114891 | J7: 4909263
B8: Investments | G8: 18887294 | H8: 4016013 | I8: =SUM(G8:H8) -> 22903307
B9: Receivables (net of allowance for uncollectibles) | G9: 22260635 | H9: 1210201 | I9: =SUM(G9:H9) -> 23470836 | J9: 3563353
B10: Notes receivable: | I10: =SUM(G10:H10) -> 0
C11: Due within one year | G11: 530000 | I11: =SUM(G11:H11) -> 530000
C12: Due in more than one year | G12: 550000 | I12: =SUM(G12:H12) -> 550000
C13: Estimated third-party payor settlements | I13: =SUM(G13:H13) -> 0 | J13: 310553
B14: Internal balance | G14: -19032 | H14: 19032 | I14: =SUM(G14:H14) -> 0
B15: Inventories | G15: 36691 | H15: 203686 | I15: =SUM(G15:H15) -> 240377 | J15: 352342
B16: Prepaid items | G16: 159259 | H16: 9982 | I16: =SUM(G16:H16) -> 169241
B17: Restricted assets | I17: =SUM(G17:H17) -> 0
C18: Cash and cash equivalents | H18: 515927 | I18: =SUM(G18:H18) -> 515927
C19: Held by trustee for debt service | I19: =SUM(G19:H19) -> 0 | J19: 1234565
C20: Internally designated for capital acquisition | I20: =SUM(G20:H20) -> 0 | J20: 11466837
B21: Capital assets (net of accumulated depreciation) | G21: 66294696 | H21: 13027858 | I21: =SUM(G21:H21) -> 79322554 | J21: 20970927
B22: Other assets, net | H22: 245 | I22: =SUM(G22:H22) -> 245 | J22: 418547
B24: Total Assets | G24: =SUM(G7:G21) -> 127811944 | H24: =SUM(H7:H22) -> 25005434 | I24: =SUM(I7:I22) -> 152817378 | J24: =SUM(J7:J22) -> 43226387
A26: DEFERRED OUTFLOWS OF RESOURCES
C27: Pension liability | G27: 1749011 | H27: 235540 | I27: =SUM(G27:H27) -> 1984551
C28: Deferred charge on refunding | G28: 147272 | I28: =SUM(G28:H28) -> 147272 | J28: 1111336
D29: Total deferred outflows of resources | G29: =SUM(G27:G28) -> 1896283 | H29: =SUM(H27:H28) -> 235540 | I29: =SUM(I27:I28) -> 2131823 | J29: =SUM(J27:J28) -> 1111336
A31: LIABILITIES
B32: Accounts payable and other current liabilities | G32: 3219582 | H32: 279772 | I32: =SUM(G32:H32) -> 3499354 | J32: 676770
B33: Other liabilities | G33: 61456 | I33: =SUM(G33:H33) -> 61456
B34: Accrued expenses | G34: 1137165 | H34: 41486 | I34: =SUM(G34:H34) -> 1178651 | J34: 747782
B35: Liabilities payable from restricted assets | H35: 494541 | I35: =SUM(G35:H35) -> 494541
B36: Long-term liabilities: | I36: =SUM(G36:H36) -> 0
D37: Other post-employment benefits | G37: 2206570 | H37: 372652 | I37: =SUM(G37:H37) -> 2579222
D38: Pension liability | G38: 392488 | H38: 45934 | I38: =SUM(G38:H38) -> 438422
D39: Due within one year | G39: 1587532 | H39: 65124 | I39: =SUM(G39:H39) -> 1652656 | J39: 1033484
D40: Due in more than one year | G40: 5763974 | H40: 79397 | I40: =SUM(G40:H40) -> 5843371 | J40: 14234263
C42: Total Liabilities | G42: =SUM(G32:G40) -> 14368767 | H42: =SUM(H32:H40) -> 1378906 | I42: =SUM(I32:I40) -> 15747673 | J42: =SUM(J32:J40) -> 16692299
A44: DEFERRED INFLOWS OF RESOURCES
C45: Pension liability | G45: 187300 | H45: 21527 | I45: =SUM(G45:H45) -> 208827
A47: NET ASSETS
B48: Net invested in capital assets | G48: 60873245 | H48: 13027858 | I48: =SUM(G48:H48) -> 73901103 | J48: 6773753
B49: Restricted for:
C50: General government | G50: 8506336 | I50: =SUM(G50:H50) -> 8506336
C51: Culture and recreation | G51: 5990063 | I51: =SUM(G51:H51) -> 5990063
C52: Debt service | G52: 1557524 | I52: =SUM(G52:H52) -> 1557524 | J52: 1234564
C53: Capital projects | G53: 898744 | I53: =SUM(G53:H53) -> 898744
C54: Health and welfare | G54: 7058418 | I54: =SUM(G54:H54) -> 7058418
C55: Highways and streets | G55: 5430945 | I55: =SUM(G55:H55) -> 5430945
C56: Public safety | G56: 14651790 | I56: =SUM(G56:H56) -> 14651790
C57: Sanitation | G57: 3288760 | I57: =SUM(G57:H57) -> 3288760
C58: Group health insurance claims | G58: 1826321 | I58: =SUM(G58:H58) -> 1826321
C59: Other purposes | G59: 5904 | I59: =SUM(G59:H59) -> 5904
B60: Unrestricted | G60: 5064110 | H60: 10815683 | I60: =SUM(G60:H60) -> 15879793 | J60: 19637107
B62: Total Net Assets | G62: =SUM(G48:G61) -> 115152160 | H62: =SUM(H48:H60) -> 23843541 | I62: =SUM(I47:I60) -> 138995701 | J62: =SUM(J47:J60) -> 27645424
B64: Total Liabilities and Net Assets | G64: =G62+G42+G45 -> 129708227 | H64: =H62+H42+H45 -> 25243974 | I64: =I62+I42+I45 -> 154952201 | J64: =J62+J42+J45 -> 44337723

Sheet St. John the Baptist
C1: St. John the Baptist Parish 2015 Statement of Net Assets
C2: Issued: December 31, 2015
G4: Primary Government | J4: Component Unit
G5: Governmental Activities | H5: Business-Type Activities | I5: Total | J5: Library
A6: ASSETS
B7: Cash and cash equivalents | G7: 73371436 | H7: 1361362 | I7: =SUM(G7:H7) -> 74732798 | J7: 6386074
B8: Inventory, at cost | H8: 572914 | I8: =SUM(G8:H8) -> 572914
B9: Receivables (net of allowances) | I9: =SUM(G9:H9) -> 0
C10: Accounts | G10: 418189 | H10: 2999215 | I10: =SUM(G10:H10) -> 3417404
C11: Ad valorem taxes | G11: 11942568 | I11: =SUM(G11:H11) -> 11942568 | J11: 4424379
C12: Sales and use taxes | G12: 4169749 | I12: =SUM(G12:H12) -> 4169749
C13: Other | G13: 194298 | I13: =SUM(G13:H13) -> 194298 | J13: 59593
B14: Due from other governments | G14: 3982244 | H14: 768448 | I14: =SUM(G14:H14) -> 4750692
B15: Prepaid items | G15: 472358 | H15: 137008 | I15: =SUM(G15:H15) -> 609366
B16: Restricted assets | H16: 1383806 | I16: =SUM(G16:H16) -> 1383806
B17: Internal balances | G17: 2816901 | H17: -2816901 | I17: =SUM(G17:H17) -> 0
B18: Capital assets not being depreciated | G18: 23354096 | H18: 5028428 | I18: =SUM(G18:H18) -> 28382524
B19: Capital assets being depreciated | I19: =SUM(G19:H19) -> 0
C20: (net of accumulated depreciation) | G20: 73814709 | H20: 121828578 | I20: =SUM(G20:H20) -> 195643287 | J20: 4988070
B22: Total Assets | G22: =SUM(G7:G20) -> 194536548 | H22: =SUM(H7:H20) -> 131262858 | I22: =SUM(I7:I20) -> 325799406 | J22: =SUM(J7:J20) -> 15858116
A24: DEFERRED OUTFLOWS OF RESOURCES
B25: Deferred amounts related to pension liability | G25: 2601141 | H25: 852671 | I25: 3453812 | J25: 274793
C26: Total Deferred outflows of resources | G26: =G25 -> 2601141 | H26: =H25 -> 852671 | I26: =I25 -> 3453812 | J26: =J25 -> 274793
A28: LIABILITIES
B29: Accounts, salaries, and other payables | G29: 4700672 | H29: 2436086 | I29: =SUM(G29:H29) -> 7136758 | J29: 29466
B30: Contracts payable | G30: 2034827 | I30: =SUM(G30:H30) -> 2034827
B31: Deposits due others | H31: 1221278 | I31: =SUM(G31:H31) -> 1221278
B32: Other liabilities | G32: 33935 | H32: 59233 | I32: =SUM(G32:H32) -> 93168 | J32: 181626
B33: Interest payable | G33: 211473 | H33: 9661 | I33: =SUM(G33:H33) -> 221134
B34: Noncurrent liabilities: | I34: =SUM(G34:H34) -> 0
C35: Due within one year | G35: 6968614 | H35: 335000 | I35: =SUM(G35:H35) -> 7303614 | J35: 37422
C36: Due in more than one year | G36: 98191044 | H36: 5513233 | I36: =SUM(G36:H36) -> 103704277 | J36: 1110596
C38: Total Liabilities | G38: =SUM(G29:G36) -> 112140565 | H38: =SUM(H29:H36) -> 9574491 | I38: =SUM(I29:I36) -> 121715056 | J38: =SUM(J29:J36) -> 1359110
A40: DEFERRED INFLOWS OF RESOURCES
B41: Deferred amounts related to pension liability | G41: 958119 | H41: 97444 | I41: =SUM(G41:H41) -> 1055563 | J41: 24606
C42: Total Deferred inflows of resources | G42: =G41 -> 958119 | H42: =H41 -> 97444 | I42: =I41 -> 1055563 | J42: =J41 -> 24606
A44: NET ASSETS
B45: Net investment in capital assets | G45: 30387143 | H45: 121008773 | I45: =SUM(G45:H45) -> 151395916 | J45: 4988070
B46: Restricted for: | I46: =SUM(G46:H46) -> 0
C47: Special revenue | G47: 23653250 | I47: =SUM(G47:H47) -> 23653250
C48: Debt service | G48: 14125296 | H48: 396000 | I48: =SUM(G48:H48) -> 14521296
C49: Capital projects | I49: =SUM(G49:H49) -> 0
C50: Customer deposits | H50: 214541 | I50: =SUM(G50:H50) -> 214541
C51: Endowment | I51: =SUM(G51:H51) -> 0 | J51: 5000
B52: Unrestricted | G52: 15873316 | H52: 824280 | I52: =SUM(G52:H52) -> 16697596 | J52: 9756123
B54: Total Net Assets | G54: =SUM(G45:G52) -> 84039005 | H54: =SUM(H45:H52) -> 122443594 | I54: =SUM(I45:I52) -> 206482599 | J54: =SUM(J45:J52) -> 14749193
B56: Total Liabilities and Net Assets | G56: =G54+G38+G42 -> 197137689 | H56: =H54+H38+H42 -> 132115529 | I56: =I54+I38+I42 -> 329253218 | J56: =J54+J38+J42 -> 16132909

Sheet St. Landry
D1: St. Landry Parish 2015 Statement of Net Assets
D2: Issued: December 31, 2015
H4: Governmental Activities | I4: Component Units | J4: Total
A5: ASSETS
B6: Current Assets
C7: Cash and interest-bearing deposits | H7: 939373 | I7: 1280142 | J7: =SUM(H7:I7) -> 2219515
C8: Receivables, net | H8: 6386342 | I8: 635460 | J8: =SUM(H8:I8) -> 7021802
C9: Prepaid expenditures | H9: 259868 | J9: =SUM(H9:I9) -> 259868
C10: Due from agency funds | H10: 300878 | J10: =SUM(H10:I10) -> 300878
C11: Due from component units | H11: 12272 | J11: =SUM(H11:I11) -> 12272
C12: Due from other governments | H12: 129935 | J12: =SUM(H12:I12) -> 129935
C13: Due from primary government | I13: 6389 | J13: =SUM(H13:I13) -> 6389
C15: Total Current Assets | H15: =SUM(H7:H13) -> 8028668 | I15: =SUM(I7:I13) -> 1921991 | J15: =SUM(J7:J13) -> 9950659
B17: Noncurrent assets
C18: Cash and cash equivalents- restricted | H18: 2837846 | J18: =SUM(H18:I18) -> 2837846
C19: Investments-restricted | H19: 28604186 | J19: =SUM(H19:I19) -> 28604186
C20: Capital assets, net | H20: 48348426 | I20: 2840184 | J20: =SUM(H20:I20) -> 51188610
C22: Total Assets | H22: =H20+H19+H18+H15 -> 87819126 | I22: =I20+I19+I18+I15 -> 4762175 | J22: =J20+J19+J18+J15 -> 92581301
A24: DEFERRED OUTFLOWS OF RESOURCES
B25: Deferred outflows of resources related to pensions | H25: 886670 | J25: =SUM(H25:I25) -> 886670
A27: LIABILITIES
B28: Current
C29: Accounts payable | H29: 5110250 | I29: 185254 | J29: =SUM(H29:I29) -> 5295504
C30: Accrued expenses | H30: 430982 | J30: =SUM(H30:I30) -> 430982
C31: Accrued interest | H31: 91816 | I31: 19406 | J31: =SUM(H31:I31) -> 111222
C32: Bonds payable | H32: 3554167 | I32: 85000 | J32: =SUM(H32:I32) -> 3639167
C33: Unearned revenue | H33: 5337 | J33: =SUM(H33:I33) -> 5337
C34: Unamortized premium | H34: 109951 | J34: =SUM(H34:I34) -> 109951
C35: Compensated absences | H35: 104452 | I35: 7820 | J35: =SUM(H35:I35) -> 112272
C36: Due to agency funds | H36: 106926 | J36: =SUM(H36:I36) -> 106926
C37: Due to component units | H37: 6389 | J37: =SUM(H37:I37) -> 6389
C38: Due primary government | I38: 12272 | J38: =SUM(H38:I38) -> 12272
D40: Total Current Liabilities | H40: =SUM(H29:H37) -> 9520270 | I40: =SUM(I28:I38) -> 309752 | J40: =SUM(J29:J38) -> 9830022
B42: Noncurrent
C43: Claims payable | H43: 171605 | J43: =SUM(H43:I43) -> 171605
C44: Bonds payable | H44: 55065500 | I44: 1005000 | J44: =SUM(H44:I44) -> 56070500
C45: Unamortized premium | H45: 1319417 | J45: =SUM(H45:I45) -> 1319417
C46: Net pension liability | H46: 187309
D48: Total Noncurrent Liabilities | H48: =SUM(H43:H46) -> 56743831 | I48: =SUM(I43:I46) -> 1005000 | J48: =SUM(J43:J46) -> 57561522
D50: Total Liabilities | H50: =SUM(H40+H48) -> 66264101 | I50: =SUM(I40+I48) -> 1314752 | J50: =SUM(H50:I50) -> 67578853
A52: DEFERRED INFLOWS OF RESOURCES
B53: Deferred inflows of resources related to pensions | H53: 83266 | J53: =SUM(H53:I53) -> 83266
A55: NET ASSETS
B56: Net investment in capital assets | H56: 16184142 | I56: 1750184 | J56: =SUM(H56:I56) -> 17934326
B57: Restricted for debt service | H57: 30704 | J57: =SUM(H57:I57) -> 30704
B58: Restricted- roads | H58: 2131196 | J58: =SUM(H58:I58) -> 2131196
B59: Restricted-other | H59: 1071838 | J59: =SUM(H59:I59) -> 1071838
B60: Unrestricted | H60: 2940458 | I60: 1697239 | J60: =SUM(H60:I60) -> 4637697
C62: Total Net Assets | H62: =SUM(H56:H60) -> 22358338 | I62: =SUM(I56:I60) -> 3447423 | J62: =SUM(J55:J60) -> 25805761
C64: Total Liabilities and Net Assets | H64: =H62+H50+H53 -> 88705705 | I64: =I62+I50+I53 -> 4762175 | J64: =J62+J50+J53 -> 93467880

Sheet St. Martin
D1: St. Martin Parish 2015 Statement of Net Assets
D2: Issued: December 31, 2015
H3: Primary Government
H4: Governmental Activities | I4: Business-Type Activities | J4: Total
A5: ASSETS
C6: Cash and cash equivalents | H6: 29661318 | J6: =SUM(H6:I6) -> 29661318
C7: Receivables | H7: 12366264 | I7: 312799 | J7: =SUM(H7:I7) -> 12679063
C8: Internal balances | H8: 348346 | J8: =SUM(H8:I8) -> 348346
C9: Due from other governments | H9: 431052 | J9: =SUM(H9:I9) -> 431052
C10: Capital assets:
D11: Non-depreciable | H11: 4470956 | J11: =SUM(H11:I11) -> 4470956
D12: Depreciable (net) | H12: 66080508 | J12: =SUM(H12:I12) -> 66080508
C14: Total Assets | H14: =SUM(H6:H12) -> 113358444 | I14: =SUM(I6:I12) -> 312799 | J14: =SUM(J6:J12) -> 113671243
A16: DEFERRED OUTFLOWS OF RESOURCES
B17: Pension related | H17: 773085 | J17: =SUM(H17:I17) -> 773085
A19: LIABILITIES
C20: Accounts payable | H20: 647745 | I20: 808 | J20: =SUM(H20:I20) -> 648553
C21: Internal balances | I21: 348346 | J21: =SUM(H21:I21) -> 348346
C22: Accrued interest payable | H22: 236215 | J22: =SUM(H22:I22) -> 236215
C23: Unearned revenues | H23: 28084 | J23: =SUM(H23:I23) -> 28084
C24: Due to other governments | H24: 89704 | J24: =SUM(H24:I24) -> 89704
C25: Other liabilities | H25: 262202 | I25: 1060 | J25: =SUM(H25:I25) -> 263262
C26: Long-term liabilities:
D27: Bonds payable, due within one year | H27: 1957000 | J27: =SUM(H27:I27) -> 1957000
D28: Bonds payable, due in more than one year | H28: 19053000 | J28: =SUM(H28:I28) -> 19053000
D29: Capital leases payable, due within one year | H29: 300849 | J29: =SUM(H29:I29) -> 300849
D30: Capital leases payable, due in more than one year | H30: 871493 | J30: =SUM(H30:I30) -> 871493
D31: Net pension liability | H31: 168897
D32: OPEB liability-due in more than one year | H32: 7275263 | J32: =SUM(H32:I32) -> 7275263
D33: Compensated absences payable | H33: 416398 | J33: =SUM(H33:I33) -> 416398
D35: Total Liabilities | H35: =SUM(H20:H33) -> 31306850 | I35: =SUM(I20:I33) -> 350214 | J35: =SUM(H35:I35) -> 31657064
A37: DEFERRED INFLOWS OF RESOURCES
B38: Pension related | H38: 81839 | J38: =SUM(H38:I38) -> 81839
A40: NET ASSETS
B41: Net investment in capital assets | H41: 48132907 | J41: =SUM(H41:I41) -> 48132907
B42: Restricted for:
C43: Debt service | H43: 6603250 | J43: =SUM(H43:I43) -> 6603250
C44: Other purposes | H44: 29337526 | I44: 49847 | J44: =SUM(H44:I44) -> 29387373
B45: Unrestricted (deficit) | H45: -1330843 | I45: -87262 | J45: =SUM(H45:I45) -> -1418105
C47: Total Net Assets | H47: =SUM(H41:H45) -> 82742840 | I47: =SUM(I41:I45) -> -37415 | J47: =SUM(J40:J45) -> 82705425
C49: Total Liabilities and Net Assets | H49: =H47+H35+H38 -> 114131529 | I49: =I47+I35+I38 -> 312799 | J49: =J47+J35+J38 -> 114444328

Sheet St. Mary
D1: St.Mary Parish 2015 Statement of Net Assets
D2: Issued: December 31, 2015
H4: Primary Government
H5: Governmental Activities | I5: Business-type Activities | J5: Total | K5: Component Units | L5: Total
A6: ASSETS
B7: CURRENT ASSETS
C8: Cash and cash equivalents | H8: 1706560 | I8: 2108836 | J8: =SUM(H8:I8) -> 3815396 | K8: 38926346 | L8: =SUM(J8:K8) -> 42741742
C9: Investments | H9: 10599815 | I9: 1500025 | J9: =SUM(H9:I9) -> 12099840 | K9: 13837682 | L9: =SUM(J9:K9) -> 25937522
C10: Receivables (net of allowances for uncollectibles) | H10: 895116 | I10: 645153 | J10: =SUM(H10:I10) -> 1540269 | K10: 2591869 | L10: =SUM(J10:K10) -> 4132138
C11: Other recievables | J11: =SUM(H11:I11) -> 0 | K11: 1447686 | L11: =SUM(J11:K11) -> 1447686
C12: Due from St. Mary Parish Council | J12: =SUM(H12:I12) -> 0 | K12: 169338 | L12: =SUM(J12:K12) -> 169338
C13: Due from component units | H13: 2283621 | J13: =SUM(H13:I13) -> 2283621 | K13: 24392 | L13: =SUM(J13:K13) -> 2308013
C14: Due from other governments | H14: 8087968 | I14: 101122 | J14: =SUM(H14:I14) -> 8189090 | K14: 6941099 | L14: =SUM(J14:K14) -> 15130189
C15: Prepaid items | J15: =SUM(H15:I15) -> 0 | K15: 1035453 | L15: =SUM(J15:K15) -> 1035453
C16: Inventory | J16: =SUM(H16:I16) -> 0 | K16: 1050873 | L16: =SUM(J16:K16) -> 1050873
C17: Other assets | H17: 4220 | J17: =SUM(H17:I17) -> 4220 | K17: 6227 | L17: =SUM(J17:K17) -> 10447
C18: Internal balances | H18: -4924271 | I18: 4924271 | J18: =SUM(H18:I18) -> 0 | L18: =SUM(J18:K18) -> 0
C20: Total Current Assets | H20: =SUM(H8:H18) -> 18653029 | I20: =SUM(I8:I18) -> 9279407 | J20: =SUM(J8:J18) -> 27932436 | K20: =SUM(K8:K18) -> 66030965 | L20: =SUM(L8:L18) -> 93963401
B22: NONCURRENT ASSETS
C23: Restricted Assets
D24: Cash | I24: 3127201 | J24: =SUM(H24:I24) -> 3127201 | K24: 8669039 | L24: =SUM(J24:K24) -> 11796240
D25: Investments | I25: 845307 | J25: =SUM(H25:I25) -> 845307 | K25: 3185919 | L25: =SUM(J25:K25) -> 4031226
D26: Other | J26: =SUM(H26:I26) -> 0 | K26: 1903 | L26: =SUM(J26:K26) -> 1903
C27: Investment in Berwick Bayou Vista Joint Waterworks Commission | J27: =SUM(H27:I27) -> 0 | K27: 739231 | L27: =SUM(J27:K27) -> 739231
B28: Capital Assets | J28: =SUM(H28:I28) -> 0 | L28: =SUM(J28:K28) -> 0
C29: Land and improvements | H29: 1870876 | I29: 3802599 | J29: =SUM(H29:I29) -> 5673475 | K29: 5330381 | L29: =SUM(J29:K29) -> 11003856
C30: Buildings, net of accumulated depreciation | H30: 9576008 | I30: 133950 | J30: =SUM(H30:I30) -> 9709958 | K30: 35513568 | L30: =SUM(J30:K30) -> 45223526
C31: Improvements other than buildings, net of accumulated depreciation | H31: 14609772 | I31: 15998079 | J31: =SUM(H31:I31) -> 30607851 | K31: 30237734 | L31: =SUM(J31:K31) -> 60845585
C32: Equipment and furniture, net of accumulated depreciation | H32: 2435936 | I32: 1867113 | J32: =SUM(H32:I32) -> 4303049 | K32: 13012670 | L32: =SUM(J32:K32) -> 17315719
C33: Infrastructure, net of accumulated depreciation | H33: 76347538 | J33: =SUM(H33:I33) -> 76347538 | K33: 8497050 | L33: =SUM(J33:K33) -> 84844588
C34: Construction in progress | H34: 8736229 | I34: 154961 | J34: =SUM(H34:I34) -> 8891190 | K34: 3992972 | L34: =SUM(J34:K34) -> 12884162
C36: Total noncurrent assets | H36: =SUM(H23:H34) -> 113576359 | I36: =SUM(I23:I34) -> 25929210 | J36: =SUM(J23:J34) -> 139505569 | K36: =SUM(K23:K34) -> 109180467 | L36: =SUM(L23:L34) -> 248686036
C38: TOTAL ASSETS | H38: =H20+H36 -> 132229388 | I38: =I20+I36 -> 35208617 | J38: =J20+J36 -> 167438005 | K38: =K20+K36 -> 175211432 | L38: =L20+L36 -> 342649437
A40: DEFERRED OUTFLOWS OF RESOURCES
B41: Deferred charges on refunding | H41: 4354773 | J41: =SUM(H41:I41) -> 4354773 | K41: 150613 | L41: =SUM(J41:K41) -> 4505386
B42: Deferred charges- pensions | H42: 5253107 | I42: 383334 | J42: =SUM(H42:I42) -> 5636441 | K42: 15477120 | L42: =SUM(J42:K42) -> 21113561
C43: TOTAL DEFERRED OUTFLOWS OF RESOURCES | H43: =SUM(H41:H42) -> 9607880 | I43: =SUM(I41:I42) -> 383334 | J43: =SUM(J41:J42) -> 9991214 | K43: =SUM(K41:K42) -> 15627733 | L43: =SUM(L41:L42) -> 25618947
A45: LIABILITIES
B46: CURRENT LIABILITIES
C47: Accounts, salaries and other payables | H47: 951263 | I47: 377024 | J47: =SUM(H47:I47) -> 1328287 | K47: 1994206 | L47: =SUM(J47:K47) -> 3322493
C48: Contracts payable | H48: 1389444 | J48: =SUM(H48:I48) -> 1389444 | K48: 52517 | L48: =SUM(J48:K48) -> 1441961
C49: Retainage payable | H49: 515624 | I49: 54509 | J49: =SUM(H49:I49) -> 570133 | K49: 8700 | L49: =SUM(J49:K49) -> 578833
C50: Accrued liabilities | H50: 228194 | J50: =SUM(H50:I50) -> 228194 | K50: 1390050 | L50: =SUM(J50:K50) -> 1618244
C51: Accrued interest payable | H51: 221020 | J51: =SUM(H51:I51) -> 221020 | K51: 36866 | L51: =SUM(J51:K51) -> 257886
C52: Deferred revenue | H52: 13000 | J52: =SUM(H52:I52) -> 13000 | L52: =SUM(J52:K52) -> 13000
C53: Due to St. Mary Parish Council | J53: =SUM(H53:I53) -> 0 | K53: 363694 | L53: =SUM(J53:K53) -> 363694
C54: Due to component units | H54: 1369 | J54: =SUM(H54:I54) -> 1369 | K54: 48040 | L54: =SUM(J54:K54) -> 49409
C55: Due to other governments | H55: 456210 | J55: =SUM(H55:I55) -> 456210 | K55: 467521 | L55: =SUM(J55:K55) -> 923731
C56: Payable from restricted assets | J56: =SUM(H56:I56) -> 0 | K56: 677445 | L56: =SUM(J56:K56) -> 677445
C57: Current portion of long term debt | H57: 2309000 | I57: 745000 | J57: =SUM(H57:I57) -> 3054000 | K57: 3130360 | L57: =SUM(J57:K57) -> 6184360
D59: TOTAL CURRENT LIABILITIES | H59: =SUM(H47:H57) -> 6085124 | I59: =SUM(I47:I57) -> 1176533 | J59: =SUM(J47:J57) -> 7261657 | K59: =SUM(K47:K57) -> 8169399 | L59: =SUM(L47:L57) -> 15431056
B61: Noncurrent liabilities
C62: Other post-employment benefits | H62: 7643900 | I62: 1188600 | J62: =SUM(H62:I62) -> 8832500 | K62: 1045214 | L62: =SUM(J62:K62) -> 9877714
C63: Compensated absences | H63: 212000 | J63: =SUM(H63:I63) -> 212000 | K63: 130910 | L63: =SUM(J63:K63) -> 342910
C64: Noncurrent portion of long-term debt | H64: 16054694 | I64: 11416980 | J64: =SUM(H64:I64) -> 27471674 | K64: 29999410 | L64: =SUM(J64:K64) -> 57471084
C65: Due to St. Mary Parish Council | J65: =SUM(H65:I65) -> 0 | K65: 1337900 | L65: =SUM(J65:K65) -> 1337900
C66: Net pension liabilitiy | H66: 238013 | I66: 54231 | J66: =SUM(H66:I66) -> 292244 | L66: =SUM(J66:K66) -> 292244
C67: Landfill closure and post-closure care costs | I67: 4246000 | J67: =SUM(H67:I67) -> 4246000 | K67: 2729107 | L67: =SUM(J67:K67) -> 6975107
D69: TOTAL NONCURRENT LIABILITIES | H69: =SUM(H62:H67) -> 24148607 | I69: =SUM(I62:I67) -> 16905811 | J69: =SUM(J62:J67) -> 41054418 | K69: =SUM(K62:K67) -> 35242541 | L69: =SUM(L62:L67) -> 76296959
D71: Total Liabilities | H71: =H69+H59 -> 30233731 | I71: =I69+I59 -> 18082344 | J71: =J69+J59 -> 48316075 | K71: =K69+K59 -> 43411940 | L71: =L69+L59 -> 91728015
A73: DEFERRED INFLOWS OF RESOURCES
B74: Unearned revenue | K74: 135497 | L74: =SUM(J74:K74) -> 135497
B75: Deferred inflows related to pension | H75: 107774 | I75: 24557 | J75: 132331 | K75: 748863 | L75: 881194
D76: Total deferred outflows of resources | H76: =SUM(H74:H75) -> 107774 | I76: =SUM(I74:I75) -> 24557 | J76: =SUM(J74:J75) -> 132331 | K76: =SUM(K74:K75) -> 884360 | L76: =SUM(L74:L75) -> 1016691
A78: NET ASSETS
B79: Net investment in capital assets, net of related debt | H79: 94485041 | I79: 9794722 | J79: =SUM(H79:I79) -> 104279763 | K79: 72931813 | L79: =SUM(J79:K79) -> 177211576
B80: Restricted for:
C81: Capital projects | K81: 4569482 | L81: =SUM(J81:K81) -> 4569482
C82: Debt service | H82: 904960 | I82: 911930 | J82: 1816890 | K82: 3173517 | L82: =SUM(J82:K82) -> 4990407
C83: Other purposes | H83: 4329454 | I83: -1294654 | J83: 3034800 | K83: 6756281 | L83: =SUM(J83:K83) -> 9791081
B84: Unrestricted | H84: 3520714 | I84: 8167099 | J84: 11687813 | K84: 45137297 | L84: =SUM(J84:K84) -> 56825110
L85: ='St. Tammany'!S1 -> 0
C86: Total Net Assets | H86: =SUM(H79:H84) -> 103240169 | I86: =SUM(I79:I84) -> 17579097 | J86: =SUM(J79:J84) -> 120819266 | K86: =SUM(K79:K84) -> 132568390 | L86: =SUM(L79:L85) -> 253387656
C88: Total Liabilities and Net Assets | H88: =SUM(H86+H71) -> 133473900 | I88: =SUM(I86+I71) -> 35661441 | J88: =SUM(J86+J71) -> 169135341 | K88: =SUM(K86+K71) -> 175980330 | L88: =SUM(L86+L71) -> 345115671

Sheet St. Tammany
D1: St.Tammany Parish 2015 Statement of Net Assets
D2: Issued: December 31, 2015
H4: Primary Government
H5: Governmental Activities | I5: Business-type Activities | J5: Total | K5: Component Units | L5: Total
A6: ASSETS
C7: Cash and cash equivalents | H7: 46765205 | I7: 2960256 | J7: =SUM(H7:I7) -> 49725461 | K7: 52295363 | L7: =SUM(J7:K7) -> 102020824
C8: Investments | H8: 141077508 | I8: 11641597 | J8: =SUM(H8:I8) -> 152719105 | K8: 2891660 | L8: =SUM(J8:K8) -> 155610765
C9: Receivables (net of allowances for uncollectibles) | H9: 55840630 | I9: 1003100 | J9: =SUM(H9:I9) -> 56843730 | K9: 66423594 | L9: =SUM(J9:K9) -> 123267324
C10: Due from primary government/component units | H10: 131407 | J10: =SUM(H10:I10) -> 131407 | K10: 9680596 | L10: =SUM(J10:K10) -> 9812003
C11: Inventory | J11: =SUM(H11:I11) -> 0 | K11: 1888309 | L11: =SUM(J11:K11) -> 1888309
C12: Prepaid items | H12: 186111 | J12: =SUM(H12:I12) -> 186111 | K12: 817946 | L12: =SUM(J12:K12) -> 1004057
C13: Restricted assets | H13: 10194191 | I13: 4516298 | J13: =SUM(H13:I13) -> 14710489 | K13: 3490696 | L13: =SUM(J13:K13) -> 18201185
C14: Other assets | H14: 16586 | I14: 13159 | J14: =SUM(H14:I14) -> 29745 | K14: 29283 | L14: =SUM(J14:K14) -> 59028
C15: Capital assets: | L15: =SUM(J15:K15) -> 0
D16: Land, improvements and construction in progress | H16: 112993238 | I16: 1247397 | J16: =SUM(H16:I16) -> 114240635 | K16: 12528675 | L16: =SUM(J16:K16) -> 126769310
D17: Other capital assets, net of depreciation | H17: 352355855 | I17: 36149330 | J17: =SUM(H17:I17) -> 388505185 | K17: 75153666 | L17: =SUM(J17:K17) -> 463658851
C19: Total Assets | H19: =SUM(H7:H17) -> 719560731 | I19: =SUM(I7:I17) -> 57531137 | J19: =SUM(J7:J17) -> 777091868 | K19: =SUM(K7:K17) -> 225199788 | L19: =SUM(L7:L17) -> 1002291656
A21: DEFERRED OUTFLOWS OF RESOURCES
B22: Deferred charges on refunding | H22: 4354773 | J22: =SUM(H22:I22) -> 4354773 | K22: 150613 | L22: =SUM(J22:K22) -> 4505386
B23: Deferred charges- pensions | H23: 5253107 | I23: 383334 | J23: =SUM(H23:I23) -> 5636441 | K23: 15477120 | L23: =SUM(J23:K23) -> 21113561
C24: TOTAL DEFERRED OUTFLOWS OF RESOURCES | H24: =SUM(H22:H23) -> 9607880 | I24: =SUM(I22:I23) -> 383334 | J24: =SUM(J22:J23) -> 9991214 | K24: =SUM(K22:K23) -> 15627733 | L24: =SUM(L22:L23) -> 25618947
A26: LIABILITIES
C27: Accounts, salaries and other payables | H27: 19577482 | I27: 726832 | J27: =SUM(H27:I27) -> 20304314 | K27: 4318390 | L27: =SUM(J27:K27) -> 24622704
C28: Payable from restricted assets | J28: =SUM(H28:I28) -> 0 | K28: 143511 | L28: =SUM(J28:K28) -> 143511
C29: Due to primary government/component units | H29: 9598702 | J29: =SUM(H29:I29) -> 9598702 | K29: 213301 | L29: =SUM(J29:K29) -> 9812003
C30: Unearned revenues | H30: 4342746 | J30: =SUM(H30:I30) -> 4342746 | K30: 536050 | L30: =SUM(J30:K30) -> 4878796
C31: Other liabilities | H31: 2397283 | I31: 1382383 | J31: =SUM(H31:I31) -> 3779666 | K31: 51423 | L31: =SUM(J31:K31) -> 3831089
C32: Interest payable | H32: 493442 | I32: 813809 | J32: =SUM(H32:I32) -> 1307251 | K32: 499313 | L32: =SUM(J32:K32) -> 1806564
B33: Noncurrent liabilities | J33: =SUM(H33:I33) -> 0 | L33: =SUM(J33:K33) -> 0
C34: Due within one year | H34: 8460000 | I34: 745000 | J34: =SUM(H34:I34) -> 9205000 | K34: 5124743 | L34: =SUM(J34:K34) -> 14329743
C35: Due in more than one year | H35: 85196482 | I35: 40034585 | J35: =SUM(H35:I35) -> 125231067 | K35: 92826870 | L35: =SUM(J35:K35) -> 218057937
D37: Total Liabilities | H37: =SUM(H27:H35) -> 130066137 | I37: =SUM(I27:I35) -> 43702609 | J37: =SUM(J27:J35) -> 173768746 | K37: =SUM(K27:K35) -> 103713601 | L37: =SUM(L27:L35) -> 277482347
A39: DEFERRED INFLOWS OF RESOURCES
B40: Deferred charges- pensions | H40: 442573 | I40: 32296 | J40: =SUM(H40:I40) -> 474869 | K40: 5627501 | L40: =SUM(J40:K40) -> 6102370
D41: Total deferred inflows of resources
A43: NET ASSETS
B44: Net investment incapital assets | H44: 391686503 | I44: -3303860 | J44: =SUM(H44:I44) -> 388382643 | K44: 52509148 | L44: =SUM(J44:K44) -> 440891791
B45: Restricted for: | J45: =SUM(H45:I45) -> 0 | L45: =SUM(J45:K45) -> 0
C46: Capital projects | H46: 11574912 | I46: 774807 | J46: =SUM(H46:I46) -> 12349719 | L46: =SUM(J46:K46) -> 12349719
C47: Culture and recreation | H47: 300716 | J47: =SUM(H47:I47) -> 300716 | L47: =SUM(J47:K47) -> 300716
C48: Debt service | H48: 10462496 | I48: 3741460 | J48: =SUM(H48:I48) -> 14203956 | K48: 4334117 | L48: =SUM(J48:K48) -> 18538073
C49: Economic development | H49: 543586 | J49: =SUM(H49:I49) -> 543586 | L49: =SUM(J49:K49) -> 543586
C50: Health and welfare | H50: 7356828 | J50: =SUM(H50:I50) -> 7356828 | L50: =SUM(J50:K50) -> 7356828
C51: Judicial | H51: 12864836 | J51: =SUM(H51:I51) -> 12864836 | L51: =SUM(J51:K51) -> 12864836
C52: Lighting districts | H52: 4749320 | J52: =SUM(H52:I52) -> 4749320 | L52: =SUM(J52:K52) -> 4749320
C53: Public safety | H53: 13840913 | J53: =SUM(H53:I53) -> 13840913 | L53: =SUM(J53:K53) -> 13840913
C54: Roads, bridges, and drainage | H54: 90851013 | J54: =SUM(H54:I54) -> 90851013 | L54: =SUM(J54:K54) -> 90851013
C55: Transit | H55: 16245 | J55: =SUM(H55:I55) -> 16245 | L55: =SUM(J55:K55) -> 16245
B56: Unrestricted | H56: 54412533 | I56: 12967159 | J56: =SUM(H56:I56) -> 67379692 | K56: 74643154 | L56: =SUM(J56:K56) -> 142022846
L57: ='St. Tammany'!S1 -> 0
C58: Total Net Assets | H58: =SUM(H44:H56) -> 598659901 | I58: =SUM(I44:I56) -> 14179566 | J58: =SUM(J44:J56) -> 612839467 | K58: =SUM(K44:K56) -> 131486419 | L58: =SUM(L44:L57) -> 744325886
C60: Total Liabilities and Net Assets | H60: =H58+H37+H40 -> 729168611 | I60: =I58+I37+I40 -> 57914471 | J60: =J58+J37+J40 -> 787083082 | K60: =K58+K37+K40 -> 240827521 | L60: =L58+L37+L40 -> 1027910603

Sheet Tangipahoa
D1: Tangipahoa Parish 2015 Statement of Net Assets
D2: Issued: December 31, 2015
H4: Primary Government | I4: Component Units
H5: Governmental Activities | I5: Governmental Activities
A6: ASSETS
C7: Cash and cash equivalents | H7: 19337786 | I7: 6159362
C8: Investment in certificates of deposit | I8: 468057
C9: Receivebles, net | H9: 10441900 | I9: 6298508
C10: Due from other governments | H10: 330751
C11: Restricted assets- cash | H11: 1011547
C12: Prepaid insurance | I12: 51144
C13: Capital assets (net) | H13: 181095010 | I13: 9382514
C15: Total Assets | H15: =SUM(H7:H13) -> 212216994 | I15: =SUM(I7:I13) -> 22359585
A17: Deferred outflow of resources | H17: 2373098
A19: LIABILITIES
C20: Accounts, salaries, and other payables | H20: 2905922 | I20: 448624
C21: Deferred Revenue- Nonprofits | I21: 59615
C22: Due to other governments | H22: 439705 | I22: 9032
C23: Due to volunteer fire departments | I23: 1241398
C24: Noncurrent liabilities:
D25: Due within one year | H25: 105000 | I25: 243944
D26: Due in more than one year | H26: 9146186 | I26: 66982
D27: Postemployment healthcare benefits payable | H27: 1877091
D28: Net pension Liability | H28: 460676
D30: Total Liabilities | H30: =SUM(H20:H28) -> 14934580 | I30: =SUM(I20:I28) -> 2069595
A32: Deferred inflow of resources
C33: Grant funds | H33: 7500
C34: GASB 68- Pension | H34: 216788
C36: Total Deferred inflow of resources | H36: =SUM(H33:H34) -> 224288 | I36: =SUM(I33:I34) -> 0
A38: NET ASSETS
B39: Net investment in capital assets | H39: 178715010 | I39: 9071588
B40: Restricted for:
C41: Debt service | H41: 286243
C42: Other purposes | H42: 981887 | I42: 11218402
B43: Unrestricted | H43: 19448084
C45: Total Net Assets | H45: =SUM(H39:H43) -> 199431224 | I45: =SUM(I39:I43) -> 20289990
C47: Total Liabilities and Net Assets | H47: =H45+H30+H36 -> 214590092 | I47: =I45+I30+I36 -> 22359585

Sheet Tensas
C1: Tensas Parish 2015 Statement of Net Assets
C2: Issued: December 31, 2015
G4: Governmental Activities
A5: ASSETS
B6: Cash and cash equivalents | G6: 1759690
B7: Receivables | G7: 1094058
B8: Amounts held by trustee for landfill closure
C9: and post-closure care costs | G9: 1024913
B10: Restricted assets | G10: 21703
B11: Capital assets, net | G11: 8437537
B13: Total Assets | G13: =SUM(G6:G11) -> 12337901
A15: Deferred outflows of resources | G15: 227905
A17: LIABILITIES
B18: Accounts, salaries, and other payables | G18: 307444
B19: Intergovernmental payables | G19: 47165
B20: Long-term liabilities:
C21: Due within one year | G21: 68712
C22: Due in more than one year | G22: 1362849
C23: Net pension liability | G23: 75877
C25: Total Liabilities | G25: =SUM(G18:G23) -> 1862047
A27: Deferred inflows of resources | G27: 29043
A29: NET ASSETS
B30: Invested in capital assets, net of related debt | G30: 7074688
B31: Restricted for:
C32: Debt service | G32: 21704
C33: Landfill closure | G33: 989796
B34: Unrestricted | G34: 2588528
B36: Total Net Assets | G36: =SUM(G30:G34) -> 10674716
B38: Total Liabilities and Net Assets | G38: =G36+G25+G27 -> 12565806

Sheet Terrebonne
D1: Terrebonne Parish 2015 Statement of Net Assets
D2: Issued: December 31, 2015
H4: Primary Government
H5: Governmental Activities | I5: Business-Type Activities | J5: Total | K5: Component Unit
A6: ASSETS
C7: Cash and cash equivalents | H7: 93714529 | I7: 27575132 | J7: =SUM(H7:I7) -> 121289661 | K7: 147295252
C8: Investments | H8: 56926773 | I8: 19547952 | J8: =SUM(H8:I8) -> 76474725 | K8: 199812055
C9: Receivables | H9: 15878382 | I9: 7412062 | J9: =SUM(H9:I9) -> 23290444 | K9: 43776065
C10: Internal balances | H10: -5944210 | I10: 5944210 | J10: =SUM(H10:I10) -> 0
C11: Due from other governments | H11: 45719610 | I11: 10410466 | J11: =SUM(H11:I11) -> 56130076 | K11: 23896489
C12: Due from component units | H12: 3316 | J12: =SUM(H12:I12) -> 3316 | K12: 1500000
C13: Inventories | H13: 2070087 | I13: 18941 | J13: =SUM(H13:I13) -> 2089028 | K13: 5106157
C14: Other assets | H14: 735880 | I14: 2413422 | J14: =SUM(H14:I14) -> 3149302 | K14: 15151339
C15: Restricted assets:
D16: Cash and cash equivalents | H16: 252558 | I16: 1164158 | J16: =SUM(H16:I16) -> 1416716 | K16: 21334329
D17: Investments | I17: 2531307 | J17: =SUM(I17) -> 2531307
C18: Investment in joint venture | I18: 684161 | J18: =SUM(I18) -> 684161
C19: Capital assets: | J19: =SUM(H19:I19) -> 0
D20: Non-depreciable | H20: 77386614 | I20: 10304581 | J20: =SUM(H20:I20) -> 87691195 | K20: 51239032
D21: Depreciable, net | H21: 269194382 | I21: 144426646 | J21: =SUM(H21:I21) -> 413621028 | K21: 668866250
C23: Total Assets | H23: =SUM(H7:H21) -> 555937921 | I23: =SUM(I7:I21) -> 232433038 | J23: =SUM(J7:J21) -> 788370959 | K23: =SUM(K7:K21) -> 1177976968
A25: Deferred Outflows of Resources | H25: 9401213 | I25: 634577 | J25: =SUM(H25:I25) -> 10035790 | K25: 5348151
A27: LIABILITIES
C28: Accounts payable and other current liabilities | H28: 20807027 | I28: 4833422 | J28: =SUM(H28:I28) -> 25640449 | K28: 61813380
C29: Accrued interest payable | H29: 1301932 | J29: =SUM(H29:I29) -> 1301932
C30: Due to other governments | H30: 1244861 | I30: 151349 | J30: =SUM(H30:I30) -> 1396210 | K30: 639377
C31: Due to component units | H31: 1500000 | J31: =SUM(H31:I31) -> 1500000 | K31: 3316
C32: Grant Advancements | H32: 93029 | I32: 1229929 | J32: =SUM(H32:I32) -> 1322958
C33: Liabilities payable from restricted assets | J33: =SUM(H33:I33) -> 0
C34: Noncurrent liabilities: | J34: =SUM(H34:I34) -> 0
D35: Due within one year | H35: 6565223 | I35: 1365685 | J35: =SUM(H35:I35) -> 7930908 | K35: 7970686
D36: Due in more than one year | H36: 138353865 | I36: 17058711 | J36: =SUM(H36:I36) -> 155412576 | K36: 216460430
D38: Total Liabilities | H38: =SUM(H28:H36) -> 169865937 | I38: =SUM(I28:I36) -> 24639096 | J38: =SUM(J28:J36) -> 194505033 | K38: =SUM(K28:K36) -> 286887189
A40: Deferred Inflows of Resources | H40: 28281769 | I40: 10596811 | J40: =SUM(H40:I40) -> 38878580 | K40: 25232227
A42: NET ASSETS
B43: Invested in capital assets, net of related debt | H43: 290332613 | I43: 141182208 | J43: =SUM(H43:I43) -> 431514821 | K43: 585506253
B44: Restricted for: | J44: =SUM(H44:I44) -> 0
C45: General governments | H45: 206754 | J45: =SUM(H45:I45) -> 206754
C46: Streets and drainage | H46: 9125176 | J46: =SUM(H46) -> 9125176
C47: Capital projects | H47: 19650969 | J47: =SUM(H47) -> 19650969 | K47: 11454970
C48: Debt service | H48: 14859733 | J48: =SUM(H48:I48) -> 14859733 | K48: 11499226
C49: Health and welfare | H49: 5673147 | J49: =SUM(H49) -> 5673147
C50: Economic development and assistance | H50: 472232 | J50: =SUM(H50) -> 472232
C51: Urban redevelopment and assistance | H51: 2830103 | J51: =SUM(H51) -> 2830103
C52: Culture and recreation | H52: 2684923 | J52: =SUM(H52) -> 2684923
C53: Utilities | I53: 35823051 | J53: =SUM(I53) -> 35823051
C54: Sewerage | I54: 8281536 | J54: =SUM(I54) -> 8281536
C55: Sanitation | I55: 12871672 | J55: =SUM(I55) -> 12871672
C56: Other purposes | K56: 6649340
B57: Unrestricted | H57: 11910655 | I57: -317459 | J57: =SUM(H57:I57) -> 11593196 | K57: 256095914
C59: Total Net Assets | H59: =SUM(H43:H57) -> 357746305 | I59: =SUM(I43:I57) -> 197841008 | J59: =SUM(J43:J57) -> 555587313 | K59: =SUM(K42:K57) -> 871205703
C61: Total Liabilities and Net Assets | H61: =H59+H38+H40 -> 555894011 | I61: =I59+I38+I40 -> 233076915 | J61: =J59+J38+J40 -> 788970926 | K61: =K59+K38+K40 -> 1183325119

Sheet Union
C1: Union Parish 2015 Statement of Net Assets
C2: Issued: December 31, 2015
G4: Governmental Activities
A5: ASSETS
B6: Cash and cash equivalents | G6: 7912131
B7: Investments | G7: 7613142
B8: Receivables | G8: 4052420
B9: Capital assets, net of accumulated depreciation | G9: 11934675
B11: Total Assets | G11: =SUM(G6:G9) -> 31512368
A13: DEFERRED OUTFLOWS
B14: Deferred outflows- pension related | G14: 290544
A16: LIABILITIES
B17: Cash overdraft | G17: 947080
B18: Accounts, salaries and other payables | G18: 669465
B19: Deposits due others | G19: 385020
B20: Compensated absences | G20: 226337
B21: Public building revenue bonds due within one year | G21: 19000
B22: Public building revenue bonds due in more than one year | G22: 198000
B23: Sales Tax Bonds Payable | G23: 300000
B24: Net OPEB obligation | G24: 1386006
B25: Net pension liability | G25: 162131
B26: Landfill closure/postclosure care | G26: 6346327
C28: Total Liabilities | G28: =SUM(G17:G26) -> 10639366
A30: DEFERRED INFLOWS
B31: Deferred inflows- pension related | G31: 69433
B32: Grant revenues pending | G32: 14194
C33: Total deferred inflows | G33: =SUM(G31:G32) -> 83627
A35: NET ASSETS
B36: Net investment in capital assets | G36: 11717675
B37: Restricted for landfill closure/postclosure care | G37: 5251456
B38: Unrestricted | G38: 4110788
B40: Total Net Assets | G40: =SUM(G36:G38) -> 21079919
B42: Total Liabilities and Net Assets | G42: =G40+G28+G33 -> 31802912

Sheet Vermilion
D1: Vermillion Parish 2015 Statement of Net Assets
D2: Issued: December 31, 2015
H4: Primary Government | I4: Component Units
H5: Governmental Activities | I5: Criminal Court Fund | J5: Tourist Commission
A6: ASSETS
C7: Cash and interest-bearing deposits | H7: 57109921 | I7: 42923 | J7: 221254
C8: Receivables, net | H8: 676865 | J8: 100
C9: Due from component unit | H9: 630
C10: Due from other governmental units | H10: 7336187 | I10: 142112 | J10: 6783
C11: Prepaid expenses | H11: 30558
C12: Capital assets, net | H12: 83915954
C14: Total Assets | H14: =SUM(H7:H12) -> 149070115 | I14: =SUM(I7:I12) -> 185035 | J14: =SUM(J7:J12) -> 228137
A16: DEFERRED OUTFLOWS OF RESOURCES
C17: Deferred outflows of resources- pensions | H17: 1170795 | I17: 102430 | J17: 9580
A19: LIABILITIES
C20: Accounts and other payables | H20: 995077 | I20: 26515 | J20: 9194
C21: Contracts payable | H21: 241028
C22: Retainage payable | H22: 93660
C23: Due to primary government | I23: 630
C24: Accrued interest payable | H24: 21678
C25: Long-term liabilities:
D26: Other post employment benefits payable | H26: 1909493
D27: Net pension liability | H27: 366077 | I27: 18951 | J27: 2050
D28: Due within one year | H28: 390000
D29: Due in more than one year | H29: 3235660
D31: Total Liabilities | H31: =SUM(H20:H29) -> 7252673 | I31: =SUM(I20:I29) -> 46096 | J31: =SUM(J20:J29) -> 11244
A33: DEFERRED INFLOWS OF RESOURCES
C34: Deferred inflows of resources- pensions | H34: 158514 | I34: 8653 | J34: 911
C35: Deferred revenues | H35: 719245
D36: Total deferred inflows of resources | H36: =SUM(H34:H35) -> 877759 | I36: =SUM(I34:I35) -> 8653 | J36: =SUM(J34:J35) -> 911
A38: NET ASSETS
B39: Net investment in capital assets | H39: 82526629
B40: Restricted for:
C41: Debt service | H41: 1357954
C42: Other purposes | H42: 38123804
B43: Unrestricted | H43: 20102091 | I43: 232716 | J43: 225562
C45: Total Net Assets | H45: =SUM(H39:H43) -> 142110478 | I45: =SUM(I39:I43) -> 232716 | J45: =SUM(J38:J43) -> 225562
C47: Total Liabilities and Net Assets | H47: =H45+H31+H36 -> 150240910 | I47: =I45+I31+I36 -> 287465 | J47: =J45+J31+J36 -> 237717

Sheet Vernon
D1: Vernon Parish 2015 Statement of Net Assets
D2: Issued: December 31, 2015
H5: 2014 | I5: 2013
A6: ASSETS
C7: Cash and cash equivalents | H7: 16525269 | I7: 17372780
C8: Investments, at fair market value | H8: 1246278 | I8: 1246151
C9: Receivebles | H9: 6418537 | I9: 6948566
C10: Other | I10: 39589
C11: Capital assets (net of accumulated depreciation):
D12: Land | H12: 1720977 | I12: 1695977
D13: Construction in progress | I13: 7715076
D14: Buildings and improvements | H14: 14160585 | I14: 6171031
D15: Furniture and equipment | H15: 8373957 | I15: 6171031
D16: Infrastructure | H16: 33590432 | I16: 28172702
D17: Library book collection | H17: 603368 | I17: 587324
A19: Deferred inflows on pension benefit obligations | H19: 20387
C21: Total Assets | H21: =SUM(H7:H17) -> 82639403 | I21: =SUM(I7:I17) -> 76120227
A23: LIABILITIES
C24: Accounts, salaries, and other payables | H24: 868778 | I24: 937890
C25: Interest payable | H25: 386068 | I25: 386068
C26: Long-term liabilities:
D27: Due within one year | H27: 942892 | I27: 899766
D28: Due in more than one year | H28: 26491506 | I28: 23684078
A30: Deferred inflows on pension benefit obligations | H30: 185372 | I30: 44879
D32: Total Liabilities | H32: =SUM(H24:H28) -> 28689244 | I32: =SUM(I24:I28) -> 25907802
A34: NET ASSETS
B35: Invested in capital assets, net of related debt | H35: 48848704 | I35: 73245853
B36: Restricted for:
C37: Debt service | H37: 722702 | I37: 712202
C38: Employee benefits | H38: 2893672 | I38: 2427545
B39: Unrestricted | H39: 1320096 | I39: 6284988
C41: Total Net Assets | H41: =SUM(H35:H39) -> 53785174 | I41: =SUM(I35:I39) -> 82670588
C43: Total Liabilities and Net Assets | H43: =H41+H32+H30 -> 82659790 | I43: =I41+I32+I30 -> 108623269

Sheet Washington
D1: Washington Parish 2015 Statement of Net Assets
D2: Issued: December 31, 2015
H4: Primary Government
H5: Governmental Activities | I5: Business-Type Activities | J5: Total
A6: ASSETS
C7: Cash | H7: 3975044 | I7: 220076 | J7: =SUM(H7:I7) -> 4195120
C8: Investments | H8: 2969821 | J8: =SUM(H8:I8) -> 2969821
C9: Receivables | H9: 5566583 | J9: =SUM(H9:I9) -> 5566583
C10: FEMA receivable | H10: 62812 | J10: =SUM(H10:I10) -> 62812
C11: Notes receivable | I11: 33985 | J11: =SUM(H11:I11) -> 33985
C12: Due from other governments | H12: 73510 | J12: =SUM(H12:I12) -> 73510
C13: Equity in Choctaw Road Landfill | H13: 1523456 | J13: =SUM(H13:I13) -> 1523456
C14: Restricted other assets | H14: 903533 | J14: =SUM(H14:I14) -> 903533
C15: Capital assets | J15: =SUM(H15:I15) -> 0
D16: Land | H16: 2513741 | J16: =SUM(H16:I16) -> 2513741
D17: Construction in progress | H17: 434154 | J17: =SUM(H17:I17) -> 434154
D18: Other capital assets, net of depreciation | H18: 35342409 | I18: 1539 | J18: =SUM(H18:I18) -> 35343948
C20: Total Assets | H20: =SUM(H7:H18) -> 53365063 | I20: =SUM(I7:I18) -> 255600 | J20: =SUM(J7:J18) -> 53620663
A22: DEFERRED OUTFLOWS OF RESOURCES
C23: Changes in proportion and differences | J23: =SUM(H23:I23) -> 0
D24: between contributions and proportionate | H24: 291797 | J24: =SUM(H24:I24) -> 291797
C25: Contributions subsequent to the measurement date | H25: 422972 | J25: =SUM(H25:I25) -> 422972
C26: TOTAL DEFERRED OUTFLOWS OF RESOURCES | H26: =SUM(H23:H25) -> 714769 | I26: =SUM(I23:I25) -> 0 | J26: =SUM(J23:J25) -> 714769
A29: LIABILITIES
C30: Accounts payable | H30: 684647 | I30: 67 | J30: =SUM(H30:I30) -> 684714
C31: Advanced revenue | H31: 853311 | J31: =SUM(H31:I31) -> 853311
C32: Due to FEMA | H32: 16418 | J32: =SUM(H32:I32) -> 16418
C33: Due to other governments | H33: 735348 | I33: 29006 | J33: =SUM(H33:I33) -> 764354
C34: OPEB liability | H34: 819356 | J34: =SUM(H34:I34) -> 819356
C35: Net pension liability | H35: 140536 | J35: =SUM(H35:I35) -> 140536
C36: Long-term liabilities: | J36: =SUM(H36:I36) -> 0
D37: Portion due within one year | H37: 1589575 | J37: =SUM(H37:I37) -> 1589575
D38: Portion due in more than one year | H38: 1535000 | J38: =SUM(H38:I38) -> 1535000
D40: Total Liabilities | H40: =SUM(H30:H38) -> 6374191 | I40: =SUM(I30:I38) -> 29073 | J40: =SUM(J30:J38) -> 6403264
A42: DEFERRED INFLOWS OF RESOURCES
C43: Changes in proportion and differences
D44: between contributions and proportionate | H44: 719 | J44: =SUM(H44:I44) -> 719
C45: Contributions subsequent to the measurement date | H45: 62474 | J45: =SUM(H45:I45) -> 62474
C46: TOTAL DEFERRED INFLOWS OF RESOURCES | H46: =SUM(H44:H45) -> 63193 | I46: =SUM(I44:I45) -> 0 | J46: =SUM(J44:J45) -> 63193
A48: NET ASSETS
B49: Net invested in capital assets | H49: 35259109 | J49: =SUM(H49:I49) -> 35259109
B50: Restricted for:
C51: Capital projects | H51: 903667 | J51: =SUM(H51:I51) -> 903667
C52: Health and welfare | H52: 947374 | I52: 12979 | J52: =SUM(H52:I52) -> 960353
C53: Solid waste disposal | H53: 1714073 | J53: =SUM(H53:I53) -> 1714073
C54: Debt service | H54: 1557083 | J54: =SUM(H54:I54) -> 1557083
C55: Highways and bridges | H55: 3330668 | J55: =SUM(H55:I55) -> 3330668
C56: Other purposes | H56: 1862054 | J56: =SUM(H56:I56) -> 1862054
B57: Unrestricted | H57: 2068420 | I57: 216548 | J57: =SUM(H57:I57) -> 2284968
C59: Total Net Assets | H59: =SUM(H49:H57) -> 47642448 | I59: =SUM(I49:I57) -> 229527 | J59: =SUM(J48:J57) -> 47871975
C61: Total Liabilities and Net Assets | H61: =H59+H40+H46 -> 54079832 | I61: =I59+I40+I46 -> 258600 | J61: =J59+J40+J46 -> 54338432

Sheet Webster
D1: Webster Parish 2015 Statement of Net Assets
D2: Issued: December 31, 2015
H4: Primary Government | I4: Component Units
H5: Governmental Activities | I5: E-911
A6: ASSETS
C7: Cash and cash equivalents | H7: 4888461 | I7: 334414
C8: Investments | H8: 6218447 | I8: 357922
C9: Receivables | H9: 6087509 | I9: 70837
C10: Prepaid items | H10: 301660 | I10: 25607
C11: Capital assets not being depreciated | H11: 1719932 | I11: 5000
C12: Capital assets, net of accumulated depreciation | H12: 10791881 | I12: 239582
C14: Total Assets | H14: =SUM(H7:H12) -> 30007890 | I14: =SUM(I7:I12) -> 1033362
A16: Deferred outflows of resources
B17: Deferred outflows related to pensions | H17: 732297
C18: Total deferred outflows of resources | H18: =H17 -> 732297 | I18: =I17 -> 0
A20: LIABILITIES
C21: Accounts payable vendors | H21: 233295 | I21: 54751
C22: Accrued payroll liabilities | H22: 204828 | I22: 165
C23: Interest payable | H23: 15573
C24: Due to other governments | H24: 159042
C25: Taxes paid under protest | H25: 45918
C26: Long-term liabilities:
D27: Due within one year | H27: 440773
D28: Due in more than one year | H28: 3699514
D30: Total Liabilities | H30: =SUM(H21:H28) -> 4798943 | I30: =SUM(I21:I28) -> 54916
A32: Deferred inflows of resources
B33: Deferred inflows related to pensions | H33: 93626
C34: Total deferred inflows of resources | H34: =H33 -> 93626 | I34: =I33 -> 0
A36: NET ASSETS
B37: Net investment in capital assets | H37: 12291749 | I37: 244582
B38: Restricted for:
C39: Solid waste collection, road and jail | H39: 749371
C40: Library | H40: 2646112
C41: Road | H41: 2161081
C42: Courthouse and health unit | H42: 1559516
C43: DA salaries and benefits | H43: 1760
C44: Criminal court | H44: 38711
C45: Court reporter | H45: 11724
B46: Unrestricted | H46: 4386594 | I46: 733864
C48: Total Net Assets | H48: =SUM(H37:H46) -> 23846618 | I48: =SUM(I36:I46) -> 978446
C50: Total Liabilities and Net Assets | H50: =H48+H30+H34 -> 28739187 | I50: =I48+I30+I34 -> 1033362

Sheet West Baton Rouge
C1: West Baton Rouge Parish 2015 Statement of Net Assets
C2: Issued: December 31, 2015
G4: Primary Government
G5: Governmental Activities
A6: ASSETS
B7: Cash and cash equivalents | G7: 10377791
B8: Investments | G8: 21163469
B9: Investments - restricted | G9: 108000
B10: Taxes receivable | G10: 8355889
B11: Restricted cash | G11: 189063
B12: Due from other governments | G12: 1876766
B13: Other receivables | G13: 32880
B14: Capital assets:
C15: Non-Depreciable | G15: 4185728
C16: Depreciable | G16: 59896413
B18: Total Assets | G18: =SUM(G7:G16) -> 106185999
A20: DEFERRED OUTFLOWS OF RESOURCES
B21: Resources related to pensions | G21: 1658855
A23: LIABILITIES
B24: Accounts payable | G24: 817207
B25: Noncurrent liabilities:
C26: Due in one year | G26: 352000
C27: Due in more than one year | G27: 9116320
B28: Net pension liability | G28: 581665
C30: Total Liabilities | G30: =SUM(G24:G28) -> 10867192
A32: DEFERRED INFLOWS OF RESOURCES
B33: Resources related to pensions | G33: 237883
B34: Grant advances | G34: 366242
B35: Unavailable revenue - property taxes | G35: 9081687
C36: Total deferred inflows of resources | G36: =SUM(G33:G35) -> 9685812
A38: NET ASSETS
B39: Net investment in capital assets | G39: 60257141
B40: Restricted for:
C41: Debt service | G41: 323029
C42: Poydras endowment | G42: 116203
B43: Unrestricted | G43: 26595477
B45: Total Net Assets | G45: =SUM(G39:G43) -> 87291850
B47: Total Liabilities and Net Assets | G47: =G45+G30 -> 98159042

Sheet West Carroll
D1: West Carroll Parish 2015 Statement of Net Assets
D2: Issued: December 31, 2015
H4: Primary Government
H5: Governmental Activities
A6: ASSETS
C7: Cash and cash equivalents | H7: 6646178
C8: Receivables | H8: 1224084
C9: Deposits held in trust | H9: 871963
C10: Capital assets, net of accumulated depreciation | H10: 13933687
C12: Total Assets | H12: =SUM(H7:H10) -> 22675912
A14: DEFERRED OUTFLOWS
C15: Pension related | H15: 102013
A17: LIABILITIES
C18: Accounts, salaries and other payables | H18: 201775
C19: Compensated absences | H19: 99400
C20: Certificates of indebtedness due within one year | H20: 14133
C21: Certificates of indebtedness due in more than one | H21: 67339
C22: Net pension liability | H22: 102273
C23: Landfill closure/post closure care | H23: 2604250
D25: Total Liabilities | H25: =SUM(H18:H23) -> 3089170
A27: DEFERRED INFLOWS
C28: Pension related | H28: 24649
A30: NET ASSETS
B31: Net investment in capital assets | H31: 13852215
B32: Restricted for:
C33: Public works | H33: 5564983
C34: Public safety | H34: 398497
C35: Health and welfare | H35: 533945
C36: Transportation | H36: 46436
C37: Economic Development | H37: 115108
C38: Landfill closure/postclosure | H38: 871963
B39: Unrestricted | H39: -1719041
C41: Total Net Assets | H41: =SUM(H31:H39) -> 19664106
C43: Total Liabilities and Net Assets | H43: =H41+H25 -> 22753276

Sheet West Feliciana
D1: West Feliciana Parish 2015 Statement of Net Assets
D2: Issued: June 30, 2015
H4: Primary Government | K4: Component Unit
H5: Governmental Activities | I5: Business-Type Activities | J5: Total | K5: Business-type Activities
A6: ASSETS
C7: Cash and cash equivalents | H7: 110339 | I7: 465156 | J7: =SUM(H7:I7) -> 575495 | K7: 4686062
C8: Certificates of deposit | J8: =SUM(H8:I8) -> 0 | K8: 2997251
C9: Investments | H9: 10899604 | I9: 278861 | J9: =SUM(H9:I9) -> 11178465
C10: Taxes receivable | H10: 302613 | J10: 302613 | K10: 700725
C11: Due from other governments | H11: 138401 | J11: =SUM(H11:I11) -> 138401
C12: Accouns receivable (net) | H12: 107324 | I12: 101572 | J12: =SUM(H12:I12) -> 208896 | K12: 3215993
C13: Inventory | J13: =SUM(H13:I13) -> 0 | K13: 107277
C14: Due from third party payors | K14: 502229
C15: Prepaid expenses | H15: 178716 | I15: 28502 | J15: =SUM(H15:I15) -> 207218 | K15: 262525
C16: Restricted assets: | J16: =SUM(H16:I16) -> 0
D17: Cash and cash equivalents | H17: 454 | I17: 150579 | J17: =SUM(H17:I17) -> 151033 | K17: 5238252
D18: Certificates of deposit | J18: =SUM(H18:I18) -> 0 | K18: 1038904
D19: Investments | H19: 402650 | I19: 205353 | J19: =SUM(H19:I19) -> 608003 | K19: 4812156
C20: Capital assets: | J20: =SUM(H20:I20) -> 0
D21: Land and construction in progress | H21: 1388267 | I21: 222849 | J21: =SUM(H21:I21) -> 1611116 | K21: 3117632
D22: Depreciable, net | H22: 18060953 | I22: 9456996 | J22: =SUM(H22:I22) -> 27517949 | K22: 4707616
C24: Total Assets | H24: =SUM(H7:H22) -> 31589321 | I24: =SUM(I7:I22) -> 10909868 | J24: =SUM(J7:J22) -> 42499189 | K24: =SUM(K7:K22) -> 31386622
A27: LIABILITIES
C28: Accounts payable | H28: 457756 | I28: 47471 | J28: =SUM(H28:I28) -> 505227 | K28: 515409
C29: Accrued expenses and other liabilities | H29: 140421 | I29: 19858 | J29: =SUM(H29:I29) -> 160279 | K29: 1057189
C30: Customer deposits | I30: 150579 | J30: =SUM(H30:I30) -> 150579
C31: Internal balances | H31: 33061 | I31: -33061 | J31: =SUM(H31:I31) -> 0
C32: Long-term liabilities:
D33: Due within one year | H33: 202787 | I33: 132418 | J33: =SUM(H33:I33) -> 335205
D34: Due beyond one year | H34: 3573051 | I34: 3046345 | J34: =SUM(H34:I34) -> 6619396
D35: Net pension liability | H35: 52408 | I35: 1627 | J35: 54035
D37: Total Liabilities | H37: =SUM(H28:H35) -> 4459484 | I37: =SUM(I28:I35) -> 3365237 | J37: =SUM(J28:J35) -> 7824721 | K37: =SUM(K28:K35) -> 1572598
A40: NET ASSETS
B41: Net investment in capital assets | H41: 16144220 | I41: 6577030 | J41: 22721250 | K41: 7825248
B42: Restricted for:
C43: Debt service | H43: 429308 | I43: 205353 | J43: =SUM(H43:I43) -> 634661
C44: Capital improvements | H44: 2033238 | J44: =SUM(H44) -> 2033238 | K44: 11089312
C45: Health unit | H45: 1201206 | J45: =SUM(H45) -> 1201206
C46: Library | H46: 752069 | J46: =SUM(H46) -> 752069
C47: Other | H47: 592908 | J47: =SUM(H47) -> 592908
B48: Unrestricted | H48: 6075121 | I48: 796954 | J48: =SUM(H48:I48) -> 6872075 | K48: 10899464
C50: Total Net Assets | H50: =SUM(H41:H48) -> 27228070 | I50: =SUM(I41:I48) -> 7579337 | J50: =SUM(J41:J48) -> 34807407 | K50: =SUM(K40:K48) -> 29814024
C52: Total Liabilities and Net Assets | H52: =H50+H37 -> 31687554 | I52: =I50+I37 -> 10944574 | J52: =J50+J37 -> 42632128 | K52: =K50+K37 -> 31386622

Sheet Winn
D1: Winn Parish 2015 Statement of Net Assets
D2: Issued: December 31, 2015
H5: 2014 | I5: 2013
A6: ASSETS
C7: Cash and cash equivalents | H7: 2488883 | I7: 1954725
C8: Receivebles | H8: 2915973 | I8: 2232420
C9: Capital assets (net of accumulated depreciation):
D10: Nondepreciable:
E11: Land | H11: 223675 | I11: 223675
E12: Construction in progress | H12: 1140707
D13: Depreciable:
E14: Buildings and improvements | H14: 3393870 | I14: 3516302
E15: Furniture, equipment, and other | H15: 699638 | I15: 624965
E16: Infrastructure - roads and bridges | H16: 1977000 | I16: 1529469
C17: Deferred outflows for pension benefit obligations | H17: 297779
C19: Total Assets | H19: =SUM(H7:H16) -> 12839746 | I19: =SUM(I7:I16) -> 10081556
A21: LIABILITIES
C22: Accounts, salaries, and other payables | H22: 1235643 | I22: 232973
C23: Interest payable | H23: 33839 | I23: 38485
C24: Section 8 housing debt
C25: Long-term liabilities:
D26: Due within one year | H26: 235000 | I26: 225000
D27: Due in more than one year | H27: 1639848 | I27: 1836600
D29: Total Liabilities | H29: =SUM(H22:H27) -> 3144330 | I29: =SUM(I22:I27) -> 2333058
C30: Deferred inflows- deferred revenues
A32: NET ASSETS
B33: Net investment in capital assets | H33: 5649891 | I33: 3884412
B34: Unrestricted | H34: 4268692 | I34: 3850944
C36: Total Net Assets | H36: =SUM(H33:H34) -> 9918583 | I36: =SUM(I33:I34) -> 7735356
C38: Total Liabilities and Net Assets | H38: =H36+H29 -> 13062913 | I38: =I36+I29 -> 10068414

Sheet CSG
A1: 2014-SONA
C2: Assets: | N2: Liabilities: | S2: Non-Current/Long-Term Liabilities: | AA2: Net Assets:
A3: Denotes Error Found in Statement | C3: Cash | D3: Investments | E3: Receivables | F3: Capital Assets | G3: Transfers | H3: Other Assets | I3: Total Assets (Sum) | J3: Accuracy | K3: Accuracy | M3: Accounts Payable | N3: Compensated Absences Payable | O3: Bonds Payable Due within 1 Year | P3: Bonds Payable Due after 1 Year | Q3: Government Transfers | R3: Payable within 1 Year | S3: Payable after 1 Year | T3: Other Liabilities | U3: Total Liabilities (Sum) | V3: Accuracy | W3: Accuracy | Z3: Invested in Capital Assets, Net of Related Debt | AA3: Restricted Assets | AB3: Unrestricted Assets | AC3: Total Net Assets (Sum) | AD3: Total Liabilites and Net Assets (Sum) | AE3: Accuracy | AF3: Accuracy
A4: Parish's Statement Not Available | L4: Deferred Outflows of Resources | X4: PARISH | Y4: Deferred Inflows of Resources
B5: County | L5: PARISH | Y5: PARISH
B6: Acadia | C6: =Acadia!H8 -> 9195544 | D6: =Acadia!H9 -> 7939036 | E6: =Acadia!H10+Acadia!H11+Acadia!H12 -> 6569586 | F6: =Acadia!H16+Acadia!H17 -> 51958817 | G6: =Acadia!H13+Acadia!H14 -> 570637 | I6: =SUM(C6:H6) -> 76233620 | J6: =IF(I6=K6, "ok", "check") -> ok | K6: =Acadia!H19 -> 76233620 | L6: =Acadia!H24 -> 665400 | M6: =Acadia!H28+Acadia!H30+Acadia!H32 -> 2003627 | N6: =Acadia!H37+Acadia!H40 -> 335044 | O6: =Acadia!H36 -> 1587435 | P6: =Acadia!H39 -> 9865913 | T6: =Acadia!H41+Acadia!H42+Acadia!H31 -> 5528330 | U6: =SUM(M6:T6) -> 19320349 | V6: =IF(U6=W6, "ok", "check") -> ok | W6: =Acadia!H44 -> 19320349 | Y6: =Acadia!H48 -> 178983 | Z6: =Acadia!H51 -> 40505469 | AA6: =Acadia!H53+Acadia!H54+Acadia!H55 -> 17402203 | AB6: =Acadia!H56 -> -507984 | AC6: =SUM(Z6:AB6) -> 57399688 | AD6: =SUM(AC6,U6,Y6) -> 76899020 | AE6: =IF(AD6=AF6, "ok", "check") -> ok | AF6: =Acadia!H60 -> 76899020
B7: Allen | C7: =Allen!G6 -> 4069562 | E7: =Allen!G7 -> 2833111 | F7: =Allen!G10+Allen!G11 -> 23784501 | H7: =Allen!G8+Allen!G9 -> 807574 | I7: =SUM(C7:H7) -> 31494748 | J7: =IF(I7=K7, "ok", "check") -> ok | K7: =Allen!G13 -> 31494748 | L7: =Allen!G16 -> 31771531 | M7: =Allen!G19+Allen!G20 -> 830187 | O7: =Allen!G22+Allen!G24 -> 283759 | P7: =Allen!G27+Allen!G28 -> 1448246 | T7: =Allen!G26+Allen!G21 -> 1359985 | U7: =SUM(M7:T7) -> 3922177 | V7: =IF(U7=W7, "ok", "check") -> ok | W7: =Allen!G30 -> 3922177 | Y7: =Allen!G32 -> 24855 | Z7: =Allen!G35 -> 22129069 | AA7: =Allen!G37+Allen!G38+Allen!G39+Allen!G40+Allen!G41+Allen!G42+Allen!G43 -> 5716350 | AB7: =Allen!G44 -> -20920 | AC7: =SUM(Z7:AB7) -> 27824499 | AD7: =SUM(AC7,U7,Y7) -> 31771531 | AE7: =IF(AD7=AF7, "ok", "check") -> ok | AF7: =Allen!G48 -> 31771531
B8: Ascension | C8: =Ascension!I8 -> 32250738 | D8: =Ascension!I9 -> 135507608 | E8: =Ascension!I10 -> 35732327 | F8: =Ascension!I17+Ascension!I18 -> 227315163 | G8: =Ascension!I11 -> 5417238 | H8: =Ascension!I12+Ascension!I13 -> 251838 | I8: =SUM(C8:H8) -> 436474912 | J8: =IF(I8=K8, "ok", "check") -> ok | K8: =Ascension!I20 -> 436474912 | L8: =Ascension!I24 -> 6506451 | M8: =Ascension!I31+Ascension!I32 -> 8246829 | O8: =Ascension!I39 -> 354297 | P8: =Ascension!I40 -> 904237 | Q8: =Ascension!I33 -> 472207 | R8: =Ascension!I42 -> 5546774 | S8: =Ascension!I43+Ascension!I44+Ascension!I45 -> 81229155 | T8: =Ascension!I34+Ascension!I36+Ascension!I37 -> 5910689 | U8: =SUM(M8:T8) -> 102664188 | V8: =IF(U8=W8, "ok", "check") -> ok | W8: =Ascension!I47 -> 102664188 | Y8: =Ascension!I52 -> 864558 | Z8: =Ascension!I55 -> 129059066 | AA8: =Ascension!I57+Ascension!I58+Ascension!I59+Ascension!I60+Ascension!I61+Ascension!I62+Ascension!I63 -> 132695918 | AB8: =Ascension!I64 -> 81533262 | AC8: =SUM(Z8:AB8) -> 343288246 | AD8: =SUM(AC8,U8,Y8) -> 446816992 | AE8: =IF(AD8=AF8, "ok", "check") -> ok | AF8: =Ascension!I68 -> 446816992
B9: Assumption | C9: =Assumption!H7 -> 5055668 | D9: =Assumption!H8+Assumption!H12 -> 59397814 | E9: =Assumption!H9 -> 5990950 | H9: =Assumption!H10 -> 139035 | I9: =SUM(C9:H9) -> 70583467 | J9: =IF(I9=K9, "ok", "check") -> ok | K9: =Assumption!H14 -> 70583467 | L9: =Assumption!H18 -> 546760 | M9: =Assumption!H22+Assumption!H23+Assumption!H25 -> 2794508 | T9: =Assumption!H30+Assumption!H26+Assumption!H24 -> 1011241 | U9: =SUM(M9:T9) -> 3805749 | V9: =IF(U9=W9, "ok", "check") -> ok | W9: =Assumption!H32 -> 3805749 | Y9: =Assumption!H36 -> 70848 | Z9: =Assumption!H39 -> 44674146 | AB9: =Assumption!H41 -> 22579484 | AC9: =SUM(Z9:AB9) -> 67253630 | AD9: =SUM(AC9,U9,Y9) -> 71130227 | AE9: =IF(AD9=AF9, "ok", "check") -> ok | AF9: =Assumption!H45 -> 71130227
B10: Avoyelles | C10: =Avoyelles!H7 -> 10522207 | E10: =Avoyelles!H8 -> 33789 | F10: =Avoyelles!H12 -> 4318512 | G10: =Avoyelles!H9 -> 2575929 | H10: =Avoyelles!H10+Avoyelles!H11 -> 1884776 | I10: =SUM(C10:H10) -> 19335213 | J10: =IF(I10=K10, "ok", "check") -> ok | K10: =Avoyelles!H14 -> 19335213 | M10: =Avoyelles!H19 -> 689137 | R10: =Avoyelles!H23 -> 30149 | S10: =Avoyelles!H24 -> 64772 | T10: =Avoyelles!H20+Avoyelles!H21+Avoyelles!H25 -> 181332 | U10: =SUM(M10:T10) -> 965390 | V10: =IF(U10=W10, "ok", "check") -> ok | W10: =Avoyelles!H27 -> 965390 | Z10: =Avoyelles!H32 -> 6094458 | AB10: =Avoyelles!H33 -> 12415547 | AC10: =SUM(Z10:AB10) -> 18510005 | AD10: =SUM(AC10,U10,Y10) -> 19475395 | AE10: =IF(AD10=AF10, "ok", "check") -> ok | AF10: =Avoyelles!H37 -> 19475395
B11: Beauregard | C11: =Beauregard!G6 -> 25520552 | E11: =Beauregard!G7 -> 6425452 | F11: =Beauregard!G11+Beauregard!G12+Beauregard!G13+Beauregard!G14+Beauregard!G15 -> 35981007 | H11: =Beauregard!G8+Beauregard!G9 -> 561035 | I11: =SUM(C11:H11) -> 68488046 | J11: =IF(I11=K11, "ok", "check") -> ok | K11: =Beauregard!G17 -> 68488046 | L11: =Beauregard!G20 -> 587818 | M11: =Beauregard!G23+Beauregard!G24 -> 1565028 | R11: =Beauregard!G27 -> 1256668 | S11: =Beauregard!G28 -> 13691999 | T11: =Beauregard!G25 -> 148204 | U11: =SUM(M11:T11) -> 16661899 | V11: =IF(U11=W11, "ok", "check") -> ok | W11: =Beauregard!G30 -> 16661899 | Y11: =Beauregard!G33 -> 99372 | Z11: =Beauregard!G36 -> 21141007 | AA11: =Beauregard!G38+Beauregard!G39+Beauregard!G40+Beauregard!G41+Beauregard!G42+Beauregard!G43+Beauregard!G44+Beauregard!G45+Beauregard!G46+Beauregard!G47 -> 29436387 | AB11: =Beauregard!G48 -> 1737199 | AC11: =SUM(Z11:AB11) -> 52314593 | AD11: =SUM(AC11,U11) -> 68976492 | AE11: =IF(AD11=AF11, "ok", "check") -> ok | AF11: =Beauregard!G52 -> 68976492
B12: Bienville | C12: =Bienville!G6 -> 16858491 | E12: =Bienville!G7 -> 4654602 | F12: =Bienville!G8 -> 22261869 | I12: =SUM(C12:H12) -> 43774962 | J12: =IF(I12=K12, "ok", "check") -> ok | K12: =Bienville!G10 -> 43774962 | L12: =Bienville!G14 -> 134448 | M12: =Bienville!G17+Bienville!G18+Bienville!G19 -> 380370 | N12: =Bienville!G23 -> 87473 | O12: =Bienville!G20 -> 9895000 | T12: =Bienville!G21+Bienville!G22+Bienville!G24+Bienville!G25 -> 2272690 | U12: =SUM(M12:T12) -> 12635533 | V12: =IF(U12=W12, "ok", "check") -> ok | W12: =Bienville!G27 -> 12635533 | Y12: =Bienville!G30 -> 46967 | Z12: =Bienville!G33 -> 12366869 | AB12: =Bienville!G34 -> 18860041 | AC12: =SUM(Z12:AB12) -> 31226910 | AD12: =SUM(AC12,U12,Y12) -> 43909410 | AE12: =IF(AD12=AF12, "ok", "check") -> ok | AF12: =Bienville!G38 -> 43909410
B13: Bossier | C13: =Bossier!H7+Bossier!H8 -> 46120367 | D13: =Bossier!H9+Bossier!H10 -> 13617426 | E13: =Bossier!H11 -> 18410937 | F13: =Bossier!H14+Bossier!H15 -> 287462625 | H13: =Bossier!H12+Bossier!H16 -> 9099384 | I13: =SUM(C13:H13) -> 374710739 | J13: =IF(I13=K13, "ok", "check") -> ok | K13: =Bossier!H18 -> 374710739 | L13: =Bossier!H21 -> 2017962 | M13: =Bossier!H25 -> 3040969 | R13: =Bossier!H29 -> 4779068 | S13: =Bossier!H30 -> 65724929 | U13: =SUM(M13:T13) -> 73544966 | V13: =IF(U13=W13, "ok", "check") -> ok | W13: =Bossier!H32 -> 73544966 | Y13: =Bossier!H38 -> 15229888 | Z13: =Bossier!H41 -> 241133940 | AA13: =Bossier!H43+Bossier!H44+Bossier!H45+Bossier!H46+Bossier!H47+Bossier!H48+Bossier!H49+Bossier!H50 -> 23609034 | AB13: =Bossier!H51 -> 23210873 | AC13: =SUM(Z13:AB13) -> 287953847 | AD13: =SUM(AC13,U13,Y13) -> 376728701 | AE13: =IF(AD13=AF13, "ok", "check") -> ok | AF13: =Bossier!H55 -> 376728701
B14: Caddo | C14: =Caddo!H7 -> 5950999 | D14: =Caddo!H8 -> 124633857 | E14: =Caddo!H9 -> 44347039 | F14: =Caddo!H15+Caddo!H16 -> 161621740 | G14: =Caddo!H10 -> 2274558 | H14: =Caddo!H12+Caddo!H13 -> 134881 | I14: =SUM(C14:H14) -> 338963074 | J14: =IF(I14=K14, "ok", "check") -> ok | K14: =Caddo!H18 -> 338963074 | L14: =Caddo!H24 -> 342242285 | M14: =Caddo!H27+Caddo!H28+Caddo!H29+Caddo!H30+Caddo!H31 -> 5295787 | Q14: =Caddo!H32+Caddo!H33 -> 1176460 | R14: =Caddo!H36 -> 3181419 | S14: =Caddo!H37+Caddo!H38+Caddo!H39 -> 39998835 | T14: =Caddo!H34 -> 34466 | U14: =SUM(M14:T14) -> 49686967 | V14: =IF(U14=W14, "ok", "check") -> ok | W14: =Caddo!H41 -> 49686967 | Y14: =Caddo!H48 -> 490293 | Z14: =Caddo!H51 -> 135822820 | AA14: =Caddo!H53+Caddo!H54+Caddo!H55+Caddo!H56+Caddo!H57+Caddo!H58+Caddo!H59+Caddo!H60 -> 92558691 | AB14: =Caddo!H62 -> 63756848 | AC14: =SUM(Z14:AB14) -> 292138359 | AD14: =SUM(AC14,U14,Y14) -> 342315619 | AE14: =IF(AD14=AF14, "ok", "check") -> ok | AF14: =Caddo!H66 -> 342315619
B15: Calcasieu | C15: =Calcasieu!H7 -> 47833925 | D15: =Calcasieu!H8 -> 254012189 | E15: =Calcasieu!H9+Calcasieu!H10+Calcasieu!H13 -> 64851295 | F15: =Calcasieu!H22+Calcasieu!H23 -> 530837466 | G15: =Calcasieu!H11 -> 4408 | H15: =Calcasieu!H14+Calcasieu!H15 -> 1486747 | I15: =SUM(C15:H15) -> 899026030 | J15: =IF(I15=K15, "ok", "check") -> ok | K15: =Calcasieu!H25 -> 899026030 | L15: =Calcasieu!H28 -> 0 | M15: =Calcasieu!H34+Calcasieu!H35 -> 12251202 | Q15: =Calcasieu!H36 -> 60846 | R15: =Calcasieu!H41 -> 2926865 | S15: =Calcasieu!H42 -> 9767208 | T15: =Calcasieu!H37+Calcasieu!H38 -> 3554634 | U15: =SUM(M15:T15) -> 28560755 | V15: =IF(U15=W15, "ok", "check") -> ok | W15: =Calcasieu!H44 -> 28560755 | Y15: =Calcasieu!H50 -> 50608056 | Z15: =Calcasieu!H54 -> 530837466 | AA15: =Calcasieu!H57+Calcasieu!H58 -> 208831216 | AB15: =Calcasieu!H59 -> 86151868 | AC15: =SUM(Z15:AB15) -> 825820550 | AD15: =SUM(AC15,U15,Y15) -> 904989361 | AE15: =IF(AD15=AF15, "ok", "check") -> ok | AF15: =Calcasieu!H63 -> 904989361
B16: Caldwell | C16: =Caldwell!G6 -> 7400441 | E16: =Caldwell!G7 -> 1902779 | F16: =Caldwell!G8 -> 16886347 | I16: =SUM(C16:H16) -> 26189567 | J16: =IF(I16=K16, "ok", "check") -> ok | K16: =Caldwell!G10 -> 26189567 | M16: =Caldwell!G17 -> 436806 | N16: =Caldwell!G19 -> 102079 | Q16: =Caldwell!G18 -> 57698 | T16: =Caldwell!G20 -> 86662 | U16: =SUM(M16:T16) -> 683245 | V16: =IF(U16=W16, "ok", "check") -> ok | W16: =Caldwell!G22 -> 683245 | Y16: =Caldwell!G25 -> 35166 | Z16: =Caldwell!G28 -> 16886347 | AA16: =Caldwell!G29 -> 8172641 | AB16: =Caldwell!G30 -> 497998 | AC16: =SUM(Z16:AB16) -> 25556986 | AD16: =SUM(AC16,U16,Y16) -> 26275397 | AE16: =IF(AD16=AF16, "ok", "check") -> ok | AF16: =Caldwell!G34 -> 26275397
B17: Cameron | C17: =Cameron!G6 -> 16575500 | D17: =Cameron!G7 -> 11477630 | E17: =Cameron!G8 -> 13918620 | F17: =Cameron!G11 -> 123784927 | H17: =Cameron!G9+Cameron!G10 -> 2055319 | I17: =SUM(C17:H17) -> 167811996 | J17: =IF(I17=K17, "ok", "check") -> ok | K17: =Cameron!G13 -> 167811996 | M17: =Cameron!G18+Cameron!G21 -> 2021750 | Q17: =Cameron!G19 -> 2551196 | R17: =Cameron!G23 -> 1183863 | S17: =Cameron!G24 -> 3075083 | T17: =Cameron!G20 -> 17231 | U17: =SUM(M17:T17) -> 8849123 | V17: =IF(U17=W17, "ok", "check") -> ok | W17: =Cameron!G26 -> 8849123 | Y17: =Cameron!G28 -> 1986478 | Z17: =Cameron!G31 -> 121538091 | AA17: =Cameron!G33+Cameron!G34+Cameron!G35+Cameron!G36+Cameron!G37 -> 2795451 | AB17: =Cameron!G38 -> 33659569 | AC17: =SUM(Z17:AB17) -> 157993111 | AD17: =SUM(AC17,U17,Y17) -> 168828712 | AE17: =IF(AD17=AF17, "ok", "check") -> ok | AF17: =Cameron!G42 -> 168828712
B18: Catahoula | C18: =Catahoula!H9+Catahoula!H8+Catahoula!H7 -> 2211892 | E18: =Catahoula!H10 -> 1487134 | F18: =Catahoula!H12 -> 6900530 | H18: =Catahoula!H11 -> 83326 | I18: =SUM(C18:H18) -> 10682882 | J18: =IF(I18=K18, "ok", "check") -> ok | K18: =Catahoula!H14 -> 10682882 | L18: =Catahoula!H17 -> 54981 | M18: =Catahoula!H20 -> 656405 | N18: =Catahoula!H21 -> 36269 | R18: =Catahoula!H22 -> 107000 | S18: =Catahoula!H23+Catahoula!H24 -> 191562 | U18: =SUM(M18:T18) -> 991236 | V18: =IF(U18=W18, "ok", "check") -> ok | W18: =Catahoula!H26 -> 991236 | Y18: =Catahoula!H31 -> 26882 | Z18: =Catahoula!H34 -> 6900530 | AA18: =Catahoula!H35 -> 2035217 | AB18: =Catahoula!H36 -> 783998 | AC18: =SUM(Z18:AB18) -> 9719745 | AD18: =SUM(AC18,U18,Y18) -> 10737863 | AE18: =IF(AD18=AF18, "ok", "check") -> ok | AF18: =Catahoula!H40 -> 10737863
B19: Claiborne | C19: =Claiborne!G6 -> 6780670 | D19: =Claiborne!G7 -> 793544 | E19: =Claiborne!G8 -> 3238498 | F19: =Claiborne!G11 -> 8351695 | H19: =Claiborne!G9+Claiborne!G10 -> 132197 | I19: =SUM(C19:H19) -> 19296604 | J19: =IF(I19=K19, "ok", "check") -> ok | K19: =Claiborne!G13 -> 19296604 | L19: =Claiborne!G16 -> 129494 | M19: =Claiborne!G19 -> 547636 | N19: =Claiborne!G22 -> 70564 | Q19: =Claiborne!G20 -> 14025 | R19: =Claiborne!G23 -> 155000 | S19: =Claiborne!G24 -> 1390000 | T19: =Claiborne!G25+Claiborne!G21 -> 102866 | U19: =SUM(M19:T19) -> 2280091 | V19: =IF(U19=W19, "ok", "check") -> ok | W19: =Claiborne!G27 -> 2280091 | Y19: =Claiborne!G30 -> 33504 | Z19: =Claiborne!G33 -> 6806695 | AA19: =Claiborne!G35+Claiborne!G36+Claiborne!G37+Claiborne!G38+Claiborne!G39+Claiborne!G40 -> 5527961 | AB19: =Claiborne!G41 -> 4777847 | AC19: =SUM(Z19:AB19) -> 17112503 | AD19: =SUM(AC19,U19,Y19) -> 19426098 | AE19: =IF(AD19=AF19, "ok", "check") -> ok | AF19: =Claiborne!G45 -> 19426098
B20: Concordia | C20: =Concodria!G7+Concodria!G8 -> 10550680 | E20: =Concodria!G9+Concodria!G10+Concodria!G11+Concodria!G12 -> 2051861 | I20: =SUM(C20:H20) -> 12602541 | J20: =IF(I20=K20, "ok", "check") -> ok | K20: =Concodria!G14 -> 12602541 | L20: =Concodria!G22 -> 22917340 | M20: =Concodria!G26+Concodria!G28 -> 434484 | R20: =Concodria!G29 -> 413369 | S20: =Concodria!G34 -> 76459 | T20: =Concodria!G33+Concodria!G27 -> 8511844 | U20: =SUM(M20:T20) -> 9436156 | V20: =IF(U20=W20, "ok", "check") -> ok | W20: =Concodria!G37 -> 9436156 | Y20: =Concodria!G40 -> 34846 | Z20: =Concodria!G43 -> 1247208 | AA20: =Concodria!G45+Concodria!G46 -> 8247768 | AB20: =Concodria!G47 -> 3951362 | AC20: =SUM(Z20:AB20) -> 13446338 | AD20: =SUM(AC20,U20,Y20) -> 22917340 | AE20: =IF(AD20=AF20, "ok", "check") -> ok | AF20: =Concodria!G51 -> 22917340
B21: DeSoto | C21: =DeSoto!H7 -> 8494984 | D21: =DeSoto!H8 -> 20852796 | E21: =DeSoto!H9 -> 13253156 | F21: =DeSoto!H11 -> 76265772 | H21: =DeSoto!H10 -> 26264 | I21: =SUM(C21:H21) -> 118892972 | J21: =IF(I21=K21, "ok", "check") -> ok | K21: =DeSoto!H13 -> 118892972 | M21: =DeSoto!H19 -> 1358547 | N21: =DeSoto!H25 -> 323506 | Q21: =DeSoto!H23 -> 154306 | R21: =DeSoto!H29 -> 449 | T21: =DeSoto!H27+DeSoto!H26+DeSoto!H24+DeSoto!H22+DeSoto!H21+DeSoto!H20 -> 5940756 | U21: =SUM(M21:T21) -> 7777564 | V21: =IF(U21=W21, "ok", "check") -> ok | W21: =DeSoto!H31 -> 7777564 | Z21: =DeSoto!H36 -> 76265323 | AA21: =DeSoto!H37 -> 449 | AB21: =DeSoto!H38 -> 35278671 | AC21: =SUM(Z21:AB21) -> 111544443 | AD21: =SUM(AC21,U21,Y21) -> 119322007 | AE21: =IF(AD21=AF21, "ok", "check") -> ok | AF21: =DeSoto!H42 -> 119322007
B22: East Baton Rouge | C22: ='East Baton Rouge'!H8 -> 166127175 | D22: ='East Baton Rouge'!H9 -> 211759186 | E22: ='East Baton Rouge'!H10+'East Baton Rouge'!H13 -> 56651587 | F22: ='East Baton Rouge'!H22+'East Baton Rouge'!H23 -> 891275868 | G22: ='East Baton Rouge'!H11 -> 84333564 | H22: ='East Baton Rouge'!H12+'East Baton Rouge'!H14 -> 1279414 | I22: =SUM(C22:H22) -> 1411426794 | J22: =IF(I22=K22, "ok", "check") -> ok | K22: ='East Baton Rouge'!H25 -> 1411426794 | L22: ='East Baton Rouge'!H32 -> 96236116 | M22: ='East Baton Rouge'!H35 -> 27771571 | Q22: ='East Baton Rouge'!H37 -> 490429 | R22: ='East Baton Rouge'!H43 -> 35509330 | S22: ='East Baton Rouge'!H44 -> 1236678992 | T22: ='East Baton Rouge'!H36+'East Baton Rouge'!H38+'East Baton Rouge'!H39+'East Baton Rouge'!H40+'East Baton Rouge'!H41 -> 21932705 | U22: =SUM(M22:T22) -> 1322383027 | V22: =IF(U22=W22, "ok", "check") -> ok | W22: ='East Baton Rouge'!H46 -> 1322383027 | Y22: ='East Baton Rouge'!H51 -> 8127460 | Z22: ='East Baton Rouge'!H54 -> 665194789 | AA22: ='East Baton Rouge'!H56+'East Baton Rouge'!H57+'East Baton Rouge'!H59 -> 166068834 | AB22: ='East Baton Rouge'!H60 -> -650015599 | AC22: =SUM(Z22:AB22) -> 181248024 | AD22: =SUM(AC22,U22,Y22) -> 1511758511 | AE22: =IF(AD22=AF22, "ok", "check") -> ok | AF22: ='East Baton Rouge'!H64 -> 1511758511
B23: East Carroll | C23: ='East Carroll'!H7 -> 1995746 | D23: ='East Carroll'!H8 -> 719027 | E23: ='East Carroll'!H9 -> 2907365 | F23: ='East Carroll'!H12+'East Carroll'!H13 -> 6158446 | I23: =SUM(C23:H23) -> 11780584 | J23: =IF(I23=K23, "ok", "check") -> ok | K23: ='East Carroll'!H15 -> 11780584 | M23: ='East Carroll'!H22+'East Carroll'!H23 -> 117666 | R23: ='East Carroll'!H25 -> 213975 | S23: ='East Carroll'!H26 -> 310647 | U23: =SUM(M23:T23) -> 642288 | V23: =IF(U23=W23, "ok", "check") -> ok | W23: ='East Carroll'!H28 -> 642288 | Y23: ='East Carroll'!H32 -> 39401 | Z23: ='East Carroll'!H35 -> 5701437 | AA23: ='East Carroll'!H37+'East Carroll'!H38+'East Carroll'!H39+'East Carroll'!H40+'East Carroll'!H41+'East Carroll'!H42+'East Carroll'!H43+'East Carroll'!H44+'East Carroll'!H45 -> 4775557 | AB23: ='East Carroll'!H47 -> 909109 | AC23: =SUM(Z23:AB23) -> 11386103 | AD23: =SUM(AC23,U23,Y23) -> 12067792 | AE23: =IF(AD23=AF23, "ok", "check") -> ok | AF23: ='East Carroll'!H51 -> 12067792
B24: East Feliciana | C24: ='East Feliciana'!G6 -> 4577606 | E24: ='East Feliciana'!G7 -> 1201051 | F24: ='East Feliciana'!G10 -> 14087861 | G24: ='East Feliciana'!G8+'East Feliciana'!G9 -> 1959767 | I24: =SUM(C24:H24) -> 21826285 | J24: =IF(I24=K24, "ok", "check") -> ok | K24: ='East Feliciana'!G12 -> 21826285 | L24: ='East Feliciana'!G15 -> 132270 | M24: ='East Feliciana'!G19 -> 98217 | N24: ='East Feliciana'!G23 -> 8736 | Q24: ='East Feliciana'!G20+'East Feliciana'!G21 -> 1417178 | T24: ='East Feliciana'!G22 -> 66241 | U24: =SUM(M24:T24) -> 1590372 | V24: =IF(U24=W24, "ok", "check") -> ok | W24: ='East Feliciana'!G25 -> 1590372 | Y24: ='East Feliciana'!G29 -> 23363 | Z24: ='East Feliciana'!G32 -> 14087861 | AA24: ='East Feliciana'!G34+'East Feliciana'!G35+'East Feliciana'!G36 -> 4934203 | AB24: ='East Feliciana'!G37 -> 1322756 | AC24: =SUM(Z24:AB24) -> 20344820 | AD24: =SUM(AC24,U24,Y24) -> 21958555 | AE24: =IF(AD24=AF24, "ok", "check") -> ok | AF24: ='East Feliciana'!G41 -> 21958555
B25: Evangeline | C25: =Evangeline!H7 -> 9976548 | D25: =Evangeline!H13 -> 7198420 | E25: =Evangeline!H8 -> 7163 | F25: =Evangeline!H14 -> 47031804 | G25: =Evangeline!H9 -> 6075704 | H25: =Evangeline!H10 -> 46456 | I25: =SUM(C25:H25) -> 70336095 | J25: =IF(I25=K25, "ok", "check") -> ok | K25: =Evangeline!H16 -> 70336095 | L25: =Evangeline!H18 -> 560010 | M25: =Evangeline!H22+Evangeline!H23+Evangeline!H25 -> 3168413 | R25: =Evangeline!H29 -> 1889000 | S25: =Evangeline!H30+Evangeline!H31 -> 28329881 | T25: =Evangeline!H24+Evangeline!H26 -> 312615 | U25: =SUM(M25:T25) -> 33699909 | V25: =IF(U25=W25, "ok", "check") -> ok | W25: =Evangeline!H33 -> 33699909 | Z25: =Evangeline!H38 -> 24827361 | AA25: =Evangeline!H39 -> 144210 | AB25: =Evangeline!H40 -> 12141928 | AC25: =SUM(Z25:AB25) -> 37113499 | AD25: =SUM(AC25,U25,Y25) -> 70813408 | AE25: =IF(AD25=AF25, "ok", "check") -> ok | AF25: =Evangeline!H44 -> 70813408
B26: Franklin | C26: =Franklin!G6 -> 9845125 | E26: =Franklin!G7 -> 3565030 | F26: =Franklin!G8 -> 19315782 | I26: =SUM(C26:H26) -> 32725937 | J26: =IF(I26=K26, "ok", "check") -> ok | K26: =Franklin!G10 -> 32725937 | M26: =Franklin!G17+Franklin!G18+Franklin!G20 -> 527170 | N26: =Franklin!G19 -> 97918 | Q26: =Franklin!G24 -> 72472 | R26: =Franklin!G22 -> 31000 | S26: =Franklin!G23 -> 72000 | T26: =Franklin!G25 -> 1566426 | U26: =SUM(M26:T26) -> 2366986 | V26: =IF(U26=W26, "ok", "check") -> ok | W26: =Franklin!G27 -> 2366986 | Y26: =Franklin!G30 -> 28927 | Z26: =Franklin!G33 -> 19170120 | AB26: =Franklin!G34 -> 11271104 | AC26: =SUM(Z26:AB26) -> 30441224 | AD26: =SUM(AC26,U26,Y26) -> 32837137 | AE26: =IF(AD26=AF26, "ok", "check") -> ok | AF26: =Franklin!G38 -> 32837137
B27: Grant | C27: =Grant!H7 -> 1607559 | E27: =Grant!H8 -> 1476524 | F27: =Grant!H11+Grant!H12+Grant!H13 -> 6116377 | I27: =SUM(C27:H27) -> 9200460 | J27: =IF(I27=K27, "ok", "check") -> ok | K27: =Grant!H15 -> 9200460 | L27: =Grant!H17 -> 327152 | M27: =Grant!H20+Grant!H21 -> 514131 | N27: =Grant!H25 -> 48059 | R27: =Grant!H27 -> 97605 | S27: =Grant!H28 -> 149857 | T27: =Grant!H29 -> 95921 | U27: =SUM(M27:T27) -> 905573 | V27: =IF(U27=W27, "ok", "check") -> ok | W27: =Grant!H31 -> 905573 | Y27: =Grant!H33 -> 101227 | Z27: =Grant!H36 -> 5836045 | AA27: =Grant!H38+Grant!H39+Grant!H40 -> 1815365 | AB27: =Grant!H41 -> 869402 | AC27: =SUM(Z27:AB27) -> 8520812 | AD27: =SUM(AC27,U27,Y27) -> 9527612 | AE27: =IF(AD27=AF27, "ok", "check") -> ok | AF27: =Grant!H45 -> 9527612
B28: Iberia | C28: =Iberia!H7 -> 46860646 | D28: =Iberia!H8 -> 63081 | E28: =Iberia!H9 -> 7717579 | F28: =Iberia!H19+Iberia!H20 -> 94128935 | G28: =Iberia!H11 -> 3219065 | H28: =Iberia!H10 -> 1989685 | I28: =SUM(C28:H28) -> 153978991 | J28: =IF(I28=K28, "ok", "check") -> ok | K28: =Iberia!H22:H22 -> 153978991 | L28: =Iberia!H27 -> 1266943 | M28: =Iberia!H30+Iberia!H31+Iberia!H32+Iberia!H38 -> 2421887 | Q28: =Iberia!H33+Iberia!H34 -> 978926 | R28: =Iberia!H43 -> 1825318 | S28: =Iberia!H44 -> 13093322 | T28: =Iberia!H36+Iberia!H41+Iberia!H42 -> 5907636 | U28: =SUM(M28:T28) -> 24227089 | V28: =IF(U28=W28, "ok", "check") -> ok | W28: =Iberia!H46 -> 24227089 | Y28: =Iberia!H49 -> 109223 | Z28: =Iberia!H52 -> 80033586 | AA28: =Iberia!H54+Iberia!H55+Iberia!H56+Iberia!H57+Iberia!H58 -> 30104905 | AB28: =Iberia!H59 -> 20771131 | AC28: =SUM(Z28:AB28) -> 130909622 | AD28: =SUM(AC28,U28,Y28) -> 155245934 | AE28: =IF(AD28=AF28, "ok", "check") -> ok | AF28: =Iberia!H63 -> 155245934
B29: Iberville | C29: =Iberville!H8+Iberville!H15 -> 30413280 | E29: =Iberville!H10 -> 9106856 | F29: =Iberville!H17+Iberville!H18+Iberville!H19+Iberville!H20+Iberville!H21 -> 117701950 | H29: =Iberville!H12+Iberville!H13 -> 1223108 | I29: =SUM(C29:H29) -> 158445194 | J29: =IF(I29=K29, "ok", "check") -> ok | K29: =Iberville!H23 -> 158445194 | L29: =Iberville!H26 -> 1111407 | M29: =Iberville!H29+Iberville!H33 -> 4312803 | R29: =Iberville!H38 -> 1415089 | S29: =Iberville!H39 -> 18163086 | T29: =Iberville!H36+Iberville!H37 -> 790277 | U29: =SUM(M29:T29) -> 24681255 | V29: =IF(U29=W29, "ok", "check") -> ok | W29: =Iberville!H41 -> 24681255 | Y29: =Iberville!H44 -> 97127 | Z29: =Iberville!H47 -> 99077563 | AA29: =Iberville!H49+Iberville!H50+Iberville!H51+Iberville!H52+Iberville!H53+Iberville!H54+Iberville!H55+Iberville!H56 -> 23751758 | AB29: =Iberville!H57 -> 11948898 | AC29: =SUM(Z29:AB29) -> 134778219 | AD29: =SUM(AC29,U29,Y29) -> 159556601 | AE29: =IF(AD29=AF29, "ok", "check") -> ok | AF29: =Iberville!H61 -> 159556601
B30: Jackson | C30: ='Jackson '!G6 -> 10715548 | E30: ='Jackson '!G7 -> 5708768 | F30: ='Jackson '!G10+'Jackson '!G11 -> 17232753 | H30: ='Jackson '!G8 -> 43519 | I30: =SUM(C30:H30) -> 33700588 | J30: =IF(I30=K30, "ok", "check") -> ok | K30: ='Jackson '!G13 -> 33700588 | L30: ='Jackson '!G17 -> 425617 | M30: ='Jackson '!G20 -> 491701 | R30: ='Jackson '!G23 -> 372241 | S30: ='Jackson '!G24 -> 3340963 | T30: ='Jackson '!G21 -> 25321 | U30: =SUM(M30:T30) -> 4230226 | V30: =IF(U30=W30, "ok", "check") -> ok | W30: ='Jackson '!G26 -> 4230226 | Y30: ='Jackson '!G30 -> 64691 | Z30: ='Jackson '!G33 -> 14791909 | AA30: ='Jackson '!G35+'Jackson '!G36+'Jackson '!G37+'Jackson '!G38+'Jackson '!G39+'Jackson '!G40+'Jackson '!G41+'Jackson '!G42+'Jackson '!G43+'Jackson '!G44 -> 11746525 | AB30: ='Jackson '!G45 -> 3292854 | AC30: =SUM(Z30:AB30) -> 29831288 | AD30: =SUM(AC30,U30,Y30) -> 34126205 | AE30: =IF(AD30=AF30, "ok", "check") -> ok | AF30: ='Jackson '!G49 -> 34126205
B31: Jefferson | C31: =Jefferson!H9 -> 5540 | D31: =Jefferson!H10 -> 73132 | E31: =Jefferson!H14+Jefferson!H15+Jefferson!H16+Jefferson!H19 -> 268489 | F31: =Jefferson!H35+Jefferson!H36 -> 1315842 | H31: =Jefferson!H11+Jefferson!H21+Jefferson!H33 -> 570151 | I31: =SUM(C31:H31) -> 2233154 | J31: =IF(I31=K31, "ok", "check") -> ok | K31: =Jefferson!H40 -> 2233154 | L31: =Jefferson!H47 -> 44672 | M31: =Jefferson!H51+Jefferson!H52+Jefferson!H53+Jefferson!H56+Jefferson!H57+Jefferson!H58 -> 49708 | R31: =Jefferson!H54 -> 34211 | S31: =Jefferson!H75 -> 413686 | T31: =Jefferson!H71+Jefferson!H59+Jefferson!H55 -> 254441 | U31: =SUM(M31:T31) -> 752046 | V31: =IF(U31=W31, "ok", "check") -> ok | W31: =Jefferson!H79 -> 752046 | Y31: =Jefferson!H82 -> 4096 | Z31: =Jefferson!H85 -> 991422 | AA31: =Jefferson!H87+Jefferson!H88+Jefferson!H89+Jefferson!H90+Jefferson!H91+Jefferson!H92+Jefferson!H93+Jefferson!H94+Jefferson!H95+Jefferson!H96+Jefferson!H98 -> 443291 | AB31: =Jefferson!H99 -> 86971 | AC31: =SUM(Z31:AB31) -> 1521684 | AD31: =SUM(AC31,U31,Y31) -> 2277826 | AE31: =IF(AD31=AF31, "ok", "check") -> ok | AF31: =Jefferson!H103 -> 2277826
