Workbook

Sheet Acadia
D1: Acadia PARISH POLICE JURY
D2: Capital Assets
D3: For the Year Ended December 31, 2015
G5: Beginning Balance | H5: Increases | I5: Decreases | J5: Ending Balance | K5: Cross Sectional
A7: Governmental Activities:
B8: Capital assets, not being depreciated:
C9: Land | G9: 1329008 | J9: =SUM(G9:I9) -> 1329008 | K9: =SUM(J9) -> 1329008
C10: Construction in progress | G10: 616503 | H10: 1825499 | I10: -2066442 | J10: =SUM(G10:I10) -> 375560 | K10: =SUM(J10) -> 375560
D12: Total capital assets, not being depreciated | G12: =SUM(G8:G11) -> 1945511 | H12: =SUM(H8:H11) -> 1825499 | I12: =SUM(I8:I11) -> -2066442 | J12: =SUM(J8:J11) -> 1704568
A14: Capital assets being depreciated:
B15: Buildings and improvements | G15: 23688240 | H15: 54286 | I15: -5973 | J15: =SUM(G15:I15) -> 23736553
B16: Machinery and equipment | G16: 12080397 | H16: 1258934 | I16: -1963756 | J16: =SUM(G16:I16) -> 11375575
B17: Improvements, other than buildings | G17: 773911 | J17: =SUM(G17:I17) -> 773911
B18: Infrastructure | G18: 48425719 | H18: 2244538 | I18: -94604 | J18: =SUM(G18:I18) -> 50575653
D20: Total capital assets being depreciated | G20: =SUM(G15:G19) -> 84968267 | H20: =SUM(H15:H19) -> 3557758 | I20: =SUM(I15:I19) -> -2064333 | J20: =SUM(J15:J19) -> 86461692
A22: Less accumulated depreciation for:
B23: Buildings and improvements | G23: -7150978 | H23: -448517 | I23: 5437 | J23: =SUM(G23:I23) -> -7594058 | K23: =J15+J23 -> 16142495
B24: Machinery and equipment | G24: -7128864 | H24: -746121 | I24: 1530246 | J24: =SUM(G24:I24) -> -6344739 | K24: =J16+J24 -> 5030836
B25: Improvements, other than buildings | G25: -414655 | H25: -9777 | J25: =SUM(G25:I25) -> -424432 | K25: =J17+J25 -> 349479
B26: Infrastructure | G26: -19905142 | H26: -2021531 | I26: 82459 | J26: =SUM(G26:I26) -> -21844214 | K26: =J18+J26 -> 28731439
D28: Total accumulated depreciation | G28: =SUM(G23:G27) -> -34599639 | H28: =SUM(H23:H27) -> -3225946 | I28: =SUM(I23:I27) -> 1618142 | J28: =SUM(J23:J27) -> -36207443
B30: Total capital assets being depreciated, net | G30: =G20+G28 -> 50368628 | H30: =H20+H28 -> 331812 | I30: =I20+I28 -> -446191 | J30: =J20+J28 -> 50254249
B32: Governmental activities capital assets, net | G32: =G30+G12 -> 52314139 | H32: =H30+H12 -> 2157311 | I32: =I30+I12 -> -2512633 | J32: =J30+J12 -> 51958817 | K32: =SUM(K23:K26,K9:K10) -> 51958817

Sheet Allen
D1: Acadia PARISH POLICE JURY
D2: Capital Assets
D3: 5For the Year Ended December 31, 2015
G5: Beginning Balance | H5: Increases | I5: Decreases | J5: Ending Balance | K5: Cross Sectional
A7: Governmental Activities:
B8: Capital assets, not being depreciated:
C9: Construction in progress | G9: 98703 | H9: 733474 | J9: =SUM(G9:I9) -> 832177 | K9: =J9 -> 832177
C10: Land | G10: 572300 | J10: =SUM(G10:I10) -> 572300 | K10: =J10 -> 572300
J11: =SUM(G11:I11) -> 0
D12: Total capital assets, not being depreciated | G12: =SUM(G9:G10) -> 671003 | H12: =SUM(H9:H10) -> 733474 | I12: =SUM(I9:I10) -> 0 | J12: =SUM(J9:J10) -> 1404477
A14: Capital assets being depreciated:
B15: Buildings | G15: 4595339 | J15: =SUM(G15:I15) -> 4595339
B16: Improvements, other than buildings | G16: 5855585 | J16: =SUM(G16:I16) -> 5855585
B17: Furniture and fixtures | G17: 431836 | J17: =SUM(G17:I17) -> 431836
B18: Vehicles | G18: 824249 | J18: =SUM(G18:I18) -> 824249
B19: Machinery and equipment | G19: 3482205 | H19: 229473 | I19: -37240 | J19: =SUM(G19:I19) -> 3674438
B20: Infrastructure | G20: 28219912 | J20: =SUM(G20:I20) -> 28219912
D21: Total capital assets being depreciated | G21: =SUM(G15:G20) -> 43409126 | H21: =SUM(H15:H20) -> 229473 | I21: =SUM(I15:I20) -> -37240 | J21: =SUM(J15:J20) -> 43601359
A23: Less accumulated depreciation for:
B24: Buildings | G24: 1889518 | H24: 102571 | J24: =SUM(G24:I24) -> 1992089 | K24: =SUM(J15-J24) -> 2603250
B25: Improvements, other than buildings | G25: 2376805 | H25: 171245 | J25: =SUM(G25:I25) -> 2548050 | K25: =SUM(J16-J25) -> 3307535
B26: Furniture and fixtures | G26: 343425 | H26: 33565 | J26: =SUM(G26:I26) -> 376990 | K26: =SUM(J17-J26) -> 54846
B27: Vehicles | G27: 667485 | H27: 48766 | J27: =SUM(G27:I27) -> 716251 | K27: =SUM(J18-J27) -> 107998
B28: Machinery and equipment | G28: 2382902 | H28: 203919 | I28: -22014 | J28: =SUM(G28:I28) -> 2564807 | K28: =SUM(J19-J28) -> 1109631
B29: Infrastructure | G29: 12446165 | H29: 584415 | J29: =SUM(G29:I29) -> 13030580 | K29: =SUM(J20-J29) -> 15189332
D30: Total accumulated depreciation | G30: =SUM(G24:G29) -> 20106300 | H30: =SUM(H24:H29) -> 1144481 | I30: =SUM(I24:I29) -> -22014 | J30: =SUM(J24:J29) -> 21228767
B32: Total capital assets being depreciated, net | G32: =G21-G30 -> 23302826 | H32: =H21-H30 -> -915008 | I32: =I21-I30 -> -15226 | J32: =SUM(G32:I32) -> 22372592
B35: Governmental activities capital assets, net | G35: =SUM(G32+G12) -> 23973829 | H35: =SUM(H32+H12) -> -181534 | I35: =SUM(I32+I12) -> -15226 | J35: =SUM(G35:I35) -> 23777069

Sheet Ascension
D1: ASCENSION PARISH POLICE JURY
D2: Capital Assets
D3: For the Year Ended December 31, 2015
I5: Beginning Balance | J5: Increases | K5: Decreases | L5: Ending Balance | M5: Cross Sectional
A7: Governmental Activities:
B8: Capital assets, not being depreciated:
C9: Land | I9: 17327 | L9: =SUM(I9:K9) -> 17327 | M9: =SUM(L9) -> 17327
C10: Construction in progress | I10: 15500 | J10: 23678 | K10: -10389 | L10: =SUM(I10:K10) -> 28789 | M10: =SUM(L10) -> 28789
D12: Total capital assets, not being depreciated | I12: =SUM(I8:I11) -> 32827 | J12: =SUM(J8:J11) -> 23678 | K12: =SUM(K8:K11) -> -10389 | L12: =SUM(L8:L11) -> 46116
A14: Capital assets being depreciated:
B15: Buildings | I15: 103230 | J15: 10128 | L15: =SUM(I15:K15) -> 113358
B16: Vehicles | I16: 13844 | J16: 866 | K16: -65 | L16: =SUM(I16:K16) -> 14645
B17: Equipment | I17: 13441 | J17: 2019 | K17: -34 | L17: =SUM(I17:K17) -> 15426
B18: Furniture and fixtures | I18: 1121 | J18: 405 | L18: =SUM(I18:K18) -> 1526
B19: Library materials | I19: 2478 | J19: 486 | K19: -571 | L19: =SUM(I19:K19) -> 2393
B20: Infrastructure | I20: 228723 | J20: 2695 | L20: =SUM(I20:K20) -> 231418
D22: Total capital assets being depreciated | I22: =SUM(I15:I21) -> 362837 | J22: =SUM(J15:J21) -> 16599 | K22: =SUM(K15:K21) -> -670 | L22: =SUM(L15:L20) -> 378766
A24: Less accumulated depreciation for:
B25: Buildings | I25: -23538 | J25: -3382 | L25: =SUM(I25:K25) -> -26920 | M25: =SUM(L25,L15) -> 86438
B26: Vehicles | I26: -8853 | J26: -749 | K26: 65 | L26: =SUM(I26:K26) -> -9537 | M26: =SUM(L26,L16) -> 5108
B27: Equipment | I27: -9933 | J27: -1039 | K27: 34 | L27: =SUM(I27:K27) -> -10938 | M27: =SUM(L27,L17) -> 4488
B28: Furniture and fixtures | I28: -724 | J28: -82 | L28: =SUM(I28:K28) -> -806 | M28: =SUM(L28,L18) -> 720
B29: Library materials | I29: -1555 | J29: -479 | K29: 571 | L29: =SUM(I29:K29) -> -1463 | M29: =SUM(L29,L19) -> 930
B30: Infrastructure | I30: -137255 | J30: -10648 | L30: =SUM(I30:K30) -> -147903 | M30: =SUM(L30,L20) -> 83515
D32: Total accumulated depreciation | I32: =SUM(I25:I31) -> -181858 | J32: =SUM(J25:J31) -> -16379 | K32: =SUM(K25:K31) -> 670 | L32: =SUM(L25:L31) -> -197567
B34: Total capital assets being depreciated, net | I34: =I22+I32 -> 180979 | J34: =J22+J32 -> 220 | K34: =K22+K32 -> 0 | L34: =L22+L32 -> 181199
B36: Governmental activities capital assets, net | I36: =I32+I22+I12 -> 213806 | J36: =J32+J22+J12 -> 23898 | K36: =K32+K22+K12 -> -10389 | L36: =L32+L22+L12 -> 227315 | M36: =SUM(M25:M30,M9:M10) -> 227315
I39: Beginning Balance | J39: Increases | K39: Decreases | L39: Ending Balance
A40: Business-Type Activities:
B41: Capital assets, not being depreciated:
C42: Land | I42: 670 | L42: =SUM(I42:K42) -> 670 | M42: =SUM(L42) -> 670
C43: Construction in progress | I43: 1007 | J43: 237 | K43: -259 | L43: =SUM(I43:K43) -> 985 | M43: =SUM(L43) -> 985
D45: Total capital assets, not being depreciated | I45: =SUM(I41:I44) -> 1677 | J45: =SUM(J41:J44) -> 237 | K45: =SUM(K41:K44) -> -259 | L45: =SUM(L41:L44) -> 1655
B47: Capital assets, depreciable:
C48: Sewer systems | I48: 5779 | L48: =SUM(I48:K48) -> 5779
C49: Water systems | I49: 765 | L49: =SUM(I49:K49) -> 765
C50: Machinery & Equipment | I50: 181 | J50: 84 | K50: -16 | L50: =SUM(I50:K50) -> 249
C51: Lamar Dixon Expo Center | I51: 8107 | J51: 230 | L51: =SUM(I51:K51) -> 8337
D53: Total capital assets, depreciable | I53: =SUM(I47:I51) -> 14832 | J53: =SUM(J47:J51) -> 314 | K53: =SUM(K47:K51) -> -16 | L53: =SUM(L47:L51) -> 15130
B55: Less accumulated depreciation for:
C56: Sewer systems | I56: -2342 | J56: -289 | L56: =SUM(I56:K56) -> -2631 | M56: =SUM(L56,L48) -> 3148
C57: Water systems | I57: -415 | J57: -11 | L57: =SUM(I57:K57) -> -426 | M57: =SUM(L57,L49) -> 339
C58: Machinery & Equipment | I58: -90 | J58: -18 | K58: 16 | L58: =SUM(I58:K58) -> -92 | M58: =SUM(L58,L50) -> 157
C59: Lamar Dixon Expo Center | I59: -1893 | J59: -453 | L59: =SUM(I59:K59) -> -2346 | M59: =SUM(L59,L51) -> 5991
D61: Total accumulated depreciation | I61: =SUM(I56:I59) -> -4740 | J61: =SUM(J56:J59) -> -771 | K61: =SUM(K56:K59) -> 16 | L61: =SUM(L56:L59) -> -5495
D63: Total capital assets, depreciable, net | I63: =I53+I61 -> 10092 | J63: =J53+J61 -> -457 | K63: =K53+K61 -> 0 | L63: =L53+L61 -> 9635
D65: Business-type activities capital assets, net | I65: =I63+I45 -> 11769 | J65: =J63+J45 -> -220 | K65: =K63+K45 -> -259 | L65: =L63+L45 -> 11290 | M65: =SUM(M56:M59,M42:M43) -> 11290

Sheet Assumption
D1: Assumption PARISH POLICE JURY
D2: Capital Assets
D3: For the Year Ended December 31, 2015
I5: Balance 12/31/2014 | J5: 2015 Additions | K5: 2015 Deletions | L5: 2015 Reclassifications | M5: Balance 12/31/2015 | N5: Cross Sectional
A7: Primary Government
A8: Government Activities:
B9: Land | I9: 2334193 | J9: 93366 | K9: -1600 | M9: =SUM(I9:K9) -> 2425959 | N9: =M9 -> 2425959
B10: Buildings | I10: 23864600 | J10: 85276 | K10: -1100 | L10: 25577 | M10: =SUM(I10:K10) -> 23948776 | N10: =M10 -> 23948776
B11: Improvements other than buildings | I11: 11757126 | J11: 206249 | K11: -34717 | L11: 371937 | M11: =SUM(I11:K11) -> 11928658
B12: Roads | I12: 16226076 | J12: 491740 | K12: -8001 | M12: =SUM(I12:K12) -> 16709815
B13: Bridges | I13: 588844 | M13: =SUM(I13:K13) -> 588844
B14: Equipmet and other | I14: 7306012 | J14: 692596 | K14: -275906 | M14: =SUM(I14:K14) -> 7722702
B15: Construction in progress | I15: 701781 | J15: 3421482 | K15: -80927 | L15: -397514 | M15: =SUM(I15:K15) -> 4042336
C16: Totals | I16: =SUM(I9:I15) -> 62778632 | J16: =SUM(J9:J15) -> 4990709 | K16: =SUM(K9:K15) -> -402251 | L16: =SUM(L9:L15) -> 0 | M16: =SUM(M9:M15) -> 67367090
D18: Total accumulated depreciation | I18: -20484668 | J18: -2397781 | K18: 189505 | M18: =SUM(I18:L18) -> -22692944 | N18: only shows total accumulated depreciation
A20: Governmental activities, capital assets, net | I20: =SUM(I16+I18) -> 42293964 | J20: =SUM(J16+J18) -> 2592928 | K20: =SUM(K16+K18) -> -212746 | L20: =SUM(L16+L18) -> 0 | M20: =SUM(M16+M18) -> 44674146 | N20: =SUM(N9:N17) -> 26374735

Sheet Avoyelles
D1: AVOYELLES PARISH POLICE JURY
D2: Capital Assets
D3: For the Year Ended December 31, 2015
G5: Balance 01/01/14 | H5: Additions | I5: Decreases | J5: Balance 12/31/14 | K5: Cross Sectional
A7: Governmental Activities:
B8: Capital assets, not being depreciated:
C9: Land | G9: 590548 | J9: =SUM(G9:I9) -> 590548 | K9: =SUM(J9) -> 590548
C10: Construction in progress | H10: 1185398 | J10: =SUM(G10:I10) -> 1185398 | K10: =SUM(J10) -> 1185398
D12: Total capital assets, not being depreciated | G12: =SUM(G8:G11) -> 590548 | H12: =SUM(H8:H11) -> 1185398 | I12: =SUM(I8:I11) -> 0 | J12: =SUM(J8:J11) -> 1775946
A14: Capital assets being depreciated:
B15: Buildings and improvements | G15: 5369883 | J15: =SUM(G15:I15) -> 5369883
B16: Equipment, furniture and fixtures | G16: 624821 | H16: 22110 | I16: -3717 | J16: =SUM(G16:I16) -> 643214
B17: Infrastructure | G17: 78140 | J17: =SUM(G17:I17) -> 78140
B18: Heavy equipment | G18: 3436008 | H18: 81907 | I18: -35726 | J18: =SUM(G18:I18) -> 3482189
D20: Total capital assets being depreciated | G20: =SUM(G18+G17+G16+G15+G12) -> 10099400 | H20: =SUM(H18+H17+H16+H15+H12) -> 1289415 | I20: =SUM(I18+I17+I16+I15+I12) -> -39443 | J20: =SUM(J18+J17+J16+J15+J12) -> 11349372
A22: Less accumulated depreciation for:
B23: Buildings and improvements | G23: 1637135 | H23: 200275 | J23: =SUM(G23:I23) -> 1837410 | K23: =J15-J23 -> 3532473
B24: Equipment, furniture and fixtures | G24: 550732 | H24: 21545 | I24: -3717 | J24: =SUM(G24:I24) -> 568560 | K24: =J16-J24 -> 74654
B25: Infrastructure | G25: 40698 | H25: 6213 | J25: =SUM(G25:I25) -> 46911 | K25: =J17-J25 -> 31229
B26: Heavy equipment | G26: 2680975 | H26: 143981 | I26: -22923 | J26: =SUM(G26:I26) -> 2802033 | K26: =J18-J26 -> 680156
D28: Total accumulated depreciation | G28: =SUM(G23:G26) -> 4909540 | H28: =SUM(H23:H27) -> 372014 | I28: =SUM(I23:I27) -> -26640 | J28: =SUM(J23:J27) -> 5254914
B30: Governmental activities capital assets, net | G30: =SUM(G20-G28) -> 5189860 | H30: =SUM(H20-H28) -> 917401 | I30: =SUM(I20-I28) -> -12803 | J30: =SUM(J20-J28) -> 6094458 | K30: =SUM(K23:K26,K9:K10) -> 6094458

Sheet Beauregard
D1: BEAUREGARD PARISH POLICE JURY
D2: Capital Assets
D3: For the Year Ended December 31, 2015
I5: Beginning Balance | J5: Additions | K5: Deletions | L5: Transfers | M5: Ending Balance | N5: Cross Sectional
A7: Government Activities:
A8: Capital assets, not being depreciated:
B9: Land | I9: 688379 | J9: 10400 | M9: =SUM(I9:L9) -> 698779 | N9: =SUM(M9) -> 698779
B10: Construction in progress | I10: 2175229 | J10: 6501660 | L10: -3036656 | M10: =SUM(I10:L10) -> 5640233 | N10: =SUM(M10) -> 5640233
C11: Total assets not being depreciated | I11: =SUM(I9:I10) -> 2863608 | J11: =SUM(J9:J10) -> 6512060 | K11: =SUM(K9:K10) -> 0 | L11: =SUM(L9:L10) -> -3036656 | M11: =SUM(M9:M10) -> 6339012
A13: Capital assets being depreciated:
B14: Buildings and improvements | I14: 17820827 | J14: 9759 | L14: 3036656 | M14: =SUM(I14:L14) -> 20867242
B15: Infrastructure | I15: 42862850 | M15: =SUM(I15:L15) -> 42862850
B16: Furniture and equipment | I16: 12511676 | J16: 441044 | M16: =SUM(I16:L16) -> 12952720
C17: Total capital assets being depreciated | I17: =SUM(I14:I16) -> 73195353 | J17: =SUM(J14:J16) -> 450803 | K17: =SUM(K14:K16) -> 0 | L17: =SUM(L14:L16) -> 3036656 | M17: =SUM(M14:M16) -> 76682812
A19: Less accumulated depreciation for:
B20: Buildings and improvements | I20: -8634982 | J20: -563822 | M20: =SUM(I20:L20) -> -9198804 | N20: =SUM(M20,M14) -> 11668438
B21: Infrastructure | I21: -27471416 | J21: -1115249 | M21: =SUM(I21:L21) -> -28586665 | N21: =SUM(M21,M15) -> 14276185
B22: Furniture and equipment | I22: -8415337 | J22: -840011 | M22: =SUM(I22:L22) -> -9255348 | N22: =M16+M22 -> 3697372
C23: Total accumulated depreciation | I23: =SUM(I20:I22) -> -44521735 | J23: =SUM(J20:J22) -> -2519082 | K23: =SUM(K20:K22) -> 0 | L23: =SUM(L20:L22) -> 0 | M23: =SUM(M20:M22) -> -47040817
B24: Total capital assets being depreciated, net | I24: =I23+I17 -> 28673618 | J24: =J23+J17 -> -2068279 | K24: =K23+K17 -> 0 | L24: =L23+L17 -> 3036656 | M24: =M23+M17 -> 29641995
B25: Governmental activities capital assets, net | I25: =I11+I24 -> 31537226 | J25: =J11+J24 -> 4443781 | K25: =K11+K24 -> 0 | L25: =L11+L24 -> 0 | M25: =M11+M24 -> 35981007 | N25: =SUM(N20:N22,N9:N10) -> 35981007

Sheet Bienville
D1: BIENVILLE PARISH POLICE JURY
D2: Capital Assets
D3: For the Year Ended December 31, 2015
I5: Beginning Balance | J5: Increases | K5: Decreases | L5: Ending Balance | M5: Cross Sectional
A7: Governmental Activities:
B8: Capital assets, not being depreciated:
C9: Land | I9: 660250 | L9: =SUM(I9:K9) -> 660250 | M9: =SUM(L9) -> 660250
D11: Total capital assets, not being depreciated | I11: =SUM(I8:I9) -> 660250 | J11: =SUM(J8:J9) -> 0 | K11: =SUM(K8:K9) -> 0 | L11: =SUM(L8:L9) -> 660250
M12: =SUM(L12) -> 0
A13: Capital assets being depreciated: | M13: =SUM(L13) -> 0
B14: Infrastructure | M14: =SUM(L14) -> 0
C15: Roads | I15: 22192672 | J15: 1170771 | L15: =SUM(I15:K15) -> 23363443
C16: Bridges | I16: 2537698 | L16: =SUM(I16:K16) -> 2537698
B17: Buildings and Improvements | I17: 16851833 | J17: 140528 | L17: =SUM(I17:K17) -> 16992361
B18: Office furniture and equipment | I18: 541664 | L18: =SUM(I18:K18) -> 541664
B19: Heavy Equipment | I19: 1773268 | J19: 285150 | K19: -196548 | L19: =SUM(I19:K19) -> 1861870
B20: Vehicles | I20: 1301447 | L20: =SUM(I20:K20) -> 1301447
B21: Miscellaneous equipment | I21: 514738 | J21: 2950 | L21: =SUM(I21:K21) -> 517688
D23: Total capital assets being depreciated | I23: =SUM(I14:I21) -> 45713320 | J23: =SUM(J14:J21) -> 1599399 | K23: =SUM(K14:K21) -> -196548 | L23: =SUM(L14:L21) -> 47116171
A25: Less accumulated depreciation for:
B26: Infrastructure
C27: Roads | I27: -16676946 | J27: -1106600 | L27: =SUM(I27:K27) -> -17783546 | M27: =SUM(L27,L15) -> 5579897
C28: Bridges | I28: -1358294 | J28: -39480 | L28: =SUM(I28:K28) -> -1397774 | M28: =SUM(L28,L16) -> 1139924
B29: Buildings and Improvements | I29: -3296507 | J29: -369027 | L29: =SUM(I29:K29) -> -3665534 | M29: =SUM(L29,L17) -> 13326827
B30: Office furniture and equipment | I30: -230177 | J30: -103829 | L30: =SUM(I30:K30) -> -334006 | M30: =SUM(L30,L18) -> 207658
B31: Heavy Equipment | I31: -1207999 | J31: -126234 | K31: 196548 | L31: =SUM(I31:K31) -> -1137685 | M31: =SUM(L31,L19) -> 724185
B32: Vehicles | I32: -702086 | J32: -85483 | L32: =SUM(I32:K32) -> -787569 | M32: =SUM(L32,L20) -> 513878
B33: Miscellaneous equipment | I33: -388568 | J33: -19870 | L33: =SUM(I33:K33) -> -408438 | M33: =SUM(L33,L21) -> 109250
M34: =SUM(L34,L22) -> 0
D35: Total accumulated depreciation | I35: =SUM(I26:I33) -> -23860577 | J35: =SUM(J26:J33) -> -1850523 | K35: =SUM(K26:K33) -> 196548 | L35: =SUM(L27:L33) -> -25514552
B37: Total capital assets being depreciated, net | I37: =I23+I35 -> 21852743 | J37: =J23+J35 -> -251124 | K37: =K23+K35 -> 0 | L37: =L23+L35 -> 21601619
M38: =SUM(L38,L26) -> 0
B39: Total capital assets (net) | I39: =I35+I23+I11 -> 22512993 | J39: =J35+J23+J11 -> -251124 | K39: =K35+K23+K11 -> 0 | L39: =L35+L23+L11 -> 22261869 | M39: =SUM(M9:M33) -> 22261869

Sheet Bossier
D1: BOSSIER PARISH POLICE JURY
D2: Capital Assets
D3: For the Year Ended December 31, 2015
I5: Beginning Balance | J5: Transfers | K5: Additions | L5: Deletions | M5: Ending Balance | N5: Cross Sectional
A7: Primary Government
A8: Government Activities:
A9: Capital assets, not being depreciated:
B10: Land | I10: 12972258 | K10: 959710 | L10: -18021 | M10: =SUM(I10:L10) -> 13913947 | N10: =SUM(M10) -> 13913947
B11: Construction in progress | I11: 6272099 | J11: -2635042 | K11: 3588162 | M11: =SUM(I11:L11) -> 7225219 | N11: =SUM(M11) -> 7225219
C12: Total assets not being depreciated | I12: =SUM(I10:I11) -> 19244357 | J12: =SUM(J10:J11) -> -2635042 | K12: =SUM(K10:K11) -> 4547872 | L12: =SUM(L10:L11) -> -18021 | M12: =SUM(M10:M11) -> 21139166
A14: Capital assets being depreciated:
B15: Buildings and improvements | I15: 108272538 | J15: 2260863 | K15: 1606894 | M15: =SUM(I15:L15) -> 112140295
B16: Infrastructure | I16: 231447108 | J16: 374179 | K16: 4838518 | M16: =SUM(I16:L16) -> 236659805
B17: Furniture, equipment and vehicles | I17: 10918840 | J17: -27873 | K17: 598807 | L17: -9900 | M17: =SUM(I17:L17) -> 11479874
B18: Library books and information material | I18: 5191486 | K18: 700039 | M18: =SUM(I18:L18) -> 5891525
C19: Total capital assets being depreciated | I19: =SUM(I15:I18) -> 355829972 | J19: =SUM(J15:J18) -> 2607169 | K19: =SUM(K15:K18) -> 7744258 | L19: =SUM(L15:L18) -> -9900 | M19: =SUM(M15:M18) -> 366171499
A21: Less accumulated depreciation for:
B22: Buildings and improvements | I22: -26669928 | K22: -2910297 | M22: =SUM(I22:L22) -> -29580225 | N22: =SUM(M22,M15) -> 82560070
B23: Infrastructure | I23: -52405834 | K23: -5850138 | M23: =SUM(I23:L23) -> -58255972 | N23: =SUM(M23,M16) -> 178403833
B24: Furniture, equipment and vehicles | I24: -6891385 | J24: 27873 | K24: -731836 | L24: 9900 | M24: =SUM(I24:L24) -> -7585448 | N24: =SUM(M24,M17) -> 3894426
B25: Library books and information material | I25: -3981082 | K25: -445313 | M25: =SUM(I25:L25) -> -4426395 | N25: =M18+M25 -> 1465130
C26: Total accumulated depreciation | I26: =SUM(I22:I25) -> -89948229 | J26: =SUM(J22:J25) -> 27873 | K26: =SUM(K22:K25) -> -9937584 | L26: =SUM(L22:L25) -> 9900 | M26: =SUM(M22:M25) -> -99848040
B28: Total capital assets being depreciated, net | I28: =I26+I19 -> 265881743 | J28: =J26+J19 -> 2635042 | K28: =K26+K19 -> -2193326 | L28: =L26+L19 -> 0 | M28: =M26+M19 -> 266323459
B30: Governmental activities capital assets, net | I30: =I12+I28 -> 285126100 | J30: =J12+J28 -> 0 | K30: =K12+K28 -> 2354546 | L30: =L12+L28 -> -18021 | M30: =M12+M28 -> 287462625 | N30: =SUM(N22:N25,N10:N11) -> 287462625
I33: Beginning Balance | J33: Transfers | K33: Additions | L33: Deletions | M33: Ending Balance
A35: Business-type Activities:
A36: Capital assets not being depreciated:
B37: Land | I37: 1411812 | K37: 46557 | M37: =SUM(I37:L37) -> 1458369 | N37: =SUM(M37) -> 1458369
B38: Goodwill | I38: 1226000 | M38: =SUM(I38:L38) -> 1226000 | N38: =SUM(M38) -> 1226000
B39: Construction in progress | I39: 13631606 | K39: 19762105 | M39: =SUM(I39:L39) -> 33393711 | N39: =SUM(M39) -> 33393711
C40: Total assets not being depreciated | I40: =SUM(I37:I39) -> 16269418 | J40: =SUM(J37:J39) -> 0 | K40: =SUM(K37:K39) -> 19808662 | L40: =SUM(L37:L39) -> 0 | M40: =SUM(M37:M39) -> 36078080
A42: Capital assets being depreciated:
B43: Furniture, equipment and vehicles | I43: 197481 | J43: 27873 | K43: 176236 | M43: =SUM(I43:L43) -> 401590
B44: Buildings and improvements | I44: 4953684 | M44: =SUM(I44:L44) -> 4953684
C45: Total capital assets being depreciated | I45: =SUM(I43:I44) -> 5151165 | J45: =SUM(J43:J44) -> 27873 | K45: =SUM(K43:K44) -> 176236 | L45: =SUM(L43:L44) -> 0 | M45: =SUM(M43:M44) -> 5355274
A47: Less accumulated depreciation for:
B48: Furniture, equipment and vehicles | I48: -5355 | J48: -27873 | K48: -19179 | L48: 0 | M48: =SUM(I48:L48) -> -52407 | N48: =SUM(M48,M43) -> 349183
B49: Buildings and improvements | I49: -535885 | K49: -209007 | L49: 0 | M49: =SUM(I49:L49) -> -744892 | N49: =SUM(M49,M44) -> 4208792
C50: Total accumulated depreciation | I50: =SUM(I48:I49) -> -541240 | J50: =SUM(J48:J49) -> -27873 | K50: =SUM(K48:K49) -> -228186 | L50: =SUM(L48:L49) -> 0 | M50: =SUM(M48:M49) -> -797299
B52: Total capital assets being depreciated, net | I52: =SUM(I50,I45) -> 4609925 | J52: =SUM(J50,J45) -> 0 | K52: =SUM(K50,K45) -> -51950 | L52: =SUM(L50,L45) -> 0 | M52: =SUM(M50,M45) -> 4557975
B54: Business-type activities capital assets, net | I54: =I40+I52 -> 20879343 | J54: =J40+J52 -> 0 | K54: =K40+K52 -> 19756712 | L54: =L40+L52 -> 0 | M54: =M40+M52 -> 40636055 | N54: =SUM(N48:N49,N37:N39) -> 40636055

Sheet Caddo
D1: CADDO PARISH POLICE JURY
D2: Capital Assets
D3: For the Year Ended December 31, 2015
I5: Balance December 31, 2014 | J5: Prior Period Adjustment | K5: Additions | L5: Reductions | M5: Balance December 31, 2015 | N5: Cross Sectional
A7: Government Activities:
A8: Capital assets, not being depreciated:
B9: Land and land improvements | I9: 14578409 | J9: -5261444 | K9: 4758 | M9: =SUM(I9:L9) -> 9321723 | N9: =SUM(M9) -> 9321723
B10: Construction in progress | I10: 5935905 | J10: -4879118 | K10: 694345 | L10: -1372146 | M10: =SUM(I10:L10) -> 378986 | N10: =M10 -> 378986
C11: Total capital assets not being depreciated | I11: =SUM(I9:I10) -> 20514314 | J11: =SUM(J9:J10) -> -10140562 | L11: =SUM(L9:L10) -> -1372146 | M11: =SUM(M9:M10) -> 9700709
A13: Capital assets being depreciated:
B14: Buildings and structures | I14: 101006420 | J14: -27419780 | K14: 1461633 | L14: 1935739 | M14: =SUM(I14:L14) -> 76984012
B15: Equipment and vehicles | I15: 40622356 | J15: -20482923 | K15: 1027653 | L15: -742750 | M15: =SUM(I15:L15) -> 20424336
B16: Infrastructure | I16: 389831937 | K16: 4640426 | L16: -349409 | M16: =SUM(I16:L16) -> 394122954
C17: Total capital assets being depreciated | I17: =SUM(I14:I16) -> 531460713 | J17: =SUM(J14:J16) -> -47902703 | L17: =SUM(L14:L16) -> 843580 | M17: =SUM(M14:M16) -> 491531302
A19: Less accumulated depreciation for:
B20: Buildings and structures | I20: -39428268 | J20: 8104099 | K20: -1887048 | L20: 354964 | M20: =SUM(I20:L20) -> -32856253 | N20: =SUM(M20,M14) -> 44127759
B21: Equipment and vehicles | I21: -28334316 | J21: 16004144 | K21: -1443065 | L21: 741472 | M21: =SUM(I21:L21) -> -13031765 | N21: =SUM(M21,M15) -> 7392571
B22: Infrastructure | I22: -280269332 | K22: -9895425 | L22: 313982 | M22: =SUM(I22:L22) -> -289850775 | N22: =M16+M22 -> 104272179
C23: Total accumulated depreciation | I23: =SUM(I20:I22) -> -348031916 | J23: =SUM(J20:J22) -> 24108243 | L23: =SUM(L20:L22) -> 1410418 | M23: =SUM(M20:M22) -> -335738793
B24: Total capital assets being depreciated, net | I24: =I23+I17 -> 183428797 | J24: =J23+J17 -> -23794460 | L24: =L23+L17 -> 2253998 | M24: =M23+M17 -> 155792509
B25: Capital assets, net | I25: =I11+I24 -> 203943111 | J25: =J11+J24 -> -33935022 | L25: =L11+L24 -> 881852 | M25: =M11+M24 -> 165493218 | N25: =SUM(N20:N22,N9:N10) -> 165493218

Sheet Calcasieu
D1: CALCASIEU PARISH POLICE JURY
D2: Capital Assets
D3: For the Year Ended December 31, 2015
I5: Beginning Balance | J5: Increases | K5: Decreases | L5: Ending Balance | M5: Cross Sectional
A7: Governmental Activities:
B8: Capital assets, not being depreciated:
C9: Land and Right of Ways | I9: 18022266 | J9: 1631096 | L9: =SUM(I9:K9) -> 19653362 | M9: =SUM(L9) -> 19653362
C10: Construction in progress | I10: 7601504 | J10: 11679044 | K10: -6386293 | L10: =SUM(I10:K10) -> 12894255 | M10: =SUM(L10) -> 12894255
C11: Roads | I11: 395417424 | L11: =SUM(I11:K11) -> 395417424 | M11: =SUM(L11) -> 395417424
D13: Total capital assets, not being depreciated | I13: =SUM(I8:I11) -> 421041194 | J13: =SUM(J8:J11) -> 13310140 | K13: =SUM(K8:K11) -> -6386293 | L13: =SUM(L8:L11) -> 427965041
A15: Capital assets being depreciated:
B16: Buildings and Improvements | I16: 133128418 | J16: 8180797 | L16: =SUM(I16:K16) -> 141309215
B17: Machinery and Equipment | I17: 34157047 | J17: 3839777 | K17: -2582340 | L17: =SUM(I17:K17) -> 35414484
B18: Bridges ++ | I18: 14332967 | L18: =SUM(I18:K18) -> 14332967
D20: Total capital assets being depreciated | I20: =SUM(I16:I19) -> 181618432 | J20: =SUM(J16:J19) -> 12020574 | K20: =SUM(K16:K19) -> -2582340 | L20: =SUM(L16:L18) -> 191056666
A22: Less accumulated depreciation for:
B23: Buildings and Improvements | I23: -58486576 | J23: -3664784 | L23: =SUM(I23:K23) -> -62151360 | M23: =SUM(L23,L16) -> 79157855
B24: Machinery and Equipment | I24: -20960602 | J24: -2964284 | K24: 2447325 | L24: =SUM(I24:K24) -> -21477561 | M24: =SUM(L24,L17) -> 13936923
B25: Bridges ++ | I25: -4227106 | J25: -328214 | L25: =SUM(I25:K25) -> -4555320 | M25: =SUM(L25,L18) -> 9777647
D27: Total accumulated depreciation | I27: =SUM(I23:I26) -> -83674284 | J27: =SUM(J23:J26) -> -6957282 | K27: =SUM(K23:K26) -> 2447325 | L27: =SUM(L23:L26) -> -88184241
B29: Total capital assets being depreciated, net | I29: =I20+I27 -> 97944148 | J29: =J20+J27 -> 5063292 | K29: =K20+K27 -> -135015 | L29: =L20+L27 -> 102872425
B31: Governmental activities capital assets, net | I31: =I27+I20+I13 -> 518985342 | J31: =J27+J20+J13 -> 18373432 | K31: =K27+K20+K13 -> -6521308 | L31: =L27+L20+L13 -> 530837466 | M31: =SUM(L31, L22) -> 530837466
I33: Beginning Balance | J33: Increases | K33: Decreases | L33: Ending Balance
A34: Business-Type Activities:
B35: Capital assets, not being depreciated:
C36: Land and Right of Ways | I36: 227920 | L36: =SUM(I36:K36) -> 227920 | M36: =SUM(L36) -> 227920
C37: Construction in progress | I37: 24850 | K37: -24850 | L37: =SUM(I37:K37) -> 0 | M37: =SUM(L37) -> 0
D39: Total capital assets, not being depreciated | I39: =SUM(I35:I38) -> 252770 | J39: =SUM(J35:J38) -> 0 | K39: =SUM(K35:K38) -> -24850 | L39: =SUM(L35:L38) -> 227920
B41: Capital assets, depreciable:
C42: Non-Building Improvements | I42: 11861515 | J42: 490556 | L42: =SUM(I42:K42) -> 12352071 | M42: The numbers are wrong in the source audit
C43: Building and Improvements | I43: 152215 | J43: 7700 | L43: =SUM(I43:K43) -> 159915
C44: Infrastructure | I44: 3862766 | J44: 173256 | K44: -17857 | L44: =SUM(I44:K44) -> 4018165
C45: Machinery and Equipment | I45: 281112 | J45: 17243 | K45: -45239 | L45: =SUM(I45:K45) -> 253116
D47: Total capital assets, depreciable | I47: =SUM(I41:I45) -> 16157608 | J47: =SUM(J41:J45) -> 688755 | K47: =SUM(K41:K45) -> -63096 | L47: =SUM(L41:L45) -> 16783267
B49: Less accumulated depreciation for:
C50: Non-Building Improvements | I50: -4427162 | J50: -345923 | L50: =SUM(I50:K50) -> -4773085 | M50: =SUM(L50,L42) -> 7578986
C51: Building and Improvements | I51: -134097 | J51: -2184 | L51: =SUM(I51:K51) -> -136281 | M51: =SUM(L51,L43) -> 23634
C52: Infrastructure | I52: -1899622 | J52: -132613 | K52: 17857 | L52: =SUM(I52:K52) -> -2014378 | M52: =SUM(L52,L44) -> 2003787
C53: Machinery and Equipment | I53: -212606 | J53: -12061 | K53: 45239 | L53: =SUM(I53:K53) -> -179428 | M53: =SUM(L53,L45) -> 73688
D55: Total accumulated depreciation | I55: =SUM(I50:I53) -> -6673487 | J55: =SUM(J50:J53) -> -492781 | K55: =SUM(K50:K53) -> 63096 | L55: =SUM(L50:L53) -> -7103172
D57: Total capital assets, depreciable, net | I57: =I47+I55 -> 9484121 | J57: =J47+J55 -> 195974 | K57: =K47+K55 -> 0 | L57: =L47+L55 -> 9680095
D59: Business-type activities capital assets, net | I59: =I57+I39 -> 9736891 | J59: =J57+J39 -> 195974 | K59: =K57+K39 -> -24850 | L59: =L57+L39 -> 9908015 | M59: =SUM(M50:M53,M36:M37) -> 9908015

Sheet Caldwell
D1: CALDWELL PARISH POLICE JURY
D2: Capital Assets
D3: For the Year Ended December 31, 2015
I5: Beginning Balance | J5: Transfers | K5: Additions | L5: Deletions | M5: Ending Balance | N5: Cross Sectional
A7: Primary Government
A8: Government Activities:
A9: Capital assets, not being depreciated:
B10: Land | I10: 420095 | M10: =SUM(I10:L10) -> 420095 | N10: =SUM(M10) -> 420095
B11: Construction in progress | I11: 10535878 | K11: 2280297 | L11: -64210 | M11: =SUM(I11:L11) -> 12751965 | N11: =SUM(M11) -> 12751965
C12: Total assets not being depreciated | I12: =SUM(I10:I11) -> 10955973 | J12: =SUM(J10:J11) -> 0 | K12: =SUM(K10:K11) -> 2280297 | L12: =SUM(L10:L11) -> -64210 | M12: =SUM(M10:M11) -> 13172060
A14: Capital assets being depreciated:
B15: Infrastructure
C16: Roads | I16: 47897858 | K16: 752065 | M16: =SUM(I16:L16) -> 48649923
C17: Bridges | I17: 642997 | K17: 20000 | M17: =SUM(I17:L17) -> 662997
B18: Buildings and improvements | I18: 2983905 | K18: 100141 | M18: =SUM(I18:L18) -> 3084046
B19: Land improvements | I19: 716214 | M19: =SUM(I19:L19) -> 716214
B20: Heavy equipment | I20: 1497882 | K20: 45000 | M20: =SUM(I20:L20) -> 1542882
B21: Vehicles | I21: 1187227 | M21: =SUM(I21:L21) -> 1187227
B22: Public works equipment | I22: 285706 | K22: 3767 | M22: =SUM(I22:L22) -> 289473
B23: Office furniture and equipment | I23: 681048 | M23: =SUM(I23:L23) -> 681048
C24: Total capital assets being depreciated | I24: =SUM(I16:I23) -> 55892837 | J24: =SUM(J16:J23) -> 0 | K24: =SUM(K16:K23) -> 920973 | L24: =SUM(L16:L23) -> 0 | M24: =SUM(M16:M23) -> 56813810
A26: Less accumulated depreciation for:
B27: Infrastructure
C28: Roads | I28: -46301262 | K28: -147599 | M28: =SUM(I28:L28) -> -46448861 | N28: =SUM(M28,M16) -> 2201062
C29: Bridges | I29: -642110 | K29: -1554 | M29: =SUM(I29:L29) -> -643664 | N29: =SUM(M29,M17) -> 19333
B30: Buildings and improvements | I30: -2619326 | K30: -23570 | M30: =SUM(I30:L30) -> -2642896 | N30: =SUM(M30,M18) -> 441150
B31: Land improvements | I31: -217293 | K31: -30808 | M31: =SUM(I31:L31) -> -248101 | N31: =SUM(M31,M19) -> 468113
B32: Heavy equipment | I32: -1223555 | K32: -53443 | M32: =SUM(I32:L32) -> -1276998 | N32: =SUM(M32,M20) -> 265884
B33: Vehicles | I33: -1114933 | K33: -30076 | M33: =SUM(I33:L33) -> -1145009 | N33: =SUM(M33,M21) -> 42218
B34: Public works equipment | I34: -129191 | K34: -24085 | M34: =SUM(I34:L34) -> -153276 | N34: =SUM(M34,M22) -> 136197
B35: Office furniture and equipment | I35: -492028 | K35: -48690 | M35: =SUM(I35:L35) -> -540718 | N35: =SUM(M35,M23) -> 140330
C36: Total accumulated depreciation | I36: =SUM(I27:I35) -> -52739698 | J36: =SUM(J27:J35) -> 0 | K36: =SUM(K27:K35) -> -359825 | L36: =SUM(L27:L35) -> 0 | M36: =SUM(M27:M35) -> -53099523
B38: Total capital assets being depreciated, net | I38: =I36+I24 -> 3153139 | J38: =J36+J24 -> 0 | K38: =K36+K24 -> 561148 | L38: =L36+L24 -> 0 | M38: =M36+M24 -> 3714287
B40: Governmental activities capital assets, net | I40: =I12+I38 -> 14109112 | J40: =J12+J38 -> 0 | K40: =K12+K38 -> 2841445 | L40: =L12+L38 -> -64210 | M40: =M12+M38 -> 16886347 | N40: =SUM(N27:N35,N10:N11) -> 16886347

Sheet Cameron
D1: Cameron PARISH POLICE JURY
D2: Capital Assets
D3: For the Year Ended December 31, 2015
I5: Beginning Balance | J5: Additions | K5: Deletions | L5: Ending Balance | M5: Cross Sectional
A7: Primary Government
A8: Government Activities:
B10: Land | L10: =SUM(I10:K10) -> 0 | M10: =SUM(L10) -> 0
B11: Construction in progress | L11: =SUM(I11:K11) -> 0 | M11: =SUM(L11) -> 0
B12: Building and improvements | L12: =SUM(I12:K12) -> 0
B13: Books and videos | L13: =SUM(I13:K13) -> 0
B14: Equipment and furniture | L14: =SUM(I14:K14) -> 0
B15: Infrastructure | L15: =SUM(I15:K15) -> 0
C16: Total capital assets at historical costs | I16: =SUM(I10:I15) -> 0 | J16: =SUM(J10:J15) -> 0 | K16: =SUM(K10:K15) -> 0 | L16: =SUM(L10:L15) -> 0
A18: Capital Assets being Depreciated
B19: Building and improvements | L19: =SUM(I19:K19) -> 0
B20: Books and videos | L20: =SUM(I20:K20) -> 0
B21: Equipment and furniture | L21: =SUM(I21:K21) -> 0
B22: Infrastructure | L22: =SUM(I22:K22) -> 0
C23: Total Capital being Depreciated | I23: =SUM(I17:I22) -> 0 | J23: =SUM(J17:J22) -> 0 | K23: =SUM(K17:K22) -> 0 | L23: =SUM(L17:L22) -> 0 | O23: =SUM(O19:O22) -> 0
L24: =SUM(L18:L23) -> 0
A25: Accumulated Depreciation | L25: =SUM(L19:L24) -> 0
B26: Building and improvements | L26: =SUM(L20:L25) -> 0 | M26: =L19+L26 -> 0
B27: Books and videos | L27: =SUM(L21:L26) -> 0 | M27: =L20+L27 -> 0
B28: Equipment and furniture | L28: =SUM(L22:L27) -> 0 | M28: =L21+L28 -> 0
B29: Infrastructure | L29: =SUM(L23:L28) -> 0 | M29: =L22+L29 -> 0
C30: Total Accumulated Depreciation | I30: =SUM(I25:I29) -> 0 | J30: =SUM(J25:J29) -> 0 | K30: =SUM(K25:K29) -> 0 | L30: =SUM(L25:L29) -> 0
C32: Less accumulated depreciation | L32: =SUM(I32:K32) -> 0
C34: Total capital assets, net | I34: =SUM(I16,I32) -> 0 | J34: =SUM(J16,J32) -> 0 | K34: =K16-K32 -> 0 | L34: =SUM(L16,L32) -> 0 | M34: =SUM(M10:M29) -> 0

Sheet Catahoula
D1: CATAHOULA PARISH POLICE JURY
D2: Capital Assets
D3: For the Year Ended December 31, 2015
I5: Beginning Balance | J5: Adjustments | K5: Additions | L5: Deletions | M5: Ending Balance | N5: Cross Sectional
A7: Primary Government
A8: Government Activities:
A9: Capital assets, not being depreciated:
B10: Land | I10: 112200 | M10: =SUM(I10:L10) -> 112200 | N10: =SUM(M10) -> 112200
B11: Construction in progress | I11: 33780 | K11: 1386372 | M11: =SUM(I11:L11) -> 1420152 | N11: =SUM(M11) -> 1420152
C12: Total assets not being depreciated | I12: =SUM(I10:I11) -> 145980 | J12: =SUM(J10:J11) -> 0 | K12: =SUM(K10:K11) -> 1386372 | L12: =SUM(L10:L11) -> 0 | M12: =SUM(M10:M11) -> 1532352
A14: Capital assets being depreciated:
B15: Infrastructure-roads and bridges | I15: 11514532 | K15: 60445 | M15: =SUM(I15:L15) -> 11574977
B16: Buildings | I16: 2996844 | K16: 6778 | M16: =SUM(I16:L16) -> 3003622
B17: Improvements | I17: 1543519 | K17: 12840 | M17: =SUM(I17:L17) -> 1556359
B18: Equipment | I18: 1416128 | K18: 14033 | M18: =SUM(I18:L18) -> 1430161
B19: Heavy equipment | I19: 991480 | M19: =SUM(I19:L19) -> 991480
B20: Vehicles | I20: 549424 | K20: 29606 | M20: =SUM(I20:L20) -> 579030
B21: Books and periodicals | I21: 710868 | K21: 34889 | L21: -21046 | M21: =SUM(I21:L21) -> 724711
C22: Total capital assets being depreciated | I22: =SUM(I15:I21) -> 19722795 | J22: =SUM(J15:J21) -> 0 | K22: =SUM(K15:K21) -> 158591 | L22: =SUM(L15:L21) -> -21046 | M22: =SUM(M15:M21) -> 19860340
A24: Less accumulated depreciation for:
B25: Infrastructure - roads and bridges | I25: 8482039 | K25: 112330 | M25: =SUM(I25:L25) -> 8594369 | N25: =M15-M25 -> 2980608
B26: Buildings | I26: 2571739 | K26: 18632 | M26: =SUM(I26:L26) -> 2590371 | N26: =M16-M26 -> 413251
B27: Improvements | I27: 262987 | K27: 61740 | M27: =SUM(I27:L27) -> 324727 | N27: =M17-M27 -> 1231632
B28: Equipment | I28: 1164822 | K28: 52303 | M28: =SUM(I28:L28) -> 1217125 | N28: =M18-M28 -> 213036
B29: Heavy equipment | I29: 681467 | K29: 54023 | M29: =SUM(I29:L29) -> 735490 | N29: =M19-M29 -> 255990
B30: Vehicles | I30: 347870 | K30: 42525 | M30: =SUM(I30:L30) -> 390395 | N30: =M20-M30 -> 188635
B31: Books and periodicals | I31: 626802 | K31: 33929 | L31: -21046 | M31: =SUM(I31:L31) -> 639685 | N31: =M21-M31 -> 85026
C32: Total accumulated depreciation | I32: =SUM(I25:I31) -> 14137726 | J32: =SUM(J25:J31) -> 0 | K32: =SUM(K25:K31) -> 375482 | L32: =SUM(L25:L31) -> -21046 | M32: =SUM(M25:M31) -> 14492162
B34: Total capital assets being depreciated, net | I34: =I22-I32 -> 5585069 | J34: =J22-J32 -> 0 | K34: =K22-K32 -> -216891 | L34: =L22-L32 -> 0 | M34: =M22-M32 -> 5368178
B36: Governmental activities capital assets, net | I36: =I12+I34 -> 5731049 | J36: =J12+J34 -> 0 | K36: =K12+K34 -> 1169481 | L36: =L12+L34 -> 0 | M36: =M12+M34 -> 6900530 | N36: =SUM(N25:N31, N10:N12) -> 6900530

Sheet Claiborne
D1: CLAIBORNE PARISH POLICE JURY
D2: Capital Assets
D3: For the Year Ended December 31, 2015
I5: Beginning Balance | J5: Transfers | K5: Additions | L5: Deletions | M5: Ending Balance | N5: Cross Sectional
A7: Primary Government
A8: Government Activities:
A9: Capital assets, not being depreciated:
B10: Land
C11: Police Jury | I11: 220570 | M11: =SUM(I11:L11) -> 220570 | N11: =SUM(M11) -> 220570
C12: Library | I12: 3580 | M12: =SUM(I12:L12) -> 3580 | N12: =SUM(M12) -> 3580
C13: Office of Community Service | I13: 30000 | M13: =SUM(I13:L13) -> 30000 | N13: =SUM(M13) -> 30000
C14: Adjudicated property | I14: 16638 | K14: 3729 | L14: -667 | M14: =SUM(I14:L14) -> 19700 | N14: =SUM(M14) -> 19700
B15: Construction in progress | I15: 43262 | K15: 318842 | L15: -52985 | M15: =SUM(I15:L15) -> 309119 | N15: =SUM(M15) -> 309119
C16: Total assets not being depreciated | I16: =SUM(I10:I15) -> 314050 | J16: =SUM(J10:J15) -> 0 | K16: =SUM(K10:K15) -> 322571 | L16: =SUM(L10:L15) -> -53652 | M16: =SUM(M10:M15) -> 582969
A18: Capital assets being depreciated:
B19: Infrastructure
C20: Roads | I20: 15517189 | M20: =SUM(I20:L20) -> 15517189
C21: Bridges | I21: 1912668 | M21: =SUM(I21:L21) -> 1912668
B22: Land improvements | I22: 15995 | M22: =SUM(I22:L22) -> 15995
B23: Buildings and improvements | I23: 2590565 | K23: 164257 | M23: =SUM(I23:L23) -> 2754822
B24: Public works heavy equipment | I24: 2859173 | K24: 85134 | L24: -44815 | M24: =SUM(I24:L24) -> 2899492
B25: Public works other equipment | I25: 64075 | M25: =SUM(I25:L25) -> 64075
B26: Vehicles | I26: 218079 | K26: 34038 | M26: =SUM(I26:L26) -> 252117
B27: Other furniture and equipment | I27: 250841 | M27: =SUM(I27:L27) -> 250841
B28: Office of Emergency Preparedness and Homeland Security: | M28: =SUM(I28:L28) -> 0
C29: Vehicles | I29: 67031 | L29: -17907 | M29: =SUM(I29:L29) -> 49124
C30: Office furniture and equipment | I30: 50506 | M30: =SUM(I30:L30) -> 50506
C31: Buildings and improvements | I31: 13205 | M31: =SUM(I31:L31) -> 13205
B32: Office of Community Service | M32: =SUM(I32:L32) -> 0
C33: Land improvements | I33: 7800 | M33: =SUM(I33:L33) -> 7800
C34: Buildings and improvements | I34: 62156 | M34: =SUM(I34:L34) -> 62156
C35: Vehicles | I35: 382847 | K35: 57596 | L35: -67690 | M35: =SUM(I35:L35) -> 372753
C36: Office furniture and equipment | I36: 116327 | M36: =SUM(I36:L36) -> 116327
B37: Library | M37: =SUM(I37:L37) -> 0
C38: Building and improvement | I38: 3855244 | M38: =SUM(I38:L38) -> 3855244
C39: Vehicles | I39: 49901 | M39: =SUM(I39:L39) -> 49901
C40: Furniture and equipment | I40: 327121 | M40: =SUM(I40:L40) -> 327121
C41: Books and videos | I41: 737204 | K41: 43077 | L41: -45212 | M41: =SUM(I41:L41) -> 735069
C42: Total capital assets being depreciated | I42: =SUM(I19:I41) -> 29097927 | J42: =SUM(J19:J41) -> 0 | K42: =SUM(K19:K41) -> 384102 | L42: =SUM(L19:L41) -> -175624 | M42: =SUM(M19:M41) -> 29306405
A44: Less accumulated depreciation for:
B45: Infrastructure
C46: Roads | I46: 14413195 | K46: 37184 | M46: =SUM(I46:L46) -> 14450379 | N46: =SUM(M20-M46) -> 1066810
C47: Bridges | I47: 1257134 | K47: 36672 | M47: =SUM(I47:L47) -> 1293806 | N47: =SUM(M21-M47) -> 618862
B48: Land improvements | I48: 14862 | K48: 800 | M48: =SUM(I48:L48) -> 15662 | N48: =SUM(M22-M48) -> 333
B49: Buildings and improvements | I49: 1547600 | K49: 66391 | M49: =SUM(I49:L49) -> 1613991 | N49: =SUM(M23-M49) -> 1140831
B50: Public works heavy equipment | I50: 1675312 | K50: 206262 | L50: -38881 | M50: =SUM(I50:L50) -> 1842693 | N50: =SUM(M24-M50) -> 1056799
B51: Public works other equipment | I51: 42931 | K51: 3200 | M51: =SUM(I51:L51) -> 46131 | N51: =SUM(M25-M51) -> 17944
B52: Vehicles | I52: 109555 | K52: 18152 | M52: =SUM(I52:L52) -> 127707 | N52: =SUM(M26-M52) -> 124410
B53: Office furniture and equipment | I53: 104519 | K53: 24479 | M53: =SUM(I53:L53) -> 128998 | N53: =SUM(M27-M53) -> 121843
B54: Office of Emergency Preparedness and Homeland Security | M54: =SUM(I54:L54) -> 0 | N54: =SUM(M28-M54) -> 0
C55: Vehicles | I55: 45876 | K55: 4303 | L55: -17907 | M55: =SUM(I55:L55) -> 32272 | N55: =SUM(M29-M55) -> 16852
C56: Office furniture and equipment | I56: 49196 | K56: 336 | M56: =SUM(I56:L56) -> 49532 | N56: =SUM(M30-M56) -> 974
C57: Buildings and improvements | I57: 3685 | K57: 660 | M57: =SUM(I57:L57) -> 4345 | N57: =SUM(M31-M57) -> 8860
B58: Office of Community services | M58: =SUM(I58:L58) -> 0 | N58: =SUM(M32-M58) -> 0
C59: Land improvements | I59: 7800 | M59: =SUM(I59:L59) -> 7800 | N59: =SUM(M33-M59) -> 0
C60: Buildings and improvements | I60: 46791 | K60: 2071 | M60: =SUM(I60:L60) -> 48862 | N60: =SUM(M34-M60) -> 13294
C61: Vehicles | I61: 343018 | K61: 22929 | L61: -67691 | M61: =SUM(I61:L61) -> 298256 | N61: =SUM(M35-M61) -> 74497
C62: Office furniture and equipment | I62: 113454 | K62: 1573 | M62: =SUM(I62:L62) -> 115027 | N62: =SUM(M36-M62) -> 1300
B63: Library | M63: =SUM(I63:L63) -> 0 | N63: =SUM(M37-M63) -> 0
C64: Building and improvement | I64: 519995 | K64: 99909 | M64: =SUM(I64:L64) -> 619904 | N64: =SUM(M38-M64) -> 3235340
C65: Vehicles | I65: 49901 | M65: =SUM(I65:L65) -> 49901 | N65: =SUM(M39-M65) -> 0
C66: Furniture and equipment | I66: 71702 | K66: 26567 | M66: =SUM(I66:L66) -> 98269 | N66: =SUM(M40-M66) -> 228852
C67: Books and videos | I67: 703483 | K67: 35873 | L67: -45212 | M67: =SUM(I67:L67) -> 694144 | N67: =SUM(M41-M67) -> 40925
C68: Total accumulated depreciation | I68: =SUM(I45:I67) -> 21120009 | J68: =SUM(J45:J67) -> 0 | K68: =SUM(K45:K67) -> 587361 | L68: =SUM(L45:L67) -> -169691 | M68: =SUM(M45:M67) -> 21537679
B70: Total capital assets being depreciated, net | I70: =I42-I68 -> 7977918 | J70: =J42-J68 -> 0 | K70: =K42-K68 -> -203259 | L70: =L42-L68 -> -5933 | M70: =M42-M68 -> 7768726
B72: Governmental activities capital assets, net | I72: =I16+I70 -> 8291968 | J72: =J16+J70 -> 0 | K72: =K16+K70 -> 119312 | L72: =L16+L70 -> -59585 | M72: =M16+M70 -> 8351695 | N72: =SUM(N45:N67,N10:N15) -> 8351695

Sheet Concordia
D1: Concordia PARISH POLICE JURY
D2: Capital Assets
D3: For the Year Ended December 31, 2015
I5: Beginning Balance | J5: Additions | K5: Dispositions | L5: Balance 12/31/15 | M5: Cross Sectional
A7: Governmental Activities:
B8: Capital assets, not being depreciated:
C9: Land | I9: 7038 | L9: =SUM(I9:K9) -> 7038 | M9: =SUM(L9) -> 7038
C10: Construction in progress | I10: 12250 | J10: 355613 | L10: =SUM(I10:K10) -> 367863 | M10: =SUM(L10) -> 367863
D11: Total capital assets, not being depreciated | I11: =SUM(I8:I10) -> 19288 | J11: =SUM(J8:J10) -> 355613 | K11: =SUM(K8:K9) -> 0 | L11: =SUM(L9:L10) -> 374901
M12: =SUM(L12) -> 0
A13: Capital assets being depreciated: | M13: =SUM(L13) -> 0
B14: Buildings and Improvements | I14: 5994190 | J14: 263926 | L14: =SUM(I14:K14) -> 6258116 | N14: missing Less Accumulated depreciation for each
B15: Furniture and fixtures | I15: 436844 | L15: =SUM(I15:K15) -> 436844 | N15: capital asset, only shows total accumulated
B16: Machinery and equipment | I16: 2572694 | J16: 88584 | L16: =SUM(I16:K16) -> 2661278 | N16: depreciation
B17: Transportation equipment | I17: 1049687 | L17: =SUM(I17:K17) -> 1049687
B18: Roads and bridges | I18: 12195458 | L18: =SUM(I18:K18) -> 12195458
M19: =SUM(L19) -> 0
D20: Total capital assets being depreciated | I20: =SUM(I14:I18) -> 22248873 | J20: =SUM(J14:J18) -> 352510 | K20: =SUM(K14:K18) -> 0 | L20: =SUM(L14:L18) -> 22601383
A22: Accumulated depreciation | I22: -12052532 | J22: -843656 | L22: =SUM(I22:K22) -> -12896188
B24: Total capital assets being depreciated, net | I24: =SUM(I22+I20) -> 10196341 | J24: =SUM(J22+J20) -> -491146 | K24: =SUM(K22+K20) -> 0 | L24: =SUM(L22+L20) -> 9705195
B26: Total capital assets (net) | I26: =I22+I20+I11 -> 10215629 | J26: =J22+J20+J11 -> -135533 | K26: =K22+K20+K11 -> 0 | L26: =L22+L20+L11 -> 10080096 | M26: =SUM(M9:M22) -> 374901

Sheet DeSoto
D1: DeSoto PARISH POLICE JURY
D2: Capital Assets
D3: For the Year Ended December 31, 2015
I5: Beginning Balance | J5: Additions | K5: Deletions | L5: Ending Balance | M5: Cross Sectional
A7: Primary Government
A8: Government Activities:
A9: Capital assets, not being depreciated:
B10: Land | I10: 1979943 | L10: =SUM(I10:K10) -> 1979943 | M10: =SUM(L10) -> 1979943
B11: Construction in progress | I11: 1040897 | J11: 3193524 | K11: -581402 | L11: =SUM(I11:K11) -> 3653019 | M11: =SUM(L11) -> 3653019
C12: Total assets not being depreciated | I12: =SUM(I10:I11) -> 3020840 | J12: =SUM(J10:J11) -> 3193524 | K12: =SUM(K10:K11) -> -581402 | L12: =SUM(L10:L11) -> 5632962
A14: Capital assets being depreciated:
B15: Buildings and improvements | I15: 26374042 | J15: 487809 | L15: =SUM(I15:K15) -> 26861851
B16: Land improvements - structures | I16: 6273341 | J16: 643786 | L16: =SUM(I16:K16) -> 6917127
B17: Furniture and equipment | I17: 13524501 | J17: 1301926 | K17: -627908 | L17: =SUM(I17:K17) -> 14198519
B18: Infrastructure | I18: 219055673 | J18: 1445830 | K18: -8276 | L18: =SUM(I18:K18) -> 220493227
C19: Total capital assets being depreciated | I19: =SUM(I15:I18) -> 265227557 | J19: =SUM(J15:J18) -> 3879351 | K19: =SUM(K15:K18) -> -636184 | L19: =SUM(L15:L18) -> 268470724
A21: Less accumulated depreciation for:
B22: Buildings and improvements | I22: 12433851 | J22: 668535 | L22: =SUM(I22:K22) -> 13102386 | M22: =SUM(L15-L22) -> 13759465
B23: Land improvements - structures | I23: 632589 | J23: 325983 | L23: =SUM(I23:K23) -> 958572 | M23: =SUM(L16-L23) -> 5958555
B24: Furniture and equipment | I24: 8155928 | J24: 1093304 | K24: -603778 | L24: =SUM(I24:K24) -> 8645454 | M24: =SUM(L17-L24) -> 5553065
B25: Infrastructure | I25: 173244304 | J25: 1887198 | L25: =SUM(I25:K25) -> 175131502 | M25: =SUM(L18-L25) -> 45361725
C26: Total accumulated depreciation | I26: =SUM(I22:I25) -> 194466672 | J26: =SUM(J22:J25) -> 3975020 | K26: =SUM(K22:K25) -> -603778 | L26: =SUM(L22:L25) -> 197837914
B28: Total capital assets being depreciated, net | I28: =I19-I26 -> 70760885 | J28: =J19-J26 -> -95669 | K28: =K19-K26 -> -32406 | L28: =L19-L26 -> 70632810
B30: Governmental activities capital assets, net | I30: =I12+I28 -> 73781725 | J30: =J12+J28 -> 3097855 | K30: =K12+K28 -> -613808 | L30: =L12+L28 -> 76265772 | M30: =SUM(M9:M29) -> 76265772
I32: Beginning Balance | J32: Increases | K32: Decreases | L32: Ending Balance
A33: Business-Type Activities:
B34: Capital assets, not being depreciated:
C35: Land | I35: 10175 | L35: =SUM(I35:K35) -> 10175 | M35: =SUM(L35) -> 10175
B37: Capital assets, depreciable:
C38: Sewer system | I38: 373375 | L38: =SUM(I38:K38) -> 373375
C39: Treatment plant | I39: 101180 | L39: =SUM(I39:K39) -> 101180
D41: Total capital assets, depreciable | I41: =SUM(I37:I39) -> 474555 | J41: =SUM(J37:J39) -> 0 | K41: =SUM(K37:K39) -> 0 | L41: =SUM(L37:L39) -> 474555
B43: Less accumulated depreciation for:
C44: Sewer system | I44: 373375 | L44: =SUM(I44:K44) -> 373375 | M44: =L38-L44 -> 0
C45: Treatment plant | I45: 101180 | L45: =SUM(I45:K45) -> 101180 | M45: =L39-L45 -> 0
D47: Total accumulated depreciation | I47: =SUM(I44:I45) -> 474555 | J47: =SUM(J44:J45) -> 0 | K47: =SUM(K44:K45) -> 0 | L47: =SUM(L44:L45) -> 474555
D49: Total capital assets - net | I49: =I35+I41-I47 -> 10175 | J49: =J35+J41-J47 -> 0 | K49: =K35+K41-K47 -> 0 | L49: =SUM(I49:K49) -> 10175 | M49: =SUM(J49:L49) -> 10175

Sheet East Baton Rouge
D1: East Baton Rouge PARISH POLICE JURY
D2: Capital Assets
D3: For the Year Ended December 31, 2015
I5: Balance 1/1/2015 | J5: Increases | K5: Decreases | L5: Adjustments | M5: Balance 12/31/2015 | N5: Cross Sectional
A7: Primary Government
A8: Government Activities:
A9: Capital assets, not being depreciated:
B10: Land and right-of-way | I10: 160234370 | J10: 1275882 | L10: 589754 | M10: =SUM(I10:L10) -> 162100006 | N10: =SUM(M10) -> 162100006
B11: Construction work in progress | I11: 48647850 | J11: 15844784 | L11: -27601230 | M11: =SUM(I11:L11) -> 36891404 | N11: =SUM(M11) -> 36891404
C12: Total assets not being depreciated | I12: =SUM(I10:I11) -> 208882220 | J12: =SUM(J10:J11) -> 17120666 | K12: =SUM(K10:K11) -> 0 | L12: =SUM(L10:L11) -> -27011476 | M12: =SUM(M10:M11) -> 198991410
A14: Capital assets being depreciated:
B15: Buildings | I15: 294781300 | J15: 3310495 | K15: -17370 | L15: 3029128 | M15: =SUM(I15:L15) -> 301103553
B16: Improvements (other than buildings)
C17: and infrastructure | I17: 925358411 | J17: 24876550 | L17: 27169558 | M17: =SUM(I17:L17) -> 977404519
B18: Equipment and equipment under lease | I18: 125057714 | J18: 9414357 | K18: -1902165 | M18: =SUM(I18:L18) -> 132569906
C19: Total capital assets being depreciated | I19: =SUM(I15:I18) -> 1345197425 | J19: =SUM(J15:J18) -> 37601402 | K19: =SUM(K15:K18) -> -1919535 | L19: =SUM(L15:L18) -> 30198686 | M19: =SUM(M15:M18) -> 1411077978
A21: Less accumulated depreciation for:
B22: Buildings | I22: -160400815 | J22: -6871899 | K22: 17370 | L22: 0 | M22: =SUM(I22:L22) -> -167255344 | N22: =SUM(M22,M15) -> 133848209
B23: Improvements (other than buildings) | L23: 0
C24: and infrastructure | I24: -414853563 | J24: -29618025 | L24: 0 | M24: =SUM(I24:L24) -> -444471588 | N24: =SUM(M24,M17) -> 532932931
B25: Equipment and equipment under lease | I25: -100176889 | J25: -8774917 | K25: 1885218 | L25: 0 | M25: =SUM(I25:L25) -> -107066588 | N25: =M18+M25 -> 25503318
C26: Total accumulated depreciation | I26: =SUM(I22:I25) -> -675431267 | J26: =SUM(J22:J25) -> -45264841 | K26: =SUM(K22:K25) -> 1902588 | L26: =SUM(L22:L25) -> 0 | M26: =SUM(M22:M25) -> -718793520
B28: Total capital assets being depreciated, net | I28: =I26+I19 -> 669766158 | J28: =J26+J19 -> -7663439 | K28: =K26+K19 -> -16947 | L28: =L26+L19 -> 30198686 | M28: =M26+M19 -> 692284458
B30: Governmental activities capital assets, net | I30: =I12+I28 -> 878648378 | J30: =J12+J28 -> 9457227 | K30: =K12+K28 -> -16947 | L30: =L12+L28 -> 3187210 | M30: =M12+M28 -> 891275868 | N30: =SUM(N10:N25) -> 891275868
I33: Beginning Balance | J33: Transfers | K33: Additions | L33: Deletions | M33: Ending Balance
A35: Business-type Activities:
A36: Capital assets not being depreciated:
B37: Land and right-of-way | I37: 91492232 | J37: 3021918 | L37: 21757 | M37: =SUM(I37:L37) -> 94535907 | N37: =SUM(M37) -> 94535907
B38: Noise mitigation | I38: 58392539 | M38: =SUM(I38:L38) -> 58392539 | N38: =SUM(M38) -> 58392539
B39: Construction work in progress | I39: 119514214 | J39: 102253246 | K39: -806075 | L39: -24261371 | M39: =SUM(I39:L39) -> 196700014 | N39: =SUM(M39) -> 196700014
C40: Total assets not being depreciated | I40: =SUM(I37:I39) -> 269398985 | J40: =SUM(J37:J39) -> 105275164 | K40: =SUM(K37:K39) -> -806075 | L40: =SUM(L37:L39) -> -24239614 | M40: =SUM(M37:M39) -> 349628460
A42: Capital assets being depreciated:
B43: Buildings | I43: 234674097 | J43: 2074825 | L43: 230033 | M43: =SUM(I43:L43) -> 236978955
B44: Improvements (other than buildings)
C45: and infrastructure | I45: 2076900538 | J45: 71376600 | K45: -2032363 | L45: 24711433 | M45: =SUM(I45:L45) -> 2170956208
B46: Equipment | I46: 9889878 | J46: 1035921 | K46: -610775 | M46: =SUM(I46:L46) -> 10315024
C47: Total capital assets being depreciated | I47: =SUM(I43:I46) -> 2321464513 | J47: =SUM(J43:J46) -> 74487346 | K47: =SUM(K43:K46) -> -2643138 | L47: =SUM(L43:L46) -> 24941466 | M47: =SUM(M43:M46) -> 2418250187
A49: Less accumulated depreciation for:
B50: Buildings | I50: -117563006 | J50: -9149192 | L50: 0 | M50: =SUM(I50:L50) -> -126712198 | N50: =SUM(M50,M43) -> 110266757
B51: Improvements (other than buildings) | L51: 0 | M51: =SUM(I51:L51) -> 0 | N51: =SUM(M51,M44) -> 0
C52: and infrastructure | I52: -678994828 | J52: -74367692 | K52: 1631729 | M52: =SUM(I52:L52) -> -751730791 | N52: =SUM(M52,M45) -> 1419225417
B53: Equipment | I53: -9153040 | J53: -312436 | K53: 610775 | M53: =SUM(I53:L53) -> -8854701 | N53: =SUM(M53,M46) -> 1460323
C54: Total accumulated depreciation | I54: =SUM(I50:I53) -> -805710874 | J54: =SUM(J50:J53) -> -83829320 | K54: =SUM(K50:K53) -> 2242504 | L54: =SUM(L50:L53) -> 0 | M54: =SUM(M50:M53) -> -887297690
B56: Total capital assets being depreciated, net | I56: =SUM(I54,I47) -> 1515753639 | J56: =SUM(J54,J47) -> -9341974 | K56: =SUM(K54,K47) -> -400634 | L56: =SUM(L54,L47) -> 24941466 | M56: =SUM(M54,M47) -> 1530952497
B58: Business-type activities capital assets, net | I58: =I40+I56 -> 1785152624 | J58: =J40+J56 -> 95933190 | K58: =K40+K56 -> -1206709 | L58: =L40+L56 -> 701852 | M58: =M40+M56 -> 1880580957 | N58: =SUM(N50:N53,N37:N39) -> 1880580957

Sheet East Carroll
D1: East Carroll PARISH POLICE JURY
D2: Capital Assets
D3: For the Year Ended December 31, 2015
A5: Governmental Activites | I5: Beginning Balance | J5: Additions | K5: Deletions | L5: Ending Balance | M5: Cross Sectional
A6: Nondepreciable capital assets:
B7: Land | I7: 274665 | L7: =SUM(I7:K7) -> 274665 | M7: =SUM(L7) -> 274665
B8: Airport Land | I8: 101000 | L8: =SUM(I8:K8) -> 101000 | M8: =SUM(L8) -> 101000
B9: Construction in progress | I9: 265027 | J9: 55204 | L9: =SUM(I9:K9) -> 320231 | M9: =SUM(L9) -> 320231
C10: Total assets not being depreciated | I10: =SUM(I7:I9) -> 640692 | J10: =SUM(J7:J9) -> 55204 | K10: =SUM(K7:K9) -> 0 | L10: =SUM(L7:L9) -> 695896
A12: Depreciable capital assets
B13: Buildings | I13: 2645963 | L13: =SUM(I13:K13) -> 2645963
B14: Office equipment | I14: 312527 | L14: =SUM(I14:K14) -> 312527
B15: Furniture & fixtures | I15: 67399 | L15: =SUM(I15:K15) -> 67399
B16: Construction equipment | I16: 1932706 | J16: 160074 | L16: =SUM(I16:K16) -> 2092780
B17: Vehicles | I17: 2961374 | J17: 115423 | L17: =SUM(I17:K17) -> 3076797
B18: Books, periodicals & law books | I18: 342548 | L18: =SUM(I18:K18) -> 342548
B19: Infrastructure | L19: =SUM(I19:K19) -> 0
C20: Airport hangars | I20: 25000 | L20: =SUM(I20:K20) -> 25000
C21: Airport runway | I21: 1130666 | L21: =SUM(I21:K21) -> 1130666
C22: Road right-of-way | I22: 558234 | L22: =SUM(I22:K22) -> 558234 | M22: =SUM(J22:L22) -> 558234
C23: Road surface | I23: 9140845 | L23: =SUM(I23:K23) -> 9140845
C24: Bridges | I24: 1759091 | L24: =SUM(I24:K24) -> 1759091
C25: Total capital assets being depreciated | I25: =SUM(I13:I24) -> 20876353 | J25: =SUM(J13:J24) -> 275497 | K25: =SUM(K13:K24) -> 0 | L25: =SUM(L13:L24) -> 21151850
A27: Less accumulated depreciation for:
B28: Buildings | I28: 1637164 | J28: 48794 | L28: =SUM(I28:K28) -> 1685958 | M28: =SUM(L13-L28) -> 960005
B29: Office equipment | I29: 258438 | J29: 21858 | L29: =SUM(I29:K29) -> 280296 | M29: =SUM(L14-L29) -> 32231
B30: Furniture & fixtures | I30: 38879 | J30: 6254 | L30: =SUM(I30:K30) -> 45133 | M30: =SUM(L15-L30) -> 22266
B31: Construction equipment | I31: 873317 | J31: 172361 | L31: =SUM(I31:K31) -> 1045678 | M31: =SUM(L16-L31) -> 1047102
B32: Vehicles | I32: 2086373 | J32: 190015 | L32: =SUM(I32:K32) -> 2276388 | M32: =SUM(L17-L32) -> 800409
B33: Books, periodicals & law books | I33: 342548 | L33: =SUM(I33:K33) -> 342548 | M33: =SUM(L18-L33) -> 0
B34: Infrastructure | L34: =SUM(I34:K34) -> 0 | M34: =SUM(L19-L34) -> 0
C35: Airport hangars | I35: 24688 | J35: 312 | L35: =SUM(I35:K35) -> 25000 | M35: =SUM(L20-L35) -> 0
C36: Airport runway | I36: 233307 | J36: 28266 | L36: =SUM(I36:K36) -> 261573 | M36: =SUM(L21-L36) -> 869093
C37: Road surface | I37: 8468531 | J37: 35595 | L37: =SUM(I37:K37) -> 8504126 | M37: =SUM(L23-L37) -> 636719
C38: Bridges | I38: 1194817 | J38: 27783 | L38: =SUM(I38:K38) -> 1222600 | M38: =SUM(L24-L38) -> 536491
C39: Total accumulated depreciation | I39: =SUM(I28:I38) -> 15158062 | J39: =SUM(J28:J38) -> 531238 | K39: =SUM(K28:K38) -> 0 | L39: =SUM(L28:L38) -> 15689300
B41: Total capital assets being depreciated, net | I41: =SUM(I25-I39) -> 5718291 | J41: =SUM(J25-J39) -> -255741 | K41: =SUM(K25-K39) -> 0 | L41: =SUM(L25-L39) -> 5462550
B43: Governmental activities capital assets, net | I43: =I10+I41 -> 6358983 | J43: =J10+J41 -> -200537 | K43: =K10+K41 -> 0 | L43: =L10+L41 -> 6158446 | M43: =SUM(M7:M38) -> 6158446

Sheet East Feliciana
D1: EAST FELICIANA PARISH POLICE JURY
D2: Capital Assets
D3: For the Year Ended December 31, 2015
I5: Beginning Balance | J5: Additions | K5: Deletions | L5: Ending Balance | M5: Cross Sectional
A7: Governmental Activities:
B8: Capital assets, not being depreciated:
C9: Land | I9: 259230 | L9: =SUM(I9:K9) -> 259230 | M9: =L9 -> 259230
D10: Total capital assets, not being depreciated | I10: =SUM(I9) -> 259230 | J10: =SUM(J9) -> 0 | K10: =SUM(K9) -> 0 | L10: =SUM(L9) -> 259230
A12: Capital assets being depreciated:
B13: Buildings | I13: 9943571 | L13: =SUM(I13:J13) -> 9943571
B14: Less: accumulated depreciation | I14: -4568786 | J14: -207415 | L14: =SUM(I14:J14) -> -4776201
D15: Net Buildings | I15: =SUM(I13:I14) -> 5374785 | J15: =SUM(J13:J14) -> -207415 | K15: =SUM(K13:K14) -> 0 | L15: =SUM(L13:L14) -> 5167370 | M15: =SUM(L13:L14) -> 5167370
B17: Equipment/Vehicles | I17: 4554913 | J17: 26880 | K17: -345795 | L17: =SUM(I17:K17) -> 4235998
B18: Less: accumulated depreciation | I18: -2546365 | J18: -200401 | K18: 345795 | L18: =SUM(I18:K18) -> -2400971
D19: Net Equipment/vehicles | I19: =SUM(I17:I18) -> 2008548 | J19: =SUM(J17:J18) -> -173521 | K19: =SUM(K17:K18) -> 0 | L19: =SUM(L17:L18) -> 1835027 | M19: =SUM(L17:L18) -> 1835027
B21: Streets/Bridges | I21: 5904195 | J21: 2007111 | L21: =SUM(I21:J21) -> 7911306
B22: Less: accumulated depreciation | I22: -685009 | J22: -400064 | L22: =SUM(I22:J22) -> -1085073
D23: Net Furniture and fixtures | I23: =SUM(I21:I22) -> 5219186 | J23: =SUM(J21:J22) -> 1607047 | K23: =SUM(K21:K22) -> 0 | L23: =SUM(I23:J23) -> 6826233 | M23: =SUM(L21:L22) -> 6826233
B24: Capital assets, being depreciated, net | I24: =SUM(I15+I19+I23) -> 12602519 | J24: =SUM(J15+J19+J23) -> 1226111 | K24: =SUM(K15+K19+K23) -> 0 | L24: =SUM(L15+L19+L23) -> 13828630
B25: Capital assets, net | I25: =SUM(I10+I24) -> 12861749 | J25: =SUM(J10+J24) -> 1226111 | K25: =SUM(K10+K24) -> 0 | L25: =SUM(L10+L24) -> 14087860 | M25: =SUM(M9:M23) -> 14087860

Sheet Evangeline
D1: Evangeline PARISH POLICE JURY
D2: Capital Assets
D3: For the Year Ended December 31, 2015
I5: Beginning Balance | J5: Additions | K5: Deletions | L5: Ending Balance | M5: Cross Sectional
A7: Primary Government
A8: Government Activities:
A9: Capital assets, not being depreciated:
B10: Land | I10: 876298 | J10: 5000 | L10: =SUM(I10:K10) -> 881298 | M10: =SUM(L10) -> 881298
B11: Construction in progress | I11: 3632280 | J11: 22622676 | K11: -336299 | L11: =SUM(I11:K11) -> 25918657 | M11: =SUM(L11) -> 25918657
A12: Other capital assets:
B13: Buildings and improvements | I13: 13449894 | L13: =SUM(I13:K13) -> 13449894
B14: Infrastructure | I14: 21491821 | J14: 680445 | L14: =SUM(I14:K14) -> 22172266
B15: Vehicles | I15: 704276 | L15: =SUM(I15:K15) -> 704276
B16: Equipment, furniture and fixtures | I16: 6398790 | J16: 299345 | K16: -65049 | L16: =SUM(I16:K16) -> 6633086
C17: Total capital assets | I17: =SUM(I10:I16) -> 46553359 | J17: =SUM(J10:J16) -> 23607466 | K17: =SUM(K10:K16) -> -401348 | L17: =SUM(L10:L16) -> 69759477
A19: Less accumulated depreciation for:
B20: Buildings | I20: 4808668 | J20: 375776 | L20: =SUM(I20:K20) -> 5184444 | M20: =L13-L20 -> 8265450
B21: Infrastructure | I21: 11081230 | J21: 1065788 | L21: =SUM(I21:K21) -> 12147018 | M21: =L14-L21 -> 10025248
B22: Vehicles | I22: 625080 | J22: 42729 | L22: =SUM(I22:K22) -> 667809 | M22: =L15-L22 -> 36467
B23: Equipment, furniture and fixtures | I23: 4391016 | J23: 398640 | K23: -61254 | L23: =SUM(I23:K23) -> 4728402 | M23: =L16-L23 -> 1904684
C24: Total accumulated depreciation | I24: =SUM(I20:I23) -> 20905994 | J24: =SUM(J20:J23) -> 1882933 | K24: =SUM(K20:K23) -> -61254 | L24: =SUM(L20:L23) -> 22727673
B26: Governmental activities capital assets, net | I26: =I17-I24 -> 25647365 | J26: =J17-J24 -> 21724533 | K26: =K17-K24 -> -340094 | L26: =L17-L24 -> 47031804 | M26: =SUM(M10:M23) -> 47031804
I29: Beginning Balance | J29: Additions | K29: Deletions | L29: Ending Balance | M29: Cross Sectional
A31: Business-type Activities:
A32: Capital assets being depreciated:
B33: Sewer System | I33: 828812 | L33: =SUM(I33:K33) -> 828812
B34: Equipment, furniture and fixtures | I34: 19769 | L34: =SUM(I34:K34) -> 19769
C35: Total capital assets | I35: =SUM(I33:I34) -> 848581 | J35: =SUM(J33:J34) -> 0 | K35: =SUM(K33:K34) -> 0 | L35: =SUM(L33:L34) -> 848581
A37: Less accumulated depreciation for:
B38: Sewer System | L38: =SUM(I38:K38) -> 0 | M38: =L33-L38 -> 828812 | N38: Wrong on audit
B39: Equipment, furniture and fixtures | L39: =SUM(I39:K39) -> 0 | M39: =L34-L39 -> 19769
C40: Total accumulated depreciation | I40: =SUM(I38:I39) -> 0 | J40: =SUM(J38:J39) -> 0 | K40: =SUM(K38:K39) -> 0 | L40: =SUM(I40:K40) -> 0
B43: Business-type activities capital assets, net | I43: =SUM(I35+I40) -> 848581 | J43: =SUM(J35-J40) -> 0 | K43: =SUM(K35-K40) -> 0 | L43: =SUM(L35-L40) -> 848581 | M43: =SUM(M33:M34:M40) -> 848581

Sheet Franklin
D1: Franklin PARISH POLICE JURY
D2: Capital Assets
D3: For the Year Ended December 31, 2015
I5: Balance January 1,2015 | J5: Additions | K5: Deletions | L5: Balance December 31,2015 | M5: Cross Sectional
A7: Primary Government
A8: Government Activities:
A9: Capital assets, not being depreciated:
B10: Land | I10: 390416 | L10: =SUM(I10:K10) -> 390416 | M10: =L10 -> 390416
B11: Construction in progess | I11: 2087938 | J11: 872809 | K11: -1762753 | L11: =SUM(I11:K11) -> 1197994 | M11: =L11 -> 1197994
B12: Assets under Capital Lease | I12: 70000 | L12: =SUM(I12:K12) -> 70000 | M12: =L12 -> 70000
C13: Total capital assets not being depreciated | I13: =SUM(I10:I12) -> 2548354 | J13: =SUM(J10:J12) -> 872809 | K13: =SUM(K10:K12) -> -1762753 | L13: =SUM(L10:L12) -> 1658410
A15: Capital assets being depreciated:
B16: Infrastructure - roads | I16: 87396267 | J16: 399629 | L16: =SUM(I16:K16) -> 87795896
B17: Infrastructure - bridges | I17: 3366140 | L17: =SUM(I17:K17) -> 3366140
B18: Buildings and improvements | I18: 4772535 | J18: 1762753 | L18: =SUM(I18:K18) -> 6535288
B19: Improvements other than buildings | I19: 2593516 | J19: 256799 | L19: =SUM(I19:K19) -> 2850315
B20: Office furniture and equipment | I20: 63648 | L20: =SUM(I20:K20) -> 63648
B21: Heavy equipment | I21: 1773388 | J21: 209900 | K21: -145903 | L21: =SUM(I21:K21) -> 1837385
B22: Other equipment | I22: 495797 | J22: 162692 | K22: -5800 | L22: =SUM(I22:K22) -> 652689
B23: Vehicles | I23: 1223973 | J23: 29022 | K23: -29051 | L23: =SUM(I23:K23) -> 1223944
C24: Total capital assets being depreciated | I24: =SUM(I16:I23) -> 101685264 | J24: =SUM(J16:J23) -> 2820795 | K24: =SUM(K16:K23) -> -180754 | L24: =SUM(L16:L23) -> 104325305
A26: Less accumulated depreciation for:
B27: Infrastructure - roads | I27: -75900253 | J27: -755040 | L27: =SUM(I27:K27) -> -76655293 | M27: =SUM(L16+L27) -> 11140603
B28: Infrastructure - bridges | I28: -1666388 | J28: -43749 | L28: =SUM(I28:K28) -> -1710137 | M28: =SUM(L17+L28) -> 1656003
B29: Buildings and improvements | I29: -3576477 | J29: -149069 | L29: =SUM(I29:K29) -> -3725546 | M29: =SUM(L18+L29) -> 2809742
B30: Improvements other than buildings | I30: -1780273 | J30: -119590 | L30: =SUM(I30:K30) -> -1899863 | M30: =SUM(L19+L30) -> 950452
B31: Office furniture and equipment | I31: -60134 | J31: -1119 | L31: =SUM(I31:K31) -> -61253 | M31: =SUM(L20+L31) -> 2395
B32: Heavy equipment | I32: -986622 | J32: -129446 | K32: 114764 | L32: =SUM(I32:K32) -> -1001304 | M32: =SUM(L21+L32) -> 836081
B33: Other equipment | I33: -387104 | J33: -63299 | K33: 5800 | L33: =SUM(I33:K33) -> -444603 | M33: =SUM(L22+L33) -> 208086
B34: Vehicles | I34: -1146699 | J34: -52286 | K34: 29051 | L34: =SUM(I34:K34) -> -1169934 | M34: =SUM(L23+L34) -> 54010
C35: Total accumulated depreciation | I35: =SUM(I27:I34) -> -85503950 | J35: =SUM(J27:J34) -> -1313598 | K35: =SUM(K27:K34) -> 149615 | L35: =SUM(L27:L34) -> -86667933
B36: Total capital assets being depreciated, net | I36: =SUM(I24+I35) -> 16181314 | J36: =SUM(J24+J35) -> 1507197 | K36: =SUM(K24+K35) -> -31139 | L36: =SUM(L24+L35) -> 17657372
B38: Total capital assets, net | I38: =I13+I36 -> 18729668 | J38: =J13+J36 -> 2380006 | K38: =K13+K36 -> -1793892 | L38: =L13+L36 -> 19315782 | M38: =SUM(M10:M34) -> 19315782

Sheet Grant
D1: Grant PARISH POLICE JURY
D2: Capital Assets
D3: For the Year Ended December 31, 2015
I5: Beginning Balance | J5: Additions | K5: Disposals | L5: Ending Balance | M5: Cross Sectional
A7: Primary Government
A8: Government Activities:
A9: Capital assets, not being depreciated:
B10: Construction in progress | I10: 60410 | J10: 349599 | L10: =SUM(I10:K10) -> 410009 | M10: =SUM(L10) -> 410009
B11: Land | I11: 203250 | L11: =SUM(I11:K11) -> 203250 | M11: =SUM(L11) -> 203250
C12: Total | I12: =SUM(I10:I11) -> 263660 | J12: =SUM(J10:J11) -> 349599 | K12: =SUM(K10:K11) -> 0 | L12: =SUM(L10:L11) -> 613259
A14: Depreciable Capital Assets | L14: =SUM(I14:K14) -> 0 | M14: =SUM(L14) -> 0
B15: Buildings and improvements | I15: 2641293 | L15: =SUM(I15:K15) -> 2641293
B16: Furniture, fixtures and equipment | I16: 2610480 | J16: 316687 | K16: -288103 | L16: =SUM(I16:K16) -> 2639064
B17: Infrastructure | I17: 4452468 | L17: =SUM(I17:K17) -> 4452468
B18: Solid Waste Station | I18: 209647 | L18: =SUM(I18:K18) -> 209647
B19: Accumulated Depreciation | I19: -4336515 | J19: -388373 | K19: 285534 | L19: =SUM(I19:K19) -> -4439354
C20: Total | I20: =SUM(I14:I19) -> 5577373 | J20: =SUM(J14:J19) -> -71686 | K20: =SUM(K14:K19) -> -2569 | L20: =SUM(L14:L19) -> 5503118 | M20: =SUM(L20) -> 5503118
B23: Governmental activities capital assets, net | I23: =SUM(I20+I12) -> 5841033 | J23: =SUM(J20+J12) -> 277913 | K23: =SUM(K20+K12) -> -2569 | L23: =SUM(L12+L20) -> 6116377
I26: Beginning Balance | J26: Additions | K26: Deletions | L26: Ending Balance | M26: Cross Sectional
A28: Business-type Activities:
A29: Non Depreciable Capital Assets
B30: Construction in progress | J30: 20000 | L30: =SUM(I30:K30) -> 20000 | M30: =L30 -> 20000
A32: Depreciable Capital Assets
B33: Distribution System | I33: 1245902 | L33: =SUM(I33:K33) -> 1245902
B34: Buildings | I34: 7253 | L34: =SUM(I34:K34) -> 7253
B35: Equipment | I35: 259207 | L35: =SUM(I35:K35) -> 259207
B36: Accumulated Depreciation | I36: -1163125 | J36: -36640 | L36: =SUM(I36:K36) -> -1199765
C37: Total assets being depreciated | I37: =SUM(I33:I36) -> 349237 | J37: =SUM(J33:J36) -> -36640 | K37: =SUM(K33:K35) -> 0 | L37: =SUM(L33:L35) -> 1512362 | M37: =SUM(L37) -> 1512362
A39: Less accumulated depreciation for:
B40: Distribution System | I40: only shows total accumulated depreciation
B41: Buildings
B42: Equipment
C43: Total accumulated depreciation | I43: =SUM(I40:I42) -> 0 | L43: =SUM(I43:K43) -> 0
C44: Total capital assets being depreciated, net | I44: =SUM(I33:I36) -> 349237 | J44: =SUM(J42+J37) -> -36640 | K44: =SUM(K42+K37) -> 0 | L44: =SUM(L43+L37) -> 1512362
C45: Business-type activities capital assets, net | I45: =SUM(I43+I37) -> 349237 | J45: =SUM(J42+J37) -> -36640 | K45: =SUM(K42+K37) -> 0 | L45: =SUM(L43+L37) -> 1512362 | M45: =SUM(M37+O37) -> 1512362

Sheet Iberia
D1: Iberia PARISH POLICE JURY
D2: Capital Assets
D3: For the Year Ended December 31, 2015
I5: Beginning Balance | J5: Additions | K5: Deletions | L5: Ending Balance | M5: Cross Sectional
A8: Primary Government
A9: Governmental Activities:
A10: Capital assets, not being depreciated:
B11: Land | I11: 2466687 | J11: 35488 | L11: =SUM(I11:K11) -> 2502175 | M11: =SUM(L11) -> 2502175
B12: Construction in progress | I12: 5040099 | J12: 2440961 | K12: -1459802 | L12: =SUM(I12:K12) -> 6021258 | M12: =SUM(L12) -> 6021258
C13: Total assets not being depreciated | I13: =SUM(I11:I12) -> 7506786 | J13: =SUM(J11:J12) -> 2476449 | K13: =SUM(K11:K12) -> -1459802 | L13: =SUM(L11:L12) -> 8523433
A16: Capital assets, being depreciated:
B17: Land Improvements | I17: 10470 | L17: =SUM(I17:K17) -> 10470
B18: Buildings and improvements | I18: 31908823 | J18: 1292378 | L18: =SUM(I18:K18) -> 33201201
B19: Furniture and equipment | I19: 10675628 | J19: 979357 | L19: =SUM(I19:K19) -> 11654985
B20: Infrastructure | I20: 122899489 | J20: 1147991 | L20: =SUM(I20:K20) -> 124047480
C21: Total capital assets being depreciated | I21: =SUM(I13:I20) -> 173001196 | J21: =SUM(J13:J20) -> 5896175 | K21: =SUM(K13:K20) -> -1459802 | L21: =SUM(L13:L20) -> 177437569
A23: Less accumulated depreciation for:
B24: Land Improvements | I24: 7898 | J24: 524 | L24: =SUM(I24:K24) -> 8422 | M24: =SUM(L17-L24) -> 2048
B25: Buildings and improvements | I25: 17932366 | J25: 769878 | L25: =SUM(I25:K25) -> 18702244 | M25: =SUM(L18-L25) -> 14498957
B26: Furniture and equipment | I26: 7174810 | J26: 713225 | L26: =SUM(I26:K26) -> 7888035 | M26: =SUM(L19-L26) -> 3766950
B27: Infrastructure | I27: 53665374 | J27: 3044559 | L27: =SUM(I27:K27) -> 56709933 | M27: =SUM(L20-L27) -> 67337547
C28: Total accumulated depreciation | I28: =SUM(I24:I27) -> 78780448 | J28: =SUM(J24:J27) -> 4528186 | K28: =SUM(K24:K27) -> 0 | L28: =SUM(L24:L27) -> 83308634
B30: Total capital assets being depreciated, net | I30: =SUM(I21-I28) -> 94220748 | J30: =SUM(J21-J28) -> 1367989 | K30: =SUM(K21-K28) -> -1459802 | L30: =SUM(L21-L28) -> 94128935 | M30: =SUM(M11:M27) -> 94128935

Sheet Iberville
D1: IBERVILLE PARISH POLICE JURY
D2: Capital Assets
D3: For the Year Ended December 31, 2015
B5: Primary Government - Governmental Activities:
E6: Land | F6: Construction in Progress | G6: Buildings and Improvement | H6: Infrastructure | I6: Furniture and Equipment | J6: Total
C7: Cost at December 31, 2013 | E7: 3105380 | F7: 22208945 | G7: 40466792 | H7: 84241904 | I7: 28732575 | J7: =SUM(E7:I7) -> 178755596
D8: Additions | E8: 127000 | F8: 1222654 | G8: 558443 | H8: 2550340 | I8: 3701643 | J8: =SUM(E8:I8) -> 8160080
D9: Reclassification | F9: -22208945 | G9: 22208945
D10: Deletions | J10: =SUM(E10:I10) -> 0
C11: Cost at December 31, 2014 | E11: =SUM(E7:E10) -> 3232380 | F11: =SUM(F7:F10) -> 1222654 | G11: =SUM(G7:G10) -> 63234180 | H11: =SUM(H7:H10) -> 86792244 | I11: =SUM(I7:I10) -> 32434218 | J11: =SUM(J7:J10) -> 186915676
B13: Depreciation:
C14: Accumulated Depreciation
C15: at December 31, 2013 | G15: 9471575 | H15: 29050535 | I15: 24955750 | J15: =SUM(E15:I15) -> 63477860
D16: Additions | G16: 1514193 | H16: 2861280 | I16: 1360393 | J16: =SUM(E16:I16) -> 5735866
D17: Deletions | J17: =SUM(E17:I17) -> 0
C18: Accumulated Depreciation | F18: -
C19: at December 31, 2014 | E19: =SUM(E15:E17) -> 0 | F19: =SUM(F15:F17) -> 0 | G19: =SUM(G15:G17) -> 10985768 | H19: =SUM(H15:H17) -> 31911815 | I19: =SUM(I15:I17) -> 26316143 | J19: =SUM(J15:J17) -> 69213726
C22: Capital Assets net of
C23: Accumulated Depreciation
C24: at December 31, 2014 | E24: =SUM(E11- E19) -> 3232380 | F24: =SUM(F11- F19) -> 1222654 | G24: =SUM(G11- G19) -> 52248412 | H24: =SUM(H11- H19) -> 54880429 | I24: =SUM(I11- I19) -> 6118075 | J24: =SUM(J11- J19) -> 117701950
C26: Cross Sectional | E26: =E11 -> 3232380 | F26: =F11 -> 1222654 | G26: =SUM(G24) -> 52248412 | H26: =SUM(H24) -> 54880429 | I26: =SUM(I24) -> 6118075 | J26: =SUM(J24) -> 117701950
B28: Primary Government - Business Type Activities:
E29: Land | F29: Construction in Progress | G29: Buildings and Improvement | H29: Equipment | I29: Total
C30: Cost at December 31, 2013 | E30: 193511 | F30: 687059 | G30: 19198701 | H30: 1314793 | I30: =SUM(E30:H30) -> 21394064
D31: Additions | F31: 286708 | G31: 395439 | H31: 208394 | I31: =SUM(F31:H31) -> 890541
D32: Transfer | F32: -973767 | G32: 973767 | I32: =SUM(F32:H32) -> 0
D33: Deletions | G33: -20267 | H33: -260883 | I33: =SUM(F33:H33) -> -281150
C34: Cost at December 31, 2014 | E34: =SUM(E30:E33) -> 193511 | F34: =SUM(F30:F33) -> 0 | G34: =SUM(G30:G33) -> 20547640 | H34: =SUM(H30:H33) -> 1262304 | I34: =SUM(I30:I33) -> 22003455
B36: Depreciation:
C37: Accumulated Depreciation
C38: at December 31, 2012 | G38: 9490499 | H38: 977796 | I38: =SUM(E38:H38) -> 10468295
D39: Additions | G39: 534019 | H39: 79644 | I39: =SUM(E39:H39) -> 613663
D40: Transfer | I40: =SUM(E40:H40) -> 0
D41: Deletions | H41: -281150 | I41: =SUM(E41:H41) -> -281150
C42: Accumulated Depreciation
C43: at December 31, 2013 | E43: =SUM(E38:E41) -> 0 | F43: =SUM(F38:F41) -> 0 | G43: =SUM(G38:G41) -> 10024518 | H43: =SUM(H38:H41) -> 776290 | I43: =SUM(I38:I41) -> 10800808
C45: Capital Assets net of
C46: Accumulated Depreciation
C47: at December 31, 2013 | E47: =SUM(E34-E43) -> 193511 | F47: =SUM(F34-F43) -> 0 | G47: =SUM(G34-G43) -> 10523122 | H47: =SUM(H34-H43) -> 486014 | I47: =SUM(I34-I43) -> 11202647
C50: Cross Sectional | E50: =SUM(E47) -> 193511 | F50: =SUM(F47) -> 0 | G50: =SUM(G47) -> 10523122 | H50: =SUM(H47) -> 486014 | I50: =SUM(I47) -> 11202647

Sheet Jackson
D1: Jackson PARISH POLICE JURY
D2: Capital Assets
D3: For the Year Ended December 31, 2015
I5: Beginning Balance | J5: Additions | K5: Deletions | L5: Ending balance | M5: Cross Sectional
A7: Primary Government
A8: Government Activities:
A9: Capital assets, not being depreciated:
B10: Land | I10: 433912 | L10: =SUM(I10:K10) -> 433912 | M10: =L10 -> 433912
B11: Construction in progess | I11: 25909 | J11: 318799 | K11: -344708 | L11: =SUM(I11:K11) -> 0 | M11: =L11 -> 0
C12: Total capital assets not being depreciated | I12: =SUM(I10:I11) -> 459821 | J12: =SUM(J10:J11) -> 318799 | K12: =SUM(K10:K11) -> -344708 | L12: =SUM(L10:L11) -> 433912
A14: Capital assets being depreciated:
B15: Buildings and improvements | I15: 9080640 | J15: 344708 | L15: =SUM(I15:K15) -> 9425348
B16: Vehicles | I16: 2610534 | J16: 79544 | L16: =SUM(I16:K16) -> 2690078
B17: Equipment/machinery/furniture | I17: 3867020 | J17: 263886 | K17: -72640 | L17: =SUM(I17:K17) -> 4058266
B18: Infrastructure/Roads | I18: 18597632 | J18: 2453053 | L18: =SUM(I18:K18) -> 21050685
C19: Total capital assets being depreciated | I19: =SUM(I15:I18) -> 34155826 | J19: =SUM(J15:J18) -> 3141191 | K19: =SUM(K15:K18) -> -72640 | L19: =SUM(L15:L18) -> 37224377
A21: Less accumulated depreciation for:
B22: Buildings and improvements | I22: 2734796 | J22: 226345 | L22: =SUM(I22:K22) -> 2961141 | M22: =SUM(L15-L22) -> 6464207
B23: Vehicles | I23: 1766758 | J23: 166330 | L23: =SUM(I23:K23) -> 1933088 | M23: =SUM(L16-L23) -> 756990
B24: Equipment/machinery/furniture | I24: 2138762 | J24: 488370 | K24: -72640 | L24: =SUM(I24:K24) -> 2554492 | M24: =SUM(L17-L24) -> 1503774
B25: Infrastructure/Roads | I25: 11523977 | J25: 1452838 | L25: =SUM(I25:K25) -> 12976815 | M25: =SUM(L18-L25) -> 8073870
C26: Total accumulated depreciation | I26: =SUM(I22:I25) -> 18164293 | J26: =SUM(J22:J25) -> 2333883 | K26: =SUM(K22:K25) -> -72640 | L26: =SUM(L22:L25) -> 20425536
B27: Total capital assets being depreciated, net | I27: =SUM(I19-I26) -> 15991533 | J27: =SUM(J19-J26) -> 807308 | K27: =SUM(K19-K26) -> 0 | L27: =SUM(L19-L26) -> 16798841
B29: Total capital assets, net | I29: =I12+I27 -> 16451354 | J29: =J12+J27 -> 1126107 | K29: =K12+K27 -> -344708 | L29: =L12+L27 -> 17232753 | M29: =SUM(M10:M25) -> 17232753

Sheet Jefferson Davis
D1: Jefferson Davis PARISH POLICE JURY
D2: Capital Assets
D3: For the Year Ended December 31, 2015
I5: Beginning Balance | J5: Additions | K5: Deletions | L5: Transfers | M5: Ending Balance | N5: Cross Sectional
A7: Primary Government
A8: Government Activities:
A9: Capital assets, not being depreciated:
B10: Land | I10: 846907 | M10: =SUM(I10:L10) -> 846907 | N10: =SUM(M10) -> 846907
B11: Construction in progress | I11: 767244 | J11: 1145166 | K11: -738439 | M11: =SUM(I11:L11) -> 1173971 | N11: =SUM(M11) -> 1173971
C12: Total assets not being depreciated | I12: =SUM(I10:I11) -> 1614151 | J12: =SUM(J10:J11) -> 1145166 | K12: =SUM(K10:K11) -> -738439 | L12: =SUM(L10:L11) -> 0 | M12: =SUM(M10:M11) -> 2020878
A14: Capital assets being depreciated:
B15: Buildings and improvements | I15: 12763114 | J15: 521658 | M15: =SUM(I15:L15) -> 13284772
B16: Vehicles | I16: 5977409 | J16: 339319 | K16: -26962 | M16: =SUM(I16:L16) -> 6289766
B17: Maintenance equipment | I17: 2286856 | J17: 34383 | K17: -65630 | M17: =SUM(I17:L17) -> 2255609
B18: Machinery and equipment | I18: 1642142 | J18: 88011 | M18: =SUM(I18:L18) -> 1730153
B19: Office furniture and equipment | I19: 351515 | J19: 6525 | M19: =SUM(I19:L19) -> 358040
B20: Sewer and sewer improvements | I20: 318782 | M20: =SUM(I20:L20) -> 318782
B21: Infrastructure | I21: 24213778 | J21: 827511 | M21: =SUM(I21:L21) -> 25041289
C22: Total capital assets being depreciated | I22: =SUM(I15:I21) -> 47553596 | J22: =SUM(J15:J21) -> 1817407 | K22: =SUM(K15:K21) -> -92592 | L22: =SUM(L15:L21) -> 0 | M22: =SUM(M15:M21) -> 49278411
A24: Less accumulated depreciation for:
B25: Buildings and improvements | I25: 4432702 | J25: 456588 | M25: =SUM(I25:L25) -> 4889290 | N25: =M15-M25 -> 8395482
B26: Vehicles | I26: 3034416 | J26: 404251 | K26: -26962 | M26: =SUM(I26:L26) -> 3411705 | N26: =M16-M26 -> 2878061
B27: Maintenance equipment | I27: 1318038 | J27: 150420 | K27: -65630 | M27: =SUM(I27:L27) -> 1402828 | N27: =M17-M27 -> 852781
B28: Machinery and equipment | I28: 1344664 | J28: 79090 | M28: =SUM(I28:L28) -> 1423754 | N28: =M18-M28 -> 306399
B29: Office furniture and equipment | I29: 293559 | J29: 21501 | M29: =SUM(I29:L29) -> 315060 | N29: =M19-M29 -> 42980
B30: Sewer and sewer improvements | I30: 79598 | J30: 7970 | M30: =SUM(I30:L30) -> 87568 | N30: =M20-M30 -> 231214
B31: Infrastrucuture | I31: 4681236 | J31: 824034 | M31: =SUM(I31:L31) -> 5505270 | N31: =M21-M31 -> 19536019
C32: Total accumulated depreciation | I32: =SUM(I25:I31) -> 15184213 | J32: =SUM(J25:J31) -> 1943854 | K32: =SUM(K25:K31) -> -92592 | L32: =SUM(L25:L31) -> 0 | M32: =SUM(M25:M31) -> 17035475
B34: Total capital assets being depreciated, net | I34: =I22-I32 -> 32369383 | J34: =J22-J32 -> -126447 | K34: =K22-K32 -> 0 | L34: =L22-L32 -> 0 | M34: =M22-M32 -> 32242936
B36: Governmental activities capital assets, net | I36: =I12+I34 -> 33983534 | J36: =J12+J34 -> 1018719 | K36: =K12+K34 -> -738439 | L36: =L12+L34 -> 0 | M36: =M12+M34 -> 34263814 | N36: =SUM(N25:N31, N10:N12) -> 34263814

Sheet Jefferson
D1: Jefferson PARISH POLICE JURY
D2: Capital Assets
D3: For the Year Ended December 31, 2015
I5: Beginning Balance | J5: Increases | K5: Deletions | L5: Completed Construction | M5: Transfers (To) From Other Funds | N5: Ending Balance | O5: Cross Sectional
A6: Primary Government
A7: Governmental Activities:
A8: Capital assets, not being depreciated:
B9: Land and land improvements | I9: 66997 | L9: 254 | N9: =SUM(I9:M9) -> 67251 | O9: =SUM(N9) -> 67251
B10: Construction in progress | I10: 166705 | J10: 153412 | L10: -166601 | M10: -17783 | N10: =SUM(I10:M10) -> 135733 | O10: =SUM(N10) -> 135733
C11: Total assets not being depreciated | I11: =SUM(I9:I10) -> 233702 | J11: =SUM(J9:J10) -> 153412 | K11: =SUM(K9:K10) -> 0 | L11: =SUM(L9:L10) -> -166347 | M11: =SUM(M9:M10) -> -17783 | N11: =SUM(N9:N10) -> 202984
A13: Capital assets being depreciated:
B14: Buildings | I14: 385110 | L14: 65242 | M14: 169 | N14: =SUM(I14:M14) -> 450521
B15: Improvements other than buildings | I15: 191660 | L15: 12561 | M15: -106 | N15: =SUM(I15:M15) -> 204115
B16: Vehicles | I16: 59485 | J16: 3319 | K16: -301 | M16: 241 | N16: =SUM(I16:M16) -> 62744
B17: Machinery & equipment | I17: 257852 | J17: 1613 | K17: -163 | L17: 6158 | M17: 210 | N17: =SUM(I17:M17) -> 265670
B18: Infrastructure | I18: 3090289 | L18: 82386 | M18: -100 | N18: =SUM(I18:M18) -> 3172575
C19: Total capital assets being depreciated | I19: =SUM(I14:I18) -> 3984396 | J19: =SUM(J14:J18) -> 4932 | K19: =SUM(K14:K18) -> -464 | L19: =SUM(L14:L18) -> 166347 | M19: =SUM(M14:M18) -> 414 | N19: =SUM(N14:N18) -> 4155625
A21: Less accumulated depreciation for:
B22: Buildings | I22: 180406 | J22: 10252 | M22: 27 | N22: =SUM(I22:M22) -> 190685 | O22: =SUM(N22,N14) -> 641206
B23: Improvements other than buildings | I23: 84324 | J23: 8002 | M23: -27 | N23: =SUM(I23:M23) -> 92299 | O23: =SUM(N23,N15) -> 296414
B24: Vehicles | I24: 48084 | J24: 4322 | K24: -288 | M24: 213 | N24: =SUM(I24:M24) -> 52331 | O24: =SUM(N24,N16) -> 115075
B25: Machinery & equipment | I25: 207697 | J25: 4108 | K25: -160 | M25: 241 | N25: =SUM(I25:M25) -> 211886 | O25: =N17+N25 -> 477556
B26: Infrastructure | I26: 2471124 | J26: 24455 | M26: -13 | N26: =SUM(I26:M26) -> 2495566 | O26: =N18+N26 -> 5668141
C27: Total accumulated depreciation | I27: =SUM(I22:I26) -> 2991635 | J27: =SUM(J22:J26) -> 51139 | K27: =SUM(K22:K26) -> -448 | L27: =SUM(L22:L26) -> 0 | M27: =SUM(M22:M26) -> 441 | N27: =SUM(N22:N26) -> 3042767
B29: Total capital assets being depreciated, net | I29: =SUM(I19-I27) -> 992761 | J29: =SUM(J19-J27) -> -46207 | K29: =SUM(K19-K27) -> -16 | L29: =SUM(L19-L27) -> 166347 | M29: =SUM(M19-M27) -> -27 | N29: =SUM(N19-N27) -> 1112858
B31: Governmental activities capital assets, net | I31: =I11+I29 -> 1226463 | J31: =J11+J29 -> 107205 | K31: =K11+K29 -> -16 | L31: =L11+L29 -> 0 | M31: =M11+M29 -> -17810 | N31: =N11+N29 -> 1315842 | O31: =SUM(O22:O26,O9:O10) -> 7401376
I34: Beginning Balance | J34: Increases | K34: Decreases | L34: Completed Construction | M34: Transfers (To) From Other Funds | N34: Ending Balance
A36: Business-type Activities:
A37: Capital assets not being depreciated:
B38: Land and Land improvements | I38: 39229 | J38: 50 | N38: =SUM(I38:M38) -> 39279 | O38: =SUM(N38) -> 39279
B39: Construction in progress | I39: 16707 | J39: 17587 | K39: -187 | L39: -22778 | N39: =SUM(I39:M39) -> 11329 | O39: =SUM(N39) -> 11329
C40: Total capital assets being depreciated | I40: =SUM(I38:I39) -> 55936 | J40: =SUM(J38:J39) -> 17637 | K40: =SUM(K38:K39) -> -187 | L40: =SUM(L38:L39) -> -22778 | M40: =SUM(M38:M39) -> 0 | N40: =SUM(N38:N39) -> 50608
A42: Capital assets being depreciated:
B43: Buildings | I43: 236691 | L43: 9696 | N43: =SUM(I43:M43) -> 246387
B44: Collection and distribution systems | I44: 646961 | L44: 1453 | M44: 12082 | N44: =SUM(I44:M44) -> 660496
B45: Plants | I45: 260269 | L45: 434 | M45: 4682 | N45: =SUM(I45:M45) -> 265385
B46: Improvements other than buildings | I46: 16339 | N46: =SUM(I46:M46) -> 16339
B47: Machinery & equipment | I47: 247721 | J47: 1703 | K47: -32441 | L47: 11195 | M47: -217 | N47: =SUM(I47:M47) -> 227961
B48: Vehicles | I48: 13670 | J48: 678 | M48: -241 | N48: =SUM(I48:M48) -> 14107
C49: Total capital assets being depreciated | I49: =SUM(I43:I48) -> 1421651 | J49: =SUM(J43:J48) -> 2381 | K49: =SUM(K43:K48) -> -32441 | L49: =SUM(L43:L48) -> 22778 | M49: =SUM(M43:M48) -> 16306 | N49: =SUM(N43:N48) -> 1430675
A51: Less accumulated depreciation for:
B52: Buildings | I52: 145564 | J52: 6679 | K52: -17 | N52: =SUM(I52:M52) -> 152226 | O52: =SUM(N43-N52) -> 94161
B53: Collection and distribution systems | I53: 286316 | J53: 14880 | K53: 0 | M53: 18 | N53: =SUM(I53:M53) -> 301214 | O53: =SUM(N44-N53) -> 359282
B54: Plant | I54: 121003 | J54: 5570 | N54: =SUM(I54:M54) -> 126573 | O54: =SUM(N45-N54) -> 138812
B55: Improvements other than buildings | I55: 11979 | J55: 1209 | N55: =SUM(I55:M55) -> 13188 | O55: =SUM(N46-N55) -> 3151
B56: Machiney & equipment | I56: 203490 | J56: 14770 | K56: -30944 | M56: -217 | N56: =SUM(I56:M56) -> 187099 | O56: =SUM(N47-N56) -> 40862
B57: Vehicles | I57: 10355 | J57: 1107 | M57: -206 | N57: =SUM(I57:M57) -> 11256 | O57: =SUM(N48-N57) -> 2851
C58: Total accumulated depreciation | I58: =SUM(I52:I57) -> 778707 | J58: =SUM(J52:J57) -> 44215 | K58: =SUM(K52:K57) -> -30961 | L58: =SUM(L52:L57) -> 0 | M58: =SUM(M52:M57) -> -405 | N58: =SUM(N52:N57) -> 791556
C60: Total capital assets bring depreciated, net | I60: =SUM(I49-I58) -> 642944 | J60: =SUM(J49-J58) -> -41834 | K60: =SUM(K49-K58) -> -1480 | L60: =SUM(L49-L58) -> 22778 | M60: =SUM(M49-M58) -> 16711 | N60: =SUM(N49-N58) -> 639119
B61: Business-type activities capital assets, net | I61: =SUM(I60+I40) -> 698880 | J61: =SUM(J60+J40) -> -24197 | K61: =SUM(K60+K40) -> -1667 | L61: =SUM(L60+L40) -> 0 | M61: =SUM(M60+M40) -> 16711 | N61: =SUM(N60+N40) -> 689727 | O61: =SUM(O38:O57) -> 689727

Sheet Lafayette
D1: Lafayette PARISH POLICE JURY
D2: Capital Assets
D3: For the Year Ended December 31, 2015
I5: Balance 11/01/14 | J5: Additions | K5: Deletions | L5: Balance 10/31/15 | M5: Cross Sectional
A8: Governmental activities:
A9: Capital assets not being depreciated:
B10: Land | I10: 40295476 | J10: 2628659 | L10: =SUM(I10:K10) -> 42924135 | M10: =SUM(L10) -> 42924135
B11: Construction in progress | I11: 29613976 | J11: 25745818 | K11: -28496390 | L11: =SUM(I11:K11) -> 26863404 | M11: =SUM(L11) -> 26863404
C12: Total assets not being depreciated | I12: =SUM(I10:I11) -> 69909452 | J12: =SUM(J10:J11) -> 28374477 | K12: =SUM(K10:K11) -> -28496390 | L12: =SUM(L10:L11) -> 69787539
A14: Other capital assets:
B15: Land improvements | I15: 7182009 | J15: 659410 | L15: =SUM(I15:K15) -> 7841419
B16: Buildings and improvements | I16: 187609847 | J16: 5626430 | L16: =SUM(I16:K16) -> 193236277
B17: Vehicles | I17: 54081764 | J17: 4174055 | K17: -3373559 | L17: =SUM(I17:K17) -> 54882260
B18: Movables | I18: 36390044 | J18: 5940558 | K18: -1985137 | L18: =SUM(I18:K18) -> 40345465
B19: Infrastructure | I19: 670999495 | J19: 20117993 | L19: =SUM(I19:K19) -> 691117488
C20: Total capital assets being depreciated | I20: =SUM(I12:I19) -> 1026172611 | J20: =SUM(J12:J19) -> 64892923 | K20: =SUM(K12:K19) -> -33855086 | L20: =SUM(L12:L19) -> 1057210448
A22: Less accumulated depreciation for:
B23: Land improvements | I23: 1059223 | J23: 289218 | L23: =SUM(I23:K23) -> 1348441 | M23: =SUM(L15-L23) -> 6492978
B24: Buildings and improvements | I24: 84764511 | J24: 4110398 | L24: =SUM(I24:K24) -> 88874909 | M24: =SUM(L16-L24) -> 104361368
B25: Vehicles | I25: 34495231 | J25: 3639019 | K25: -3087280 | L25: =SUM(I25:K25) -> 35046970 | M25: =SUM(L17-L25) -> 19835290
B26: Moveables | I26: 23755589 | J26: 2862866 | K26: -1835299 | L26: =SUM(I26:K26) -> 24783156 | M26: =SUM(L18-L26) -> 15562309
B27: Infrastructure | I27: 289970805 | J27: 17685158 | L27: =SUM(I27:K27) -> 307655963 | M27: =SUM(L19-L27) -> 383461525
C28: Total accumulated depreciation | I28: =SUM(I23:I27) -> 434045359 | J28: =SUM(J23:J27) -> 28586659 | K28: =SUM(K23:K27) -> -4922579 | L28: =SUM(L23:L27) -> 457709439
B30: Governmental activities capital assets, net | I30: =SUM(I20-I28) -> 592127252 | J30: =SUM(J20-J28) -> 36306264 | K30: =SUM(K20-K28) -> -28932507 | L30: =SUM(L20-L28) -> 599501009 | M30: =SUM(M10:M27) -> 599501009
I34: Beginning Balance | J34: Increases | K34: Decreases | L34: Ending Balance
A36: Business-type Activities:
A37: Capital assets not being depreciated:
B38: Land | I38: 22263203 | J38: 2015145 | L38: =SUM(I38:K38) -> 24278348 | M38: =SUM(L38) -> 24278348
B39: Construction in progress | I39: 76453802 | J39: 39141531 | K39: -36524788 | L39: =SUM(I39:K39) -> 79070545 | M39: =SUM(L39) -> 79070545
C40: Total capital assets being depreciated | I40: =SUM(I38:I39) -> 98717005 | J40: =SUM(J38:J39) -> 41156676 | K40: =SUM(K38:K39) -> -36524788 | L40: =SUM(L38:L39) -> 103348893
A42: Capital assets being depreciated:
B43: Buildings and improvements | I43: 3159649 | L43: =SUM(I43:K43) -> 3159649
B44: Electric plant | I44: 732214815 | J44: 18338046 | K44: -1873062 | L44: =SUM(I44:K44) -> 748679799
B45: Water plant | I45: 151589663 | J45: 3377412 | K45: -171642 | L45: =SUM(I45:K45) -> 154795433
B46: Sewer plant | I46: 223984918 | J46: 6315134 | K46: -379980 | L46: =SUM(I46:K46) -> 229920072
B47: Fiber optics | I47: 133402614 | J47: 6956850 | K47: -100213 | L47: =SUM(I47:K47) -> 140259251
B48: Equipment | I48: 18640428 | J48: 19278 | K48: -67795 | L48: =SUM(I48:K48) -> 18591911
C49: Total capital assets being depreciated | I49: =SUM(I40:I48) -> 1361709092 | J49: =SUM(J40:J48) -> 76163396 | K49: =SUM(K40:K48) -> -39117480 | L49: =SUM(L40:L48) -> 1398755008
A51: Less accumulated depreciation for:
B52: Buildings and improvements | I52: 2939937 | J52: 8405 | L52: =SUM(I52:K52) -> 2948342 | M52: =SUM(L43-L52) -> 211307
B53: Electric plant | I53: 405262897 | J53: 16345248 | K53: -1346864 | L53: =SUM(I53:K53) -> 420261281 | M53: =SUM(L44-L53) -> 328418518
B54: Water plant | I54: 58032025 | J54: 4052071 | K54: -161322 | L54: =SUM(I54:K54) -> 61922774 | M54: =SUM(L45-L54) -> 92872659
B55: Sewer plant | I55: 69744710 | J55: 4948130 | K55: -375328 | L55: =SUM(I55:K55) -> 74317512 | M55: =SUM(L46-L55) -> 155602560
B56: Fiber optics | I56: 51522178 | J56: 10808046 | K56: -47135 | L56: =SUM(I56:K56) -> 62283089 | M56: =SUM(L47-L56) -> 77976162
B57: Equipment | I57: 4703849 | J57: 613530 | K57: -67198 | L57: =SUM(I57:K57) -> 5250181 | M57: =SUM(L48-L57) -> 13341730
C58: Total accumulated depreciation | I58: =SUM(I52:I57) -> 592205596 | J58: =SUM(J52:J57) -> 36775430 | K58: =SUM(K52:K57) -> -1997847 | L58: =SUM(L52:L57) -> 626983179
C60: Business-type activities capital assets, net | I60: =SUM(I49-I58) -> 769503496 | J60: =SUM(J49-J58) -> 39387966 | K60: =SUM(K49-K58) -> -37119633 | L60: =SUM(L49-L58) -> 771771829 | M60: =SUM(M38:M57) -> 771771829

Sheet Lafourche
D1: Laforche PARISH POLICE JURY
D2: Capital Assets
D3: For the Year Ended December 31, 2014
I5: Beginning Balance | J5: Increases | K5: Deletions & Adjustments | L5: Ending Balance | M5: Cross Sectional
A8: Governmental activities:
A9: Capital assets not being depreciated:
B10: Land | I10: 1315603 | K10: -18327 | L10: =SUM(I10:K10) -> 1297276 | M10: =SUM(L10) -> 1297276
B11: Construction in progress | I11: 23784976 | J11: 20685900 | K11: -5955299 | L11: =SUM(I11:K11) -> 38515577 | M11: =SUM(L11) -> 38515577
C12: Total assets not being depreciated | I12: =SUM(I10:I11) -> 25100579 | J12: =SUM(J10:J11) -> 20685900 | K12: =SUM(K10:K11) -> -5973626 | L12: =SUM(L10:L11) -> 39812853
A14: Other capital assets:
B15: Buildings | I15: 31297591 | J15: 221815 | K15: -1542838 | L15: =SUM(I15:K15) -> 29976568
B16: Infrastructure | I16: 107706220 | J16: 1339825 | K16: 7301 | L16: =SUM(I16:K16) -> 109053346
B17: Drainage & Other Improvements | I17: 2620893 | J17: 250985 | L17: =SUM(I17:K17) -> 2871878
B18: Pumps & Sewage | I18: 37298577 | J18: 3863445 | K18: -11191 | L18: =SUM(I18:K18) -> 41150831
B19: Equipment & Furniture | I19: 7510173 | J19: 476481 | K19: -128406 | L19: =SUM(I19:K19) -> 7858248
B20: Vehicles & Equipment | I20: 9807167 | J20: 1026194 | K20: -103847 | L20: =SUM(I20:K20) -> 10729514
C21: Total capital assets being depreciated | I21: =SUM(I15:I20) -> 196240621 | J21: =SUM(J15:J20) -> 7178745 | K21: =SUM(K15:K20) -> -1778981 | L21: =SUM(L15:L20) -> 201640385
D23: Total Cost of Capital Assets | I23: =SUM(I21+I12) -> 221341200 | J23: =SUM(J21+J12) -> 27864645 | K23: =SUM(K21+K12) -> -7752607 | L23: =SUM(L21+L12) -> 241453238
A25: Less accumulated depreciation for:
B26: Buildings | I26: -6868054 | J26: -743074 | K26: 63120 | L26: =SUM(I26:K26) -> -7548008 | M26: =SUM(L15+L26) -> 22428560
B27: Infrastructure | I27: -89548006 | J27: -4157823 | K27: 3777 | L27: =SUM(I27:K27) -> -93702052 | M27: =SUM(L16+L27) -> 15351294
B28: Drainage & Other Improvements | I28: -1351227 | J28: -196423 | L28: =SUM(I28:K28) -> -1547650 | M28: =SUM(L17+L28) -> 1324228
B29: Pumps & Sewage | I29: -29861782 | J29: -667226 | K29: 3872 | L29: =SUM(I29:K29) -> -30525136 | M29: =SUM(L18+L29) -> 10625695
B30: Equipment & Furniture | I30: -4184846 | J30: -350955 | K30: -244925 | L30: =SUM(I30:K30) -> -4780726 | M30: =SUM(L19+L30) -> 3077522
B31: Vehicles & Equipment | I31: -6474800 | J31: -580091 | K31: -82279 | L31: =SUM(I31:K31) -> -7137170 | M31: =SUM(L20+L31) -> 3592344
C32: Total accumulated depreciation | I32: =SUM(I26:I31) -> -138288715 | J32: =SUM(J26:J31) -> -6695592 | K32: =SUM(K26:K31) -> -256435 | L32: =SUM(L26:L31) -> -145240742
C34: Net Depreciable Capital Assets | I34: =SUM(I21+I32) -> 57951906 | L34: =SUM(L21+L32) -> 56399643
C36: Net Capital Assets | I36: 83052485 | L36: =SUM(L23+L32) -> 96212496 | M36: =SUM(M10:M31) -> 96212496

Sheet Laforche
D1: Laforche PARISH POLICE JURY
D2: Capital Assets
D3: For the Year Ended December 31, 2015
I5: Beginning Balance | J5: Increases | K5: Deletions & Adjustments | L5: Ending Balance | M5: Cross Sectional
A6: Governmental activities:
A7: Capital assets not being depreciated:
B8: Land | I8: 1297276 | J8: 32175 | K8: -3000 | L8: =SUM(I8:K8) -> 1326451 | M8: =SUM(L8) -> 1326451
B9: Construction in progress | I9: 38515577 | J9: 12534733 | K9: -37159762 | L9: =SUM(I9:K9) -> 13890548 | M9: =SUM(L9) -> 13890548
C10: Total assets not being depreciated | I10: =SUM(I8:I9) -> 39812853 | J10: =SUM(J8:J9) -> 12566908 | K10: =SUM(K8:K9) -> -37162762 | L10: =SUM(L8:L9) -> 15216999
A12: Other capital assets:
B13: Buildings | I13: 29976568 | J13: 3042963 | K13: -80366 | L13: =SUM(I13:K13) -> 32939165
B14: Infrastructure | I14: 109053346 | J14: 17841157 | K14: -853834 | L14: =SUM(I14:K14) -> 126040669
B15: Drainage & Other Improvements | I15: 2871878 | J15: 1360579 | L15: =SUM(I15:K15) -> 4232457
B16: Pumps & Sewage | I16: 41150831 | J16: 13906676 | K16: -57434 | L16: =SUM(I16:K16) -> 55000073
B17: Equipment & Furniture | I17: 7858248 | J17: 966254 | K17: -166990 | L17: =SUM(I17:K17) -> 8657512
B18: Vehicles & Equipment | I18: 10729514 | J18: 515891 | K18: 65512 | L18: =SUM(I18:K18) -> 11310917
C19: Total capital assets being depreciated | I19: =SUM(I13:I18) -> 201640385 | J19: =SUM(J13:J18) -> 37633520 | K19: =SUM(K13:K18) -> -1093112 | L19: =SUM(L13:L18) -> 238180793
D21: Total Cost of Capital Assets | I21: =SUM(I19+I10) -> 241453238 | J21: =SUM(J19+J10) -> 50200428 | K21: =SUM(K19+K10) -> -38255874 | L21: =SUM(L19+L10) -> 253397792
A23: Less accumulated depreciation for:
B24: Buildings | I24: -7548008 | J24: -932230 | K24: -92794 | L24: =SUM(I24:K24) -> -8573032 | M24: =SUM(L13+L24) -> 24366133
B25: Infrastructure | I25: -93702052 | J25: -3483699 | K25: 1178000 | L25: =SUM(I25:K25) -> -96007751 | M25: =SUM(L14+L25) -> 30032918
B26: Drainage & Other Improvements | I26: -1547650 | J26: -262443 | L26: =SUM(I26:K26) -> -1810093 | M26: =SUM(L15+L26) -> 2422364
B27: Pumps & Sewage | I27: -30525136 | J27: -1291775 | K27: -7631 | L27: =SUM(I27:K27) -> -31824542 | M27: =SUM(L16+L27) -> 23175531
B28: Equipment & Furniture | I28: -4780726 | J28: -1059332 | K28: 89213 | L28: =SUM(I28:K28) -> -5750845 | M28: =SUM(L17+L28) -> 2906667
B29: Vehicles & Equipment | I29: -7137170 | J29: -656320 | K29: 149490 | L29: =SUM(I29:K29) -> -7644000 | M29: =SUM(L18+L29) -> 3666917
C30: Total accumulated depreciation | I30: =SUM(I24:I29) -> -145240742 | J30: =SUM(J24:J29) -> -7685799 | K30: =SUM(K24:K29) -> 1316278 | L30: =SUM(L24:L29) -> -151610263
C32: Net Depreciable Capital Assets | I32: =SUM(I19+I30) -> 56399643 | L32: =SUM(L19+L30) -> 86570530
C34: Net Capital Assets | I34: =SUM(I21+I30) -> 96212496 | J34: =SUM(J21+J30) -> 42514629 | K34: =SUM(K21+K30) -> -36939596 | L34: =SUM(L21+L30) -> 101787529 | M34: =SUM(M8:M29) -> 101787529 | O34: Number wrong in audit

Sheet LaSalle
D1: LaSalle PARISH POLICE JURY
D2: Capital Assets
D3: For the Year Ended December 31, 2015
I5: Balance January 1,2015 | J5: Additions | K5: Deletions | L5: Balance December 31,2015 | M5: Cross Sectional
A6: Police Jury:
A7: Capital assets not being depreciated:
B8: Land | I8: 477208 | L8: =SUM(I8:K8) -> 477208 | M8: =SUM(L8) -> 477208
B9: Construction in progress | I9: 924257 | J9: 294521 | K9: -1218778 | L9: =SUM(I9:K9) -> 0 | M9: =SUM(L9) -> 0
C10: Total assets not being depreciated | I10: =SUM(I8:I9) -> 1401465 | J10: =SUM(J8:J9) -> 294521 | K10: =SUM(K8:K9) -> -1218778 | L10: =SUM(L8:L9) -> 477208
A12: Other capital assets:
B13: Infrastructure - roads and bridges | I13: 77514813 | J13: 2788261 | K13: -209751 | L13: =SUM(I13:K13) -> 80093323
B14: Buildings and improvements | I14: 2369699 | L14: =SUM(I14:K14) -> 2369699
B15: Office furniture and equipment | I15: 788090 | L15: =SUM(I15:K15) -> 788090
B16: Heavy equipment | I16: 2357074 | L16: =SUM(I16:K16) -> 2357074
B17: Other equipment | I17: 102781 | J17: 72278 | L17: =SUM(I17:K17) -> 175059
B18: Vehicles | I18: 323881 | L18: =SUM(I18:K18) -> 323881
C19: Total capital assets being depreciated | I19: =SUM(I13:I18) -> 83456338 | J19: =SUM(J13:J18) -> 2860539 | K19: =SUM(K13:K18) -> -209751 | L19: =SUM(L13:L18) -> 86107126
B20: Total police jury capital assets | I20: =SUM(I19+I10) -> 84857803 | J20: =SUM(J19+J10) -> 3155060 | K20: =SUM(K19+K10) -> -1428529 | L20: =SUM(L19+L10) -> 86584334
A22: Library:
A23: Capital assets not being depreciated:
B24: Land | I24: 23810 | L24: =SUM(I24:K24) -> 23810 | M24: =SUM(L24) -> 23810
B25: Construction in progress | L25: =SUM(I25:K25) -> 0
C26: Total assets not being depreciated | I26: =SUM(I24:I25) -> 23810 | J26: =SUM(J24:J25) -> 0 | K26: =SUM(K24:K25) -> 0 | L26: =SUM(L24:L25) -> 23810
B27: Capital assets not being depreciated:
C28: Books | I28: 516659 | J28: 40275 | K28: -53742 | L28: =SUM(I28:K28) -> 503192 | M28: =SUM(L28) -> 503192
C29: Vehicles | I29: 44382 | L29: =SUM(I29:K29) -> 44382 | M29: =SUM(L29) -> 44382
C30: Buildings | I30: 813566 | L30: =SUM(I30:K30) -> 813566 | M30: =SUM(L30) -> 813566
C31: Furniture | I31: 135262 | L31: =SUM(I31:K31) -> 135262 | M31: =SUM(L31) -> 135262
C32: Equipment | I32: 65071 | J32: 9204 | K32: -11016 | L32: =SUM(I32:K32) -> 63259 | M32: =SUM(L32) -> 63259
D33: Total library assets being depreciated | I33: =SUM(I28:I32) -> 1574940 | J33: =SUM(J28:J32) -> 49479 | K33: =SUM(K28:K32) -> -64758 | L33: =SUM(L28:L32) -> 1559661
C34: Total library capital assets | I34: =SUM(I33+I26) -> 1598750 | J34: =SUM(J33+J26) -> 49479 | K34: =SUM(K33+K26) -> -64758 | L34: =SUM(L33+L26) -> 1583471
B36: Total capital assets bring depreciated | I36: =SUM(I19+I33) -> 85031278 | J36: =SUM(J19+J33) -> 2910018 | K36: =SUM(K19+K33) -> -274509 | L36: =SUM(I36:K36) -> 87666787
B37: Total capital assets | I37: =SUM(I20+I34) -> 86456553 | J37: =SUM(J20+J34) -> 3204539 | K37: =SUM(K20+K34) -> -1493287 | L37: =SUM(L20+L34) -> 88167805
A39: Less accumulated depreciation for:
B40: Infrastructure - roads and bridges | I40: -74692234 | J40: -211033 | K40: 209751 | L40: =SUM(I40:K40) -> -74693516 | M40: =SUM(L13+L40) -> 5399807
B41: Buildings and improvements | I41: -1555397 | J41: -68025 | L41: =SUM(I41:K41) -> -1623422 | M41: =SUM(L14+L41) -> 746277
B42: Office furniture and equipment | I42: -219479 | J42: -97917 | L42: =SUM(I42:K42) -> -317396 | M42: =SUM(L42+L15) -> 470694
B43: Heavy equipment | I43: -2042408 | J43: -98792 | L43: =SUM(I43:K43) -> -2141200 | M43: =SUM(L43+L16) -> 215874
B44: Other equipment | I44: -297847 | J44: -34797 | K44: 11016 | L44: =SUM(I44:K44) -> -321628 | M44: =SUM(L44+L17) -> -146569
B45: Vehicles | I45: -226477 | J45: -50656 | L45: =SUM(I45:K45) -> -277133 | M45: =SUM(L45+L18) -> 46748
B46: Books | I46: -358371 | J46: -35972 | K46: 53742 | L46: =SUM(I46:K46) -> -340601 | M46: =SUM(J46:L46) -> -322831
C47: Total accumulated depreciation | I47: =SUM(I40:I46) -> -79392213 | J47: =SUM(J40:J46) -> -597192 | K47: =SUM(K40:K46) -> 274509 | L47: =SUM(L40:L46) -> -79714896
B49: Total capital assets being depreciated (net) | I49: =SUM(I47+I36) -> 5639065 | J49: =SUM(J47+J36) -> 2312826 | K49: =SUM(K47+K36) -> 0 | L49: =SUM(L47+L36) -> 7951891
B51: Total capital assets (net) | I51: =SUM(I47+I37) -> 7064340 | J51: =SUM(J47+J37) -> 2607347 | L51: =SUM(L47+L37) -> 8452909 | M51: =SUM(M8:M46) -> 8470679

Sheet Lincoln
D1: LINCOLN PARISH POLICE JURY
D2: Capital Assets
D3: For the Year Ended December 31, 2015
I5: 2014 Balance | J5: Additions | K5: Disposals | L5: 2015 Balance | M5: Cross sectional
A7: Non-Depreciable Assets:
B8: Land | I8: 1679286 | L8: =SUM(I8:K8) -> 1679286 | M8: =L8 -> 1679286
B9: Infrastructure -CIP
B10: Improvements
B11: Total capital assets, not being depreciated | I11: =SUM(I8:I10) -> 1679286 | J11: =SUM(J8:J10) -> 0 | K11: =SUM(K8:K10) -> 0 | L11: =SUM(L8:L10) -> 1679286
A13: Depreciable Assets
B14: Buildings | I14: 10792475 | L14: =SUM(I14:K14) -> 10792475
B15: Infrastructure | I15: 26278488 | J15: 23756 | L15: =SUM(I15:K15) -> 26302244
B16: Improvements | I16: 9586703 | J16: 30576 | K16: -38993 | L16: =SUM(I16:K16) -> 9578286
B17: Vehicles | I17: 1620054 | J17: 252982 | K17: -56209 | L17: =SUM(I17:K17) -> 1816827
B18: Furniture and Fixtures | I18: 1377254 | J18: 2911 | L18: =SUM(I18:K18) -> 1380165
B19: Machinery and Equipment | I19: 4268749 | J19: 747397 | L19: =SUM(I19:K19) -> 5016146
B20: Total capital assets, being depreciated | I20: =SUM(I14:I19) -> 53923723 | J20: =SUM(J14:J19) -> 1057622 | K20: =SUM(K14:K19) -> -95202 | L20: =SUM(L14:L19) -> 54886143
A22: Less: Accumulated Depreciation:
B23: Buildings | I23: -5014588 | J23: -212664 | L23: =SUM(I23:K23) -> -5227252 | M23: =L14+L23 -> 5565223
B24: Infrastructure | I24: -18811474 | J24: -299809 | L24: =SUM(I24:K24) -> -19111283 | M24: =L15+L24 -> 7190961
B25: Improvements | I25: -3917163 | J25: -358930 | L25: =SUM(I25:K25) -> -4276093 | M25: =L16+L25 -> 5302193
B26: Vehicles | I26: -1052002 | J26: -78887 | L26: =SUM(I26:K26) -> -1130889 | M26: =L17+L26 -> 685938
B27: Furniture and Fixtures | I27: -1112413 | J27: -33279 | L27: =SUM(I27:K27) -> -1145692 | M27: =L18+L27 -> 234473
B28: Machinery and equipment | I28: -2734960 | J28: -281215 | L28: =SUM(I28:K28) -> -3016175 | M28: =L19+L28 -> 1999971
B29: Total accumulated depreciation | I29: =SUM(I23:I28) -> -32642600 | J29: =SUM(J23:J28) -> -1264784 | K29: =SUM(K23:K28) -> 0 | L29: =SUM(L23:L28) -> -33907384
D31: Total capital assets being depreciated, net | I31: =SUM(I20+I29) -> 21281123 | J31: =SUM(J20+J29) -> -207162 | K31: =SUM(K20+K29) -> -95202 | L31: =SUM(L20+L29) -> 20978759
D33: Total Capital Assets | I33: =SUM(I11+I31) -> 22960409 | J33: =SUM(J11+J31) -> -207162 | K33: =SUM(K11+K31) -> -95202 | L33: =SUM(L11+L31) -> 22658045 | M33: =SUM(M8:M28) -> 22658045

Sheet Livingston
D1: LIVINGSTON PARISH POLICE JURY
D2: Capital Assets
D3: For the Year Ended December 31, 2015
I5: Balance January 1, 2015 | L5: Balance December 31, 2015 | M5: Cross Sectional
J6: Increases | K6: Decreases
A7: Governmental Activities
A8: Capital Assets Not Being Depreciated
B9: Land | I9: 5844429 | J9: 321545 | K9: -1142 | L9: =SUM(I9:K9) -> 6164832 | M9: =SUM(L9) -> 6164832
B10: Construction in progress | I10: 5706789 | J10: 3444417 | K10: -4824802 | L10: =SUM(I10:K10) -> 4326404 | M10: =SUM(L10) -> 4326404
C11: Total Capital assets not being depreciated | I11: =SUM(I9:I10) -> 11551218 | J11: =SUM(J9:J10) -> 3765962 | K11: =SUM(K9:K10) -> -4825944 | L11: =SUM(L9:L10) -> 10491236
A12: Capital Assets Being Depreciated
B13: Buildings | I13: 74469439 | J13: 57433 | L13: =SUM(I13:K13) -> 74526872
B14: Recreational Facilities | I14: 3758232 | L14: =SUM(I14:K14) -> 3758232
B15: Machinery and Equipment | I15: 6993772 | J15: 368579 | K15: -16749 | L15: =SUM(I15:K15) -> 7345602
B16: Sewer System | I16: 2126234 | L16: =SUM(I16:K16) -> 2126234
B17: Infrastructure | I17: 146362543 | J17: 4445825 | K17: -711380 | L17: =SUM(I17:K17) -> 150096988
B18: Furniture and Fixtures | I18: 250660 | J18: 200460 | L18: =SUM(I18:K18) -> 451120
C19: Total Capital Assets Being Depreciated | I19: =SUM(I13:I18) -> 233960880 | J19: =SUM(J13:J18) -> 5072297 | K19: =SUM(K13:K18) -> -728129 | L19: =SUM(L13:L18) -> 238305048
A20: Less accumulated depreciation for:
B21: Buildings | I21: -10857829 | J21: -1851987 | L21: =SUM(I21:K21) -> -12709816 | M21: =SUM(L21,L13) -> 61817056
B22: Recreational Facilities | I22: -352335 | J22: -93956 | L22: =SUM(I22:K22) -> -446291 | M22: =SUM(L22,L14) -> 3311941
B23: Machinery and Equipment | I23: -5153332 | J23: -526664 | K23: 16749 | L23: =SUM(I23:K23) -> -5663247 | M23: =SUM(L23,L15) -> 1682355
B24: Sewer System | I24: -383434 | J24: -141749 | L24: =SUM(I24:K24) -> -525183 | M24: =SUM(L24,L16) -> 1601051
B25: Infrastructure | I25: -85196242 | J25: -9213102 | K25: 711380 | L25: =SUM(I25:K25) -> -93697964 | M25: =SUM(L25,L17) -> 56399024
B26: Furniture and Fixtures | I26: -232454 | J26: -31757 | L26: =SUM(I26:K26) -> -264211 | M26: =SUM(L26,L18) -> 186909
C27: Total accumulated depreciation | I27: =SUM(I21:I26) -> -102175626 | J27: =SUM(J21:J26) -> -11859215 | K27: =SUM(K21:K26) -> 728129 | L27: =SUM(L21:L26) -> -113306712
C28: Total Capital Assets Being Depreciated, Net | I28: =SUM(I27+I19) -> 131785254 | J28: =SUM(J27+J19) -> -6786918 | K28: =SUM(K27+K19) -> 0 | L28: =SUM(L27+L19) -> 124998336
C29: Capital Assets, net | I29: =I11+I28 -> 143336472 | J29: =J11+J28 -> -3020956 | K29: =K11+K28 -> -4825944 | L29: =L11+L28 -> 135489572 | M29: =SUM(M21:M26,M9:M10) -> 135489572
A32: Business-Type activities
A33: Capital Assets Not Being Depreciated
B34: Land | I34: 13243 | L34: =SUM(I34:K34) -> 13243 | M34: =SUM(L34) -> 13243
B35: Construction in progress | I35: 51119 | J35: 54831 | K35: -105950 | L35: =SUM(I35:K35) -> 0 | M35: =SUM(L35) -> 0
C36: Total Capital assets not being depreciated | I36: =SUM(I34:I35) -> 64362 | J36: =SUM(J34:J35) -> 54831 | K36: =SUM(K34:K35) -> -105950 | L36: =SUM(L34:L35) -> 13243
A37: Capital Assets Being Depreciated
B38: Utility system | I38: 9945658 | J38: 171420 | K38: -684248 | L38: =SUM(I38:K38) -> 9432830
C39: Total Capital Assets being Depreciated | I39: =SUM(I38:I38) -> 9945658 | J39: =SUM(J38:J38) -> 171420 | K39: =SUM(K38:K38) -> -684248 | L39: =SUM(L38:L38) -> 9432830
A40: Less accumulated depreciation for:
B41: Utility System | I41: -2134018 | J41: -297410 | K41: 36351 | L41: =SUM(I41:K41) -> -2395077 | M41: =SUM(L41,L38) -> 7037753
C42: Total accumulated depreciation | I42: =SUM(I41:I41) -> -2134018 | J42: =SUM(J41:J41) -> -297410 | K42: =SUM(K41:K41) -> 36351 | L42: =SUM(L41:L41) -> -2395077
C43: Total depreciable capital assets, net | I43: =SUM(I39+I42) -> 7811640 | J43: =SUM(J39+J42) -> -125990 | K43: =SUM(K39+K42) -> -647897 | L43: =SUM(L39+L42) -> 7037753
C44: Capital Assets, net | I44: =I36+I43 -> 7876002 | J44: =J36+J43 -> -71159 | K44: =K36+K43 -> -753847 | L44: =L36+L43 -> 7050996 | M44: =SUM(M41,M34:M35) -> 7050996

Sheet Madison
D1: MADISON PARISH POLICE JURY
D2: Capital Assets
D3: For the Year Ended December 31, 2015
I5: Balance Beginning | L5: Balance Ending | M5: Cross Sectional
J6: Additions | K6: Deletions
A7: Governmental Activities
A8: Not subject to depreciation
B9: Land | I9: 188750 | L9: =SUM(I9:K9) -> 188750 | M9: =SUM(L9) -> 188750
B10: Quebec road | I10: 3771405 | L10: =SUM(I10:K10) -> 3771405 | M10: =L10 -> 3771405
A11: Subject to depreciation:
B12: Health unit | I12: 1688635 | L12: =SUM(I12:K12) -> 1688635 | M12: =L12 -> 1688635
B13: Buildings and improvements | I13: 6005279 | L13: =SUM(I13:K13) -> 6005279
B14: Furniture and equipment | I14: 3478202 | J14: 51325 | K14: -43966 | L14: =SUM(I14:K14) -> 3485561
B15: Books and periodicals | I15: 517099 | J15: 45380 | K15: -31968 | L15: =SUM(I15:K15) -> 530511
C16: Total | I16: =SUM(I9:I15) -> 15649370 | J16: =SUM(J9:J15) -> 96705 | K16: =SUM(K9:K15) -> -75934 | L16: =SUM(L9:L15) -> 15670141
A17: Less accumulated depreciation
B18: Buildings and improvements | I18: 4559899 | J18: 145787 | L18: =SUM(I18:K18) -> 4705686 | M18: =L13-L18 -> 1299593
B19: Furniture and equipment | I19: 2588760 | J19: 233115 | K19: -43966 | L19: =SUM(I19:K19) -> 2777909 | M19: =L14-L19 -> 707652
B20: Books and periodicals | I20: 413573 | J20: 53051 | K20: -31968 | L20: =SUM(I20:K20) -> 434656 | M20: =L15-L20 -> 95855
C21: Total | I21: =SUM(I18:I20) -> 7562232 | J21: =SUM(J18:J20) -> 431953 | K21: =SUM(K18:K20) -> -75934 | L21: =SUM(L18:L20) -> 7918251
B22: Governmental activities capital assets, net | I22: =I16-I21 -> 8087138 | J22: =J16-J21 -> -335248 | K22: =K16-K21 -> 0 | L22: =L16-L21 -> 7751890 | M22: =SUM(M9:M20) -> 7751890

Sheet Morehouse
D1: MOREHOUSE PARISH POLICE JURY
D2: Capital Assets
D3: For the Year Ended December 31, 2015
I5: Balance January 1, 2015 | J5: Additions | K5: Deletions | L5: Balance December, 31, 2015 | M5: Cross sectional
A7: Governmental activities
A8: Not subject to depreciation:
B9: Land | I9: 188750 | L9: =SUM(I9:K9) -> 188750 | M9: =L9 -> 188750
B10: Quebec Road | I10: 3771405 | L10: =SUM(I10:K10) -> 3771405 | M10: =L10 -> 3771405
B11: Total | I11: =SUM(I9:I10) -> 3960155 | J11: =SUM(J9:J10) -> 0 | K11: =SUM(K9:K10) -> 0 | L11: =SUM(L9:L10) -> 3960155
A12: Subject to depreciation:
B13: Health Unit | I13: 1688635 | L13: =SUM(I13:K13) -> 1688635 | M13: =L13 -> 1688635
B14: Buildings and improvements | I14: 6005279 | L14: =SUM(I14:K14) -> 6005279
B15: Furniture and equipment | I15: 3478202 | J15: 51325 | K15: -43966 | L15: =SUM(I15:K15) -> 3485561
B16: Books and periodicals | I16: 517099 | J16: 45380 | K16: -31968 | L16: =SUM(I16:K16) -> 530511
B17: Total | I17: =SUM(I13:I16) -> 11689215 | J17: =SUM(J13:J16) -> 96705 | K17: =SUM(K13:K16) -> -75934 | L17: =SUM(L13:L16) -> 11709986 | N17: only the totals don’t match source
A18: Less accumulated depreciation for:
B19: Buildings and improvements | I19: 4559899 | J19: 145787 | L19: =SUM(I19:K19) -> 4705686 | M19: =L14-L19 -> 1299593
B20: Furniture and equipment | I20: 2588760 | J20: 233115 | K20: -43966 | L20: =SUM(I20:K20) -> 2777909 | M20: =L15-L20 -> 707652
B21: Books and periodicals | I21: 413573 | J21: 53051 | K21: -31968 | L21: =SUM(I21:K21) -> 434656 | M21: =L16-L21 -> 95855
B22: Total accumulated depreciation | I22: =SUM(I19:I21) -> 7562232 | J22: =SUM(J19:J21) -> 431953 | K22: =SUM(K19:K21) -> -75934 | L22: =SUM(L19:L21) -> 7918251
D24: Governmental activities capital assets, net | I24: =SUM(I17-I22+I11) -> 8087138 | J24: =SUM(J17-J22+J11) -> -335248 | K24: =SUM(K17-K22+K11) -> 0 | L24: =SUM(L17-L22+L11) -> 7751890 | M24: =SUM(M9:M21) -> 7751890

Sheet Natchitoches
D1: NATCHITOCHES PARISH POLICE JURY
D2: Capital Assets
D3: For the Year Ended December 31, 2015
I5: Beginning Balance | M5: Ending Balance | N5: Cross Sectional
J6: Increases | K6: Decreases | L6: Transfers
A7: Governmental Activities
A8: General Fund:
A9: Capital assets; not depreciated
B10: Land | I10: 443958 | M10: =SUM(I10:K10) -> 443958 | N10: =M10 -> 443958
B11: CIP | I11: 45608 | K11: -45608 | M11: =SUM(I11:K11) -> 0 | N11: =M11 -> 0
A12: Capital assets; depreciated
B13: Building | I13: 5180471 | J13: 655759 | L13: -107000 | M13: =SUM(I13:L13) -> 5729230
B14: Office Equipment | I14: 214873 | J14: 2524 | M14: =SUM(I14:K14) -> 217397
B15: Other Equipment | I15: 58155 | M15: =SUM(I15:K15) -> 58155
B16: Vehicles | I16: 230923 | L16: -25571 | M16: =SUM(I16:L16) -> 205352
C17: Total assets | I17: =SUM(I10:I16) -> 6173988 | J17: =SUM(J10:J16) -> 658283 | K17: =SUM(K10:K16) -> -45608 | L17: =SUM(L10:L16) -> -132571 | M17: =SUM(M10:M16) -> 6654092
A19: Accumulated depreciation:
B20: Building | I20: 3434850 | J20: 74523 | M20: =SUM(I20:K20) -> 3509373 | N20: =M13-M20 -> 2219857
B21: Office Equipment | I21: 212725 | J21: 1621 | M21: =SUM(I21:K21) -> 214346 | N21: =M14-M21 -> 3051
B22: Other Equipment | I22: 49194 | J22: 1994 | M22: =SUM(I22:K22) -> 51188 | N22: =M15-M22 -> 6967
B23: Vehicles | I23: 230923 | L23: -25571 | M23: =SUM(I23:L23) -> 205352 | N23: =M16-M23 -> 0
C24: Total accumulated depreciation | I24: =SUM(I20:I23) -> 3927692 | J24: =SUM(J20:J23) -> 78138 | K24: =SUM(K20:K23) -> 0 | L24: =SUM(L20:L23) -> -25571 | M24: =SUM(M20:M23) -> 3980259
A26: Civil Defense
A27: Capital assets; depreciated-
B28: Office Equipment | I28: 38504 | M28: =SUM(I28:K28) -> 38504
B29: Other Equipment | I29: 18265 | K29: -18265 | M29: =SUM(I29:K29) -> 0
C30: Total assets | I30: =SUM(I27:I29) -> 56769 | J30: =SUM(J27:J29) -> 0 | K30: =SUM(K27:K29) -> -18265 | L30: =SUM(L27:L29) -> 0 | M30: =SUM(M27:M29) -> 38504
A32: Accumulated depreciation:
B33: Office Equipment | I33: 38504 | M33: =SUM(I33:K33) -> 38504 | N33: =SUM(M28-M33) -> 0
B34: Other Equipment | I34: 18265 | K34: -18265 | M34: =SUM(I34:K34) -> 0 | N34: =SUM(M29-M34) -> 0
C35: Total accumulated depreciation | I35: =SUM(I33:I34) -> 56769 | J35: =SUM(J33:J34) -> 0 | K35: =SUM(K33:K34) -> -18265 | L35: =SUM(L33:L34) -> 0 | M35: =SUM(M33:M34) -> 38504
A37: Criminal Court/DA
A38: Capital Assets; depreciated
B39: Office Equipment | I39: 38580 | M39: =SUM(I39:K39) -> 38580
B40: Other Equipment | I40: 36564 | M40: =SUM(I40:K40) -> 36564
B41: Vehicles | J41: 45272 | M41: =SUM(I41:L41) -> 45272
C42: Total assets | I42: =SUM(I39:I41) -> 75144 | J42: =SUM(J39:J41) -> 45272 | K42: =SUM(K39:K41) -> 0 | L42: =SUM(L39:L41) -> 0 | M42: =SUM(M39:M41) -> 120416
A44: Accumulated depreciation:
B45: Office Equipment | I45: 38580 | M45: =SUM(I45:K45) -> 38580 | N45: =SUM(M39-M45) -> 0
B46: Other Equipment | I46: 36564 | M46: =SUM(I46:K46) -> 36564 | N46: =SUM(M40-M46) -> 0
B47: Vehicles | J47: 4814 | M47: =SUM(I47:K47) -> 4814 | N47: =SUM(M41-M47) -> 40458
C48: Total accumulated depreciation | I48: =SUM(I45:I47) -> 75144 | J48: =SUM(J45:J47) -> 4814 | K48: =SUM(K45:K47) -> 0 | L48: =SUM(L45:L47) -> 0 | M48: =SUM(M45:M47) -> 79958
A50: Health Unit
A51: Capital Assets; depreciated
B52: Building | I52: 846415 | J52: 2195 | M52: =SUM(I52:K52) -> 848610
B53: Office Equipment | I53: 56354 | M53: =SUM(I53:K53) -> 56354
B54: Other Equipment | I54: 66853 | J54: 26503 | K54: -21245 | M54: =SUM(I54:K54) -> 72111
B55: Vehicles | I55: 214790 | J55: 22045 | K55: -20596 | M55: =SUM(I55:K55) -> 216239
C56: Total assets | I56: =SUM(I51:I55) -> 1184412 | J56: =SUM(J51:J55) -> 50743 | K56: =SUM(K51:K55) -> -41841 | L56: =SUM(L51:L55) -> 0 | M56: =SUM(M51:M55) -> 1193314
A58: Accumulated depreciation:
B59: Building | I59: 570220 | J59: 21307 | M59: =SUM(I59:L59) -> 591527 | N59: =SUM(M52-M59) -> 257083
B60: Office Equipment | I60: 54056 | J60: 2298 | M60: =SUM(I60:L60) -> 56354 | N60: =SUM(M53-M60) -> 0
B61: Other Equipment | I61: 62339 | J61: 2332 | K61: -18745 | M61: =SUM(I61:L61) -> 45926 | N61: =SUM(M54-M61) -> 26185
B62: Vehicles | I62: 154949 | J62: 17346 | K62: -8826 | M62: =SUM(I62:L62) -> 163469 | N62: =SUM(M55-M62) -> 52770
C63: Total accumulated depreciation | I63: =SUM(I59:I62) -> 841564 | J63: =SUM(J59:J62) -> 43283 | K63: =SUM(K59:K62) -> -27571 | L63: =SUM(L59:L62) -> 0 | M63: =SUM(M59:M62) -> 857276
A65: Government Building:
A66: Capital Assets; depreciated
B67: Building | J67: 3800 | L67: 107000 | M67: =SUM(I67:L67) -> 110800
B68: Other Equipment | I68: 40482 | J68: 12091 | M68: =SUM(I68:L68) -> 52573
B69: Vehicles | M69: =SUM(I69:L69) -> 0
C70: Total assets | I70: =SUM(I67:I69) -> 40482 | J70: =SUM(J67:J69) -> 15891 | K70: =SUM(K67:K69) -> 0 | L70: =SUM(L67:L69) -> 107000 | M70: =SUM(M67:M69) -> 163373
A72: Accumulated depreciation:
B73: Building | J73: 4438 | M73: =SUM(I73:L73) -> 4438 | N73: =SUM(M67-M73) -> 106362
B74: Other Equipment | I74: 22205 | J74: 4700 | M74: =SUM(I74:L74) -> 26905 | N74: =SUM(M68-M74) -> 25668
B75: Vehicles | M75: =SUM(I75:L75) -> 0 | N75: =SUM(M69-M75) -> 0
C76: Total accumulated depreciation | I76: =SUM(I75) -> 0 | J76: =SUM(J75) -> 0 | K76: =SUM(K75) -> 0 | L76: =SUM(L75) -> 0 | M76: =SUM(M75) -> 0
A78: Head Start
A79: Capital Assets; depreciated
B80: Building | I80: 135848 | J80: 21200 | M80: =SUM(I80:K80) -> 157048
B81: Office Equipment | I81: 155209 | J81: 8051 | K81: -1499 | M81: =SUM(I81:K81) -> 161761
B82: Other Equipment | I82: 362980 | J82: 14295 | K82: -20606 | M82: =SUM(I82:K82) -> 356669
B83: Vehicles | I83: 168351 | M83: =SUM(I83:K83) -> 168351
C84: Total assets | I84: =SUM(I80:I83) -> 822388 | J84: =SUM(J80:J83) -> 43546 | K84: =SUM(K80:K83) -> -22105 | L84: =SUM(L80:L83) -> 0 | M84: =SUM(M80:M83) -> 843829
A86: Accumulated depreciation:
B87: Building | I87: 123089 | J87: 6707 | M87: =SUM(I87:L87) -> 129796 | N87: =SUM(M80-M87) -> 27252
B88: Office Equipment | I88: 153359 | J88: 2031 | K88: -1499 | M88: =SUM(I88:L88) -> 153891 | N88: =SUM(M81-M88) -> 7870
B89: Other Equipment | I89: 269414 | J89: 26817 | K89: -19696 | M89: =SUM(I89:L89) -> 276535 | N89: =SUM(M82-M89) -> 80134
B90: Vehicles | I90: 168351 | M90: =SUM(I90:L90) -> 168351 | N90: =SUM(M83-M90) -> 0
C91: Total accumulated depreciation | I91: =SUM(I87:I90) -> 714213 | J91: =SUM(J87:J90) -> 35555 | K91: =SUM(K87:K90) -> -21195 | L91: =SUM(L87:L90) -> 0 | M91: =SUM(M87:M90) -> 728573
A93: LIHEAP
A94: Capital Assets; depreciated
B95: Office Equipment | I95: 2756 | M95: =SUM(I95:L95) -> 2756
C96: Total assets | I96: =SUM(I95) -> 2756 | J96: =SUM(J95) -> 0 | K96: =SUM(K95) -> 0 | L96: =SUM(L95) -> 0 | M96: =SUM(M95) -> 2756
A98: Accumulated depreciation:
B99: Office Equipment | I99: 2756 | M99: =SUM(I99:L99) -> 2756 | N99: =SUM(M95-M99) -> 0
C100: Total accumulated depreciation | I100: =SUM(I99) -> 2756 | J100: =SUM(J99) -> 0 | K100: =SUM(K99) -> 0 | L100: =SUM(L99) -> 0 | M100: =SUM(M99) -> 2756
A102: Rural Transit:
A103: Capital Assets; depreciated
B104: Vehicles | I104: 15425 | K104: -15425 | M104: =SUM(I104:L104) -> 0
C105: Total assets | I105: =SUM(I104) -> 15425 | J105: =SUM(J104) -> 0 | K105: =SUM(K104) -> -15425 | L105: =SUM(L104) -> 0 | M105: =SUM(M104) -> 0
A107: Accumulated depreciation:
B108: Vehicles | I108: 15425 | K108: -15425 | M108: =SUM(I108:K108) -> 0 | N108: =SUM(M104-M108) -> 0
C109: Total accumulated depreciation | I109: =SUM(I108) -> 15425 | J109: =SUM(J108) -> 0 | K109: =SUM(K108) -> -15425 | M109: =SUM(M108) -> 0
A111: Library:
A112: Capital Assets; depreciated
B113: Office Equipment | I113: 311700 | J113: 4991 | K113: -2737 | M113: =SUM(I113:K113) -> 313954
B114: Vehicles | I114: 275501 | M114: =SUM(I114:K114) -> 275501
B115: Books, Recordings, etc. | I115: 1938020 | J115: 124363 | K115: -159043 | M115: =SUM(I115:K115) -> 1903340
C116: Total assets | I116: =SUM(I113:I115) -> 2525221 | J116: =SUM(J113:J115) -> 129354 | K116: =SUM(K113:K115) -> -161780 | L116: =SUM(L113:L115) -> 0 | M116: =SUM(M113:M115) -> 2492795
A118: Accumulated depreciation:
...

Sheet Orleans
D1: ORLEANS PARISH POLICE JURY
D2: Capital Assets
D3: For the Year Ended December 31, 2015
I5: Balance January 1, 2015 | J5: Additions | K5: Deletions | L5: Transfers | M5: Balance December 31, 2015 | N5: Cross Sectional
A7: Nondepreciable capital assets
B8: Land | I8: 94474 | M8: =SUM(I8:L8) -> 94474 | N8: =M8 -> 94474
B9: Construction in progress | I9: 396705 | J9: 107356 | L9: -96652 | M9: =SUM(I9:L9) -> 407409 | N9: =M9 -> 407409
C10: Total nondepreciable capital assets | I10: =SUM(I8:I9) -> 491179 | J10: =SUM(J8:J9) -> 107356 | K10: =SUM(K8:K9) -> 0 | L10: =SUM(L8:L9) -> -96652 | M10: =SUM(M8:M9) -> 501883
A12: Depreciable capital assets
B13: Infrastructure | I13: 2594250 | J13: 5209 | L13: -3987 | M13: =SUM(I13:L13) -> 2595472
B14: Buildings and Improvements | I14: 422462 | J14: 80944 | L14: 3987 | M14: =SUM(I14:L14) -> 507393
B15: Equipment and vehicles | I15: 104231 | J15: 11628 | K15: -47 | M15: =SUM(I15:L15) -> 115812
B16: Other | I16: 40492 | M16: =SUM(I16:L16) -> 40492
C17: Total depreciable capital assets | I17: =SUM(I13:I16) -> 3161435 | J17: =SUM(J13:J16) -> 97781 | K17: =SUM(K13:K16) -> -47 | L17: =SUM(L13:L16) -> 0 | M17: =SUM(M13:M16) -> 3259169
A19: Less accumulated depreciation for:
B20: Infrastructure | I20: 1820222 | J20: 60643 | L20: -322 | M20: =SUM(I20:L20) -> 1880543 | N20: =M13-M20 -> 714929
B21: Buildings and improvements | I21: 123287 | J21: 19147 | L21: 322 | M21: =SUM(I21:L21) -> 142756 | N21: =M14-M21 -> 364637
B22: Equipment and vehicles | I22: 88515 | J22: 5309 | K22: -47 | M22: =SUM(I22:L22) -> 93777 | N22: =M15-M22 -> 22035
B23: Other | I23: 31537 | J23: 1307 | M23: =SUM(I23:L23) -> 32844 | N23: =M16-M23 -> 7648
C24: Total accumulated depreciation | I24: =SUM(I20:I23) -> 2063561 | J24: =SUM(J20:J23) -> 86406 | K24: =SUM(K20:K23) -> -47 | L24: =SUM(L20:L23) -> 0 | M24: =SUM(M20:M23) -> 2149920
B25: Total depreciable capital assets, net | I25: =I17-I24 -> 1097874 | J25: =J17-J24 -> 11375 | K25: =K17-K24 -> 0 | L25: =L17-L24 -> 0 | M25: =M17-M24 -> 1109249
B26: Total | I26: =I25+I10 -> 1589053 | J26: =J25+J10 -> 118731 | K26: =K25+K10 -> 0 | L26: =L25+L10 -> -96652 | M26: =M25+M10 -> 1611132 | N26: =SUM(N8:N23) -> 1611132

Sheet Ouachita
D1: OUACHITA PARISH POLICE JURY
D2: Capital Assets
D3: For the Year Ended December 31, 2015
J5: Governmental Activities
I6: Balance January 1, 2015 | J6: Additions and Transfers | K6: Deletions and Transfers | L6: Balance December 31, 2015 | M6: Cross Sectional
A8: Capital assets, not being depreciated
B9: Land | I9: 12244547 | L9: =SUM(I9:K9) -> 12244547 | M9: =SUM(L9) -> 12244547
B10: Construction in progress | I10: 10535196 | J10: 9817301 | K10: -550787 | L10: =SUM(I10:K10) -> 19801710 | M10: =SUM(L10) -> 19801710
C11: Total Capital assets, not being depreciated | I11: =SUM(I9:I10) -> 22779743 | J11: =SUM(J9:J10) -> 9817301 | K11: =SUM(K9:K10) -> -550787 | L11: =SUM(L9:L10) -> 32046257
A13: Capital assets being depreciated
B14: Buildings | I14: 58928974 | J14: 327560 | K14: -40343 | L14: =SUM(I14:K14) -> 59216191
B15: Furniture, fixtures and equipment | I15: 33034265 | J15: 2976955 | K15: -731267 | L15: =SUM(I15:K15) -> 35279953
B16: Books | I16: 4307666 | J16: 570318 | K16: -396517 | L16: =SUM(I16:K16) -> 4481467
B17: Infrastructure:
C18: Roads | I18: 256020340 | L18: =SUM(I18:K18) -> 256020340
C19: Bridges | I19: 6541105 | L19: =SUM(I19:K19) -> 6541105
C20: Drainage | I20: 2456171 | J20: 551436 | L20: =SUM(I20:K20) -> 3007607
C21: Total capital assets, being depreciated | I21: =SUM(I14:I20) -> 361288521 | J21: =SUM(J14:J20) -> 4426269 | K21: =SUM(K14:K20) -> -1168127 | L21: =SUM(L14:L20) -> 364546663
A23: Total capital assets before being accumulated depreciated | I23: =I21+I11 -> 384068264 | J23: =J21+J11 -> 14243570 | K23: =K21+K11 -> -1718914 | L23: =L21+L11 -> 396592920
A25: Less accumulated depreciation
B26: Buildings | I26: 22099502 | J26: 1381228 | K26: -18457 | L26: =SUM(I26:K26) -> 23462273 | M26: =L14-L26 -> 35753918
B27: Furniture, fixtures and equipment | I27: 21214818 | J27: 2299364 | K27: -721532 | L27: =SUM(I27:K27) -> 22792650 | M27: =L15-L27 -> 12487303
B28: Books | I28: 2768792 | J28: 510563 | K28: -396517 | L28: =SUM(I28:K28) -> 2882838 | M28: =L16-L28 -> 1598629
B29: Infrastructure:
C30: Roads | I30: 154018282 | J30: 6391762 | L30: =SUM(I30:K30) -> 160410044 | M30: =L18-L30 -> 95610296
C31: Bridges | I31: 2703374 | J31: 87215 | L31: =SUM(I31:K31) -> 2790589 | M31: =L19-L31 -> 3750516
C32: Drainage | I32: 296920 | J32: 118467 | L32: =SUM(I32:K32) -> 415387 | M32: =L20-L32 -> 2592220
C33: Total accumulated depreciation | I33: =SUM(I26:I32) -> 203101688 | J33: =SUM(J26:J32) -> 10788599 | K33: =SUM(K26:K32) -> -1136506 | L33: =SUM(L26:L32) -> 212753781
B34: Governmental activities capital assets, net | I34: =I23-I33 -> 180966576 | J34: =J23-J33 -> 3454971 | K34: =K23-K33 -> -582408 | L34: =L23-L33 -> 183839139 | M34: =SUM(M26:M32,M9:M10) -> 183839139

Sheet Plaquemines
D1: PLAQUEMINES PARISH POLICE JURY
D2: Capital Assets
D3: For the Year Ended December 31, 2015
I5: Beginning Balance | J5: Additions | K5: Deductions | L5: Ending Balance | M5: Cross Sectional
A6: Governmental-Type Activities:
A7: Capital assets, not being depreciated:
B8: Land | I8: 13523564 | L8: =SUM(I8:K8) -> 13523564 | M8: =L8 -> 13523564
B9: Construction in progress | I9: 134839305 | J9: 19545520 | K9: -57406127 | L9: =SUM(I9:K9) -> 96978698 | M9: =L9 -> 96978698
B10: Construction in progress-FEMA Projects | I10: 12492211 | J10: 12064144 | L10: =SUM(I10:K10) -> 24556355 | M10: =L10 -> 24556355
C11: Total capital assets not being depreciated | I11: =SUM(I8:I10) -> 160855080 | J11: =SUM(J8:J10) -> 31609664 | K11: =SUM(K8:K10) -> -57406127 | L11: =SUM(L8:L10) -> 135058617
A13: Capital assets, being depreciated:
B14: Buildings and improvements | I14: 161537374 | J14: 6695539 | K14: -3204873 | L14: =SUM(I14:K14) -> 165028040
B15: Improvements other than buildings | I15: 85604109 | J15: 11391664 | K15: -13976601 | L15: =SUM(I15:K15) -> 83019172
B16: Machinery and Equipment | I16: 43562198 | J16: 2961802 | K16: -2011046 | L16: =SUM(I16:K16) -> 44512954
B17: Infrastructure | I17: 252815578 | J17: 26124290 | K17: -904089 | L17: =SUM(I17:K17) -> 278035779
C18: Total capital assets being depreciated | I18: =SUM(I14:I17) -> 543519259 | J18: =SUM(J14:J17) -> 47173295 | K18: =SUM(K14:K17) -> -20096609 | L18: =SUM(L14:L17) -> 570595945
A20: Less accumulated depreciation
B21: Buildings and improvements | I21: -34192089 | J21: -4501520 | K21: 52245 | L21: =SUM(I21:K21) -> -38641364 | M21: =L14+L21 -> 126386676
B22: Improvements other than buildings | I22: -9500606 | J22: -2426343 | K22: 260880 | L22: =SUM(I22:K22) -> -11666069 | M22: =L15+L22 -> 71353103
B23: Machinery and Equipment | I23: -21137335 | J23: -2445833 | K23: 1199558 | L23: =SUM(I23:K23) -> -22383610 | M23: =L16+L23 -> 22129344
B24: Infrastructure | I24: -166618823 | J24: -2186611 | L24: =SUM(I24:K24) -> -168805434 | M24: =L17+L24 -> 109230345
C25: Total accumulated depreciation | I25: =SUM(I21:I24) -> -231448853 | J25: =SUM(J21:J24) -> -11560307 | K25: =SUM(K21:K24) -> 1512683 | L25: =SUM(L21:L24) -> -241496477
A27: Total Capital Assets, being depreciated, net | I27: =I18+I25 -> 312070406 | J27: =J18+J25 -> 35612988 | K27: =K18+K25 -> -18583926 | L27: =L18+L25 -> 329099468
A28: Governmental Activities, net | I28: =I11+I27 -> 472925486 | J28: =J11+J27 -> 67222652 | K28: =K11+K27 -> -75990053 | L28: =L11+L27 -> 464158085 | M28: =SUM(M8:M25) -> 464158085
A31: Business-Type Activities:
A32: Capital assets, not being depreciated:
B33: Land | I33: 52000 | L33: =SUM(I33:K33) -> 52000 | M33: =L33 -> 52000
B34: Construction in Progress | I34: 27712347 | J34: 5523911 | K34: -7251313 | L34: =SUM(I34:K34) -> 25984945 | M34: =L34 -> 25984945
A35: Total capital assets not being depreciated | I35: =SUM(I33:I34) -> 27764347 | J35: =SUM(J33:J34) -> 5523911 | K35: =SUM(K33:K34) -> -7251313 | L35: =SUM(L33:L34) -> 26036945
A37: Capital assets being depreciated
B38: Buildings and Improvements | I38: 36166045 | J38: 2869620 | K38: -58133 | L38: =SUM(I38:K38) -> 38977532
B39: Improvements other than buildings | I39: 91736274 | J39: 291945 | K39: -257392 | L39: =SUM(I39:K39) -> 91770827
B40: Machinery and Equipment | I40: 3832014 | J40: 447744 | K40: -378698 | L40: =SUM(I40:K40) -> 3901060
B41: Infrastructure | I41: 4451924 | J41: 4638425 | L41: =SUM(I41:K41) -> 9090349
C42: Total capital assets being depreciated | I42: =SUM(I38:I41) -> 136186257 | J42: =SUM(J38:J41) -> 8247734 | K42: =SUM(K38:K41) -> -694223 | L42: =SUM(L38:L41) -> 143739768
A44: Less accumulated depreciation for
B45: Buildings and Improvements | I45: -10188074 | J45: -827992 | L45: =SUM(I45:K45) -> -11016066 | M45: =L38+L45 -> 27961466
B46: Improvements other than buildings | I46: -47666191 | J46: -3289596 | L46: =SUM(I46:K46) -> -50955787 | M46: =L39+L46 -> 40815040
B47: Machinery and Equipment | I47: -2465756 | J47: -231085 | K47: 343947 | L47: =SUM(I47:K47) -> -2352894 | M47: =L40+L47 -> 1548166
B48: Infrastructure | I48: -119833 | J48: -142696 | L48: =SUM(I48:K48) -> -262529 | M48: =L41+L48 -> 8827820
C49: Total accumulated depreciation | I49: =SUM(I45:I48) -> -60439854 | J49: =SUM(J45:J48) -> -4491369 | K49: =SUM(K45:K48) -> 343947 | L49: =SUM(L45:L48) -> -64587276
A51: Total capital assets being depreciated, net | I51: =I42+I49 -> 75746403 | J51: =J42+J49 -> 3756365 | K51: =K42+K49 -> -350276 | L51: =L42+L49 -> 79152492
A53: Business-type activities, net | I53: =I35+I51 -> 103510750 | J53: =J35+J51 -> 9280276 | K53: =K35+K51 -> -7601589 | L53: =L35+L51 -> 105189437 | M53: =SUM(M33:M51) -> 105189437

Sheet Pointe Coupee
D1: POINTE COUPEE PARISH POLICE JURY
D2: Capital Assets
D3: For the Year Ended December 31, 2015
I5: Beginning Balance | J5: Increases | K5: Decreases | L5: Ending Balance | M5: Cross Sectional
A6: Governmental Activities:
A7: Capital assets, not being depreciated:
B8: Land | I8: 841274 | L8: =SUM(I8:K8) -> 841274 | M8: =L8 -> 841274
B9: Construction in progress | I9: 618897 | J9: 2584578 | L9: =SUM(I9:K9) -> 3203475 | M9: =L9 -> 3203475
C10: Total capital assets not being depreciated | I10: =SUM(I8:I9) -> 1460171 | J10: =SUM(J8:J9) -> 2584578 | K10: =SUM(K8:K9) -> 0 | L10: =SUM(L8:L9) -> 4044749
A12: Capital assets, being depreciated:
B13: Buildings and improvements | I13: 9156077 | J13: 652962 | L13: =SUM(I13:K13) -> 9809039
B14: Library collection | I14: 3065316 | J14: 95570 | K14: -4042 | L14: =SUM(I14:K14) -> 3156844
B15: Equipment, furnishings, and vehicles | I15: 7196401 | J15: 106030 | L15: =SUM(I15:K15) -> 7302431
B16: Infrastructure | I16: 13260397 | J16: 27775 | L16: =SUM(I16:K16) -> 13288172
C17: Total capital assets being depreciated | I17: =SUM(I13:I16) -> 32678191 | J17: =SUM(J13:J16) -> 882337 | K17: =SUM(K13:K16) -> -4042 | L17: =SUM(L13:L16) -> 33556486
A19: Less accumulated depreciation for
B20: Buildings and improvements | I20: 4326307 | J20: 226560 | L20: =SUM(I20:K20) -> 4552867 | M20: =L13+L20 -> 14361906
B21: Library collection | I21: 2602281 | J21: 128808 | K21: -4042 | L21: =SUM(I21:K21) -> 2727047 | M21: =L14+L21 -> 5883891
B22: Equipment, furnishings, and vehicles | I22: 6851465 | J22: 124939 | L22: =SUM(I22:K22) -> 6976404 | M22: =L15+L22 -> 14278835
B23: Infrastructure | I23: 3424582 | J23: 685271 | L23: =SUM(I23:K23) -> 4109853 | M23: =L16+L23 -> 17398025
C24: Total accumulated depreciation | I24: =SUM(I20:I23) -> 17204635 | J24: =SUM(J20:J23) -> 1165578 | K24: =SUM(K20:K23) -> -4042 | L24: =SUM(L20:L23) -> 18366171
A26: Total Capital Assets, being depreciated, net | I26: =I17+I24 -> 49882826 | J26: =J17+J24 -> 2047915 | K26: =K17+K24 -> -8084 | L26: =L17+L24 -> 51922657
A27: Governmental Activities capital assets, net | I27: =I10+I26 -> 51342997 | J27: =J10+J26 -> 4632493 | K27: =K10+K26 -> -8084 | L27: =L10+L26 -> 55967406 | M27: =SUM(M8:M25) -> 55967406
A30: Business-Type Activities:
A31: Capital assets, not being depreciated:
B32: Construction in Progress | J32: 191535 | L32: =SUM(I32:K32) -> 191535 | M32: =L32 -> 191535
B33: Land | I33: 45233 | L33: =SUM(I33:K33) -> 45233 | M33: =L33 -> 45233
A35: Capital assets being depreciated
B36: Utility systems and related equipment | I36: 7924013 | J36: 249406 | L36: =SUM(I36:K36) -> 8173419
B37: Less accumulated depreciation | I37: -5862789 | J37: -226652 | L37: =SUM(I37:K37) -> -6089441
A39: Total capital assets being depreciated, net | I39: =SUM(I36:I37) -> 2061224 | J39: =SUM(J36:J37) -> 22754 | K39: =SUM(K36:K37) -> 0 | L39: =SUM(L36:L37) -> 2083978 | M39: =L39 -> 2083978
A41: Business-type activities capital assets, net | I41: =SUM(I39,I33) -> 2106457 | J41: =SUM(J39,J33) -> 22754 | K41: =SUM(K39,K33) -> 0 | L41: =SUM(L39,L33) -> 2129211 | M41: =SUM(M33:M39) -> 2129211

Sheet Rapides
D1: RAPIDES PARISH POLICE JURY
D2: Capital Assets
D3: For the Year Ended December 31, 2015
C5: Primary Government - Governmental Activities:
E6: Land | F6: Construction in Progress | G6: Buildings and Improvements | H6: Furniture and Equipment | I6: Infrastructure | J6: Total
C7: Beginning balance | E7: 1991998 | F7: 4503009 | G7: 25842304 | H7: 23946814 | I7: 346773509 | J7: =SUM(E7:I7) -> 403057634
D8: Additions | E8: 1133050 | F8: 11789224 | G8: 482721 | H8: 805282 | I8: 2842177 | J8: =SUM(E8:I8) -> 17052454
D9: Deletions | F9: -3950167 | G9: -139311 | H9: -1217194 | J9: =SUM(E9:I9) -> -5306672
C10: Ending balance | E10: =SUM(E7:E9) -> 3125048 | F10: =SUM(F7:F9) -> 12342066 | G10: =SUM(G7:G9) -> 26185714 | H10: =SUM(H7:H9) -> 23534902 | I10: =SUM(I7:I9) -> 349615686 | J10: =SUM(E10:I10) -> 414803416
B12: Accumulated depreciation:
C13: Beginning balance | G13: -15819276 | H13: -15912415 | I13: -317214998 | J13: =SUM(E13:I13) -> -348946689
D14: Additions | G14: -582821 | H14: -1355651 | I14: -1047236 | J14: =SUM(E14:I14) -> -2985708
D15: Deletions | G15: 139311 | H15: 1107918 | J15: =SUM(E15:I15) -> 1247229
C16: Ending balance | E16: =SUM(E13:E15) -> 0 | F16: =SUM(F13:F15) -> 0 | G16: =SUM(G13:G15) -> -16262786 | H16: =SUM(H13:H15) -> -16160148 | I16: =SUM(I13:I15) -> -318262234 | J16: =SUM(J13:J15) -> -350685168
C18: Ending balance, net | E18: =SUM(E16,E10) -> 3125048 | F18: =SUM(F16,F10) -> 12342066 | G18: =SUM(G16,G10) -> 9922928 | H18: =SUM(H16,H10) -> 7374754 | I18: =SUM(I16,I10) -> 31353452 | J18: =SUM(J16,J10) -> 64118248
C20: Cross Sectional | E20: =E10 -> 3125048 | F20: =F10 -> 12342066 | G20: =G10+G16 -> 9922928 | H20: =H10+H16 -> 7374754 | I20: =I10+I16 -> 31353452 | J20: =J10+J16 -> 64118248

Sheet Red River
D1: RED RIVER PARISH POLICE JURY
D2: Capital Assets
D3: For the Year Ended December 31, 2015
I5: Balance at December 31, 2014 | J5: Additions | K5: Retirements | L5: Balance at December 31, 2015 | M5: Cross Sectional
A7: Capital assets, not being depreciated:
B8: Land | I8: 301537 | L8: =SUM(I8:K8) -> 301537 | M8: =L8 -> 301537
B9: Construction in progress | I9: 792015 | J9: 196344 | K9: -293735 | L9: =SUM(I9:K9) -> 694624 | M9: =L9 -> 694624
C10: Total capital assets not being depreciated | I10: =SUM(I8:I9) -> 1093552 | J10: =SUM(J8:J9) -> 196344 | K10: =SUM(K8:K9) -> -293735 | L10: =SUM(L8:L9) -> 996161
A12: Capital assets, being depreciated:
B13: Buildings and building improvements | I13: 10797497 | J13: 54864 | L13: =SUM(I13:K13) -> 10852361
B14: Less accumulated depreciation | I14: -6067854 | J14: -325311 | L14: =SUM(I14:K14) -> -6393165 | M14: =L13+L14 -> 4459196
C15: Total buildings and building improvements | I15: =SUM(I13:I14) -> 4729643 | J15: =SUM(J13:J14) -> -270447 | K15: =SUM(K13:K14) -> 0 | L15: =SUM(L13:L14) -> 4459196
B17: Streets, parking lots and other improvements | I17: 10776243 | J17: 2271979 | L17: =SUM(I17:K17) -> 13048222
B18: Less accumulated depreciation | I18: -2496273 | J18: -1107283 | L18: =SUM(I18:K18) -> -3603556 | M18: =L17+L18 -> 9444666
C19: Total streets, parking lots and other improvements | I19: =SUM(I17:I18) -> 8279970 | J19: =SUM(J17:J18) -> 1164696 | K19: =SUM(K17:K18) -> 0 | L19: =SUM(L17:L18) -> 9444666
B21: Furniture, equipment, and vehicles | I21: 3076922 | J21: 421680 | L21: =SUM(I21:K21) -> 3498602
B22: Less accumulated depreciation | I22: -1955699 | J22: -471449 | L22: =SUM(I22:K22) -> -2427148 | M22: =L21+L22 -> 1071454
C23: Total furniture, equipment, and vehicles | I23: =SUM(I21:I22) -> 1121223 | J23: =SUM(J21:J22) -> -49769 | K23: =SUM(K21:K22) -> 0 | L23: =SUM(L21:L22) -> 1071454
B25: Library books and information materials | I25: 216528 | J25: 16004 | K25: -63415 | L25: =SUM(I25:K25) -> 169117
B26: Less accumulated depreciation | I26: -142622 | J26: -16911 | K26: 63415 | L26: =SUM(I26:K26) -> -96118 | M26: =L25+L26 -> 72999
C27: Total library books and information materials | I27: =SUM(I25:I26) -> 73906 | J27: =SUM(J25:J26) -> -907 | K27: =SUM(K25:K26) -> 0 | L27: =SUM(L25:L26) -> 72999
A29: Total capital assets being depreciated | I29: =I27+I23+I19+I15 -> 14204742 | J29: =J27+J23+J19+J15 -> 843573 | K29: =K27+K23+K19+K15 -> 0 | L29: =L27+L23+L19+L15 -> 15048315
A31: Governmental activities total capital assets, net | I31: =I29+I10 -> 15298294 | J31: =J29+J10 -> 1039917 | K31: =K29+K10 -> -293735 | L31: =L29+L10 -> 16044476 | M31: =SUM(M8:M29) -> 16044476
A33: Business-type Activities
A34: Capital assets, not being depreciated
B35: Contstruction in progress | J35: 23130 | L35: =SUM(I35:K35) -> 23130 | M35: =L35 -> 23130
B36: Total assets not being depreciated | I36: =SUM(I34:I35) -> 0 | J36: =SUM(J34:J35) -> 23130 | K36: =SUM(K34:K35) -> 0 | L36: =SUM(L34:L35) -> 23130
A39: Capital assets, being depreciated
B40: Sewer system | I40: 1205548 | L40: =SUM(I40:K40) -> 1205548
B41: Less accumulated depreciated | I41: -942668 | J41: -80790 | L41: =SUM(I41:K41) -> -1023458 | M41: =SUM(L40:L41) -> 182090
C42: Total Sewer system | I42: =SUM(I40:I41) -> 262880 | J42: =SUM(J40:J41) -> -80790 | K42: =SUM(K40:K41) -> 0 | L42: =SUM(L40:L41) -> 182090
C44: Total capital assets, being depreciated | I44: =SUM(I42) -> 262880 | J44: =SUM(J42) -> -80790 | K44: =SUM(K42) -> 0 | L44: =SUM(L42) -> 182090 | M44: =M41 -> 182090
A46: Business-type activities
C47: Total capital assets, net | I47: =SUM(I44+I36) -> 262880 | J47: =SUM(J44+J36) -> -57660 | K47: =SUM(K44+K36) -> 0 | L47: =SUM(L44+L36) -> 205220
A48: Primary government
C49: Total capital assets, net | I49: =SUM(I31+I47) -> 15561174 | J49: =SUM(J31+J47) -> 982257 | K49: =SUM(K31+K47) -> -293735 | L49: =SUM(L31+L47) -> 16249696 | M49: =SUM(M8:M41) -> 32294172

Sheet Richland
D1: RICHLAND PARISH POLICE JURY
D2: Capital Assets
D3: For the Year Ended December 31, 2015
I5: Beginning, January 1, 2015 | J5: Additions | K5: Deletions | L5: Balance- Deceomber 31, 2015 | M5: Cross Sectional
A8: Capital assets, not being depreciated:
B9: Land | I9: 311523 | L9: =SUM(I9:K9) -> 311523 | M9: =L9 -> 311523
A11: Capital assets, being depreciated:
B12: Buildings and improvements | I12: 3106781 | L12: =SUM(I12:K12) -> 3106781
B13: Machinery and equipment | I13: 3975875 | J13: 195045 | L13: =SUM(I13:K13) -> 4170920
C14: Total capital assets being depreciated | I14: =SUM(I12:I13) -> 7082656 | J14: =SUM(J12:J13) -> 195045 | K14: =SUM(K12:K13) -> 0 | L14: =SUM(L12:L13) -> 7277701
A16: Less accumulated depreciation for
B17: Buildings and improvements | I17: 1427793 | J17: 43555 | L17: =SUM(I17:K17) -> 1471348 | M17: =L12-L17 -> 1635433
B18: Machinery and Equipment | I18: 3346584 | J18: 206986 | L18: =SUM(I18:K18) -> 3553570 | M18: =L13-L18 -> 617350
C19: Total accumulated depreciation | I19: =SUM(I17:I18) -> 4774377 | J19: =SUM(J17:J18) -> 250541 | K19: =SUM(K17:K18) -> 0 | L19: =SUM(L17:L18) -> 5024918
A21: Total Capital Assets, being depreciated | I21: =I14-I19 -> 2308279 | J21: =J14-J19 -> -55496 | K21: =K14-K19 -> 0 | L21: =L14-L19 -> 2252783
A23: Total Capital Assets, net | I23: =SUM(I9+I21) -> 2619802 | J23: =SUM(J9+J21) -> -55496 | K23: =SUM(K9+K21) -> 0 | L23: =SUM(L9+L21) -> 2564306 | M23: =SUM(M8:M19) -> 2564306

Sheet Sabine
D1: SABINE PARISH POLICE JURY
D2: Capital Assets
D3: For the Year Ended December 31, 2015
I5: Beginning Balance | J5: Additions | K5: Deductions | L5: Ending Balance | M5: Cross Sectional
B6: Land | I6: 639576 | L6: =SUM(I6:K6) -> 639576 | M6: =L6 -> 639576
B7: Construction in progress | I7: 2281793 | J7: 21717 | K7: -2303510 | L7: =SUM(I7:K7) -> 0 | M7: =L7 -> 0
B8: Buildings | I8: 3339381 | L8: =SUM(I8:K8) -> 3339381
B9: Machinery and equipment | I9: 6177923 | J9: 363883 | L9: =SUM(I9:K9) -> 6541806
B10: Furniture and fixtures | I10: 93561 | J10: 13854 | L10: =SUM(I10:K10) -> 107415
B11: Infrastructure | I11: 66408345 | J11: 2303510 | L11: =SUM(I11:K11) -> 68711855
C12: Total capital assets | I12: =SUM(I6:I11) -> 78940579 | J12: =SUM(J6:J11) -> 2702964 | K12: =SUM(K6:K11) -> -2303510 | L12: =SUM(L6:L11) -> 79340033
A14: Depreciation
B15: Buildings | I15: -1140090 | J15: -69588 | L15: =SUM(I15:K15) -> -1209678 | M15: =L8+L15 -> 2129703
B16: Machinery and Equipment | I16: -3234448 | J16: -323480 | L16: =SUM(I16:K16) -> -3557928 | M16: =L9+L16 -> 2983878
B17: Furniture and fixtures | I17: -80988 | J17: -5346 | L17: =SUM(I17:K17) -> -86334 | M17: =L10+L17 -> 21081
B18: Infrastructure | I18: -60607508 | J18: -143379 | L18: =SUM(I18:K18) -> -60750887 | M18: =L11+L18 -> 7960968
C19: Total accumulated depreciation | I19: =SUM(I15:I18) -> -65063034 | J19: =SUM(J15:J18) -> -541793 | K19: =SUM(K15:K18) -> 0 | L19: =SUM(L15:L18) -> -65604827
A21: Net capital assets | I21: =SUM(I12+I19) -> 13877545 | J21: =SUM(J12+J19) -> 2161171 | K21: =SUM(K12+K19) -> -2303510 | L21: =SUM(L12+L19) -> 13735206 | M21: =SUM(M6:M18) -> 13735206

Sheet St. Bernard
D1: ST. BERNARD PARISH POLICE JURY
D2: Capital Assets
D3: For the Year Ended December 31, 2015
I5: Balance January 1, 2015 | J5: Additions | K5: Deletions and adjustments | L5: Balance December 31, 2015 | M5: Cross Sectional
A6: Governmental-Type Activities:
A7: Nondepreciable capital assets
B8: Land | I8: 19826039 | J8: 32115 | L8: =SUM(I8:K8) -> 19858154 | M8: =L8 -> 19858154
B9: Construction in progress | I9: 16929777 | J9: 20736569 | K9: -3159924 | L9: =SUM(I9:K9) -> 34506422 | M9: =L9 -> 34506422
C10: Total nondepreciable capital assets | I10: =SUM(I8:I9) -> 36755816 | J10: =SUM(J8:J9) -> 20768684 | K10: =SUM(K8:K9) -> -3159924 | L10: =SUM(L8:L9) -> 54364576
A12: Depreciable capital assets
B13: Land improvements | I13: 862954 | L13: =SUM(I13:K13) -> 862954
B14: Buildings and improvements | I14: 132127057 | J14: 1453663 | L14: =SUM(I14:K14) -> 133580720
B15: Furniture, fixtures, and equipment | I15: 440835 | J15: 34995 | L15: =SUM(I15:K15) -> 475830
B16: Machinery and equipment | I16: 19119119 | J16: 2229746 | K16: -2702960 | L16: =SUM(I16:K16) -> 18645905
B17: Road system | I17: 260907225 | J17: 1765763 | L17: =SUM(I17:K17) -> 262672988
B18: Bridges | I18: 1363360 | L18: =SUM(I18:K18) -> 1363360
C19: Total depreciable capital assets | I19: =SUM(I13:I18) -> 414820550 | J19: =SUM(J13:J18) -> 5484167 | K19: =SUM(K13:K18) -> -2702960 | L19: =SUM(L13:L18) -> 417601757
A21: Less: accumulated depreciation
C22: Land Improvements | M22: =L13+L22 -> 862954
C23: Buildings | M23: =L14+L23 -> 133580720
C24: Furniture, fixtures, and equipment | M24: =L15+L24 -> 475830
C25: Machinery and equipment | I25: Missing in source audit | M25: =L16+L25 -> 18645905
C26: Road system | M26: =L17+L26 -> 262672988
C27: Bridges | M27: =L18+L27 -> 1363360
C28: Total accumulated depreciation | I28: -66718456 | J28: -16406778 | K28: 1995698 | L28: =SUM(I28:K28) -> -81129536
C30: Total depreciable capital assets, net | I30: =SUM(I28+I19) -> 348102094 | J30: =SUM(J28+J19) -> -10922611 | K30: =SUM(K28+K19) -> -707262 | L30: =SUM(L28+L19) -> 336472221
C31: Total governmental activities capital assets, net | I31: =SUM(I30+I10) -> 384857910 | J31: =SUM(J30+J10) -> 9846073 | K31: =SUM(K30+K10) -> -3867186 | L31: =SUM(L30+L10) -> 390836797 | M31: =SUM(M8:M27) -> 471966333
A34: Business-Type Activities:
A35: Nondepreciable capital assets
B36: Land | I36: 221036 | L36: =SUM(I36:K36) -> 221036 | M36: =L36 -> 221036
B37: Construction in progress | I37: 54919030 | J37: 4848194 | L37: =SUM(I37:K37) -> 59767224 | M37: =L37 -> 59767224
C38: Total nondepreciable capital assets | I38: =SUM(I36:I37) -> 55140066 | J38: =SUM(J37:J37) -> 4848194 | K38: =SUM(K37:K37) -> 0 | L38: =SUM(L36:L37) -> 59988260
A40: Depreciable capital assets
B41: Buildings | I41: 87242281 | L41: =SUM(I41:K41) -> 87242281
B42: Furniture, fixtures, and equipment | I42: 36492 | L42: =SUM(I42:K42) -> 36492
B43: Machinery and equipment | I43: 1667222 | J43: 539259 | K43: -116492 | L43: =SUM(I43:K43) -> 2089989
B44: Infrastructure | I44: 187944606 | J44: 86891 | L44: =SUM(I44:K44) -> 188031497
C45: Total depreciable capital assets | I45: =SUM(I41:I44) -> 276890601 | J45: =SUM(J41:J44) -> 626150 | K45: =SUM(K41:K44) -> -116492 | L45: =SUM(L41:L44) -> 277400259
A47: Less: accumulated depreciation
B48: Buildings | M48: =L41+L48 -> 87242281
B49: Furniture, fixtures, and equipment | I49: Missing in source audit | M49: =L42+L49 -> 36492
B50: Machinery and equipment | M50: =L43+L50 -> 2089989
B51: Infrastructure | M51: =L44+L51 -> 188031497
C52: Total accumulated depreciation | I52: -114547938 | J52: -15938797 | K52: 106343 | L52: =SUM(I52:K52) -> -130380392
C54: Total depreciable capital assets, net | I54: =SUM(I45+I52) -> 162342663 | J54: =SUM(J45+J52) -> -15312647 | K54: =SUM(K45+K52) -> -10149 | L54: =SUM(L45+L52) -> 147019867
C55: Total business-type activities capital assets, net | I55: =I38+I54 -> 217482729 | J55: =J38+J54 -> -10464453 | K55: =K38+K54 -> -10149 | L55: =L38+L54 -> 207008127 | M55: =SUM(M36:M51) -> 337388519

Sheet St. Charles
D1: ST. CHARLES PARISH
D2: Capital Assets
D3: For the Year Ended December 31, 2015
I5: Balance at December 31, 2014 | J5: Additions | K5: Deletions | L5: Adjustments | M5: Balance at December 31, 2015 | N5: Cross Sectional
A6: Governmental Activities
A7: Capital assets, not being depreciated:
A8: Land | I8: 10484811 | J8: 165000 | L8: 20000 | M8: =SUM(I8:L8) -> 10669811 | N8: =M8 -> 10669811
A9: Infrastructure | I9: 14855447 | M9: =SUM(I9:L9) -> 14855447 | N9: =M9 -> 14855447
A10: Construction in progress | I10: 34185224 | J10: 25048849 | K10: -7378764 | L10: -1500 | M10: =SUM(I10:L10) -> 51853809 | N10: =M10 -> 51853809
B11: Total assets not being depreciated | I11: =SUM(I8:I10) -> 59525482 | J11: =SUM(J8:J10) -> 25213849 | K11: =SUM(K8:K10) -> -7378764 | L11: =SUM(L8:L10) -> 18500 | M11: =SUM(M8:M10) -> 77379067
A13: Capital assets, being depreciated:
A14: Buildings | I14: 51008943 | J14: 1359732 | K14: -108737 | M14: =SUM(I14:L14) -> 52259938
A15: Improvements other than buildings | I15: 84057170 | J15: 6534160 | K15: -20180 | L15: 276714 | M15: =SUM(I15:L15) -> 90847864
A16: Machinery and equipment | I16: 39412787 | J16: 2799874 | K16: -852457 | L16: -18623 | M16: =SUM(I16:L16) -> 41341581
A17: Infrastructure | I17: 111422111 | K17: -635245 | L17: 1623977 | M17: =SUM(I17:L17) -> 112410843
C18: Total capital assets being depreciated | I18: =SUM(I14:I17) -> 285901011 | J18: =SUM(J14:J17) -> 10693766 | K18: =SUM(K14:K17) -> -1616619 | L18: =SUM(L14:L17) -> 1882068 | M18: =SUM(M14:M17) -> 296860226
A20: Less accumulated depreciation for:
A21: Buildings | I21: -13081461 | J21: -1405179 | K21: 92524 | M21: =SUM(I21:L21) -> -14394116 | N21: =M14+M21 -> 37865822
A22: Improvements other than buildings | I22: -37015483 | J22: -4362465 | K22: 19701 | M22: =SUM(I22:L22) -> -41358247 | N22: =M15+M22 -> 49489617
A23: Machinery and equipment | I23: -29017151 | J23: -2275415 | K23: 868124 | M23: =SUM(I23:L23) -> -30424442 | N23: =M16+M23 -> 10917139
A24: Infrastructure | I24: -68695022 | J24: -3317181 | K24: 132449 | M24: =SUM(I24:L24) -> -71879754 | N24: =M17+M24 -> 40531089
C25: Total accumulated depreciation | I25: =SUM(I21:I24) -> -147809117 | J25: =SUM(J21:J24) -> -11360240 | K25: =SUM(K21:K24) -> 1112798 | L25: =SUM(L21:L24) -> 0 | M25: =SUM(M21:M24) -> -158056559
A27: Total capital assets being depreciated, net | I27: =SUM(I18+I25) -> 138091894 | J27: =SUM(J18+J25) -> -666474 | K27: =SUM(K18+K25) -> -503821 | L27: =SUM(L18+L25) -> 1882068 | M27: =SUM(M18+M25) -> 138803667
A29: Total governmental activities capital assets, net | I29: =I11+I27 -> 197617376 | J29: =J11+J27 -> 24547375 | K29: =K11+K27 -> -7882585 | L29: =L11+L27 -> 1900568 | M29: =M11+M27 -> 216182734 | N29: =SUM(N8:N27) -> 216182734
A32: Business-type Activities
A33: Land | I33: 824777 | M33: =SUM(I33:L33) -> 824777 | N33: =M33 -> 824777
A34: Construction in progress | I34: 3944738 | J34: 842378 | K34: -2144768 | M34: =SUM(I34:L34) -> 2642348 | N34: =M34 -> 2642348
B35: Total assets not being depreciated | I35: =SUM(I33:I34) -> 4769515 | J35: =SUM(J33:J34) -> 842378 | K35: =SUM(K33:K34) -> -2144768 | L35: =SUM(L33:L34) -> 0 | M35: =SUM(M33:M34) -> 3467125
A37: Capital assets, being depreciated:
A38: Buildings and improvements | I38: 213642913 | J38: 2666344 | K38: -102193 | L38: 564794 | M38: =SUM(I38:L38) -> 216771858
A39: Machinery and equipment | I39: 15591141 | J39: 466649 | K39: -482608 | L39: 15794 | M39: =SUM(I39:L39) -> 15590976
C40: Total capital assets being depreciated | I40: =SUM(I38:I39) -> 229234054 | J40: =SUM(J38:J39) -> 3132993 | K40: =SUM(K38:K39) -> -584801 | L40: =SUM(L38:L39) -> 580588 | M40: =SUM(M38:M39) -> 232362834
A42: Less accumulated depreciation for:
A43: Buildings and improvements | I43: -87221759 | J43: -5694841 | K43: 102193 | M43: =SUM(I43:L43) -> -92814407 | N43: =M38+M43 -> 123957451
A44: Machinery and equipment | I44: -13816530 | J44: -543160 | K44: 482608 | M44: =SUM(I44:L44) -> -13877082 | N44: =M39+M44 -> 1713894
C45: Total accumulated depreciation | I45: =SUM(I43:I44) -> -101038289 | J45: =SUM(J43:J44) -> -6238001 | K45: =SUM(K43:K44) -> 584801 | L45: =SUM(L43:L44) -> 0 | M45: =SUM(M43:M44) -> -106691489
A47: Total capital assets being depreciated, net | I47: =SUM(I40+I45) -> 128195765 | J47: =SUM(J40+J45) -> -3105008 | K47: =SUM(K40+K45) -> 0 | L47: =SUM(L40+L45) -> 580588 | M47: =SUM(M40+M45) -> 125671345
A49: Total business type activities capital assets, net | I49: =I35+I47 -> 132965280 | J49: =J35+J47 -> -2262630 | K49: =K35+K47 -> -2144768 | L49: =L35+L47 -> 580588 | M49: =M35+M47 -> 129138470 | N49: =SUM(N33:N47) -> 129138470

Sheet St. Helena
D1: ST. HELENA PARISH POLICE JURY
D2: Capital Assets
D3: For the Year Ended December 31, 2015
I5: Beginning Balance | J5: Increases | K5: Decreases | L5: Adjustments | M5: Ending Balance | N5: Cross Sectional
A6: Governmental Activities Capital Assets:
A7: Capital assets, not being depreciated:
B8: Land | I8: 235036 | J8: 7700 | M8: =SUM(I8:L8) -> 242736 | N8: =M8 -> 242736
B9: Construction in progress | I9: 2104367 | J9: 469304 | K9: -2137914 | M9: =SUM(I9:L9) -> 435757 | N9: =M9 -> 435757
C10: Total assets not being depreciated | I10: =SUM(I8:I9) -> 2339403 | J10: =SUM(J8:J9) -> 477004 | K10: =SUM(K8:K9) -> -2137914 | L10: =SUM(L8:L9) -> 0 | M10: =SUM(M8:M9) -> 678493
A12: Capital assets, being depreciated:
B13: Buildings and improvements | I13: 5807271 | J13: 456694 | K13: -16188 | M13: =SUM(I13:L13) -> 6247777
B14: Machinery and Improvements | I14: 6583657 | J14: 357161 | K14: -467835 | M14: =SUM(I14:L14) -> 6472983
B15: Infrastructure | I15: 10537775 | J15: 1692804 | M15: =SUM(I15:L15) -> 12230579
C16: Total capital assets being depreciated | I16: =SUM(I13:I15) -> 22928703 | J16: =SUM(J13:J15) -> 2506659 | K16: =SUM(K13:K15) -> -484023 | L16: =SUM(L13:L15) -> 0 | M16: =SUM(M13:M15) -> 24951339
A18: Less accumulated depreciation for
B19: Buildings and improvements | I19: -2036901 | J19: -146494 | K19: 7091 | M19: =SUM(I19:L19) -> -2176304 | N19: =M13+M19 -> 4071473
B20: Machinery and Equipment | I20: -4121126 | J20: -451811 | K20: 439326 | M20: =SUM(I20:L20) -> -4133611 | N20: =M14+M20 -> 2339372
B21: Infrastructure | I21: -1242614 | J21: -281158 | M21: =SUM(I21:L21) -> -1523772 | N21: =M15+M21 -> 10706807
C22: Total accumulated depreciation | I22: =SUM(I19:I21) -> -7400641 | J22: =SUM(J19:J21) -> -879463 | K22: =SUM(K19:K21) -> 446417 | L22: =SUM(L19:L21) -> 0 | M22: =SUM(M19:M21) -> -7833687
A24: Total Capital Assets, being depreciated, net | I24: =I16+I22 -> 15528062 | J24: =J16+J22 -> 1627196 | K24: =K16+K22 -> -37606 | L24: =L16+L22 -> 0 | M24: =M16+M22 -> 17117652
A25: Total Governmental activities capital assets, net | I25: =I10+I24 -> 17867465 | J25: =J10+J24 -> 2104200 | K25: =K10+K24 -> -2175520 | L25: =L10+L24 -> 0 | M25: =M10+M24 -> 17796145 | N25: =SUM(N8:N23) -> 17796145

Sheet St. James
D1: ST. JAMES PARISH POLICE JURY
D2: Capital Assets
D3: For the Year Ended December 31, 2015
I5: Beginning Balance | J5: Increases | K5: Decreases | L5: Ending Balance | M5: Cross Sectional
A6: Governmental Activities:
A7: Capital assets, not being depreciated:
B8: Land | I8: 21340364 | J8: 3216059 | L8: =SUM(I8:K8) -> 24556423 | M8: =L8 -> 24556423
B9: Construction in progress | I9: 7175955 | J9: 2655358 | K9: -1637686 | L9: =SUM(I9:K9) -> 8193627 | M9: =L9 -> 8193627
C10: Total assets not being depreciated | I10: =SUM(I8:I9) -> 28516319 | J10: =SUM(J8:J9) -> 5871417 | K10: =SUM(K8:K9) -> -1637686 | L10: =SUM(L8:L9) -> 32750050
A12: Capital assets, being depreciated
A13: Buildings | I13: 21261074 | J13: 829737 | K13: -635919 | L13: =SUM(I13:K13) -> 21454892
A14: Improvements other than buildings | I14: 4688312 | J14: 93210 | L14: =SUM(I14:K14) -> 4781522
A15: Machinery and equipment | I15: 15005944 | J15: 1896380 | K15: -393013 | L15: =SUM(I15:K15) -> 16509311
A16: Library collection | I16: 1907503 | J16: 87209 | K16: -3532 | L16: =SUM(I16:K16) -> 1991180
A17: Infrastructure | I17: 58191263 | L17: =SUM(I17:K17) -> 58191263
B18: Total capital assets being depreciated | I18: =SUM(I13:I17) -> 101054096 | J18: =SUM(J13:J17) -> 2906536 | K18: =SUM(K13:K17) -> -1032464 | L18: =SUM(L13:L17) -> 102928168
A20: Less accumulated depreciation for
A21: Buildings | I21: -7356971 | J21: -663822 | K21: 348673 | L21: =SUM(I21:K21) -> -7672120 | M21: =L13+L21 -> 13782772
A22: Improvements other than buildings | I22: -1499493 | J22: -193578 | L22: =SUM(I22:K22) -> -1693071 | M22: =L14+L22 -> 3088451
A23: Machinery and equipment | I23: -9398519 | J23: -1218641 | K23: 339586 | L23: =SUM(I23:K23) -> -10277574 | M23: =L15+L23 -> 6231737
A24: Library collection | I24: -1837029 | J24: -70474 | K24: 3532 | L24: =SUM(I24:K24) -> -1903971 | M24: =L16+L24 -> 87209
A25: Infrastructure | I25: -46351040 | J25: -1485746 | L25: =SUM(I25:K25) -> -47836786 | M25: =L17+L25 -> 10354477
A26: Total accumulated depreciation | I26: =SUM(I21:I25) -> -66443052 | J26: =SUM(J21:J25) -> -3632261 | K26: =SUM(K21:K25) -> 691791 | L26: =SUM(L21:L25) -> -69383522
A28: Total capital assets, being depreciated, net | I28: =SUM(I26+I18) -> 34611044 | J28: =SUM(J26+J18) -> -725725 | K28: =SUM(K26+K18) -> -340673 | L28: =SUM(L26+L18) -> 33544646
A29: Governmental activities capital assets, net | I29: =SUM(I10+I18+I26) -> 63127363 | J29: =SUM(J10+J18+J26) -> 5145692 | K29: =SUM(K10+K18+K26) -> -1978359 | L29: =SUM(L10+L18+L26) -> 66294696 | M29: =SUM(M8:M25) -> 66294696
A31: Business-type activities:
A32: Capital assets, not being depreciated
A33: Land | I33: 1050000 | L33: =SUM(I33:K33) -> 1050000 | M33: =L33 -> 1050000
A34: Construction in progress | I34: 47480 | J34: 112176 | L34: =SUM(I34:K34) -> 159656 | M34: =L34 -> 159656
A35: Total capital assets, not being depreciated | I35: =SUM(I33:I34) -> 1097480 | J35: =SUM(J33:J34) -> 112176 | K35: =SUM(K33:K34) -> 0 | L35: =SUM(L33:L34) -> 1209656
A37: Capital assets, being depreciated
A38: Buildings | I38: 6061170 | L38: =SUM(I38:K38) -> 6061170
A39: Gas distribution system | I39: 2098948 | L39: =SUM(I39:K39) -> 2098948
A40: Water distribution system | I40: 21854558 | J40: 656847 | L40: =SUM(I40:K40) -> 22511405
A41: Office furniture, fixtures, and equipment | I41: 751073 | L41: =SUM(I41:K41) -> 751073
A42: Transportation equipment | I42: 593885 | J42: 17776 | K42: -95727 | L42: =SUM(I42:K42) -> 515934
A43: Total capital assets, being depcreciated | I43: =SUM(I38:I42) -> 31359634 | J43: =SUM(J38:J42) -> 674623 | K43: =SUM(K38:K42) -> -95727 | L43: =SUM(L38:L42) -> 31938530
A45: Less accumulated depreciation for
A46: Buildings | I46: -5521169 | J46: -188710 | L46: =SUM(I46:K46) -> -5709879 | M46: =SUM(L38+L46) -> 351291
A47: Gas distribution system | I47: -1591610 | J47: -22122 | L47: =SUM(I47:K47) -> -1613732 | M47: =SUM(L39+L47) -> 485216
A48: Water distribution system | I48: -11104329 | J48: -615291 | L48: =SUM(I48:K48) -> -11719620 | M48: =SUM(L40+L48) -> 10791785
A49: Office furniture, fixtures, and equipment | I49: -733578 | J49: -6336 | L49: =SUM(I49:K49) -> -739914 | M49: =SUM(L41+L49) -> 11159
A50: Transportation equipment | I50: -370315 | J50: -62304 | K50: 95436 | L50: =SUM(I50:K50) -> -337183 | M50: =SUM(L42+L50) -> 178751
A51: Total accumulated depreciation | I51: =SUM(I46:I50) -> -19321001 | J51: =SUM(J46:J50) -> -894763 | K51: =SUM(K46:K50) -> 95436 | L51: =SUM(L46:L50) -> -20120328
A53: Total capital assets, being depreciated, net | I53: =SUM(I43+I51) -> 12038633 | J53: =SUM(J43+J51) -> -220140 | K53: =SUM(K43+K51) -> -291 | L53: =SUM(L43+L51) -> 11818202
A55: Business-type activities capital assets, net | I55: =SUM(I35+I53) -> 13136113 | J55: =SUM(J35+J53) -> -107964 | K55: =SUM(K35+K53) -> -291 | L55: =SUM(L35+L53) -> 13027858 | M55: =SUM(M33:M50) -> 13027858

Sheet St. John the Baptist
D1: ST. JOHN THE BAPTIST PARISH POLICE JURY
D2: Capital Assets
D3: For the Year Ended December 31, 2014
I5: 42005 | J5: Additions | K5: Reductions | L5: Decmber 31, 2015 | M5: Cross Sectional
A6: Governmental Activities
A7: Capital assets, not being depreciated:
B8: Land | I8: 3976254 | L8: =SUM(I8:K8) -> 3976254 | M8: =L8 -> 3976254
B9: Construction in progress | I9: 11706152 | J9: 13666808 | K9: -5995118 | L9: =SUM(I9:K9) -> 19377842 | M9: =L9 -> 19377842
B10: Total assets not being depreciated | I10: =SUM(I8:I9) -> 15682406 | J10: =SUM(J8:J9) -> 13666808 | K10: =SUM(K8:K9) -> -5995118 | L10: =SUM(L8:L9) -> 23354096
A12: Capital assets, being depreciated:
B13: Buildings and building improvements | I13: 33894846 | J13: 3881722 | L13: =SUM(I13:K13) -> 37776568
B14: Infrastructure | I14: 173920180 | J14: 1389074 | L14: =SUM(I14:K14) -> 175309254
B15: Drainage system | I15: 21421466 | J15: 89745 | L15: =SUM(I15:K15) -> 21511211
B16: Furniture, fixtures, and equipment | I16: 11265398 | J16: 399664 | K16: -49242 | L16: =SUM(I16:K16) -> 11615820
B17: Vehicles | I17: 9705461 | J17: 2519639 | K17: -13537 | L17: =SUM(I17:K17) -> 12211563
B18: Total capital assets being depreciated | I18: =SUM(I13:I17) -> 250207351 | J18: =SUM(J13:J17) -> 8279844 | K18: =SUM(K13:K17) -> -62779 | L18: =SUM(L13:L17) -> 258424416
A20: Less accumulated depreciation for:
B21: Buildings and building improvements | I21: 10040474 | J21: 1160619 | L21: =SUM(I21:K21) -> 11201093 | M21: =L13-L21 -> 26575475
B22: Infrastructure | I22: 147338268 | J22: 1906237 | L22: =SUM(I22:K22) -> 149244505 | M22: =L14-L22 -> 26064749
B23: Drainage system | I23: 6683164 | J23: 533625 | L23: =SUM(I23:K23) -> 7216789 | M23: =L15-L23 -> 14294422
B24: Furniture, fixtures, and equipment | I24: 8088701 | J24: 823762 | K24: -49242 | L24: =SUM(I24:K24) -> 8863221 | M24: =L16-L24 -> 2752599
B25: Vehicles | I25: 7561507 | J25: 536129 | K25: -13537 | L25: =SUM(I25:K25) -> 8084099 | M25: =L17-L25 -> 4127464
B26: Total accumulated depreciation | I26: =SUM(I21:I25) -> 179712114 | J26: =SUM(J21:J25) -> 4960372 | K26: =SUM(K21:K25) -> -62779 | L26: =SUM(L21:L25) -> 184609707
A27: Total capital assets being depreciated, net | I27: =SUM(I18-I26) -> 70495237 | J27: =SUM(J18-J26) -> 3319472 | K27: =SUM(K18-K26) -> 0 | L27: =SUM(L18-L26) -> 73814709
A28: Total governmental activities capital assets, net | I28: =SUM(I10+I27) -> 86177643 | J28: =SUM(J10+J27) -> 16986280 | K28: =SUM(K10+K27) -> -5995118 | L28: =SUM(L10+L27) -> 97168805 | M28: =SUM(M8:M26) -> 97168805
A31: Business-Type Activities:
A32: Capital assets, not being depreciated:
B33: Land | I33: 1678616 | L33: =SUM(I33:K33) -> 1678616 | M33: =L33 -> 1678616
B34: Construction in progress | I34: 1487729 | J34: 2489079 | K34: -626996 | L34: =SUM(I34:K34) -> 3349812 | M34: =L34 -> 3349812
C35: Total capital assets not being depreciated | I35: =SUM(I33:I34) -> 3166345 | J35: =SUM(J33:J34) -> 2489079 | K35: =SUM(K33:K34) -> -626996 | L35: =SUM(L33:L34) -> 5028428
A37: Capital assets, being depreciated
A38: Buildings and building improvements | I38: 14522758 | J38: 20509 | L38: =SUM(I38:K38) -> 14543267
A39: Systems-water and sewer | I39: 208285994 | J39: 2384589 | L39: =SUM(I39:K39) -> 210670583
A40: Furniture, fixtures, and equipment | I40: 5704270 | J40: 79923 | K40: -4649 | L40: =SUM(I40:K40) -> 5779544
A41: Vehicles | I41: 1927212 | J41: 58016 | K41: -135024 | L41: =SUM(I41:K41) -> 1850204
A42: Total capital assets, being depreciated | I42: =SUM(I38:I41) -> 230440234 | J42: =SUM(J38:J41) -> 2543037 | K42: =SUM(K38:K41) -> -139673 | L42: =SUM(I42:K42) -> 232843598
A44: Less accumulated depreciation for
A45: Buildings and building improvements | I45: 2702149 | J45: 388398 | L45: =SUM(I45:K45) -> 3090547 | M45: =L38-L45 -> 11452720
A46: Systems-water and sewer | I46: 98947309 | J46: 4510636 | L46: =SUM(I46:K46) -> 103457945 | M46: =L39-L46 -> 107212638
A47: Furniture, fixtures, and equipment | I47: 2524196 | J47: 256826 | K47: -4473 | L47: =SUM(I47:K47) -> 2776549 | M47: =L40-L47 -> 3002995
A48: Vehicles | I48: 1749737 | J48: 61396 | K48: -121154 | L48: =SUM(I48:K48) -> 1689979 | M48: =L41-L48 -> 160225
A49: Total accumulated depreciation | I49: =SUM(I45:I48) -> 105923391 | J49: =SUM(J45:J48) -> 5217256 | K49: =SUM(K45:K48) -> -125627 | L49: =SUM(I49:K49) -> 111015020
A50: Total capital assets, being depreciated, net | I50: =SUM(I42-I49) -> 124516843 | J50: =SUM(J42-J49) -> -2674219 | K50: =SUM(K42-K49) -> -14046 | L50: =SUM(L42-L49) -> 121828578
A51: Total business-type activities capital assets, net | I51: =SUM(I35+I50) -> 127683188 | J51: =SUM(J35+J50) -> -185140 | K51: =SUM(K35+K50) -> -641042 | L51: =SUM(L35+L50) -> 126857006 | M51: =SUM(M33:M49) -> 126857006

Sheet St. Landry
D1: ST. LANDRY PARISH POLICE JURY
D2: Capital Assets
D3: For the Year Ended December 31, 2015
I5: Balance 12/31/14 | J5: Additions | K5: Deletions | L5: Balance 12/31/14 | M5: Cross Sectional
A6: Primary Government
A7: Governmental Activities:
A8: Capital assets, not being depreciated:
B9: Land | I9: 499243 | L9: =SUM(I9:K9) -> 499243 | M9: =L9 -> 499243
B10: Construction in progress- infrastructure | I10: 9080748 | J10: 9583390 | K10: -9080748 | L10: =SUM(I10:K10) -> 9583390 | M10: =L10 -> 9583390
I11: =SUM(I9:I10) -> 9579991 | J11: =SUM(J9:J10) -> 9583390 | K11: =SUM(K9:K10) -> -9080748 | L11: =SUM(L9:L10) -> 10082633
A12: Capital assets, being depreciated:
B13: Buildings and improvements | I13: 14525602 | J13: 7983 | L13: =SUM(I13:K13) -> 14533585
B14: Vehicles | I14: 520767 | K14: -31212 | L14: =SUM(I14:K14) -> 489555
B15: Equipment, furniture and fixtures | I15: 4439245 | J15: 5403 | K15: -303809 | L15: =SUM(I15:K15) -> 4140839
B16: Improvements other than buildings | I16: 6619637 | L16: =SUM(I16:K16) -> 6619637
I17: =SUM(I13:I16) -> 26105251 | J17: =SUM(J13:J16) -> 13386 | K17: =SUM(K13:K16) -> -335021 | L17: =SUM(I17:K17) -> 25783616
A18: Less accumulated depreciation for
B19: Buildings and improvements | I19: -10860739 | J19: -253565 | L19: =SUM(I19:K19) -> -11114304 | M19: =L13+L19 -> 3419281
B20: Vehicles | I20: -233144 | J20: -78944 | K20: 31176 | L20: =SUM(I20:K20) -> -280912 | M20: =L14+L20 -> 208643
B21: Equipment, furniture and fixtures | I21: -3425449 | J21: -324539 | K21: 302708 | L21: =SUM(I21:K21) -> -3447280 | M21: =L15+L21 -> 693559
B22: Improvements other than buildings | I22: -3084763 | J22: -236467 | L22: =SUM(I22:K22) -> -3321230 | M22: =L16+L22 -> 3298407
I23: =SUM(I19:I22) -> -17604095 | J23: =SUM(J19:J22) -> -893515 | K23: =SUM(K19:K22) -> 333884 | L23: =SUM(L19:L22) -> -18163726
A24: Total Capital Assets being depreciated, net | I24: =SUM(I17+I23) -> 8501156 | J24: =SUM(J17+J23) -> -880129 | K24: =SUM(K17+K23) -> -1137 | L24: =SUM(L17+L23) -> 7619890
A25: Governmental activities capital assets, net | I25: =SUM(I11+I17+I23) -> 18081147 | J25: =SUM(J11+J17+J23) -> 8703261 | K25: =SUM(K11+K17+K23) -> -9081885 | L25: =SUM(L11+L17+L23) -> 17702523 | M25: =SUM(M9:M23) -> 17702523

Sheet St. Martin
D1: ST. MARTIN PARISH POLICE JURY
D2: Capital Assets
D3: For the Year Ended December 31, 2015
I5: Beginning Balance | J5: Acquisitions | K5: Dispositions | L5: Ending Balance | M5: Cross Sectional
A6: Primary Government
A7: Governmental-Type Activities:
A8: Capital assets, not being depreciated:
B9: Land | I9: 1560115 | J9: 56200 | L9: =SUM(I9:K9) -> 1616315 | M9: =L9 -> 1616315
B10: Construction in progress | I10: 1213143 | J10: 1641498 | L10: =SUM(I10:K10) -> 2854641 | M10: =L10 -> 2854641
C11: Total assets not being depreciated | I11: =SUM(I9:I10) -> 2773258 | J11: =SUM(J9:J10) -> 1697698 | K11: =SUM(K9:K10) -> 0 | L11: =SUM(L9:L10) -> 4470956
A13: Capital assets, being depreciated:
B14: Buildings and improvements | I14: 36316273 | J14: 218679 | L14: =SUM(I14:K14) -> 36534952
B15: Machinery and equipment | I15: 15331824 | J15: 1670187 | K15: -810415 | L15: =SUM(I15:K15) -> 16191596
B16: Improvements, other than buildings | I16: 1781934 | J16: 31019 | L16: =SUM(I16:K16) -> 1812953
B17: Roads and bridges | I17: 43807018 | L17: =SUM(I17:K17) -> 43807018
C18: Total capital assets being depreciated | I18: =SUM(I14:I17) -> 97237049 | J18: =SUM(J14:J17) -> 1919885 | K18: =SUM(K14:K17) -> -810415 | L18: =SUM(L14:L17) -> 98346519
A20: Less accumulated depreciation for
B21: Buildings | I21: 8263206 | J21: 911552 | L21: =SUM(I21:K21) -> 9174758 | M21: =L14-L21 -> 27360194
B22: Machinery and Equipment | I22: 10122075 | J22: 1390435 | K22: -810415 | L22: =SUM(I22:K22) -> 10702095 | M22: =L15-L22 -> 5489501
B23: Improvements, other than buildings | I23: 747587 | J23: 71897 | L23: =SUM(I23:K23) -> 819484 | M23: =L16-L23 -> 993469
B24: Roads and bridges | I24: 10143450 | J24: 1426224 | L24: =SUM(I24:K24) -> 11569674 | M24: =L17-L24 -> 32237344
C25: Total accumulated depreciation | I25: =SUM(I21:I24) -> 29276318 | J25: =SUM(J21:J24) -> 3800108 | K25: =SUM(K21:K24) -> -810415 | L25: =SUM(L21:L24) -> 32266011
A27: Total Capital Assets being depreciated, net | I27: =I18-I25 -> 67960731 | J27: =J18-J25 -> -1880223 | K27: =K18-K25 -> 0 | L27: =L18-L25 -> 66080508
A28: Governmental activities capital assets, net | I28: =I11+I27 -> 70733989 | J28: =J11+J27 -> -182525 | K28: =K11+K27 -> 0 | L28: =L11+L27 -> 70551464 | M28: =SUM(M9:M26) -> 70551464

Sheet St Mary
E1: ST. TAMMANY PARISH POLICE JURY
E2: Capital Assets
E3: For the Year Ended December 31, 2015
A6: Primary Government | J6: Beginning Balance | K6: Increases | L6: Decreases | M6: Transfers | N6: Ending Balance | O6: Cross Sectional
A7: Governmental Activities
B8: Capital assets, not being depreciated:
C9: Land | J9: 1870876 | N9: =SUM(J9:M9) -> 1870876 | O9: =N9 -> 1870876
C10: Construction in progress | J10: 2899550 | K10: 9313636 | M10: -3476957 | N10: =SUM(J10:M10) -> 8736229 | O10: =N10 -> 8736229
D11: Total capital assets not being depreciated | J11: =SUM(J9:J10) -> 4770426 | K11: =SUM(K9:K10) -> 9313636 | L11: =SUM(L9:L10) -> 0 | M11: =SUM(M9:M10) -> -3476957 | N11: =SUM(N9:N10) -> 10607105
B13: Other capital assets:
C14: Infrastructure | J14: 130977942 | K14: 655182 | M14: 3374145 | N14: =SUM(J14:M14) -> 135007269
C15: Buildings | J15: 17516962 | N15: =SUM(J15:M15) -> 17516962
C16: Equipment and furniture | J16: 11247366 | K16: 852825 | N16: =SUM(J16:M16) -> 12100191
C17: Improvements | J17: 24019462 | K17: 567289 | M17: 102812 | N17: =SUM(J17:M17) -> 24689563
D18: Total capital assets being depreciated | J18: =SUM(J14:J17) -> 183761732 | K18: =SUM(K14:K17) -> 2075296 | L18: =SUM(L14:L17) -> 0 | M18: =SUM(M14:M17) -> 3476957 | N18: =SUM(N14:N17) -> 189313985
B20: Less accumulated depreciation for:
C21: Infrastructure | J21: -55417419 | K21: -3242312 | N21: =SUM(J21:M21) -> -58659731 | O21: =N14+N21 -> 76347538
C22: Buildings | J22: -7468731 | K22: -472223 | N22: =SUM(J22:M22) -> -7940954 | O22: =N15+N22 -> 9576008
C23: Equipment and furniture | J23: -9037216 | K23: -627039 | N23: =SUM(J23:M23) -> -9664255 | O23: =N16+N23 -> 2435936
C24: Improvements | J24: -8989185 | K24: -1090606 | N24: =SUM(J24:M24) -> -10079791 | O24: =N17+N24 -> 14609772
D25: Total accumulated depreciation | J25: =SUM(J21:J24) -> -80912551 | K25: =SUM(K21:K24) -> -5432180 | L25: =SUM(L21:L24) -> 0 | M25: =SUM(M21:M24) -> 0 | N25: =SUM(N21:N24) -> -86344731
D26: Other capital assets, net | J26: =SUM(J18+J25) -> 102849181 | K26: =SUM(K18+K25) -> -3356884 | L26: =SUM(L18+L25) -> 0 | N26: =SUM(N18+N25) -> 102969254
D27: Governmental capital assets, net | J27: =SUM(J11+J26) -> 107619607 | K27: =SUM(K11+K26) -> 5956752 | L27: =SUM(L11+L26) -> 0 | N27: =SUM(N11+N26) -> 113576359 | O27: =SUM(O9:O26) -> 113576359
A29: Business-type Activities
B30: Capital assets, not being depreciated
C31: Construction in Progress | J31: 50068 | K31: 104893 | N31: =SUM(J31:M31) -> 154961 | O31: =N31 -> 154961
C32: Land | J32: 2052372 | N32: =SUM(J32:M32) -> 2052372 | O32: =N32 -> 2052372
C33: Land improvements | J33: 1750227 | N33: =SUM(J33:M33) -> 1750227 | O33: =N33 -> 1750227
D34: Total capital assets not being depreciated | J34: =SUM(J31:J33) -> 3852667 | K34: =SUM(K31:K33) -> 104893 | L34: =SUM(L31:L33) -> 0 | M34: =SUM(M31:M33) -> 0 | N34: =SUM(N31:N33) -> 3957560
B36: Other capital asets:
C37: Buildings | J37: 4455578 | N37: =SUM(J37:M37) -> 4455578
C38: Equipment | J38: 7815011 | K38: 662816 | L38: -218500 | N38: =SUM(J38:M38) -> 8259327
C39: Improvements | J39: 18721946 | K39: 1094021 | N39: =SUM(J39:M39) -> 19815967
E40: Total capital assets being depreciated | J40: =SUM(J37:J39) -> 30992535 | K40: =SUM(K37:K39) -> 1756837 | L40: =SUM(L37:L39) -> -218500 | M40: =SUM(M37:M39) -> 0 | N40: =SUM(N37:N39) -> 32530872
B42: Less accumulated depreciation for
C43: Buildings | J43: -4312628 | K43: -9000 | N43: =SUM(J43:M43) -> -4321628 | O43: =SUM(N43+N37) -> 133950
C44: Equipment | J44: -5870594 | K44: -681857 | L44: 160237 | N44: =SUM(J44:M44) -> -6392214 | O44: =SUM(N44+N38) -> 1867113
C45: Improvements | J45: -3328039 | K45: -489849 | N45: =SUM(J45:M45) -> -3817888 | O45: =SUM(N45+N39) -> 15998079
D46: Total accumulated depreciation | J46: =SUM(J43:J45) -> -13511261 | K46: =SUM(K43:K45) -> -1180706 | L46: =SUM(L43:L45) -> 160237 | M46: 0 | N46: =SUM(N43:N45) -> -14531730
D47: Other capital assets, net | J47: =SUM(J40+J46) -> 17481274 | K47: =SUM(K40+K46) -> 576131 | L47: =SUM(L40+L46) -> -58263 | M47: =SUM(M40+M46) -> 0 | N47: =SUM(N40+N46) -> 17999142
D48: Business-type activities capital assets, net | J48: =SUM(J34+J47) -> 21333941 | K48: =SUM(K34+K47) -> 681024 | L48: =SUM(L34+L47) -> -58263 | M48: =SUM(M34+M47) -> 0 | N48: =SUM(N34+N47) -> 21956702 | O48: =SUM(O31:O45) -> 21956702

Sheet St. Tammany
E1: ST. TAMMANY PARISH POLICE JURY
E2: Capital Assets
E3: For the Year Ended December 31, 2015
J5: Beginning Balance | K5: Increases | L5: Decreases | M5: Re-classes | N5: Ending Balance | O5: Cross Sectional
B7: Primary Government
B8: Governmental Activities
B9: Capital assets, not being depreciated:
B10: Land | J10: 44520378 | K10: 3349577 | M10: 12016 | N10: =SUM(J10:M10) -> 47881971 | O10: =N10 -> 47881971
B11: Land improvements-non-exhaustible | J11: 2362283 | M11: 40575 | N11: =SUM(J11:M11) -> 2402858 | O11: =N11 -> 2402858
B12: Construction in progress | J12: 2179839 | K12: 2329926 | L12: -2415 | M12: -2548789 | N12: =SUM(J12:M12) -> 1958561 | O12: =N12 -> 1958561
B13: Infrastructure:
C14: Land | J14: 21899120 | K14: 336584 | L14: -1090561 | M14: 100921 | N14: =SUM(J14:M14) -> 21246064 | O14: =N14 -> 21246064
C15: Land Improvements-non-exhaustible | J15: 19395315 | K15: 1805955 | L15: -21488 | M15: 484857 | N15: =SUM(J15:M15) -> 21664639 | O15: =N15 -> 21664639
C16: Construction in progress | J16: 24956579 | K16: 23405510 | L16: -407874 | M16: -31833687 | N16: =SUM(J16:M16) -> 16120528 | O16: =N16 -> 16120528
C17: Total capital assets not being depreciated | J17: =SUM(J10:J16) -> 115313514 | K17: =SUM(K10:K16) -> 31227552 | L17: =SUM(L10:L16) -> -1522338 | M17: =SUM(M10:M16) -> -33744107 | N17: =SUM(N10:N16) -> 111274621
B18: Capital assets, being depreciated:
B19: Land Improvements | J19: 4897831 | N19: =SUM(J19:M19) -> 4897831
B20: Buildings | J20: 99215360 | K20: 19838172 | M20: 1344826 | N20: =SUM(J20:M20) -> 120398358
B21: Building improvements | J21: 5995184 | N21: =SUM(J21:M21) -> 5995184
B22: Water and sewer systems | J22: 632317 | N22: =SUM(J22:M22) -> 632317
B23: Vehicles | J23: 4052973 | K23: 655553 | L23: -274264 | M23: 226664 | N23: =SUM(J23:M23) -> 4660926
B24: Machinery and equipment | J24: 24515179 | K24: 1712976 | L24: -437687 | M24: 17898 | N24: =SUM(J24:M24) -> 25808366
B25: Office/other equipment | J25: 10956507 | K25: 2614158 | M25: 1018324 | N25: =SUM(J25:M25) -> 14588989
B26: Infrastructure:
C27: Roads | J27: 280946958 | K27: 1211024 | L27: -3811168 | M27: 24989139 | N27: =SUM(J27:M27) -> 303335953
C28: Other | J28: 38209199 | K28: 964093 | L28: -1081475 | M28: 6083509 | N28: =SUM(J28:M28) -> 44175326
D29: Total capital assets being depreciated | J29: =SUM(J19:J28) -> 469421508 | K29: =SUM(K19:K28) -> 26995976 | L29: =SUM(L19:L28) -> -5604594 | M29: =SUM(M19:M28) -> 33680360 | N29: =SUM(N19:N28) -> 524493250
B30: Less accumulated depreciation for:
B31: Land Improvements | J31: -2058765 | K31: -361628 | N31: =SUM(J31:M31) -> -2420393 | O31: =N19+N31 -> 2477438
B32: Buildings | J32: -28789552 | K32: -3822455 | N32: =SUM(J32:M32) -> -32612007 | O32: =N20+N32 -> 87786351
B33: Building improvements | J33: -1349748 | K33: -280797 | N33: =SUM(J33:M33) -> -1630545 | O33: =N21+N33 -> 4364639
B34: Water and sewer systems | J34: -152944 | K34: -25292 | N34: =SUM(J34:M34) -> -178236 | O34: =N22+N34 -> 454081
B35: Vehicles | J35: -3696824 | K35: -159929 | L35: 274264 | M35: -220024 | N35: =SUM(J35:M35) -> -3802513 | O35: =N23+N35 -> 858413
B36: Machinery and equipment | J36: -19772533 | K36: -1142044 | L36: 437687 | M36: -7418 | N36: =SUM(J36:M36) -> -20484308 | O36: =N24+N36 -> 5324058
B37: Office/other equipment | J37: -8015601 | K37: -988533 | M37: -768121 | N37: =SUM(J37:M37) -> -9772255 | O37: =N25+N37 -> 4816734
B38: Infrastructure:
C39: Roads | J39: -106024698 | K39: -10769355 | L39: 2514078 | N39: =SUM(J39:M39) -> -114279975 | O39: =N27+N39 -> 189055978
C40: Other | J40: -6188350 | K40: -1492935 | L40: 47150 | N40: =SUM(J40:M40) -> -7634135 | O40: =N28+N40 -> 36541191
D41: Total accumulated depreciation | J41: =SUM(J31:J40) -> -176049015 | K41: =SUM(K31:K40) -> -19042968 | L41: =SUM(L31:L40) -> 3273179 | M41: =SUM(M31:M40) -> -995563 | N41: =SUM(N31:N40) -> -192814367
B42: Total capital assets being depreciated, net | J42: =SUM(J29+J41) -> 293372493 | K42: =SUM(K29+K41) -> 7953008 | L42: =SUM(L29+L41) -> -2331415 | M42: =SUM(M29+M41) -> 32684797 | N42: =SUM(N29+N41) -> 331678883
A44: Internal Service Fund
B45: Capital assets, not being depreciated:
B46: Land | J46: 1718617 | N46: =SUM(J46:M46) -> 1718617 | O46: =N46 -> 1718617
C47: Total capital assets not being depreciated | J47: =SUM(J46:J46) -> 1718617 | K47: =SUM(K46:K46) -> 0 | L47: 0 | M47: =SUM(M46:M46) -> 0 | N47: =SUM(J47:M47) -> 1718617
B48: Capital assets, being depreciated:
B49: Land Improvements | J49: 455413 | N49: =SUM(J49:M49) -> 455413
B50: Buildings | J50: 23637722 | N50: =SUM(J50:M50) -> 23637722
B51: Building Improvements | J51: 5881376 | M51: 1169570 | N51: =SUM(J51:M51) -> 7050946
B52: Vehicles | J52: 226664 | M52: -226664 | N52: =SUM(J52:M52) -> 0
B53: Machinery and equipment | J53: 9999 | K53: 7899 | M53: -17898 | N53: =SUM(J53:M53) -> 0
B54: Office/other equipment | J54: 2220206 | K54: 216050 | M54: -983931 | N54: =SUM(J54:M54) -> 1452325
D55: Total capital assets being depreciated | J55: =SUM(J49:J54) -> 32431380 | K55: =SUM(K49:K54) -> 223949 | L55: =SUM(L49:L54) -> 0 | M55: =SUM(M49:M54) -> -58923 | N55: =SUM(N49:N54) -> 32596406
B56: Less accumulated depreciation for:
B57: Land Improvements | J57: -190843 | K57: -22771 | N57: =SUM(J57:M57) -> -213614 | O57: =N49+N57 -> 241799
B58: Buildings | J58: -8355165 | K58: -577766 | N58: =SUM(J58:M58) -> -8932931 | O58: =N50+N58 -> 14704791
B59: Building Improvements | J59: -1764712 | K59: -305736 | N59: =SUM(J59:M59) -> -2070448 | O59: =N51+N59 -> 4980498
B60: Vehicles | J60: -201342 | K60: -18681 | M60: 220023 | N60: =SUM(J60:M60) -> 0 | O60: =N52+N60 -> 0
B61: Machinery and equipment | J61: -5238 | K61: -2181 | M61: 7419 | N61: =SUM(J61:M61) -> 0 | O61: =N53+N61 -> 0
B62: Office/Other Equipment | J62: -1228849 | K62: -241713 | M62: 768121 | N62: =SUM(J62:M62) -> -702441 | O62: =N54+N62 -> 749884
C63: Toal accumulated depreciation | J63: =SUM(J57:J62) -> -11746149 | K63: =SUM(K57:K62) -> -1168848 | L63: =SUM(L57:L62) -> 0 | M63: =SUM(M57:M62) -> 995563 | N63: =SUM(N57:N62) -> -11919434
D64: Total capital assets being depreciated, net | J64: =SUM(J55+J63) -> 20685231 | K64: =SUM(K55+K63) -> -944899 | L64: =SUM(L55+L63) -> 0 | M64: =SUM(M55+M63) -> 936640 | N64: =SUM(N55+N63) -> 20676972
D65: Total Capital Assets Internal Service Funds, net | J65: =SUM(J47+J55+J63) -> 22403848 | K65: =SUM(K47+K55+K63) -> -944899 | L65: =SUM(L47+L55+L63) -> 0 | M65: =SUM(M47+M55+M63) -> 936640 | N65: =SUM(N47+N55+N63) -> 22395589
D66: Total Capital Assets Governmental Activities, net | J66: =SUM(J17+J29+J41+J47+J55+J63) -> 431089855 | K66: =SUM(K17+K29+K41+K47+K55+K63) -> 38235661 | L66: =SUM(L17+L29+L41+L47+L55+L63) -> -3853753 | M66: =SUM(M17+M29+M41+M47+M55+M63) -> -122670 | N66: =SUM(N17+N29+N41+N47+N55+N63) -> 465349093 | O66: =SUM(O10:O62) -> 465349093
A68: Business-type Activities
B69: Capital assets, not being depreciated
C70: Land | J70: 575567 | M70: 1993 | N70: =SUM(J70:M70) -> 577560 | O70: =N70 -> 577560
C71: Construction in Progress | J71: 1129272 | K71: 211772 | M71: -671207 | N71: =SUM(J71:M71) -> 669837 | O71: =N71 -> 669837
C72: Total capital assets not being depreciated | J72: =SUM(J70:J71) -> 1704839 | K72: =SUM(K70:K71) -> 211772 | L72: =SUM(L70:L71) -> 0 | M72: =SUM(M70:M71) -> -669214 | N72: =SUM(N70:N71) -> 1247397
B73: Capital assets being depreciated
C74: Land Improvements | J74: 50707 | N74: =SUM(J74:M74) -> 50707
C75: Buildings | J75: 13376 | N75: =SUM(J75:M75) -> 13376
C76: Vehicles | J76: 560012 | K76: 188185 | L76: -24402 | N76: =SUM(J76:M76) -> 723795
C77: Machinery and Equipment | J77: 566681 | K77: 26709 | L77: -800 | N77: =SUM(J77:M77) -> 592590
C78: Office/Other Equipment | J78: 6354 | N78: =SUM(J78:M78) -> 6354
C79: Infrastructure | N79: =SUM(J79:M79) -> 0
D80: Sewer equipment, lines and pumps | J80: 35128581 | K80: 120924 | M80: 249056 | N80: =SUM(J80:M80) -> 35498561
D81: Water equipment, lines and wells | J81: 17454857 | K81: 74268 | M81: 542828 | N81: =SUM(J81:M81) -> 18071953
E82: Total capital assets being depreciated | J82: =SUM(J74:J81) -> 53780568 | K82: =SUM(K74:K81) -> 410086 | L82: =SUM(L74:L81) -> -25202 | M82: =SUM(M74:M81) -> 791884 | N82: =SUM(N74:N81) -> 54957336
B83: Less accumulated depreciation for
C84: Land improvements | J84: -11550 | K84: -2535 | N84: =SUM(J84:M84) -> -14085 | O84: =SUM(N84+N74) -> 36622
C85: Buildings | J85: -2720 | K85: -535 | N85: =SUM(J85:M85) -> -3255 | O85: =SUM(N85+N75) -> 10121
C86: Vehicles | J86: -286132 | K86: -76428 | L86: 24402 | N86: =SUM(J86:M86) -> -338158 | O86: =SUM(N86+N76) -> 385637
C87: Machinery and Equipment | J87: -354522 | K87: -54246 | L87: 800 | N87: =SUM(J87:M87) -> -407968 | O87: =SUM(N87+N77) -> 184622
C88: Office/Other Equipment | J88: -1664 | K88: -908 | N88: =SUM(J88:M88) -> -2572 | O88: =SUM(N88+N78) -> 3782
C89: Infrastructure: | O89: =SUM(N89+N79) -> 0
D90: Sewer equipment, lines and pumps | J90: -12009584 | K90: -1628846 | N90: =SUM(J90:M90) -> -13638430 | O90: =SUM(N90+N80) -> 21860131
D91: Water equipment, lines and wells | J91: -3744271 | K91: -659267 | N91: =SUM(J91:M91) -> -4403538 | O91: =SUM(N91+N81) -> 13668415
D92: Total accumulated depreciation | J92: =SUM(J84:J91) -> -16410443 | K92: =SUM(K84:K91) -> -2422765 | L92: =SUM(L84:L91) -> 25202 | M92: 0 | N92: =SUM(N84:N91) -> -18808006
B93: Total capital assets being depreciated, net | J93: =SUM(J82+J92) -> 37370125 | K93: =SUM(K82+K92) -> -2012679 | L93: =SUM(L82+L92) -> 0 | M93: =SUM(M82+M92) -> 791884 | N93: =SUM(N82+N92) -> 36149330
B94: Total capital assets business-type activities, net | J94: =SUM(J72+J93) -> 39074964 | K94: =SUM(K72+K93) -> -1800907 | L94: =SUM(L72+L93) -> 0 | M94: =SUM(M72+M93) -> 122670 | N94: =SUM(N72+N93) -> 37396727 | O94: =SUM(O70:O91) -> 37396727
B95: Total capital assets- primary government, net | J95: =SUM(J94+J66) -> 470164819 | K95: =SUM(K66+K94) -> 36434754 | L95: =SUM(L66+L94) -> -3853753 | M95: =SUM(M66+M94) -> 0 | N95: =SUM(N66+N94) -> 502745820

Sheet Tangipahoa
D1: TANGIPAHOA PARISH POLICE JURY
D2: Capital Assets
D3: For the Year Ended December 31, 2015
I5: Balance 12/31/14 | J5: Increase | K5: Decreases | L5: Balance 12/31/15 | M5: Cross Sectional
A6: Governmental Activities:
A7: Capital assets, not being depreciated:
C8: Land | I8: 2910644 | J8: 169833 | L8: =SUM(I8:K8) -> 3080477 | M8: =L8 -> 3080477
C9: Infrastructure (Land and Base) | I9: 72012465 | J9: 423000 | L9: =SUM(I9:K9) -> 72435465 | M9: =L9 -> 72435465
C10: Construction in progress | I10: 2517758 | J10: 6952110 | K10: -4417296 | L10: =SUM(I10:K10) -> 5052572 | M10: =L10 -> 5052572
D11: Total assets not being depreciated | I11: =SUM(I8:I10) -> 77440867 | J11: =SUM(J8:J10) -> 7544943 | K11: =SUM(K8:K10) -> -4417296 | L11: =SUM(L8:L10) -> 80568514
A13: Capital assets, being depreciated:
B14: Buildings | I14: 49029786 | J14: 162105 | L14: =SUM(I14:K14) -> 49191891
B15: Infrastructure | I15: 118793905 | J15: 4074659 | K15: -1561683 | L15: =SUM(I15:K15) -> 121306881
B16: Equipment | I16: 16831741 | J16: 633381 | K16: -174177 | L16: =SUM(I16:K16) -> 17290945
D17: Total capital assets being depreciated | I17: =SUM(I14:I16) -> 184655432 | J17: =SUM(J14:J16) -> 4870145 | K17: =SUM(K14:K16) -> -1735860 | L17: =SUM(I17:K17) -> 187789717
A19: Less accumulated depreciation for
B20: Buildings | I20: 13019958 | J20: 1218293 | L20: =SUM(I20:K20) -> 14238251 | M20: =L14-L20 -> 34953640
B21: Infrastructure | I21: 57723955 | J21: 4292630 | K21: -796952 | L21: =SUM(I21:K21) -> 61219633 | M21: =L15-L21 -> 60087248
B22: Equipment | I22: 10724250 | J22: 1230211 | K22: -149124 | L22: =SUM(I22:K22) -> 11805337 | M22: =L16-L22 -> 5485608
D23: Total accumulated depreciation | I23: =SUM(I20:I22) -> 81468163 | J23: =SUM(J20:J22) -> 6741134 | K23: =SUM(K20:K22) -> -946076 | L23: =SUM(I23:K23) -> 87263221
A25: Total Capital Assets being depreciated, net | I25: =I17-I23 -> 103187269 | J25: =J17-J23 -> -1870989 | K25: =K17-K23 -> -789784 | L25: =L17-L23 -> 100526496
A26: Total Governmental activities, capital assets, net | I26: =I11+I25 -> 180628136 | J26: =J11+J25 -> 5673954 | K26: =K11+K25 -> -5207080 | L26: =L11+L25 -> 181095010 | M26: =SUM(M8:M24) -> 181095010

Sheet Tensas
D1: TENSAS PARISH POLICE JURY
D2: Capital Assets
D3: For the Year Ended December 31, 2015
I5: Balance, beginning | J5: Increase | K5: Decreases | L5: Balance, ending | M5: Cross Sectional
A6: Governmental-Type Activities:
A7: Capital assets, not being depreciated:
C8: Land | I8: 743698 | L8: =SUM(I8:K8) -> 743698 | M8: =L8 -> 743698
A10: Capital assets, being depreciated:
B11: Buildings | I11: 8889947 | L11: =SUM(I11:K11) -> 8889947
B12: Furniture, fixtures, and equipment | I12: 4405843 | J12: 237271 | K12: -15296 | L12: =SUM(I12:K12) -> 4627818
D13: Total capital assets being depreciated | I13: =SUM(I11:I12) -> 13295790 | J13: =SUM(J11:J12) -> 237271 | K13: =SUM(K11:K12) -> -15296 | L13: =SUM(I13:K13) -> 13517765
A15: Primary Government
A16: Less accumulated depreciation
B17: Buildings | I17: -1616467 | J17: -252702 | L17: =SUM(I17:K17) -> -1869169 | M17: =L11+L17 -> 7020778
B18: Furniture, fixtures, and equipment | I18: -3768073 | J18: -201980 | K18: 15296 | L18: =SUM(I18:K18) -> -3954757 | M18: =L12+L18 -> 673061
D19: Total accumulated depreciation | I19: =SUM(I17:I18) -> -5384540 | J19: =SUM(J17:J18) -> -454682 | K19: =SUM(K17:K18) -> 15296 | L19: =SUM(I19:K19) -> -5823926
A21: Total accumulated depreciation | I21: =SUM(I13+I19) -> 7911250 | J21: =SUM(J13+J19) -> -217411 | K21: =SUM(K13+K19) -> 0 | L21: =SUM(L13+L19) -> 7693839
A22: Total depreciable capital assets, net
A23: Governmental activities, capital assets, net | I23: =SUM(I21+I8) -> 8654948 | J23: =SUM(J21+J8) -> -217411 | K23: =SUM(K21+K8) -> 0 | L23: =SUM(L21+L8) -> 8437537 | M23: =SUM(M8:M20) -> 8437537

Sheet Terrebonne
E1: TERREBONNE PARISH POLICE JURY
E2: Capital Assets
E3: For the Year Ended December 31, 2015
J5: Balance 01/01/15 | K5: Additions | L5: Adjustments and Deletions | M5: Balance 12/31/15 | N5: Cross Sectional
B6: Capital assets, not being depreciated:
B7: Land | J7: 6470003 | M7: =SUM(J7:L7) -> 6470003 | N7: =M7 -> 6470003
B8: Construction in progress | J8: 57371869 | K8: 32259317 | L8: -18714575 | M8: =SUM(J8:L8) -> 70916611 | N8: =M8 -> 70916611
C9: Total capital assets not being depreciated | J9: =SUM(J7:J8) -> 63841872 | K9: =SUM(K7:K8) -> 32259317 | L9: =SUM(L7:L8) -> -18714575 | M9: =SUM(M7:M8) -> 77386614
B10: Capital assets, being depreciated:
B11: Buildings | J11: 53374935 | K11: 776812 | L11: -54286 | M11: =SUM(J11:L11) -> 54097461
B12: Equipment | J12: 64774165 | K12: 3153102 | L12: -8738146 | M12: =SUM(J12:L12) -> 59189121
B13: Infrastructure | J13: 281274424 | K13: 21359818 | M13: =SUM(J13:L13) -> 302634242
D14: Total capital assets being depreciated | J14: =SUM(J11:J13) -> 399423524 | K14: =SUM(K11:K13) -> 25289732 | L14: =SUM(L11:L13) -> -8792432 | M14: =SUM(M11:M13) -> 415920824
B15: Less accumulated depreciation for:
B16: Buildings | J16: -22580427 | K16: -1341585 | L16: 32400 | M16: =SUM(J16:L16) -> -23889612 | N16: =M11+M16 -> 30207849
B17: Equipment | J17: -44423217 | K17: -3281089 | L17: 7605356 | M17: =SUM(J17:L17) -> -40098950 | N17: =M12+M17 -> 19090171
B18: Infrastructure: | J18: -74420260 | K18: -8317620 | M18: =SUM(J18:L18) -> -82737880 | N18: =M13+M18 -> 219896362
D19: Total accumulated depreciation | J19: =SUM(J16:J18) -> -141423904 | K19: =SUM(K16:K18) -> -12940294 | L19: =SUM(L16:L18) -> 7637756 | M19: =SUM(M16:M18) -> -146726442
B20: Total capital assets being depreciated, net | J20: =SUM(J14+J19) -> 257999620 | K20: =SUM(K14+K19) -> 12349438 | L20: =SUM(L14+L19) -> -1154676 | M20: =SUM(M14+M19) -> 269194382
B21: Total governmental activities capital assets, net | J21: =SUM(J9+J14+J19) -> 321841492 | K21: =SUM(K9+K14+K19) -> 44608755 | L21: =SUM(L9+L14+L19) -> -19869251 | M21: =SUM(M9+M14+M19) -> 346580996 | N21: =SUM(N7:N19) -> 346580996
A24: Business-type Activities
B25: Capital assets, not being depreciated:
B26: Land | J26: 3692923 | M26: =SUM(J26:L26) -> 3692923 | N26: =M26 -> 3692923
B27: Construction in progress | J27: 2785867 | K27: 5887449 | L27: -2061658 | M27: =SUM(J27:L27) -> 6611658 | N27: =M27 -> 6611658
C28: Total capital assets not being depreciated | J28: =SUM(J26:J27) -> 6478790 | K28: =SUM(K26:K27) -> 5887449 | L28: =SUM(L26:L27) -> -2061658 | M28: =SUM(J28:L28) -> 10304581
B29: Capital assets, being depreciated:
B30: Electric system and buildings | J30: 101579366 | K30: 1897620 | M30: =SUM(J30:L30) -> 103476986
B31: Gas distributions system and buildings | J31: 30876900 | K31: 1520794 | M31: =SUM(J31:L31) -> 32397694
B32: Sewer system and buildings | J32: 136662164 | K32: 2151452 | M32: =SUM(J32:L32) -> 138813616
B33: Sanitation and buildings | J33: 8606787 | K33: 73203 | M33: =SUM(J33:L33) -> 8679990
B34: Civic center buildings and equipment | J34: 19296686 | K34: 16748 | L34: -31231 | M34: =SUM(J34:L34) -> 19282203
B35: Machinery and equipment | J35: 8725765 | K35: 422152 | L35: 29764 | M35: =SUM(J35:L35) -> 9177681
D36: Total capital assets being depreciated | J36: =SUM(J30:J35) -> 305747668 | K36: =SUM(K30:K35) -> 6081969 | L36: =SUM(L30:L35) -> -1467 | M36: =SUM(M30:M35) -> 311828170
B37: Less accumulated depreciation for:
B38: Electric system and buildings | J38: -70748837 | K38: -2287891 | M38: =SUM(J38:L38) -> -73036728 | N38: =M30+M38 -> 30440258
B39: Gas distributions system and buildings | J39: -15511551 | K39: -1110591 | M39: =SUM(J39:L39) -> -16622142 | N39: =M31+M39 -> 15775552
B40: Sewer system and buildings | J40: -57940466 | K40: -3301011 | M40: =SUM(J40:L40) -> -61241477 | N40: =M32+M40 -> 77572139
B41: Sanitation | J41: -1378179 | K41: -225570 | M41: =SUM(J41:L41) -> -1603749 | N41: =M33+M41 -> 7076241
B42: Civic center buildings and equipment | J42: -8406035 | K42: -516590 | L42: 31231 | M42: =SUM(J42:L42) -> -8891394 | N42: =M34+M42 -> 10390809
B43: Machinery and equipment | J43: -5606722 | K43: -381689 | L43: -17623 | M43: =SUM(J43:L43) -> -6006034 | N43: =M35+M43 -> 3171647
D44: Total accumulated depreciation | J44: =SUM(J38:J43) -> -159591790 | K44: =SUM(K38:K43) -> -7823342 | L44: =SUM(L38:L43) -> 13608 | M44: =SUM(J44:L44) -> -167401524
B45: Total capital assets being depreciated, net | J45: =SUM(J36+J44) -> 146155878 | K45: =SUM(K36+K44) -> -1741373 | L45: =SUM(L36+L44) -> 12141 | M45: =SUM(M36+M44) -> 144426646
B46: Total business-type activities capital assets, net | J46: =SUM(J28+J36+J44) -> 152634668 | K46: =SUM(K28+K36+K44) -> 4146076 | L46: =SUM(L28+L36+L44) -> -2049517 | M46: =SUM(M28+M36+M44) -> 154731227 | N46: =SUM(N26:N43) -> 154731227

Sheet Union
D1: UNION PARISH POLICE JURY
D2: Capital Assets
D3: For the Year Ended December 31, 2015
I5: Beginning Balance | J5: Additions | K5: Deletions | L5: Ending Balance | M5: Cross Sectional
A6: Governmental-Type Activities:
A7: Capital assets, not being depreciated:
B8: Land | I8: 962888 | L8: =SUM(I8:K8) -> 962888 | M8: =L8 -> 962888
B9: Construction in progress | J9: 63135 | L9: =SUM(I9:K9) -> 63135 | M9: =L9 -> 63135
C10: Total assets not being depreciated | I10: =SUM(I8:I9) -> 962888 | J10: =SUM(J8:J9) -> 63135 | K10: =SUM(K8:K9) -> 0 | L10: =SUM(L8:L9) -> 1026023
A12: Capital assets, being depreciated:
B13: Land improvements | I13: 1793309 | L13: =SUM(I13:K13) -> 1793309
B14: Buildings and improvements | I14: 9285405 | L14: =SUM(I14:K14) -> 9285405
B15: Other improvements | I15: 1838085 | L15: =SUM(I15:K15) -> 1838085
B16: Fire, sewer and water system improvements | I16: 1885608 | L16: =SUM(I16:K16) -> 1885608
B17: Public works equipment | I17: 6771610 | J17: 521826 | K17: -1116490 | L17: =SUM(I17:K17) -> 6176946
B18: Vehicles | I18: 2131958 | J18: 60807 | K18: -349481 | L18: =SUM(I18:K18) -> 1843284
B19: Office furniture and equipment | I19: 699030 | L19: =SUM(I19:K19) -> 699030
B20: Library:
C21: Building and improvements | I21: 227302 | J21: 3000 | L21: =SUM(I21:K21) -> 230302
C22: Vehicle | I22: 105530 | L22: =SUM(I22:K22) -> 105530
C23: Office furniture and equipment | I23: 128378 | L23: =SUM(I23:K23) -> 128378
C24: Books and videos | I24: 740350 | J24: 104705 | K24: -28998 | L24: =SUM(I24:K24) -> 816057
C25: Total capital assets being depreciated | I25: =SUM(I13:I24) -> 25606565 | J25: =SUM(J13:J24) -> 690338 | K25: =SUM(K13:K24) -> -1494969 | L25: =SUM(L13:L24) -> 24801934
A27: Less accumulated depreciation for
B28: Land improvements | I28: 654700 | J28: 59347 | L28: =SUM(I28:K28) -> 714047 | M28: =L13-L28 -> 1079262
B29: Buildings and improvements | I29: 4263516 | J29: 230886 | L29: =SUM(I29:K29) -> 4494402 | M29: =L14-L29 -> 4791003
B30: Other improvements | I30: 69176 | J30: 81509 | L30: =SUM(I30:K30) -> 150685 | M30: =L15-L30 -> 1687400
B31: Fire, sewer and water system improvements | I31: 1222079 | J31: 101361 | L31: =SUM(I31:K31) -> 1323440 | M31: =L16-L31 -> 562168
B32: Public works equipment | I32: 4613560 | J32: 386437 | K32: -1104773 | L32: =SUM(I32:K32) -> 3895224 | M32: =L17-L32 -> 2281722
B33: Vehicles | I33: 1870934 | J33: 99732 | K33: -349481 | L33: =SUM(I33:K33) -> 1621185 | M33: =L18-L33 -> 222099
B34: Office furniture and equipment | I34: 670968 | J34: 12316 | L34: =SUM(I34:K34) -> 683284 | M34: =L19-L34 -> 15746
B35: Library:
C36: Building and improvements | I36: 190759 | J36: 4302 | L36: =SUM(I36:K36) -> 195061 | M36: =L21-L36 -> 35241
C37: Vehicle | I37: 63318 | J37: 10553 | L37: =SUM(I37:K37) -> 73871 | M37: =L22-L37 -> 31659
C38: Office furniture and equipment | I38: 128378 | L38: =SUM(I38:K38) -> 128378 | M38: =L23-L38 -> 0
C39: Books and videos | I39: 594175 | J39: 60245 | K39: -28998 | L39: =SUM(I39:K39) -> 625422 | M39: =L24-L39 -> 190635
C40: Total accumulated depreciation | I40: =SUM(I28:I39) -> 14341563 | J40: =SUM(J28:J39) -> 1046688 | K40: =SUM(K28:K39) -> -1483252 | L40: =SUM(L28:L39) -> 13904999
A42: Total Capital Assets being depreciated, net | I42: =I25-I40 -> 11265002 | J42: =J25-J40 -> -356350 | K42: =K25-K40 -> -11717 | L42: =L25-L40 -> 10896935
A43: Total capital assets, net | I43: =I10+I42 -> 12227890 | J43: =J10+J42 -> -293215 | K43: =K10+K42 -> -11717 | L43: =L10+L42 -> 11922958 | M43: =SUM(M8:M41) -> 11922958

Sheet Vermillion
D1: VERMILLION PARISH POLICE JURY
D2: Capital Assets
D3: For the Year Ended December 31, 2015
I5: Balance 01/01/15 | J5: Increases | K5: Decreases | L5: Balance 12/31/15 | M5: Cross Sectional
A6: Governmental activities
A7: Capital assets, not being depreciated:
B8: Police Jury:
B9: Land | I9: 2327396 | L9: =SUM(I9:K9) -> 2327396 | M9: =L9 -> 2327396
B10: Construction in progress | I10: 2956638 | J10: 4149108 | K10: -5399014 | L10: =SUM(I10:K10) -> 1706732 | M10: =L10 -> 1706732
C11: Total assets not being depreciated | I11: =SUM(I9:I10) -> 5284034 | J11: =SUM(J9:J10) -> 4149108 | K11: =SUM(K9:K10) -> -5399014 | L11: =SUM(L9:L10) -> 4034128
A13: Capital assets, being depreciated:
B14: Police Jury:
C15: Buildings and improvements | I15: 19748344 | J15: 4574782 | L15: =SUM(I15:K15) -> 24323126
C16: Furniture and equipment | I16: 21708077 | J16: 2247290 | K16: -130642 | L16: =SUM(I16:K16) -> 23824725
B17: Infrastructure:
C18: Road surfaces | I18: 135593526 | J18: 623248 | L18: =SUM(I18:K18) -> 136216774
C19: Bridges and drainage improvements | I19: 17138010 | J19: 171369 | L19: =SUM(I19:K19) -> 17309379
C20: Total capital assets being depreciated | I20: =SUM(I15:I19) -> 194187957 | J20: =SUM(J15:J19) -> 7616689 | K20: =SUM(K15:K19) -> -130642 | L20: =SUM(L15:L19) -> 201674004
A22: Less accumulated depreciation for
B23: Police Jury:
C24: Building improvements | I24: 10710224 | J24: 458121 | L24: =SUM(I24:K24) -> 11168345 | M24: =L15-L24 -> 13154781
C25: Furniture and equipment | I25: 17170731 | J25: 934214 | K25: -130642 | L25: =SUM(I25:K25) -> 17974303 | M25: =L16-L25 -> 5850422
B26: Infrastructure:
C27: Road surfaces | I27: 85200915 | J27: 2464759 | L27: =SUM(I27:K27) -> 87665674 | M27: =L18-L27 -> 48551100
C28: Bridges and drainage improvements | I28: 4585735 | J28: 398121 | L28: =SUM(I28:K28) -> 4983856 | M28: =L19-L28 -> 12325523
C29: Total accumulated depreciation | I29: =SUM(I24:I28) -> 117667605 | J29: =SUM(J24:J28) -> 4255215 | K29: =SUM(K24:K28) -> -130642 | L29: =SUM(L24:L28) -> 121792178
A31: Total Capital Assets being depreciated, net | I31: =I20-I29 -> 76520352 | J31: =J20-J29 -> 3361474 | K31: =K20-K29 -> 0 | L31: =L20-L29 -> 79881826
A32: Governmental activities capital assets, net | I32: =I11+I31 -> 81804386 | J32: =J11+J31 -> 7510582 | K32: =K11+K31 -> -5399014 | L32: =L11+L31 -> 83915954 | M32: =SUM(M9:M30) -> 83915954

Sheet Vernon
B1: VERNON PARISH POLICE JURY
B2: Capital Assets
B3: For the Year Ended December 31, 2015
A5: Primary Government - Governmental Activities:
C6: Land | D6: Construction in Progress | E6: Buildings and improvements | F6: Machinery and Equipment | G6: Infrastructure | H6: Library Book Collections | I6: Total
A7: Beginning balance | C7: 1695977 | D7: 7715076 | E7: 12270421 | F7: 21988811 | G7: 52860094 | H7: 2133564 | I7: =SUM(C7:H7) -> 98663943
B8: Additions | C8: 25000 | E8: 15993895 | F8: 1097371 | G8: 7843603 | H8: 216564 | I8: =SUM(C8:H8) -> 25176433
B9: Deletions | D9: -7715076 | E9: -7715075 | F9: -584267 | G9: -116000 | I9: =SUM(C9:H9) -> -16130418
A10: Ending balance | C10: =SUM(C7:C9) -> 1720977 | D10: =SUM(D7:D9) -> 0 | E10: =SUM(E7:E9) -> 20549241 | F10: =SUM(F7:F9) -> 22501915 | G10: =SUM(G7:G9) -> 60587697 | H10: =SUM(H7:H9) -> 2350128 | I10: =SUM(C10:H10) -> 107709958
A12: Less accumulated depreciation | C12: 0 | E12: -6388656 | F12: -14127958 | G12: -26997265 | H12: -1746760 | I12: =SUM(C12:H12) -> -49260639
A14: Capital assets, net | C14: =SUM(C10+C12) -> 1720977 | D14: =SUM(D10+D12) -> 0 | E14: =SUM(E10+E12) -> 14160585 | F14: =SUM(F10+F12) -> 8373957 | G14: =SUM(G10+G12) -> 33590432 | H14: =SUM(H10+H12) -> 603368 | I14: =SUM(I12,I10) -> 58449319 | J14: =SUM(J7:J13) -> 0
A16: Cross sectional | C16: =C10 -> 1720977 | D16: =D10 -> 0 | E16: =E10+E12 -> 14160585 | F16: =F10+F12 -> 8373957 | G16: =G10+G12 -> 33590432 | H16: =H10+H12 -> 603368 | I16: =SUM(I10+I12) -> 58449319

Sheet Washington
D1: WEBSTER PARISH POLICE JURY
D2: Capital Assets
D3: For the Year Ended December 31, 2015
I5: Balance 12/31/14 | J5: Increases | K5: Decreases | L5: Balance 12/31/15 | M5: Cross Sectional
A6: Governmental Activities:
A7: Capital assets, not being depreciated:
B8: Land | I8: 2535169 | J8: 774 | K8: -22202 | L8: =SUM(I8:K8) -> 2513741 | M8: =L8 -> 2513741
B9: Construction in progress | I9: 458085 | J9: 607052 | K9: -630983 | L9: =SUM(I9:K9) -> 434154 | M9: =L9 -> 434154
C10: Total | I10: =SUM(I8:I9) -> 2993254 | J10: =SUM(J8:J9) -> 607826 | K10: =SUM(K8:K9) -> -653185 | L10: =SUM(L8:L9) -> 2947895
A12: Other capital assets
B13: Buildings | I13: 10782212 | J13: 587732 | L13: =SUM(I13:K13) -> 11369944
B14: Equipment | I14: 6704502 | J14: 170273 | K14: -549962 | L14: =SUM(I14:K14) -> 6324813
B15: Books | I15: 1391013 | L15: =SUM(I15:K15) -> 1391013
B16: Asphalt roads | I16: 20989059 | L16: =SUM(I16:K16) -> 20989059
B17: 3-shot roads | I17: 7152416 | J17: 952528 | K17: -83593 | L17: =SUM(I17:K17) -> 8021351
B18: Bridges and culverts | I18: 23204994 | L18: =SUM(I18:K18) -> 23204994
C19: Total | I19: =SUM(I13:I18) -> 70224196 | J19: =SUM(J13:J18) -> 1710533 | K19: =SUM(K13:K18) -> -633555 | L19: =SUM(L13:L18) -> 71301174
A21: Less accumulated depreciation for
B22: Buildings | I22: -4668775 | J22: -278280 | L22: =SUM(I22:K22) -> -4947055 | M22: =L13+L22 -> 6422889
B23: Equipment | I23: -5653156 | J23: -219862 | K23: 549962 | L23: =SUM(I23:K23) -> -5323056 | M23: =L14+L23 -> 1001757
B24: Books | I24: -1390859 | J24: -154 | L24: =SUM(I24:K24) -> -1391013 | M24: =L15+L24 -> 0
B25: Asphalt roads | I25: -13852737 | J25: -1399271 | L25: =SUM(I25:K25) -> -15252008 | M25: =L16+L25 -> 5737051
B26: 3-shot roads | I26: -2651431 | J26: -149738 | K26: 83593 | L26: =SUM(I26:K26) -> -2717576 | M26: =L17+L26 -> 5303775
B27: Bridges and culverts | I27: -5900210 | J27: -427847 | L27: =SUM(I27:K27) -> -6328057 | M27: =L18+L27 -> 16876937
C28: Total accumulated depreciation | I28: =SUM(I22:I27) -> -34117168 | J28: =SUM(J22:J27) -> -2475152 | K28: =SUM(K22:K27) -> 633555 | L28: =SUM(L22:L27) -> -35958765
A30: Total Capital Assets being depreciated | I30: =I19+I28 -> 36107028 | J30: =J19+J28 -> -764619 | K30: =K19+K28 -> 0 | L30: =L19+L28 -> 35342409
A31: Governmental activities capital assets, net | I31: =I10+I30 -> 39100282 | J31: =J10+J30 -> -156793 | K31: =K10+K30 -> -653185 | L31: =L10+L30 -> 38290304 | M31: =SUM(M8:M29) -> 38290304
I34: Balance 12/31/14 | J34: Increases | K34: Decreases | L34: Balance 12/31/15 | M34: Cross Sectional
A35: Business-type Activities:
B37: Property, plant & equipment | I37: 1140 | J37: 1271 | L37: =SUM(I37:K37) -> 2411
B38: Less accumulated depreciation | I38: -475 | J38: -397 | L38: =SUM(I38:K38) -> -872
C39: Totals | I39: =SUM(I37:I38) -> 665 | J39: =SUM(J37:J38) -> 874 | K39: =SUM(K37:K38) -> 0 | L39: =SUM(L37:L38) -> 1539 | M39: =SUM(L37+L38) -> 1539

Sheet Webster
D1: WEBSTER PARISH POLICE JURY
D2: Capital Assets
D3: For the Year Ended December 31, 2015
I5: Beginning Balance | J5: Increases | K5: Decreases | L5: Balance at Ending | M5: Cross Sectional
A6: Governmental Activities:
A7: Capital assets, not being depreciated:
B8: Land | I8: 1212782 | J8: 60000 | L8: =SUM(I8:K8) -> 1272782 | M8: =L8 -> 1272782
B9: Construction in progress | I9: 93735 | J9: 447150 | K9: -93735 | L9: =SUM(I9:K9) -> 447150 | M9: =L9 -> 447150
C10: Total | I10: =SUM(I8:I9) -> 1306517 | J10: =SUM(J8:J9) -> 507150 | K10: =SUM(K8:K9) -> -93735 | L10: =SUM(L8:L9) -> 1719932
A12: Capital assets, being depreciated:
B13: Buildings and improvements | I13: 12931087 | J13: 102668 | L13: =SUM(I13:K13) -> 13033755
B14: Infrastructure | I14: 2458750 | J14: 257080 | L14: =SUM(I14:K14) -> 2715830
B15: Furniture, equipment and vehicles | I15: 5697267 | J15: 567495 | K15: -50860 | L15: =SUM(I15:K15) -> 6213902
B16: Library books and information materials | I16: 1544153 | J16: 344591 | K16: -420903 | L16: =SUM(I16:K16) -> 1467841
