Workbook

Sheet Acadia
D1: Acadia Combined Balance Sheet
D2: Issued: December 31, 2014
K4: General Fund | L4: Parish Road Fund | M4: Sales Tax Fund | N4: 1% Sales Tax District No. 2 Fund | O4: Other Governmental Funds | P4: Total Governmental Funds
A5: Assets:
B6: Cash | K6: 540140 | L6: 1236744 | M6: 2071316 | N6: 402027 | O6: 4721780 | P6: =SUM(K6:O6) -> 8972007
B7: Investments | K7: 146420 | L7: 12735 | M7: 4012797 | N7: 137096 | O7: 3587521 | P7: =SUM(K7:O7) -> 7896569
B8: Tax Receivable | K8: 205441 | L8: 125026 | O8: 166701 | P8: =SUM(K8:O8) -> 497168
B9: Special assessments receivable | O9: 18188 | P9: =SUM(K9:O9) -> 18188
B10: Other receivables | K10: 53983 | O10: 2221 | P10: =SUM(K10:O10) -> 56204
B11: Due from other governmental entities, net of allowance | P11: =SUM(K11:O11) -> 0
C12: for doubtful accounts | K12: 1976300 | L12: 1115492 | M12: 596161 | N12: 169936 | O12: 1503096 | P12: =SUM(K12:O12) -> 5360985
B13: Due from other funds | K13: 92143 | P13: =SUM(K13:O13) -> 92143
B14: Due from component units | K14: 20249 | P14: =SUM(K14:O14) -> 20249
E16: Total assets: | K16: =SUM(K6:K14) -> 3034676 | L16: =SUM(L6:L14) -> 2489997 | M16: =SUM(M6:M14) -> 6680274 | N16: =SUM(N6:N14) -> 709059 | O16: =SUM(O6:O14) -> 9999507 | P16: =SUM(P6:P14) -> 22913513
A18: LIABILITIES AND FUND BALANCES
B19: Liabilities:
C20: Accounts payable | K20: 296256 | L20: 30127 | M20: 363174 | N20: 7842 | O20: 174085 | P20: =SUM(K20:O20) -> 871484
C21: Retainage payable | M21: 7879 | P21: =SUM(K21:O21) -> 7879
C22: Accrued liabilities and other payables | K22: 509448 | L22: 41776 | O22: 55702 | P22: =SUM(K22:O22) -> 606926
C23: Unearned revenue | L23: 45000 | P23: =SUM(K23:O23) -> 45000
C24: Due to other funds | L24: 45977 | M24: 30914 | O24: 15252 | P24: =SUM(K24:O24) -> 92143
E26: Total liabilities: | K26: =SUM(K20:K24) -> 805704 | L26: =SUM(L20:L24) -> 162880 | M26: =SUM(M20:M24) -> 401967 | N26: =SUM(N20:N24) -> 7842 | O26: =SUM(O20:O24) -> 245039 | P26: =SUM(P20:P24) -> 1623432
A28: DEFERRED INFLOWS OF RESOURCES
C29: Unavailable revenue- special assessments | O29: 18188 | P29: =SUM(K29:O29) -> 18188
E31: Total deferred inflows of resources | K31: =SUM(K29:K29) -> 0 | L31: =SUM(L29:L29) -> 0 | M31: =SUM(M29:M29) -> 0 | N31: =SUM(N29:N29) -> 0 | O31: =SUM(O29:O29) -> 18188 | P31: =SUM(P29:P29) -> 18188
B33: Fund Balances
C34: Restricted for:
D35: Property tax dedication | K35: 523200 | L35: 2327117 | P35: 2850317
D36: Sales tax dedication | M36: 6278307 | N36: 701217 | P36: 6979524
D37: Debt retirement | O37: 1657465 | P37: 1657465
D38: Mosquito control | O38: 1920316 | P38: 1920316
D39: Cooperative extension operation and maintenance | O39: 1537845 | P39: 1537845
C40: Committed to:
D41: Road maintenance and construction | O41: 978527 | P41: 978527
D42: Health unit operation and maintenance | O42: 1581065 | P42: 1581065
D43: Rice Arena operation and maintenance | O43: 840917 | P43: 840917
C44: Assigned:
D45: Capital projects | O45: 267910 | P45: =SUM(K45:O45) -> 267910
D46: Economic development | O46: 632064 | P46: =SUM(K46:O46) -> 632064
D47: Airport | O47: 276955 | P47: =SUM(K47:O47) -> 276955
D48: Other | O48: 43216 | P48: =SUM(K48:O48) -> 43216
C49: Unassigned | K49: 1705772 | P49: =SUM(K49:O49) -> 1705772
E51: Total fund balances: | K51: =SUM(K34:K49) -> 2228972 | L51: =SUM(L34:L49) -> 2327117 | M51: =SUM(M34:M49) -> 6278307 | N51: =SUM(N34:N49) -> 701217 | O51: =SUM(O34:O49) -> 9736280 | P51: =SUM(P34:P49) -> 21271893
E53: Total liabilities and fund balances: | K53: =SUM(K51,K26,K31) -> 3034676 | L53: =SUM(L51,L26,L31) -> 2489997 | M53: =SUM(M51,M26,M31) -> 6680274 | N53: =SUM(N51,N26,N31) -> 709059 | O53: =SUM(O51,O26,O31) -> 9999507 | P53: =SUM(P51,P26,P31) -> 22913513

Sheet Allen
D1: Allen Combined Balance Sheet
D2: Issued: December 31, 2014
K5: General | L5: Solid Waste Fund | M5: Hospital Retrofit Fund | N5: Compact Fund | O5: Parish Road Fund | P5: Road District #2 Mtc. Fund | Q5: Road District #3 Mtc. Fund | R5: Nonmajor Governmental Funds | S5: Total Governmental Funds
A6: Assets:
B7: Cash | K7: 240932 | L7: 547105 | M7: 187 | N7: 294855 | O7: 11995 | P7: 832228 | Q7: 1631244 | R7: 1305121 | S7: =SUM(K7:R7) -> 4863667
B8: Receivables | K8: 234039 | N8: 98228 | P8: 602271 | Q8: 534089 | R8: 1330446 | S8: =SUM(K8:R8) -> 2799073
B9: Due from other governments | K9: 281570 | L9: 131093 | O9: 32096 | R9: 142310 | S9: =SUM(K9:R9) -> 587069
B10: Inventory | R10: 45179 | S10: =SUM(K10:R10) -> 45179
B11: Due from other funds | K11: 41502 | P11: 224 | Q11: 626 | R11: 20107 | S11: =SUM(K11:R11) -> 62459
B12: Prepaid assets | N12: 2989 | S12: =SUM(K12:R12) -> 2989
E14: Total Assets: | K14: =SUM(K7:K12) -> 798043 | L14: =SUM(L7:L12) -> 678198 | M14: =SUM(M7:M12) -> 187 | N14: =SUM(N7:N12) -> 396072 | O14: =SUM(O7:O12) -> 44091 | P14: =SUM(P7:P12) -> 1434723 | Q14: =SUM(Q7:Q12) -> 2165959 | R14: =SUM(R7:R12) -> 2843163 | S14: =SUM(S7:S12) -> 8360436
A16: LIABILITIES AND FUND BALANCES
B17: Liabilities:
C18: Accounts payable | K18: 76705 | L18: 131565 | N18: 11830 | O18: 52130 | P18: 35637 | Q18: 34224 | R18: 284546 | S18: =SUM(K18:R18) -> 626637
C19: Unearned revenue | R19: 48703 | S19: =SUM(K19:R19) -> 48703
C20: Due to other funds | K20: 4923 | N20: 3715 | O20: 24829 | R20: 28992 | S20: =SUM(K20:R20) -> 62459
E22: Total liabilities: | K22: =SUM(K18:K20) -> 81628 | L22: =SUM(L18:L20) -> 131565 | M22: =SUM(M18:M20) -> 0 | N22: =SUM(N18:N20) -> 15545 | O22: =SUM(O18:O20) -> 76959 | P22: =SUM(P18:P20) -> 35637 | Q22: =SUM(Q18:Q20) -> 34224 | R22: =SUM(R18:R20) -> 362241 | S22: =SUM(S18:S20) -> 737799
A24: DEFERRED INFLOWS OF RESROUCES
C25: Unavailable revenue | K25: 20863 | P25: 51888 | Q25: 36961 | R25: 143440 | S25: =SUM(K25:R25) -> 253152
E27: Total deferred inflows of resources | K27: =SUM(K25:K25) -> 20863 | L27: =SUM(L25:L25) -> 0 | M27: =SUM(M25:M25) -> 0 | N27: =SUM(N25:N25) -> 0 | O27: =SUM(O25:O25) -> 0 | P27: =SUM(P25:P25) -> 51888 | Q27: =SUM(Q25:Q25) -> 36961 | R27: =SUM(R25:R25) -> 143440 | S27: =SUM(S25:S25) -> 253152
B29: Fund Balances
C30: Nonspendable - prepaids | N30: 2989 | S30: =SUM(K30:R30) -> 2989
C31: Nonspendable- inventroy | R31: 45179 | S31: =SUM(K31:R31) -> 45179
C32: Restricted: | S32: =SUM(K32:R32) -> 0
D33: Judicial | R33: 707217 | S33: =SUM(K33:R33) -> 707217
D34: Other general government | N34: 377538 | S34: =SUM(K34:R34) -> 377538
D35: Public safety | R35: 874 | S35: =SUM(K35:R35) -> 874
D36: Public works | O36: 32096 | P36: 1347198 | Q36: 2094774 | R36: 1404273 | S36: =SUM(K36:R36) -> 4878341
D37: Economic development | R37: 29735 | S37: =SUM(K37:R37) -> 29735
D38: Sanitation | L38: 546633 | S38: =SUM(K38:R38) -> 546633
D39: Capital projects | M39: 187 | R39: 120650 | S39: =SUM(K39:R39) -> 120837
D40: Debt service | R40: 256 | S40: =SUM(K40:R40) -> 256
C41: Committed: | S41: =SUM(K41:R41) -> 0
D42: Other general government | R42: 1142 | S42: =SUM(K42:R42) -> 1142
C43: Assigned: | S43: =SUM(K43:R43) -> 0
D44: Other general government | R44: 20767 | S44: =SUM(K44:R44) -> 20767
D45: Public works | R45: 8713 | S45: =SUM(K45:R45) -> 8713
C46: Negative unassigned | O46: -64964 | R46: -1324 | S46: =SUM(K46:R46) -> -66288
C47: Unassigned | K47: 695552 | S47: =SUM(K47:R47) -> 695552
E49: Total fund balance: | K49: =SUM(K30:K47) -> 695552 | L49: =SUM(L30:L47) -> 546633 | M49: =SUM(M30:M47) -> 187 | N49: =SUM(N30:N47) -> 380527 | O49: =SUM(O30:O47) -> -32868 | P49: =SUM(P30:P47) -> 1347198 | Q49: =SUM(Q30:Q47) -> 2094774 | R49: =SUM(R30:R47) -> 2337482 | S49: =SUM(S30:S47) -> 7369485
E51: Total liabilities, deffered inflows of resources and fund balances: | K51: =K49+K27+K22 -> 798043 | L51: =L49+L27+L22 -> 678198 | M51: =M49+M27+M22 -> 187 | N51: =N49+N27+N22 -> 396072 | O51: =O49+O27+O22 -> 44091 | P51: =P49+P27+P22 -> 1434723 | Q51: =Q49+Q27+Q22 -> 2165959 | R51: =R49+R27+R22 -> 2843163 | S51: =S49+S27+S22 -> 8360436

Sheet Assumption
D1: Assumption Combined Balance Sheet
D2: Issued: December 31, 2014
K4: General Fund | L4: Sales and Use Tax | M4: Solid Waste | N4: Section Eight Housing | O4: Other Governmental Funds | P4: Total
A5: Assets:
B6: Cash and cash equivalents | K6: 868790 | L6: 198524 | M6: 129671 | N6: 13058 | O6: 1614714 | P6: =SUM(K6:O6) -> 2824757
B7: Investments | K7: 6190618 | L7: 1663083 | M7: 1065776 | O7: 9204014 | P7: =SUM(K7:O7) -> 18123491
B8: Receivables | K8: 1286511 | L8: 300205 | M8: 192531 | N8: 2782 | O8: 3987441 | P8: =SUM(K8:O8) -> 5769470
B9: Due from other funds | K9: 4395 | O9: 55062 | P9: =SUM(K9:O9) -> 59457
E11: Total assets: | K11: =SUM(K6:K9) -> 8350314 | L11: =SUM(L6:L9) -> 2161812 | M11: =SUM(M6:M9) -> 1387978 | N11: =SUM(N6:N9) -> 15840 | O11: =SUM(O6:O9) -> 14861231 | P11: =SUM(P6:P9) -> 26777175
A13: LIABILITIES AND FUND BALANCES
B14: Liabilities:
C15: Accounts payable | K15: 43061 | L15: 17906 | M15: 224 | N15: -1476 | O15: 494562 | P15: =SUM(K15:O15) -> 554277
C16: Salaries payable | K16: 16882 | L16: 20227 | O16: 92776 | P16: =SUM(K16:O16) -> 129885
C17: Due to other funds | K17: 49146 | L17: 3097 | O17: 7214 | P17: =SUM(K17:O17) -> 59457
C18: Other liabilities | K18: 217186 | L18: 11144 | N18: 2144 | O18: 192160 | P18: =SUM(K18:O18) -> 422634
E20: Total liabilities: | K20: =SUM(K15:K18) -> 326275 | L20: =SUM(L15:L18) -> 52374 | M20: =SUM(M15:M18) -> 224 | N20: =SUM(N15:N18) -> 668 | O20: =SUM(O15:O18) -> 786712 | P20: =SUM(P15:P18) -> 1166253
B22: Fund Balances
C23: Restricted | L23: 2109438 | N23: 6673 | O23: 13173048 | P23: =SUM(K23:O23) -> 15289159
C24: Assigned | K24: 36555 | M24: 1387754 | N24: 8499 | O24: 901471 | P24: =SUM(K24:O24) -> 2334279
C25: Unassigned | K25: 7987484 | P25: =SUM(K25:O25) -> 7987484
E27: Total fund balance: | K27: =SUM(K23:K25) -> 8024039 | L27: =SUM(L23:L25) -> 2109438 | M27: =SUM(M23:M25) -> 1387754 | N27: =SUM(N23:N25) -> 15172 | O27: =SUM(O23:O25) -> 14074519 | P27: =SUM(P23:P25) -> 25610922
E29: Total liabilities and fund balances: | K29: =SUM(K27,K20) -> 8350314 | L29: =SUM(L27,L20) -> 2161812 | M29: =SUM(M27,M20) -> 1387978 | N29: =SUM(N27,N20) -> 15840 | O29: =SUM(O27,O20) -> 14861231 | P29: =SUM(P27,P20) -> 26777175

Sheet Avoyelles
D1: Avoyelles Combined Balance Sheet
D2: Issued: December 31, 2014
K4: General | L4: Road & Bridge | M4: Solid Waste | N4: Drainage | O4: Health Unit | P4: Library | Q4: Section 8 | R4: Brudd Construction LCDBG | S4: Other Governmental Funds | T4: Total Governmental Funds
A5: Assets:
B6: Cash and interest-bearing deposits | K6: 858064 | L6: 1095076 | M6: 3825801 | N6: 463470 | O6: 1699451 | P6: 983701 | Q6: 207348 | R6: 33 | S6: 310915 | T6: =SUM(K6:S6) -> 9443859
B7: Receivables | K7: 54360 | Q7: 1299 | S7: 774 | T7: =SUM(K7:S7) -> 56433
B8: Due from other governmental units | K8: 366301 | L8: 182785 | M8: 274162 | N8: 418315 | O8: 479260 | P8: 740903 | R8: 149799 | S8: 20369 | T8: =SUM(K8:S8) -> 2631894
B9: Due from other funds | S9: 2153 | T9: =SUM(K9:S9) -> 2153
B10: Prepaid items | K10: 38135 | L10: 29523 | M10: 22694 | N10: 15137 | O10: 8637 | P10: 29863 | Q10: 1109 | S10: 3622 | T10: =SUM(K10:S10) -> 148720
E12: Total Assets: | K12: =SUM(K6:K10) -> 1316860 | L12: =SUM(L6:L10) -> 1307384 | M12: =SUM(M6:M10) -> 4122657 | N12: =SUM(N6:N10) -> 896922 | O12: =SUM(O6:O10) -> 2187348 | P12: =SUM(P6:P10) -> 1754467 | Q12: =SUM(Q6:Q10) -> 209756 | R12: =SUM(R6:R10) -> 149832 | ... T12: =SUM(T6:T10) -> 12283059
A14: LIABILITIES, DEFERRED INFLOWS OF RESOURCES AND FUND BALANCES
B16: Liabilities:
C17: Accounts, salaries, and other payables | K17: 122570 | L17: 57110 | M17: 259132 | N17: 29119 | O17: 23273 | P17: 53739 | Q17: 1638 | R17: 149799 | S17: 16022 | T17: =SUM(K17:S17) -> 712402
C18: Unearned revenue | Q18: 36260 | T18: =SUM(K18:S18) -> 36260
C19: Due to other funds | K19: 2153 | T19: =SUM(K19:S19) -> 2153
E21: Total liabilities: | K21: =SUM(K17:K19) -> 124723 | L21: =SUM(L17:L19) -> 57110 | M21: =SUM(M17:M19) -> 259132 | N21: =SUM(N17:N20) -> 29119 | O21: =SUM(O17:O19) -> 23273 | P21: =SUM(P17:P19) -> 53739 | Q21: =SUM(Q17:Q19) -> 37898 | R21: =SUM(R17:R19) -> 149799 | S21: =SUM(S17:S19) -> 16022 | T21: =SUM(T17:T19) -> 750815
A23: DEFERRED INFLOWS OF RESOURCES
C24: Unavailable revenue | K24: 78528 | N24: 62869 | O24: 71834 | P24: 111343 | T24: =SUM(K24:S24) -> 324574
B26: Fund Balances
C27: Nonspendable | K27: 38135 | L27: 29523 | M27: 22694 | N27: 15137 | O27: 8637 | P27: 29863 | Q27: 1109 | S27: 3622 | T27: =SUM(K27:S27) -> 148720
C28: Restricted | T28: =SUM(K28:S28) -> 0
D29: Public safety | S29: 24786 | T29: =SUM(K29:S29) -> 24786
D30: Public works | L30: 1220751 | M30: 3840831 | N30: 789797 | R30: 33 | S30: 74395 | T30: =SUM(K30:S30) -> 5925807
D31: Health and welfare | O31: 2083604 | Q31: 170749 | T31: =SUM(K31:S31) -> 2254353
D32: Culture and recreation | P32: 1559522 | T32: =SUM(K32:S32) -> 1559522
D33: Economic development | S33: 222948 | T33: =SUM(K33:S33) -> 222948
C34: Unassigned (deficit) | K34: 1075474 | S34: -3940 | T34: =SUM(K34:S34) -> 1071534
E36: Total fund balance: | K36: =SUM(K27:K35) -> 1113609 | L36: =SUM(L27:L34) -> 1250274 | M36: =SUM(M27:M34) -> 3863525 | N36: =SUM(N27:N34) -> 804934 | O36: =SUM(O27:O34) -> 2092241 | P36: =SUM(P27:P34) -> 1589385 | Q36: =SUM(Q27:Q34) -> 171858 | R36: =SUM(R27:R34) -> 33 | S36: =SUM(S27:S34) -> 321811 | T36: =SUM(T27:T34) -> 11207670
E38: Total liabilities and fund balances: | K38: =SUM(K36+K24+K21) -> 1316860 | L38: =SUM(L36+L24+L21) -> 1307384 | M38: =SUM(M36+M24+M21) -> 4122657 | N38: =SUM(N36+N24+N21) -> 896922 | O38: =SUM(O36+O24+O21) -> 2187348 | P38: =SUM(P36+P24+P21) -> 1754467 | Q38: =SUM(Q36+Q24+Q21) -> 209756 | R38: =SUM(R36+R24+R21) -> 149832 | ... T38: =SUM(T36+T24+T21) -> 12283059

Sheet Beauregard
D1: Beauregard Combined Balance Sheet
D2: Issued: December 31, 2014
K4: General Fund | L4: Parishwide Road Special Revenue | M4: Road District No. 6 Special Revenue | N4: Sales Tax District No. 1 Special Revenue | O4: Health Unit Special Revenue | P4: Criminal Court Special Revenue | Q4: South Beau. Rec. Dist. No. 2 Special Revenue | R4: South Beau. Rec. Dist. No. 2 Capital Projects | S4: Nonmajor Governmental Funds | T4: Total Governmental Funds
A5: Assets:
B6: Equity in pooled cash | K6: 558156 | L6: 964630 | M6: 789100 | N6: 3863482 | O6: 2026435 | P6: 24397 | Q6: 868165 | R6: 227293 | S6: 8224114 | T6: =SUM(K6:S6) -> 17545772
B7: Receivables | K7: 1052346 | L7: 44561 | M7: 955138 | N7: 753419 | O7: 562752 | P7: 51243 | Q7: 534125 | S7: 3020561 | T7: =SUM(K7:S7) -> 6974145
B8: Interfund receivable | K8: 23950 | L8: 11404 | R8: 75510 | T8: =SUM(K8:S8) -> 110864
B9: Inventory | M9: 31579 | S9: 172931 | T9: =SUM(K9:S9) -> 204510
E11: Total assets: | K11: =SUM(K6:K9) -> 1634452 | L11: =SUM(L6:L9) -> 1020595 | M11: =SUM(M6:M9) -> 1775817 | N11: =SUM(N6:N9) -> 4616901 | O11: =SUM(O6:O9) -> 2589187 | P11: =SUM(P6:P9) -> 75640 | Q11: =SUM(Q6:Q9) -> 1402290 | R11: =SUM(R6:R9) -> 302803 | ... T11: =SUM(T6:T9) -> 24835291
A13: LIABILITIES
B14: Liabilities:
C15: Accounts payable | K15: 147115 | L15: 9960 | M15: 106431 | N15: 125706 | O15: 20011 | P15: 24755 | Q15: 19134 | R15: 169925 | S15: 225745 | T15: =SUM(K15:S15) -> 848782
C16: Payroll liabilities | K16: 179556 | T16: =SUM(K16:S16) -> 179556
C17: Interfund payable | S17: 110864 | T17: =SUM(K17:S17) -> 110864
E19: Total liabilities: | K19: =SUM(K15:K17) -> 326671 | L19: =SUM(L15:L17) -> 9960 | M19: =SUM(M15:M17) -> 106431 | N19: =SUM(N15:N17) -> 125706 | O19: =SUM(O15:O17) -> 20011 | P19: =SUM(P15:P17) -> 24755 | Q19: =SUM(Q15:Q17) -> 19134 | R19: =SUM(R15:R17) -> 169925 | ... T19: =SUM(T15:T17) -> 1139202
A21: DEFERRED INFLOWS OF RESOURCES
B22: Unavailable revenue | K22: 142282 | M22: 18968 | O22: 17879 | Q22: 6802 | S22: 96186 | T22: =SUM(K22:S22) -> 282117
C23: Total deferred inflows of resources | K23: =K22 -> 142282 | L23: =L22 -> 0 | M23: =M22 -> 18968 | N23: =N22 -> 0 | O23: =O22 -> 17879 | P23: =P22 -> 0 | Q23: =Q22 -> 6802 | R23: =R22 -> 0 | ... T23: =T22 -> 282117
B25: Fund Balances:
C26: Nonspendable - inventory | M26: 31579 | S26: 172931 | T26: =SUM(K26:S26) -> 204510
C27: Restricted:
D28: Purchases of equipment | L28: 306908 | T28: =SUM(K28:S28) -> 306908
D29: Public safety | S29: 1932609 | T29: =SUM(K29:S29) -> 1932609
D30: Public works | L30: 703727 | M30: 1618839 | S30: 4220434 | T30: =SUM(K30:S30) -> 6543000
D31: Health and welfare | O31: 2551297 | T31: =SUM(K31:S31) -> 2551297
D32: Culture and recreation | S32: 536904 | T32: =SUM(K32:S32) -> 536904
D33: Sanitation | N33: 4491195 | T33: =SUM(K33:S33) -> 4491195
D34: Other general government | S34: 151475 | T34: =SUM(K34:S34) -> 151475
D35: Capital projects | S35: 3820546 | T35: =SUM(K35:S35) -> 3820546
D36: Debt service | S36: 149912 | T36: =SUM(K36:S36) -> 149912
C37: Unassigned | K37: 1165499 | P37: 50885 | Q37: 1376354 | R37: 132878 | T37: =SUM(K37:S37) -> 2725616
E39: Total fund balance: | K39: =SUM(K26:K37) -> 1165499 | L39: =SUM(L26:L37) -> 1010635 | M39: =SUM(M26:M37) -> 1650418 | N39: =SUM(N26:N37) -> 4491195 | O39: =SUM(O26:O37) -> 2551297 | P39: =SUM(P26:P37) -> 50885 | Q39: =SUM(Q26:Q37) -> 1376354 | R39: =SUM(R26:R37) -> 132878 | ... T39: =SUM(T26:T37) -> 23413972
E41: Total liabilities, deferred inflows of resources, and fund balances: | K41: =K39+K22+K19 -> 1634452 | L41: =L39+L22+L19 -> 1020595 | M41: =M39+M22+M19 -> 1775817 | N41: =N39+N22+N19 -> 4616901 | O41: =O39+O22+O19 -> 2589187 | P41: =P39+P22+P19 -> 75640 | Q41: =Q39+Q22+Q19 -> 1402290 | R41: =R39+R22+R19 -> 302803 | ... T41: =T39+T22+T19 -> 24835291

Sheet Bienville
D1: Bienville Combined Balance Sheet
D2: Issued: December 31, 2014
K4: General Fund | L4: Road Maintenance | M4: Solid Waste | N4: Debt Service Fund | O4: Other Governmental Funds | P4: Total
A5: Assets:
B6: Cash and cash equivalents | K6: 4705355 | L6: 7519393 | M6: 3666093 | N6: 1027431 | O6: 248630 | P6: =SUM(K6:O6) -> 17166902
B7: Receivables | K7: 1810762 | L7: 1957619 | M7: 367810 | N7: 1131815 | O7: 6442 | P7: =SUM(K7:O7) -> 5274448
E9: Total assets: | K9: =SUM(K6:K7) -> 6516117 | L9: =SUM(L6:L7) -> 9477012 | M9: =SUM(M6:M7) -> 4033903 | N9: =SUM(N6:N7) -> 2159246 | O9: =SUM(O6:O7) -> 255072 | P9: =SUM(P6:P7) -> 22441350
A11: LIABILITIES AND FUND BALANCES
B12: Liabilities:
C13: Accounts payable | K13: 93421 | L13: 21716 | M13: 95478 | P13: =SUM(K13:O13) -> 210615
C14: Salaries and related payable | K14: 7411 | L14: 22841 | P14: =SUM(K14:O14) -> 30252
C15: Deferred revenues | K15: 70000 | P15: =SUM(K15:O15) -> 70000
E17: Total liabilities: | K17: =SUM(K13:K15) -> 170832 | L17: =SUM(L13:L15) -> 44557 | M17: =SUM(M13:M15) -> 95478 | N17: =SUM(N13:N15) -> 0 | O17: =SUM(O13:O15) -> 0 | P17: =SUM(P13:P15) -> 310867
B19: Fund Balances
C20: Non spendable | O20: 16 | P20: =SUM(K20:O20) -> 16
C21: Restricted | P21: =SUM(K21:O21) -> 0
D22: Other general government | O22: 146447 | P22: =SUM(K22:O22) -> 146447
D23: Public works | L23: 9432455 | M23: 3938425 | O23: 14464 | P23: =SUM(K23:O23) -> 13385344
D24: Health and welfare | O24: 57744 | P24: =SUM(K24:O24) -> 57744
D25: Economic development | O25: 34025 | P25: =SUM(K25:O25) -> 34025
C26: Assigned | N26: 2159246 | O26: 2376 | P26: =SUM(K26:O26) -> 2161622
C27: Unassigned | K27: 6345285 | P27: =SUM(K27:O27) -> 6345285
E29: Total fund balance: | K29: =SUM(K21:K27) -> 6345285 | L29: =SUM(L21:L27) -> 9432455 | M29: =SUM(M21:M27) -> 3938425 | N29: =SUM(N21:N27) -> 2159246 | O29: =SUM(O20:O27) -> 255072 | P29: =SUM(P20:P27) -> 22130483
E31: Total liabilities and fund balances: | K31: =SUM(K29,K17) -> 6516117 | L31: =SUM(L29,L17) -> 9477012 | M31: =SUM(M29,M17) -> 4033903 | N31: =SUM(N29,N17) -> 2159246 | O31: =SUM(O29,O17) -> 255072 | P31: =SUM(P29,P17) -> 22441350

Sheet Bossier
D1: Bossier Combined Balance Sheet
D2: Issued: December 31, 2014
K5: General | L5: HIghway | M5: Library | N5: Capital Improvement | O5: LCDA Sewer Construction | P5: Corrections | Q5: LCDA Public Improvements | R5: Other Governmental Funds | S5: Total Governmental Funds
A6: Assets:
B7: Cash and cash equivalents | K7: 4175695 | L7: 5369423 | M7: 8807171 | N7: 8191172 | O7: 66569 | P7: 2403514 | Q7: 1542077 | R7: 9948521 | S7: =SUM(K7:R7) -> 40504142
B8: Investments | K8: 170335 | S8: =SUM(K8:R8) -> 170335
B9: Receivables | K9: 2966234 | L9: 4354103 | M9: 7367030 | N9: 1053726 | P9: 2971772 | Q9: 3324947 | R9: 1036700 | S9: =SUM(K9:R9) -> 23074512
B10: Restricted cash | M10: 21875 | O10: 3037776 | R10: 1819576 | S10: =SUM(K10:R10) -> 4879227
B11: Due from other funds | K11: 69371 | R11: 6373 | S11: =SUM(K11:R11) -> 75744
B12: Advance to waterworks/sewer district | O12: 8243332 | S12: =SUM(K12:R12) -> 8243332
E14: Total Assets: | K14: =SUM(K7:K12) -> 7381635 | L14: =SUM(L7:L12) -> 9723526 | M14: =SUM(M7:M12) -> 16196076 | N14: =SUM(N7:N12) -> 9244898 | O14: =SUM(O7:O12) -> 11347677 | P14: =SUM(P7:P12) -> 5375286 | Q14: =SUM(Q7:Q12) -> 4867024 | R14: =SUM(R7:R12) -> 12811170 | S14: =SUM(S7:S12) -> 76947292
A16: LIABILITIES, DEFERRED INFLOWS OF RESOURCES, AND FUND BALANCES
B17: Liabilities:
C18: Accounts payable | K18: 353048 | L18: 526769 | M18: 384043 | N18: 56514 | P18: 248149 | Q18: 3324947 | R18: 223062 | S18: =SUM(K18:R18) -> 5116532
C19: Due to other funds | L19: 55782 | N19: 11300 | R19: 8662 | S19: =SUM(K19:R19) -> 75744
E21: Total liabilities: | K21: =SUM(K18:K19) -> 353048 | L21: =SUM(L18:L19) -> 582551 | M21: =SUM(M18:M19) -> 384043 | N21: =SUM(N18:N19) -> 67814 | O21: =SUM(O18:O19) -> 0 | P21: =SUM(P18:P19) -> 248149 | Q21: =SUM(Q18:Q19) -> 3324947 | R21: =SUM(R18:R19) -> 231724 | S21: =SUM(S18:S19) -> 5192276
A23: DEFERRED INFLOWS OF RESROUCES
B24: Unavailable revenue
C25: Property taxes | K25: 1948025 | L25: 1966068 | M25: 7404640 | P25: 2934461 | R25: 811884 | S25: =SUM(K25:R25) -> 15065078
C26: Other | K26: 73369 | L26: 450013 | M26: 5117 | N26: 16695 | P26: 4747 | Q26: 113041 | R26: 6963 | S26: =SUM(K26:R26) -> 669945
E28: Total deferred inflows of resources | K28: =SUM(K24:K26) -> 2021394 | L28: =SUM(L24:L26) -> 2416081 | M28: =SUM(M24:M26) -> 7409757 | N28: =SUM(N24:N26) -> 16695 | O28: =SUM(O24:O26) -> 0 | P28: =SUM(P24:P26) -> 2939208 | Q28: =SUM(Q24:Q26) -> 113041 | R28: =SUM(R24:R26) -> 818847 | S28: =SUM(S24:S26) -> 15735023
B30: Fund Balances
C31: Nonspendable | O31: 8243332 | S31: =SUM(K31:R31) -> 8243332
C32: Restricted | M32: 8009313 | N32: 9022454 | O32: 3104345 | P32: 748940 | R32: 6720965 | S32: =SUM(K32:R32) -> 27606017
C33: Assigned | K33: 3087683 | L33: 6724894 | M33: 392963 | N33: 137935 | P33: 1438989 | Q33: 1429036 | R33: 5039634 | S33: =SUM(K33:R33) -> 18251134
C34: Unassigned | K34: 1919510 | S34: =SUM(K34:R34) -> 1919510
E36: Total fund balance: | K36: =SUM(K31:K34) -> 5007193 | L36: =SUM(L31:L34) -> 6724894 | M36: =SUM(M31:M34) -> 8402276 | N36: =SUM(N31:N34) -> 9160389 | O36: =SUM(O31:O34) -> 11347677 | P36: =SUM(P31:P34) -> 2187929 | Q36: =SUM(Q31:Q34) -> 1429036 | R36: =SUM(R31:R34) -> 11760599 | S36: =SUM(S31:S34) -> 56019993
E38: Total liabilities, deffered inflows of resources and fund balances: | K38: =SUM(K21+K28+K36) -> 7381635 | L38: =SUM(L21+L28+L36) -> 9723526 | M38: =SUM(M21+M28+M36) -> 16196076 | N38: =SUM(N21+N28+N36) -> 9244898 | O38: =SUM(O21+O28+O36) -> 11347677 | P38: =SUM(P21+P28+P36) -> 5375286 | Q38: =SUM(Q21+Q28+Q36) -> 4867024 | R38: =SUM(R21+R28+R36) -> 12811170 | S38: =SUM(S21+S28+S36) -> 76947292

Sheet Caddo
D1: Caddo Combined Balance Sheet
D2: Issued: December 31, 2014
K4: General Fund | L4: Shreve Memorial Library Fund | M4: Detention Facilities Fund | N4: Solid Waste Disposal Fund | O4: Public Works Fund | P4: Head Start Fund | Q4: Biomedical Fund | R4: Capital Outlay Fund | S4: Criminal Justice Fund | T4: Other Governmental Funds | U4: Total Governmental Funds
A5: Assets:
B6: Cash and cash equivalents | K6: 4050798 | L6: 4652337 | M6: 74242 | N6: 1836315 | O6: 1161308 | R6: 1278346 | T6: 2423536 | U6: =SUM(K6:T6) -> 15476882
B7: Investments | K7: 42798639 | M7: 790823 | N7: 19398481 | O7: 12267698 | R7: 13509976 | T7: 25597710 | U7: =SUM(K7:T7) -> 114363327
B8: Receivables, net:
C9: Ad valorem taxes | K9: 6259610 | L9: 14004529 | M9: 7984497 | O9: 6242739 | Q9: 2647217 | S9: 4861016 | T9: 13798567 | U9: =SUM(K9:T9) -> 55798175
C10: Paving assessments | O10: 210777 | U10: =SUM(K10:T10) -> 210777
C11: Other | K11: 64493 | M11: 208 | N11: 10948 | T11: 215445 | U11: =SUM(K11:T11) -> 291094
C12: Accrued interest | K12: 133264 | M12: 2442 | N12: 60412 | O12: 38201 | R12: 42055 | T12: 79722 | U12: =SUM(K12:T12) -> 356096
B13: Due from other funds | K13: 1191129 | L13: 223421 | M13: 110701 | N13: 530502 | O13: 432651 | R13: 455926 | T13: 1284047 | U13: =SUM(K13:T13) -> 4228377
B14: Due from other governments | K14: 158300 | L14: 259508 | M14: 181778 | N14: 554903 | O14: 1615801 | Q14: 49200 | S14: 89329 | T14: 596025 | U14: =SUM(K14:T14) -> 3504844
B15: Inventories | O15: 97808 | U15: =SUM(K15:T15) -> 97808
B16: Other assets | L16: 116149 | U16: =SUM(K16:T16) -> 116149
E18: Total assets: | K18: =SUM(K6:K16) -> 54656233 | L18: =SUM(L6:L16) -> 19255944 | M18: =SUM(M6:M16) -> 9144691 | N18: =SUM(N6:N16) -> 22391561 | O18: =SUM(O6:O16) -> 22066983 | P18: =SUM(P6:P16) -> 0 | Q18: =SUM(Q6:Q16) -> 2696417 | R18: =SUM(R6:R16) -> 15286303 | ... U18: =SUM(U6:U16) -> 194443529
A20: LIABILITIES AND FUND BALANCES
B21: Liabilities:
C22: Accounts payable | K22: 117176 | L22: 223421 | M22: 167064 | N22: 282200 | O22: 556181 | Q22: 230614 | R22: 632951 | T22: 626010 | U22: =SUM(K22:T22) -> 2835617
C23: Accrued liabilities | K23: 154394 | L23: 155575 | M23: 29305 | N23: 54604 | O23: 153622 | T23: 371076 | U23: =SUM(K23:T23) -> 918576
C24: Retainage payable | R24: 353334 | U24: =SUM(K24:T24) -> 353334
C25: Due to other funds | Q25: 1539057 | S25: 2813006 | T25: 223421 | U25: =SUM(K25:T25) -> 4575484
C26: Unearned revenue | K26: 35478 | U26: =SUM(K26:T26) -> 35478
C27: Due to component units | M27: 520956 | U27: =SUM(K27:T27) -> 520956
C28: Due to other governments | K28: 14769 | N28: 3202 | O28: 12845 | S28: 78154 | T28: 9176 | U28: =SUM(K28:T28) -> 118146
E30: Total liabilities: | K30: =SUM(K22:K28) -> 321817 | L30: =SUM(L22:L28) -> 378996 | M30: =SUM(M22:M28) -> 717325 | N30: =SUM(N22:N28) -> 340006 | O30: =SUM(O22:O28) -> 722648 | P30: =SUM(P22:P28) -> 0 | Q30: =SUM(Q22:Q28) -> 1769671 | R30: =SUM(R22:R28) -> 986285 | ... U30: =SUM(U22:U28) -> 9357591
A32: DEFERRED INFLOWS OF RESOURCES
B33: Unavailable revenue - property taxes | K33: 66472 | L33: 123269 | M33: 76073 | O33: 52029 | Q33: 15517 | S33: 21548 | T33: 119337 | U33: =SUM(K33:T33) -> 474245
B34: Unavailable revenue - special assessments | O34: 106570 | U34: =SUM(K34:T34) -> 106570
E36: Total deferred inflows: | K36: =SUM(K33:K34) -> 66472 | L36: =SUM(L33:L34) -> 123269 | M36: =SUM(M33:M34) -> 76073 | N36: =SUM(N33:N34) -> 0 | O36: =SUM(O33:O34) -> 158599 | P36: =SUM(P33:P34) -> 0 | Q36: =SUM(Q33:Q34) -> 15517 | R36: =SUM(R33:R34) -> 0 | ... U36: =SUM(U33:U34) -> 580815
B38: Fund Balances:
C39: Nonspendable:
D40: Prepaid expenses | L40: 116149 | U40: =SUM(K40:T40) -> 116149
C41: Restricted for:
D42: Criminal justice | M42: 8121127 | S42: 1999865 | T42: 3624174 | U42: =SUM(K42:T42) -> 13745166
D43: Health and welfare | T43: 4552822 | U43: =SUM(K43:T43) -> 4552822
D44: Highways, streets and drainage | O44: 19345933 | U44: =SUM(K44:T44) -> 19345933
D45: Building facilities | T45: 7739454 | U45: =SUM(K45:T45) -> 7739454
D46: Sanitation | N46: 21744403 | U46: =SUM(K46:T46) -> 21744403
D47: Culture and recreation | L47: 18637530 | T47: 3065257 | U47: =SUM(K47:T47) -> 21702787
D48: Economic development | Q48: 509783 | U48: =SUM(K48:T48) -> 509783
D49: Debt service | T49: 2961531 | U49: =SUM(K49:T49) -> 2961531
D50: Capital projects | R50: 14300018 | T50: 8820578 | U50: =SUM(K50:T50) -> 23120596
C51: Committed to:
D52: Contingencies | K52: 37337820 | U52: =SUM(K52:T52) -> 37337820
D53: Economic development | T53: 987522 | U53: =SUM(K53:T53) -> 987522
D54: Subsequent year's expenditures | K54: 465823 | M54: 230166 | N54: 307152 | O54: 1839803 | Q54: 401446 | S54: 37772 | T54: 1563606 | U54: =SUM(K54:T54) -> 4845768
C55: Assigned to:
D56: Special services | T56: 9331088 | U56: =SUM(K56:T56) -> 9331088
D57: Future claims | K57: 600000 | U57: =SUM(K57:T57) -> 600000
C58: Unassigned | K58: 15864301 | U58: =SUM(K58:T58) -> 15864301
E60: Total fund balance: | K60: =SUM(K39:K58) -> 54267944 | L60: =SUM(L39:L58) -> 18753679 | M60: =SUM(M39:M58) -> 8351293 | N60: =SUM(N39:N58) -> 22051555 | O60: =SUM(O39:O58) -> 21185736 | P60: =SUM(P39:P58) -> 0 | Q60: =SUM(Q39:Q58) -> 911229 | R60: =SUM(R39:R58) -> 14300018 | ... U60: =SUM(U39:U58) -> 184505123
E62: Total liabilities. Deferred inflows, and fund balances: | K62: =K60+K36+K30 -> 54656233 | L62: =L60+L36+L30 -> 19255944 | M62: =M60+M36+M30 -> 9144691 | N62: =N60+N36+N30 -> 22391561 | O62: =O60+O36+O30 -> 22066983 | P62: =P60+P36+P30 -> 0 | Q62: =Q60+Q36+Q30 -> 2696417 | R62: =R60+R36+R30 -> 15286303 | ... U62: =U60+U36+U30 -> 194443529

Sheet Calcasieu
D1: Calcasieu Combined Balance Sheet
D2: Issued: December 31, 2014
K4: General Fund | L4: Public Works Operating Fund | M4: Office of Juvenille Justice Services Fund | N4: Calcasieu Parish Library Fund | O4: Road Capital Improvement Fund | P4: Nonmajor Governmental Funds | Q4: Total Governmental Funds
A5: Assets:
B6: Cash and Cash Equivalents | K6: 13551446 | L6: 6565108 | M6: 1654498 | N6: 1265610 | O6: 24111044 | P6: 9718103 | Q6: =SUM(K6:P6) -> 56865809
B7: Investments | K7: 47934238 | L7: 24075466 | M7: 6045826 | N7: 4625424 | O7: 88207759 | P7: 32237731 | Q7: =SUM(K7:P7) -> 203126444
B8: Receivable (net of allowance for uncollectibles):
C9: Property taxes | K9: 11445770 | M9: 5978869 | N9: 9886992 | O9: 5955341 | P9: 13393692 | Q9: =SUM(K9:P9) -> 46660664
C10: Sales taxes | L10: 883373 | O10: 1664193 | P10: 611253 | Q10: =SUM(K10:P10) -> 3158819
C11: Franchise taxes | K11: 306693 | Q11: =SUM(K11:P11) -> 306693
B12: Interest receivable | K12: 87255 | L12: 40812 | M12: 11252 | N12: 9545 | O12: 149696 | P12: 56962 | Q12: =SUM(K12:P12) -> 355522
B13: Other receivables | K13: 3963032 | M13: 25357 | N13: 29 | P13: 93232 | Q13: 4081650
B14: Intergovernmental receivable | K14: 252131 | L14: 4460 | M14: 223705 | O14: 322310 | P14: 1194029 | Q14: =SUM(K14:P14) -> 1996635
B15: Due from other funds | K15: 547460 | M15: 1505 | N15: 4456 | P15: 169048 | Q15: =SUM(K15:P15) -> 722469
B16: Due from component units | K16: 26195 | P16: 930 | Q16: =SUM(K16:P16) -> 27125
B17: Loans receivable | K17: 33189 | Q17: =SUM(K17:P17) -> 33189
B18: Prepaid items | M18: 30746 | P18: 35170 | Q18: =SUM(K18:P18) -> 65916
B19: Inventory | L19: 747312 | P19: 428089 | Q19: =SUM(K19:P19) -> 1175401
E21: Total assets: | K21: =SUM(K6:K19) -> 78147409 | L21: =SUM(L6:L19) -> 32316531 | M21: =SUM(M6:M19) -> 13971758 | N21: =SUM(N6:N19) -> 15792056 | O21: =SUM(O6:O19) -> 120410343 | P21: =SUM(P6:P19) -> 57938239 | Q21: =SUM(Q6:Q19) -> 318576336
A23: LIABILITIES AND FUND BALANCES
B24: Liabilities:
C25: Accounts payable | K25: 1530460 | L25: 1066469 | M25: 132234 | N25: 104967 | O25: 1416409 | P25: 1285041 | Q25: =SUM(K25:P25) -> 5535580
C26: Accrued liabilities | K26: 297380 | L26: 235919 | M26: 109926 | N26: 140146 | P26: 116324 | Q26: =SUM(K26:P26) -> 899695
C27: Intergovernmental payable | P27: 292884 | Q27: =SUM(K27:P27) -> 292884
C28: Due to other funds | K28: 175076 | P28: 563212 | Q28: =SUM(K28:P28) -> 738288
C29: Due to component units | K29: 26439 | L29: 308 | P29: 29834 | Q29: =SUM(K29:P29) -> 56581
C30: Unearned revenue | K30: 2292 | M30: 29765 | P30: 1054250 | Q30: =SUM(K30:P30) -> 1086307
C31: Retainage payable | K31: 34899 | L31: 26341 | N31: 4456 | O31: 175177 | P31: 255072 | Q31: =SUM(K31:P31) -> 495945
C32: Other liabilities | K32: 92400 | L32: 86320 | P32: 38598 | Q32: =SUM(K32:P32) -> 217318
C33: Enterprize zone rebate liability | L33: 154500 | Q33: 154500
E35: Total liabilities: | K35: =SUM(K25:K32) -> 2158946 | L35: =SUM(L25:L33) -> 1569857 | M35: =SUM(M25:M33) -> 271925 | N35: =SUM(N25:N32) -> 249569 | O35: =SUM(O25:O32) -> 1591586 | P35: =SUM(P25:P32) -> 3635215 | Q35: =SUM(Q25:Q33) -> 9477098
A37: DEFERRED INFLOWS OF RESOURCES
C38: Property taxes levied for the next fiscal year | K38: 11531978 | M38: 6037189 | N38: 9982988 | O38: 6023191 | P38: 13520745 | Q38: 47096091
C39: Unavailable revenue | M39: 8532 | P39: 17026 | Q39: =SUM(K39:P39) -> 25558
E41: Total deferred inflows of resources | K41: =SUM(K38:K39) -> 11531978 | L41: =SUM(L38:L39) -> 0 | M41: =SUM(M38:M39) -> 6045721 | N41: =SUM(N38:N39) -> 9982988 | O41: =SUM(O38:O39) -> 6023191 | P41: =SUM(P38:P39) -> 13537771 | Q41: =SUM(Q38:Q39) -> 47121649
B43: Fund Balances
C44: Nonspendable:
D45: Prepaid items | M45: 30746 | P45: 35170 | Q45: =SUM(K45:P45) -> 65916
D46: Inventories | L46: 747312 | P46: 428089 | Q46: =SUM(K46:P46) -> 1175401
D47: Loans receivable | K47: 25764 | Q47: =SUM(K47:P47) -> 25764
C48: Restricted:
D49: Agriculture and community services | K49: 250780 | Q49: =SUM(K49:P49) -> 250780
D50: Public works operations | L50: 29999362 | Q50: =SUM(K50:P50) -> 29999362
D51: Library purposes | M51: 7623366 | Q51: =SUM(K51:P51) -> 7623366
D52: Roads and infrastructure | N52: 5559499 | O52: 112795556 | Q52: =SUM(K52:P52) -> 118355055
D53: Other restrictions | P53: 26239214 | Q53: =SUM(K53:P53) -> 26239214
C54: Assigned:
D55: Animal services | K55: 63127 | Q55: =SUM(K55:P55) -> 63127
D56: Parks operations | K56: 750649 | Q56: =SUM(K56:P56) -> 750649
D57: Training center operations | K57: 459859 | Q57: =SUM(K57:P57) -> 459859
D58: Future capital needs | K58: 14552880 | P58: 14062780 | Q58: =SUM(K58:P58) -> 28615660
D59: Matching funds for capital grants | K59: 11163729 | Q59: =SUM(K59:P59) -> 11163729
D60: Major infrastructure | K60: 6175000 | Q60: =SUM(K60:P60) -> 6175000
D61: Cooperative endeavor agreements | K61: 1588968 | Q61: =SUM(K61:P61) -> 1588968
C62: Unassigned | K62: 29425729 | Q62: =SUM(K62:P62) -> 29425729
E64: Total fund balances: | K64: =SUM(K45:K62) -> 64456485 | L64: =SUM(L45:L62) -> 30746674 | M64: =SUM(M45:M62) -> 7654112 | N64: =SUM(N45:N62) -> 5559499 | O64: =SUM(O45:O62) -> 112795556 | P64: =SUM(P45:P62) -> 40765253 | Q64: =SUM(Q45:Q62) -> 261977579
E66: Total liabilities and fund balances: | K66: =SUM(K64,K35,K41) -> 78147409 | L66: =SUM(L64,L35,L41) -> 32316531 | M66: =SUM(M64,M35,M41) -> 13971758 | N66: =SUM(N64,N35,N41) -> 15792056 | O66: =SUM(O64,O35,O41) -> 120410333 | P66: =SUM(P64,P35,P41) -> 57938239 | Q66: =SUM(Q64,Q35,Q41) -> 318576326

Sheet Caldwell
D1: Caldwell Combined Balance Sheet
D2: Issued: December 31, 2014
K4: General Fund | L4: Road Maintenance | M4: Recreation | N4: Solid Waste | O4: Blacktop Road | P4: Bayou Dechere Resevoir | Q4: LCDBG | R4: Other Governmental Funds | S4: Total Governmental Funds
A5: Assets:
B6: Cash and Cash Equivalents | K6: 1128303 | L6: 392947 | M6: 695339 | N6: 2048365 | O6: 1975178 | P6: 115740 | Q6: 40 | R6: 1504656 | S6: =SUM(K6:R6) -> 7860568
B7: Investments | K7: 292218 | L7: 520897 | M7: 309967 | N7: 103678 | R7: 594637 | S7: =SUM(K7:R7) -> 1821397
B8: Due from other funds | K8: 2700 | L8: 25652 | R8: 36402 | S8: =SUM(K8:R8) -> 64754
E10: Total assets: | K10: =SUM(K6:K8) -> 1423221 | L10: =SUM(L6:L8) -> 939496 | M10: =SUM(M6:M8) -> 1005306 | N10: =SUM(N6:N8) -> 2152043 | O10: =SUM(O6:O8) -> 1975178 | P10: =SUM(P6:P8) -> 115740 | Q10: =SUM(Q6:Q8) -> 40 | R10: =SUM(R6:R8) -> 2135695 | S10: =SUM(S6:S8) -> 9746719
A12: LIABILITIES AND FUND BALANCES
B13: Liabilities:
C14: Accounts payable | K14: 80438 | L14: 20492 | M14: 19501 | N14: 44917 | O14: 3162 | R14: 37335 | S14: =SUM(K14:R14) -> 205845
C15: Saleries and related payables | K15: 15497 | L15: 13849 | M15: 1787 | R15: 7111 | S15: =SUM(K15:R15) -> 38244
C16: Due to other agencies | K16: 57698 | S16: =SUM(K16:R16) -> 57698
C17: Due to other funds | K17: 62054 | L17: 2700 | S17: =SUM(K17:R17) -> 64754
E19: Total liabilities: | K19: =SUM(K14:K17) -> 215687 | L19: =SUM(L14:L17) -> 37041 | M19: =SUM(M14:M17) -> 21288 | N19: =SUM(N14:N17) -> 44917 | O19: =SUM(O14:O17) -> 3162 | P19: =SUM(P14:P17) -> 0 | Q19: =SUM(Q14:Q17) -> 0 | R19: =SUM(R14:R17) -> 44446 | S19: =SUM(S14:S17) -> 366541
B21: Fund Balances
C22: Unassigned | K22: 1207534 | S22: =SUM(K22:P22) -> 1207534
C23: Restricted | L23: 902455 | M23: 984018 | N23: 2107126 | O23: 1972016 | P23: 115740 | Q23: 40 | R23: 2091249 | S23: =SUM(K23:R23) -> 8172644
E25: Total fund balances: | K25: =SUM(K22:K23) -> 1207534 | L25: =SUM(L22:L23) -> 902455 | M25: =SUM(M22:M23) -> 984018 | N25: =SUM(N22:N23) -> 2107126 | O25: =SUM(O22:O23) -> 1972016 | P25: =SUM(P22:P23) -> 115740 | Q25: =SUM(Q22:Q23) -> 40 | R25: =SUM(R22:R23) -> 2091249 | S25: =SUM(S22:S23) -> 9380178
E27: Total liabilities and fund balances: | K27: =SUM(K25+K19) -> 1423221 | L27: =SUM(L25+L19) -> 939496 | M27: =SUM(M25+M19) -> 1005306 | N27: =SUM(N25+N19) -> 2152043 | O27: =SUM(O25+O19) -> 1975178 | P27: =SUM(P25+P19) -> 115740 | Q27: =SUM(Q25+Q19) -> 40 | R27: =SUM(R25+R19) -> 2135695 | S27: =SUM(S25+S19) -> 9746719

Sheet Cameron
D1: Cameron Combined Balance Sheet
D2: Issued: December 31, 2014
K4: General Fund | L4: Road & Bridge Maintenance | M4: Long-Term Community Recovery | N4: Non-Major | O4: Total Governmental Funds
A5: Assets:
B6: Cash | K6: 11614255 | L6: 30849 | M6: 100 | N6: 16822104 | O6: =SUM(K6:N6) -> 28467308
B7: Receivables, net | K7: 7957122 | L7: 1862489 | M7: 1691825 | N7: 5103359 | O7: =SUM(K7:N7) -> 16614795
B8: Inventory, at cost | K8: 1793767 | L8: 28999 | O8: =SUM(K8:N8) -> 1822766
B9: Other | K9: 66729 | L9: 46475 | N9: 33506 | O9: 4081650
B10: Interfund receivables | K10: 2631117 | L10: 402547 | N10: 2742552 | O10: =SUM(K10:N10) -> 5776216
E12: Total assets: | K12: =SUM(K6:K10) -> 24062990 | L12: =SUM(L6:L10) -> 2371359 | M12: =SUM(M6:M10) -> 1691925 | N12: =SUM(N6:N10) -> 24701521 | O12: =SUM(O6:O10) -> 56762735
A14: LIABILITIES AND FUND BALANCES
B15: Liabilities:
C16: Accounts, salaries, and other payables | K16: 397951 | L16: 50177 | M16: 2367492 | N16: 1053795 | O16: =SUM(K16:N16) -> 3869415
C17: Due to other agencies | K17: 2623074 | O17: =SUM(K17:N17) -> 2623074
C18: Unearned revenue | K18: 7413 | M18: 9818 | O18: =SUM(K18:N18) -> 17231
C19: Interfund payables | K19: 3145100 | M19: 380933 | N19: 2250183 | O19: =SUM(K19:N19) -> 5776216
E21: Total liabilities: | K21: =SUM(K16:K19) -> 6173538 | L21: =SUM(L16:L19) -> 50177 | M21: =SUM(M16:M19) -> 2758243 | N21: =SUM(N16:N19) -> 3303978 | O21: =SUM(O16:O19) -> 12285936
A23: DEFERRED INFLOWS OF RESOURCES
E25: Total deferred inflows of resources | K25: =SUM(K24) -> 0 | L25: =SUM(L24) -> 0 | M25: =SUM(M24) -> 0 | N25: =SUM(N24) -> 0 | O25: =SUM(O24) -> 0
B27: Fund Balances
C28: Nonspendable:
D29: Inventories | K29: 1793767 | L29: 28999 | O29: =SUM(K29:N29) -> 1822766
D30: Prepaid expenses | K30: 66729 | L30: 46475 | N30: 33508 | O30: =SUM(K30:N30) -> 146712
C31: Restricted:
D32: Judicial | N32: 58817 | O32: =SUM(K32:N32) -> 58817
D33: Debt service | N33: 999067 | O33: =SUM(K33:N33) -> 999067
D34: Tourism development | N34: 39983 | O34: =SUM(K34:N34) -> 39983
C35: Commited to: | O35: =SUM(K35:N35) -> 0
D36: Infrastructure maintenance | L36: 2224889 | O36: =SUM(K36:N36) -> 2224889
D37: Culture and recreation | N37: 5560799 | O37: =SUM(K37:N37) -> 5560799
D38: Public safety | N38: 5114106 | O38: =SUM(K38:N38) -> 5114106
D39: Judicial | N39: 3509737 | O39: =SUM(K39:N39) -> 3509737
D40: Health and welfare | N40: 5585323 | O40: =SUM(K40:N40) -> 5585323
D41: Law enforcement building construction | N41: 208078 | O41: =SUM(K41:N41) -> 208078
D42: Library construction | N42: 42777 | O42: =SUM(K42:N42) -> 42777
D43: Administrative building construction | N43: 171986 | O43: =SUM(K43:N43) -> 171986
D44: Other capital projects | L44: 20819 | N44: -119317 | O44: =SUM(K44:N44) -> -98498
D45: Other purposes | K45: 130576 | O45: =SUM(K45:N45) -> 130576
C46: Assigned: | O46: =SUM(K46:N46) -> 0
D47: judicial | N47: 7483 | O47: =SUM(K47:N47) -> 7483
D48: Health and welfare | N48: 11002 | O48: =SUM(K48:N48) -> 11002
D49: Public safety | N49: 129246 | O49: =SUM(K49:N49) -> 129246
D50: Culture and recreation | N50: 44950 | O50: =SUM(K50:N50) -> 44950
D51: Othercapital projects | M51: -1066318 | O51: =SUM(K51:N51) -> -1066318
C52: Unassigned | K52: 15898380 | O52: =SUM(K52:N52) -> 15898380
E54: Total fund balances: | K54: =SUM(K29:K52) -> 17889452 | L54: =SUM(L29:L52) -> 2321182 | M54: =SUM(M29:M52) -> -1066318 | N54: =SUM(N29:N52) -> 21397545 | O54: =SUM(O29:O52) -> 40541861
E56: Total liabilities and fund balances: | K56: =SUM(K54,K21,K25) -> 24062990 | L56: =SUM(L54,L21,L25) -> 2371359 | M56: =SUM(M54,M21,M25) -> 1691925 | N56: =SUM(N54,N21,N25) -> 24701523 | O56: =SUM(O54,O21,O25) -> 52827797

Sheet Catahoula
D1: Catahoula Combined Balance Sheet
D2: Issued: December 31, 2014
K5: General | L5: Road and Bridge | M5: Hard Surfacing | N5: Sanitation | O5: Library | P5: Heatlh Unit | Q5: Other Governmental Funds | R5: Total Governmental Funds
A6: Assets:
B7: Cash and cash equivalents | K7: 629573 | L7: 114529 | M7: 375026 | N7: 433150 | O7: 284606 | P7: 352292 | Q7: 101420 | R7: =SUM(K7:Q7) -> 2290596
B8: Cash restricted for debt service | Q8: 26910 | R8: =SUM(K8:Q8) -> 26910
B9: Cash restricted for capital project | Q9: 293899 | R9: =SUM(K9:Q9) -> 293899
B10: Receivables | K10: 519222 | L10: 46606 | M10: 62020 | N10: 38762 | O10: 309409 | P10: 76875 | Q10: 63443 | R10: =SUM(K10:Q10) -> 1116337
B11: Other assets | K11: 32620 | L11: 16112 | M11: 24500 | P11: 2732 | Q11: 3617 | R11: =SUM(K11:Q11) -> 79581
E13: Total Assets: | K13: =SUM(K7:K11) -> 1181415 | L13: =SUM(L7:L11) -> 177247 | M13: =SUM(M7:M11) -> 461546 | N13: =SUM(N7:N11) -> 471912 | O13: =SUM(O7:O11) -> 594015 | P13: =SUM(P7:P11) -> 431899 | Q13: =SUM(Q7:Q11) -> 489289 | R13: =SUM(R7:R11) -> 3807323
A15: LIABILITIES, DEFERRED INFLOWS OF RESOURCES, AND FUND BALANCES
B16: Liabilities:
C17: Accounts payable | K17: 50383 | L17: 7667 | M17: 6412 | N17: 36962 | O17: 16867 | P17: 5531 | Q17: 5814 | R17: =SUM(K17:Q17) -> 129636
C18: Salaries and related payables | K18: 3126 | L18: 5837 | M18: 2983 | Q18: 3137 | R18: =SUM(K18:Q18) -> 15083
E20: Total liabilities: | K20: =SUM(K17:K18) -> 53509 | L20: =SUM(L17:L18) -> 13504 | M20: =SUM(M17:M18) -> 9395 | N20: =SUM(N17:N18) -> 36962 | O20: =SUM(O17:O18) -> 16867 | P20: =SUM(P17:P18) -> 5531 | Q20: =SUM(Q17:Q18) -> 8951 | R20: =SUM(R17:R18) -> 144719
A22: DEFERRED INFLOWS OF RESROUCES
B23: Ad valorem taxes and state revenue sharing - unavailable | K23: 59384 | O23: 43715 | P23: 10929 | Q23: 20284 | R23: =SUM(K23:Q23) -> 134312
E25: Total deferred inflows of resources | K25: =SUM(K23:K23) -> 59384 | L25: =SUM(L23:L23) -> 0 | M25: =SUM(M23:M23) -> 0 | N25: =SUM(N23:N23) -> 0 | O25: =SUM(O23:O23) -> 43715 | P25: =SUM(P23:P23) -> 10929 | Q25: =SUM(Q23:Q23) -> 20284 | R25: =SUM(R23:R23) -> 134312
B27: Fund Balances
C28: Restricted | L28: 163743 | M28: 452151 | N28: 434950 | O28: 533433 | P28: 415439 | Q28: 460054 | R28: =SUM(K28:Q28) -> 2459770
C29: Unassigned | K29: 1068522 | R29: =SUM(K29:Q29) -> 1068522
E31: Total fund balance: | K31: =SUM(K28:K29) -> 1068522 | L31: =SUM(L28:L29) -> 163743 | M31: =SUM(M28:M29) -> 452151 | N31: =SUM(N28:N29) -> 434950 | O31: =SUM(O28:O29) -> 533433 | P31: =SUM(P28:P29) -> 415439 | Q31: =SUM(Q28:Q29) -> 460054 | R31: =SUM(R28:R29) -> 3528292
E33: Total liabilities, deffered inflows of resources and fund balances: | K33: =K20+K25+K31 -> 1181415 | L33: =L20+L25+L31 -> 177247 | M33: =M20+M25+M31 -> 461546 | N33: =N20+N25+N31 -> 471912 | O33: =O20+O25+O31 -> 594015 | P33: =P20+P25+P31 -> 431899 | Q33: =Q20+Q25+Q31 -> 489289 | R33: =R20+R25+R31 -> 3807323

Sheet Claiborne
D1: Claiborne Combined Balance Sheet
D2: Issued: December 31, 2014
K5: General | L5: Parish Road | M5: Library Maintenance | N5: Sales Tax | O5: Criminal Court | P5: Section 8 | Q5: Other Governmental Funds | R5: Total Governmental Funds
A6: Assets:
B7: Cash and cash equivalents | K7: 3314766 | L7: 132318 | M7: 763700 | N7: 946574 | O7: 79956 | P7: 57110 | Q7: 974702 | R7: =SUM(K7:Q7) -> 6269126
B8: Investments | K8: 443112 | L8: 3040 | M8: 6249 | N8: 339032 | Q8: 5778 | R8: =SUM(K8:Q8) -> 797211
B9: Receivables | K9: 618190 | L9: 1008728 | M9: 709657 | N9: 74185 | Q9: 673745 | R9: =SUM(K9:Q9) -> 3084505
B10: Due from other funds | K10: 1094 | R10: =SUM(K10:Q10) -> 1094
B11: Due from other agencies | K11: 22416 | R11: =SUM(K11:Q11) -> 22416
B12: Deferred charges | K12: 107283 | R12: =SUM(K12:Q12) -> 107283
E14: Total Assets: | K14: =SUM(K7:K12) -> 4506861 | L14: =SUM(L7:L12) -> 1144086 | M14: =SUM(M7:M12) -> 1479606 | N14: =SUM(N7:N12) -> 1359791 | O14: =SUM(O7:O12) -> 79956 | P14: =SUM(P7:P12) -> 57110 | Q14: =SUM(Q7:Q12) -> 1654225 | R14: =SUM(R7:R12) -> 10281635
A16: LIABILITIES, DEFERRED INFLOWS OF RESOURCES, AND FUND BALANCES
B17: Liabilities:
C18: Accounts, salaries and other payables | K18: 224147 | L18: 98585 | M18: 16827 | N18: 55004 | O18: 25785 | P18: 300 | Q18: 26219 | R18: =SUM(K18:Q18) -> 446867
C19: Due to other funds | L19: 538 | M19: 456 | Q19: 100 | R19: =SUM(K19:Q19) -> 1094
C20: Due to other agencies | P20: 14025 | R20: =SUM(K20:Q20) -> 14025
E22: Total liabilities: | K22: =SUM(K18:K20) -> 224147 | L22: =SUM(L18:L20) -> 99123 | M22: =SUM(M18:M20) -> 17283 | N22: =SUM(N18:N20) -> 55004 | O22: =SUM(O18:O20) -> 25785 | P22: =SUM(P18:P20) -> 14325 | Q22: =SUM(Q18:Q20) -> 26319 | R22: =SUM(R18:R20) -> 461986
A24: DEFERRED INFLOWS OF RESROUCES
B25: Unavailable ad valorem tax revenue | K25: 54472 | L25: 104733 | M25: 68044 | P25: 15626 | Q25: 64421 | R25: =SUM(K25:Q25) -> 307296
E27: Total deferred inflows of resources | K27: =SUM(K25:K25) -> 54472 | L27: =SUM(L25:L25) -> 104733 | M27: =SUM(M25:M25) -> 68044 | N27: =SUM(N25:N25) -> 0 | O27: =SUM(O25:O25) -> 0 | P27: =SUM(P25:P25) -> 15626 | Q27: =SUM(Q25:Q25) -> 64421 | R27: =SUM(R25:R25) -> 307296
B29: Fund Balances
C30: Restricted fund balances | K30: 485567 | L30: 940230 | M30: 1394279 | N30: 1304787 | O30: 54171 | P30: 27159 | Q30: 1563485 | R30: =SUM(K30:Q30) -> 5769678
C31: Unassigned fund balances | K31: 3742675 | R31: =SUM(K31:Q31) -> 3742675
E33: Total fund balance: | K33: =SUM(K30:K31) -> 4228242 | L33: =SUM(L30:L31) -> 940230 | M33: =SUM(M30:M31) -> 1394279 | N33: =SUM(N30:N31) -> 1304787 | O33: =SUM(O30:O31) -> 54171 | P33: =SUM(P30:P31) -> 27159 | Q33: =SUM(Q30:Q31) -> 1563485 | R33: =SUM(R30:R31) -> 9512353
E35: Total liabilities, deffered inflows of resources and fund balances: | K35: =SUM(K22+K27+K33) -> 4506861 | L35: =SUM(L22+L27+L33) -> 1144086 | M35: =SUM(M22+M27+M33) -> 1479606 | N35: =SUM(N22+N27+N33) -> 1359791 | O35: =SUM(O22+O27+O33) -> 79956 | P35: =SUM(P22+P27+P33) -> 57110 | Q35: =SUM(Q22+Q27+Q33) -> 1654225 | R35: =SUM(R22+R27+R33) -> 10281635

Sheet Concordia
D1: Concordia Combined Balance Sheet
D2: Issued: December 31, 2014
M4: Major Funds
K5: General Fund | L5: Drainage Fund | M5: Sales Tax Fund | N5: Road Debt Service Fund | O5: Public Health Fund | P5: Other Governmental Funds | Q5: Total Governmental Funds
A6: Assets:
B7: Cash and cash equivalents | K7: 3075673 | L7: 1018003 | M7: 1748390 | O7: 441379 | P7: 750518 | Q7: =SUM(K7:P7) -> 7033963
B8: Cash and cash equivalents - restricted | N8: 2563431 | Q8: =SUM(K8:P8) -> 2563431
B9: Accounts recievable | K9: 47869 | L9: 12215 | O9: 35363 | P9: 120495 | Q9: =SUM(K9:P9) -> 215942
B10: Ad valorem taxes receivable, net | K10: 250020 | L10: 1101391 | O10: 199355 | Q10: =SUM(K10:P10) -> 1550766
B11: Sales and use taxes recievable | M11: 257934 | Q11: =SUM(K11:P11) -> 257934
B12: Severancetaxes receivable | K12: 143713 | Q12: =SUM(K12:P12) -> 143713
B13: State revenue sharing receivable | Q13: =SUM(K13:P13) -> 0
B14: Due from other funds | K14: 12550 | L14: 12000 | N14: 80000 | P14: 74200 | Q14: =SUM(K14:P14) -> 178750
E16: Total Assets: | K16: =SUM(K7:K14) -> 3529825 | L16: =SUM(L7:L14) -> 2143609 | M16: =SUM(M7:M14) -> 2006324 | N16: =SUM(N7:N14) -> 2643431 | O16: =SUM(O7:O14) -> 676097 | P16: =SUM(P7:P14) -> 945213 | Q16: =SUM(Q7:Q14) -> 11944499
A18: LIABILITIES
C19: Accounts payable | K19: 69082 | M19: 21581 | O19: 35363 | P19: 49925 | Q19: =SUM(K19:P19) -> 175951
C20: Accrued payroll and benefits | K20: 36195 | L20: 26322 | P20: 21455 | Q20: =SUM(K20:P20) -> 83972
C21: Due to other funds | M21: 178750 | Q21: =SUM(K21:P21) -> 178750
E23: Total liabilities: | K23: =SUM(K19:K21) -> 105277 | L23: =SUM(L19:L21) -> 26322 | M23: =SUM(M19:M21) -> 200331 | N23: =SUM(N19:N21) -> 0 | O23: =SUM(O19:O21) -> 35363 | P23: =SUM(P19:P21) -> 71380 | Q23: =SUM(Q19:Q21) -> 438673
A25: DEFERRED INFLOWS OF RESROUCES
B26: Unavailable ad valorem taxes | K26: 11753 | L26: 51777 | O26: 9372 | Q26: =SUM(K26:P26) -> 72902
E28: Total deferred inflows of resources | K28: =SUM(K26:K26) -> 11753 | L28: =SUM(L26:L26) -> 51777 | M28: =SUM(M26:M26) -> 0 | N28: =SUM(N26:N26) -> 0 | O28: =SUM(O26:O26) -> 9372 | P28: =SUM(P26:P26) -> 0 | Q28: =SUM(Q26:Q26) -> 72902
A30: Fund Balances
C31: Restricted | Q31: =SUM(K31:P31) -> 0
D32: Debt service | N32: 2643431 | Q32: =SUM(K32:P32) -> 2643431
C33: Committed | Q33: =SUM(K33:P33) -> 0
D34: Special reverse projects | L34: 2065510 | M34: 1805993 | O34: 631362 | P34: 873833 | Q34: =SUM(K34:P34) -> 5376698
C35: Unassigned | K35: 3412795 | Q35: =SUM(K35:P35) -> 3412795
E37: Total fund balance: | K37: =SUM(K31:K35) -> 3412795 | L37: =SUM(L31:L35) -> 2065510 | M37: =SUM(M31:M35) -> 1805993 | N37: =SUM(N31:N35) -> 2643431 | O37: =SUM(O31:O35) -> 631362 | P37: =SUM(P31:P35) -> 873833 | Q37: =SUM(Q31:Q35) -> 11432924
E39: Total liabilities, deffered inflows of resources and fund balances: | K39: =SUM(K23+K28+K37) -> 3529825 | L39: =SUM(L23+L28+L37) -> 2143609 | M39: =SUM(M23+M28+M37) -> 2006324 | N39: =SUM(N23+N28+N37) -> 2643431 | O39: =SUM(O23+O28+O37) -> 676097 | P39: =SUM(P23+P28+P37) -> 945213 | Q39: =SUM(Q23+Q28+Q37) -> 11944499

Sheet DeSoto
D1: DeSoto Combined Balance Sheet
D2: Issued: December 31, 2014
K4: General Fund | L4: Solid Waste Fund | M4: Road Fund | N4: Airport Fund | O4: Jail Fund | P4: Sales Tax | Q4: Other Governmental Funds | R4: Total Governmental Funds
A5: Assets:
B6: Cash and Cash Equivalents | K6: 1781428 | L6: 3599880 | M6: 1648535 | N6: 345044 | O6: 4820618 | P6: 3000 | Q6: 964292 | R6: =SUM(K6:Q6) -> 13162797
B7: Investments | K7: 7067168 | L7: 6352258 | M7: 10699 | N7: 6925401 | P7: 0 | Q7: 0 | R7: =SUM(K7:Q7) -> 20355526
B8: Revenue Receivables | K8: 4148243 | L8: 4276536 | M8: 4141732 | N8: 65057 | P8: 805224 | Q8: 178376 | R8: =SUM(K8:Q8) -> 13615168
B9: Inventory | K9: 0 | M9: 0 | N9: 38185 | P9: 0 | Q9: 0 | R9: =SUM(K9:Q9) -> 38185
B10: Due from Other Funds | K10: 201448 | L10: 119358 | M10: 397861 | O10: 79572 | P10: 0 | Q10: 0 | R10: =SUM(K10:Q10) -> 798239
B11: Noncurrent Receivable | K11: 0 | M11: 44000 | P11: 0 | Q11: 0 | R11: =SUM(K11:Q11) -> 44000
E13: Total assets: | K13: =SUM(K6:K11) -> 13198287 | L13: =SUM(L6:L11) -> 14348032 | M13: =SUM(M6:M11) -> 6242827 | N13: =SUM(N6:N11) -> 7373687 | O13: =SUM(O6:O11) -> 4900190 | P13: =SUM(P6:P11) -> 808224 | Q13: =SUM(Q6:Q11) -> 1142668 | R13: =SUM(R6:R11) -> 48013915
A15: LIABILITIES AND FUND BALANCES
B16: Liabilities:
C17: Accounts payable | K17: 296375 | L17: 245861 | M17: 345433 | N17: 7088 | O17: 22052 | P17: 9502 | Q17: 180044 | R17: =SUM(K17:Q17) -> 1106355
C18: Due to other funds | K18: 0 | P18: 599791 | Q18: 198448 | R18: =SUM(K18:Q18) -> 798239
C19: Master bank Overdrafts | K19: 0 | P19: 0 | Q19: 55314 | R19: =SUM(K19:Q19) -> 55314
C20: Due to other governments | K20: 8966 | P20: 198931 | Q20: 0 | R20: =SUM(K20:Q20) -> 207897
C21: Advance from grantors | K21: 0 | P21: 0 | Q21: 22885 | R21: =SUM(K21:Q21) -> 22885
C22: Deposits | K22: 1800 | P22: 0 | Q22: 0 | R22: =SUM(K22:Q22) -> 1800
E24: Total liabilities: | K24: =SUM(K17:K22) -> 307141 | L24: =SUM(L17:L22) -> 245861 | M24: =SUM(M17:M22) -> 345433 | N24: =SUM(N17:N22) -> 7088 | O24: =SUM(O17:O22) -> 22052 | P24: =SUM(P17:P22) -> 808224 | Q24: =SUM(Q17:Q22) -> 456691 | R24: =SUM(R17:R22) -> 2192490
A26: DEFERRED INFLOWS OF RESOURCES
C27: Unavailable Property Taxes | K27: 236806 | L27: 195922 | M27: 175995 | Q27: 0 | R27: =SUM(K27:Q27) -> 608723
E29: Total deferred inflows of resources | K29: =SUM(K27:K27) -> 236806 | L29: =SUM(L27:L27) -> 195922 | M29: =SUM(M27:M27) -> 175995 | N29: =SUM(N27:N27) -> 0 | O29: =SUM(O27:O27) -> 0 | P29: =SUM(P27:P27) -> 0 | Q29: =SUM(Q27:Q27) -> 0 | R29: =SUM(R27:R27) -> 608723
B31: Fund Balances
C32: Nonspendable:
D33: Inventories | K33: 0 | N33: 38185 | R33: =SUM(K33:Q33) -> 38185
C34: Restricted: | R34: =SUM(K34:Q34) -> 0
D35: Airport | K35: 0 | N35: 7328414 | R35: =SUM(K35:Q35) -> 7328414
D36: Judicial | K36: 0 | Q36: 69 | R36: =SUM(K36:Q36) -> 69
D37: Public Safety | K37: 0 | O37: 4878138 | R37: =SUM(K37:Q37) -> 4878138
D38: Roads | K38: 0 | M38: 5721399 | R38: =SUM(K38:Q38) -> 5721399
D39: Sanitation | K39: 0 | L39: 13906249 | R39: =SUM(K39:Q39) -> 13906249
D40: Health & Welfare | K40: 0 | Q40: 52581 | R40: =SUM(K40:Q40) -> 52581
D41: Witness & Juror Fees | K41: 0 | Q41: 458392 | R41: =SUM(K41:Q41) -> 458392
C42: Assigned: | R42: =SUM(K42:Q42) -> 0
D43: Self-Insured Premiums | K43: 13809 | R43: =SUM(K43:Q43) -> 13809
D44: Animal Control | K44: 0 | Q44: 174935 | R44: =SUM(K44:Q44) -> 174935
C45: Unassigned | K45: 12640531 | R45: =SUM(K45:Q45) -> 12640531
E47: Total fund balances: | K47: =SUM(K33:K45) -> 12654340 | L47: =SUM(L33:L45) -> 13906249 | M47: =SUM(M33:M45) -> 5721399 | N47: =SUM(N33:N45) -> 7366599 | O47: =SUM(O33:O45) -> 4878138 | P47: =SUM(P33:P45) -> 0 | Q47: =SUM(Q33:Q45) -> 685977 | R47: =SUM(R33:R45) -> 45212702
E49: Total liabilities and fund balances: | K49: =SUM(K47,K24,K29) -> 13198287 | L49: =SUM(L47,L24,L29) -> 14348032 | M49: =SUM(M47,M24,M29) -> 6242827 | N49: =SUM(N47,N24,N29) -> 7373687 | O49: =SUM(O47,O24,O29) -> 4900190 | P49: =SUM(P47,P24,P29) -> 808224 | Q49: =SUM(Q47,Q24,Q29) -> 1142668 | R49: =SUM(R47,R24,R29) -> 48013915

Sheet East Baton Rouge
D1: East Baton Rouge Combined Balance Sheet
D2: Issued: December 31, 2014
K5: General Fund | L5: Library Board of Control | M5: Grants | N5: Capital Projects | O5: Other Governmental Funds | P5: Total Governmental Funds
A6: Assets:
B7: Cash and cash equivalents (note 3) | K7: 49746105 | L7: 31703021 | M7: 2858777 | N7: 56478568 | O7: 35307663 | P7: =SUM(K7:O7) -> 176094134
B8: Investments (note 3) | K8: 56096672 | L8: 35750216 | M8: 3223727 | N8: 63774265 | O8: 29946347 | P8: =SUM(K8:O8) -> 188791227
B9: Property taxes receivable - net (note 4) | K9: 6313250 | L9: 9316072 | O9: 7242340 | P9: =SUM(K9:O9) -> 22871662
B10: Gross receipts business taxes receivable | K10: 4472777 | P10: =SUM(K10:O10) -> 4472777
B11: Sales taxes receivable | K11: 16926471 | N11: 2655398 | O11: 1649370 | P11: =SUM(K11:O11) -> 21231239
B12: Interest and penalties receivable on taxes | K12: 86002 | P12: =SUM(K12:O12) -> 86002
B13: Accounts receivable - net (note 13) | K13: 1884952 | L13: 5458 | M13: 12954 | N13: 191521 | O13: 2248970 | P13: =SUM(K13:O13) -> 4343855
B14: Accrued interest receivable | K14: 34764 | L14: 23692 | M14: 2411 | N14: 35738 | O14: 18477 | P14: =SUM(K14:O14) -> 115082
B15: Due from other funds (Note 11) | K15: 8229078 | N15: 31211723 | P15: =SUM(K15:O15) -> 39440801
B16: Due from other governments (Note 11) | K16: 20692325 | L16: 30188558 | M16: 7115771 | N16: 3687777 | O16: 22850519 | P16: =SUM(K16:O16) -> 84534950
B17: Loans receivable | K17: 427500 | M17: 3187176 | P17: =SUM(K17:O17) -> 3614676
B18: Inventory | K18: 556855 | P18: 556855
E19: Total Assets: | K19: =SUM(K7:K18) -> 165466751 | L19: =SUM(L7:L18) -> 106987017 | M19: =SUM(M7:M18) -> 16400816 | N19: =SUM(N7:N18) -> 158034990 | O19: =SUM(O7:O18) -> 99263686 | P19: =SUM(P7:P18) -> 546153260
A21: LIABILITIES, DEFERRED INFLOWS OF RESOURCES, AND FUND BALANCES
B22: Liabilities:
C23: Accounts and contracts payable | K23: 18371016 | L23: 1315828 | M23: 3533271 | N23: 15798123 | O23: 3326142 | P23: =SUM(K23:O23) -> 42344380
C24: Due to other funds (Note 11) | L24: 30652157 | O24: 8788644 | P24: =SUM(K24:O24) -> 39440801
C25: Due to other governments | K25: 7384834 | O25: 313036 | P25: =SUM(K25:O25) -> 7697870
C26: Accrued payables | K26: 7975572 | L26: 897065 | M26: 686821 | N26: 13967 | O26: 1592600 | P26: =SUM(K26:O26) -> 11166025
C27: Unearned revenue | M27: 664583 | N27: 398579 | P27: =SUM(K27:O27) -> 1063162
C28: Deposits and escrow accounts | K28: 18011657 | M28: 131910 | P28: =SUM(K28:O28) -> 18143567
E30: Total liabilities: | K30: =SUM(K23:K28) -> 51743079 | L30: =SUM(L23:L29) -> 32865050 | M30: =SUM(M23:M29) -> 5016585 | N30: =SUM(N23:N29) -> 16210669 | O30: =SUM(O23:O29) -> 14020422 | P30: =SUM(P23:P29) -> 119855805
A32: DEFERRED INFLOWS OF RESROUCES
B33: Unavailable revenue- property taxes | K33: 733458 | L33: 900636 | O33: 834079 | P33: =SUM(K33:O33) -> 2468173
B34: Unavailable revenue- revenue sharing | K34: 657671 | O34: 77028 | P34: =SUM(K34:O34) -> 734699
B35: Resources recieved before time requirements | M35: 351292 | P35: =SUM(K35:O35) -> 351292
E37: Total deferred inflows of resources | K37: =SUM(K33:K35) -> 1391129 | L37: =SUM(L33:L35) -> 900636 | M37: =SUM(M33:M35) -> 351292 | N37: =SUM(N33:N35) -> 0 | O37: =SUM(O33:O35) -> 911107 | P37: =SUM(P33:P35) -> 3554164
B39: Fund Balances
C40: Nonspendable | K40: 556855 | P40: =SUM(K40:O40) -> 556855
C41: Restricted | K41: 1256695 | L41: 73221331 | M41: 11032939 | P41: =SUM(K41:O41) -> 85510965
C42: Committed | K42: 62492744 | N42: 119656017 | O42: 76376834 | P42: =SUM(K42:O42) -> 258525595
C43: Assigned | K43: 32590252 | N43: 22168304 | O43: 7955323 | P43: =SUM(K43:O43) -> 62713879
C44: Unassigned | K44: 15435997 | P44: =SUM(K44:O44) -> 15435997
E46: Total fund balance: | K46: =SUM(K40:K44) -> 112332543 | L46: =SUM(L40:L44) -> 73221331 | M46: =SUM(M40:M44) -> 11032939 | N46: =SUM(N40:N44) -> 141824321 | O46: =SUM(O40:O44) -> 84332157 | P46: =SUM(P40:P44) -> 422743291
E48: Total liabilities, deffered inflows of resources and fund balances: | K48: =SUM(K30+K37+K46) -> 165466751 | L48: =SUM(L30+L37+L46) -> 106987017 | M48: =SUM(M30+M37+M46) -> 16400816 | N48: =SUM(N30+N37+N46) -> 158034990 | O48: =SUM(O30+O37+O46) -> 99263686 | P48: =SUM(P30+P37+P46) -> 546153260

Sheet East Carroll
D1: East Carroll Combined Balance Sheet
D2: Issued: December 31, 2014
K4: General | L4: Road Maintenance and Construction | M4: Garbage District No. 1 | N4: Library | O4: Drainage Maintenance | P4: Health Unit | Q4: Nonmajor Governmental | R4: Total
A5: Assets:
B6: Cash and Cash Equivalents | K6: 228072 | L6: 775488 | M6: 45691 | N6: 162492 | O6: 195861 | P6: 430539 | Q6: 437063 | R6: =SUM(K6:Q6) -> 2275206
B7: Investments | L7: 191576 | M7: 209365 | N7: 211588 | O7: 61674 | P7: 28773 | Q7: 70691 | R7: =SUM(K7:Q7) -> 773667
B8: Receivables | K8: 649311 | L8: 431856 | M8: 320248 | N8: 272180 | O8: 448705 | P8: 156950 | Q8: 272263 | R8: =SUM(K8:Q8) -> 2551513
B9: Interfund receivables | K9: 6218 | L9: 3670 | R9: =SUM(K9:Q9) -> 9888
E11: Total assets: | K11: =SUM(K6:K9) -> 883601 | L11: =SUM(L6:L9) -> 1402590 | M11: =SUM(M6:M9) -> 575304 | N11: =SUM(N6:N9) -> 646260 | O11: =SUM(O6:O9) -> 706240 | P11: =SUM(P6:P9) -> 616262 | Q11: =SUM(Q6:Q9) -> 780017 | R11: =SUM(R6:R9) -> 5610274
A13: LIABILITIES, DEFERRED INFLOWS OF RESOURCES, AND FUND BALANCES
B14: Liabilities:
C15: Accounts payable | K15: 172155 | L15: 6614 | M15: 9807 | N15: 3076 | O15: 3149 | P15: 35 | Q15: 12821 | R15: =SUM(K15:Q15) -> 207657
C16: Interfund payables | L16: 1837 | M16: 4790 | N16: 3261 | R16: =SUM(K16:Q16) -> 9888
E18: Total liabilities: | K18: =SUM(K15:K16) -> 172155 | L18: =SUM(L15:L16) -> 8451 | M18: =SUM(M15:M16) -> 14597 | N18: =SUM(N15:N16) -> 6337 | O18: =SUM(O15:O16) -> 3149 | P18: =SUM(P15:P16) -> 35 | Q18: =SUM(Q15:Q16) -> 12821 | R18: =SUM(R15:R16) -> 217545
A20: Deferred Inflows of Resources
B21: Unavailable revenue- property taxes | K21: 23541 | L21: 21246 | M21: 23101 | N21: 21194 | O21: 21246 | P21: 12221 | Q21: 17696 | R21: =SUM(K21:Q21) -> 140245
E23: Total deferred inflows of resources | K23: =SUM(K19:K21) -> 23541 | L23: =SUM(L19:L21) -> 21246 | M23: =SUM(M19:M21) -> 23101 | N23: =SUM(N19:N21) -> 21194 | O23: =SUM(O19:O21) -> 21246 | P23: =SUM(P19:P21) -> 12221 | Q23: =SUM(Q19:Q21) -> 17696 | R23: =SUM(R19:R21) -> 140245 | ... Z23: =SUM(Z19:Z21) -> 0
A25: Fund Balances
C26: Restricted | L26: 1372893 | M26: 537606 | N26: 618729 | O26: 681845 | P26: 604006 | Q26: 749500 | R26: =SUM(K26:Q26) -> 4564579
C27: Unassigned | K27: 687905 | R27: =SUM(K27:Q27) -> 687905
E29: Total fund balance: | K29: =SUM(K26:K27) -> 687905 | L29: =SUM(L26:L27) -> 1372893 | M29: =SUM(M26:M27) -> 537606 | N29: =SUM(N26:N27) -> 618729 | O29: =SUM(O26:O27) -> 681845 | P29: =SUM(P26:P27) -> 604006 | Q29: =SUM(Q26:Q27) -> 749500 | R29: =SUM(R26:R27) -> 5252484
E31: Total liabilities, deferred inflows of resources, and fund balances: | K31: =SUM(K29+K23+K18) -> 883601 | L31: =SUM(L29+L23+L18) -> 1402590 | M31: =SUM(M29+M23+M18) -> 575304 | N31: =SUM(N29+N23+N18) -> 646260 | O31: =SUM(O29+O23+O18) -> 706240 | P31: =SUM(P29+P23+P18) -> 616262 | Q31: =SUM(Q29+Q23+Q18) -> 780017 | R31: =SUM(R29+R23+R18) -> 5610274

Sheet East Feliciana
D1: East Feliciana Combined Balance Sheet
D2: Issued: December 31, 2014
K4: General Fund | L4: Roads and Bridges | M4: Solid Waste | N4: Other Governmental Funds | O4: Total Governmental Funds
A5: Assets:
B6: Cash and cash equivalents | K6: 810939.55 | L6: 1278350 | M6: 2485602.7 | N6: 427717.31 | O6: =SUM(K6:N6) -> 5002609.6
B7: Receivables, net:
C8: Accounts | N8: 12336.64 | O8: =SUM(K8:N8) -> 12336.64
C9: Taxes | K9: 396124.82 | M9: 284115.73 | N9: 432247.63 | O9: =SUM(K9:N9) -> 1112488.2
B10: Due from other funds | K10: 268988.48 | L10: 287054.02 | M10: 1275000 | O10: =SUM(K10:N10) -> 1831042.5
B11: Due from other govt agencies | K11: 19747 | L11: 44917.96 | N11: 27307 | O11: =SUM(K11:N11) -> 91971.96
E13: Total assets: | K13: =SUM(K6:K11) -> 1495799.9 | L13: =SUM(L6:L11) -> 1610322 | M13: =SUM(M6:M11) -> 4044718.5 | N13: =SUM(N6:N11) -> 899608.58 | O13: =SUM(O6:O11) -> 8050448.9
A15: LIABILITIES AND FUND BALANCES
B16: Liabilities:
C17: Accounts payable | K17: 69255.2 | L17: 581663.58 | M17: 84757.3 | O17: =SUM(K17:N17) -> 735676.08
C18: Due to other funds | K18: 14435.04 | L18: 1275000 | M18: 21947.19 | N18: 152885.34 | O18: =SUM(K18:N18) -> 1464267.6
C19: Due to other govt agencies | N19: 2729.05 | O19: =SUM(K19:N19) -> 2729.05
E21: Total liabilities: | K21: =SUM(K17:K19) -> 83690.24 | L21: =SUM(L17:L19) -> 1856663.6 | M21: =SUM(M17:M19) -> 106704.49 | N21: =SUM(N17:N19) -> 155614.39 | O21: =SUM(O17:O19) -> 2202672.7
A23: Deferred inflows of resources:
B24: Unavailable revenue | K24: 47055.21 | N24: 26280.13 | O24: =SUM(K24:N24) -> 73335.34
A26: Fund Balances (Deficit):
C27: Restricted for: | O27: =SUM(K27:N27) -> 0
D28: Health unit oper/maintenance | N28: 845785.87 | O28: =SUM(K28:N28) -> 845785.87
D29: Homeland security | K29: 45514.34 | O29: =SUM(K29:N29) -> 45514.34
D30: Solid waste management | M30: 3938014 | O30: =SUM(K30:N30) -> 3938014
C31: Committed to:
D32: Debt service | L32: -246341.59 | O32: =SUM(K32:N32) -> -246341.59
D33: Road improvements | N33: -128071.81 | O33: =SUM(K33:N33) -> -128071.81
D34: Coroner/court operations | O34: =SUM(K34:N34) -> 0
D35: Claims and judgements | K35: 45500 | O35: =SUM(K35:N35) -> 45500
C36: Unassigned | K36: 1274040.1 | O36: =SUM(K36:N36) -> 1274040.1
E38: Total fund balance: | K38: =SUM(K28:K36) -> 1365054.4 | L38: =SUM(L28:L36) -> -246341.59 | M38: =SUM(M28:M36) -> 3938014 | N38: =SUM(N28:N36) -> 717714.06 | O38: =SUM(O28:O36) -> 5774440.8
E40: Total liabilities, deferred inflows of resources, and fund balances: | K40: =SUM(K38+K24+K21) -> 1495799.9 | L40: =SUM(L38+L24+L21) -> 1610322 | M40: =SUM(M38+M24+M21) -> 4044718.5 | N40: =SUM(N38+N24+N21) -> 899608.58 | O40: =SUM(O38+O24+O21) -> 8050448.9

Sheet Evangeline
D1: Evangeline Combined Balance Sheet
D2: Issued: December 31, 2014
K4: Parish Road Fund | L4: Criminal Court Fund | M4: Industrial District No. 1 | N4: Crooked Creek Recreation Fund | O4: Reddell Sewer System Maintenance Fund | P4: Cemetery District Maintenance Fund | Q4: Country Estate Sewer System Fund | R4: Eugene Subdivision Sewer System Fund | S4: Health Unit Maintenance | T4: Total
A5: Assets:
B6: Cash and interest-bearing deposits | K6: 587936 | L6: 11062 | M6: 269504 | O6: 32563 | P6: 1014924 | Q6: 6974 | R6: 2368 | S6: 1126328 | T6: =SUM(K6:S6) -> 3051659
B7: Receivables, net | O7: 1579 | Q7: 860 | R7: 587 | T7: =SUM(K7:S7) -> 3026
B8: Due from other gonvernmental units | K8: 81043 | L8: 24120 | P8: 391077 | S8: 516485 | T8: =SUM(K8:S8) -> 1012725
B9: Other assets | M9: 5000 | T9: =SUM(K9:S9) -> 5000
E11: Total assets: | K11: =SUM(K6:K9) -> 668979 | L11: =SUM(L6:L9) -> 35182 | M11: =SUM(M6:M9) -> 274504 | N11: =SUM(N6:N9) -> 0 | O11: =SUM(O6:O9) -> 34142 | P11: =SUM(P6:P9) -> 1406001 | Q11: =SUM(Q6:Q9) -> 7834 | R11: =SUM(R6:R9) -> 2955 | ... T11: =SUM(T6:T9) -> 4072410
A13: LIABILITIES, DEFERRED INFLOWS OF RESOURCES, AND FUND BALANCES
B14: Liabilities:
C15: Cash overdraft | N15: 7145 | T15: =SUM(K15:S15) -> 7145
C16: Accounts payable | K16: 82573 | L16: 6450 | M16: 734 | N16: 3645 | O16: 2949 | P16: 480 | Q16: 235 | R16: 558 | S16: 4448 | T16: =SUM(K16:S16) -> 102072
C17: Unearned revenue | M17: 260333 | T17: =SUM(K17:S17) -> 260333
C18: Due to other funds | N18: 9939 | T18: =SUM(K18:S18) -> 9939
C19: Sewer deposits payable | O19: 8292 | Q19: 1133 | R19: 1637 | T19: =SUM(K19:S19) -> 11062
E21: Total liabilities: | K21: =SUM(K15:K19) -> 82573 | L21: =SUM(L15:L19) -> 6450 | M21: =SUM(M15:M19) -> 261067 | N21: =SUM(N15:N19) -> 20729 | O21: =SUM(O15:O19) -> 11241 | P21: =SUM(P15:P19) -> 480 | Q21: =SUM(Q15:Q19) -> 1368 | R21: =SUM(R15:R19) -> 2195 | ... T21: =SUM(T15:T19) -> 390551
A24: Fund Balances
C25: Assigned-
D26: Judicial | L26: 28732 | T26: =SUM(K26:S26) -> 28732
D27: Public Works | K27: 586406 | M27: 13437 | O27: 22901 | P27: 1405521 | Q27: 6466 | R27: 760 | T27: =SUM(K27:S27) -> 2035491
D28: Health and Welfare | S28: 1638365 | T28: =SUM(K28:S28) -> 1638365
C29: Unassigned (deficit) | N29: -20729 | T29: =SUM(K29:S29) -> -20729
E31: Total fund balance: | K31: =SUM(K25:K29) -> 586406 | L31: =SUM(L25:L29) -> 28732 | M31: =SUM(M25:M29) -> 13437 | N31: =SUM(N25:N29) -> -20729 | O31: =SUM(O25:O29) -> 22901 | P31: =SUM(P25:P29) -> 1405521 | Q31: =SUM(Q25:Q29) -> 6466 | R31: =SUM(R25:R29) -> 760 | ... T31: =SUM(T25:T29) -> 3681859
E33: Total liabilities, deferred inflows of resources, and fund balances: | K33: =SUM(K31+K21) -> 668979 | L33: =SUM(L31+L21) -> 35182 | M33: =SUM(M31+M21) -> 274504 | N33: =SUM(N31+N21) -> 0 | O33: =SUM(O31+O21) -> 34142 | P33: =SUM(P31+P21) -> 1406001 | Q33: =SUM(Q31+Q21) -> 7834 | R33: =SUM(R31+R21) -> 2955 | ... T33: =SUM(T31+T21) -> 4072410

Sheet Franklin
D1: Franklin Combined Balance Sheet
D2: Issued: December 31, 2014
K4: General | L4: Road and Bridge | M4: Drainage Maintenance | N4: Parish Equipment | O4: Sales Tax | P4: IKE GUSTAV | Q4: Other Governmental Funds | R4: Total
A5: Assets:
B6: Cash and Cash Equivalents | K6: 280695 | L6: 2771342 | M6: 313980 | N6: 879589 | O6: 1657381 | P6: 14284 | Q6: 2643101 | R6: =SUM(K6:Q6) -> 8560372
B7: Receivables | K7: 326713 | L7: 215084 | M7: 982769 | N7: 714422 | O7: 93816 | P7: 215661 | Q7: 1248283 | R7: =SUM(K7:Q7) -> 3796748
B8: Due from other funds | K8: 101158 | R8: =SUM(K8:Q8) -> 101158
E10: Total assets: | K10: =SUM(K6:K8) -> 708566 | L10: =SUM(L6:L8) -> 2986426 | M10: =SUM(M6:M8) -> 1296749 | N10: =SUM(N6:N8) -> 1594011 | O10: =SUM(O6:O8) -> 1751197 | P10: =SUM(P6:P8) -> 229945 | Q10: =SUM(Q6:Q8) -> 3891384 | R10: =SUM(R6:R8) -> 12458278
A12: LIABILITIES, DEFERRED INFLOWS OF RESOURCES, AND FUND BALANCES
B13: Liabilities:
C14: Accounts payable | K14: 15422 | L14: 8473 | M14: 37003 | N14: 34250 | O14: 92094 | P14: 229895 | Q14: 80493 | R14: =SUM(K14:Q14) -> 497630
C15: Payroll withholdings payable | K15: 67733 | R15: =SUM(K15:Q15) -> 67733
C16: Due to other funds | O16: 63016 | Q16: 38142 | R16: =SUM(K16:Q16) -> 101158
E17: Total liabilities: | K17: =SUM(K14:K15) -> 83155 | L17: =SUM(L14:L15) -> 8473 | M17: =SUM(M14:M15) -> 37003 | N17: =SUM(N14:N15) -> 34250 | O17: =SUM(O14:O16) -> 155110 | P17: =SUM(P14:P16) -> 229895 | Q17: =SUM(Q14:Q16) -> 118635 | R17: =SUM(R14:R16) -> 666521
A19: Fund Equity - Fund Balances
C20: Restricted
D21: Other General Government | Q21: 1019996 | R21: =SUM(K21:Q21) -> 1019996
D22: Health and Welfare | Q22: 599747 | R22: =SUM(K22:Q22) -> 599747
D23: Culture and recreation | Q23: -6300 | R23: =SUM(K23:Q23) -> -6300
D24: Public safety | Q24: 644985 | R24: =SUM(K24:Q24) -> 644985
D25: Public works | L25: 2977953 | M25: 1259746 | N25: 1559761 | O25: 1596087 | Q25: 774008 | R25: =SUM(K25:Q25) -> 8167555
D26: Economic development | Q26: 709046 | R26: =SUM(K26:Q26) -> 709046
D27: Committed | Q27: 31267 | R27: =SUM(K27:Q27) -> 31267
C28: Assigned | P28: 50 | R28: =SUM(K28:Q28) -> 50
C29: Unassigned | K29: 625411 | R29: =SUM(K29:Q29) -> 625411
E31: Total fund balance: | K31: =SUM(K20:K29) -> 625411 | L31: =SUM(L20:L29) -> 2977953 | M31: =SUM(M20:M29) -> 1259746 | N31: =SUM(N20:N29) -> 1559761 | O31: =SUM(O20:O29) -> 1596087 | P31: =SUM(P20:P29) -> 50 | Q31: =SUM(Q20:Q29) -> 3772749 | R31: =SUM(R20:R29) -> 11791757
E33: Total liabilities, deferred inflows of resources, and fund balances: | K33: =SUM(K31+K17) -> 708566 | L33: =SUM(L31+L17) -> 2986426 | M33: =SUM(M31+M17) -> 1296749 | N33: =SUM(N31+N17) -> 1594011 | O33: =SUM(O31+O17) -> 1751197 | P33: =SUM(P31+P17) -> 229945 | Q33: =SUM(Q31+Q17) -> 3891384 | R33: =SUM(R31+R17) -> 12458278

Sheet Grant
D1: Grant Parish Combined Balance Sheet
D2: Issued: December 31, 2014
K4: General Fund | L4: Parish Road Maintenance | M4: Sanitary Landfill Maintenance | N4: Head Start | O4: South Grant Sewer | P4: Other Governmental Funds | Q4: Total Governmental Funds
A5: Assets:
B6: Cash and Cash Equivalents | K6: 297567 | L6: 229870 | M6: 440932 | N6: 74993 | O6: 69537 | P6: 684281 | Q6: =SUM(K6:P6) -> 1797180
B7: Receivables (net) | K7: 355627 | L7: 449132 | M7: 199572 | O7: 135191 | P7: 333150 | Q7: =SUM(K7:P7) -> 1472672
B8: Interfund Receivables | K8: 153659 | L8: 43350 | M8: 3016 | P8: 11978 | Q8: =SUM(K8:P8) -> 212003
E9: Total assets: | K9: =SUM(K6:K8) -> 806853 | L9: =SUM(L6:L8) -> 722352 | M9: =SUM(M6:M8) -> 643520 | N9: =SUM(N6:N8) -> 74993 | O9: =SUM(O6:O8) -> 204728 | P9: =SUM(P6:P8) -> 1029409 | Q9: =SUM(Q6:Q8) -> 3481855
A11: LIABILITIES AND FUND BALANCES
B12: Liabilities:
C13: Accounts payable | K13: 125505 | L13: 58760 | M13: 32320 | N13: 74993 | O13: 180255 | P13: 55314 | Q13: =SUM(K13:P13) -> 527147
C14: Interfund Payables | K14: 11500 | L14: 2232 | M14: 110499 | P14: 87772 | Q14: =SUM(K14:P14) -> 212003
C15: Unearned revenue | P15: 17112 | Q15: =SUM(K15:P15) -> 17112
E16: Total liabilities: | K16: =SUM(K13:K15) -> 137005 | L16: =SUM(L13:L15) -> 60992 | M16: =SUM(M13:M15) -> 142819 | N16: =SUM(N13:N15) -> 74993 | O16: =SUM(O13:O15) -> 180255 | P16: =SUM(P13:P15) -> 160198 | Q16: =SUM(Q13:Q15) -> 756262
B18: Fund Balances
C19: Restricted:
D20: Maintenance | L20: 661360 | M20: 500701 | P20: 677752 | Q20: =SUM(K20:P20) -> 1839813
D21: Judicial | P21: 25525 | Q21: =SUM(K21:P21) -> 25525
D22: Construction | P22: 51676 | Q22: =SUM(K22:P22) -> 51676
C23: Committed To:
D24: Maintenance | P24: 20277 | Q24: =SUM(K24:P24) -> 20277
D25: Construction | O25: 24473 | Q25: =SUM(K25:P25) -> 24473
D26: Litter Abatement | P26: 3354 | Q26: =SUM(K26:P26) -> 3354
D27: General Purposes | P27: 120413 | Q27: =SUM(K27:P27) -> 120413
C28: Unassigned | K28: 669848 | P28: -29786 | Q28: =SUM(K28:P28) -> 640062
E29: Total fund balances: | K29: =SUM(K19:K28) -> 669848 | L29: =SUM(L19:L28) -> 661360 | M29: =SUM(M19:M28) -> 500701 | N29: =SUM(N19:N28) -> 0 | O29: =SUM(O19:O28) -> 24473 | P29: =SUM(P19:P28) -> 869211 | Q29: =SUM(Q19:Q28) -> 2725593
E31: Total liabilities and fund balances: | K31: =SUM(K16+K29) -> 806853 | L31: =SUM(L16+L29) -> 722352 | M31: =SUM(M16+M29) -> 643520 | N31: =SUM(N16+N29) -> 74993 | O31: =SUM(O16+O29) -> 204728 | P31: =SUM(P16+P29) -> 1029409 | Q31: =SUM(Q16+Q29) -> 3481855

Sheet Iberia
D1: Iberia Combined Balance Sheet
D2: Issued: December 31, 2014
K4: General | L4: Public Library | M4: Sales Tax | N4: Public Buildings Maintenance | O4: Paarish Wide Drainage Maintenance | P4: Royalty | Q4: Mosquito Control/ Drainage Program | R4: Other Governmental Funds | S4: Total
A5: Assets:
B6: Cash and interest-bearing deposits | K6: 629648 | L6: 5373117 | M6: 6180261 | N6: 3164180 | O6: 3526522 | P6: 7144695 | R6: 14251776 | S6: =SUM(K6:R6) -> 40270199
B7: Investments | L7: 72229 | S7: =SUM(K7:R7) -> 72229
B8: Receivables, net | K8: 1192642 | L8: 2020613 | M8: 56 | N8: 2089725 | O8: 1372834 | R8: 1200314 | S8: =SUM(K8:R8) -> 7876184
B9: Due from other funds | K9: 156387 | L9: 1360 | N9: 324469 | P9: 274 | R9: 50705 | S9: =SUM(K9:R9) -> 533195
B10: Advance to component unit | K10: 1740688 | P10: 72957 | S10: =SUM(K10:R10) -> 1813645
B11: Due from other governmental agencies | K11: 274552 | L11: 79148 | M11: 293658 | N11: 54890 | O11: 39613 | P11: 1223167 | Q11: 296327 | R11: 847083 | S11: =SUM(K11:R11) -> 3108438
E12: Total assets: | K12: =SUM(K6:K11) -> 3993917 | L12: =SUM(L6:L11) -> 7546467 | M12: =SUM(M6:M11) -> 6473975 | N12: =SUM(N6:N11) -> 5633264 | O12: =SUM(O6:O11) -> 4938969 | P12: =SUM(P6:P11) -> 8441093 | Q12: =SUM(Q6:Q11) -> 296327 | R12: =SUM(R6:R11) -> 16349878 | S12: =SUM(S6:S11) -> 53673890
A14: LIABILITIES, DEFERRED INFLOWS OF RESOURCES, AND FUND BALANCES
B15: Liabilities:
C16: Accounts payable | K16: 178909 | L16: 12188 | M16: 218188 | N16: 13608 | O16: 34543 | P16: 121471 | R16: 392068 | S16: =SUM(K16:R16) -> 970975
C17: Accrued expenses | K17: 89527 | L17: 30929 | M17: 2402 | N17: 5214 | O17: 23816 | P17: 9341 | R17: 60701 | S17: =SUM(K17:R17) -> 221930
C18: Contracts payable | P18: 213186 | R18: 148546 | S18: =SUM(K18:R18) -> 361732
C19: Retainage payable | P19: 164651 | R19: 41042 | S19: =SUM(K19:R19) -> 205693
C20: Due to other funds | K20: 396297 | L20: 26075 | M20: 54409 | N20: 24310 | O20: 123579 | P20: 50696 | R20: 323592 | S20: =SUM(K20:R20) -> 998958
C21: Due to other governmental agencies | K21: 52712 | L21: 95004 | N21: 98547 | O21: 64551 | R21: 51140 | S21: =SUM(K21:R21) -> 361954
C22: Due to component units | K22: 21 | Q22: 296327 | R22: 36873 | S22: =SUM(K22:R22) -> 333221
C23: Advances from grantors and assessments | R23: 126545 | S23: =SUM(K23:R23) -> 126545
E24: Total liabilities: | K24: =SUM(K16:K23) -> 717466 | L24: =SUM(L16:L23) -> 164196 | M24: =SUM(M16:M23) -> 274999 | N24: =SUM(N16:N23) -> 141679 | O24: =SUM(O16:O23) -> 246489 | P24: =SUM(P16:P23) -> 559345 | Q24: =SUM(Q16:Q23) -> 296327 | R24: =SUM(R16:R23) -> 1180507 | S24: =SUM(S16:S23) -> 3581008
A27: Fund Balances
C28: Nonspendable | R28: 68863 | S28: =SUM(K28:R28) -> 68863
C29: Restricted | L29: 7382271 | M29: 6198976 | N29: 5491585 | O29: 4692480 | R29: 4650708 | S29: =SUM(K29:R29) -> 28416020
C30: Committed | K30: 515153 | R30: 5128563 | S30: =SUM(K30:R30) -> 5643716
C31: Assigned | K31: 1948661 | P31: 7881748 | R31: 5321237 | S31: =SUM(K31:R31) -> 15151646
C32: Unassigned | K32: 812637 | S32: =SUM(K32:R32) -> 812637
E33: Total fund balance: | K33: =SUM(K28:K32) -> 3276451 | L33: =SUM(L28:L32) -> 7382271 | M33: =SUM(M28:M32) -> 6198976 | N33: =SUM(N28:N32) -> 5491585 | O33: =SUM(O28:O32) -> 4692480 | P33: =SUM(P28:P32) -> 7881748 | Q33: =SUM(Q28:Q32) -> 0 | R33: =SUM(R28:R32) -> 15169371 | S33: =SUM(S28:S32) -> 50092882
E35: Total liabilities, deferred inflows of resources, and fund balances: | K35: =SUM(K33+K24) -> 3993917 | L35: =SUM(L33+L24) -> 7546467 | M35: =SUM(M33+M24) -> 6473975 | N35: =SUM(N33+N24) -> 5633264 | O35: =SUM(O33+O24) -> 4938969 | P35: =SUM(P33+P24) -> 8441093 | Q35: =SUM(Q33+Q24) -> 296327 | R35: =SUM(R33+R24) -> 16349878 | S35: =SUM(S33+S24) -> 53673890

Sheet Iberville
D1: Iberville Combined Balance Sheet
D2: Issued: December 31, 2014
K4: General | L4: Drainage Maintenance | M4: Public Building Maintenance | N4: Sales Tax Roads | O4: Solid Waste | P4: Capital Improvement | Q4: Iberville Parish Medical Facility CSBG | R4: Louisiana Recovery Authority | S4: Other Governmental Funds | T4: Total Governmental Funds
A5: Assets:
B6: Cash and cash equivalents | K6: 3576173 | L6: 820428 | M6: 561406 | N6: 3977828 | O6: 3209225 | P6: 3021131 | Q6: 1275556 | R6: 49993 | S6: 7335673 | T6: =SUM(K6:S6) -> 23827413
B7: Receivables (net of allowance for uncollectible) | K7: 2304610 | L7: 2580739 | M7: 1496419 | N7: 399415 | O7: 524785 | P7: 188268 | Q7: 1400321 | R7: 424350 | S7: 800959 | T7: =SUM(K7:S7) -> 10119866
B8: Prepaid items | K8: 292436 | L8: 29450 | M8: 205200 | N8: 29500 | O8: 4000 | T8: =SUM(K8:S8) -> 560586
B9: Due From Other Funds | T9: =SUM(K9:S9) -> 0
B10: Cash - restricted | K10: 100000 | T10: =SUM(K10:S10) -> 100000
B11: Other assets | S11: 48880 | T11: =SUM(K11:S11) -> 48880
E12: Total assets: | K12: =SUM(K6:K11) -> 6273219 | L12: =SUM(L6:L11) -> 3430617 | M12: =SUM(M6:M11) -> 2263025 | N12: =SUM(N6:N11) -> 4406743 | O12: =SUM(O6:O11) -> 3738010 | P12: =SUM(P6:P11) -> 3209399 | Q12: =SUM(Q6:Q11) -> 2675877 | R12: =SUM(R6:R11) -> 474343 | ... T12: =SUM(T6:T11) -> 34656745
A14: LIABILITIES, DEFERRED INFLOWS OF RESOURCES, AND FUND BALANCES
B15: Liabilities:
C16: Accounts payable | K16: 464239 | L16: 84406 | M16: 155322 | N16: 115584 | O16: 255771 | P16: 129393 | Q16: 1400321 | S16: 214072 | T16: =SUM(K16:S16) -> 2819108
T17: =SUM(K17:S17) -> 0
C18: Due to other funds | T18: =SUM(K18:S18) -> 0
C19: Other payables | K19: 465581 | L19: 136923 | M19: 84546 | N19: 38867 | O19: 7485 | P19: 53239 | R19: 374334 | S19: 60018 | T19: =SUM(K19:S19) -> 1220993
E20: Total liabilities: | K20: =SUM(K16:K19) -> 929820 | L20: =SUM(L16:L19) -> 221329 | M20: =SUM(M16:M19) -> 239868 | N20: =SUM(N16:N19) -> 154451 | O20: =SUM(O16:O19) -> 263256 | P20: =SUM(P16:P19) -> 182632 | Q20: =SUM(Q16:Q19) -> 1400321 | R20: =SUM(R16:R19) -> 374334 | ... T20: =SUM(T16:T19) -> 4040101
A23: Fund Balances
C24: Non Spendable | K24: 392436 | L24: 29450 | M24: 205200 | N24: 29500 | O24: 4000 | T24: =SUM(K24:S24) -> 660586
C25: Restricted | K25: 139220 | L25: 3179838 | M25: 1817957 | N25: 4222792 | O25: 3470754 | P25: 3026767 | Q25: 1275556 | R25: 100009 | S25: 6898567 | T25: =SUM(K25:S25) -> 24131460
C26: Committed | S26: 1012855 | T26: =SUM(K26:S26) -> 1012855
C27: Assigned | T27: =SUM(K27:S27) -> 0
C28: Unassigned | K28: 4811743 | T28: =SUM(K28:S28) -> 4811743
E29: Total fund balance: | K29: =SUM(K24:K28) -> 5343399 | L29: =SUM(L24:L28) -> 3209288 | M29: =SUM(M24:M28) -> 2023157 | N29: =SUM(N24:N28) -> 4252292 | O29: =SUM(O24:O28) -> 3474754 | P29: =SUM(P24:P28) -> 3026767 | Q29: =SUM(Q24:Q28) -> 1275556 | R29: =SUM(R24:R28) -> 100009 | ... T29: =SUM(T24:T28) -> 30616644
E31: Total liabilities, deferred inflows of resources, and fund balances: | K31: =SUM(K29+K20) -> 6273219 | L31: =SUM(L29+L20) -> 3430617 | M31: =SUM(M29+M20) -> 2263025 | N31: =SUM(N29+N20) -> 4406743 | O31: =SUM(O29+O20) -> 3738010 | P31: =SUM(P29+P20) -> 3209399 | Q31: =SUM(Q29+Q20) -> 2675877 | R31: =SUM(R29+R20) -> 474343 | ... T31: =SUM(T29+T20) -> 34656745

Sheet Jackson
D1: Jackson Combined Balance Sheet
D2: Issued: December 31, 2014
K4: General | L4: Road Fund | M4: Solid Waste | N4: Library | O4: Asphalt Fund | P4: Health Unit | Q4: Sales Tax | R4: Nonmajor Governmental | S4: Total
A5: Assets:
B6: Cash and Cash Equivalents | K6: 2462652 | L6: 1815855 | M6: 1168736 | N6: 1176592 | O6: 1541497 | P6: 98626 | Q6: 311089 | R6: 723873 | S6: =SUM(K6:R6) -> 9298920
B7: Revenue Receivables | K7: 1278246 | L7: 1249643 | M7: 223486 | N7: 857253 | O7: 1040949 | P7: 183698 | Q7: 147917 | S7: =SUM(K7:R7) -> 4981192
B8: Interfund receivables | K8: 50000 | M8: 0 | P8: 0 | R8: 0 | S8: =SUM(K8:R8) -> 50000
B9: Prepaid Items | K9: 3850 | L9: 4746 | M9: 9815 | N9: 50710 | O9: 4746 | P9: 1635 | R9: 0 | S9: =SUM(K9:R9) -> 75502
E11: Total assets: | K11: =SUM(K6:K9) -> 3794748 | L11: =SUM(L6:L9) -> 3070244 | M11: =SUM(M6:M9) -> 1402037 | N11: =SUM(N6:N9) -> 2084555 | O11: =SUM(O6:O9) -> 2587192 | P11: =SUM(P6:P9) -> 283959 | Q11: =SUM(Q6:Q9) -> 459006 | R11: =SUM(R6:R9) -> 723873 | S11: =SUM(S6:S9) -> 14405614
A13: LIABILITIES AND FUND BALANCES
B14: Liabilities:
C15: Accounts, salaries and other payables | K15: 71630 | L15: 108144 | M15: 33203 | N15: 95691 | O15: 296 | P15: 1612 | S15: =SUM(K15:R15) -> 310576
C16: Interfund payables | K16: 0 | P16: 50000 | S16: =SUM(K16:R16) -> 50000
C17: Sequrity deposits | K17: 4075 | L17: 26724 | P17: 0 | S17: =SUM(K17:R17) -> 30799
E19: Total liabilities: | K19: =SUM(K15:K17) -> 75705 | L19: =SUM(L15:L17) -> 134868 | M19: =SUM(M15:M17) -> 33203 | N19: =SUM(N15:N17) -> 95691 | O19: =SUM(O15:O17) -> 296 | P19: =SUM(P15:P17) -> 51612 | Q19: =SUM(Q15:Q17) -> 0 | R19: =SUM(R15:R17) -> 0 | S19: =SUM(S15:S17) -> 391375
A21: DEFERRED INFLOWS OF RESOURCES
C22: Unavailable revenue-property taxes | K22: 99362 | L22: 106782 | N22: 76428 | O22: 92806 | P22: 16378 | R22: 0 | S22: =SUM(K22:R22) -> 391756
E24: Total deferred inflows of resources | K24: =SUM(K22:K22) -> 99362 | L24: =SUM(L22:L22) -> 106782 | M24: =SUM(M22:M22) -> 0 | N24: =SUM(N22:N22) -> 76428 | O24: =SUM(O22:O22) -> 92806 | P24: =SUM(P22:P22) -> 16378 | Q24: =SUM(Q22:Q22) -> 0 | R24: =SUM(R22:R22) -> 0 | S24: =SUM(S22:S22) -> 391756
B26: Fund Balances
C27: Nonspendable - prepaid items | K27: 3850 | L27: 4746 | M27: 9815 | N27: 50710 | O27: 4746 | P27: 1635 | S27: =SUM(K27:R27) -> 75502
C28: Restricted | K28: 42300 | L28: 2823848 | M28: 1359019 | N28: 1861726 | O28: 2489344 | P28: 214334 | Q28: 459006 | R28: 610282 | S28: =SUM(K28:R28) -> 9859859
C29: Committed | K29: 1015761 | R29: 113591 | S29: =SUM(K29:R29) -> 1129352
C30: Unassigned | K30: 2557770 | S30: =SUM(K30:R30) -> 2557770
E32: Total fund balances: | K32: =SUM(K27:K30) -> 3619681 | L32: =SUM(L27:L30) -> 2828594 | M32: =SUM(M27:M30) -> 1368834 | N32: =SUM(N27:N30) -> 1912436 | O32: =SUM(O27:O30) -> 2494090 | P32: =SUM(P27:P30) -> 215969 | Q32: =SUM(Q27:Q30) -> 459006 | R32: =SUM(R27:R30) -> 723873 | S32: =SUM(S27:S30) -> 13622483
E34: Total liabilities and fund balances: | K34: =SUM(K32,K19,K24) -> 3794748 | L34: =SUM(L32,L19,L24) -> 3070244 | M34: =SUM(M32,M19,M24) -> 1402037 | N34: =SUM(N32,N19,N24) -> 2084555 | O34: =SUM(O32,O19,O24) -> 2587192 | P34: =SUM(P32,P19,P24) -> 283959 | R34: =SUM(R32,R19,R24) -> 723873 | S34: =SUM(S32,S19,S24) -> 14405614

Sheet Jefferson Davis
D1: Jefferson Combined Balance Sheet
D2: Issued: December 31, 2014
K4: General Fund | L4: Road Sales Tax No. 1 Sales Tax Fund | M4: Criminal Court Fund | N4: Section 8 Housing Fund | O4: Road Sales Tax No. 1 Sinking Fund | P4: Other Governmental Funds | Q4: Total Governmental Funds
A5: Assets:
B6: Cash and Cash Equivalents | K6: 6883837 | L6: 5955273 | M6: 1824 | N6: 21961 | P6: 7051908 | Q6: =SUM(K6:P6) -> 19914803
B7: Investments | K7: 678247 | O7: 0 | P7: 1433956 | Q7: =SUM(K7:P7) -> 2112203
B8: Receivables | K8: 93939 | L8: 460821 | M8: 116744 | N8: 37 | P8: 746750 | Q8: =SUM(K8:P8) -> 1418291
B9: Due from Other Funds | K9: 300 | O9: 0 | P9: 62102 | Q9: =SUM(K9:P9) -> 62402
B10: Restricted cash and cash equivalents | K10: 0 | L10: 1552823 | O10: 1076217 | P10: 78619 | Q10: =SUM(K10:P10) -> 2707659
E12: Total assets: | K12: =SUM(K6:K10) -> 7656323 | L12: =SUM(L6:L10) -> 7968917 | M12: =SUM(M6:M10) -> 118568 | N12: =SUM(N6:N10) -> 21998 | O12: =SUM(O6:O10) -> 1076217 | P12: =SUM(P6:P10) -> 9373335 | Q12: =SUM(Q6:Q10) -> 26215358
A14: LIABILITIES AND FUND BALANCES
B15: Liabilities:
C16: Accounts, salaries, and other payables | K16: 69611 | L16: 177370 | M16: 137571 | N16: 260 | O16: 825 | P16: 234145 | Q16: =SUM(K16:P16) -> 619782
C17: Contracts payable | K17: 0 | P17: 161303 | Q17: =SUM(K17:P17) -> 161303
C18: Deposits to others | K18: 550500 | O18: 0 | P18: 0 | Q18: =SUM(K18:P18) -> 550500
C19: Other liabilities | K19: 140 | Q19: =SUM(K19:P19) -> 140
C20: Due to other funds | P20: 62402 | Q20: =SUM(K20:P20) -> 62402
E21: Total liabilities: | K21: =SUM(K16:K20) -> 620251 | L21: =SUM(L16:L20) -> 177370 | M21: =SUM(M16:M20) -> 137571 | N21: =SUM(N16:N20) -> 260 | O21: =SUM(O16:O20) -> 825 | P21: =SUM(P16:P20) -> 457850 | Q21: =SUM(Q16:Q20) -> 1394127
A23: DEFERRED INFLOWS OF RESOURCES
C24: Deferred revenues | K24: 102290 | P24: 407305 | Q24: =SUM(K24:P24) -> 509595
E26: Total deferred inflows of resources | K26: =SUM(K24:K24) -> 102290 | L26: =SUM(L24:L24) -> 0 | M26: =SUM(M24:M24) -> 0 | N26: =SUM(N24:N24) -> 0 | O26: =SUM(O24:O24) -> 0 | P26: =SUM(P24:P24) -> 407305 | Q26: =SUM(Q24:Q24) -> 509595
B28: Fund Balances
C29: Restricted: | Q29: =SUM(K29:P29) -> 0
D30: Public safety | K30: 0 | P30: 4888543 | Q30: =SUM(K30:P30) -> 4888543
D31: PUblic works | K31: 0 | L31: 6238724 | P31: 1919696 | Q31: =SUM(K31:P31) -> 8158420
D32: Health and welfare | K32: 0 | N32: 21738 | P32: 355182 | Q32: =SUM(K32:P32) -> 376920
D33: Debt service | K33: 0 | L33: 1552823 | O33: 1075392 | P33: 29437 | Q33: =SUM(K33:P33) -> 2657652
D34: Other general government | K34: 0 | P34: 1340505 | Q34: =SUM(K34:P34) -> 1340505
C35: Assigned: | Q35: =SUM(K35:P35) -> 0
D36: Jali capital project | K36: 538003 | Q36: =SUM(K36:P36) -> 538003
C37: Unassigned | K37: 6395779 | M37: -19003 | P37: -25183 | Q37: =SUM(K37:P37) -> 6351593
E39: Total fund balances: | K39: =SUM(K29:K37) -> 6933782 | L39: =SUM(L29:L37) -> 7791547 | M39: =SUM(M29:M37) -> -19003 | N39: =SUM(N29:N37) -> 21738 | O39: =SUM(O29:O37) -> 1075392 | P39: =SUM(P29:P37) -> 8508180 | Q39: =SUM(Q29:Q37) -> 24311636
E41: Total liabilities and fund balances: | K41: =SUM(K39,K21,K26) -> 7656323 | L41: =SUM(L39,L21,L26) -> 7968917 | M41: =SUM(M39,M21,M26) -> 118568 | N41: =SUM(N39,N21,N26) -> 21998 | O41: =SUM(O39,O21,O26) -> 1076217 | P41: =SUM(P39,P21,P26) -> 9373335 | Q41: =SUM(Q39,Q21,Q26) -> 26215358

Sheet Jefferson
D1: Jefferson Combined Balance Sheet
D2: Issued: December 31, 2014
K5: General Fund | L5: Federal and State Grants | M5: East Bank Consolidated Fire Dictrict | N5: Library | O5: Drainage and Pump Station Capital | P5: Road & Street Capital Improvements | Q5: Other Governmental Funds | R5: Total Governmental Funds
A6: Assets:
B7: Cash and cash equivalents | K7: 8 | O7: 693 | P7: 42 | Q7: 4242 | R7: =SUM(K7:Q7) -> 4985
B8: Investments | O8: 25284 | P8: 18432 | Q8: 9878 | R8: =SUM(K8:Q8) -> 53594
B9: Share of pooled assets | K9: 14086 | L9: 2226 | M9: 13398 | N9: 30324 | O9: 109350 | P9: 78289 | Q9: 219264 | R9: =SUM(K9:Q9) -> 466937
B10: Receivables, net of allowances for estimated uncollectibles | R10: =SUM(K10:Q10) -> 0
C11: Intrerest | O11: 10 | P11: 15 | Q11: 3 | R11: =SUM(K11:Q11) -> 28
C12: Ad valorem tax | K12: 4151 | M12: 38488 | N12: 21074 | O12: 15929 | Q12: 116720 | R12: =SUM(K12:Q12) -> 196362
C13: Accounts | K13: 941 | L13: 24 | Q13: 4397 | R13: =SUM(K13:Q13) -> 5362
C14: Intergovernmental | K14: 15745 | L14: 17028 | M14: 40 | N14: 31 | O14: 4164 | P14: 1576 | Q14: 24316 | R14: =SUM(K14:Q14) -> 62900
B15: Inventories | Q15: 2049 | R15: =SUM(K15:Q15) -> 2049
B16: Deposits and other assets | K16: 1096 | R16: =SUM(K16:Q16) -> 1096
E17: Total Assets: | K17: =SUM(K7:K16) -> 36027 | L17: =SUM(L7:L16) -> 19278 | M17: =SUM(M7:M16) -> 51926 | N17: =SUM(N7:N16) -> 51429 | O17: =SUM(O7:O16) -> 155430 | P17: =SUM(P7:P16) -> 98354 | Q17: =SUM(Q7:Q16) -> 380869 | R17: =SUM(R7:R16) -> 793313
A19: LIABILITIES, DEFERRED INFLOWS OF RESOURCES, AND FUND BALANCES
B20: Liabilities:
C21: Accounts and contracts payable | K21: 2290 | L21: 2344 | M21: 70 | N21: 336 | O21: 4671 | P21: 6642 | Q21: 10825 | R21: =SUM(K21:Q21) -> 27178
C22: Intergovernmental payable | K22: 1 | L22: 454 | O22: 2 | Q22: 1940 | R22: =SUM(K22:Q22) -> 2397
C23: Due to other governments | L23: 12090 | Q23: 309 | R23: =SUM(K23:Q23) -> 12399
C24: Deposits | K24: 56 | R24: =SUM(K24:Q24) -> 56
C25: Other payables and accruals | K25: 6019 | R25: =SUM(K25:Q25) -> 6019
E26: Total liabilities: | K26: =SUM(K21:K25) -> 8366 | L26: =SUM(L21:L25) -> 14888 | M26: =SUM(M21:M25) -> 70 | N26: =SUM(N21:N25) -> 336 | O26: =SUM(O21:O25) -> 4673 | P26: =SUM(P21:P25) -> 6642 | Q26: =SUM(Q21:Q25) -> 13074 | R26: =SUM(R21:R25) -> 48049
A28: DEFERRED INFLOWS OF RESROUCES
B29: Unavailable revenue- property taxes | K29: 4157 | M29: 38549 | N29: 21103 | O29: 15951 | Q29: 118924 | R29: =SUM(K29:Q29) -> 198684
E30: Total deferred inflows of resources | K30: =SUM(K29:K29) -> 4157 | L30: =SUM(L29:L29) -> 0 | M30: =SUM(M29:M29) -> 38549 | N30: =SUM(N29:N29) -> 21103 | O30: =SUM(O29:O29) -> 15951 | P30: =SUM(P29:P29) -> 0 | Q30: =SUM(Q29:Q29) -> 118924 | R30: =SUM(R29:R29) -> 198684
B32: Fund Balances
C33: Nonspendable | Q33: 2049 | R33: =SUM(K33:Q33) -> 2049
C34: Restricted | K34: 1862 | L34: 4390 | M34: 13307 | N34: 29990 | O34: 134806 | P34: 91712 | Q34: 153391 | R34: =SUM(K34:Q34) -> 429458
C35: Committed | K35: 5016 | Q35: 93431 | R35: =SUM(K35:Q35) -> 98447
C36: Assigned | R36: =SUM(K36:Q36) -> 0
C37: Unassigned | K37: 16626 | R37: =SUM(K37:Q37) -> 16626
E39: Total fund balance: | K39: =SUM(K33:K37) -> 23504 | L39: =SUM(L33:L37) -> 4390 | M39: =SUM(M33:M37) -> 13307 | N39: =SUM(N33:N37) -> 29990 | O39: =SUM(O33:O37) -> 134806 | P39: =SUM(P33:P37) -> 91712 | Q39: =SUM(Q33:Q37) -> 248871 | R39: =SUM(R33:R37) -> 546580
E41: Total liabilities, deffered inflows of resources and fund balances: | K41: =SUM(K26+K30+K39) -> 36027 | L41: =SUM(L26+L30+L39) -> 19278 | M41: =SUM(M26+M30+M39) -> 51926 | N41: =SUM(N26+N30+N39) -> 51429 | O41: =SUM(O26+O30+O39) -> 155430 | P41: =SUM(P26+P30+P39) -> 98354 | Q41: =SUM(Q26+Q30+Q39) -> 380869 | R41: =SUM(R26+R30+R39) -> 793313

Sheet Lafayette
D1: Lafayette Combined Balance Sheet
D2: Issued: October 31, 2014
K4: General | L4: Sales Tax Capital Improvements | M4: Other Governmental Funds | N4: Total Governmental Funds
A5: Assets:
B6: Cash | K6: 1063216 | L6: 306677 | M6: 2147870 | N6: =SUM(K6:M6) -> 3517763
B7: Investments | K7: 30300501 | L7: 33047132 | M7: 209732485 | N7: =SUM(K7:M7) -> 273080118
B8: Accounts receivable, net | K8: 1365636 | L8: 92505 | M8: 866392 | N8: =SUM(K8:M8) -> 2324533
B9: Loans receivable | M9: 2289941 | N9: =SUM(K9:M9) -> 2289941
B10: Allowance for uncollectible loans | M10: -32712 | N10: =SUM(K10:M10) -> -32712
B11: Assessments receivable | M11: 193219 | N11: =SUM(K11:M11) -> 193219
B12: Accrued interest receivable | K12: 24557 | L12: 26783 | M12: 265712 | N12: =SUM(K12:M12) -> 317052
B13: Due from other funds | K13: 5264456 | L13: 5699143 | M13: 666509 | N13: =SUM(K13:M13) -> 11630108
B14: Due from component units | K14: 26444 | N14: =SUM(K14:M14) -> 26444
B15: Due from other governmental agencies | K15: 957915 | M15: 12153998 | N15: =SUM(K15:M15) -> 13111913
B16: Inventories, at cost | L16: 259187 | M16: 23210 | N16: =SUM(K16:M16) -> 282397
B17: Prepaid items | K17: 2613 | M17: 93795 | N17: =SUM(K17:M17) -> 96408
E19: Total assets: | K19: =SUM(K6:K17) -> 39005338 | L19: =SUM(L6:L17) -> 39431427 | M19: =SUM(M6:M18) -> 228400419 | N19: =SUM(N6:N17) -> 306837184
A21: LIABILITIES AND FUND BALANCES
B22: Liabilities:
C23: Cash overdraft | M23: 3007972 | N23: =SUM(K23:M23) -> 3007972
C24: Accounts payable | K24: 607786 | L24: 199128 | M24: 1226038 | N24: =SUM(K24:M24) -> 2032952
C25: Accrued salaries and benefits | K25: 774221 | L25: 43201 | M25: 465910 | N25: =SUM(K25:M25) -> 1283332
C26: Contracts payable | L26: 204045 | M26: 1945947 | N26: =SUM(K26:M26) -> 2149992
C27: Retainage payable | K27: 3525 | L27: 246848 | M27: 1171574 | N27: =SUM(K27:M27) -> 1421947
C28: Other payables | K28: 294293 | M28: 118540 | N28: =SUM(K28:M28) -> 412833
C29: Due to other funds | K29: 891887 | L29: 62314 | M29: 10768505 | N29: =SUM(K29:M29) -> 11722706
C30: Due to component units | K30: 34784 | N30: =SUM(K30:M30) -> 34784
C31: Due to other governmental agencies | M31: 929285 | N31: =SUM(K31:M31) -> 929285
C32: Unearned revenue | K32: 3094 | L32: 28480 | M32: 170409 | N32: =SUM(K32:M32) -> 201983
E34: Total liabilities: | K34: =SUM(K23:K32) -> 2609590 | L34: =SUM(L23:L32) -> 784016 | M34: =SUM(M23:M32) -> 19804180 | N34: =SUM(N23:N32) -> 23197786
B36: Fund Balances
C37: Nonspendable -
D38: Inventories | L38: 259187 | M38: 23210 | N38: =SUM(K38:M38) -> 282397
D39: Prepaid items | K39: 2613 | M39: 93795 | N39: =SUM(K39:M39) -> 96408
C40: Restricted - | N40: =SUM(K40:M40) -> 0
D41: Capital expenditures | N41: =SUM(K41:M41) -> 0
D42: Debt service | L42: 38388224 | M42: 114365602 | N42: =SUM(K42:M42) -> 152753826
D43: Operations and maintenance | M43: 45707878 | N43: =SUM(K43:M43) -> 45707878
D44: Purpose of grantors and donors | M44: 40148177 | N44: =SUM(K44:M44) -> 40148177
C45: Committed - | M45: 4895977 | N45: =SUM(K45:M45) -> 4895977
D46: Incomplete projects | K46: 531077 | M46: 209492 | N46: =SUM(K46:M46) -> 740569
C47: Assigned - | N47: =SUM(K47:M47) -> 0
D48: Subsequent year's expenditures | K48: 1594458 | M48: 3152108 | N48: =SUM(K48:M48) -> 4746566
C49: Unassigned | K49: 34267600 | N49: =SUM(K49:M49) -> 34267600
E51: Total fund balance: | K51: =SUM(K38:K49) -> 36395748 | L51: =SUM(L38:L49) -> 38647411 | M51: =SUM(M38:M49) -> 208596239 | N51: =SUM(N37:N49) -> 283639398
E53: Total liabilities and fund balances: | K53: =SUM(K51,K34) -> 39005338 | L53: =SUM(L34,L51) -> 39431427 | M53: =SUM(M34,M51) -> 228400419 | N53: =SUM(N34,N51) -> 306837184

Sheet Lafourche
D1: Lafourche Combined Balance Sheet
D2: Issued: December 31, 2014
O4: Major Funds
K5: General | L5: Roads and Bridges | M5: Drainage | N5: Solid Waste | O5: Library Commission | P5: 2005 Road Construction | Q5: Capital Projects Fund | R5: Non-Major Funds | S5: Total
A6: Assets:
B7: Cash and cash equivalents | K7: 2764394 | O7: 980438 | P7: 12537521 | R7: 3883292 | S7: =SUM(K7:R7) -> 20165645
B8: Investments | K8: 91 | L8: 4486 | M8: 642 | N8: 869499 | O8: 6974174 | P8: 11701 | R8: 13783411 | S8: =SUM(K8:R8) -> 21644004
B9: Receivables | K9: 1029659 | L9: 192240 | N9: 82715 | O9: 35918 | R9: 1422953 | S9: =SUM(K9:R9) -> 2763485
B10: Due from other governmental units | K10: 3167286 | L10: 4158782 | M10: 5655254 | N10: 756188 | O10: 5708241 | R10: 11217817 | S10: =SUM(K10:R10) -> 30663568
B11: Due from other funds | K11: 11180364 | N11: 1144799 | O11: 108889 | Q11: 598882 | R11: 11229235 | S11: =SUM(K11:R11) -> 24262169
B12: Other current assets | R12: 1470429 | S12: =SUM(K12:R12) -> 1470429
B13: Prepaid assets | K13: 1089087 | S13: =SUM(K13:R13) -> 1089087
E15: Total Assets: | K15: =SUM(K7:K13) -> 19230881 | L15: =SUM(L7:L13) -> 4355508 | M15: =SUM(M7:M13) -> 5655896 | N15: =SUM(N7:N13) -> 2853201 | O15: =SUM(O7:O13) -> 13807660 | P15: =SUM(P7:P13) -> 12549222 | Q15: =SUM(Q7:Q13) -> 598882 | R15: =SUM(R7:R13) -> 43007137 | S15: =SUM(S7:S13) -> 102058387
A17: LIABILITIES AND FUND BALANCES
B18: Liabilities:
C19: Accounts payable and accrued expenses | K19: 186024 | L19: 43799 | M19: 121653 | N19: 646399 | O19: 48872 | P19: 209772 | Q19: 416277 | R19: 473489 | S19: =SUM(K19:R19) -> 2146285
C20: Contracts and retainages payable | K20: 71874 | O20: 19222 | P20: 929260 | Q20: 423051 | R20: 823359 | S20: =SUM(K20:R20) -> 2266766
C21: Salaries and benefits payable | K21: 100484 | L21: 191744 | M21: 144005 | N21: 11030 | O21: 204237 | R21: 285311 | S21: =SUM(K21:R21) -> 936811
C22: Due to other funds | K22: 14758087 | L22: 2046507 | M22: 2438233 | P22: 783776 | R22: 4462221 | S22: =SUM(K22:R22) -> 24488824
C23: Due to other governmental units | K23: 158493 | L23: 12572 | O23: 1421 | P23: 164 | Q23: 9297 | R23: 751197 | S23: =SUM(K23:R23) -> 933144
C24: Other current liabilities | R24: 571425 | S24: =SUM(K24:R24) -> 571425
E26: Total liabilities: | K26: =SUM(K19:K24) -> 15274962 | L26: =SUM(L19:L24) -> 2294622 | N26: =SUM(N19:N24) -> 657429 | O26: =SUM(O19:O24) -> 273752 | P26: =SUM(P19:P24) -> 1922972 | Q26: =SUM(Q19:Q24) -> 848625 | R26: =SUM(R19:R24) -> 7367002 | S26: =SUM(S19:S24) -> 31343255
B28: Fund Balances
C29: Non-spendable for prepaid assets | K29: 1089087 | S29: =SUM(K29:R29) -> 1089087
C30: Restricted:
D31: Capital projects | K31: 61175 | M31: 47230 | P31: 10626250 | R31: 1717429 | S31: =SUM(K31:R31) -> 12452084
D32: Judicial programs | R32: 3611261 | S32: =SUM(K32:R32) -> 3611261
D33: Federal and state grant programs | R33: 658167 | S33: =SUM(K33:R33) -> 658167
D34: Debt service | R34: 6338397 | S34: =SUM(K34:R34) -> 6338397
C35: Commited:
D36: Public safety | R36: 1372195 | S36: =SUM(K36:R36) -> 1372195
D37: Public works | L37: 2060886 | M37: 2904775 | N37: 2195772 | R37: 17863463 | S37: =SUM(K37:R37) -> 25024896
D38: Culture and recreation | O38: 13533908 | R38: 1945436 | S38: =SUM(K38:R38) -> 15479344
D39: Health and community services | R39: 2147643 | S39: =SUM(K39:R39) -> 2147643
C40: Unassigned | K40: 2805657 | Q40: -249743 | R40: -10856 | S40: =SUM(K40:R40) -> 2545058
E42: Total fund balance: | K42: =SUM(K29:K41) -> 3955919 | L42: =SUM(L29:L40) -> 2060886 | M42: =SUM(M29:M40) -> 2952005 | N42: =SUM(N29:N40) -> 2195772 | O42: =SUM(O29:O40) -> 13533908 | P42: =SUM(P29:P40) -> 10626250 | Q42: =SUM(Q29:Q40) -> -249743 | R42: =SUM(R29:R40) -> 35643135 | S42: =SUM(S29:S40) -> 70718132
E44: Total liabilities and fund balances: | K44: =SUM(K42,K26) -> 19230881 | L44: =SUM(L26,L42) -> 4355508 | M44: =SUM(M26,M42) -> 2952005 | N44: =SUM(N26,N42) -> 2853201 | O44: =SUM(O26,O42) -> 13807660 | P44: =SUM(P26,P42) -> 12549222 | Q44: =SUM(Q26,Q42) -> 598882 | R44: =SUM(R26,R42) -> 43010137 | S44: =SUM(S26,S42) -> 102061387

Sheet LaSalle
D1: LaSalle Combined Balance Sheet
D2: Issued: December 31, 2014
K4: General Fund | L4: Road and Bridge | M4: Courthouse Maintenance | N4: Garbage District | O4: Library | P4: Criminal Court | Q4: Other Governmental Funds | R4: Total Governmental Funds
A5: Assets:
B6: Cash and equivalents | K6: 514070 | N6: 50133 | O6: 1127875 | Q6: 870550 | R6: =SUM(K6:Q6) -> 2562628
B7: Prepaid lease payments | L7: 4283 | N7: 3783 | Q7: 4374 | R7: =SUM(K7:Q7) -> 12440
B8: Receivables | K8: 1344835 | L8: 726976 | M8: 551388 | N8: 688318 | O8: 644365 | P8: 4833 | Q8: 706467 | R8: =SUM(K8:Q8) -> 4667182
E10: Total assets: | K10: =SUM(K6:K8) -> 1858905 | L10: =SUM(L6:L8) -> 731259 | M10: =SUM(M6:M8) -> 551388 | N10: =SUM(N6:N8) -> 742234 | O10: =SUM(O6:O8) -> 1772240 | P10: =SUM(P6:P8) -> 4833 | Q10: =SUM(Q6:Q8) -> 1581391 | R10: =SUM(R6:R8) -> 7242250
A12: LIABILITIES AND FUND BALANCES
B13: Liabilities:
C14: Cash overdraft | L14: 355829 | M14: 148327 | P14: 212407 | Q14: 16819 | R14: =SUM(K14:Q14) -> 733382
C15: Accounts payable | K15: 959716 | L15: 34564 | M15: 33257 | N15: 49982 | O15: 22817 | P15: 10666 | Q15: 46499 | R15: =SUM(K15:Q15) -> 1157501
C16: Salaries and related payable | K16: 31154 | L16: 8829 | M16: 897 | N16: 2343 | O16: 2514 | P16: 3272 | Q16: 323 | R16: =SUM(K16:Q16) -> 49332
E18: Total liabilities: | K18: =SUM(K14:K16) -> 990870 | L18: =SUM(L14:L16) -> 399222 | M18: =SUM(M14:M16) -> 182481 | N18: =SUM(N14:N16) -> 52325 | O18: =SUM(O14:O16) -> 25331 | P18: =SUM(P14:P16) -> 226345 | Q18: =SUM(Q14:Q16) -> 63641 | R18: =SUM(R14:R16) -> 1940215
B20: Fund Balances:
C21: Nonspendable | Q21: 4374 | R21: =SUM(K21:Q21) -> 4374
C22: Restricted:
D23: Other general government | M23: 368907 | P23: -221512 | R23: =SUM(K23:Q23) -> 147395
D24: Public works | L24: 332037 | N24: 689909 | Q24: 1211014 | R24: =SUM(K24:Q24) -> 2232960
D25: Health and welfare | Q25: 217935 | R25: =SUM(K25:Q25) -> 217935
D26: Culture and recreation | O26: 1746909 | R26: =SUM(K26:Q26) -> 1746909
C27: Committed | Q27: 84427 | R27: =SUM(K27:Q27) -> 84427
C28: Unassigned | K28: 868035 | R28: =SUM(K28:Q28) -> 868035
E30: Total Fund Equity- fund balances (deficit) | K30: =SUM(K21:K28) -> 868035 | L30: =SUM(L21:L28) -> 332037 | M30: =SUM(M21:M28) -> 368907 | N30: =SUM(N21:N28) -> 689909 | O30: =SUM(O21:O28) -> 1746909 | P30: =SUM(P21:P28) -> -221512 | Q30: =SUM(Q21:Q28) -> 1517750 | R30: =SUM(R21:R28) -> 5302035
E32: Total liabilities and fund balances: | K32: =K30+K18 -> 1858905 | L32: =L30+L18 -> 731259 | M32: =M30+M18 -> 551388 | N32: =N30+N18 -> 742234 | O32: =O30+O18 -> 1772240 | P32: =P30+P18 -> 4833 | Q32: =Q30+Q18 -> 1581391 | R32: =R30+R18 -> 7242250

Sheet Lincoln
D1: Lincoln Combined Balance Sheet
D2: Issued: December 31, 2014
K4: General Fund | L4: Road Construction Fund | M4: Road Maintenance Fund | N4: Library Fund | O4: Solid Waste Disposal Fund | P4: Solid Waste Disposal Equipment Reserve Fund | Q4: Hospital Proceeds Fund | R4: Nonmajor Governmental Funds | S4: Total Governmental Funds
A5: Assets:
B6: Cash and cash equivalents | K6: 204938 | L6: 1865824 | M6: 1265229 | N6: 419959 | O6: 38202 | P6: 114368 | Q6: 374947 | R6: 5184418 | S6: =SUM(K6:R6) -> 9467885
B7: Investments | K7: 2057619 | L7: 536000 | M7: 1012717 | N7: 2420098 | P7: 2970546 | Q7: 9975070 | R7: 3499446 | S7: =SUM(K7:R7) -> 22471496
B8: Receivables | K8: 1160680 | L8: 1647472 | M8: 1647018 | N8: 1848613 | O8: 601420 | P8: 2400 | R8: 758403 | S8: =SUM(K8:R8) -> 7666006
B9: Prepaid expenses | K9: 5155 | L9: 1332 | M9: 1332 | S9: =SUM(K9:R9) -> 7819
B10: Due from other funds | K10: 1135940 | L10: 4619 | M10: 4624 | O10: 4327 | R10: 817628 | S10: =SUM(K10:R10) -> 1967138
B11: Due from other entities | K11: 788916 | R11: 25082 | S11: =SUM(K11:R11) -> 813998
B12: Inventory | L12: 11582 | S12: =SUM(K12:N12) -> 11582
E14: Total Assets: | K14: =SUM(K6:K12) -> 5353248 | L14: =SUM(L6:L12) -> 4066829 | M14: =SUM(M6:M12) -> 3930920 | N14: =SUM(N6:N12) -> 4688670 | O14: =SUM(O6:O12) -> 643949 | P14: =SUM(P6:P12) -> 3087314 | Q14: =SUM(Q6:Q12) -> 10350017 | R14: =SUM(R6:R12) -> 10284977 | S14: =SUM(S6:S12) -> 42405924
A16: LIABILITIES AND FUND BALANCES
B17: Liabilities:
C18: Accounts payable | K18: 327241 | L18: 52872 | M18: 52856 | N18: 119766 | O18: 593193 | Q18: 1985 | R18: 107160 | S18: =SUM(K18:R18) -> 1255073
C19: Due to other funds | K19: 1220242 | Q19: 348032 | R19: 398864 | S19: =SUM(K19:R19) -> 1967138
C20: Due to other entities | K20: 440046 | R20: 280914 | S20: =SUM(K20:R20) -> 720960
E22: Total liabilities: | K22: =SUM(K18:K20) -> 1987529 | L22: =SUM(L18:L20) -> 52872 | M22: =SUM(M18:M20) -> 52856 | N22: =SUM(N18:N20) -> 119766 | O22: =SUM(O18:O20) -> 593193 | P22: =SUM(P18:P20) -> 0 | Q22: =SUM(Q18:Q20) -> 350017 | R22: =SUM(R18:R20) -> 786938 | S22: =SUM(S18:S20) -> 3943171
B24: Fund Balances
C25: Nonspendable | K25: 5155 | L25: 11582 | S25: =SUM(K25:R25) -> 16737
C26: Restricted | R26: 432059 | S26: =SUM(K26:R26) -> 432059
C27: Committed | S27: =SUM(K27:R27) -> 0
C28: Assigned | L28: 4002375 | M28: 3878064 | N28: 4568904 | O28: 50756 | P28: 3087314 | Q28: 10000000 | R28: 9065980 | S28: =SUM(K28:R28) -> 34653393
C29: Unassigned | K29: 3360564 | S29: =SUM(K29:N29) -> 3360564
E31: Total fund equity | K31: =SUM(K25:K30) -> 3365719 | L31: =SUM(L25:L29) -> 4013957 | M31: =SUM(M25:M29) -> 3878064 | N31: =SUM(N25:N29) -> 4568904 | O31: =SUM(O25:O29) -> 50756 | P31: =SUM(P25:P29) -> 3087314 | Q31: =SUM(Q25:Q29) -> 10000000 | R31: =SUM(R25:R29) -> 9498039 | S31: =SUM(S24:S29) -> 38462753
E33: Total liabilities and fund equity | K33: =K31+K22 -> 5353248 | L33: =L31+L22 -> 4066829 | M33: =M31+M22 -> 3930920 | N33: =N31+N22 -> 4688670 | O33: =O31+O22 -> 643949 | P33: =P31+P22 -> 3087314 | Q33: =Q31+Q22 -> 10350017 | R33: =R31+R22 -> 10284977 | S33: =S31+S22 -> 42405924

Sheet Livingston
D1: Livingston Combined Balance Sheet
D2: Issued: December 31, 2014
K4: Major Funds
K5: General Fund | L5: Health Unit Fund | M5: Jail Sales Tax Fund | N5: Road Fund | O5: Courthouse Capital Project Fund | P5: Road 06 Sinking Fund | Q5: Other Governemntal Funds | R5: Total Governmental Funds
A6: Assets:
B7: Cash and cash equivalents | K7: 159272 | L7: 1928496 | N7: 4158134 | Q7: 3479585 | R7: =SUM(K7:Q7) -> 9725487
B8: Pooled Cash in Other Funds | K8: 1550475 | R8: =SUM(K8:Q8) -> 1550475
B9: Investments | K9: 71236 | L9: 3068115 | N9: 268772 | R9: =SUM(K9:Q9) -> 3408123
B10: Receivables, net of allowance | K10: 487999 | L10: 80 | M10: 49 | N10: 1070 | Q10: 424735 | R10: =SUM(K10:Q10) -> 913933
B11: Restricted assets: | R11: =SUM(K11:Q11) -> 0
C12: Cash | K12: 90364 | O12: 1161340 | P12: 3471867 | Q12: 4051023 | R12: =SUM(K12:Q12) -> 8774594
B13: Inventory | M13: 14210 | N13: 213055 | R13: =SUM(K13:Q13) -> 227265
B14: Prepaid expenses | N14: 132881 | R14: =SUM(K14:Q14) -> 132881
B15: Due from component units | Q15: 116951 | R15: =SUM(K15:Q15) -> 116951
B16: Due from other funds | K16: 4026470 | N16: 1388509 | Q16: 153329 | R16: =SUM(K16:Q16) -> 5568308
B17: Due from other governments | K17: 1883691 | L17: 1829439 | M17: 690606 | N17: 4351426 | Q17: 1579017 | R17: =SUM(K17:Q17) -> 10334179
B18: Advance to jail sales tax fund | K18: 3431708 | L18: 300000 | R18: =SUM(K18:Q18) -> 3731708
E20: Total Assets: | K20: =SUM(K7:K18) -> 11701215 | L20: =SUM(L7:L18) -> 7126130 | M20: =SUM(M7:M18) -> 704865 | N20: =SUM(N7:N18) -> 10513847 | O20: =SUM(O7:O18) -> 1161340 | P20: =SUM(P7:P18) -> 3471867 | Q20: =SUM(Q7:Q18) -> 9804640 | R20: =SUM(R7:R18) -> 44483904
A22: LIABILITIES AND FUND BALANCES
B23: Liabilities:
C24: Accounts payables | K24: 625412 | L24: 30450 | M24: 77101 | N24: 221383 | O24: 1228560 | Q24: 1080409 | R24: =SUM(K24:Q24) -> 3263315
C25: Deficit in Pooled Cash | M25: 1548516 | Q25: 1959 | R25: =SUM(K25:Q25) -> 1550475
C26: Accrued expenses payable | K26: 196958 | L26: 45752 | M26: 31196 | N26: 243134 | Q26: 18990 | R26: =SUM(K26:Q26) -> 536030
C27: Due to component units | Q27: 136508 | R27: =SUM(K27:Q27) -> 136508
C28: Due to other governments | K28: 217430 | L28: 83014 | M28: 54063 | N28: 120634 | Q28: 28161 | R28: =SUM(K28:Q28) -> 503302
C29: Due to other funds | K29: 991277 | L29: 227549 | M29: 2624842 | N29: 1303434 | Q29: 398823 | R29: =SUM(K29:Q29) -> 5545925
C30: Unearned revenue | K30: 19700 | R30: =SUM(K30:Q30) -> 19700
C31: Advances from other funds | M31: 3731708 | R31: =SUM(K31:Q31) -> 3731708
E33: Total liabilities: | K33: =SUM(K24:K31) -> 2050777 | L33: =SUM(L24:L31) -> 386765 | M33: =SUM(M24:M31) -> 8067426 | N33: =SUM(N24:N31) -> 1888585 | O33: =SUM(O24:O31) -> 1228560 | P33: =SUM(P24:P31) -> 0 | Q33: =SUM(Q24:Q31) -> 1664850 | R33: =SUM(R24:R31) -> 15286963
B35: Fund Balances
C36: Non-spendable:
D37: Inventory | M37: 14210 | N37: 213055 | R37: =SUM(K37:Q37) -> 227265
D38: Advances | K38: 3431708 | L38: 300000 | R38: =SUM(K38:Q38) -> 3731708
C39: Restricted for:
D40: Construction | Q40: 2452531 | R40: =SUM(K40:Q40) -> 2452531
D41: Criminal court | Q41: 58414 | R41: =SUM(K41:Q41) -> 58414
D42: Criminal court witness | Q42: 33480 | R42: =SUM(K42:Q42) -> 33480
D43: Debt service | P43: 3471867 | Q43: 5052388 | R43: =SUM(K43:Q43) -> 8524255
D44: Grant expenditures | K44: 90364 | R44: =SUM(K44:Q44) -> 90364
C45: Commited to:
D46: Construction | N46: 467590 | R46: =SUM(K46:Q46) -> 467590
D47: State grant programs | N47: 448367 | R47: =SUM(K47:Q47) -> 448367
D48: Federal grant programs | K48: 22500 | R48: =SUM(K48:Q48) -> 22500
D49: Other purposes | K49: 15233 | R49: =SUM(K49:Q49) -> 15233
C50: Assigned to:
D51: Bingo | Q51: 1925 | R51: =SUM(K51:Q51) -> 1925
D52: Construction | Q52: 242461 | R52: =SUM(K52:Q52) -> 242461
D53: Court fees | Q53: 396353 | R53: =SUM(K53:Q53) -> 396353
D54: Health unit | L54: 6439365 | R54: =SUM(K54:Q54) -> 6439365
D55: Road | N55: 7496250 | R55: =SUM(K55:Q55) -> 7496250
D56: Other purposes | K56: 248113 | R56: =SUM(K56:Q56) -> 248113
C57: Unassigned | K57: 5842520 | M57: -7376771 | O57: -67220 | Q57: -97762 | R57: =SUM(K57:Q57) -> -1699233
E59: Total fund balances (Deficits): | K59: =SUM(K36:K58) -> 9650438 | L59: =SUM(L37:L57) -> 6739365 | M59: =SUM(M36:M57) -> -7362561 | N59: =SUM(N37:N57) -> 8625262 | O59: =SUM(O37:O57) -> -67220 | P59: =SUM(P37:P57) -> 3471867 | Q59: =SUM(Q37:Q57) -> 8139790 | R59: =SUM(R37:R57) -> 29196941
E61: Total liabilities and fund balances (Deficits): | K61: =SUM(K59,K33) -> 11701215 | L61: =SUM(L33,L59) -> 7126130 | M61: =SUM(M33,M59) -> 704865 | N61: =SUM(N33,N59) -> 10513847 | O61: =SUM(O33,O59) -> 1161340 | P61: =SUM(P33,P59) -> 3471867 | Q61: =SUM(Q33,Q59) -> 9804640 | R61: =SUM(R33,R59) -> 44483904

Sheet Madison
D1: Madison Combined Balance Sheet
D2: Issued: December 31, 2014
K5: General Fund | L5: Library | M5: Garbage Maintenance | N5: Health Unit | O5: Public Works | P5: Courthouse and Jail | Q5: Other Governmental Funds | R5: Total
A6: Assets:
B7: Cash and cash equivalents | K7: 261440 | L7: 596418 | M7: 891535 | N7: 967005 | O7: 116974 | P7: 2459729 | Q7: 767032 | R7: =SUM(K7:Q7) -> 6060133
B8: Investments | L8: 263635 | P8: 2035614 | Q8: 673193 | R8: =SUM(K8:Q8) -> 2972442
B9: Receivables | K9: 462351 | L9: 495127 | M9: 466589 | N9: 243533 | O9: 1595525 | P9: 1279219 | Q9: 334508 | R9: =SUM(K9:Q9) -> 4876852
B10: Interfund receivables | K10: 247391 | L10: 250 | M10: 292115 | P10: 855 | R10: =SUM(K10:Q10) -> 540611
E12: Total Assets: | K12: =SUM(K7:K10) -> 971182 | L12: =SUM(L7:L10) -> 1355430 | M12: =SUM(M7:M10) -> 1650239 | N12: =SUM(N7:N10) -> 1210538 | O12: =SUM(O7:O10) -> 1712499 | P12: =SUM(P7:P10) -> 5775417 | Q12: =SUM(Q7:Q10) -> 1774733 | R12: =SUM(R7:R10) -> 14450038
A14: LIABILITIES AND FUND BALANCES
B15: Liabilities:
C16: Accounts, salaries and other payables | K16: 126005 | L16: 6605 | M16: 6049 | N16: 85 | O16: 10792 | P16: 38659 | Q16: 75339 | R16: 263534
C17: Interfund payables | O17: 292115 | Q17: 248496 | R17: =SUM(K17:Q17) -> 540611
E19: Total liabilities: | K19: =SUM(K16:K17) -> 126005 | L19: =SUM(L16:L17) -> 6605 | M19: =SUM(M16:M17) -> 6049 | N19: =SUM(N16:N17) -> 85 | O19: =SUM(O16:O17) -> 302907 | P19: =SUM(P16:P17) -> 38659 | Q19: =SUM(Q16:Q17) -> 323835 | R19: =SUM(R16:R17) -> 804145
B21: Fund Balances
C22: Restricted | L22: 1348825 | M22: 1644190 | N22: 1210453 | O22: 1409592 | P22: 5736758 | Q22: 1450898 | R22: =SUM(K22:Q22) -> 12800716
C23: Unassigned | K23: 845177 | R23: =SUM(K23:Q23) -> 845177
E25: Total fund balances: | K25: =SUM(K22:K24) -> 845177 | L25: =SUM(L22:L23) -> 1348825 | M25: =SUM(M22:M23) -> 1644190 | N25: =SUM(N22:N23) -> 1210453 | O25: =SUM(O22:O23) -> 1409592 | P25: =SUM(P22:P23) -> 5736758 | Q25: =SUM(Q22:Q23) -> 1450898 | R25: =SUM(R22:R23) -> 13645893
E27: Total liabilities and fund balances: | K27: =K25+K19 -> 971182 | L27: =L25+L19 -> 1355430 | M27: =M25+M19 -> 1650239 | N27: =N25+N19 -> 1210538 | O27: =O25+O19 -> 1712499 | P27: =P25+P19 -> 5775417 | Q27: =Q25+Q19 -> 1774733 | R27: =R25+R19 -> 14450038

Sheet Morehouse
D1: Morehouse Combined Balance Sheet
D2: Issued: December 31, 2014
K5: General | L5: Road Maintenance | M5: Drainage Maintenance | N5: Building Maintenance | O5: Solid Waste | P5: Health Unit | Q5: Criminal Court | R5: Other Governmental Funds | S5: Total Governmental Funds
A6: Assets:
B7: Cash | L7: 751280 | M7: 1132860 | O7: 1366807 | P7: 669396 | R7: 289649 | S7: =SUM(K7:R7) -> 4209992
B8: Investments | K8: 25000 | L8: 100000 | M8: 375000 | P8: 25000 | R8: 15000 | S8: =SUM(K8:R8) -> 540000
B9: Receivables | K9: 599680 | L9: 837653 | M9: 352201 | N9: 224142 | P9: 138114 | Q9: 9798 | R9: 82097 | S9: =SUM(K9:R9) -> 2243685
B10: Due from other Funds | K10: 1686 | L10: 2559 | M10: 2384 | N10: 16887 | O10: 2534 | P10: 230 | Q10: 1531 | S10: =SUM(K10:R10) -> 27811
E12: Total Assets: | K12: =SUM(K7:K10) -> 626366 | L12: =SUM(L7:L10) -> 1691492 | M12: =SUM(M7:M10) -> 1862445 | N12: =SUM(N7:N10) -> 241029 | O12: =SUM(O7:O10) -> 1369341 | P12: =SUM(P7:P10) -> 832740 | Q12: =SUM(Q7:Q10) -> 11329 | R12: =SUM(R7:R10) -> 386746 | S12: =SUM(S7:S10) -> 7021488
A14: LIABILITIES
C15: Bank overdraft | K15: 1541795 | N15: 242542 | Q15: 361541 | S15: =SUM(K15:R15) -> 2145878
C16: Accounts payable | K16: 148143 | L16: 17744 | M16: 4965 | N16: 27192 | O16: 47648 | P16: 1298 | Q16: 234 | R16: 3413 | S16: =SUM(K16:R16) -> 250637
C17: Payroll accruals and withholdings | K17: 23353 | Q17: 4292 | S17: =SUM(K17:R17) -> 27645
C18: Due to other funds | K18: 9108 | L18: 1962 | P18: 16741 | S18: =SUM(K18:R18) -> 27811
E20: Total liabilities: | K20: =SUM(K15:K18) -> 1722399 | L20: =SUM(L15:L18) -> 19706 | M20: =SUM(M15:M18) -> 4965 | N20: =SUM(N15:N18) -> 269734 | O20: =SUM(O15:O18) -> 47648 | P20: =SUM(P15:P18) -> 18039 | Q20: =SUM(Q15:Q18) -> 366067 | R20: =SUM(R15:R18) -> 3413 | S20: =SUM(S15:S18) -> 2451971
A22: DEFERRED INFLOWS OF RESOURCES
C23: Property taxes | K23: 523992 | L23: 773139 | M23: 353324 | N23: 224455 | P23: 138555 | R23: 78982 | S23: =SUM(K23:R23) -> 2092447
B25: Fund Balances
C26: Restricted for special revenue | L26: 898647 | M26: 1504156 | O26: 1321693 | P26: 676146 | R26: 304351 | S26: =SUM(K26:R26) -> 4704993
C27: Unassigned for special revenue (deficit) | N27: -253160 | Q27: -354738 | S27: =SUM(K27:R27) -> -607898
C28: Unassigned (deficit) | K28: -1620025 | S28: =SUM(K28:R28) -> -1620025
E30: Total fund balance: | K30: =SUM(K26:K29) -> -1620025 | L30: =SUM(L26:L28) -> 898647 | M30: =SUM(M26:M28) -> 1504156 | N30: =SUM(N26:N28) -> -253160 | O30: =SUM(O26:O28) -> 1321693 | P30: =SUM(P26:P28) -> 676146 | Q30: =SUM(Q26:Q28) -> -354738 | R30: =SUM(R26:R28) -> 304351 | S30: =SUM(S26:S28) -> 2477070
E32: Total liabilities, deferred inflows of resources, and fund balances: | K32: =K30+K23+K20 -> 626366 | L32: =L30+L23+L20 -> 1691492 | M32: =M30+M23+M20 -> 1862445 | N32: =N30+N23+N20 -> 241029 | O32: =O30+O23+O20 -> 1369341 | P32: =P30+P23+P20 -> 832740 | Q32: =Q30+Q23+Q20 -> 11329 | R32: =R30+R23+R20 -> 386746 | S32: =S30+S23+S20 -> 7021488

Sheet Natchitoches (2)
D1: Natchitoches Combined Balance Sheet
D2: Issued: December 31, 2014
K4: Major Funds
K5: General Fund | L5: Road Maintenance Fund | M5: Sales Tax Fund | N5: Parish Library Fund | O5: Disposal Solid Waste | P5: Government Building Fund | Q5: Head Start Fund | R5: Nonmajor Funds | S5: Total Governmental Funds
A6: Assets:
B7: Cash and cash equivalents | K7: 740202 | L7: 683790 | M7: 1921386 | N7: 1683883 | O7: 108865 | P7: 1017047 | Q7: 2212 | R7: 1180560 | S7: =SUM(K7:R7) -> 7337945
B8: Revenue receivables | K8: 849011 | L8: 1283183 | M8: 232861 | N8: 1973416 | P8: 803950 | R8: 949786 | S8: =SUM(K8:R8) -> 6092207
E10: Total Assets: | K10: =SUM(K7:K8) -> 1589213 | L10: =SUM(L7:L8) -> 1966973 | M10: =SUM(M7:M8) -> 2154247 | N10: =SUM(N7:N8) -> 3657299 | O10: =SUM(O7:O8) -> 108865 | P10: =SUM(P7:P8) -> 1820997 | Q10: =SUM(Q7:Q8) -> 2212 | R10: =SUM(R7:R8) -> 2130346 | S10: =SUM(S7:S8) -> 13430152
A12: LIABILITIES
C13: Cash overdraft | Q13: 4453 | R13: 5562 | S13: =SUM(K13:R13) -> 10015
C14: Accounts payable | K14: 323400 | L14: 37501 | N14: 38575 | O14: 96352 | P14: 10444 | Q14: 12478 | R14: 45539 | S14: =SUM(K14:R14) -> 564289
C15: Accrued Payroll | L15: 23700 | N15: 8996 | O15: 20897 | P15: 3363 | Q15: 2562 | R15: 16458 | S15: =SUM(K15:R15) -> 75976
C16: Due to Other Governments | R16: 834223 | S16: =SUM(K16:R16) -> 834223
E18: Total liabilities: | K18: =SUM(K13:K15) -> 323400 | L18: =SUM(L13:L15) -> 61201 | M18: =SUM(M13:M15) -> 0 | N18: =SUM(N13:N15) -> 47571 | O18: =SUM(O13:O15) -> 117249 | P18: =SUM(P13:P15) -> 13807 | Q18: =SUM(Q13:Q15) -> 19493 | R18: =SUM(R13:R16) -> 901782 | S18: =SUM(S13:S16) -> 1484503
B20: Fund Balances
C21: Restricted | L21: 1905772 | M21: 2154247 | N21: 3609728 | P21: 1807190 | R21: 2057911 | S21: =SUM(K21:R21) -> 11534848
C22: Unassigned | K22: 1265813 | O22: -8384 | Q22: -17281 | R22: -829347 | S22: =SUM(K22:R22) -> 410801
E24: Total fund balance: | K24: =SUM(K21:K22) -> 1265813 | L24: =SUM(L21:L22) -> 1905772 | M24: =SUM(M21:M22) -> 2154247 | N24: =SUM(N21:N22) -> 3609728 | O24: =SUM(O21:O22) -> -8384 | P24: =SUM(P21:P22) -> 1807190 | Q24: =SUM(Q21:Q22) -> -17281 | R24: =SUM(R21:R22) -> 1228564 | S24: =SUM(S21:S22) -> 11945649
E26: Total liabilities and fund balances: | K26: =K24+K18 -> 1589213 | L26: =L24+L18 -> 1966973 | M26: =M24+M18 -> 2154247 | N26: =N24+N18 -> 3657299 | O26: =O24+O18 -> 108865 | P26: =P24+P18 -> 1820997 | Q26: =Q24+Q18 -> 2212 | R26: =R24+R18 -> 2130346 | S26: =S24+S18 -> 13430152

Sheet Natchitoches
D1: Natchitoches Combined Balance Sheet
D2: Issued: May 31, 2014
K4: Major Funds
K5: General Fund | L5: Capital Projects Sales Tax Fund | M5: Nonmajor Funds | N5: Total Governmental Funds
A6: Assets:
B7: Cash and cash equivalents | K7: 2371039 | L7: 16258872 | M7: 9989308 | N7: =SUM(K7:M7) -> 28619219
B8: Revenue receivables | K8: 448711 | L8: 314192 | M8: 1319044 | N8: =SUM(K8:M8) -> 2081947
B9: Due from other Funds | N9: =SUM(K9:M9) -> 0
B10: Inventory | M10: 28871 | N10: =SUM(K10:M10) -> 28871
B11: Prepaid Expenses | K11: 7575 | M11: 3415 | N11: =SUM(K11:M11) -> 10990
E13: Total Assets: | K13: =SUM(K7:K11) -> 2827325 | L13: =SUM(L7:L11) -> 16573064 | M13: =SUM(M7:M11) -> 11340638 | N13: =SUM(N7:N11) -> 30741027
A15: LIABILITIES
C16: Cash overdraft | M16: 1234953 | N16: =SUM(K16:M16) -> 1234953
C17: Accounts payable | K17: 82957 | L17: 123191 | M17: 570179 | N17: =SUM(K17:M17) -> 776327
C18: Accrued expenses | K18: 500245 | L18: 133576 | M18: 432680 | N18: =SUM(K18:M18) -> 1066501
C19: Due to other funds | N19: =SUM(K19:M19) -> 0
C20: Accrued Payroll | K20: 207685 | M20: 8848 | N20: =SUM(K20:M20) -> 216533
E22: Total liabilities: | K22: =SUM(K16:K20) -> 790887 | L22: =SUM(L16:L20) -> 256767 | M22: =SUM(M16:M20) -> 2246660 | N22: =SUM(N16:N20) -> 3294314
B24: Fund Balances
C25: Nonspendable | K25: 7575 | M25: 3415 | N25: =SUM(K25:M25) -> 10990
C26: Restricted | L26: 16316297 | M26: 2493057 | N26: =SUM(K26:M26) -> 18809354
C27: Committed | M27: 7883342 | N27: =SUM(K27:M27) -> 7883342
C28: Unassigned | K28: 2028863 | M28: -1285836 | N28: =SUM(K28:M28) -> 743027
E30: Total fund balance: | K30: =SUM(K25:K28) -> 2036438 | L30: =SUM(L25:L28) -> 16316297 | M30: =SUM(M25:M28) -> 9093978 | N30: =SUM(N25:N28) -> 27446713
E32: Total liabilities and fund balances: | K32: =K30+K22 -> 2827325 | L32: =L30+L22 -> 16573064 | M32: =M30+M22 -> 11340638 | N32: =N30+N22 -> 30741027

Sheet Orleans
D1: Orleans Combined Balance Sheet
D2: Issued: December 31, 2014
I3: (amounts in thousands)
K5: General Fund | L5: HUD | M5: Federal UDAG | N5: FEMA | O5: Debt Service | P5: Capital Projects | Q5: Louisiana Office of Community Development | R5: Nonmajor Governmental | S5: Total Governmental Funds
A6: Assets:
B7: Cash and cash equivalents | K7: 24006 | L7: 3 | M7: 12775 | O7: 326 | P7: 29203 | Q7: 1269 | R7: 23454 | S7: =SUM(K7:R7) -> 91036
B8: Investments | K8: 768 | O8: 74526 | P8: 103615 | R8: 11116 | S8: =SUM(K8:R8) -> 190025
B9: Receivables (net of allowance for uncollectibles): | S9: =SUM(K9:R9) -> 0
C10: Sales taxes | K10: 17642 | S10: =SUM(K10:R10) -> 17642
C11: Property taxes | K11: 4835 | O11: 2970 | R11: 451 | S11: =SUM(K11:R11) -> 8256
C12: Franchise taxes | K12: 6695 | S12: =SUM(K12:R12) -> 6695
C13: Accounts | K13: 11649 | L13: 153 | P13: 10 | Q13: 446 | R13: 2347 | S13: =SUM(K13:R13) -> 14605
C14: Grantee loans | M14: 658 | S14: =SUM(K14:R14) -> 658
B15: Due from other funds | K15: 18337 | N15: 3934 | R15: 1306 | S15: =SUM(K15:R15) -> 23577
B16: Due from other governments | K16: 1812 | L16: 6810 | N16: 8729 | P16: 27285 | Q16: 6088 | R16: 5814 | S16: =SUM(K16:R16) -> 56538
B17: Due from component units | K17: 4423 | P17: 10467 | S17: =SUM(K17:R17) -> 14890
B18: Advances to other funds | K18: 2 | S18: =SUM(K18:R18) -> 2
B19: Other assets | K19: 3 | R19: 12 | S19: =SUM(K19:R19) -> 15
E21: Total Assets: | K21: =SUM(K7:K20) -> 90172 | L21: =SUM(L7:L19) -> 6966 | M21: =SUM(M7:M19) -> 13433 | N21: =SUM(N7:N19) -> 12663 | O21: =SUM(O7:O19) -> 77822 | P21: =SUM(P7:P19) -> 170580 | Q21: =SUM(Q7:Q19) -> 7803 | R21: =SUM(R7:R19) -> 44500 | S21: =SUM(S7:S19) -> 423939
A23: LIABILITIES
C24: Accounts payable | K24: 30650 | L24: 5352 | M24: 67 | N24: 1208 | P24: 26297 | Q24: 6547 | R24: 6770 | S24: =SUM(K24:R24) -> 76891
C25: Retainages payable | P25: 3658 | S25: =SUM(K25:R25) -> 3658
C26: Accrued expenses | L26: 132 | M26: 3 | N26: 147 | O26: 17 | Q26: 136 | R26: 241 | S26: =SUM(K26:R26) -> 676
C27: Due to other funds | K27: 55 | L27: 12394 | N27: 3495 | P27: 3939 | R27: 3694 | S27: =SUM(K27:R27) -> 23577
C28: Due to other governments | K28: 1254 | N28: 8462 | Q28: 2153 | R28: 688 | S28: =SUM(K28:R28) -> 12557
C29: Due to component units | K29: 7087 | P29: 59 | S29: =SUM(K29:R29) -> 7146
C30: Advances from other funds | R30: 2 | S30: =SUM(K30:R30) -> 2
E32: Total liabilities: | K32: =SUM(K24:K30) -> 39046 | L32: =SUM(L24:L30) -> 17878 | M32: =SUM(M24:M29) -> 70 | N32: =SUM(N24:N30) -> 13312 | O32: =SUM(O24:O30) -> 17 | P32: =SUM(P24:P31) -> 33953 | Q32: =SUM(Q24:Q30) -> 8836 | R32: =SUM(R24:R30) -> 11395 | S32: =SUM(S24:S30) -> 124507
A34: DEFERRED INFLOWS OF RESOURCES
C35: Unavailable revenue | K35: 8142 | L35: 6396 | N35: 2087 | O35: 4289 | P35: 23141 | Q35: 4079 | R35: 2235 | S35: =SUM(K35:R35) -> 50369
E37: Total deferred inflows of resources: | K37: =SUM(K35) -> 8142 | L37: =SUM(L35) -> 6396 | M37: =SUM(M35) -> 0 | N37: =SUM(N35) -> 2087 | O37: =SUM(O35) -> 4289 | P37: =SUM(P35) -> 23141 | Q37: =SUM(Q35) -> 4079 | R37: =SUM(R35) -> 2235 | S37: =SUM(S35) -> 50369
B39: Fund Balances
C40: Nonspendable | M40: 658 | R40: 974 | S40: =SUM(K40:R40) -> 1632
C41: Restricted | M41: 12705 | O41: 73516 | P41: 51081 | R41: 15504 | S41: =SUM(K41:R41) -> 152806
C42: Committed | K42: 26399 | P42: 62405 | R42: 19192 | S42: =SUM(K42:R42) -> 107996
C43: Assigned | K43: 5970 | R43: 315 | S43: =SUM(K43:R43) -> 6285
C44: Unassigned | K44: 10615 | L44: -17308 | N44: -2736 | Q44: -5112 | R44: -5115 | S44: =SUM(K44:R44) -> -19656
E46: Total fund balance: | K46: =SUM(K40:K45) -> 42984 | L46: =SUM(L41:L44) -> -17308 | M46: =SUM(M40:M44) -> 13363 | N46: =SUM(N41:N44) -> -2736 | O46: =SUM(O40:O44) -> 73516 | P46: =SUM(P40:P44) -> 113486 | Q46: =SUM(Q40:Q44) -> -5112 | R46: =SUM(R40:R44) -> 30870 | S46: =SUM(S39:S44) -> 249063
E48: Total liabilities,deferred inflows of resources, and fund balances: | K48: =SUM(K46+K32+K37) -> 90172 | L48: =SUM(L46+L32+L37) -> 6966 | M48: =SUM(M46+M32+M37) -> 13433 | N48: =SUM(N46+N32+N37) -> 12663 | O48: =SUM(O46+O32+O37) -> 77822 | P48: =SUM(P46+P32+P37) -> 170580 | Q48: =SUM(Q46+Q32+Q37) -> 7803 | R48: =SUM(R46+R32+R37) -> 44500 | S48: =SUM(S46+S32+S37) -> 423939

Sheet Ouachita
D1: Ouachita Combined Balance Sheet
D2: Issued: December 31, 2014
K3: Major Funds | Q3: Aggregate remaining funds
N4: Special Revenue Funds
K5: General Fund 001 | L5: Public Works Fund 102 | M5: Fire Department Fund 104 | N5: Public Library Fund 105 | O5: Correctional Center Fund 110 | P5: Urban System Fund 132 | Q5: Other Governemntal Funds | R5: Total
A6: Assets:
B7: Cash and cash equivalents | K7: 3114148 | L7: 3823534 | M7: 3031680 | N7: 2243976 | O7: 3291518 | P7: 974693 | Q7: 15651508 | R7: =SUM(K7:Q7) -> 32131057
B8: Investments | K8: 3248000 | L8: 1000000 | M8: 7000000 | N8: 2000000 | O8: 1000000 | Q8: 9000000 | R8: =SUM(K8:Q8) -> 23248000
B9: Receivables:
C10: Ad valorem taxes | K10: 2931791 | M10: 9173633 | N10: 7000975 | O10: 8622359 | Q10: 4513380 | R10: =SUM(K10:Q10) -> 32242138
C11: Sales taxes | L11: 1285849 | M11: 1374170 | R11: =SUM(K11:Q11) -> 2660019
C12: Special assessments | L12: 7050 | Q12: 155386 | R12: =SUM(K12:Q12) -> 162436
C13: Other receivables | K13: 441792 | L13: 47745 | M13: 1641 | N13: 23348 | O13: 90123 | Q13: 347992 | R13: =SUM(K13:Q13) -> 952641
B14: Due from other funds | K14: 506144 | R14: =SUM(K14:Q14) -> 506144
B15: Due from other governments | K15: 527267 | N15: 116587 | O15: 372943 | P15: 425156 | Q15: 2222687 | R15: =SUM(K15:Q15) -> 3664640
B16: Prepaid expenses and other assets | K16: 45 | N16: 200 | Q16: 68751 | R16: =SUM(K16:Q16) -> 68996
B17: Inventories | K17: 4768 | L17: 266189 | O17: 104709 | Q17: 164010 | R17: =SUM(K17:Q17) -> 539676
E19: Total Assets: | K19: =SUM(K7:K17) -> 10773955 | L19: =SUM(L7:L17) -> 6430367 | M19: =SUM(M7:M17) -> 20581124 | N19: =SUM(N7:N17) -> 11385086 | O19: =SUM(O7:O17) -> 13481652 | P19: =SUM(P7:P17) -> 1399849 | Q19: =SUM(Q7:Q17) -> 32123714 | R19: =SUM(R7:R17) -> 96175747
A21: LIABILITIES AND FUND EQUITY
B22: Liabilities:
C23: Accounts payable and accrued expenses | K23: 1018691 | L23: 537386 | M23: 991553 | N23: 465402 | O23: 796859 | P23: 471176 | Q23: 2161812 | R23: =SUM(K23:Q23) -> 6442879
C24: Due to other funds | Q24: 421482 | R24: =SUM(K24:Q24) -> 421482
C25: Unearned revenues | K25: 337324 | L25: 27555 | P25: 646887 | Q25: 7489 | R25: =SUM(K25:Q25) -> 1019255
C26: Deposits held | K26: 4870 | L26: 214079 | O26: 2851 | Q26: 12325 | R26: =SUM(K26:Q26) -> 234125
E28: Total liabilities: | K28: =SUM(K23:K26) -> 1360885 | L28: =SUM(L23:L26) -> 779020 | M28: =SUM(M23:M26) -> 991553 | N28: =SUM(N23:N26) -> 465402 | O28: =SUM(O23:O26) -> 799710 | P28: =SUM(P23:P26) -> 1118063 | Q28: =SUM(Q23:Q26) -> 2603108 | R28: =SUM(R23:R26) -> 8117741
B30: Fund Equity
C31: Fund balances
C32: Non-spendable:
D33: Prepaid expenses and other assets | K33: 45 | N33: 200 | Q33: 68751 | R33: =SUM(K33:Q33) -> 68996
D34: Inventories | K34: 4768 | L34: 266189 | O34: 104709 | Q34: 164010 | R34: =SUM(K34:Q34) -> 539676
C35: Spendable:
D36: Restricted | L36: 5385158 | M36: 19589571 | N36: 10919484 | O36: 12577233 | P36: 281786 | Q36: 28150638 | R36: =SUM(K36:Q36) -> 76903870
D37: Committed | K37: 4350574 | Q37: 1137207 | R37: =SUM(K37:Q37) -> 5487781
D38: Unassigned | K38: 5057683 | R38: =SUM(K38:Q38) -> 5057683
E40: Total fund balance: | K40: =SUM(K32:K39) -> 9413070 | L40: =SUM(L33:L38) -> 5651347 | M40: =SUM(M33:M38) -> 19589571 | N40: =SUM(N33:N38) -> 10919684 | O40: =SUM(O33:O38) -> 12681942 | P40: =SUM(P33:P38) -> 281786 | Q40: =SUM(Q33:Q38) -> 29520606 | R40: =SUM(R33:R38) -> 88058006
E42: Total liabilities and fund equity: | K42: =SUM(K40,K28) -> 10773955 | L42: =SUM(L28,L40) -> 6430367 | M42: =SUM(M28,M40) -> 20581124 | N42: =SUM(N28,N40) -> 11385086 | O42: =SUM(O28,O40) -> 13481652 | P42: =SUM(P28,P40) -> 1399849 | Q42: =SUM(Q28,Q40) -> 32123714 | R42: =SUM(R28,R40) -> 96175747

Sheet Plaquemines
D1: Plaquemines Combined Balance Sheet
D2: Issued: December 31, 2014
K5: General Fund | L5: Fire Fighting | M5: FEMA Management | N5: Series 2012 A Coastal Restorations | O5: Series 2012 B Courthouse | P5: Capital Improvements | Q5: Other Governmental Funds | R5: Total Governmental Funds
A6: Assets:
B7: Cash and cash equivalents | K7: 11106929 | L7: 9244202 | N7: 47428971 | O7: 24550837 | Q7: 21033964 | R7: =SUM(K7:Q7) -> 113364903
B8: Investments | K8: 876257 | L8: 93696 | Q8: 3746392 | R8: =SUM(K8:Q8) -> 4716345
B9: Receivables (net of allowances for uncollectibles) | K9: 14447460 | L9: 1286940 | M9: 44844091 | Q9: 10698704 | R9: =SUM(K9:Q9) -> 71277195
B10: Due from other funds | K10: 37397371 | O10: 4000 | Q10: 201754 | R10: =SUM(K10:Q10) -> 37603125
B11: Prepaid items | K11: 1393406 | Q11: 247154 | R11: =SUM(K11:Q11) -> 1640560
B12: Interfund loan | K12: 2073727 | R12: =SUM(K12:P12) -> 2073727
E14: Total Assets: | K14: =SUM(K7:K12) -> 67295150 | L14: =SUM(L7:L12) -> 10624838 | M14: =SUM(M7:M12) -> 44844091 | N14: =SUM(N7:N12) -> 47428971 | O14: =SUM(O7:O12) -> 24554837 | P14: =SUM(P7:P12) -> 0 | Q14: =SUM(Q7:Q12) -> 35927968 | R14: =SUM(R7:R12) -> 230675855
A16: LIABILITIES AND FUND BALANCES
B17: Liabilities:
C18: Accounts, salaries and other payables | K18: 4512564 | L18: 636746 | M18: 2400760 | N18: 482853 | O18: 521820 | Q18: 2526569 | R18: =SUM(K18:Q18) -> 11081312
C19: Compensated absences payable | K19: 722865 | Q19: 369013 | R19: =SUM(K19:Q19) -> 1091878
C20: Unearned revenues | M20: 4944703 | R20: =SUM(K20:Q20) -> 4944703
C21: Deposits due others | K21: 33275 | R21: =SUM(K21:Q21) -> 33275
C22: Due to other funds | K22: 139869 | M22: 33442900 | N22: 290593 | O22: 85389 | Q22: 3644374 | R22: =SUM(K22:Q22) -> 37603125
C23: Other | K23: 625708 | L23: 6267 | Q23: 101025 | R23: =SUM(K23:Q23) -> 733000
E25: Total liabilities: | K25: =SUM(K18:K23) -> 6034281 | L25: =SUM(L18:L23) -> 643013 | M25: =SUM(M18:M23) -> 40788363 | N25: =SUM(N18:N24) -> 773446 | O25: =SUM(O18:O23) -> 607209 | P25: =SUM(P18:P23) -> 0 | Q25: =SUM(Q18:Q23) -> 6640981 | R25: =SUM(R18:R23) -> 55487293
A27: DEFERRED INFLOWS OF RESROUCES
C28: Deferred revenues | K28: 3961641 | P28: 4133456 | Q28: 10403484 | R28: =SUM(K28:Q28) -> 18498581
B30: Fund Balances
C31: Non Spendable | K31: 3344922 | R31: =SUM(K31:Q31) -> 3344922
C32: Restricted | K32: 2246495 | L32: 9237052 | M32: 4055728 | N32: 46655525 | O32: 23947628 | Q32: 21039104 | R32: =SUM(K32:Q32) -> 107181532
C33: Committed | K33: 53699608 | R33: =SUM(K33:Q33) -> 53699608
C34: Assigned | L34: 744773 | Q34: 99658 | R34: =SUM(K34:Q34) -> 844431
C35: Unassigned (Deficit) | K35: -2011795 | P35: -4133456 | Q35: -2255259 | R35: =SUM(K35:Q35) -> -8400510
E37: Total fund balance: | K37: =SUM(K31:K35) -> 57279230 | L37: =SUM(L31:L35) -> 9981825 | M37: =SUM(M31:M35) -> 4055728 | N37: =SUM(N31:N35) -> 46655525 | O37: =SUM(O31:O35) -> 23947628 | P37: =SUM(P31:P35) -> -4133456 | Q37: =SUM(Q31:Q35) -> 18883503 | R37: =SUM(R31:R35) -> 156669983
E39: Total liabilities and fund balances: | K39: =SUM(K37,K25,K28) -> 67275152 | L39: =SUM(L37,L25,L28) -> 10624838 | M39: =SUM(M37,M25,M28) -> 44844091 | N39: =SUM(N37,N25,N28) -> 47428971 | O39: =SUM(O37,O25,O28) -> 24554837 | P39: =SUM(P37,P25,P28) -> 0 | Q39: =SUM(Q37,Q25,Q28) -> 35927968 | R39: =SUM(R37,R25,R28) -> 230655857

Sheet Pointe Couppe 
D1: Pointe Coupee Combined Balance Sheet
D2: Issued: December 31, 2014
K4: General | L4: Parishwide drainage | M4: Roads and Bridges | N4: Pointe Coupee Library (1) | O4: Detention Center | P4: Road Construction | Q4: Debt Service Road Improvement | R4: Other Governmental Funds | S4: Total Governmental Funds
A5: Assets:
B6: Cash and cash equivalents | K6: 119668 | L6: 83428 | M6: 22216 | N6: 1264119 | O6: 32075 | P6: 518294 | Q6: 136805 | R6: 102998 | S6: =SUM(K6:R6) -> 2279603
B7: Investments | N7: 706925 | S7: =SUM(K7:R7) -> 706925
B8: Accounts receivable, net | K8: 1303228 | L8: 134455 | N8: 1591230 | O8: 22017 | Q8: 183478 | R8: 74416 | S8: =SUM(K8:R8) -> 3308824
B9: Due from other governments | K9: 282816 | L9: 345830 | M9: 48201 | Q9: 1411 | R9: 22528 | S9: =SUM(K9:R9) -> 700786
B10: Due from other funds | K10: 1666026 | P10: 95000 | Q10: 1875000 | R10: 250000 | S10: =SUM(K10:R10) -> 3886026
B11: Prepaid items | K11: 90129 | R11: 18 | S11: =SUM(K11:R11) -> 90147
B12: Other assets | K12: 12371 | L12: 335 | R12: 660 | S12: =SUM(K12:R12) -> 13366
E14: Total Assets: | K14: =SUM(K6:K12) -> 3474238 | L14: =SUM(L6:L12) -> 564048 | M14: =SUM(M6:M12) -> 70417 | N14: =SUM(N6:N12) -> 3562274 | O14: =SUM(O6:O12) -> 54092 | P14: =SUM(P6:P12) -> 613294 | Q14: =SUM(Q6:Q12) -> 2196694 | R14: =SUM(R6:R12) -> 450620 | S14: =SUM(S6:S12) -> 10985677
A16: LIABILITIES, DEFERRED INFLOWS OF RESOURCES AND FUND BALANCES
B17: Liabilities:
C18: Accounts payable and accrued expenses | K18: 361105 | L18: 367545 | M18: 66657 | N18: 128682 | O18: 56814 | R18: 20343 | S18: =SUM(K18:R18) -> 1001146
C19: Due to other governments | K19: 476736 | S19: =SUM(K19:R19) -> 476736
C20: Due to other funds | K20: 2409350 | L20: 194000 | O20: 904000 | R20: 77000 | S20: =SUM(K20:R20) -> 3584350
E22: Total liabilities: | K22: =SUM(K18:K20) -> 3247191 | L22: =SUM(L18:L20) -> 561545 | M22: =SUM(M18:M20) -> 66657 | N22: =SUM(N18:N21) -> 128682 | O22: =SUM(O18:O20) -> 960814 | P22: =SUM(P18:P20) -> 0 | Q22: =SUM(Q18:Q20) -> 0 | R22: =SUM(R18:R20) -> 97343 | S22: =SUM(S18:S20) -> 5062232
A24: DEFERRED INFLOWS OF RESROUCES
C25: Unavailable revenues | K25: 75652 | S25: =SUM(K25:R25) -> 75652
B27: Fund Balances
C28: Nonspendable | K28: 90129 | R28: 18 | S28: =SUM(K28:R28) -> 90147
C29: Restricted | P29: 613294 | Q29: 2196694 | S29: =SUM(K29:R29) -> 2809988
C30: Committed | K30: 61266 | L30: 2503 | M30: 3760 | N30: 3433592 | R30: 353259 | S30: =SUM(K30:R30) -> 3854380
C31: Unassigned | O31: -906722 | S31: =SUM(K31:R31) -> -906722
E33: Total fund balance: | K33: =SUM(K28:K32) -> 151395 | L33: =SUM(L28:L32) -> 2503 | M33: =SUM(M28:M32) -> 3760 | N33: =SUM(N28:N32) -> 3433592 | O33: =SUM(O28:O32) -> -906722 | P33: =SUM(P28:P32) -> 613294 | Q33: =SUM(Q28:Q32) -> 2196694 | R33: =SUM(R28:R32) -> 353277 | S33: =SUM(S28:S32) -> 5847793
E35: Total liabilities and fund balances: | K35: =SUM(K33,K22,K25) -> 3474238 | L35: =SUM(L33,L22,L25) -> 564048 | M35: =SUM(M33,M22,M25) -> 70417 | N35: =SUM(N33,N22,N25) -> 3562274 | O35: =SUM(O33,O22,O25) -> 54092 | P35: =SUM(P33,P22,P25) -> 613294 | Q35: =SUM(Q33,Q22,Q25) -> 2196694 | R35: =SUM(R33,R22,R25) -> 450620 | S35: =SUM(S33,S22,S25) -> 10985677

Sheet Rapides
D1: Rapides Combined Balance Sheet
D2: Issued: December 31, 2014
K5: General Fund | L5: Road and Bridge Fund | M5: Fire Protection District No. 2 Fund | N5: Other Governmental Funds | O5: 2014 Total Governmental Funds | P5: 2013 Total Governmental Funds
A6: Assets:
B7: Cash and cash equivalents | K7: 2441648 | L7: 960666 | M7: 4413988 | N7: 43269164 | O7: =SUM(K7:N7) -> 51085466 | P7: 50024032
B8: Receivables | K8: 2711674 | L8: 394695 | M8: 4726644 | N8: 14999707 | O8: =SUM(K8:N8) -> 22832720 | P8: 22585071
B9: Interfund receivables | K9: 123363 | N9: 2376 | O9: =SUM(K9:N9) -> 125739 | P9: 106544
B10: Other | N10: 516 | O10: =SUM(K10:N10) -> 516 | P10: 492
E12: Total Assets: | K12: =SUM(K7:K10) -> 5276685 | L12: =SUM(L7:L9) -> 1355361 | M12: =SUM(M7:M9) -> 9140632 | N12: =SUM(N7:N10) -> 58271763 | O12: =SUM(O7:O11) -> 74044441 | P12: =SUM(P7:P10) -> 72716139
A14: LIABILITIES AND FUND BALANCES
B15: Liabilities:
C16: Accounts payable | K16: 110137 | L16: 18817 | M16: 151581 | N16: 635730 | O16: =SUM(K16:N16) -> 916265 | P16: 1276458
C17: Interfund payables | K17: 8250 | N17: 120489 | O17: =SUM(K17:N17) -> 128739 | P17: 106544
C18: Deferred revenues | N18: 632212 | O18: =SUM(K18:N18) -> 632212 | P18: 1693311
E20: Total liabilities: | K20: =SUM(K16:K18) -> 118387 | L20: =SUM(L16:L18) -> 18817 | M20: =SUM(M16:M18) -> 151581 | N20: =SUM(N16:N18) -> 1388431 | O20: =SUM(O16:O18) -> 1677216 | P20: =SUM(P16:P18) -> 3076313
B22: Fund Balances
C23: Reserved for:
D24: Judicial | N24: 178151 | O24: =SUM(K24:N24) -> 178151 | P24: 168416
D25: Other general government | N25: 179091 | O25: =SUM(K25:N25) -> 179091 | P25: 356979
D26: Public safety | K26: 219601 | M26: 8989051 | N26: 11853235 | O26: =SUM(K26:N26) -> 21061887 | P26: 20347045
D27: Public works | L27: 1336544 | N27: 15790189 | O27: =SUM(K27:N27) -> 17126733 | P27: 15023971
D28: Health and welfare | N28: 4102147 | O28: =SUM(K28:N28) -> 4102147 | P28: 3791353
D29: Culture and recreation | N29: 21484034 | O29: =SUM(K29:N29) -> 21484034 | P29: 22222089
D30: Debt service | N30: 3296487 | O30: =SUM(K30:N30) -> 3296487 | P30: 2945708
D31: Employee benefits | K31: 1266984 | O31: =SUM(K31:N31) -> 1266984 | P31: 998122
C32: Unassigned | K32: 3674712 | O32: =SUM(K32:N32) -> 3674712 | P32: 3786144
E34: Total fund balance: | K34: =SUM(K23:K32) -> 5161297 | L34: =SUM(L23:L32) -> 1336544 | M34: =SUM(M23:M32) -> 8989051 | N34: =SUM(N23:N32) -> 56883334 | O34: =SUM(O23:O32) -> 72370226 | P34: =SUM(P23:P33) -> 69639827
E36: Total liabilities and fund balances: | K36: =SUM(K34,K20) -> 5279684 | L36: =SUM(L20,L34) -> 1355361 | M36: =SUM(M20,M34) -> 9140632 | N36: =SUM(N20,N34) -> 58271765 | O36: =SUM(O20,O34) -> 74047442 | P36: =SUM(P20+P34) -> 72716140

Sheet Red River
D1: Red River Combined Balance Sheet
D2: Issued: December 31, 2014
K4: General Fund | L4: Sales Tax Fund | M4: Ambulance Service Fund | N4: Library Fund | O4: Unit 1 Road Fund | P4: Public Facilities Maintenance Fund | Q4: Other non-major Governmental Funda | R4: Total
A5: Assets:
B6: Cash | K6: 3858507 | L6: 1669150 | M6: 1341444 | N6: 1725707 | O6: 739740 | P6: 1214386 | Q6: 1970277 | R6: =SUM(K6:Q6) -> 12519211
B7: Investments | K7: 2000000 | L7: 9335860 | M7: 6830520 | N7: 648599 | Q7: 239909 | R7: =SUM(K7:Q7) -> 19054888
B8: Receivables | K8: 1010211 | L8: 229286 | M8: 138909 | N8: 1628080 | O8: 28478 | P8: 881416 | Q8: 508105 | R8: =SUM(K8:Q8) -> 4424485
B9: Prepaid expenses | K9: 9185 | M9: 4960 | N9: 1158 | P9: 3050 | R9: =SUM(K9:P9) -> 18353
E11: Total Assets: | K11: =SUM(K6:K9) -> 6877903 | L11: =SUM(L6:L9) -> 11234296 | M11: =SUM(M6:M9) -> 8315833 | N11: =SUM(N6:N9) -> 4003544 | O11: =SUM(O6:O9) -> 768218 | P11: =SUM(P6:P9) -> 2098852 | Q11: =SUM(Q6:Q9) -> 2718291 | R11: =SUM(R6:R9) -> 36016937
A13: DEFERRED OUTLFLOWS OF RESOURCES
E15: Total Assets and deferred outflows | K15: =SUM(K11) -> 6877903 | L15: =SUM(L11) -> 11234296 | M15: =SUM(M11) -> 8315833 | N15: =SUM(N11) -> 4003544 | O15: =SUM(O11) -> 768218 | P15: =SUM(P11) -> 2098852 | Q15: =SUM(Q11) -> 2718291 | R15: =SUM(R11) -> 36016937
A18: LIABILITIES
C19: Accounts payable and accrued expenses | K19: 175746 | L19: 630 | M19: 22499 | N19: 172974 | O19: 28263 | P19: 253924 | Q19: 68977 | R19: =SUM(K19:Q19) -> 723013
E21: Total liabilities: | K21: =SUM(K19:K19) -> 175746 | L21: =SUM(L19:L19) -> 630 | M21: =SUM(M19:M19) -> 22499 | N21: =SUM(N19:N19) -> 172974 | O21: =SUM(O19:O19) -> 28263 | P21: =SUM(P19:P19) -> 253924 | Q21: =SUM(Q19:Q19) -> 68977 | R21: =SUM(R19:R19) -> 723013
A23: DEFERRED INFLOWS OF RESOURCES | K23: 4747 | N23: 10571 | P23: 4539 | Q23: 3016 | R23: =SUM(K23:Q23) -> 22873
B25: Fund Balances
C26: Nonspendable:
D27: Prepaid expenses | K27: 9185 | M27: 4960 | N27: 1158 | P27: 3050 | R27: =SUM(K27:P27) -> 18353
C28: Spendable:
C29: Restricted:
D30: Dedicated property taxes | N30: 3818841 | Q30: 1958043 | R30: =SUM(K30:Q30) -> 5776884
D31: Dedicated sales taxes | M31: 7062267 | Q31: 112876 | R31: =SUM(K31:Q31) -> 7175143
D32: Court fees for juror compensation | Q32: 215398 | R32: =SUM(K32:Q32) -> 215398
D33: Federal and state grant programs | Q33: 266483 | R33: =SUM(K33:Q33) -> 266483
C34: Committed: | R34: =SUM(K34:Q34) -> 0
D35: Criminal court costs | Q35: 92093 | R35: =SUM(K35:Q35) -> 92093
D36: Ambulance services | M36: 1226107 | R36: =SUM(K36:Q36) -> 1226107
D37: Road maintenance and improvements | O37: 739955 | Q37: 1405 | R37: =SUM(K37:Q37) -> 741360
D38: Public facilities maintenance | P38: 1837339 | R38: =SUM(K38:Q38) -> 1837339
D39: Buildings and infrastructure | L39: 11233666 | R39: =SUM(K39:Q39) -> 11233666
C40: Unassigned | K40: 6688225 | R40: =SUM(K40:Q40) -> 6688225
E42: Total fund balance: | K42: =SUM(K27:K41) -> 6697410 | L42: =SUM(L27:L40) -> 11233666 | M42: =SUM(M27:M40) -> 8293334 | N42: =SUM(N27:N40) -> 3819999 | O42: =SUM(O27:O40) -> 739955 | P42: =SUM(P27:P40) -> 1840389 | Q42: =SUM(Q27:Q40) -> 2646298 | R42: =SUM(R27:R40) -> 35271051
E44: Total liabilities, deferred inflows, and fund balances: | K44: =K42+K23+K21 -> 6877903 | L44: =L42+L23+L21 -> 11234296 | M44: =M42+M23+M21 -> 8315833 | N44: =N42+N23+N21 -> 4003544 | O44: =O42+O23+O21 -> 768218 | P44: =P42+P23+P21 -> 2098852 | Q44: =Q42+Q23+Q21 -> 2718291 | R44: =R42+R23+R21 -> 36016937

Sheet Richland
D1: Richland Combined Balance Sheet
D2: Issued: December 31, 2014
K5: General | L5: Capital Projects | M5: Road Maintenance | N5: Drainage Maintenance | O5: Library | P5: Other Governmental Funds | Q5: Total Governmental Funds
A6: ASSETS
B7: Cash | K7: 1865478 | L7: 11230 | M7: 1018058 | N7: 1393007 | O7: 3191359 | P7: 677281 | Q7: =SUM(K7:P7) -> 8156413
B8: Receivables | K8: 1080288 | L8: 125819 | M8: 55379 | O8: 1306290 | P8: 230476 | Q8: =SUM(K8:P8) -> 2798252
E10: Total Assets: | K10: =SUM(K7:K8) -> 2945766 | L10: =SUM(L7:L8) -> 137049 | M10: =SUM(M7:M8) -> 1073437 | N10: =SUM(N7:N8) -> 1393007 | O10: =SUM(O7:O8) -> 4497649 | P10: =SUM(P7:P8) -> 907757 | Q10: =SUM(Q7:Q8) -> 10954665
A12: LIABILITIES
C13: Accounts payable | K13: 56121 | L13: 159525 | M13: 117544 | N13: 5913 | O13: 20791 | P13: 31825 | Q13: =SUM(K13:P13) -> 391719
C14: Payroll accruals and withholdings | K14: 62400 | Q14: =SUM(K14:P14) -> 62400
E16: Total liabilities: | K16: =SUM(K13:K14) -> 118521 | L16: =SUM(L13:L14) -> 159525 | M16: =SUM(M13:M14) -> 117544 | N16: =SUM(N13:N15) -> 5913 | O16: =SUM(O13:O14) -> 20791 | P16: =SUM(P13:P14) -> 31825 | Q16: =SUM(Q13:Q14) -> 454119
A18: DEFERRED INFLOWS OF RESROUCES
C19: Property taxes | K19: 1095007 | O19: 1337831 | P19: 234673 | Q19: 2667511
B21: Fund Balance
C22: Restricted for special revenue | M22: 955893 | N22: 1387094 | O22: 3139027 | P22: 641259 | Q22: =SUM(K22:P22) -> 6123273
C23: Unassigned (deficit) | K23: 1732238 | L23: -22476 | Q23: =SUM(K23:P23) -> 1709762
E25: Total fund balances: | K25: =SUM(K22:K24) -> 1732238 | L25: =SUM(L22:L23) -> -22476 | M25: =SUM(M22:M23) -> 955893 | N25: =SUM(N22:N23) -> 1387094 | O25: =SUM(O22:O23) -> 3139027 | P25: =SUM(P22:P23) -> 641259 | Q25: =SUM(Q22:Q23) -> 7833035
E27: Total liabilities, deferred inflows of resources, and fund balances: | K27: =SUM(K25,K16,K19) -> 2945766 | L27: =SUM(L25,L16,L19) -> 137049 | M27: =SUM(M25,M16,M19) -> 1073437 | N27: =SUM(N25,N16,N19) -> 1393007 | O27: =SUM(O25,O16,O19) -> 4497649 | P27: =SUM(P25,P16,P19) -> 907757 | Q27: =SUM(Q25,Q16,Q19) -> 10954665

Sheet Sabine
D1: Sabine Combined Balance Sheet
D2: Issued: December 31, 2014
K5: General Fund | L5: Capital Projects | M5: Road Maintenance | N5: Drainage Maintenance | O5: Library | P5: Other Governmental Funds | Q5: Total Governmental Funds
A6: Assets:
B7: Cash | K7: 1865478 | L7: 11230 | M7: 1018058 | N7: 1393007 | O7: 3191359 | P7: 677281 | Q7: =SUM(K7:P7) -> 8156413
B8: Receivables | K8: 1080288 | L8: 125819 | M8: 55379 | O8: 1306290 | P8: 230476 | Q8: =SUM(K8:P8) -> 2798252
E10: Total Assets: | K10: =SUM(K7:K8) -> 2945766 | L10: =SUM(L7:L8) -> 137049 | M10: =SUM(M7:M8) -> 1073437 | N10: =SUM(N7:N8) -> 1393007 | O10: =SUM(O7:O8) -> 4497649 | P10: =SUM(P7:P8) -> 907757 | Q10: =SUM(Q7:Q8) -> 10954665
A12: Liabilities
C13: Accounts payable | K13: 56121 | L13: 159525 | M13: 117544 | N13: 5913 | O13: 20791 | P13: 31825 | Q13: =SUM(K13:P13) -> 391719
C14: Payroll accruals and witholdings | K14: 62400 | Q14: =SUM(K14:P14) -> 62400
E16: Total liabilities: | K16: =SUM(K13:K14) -> 118521 | L16: =SUM(L13:L14) -> 159525 | M16: =SUM(M13:M14) -> 117544 | N16: =SUM(N13:N14) -> 5913 | O16: =SUM(O13:O14) -> 20791 | P16: =SUM(P13:P14) -> 31825 | Q16: =SUM(Q13:Q14) -> 454119
A18: Deferred inflows of resources
C19: Property taxes | K19: 1095007 | O19: 1337831 | P19: 234673 | Q19: =SUM(K19:P19) -> 2667511
A21: Fund Balances
C22: Restricted for maintenance and operation | M22: 955893 | N22: 1387094 | O22: 3139027 | P22: 641259 | Q22: =SUM(K22:P22) -> 6123273
C23: Unassigned (deficit) | K23: 1732238 | L23: -22476 | Q23: =SUM(K23:P23) -> 1709762
E25: Total fund balances: | K25: =SUM(K22:K23) -> 1732238 | L25: =SUM(L22:L23) -> -22476 | M25: =SUM(M22:M23) -> 955893 | N25: =SUM(N22:N23) -> 1387094 | O25: =SUM(O22:O23) -> 3139027 | P25: =SUM(P22:P23) -> 641259 | Q25: =SUM(Q22:Q24) -> 7833035
E27: Total liabilities, deferred inflows of resources, and fund balances: | K27: =SUM(K16+K19+K25) -> 2945766 | L27: =SUM(L16+L19+L25) -> 137049 | M27: =SUM(M16+M19+M25) -> 1073437 | N27: =SUM(N16+N19+N25) -> 1393007 | O27: =SUM(O16+O19+O25) -> 4497649 | P27: =SUM(P16+P19+P25) -> 907757 | Q27: =SUM(Q16+Q19+Q25) -> 10954665

Sheet St. Bernard
D1: St. Bernard Combined Balance Sheet
D2: Issued: December 31, 2014
M4: Special Revenue Funds
K5: General Fund | L5: CDBG Disaster Fund | M5: Disaster Recovery Fund | N5: Consolidated Fire Protection District No. 1-2 | O5: Non-Major Governmental Funds | P5: Total
A6: Assets:
B7: Cash and cash equivalents | K7: 6265640 | L7: 276311 | M7: 10022048 | N7: 969513 | O7: 16074547 | P7: =SUM(K7:O7) -> 33608059
B8: Investments - land held for sale | K8: 4229000 | P8: =SUM(K8:O8) -> 4229000
B9: Receivables: | P9: =SUM(K9:O9) -> 0
C10: Sales and use taxes | K10: 1972145 | O10: 657382 | P10: =SUM(K10:O10) -> 2629527
C11: Property taxes | K11: 878056 | N11: 8775527 | O11: 3526171 | P11: =SUM(K11:O11) -> 13179754
C12: Cable franchise fees | K12: 92741 | P12: =SUM(K12:O12) -> 92741
C13: Intergovernmental | K13: 868332 | L13: 2349717 | M13: 13607598 | N13: 385738 | O13: 5254041 | P13: =SUM(K13:O13) -> 22465426
C14: Grass liens receivable | K14: 74702 | P14: =SUM(K14:O14) -> 74702
C15: Other | K15: 54105 | O15: 543718 | P15: =SUM(K15:O15) -> 597823
B16: Due from other funds | K16: 4549014 | M16: 12450962 | O16: 3599138 | P16: =SUM(K16:O16) -> 20599114
B17: Prepaid | K17: 98722 | N17: 20296 | O17: 89552 | P17: =SUM(K17:O17) -> 208570
E19: Total Assets: | K19: =SUM(K7:K17) -> 19082457 | L19: =SUM(L7:L16) -> 2626028 | M19: =SUM(M7:M16) -> 36080608 | N19: =SUM(N7:N17) -> 10151074 | O19: =SUM(O7:O17) -> 29744549 | P19: =SUM(P7:P17) -> 97684716
A21: LIABILITIES AND FUND BALANCES
C22: Accounts payable | K22: 1548427 | L22: 994984 | M22: 12042292 | N22: 459178 | O22: 4249881 | P22: =SUM(K22:O22) -> 19294762
C23: Retainage payable | K23: 21091 | L23: 1564987 | M23: 3786329 | O23: 90869 | P23: =SUM(K23:O23) -> 5463276
C24: Salaries and payroll deductions payable | K24: 573408 | N24: 519387 | O24: 450588 | P24: =SUM(K24:O24) -> 1543383
C25: Due to other funds | K25: 6171546 | L25: 213515 | M25: 12514280 | N25: 615248 | O25: 4335331 | P25: =SUM(K25:O25) -> 23849920
C26: Advance collections | K26: 69188 | P26: =SUM(K26:O26) -> 69188
C27: Short-term certificates of indebtedness | K27: 1984485 | N27: 4776447 | P27: =SUM(K27:O27) -> 6760932
E29: Total liabilities: | K29: =SUM(K22:K27) -> 10368145 | L29: =SUM(L22:L27) -> 2773486 | M29: =SUM(M22:M27) -> 28342901 | N29: =SUM(N22:N27) -> 6370260 | O29: =SUM(O22:O27) -> 9126669 | P29: =SUM(P22:P27) -> 56981461
A31: Deferred inflows of resources
B32: Unavailable revenues | K32: 4625602 | L32: 2330543 | M32: 9838302 | N32: 194090 | O32: 4062728 | P32: =SUM(K32:O32) -> 21051265
E33: Total deferred inflows of resources | K33: =SUM(K32) -> 4625602 | L33: =SUM(L32) -> 2330543 | M33: =SUM(M32) -> 9838302 | N33: =SUM(N32) -> 194090 | O33: =SUM(O32) -> 4062728 | P33: =SUM(P32) -> 21051265
B35: Fund Balances
C36: Nonspendable
D37: Prepaid items | K37: 98722 | O37: 89552 | P37: =SUM(K37:O37) -> 188274
C38: Restricted
D39: Mortgage refunding | K39: 91185 | P39: =SUM(K39:O39) -> 91185
D40: Debt service | O40: 3497452 | P40: =SUM(K40:O40) -> 3497452
D41: Federal programs | K41: 3070696 | O41: 2299933 | P41: =SUM(K41:O41) -> 5370629
D42: Council on aging | O42: 344708 | P42: =SUM(K42:O42) -> 344708
D43: Road lighting | O43: 48163 | P43: =SUM(K43:O43) -> 48163
D44: Health | O44: 946612 | P44: =SUM(K44:O44) -> 946612
D45: Communication | O45: 514849 | P45: =SUM(K45:O45) -> 514849
D46: Garbage | O46: 263046 | P46: =SUM(K46:O46) -> 263046
D47: Court operations | O47: 41769 | P47: =SUM(K47:O47) -> 41769
D48: Public safety | N48: 3586724 | P48: =SUM(K48:O48) -> 3586724
D49: Capital outlay | O49: 989788 | P49: =SUM(K49:O49) -> 989788
D50: BP oil spill | K50: 242786 | P50: =SUM(K50:O50) -> 242786
C51: Commited | P51: =SUM(K51:O51) -> 0
D52: Capital outlay | O52: 956733 | P52: =SUM(K52:O52) -> 956733
C53: Assigned
D54: Contingency | K54: 587321 | P54: =SUM(K54:O54) -> 587321
D55: Capital outlay | O55: 887488 | P55: =SUM(K55:O55) -> 887488
D56: Recovery | O56: 5778189 | P56: =SUM(K56:O56) -> 5778189
C57: Unassigned | L57: -2478001 | M57: -2100595 | O57: -103130 | P57: =SUM(K57:O57) -> -4681726
E59: Total fund balance: | K59: =SUM(K37:K57) -> 4090710 | L59: =SUM(L38:L57) -> -2478001 | M59: =SUM(M38:M57) -> -2100595 | N59: =SUM(N37:N57) -> 3586724 | O59: =SUM(O37:O57) -> 16555152 | P59: =SUM(P37:P58) -> 19653990
E61: Total liabilities, deferred inflows and fund balances: | K61: =SUM(K59,K29,K32) -> 19084457 | L61: =SUM(L59,L29,L32) -> 2626028 | M61: =SUM(M59,M29,M32) -> 36080608 | N61: =SUM(N59,N29,N32) -> 10151074 | O61: =SUM(O59,O29,O32) -> 29744549 | P61: =SUM(P59,P29,P32) -> 97686716

Sheet St. Charles
D1: St. Charles Combined Balance Sheet
D2: Issued: December 31, 2014
K5: General Fund | L5: Road & Drainage Maintenance & Operation | M5: Recreation Maintenance & Operation | N5: Sewer General Obligation Sinking | O5: Nonmajor Governmental Funds | P5: Total Governmental Funds
A6: Assets:
B7: Cash and Cash equivalents | K7: 1449461 | L7: 27940 | M7: 3959 | N7: 695 | O7: 222282 | P7: =SUM(K7:O7) -> 1704337
B8: Investments | K8: 41010050 | L8: 36816258 | M8: 758961 | N8: 4192183 | O8: 8358811 | P8: =SUM(K8:O8) -> 91136263
B9: Receivables, net
C10: Ad valorem taxes | K10: 3887225 | L10: 7283945 | M10: 3641975 | N10: 2697763 | O10: 8151138 | P10: =SUM(K10:O10) -> 25662046
C11: Sales taxes | K11: 1562803 | L11: 1786057 | O11: 223258 | P11: =SUM(K11:O11) -> 3572118
C12: Accounts | K12: 551 | M12: 2547 | P12: =SUM(K12:O12) -> 3098
C13: Other | K13: 369648 | L13: 59172 | M13: 5368 | O13: 19345 | P13: =SUM(K13:O13) -> 453533
B14: Due from other funds | K14: 632223 | L14: 8099 | O14: 3059 | P14: =SUM(K14:O14) -> 643381
B15: Due from other governments | K15: 1299495 | L15: 1137003 | M15: 204 | O15: 2145234 | P15: =SUM(K15:O15) -> 4581936
B16: Prepaid fees | K16: 442910 | L16: 384 | M16: 1150 | O16: 25282 | P16: =SUM(K16:O16) -> 469726
B17: Other assets | K17: 2095 | L17: 1125 | M17: 450 | O17: 600 | P17: =SUM(K17:O17) -> 4270
E19: Total Assets: | K19: =SUM(K7:K17) -> 50656461 | L19: =SUM(L7:L17) -> 47119983 | M19: =SUM(M7:M17) -> 4414614 | N19: =SUM(N7:N17) -> 6890641 | O19: =SUM(O7:O17) -> 19149009 | P19: =SUM(P7:P17) -> 128230708
A21: LIABILITIES AND FUND BALANCES
B22: Liabilities:
D23: Accounts payable | K23: 1040452 | L23: 1669542 | M23: 163668 | O23: 2222893 | P23: =SUM(K23:O23) -> 5096555
D24: Contracts payable | K24: 20782 | L24: 135788 | O24: 206548 | P24: =SUM(K24:O24) -> 363118
D25: Due to other funds | K25: 27057 | M25: 150 | O25: 8115 | P25: =SUM(K25:O25) -> 35322
D26: Due to component units | O26: 6057 | P26: =SUM(K26:O26) -> 6057
D27: Due to other governments | K27: 9962 | O27: 244427 | P27: =SUM(K27:O27) -> 254389
D28: Other liabilities | K28: 639643 | L28: 272704 | M28: 53232 | O28: 73496 | P28: =SUM(K28:O28) -> 1039075
E30: Total liabilities: | K30: =SUM(K23:K28) -> 1737896 | L30: =SUM(L23:L28) -> 2078034 | M30: =SUM(M23:M28) -> 217050 | N30: =SUM(N23:N28) -> 0 | O30: =SUM(O23:O28) -> 2761536 | P30: =SUM(P23:P28) -> 6794516
A32: DEFERRED INFLOWS OF RESOURCES
D33: Advances | K33: 4042325 | L33: 7328651 | M33: 3641975 | N33: 2697763 | O33: 8157754 | P33: =SUM(K33:O33) -> 25868468
D34: Unavailable revenues | O34: 881085 | P34: =SUM(K34:O34) -> 881085
E36: Total deferred inflows of resources: | K36: =SUM(K33) -> 4042325 | L36: =SUM(L33) -> 7328651 | M36: =SUM(M33) -> 3641975 | N36: =SUM(N33) -> 2697763 | O36: =SUM(O33:O34) -> 9038839 | P36: =SUM(P33:P34) -> 26749553
B38: Fund Balances
C39: Nonspendable | K39: 442910 | L39: 384 | M39: 1150 | O39: 25282 | P39: =SUM(K39:O39) -> 469726
C40: Restricted | K40: 53538 | L40: 33558559 | M40: 18217 | N40: 4192878 | O40: 5831532 | P40: =SUM(K40:O40) -> 43654724
C41: Commited | K41: 13940018 | L41: 4154355 | M41: 536222 | O41: 1439688 | P41: =SUM(K41:O41) -> 20070283
C42: Assigned | K42: 21019738 | O42: 54134 | P42: =SUM(K42:O42) -> 21073872
C43: Unassigned | K43: 9420036 | O43: -2002 | P43: =SUM(K43:O43) -> 9418034
E45: Total fund balances: | K45: =SUM(K39:K43) -> 44876240 | L45: =SUM(L39:L43) -> 37713298 | M45: =SUM(M39:M43) -> 555589 | N45: =SUM(N40:N43) -> 4192878 | O45: =SUM(O39:O43) -> 7348634 | P45: =SUM(P39:P43) -> 94686639
E47: Total liabilities and fund balances: | K47: =SUM(K45,K30,K36) -> 50656461 | L47: =SUM(L45,L30,L36) -> 47119983 | M47: =SUM(M45,M30,M36) -> 4414614 | N47: =SUM(N45,N30,N36) -> 6890641 | O47: =SUM(O45,O30,O36) -> 19149009 | P47: =SUM(P45,P30,P36) -> 128230708

Sheet St. Helena
D1: St. Helena Combined Balance Sheet
D2: Issued: December 31, 2014
L4: Major Funds | P4: Nonmajor Funds
K5: General Fund | L5: Road Building & Maintenance Fund | M5: Solid Waste Fund | N5: LRA CDBG Fund | O5: LGAP Grants fund | P5: Other Governmental Funds | Q5: Total Governmental Funds
A6: Assets:
B7: Cash and equivalents | K7: 87584 | L7: 1173217 | M7: 1856472 | N7: 3621 | P7: 2159131 | Q7: =SUM(K7:P7) -> 5280025
B8: Investments | P8: 153423 | Q8: =SUM(K8:P8) -> 153423
B9: Receivables, net | K9: 385187 | L9: 581482 | M9: 53091 | N9: 148478 | O9: 100000 | P9: 1548882 | Q9: =SUM(K9:P9) -> 2817120
B10: Due from other funds | K10: 150516 | P10: 4626 | Q10: =SUM(K10:P10) -> 155142
B11: Restricted cash | O11: 7797 | P11: 424053 | Q11: =SUM(K11:P11) -> 431850
E13: Total assets: | K13: =SUM(K7:K11) -> 623287 | L13: =SUM(L7:L11) -> 1754699 | M13: =SUM(M7:M11) -> 1909563 | N13: =SUM(N7:N11) -> 152099 | O13: =SUM(O7:O11) -> 107797 | P13: =SUM(P7:P12) -> 4290115 | Q13: =SUM(Q7:Q11) -> 8837560
A15: LIABILITIES AND FUND BALANCES
B16: Liabilities:
C17: Accounts payable | K17: 68427 | L17: 381161 | N17: 224629 | O17: 155550 | P17: 85124 | Q17: =SUM(K17:P17) -> 914891
C18: Other accrued liabilities | K18: 3864 | L18: 16444 | P18: 41921 | Q18: =SUM(K18:P18) -> 62229
C19: Due to other funds | N19: 14706 | O19: 16888 | P19: 123548 | Q19: =SUM(K19:P19) -> 155142
E21: Total liabilities: | K21: =SUM(K17:K19) -> 72291 | L21: =SUM(L17:L19) -> 397605 | M21: =SUM(M17:M19) -> 0 | N21: =SUM(N17:N19) -> 239335 | O21: =SUM(O17:O19) -> 172438 | P21: =SUM(P17:P19) -> 250593 | Q21: =SUM(Q17:Q19) -> 1132262
B23: Fund Balances
C24: Restricted | L24: 1357094 | M24: 1909563 | P24: 4076019 | Q24: =SUM(K24:P24) -> 7342676
C25: Unassigned | K25: 550996 | N25: -87236 | O25: -64641 | P25: -36497 | Q25: =SUM(K25:P25) -> 362622
E27: Total fund balance (deficit): | K27: =SUM(K24:K25) -> 550996 | L27: =SUM(L24:L25) -> 1357094 | M27: =SUM(M24:M25) -> 1909563 | N27: =SUM(N24:N25) -> -87236 | O27: =SUM(O24:O25) -> -64641 | P27: =SUM(P24:P25) -> 4039522 | Q27: =SUM(Q24:Q25) -> 7705298
E29: Total liabilities and fund balances: | K29: =SUM(K27,K21) -> 623287 | L29: =SUM(L21,L27) -> 1754699 | M29: =SUM(M21,M27) -> 1909563 | N29: =SUM(N21+N27) -> 152099 | O29: =SUM(O21+O27) -> 107797 | P29: =SUM(P21,P27) -> 4290115 | Q29: =SUM(Q21,Q27) -> 8837560

Sheet St. James
D1: St. James Combined Balance Sheet
D2: Issued: December 31, 2014
K5: General | L5: Public safety | M5: Courthouse, Jail, and Public Buildings Maintenance | N5: CDBG Diaster Recovery Projects | O5: Other Governmental Funds | P5: Total Governmental Funds
A6: Assets:
B7: Cash and cash equivalents | K7: 4781696 | L7: 2278944 | M7: 2406299 | N7: 524 | O7: 12730178 | P7: =SUM(K7:O7) -> 22197641
B8: Investments | K8: 1199408 | L8: 1462715 | M8: 1729971 | O8: 6408501 | P8: =SUM(K8:O8) -> 10800595
B9: Receivables (net of allowances for uncollectibles) | K9: 4922581 | L9: 2118230 | M9: 2659868 | N9: 3067966 | O9: 9383449 | P9: =SUM(K9:O9) -> 22152094
B10: Due from other funds | K10: 103041 | L10: 1996 | M10: 746714 | N10: 0 | O10: 309416 | P10: =SUM(K10:O10) -> 1161167
B11: Prepaid items | K11: 4333 | O11: 114164 | P11: =SUM(K11:O11) -> 118497
B12: Inventory | K12: 34391 | P12: =SUM(K12:O12) -> 34391
E14: Total Assets: | K14: =SUM(K7:K12) -> 11045450 | L14: =SUM(L7:L10) -> 5861885 | M14: =SUM(M7:M10) -> 7542852 | N14: =SUM(N7:N10) -> 3068490 | O14: =SUM(O7:O11) -> 28945708 | P14: =SUM(P7:P12) -> 56464385
A16: LIABILITIES AND FUND BALANCES
B17: Liabilities:
C18: Accounts payable | K18: 978641 | L18: 90333 | M18: 171072 | N18: 2661786 | O18: 1000531 | P18: =SUM(K18:O18) -> 4902363
C19: Payroll deductions and withholdings payable | K19: 157420 | L19: 1621 | M19: 42907 | O19: 302434 | P19: =SUM(K19:O19) -> 504382
C20: Due to other funds | K20: 351403 | N20: 622077 | O20: 202688 | P20: =SUM(K20:O20) -> 1176168
C21: Accrued expenses | K21: 138378 | L21: 1513 | M21: 32269 | O21: 281845 | P21: =SUM(K21:O21) -> 454005
C22: Other liabilities | O22: 118988 | P22: =SUM(K22:O22) -> 118988
E24: Total liabilities: | K24: =SUM(K18:K22) -> 1625842 | L24: =SUM(L18:L22) -> 93467 | M24: =SUM(M18:M22) -> 246248 | N24: =SUM(N18:N22) -> 3283863 | O24: =SUM(O18:O22) -> 1906486 | P24: =SUM(P18:P22) -> 7155906
B26: Fund Balances
C27: Nonspendable -prepaid items and Inventory | K27: 38724 | O27: 114164 | P27: =SUM(K27:O27) -> 152888
C28: Restricted for
D29: Culture and recreation | O29: 6188701 | P29: =SUM(K29:O29) -> 6188701
D30: Debt service | O30: 1701771 | P30: =SUM(K30:O30) -> 1701771
D31: Capital projects | O31: 1059444 | P31: =SUM(K31:O31) -> 1059444
D32: Health and welfare | K32: 5085694 | O32: 1432807 | P32: =SUM(K32:O32) -> 6518501
D33: Highways and streets | O33: 5035904 | P33: =SUM(K33:O33) -> 5035904
D34: Public safety | L34: 5768418 | O34: 7611437 | P34: =SUM(K34:O34) -> 13379855
D35: Sanitation | O35: 2961101 | P35: =SUM(K35:O35) -> 2961101
D36: Other purposes | M36: 7296604 | O36: 0 | P36: =SUM(K36:O36) -> 7296604
C37: Commited for
D38: Judicial | O38: 510732 | P38: =SUM(K38:O38) -> 510732
D39: Highways and streets | O39: 256815 | P39: =SUM(K39:O39) -> 256815
D40: Public transportation | O40: 19106 | P40: =SUM(K40:O40) -> 19106
C41: Assigned for
D42: Judicial | O42: 19839 | P42: =SUM(K42:O42) -> 19839
D43: Health and welfare | O43: 9409 | P43: =SUM(K43:O43) -> 9409
D44: Other purposes | O44: 136213 | P44: =SUM(K44:O44) -> 136213
C45: Unassigned | K45: 4295190 | N45: -215373 | O45: -18221 | P45: =SUM(K45:O45) -> 4061596
E47: Total fund balance: | K47: =SUM(K27:K45) -> 9419608 | L47: =SUM(L28:L45) -> 5768418 | M47: =SUM(M28:M45) -> 7296604 | N47: =SUM(N28:N45) -> -215373 | O47: =SUM(O27:O45) -> 27039222 | P47: =SUM(P27:P46) -> 49308479
E49: Total liabilities and fund balances: | K49: =SUM(K47,K24) -> 11045450 | L49: =SUM(L24,L47) -> 5861885 | M49: =SUM(M24,M47) -> 7542852 | N49: =SUM(N24,N47) -> 3068490 | O49: =SUM(O47+O24) -> 28945708 | P49: =SUM(P24+P47) -> 56464385

Sheet St. John the Baptist
D1: St. John the Baptist Combined Balance Sheet
D2: Issued: December 31, 2014
K4: General | L4: Sales Tax District | M4: Roads and Bridges | N4: 1992 General Obligation Sinking | O4: 2010 Sewer Construction Bond | P4: 2014 General Obligation Bond | Q4: Non-Major Governmental Funds | R4: Total Governmental Funds
A5: Assets:
B6: Cash and cash equivalents | K6: 123594 | L6: 4161873 | M6: 711962 | N6: 7013264 | O6: 13936598 | P6: 15780917 | Q6: 26975412 | R6: =SUM(K6:Q6) -> 68703620
B7: Receivables (net of allowances for uncollectible) | R7: =SUM(K7:Q7) -> 0
C8: Accounts | K8: 111895 | Q8: 219852 | R8: =SUM(K8:Q8) -> 331747
C9: Ad valorem taxes | K9: 2057106 | N9: 5062424 | Q9: 4378926 | R9: =SUM(K9:Q9) -> 11498456
C10: Sales and use taxes | K10: 14987 | L10: 1469962 | M10: 567302 | Q10: 1325009 | R10: =SUM(K10:Q10) -> 3377260
C11: Other | K11: 139 | M11: 65275 | Q11: 107191 | R11: =SUM(K11:Q11) -> 172605
B12: Due from other funds | K12: 1135361 | L12: 1629607 | M12: 972192 | Q12: 943163 | R12: =SUM(K12:Q12) -> 4680323
B13: Due from other governments | K13: 52301 | M13: 956268 | Q13: 2087713 | R13: =SUM(K13:Q13) -> 3096282
B14: Prepaid items | K14: 48645 | M14: 70698 | Q14: 31239 | R14: =SUM(K14:Q14) -> 150582
E16: Total assets: | K16: =SUM(K6:K14) -> 3544028 | L16: =SUM(L6:L14) -> 7261442 | M16: =SUM(M6:M14) -> 3343697 | N16: =SUM(N6:N14) -> 12075688 | O16: =SUM(O6:O14) -> 13936598 | P16: =SUM(P6) -> 15780917 | Q16: =SUM(Q6:Q15) -> 36068505 | R16: =SUM(R6:R14) -> 92010875
A18: LIABILITIES AND FUND BALANCES
B19: Liabilities:
C20: Accounts, salaries and other payables | K20: 817576 | M20: 1064620 | P20: 316408 | Q20: 1878308 | R20: =SUM(K20:Q20) -> 4076912
C21: Contracts payable | M21: 172537 | P21: 87391 | Q21: 682441 | R21: =SUM(K21:Q21) -> 942369
C22: Due to other funds | K22: 663101 | L22: 100000 | M22: 162856 | Q22: 2553798 | R22: =SUM(K22:Q22) -> 3479755
C23: Other liabilities | Q23: 21935 | R23: =SUM(K23:Q23) -> 21935
E25: Total liabilities: | K25: =SUM(K20:K23) -> 1480677 | L25: =SUM(L20:L22) -> 100000 | M25: =SUM(M20:M22) -> 1400013 | N25: =SUM(N20:N22) -> 0 | O25: =SUM(O20:O22) -> 0 | P25: =SUM(P20:P23) -> 403799 | Q25: =SUM(Q20:Q23) -> 5136482 | R25: =SUM(R20:R23) -> 8520971
A27: DEFERRED INFLOWS OF RESOURCES
C28: Unavailable revenue | K28: 54842 | M28: 201184 | Q28: 1845768 | R28: =SUM(K28:Q28) -> 2101794
E30: Total deferred inflows of resources: | K30: =K28 -> 54842 | L30: =SUM(L28) -> 0 | M30: =SUM(M28) -> 201184 | N30: =SUM(N28) -> 0 | O30: =SUM(O28) -> 0 | Q30: =SUM(Q28) -> 1845768 | R30: =SUM(R28) -> 2101794
B32: Fund Balances
C33: Non-spendable: | K33: 48645 | M33: 70698 | Q33: 31239 | R33: =SUM(K33:Q33) -> 150582
C34: Restricted | L34: 7161442 | M34: 1671802 | N34: 12075688 | Q34: 23007658 | R34: =SUM(K34:Q34) -> 43916590
C35: Committed | O35: 13936598 | P35: 15377118 | Q35: 6047358 | R35: =SUM(K35:Q35) -> 35361074
C36: Unassigned | K36: 1959864 | R36: =SUM(K36:Q36) -> 1959864
E38: Total fund balance: | K38: =SUM(K33:K36) -> 2008509 | L38: =SUM(L33:L36) -> 7161442 | M38: =SUM(M33:M36) -> 1742500 | N38: =SUM(N33:N36) -> 12075688 | O38: =SUM(O33:O36) -> 13936598 | P38: =SUM(P33:P36) -> 15377118 | Q38: =SUM(Q33:Q36) -> 29086255 | R38: =SUM(R33:R36) -> 81388110
E40: Total liabilities, deferred inflows, and fund balances: | K40: =SUM(K38,K25,K30) -> 3544028 | L40: =SUM(L38,L25,L30) -> 7261442 | M40: =SUM(M38,M25,M30) -> 3343697 | N40: =SUM(N38,N25,N30) -> 12075688 | O40: =SUM(O38,O25,O30) -> 13936598 | P40: =SUM(P25+P30+P38) -> 15780917 | Q40: =SUM(Q38,Q25,Q30) -> 36068505 | R40: =SUM(R38,R25,R30) -> 92010875

Sheet St. Martin
D1: St. Martin Combined Balance Sheet
D2: Issued: December 31, 2014
K5: General Fund | L5: District #1 Sales Tax Revenue Fund | M5: District #2 Sales Tax Revenue Fund | N5: Public Works Fund | O5: Parishwide Bond Sinking Fund | P5: Road Construction Fund | Q5: Capital Outlay Fund | R5: Nonmajor Governmental Funds | S5: Total Governmental Funds
A6: Assets:
B7: Cash and cash equivalents | K7: 5891187 | L7: 8921581 | M7: 9392833 | O7: 135625 | P7: 953504 | R7: 1130870 | S7: =SUM(K7:R7) -> 26425600
B8: Receivables | K8: 932007 | L8: 434625 | M8: 211894 | N8: 4558475 | O8: 1432020 | Q8: 240000 | R8: 4656787 | S8: =SUM(K8:R8) -> 12465808
B9: Due from other governmental entities | K9: 138381 | S9: =SUM(K9:R9) -> 138381
B10: Due from other funds | N10: 5295415 | O10: 3845857 | R10: 8747009 | S10: =SUM(K10:R10) -> 17888281
E12: Total Assets: | K12: =SUM(K7:K10) -> 6961575 | L12: =SUM(L7:L10) -> 9356206 | M12: =SUM(M7:M10) -> 9604727 | N12: =SUM(N7:N10) -> 9853890 | O12: =SUM(O7:O10) -> 5413502 | P12: =SUM(P7:P10) -> 953504 | Q12: =SUM(Q7:Q10) -> 240000 | R12: =SUM(R7:R10) -> 14534666 | S12: =SUM(S7:S10) -> 56918070
A14: LIABILITIES, DEFERRED INFLOWS OF RESOURCES, AND FUND BALANCES
B15: Liabilities:
C16: Accounts payable | K16: 215747 | L16: 197049 | M16: 8969 | N16: 127806 | Q16: 74281 | R16: 510711 | S16: =SUM(K16:R16) -> 1134563
C17: Accrued liabilities | K17: 23935 | M17: 1811 | N17: 33221 | R17: 39940 | S17: =SUM(K17:R17) -> 98907
C18: Unearned revenues | M18: 24101 | S18: =SUM(K18:R18) -> 24101
C19: Due to other funds | K19: 2912257 | L19: 1081243 | M19: 4641840 | P19: 3733175 | Q19: 2569001 | R19: 2717850 | S19: =SUM(K19:R19) -> 17655366
C20: Due to other governmental entities | R20: 89704 | S20: =SUM(K20:R20) -> 89704
C21: Other liabilities | K21: 174640 | S21: =SUM(K21:R21) -> 174640
E23: Total liabilities: | K23: =SUM(K16:K21) -> 3326579 | L23: =SUM(L16:L21) -> 1278292 | M23: =SUM(M16:M21) -> 4676721 | N23: =SUM(N16:N21) -> 161027 | O23: =SUM(O16:O21) -> 0 | P23: =SUM(P16:P21) -> 3733175 | Q23: =SUM(Q16:Q21) -> 2643282 | R23: =SUM(R16:R21) -> 3358205 | S23: =SUM(S16:S21) -> 19177281
A25: DEFERRED INFLOWS OF RESOURCES:
C26: Unavailable revenues | S26: =SUM(K26:R26) -> 0
B28: Fund Balances:
C29: Restricted for:
D30: Sales tax dedications | L30: 8077914 | M30: 4928006 | S30: =SUM(K30:R30) -> 13005920
D31: Other general government | R31: 112407 | S31: =SUM(K31:R31) -> 112407
D32: Public works | N32: 9692863 | R32: 619192 | S32: =SUM(K32:R32) -> 10312055
D33: Public safety | R33: 3404919 | S33: =SUM(K33:R33) -> 3404919
D34: Culture and recreation | R34: 337909 | S34: =SUM(K34:R34) -> 337909
D35: Economic development | R35: 1576497 | S35: =SUM(K35:R35) -> 1576497
D36: Health and welfare | R36: 781564 | S36: =SUM(K36:R36) -> 781564
D37: Debt service | O37: 5413502 | R37: 141721 | S37: =SUM(K37:R37) -> 5555223
D38: Capital outlay | S38: =SUM(K38:R38) -> 0
C39: Commited to: | S39: =SUM(K39:R39) -> 0
D40: Other general government | R40: 471828 | S40: =SUM(K40:R40) -> 471828
D41: Public works | R41: 488420 | S41: =SUM(K41:R41) -> 488420
D42: Public safety | S42: =SUM(K42:R42) -> 0
D43: Economic development | R43: 190298 | S43: =SUM(K43:R43) -> 190298
D44: Health and welfare | R44: 43500 | S44: =SUM(K44:R44) -> 43500
C45: Assigned to: | S45: =SUM(K45:R45) -> 0
D46: Economic development | R46: 1437829 | S46: =SUM(K46:R46) -> 1437829
D47: Debt service | R47: 19794 | S47: =SUM(K47:R47) -> 19794
C48: Unassigned | K48: 3634996 | P48: -2779671 | Q48: -2403282 | R48: 1550583 | S48: =SUM(K48:R48) -> 2626
E50: Total fund balance: | K50: =SUM(K29:K48) -> 3634996 | L50: =SUM(L29:L48) -> 8077914 | M50: =SUM(M29:M48) -> 4928006 | N50: =SUM(N29:N48) -> 9692863 | O50: =SUM(O29:O48) -> 5413502 | P50: =SUM(P29:P48) -> -2779671 | Q50: =SUM(Q29:Q48) -> -2403282 | R50: =SUM(R29:R48) -> 11176461 | S50: =SUM(S29:S48) -> 37740789
E52: Total liabilities and fund balances: | K52: =SUM(K23+K50) -> 6961575 | L52: =SUM(L50,L23,L26) -> 9356206 | M52: =SUM(M50,M23,M26) -> 9604727 | N52: =SUM(N50,N23,N26) -> 9853890 | O52: =SUM(O50,O23,O26) -> 5413502 | P52: =SUM(P50,P23,P26) -> 953504 | Q52: =SUM(Q50,Q23,Q26) -> 240000 | R52: =SUM(R50,R23,R26) -> 14534666 | S52: =SUM(S50,S23,S26) -> 56918070

Sheet St. Tammany
D1: St.Tammany Combined Balance Sheet
D2: Issued: December 31, 2014
K4: Major Funds
K5: 010, 012 General Fund | L5: 013 St. Tammany Parish Library | M5: 015 Public Works | N5: 300 Capital Improvements - General | O5: Total Non-Major Governmental Funds | P5: Total Governmental Funds
A6: Assets:
B7: Cash and Cash equivalents | K7: 1552747 | L7: 277492 | M7: 784454 | N7: 546548 | O7: 27626589 | P7: =SUM(K7:O7) -> 30787830
B8: Investments | K8: 8685447 | M8: 19140591 | N8: 21450220 | O8: 64293995 | P8: =SUM(K8:O8) -> 113570253
B9: Receivables, net of allowances for uncollectibles:
C10: Ad valorem/parcel fees | K10: 4374077 | L10: 9025649 | O10: 16428046 | P10: =SUM(K10:O10) -> 29827772
C11: Sales and use tax | M11: 7722222 | O11: 4211430 | P11: =SUM(K11:O11) -> 11933652
C12: Other | K12: 1806688 | L12: 140388 | M12: 1135575 | N12: 85877 | O12: 7295686 | P12: =SUM(K12:O12) -> 10464214
B13: Due from component units | K13: 35390 | O13: 316874 | P13: =SUM(K13:O13) -> 352264
B14: Prepaid items | K14: 8829 | M14: 6230 | O14: 5024 | P14: =SUM(K14:O14) -> 20083
B15: Restricted assets | N15: 2697704 | O15: 16316621 | P15: =SUM(K15:O15) -> 19014325
E17: Total Assets: | K17: =SUM(K7:K15) -> 16463178 | L17: =SUM(L7:L15) -> 9443529 | M17: =SUM(M7:M15) -> 28789072 | N17: =SUM(N7:N15) -> 24780349 | O17: =SUM(O7:O15) -> 136494265 | P17: =SUM(P7:P15) -> 215970393
A19: LIABILITIES
B20: Liabilities:
C21: Accounts, salaries, and other payables | K21: 2857724 | L21: 582279 | M21: 1644450 | N21: 1223794 | O21: 14543055 | P21: =SUM(K21:O21) -> 20851302
C22: Due to other funds | O22: 1676546 | P22: =SUM(K22:O22) -> 1676546
C23: Due to component units | L23: 8640205 | P23: =SUM(K23:O23) -> 8640205
C24: Unearned revenue | K24: 73336 | M24: 185872 | O24: 3040773 | P24: =SUM(K24:O24) -> 3299981
C25: Other liabilities | K25: 1636340 | L25: 19160 | M25: 28500 | O25: 315849 | P25: =SUM(K25:O25) -> 1999849
E27: Total liabilities: | K27: =SUM(K21:K25) -> 4567400 | L27: =SUM(L21:L25) -> 9241644 | M27: =SUM(M21:M25) -> 1858822 | N27: =SUM(N21:N25) -> 1223794 | O27: =SUM(O21:O25) -> 19576223 | P27: =SUM(P21:P25) -> 36467883
A29: DEFERRED INFLOWS OF RESOURCES
B30: Unavailable revenue-ad valorem/parcel fees | K30: 65830 | L30: 131526 | O30: 235907 | P30: =SUM(K30:O30) -> 433263
B31: Unavailable revenue-state revenue sharing | K31: 92821 | L31: 70359 | O31: 72341 | P31: =SUM(K31:O31) -> 235521
E33: Total deferred inflows of resources | K33: =SUM(K30:K31) -> 158651 | L33: =SUM(L30:L31) -> 201885 | M33: =SUM(M30:M31) -> 0 | N33: =SUM(N30:N31) -> 0 | O33: =SUM(O30:O31) -> 308248 | P33: =SUM(P30:P31) -> 668784
B36: Fund Balances
C37: Nonspendable, prepaid items | K37: 8829 | M37: 6230 | O37: 5024 | P37: =SUM(K37:O37) -> 20083
C38: Restricted | M38: 26187887 | N38: 23556555 | O38: 95759421 | P38: =SUM(K38:O38) -> 145503863
C39: Commited | M39: 736133 | O39: 20845349 | P39: =SUM(K39:O39) -> 21581482
C40: Unassigned | K40: 11728298 | P40: =SUM(K40:O40) -> 11728298
E42: Total fund balances: | K42: =SUM(K37:K40) -> 11737127 | L42: =SUM(L37:L40) -> 0 | M42: =SUM(M37:M40) -> 26930250 | N42: =SUM(N37:N40) -> 23556555 | O42: =SUM(O37:O40) -> 116609794 | P42: =SUM(P37:P40) -> 178833726
E44: Total liabilities, deferred inflows of resouces, and fund balances: | K44: =SUM(K27+K33+K42) -> 16463178 | L44: =SUM(L27+L33+L42) -> 9443529 | M44: =SUM(M27+M33+M42) -> 28789072 | N44: =SUM(N27+N33+N42) -> 24780349 | O44: =SUM(O27+O33+O42) -> 136494265
P48: 408686007
P50: 402395
P52: 72620538
P55: -88013974
P56: 542528692

Sheet Tangipahoa
D1: Tangipahoa Combined Balance Sheet
D2: Issued: December 31, 2014
K5: General Fund | L5: Road and Bridge Funds | M5: Garbage District No. 1 | N5: Health Unit | O5: Long Term Recovery Fund | P5: Other Governmental Funds | Q5: Total Governmental Funds
A6: Assets:
B7: Cash and Cash equivalents | K7: 33530 | L7: 8876791 | M7: 3237884 | N7: 70094 | O7: 231501 | P7: 3246034 | Q7: =SUM(K7:P7) -> 15695834
B8: Receivables, net | K8: 2202810 | L8: 1365357 | M8: 3086864 | N8: 2278085 | O8: 77983 | P8: 861646 | Q8: =SUM(K8:P8) -> 9872745
B9: Due from other governments | K9: 414377 | Q9: =SUM(K9:P9) -> 414377
B10: Due from other funds | K10: 399279 | N10: 700000 | Q10: =SUM(K10:P10) -> 1099279
B11: Restricted assets - cash | K11: 570546 | L11: 100758 | M11: 176461 | N11: 20060 | O11: 150368 | P11: 9531 | Q11: =SUM(K11:P11) -> 1027724
E13: Total Assets: | K13: =SUM(K7:K11) -> 3620542 | L13: =SUM(L7:L11) -> 10342906 | M13: =SUM(M7:M11) -> 6501209 | N13: =SUM(N7:N11) -> 3068239 | O13: =SUM(O7:O11) -> 459852 | P13: =SUM(P7:P11) -> 4117211 | Q13: =SUM(Q7:Q11) -> 28109959
A15: LIABILITIES
C16: Accounts, salaries, and other payables | K16: 618185 | L16: 1287808 | M16: 271599 | N16: 173149 | O16: 134347 | P16: 170359 | Q16: =SUM(K16:P16) -> 2655447
C17: Due to other governments | K17: 48085 | M17: 104756 | P17: 291924 | Q17: =SUM(K17:P17) -> 444765
C18: Due to other funds | K18: 700000 | O18: 176000 | P18: 233179 | Q18: =SUM(K18:P18) -> 1109179
E20: Total liabilities: | K20: =SUM(K16:K18) -> 1366270 | L20: =SUM(L16:L18) -> 1287808 | M20: =SUM(M16:M17) -> 376355 | N20: =SUM(N16:N19) -> 173149 | O20: =SUM(O16:O18) -> 310347 | P20: =SUM(P16:P18) -> 695462 | Q20: =SUM(Q16:Q18) -> 4209391
A22: Deferred Inflow of Resources
B23: Grant Funds | K23: 0 | L23: 0 | M23: 0 | N23: 0 | O23: 150368 | Q23: =SUM(K23:O23) -> 150368
E25: Total Deferred inflow of Resources | K25: 0 | L25: 0 | M25: 0 | N25: 0 | O25: =SUM(O23:O23) -> 150368 | Q25: =SUM(Q23:Q23) -> 150368
B27: Fund Balances
C28: Restricted | K28: 225386 | L28: 8970571 | M28: 6101161 | N28: 2875030 | P28: 3337814 | Q28: =SUM(K28:P28) -> 21509962
C29: Commited | K29: 497560 | P29: 49451 | Q29: =SUM(K29:P29) -> 547011
C30: Assigned | K30: 72986 | L30: 84527 | M30: 23693 | N30: 20060 | P30: 69324 | Q30: =SUM(K30:P30) -> 270590
C31: Unassigned | K31: 1458340 | O31: -863 | P31: -34840 | Q31: =SUM(K31:P31) -> 1422637
E33: Total fund balances | K33: =SUM(K28:K31) -> 2254272 | L33: =SUM(L28:L31) -> 9055098 | M33: =SUM(M28:M31) -> 6124854 | N33: =SUM(N28:N31) -> 2895090 | O33: =SUM(O28:O31) -> -863 | P33: =SUM(P28:P31) -> 3421749 | Q33: =SUM(Q28:Q31) -> 23750200
E35: Total liabilities, Deferred inflow of Resources, | K35: =SUM(K33,K20,K25) -> 3620542 | L35: =SUM(L33,L20,L25) -> 10342906 | M35: =SUM(M33,M20,M25) -> 6501209 | N35: =SUM(N33,N20,N25) -> 3068239 | O35: =SUM(O20+O25+O33) -> 459852 | P35: =SUM(P20+P25+P33) -> 4117211 | Q35: =SUM(Q33,Q20,Q25) -> 28109959
F36: and fund balances:

Sheet Tensas
D1: Tensas Combined Balance Sheet
D2: Issued: December 31, 2014
J5: General Fund | K5: Road Fund | L5: Ambulance Fund | M5: Health Unit Fund | N5: Waste Collection Fund | O5: Landfill Site Fund | P5: Fire Protection Fund | Q5: Other Governmental Funds | R5: Total
A6: Assets:
B7: Cash and cash equivalents | J7: 196285 | K7: 114758 | L7: 41693 | M7: 450731 | N7: 255434 | O7: 195926 | P7: 22745 | Q7: 695184 | R7: =SUM(J7:Q7) -> 1972756
B8: Receivables | J8: 735895 | K8: 43294 | L8: 46884 | M8: 190577 | N8: 61066 | O8: - | P8: 10824 | Q8: 325346 | R8: =SUM(J8:Q8) -> 1413886
B9: Amounts held by trustee for landfill closure and post-closure care costs | J9: - | K9: - | L9: - | M9: - | N9: - | O9: 980324 | P9: - | Q9: - | R9: =SUM(J9:Q9) -> 980324
B10: Restricted assets | J10: - | K10: - | L10: - | M10: - | N10: - | O10: - | P10: - | Q10: 24008 | R10: =SUM(J10:Q10) -> 24008
B11: Due from other funds | J11: - | K11: 36137 | L11: 39135 | M11: - | N11: 24086 | O11: - | P11: 9034 | Q11: 18069 | R11: =SUM(J11:Q11) -> 126461
E13: Total assets: | J13: =SUM(J7:J11) -> 932180 | K13: =SUM(K7:K11) -> 194189 | L13: =SUM(L7:L11) -> 127712 | M13: =SUM(M7:M11) -> 641308 | N13: =SUM(N7:N11) -> 340586 | O13: =SUM(O7:O11) -> 1176250 | P13: =SUM(P7:P11) -> 42603 | Q13: =SUM(Q7:Q11) -> 1062607 | R13: =SUM(R7:R11) -> 4517435
A15: LIABILITIES AND FUND BALANCES
B16: Liabilities:
C17: Accounts, salaries, and other payables | J17: 28113 | K17: 40171 | L17: 30629 | M17: 3211 | N17: 45911 | O17: - | P17: - | Q17: 38532 | R17: =SUM(J17:Q17) -> 186567
C18: Due to other funds | J18: 126461 | K18: - | L18: - | M18: - | N18: - | O18: - | P18: - | Q18: - | R18: =SUM(J18:Q18) -> 126461
C19: Intergovernmental payables | J19: - | K19: - | L19: - | M19: - | N19: - | O19: - | P19: 52119 | Q19: - | R19: =SUM(J19:Q19) -> 52119
E21: Total liabilities: | J21: =SUM(J17:J19) -> 154574 | K21: =SUM(K17:K19) -> 40171 | L21: =SUM(L17:L19) -> 30629 | M21: =SUM(M17:M19) -> 3211 | N21: =SUM(N17:N19) -> 45911 | O21: =SUM(O17:O19) -> 0 | P21: =SUM(P16:P19) -> 52119 | Q21: =SUM(Q17:Q19) -> 38532 | R21: =SUM(R16:R19) -> 365147
A23: Fund Balances (deficit)
C24: Restricted for:
D25: Debt service | J25: - | K25: - | L25: - | M25: - | N25: - | O25: - | P25: - | Q25: 24008 | R25: =SUM(J25:Q25) -> 24008
D26: Landfill closure | J26: - | K26: - | L26: - | M26: - | N26: - | O26: 1176250 | P26: - | Q26: - | R26: =SUM(J26:Q26) -> 1176250
C27: Committed for:
D28: Special revenue projects | J28: - | K28: 154018 | L28: 97083 | M28: 638097 | N28: 294675 | O28: - | P28: -9516 | Q28: 1000067 | R28: =SUM(J28:Q28) -> 2174424
C29: Unassigned, reported in:
D30: General | J30: 777606 | K30: - | L30: - | M30: - | N30: - | O30: - | P30: - | Q30: - | R30: =SUM(J30:Q30) -> 777606
E32: Total fund balances: | J32: =SUM(J27:J30) -> 777606 | K32: =SUM(K27:K30) -> 154018 | L32: =SUM(L27:L30) -> 97083 | M32: =SUM(M27:M30) -> 638097 | N32: =SUM(N27:N30) -> 294675 | O32: =SUM(O25:O30) -> 1176250 | P32: =SUM(P25:P30) -> -9516 | Q32: =SUM(Q25:Q30) -> 1024075 | R32: =SUM(R25:R30) -> 4152288
E34: Total liabilities and fund balances: | J34: =SUM(J32+J21) -> 932180 | K34: =SUM(K32+K21) -> 194189 | L34: =SUM(L32+L21) -> 127712 | M34: =SUM(M32+M21) -> 641308 | N34: =SUM(N32+N21) -> 340586 | O34: =SUM(O32+O21) -> 1176250 | P34: =SUM(P32+P21) -> 42603 | Q34: =SUM(Q32+Q21) -> 1062607 | R34: =SUM(R32+R21) -> 4517435

Sheet St. Landry
D1: St. Landry Combined Balance Sheet
D2: Issued: December 31, 2014
K4: General Fund | L4: Road and Bridge Maintenance Fund | M4: Health Unit Maintenance Fund | N4: Airport Maintenance Fund | O4: LCDBG Disaster Recovery Fund | P4: Road District 1 Sales Tax | Q4: Road District 1 Construction | R4: Road District 1 Sinking Fund | S4: Other Governmental Funds | T4: Total Governmental Funds
A5: Assets:
B6: Cash and interest-bearing deposits | K6: 610783 | L6: 62025 | N6: 39559 | O6: 3345 | S6: 865071 | T6: =SUM(K6:S6) -> 1580783
B7: Cash and cash equivalents, restricted | P7: 920945 | Q7: 2311081 | R7: 4 | T7: =SUM(K7:S7) -> 3232030
B8: Receivables | K8: 2409716 | L8: 142480 | M8: 1300905 | O8: 378783 | P8: 732289 | S8: 1441726 | T8: =SUM(K8:S8) -> 6405899
B9: Prepaid items | K9: 10350 | Q9: 229168 | T9: =SUM(K9:S9) -> 239518
B10: Investments, restricted | Q10: 56180653 | T10: =SUM(K10:S10) -> 56180653
B11: Due from other funds | K11: 754920 | L11: 104 | M11: 110463 | O11: 4910 | P11: 1000000 | S11: 96932 | T11: 1967329
B12: Due from agency funds | K12: 22852 | L12: 255285 | N12: 6962 | T12: =SUM(K12:S12) -> 285099
B13: Due from component units | K13: 4555 | T13: =SUM(K13:S13) -> 4555
B14: Due from other governments | K14: 140373 | T14: =SUM(K14:S14) -> 140373
E16: Total assets: | K16: =SUM(K6:K14) -> 3953549 | L16: =SUM(L6:L14) -> 459894 | M16: =SUM(M6:M14) -> 1411368 | N16: =SUM(N6:N14) -> 46521 | O16: =SUM(O6:O14) -> 387038 | P16: =SUM(P6:P14) -> 2653234 | Q16: =SUM(Q6:Q14) -> 58720902 | R16: =SUM(R6:R14) -> 4 | S16: =SUM(S6:S15) -> 2403729 | T16: =SUM(T6:T14) -> 70036239
A18: LIABILITIES AND FUND BALANCES
B19: Liabilities:
C20: Bank overdraft | M20: 217 | S20: 18794 | T20: =SUM(K20:S20) -> 19011
C21: Accounts payable | K21: 308489 | L21: 243114 | M21: 84397 | N21: 55970 | O21: 378789 | P21: 41411 | Q21: 2893888 | S21: 333639 | T21: =SUM(K21:S21) -> 4339697
C22: Accrued expenditures | K22: 222805 | L22: 70735 | M22: 45478 | N22: 5550 | S22: 15846 | T22: =SUM(K22:S22) -> 360414
C23: Defered revenue | N23: 4387 | T23: =SUM(K23:S23) -> 4387
C24: Due to agency funds | K24: 95000 | T24: =SUM(K24:S24) -> 95000
C25: Due to other funds | K25: 1102714 | L25: 211410 | M25: 343404 | N25: 67424 | S25: 242377 | T25: =SUM(K25:S25) -> 1967329
C26: Due to component units | K26: 6389 | T26: =SUM(K26:S26) -> 6389
E28: Total liabilities: | K28: =SUM(K21:K26) -> 1735397 | L28: =SUM(L21:L26) -> 525259 | M28: =SUM(M21:M26) -> 473279 | N28: =SUM(N21:N26) -> 133331 | O28: =SUM(O21:O26) -> 378789 | P28: =SUM(P21:P26) -> 41411 | Q28: =SUM(Q21:Q26) -> 2893888 | R28: =SUM(R20:R27) -> 0 | S28: =SUM(S20:S26) -> 610656 | T28: =SUM(T20:T26) -> 6792227
B30: Fund Balances
C31: Non-spendable:
D32: Prepaids | K32: 10350 | Q32: 229168 | T32: =SUM(K32:S32) -> 239518
C33: Restricted for: | T33: =SUM(K33:S33) -> 0
D34: Other general government | S34: 169372 | T34: =SUM(K34:S34) -> 169372
D35: Public works | S35: 1181404 | T35: =SUM(K35:S35) -> 1181404
D36: Prisoner expense and jury witness | K36: 245700 | T36: =SUM(K36:S36) -> 245700
D37: Judicial expenses | K37: 54672 | T37: =SUM(K37:S37) -> 54672
D38: Public safety | S38: 383212 | T38: =SUM(K38:S38) -> 383212
D39: Economic development | S39: 24800 | T39: =SUM(K39:S39) -> 24800
D40: Health and welfare | M40: 937872 | T40: =SUM(K40:S40) -> 937872
D41: Capital projects | K41: 1144 | S41: 298 | T41: =SUM(K41:S41) -> 1442
D42: Parish road construction | P42: 2611823 | Q42: 55597846 | T42: =SUM(K42:S42) -> 58209669
D43: Debt service | R43: 4 | S43: 33987 | T43: =SUM(K43:S43) -> 33991
C44: Committed to: | T44: =SUM(K44:S44) -> 0
D45: General contingencies | K45: 295101 | T45: =SUM(K45:S45) -> 295101
C46: Assigned to | T46: =SUM(K46:S46) -> 0
D47: Public works | K47: 176458 | T47: =SUM(K47:S47) -> 176458
D48: Judicial expenses | K48: 121937 | T48: =SUM(K48:S48) -> 121937
D49: Public safety | K49: 44601 | T49: =SUM(K49:S49) -> 44601
C50: Unassigned | K50: 1268189 | L50: -65365 | N50: -86810 | O50: 8249 | T50: =SUM(K50:S50) -> 1124263
T51: =SUM(K51:S51) -> 0
E52: Total fund balance: | K52: =SUM(K32:K50) -> 2218152 | L52: =SUM(L32:L50) -> -65365 | M52: =SUM(M32:M50) -> 937872 | N52: =SUM(N32:N50) -> -86810 | O52: =SUM(O32:O50) -> 8249 | P52: =SUM(P32:P50) -> 2611823 | Q52: =SUM(Q32:Q50) -> 55827014 | R52: =SUM(R32:R50) -> 4 | ... T52: =SUM(T32:T50) -> 63244012
E54: Total liabilities and fund balances: | K54: =SUM(K52,K28) -> 3953549 | L54: =SUM(L28,L52) -> 459894 | M54: =SUM(M28,M52) -> 1411151 | N54: =SUM(N28,N52) -> 46521 | O54: =SUM(O28+O52) -> 387038 | P54: =SUM(P28+P52) -> 2653234 | Q54: =SUM(Q28+Q52) -> 58720902 | R54: =SUM(R28+R52) -> 4 | S54: =SUM(S28,S52) -> 2403729 | T54: =SUM(T28,T52) -> 70036239

Sheet St. Mary
D1: St. Mary Combined Balance Sheet
D2: Issued: December 31, 2014
K5: General Fund | L5: Road Construction & Maintenance Fund | M5: Sanitation Fund | N5: Capital Improvement Fund | O5: CDBG Recovery Fund | P5: Combined Sewer Construction Fund | Q5: Other Governmental Funds | R5: Total Governmental Funds
A6: Assets:
B7: Cash and cash equivalents | K7: 543913 | L7: 123 | M7: 1 | O7: 235 | P7: 1 | Q7: 2913039 | R7: =SUM(K7:Q7) -> 3457312
B8: Investments | L8: 2711991 | M8: 684950 | N8: 3482462 | P8: 2588774 | Q8: 3606579 | R8: =SUM(K8:Q8) -> 13074756
B9: Receivables (net, where applicable of | R9: =SUM(K9:Q9) -> 0
C10: allowances for uncollectibles) | K10: 525670 | L10: 106793 | M10: 17550 | N10: 52500 | Q10: 190041 | R10: =SUM(K10:Q10) -> 892554
B11: Due from component units | K11: 1591344 | L11: 1523 | M11: 236798 | N11: 136 | P11: 669137 | R11: =SUM(K11:Q11) -> 2498938
B12: Due from other governments | K12: 3432777 | L12: 2601623 | M12: 584062 | N12: 2612456 | Q12: 1983583 | R12: =SUM(K12:Q12) -> 11214501
B13: Due from other funds | K13: 147639 | L13: 82554 | M13: 2182 | Q13: 6576 | R13: =SUM(K13:Q13) -> 238951
B14: Advances to other funds | K14: 246000 | L14: 1138310 | M14: 104951 | Q14: 1617615 | R14: =SUM(K14:Q14) -> 3106876
B15: Other assets | Q15: 71914 | R15: =SUM(K15:Q15) -> 71914
E17: Total Assets: | K17: =SUM(K7:K15) -> 6487343 | L17: =SUM(L7:L15) -> 6642917 | M17: =SUM(M7:M15) -> 1630494 | N17: =SUM(N7:N15) -> 6147554 | O17: =SUM(O7:O15) -> 235 | P17: =SUM(P7:P15) -> 3257912 | Q17: =SUM(Q7:Q15) -> 10389347 | R17: =SUM(R7:R15) -> 34555802
A19: LIABILITIES
C20: Accounts payable | K20: 609343 | L20: 223201 | M20: 214184 | Q20: 427669 | R20: =SUM(K20:Q20) -> 1474397
C21: Contracts payable | N21: 1236225 | R21: =SUM(K21:Q21) -> 1236225
C22: Retainage payable | L22: 58067 | N22: 182978 | R22: =SUM(K22:Q22) -> 241045
C23: Accrued liabilities | K23: 285491 | L23: 110932 | M23: 3759 | Q23: 139903 | R23: =SUM(K23:Q23) -> 540085
C24: Due to component units | K24: 100000 | R24: =SUM(K24:Q24) -> 100000
C25: Due to other governmental units | Q25: 104452 | R25: =SUM(K25:Q25) -> 104452
C26: Due to other funds | K26: 303170 | R26: =SUM(K26:Q26) -> 303170
C27: Advance from other funds | K27: 3425597 | L27: 123000 | N27: 3032429 | P27: 2676491 | Q27: 649714 | R27: =SUM(K27:Q27) -> 9907231
E29: Total liabilities: | K29: =SUM(K20:K27) -> 4723601 | L29: =SUM(L20:L27) -> 515200 | M29: =SUM(M20:M27) -> 217943 | N29: =SUM(N20:N27) -> 4451632 | O29: =SUM(O20:O27) -> 0 | P29: =SUM(P20:P27) -> 2676491 | Q29: =SUM(Q20:Q27) -> 1321738 | R29: =SUM(R20:R27) -> 13906605
B31: Fund Balances (deficit)
C32: Nonspendable- non-current receivables | K32: 1550000 | L32: 958000 | P32: 611137 | R32: =SUM(K32:Q32) -> 3119137
C33: Restricted for: | R33: =SUM(K33:Q33) -> 0
D34: Use in specific geographic areas | Q34: 1845025 | R34: =SUM(K34:Q34) -> 1845025
D35: Debt service | Q35: 2585368 | R35: =SUM(K35:Q35) -> 2585368
C36: Assigned for: | R36: =SUM(K36:Q36) -> 0
D37: General government | Q37: 149465 | R37: =SUM(K37:Q37) -> 149465
D38: Public safety | Q38: 56678 | R38: =SUM(K38:Q38) -> 56678
D39: Public works | L39: 5169717 | Q39: 150145 | R39: =SUM(K39:Q39) -> 5319862
D40: Culture and recreation | Q40: 289307 | R40: =SUM(K40:Q40) -> 289307
D41: Health and welfare | Q41: 635782 | R41: =SUM(K41:Q41) -> 635782
D42: Urban redevelopment and housing | Q42: 8642 | R42: =SUM(K42:Q42) -> 8642
D43: Debt service | Q43: 2647532 | R43: =SUM(K43:Q43) -> 2647532
D44: Sanitation | M44: 1412551 | R44: =SUM(K44:Q44) -> 1412551
D45: Capital projects | N45: 1695922 | O45: 235 | R45: =SUM(K45:Q45) -> 1696157
C46: Unassigned | K46: 213742 | P46: -29716 | Q46: 649665 | R46: =SUM(K46:Q46) -> 833691
E48: Total fund balance: | K48: =SUM(K32:K46) -> 1763742 | L48: =SUM(L32:L46) -> 6127717 | M48: =SUM(M32:M46) -> 1412551 | N48: =SUM(N32:N46) -> 1695922 | O48: =SUM(O32:O46) -> 235 | P48: =SUM(P32:P46) -> 581421 | Q48: =SUM(Q32:Q46) -> 9017609 | R48: =SUM(R32:R46) -> 20599197
E50: Total liabilities and fund balances: | K50: =SUM(K48+K29) -> 6487343 | L50: =SUM(L48,L29,) -> 6642917 | M50: =SUM(M48,M29,) -> 1630494 | N50: =SUM(N48,N29,) -> 6147554 | O50: =SUM(O48,O29,) -> 235 | P50: =SUM(P48,P29,) -> 3257912 | Q50: =SUM(Q48+Q29) -> 10339347 | R50: =SUM(R48+R29) -> 34505802

Sheet Terrebonne
D1: Terrebonne Combined Balance Sheet
D2: Issued: December 31, 2014
K5: General Fund | L5: Public Safety Fund | M5: Grant Fund | N5: Road and Bridge Maintenance Fund | O5: Drainage Maintenance Fund | P5: Terrebonne Levee & Conservation District Fund | Q5: Capital Projects Fund | R5: Other Governmental Funds | S5: Total Governmental Funds
A6: Assets:
B7: Cash and cash equivalents | K7: 6151643 | L7: 4469121 | M7: 13073789 | N7: 2336695 | O7: 6557089 | P7: 1962244 | Q7: 39251509 | R7: 7779430 | S7: =SUM(K7:R7) -> 81581520
B8: Investments | K8: 1326383 | M8: 2914 | N8: 991963 | O8: 1141951 | P8: 7708046 | Q8: 12115058 | R8: 21870799 | S8: =SUM(K8:R8) -> 45157114
B9: Receivables (net, where applicable of | Q9: =SUM(O9:P9) -> 0 | S9: =SUM(K9:R9) -> 0
C10: allowances for uncollectibles)
C11: Taxes | K11: 215334 | L11: 353207 | O11: 567608 | R11: 1199365 | S11: =SUM(K11:R11) -> 2335514
C12: Accounts | L12: 31772 | M12: 131224 | N12: 3159 | O12: 13153 | Q12: 65 | R12: 29802 | S12: =SUM(K12:R12) -> 209175
C13: Other | M13: 323 | Q13: =SUM(O13:P13) -> 0 | R13: 60248 | S13: =SUM(K13:R13) -> 60571
C14: Economic loans | M14: 10496724 | Q14: =SUM(O14:P14) -> 0 | S14: =SUM(K14:R14) -> 10496724
B15: Due from other funds | K15: 26546844 | L15: 37053 | M15: 877721 | N15: 176035 | O15: 151891 | P15: 125142 | Q15: 6562749 | R15: 2251183 | S15: =SUM(K15:R15) -> 36728618
B16: Due from other governmental units | K16: 6745876 | L16: 5306057 | M16: 9077635 | N16: 1260650 | O16: 7470163 | P16: 1117361 | Q16: 10119669 | R16: 13620833 | S16: =SUM(K16:R16) -> 54718244
B17: Due from component units | K17: 121923 | Q17: =SUM(O17:P17) -> 0 | S17: =SUM(K17:R17) -> 121923
B18: Inventories | M18: 14520 | Q18: =SUM(O18:P18) -> 0 | S18: =SUM(K18:R18) -> 14520
B19: Other assets | K19: 3421 | M19: 650 | N19: 40 | Q19: =SUM(O19:P19) -> 0 | S19: =SUM(K19:R19) -> 4111
B20: Restricted assets: | Q20: =SUM(O20:P20) -> 0 | S20: =SUM(K20:R20) -> 0
C21: Cash and cash equivalents | K21: 69340 | M21: 224150 | Q21: =SUM(O21:P21) -> 0 | S21: =SUM(K21:R21) -> 293490
E23: Total Assets: | K23: =SUM(K7:K21) -> 41180764 | L23: =SUM(L7:L21) -> 10197210 | M23: =SUM(M7:M21) -> 33899650 | N23: =SUM(N7:N21) -> 4768542 | O23: =SUM(O7:O21) -> 15901855 | P23: =SUM(P7:P21) -> 10912793 | Q23: =SUM(Q7:Q21) -> 68049050 | R23: =SUM(R7:R21) -> 46811660 | S23: =SUM(S7:S21) -> 231721524
A25: LIABILITIES
C26: Accounts payable and accrued expenditures | K26: 690877 | L26: 305452 | M26: 620817 | N26: 257425 | O26: 359677 | Q26: 4793247 | R26: 278331 | S26: =SUM(K26:R26) -> 7305826
C27: Liability for work completed on contracts | K27: 1446 | M27: 49695 | Q27: 1067378 | R27: 5000 | S27: =SUM(K27:R27) -> 1123519
C28: Unavailable revenue | K28: 3163965 | L28: 4349823 | O28: 6689358 | R28: 13997026 | S28: =SUM(K28:R28) -> 28200172
C29: Grant Advancement | M29: 11324603 | S29: =SUM(K29:R29) -> 11324603
C30: Due to other funds | K30: 19742994 | L30: 809194 | M30: 16058449 | N30: 552000 | O30: 883277 | P30: 24205 | Q30: 4032240 | R30: 2076477 | S30: =SUM(K30:R30) -> 44178836
C31: Due to other governmental units | K31: 616614 | L31: 218998 | M31: 668625 | N31: 19642 | O31: 24679 | Q31: 6344 | R31: 177059 | S31: =SUM(K31:R31) -> 1731961
C32: Due to component units | K32: 34 | S32: =SUM(K32:R32) -> 34
C33: Payable from restricted assets: | S33: =SUM(K33:R33) -> 0
D34: Tenents' escrow accounts | M34: 133229 | S34: =SUM(K34:R34) -> 133229
E36: Total liabilities: | K36: =SUM(K26:K34) -> 24215930 | L36: =SUM(L26:L34) -> 5683467 | M36: =SUM(M26:M34) -> 28855418 | N36: =SUM(N26:N34) -> 829067 | O36: =SUM(O26:O34) -> 7956991 | P36: =SUM(P26:P31) -> 24205 | Q36: =SUM(Q26:Q34) -> 9899209 | R36: =SUM(R26:R34) -> 16533893 | S36: =SUM(S26:S34) -> 93998180
B38: Fund Balances (deficit)
C39: Restricted for:
D40: Dedicated emergency | K40: 2500000 | S40: =SUM(K40:R40) -> 2500000
D41: Broadmoor trees | K41: 69340 | S41: =SUM(K41:R41) -> 69340
D42: Grants | M42: 3316805 | Q42: 13174010 | S42: =SUM(K42:R42) -> 16490815
D43: Capital projects | S43: =SUM(K43:R43) -> 0
D44: Drainage | O44: 2702056 | S44: =SUM(K44:R44) -> 2702056
D45: Levee and conservation | P45: 10888588 | S45: =SUM(K45:R45) -> 10888588
D46: Debt service | R46: 15059355 | S46: =SUM(K46:R46) -> 15059355
D47: Other special purposes | R47: 14231746 | S47: =SUM(K47:R47) -> 14231746
C48: Commited for: | S48: =SUM(K48:R48) -> 0
D49: Capital projects | Q49: 15990694 | S49: =SUM(K49:R49) -> 15990694
D50: Other special purposes | R50: 86742 | S50: =SUM(K50:R50) -> 86742
C51: Assigned for: | S51: =SUM(K51:R51) -> 0
D52: Subsequent year's expenditures | K52: 3127024 | S52: =SUM(K52:R52) -> 3127024
D53: Dedicated emergency | K53: 97857 | S53: =SUM(K53:R53) -> 97857
D54: Non-district recreation | K54: 329076 | S54: =SUM(K54:R54) -> 329076
D55: Parish prisoners | K55: 248839 | S55: =SUM(K55:R55) -> 248839
D56: City marshall | K56: 129947 | S56: =SUM(K56:R56) -> 129947
D57: Coastal restoration | K57: 81398 | S57: =SUM(K57:R57) -> 81398
D58: Public safety | L58: 4513743 | Q58: 28985137 | S58: =SUM(K58:R58) -> 33498880
D59: Capital projects | S59: =SUM(K59:R59) -> 0
D60: Grants | M60: 1727427 | S60: =SUM(K60:R60) -> 1727427
D61: Road and bridge | N61: 3939475 | S61: =SUM(K61:R61) -> 3939475
D62: Drainage | O62: 5242808 | S62: =SUM(K62:R62) -> 5242808
D63: Other special purposes | R63: 899924 | S63: =SUM(K63:R63) -> 899924
C64: Unassigned | K64: 10382353 | S64: =SUM(K64:R64) -> 10382353
E66: Total fund balance: | K66: =SUM(K39:K64) -> 16965834 | L66: =SUM(L39:L64) -> 4513743 | M66: =SUM(M39:M64) -> 5044232 | N66: =SUM(N39:N64) -> 3939475 | O66: =SUM(O39:O64) -> 7944864 | P66: =SUM(P39:P64) -> 10888588 | Q66: =SUM(Q39:Q64) -> 58149841 | R66: =SUM(R40:R64) -> 30277767 | S66: =SUM(S40:S64) -> 137724344
E68: Total liabilities and fund balances: | K68: =SUM(K66+K36) -> 41181764 | L68: =SUM(L66,L36,) -> 10197210 | M68: =SUM(M66,M36,) -> 33899650 | N68: =SUM(N66,N36,) -> 4768542 | O68: =SUM(O66,O36,) -> 15901855 | P68: =SUM(P66,P36,) -> 10912793 | Q68: =SUM(Q66,Q36,) -> 68049050 | R68: =SUM(R66+R36) -> 46811660 | S68: =SUM(S66+S36) -> 231722524

Sheet Union
D1: Union Combined Balance Sheet
D2: Issued: December 31, 2014
K4: General | L4: Road Maintenance | M4: Road Construction | N4: Sales Tax Landfill | O4: Detention Center | P4: Other Governmental Funds | Q4: Total Governmental Funds
A5: Assets:
B6: Cash and cash equivalents | K6: 79996 | L6: 452054 | M6: 1025625 | N6: 2922371 | O6: 500 | P6: 1775926 | Q6: =SUM(K6:P6) -> 6256472
B7: Investments | K7: 499287 | L7: 152391 | M7: 291069 | N7: 5794966 | O7: 37999 | P7: 637555 | Q7: =SUM(K7:P7) -> 7413267
B8: Receivables | K8: 1326848 | L8: 1062628 | M8: 835087 | N8: 389141 | O8: 158776 | P8: 870301 | Q8: =SUM(K8:P8) -> 4642781
B9: Due from other funds | K9: 12500 | Q9: =SUM(K9:P9) -> 12500
E11: Total assets: | K11: =SUM(K6:K9) -> 1918631 | L11: =SUM(L6:L9) -> 1667073 | M11: =SUM(M6:M9) -> 2151781 | N11: =SUM(N6:N9) -> 9106478 | O11: =SUM(O6:O9) -> 197275 | P11: =SUM(P6:P9) -> 3283782 | Q11: =SUM(Q6:Q9) -> 18325020
A13: LIABILITIES, DEFERRED INFLOWS AND FUND EQUITY
B14: Liabilities:
C15: Cash overdraft | K15: 23654 | O15: 1134940 | Q15: =SUM(K15:P15) -> 1158594
C16: Accounts payable | K16: 514177 | L16: 56279 | M16: 28951 | N16: 27044 | O16: 85160 | P16: 64618 | Q16: =SUM(K16:P16) -> 776229
C17: Salaries and related payables | K17: 89108 | L17: 16488 | N17: 10936 | P17: 18801 | Q17: =SUM(K17:P17) -> 135333
C18: Retainage payable | K18: 30838 | Q18: =SUM(K18:P18) -> 30838
C19: Deposits due others | L19: 355020 | Q19: =SUM(K19:P19) -> 355020
C20: Due to other funds | P20: 12500 | Q20: =SUM(K20:P20) -> 12500
E22: Total liabilities: | K22: =SUM(K15:K19) -> 657777 | L22: =SUM(L15:L19) -> 427787 | M22: =SUM(M15:M19) -> 28951 | N22: =SUM(N15:N19) -> 37980 | O22: =SUM(O15:O19) -> 1220100 | P22: =SUM(P15:P20) -> 95919 | Q22: =SUM(Q15:Q20) -> 2468514
A24: Deferred Inflows:
B25: Grant revenues pending | P25: 14194 | Q25: =SUM(K25:P25) -> 14194
B27: Fund equity- fund balances
C28: Restricted | L28: 1239286 | M28: 2122830 | N28: 9068498 | P28: 3181624 | Q28: =SUM(K28:P28) -> 15612238
C29: Unassigned | K29: 1260854 | O29: -1022825 | P29: -4955 | Q29: =SUM(K29:P29) -> 233074
E31: Total fund equity- fund balances: | K31: =SUM(K28:K29) -> 1260854 | L31: =SUM(L28:L29) -> 1239286 | M31: =SUM(M28:M29) -> 2122830 | N31: =SUM(N28:N29) -> 9068498 | O31: =SUM(O28:O29) -> -1022825 | P31: =SUM(P28:P29) -> 3176669 | Q31: =SUM(Q28:Q29) -> 15845312
E33: Total liabilities, deferred inflows, and fund equity: | K33: =K31+K25+K22 -> 1918631 | L33: =L31+L25+L22 -> 1667073 | M33: =M31+M25+M22 -> 2151781 | N33: =N31+N25+N22 -> 9106478 | O33: =O31+O25+O22 -> 197275 | P33: =P31+P25+P22 -> 3286782 | Q33: =Q31+Q25+Q22 -> 18328020

Sheet Vermillion
D1: Vermillion Combined Balance Sheet
D2: Issued: December 31, 2013 | E2: Issued December 31, 2014
K5: General | L5: 1976 Sales Tax Fund | M5: 1978 Sales Tax Fund | N5: 1994 Sales Tax Fund | O5: Royalty Road Fund | P5: Parishwide Public Improvement Maintenance Fund | Q5: Project Account Fund | R5: Other Governmental Funds | S5: Total (Memorandum Only)
A6: Assets:
B7: Cash and interest-bearing deposits | K7: 1093899 | L7: 10364185 | M7: 11603963 | N7: 16261676 | O7: 10551829 | P7: 508648 | Q7: 574848 | R7: 8105247 | S7: =SUM(K7:R7) -> 59064295
B8: Accounts receivable | K8: - | L8: - | M8: - | N8: 40078 | O8: - | P8: - | Q8: - | R8: 82563 | S8: =SUM(K8:R8) -> 122641
B9: Ad valorem tax receivable, net | K9: 71638 | L9: - | M9: - | N9: - | O9: - | P9: 63867 | Q9: - | R9: 210203 | S9: =SUM(K9:R9) -> 345708
B10: Accrued interest receivable | K10: - | L10: 12537 | M10: 4235 | N10: 14722 | O10: 7419 | P10: - | Q10: - | R10: 1216 | S10: =SUM(K10:R10) -> 40129
B11: Due from other funds | K11: 347334 | L11: 306 | M11: 15028 | N11: - | O11: 672413 | P11: 41301 | Q11: - | R11: 61046 | S11: =SUM(K11:R11) -> 1137428
B12: Due from component unit | K12: 111 | L12: - | M12: - | N12: - | O12: 519 | P12: - | Q12: - | R12: - | S12: =SUM(K12:R12) -> 630
B13: Due from other governmental units | K13: 2711975 | L13: 701802 | M13: 701802 | N13: 701802 | O13: 441978 | P13: 1010935 | Q13: 939834 | R13: 2914777 | S13: =SUM(K13:R13) -> 10124905
B14: Other receivables | K14: 57039 | L14: - | M14: - | N14: - | O14: - | P14: - | Q14: - | R14: 12275 | S14: =SUM(K14:R14) -> 69314
B15: Prepaid expenses | K15: - | L15: 1345 | M15: - | N15: 5516 | O15: 10776 | P15: 7768 | Q15: - | R15: 502 | S15: =SUM(K15:R15) -> 25907
E17: Total Assets: | K17: =SUM(K7:K15) -> 4281996 | L17: =SUM(L7:L15) -> 11080175 | M17: =SUM(M7:M15) -> 12325028 | N17: =SUM(N7:N15) -> 17023794 | O17: =SUM(O7:O15) -> 11684934 | P17: =SUM(P7:P15) -> 1632519 | Q17: =SUM(Q7:Q15) -> 1514682 | R17: =SUM(R7:R15) -> 11387829 | S17: =SUM(S7:S15) -> 70930957
A19: LIABILITIES, DEFERRED INFLOWS OF RESOURCES, AND FUND BALANCES
B20: Liabilities:
C21: Accounts payable | K21: 1681601 | L21: 15580 | M21: 23864 | N21: 777765 | O21: 12388 | P21: 51123 | Q21: 147992 | R21: 146879 | S21: =SUM(K21:R21) -> 2857192
C22: Contracts payable | K22: 61925 | L22: - | M22: 5057 | N22: - | O22: 293556 | P22: - | Q22: 146293 | R22: 124993 | S22: =SUM(K22:R22) -> 631824
C23: Retainage payable | K23: - | L23: - | M23: - | N23: - | O23: - | P23: - | Q23: 76008 | R23: 47303 | S23: =SUM(K23:R23) -> 123311
C24: Accrued liabilities | K24: 24683 | L24: 11625 | M24: 5529 | N24: 51703 | O24: - | P24: 70680 | Q24: - | R24: 47160 | S24: =SUM(K24:R24) -> 211380
C25: Due to other funds | K25: 103827 | L25: 3499 | M25: 852 | N25: 67787 | O25: 49059 | P25: 37299 | Q25: 862638 | R25: 12467 | S25: =SUM(K25:R25) -> 1137428
C26: Other liabilities | K26: 204262 | L26: - | M26: - | N26: - | O26: - | P26: - | Q26: - | R26: - | S26: =SUM(K26:R26) -> 204262
E28: Total liabilities: | K28: =SUM(K21:K26) -> 2076298 | L28: =SUM(L21:L26) -> 30704 | M28: =SUM(M21:M26) -> 35302 | N28: =SUM(N21:N26) -> 897255 | O28: =SUM(O21:O26) -> 355003 | P28: =SUM(P21:P26) -> 159102 | Q28: =SUM(Q21:Q26) -> 1232931 | R28: =SUM(R21:R26) -> 378802 | S28: =SUM(S21:S26) -> 5165397 | T28: =SUM(T18:T25) -> 0 | U28: =SUM(U18:U25) -> 0 | V28: =SUM(V18:V26) -> 0
A30: DEFERRED INFLOWS OF RESROUCES
C31: Deferred revenue | K31: 234110 | L31: - | M31: - | N31: 14942 | P31: 75399 | Q31: 516246 | R31: 245898 | S31: =SUM(K31:R31) -> 1086595
B33: Fund Balances
C34: Nonspendable | K34: - | L34: 1345 | M34: - | N34: 5516 | O34: 10776 | P34: 7768 | Q34: - | R34: 502 | S34: =SUM(K34:R34) -> 25907
C35: Restricted | K35: - | L35: 11048126 | M35: 12289726 | N35: 16106081 | O35: 11319155 | P35: 1390250 | Q35: - | R35: 10762627 | S35: =SUM(K35:R35) -> 62915965
C36: Assigned | K36: 28196 | L36: - | M36: - | N36: - | O36: - | P36: - | Q36: - | R36: - | S36: =SUM(K36:R36) -> 28196
C37: Unassigned | K37: 1943392 | L37: - | M37: - | N37: - | O37: - | P37: - | Q37: -234495 | R37: - | S37: =SUM(K37:R37) -> 1708897
E39: Total fund balances: | K39: =SUM(K34:K37) -> 1971588 | L39: =SUM(L34:L38) -> 11049471 | M39: =SUM(M34:M37) -> 12289726 | N39: =SUM(N34:N37) -> 16111597 | O39: =SUM(O34:O37) -> 11329931 | P39: =SUM(P34:P37) -> 1398018 | Q39: =SUM(Q34:Q37) -> -234495 | R39: =SUM(R34:R37) -> 10763129 | S39: =SUM(S34:S37) -> 64678965 | T39: =SUM(T20:T37) -> 0 | U39: =SUM(U20:U37) -> 0 | V39: =SUM(V20:V37) -> 0
E41: Total liabilities, deferred inflows of resources, and fund balances: | K41: =SUM(K39+K31+K28) -> 4281996 | L41: =SUM(L39+L28) -> 11080175 | M41: =SUM(M39+M28) -> 12325028 | N41: =SUM(N39+N28+N31) -> 17023794 | O41: =SUM(O39+O31+O28) -> 11684934 | P41: =SUM(P39+P28+P31) -> 1632519 | Q41: =SUM(Q39+Q28+Q31) -> 1514682 | R41: =SUM(R39+R28+R31) -> 11387829 | S41: =SUM(S39+S31+S28) -> 70930957

Sheet Vernon
D1: Vernon Combined Balance Sheet
D2: Issued: December 31, 2014
K5: General Fund | L5: Parishwide Maintenance Fund | M5: Sanitary Landfill Fund | N5: Health Unit Maintenance Fund | O5: Courthouse and Jail Maintenance Fund | P5: Parishwide Overlay Fund | Q5: Criminal Court Fund | R5: Library Maintenance Fund | S5: Workforce Investment Act Fund | T5: Other Governmental Funds | U5: 2014 | V5: 2013
A6: Assets:
B7: Cash and cash equivalents | K7: 4211242 | L7: 587625 | M7: 1650080 | N7: 1412702 | O7: 709944 | P7: 1568172 | Q7: 43547 | R7: 1229447 | S7: 13395 | T7: 5946626 | U7: =SUM(K7:T7) -> 17372780 | V7: 23897070
B8: Investments, at fair value | K8: - | L8: - | M8: 698017 | N8: - | O8: 548134 | P8: - | Q8: - | R8: - | S8: - | T8: - | U8: =SUM(K8:T8) -> 1246151 | V8: 1246021
B9: Receivables | K9: 563762 | L9: 783049 | M9: - | N9: 456897 | O9: 1497573 | P9: - | Q9: 29816 | R9: 1116860 | S9: 10948 | T9: 2489661 | U9: =SUM(K9:T9) -> 6948566 | V9: 6132255
B10: Interfund receivables | K10: 779969 | L10: - | M10: - | N10: - | O10: - | P10: - | Q10: - | R10: - | S10: - | T10: 136500 | U10: =SUM(K10:T10) -> 916469 | V10: 50148
B11: Other | K11: - | L11: - | M11: - | N11: - | O11: - | P11: - | Q11: - | R11: - | S11: 39589 | T11: - | U11: =SUM(K11:T11) -> 39589 | V11: 21627
E13: Total Assets: | K13: =SUM(K7:K11) -> 5554973 | L13: =SUM(L7:L11) -> 1370674 | M13: =SUM(M7:M11) -> 2348097 | N13: =SUM(N7:N11) -> 1869599 | O13: =SUM(O7:O11) -> 2755651 | P13: =SUM(P7:P11) -> 1568172 | Q13: =SUM(Q7:Q11) -> 73363 | R13: =SUM(R7:R11) -> 2346307 | ... V13: =SUM(V7:V11) -> 31347121
A15: LIABILITIES AND FUND BALANCES
A16: Liabilities
C17: Accounts, salaries, and other payables | K17: 265826 | L17: 110878 | M17: 210075 | N17: 45698 | O17: 10556 | P17: 58943 | Q17: 5086 | R17: 55952 | S17: 27489 | T17: 147387 | U17: =SUM(K17:T17) -> 937890 | V17: 831526
C18: Interfund payables | K18: 111738 | L18: - | M18: - | N18: - | O18: 18019 | P18: - | Q18: 46829 | R18: - | S18: - | T18: 739883 | U18: =SUM(K18:T18) -> 916469 | V18: 50148
C19: Deferred revenues | K19: - | L19: - | M19: - | N19: - | O19: - | P19: - | Q19: - | R19: - | S19: 36443 | T19: 8436 | U19: =SUM(K19:T19) -> 44879 | V19: 110008
