Workbook

Sheet Acadia
J1: Acadia County 2014 Statement of Activities
J2: Issued: December 31, 2014
M4: NET (EXPENSE) REVENUE AND CHANGE IN NET ASSETS
J5: PROGRAM REVENUES | M5: PRIMARY GOVERNMENT
A6: FUNCTIONS/PROGRAMS | I6: Expenses | J6: Charges for Services | K6: Operating Grants and Contributions | L6: Capital Grants and Contributions | M6: Total Governmental Activities | N6: Component Units
A7: Primary Government:
B8: Government Activities:
C9: General government | I9: -3174139 | J9: 90048 | L9: 9155 | M9: =SUM(I9:L9) -> -3074936
C10: Public safety | I10: -1842385 | J10: 20664 | K10: 133860 | L10: 204990 | M10: =SUM(I10:L10) -> -1482871
C11: Public works | I11: -5893248 | K11: 610860 | L11: 42195 | M11: =SUM(I11:L11) -> -5240193
C12: Economic development and assistance | I12: -574712 | J12: 8414 | L12: 324518 | M12: =SUM(I12:L12) -> -241780
C13: Health and welfare | I13: -7186309 | J13: 5880 | K13: 246456 | L13: 514892 | M13: =SUM(I13:L13) -> -6419081
C14: Culture and recreation | I14: -340726 | J14: 82248 | M14: =SUM(I14:L14) -> -258478
C15: Interest on long-term debt | I15: -394773 | M15: =SUM(I15:L15) -> -394773
E17: Total Government Activities | I17: =SUM(I9:I15) -> -19406292 | J17: =SUM(J9:J15) -> 207254 | K17: =SUM(K9:K15) -> 991176 | L17: =SUM(L9:L15) -> 1095750 | M17: =SUM(M9:M15) -> -17112112
A19: Component units:
B20: Acadia Parish District Criminal Court | I20: -751832 | J20: 174579 | K20: 63659 | L20: 0 | N20: =SUM(I20:M20) -> -513594
G22: General Revenues:
H23: Taxes:
I24: Property | M24: 4784714
I25: Sales | M25: 11822706
I26: Severance | M26: 1006729
I27: Fire insurance premiums | M27: 251271
I28: Occupational and insurance | M28: 486902
I29: Other | M29: 285866
H30: Grants and contributions not restricted to specific programs | M30: 443266
H31: Investment income gains (losses) | M31: 122176
H32: Loss on disposal of capital assets | M32: -44090
H33: Miscellaneous | M33: 437977
H34: Transfers | M34: -515000 | N34: 515000
H36: Total General Revenues | M36: =SUM(M24:M34) -> 19082517 | N36: =SUM(N24:N34) -> 515000
H38: Change in Net Assets | M38: =SUM(M17,M36) -> 1970405 | N38: =N36+N20 -> 1406
E41: Net Assets- Beginning | M41: 52621424 | N41: 38809
E43: Net Assets- Ending | M43: 54591829 | N43: =N41+N38 -> 40215

Sheet Allen
J1: Allen County 2014 Statement of Activities
J2: Issued: December 31, 2014
M4: NET (EXPENSE) REVENUE AND CHANGE IN NET POSITIONS
J5: PROGRAM REVENUES | M5: PRIMARY GOVERNMENT
A6: FUNCTIONS/PROGRAMS | I6: Expenses | J6: Charges for Services | K6: Operating Grants and Contributions | L6: Capital Grants and Contributions | M6: Total Governmental Activities
A7: Primary Government:
B8: Government Activities:
C9: General government | I9: -2194302 | J9: 230115 | K9: 16150 | M9: =SUM(I9:L9) -> -1948037
C10: Public safety | I10: -592121 | K10: 513 | M10: =SUM(I10:L10) -> -591608
C11: Public works | I11: -6135280 | K11: 374203 | M11: =SUM(I11:L11) -> -5761077
C12: Economic development | I12: -302516 | J12: 73693 | K12: 66854 | L12: 128448 | M12: =SUM(I12:L12) -> -33521
C13: Other governments | I13: -719358 | K13: 755647 | M13: =SUM(I13:L13) -> 36289
C14: Interest on long-term debt | I14: -4853 | M14: =SUM(I14:L14) -> -4853
E16: Total Government Activities | I16: =SUM(I9:I14) -> -9948430 | J16: =SUM(J9:J14) -> 303808 | K16: =SUM(K9:K14) -> 1213367 | L16: =SUM(L9:L14) -> 128448 | M16: =SUM(M9:M14) -> -8302807
G19: General Revenues:
H20: Taxes:
I21: Ad valorem | M21: 3151619
I22: Sales and use | M22: 1871684
I23: Severance | M23: 1135569
I24: Other | M24: 354
H25: State revenue sharing | M25: 175817
H26: All other revenues | M26: 1276190
H27: Investment earnings | M27: 14301
H28: Special items:
I29: Gain on disposal of assets | M29: 1252
H31: Total General Revenues | M31: =SUM(M21:M29) -> 7626786
H33: Change in Net Position | M33: =SUM(M16,M31) -> -676021
E35: Net Assets- Beginning of Year | M35: 30884380
E37: Net Assets- End of Year | M37: =SUM(M33,M35) -> 30208359

Sheet Assumption
J1: East Carroll County 2014 Statement of Activities
J2: Issued: December 31, 2014
L4: NET (EXPENSE) REVENUE AND CHANGES IN NET ASSETS
J5: PROGRAM REVENUES | L5: PRIMARY GOVERNMENT
A6: FUNCTIONS/PROGRAMS | I6: Expenses | J6: Charges for Services | K6: Operating Grants and Contributions | L6: Governmental Activities | M6: Component Units | N6: Total
A7: Primary Government:
B8: Government Activities:
C9: General government:
D10: Legislative | I10: 583006 | L10: -583006 | N10: =SUM(L10:M10) -> -583006
D11: Judicial | I11: 970822 | J11: 85720 | L11: -885102 | N11: =SUM(L11:M11) -> -885102
D12: Elections | I12: 51593 | L12: -51593 | N12: =SUM(L12:M12) -> -51593
D13: Finance and administrative | I13: 351185 | L13: -351185 | N13: =SUM(L13:M13) -> -351185
D14: Other general government | I14: 167869 | L14: -167869 | N14: =SUM(L14:M14) -> -167869
C15: Public safety | I15: 3430554 | J15: 705549 | K15: 191140 | L15: -2533865 | N15: =SUM(L15:M15) -> -2533865
C16: Public works | I16: 5847342 | J16: 2204841 | K16: 85615 | L16: -3556996 | N16: =SUM(L16:M16) -> -3556996
C17: Public utilities
C18: Health and welfare | I18: 2470140 | J18: 195714 | K18: 1161181 | L18: -1113245 | N18: =SUM(L18:M18) -> -1113245
C19: Culture and recreation | I19: 1276963 | J19: 10590 | K19: 742 | L19: -1265631 | N19: =SUM(L19:M19) -> -1265631
C20: Economic development and assistance | I20: 221560 | J20: 2405 | L20: -219155 | N20: =SUM(L20:M20) -> -219155
C21: Interest on long-term debt
E23: Total primary government | I23: =SUM(I10:I20) -> 15371034 | J23: =SUM(J10:J20) -> 3204819 | K23: =SUM(K10:K20) -> 1438678 | L23: =SUM(L10:L20) -> -10727647 | N23: =SUM(N10:N20) -> -10727647
B25: Buisness-type Activities:
C26: Sewer and water | I26: 3587268 | J26: 4437297 | M26: 850029 | N26: =SUM(L26:M26) -> 850029
E28: Total component units | I28: =SUM(I26:I26) -> 3587268 | J28: =SUM(J26:J26) -> 4437297 | K28: =SUM(K26:K26) -> 0 | L28: =SUM(L26:L26) -> 0 | M28: =SUM(M26:M26) -> 850029 | N28: =SUM(N26:N26) -> 850029
G31: Local sources
H32: Taxes:
I33: Ad valorem | L33: 4643634 | N33: =SUM(L33:M33) -> 4643634
I34: Sales and use taxes | L34: 4564298 | N34: =SUM(L34:M34) -> 4564298
I35: Other taxes | L35: 1071008 | N35: =SUM(L35:M35) -> 1071008
I36: Other revenue | L36: 1890578 | N36: =SUM(L36:M36) -> 1890578
H37: State sources | N37: =SUM(L37:M37) -> 0
I38: Unrestricted revenue | L38: 882766 | N38: =SUM(L38:M38) -> 882766
H40: Total General Revenues | L40: =SUM(L33:L38) -> 13052284 | M40: =SUM(M33:M38) -> 0 | N40: =SUM(N33:N38) -> 13052284
H42: Excess of revenues and special items | L42: 2278985 | M42: 1121196 | N42: =N40 -> 13052284
E44: Net Assets- Beginning of Year | L44: 64597952 | M44: 18297426 | N44: =SUM(L44:M44) -> 82895378
E46: Net Assets- End of Year | L46: =SUM(L42,L44) -> 66876937 | M46: =M44+M42 -> 19418622 | N46: =N44+N42 -> 95947662

Sheet Avoyelles
J1: Avoyelles County 2014 Statement of Activities
J2: Issued: December 31, 2014
M4: NET (EXPENSE) REVENUE AND CHANGE IN NET ASSETS
J5: PROGRAM REVENUES | M5: Governmental Activities
A6: FUNCTIONS/PROGRAMS | I6: Expenses | J6: Fees, Fines, and Charges for Services | K6: Operating Grants and Contributions | L6: Capital Grants and Contributions | M6: Governmental Activities | N6: Component Units
B7: Government Activities:
C8: General government | I8: -1411958 | J8: 84619 | L8: 62255 | M8: =SUM(I8:L8) -> -1265084
C9: Public safety | I9: -1006255 | J9: 592631 | K9: 88011 | M9: =SUM(I9:L9) -> -325613
C10: Public works | I10: -4651624 | J10: 1527 | K10: 492067 | L10: 478231 | M10: =SUM(I10:L10) -> -3679799
C11: Health and welfare | I11: -831081 | K11: 544620 | M11: =SUM(I11:L11) -> -286461
C12: Culture and recreation | I12: -629145 | J12: 14658 | M12: =SUM(I12:L12) -> -614487
C13: Economic development | I13: -296694 | K13: 25000 | M13: =SUM(I13:L13) -> -271694
E15: Total Government Activities | I15: =SUM(I8:I13) -> -8826757 | J15: =SUM(J8:J13) -> 693435 | K15: =SUM(K8:K13) -> 1149698 | L15: =SUM(L8:L13) -> 540486 | M15: =SUM(M8:M13) -> -6443138
G17: General Revenues:
H18: Taxes:
I19: Property taxes, levied for general purposes | M19: 2107549
I20: Sales and use taxes, levied for general purposes | M20: 4528838
H21: Grants and contributions not restricted to specific programs:
I22: State revenue sharing | M22: 206873
I23: Parish equalization | M23: 299658
I24: State grants | M24: 519014
I25: Casino revenue | M25: 28899
H26: Interest and investment earnings | M26: 27870
H27: Miscellaneous | M27: 67030
H28: Special item- Gain on disposal of assets | M28: 1525
H30: Total General Revenues | M30: =SUM(M19:M28) -> 7787256 | N30: =SUM(N19:N27) -> 0
H32: Change in Net Assets | M32: =SUM(M15,M30) -> 1344118 | N32: =N30 -> 0
E34: Net Assets- Beginning of Year | M34: 15278046
E36: Net Assets- End of Year | M36: =SUM(M32,M34) -> 16622164 | N36: =N34+N32 -> 0

Sheet Beauregard
J1: Beauregard County 2014 Statement of Activities
J2: Issued: December 31, 2014
J4: PROGRAM REVENUES
A5: FUNCTIONS/PROGRAMS | I5: Expenses | J5: Charges for Services | K5: Operating Grants and Contributions | L5: Capital Grants and Contributions | M5: Governmental Activities- Net (Expense) Revenue in Changes in Net Assets
A6: Primary Government:
B7: Government Activities:
C8: General government
D9: Legislative | I9: -244689 | M9: =SUM(I9:L9) -> -244689
D10: Judicial | I10: -1065401 | J10: 844291 | K10: 8400 | M10: =SUM(I10:L10) -> -212710
D11: Elections | I11: -77658 | M11: =SUM(I11:L11) -> -77658
D12: Financial and administrative | I12: -474076 | J12: 206908 | M12: =SUM(I12:L12) -> -267168
D13: Other general government activities | I13: -793563 | J13: 190115 | M13: =SUM(I13:L13) -> -603448
C14: Public safety | I14: -2444391 | K14: 78824 | M14: =SUM(I14:L14) -> -2365567
C15: Public works | I15: -8964712 | J15: 19000 | K15: 523576 | L15: 833328 | M15: =SUM(I15:L15) -> -7588808
C16: Health and welfare | I16: -530539 | K16: 31919 | M16: =SUM(I16:L16) -> -498620
C17: Culture and recreation | I17: -1412319 | K17: 88847 | M17: =SUM(I17:L17) -> -1323472
C18: Sanitation | I18: -1509263 | J18: 61968 | M18: =SUM(I18:L18) -> -1447295
C19: Other activities | I19: -121343 | M19: =SUM(I19:L19) -> -121343
C20: Interest on long-term debt | I20: -75859 | M20: =SUM(I20:L20) -> -75859
E22: Total Government Activities | I22: =SUM(I9:I20) -> -17713813 | J22: =SUM(J9:J20) -> 1322282 | K22: =SUM(K9:K20) -> 731566 | L22: =SUM(L9:L20) -> 833328 | M22: =SUM(M9:M20) -> -14826637
G24: General Revenues:
H25: Taxes:
I26: Ad valorem taxes | M26: 5571237
I27: Severance taxes | M27: 1604653
I28: Sales taxes | M28: 8947813
I29: State revenue sharing, unrestricted | M29: 125274
I30: Other taxes | M30: 179369
H31: Interest and investment earnings | M31: 15640
H32: Special items:
I33: Miscellaneous | M33: 440381
I34: Gain on disposal of assets | M34: -54099
H36: Total General Revenues and special items | M36: =SUM(M26:M34) -> 16830268
H38: Change in Net Assets | M38: =M36+M22 -> 2003631
E40: Net Assets- Beginning of Year | M40: 47805721
E42: Net Assets- End of Year | M42: =SUM(M38,M40) -> 49809352

Sheet Bienville
J1: Allen County 2014 Statement of Activities
J2: Issued: December 31, 2014
M4: NET (EXPENSE) REVENUE AND CHANGE IN NET POSITIONS
J5: PROGRAM REVENUES | M5: PRIMARY GOVERNMENT
A6: FUNCTIONS/PROGRAMS | I6: Expenses | J6: Charges for Services | K6: Operating Grants and Contributions | L6: Capital Grants and Contributions | M6: Total Governmental Activities
A7: Primary Government:
B8: Government Activities:
C9: General government | I9: -2320292 | J9: 30957 | K9: 84139 | M9: =SUM(I9:L9) -> -2205196
C10: Public safety | I10: -672115 | K10: 94203 | M10: =SUM(I10:L10) -> -577912
C11: Public works | I11: -6139111 | K11: 60383 | L11: 327795 | M11: =SUM(I11:L11) -> -5750933
C12: Health and welfare | I12: -541954 | K12: 442763 | M12: =SUM(I12:L12) -> -99191
C13: Conservation of natural resources | I13: -30848 | M13: =SUM(I13:L13) -> -30848
C14: Economic development and assistance | I14: -64978 | K14: 8567 | M14: =SUM(I14:L14) -> -56411
C15: Debt service | I15: -396683 | M15: =SUM(I15:L15) -> -396683
E17: Total Government Activities | I17: =SUM(I9:I15) -> -10165981 | J17: =SUM(J9:J15) -> 30957 | K17: =SUM(K9:K15) -> 690055 | L17: =SUM(L9:L15) -> 327795 | M17: =SUM(M9:M15) -> -9117174
G20: General Revenues:
H21: Taxes:
I22: Property taxes levied for general purposes | M22: 1536450
I23: Property taxes levied for public works | M23: 1813814
I24: Property taxes levied for debt service | M24: 1094758
I25: Sales & use taxes levied for public works | M25: 2345499
H26: Other taxes, penalties, and interest | M26: 32162
H27: Grants and contributions not restricted to specific programs | M27: 1512686
H28: Licenses and permits | M28: 82708
H29: Unrestricted investment earnings | M29: 127199
H30: Special item - gain (loss) on disposal of assets | M30: 23210
H32: Total General Revenues | M32: =SUM(M22:M30) -> 8568486
H34: Change in Net Position | M34: =SUM(M17,M32) -> -548688
E36: Net Assets- Beginning of Year | M36: 32575214
E38: Net Assets- End of Year | M38: =SUM(M34,M36) -> 32026526

Sheet Bossier
J1: Bossier 2014 Statement of Activities
J2: Issued: December 31, 2014
M3: Primary government
M4: Governmental activities
J5: PROGRAM REVENUES | M5: Net (Expenses) Revenue and Changes in Net Assets
A6: FUNCTIONS/PROGRAMS | I6: Expenses | J6: Charges for Services | K6: Operating Grants and Contributions | L6: Capital Grants and Contributions | M6: Governmental activities | N6: Buisness-type Activities | O6: Total
A7: Primary Government: Governmental Activities
C8: General government
D9: Legislative | I9: -545378 | K9: - | M9: =SUM(I9+J9) -> -545378 | O9: =SUM(M9:N9) -> -545378
D10: Judicial | I10: -3210443 | J10: 1124204 | K10: - | M10: =SUM(I10:L10) -> -2086239 | O10: =SUM(M10:N10) -> -2086239
D11: Elections | I11: -256229 | J11: - | K11: - | L11: - | M11: =SUM(I11:L11) -> -256229 | O11: =SUM(M11:N11) -> -256229
D12: Finance and administrative | I12: -1698947 | J12: 20700 | L12: - | M12: =SUM(I12:L12) -> -1678247 | O12: =SUM(M12:N12) -> -1678247
D13: Other | I13: -3276854 | J13: 236673 | K13: 609 | L13: - | M13: =SUM(I13:L13) -> -3039572 | O13: =SUM(M13:N13) -> -3039572
C14: Public safety | I14: -5879127 | J14: 343141 | K14: 44090 | M14: =SUM(I14:L14) -> -5491896 | O14: =SUM(M14:N14) -> -5491896
C15: Public works | I15: -16737152 | J15: 367165 | K15: 168188 | L15: 19662577 | M15: =SUM(I15:L15) -> 3460778 | O15: =SUM(M15:N15) -> 3460778
C16: Public utilities | I16: -61824 | M16: =SUM(I16:L16) -> -61824 | O16: =SUM(M16:N16) -> -61824
C17: Health and welfare | I17: -4799126 | J17: - | K17: 3894996 | M17: =SUM(I17:L17) -> -904130 | O17: =SUM(M17:N17) -> -904130
C18: Culture and recreation | I18: -5061207 | J18: 73887 | K18: 22892 | L18: - | M18: =SUM(I18:L18) -> -4964428 | O18: =SUM(M18:N18) -> -4964428
C19: Economic development | I19: -1887534 | J19: - | K19: - | L19: - | M19: =SUM(I19:L19) -> -1887534 | O19: =SUM(M19:N19) -> -1887534
C20: Interest on long-term debt | I20: -2064894 | J20: - | K20: - | L20: - | M20: =SUM(I20:L20) -> -2064894 | O20: =SUM(M20:N20) -> -2064894
E22: Total Government Activities | I22: =SUM(I9:I20) -> -45478715 | J22: =SUM(J8:J19) -> 2165770 | K22: =SUM(K8:K19) -> 4130775 | L22: =SUM(L8:L19) -> 19662577 | M22: =SUM(M9:M20) -> -19519593 | N22: =SUM(N9:N20) -> 0 | O22: =SUM(O9:O20) -> -19519593
B24: Business-type Activities:
C25: Sewer and water | I25: -1116728 | J25: 1769201 | K25: - | M25: - | N25: 652473 | O25: =SUM(M25:N25) -> 652473
O26: =SUM(I26:N26) -> 0
E27: Total business-type Activities | I27: =SUM(I25) -> -1116728 | J27: =SUM(J25) -> 1769201 | K27: =SUM(K25) -> 0 | L27: =SUM(L25) -> 0 | M27: =SUM(M25) -> 0 | N27: =SUM(N25) -> 652473 | O27: =SUM(O25) -> 652473
E29: Total | I29: =SUM(I22+I27) -> -46595443 | J29: =SUM(J22+J27) -> 3934971 | K29: =SUM(K22+K27) -> 4130775 | L29: =SUM(L22+L27) -> 19662577 | M29: =SUM(M22+M27) -> -19519593 | N29: =SUM(N22+N27) -> 652473 | O29: =SUM(O22+O27) -> -18867120
G32: General Revenues:
H33: Taxes:
I34: Ad valorem taxes | M34: 14361439 | O34: =SUM(M34:N34) -> 14361439
I35: Sales taxes | M35: 17506962 | O35: =SUM(M35:N35) -> 17506962
I36: Gaming tax revenues | M36: 4265533 | O36: =SUM(M36:N36) -> 4265533
I37: Franchise taxes | M37: 514614 | O37: =SUM(M37:N37) -> 514614
I38: Other taxes | M38: 1099386 | O38: =SUM(M38:N38) -> 1099386
I39: Investment earnings | M39: 65382 | N39: 2804 | O39: =SUM(M39:N39) -> 68186
I40: State revenue sharing | M40: 547857 | O40: =SUM(M40:N40) -> 547857
I41: Miscellaneous | M41: 2822201 | N41: 496 | O41: =SUM(M41:N41) -> 2822697
I42: Gain of sale of property | M42: 184504 | O42: =SUM(M42:N42) -> 184504
I43: Transfers | M43: -8676072 | N43: 8676072 | O43: =SUM(M43:N43) -> 0
H44: Total General Revenues | M44: =SUM(M34:M43) -> 32691806 | N44: =SUM(N34:N43) -> 8679372 | O44: =SUM(O34:O43) -> 41371178
H46: Change in Net Assets | M46: =SUM(M29+M44) -> 13172213 | N46: =SUM(N29+N44) -> 9331845 | O46: =SUM(O29+O44) -> 22504058
E49: Net position- Beginning | M49: 267079437 | N49: 2735299 | O49: 269814736
E51: Net position- Ending | M51: =SUM(M46,M49) -> 280251650 | N51: =SUM(N46,N49) -> 12067144 | O51: =SUM(O46,O49) -> 292318794

Sheet Caddo
J1: Caddo County 2014 Statement of Activities
J2: Issued: December 31, 2014
J5: PROGRAM REVENUES | M5: NET (EXPENSE) REVENUE AND CHANGES IN NET ASSETS
A6: FUNCTIONS/PROGRAMS | I6: Expenses | J6: Charges for Services | K6: Operating Grants and Contributions | L6: Capital Grants and Contributions | M6: Primary Government | N6: Component Units
A7: Primary Government:
B8: Government Activities:
C9: General government | I9: -9616443 | J9: 3172380 | K9: 281149 | L9: 200560 | M9: =SUM(I9:L9) -> -5962354
C10: Criminal justice | I10: -22965185 | J10: 30283 | K10: 1330598 | M10: =SUM(I10:L10) -> -21604304
C11: Health and welfare | I11: -15373363 | J11: 168282 | K11: 11286901 | L11: 319671 | M11: =SUM(I11:L11) -> -3598509
C12: Highways, streets, and drainage | I12: -23738530 | J12: 481901 | K12: 2323462 | M12: =SUM(I12:L12) -> -20933167
C13: Building facilities | I13: -6178313 | K13: 114638 | M13: =SUM(I13:K13) -> -6063675
C14: Sanitation | I14: -2620248 | M14: =SUM(I14:K14) -> -2620248
C15: Culture and recreation | I15: -15957204 | J15: 113615 | K15: 425193 | M15: =SUM(I15:K15) -> -15418396
C16: Economic development | I16: -4221537 | K16: 73851 | M16: =SUM(I16:K16) -> -4147686
C17: Interest and fees on long-term debt | I17: -2126069 | M17: =SUM(I17:K17) -> -2126069
E19: Total Government Activities | I19: =SUM(I9:I17) -> -102796892 | J19: =SUM(J9:J17) -> 3966461 | K19: =SUM(K9:K17) -> 15835792 | L19: =SUM(L9:L17) -> 520231 | M19: =SUM(M9:M17) -> -82474408
A21: Component units:
B22: Judicial services | I22: -8479315 | J22: 1131910 | K22: 6608097 | N22: =SUM(I22:M22) -> -739308
B23: Economic development | I23: -339932 | N23: =SUM(I23:M23) -> -339932
B24: Public safety | I24: -39691975 | J24: 14223855 | N24: =SUM(I24:M24) -> -25468120
B25: Fire protection services | I25: -11455942 | J25: 2883925 | K25: 3500 | L25: 134347 | N25: =SUM(I25:M25) -> -8434170
B26: Sewerage services | I26: -1215183 | J26: 1065134 | N26: =SUM(I26:M26) -> -150049
B27: Water services | I27: -1917255 | J27: 2027286 | N27: =SUM(I27:M27) -> 110031
B28: Hospital services | I28: -18299617 | J28: 15503099 | K28: 1531826 | L28: 240946 | N28: =SUM(I28:M28) -> -1023746
E30: Total component units | I30: =SUM(I22:I28) -> -81399219 | J30: =SUM(J22:J28) -> 36835209 | K30: =SUM(K22:K28) -> 8143423 | L30: =SUM(L22:L28) -> 375293 | M30: =SUM(M22:M28) -> 0 | N30: =SUM(N22:N28) -> -36045294
G32: General Revenues:
H33: Taxes:
I34: Property taxes levied for general purposes | M34: 57040935 | N34: 8149198
I35: Property taxes levied for debt service | M35: 2519914
I36: Sales taxes | M36: 13851983 | N36: 16191048
I37: Franchise taxes | M37: 220613
I38: Telephone tariff | N38: 3595485
H39: State revenue sharing and supplemental pay | N39: 503031
H40: Gaming | M40: 1791430
H41: Grants and contributions not restricted to specific programs | M41: 1273355
H42: Oil and gas leases | M42: 853285
H43: Investment earnings | M43: 930818 | N43: 118393
H44: Inmate work release revenue | N44: 1423038
H45: Fire insurance rebate | N45: 212799
H46: Miscellaneous | M46: 936432 | N46: 2437636
H48: Total General Revenues | M48: =SUM(M33:M46) -> 79418765 | N48: =SUM(N34:N46) -> 32630628
H50: Change in Net Assets | M50: =M48+M19 -> -3055643 | N50: =N48+N30 -> -3414666
H52: Net position - beginning, as previously stated | M52: 353774749 | N52: 56071996
H54: Prior period adjustment | N54: -1874824
E56: Net Assets- Beginning, as restated | M56: 353774749 | N56: 54197172
E58: Net Assets- End of Year | M58: =SUM(M50,M56) -> 350719106 | N58: =N56+N50 -> 50782506

Sheet Calcasieu
J1: Calcasieu Parish 2014 Statement of Activities
J2: Issued: December 31, 2014
M4: NET (EXPENSE) REVENUE AND CHANGE IN NET ASSETS
J5: PROGRAM REVENUES | M5: PRIMARY GOVERNMENT
A6: FUNCTIONS/PROGRAMS | I6: Expenses | J6: Charges for Services | K6: Operating Grants and Contributions | L6: Capital Grants and Contributions | M6: Governmental Activities | N6: Business-type Activities | O6: Total | P6: Component Units
A7: Primary Government:
B8: Government Activities:
C9: General government | I9: -23801813 | J9: 11462762 | K9: 361194 | L9: 260240 | M9: =SUM(I9:L9) -> -11717617 | O9: =SUM(M9:N9) -> -11717617
C10: Public safety | I10: -15334942 | J10: 974246 | K10: 1990481 | L10: 23348 | M10: =SUM(I10:L10) -> -12346867 | O10: =SUM(M10:N10) -> -12346867
C11: Public works | I11: -39564313 | J11: 755722 | K11: 4226657 | L11: 2138548 | M11: =SUM(I11:L11) -> -32443386 | O11: =SUM(M11:N11) -> -32443386
C12: Sanitation | I12: -6993188 | J12: 183 | K12: 1205 | M12: =SUM(I12:L12) -> -6991800 | O12: =SUM(M12:N12) -> -6991800
C13: Health and welfare | I13: -14834996 | J13: 140126 | K13: 7820536 | M13: =SUM(I13:L13) -> -6874334 | O13: =SUM(M13:N13) -> -6874334
C14: Culture and recreation | I14: -15996312 | J14: 1478785 | K14: 26675 | L14: 1548664 | M14: =SUM(I14:L14) -> -12942188 | O14: =SUM(M14:N14) -> -12942188
C15: Economic development | I15: -3883483 | J15: 1425178 | K15: 89559 | M15: =SUM(I15:L15) -> -2368746 | O15: =SUM(M15:N15) -> -2368746
E17: Total Government Activities | I17: =SUM(I9:I15) -> -120409047 | J17: =SUM(J9:J15) -> 16237002 | K17: =SUM(K9:K15) -> 14516307 | L17: =SUM(L9:L15) -> 3970800 | M17: =SUM(M9:M15) -> -85684938 | O17: =SUM(O9:O15) -> -85684938 | P17: =SUM(P9:P15) -> 0
B19: Business-type Activities:
C20: Water | I20: 703323 | J20: 711779 | N20: 8456 | O20: =N20 -> 8456
C21: Sewer | I21: 873402 | J21: 292967 | N21: -580435 | O21: =N21 -> -580435
E23: Total business-type Activities | I23: =SUM(I20:I21) -> 1576725 | J23: =SUM(J20:J21) -> 1004746 | K23: =SUM(K20:K21) -> 0 | L23: =SUM(L20:L21) -> 0 | M23: =SUM(M20:M21) -> 0 | N23: =SUM(N20:N21) -> -571979 | O23: =SUM(O20:O21) -> -571979
E25: Total primary government | I25: =I23+I17 -> -118832322 | J25: =J23+J17 -> 17241748 | K25: =K23+K17 -> 14516307 | L25: =L23+L17 -> 3970800 | M25: =M23+M17 -> -85684938 | N25: =N23+N17 -> -571979 | O25: =O23+O17 -> -86256917 | P25: =P23+P17 -> 0
A27: Component units:
B28: West Calcasieu Cameron Hospital | I28: -76872289 | J28: 65019753 | K28: 4077 | P28: =SUM(I28:L28) -> -11848459
B29: Sulphur Parks and Recreation | I29: -5737059 | J29: 2228194 | P29: =SUM(I29:L29) -> -3508865
B30: Gravity Drainage District No. 5 of Ward 4 | I30: -2473270 | J30: 98420 | P30: =SUM(I30:L30) -> -2374850
B31: Gravity Drainage District No. 4 of Ward 3 | I31: -2745645 | L31: 17490 | P31: =SUM(I31:L31) -> -2728155
B32: Airport Authority District No. 1 | I32: -4158495 | J32: 2095038 | K32: 204566 | L32: 3696733 | P32: =SUM(I32:L32) -> 1837842
B33: Other component units | I33: -45669669 | J33: 17745600 | K33: 4576744 | L33: 1693292 | P33: =SUM(I33:L33) -> -21654033
E35: Total component units | I35: =SUM(I28:I33) -> -137656427 | J35: =SUM(J28:J33) -> 87187005 | K35: =SUM(K28:K33) -> 4785387 | L35: =SUM(L28:L33) -> 5407515 | M35: =SUM(M28:M33) -> 0 | N35: =SUM(N28:N33) -> 0 | O35: =SUM(O28:O33) -> 0 | P35: =SUM(P28:P33) -> -40276520
G37: General Revenues:
H38: Taxes:
I39: Property | M39: 44934024 | N39: 366670 | O39: 45300694 | P39: 48130460
I40: Sales | M40: 42716206 | O40: 42716206
I41: Franchise | M41: 963051 | O41: =SUM(M41:N41) -> 963051
H42: Gaming revnues | M42: 11894569 | O42: 11894569
H43: Grants and contributions not restricted to specific programs | M43: 3123894 | O43: 3123894 | P43: 849588
H44: Investment earnings | M44: 2715152 | N44: 21576 | O44: 2736728 | P44: 489961
H45: Gain on sale of capital assets | M45: 250745 | O45: 250745 | P45: 1323256
H46: Gain on forgiveness of debt | P46: 348623
H47: Miscellaneous | M47: 42067 | N47: 600 | O47: 42667 | P47: 1736222
H48: Special items - transfer of operations | M48: 29057 | O48: 29057 | P48: -29057
G49: Transfers | M49: -440133 | N49: 440133 | O49: =SUM(M49:N49) -> 0
H51: Total General Revenues | M51: =SUM(M39:M49) -> 106228632 | N51: =SUM(N39:N49) -> 828979 | O51: =SUM(O39:O49) -> 107057611 | P51: =SUM(P39:P49) -> 52849053
H53: Change in Net Assets | M53: =SUM(M51+M25) -> 20543694 | N53: =SUM(N51+N25) -> 257000 | O53: =SUM(O51+O25) -> 20800694 | P53: =SUM(P51+P35) -> 12572533
E55: Net Assets- Beginning of Year | M55: 754326114 | N55: 10512983 | O55: 764839097 | P55: 319861846
E57: Net Assets- End of Year | M57: =SUM(M53,M55) -> 774869808 | N57: =N55+N53 -> 10769983 | O57: =O55+O53 -> 785639791 | P57: =P55+P53 -> 332434379

Sheet Caldwell
J1: Caldwell County 2014 Statement of Activities
J2: Issued: December 31, 2014
J5: PROGRAM REVENUES
A6: FUNCTIONS | I6: Expenses | J6: Charges for Services | K6: Operating Grants and Contributions | L6: Capital Grants and Contributions | M6: NET (EXPENSE) REVENUE AND CHANGES IN NET ASSETS
C7: General government | I7: -974157 | J7: 161203 | K7: 168079 | M7: =SUM(I7:L7) -> -644875
C8: Public safety | I8: -534651 | J8: 106913 | K8: 171957 | L8: 67128 | M8: =SUM(I8:L8) -> -188653
C9: Public works | I9: -2017407 | J9: 103039 | K9: 204609 | L9: 203397 | M9: =SUM(I9:L9) -> -1506362
C10: Health and welfare | I10: -147216 | K10: 70834 | M10: =SUM(I10:L10) -> -76382
C11: Culture and recreation | I11: -218065 | J11: 14422 | K11: 15367 | L11: 3423044 | M11: =SUM(I11:L11) -> 3234768
C12: Economic development and assistance | I12: -232966 | M12: =SUM(I12:L12) -> -232966
C13: Transportation | I13: -5820 | J13: 4114 | M13: =SUM(I13:L13) -> -1706
E15: Total Government Activities | I15: =SUM(I7:I13) -> -4130282 | J15: =SUM(J7:J13) -> 389691 | K15: =SUM(K7:K13) -> 630846 | L15: =SUM(L7:L13) -> 3693569 | M15: =SUM(M7:M13) -> 583824
A17: General Revenues:
A18: Property taxes levied for:
B19: General purposes | M19: 772517
B20: Public works | M20: 510944
B21: Health and welfare | M21: 127013
B22: Culture and recreation
B23: Economic development and assistance | M23: 326618
A24: Sales and use taxes levied for:
B25: General purposes | M25: 266445
B26: Public works | M26: 1686092
A27: Other taxes, penalties and interest | M27: 9870
A28: Unrestricted investment earnings | M28: 28075
A29: Other revenues | M29: 5885
E31: Total general revenues | M31: =SUM(M19:M29) -> 3733459
E33: Change in net position | M33: =SUM(M15,M31) -> 4317283
E35: Net position at beginning of year, related | M35: 19052485
E37: Net position at the end of the year | M37: =SUM(M33,M35) -> 23369768

Sheet Cameron
I1: Cameron County 2014 Statement of Activities
J2: Issued: December 31, 2014
J5: Program Revenues | L5: NET REVENUES (EXPENSES) AND CHANGES IN NET POSITION
A6: FUNCTIONS/PROGRAMS | I6: Expenses | J6: Operating Grants and Contributions | K6: Capital Grants and Contributions | L6: Governmental Activities
A7: Primary Government:
B8: Government Activities:
B9: General government:
C10: Legislative | I10: -232074 | L10: =SUM(I10:K10) -> -232074
C11: Judicial | I11: -1318873 | L11: =SUM(I11:K11) -> -1318873
C12: Elections | I12: -6843 | L12: =SUM(I12:K12) -> -6843
C13: Finance and administrative | I13: -1601427 | J13: 2930 | L13: =SUM(I13:K13) -> -1598497
C14: Other general government | I14: -2668369 | L14: =SUM(I14:K14) -> -2668369
C15: Interest on long-term debt | I15: -105744 | L15: =SUM(I15:K15) -> -105744
C16: Public safety | I16: -2803731 | J16: 2645 | K16: 2550478 | L16: =SUM(I16:K16) -> -250608
C17: Public works | I17: -6533293 | J17: 4943 | K17: 2455307 | L17: =SUM(I17:K17) -> -4073043
C18: Culture and recreation | I18: -1924589 | L18: =SUM(I18:K18) -> -1924589
C19: Health and welfare | I19: -512083 | L19: =SUM(I19:K19) -> -512083
C20: Economic development | I20: -1848271 | J20: 12474217 | L20: =SUM(I20:K20) -> 10625946
E22: Total Government Activities | I22: =SUM(I10:I20) -> -19555297 | J22: =SUM(J10:J20) -> 12484735 | K22: =SUM(K10:K20) -> 5005785 | L22: =SUM(L10:L20) -> -2064777
G24: General Revenues:
H25: Taxes:
I26: Property taxes, levied for general purposes | L26: 7216305
I27: Other taxes for general purposes | L27: 994588
H28: Licenses and permits | L28: 383734
H29: Fines, forfeitures, and court costs | L29: 144837
H30: Intergovernmental:
I31: State | L31: 5217490
I32: Local | L32: 40173
H33: Gain (loss) on disposal of capital assets | L33: 521126
H34: Interest earnings | L34: 32491
H35: Other | L35: 134116
H37: Total General Revenues | L37: =SUM(L26:L35) -> 14684860
H39: Change in Net Position | L39: =SUM(L22,L37) -> 12620083
E41: Net Assets- Beginning of Year | L41: 146194005
E43: Net Assets- End of Year | L43: =SUM(L39+L41) -> 158814088

Sheet Catahoula
J1: Catahoula County 2014 Statement of Activities
J2: Issued: December 31, 2014
J5: PROGRAM REVENUES
A6: FUNCTIONS/PROGRAMS | I6: Expenses | J6: Charges for Services | K6: Operating Grants and Contributions | L6: Capital Grants and Contributions | M6: NET (EXPENSE) REVENUE AND CHANGES IN NET ASSETS
B7: Government Activities:
C8: General government | I8: -722386 | J8: 113558 | K8: 25405 | M8: =SUM(I8:L8) -> -583423
C9: Public safety | I9: -405469 | K9: 349662 | M9: =SUM(I9:L9) -> -55807
C10: Public works | I10: -1875439 | J10: 937 | K10: 181846 | L10: 64800 | M10: =SUM(I10:L10) -> -1627856
C11: Health and welfare | I11: -240465 | K11: 291827 | M11: =SUM(I11:L11) -> 51362
C12: Culture and recreation | I12: -352181 | J12: 5648 | K12: 44756 | M12: =SUM(I12:L12) -> -301777
C13: Economic development and assistance | I13: -2792 | M13: =SUM(I13:L13) -> -2792
C14: Interest expense | I14: -4485 | M14: =SUM(I14:L14) -> -4485
E16: Total Government Activities | I16: =SUM(I8:I14) -> -3603217 | J16: =SUM(J8:J14) -> 120143 | K16: =SUM(K8:K14) -> 893496 | L16: =SUM(L8:L14) -> 64800 | M16: =SUM(M8:M14) -> -2524778
G18: General Revenues:
H19: Property taxes | M19: 864032
H20: Sales and use taxes | M20: 1753095
H21: Other taxes, penalties and interest | M21: 5214
H22: Grants and contributions not restricted to specific programs | M22: 337458
H23: Unrestricted investment earnings | M23: 6434
H24: Gain (loss) on sale of capital assets | M24: -18786
H25: Other | M25: 21987
H27: Total General Revenues | M27: =SUM(M19:M25) -> 2969434
H29: Change in Net Position | M29: =SUM(M16,M27) -> 444656
E31: Net Assets- Beginning of Year | M31: 8526187
E33: Net Assets- End of Year | M33: =SUM(M29,M31) -> 8970843

Sheet Claiborne
J1: Claiborne County 2014 Statement of Activities
J2: Issued: December 31, 2014
J4: PROGRAM REVENUES
A5: FUNCTIONS- GOVERNMENTAL ACTIVITIES | I5: Expenses | J5: Charges for Services | K5: Operating Grants and Contributions | L5: Capital Grants and Contributions | M5: NET (EXPENSE) REVENUE AND CHANGES IN NET ASSETS
B6: Government Activities:
C7: General government | I7: -1522797 | J7: 482299 | M7: =SUM(I7:L7) -> -1040498
C8: Public safety | I8: -317573 | K8: 124395 | L8: 53242 | M8: =SUM(I8:L8) -> -139936
C9: Public works | I9: -3489014 | K9: 598941 | M9: =SUM(I9:L9) -> -2890073
C10: Health and welfare | I10: -643674 | J10: 7005 | K10: 460878 | M10: =SUM(I10:L10) -> -175791
C11: Culture and recreation | I11: -676727 | J11: 3110 | K11: 27474 | M11: =SUM(I11:L11) -> -646143
C12: Economic development and assistance | I12: -60013 | M12: =SUM(I12:L12) -> -60013
C13: Conservation | I13: -5200 | M13: =SUM(I13:L13) -> -5200
C14: Interest expense | I14: -41425 | M14: =SUM(I14:L14) -> -41425
E16: Total Government Activities | I16: =SUM(I7:I14) -> -6756423 | J16: =SUM(J7:J14) -> 492414 | K16: =SUM(K7:K14) -> 1211688 | L16: =SUM(L7:L14) -> 53242 | M16: =SUM(M7:M14) -> -4999079
G18: General Revenues:
H19: Property taxes levied for:
I20: General purposes | M20: 919359
I21: Public works | M21: 1374532
I22: Culture and recreation | M22: 791597
H23: Sales and use taxes levied for public works | M23: 870929
H24: Other taxes, penalties and interest | M24: 8821
H25: Grants and contributions not restricted to specific programs | M25: 1613286
H26: Unrestricted investment earnings | M26: 129994
H27: Net increase (decreaase) in the fair value of investments | M27: 23125
H28: Gain on sale of capital assets | M28: 42509
H29: Contributions from private sources | M29: 5500
H30: Other | M30: 103549
H32: Total General Revenues and transfers | M32: =SUM(M20:M30) -> 5883201
H34: Change in Net Position | M34: =SUM(M16,M32) -> 884122
E36: Net Assets- Beginning of Year | M36: 15382153
E38: Net Assets- End of Year | M38: =SUM(M34,M36) -> 16266275

Sheet Concordia
J1: Concordia County 2014 Statement of Activities
J2: Issued: December 31, 2014
J4: PROGRAM REVENUES
A5: FUNCTIONS/PROGRAMS | I5: Expenses | J5: Charges for Services | K5: Operating Grants and Contributions | L5: Capital Grants and Contributions | M5: NET REVENUE (EXPENSE) AND CHANGES IN NET ASSETS
A6: Primary Government:
B7: Government Activities:
B8: General government:
C9: Legislative | I9: -236369 | M9: =SUM(I9:L9) -> -236369
C10: Judicial | I10: -635894 | M10: =SUM(I10:L10) -> -635894
C11: Elections | I11: -45930 | M11: =SUM(I11:L11) -> -45930
C12: Finance | I12: -337662 | M12: =SUM(I12:L12) -> -337662
C13: Other general | I13: -774236 | L13: 20505 | M13: =SUM(I13:L13) -> -753731
B14: Public safety | I14: -197180 | J14: 155840 | K14: 40326 | M14: =SUM(I14:L14) -> -1014
B15: Public works | I15: -3094988 | L15: 190512 | M15: =SUM(I15:L15) -> -2904476
B16: Health and welfare | I16: -275734 | K16: 123153 | L16: 35363 | M16: =SUM(I16:L16) -> -117218
B17: Economic development | I17: -94869 | M17: =SUM(I17:L17) -> -94869
B18: Interest | I18: -384541 | M18: =SUM(I18:L18) -> -384541
E20: Total Government Activities | I20: =SUM(I9:I18) -> -6077403 | J20: =SUM(J9:J18) -> 155840 | K20: =SUM(K9:K18) -> 163479 | L20: =SUM(L9:L18) -> 246380 | M20: =SUM(M9:M18) -> -5511704
G22: General Revenues:
H23: Taxes:
I24: Ad valorem taxes | M24: 1785913
I25: Sales taxes | M25: 2856287
I26: Other taxes | M26: 35256
H27: Intergovernmental revenues
I28: State revenue sharing | M28: 107518
I29: Severance taxes | M29: 1011692
I30: Parish transportation | M30: 320993
I31: Fire insurance premium tax | M31: 83499
I32: Parish royalty | M32: 42329
H33: Licenses and permits | M33: 266261
H34: Interest | M34: 25953
H35: Other general revenues | M35: 241635
H37: Total general revenues | M37: =SUM(M24:M35) -> 6777336
H39: Change in Net Position | M39: =SUM(M20+M37) -> 1265632
E41: Net Assets- Beginning of Year | M41: 10918102
E43: Net Assets- End of Year | M43: =SUM(M41+M39) -> 12183734

Sheet DeSoto
J1: Desoto County 2014 Statement of Activities
J2: Issued: December 31, 2014
J5: PROGRAM REVENUES | M5: NET (EXPENSES) REVENUES AND CHANGES IN NET POSITION
A6: Program Activities | I6: Expenses | J6: Fees, Fines and Charges for Services | K6: Operating Grants and Contributions | L6: Capital Grants and Contributions | M6: Governmental Activities | N6: Business-type Activities | O6: Total
A7: Primary Government:
B8: Government Activities:
B9: General government:
C10: Legislative | I10: -400475 | M10: =SUM(I10:L10) -> -400475 | O10: =SUM(M10:N10) -> -400475
C11: Judicial | I11: -2693579 | J11: 1016052 | M11: =SUM(I11:L11) -> -1677527 | O11: =SUM(M11:N11) -> -1677527
C12: Elections | I12: -101110 | M12: =SUM(I12:L12) -> -101110 | O12: =SUM(M12:N12) -> -101110
C13: Finance and administration | I13: -2029058 | J13: 312381 | K13: 11382 | M13: =SUM(I13:L13) -> -1705295 | O13: =SUM(M13:N13) -> -1705295
C14: Other | I14: -854448 | M14: =SUM(I14:L14) -> -854448 | O14: =SUM(M14:N14) -> -854448
C15: Public safety | I15: -1096246 | K15: 111066 | M15: =SUM(I15:L15) -> -985180 | O15: =SUM(M15:N15) -> -985180
C16: Public works | I16: -10446041 | J16: 197301 | L16: 398964 | M16: =SUM(I16:L16) -> -9849776 | O16: =SUM(M16:N16) -> -9849776
C17: Sanitation | I17: -4058906 | J17: 946774 | M17: =SUM(I17:L17) -> -3112132 | O17: =SUM(M17:N17) -> -3112132
C18: Culture and recreation | I18: -279817 | M18: =SUM(I18:L18) -> -279817 | O18: =SUM(M18:N18) -> -279817
C19: Health and welfare | I19: -2206951 | K19: 1605452 | M19: =SUM(I19:L19) -> -601499 | O19: =SUM(M19:N19) -> -601499
C20: Economic development | I20: -3299353 | K20: 2689861 | M20: =SUM(I20:L20) -> -609492 | O20: =SUM(M20:N20) -> -609492
C21: Transportation | I21: -814370 | J21: 242760 | K21: 160493 | M21: =SUM(I21:L21) -> -411117 | O21: =SUM(M21:N21) -> -411117
C22: Animal control | I22: -345903 | J22: 22434 | K22: 700 | M22: =SUM(I22:L22) -> -322769 | O22: =SUM(M22:N22) -> -322769
C23: Interest on long-term debt | I23: -255 | M23: =SUM(I23:L23) -> -255 | O23: =SUM(M23:N23) -> -255
E25: Total Government Activities | I25: =SUM(I10:I23) -> -28626512 | J25: =SUM(J10:J23) -> 2737702 | K25: =SUM(K10:K23) -> 4578954 | L25: =SUM(L10:L23) -> 398964 | M25: =SUM(M10:M23) -> -20910892 | O25: =SUM(O10:O23) -> -20910892
B27: Business-type Activities:
C28: Eastside sewer | I28: -33209 | J28: 13837 | N28: =SUM(I28:L28) -> -19372 | O28: =N28 -> -19372
E30: Total Government | I30: =I28+I25 -> -28659721 | J30: =J28+J25 -> 2751539 | K30: =K28+K25 -> 4578954 | L30: =L28+L25 -> 398964 | M30: =M28+M25 -> -20910892 | N30: =N28+N25 -> -19372 | O30: =O28+O25 -> -20930264
G32: General Revenues:
G33: Taxes-
H34: Ad valorem | M34: 12327537 | O34: =SUM(M34:N34) -> 12327537
H35: Sales & use | M35: 7344797 | O35: =SUM(M35:N35) -> 7344797
H36: Severance | M36: 1233958 | O36: =SUM(M36:N36) -> 1233958
H37: Tourism | M37: 104653 | O37: =SUM(M37:N37) -> 104653
H38: Video poker | M38: 137400 | O38: =SUM(M38:N38) -> 137400
H39: Investment earnings | M39: 483798 | O39: =SUM(M39:N39) -> 483798
H40: State revenue sharing | M40: 51600 | O40: =SUM(M40:N40) -> 51600
H41: Rentals, leases and royalties | M41: 624592 | O41: =SUM(M41:N41) -> 624592
H42: Other miscellaneous | M42: 421020 | O42: =SUM(M42:N42) -> 421020
H43: Transfers | M43: -19350 | N43: 19350 | O43: =SUM(M43:N43) -> 0
H45: Total General Revenues & Transfers | M45: =SUM(M34:M43) -> 22710005 | N45: =SUM(N34:N43) -> 19350 | O45: =SUM(O34:O43) -> 22729355
H47: Change in Net Position | M47: =M45+M30 -> 1799113 | N47: =N45+N30 -> -22 | O47: =O45+O30 -> 1799091
E49: Net Assets- Beginning of Year | M49: 112259766 | N49: 11911 | O49: 112271677
E51: Net Assets- End of Year | M51: =SUM(M47,M49) -> 114058879 | N51: =N49+N47 -> 11889 | O51: =O49+O47 -> 114070768

Sheet East Baton Rouge
J1: East Baton Rouge County 2014 Statement of Activities
J2: Issued: December 31, 2014
M4: NET (EXPENSE) REVENUE AND CHANGES IN NET POSITION
J5: PROGRAM REVENUES | M5: PRIMARY GOVERNMENT
A6: FUNCTIONS/PROGRAMS | I6: Expenses | J6: Charges for Services | K6: Operating Grants and Contributions | L6: Capital Grants and Contributions | M6: Governmental Activities | N6: Business-type Activities | O6: Total | P6: Component Units
A7: Primary Government:
B8: Government Activities:
C9: General government | I9: -99148612 | J9: 22795703 | K9: 320097 | M9: =SUM(I9:L9) -> -76032812 | O9: =SUM(M9:N9) -> -76032812
C10: Public safety | I10: -233011923 | J10: 27006901 | K10: 10769916 | L10: 321868 | M10: =SUM(I10:L10) -> -194913238 | O10: =SUM(M10:N10) -> -194913238
C11: Transportation | I11: -66920723 | J11: 216379 | K11: 571666 | L11: 23610909 | M11: =SUM(I11:L11) -> -42521769 | O11: =SUM(M11:N11) -> -42521769
C12: Sanitation | I12: -5790 | J12: 51270 | M12: =SUM(I12:L12) -> 45480 | O12: =SUM(M12:N12) -> 45480
C13: Health and welfare | I13: -9796865 | J13: 800646 | K13: 299188 | M13: =SUM(I13:L13) -> -8697031 | O13: =SUM(M13:N13) -> -8697031
C14: Culture and recreation | I14: -43762277 | J14: 298515 | K14: 1106189 | M14: =SUM(I14:L14) -> -42357573 | O14: =SUM(M14:N14) -> -42357573
C15: Conservation and development | I15: -46084260 | J15: 3520513 | K15: 31193540 | L15: 470640 | M15: =SUM(I15:L15) -> -10899567 | O15: =SUM(M15:N15) -> -10899567
C16: Interest and fiscal charges on long-term debt | I16: -13413000 | M16: =SUM(I16:L16) -> -13413000 | O16: =SUM(M16:N16) -> -13413000
E18: Total Government Activities | I18: =SUM(I9:I16) -> -512143450 | J18: =SUM(J9:J16) -> 54689927 | K18: =SUM(K9:K16) -> 44260596 | L18: =SUM(L9:L16) -> 24403417 | M18: =SUM(M9:M16) -> -388789510 | N18: =SUM(N9:N16) -> 0 | O18: =SUM(O9:O16) -> -388789510 | P18: =SUM(P9:P16) -> 0
B20: Business-type Activities:
C21: Airport | I21: -28541998 | J21: 17237125 | K21: 560556 | L21: 2620425 | N21: =SUM(I21:L21) -> -8123892 | O21: =SUM(M21:N21) -> -8123892
C22: Sewer | I22: -156351603 | J22: 75419472 | K22: 6819819 | L22: 5748809 | N22: =SUM(I22:L22) -> -68363503 | O22: =SUM(M22:N22) -> -68363503
C23: Solid waste collection and disposal | I23: -40892829 | J23: 37589552 | N23: =SUM(I23:K23) -> -3303277 | O23: =SUM(M23:N23) -> -3303277
C24: Convention center | I24: -13381809 | J24: 6491539 | K24: 331905 | L24: 1983034 | N24: =SUM(I24:L24) -> -4575331 | O24: =SUM(M24:N24) -> -4575331
C25: Parking facilities | I25: -2745073 | J25: 852633 | N25: =SUM(I25:K25) -> -1892440 | O25: =SUM(M25:N25) -> -1892440
E27: Total Business-type Activities | I27: =SUM(I21:I25) -> -241913312 | J27: =SUM(J21:J25) -> 137590321 | K27: =SUM(K21:K25) -> 7712280 | L27: =SUM(L21:L25) -> 10352268 | M27: =SUM(M21:M25) -> 0 | N27: =SUM(N21:N25) -> -86258443 | O27: =SUM(O21:O25) -> -86258443 | P27: =SUM(P15:P25) -> 0
E29: Total primary government | I29: =I27+I18 -> -754056762 | J29: =J27+J18 -> 192280248 | K29: =SUM(K18+K27) -> 51972876 | L29: =SUM(L18+L27) -> 34755685 | M29: =M27+M18 -> -388789510 | N29: =N27+N18 -> -86258443 | O29: =O27+O18 -> -475047953 | P29: =SUM(P17:P27) -> 0
A31: Component units:
B32: Judicial court services | I32: -58983934 | J32: 24052298 | K32: 24105511 | P32: =SUM(I32:M32) -> -10826125
B33: Economic development districts | I33: -3783707 | J33: 468858 | K33: 671397 | L33: 1825000 | P33: =SUM(I33:M33) -> -818452
B34: Mass transit | I34: -25275010 | J34: 2103473 | L34: 5460644 | P34: =SUM(I34:M34) -> -17710893
E36: Total component units | I36: =SUM(I32:I34) -> -88042651 | J36: =SUM(J32:J34) -> 26624629 | K36: =SUM(K32:K34) -> 24776908 | M36: =SUM(M32:M34) -> 0 | N36: =SUM(N32:N34) -> 0 | O36: =SUM(O32:O34) -> 0 | P36: =SUM(P32:P34) -> -29355470
G38: General Revenues:
H39: Taxes:
I40: Property | M40: 98252896 | O40: =SUM(M40:N40) -> 98252896 | P40: 16417996
I41: Gross receipts business | M41: 24761520 | O41: =SUM(M41:N41) -> 24761520
I42: Sales | M42: 223779923 | N42: 43583023 | O42: =SUM(M42:N42) -> 267362946
I43: Occupancy | M43: 2211310 | O43: =SUM(M43:N43) -> 2211310 | P43: 2246904
I44: Occupational | M44: 10664408 | O44: =SUM(M44:N44) -> 10664408
I45: Insurance premium | M45: 3734350 | O45: =SUM(M45:N45) -> 3734350
I46: Gaming admissions | M46: 9218503 | O46: =SUM(M46:N46) -> 9218503
I47: Interest and penalties - delinquent taxes | M47: 1483091 | O47: =SUM(M47:N47) -> 1483091
H48: Miscellaneous | M48: 17480 | O48: =SUM(M48:N48) -> 17480
H49: Grants and contributions not restricted to specific programs | M49: 5551706 | O49: =SUM(M49:N49) -> 5551706 | P49: 557920
H50: Investment earnings | M50: 413278 | N50: 1035201 | O50: =SUM(M50:N50) -> 1448479 | P50: 6905053
H51: Gain on sale of capital assets | M51: 813639 | N51: 147297 | O51: =SUM(M51:N51) -> 960936 | P51: 387379
H52: Transfers (to) from other funds | M52: 886331 | N52: -886331 | O52: =SUM(M52:N52) -> 0
H54: Total General Revenues and Transfers | M54: =SUM(M40:M52) -> 381788435 | N54: =SUM(N40:N52) -> 43879190 | O54: =SUM(O40:O52) -> 425667625 | P54: =SUM(P40:P51) -> 26515252
H56: Change in Net Position | M56: =M54+M29 -> -7001075 | N56: =N54+N29 -> -42379253 | O56: =O54+O29 -> -49380328 | P56: =P54+P36 -> -2840218
E58: Net Assets- Beginning of Year | M58: 614633296 | N58: 925527089 | O58: 1540160385 | P58: 45352953
E60: Net Assets- End of Year | M60: =SUM(M56,M58) -> 607632221 | N60: =N58+N56 -> 883147836 | O60: =O58+O56 -> 1490780057 | P60: =P58+P56 -> 42512735

Sheet East Carroll
J1: East Carroll County 2014 Statement of Activities
J2: Issued: December 31, 2014
J5: PROGRAM REVENUES | M5: NET (EXPENSE) REVENUE AND CHANGES IN NET POSITION
A6: FUNCTIONS/PROGRAMS | I6: Expenses | J6: Charges for Services | K6: Operating Grants and Contributions | L6: Capital Grants and Contributions | M6: Governmental Activities | N6: Business-type Activities | O6: Total
A7: Primary Government:
B8: Government Activities:
C9: General government:
D10: Legislative | I10: -39938 | M10: =SUM(I10:L10) -> -39938 | O10: =SUM(M10:N10) -> -39938
D11: Judicial | I11: -613097 | J11: 442209 | K11: 1200 | M11: =SUM(I11:L11) -> -169688 | O11: =SUM(M11:N11) -> -169688
D12: Elections | I12: -52551 | M12: =SUM(I12:L12) -> -52551 | O12: =SUM(M12:N12) -> -52551
D13: Finance and administrative | I13: -219715 | M13: =SUM(I13:L13) -> -219715 | O13: =SUM(M13:N13) -> -219715
D14: Other general government | I14: -1092292 | K14: 294206 | M14: =SUM(I14:L14) -> -798086 | O14: =SUM(M14:N14) -> -798086
C15: Public safety | I15: -452380 | K15: 113082 | L15: 450626 | M15: =SUM(I15:L15) -> 111328 | O15: =SUM(M15:N15) -> 111328
C16: Public works | I16: -1558407 | J16: 101241 | K16: 264287 | M16: =SUM(I16:L16) -> -1192879 | O16: =SUM(M16:N16) -> -1192879
C17: Health and welfare | I17: -136634 | M17: =SUM(I17:L17) -> -136634 | O17: =SUM(M17:N17) -> -136634
C18: Culture and recreation | I18: -349005 | J18: 11585 | K18: 23045 | M18: =SUM(I18:L18) -> -314375 | O18: =SUM(M18:N18) -> -314375
C19: Economic development and assistance | I19: -6860 | M19: =SUM(I19:L19) -> -6860 | O19: =SUM(M19:N19) -> -6860
C20: Transportation | I20: -31501 | M20: =SUM(I20:L20) -> -31501 | O20: =SUM(M20:N20) -> -31501
C21: Interest on long-term debt | I21: -19777 | M21: =SUM(I21:L21) -> -19777 | O21: =SUM(M21:N21) -> -19777
E23: Total Government Activities | I23: =SUM(I10:I21) -> -4572157 | J23: =SUM(J10:J21) -> 555035 | K23: =SUM(K10:K21) -> 695820 | L23: =SUM(L10:L21) -> 450626 | M23: =SUM(M10:M21) -> -2870676 | O23: =SUM(O10:O21) -> -2870676
B25: Business-type Activities:
C26: Health and welfare | I26: -630500 | J26: 3388 | K26: 631807 | L26: 0 | N26: =SUM(I26:L26) -> 4695 | O26: =SUM(M26:N26) -> 4695
E28: Total Component Units | I28: =SUM(I26:I26) -> -630500 | J28: =SUM(J26:J26) -> 3388 | K28: =SUM(K26:K26) -> 631807 | L28: =SUM(L26:L26) -> 0 | M28: =SUM(M26:M26) -> 0 | N28: =SUM(N26:N26) -> 4695 | O28: =SUM(O26:O26) -> 4695
G30: General Revenues:
H31: Taxes:
I32: Property taxes, levied for general purposes | M32: 2230477 | O32: =SUM(M32:N32) -> 2230477
I33: Property taxes, levied for debt services | M33: 72199 | O33: =SUM(M33:N33) -> 72199
I34: Sales taxes, levied for general purposes | M34: 657398 | O34: =SUM(M34:N34) -> 657398
H35: State revenue sharing | M35: 47309 | O35: =SUM(M35:N35) -> 47309
H36: Other taxes | M36: 34249 | O36: =SUM(M36:N36) -> 34249
H37: Grants and contributions not restricted to specific programs | M37: 60182 | O37: =SUM(M37:N37) -> 60182
H38: Licenses and permits | M38: 148989 | O38: =SUM(M38:N38) -> 148989
H39: Interest and investment earnings | M39: 4176 | N39: 280 | O39: =SUM(M39:N39) -> 4456
H40: Miscellaneous | M40: 127335 | O40: =SUM(M40:N40) -> 127335
H42: Total General Revenues | M42: =SUM(M32:M40) -> 3382314 | N42: =SUM(N32:N40) -> 280 | O42: =SUM(O32:O40) -> 3382594
H44: Change in Net Position | M44: =SUM(M23+M28+M42) -> 511638 | N44: =SUM(N23+N28+N42) -> 4975 | O44: =SUM(O23+O28+O42) -> 516613
E46: Net Position- Beginning of Year | M46: 10622325 | N46: 27339 | O46: =SUM(M46:N46) -> 10649664
E48: Net Position- End of Year | M48: =SUM(M44,M46) -> 11133963 | N48: =N46+N44 -> 32314 | O48: =O46+O44 -> 11166277

Sheet East Feliciana
J1: East Feliciana County 2014 Statement of Activities
J2: Issued: December 31, 2014
J5: PROGRAM REVENUES
A6: FUNCTIONS/PROGRAMS | I6: Expenses | J6: Charges for Services | K6: Operating Grants and Contributions | L6: Capital Grants and Contributions | M6: NET REVENUES (EXPENSES)
B7: Government Activities:
C8: General government | I8: -950109.55 | J8: 9207.11 | K8: 6729.26 | M8: =SUM(I8:L8) -> -934173.18
C9: Culture and recreation | I9: -4586.94 | M9: =SUM(I9:L9) -> -4586.94
C10: Economic development | I10: -9587.67 | M10: =SUM(I10:L10) -> -9587.67
C11: Health and welfare | I11: -329817.02 | K11: 132152 | M11: =SUM(I11:L11) -> -197665.02
C12: Public safety | I12: -1169097.2 | J12: 146700.56 | K12: 137752.09 | L12: 259734.7 | M12: =SUM(I12:L12) -> -624909.89
C13: Public works | I13: -2638111.1 | L13: 2136459.2 | M13: =SUM(I13:L13) -> -501651.87
E15: Total Government Activities/Primary government | I15: =SUM(I8:I13) -> -5101309.5 | J15: =SUM(J8:J13) -> 155907.67 | K15: =SUM(K8:K13) -> 276633.35 | L15: =SUM(L8:L13) -> 2396193.9 | M15: =SUM(M8:M13) -> -2272574.6
G17: General Revenues and Transfers:
H18: Intergovernmental revenues | M18: 406135.5
H19: Taxes:
I20: Ad valorem | M20: 836005.3
I21: Severance | M21: 420876.36
I22: Sales | M22: 4076159.5
H23: Franchise fees | M23: 10173.51
H24: Insurance rebates | M24: 85614.52
H25: Licenses and permits | M25: 300353.89
H26: Fines and forfeitures | M26: 85501.98
H27: Rents and other fees | M27: 99708.18
H28: Interest earned | M28: 1095.07
H29: Other revenues | M29: -7665.45
H31: Total General Revenues and Transfers | M31: =SUM(M18:M29) -> 6313958.4
H33: Change in Net Position | M33: =SUM(M15,M31) -> 4041383.8
E35: Net Assets- Beginning of Year | M35: 14654714
E37: Net Assets- End of Year | M37: =SUM(M33,M35) -> 18696097

Sheet Evangeline
J1: Evangeline County 2014 Statement of Activities
J2: Issued: December 31, 2014
J4: PROGRAM REVENUES | M4: NET (EXPENSE) REVENUE AND CHANGE IN NET ASSETS
I5: Expenses | J5: Fees, Fines, and Charges for Services | K5: Operating Grants and Contributions | L5: Capital Grants and Contributions | M5: Governmental Activities | N5: Business-type Activities | O5: Total
A6: Primary Government:
B7: Government Activities:
C8: General government | I8: -2303564 | J8: 650407 | M8: =SUM(I8:L8) -> -1653157 | O8: =SUM(M8:N8) -> -1653157
C9: Public safety | I9: -844114 | K9: 93919 | M9: =SUM(I9:L9) -> -750195 | O9: =SUM(M9:N9) -> -750195
C10: Public works | I10: -7176279 | J10: 125770 | K10: 462208 | L10: 533621 | M10: =SUM(I10:L10) -> -6054680 | O10: =SUM(M10:N10) -> -6054680
C11: Health and welfare | I11: -483095 | M11: =SUM(I11:L11) -> -483095 | O11: =SUM(M11:N11) -> -483095
C12: Culture and recreation | I12: -1293548 | J12: 237288 | K12: 26748 | M12: =SUM(I12:L12) -> -1029512 | O12: =SUM(M12:N12) -> -1029512
C13: Economic development | I13: -213035 | M13: =SUM(I13:L13) -> -213035 | O13: =SUM(M13:N13) -> -213035
C14: Interest on long-term debt | I14: -1087451 | M14: =SUM(I14:L14) -> -1087451 | O14: =SUM(M14:N14) -> -1087451
E16: Total Government Activities | I16: =SUM(I8:I14) -> -13401086 | J16: =SUM(J8:J14) -> 1013465 | K16: =SUM(K8:K14) -> 582875 | L16: =SUM(L8:L14) -> 533621 | M16: =SUM(M8:M14) -> -11271125 | O16: =SUM(O8:O14) -> -11271125
B18: Business-type Activities:
C19: Ward One sewer system | I19: -57232 | J19: 38890 | N19: =SUM(I19:L19) -> -18342 | O19: =N19 -> -18342
C20: Section 8 housing program | I20: -554475 | K20: 525342 | N20: =SUM(I20:L20) -> -29133 | O20: =N20 -> -29133
E22: Total business-type Activities | I22: =SUM(I19:I20) -> -611707 | J22: =SUM(J19:J20) -> 38890 | K22: =SUM(K19:K20) -> 525342 | L22: =SUM(L19:L20) -> 0 | M22: =SUM(M19:M20) -> 0 | N22: =SUM(N19:N20) -> -47475 | O22: =SUM(O19:O20) -> -47475
E24: Total primary government | I24: =I22+I16 -> -14012793 | J24: =J22+J16 -> 1052355 | K24: =K22+K16 -> 1108217 | L24: =L22+L16 -> 533621 | M24: =M22+M16 -> -11271125 | N24: =N22+N16 -> -47475 | O24: =O22+O16 -> -11318600
G26: General Revenues:
H27: Taxes:
I28: Property taxes, levied for general purposes | M28: 5857491 | O28: =SUM(M28:N28) -> 5857491
I29: Sales and use taxes, levied for general purposes | M29: 3282902 | O29: =SUM(M29:N29) -> 3282902
H30: Grants and contributions not restricted to specific programs:
I31: Beer taxes | M31: 5024 | O31: =SUM(M31:N31) -> 5024
I32: State revenue sharing | M32: 233286 | O32: =SUM(M32:N32) -> 233286
I33: Parish equalization | M33: 1180378 | O33: =SUM(M33:N33) -> 1180378
I34: Other state grants | M34: 201048 | O34: =SUM(M34:N34) -> 201048
H35: Interest and investment earnings | M35: 85138 | N35: 161 | O35: =SUM(M35:N35) -> 85299
H36: Miscellaneous | M36: 589263 | O36: =SUM(M36:N36) -> 589263
H38: Total General Revenues | M38: =SUM(M28:M36) -> 11434530 | N38: =SUM(N28:N36) -> 161 | O38: =SUM(O28:O36) -> 11434691
H40: Change in Net Position | M40: =M38+M24 -> 163405 | N40: =N38+N24 -> -47314 | O40: =O38+O24 -> 116091
E42: Net Position- January 1, 2014, as restated | M42: 35853785 | N42: 350804 | O42: =SUM(M42:N42) -> 36204589
E44: Net Position- December 31, 2014 | M44: =SUM(M40,M42) -> 36017190 | N44: =N42+N40 -> 303490 | O44: =O42+O40 -> 36320680

Sheet Franklin
J1: Franklin County 2014 Statement of Activities
J2: Issued: December 31, 2014
J5: PROGRAM REVENUES
A6: FUNCTIONS | I6: Expenses | J6: Charges for Services | K6: Operating Grants and Contributions | L6: Capital Grants and Contributions | M6: NET (EXPENSE) REVENUE AND CHANGES IN NET POSITION
B7: Government Activities:
C8: General government | I8: -781880 | J8: 109310 | K8: 176110 | M8: =SUM(I8:L8) -> -496460
C9: Public safety | I9: -453160 | J9: 34418 | M9: =SUM(I9:L9) -> -418742
C10: Public works | I10: -6091341 | J10: 6506 | K10: 518477 | L10: 1607679 | M10: =SUM(I10:L10) -> -3958679
C11: Health and welfare | I11: -601056 | K11: 52016 | M11: =SUM(I11:L11) -> -549040
C12: Culture and recreation | I12: -132615 | M12: =SUM(I12:L12) -> -132615
C13: Economic development and assistance | I13: -4065049 | J13: 29773 | K13: 3831571 | L13: 66198 | M13: =SUM(I13:L13) -> -137507
E15: Total Government Activities | I15: =SUM(I8:I13) -> -12125101 | J15: =SUM(J8:J13) -> 180007 | K15: =SUM(K8:K13) -> 4578174 | L15: =SUM(L8:L13) -> 1673877 | M15: =SUM(M8:M13) -> -5693043
G17: General Revenues:
H18: Taxes:
I19: Ad valorem | M19: 3303526
I20: Sales taxes | M20: 3817919
I21: State revenue sharing | M21: 176711
I22: Fire insurance rebate | M22: 85569
I23: Other taxes, penalties, and interest | M23: 10965
H24: Grants and contributions not restricted to specific programs | M24: 36450
H25: Licenses and permits | M25: 158503
H26: Unrestricted investment earnings | M26: 86215
H27: Proceeds from lease | M27: 70000
H28: Gain (loss) on disposal of assets | M28: -38951
H30: Total General Revenues | M30: =SUM(M19:M28) -> 7706907
H32: Change in Net Position | M32: =SUM(M15,M30) -> 2013864
E34: Net Assets- Beginning of Year | M34: 26782200
E36: Net Assets- End of Year | M36: =SUM(M32,M34) -> 28796064

Sheet Grant 
J1: Grant County 2014 Statement of Activities
J2: Issued: December 31, 2014
J4: PROGRAM REVENUES
A5: FUNCTIONS/PROGRAMS | I5: Expenses | J5: Charges for Services | K5: Operating Grants and Contributions | L5: Capital Grants and Contributions | M5: Net (Expenses) Revenue | N5: Governmental Activities | O5: Business-type Activities | P5: Total
A6: Primary Government:
B7: Government Activities:
C8: General government:
D9: Legislative | I9: -213011 | M9: =SUM(I9:L9) -> -213011 | P9: =SUM(O9:O9) -> 0
D10: Judicial | I10: -606967 | J10: 191523 | K10: 168396 | M10: =SUM(I10:L10) -> -247048 | P10: =SUM(O10:O10) -> 0
D11: Finance and administrative | I11: -235770 | M11: =SUM(I11:L11) -> -235770 | P11: =SUM(O11:O11) -> 0
D12: Other general government | I12: -279567 | L12: 22510 | M12: =SUM(I12:L12) -> -257057 | P12: =SUM(O12:O12) -> 0
C13: Public safety | I13: -328726 | K13: 36921 | M13: =SUM(I13:L13) -> -291805 | P13: =SUM(O13:O13) -> 0
C14: Public works | M14: =SUM(I14:L14) -> 0
D15: Road maintenance | I15: -1524011 | J15: 5549 | K15: 734652 | M15: =SUM(I15:L15) -> -783810 | P15: =SUM(O15:O15) -> 0
D16: Landfill maintenance | I16: -1080776 | J16: 81692 | K16: 17830 | M16: =SUM(I16:L16) -> -981254 | P16: =SUM(O16:O16) -> 0
D17: CDBG South Grant Sewer System | M17: =SUM(I17:L17) -> 0
D18: CDBG Herman Park Sewer System | I18: -238689 | K18: 174816 | M18: =SUM(I18:L18) -> -63873 | P18: =SUM(O18:O18) -> 0
D19: Other public works | I19: -48193 | K19: 48193 | M19: =SUM(I19:L19) -> 0 | P19: =SUM(O19:O19) -> 0
C20: Economic development | I20: -34600 | K20: 28200 | M20: =SUM(I20:L20) -> -6400 | P20: =SUM(O20:O20) -> 0
C21: Health and welfare | I21: -102862 | M21: =SUM(I21:L21) -> -102862 | P21: =SUM(O21:O21) -> 0
C22: Culture and recreation | I22: -11066 | J22: 14695 | M22: =SUM(I22:L22) -> 3629 | P22: =SUM(O22:O22) -> 0
E24: Total Government Activities | I24: =SUM(I9:I22) -> -4704238 | J24: =SUM(J9:J22) -> 293459 | K24: =SUM(K9:K22) -> 1209008 | L24: =SUM(L9:L22) -> 22510 | M24: =SUM(M9:M22) -> -3179261 | N24: =SUM(N9:N22) -> 0 | O24: =SUM(O9:O22) -> 0 | P24: =SUM(P9:P22) -> 0
B26: Business-type Activities:
C27: Utility system | I27: 598048 | J27: 660955 | M27: 62907 | P27: =SUM(O27:O27) -> 0
E29: Total business-type Activities | I29: =SUM(I27:I27) -> 598048 | J29: =SUM(J27:J27) -> 660955 | K29: =SUM(K27:K27) -> 0 | L29: =SUM(L27:L27) -> 0 | M29: =SUM(M27:M27) -> 62907 | N29: =SUM(N27:N27) -> 0 | O29: =SUM(O27:O27) -> 0 | P29: =SUM(P27:P27) -> 0
E31: Total government | I31: =I29+I24 -> -4106190 | J31: =J29+J24 -> 954414 | K31: =K29+K24 -> 1209008 | L31: =L29+L24 -> 22510 | M31: =SUM(M24+M29) -> -3116354 | N31: =N29+N24 -> 0 | O31: =O29+O24 -> 0 | P31: =P29+P24 -> 0
G33: Net (Expense) Revenue | N33: -3179261 | O33: 62907 | P33: =SUM(N33:O33) -> -3116354
G35: General Revenues:
H36: Taxes:
I37: Ad valorem | N37: 889307 | P37: =SUM(N37:O37) -> 889307
I38: Sales | N38: 1159486 | P38: =SUM(N38:O38) -> 1159486
I39: Severance | N39: 538280 | P39: =SUM(N39:O39) -> 538280
I40: Other | N40: 159990 | P40: =SUM(N40:O40) -> 159990
H41: Revenue sharing | N41: 79114 | P41: =SUM(N41:O41) -> 79114
H42: Other | N42: 124581 | O42: 3884 | P42: =SUM(N42:O42) -> 128465
H44: Total General Revenues | N44: =SUM(N37:N42) -> 2950758 | O44: =SUM(O37:O42) -> 3884 | P44: =SUM(P37:P42) -> 2954642
H46: Change in Net Assets | N46: =SUM(N44+N33) -> -228503 | O46: =SUM(O44+O33) -> 66791 | P46: =SUM(P44+P33) -> -161712
E49: Net Assets- Beginning of Year | N49: 8394999 | O49: 708050 | P49: =SUM(N49:O49) -> 9103049
E50: As Originally Reported Prior Period Adjustment | N50: 12625 | P50: =SUM(N50:O50) -> 12625
E51: As Restated | N51: 8407624 | O51: 708050 | P51: =SUM(N51:O51) -> 9115674
E52: Net Assets- End of Year | N52: =N49+N46+N50 -> 8179121 | O52: =O49+O46+O50 -> 774841 | P52: =P49+P46+P50 -> 8953962

Sheet Iberia
J1: Iberia County 2014 Statement of Activities
J2: Issued: December 31, 2014
J5: PROGRAM REVENUES | M5: NET (EXPENSE) REVENUE AND CHANGE IN NET ASSETS
A6: FUNCTIONS/PROGRAMS | I6: Expenses | J6: Fees, Fines, and Charges for Services | K6: Operating Grants and Contributions | L6: Capital Grants and Contributions | M6: PRIMARY GOVERNMENT | N6: Component Units
A7: Primary Government:
B8: Government Activities:
C9: General government | I9: -5786600 | J9: 897956 | K9: 98114 | M9: =SUM(I9:L9) -> -4790530
C10: Public safety | I10: -4622943 | J10: 549799 | K10: 180534 | L10: 42717 | M10: =SUM(I10:L10) -> -3849893
C11: Public works | I11: -12090667 | J11: 6876 | K11: 1621734 | L11: 4599488 | M11: =SUM(I11:L11) -> -5862569
C12: Health and welfare | I12: -6611112 | J12: 137935 | K12: 6264139 | M12: =SUM(I12:L12) -> -209038
C13: Culture and recreation | I13: -2835116 | K13: 21875 | M13: =SUM(I13:L13) -> -2813241
C14: Urban redevelopment and housing | I14: -852741 | K14: 692019 | M14: =SUM(I14:L14) -> -160722
C15: Economic development and assistance | I15: -425794 | K15: 43819 | M15: =SUM(I15:L15) -> -381975
C16: Unallocated depreciation | I16: -3343755 | M16: =SUM(I16:L16) -> -3343755
C17: Interest on long-term debt | I17: -359539 | M17: =SUM(I17:L17) -> -359539
E19: Total Primary government | I19: =SUM(I9:I17) -> -36928267 | J19: =SUM(J9:J17) -> 1592566 | K19: =SUM(K9:K17) -> 8922234 | L19: =SUM(L9:L17) -> 4642205 | M19: =SUM(M9:M17) -> -21771262 | N19: =SUM(N9:N17) -> 0
E21: Component units | I21: -80150485 | J21: 67700153 | K21: 4625753 | L21: 2339692 | M21: 0 | N21: -5484887
G23: General Revenues:
H24: Taxes:
I25: Property taxes | M25: 10403521 | N25: 2856136
I26: Sales and use taxes | M26: 7111581 | N26: 4696057
I27: Hotel/motel taxes | M27: 274084 | N27: 274352
I28: Severance taxes | M28: 1136974
I29: Fire insurance rebate | N29: 139315
I30: Occupational licenses | M30: 934101
H31: Grants and contributions not restricted to specific programs:
I32: State revenue sharing | M32: 443269 | N32: 437727
H33: Interest and investment earnings | M33: 320883 | N33: 328937
H34: Miscellaneous | M34: 223601 | N34: 510960
H36: Total General Revenues | M36: =SUM(M25:M34) -> 20848014 | N36: =SUM(N25:N34) -> 9243484
H38: Change in Net Position | M38: =M36+M19 -> -923248 | N38: =N36+N21 -> 3758597
E40: Net Assets- Beginning of Year, as restated | M40: 133531832 | N40: 82809047
E42: Net Assets- End of Year | M42: =SUM(M38,M40) -> 132608584 | N42: =N40+N38 -> 86567644

Sheet Iberville
J1: Iberville County 2014 Statement of Activities
J2: Issued: December 31, 2014
M4: NET (EXPENSE) REVENUE AND CHANGE IN NET POSITION
J5: PROGRAM REVENUES | M5: PRIMARY GOVERNMENT | P5: COMPONENT UNITS
A6: FUNCTIONS/PROGRAMS | I6: Expenses | J6: Charges for Services | K6: Operating Grants and Contributions | L6: Capital Grants and Contributions | M6: Governmental Activities | N6: Business-type Activities | O6: Total | P6: Governmental Activities | Q6: Business-type Activities
A7: Primary Government:
B8: Government Activities:
C9: General government | I9: -21155383 | J9: 527692 | K9: 164589 | L9: 14400 | M9: =SUM(I9:L9) -> -20448702 | O9: =SUM(M9:N9) -> -20448702
C10: Public safety | I10: -4093206 | J10: 697956 | K10: 330982 | M10: =SUM(I10:L10) -> -3064268 | O10: =SUM(M10:N10) -> -3064268
C11: Public works | I11: -12246757 | J11: 1610 | K11: 744394 | L11: 29720407 | M11: =SUM(I11:L11) -> 18219654 | O11: =SUM(M11:N11) -> 18219654
C12: Public health | I12: -2311952 | J12: 100334 | K12: 436201 | M12: =SUM(I12:L12) -> -1775417 | O12: =SUM(M12:N12) -> -1775417
C13: Economic development | I13: -267660 | M13: =SUM(I13:L13) -> -267660 | O13: =SUM(M13:N13) -> -267660
C14: Culture and recreation | I14: -824014 | J14: 12728 | K14: 126614 | M14: =SUM(I14:L14) -> -684672 | O14: =SUM(M14:N14) -> -684672
C15: Interest on long-term debt | I15: -691880 | M15: =SUM(I15:L15) -> -691880 | O15: =SUM(M15:N15) -> -691880
E17: Total Government Activities | I17: =SUM(I9:I15) -> -41590852 | J17: =SUM(J9:J15) -> 1340320 | K17: =SUM(K9:K15) -> 1802780 | L17: =SUM(L9:L15) -> 29734807 | M17: =SUM(M9:M15) -> -8712945 | O17: =SUM(O9:O15) -> -8712945 | P17: =SUM(P9:P15) -> 0 | Q17: =SUM(Q9:Q15) -> 0
B19: Business-type Activities:
C20: Water, natural gas and sewer | I20: -4928587 | J20: 5557513 | N20: =SUM(I20:L20) -> 628926 | O20: =N20 -> 628926
E22: Total business-type Activities | I22: =SUM(I20:I20) -> -4928587 | J22: =SUM(J20:J20) -> 5557513 | K22: =SUM(K20:K20) -> 0 | L22: =SUM(L20:L20) -> 0 | M22: =SUM(M20:M20) -> 0 | N22: =SUM(N20:N20) -> 628926 | O22: =SUM(O20:O20) -> 628926 | P22: =SUM(P20:P20) -> 0 | Q22: =SUM(Q20:Q20) -> 0
E24: Total primary government | I24: =I22+I17 -> -46519439 | J24: =J22+J17 -> 6897833 | K24: =K22+K17 -> 1802780 | L24: =L17+L22 -> 29734807 | M24: =M17 -> -8712945 | N24: =N22 -> 628926 | O24: =O22+O17 -> -8084019 | P24: =P22+P17 -> 0 | Q24: =Q22+Q17 -> 0
A26: Component units:
B27: Governmental activities | I27: -3371456 | J27: 120670 | K27: 100170 | P27: =SUM(I27:L27) -> -3150616
B28: Business-type activities | I28: -1724145 | J28: 1447161 | K28: 19712 | Q28: =SUM(I28:L28) -> -257272
E30: Total component units | I30: =SUM(I27:I28) -> -5095601 | J30: =SUM(J27:J28) -> 1567831 | K30: =SUM(K27:K28) -> 119882 | L30: =SUM(L27:L28) -> 0 | M30: =SUM(M27:M28) -> 0 | N30: =SUM(N27:N28) -> 0 | O30: =SUM(O27:O28) -> 0 | P30: =SUM(P27:P28) -> -3150616 | Q30: =SUM(Q27:Q28) -> -257272
G32: General Revenues:
H33: Property taxes | M33: 5872715 | O33: =SUM(M33:N33) -> 5872715 | P33: 3842978
H34: Sales taxes | M34: 19346721 | O34: =SUM(M34:N34) -> 19346721
H35: Franchise taxes | M35: 112796 | O35: =SUM(M35:N35) -> 112796
H36: Alcoholic beverage taxes | M36: 16419 | O36: =SUM(M36:N36) -> 16419
H37: Gaming taxes | M37: 125556 | O37: =SUM(M37:N37) -> 125556
H38: Unrestricted grants and contributions | M38: 1089548 | O38: =SUM(M38:N38) -> 1089548
H39: Unrestricted investment earnings | M39: 28950 | N39: 3338 | O39: =SUM(M39:N39) -> 32288 | P39: 2839 | Q39: 1599
H40: Miscellaneous revenues | M40: 5249364 | N40: 309960 | O40: =SUM(M40:N40) -> 5559324 | P40: 19590 | Q40: 55755
H41: Gain on sale of capital assets | M41: 81135 | O41: =SUM(M41:N41) -> 81135
H42: Transfers (from) to governmental activities
H44: Total General Revenues and transfers | M44: =SUM(M33:M42) -> 31923204 | N44: =SUM(N33:N42) -> 313298 | O44: =SUM(O33:O42) -> 32236502 | P44: =SUM(P33:P41) -> 3865407 | Q44: =SUM(Q34:Q42) -> 57354
H46: Change in Net Position | M46: =M44+M24 -> 23210259 | N46: =N44+N24 -> 942224 | O46: =O44+O24 -> 24152483 | P46: =SUM(P24+P30+P44) -> 714791 | Q46: =Q44+Q30 -> -199918
E48: Net Assets- Beginning of Year | M48: 104967613 | N48: 13330851 | O48: 118298464 | P48: 6255569 | Q48: 4789660
E50: Restatement to beginning net position | Q50: -225339
E52: Net Position-beginning restated | M52: =M48+M50 -> 104967613 | N52: =N48+N50 -> 13330851 | O52: =O48+O50 -> 118298464 | P52: =P48+P50 -> 6255569 | Q52: =Q48+Q50 -> 4564321
E54: Net Assets- End of Year | M54: =SUM(M46+M48+M50) -> 128177872 | N54: =SUM(N46+N48+N50) -> 14273075 | O54: =SUM(O46+O48+O50) -> 142450947 | P54: =SUM(P46+P48+P50) -> 6970360 | Q54: =SUM(Q46+Q48+Q50) -> 4364403

Sheet Jackson
J1: Jackson County 2014 Statement of Activities
J2: Issued: December 31, 2014
M4: PRIMARY GOVERNMENT
J5: PROGRAM REVENUES | M5: Governmental Activities
A6: FUNCTIONS/PROGRAMS | I6: Expenses | J6: Charges for Services | K6: Operating Grants and Contributions | L6: Capital Grants and Contributions | M6: Net (Expense) Revenue and Changes in net Position
A7: Primary Government:
B8: Government Activities:
C9: General government:
D10: Legislative | I10: -120698 | M10: =SUM(I10:L10) -> -120698
D11: Judicial | I11: -266805 | J11: 31746 | M11: =SUM(I11:L11) -> -235059
D12: Elections | I12: -24856 | M12: =SUM(I12:L12) -> -24856
D13: Finance and administrative | I13: -266474 | M13: =SUM(I13:L13) -> -266474
D14: Other general government | I14: -530878 | J14: 14205 | K14: 82205 | M14: =SUM(I14:L14) -> -434468
C15: Public safety | I15: -700715 | K15: 90688 | M15: =SUM(I15:L15) -> -610027
C16: Public works | I16: -4985065 | J16: 143664 | K16: 331971 | M16: =SUM(I16:L16) -> -4509430
C17: Health and welfare | I17: -255022 | M17: =SUM(I17:L17) -> -255022
C18: Culture and recreation | I18: -1312896 | J18: 25708 | K18: 21875 | M18: =SUM(I18:L18) -> -1265313
E20: Total Government Activities | I20: =SUM(I10:I18) -> -8463409 | J20: =SUM(J10:J18) -> 215323 | K20: =SUM(K10:K18) -> 526739 | L20: =SUM(L10:L18) -> 0 | M20: =SUM(M10:M18) -> -7721347
G22: General Revenues:
H23: Taxes:
I24: Property taxes, levied for general purposes | M24: 4409812
I25: Sales taxes, levied for general purposes | M25: 2222337
I26: State revenue sharing | M26: 80284
I27: Severance tax | M27: 807972
I28: Miscellaneous taxes | M28: 150370
H29: Licenses and permits | M29: 49490
H30: Interest and investment earnings | M30: 84964
H31: Miscellaneous | M31: 140413
H33: Total General Revenues | M33: =SUM(M24:M31) -> 7945642
H35: Change in Net Position | M35: =M33+M20 -> 224295
E37: Net Assets- Beginning of Year | M37: 29639318
E39: Net Assets- End of Year | M39: =SUM(M35,M37) -> 29863613

Sheet Jefferson Davis
J1: Jefferson Davis County 2014 Statement of Activities
J2: Issued: December 31, 2014
M4: NET (EXPENSE) REVENUE AND CHANGES IN NET ASSETS
J5: PROGRAM REVENUES | M5: Primary Government
A6: FUNCTIONS/PROGRAMS | I6: Expenses | J6: Charges for Services | K6: Operating Grants and Contributions | L6: Capital Grants and Contributions | M6: Governmental Activities
A7: Primary Government:
B8: Government Activities:
C9: General government | I9: -4071308 | J9: 1588055 | K9: 7793 | M9: =SUM(I9:L9) -> -2475460
C10: Public safety | I10: -1895472 | J10: 420073 | K10: 285939 | L10: 3008 | M10: =SUM(I10:L10) -> -1186452
C11: Public works | I11: -3604454 | K11: 490344 | L11: 683369 | M11: =SUM(I11:L11) -> -2430741
C12: Culture and recreation | I12: -92870 | J12: 18398 | M12: =SUM(I12:L12) -> -74472
C13: Health and welfare | I13: -1103142 | J13: 22815 | K13: 888573 | M13: =SUM(I13:L13) -> -191754
C14: Economic development | I14: -6928 | M14: =SUM(I14:L14) -> -6928
C15: Interest on long-term debt | I15: -689117 | M15: =SUM(I15:L15) -> -689117
E17: Total Government Activities | I17: =SUM(I9:I15) -> -11463291 | J17: =SUM(J9:J14) -> 2049341 | K17: =SUM(K9:K14) -> 1672649 | L17: =SUM(L9:L14) -> 686377 | M17: =SUM(M9:M15) -> -7054924
G19: General Revenues:
H20: Property taxes | M20: 4470525
H21: Sales tax | M21: 3752169
H22: Severance taxes | M22: 1004328
H23: State revenue sharing | M23: 133824
H24: Occupational licenses and permits | M24: 440556
H25: Grants and contributions not restricted to specific programs | M25: 354948
H26: Investment earnings | M26: 24040
H27: Other general revenues | M27: 126286
H28: Special items:
I29: Gain on sale of capital assets | M29: 1052
H31: Total General Revenues and special items | M31: =SUM(M20:M29) -> 10307728
H33: Change in Net Position | M33: =SUM(M17,M31) -> 3252804
E35: Net Assets- Beginning of Year | M35: 36282847
E37: Net Assets- End of Year | M37: =SUM(M33,M35) -> 39535651

Sheet Jefferson
J1: Jefferson County 2014 Statement of Activities
J2: Issued: December 31, 2014
K3: (amounts in thousands)
M4: NET (EXPENSE) REVENUE AND CHANGE IN NET ASSETS
J5: PROGRAM REVENUES | M5: PRIMARY GOVERNMENT
A6: FUNCTIONS/PROGRAMS | I6: Expenses | J6: Charges for Services | K6: Operating Grants and Contributions | L6: Capital Grants and Contributions | M6: Governmental Activities | N6: Business-type Activities | O6: Total | P6: Component Units
A7: Primary Government:
B8: Government Activities:
C9: General government | I9: -70717 | J9: 15168 | K9: 689 | L9: 216 | M9: =SUM(I9:L9) -> -54644 | O9: =SUM(M9:N9) -> -54644
C10: Public safety | I10: -100987 | J10: 16261 | K10: 9876 | L10: 332 | M10: =SUM(I10:L10) -> -74518 | O10: =SUM(M10:N10) -> -74518
C11: Public works | I11: -133188 | J11: 20297 | K11: 1332 | L11: 46526 | M11: =SUM(I11:L11) -> -65033 | O11: =SUM(M11:N11) -> -65033
C12: Transit | I12: -17961 | J12: 3589 | K12: 499 | L12: 2675 | M12: =SUM(I12:L12) -> -11198 | O12: =SUM(M12:N12) -> -11198
C13: Health and welfare | I13: -47945 | J13: 4266 | K13: 29205 | L13: 3201 | M13: =SUM(I13:L13) -> -11273 | O13: =SUM(M13:N13) -> -11273
C14: Culture and recreation | I14: -48043 | J14: 9033 | K14: 2089 | L14: 5404 | M14: =SUM(I14:L14) -> -31517 | O14: =SUM(M14:N14) -> -31517
C15: Economic development | K15: 60 | M15: =SUM(I15:L15) -> 60 | O15: =SUM(M15:N15) -> 60
C16: Urban redevelopment and housing | I16: -9380 | K16: 4401 | M16: =SUM(I16:L16) -> -4979 | O16: =SUM(M16:N16) -> -4979
C17: Interest on long-term debt | I17: -19721 | M17: =SUM(I17:L17) -> -19721 | O17: =SUM(M17:N17) -> -19721
E19: Total Government Activities | I19: =SUM(I9:I17) -> -447942 | J19: =SUM(J9:J17) -> 68614 | K19: =SUM(K9:K17) -> 48151 | L19: =SUM(L9:L17) -> 58354 | M19: =SUM(M9:M17) -> -272823 | O19: =SUM(O9:O17) -> -272823 | P19: =SUM(P9:P17) -> 0
B21: Business-type Activities:
C22: Consolidated Waterworks District No. 1 | I22: -38689 | J22: 32984 | L22: 421 | N22: =SUM(I22:L22) -> -5284 | O22: =SUM(M22:N22) -> -5284
C23: Consolidated Sewerage District No. 1 | I23: -44544 | J23: 24005 | L23: 418 | N23: -20121 | O23: =SUM(M23:N23) -> -20121
E25: Total Business-type Activities | I25: =SUM(I22:I23) -> -83233 | J25: =SUM(J22:J23) -> 56989 | K25: =SUM(K22:K23) -> 0 | L25: =SUM(L22:L23) -> 839 | M25: =SUM(M22:M23) -> 0 | N25: =SUM(N22:N23) -> -25405 | O25: =SUM(O22:O23) -> -25405 | P25: =SUM(P15:P23) -> 0
E27: Total primary government | I27: =I25+I19 -> -531175 | J27: =J25+J19 -> 125603 | K27: =SUM(K19+K25) -> 48151 | L27: =SUM(L19+L25) -> 59193 | M27: =M25+M19 -> -272823 | N27: =N25+N19 -> -25405 | O27: =O25+O19 -> -298228 | P27: =SUM(P18:P25) -> 0
A29: Component units:
B30: JEDCO | I30: -2872 | J30: 505 | K30: 2734 | L30: 2483 | P30: =SUM(I30:M30) -> 2850
B31: Jefferson Facilities, Inc | I31: -639 | J31: 419 | P31: =SUM(I31:L31) -> -220
B32: Jefferson Redevelopment, Inc | I32: -255 | P32: =SUM(I32:L32) -> -255
B33: Jefferson Parish Finance Authority | I33: -3463 | P33: =SUM(I33:L33) -> -3463
B34: Hospital District No. 1 | I34: -258862 | J34: 221970 | P34: =SUM(I34:L34) -> -36892
B35: Hospital District No. 2 | I35: -371516 | J35: 329862 | P35: =SUM(I35:L35) -> -41654
E37: Total component units | I37: =SUM(I30:I35) -> -637607 | J37: =SUM(J30:J35) -> 552756 | K37: =SUM(K30:K35) -> 2734 | L37: =SUM(L30:L35) -> 2483 | M37: =SUM(M30:M35) -> 0 | N37: =SUM(N30:N35) -> 0 | O37: =SUM(O30:O35) -> 0 | P37: =SUM(P30:P35) -> -79634
G39: General Revenues:
H40: Taxes:
I41: Ad valorem | M41: 191583 | N41: 19831 | O41: 211414
I42: Alcoholic beverage | M42: 424 | O42: =SUM(M42:N42) -> 424
I43: Chain store | M43: 199 | O43: =SUM(M43:N43) -> 199
I44: Franchise fees | M44: 5515 | O44: =SUM(M44:N44) -> 5515
I45: Sales | M45: 148018 | O45: =SUM(M45:N45) -> 148018
I46: Hotel/Motel | M46: 3651 | O46: =SUM(M46:N46) -> 3651
I47: Auto rental | O47: =SUM(M47:N47) -> 0
I48: Severance | M48: 986 | O48: =SUM(M48:N48) -> 986
H49: Unrestricted investment earnings | M49: 4784 | N49: 347 | O49: =SUM(M49:N49) -> 5131 | P49: 11567
H50: Miscellaneous | M50: 29676 | N50: 1195 | O50: =SUM(M50:N50) -> 30871 | P50: 42729
H51: Gain on extinguishement of debt | N51: 1175 | O51: =SUM(M51:N51) -> 1175
H52: Transfers | M52: -1541 | N52: 1541 | O52: =SUM(M52:N52) -> 0
H54: Total General Revenues and Transfers | M54: =SUM(M41:M52) -> 383295 | N54: =SUM(N41:N52) -> 24089 | O54: =SUM(O41:O52) -> 407384 | P54: =SUM(P41:P50) -> 54296
H56: Change in Net Position | M56: =M54+M27 -> 110472 | N56: =N54+N27 -> -1316 | O56: =O54+O27 -> 109156 | P56: =P54+P37 -> -25338
E58: Net Assets- Beginning of Year | M58: 1274410 | N58: 628208 | O58: 1902618 | P58: 477399
E60: Net Assets- End of Year | M60: =SUM(M56,M58) -> 1384882 | N60: =N58+N56 -> 626892 | O60: =O58+O56 -> 2011774 | P60: =P58+P56 -> 452061

Sheet Lafayette
J1: Lafayette County 2014 Statement of Activities
J2: Issued: December 31, 2014
M4: NET (EXPENSE) REVENUE AND CHANGE IN NET POSITION
J5: PROGRAM REVENUES | M5: PRIMARY GOVERNMENT
A6: FUNCTIONS/PROGRAMS | I6: Expenses | J6: Fees, Fines and Charges for Services | K6: Operating Grants and Contributions | L6: Capital Grants and Contributions | M6: Governmental Activities | N6: Business-type Activities | O6: Total | P6: Component Units
A7: Primary Government:
B8: Government Activities:
C9: General government | I9: -38819176 | J9: 13019077 | K9: 2052510 | L9: 268110 | M9: =SUM(I9:L9) -> -23479479 | O9: =SUM(M9:N9) -> -23479479
C10: Public safety | I10: -67334315 | J10: 3196455 | K10: 4721433 | L10: 9974 | M10: =SUM(I10:L10) -> -59406453 | O10: =SUM(M10:N10) -> -59406453
C11: Traffic and transportation | I11: -13107523 | J11: 3393790 | K11: 3063266 | L11: 1403057 | M11: =SUM(I11:L11) -> -5247410 | O11: =SUM(M11:N11) -> -5247410
C12: Streets and drainage | I12: -21108110 | K12: 1811127 | L12: 38533 | M12: =SUM(I12:L12) -> -19258450 | O12: =SUM(M12:N12) -> -19258450
C13: Urban redevelopment and housing | I13: -1736762 | K13: 1355630 | L13: 975805 | M13: =SUM(I13:L13) -> 594673 | O13: =SUM(M13:N13) -> 594673
C14: Culture and recreation | I14: -23687100 | J14: 6028123 | L14: 156577 | M14: =SUM(I14:L14) -> -17502400 | O14: =SUM(M14:N14) -> -17502400
C15: Health and welfare | I15: -1008645 | M15: =SUM(I15:L15) -> -1008645 | O15: =SUM(M15:N15) -> -1008645
C16: Economic opportunity | I16: -329304 | K16: 287734 | M16: =SUM(I16:L16) -> -41570 | O16: =SUM(M16:N16) -> -41570
C17: Economic development and assistance | I17: -1681934 | K17: 1234552 | M17: =SUM(I17:L17) -> -447382 | O17: =SUM(M17:N17) -> -447382
C18: Unallocated depreciation | I18: -17268060 | M18: =SUM(I18:L18) -> -17268060 | O18: =SUM(M18:N18) -> -17268060
C19: Interest on long-term debt | I19: -18701255 | K19: 1193163 | M19: =SUM(I19:L19) -> -17508092 | O19: =SUM(M19:N19) -> -17508092
E21: Total Government Activities | I21: =SUM(I9:I19) -> -204782184 | J21: =SUM(J9:J19) -> 25637445 | K21: =SUM(K9:K19) -> 15719415 | L21: =SUM(L9:L19) -> 2852056 | M21: =SUM(M9:M19) -> -160573268 | O21: =SUM(O9:O19) -> -160573268 | P21: =SUM(P9:P19) -> 0
B23: Business-type Activities:
C24: Electric | I24: -165530389 | J24: 201250850 | L24: 656112 | N24: =SUM(I24:L24) -> 36376573 | O24: =SUM(M24:N24) -> 36376573
C25: Water | I25: -17612665 | J25: 17850270 | N25: =SUM(I25:L25) -> 237605 | O25: =SUM(M25:N25) -> 237605
C26: Sewer | I26: -23127551 | J26: 28579958 | N26: =SUM(I26:L26) -> 5452407 | O26: =SUM(M26:N26) -> 5452407
C27: Communications system | I27: -35766464 | J27: 32150333 | N27: =SUM(I27:L27) -> -3616131 | O27: =SUM(M27:N27) -> -3616131
C28: Coal-fired electric plant | I28: -57398097 | J28: 58881514 | N28: =SUM(I28:L28) -> 1483417 | O28: =SUM(M28:N28) -> 1483417
C29: Solid waste collection services | I29: -13493413 | J29: 14328535 | L29: 35370 | N29: =SUM(I29:L29) -> 870492 | O29: =SUM(M29:N29) -> 870492
C30: Animal shelter control program | I30: -1308140 | J30: 395927 | L30: 9776 | N30: =SUM(I30:L30) -> -902437 | O30: =SUM(M30:N30) -> -902437
C31: CNG Service Station | I31: -187621 | J31: 290042 | N31: =SUM(I31:L31) -> 102421 | O31: =SUM(M31:N31) -> 102421
E33: Total Business-type Activities | I33: =SUM(I24:I31) -> -314424340 | J33: =SUM(J24:J31) -> 353727429 | K33: =SUM(K24:K31) -> 0 | L33: =SUM(L24:L31) -> 701258 | M33: =SUM(M24:M31) -> 0 | N33: =SUM(N24:N31) -> 40004347 | O33: =SUM(O24:O31) -> 40004347 | P33: =SUM(P17:P31) -> 0
E35: Total primary government | I35: =I33+I21 -> -519206524 | J35: =J33+J21 -> 379364874 | K35: =SUM(K21+K33) -> 15719415 | L35: =SUM(L21+L33) -> 3553314 | M35: =M33+M21 -> -160573268 | N35: =N33+N21 -> 40004347 | O35: =O33+O21 -> -120568921 | P35: =SUM(P20:P33) -> 0
D37: Component units
E38: Cajundome Commission | I38: -11192470 | J38: 8560986 | K38: 500000 | L38: 100000 | P38: =SUM(I38:L38) -> -2031484
E39: Lafayette Regional Airport | I39: -12326440 | J39: 8810894 | K39: 102510 | L39: 10401085 | P39: =SUM(I39:L39) -> 6988049
E40: Lafayette Public Trust Financing Authority | I40: -2314105 | J40: 160218 | P40: =SUM(I40:L40) -> -2153887
E41: Nonmakor component units | I41: -19492804 | J41: 13459454 | K41: 3798703 | L41: 158617 | P41: =SUM(I41:L41) -> -2076030
I42: =SUM(I38:I41) -> -45325819 | J42: =SUM(J38:J41) -> 30991552 | K42: =SUM(K38:K41) -> 4401213 | L42: =SUM(L38:L41) -> 10659702 | M42: =SUM(M38:M41) -> 0 | N42: =SUM(N38:N41) -> 0 | O42: =SUM(O38:O41) -> 0 | P42: =SUM(P38:P41) -> 726648
G45: General Revenues:
H46: Taxes:
I47: Property | M47: 70488175 | O47: =SUM(M47:N47) -> 70488175 | P47: 4908494
I48: Sales | M48: 90230904 | O48: =SUM(M48:N48) -> 90230904
I49: Occupational licenses | M49: 2976869 | O49: =SUM(M49:N49) -> 2976869
I50: Insurance premium | M50: 898582 | O50: =SUM(M50:N50) -> 898582
I51: Franchise fees | M51: 2910746 | O51: =SUM(M51:N51) -> 2910746
I52: Interest and penalties - delinquent taxes | M52: 103409 | O52: =SUM(M52:N52) -> 103409
I53: Other | M53: 75925 | O53: =SUM(M53:N53) -> 75925 | P53: 2627779
H54: Grants and contributions not restricted to specific programs | M54: 2051924 | O54: =SUM(M54:N54) -> 2051924 | P54: 47660
H55: Investment earnings | M55: 656131 | N55: 1416223 | O55: =SUM(M55:N55) -> 2072354 | P55: 514109
H56: Gain (loss) on sale of capital assets | M56: -705012 | N56: -465839 | O56: =SUM(M56:N56) -> -1170851 | P56: 7604
H57: Miscellaneous | M57: 2050007 | N57: 2565611 | O57: =SUM(M57:N57) -> 4615618 | P57: 1060656
H58: Transfers | M58: 20960736 | N58: -20960736 | O58: =SUM(M58:N58) -> 0
H60: Total General Revenues and Transfers | M60: =SUM(M47:M58) -> 192698396 | N60: =SUM(N47:N58) -> -17444741 | O60: =SUM(O47:O58) -> 175253655 | P60: =SUM(P47:P57) -> 9166302
H62: Change in Net Position | M62: =M60+M35+M42 -> 32125128 | N62: =N60+N35+N42 -> 22559606 | O62: =O60+O35+O42 -> 54684734 | P62: =P60+P35+P42 -> 9892950
E64: Net Assets- Beginning of Year | M64: 442405638 | N64: 500421844 | O64: 942827482 | P64: 190899921
E66: Net Assets- End of Year | M66: =SUM(M62,M64) -> 474530766 | N66: =N64+N62 -> 522981450 | O66: =O64+O62 -> 997512216 | P66: =P64+P62 -> 200792871

Sheet Lafourche
J1: Lafourche County 2014 Statement of Activities
J2: Issued: December 31, 2014
J5: PRIMARY GOVERNMENT | P5: Component Units
A6: FUNCTIONS/PROGRAMS | I6: Expenses | J6: Charges for Services | K6: Operating Grants and Contributions | L6: Capital Grants and Contributions | M6: Net (Expense) Revenue Governmental Activities | N6: Business-type Activities | O6: Total | P6: Total
B8: Government Activities:
C9: General government | I9: -10853554 | J9: 3939011 | K9: 1790887 | L9: 5692636 | M9: =SUM(I9:L9) -> 568980 | O9: =SUM(M9:N9) -> 568980
C10: Public safety | I10: -1239313 | J10: 13326 | K10: 54171 | M10: =SUM(I10:L10) -> -1171816 | O10: =SUM(M10:N10) -> -1171816
C11: Public works | I11: -29576012 | J11: 44100 | K11: 2441392 | L11: 5469414 | M11: =SUM(I11:L11) -> -21621106 | O11: =SUM(M11:N11) -> -21621106
C12: Health and community services | I12: -9085460 | J12: 52114 | K12: 4423306 | M12: =SUM(I12:L12) -> -4610040 | O12: =SUM(M12:N12) -> -4610040
C13: Culture and recreation | I13: -6889308 | J13: 149046 | K13: 904619 | M13: =SUM(I13:L13) -> -5835643 | O13: =SUM(M13:N13) -> -5835643
C14: Interest and fiscal charges | I14: -1758898 | M14: =SUM(I14:L14) -> -1758898 | O14: =SUM(M14:N14) -> -1758898
E16: Total Government Activities | I16: =SUM(I9:I14) -> -59402545 | J16: =SUM(J9:J14) -> 4197597 | K16: =SUM(K9:K14) -> 9614375 | L16: =SUM(L9:L14) -> 11162050 | M16: =SUM(M9:M14) -> -34428523 | O16: =SUM(O9:O14) -> -34428523 | P16: =SUM(P9:P14) -> 0
B18: Business-type Activities:
C19: Sewer | I19: -536012 | J19: 213085 | N19: -322927 | O19: =SUM(M19:N19) -> -322927
E21: Total primary government | I21: =SUM(I16+I19) -> -59938557 | J21: =J19+J16 -> 4410682 | K21: =K19+K16 -> 9614375 | L21: =L19+L16 -> 11162050 | M21: =M19+M16 -> -34428523 | N21: =N19+N16 -> -322927 | O21: =SUM(O16+O19) -> -34751450 | P21: =SUM(P15:P19) -> 0
E23: Component units | I23: -210642245 | J23: 205696771 | K23: 324381 | L23: 2390055 | M23: 0 | N23: 0 | O23: 0 | P23: =SUM(I23:L23) -> -2231038
G25: General Revenues:
H26: Taxes:
I27: Ad valorem | M27: 25399615 | O27: =SUM(M27:N27) -> 25399615 | P27: 16805929
I28: Sales | M28: 16623122 | O28: =SUM(M28:N28) -> 16623122 | P28: 830421
I29: Other | M29: 3022642 | O29: =SUM(M29:N29) -> 3022642
H30: Royalty revenue | M30: 5742812 | O30: =SUM(M30:N30) -> 5742812
H31: Interest and investment earnings | M31: 8902 | O31: =SUM(M31:N31) -> 8902 | P31: 354394
H32: Grants not restricted to specific programs | M32: 478115 | O32: =SUM(M32:N32) -> 478115 | P32: 8723313
H33: Other | M33: 647330 | O33: =SUM(M33:N33) -> 647330 | P33: 1940195
H35: Total General Revenues | M35: =SUM(M27:M33) -> 51922538 | N35: =SUM(N27:N33) -> 0 | O35: =SUM(O27:O33) -> 51922538 | P35: =SUM(P27:P33) -> 28654252
H37: Change in Net Assets | M37: =M35+M16 -> 17494015 | N37: =N35+N19 -> -322927 | O37: =O35+O21 -> 17171088 | P37: =P35+P23 -> 26423214
E39: Net Assets- Beginning of Year | M39: 104641474 | N39: 2864360 | O39: =SUM(M39:N39) -> 107505834 | P39: 454634255
E41: Net Assets- End of Year | M41: =M39+M37 -> 122135489 | N41: =N39+N37 -> 2541433 | O41: =O39+O37 -> 124676922 | P41: =P39+P37 -> 481057469

Sheet LaSalle
J1: LaSalle County 2014 Statement of Activities
J2: Issued: December 31, 2014
J5: PROGRAM REVENUES
A6: FUNCTIONS | I6: Expenses | J6: Charges for Services | K6: Operating Grants and Contributions | L6: Capital Grants and Contributions | M6: NET (EXPENSE) REVENUE AND CHANGES IN NET POSITION
A7: Primary Government:
B8: Government Activities:
C9: General government | I9: -1752222 | J9: 163215 | K9: 84504 | M9: =SUM(I9:L9) -> -1504503
C10: Public safety | I10: -551593 | J10: 2081 | M10: =SUM(I10:L10) -> -549512
C11: Public works | I11: -2720925 | K11: 423139 | L11: 504395 | M11: =SUM(I11:L11) -> -1793391
C12: Health and welfare | I12: -94559 | M12: =SUM(I12:L12) -> -94559
C13: Culture and recreation | I13: -519659 | J13: 10803 | K13: 21875 | M13: =SUM(I13:L13) -> -486981
C14: Economic development and assistance | I14: -1397335 | K14: 861654 | L14: 990764 | M14: =SUM(I14:L14) -> 455083
C15: Intergovernmental | I15: -62144 | M15: =SUM(I15:L15) -> -62144
E17: Total Government Activities | I17: =SUM(I9:I15) -> -7098437 | J17: =SUM(J9:J14) -> 176099 | K17: =SUM(K9:K14) -> 1391172 | L17: =SUM(L9:L14) -> 1495159 | M17: =SUM(M9:M15) -> -4036007
G19: General Revenues:
H20: Taxes:
I21: Ad valorem taxes | M21: 3445076
I22: State revenue sharing | M22: 58879
I23: Other taxes, penalties, and interest | M23: 6105
H24: Grants and contributions not restricted to specific programs | M24: 1354229
H25: Licenses and permits | M25: 76857
H26: Unrestricted investment earnings | M26: 61734
H27: Other | M27: 135
H29: Total General Revenues | M29: =SUM(M21:M27) -> 5003015
H31: Change in Net Position | M31: =SUM(M17,M29) -> 967008
E33: Net Assets- Beginning of Year | M33: 10927506
E35: Net Assets- End of Year | M35: =SUM(M31,M33) -> 11894514

Sheet Lincoln
J1: Lincoln County 2014 Statement of Activities
J2: Issued: December 31, 2014
J5: PROGRAM REVENUES
A6: FUNCTIONS/PROGRAM ACTIVITIES | I6: Expenses | J6: Charges for Services | K6: Operating Grants and Contributions | L6: Capital Grants and Contributions | M6: NET (EXPENSE) REVENUE AND CHANGES IN NET POSITION
B7: Government Activities:
C8: General government | I8: -3283516 | J8: 18768 | M8: =SUM(I8:L8) -> -3264748
C9: Public safety | I9: -325673 | J9: 284167 | K9: 37236 | L9: 89594 | M9: =SUM(I9:L9) -> 85324
C10: Public works | I10: -8054433 | J10: 404071 | K10: 518922 | L10: 231878 | M10: =SUM(I10:L10) -> -6899562
C11: Health and welfare | I11: -563356 | K11: 492854 | M11: =SUM(I11:L11) -> -70502
C12: Culture and Recreation | I12: -2884898 | J12: 422227 | M12: =SUM(I12:L12) -> -2462671
C13: Economic development | I13: -24798 | M13: =SUM(I13:L13) -> -24798
C14: Interest on long-term debt | I14: -127851 | M14: =SUM(I14:L14) -> -127851
E16: Total Government Activities | I16: =SUM(I8:I14) -> -15264525 | J16: =SUM(J8:J13) -> 1129233 | K16: =SUM(K8:K13) -> 1049012 | L16: =SUM(L8:L13) -> 321472 | M16: =SUM(M8:M14) -> -12764808
G18: General Revenues:
G19: Taxes:
H20: Property taxes | M20: 7067277
H21: Sales taxes | M21: 4507092
H22: Other taxes | M22: 277798
H23: Severance taxes | M23: 1175000
G24: Intergovernmental revenues | M24: 494886
G25: Fire insurance rebate | M25: 185230
G26: Other revenues | M26: 18223
G27: Rents and royalties | M27: 205034
G28: Sale of Assets | M28: 181000
G29: Transfers to other funds | M29: -472051
G30: Interest earned | M30: 124906
H32: Total General Revenues | M32: =SUM(M20:M30) -> 13764395
H34: Change in Net Position | M34: =SUM(M16,M32) -> 999587
E36: Net Assets- Beginning (Restated) | M36: 55163137
E38: Net Assets- Ending | M38: =SUM(M34,M36) -> 56162724

Sheet Livingston
J1: Livingston County 2014 Statement of Activities
J2: Issued: December 31, 2014
M4: NET (EXPENSE) REVENUE AND CHANGES IN NET ASSETS
J5: PROGRAM REVENUES | M5: PRIMARY GOVERNMENT
A6: FUNCTIONS/PROGRAMS | I6: Expenses | J6: Charges for Services | K6: Operating Grants and Contributions | L6: Capital Grants and Contributions | M6: Governmental Activities | N6: Business-type Activities | O6: Total
B7: Government Activities:
C8: General government: | I8: -6117497 | J8: 1737007 | K8: 320864 | L8: 1378927 | M8: -2680699 | O8: =M8 -> -2680699
C9: Public safety | I9: -5072256 | J9: 1219589 | K9: 487053 | L9: 69786 | M9: -3295828 | N9: - | O9: =M9 -> -3295828
C10: Public works | I10: -16464589 | J10: 23175 | K10: 1606928 | L10: 1676743 | M10: -13157743 | N10: - | O10: =M10 -> -13157743
C11: Health and welfare | I11: -1643186 | J11: 35200 | K11: 318289 | L11: - | M11: -1289697 | N11: - | O11: =M11 -> -1289697
C12: Culture and recreation | I12: -648023 | J12: - | K12: - | L12: - | M12: =SUM(I12:L12) -> -648023 | N12: - | O12: =M12 -> -648023
C13: Economic development | I13: -27000 | J13: - | K13: - | L13: - | M13: -27000 | N13: - | O13: =M13 -> -27000
C14: Debt service interest and fees | I14: -4658876 | J14: - | K14: 1316052 | L14: - | M14: -3342824 | N14: - | O14: =M14 -> -3342824
E16: Total Government Activities | I16: =SUM(I8:I14) -> -34631427 | J16: =SUM(J8:J14) -> 3014971 | K16: =SUM(K8:K14) -> 4049186 | L16: =SUM(L8:L14) -> 3125456 | M16: =SUM(M8:M14) -> -24441814 | N16: =SUM(N8:N14) -> 0 | O16: =SUM(O8:O14) -> -24441814
B18: Business-type Activities:
C19: Utilities-Water and sewer | I19: -883938 | J19: 168749 | K19: - | L19: 100000 | M19: - | N19: -615189 | O19: =SUM(M19:N19) -> -615189
E21: Total business-type Activities | I21: =SUM(I19:I19) -> -883938 | J21: =SUM(J19:J19) -> 168749 | K21: =SUM(K19:K19) -> 0 | L21: =SUM(L19:L19) -> 100000 | M21: =SUM(M19:M19) -> 0 | N21: =SUM(N19:N19) -> -615189 | O21: =SUM(O19:O19) -> -615189
E23: Total | I23: =I21+I16 -> -35515365 | J23: =J21+J16 -> 3183720 | K23: =K21+K16 -> 4049186 | L23: =L21+L16 -> 3225456 | M23: =M21+M16 -> -24441814 | N23: =N21+N16 -> -615189 | O23: =O21+O16 -> -25057003
G25: General Revenues:
H26: Taxes:
I27: Ad Valorem Taxes | M27: 6399517 | N27: - | O27: =SUM(M27:N27) -> 6399517
I28: Sales taxes | M28: 15374488 | N28: - | O28: =SUM(M28:N28) -> 15374488
I29: Franchise taxes | M29: 1429770 | O29: =SUM(M29:N29) -> 1429770
I30: Occupational | M30: 944370 | O30: =SUM(M30:N30) -> 944370
H31: Royalties | M31: 1753773 | O31: =SUM(M31:N31) -> 1753773
H32: Miscellaneous | M32: 2080149 | O32: =SUM(M32:N32) -> 2080149
H33: Use of money and property | M33: 54818 | N33: 328 | O33: =SUM(M33:N33) -> 55146
H34: Transfers | M34: -450000 | N34: 450000 | O34: -
H36: Total General Revenues and Transfers | M36: =SUM(M27:M34) -> 27586885 | N36: =SUM(N27:N34) -> 450328 | O36: =SUM(O27:O34) -> 28037213
H38: Change in Net Postition | M38: 3145071 | N38: -164861 | O38: 2980210
E40: Net Assets- Beginning of Year | M40: 88188517 | N40: 5875211 | O40: 94063728
E42: Net Assets- End of Year | M42: =SUM(M38,M40) -> 91333588 | N42: =N40+N38 -> 5710350 | O42: =O40+O38 -> 97043938

Sheet Madison
J1: Madison County 2014 Statement of Activities
J2: Issued: December 31, 2014
M3: Primary government
M4: Governmental activities
J5: PROGRAM REVENUES | M5: Net (expense)
A6: FUNCTIONS/PROGRAMS | I6: Expenses | J6: Charges for Services | K6: Operating Grants and Contributions | L6: Capital Grants and Contributions | M6: Revenues and changes in Net Assets
A7: Primary Government: Governmental Activities
C8: General government
D9: Legislative | I9: -130553 | K9: - | M9: =SUM(I9+J9) -> -130553
D10: Judicial | I10: -885420 | J10: 333349 | K10: - | M10: =SUM(I10:L10) -> -552071
D11: Elections | I11: -36954 | J11: - | K11: - | L11: - | M11: =SUM(I11:L11) -> -36954
D12: Finance and administrative | I12: -424204 | J12: - | K12: 7262 | L12: - | M12: =SUM(I12:L12) -> -416942
D13: Other general administrative | I13: -46408 | J13: 1565 | K13: - | L13: - | M13: =SUM(I13:L13) -> -44843
C14: Public safety | I14: -1173857 | J14: 41546 | K14: 19973 | L14: 41133 | M14: =SUM(I14:L14) -> -1071205
C15: Public works | I15: -3435814 | J15: 623808 | K15: 282155 | L15: 97500 | M15: =SUM(I15:L15) -> -2432351
C16: Health and welfare | I16: -332568 | J16: - | K16: 36235 | L16: 188007 | M16: =SUM(I16:L16) -> -108326
C17: Culture and recreation | I17: -514423 | J17: 473 | K17: 32682 | L17: - | M17: =SUM(I17:L17) -> -481268
C18: Economic development and assistance | I18: -53345 | J18: - | K18: - | L18: - | M18: =SUM(I18:L18) -> -53345
C19: Transportation | I19: -52623 | J19: - | K19: 16340 | L19: - | M19: =SUM(I19:L19) -> -36283
C20: Miscellaneous | I20: -2692 | J20: - | K20: - | L20: - | M20: =SUM(I20:L20) -> -2692
C21: Interest on long-term debt | I21: -2759 | J21: - | K21: - | L21: - | M21: =SUM(I21:L21) -> -2759
E23: Total Government Activities | I23: =SUM(I9:I21) -> -7091620 | J23: =SUM(J8:J19) -> 1000741 | K23: =SUM(K8:K19) -> 394647 | L23: =SUM(L8:L19) -> 326640 | M23: =SUM(M9:M21) -> -5369592
G25: General Revenues:
H26: Taxes:
I27: Property taxes, levied for general purposes | M27: 5252773
I28: Other taxes and penalties | M28: 131639
I29: State revenue sharing | M29: 95978
I30: Severance tax | M30: 40448
I31: Video poker | M31: 287064
I32: Licenses and permits | M32: 200795
I33: Interest and invcestment earnings | M33: 38954
I34: Miscellaneous | M34: 247053
H36: Total General Revenues | M36: =SUM(M27:M34) -> 6294704
H38: Change in Net Assets | M38: =SUM(M23,M36) -> 925112
E41: Net position- Beginning | M41: 20476016
E43: Net position- Ending | M43: 21401128

Sheet Morehouse
F1: Morehouse Parish 2013 Statement of Activities
F2: Issued: December 31, 2014
H5: PROGRAM REVENUES
A6: FUNCTIONS/PROGRAMS | G6: Expenses | H6: Charges for Services | I6: Operating Grants and Contributions | J6: Capital Grants and Contributions | K6: NET (EXPENSE) REVENUE AND CHANGES IN NET ASSETS
A7: Current:
B8: General government
C9: Legislative | G9: -80788 | K9: =SUM(G9:J9) -> -80788
C10: Judicial | G10: -762402 | H10: 173972 | I10: 192098 | K10: =SUM(G10:J10) -> -396332
C11: Elections | G11: -51542 | K11: =SUM(G11:J11) -> -51542
C12: Finance and administrative | G12: -129825 | H12: 241885 | K12: =SUM(G12:J12) -> 112060
C13: Other | G13: -60557 | K13: =SUM(G13:J13) -> -60557
B14: Public safety | G14: -646127 | K14: =SUM(G14:J14) -> -646127
B15: Public works | G15: -3053752 | H15: 109794 | I15: 60000 | J15: 95043 | K15: =SUM(G15:J15) -> -2788915
B16: Building maintenance | G16: -331031 | H16: 9100 | K16: =SUM(G16:J16) -> -321931
B17: Health and welfare | G17: -338186 | K17: =SUM(G17:J17) -> -338186
B18: Economic development and assistance | G18: -1155027 | K18: =SUM(G18:J18) -> -1155027
D20: Total Government Activities | G20: =SUM(G9:G18) -> -6609237 | H20: =SUM(H9:H18) -> 534751 | I20: =SUM(I9:I18) -> 252098 | J20: =SUM(J8:J18) -> 95043 | K20: =SUM(K8:K18) -> -5727345
E22: General Revenues:
F23: Taxes | K23: 3928605
F24: Intergovernmental | K24: 1793050
F25: Unrestricted investment earnings and miscellaneous | K25: 47801
F26: Special item:
G27: Gain (loss) on sale of capital assets | K27: 39339
F29: Total General Revenues and Special Item | K29: =SUM(K23:K27) -> 5808795
F31: Changes in Net position | K31: =K20+K29 -> 81450
D33: Net position- beginning of year | K33: 15871012
F35: Prior period adjustment | K35: 13314
D37: Net position- ending | K37: =SUM(K31:K35) -> 15965776

Sheet Natchitoches (2)
I1: Natchitoches 2014 Statement of Activities
I2: Issued: December 31, 2014
I5: PROGRAM REVENUES | L5: NET (EXPENSES) REVENUES AND CHANGES IN NET POSITION
A6: Program Activities | H6: Expenses | I6: Charges for Services | J6: Operating Grants and Contributions | K6: Capital Grants and Contributions | L6: Governmental Activities | M6: Total
B7: Government Activities:
C8: General government: | H8: -1644326 | I8: 4 | J8: 479189 | K8: - | L8: =SUM(H8:K8) -> -1165133 | M8: =L8 -> -1165133
C9: Public safety | H9: -2155560 | I9: 104295 | J9: 425337 | K9: - | L9: =SUM(H9:K9) -> -1625928 | M9: =L9 -> -1625928
C10: Public works | H10: -4689987 | I10: 39938 | J10: 867840 | K10: 168425 | L10: =SUM(H10:K10) -> -3613784 | M10: =L10 -> -3613784
C11: Health and welfare | H11: -4867676 | I11: - | J11: 2813454 | K11: - | L11: =SUM(H11:K11) -> -2054222 | M11: =L11 -> -2054222
C12: Recreation and culture | H12: -1902369 | I12: 22695 | J12: 25845 | K12: - | L12: =SUM(H12:K12) -> -1853829 | M12: =L12 -> -1853829
C13: Economic development | H13: -16405 | J13: 8437 | L13: =SUM(H13:K13) -> -7968 | M13: =L13 -> -7968
E15: Total Governmental Activities | H15: =SUM(H8:H13) -> -15276323 | I15: =SUM(I8:I13) -> 166932 | J15: =SUM(J8:J13) -> 4620102 | K15: =SUM(K8:K13) -> 168425 | L15: =SUM(L8:L13) -> -10320864 | M15: =SUM(M8:M13) -> -10320864
F17: General Revenues:
G18: Taxes:
H19: Ad Valorem | L19: 6071458 | M19: =SUM(L19:L19) -> 6071458
H20: Sales & Use | L20: 2268292 | M20: =SUM(L20:L20) -> 2268292
G21: Licenses & Permits | L21: 396358 | M21: =SUM(L21:L21) -> 396358
G22: Interest | L22: 13789 | M22: =SUM(L22:L22) -> 13789
G23: Miscellaneous | L23: 1387422 | M23: =SUM(L23:L23) -> 1387422
G25: Total General Revenues & Transfers | L25: =SUM(L19:L23) -> 10137319 | M25: =SUM(M19:M23) -> 10137319
G27: Change in Net Position | L27: =L25+L15 -> -183545 | M27: =M25+M15 -> -183545
E29: Net Assets at Beginning of Year | L29: 57279035 | M29: =SUM(L29:L29) -> 57279035
E31: Net Assets at End of Year | L31: =SUM(L27,L29) -> 57095490 | M31: =M29+M27 -> 57095490

Sheet Natchitoches
I1: Natchitoches 2014 Statement of Activities
I2: Issued: May 31, 2014
I5: PROGRAM REVENUES | L5: NET (EXPENSES) REVENUES AND CHANGES IN NET POSITION
A6: Program Activities | H6: Expenses | I6: Fees, Fines and Charges for Services | J6: Operating Grants and Contributions | K6: Capital Grants and Contributions | L6: Governmental Activities | M6: Business-type Activities | N6: Total
B7: Government Activities:
C8: General government: | H8: -4471910 | I8: 85 | J8: 391756 | K8: - | L8: -4080069 | M8: - | N8: =L8 -> -4080069
C9: Public safety | H9: -8764537 | I9: 200788 | J9: 715741 | K9: - | L9: -7848008 | M9: - | N9: =L9 -> -7848008
C10: Streets and Sanitation | H10: -4017771 | I10: 2003567 | J10: - | K10: 42348 | L10: -1971856 | M10: - | N10: =L10 -> -1971856
C11: Water, Sewer & Utilities | H11: -6200834 | I11: 573515 | J11: - | K11: 93174 | L11: -5534145 | M11: - | N11: =L11 -> -5534145
C12: Economic development | H12: -2133419 | I12: 631070 | J12: 109611 | K12: 1544263 | L12: 151525 | M12: - | N12: =L12 -> 151525
C13: Health and welfare | H13: -210170 | I13: - | J13: - | K13: - | L13: -210170 | M13: - | N13: =L13 -> -210170
C14: Recreation and culture | H14: -1026623 | I14: 48094 | J14: 228852 | K14: - | L14: -749677 | M14: - | N14: =L14 -> -749677
C15: Interest on long-term debt | H15: -191048 | I15: - | J15: - | K15: - | L15: -191048 | M15: - | N15: =L15 -> -191048
N16: =L16 -> 0
E17: Total Government Activities | H17: =SUM(H8:H15) -> -27016312 | I17: =SUM(I8:I15) -> 3457119 | J17: =SUM(J8:J15) -> 1445960 | K17: =SUM(K8:K15) -> 1679785 | L17: =SUM(L8:L15) -> -20433448 | M17: =SUM(M8:M15) -> 0 | N17: =SUM(N8:N15) -> -20433448
B18: Business-type Activities:
C19: Utilities Administration | H19: -1259857 | I19: 1062376 | J19: - | K19: - | L19: - | M19: -197481 | N19: =SUM(L19:M19) -> -197481
C20: Electric | H20: -23153861 | I20: 28060846 | J20: - | K20: - | L20: - | M20: 4906986 | N20: =SUM(L20:M20) -> 4906986
C21: Water | H21: -3289191 | I21: 3375649 | J21: - | K21: 5725705 | L21: - | M21: 5812163 | N21: =SUM(L21:M21) -> 5812163
C22: Sewer | H22: -2169957 | I22: 1441891 | J22: - | K22: - | L22: - | M22: -728067 | N22: =SUM(L22:M22) -> -728067
C23: Information Technology | H23: -274670 | I23: - | J23: - | K23: - | L23: - | M23: -274670 | N23: =SUM(L23:M23) -> -274670
C24: Interest on Long-term Debt | H24: -94504 | I24: - | J24: - | K24: - | L24: - | M24: -94504 | N24: =SUM(L24:M24) -> -94504
E26: Total business-type Activities | H26: =SUM(H19:H24) -> -30242040 | I26: =SUM(I19:I24) -> 33940762 | J26: =SUM(J19:J24) -> 0 | K26: =SUM(K19:K24) -> 5725705 | L26: =SUM(L19:L24) -> 0 | M26: =SUM(M19:M24) -> 9424427 | N26: =SUM(N19:N24) -> 9424427
E28: Total government | H28: =H26+H17 -> -57258352 | I28: =I26+I17 -> 37397881 | J28: =J26+J17 -> 1445960 | K28: =K26+K17 -> 7405490 | L28: =L26+L17 -> -20433448 | M28: =M26+M17 -> 9424427 | N28: =N26+N17 -> -11009021
F30: General Revenues:
G31: Taxes:
H32: Ad Valorem | L32: 2041199 | M32: - | N32: =SUM(L32:M32) -> 2041199
H33: Sales & Use | L33: 9522790 | M33: - | N33: =SUM(L33:M33) -> 9522790
H34: Franchise | L34: 415036 | M34: - | N34: =SUM(L34:M34) -> 415036
H35: Video Bingo | L35: 9522790 | M35: - | N35: =SUM(L35:M35) -> 9522790
G36: Licenses & Permits | L36: 804217 | M36: - | N36: =SUM(L36:M36) -> 804217
G37: Interest Income | L37: 299140 | M37: 81563 | N37: =SUM(L37:M37) -> 380703
G38: Gain (Loss) on Sale of Assets | L38: 83 | M38: 12025 | N38: =SUM(L38:M38) -> 12108
G39: Rental Income | L39: 115548 | M39: 123761 | N39: =SUM(L39:M39) -> 239309
G40: Insurance Recoveries | L40: 58550 | M40: 31243 | N40: =SUM(L40:M40) -> 89793
G41: Miscellaneous | L41: 332922 | M41: -7553 | N41: =SUM(L41:M41) -> 325369
G42: Transfers | L42: -1191000 | M42: -5836435 | N42: =SUM(L42:M42) -> -7027435
G44: Total General Revenues & Transfers | L44: =SUM(L32:L42) -> 21921275 | M44: =SUM(M32:M42) -> -5595396 | N44: =SUM(N32:N42) -> 16325879
G46: Change in Net Position | L46: =L44+L28 -> 1487827 | M46: =M44+M28 -> 3829031 | N46: =N44+N28 -> 5316858
E48: Net Assets at Beginning of Year | L48: 57279035 | M48: 66382314 | N48: =SUM(L48:M48) -> 123661349
E50: Net Assets at End of Year | L50: =SUM(L46,L48) -> 58766862 | M50: =M48+M46 -> 70211345 | N50: =N48+N46 -> 128978207

Sheet Ouachita
J1: Ouachita County 2013 Statement of Activities
K2: Issued: December 31, 2014
M3: NET (EXPENSE) REVENUE AND CHANGES IN NET ASSETS
J4: PROGRAM REVENUES | M4: PRIMARY GOVERNMENT
A5: FUNCTIONS/PROGRAMS | I5: Expenses | J5: Charges for Services | K5: Operating Grants and Contributions | L5: Capital Grants and Contributions | M5: Governmental Activities | N5: Business-type Activities | O5: Total
A6: Primary Government:
B7: Government Activities:
C8: General government:
D9: Legislative | I9: -199237 | J9: - | K9: - | L9: - | M9: -199237 | N9: - | O9: =SUM(M9) -> -199237
D10: Judicial | I10: -8168602 | J10: 2777409 | K10: 2307626 | L10: - | M10: -3083567 | N10: - | O10: =SUM(M10) -> -3083567
D11: Elections | I11: -256922 | J11: - | K11: - | L11: - | M11: -256922 | O11: =SUM(M11) -> -256922
D12: Finance and administration | I12: -2252610 | J12: 1659042 | K12: - | L12: - | M12: -593568 | N12: - | O12: =SUM(M12) -> -593568
D13: Other general government | I13: -7343494 | J13: - | K13: - | L13: 3846916 | M13: -3496578 | N13: - | O13: =SUM(M13) -> -3496578
E15: Total General Governement | I15: =SUM(I9:I13) -> -18220865 | J15: =SUM(J9:J13) -> 4436451 | K15: =SUM(K9:K13) -> 2307626 | L15: =SUM(L9:L13) -> 3846916 | M15: =SUM(M9:M13) -> -7629872 | N15: =SUM(N9:N13) -> 0 | O15: =SUM(O9:O13) -> -7629872
C17: Public safety | I17: -33619824 | J17: 4400899 | K17: 989132 | L17: 39139 | M17: -28190654 | N17: - | O17: =SUM(M17) -> -28190654
C18: Public works | I18: -9146458 | J18: 153646 | K18: 158604 | L18: 4581314 | M18: -4252894 | N18: - | O18: =SUM(M18) -> -4252894
C19: Health and welfare | I19: -4752257 | J19: 189225 | K19: 5078 | L19: - | M19: -4557954 | N19: - | O19: =SUM(M19) -> -4557954
C20: Culture and recreation | I20: -7266290 | J20: 231197 | K20: 29065 | L20: - | M20: -7006028 | N20: - | O20: =SUM(M20) -> -7006028
C21: Economic and governmental assistance | I21: -4697501 | J21: 374610 | K21: 4177475 | L21: - | M21: -145416 | N21: - | O21: =SUM(M21) -> -145416
E23: Total Government Activities | I23: =I17+I18+I20+I19+I21+I15 -> -77703195 | J23: =J17+J18+J20+J19+J21+J15 -> 9786028 | K23: =K17+K18+K20+K19+K21+K15 -> 7666980 | L23: =SUM(L17+L18+L13) -> 8467369 | M23: =M17+M18+M20+M19+M21+M15 -> -51782818 | N23: =SUM(N15) -> 0 | O23: =O17+O18+O20+O19+O21+O15 -> -51782818
B25: Business-type Activities:
C26: Sewer | I26: -423201 | J26: 299547 | L26: 166727 | N26: 43073 | O26: =SUM(M26:N26) -> 43073
E28: Total business-type Activities | I28: =SUM(I26) -> -423201 | J28: =SUM(J26) -> 299547 | K28: 0 | L28: =SUM(L26) -> 166727 | M28: =SUM(M26) -> 0 | N28: =SUM(N26) -> 43073 | O28: =SUM(O26) -> 43073
E30: Total primary government | I30: =SUM(I23+I28) -> -78126396 | J30: =SUM(J23+J28) -> 10085575 | K30: =SUM(K23+K28) -> 7666980 | L30: =SUM(L23+L28) -> 8634096 | M30: =SUM(M23+M28) -> -51782818 | N30: =SUM(N23+N28) -> 43073 | O30: =SUM(O23+O28) -> -51739745
G32: General Revenues:
G33: Taxes
H34: Ad valorem taxes levied for:
I35: General purposes | M35: 3104457 | O35: =SUM(M35:N35) -> 3104457
I36: Special revenue purposes | M36: 31043296 | O36: =SUM(M36:N36) -> 31043296
H37: Sales taxes levied for:
I38: Special revenue purposes | M38: 14255181 | O38: =SUM(M38:N38) -> 14255181
H39: Other taxes | M39: 3412682 | O39: =SUM(M39:N39) -> 3412682
H40: Grants and contributions not restricted to specific programs | M40: 921047 | O40: =SUM(M40:N40) -> 921047
H41: Licenses and permits | M41: 1188520 | O41: =SUM(M41:N41) -> 1188520
H42: Assessments | M42: 116898 | O42: =SUM(M42:N42) -> 116898
H43: Insurance premiums | M43: 1472023 | O43: =SUM(M43:N43) -> 1472023
H44: Interest and investment earnings | M44: 73009 | N44: 34 | O44: =SUM(M44:N44) -> 73043
H45: Rents and royalties | M45: 136996 | O45: =SUM(M45:N45) -> 136996
H46: Gain on disposals of assets (net) | M46: 177221 | O46: =SUM(M46:N46) -> 177221
H47: Miscellaneous | M47: 1594278 | O47: =SUM(M47:N47) -> 1594278
H49: Total General Revenues | M49: =SUM(M35:M47) -> 57495608 | N49: =SUM(N35:N47) -> 34 | O49: =SUM(O35:O47) -> 57495642
H51: Change in Net Position | M51: 5712790 | N51: 43107 | O51: 5755897
E53: Net position- beginning of year | M53: 262035781 | N53: 2193807 | O53: 264229588
E55: Net Assets- End of Year | M55: 267748571 | N55: 2236914 | O55: 269985485

Sheet Pointe Coupee
J1: Pointe Coupee County 2014 Statement of Activities
J2: Issued: December 31, 2014
M3: NET (EXPENSE) REVENUE AND CHANGE IN NET ASSETS
J4: PROGRAM REVENUES | M4: PRIMARY GOVERNMENT | P4: Component Units
A5: FUNCTIONS/PROGRAMS | I5: Expenses | J5: Charges for Services | K5: Operating Grants and Contributions | L5: Capital Grants and Contributions | M5: Governmental Activities | N5: Business-type Activities | O5: Total | P5: Governmental Activities | Q5: Business-type Activities | R5: Total
A6: Primary Government:
B7: Government Activities:
C8: General government | I8: -2813139 | J8: 676103 | K8: 1423232 | M8: =SUM(I8:L8) -> -713804 | O8: =SUM(M8:N8) -> -713804 | R8: =SUM(P8:Q8) -> 0
C9: Public safety | I9: -1016639 | J9: 137983 | K9: 96064 | L9: 1656315 | M9: =SUM(I9:L9) -> 873723 | O9: =SUM(M9:N9) -> 873723 | R9: =SUM(P9:Q9) -> 0
C10: Transportation and development | I10: -2760203 | J10: 2122 | K10: 109949 | M10: -2648132 | O10: =SUM(M10:N10) -> -2648132 | R10: =SUM(P10:Q10) -> 0
C11: Health and welfare | I11: -1819614 | K11: 192429 | M11: =SUM(I11:L11) -> -1627185 | O11: =SUM(M11:N11) -> -1627185 | R11: =SUM(P11:Q11) -> 0
C12: Culture and recreation | I12: -1220452 | J12: 79357 | K12: 146883 | M12: =SUM(I12:L12) -> -994212 | O12: =SUM(M12:N12) -> -994212 | R12: =SUM(P12:Q12) -> 0
C13: Drainage | I13: -1112793 | J13: 276845 | K13: 264927 | L13: 444159 | M13: =SUM(I13:L13) -> -126862 | O13: =SUM(M13:N13) -> -126862 | R13: =SUM(P13:Q13) -> 0
C14: Economic development | I14: -90609 | M14: =SUM(I14:L14) -> -90609 | O14: =SUM(M14:N14) -> -90609 | R14: =SUM(P14:Q14) -> 0
C15: Interest on long-term debt | I15: -245307 | M15: =SUM(I15:L15) -> -245307 | O15: =SUM(M15:N15) -> -245307 | R15: =SUM(P15:Q15) -> 0
R16: =SUM(P16:Q16) -> 0
E17: Total Government Activities | I17: =SUM(I8:I15) -> -11078756 | J17: =SUM(J8:J15) -> 1172410 | K17: =SUM(K8:K15) -> 2233484 | L17: =SUM(L8:L15) -> 2100474 | M17: =SUM(M8:M15) -> -5572388 | O17: =SUM(O8:O15) -> -5572388 | P17: =SUM(P8:P15) -> 0 | Q17: =SUM(Q8:Q15) -> 0 | R17: =SUM(R8:R15) -> 0
B19: Business-type Activities: | R19: =SUM(P19:Q19) -> 0
C20: Gas | I20: -1771986 | J20: 2004518 | N20: =SUM(I20:L20) -> 232532 | O20: =SUM(M20:N20) -> 232532 | R20: =SUM(P20:Q20) -> 0
C21: Water | I21: -77861 | J21: 83171 | N21: =SUM(I21:L21) -> 5310 | O21: =SUM(M21:N21) -> 5310 | R21: =SUM(P21:Q21) -> 0
C22: Solid waste | I22: -1849034 | J22: 1558712 | N22: =SUM(I22:L22) -> -290322 | O22: =SUM(M22:N22) -> -290322 | R22: =SUM(P22:Q22) -> 0
C23: Multi-use center | I23: -205663 | J23: 15487 | K23: 20250 | N23: =SUM(I23:L23) -> -169926 | O23: =SUM(M23:N23) -> -169926 | R23: =SUM(P23:Q23) -> 0
R24: =SUM(P24:Q24) -> 0
E25: Total Business-type Activities | I25: =SUM(I20:I23) -> -3904544 | J25: =SUM(J20:J23) -> 3661888 | K25: =SUM(K20:K23) -> 20250 | L25: =SUM(L20:L23) -> 0 | M25: =SUM(M20:M23) -> 0 | N25: =SUM(N20:N23) -> -222406 | O25: =SUM(O20:O23) -> -222406 | P25: =SUM(P13:P23) -> 0 | Q25: =SUM(Q13:Q23) -> 0 | R25: =SUM(R13:R23) -> 0
E27: Total primary government | I27: =I25+I17 -> -14983300 | J27: =J25+J17 -> 4834298 | K27: =SUM(K17+K25) -> 2253734 | L27: =SUM(L17+L25) -> 2100474 | M27: =M25+M17 -> -5572388 | N27: =N25+N17 -> -222406 | O27: =O25+O17 -> -5794794 | P27: =SUM(P16:P25) -> 0 | Q27: =SUM(Q16:Q25) -> 0 | R27: =SUM(R16:R25) -> 0
A29: Component units:
B30: Governmental activities | I30: -13750874 | J30: 2959667 | K30: 335156 | L30: 286640 | P30: =SUM(I30:L30) -> -10169411 | R30: =SUM(P30:Q30) -> -10169411
B31: Business-type activities | I31: -24273503 | J31: 18875884 | K31: 3217824 | L31: 899274 | Q31: =SUM(I31:L31) -> -1280521 | R31: =SUM(P31:Q31) -> -1280521
E33: Total component units | I33: =SUM(I30:I31) -> -38024377 | J33: =SUM(J30:J31) -> 21835551 | K33: =SUM(K30:K31) -> 3552980 | L33: =SUM(L30:L31) -> 1185914 | M33: =SUM(M30:M31) -> 0 | N33: =SUM(N30:N31) -> 0 | O33: =SUM(O30:O31) -> 0 | P33: =SUM(P30:P31) -> -10169411 | ... R33: =SUM(R30:R31) -> -11449932
G35: General Revenues:
H36: Taxes:
I37: Property | M37: 2910585 | O37: =SUM(M37:N37) -> 2910585 | P37: 9408057 | Q37: 218446 | R37: =SUM(P37:Q37) -> 9626503
I38: Sales | M38: 3273771 | N38: 689215 | O38: =SUM(M38:N38) -> 3962986 | P38: 848418 | Q38: 1888155 | R38: =SUM(P38:Q38) -> 2736573
I39: Franchise | M39: 25521 | O39: =SUM(M39:N39) -> 25521 | R39: =SUM(P39:Q39) -> 0
I40: Other | M40: 21388 | O40: =SUM(M40:N40) -> 21388 | P40: 151841 | Q40: 7417 | R40: =SUM(P40:Q40) -> 159258
H41: Grants and contributions not restricted to specific programs | M41: 83421 | O41: =SUM(M41:N41) -> 83421 | P41: 644596 | Q41: 747149 | R41: =SUM(P41:Q41) -> 1391745
H42: Investment earnings | M42: 6862 | N42: 168 | O42: =SUM(M42:N42) -> 7030 | P42: 45366 | Q42: -457333 | R42: =SUM(P42:Q42) -> -411967
H43: Gain (loss) on sale of capital assets, net | M43: 1453 | O43: =SUM(M43:N43) -> 1453 | P43: 8833 | Q43: 25860 | R43: =SUM(P43:Q43) -> 34693
H44: Transfers (to) from other funds | M44: 537500 | N44: -537500 | O44: =SUM(M44:N44) -> 0 | R44: =SUM(P44:Q44) -> 0
H46: Total General Revenues and transfers | M46: =SUM(M37:M44) -> 6860501 | N46: =SUM(N37:N44) -> 151883 | O46: =SUM(O37:O44) -> 7012384 | P46: =SUM(P37:P44) -> 11107111 | Q46: =SUM(Q37:Q44) -> 2429694 | R46: =SUM(R37:R44) -> 13536805
H48: Change in Net Assets | M48: =M46+M17 -> 1288113 | N48: =N46+N27 -> -70523 | O48: =O46+O27 -> 1217590 | P48: =P46+P33 -> 937700 | Q48: =Q46+Q33 -> 1149173 | R48: =R46+R33 -> 2086873
E50: Net Assets- Beginning of Year, as restated | M50: 13500998 | N50: 2020631 | O50: 15521629 | P50: 27058178 | Q50: 42135396 | R50: 69193574
E52: Net Assets- End of Year | M52: =SUM(M48,M50) -> 14789111 | N52: =N50+N48 -> 1950108 | O52: =O50+O48 -> 16739219 | P52: =P50+P48 -> 27995878 | Q52: =Q50+Q48 -> 43284569 | R52: =R50+R48 -> 71280447

Sheet Rapides
I1: Rapides Parish 2014 Statement of Activities
I2: Issued: December 31, 2014
I3: PROGRAM REVENUES | L3: NET (EXPENSE) REVENUE AND CHANGES IN NET ASSETS
A4: FUNCTIONS/PROGRAMS | H4: Expenses | I4: Charges for Services | J4: Operating Grants and Contributions | K4: Capital Grants and Contributions | L4: 2014 | M4: 2013
A5: Governmental activities:
B6: General government
C7: Legislative | H7: -436191 | L7: =SUM(H7:K7) -> -436191 | M7: -435329
C8: Judicial | H8: -4733288 | I8: 728190 | J8: 150230 | L8: =SUM(H8:K8) -> -3854868 | M8: -2039060
C9: Elections | H9: -280446 | L9: =SUM(H9:K9) -> -280446 | M9: -330382
C10: Finance and administrative | H10: -4882839 | L10: =SUM(H10:K10) -> -4882839 | M10: -3334985
C11: Other | H11: -2316930 | I11: 672200 | L11: =SUM(H11:K11) -> -1644730 | M11: -2053564
B12: Public safety | H12: -9485514 | I12: 2058577 | L12: =SUM(H12:K12) -> -7426937 | M12: -9758227
B13: Public works | H13: -12998476 | J13: 4075535 | K13: 1009261 | L13: =SUM(H13:K13) -> -7913680 | M13: -9924580
B14: Health and welfare | H14: -1516640 | J14: 733769 | L14: =SUM(H14:K14) -> -782871 | M14: -562162
B15: Culture and recreation | H15: -339518 | I15: 132205 | L15: =SUM(H15:K15) -> -207313 | M15: -1626425
B16: Economic development and assistance | H16: -7773687 | K16: 5671184 | L16: =SUM(H16:K16) -> -2102503 | M16: -1706922
B17: Debt service | H17: -882463 | L17: =SUM(H17:K17) -> -882463 | M17: -1097914
D19: Total Government Activities | H19: =SUM(H7:H17) -> -45645992 | I19: =SUM(I7:I17) -> 3591172 | J19: =SUM(J7:J17) -> 4959534 | K19: =SUM(K7:K17) -> 6680445 | L19: =SUM(L7:L17) -> -30414841 | M19: =SUM(M7:M17) -> -32869550
F21: General Revenues:
G22: Taxes:
H23: Property taxes levied for general purposes | L23: 20981914 | M23: 20306057
H24: Sales and use taxes, levied for general purposes | L24: 2241933 | M24: 2149681
H25: Sales and use taxes, levied for public works | L25: 2735358 | M25: 2523515
H26: Other taxes, licenses, and penalties | L26: 594810 | M26: 584773
G27: Licenses and permits | L27: 1156994 | M27: 602475
G28: Federal grant programs - unrestricted | L28: 173076 | M28: 994749
G29: State grant programs - unrestricted | L29: 665032 | M29: 872711
G30: Local grants | L30: 258045
G31: Interest and investment earnings | L31: 125652 | M31: 197709
G32: Miscellaneous | L32: 2655733 | M32: 415614
G34: Total General Revenues | L34: =SUM(L23:L32) -> 31588547 | M34: =SUM(M23:M32) -> 28647284
G36: Change in Net position | L36: =L34+L19 -> 1173706 | M36: =M34+M19 -> -4222266
D38: Net position- beginning of year | L38: 69234646 | M38: 73456911
D40: Net position- end of year | L40: =L38+L36 -> 70408352 | M40: =M38+M36 -> 69234645

Sheet Red River
I1: Red River County 2014 Statement of Activities
I2: Issued: December 31, 2014
I5: PROGRAM REVENUES | K5: CHANGES IN NET POSITION
H6: Expenses | I6: Charges for Services | J6: Operating Grants and Contributions | K6: Governmental Activities | L6: Business-type Activities | M6: Total
A7: Primary Government:
B8: Government Activities:
C9: General government | H9: -1586757 | I9: 161497 | J9: 193365 | K9: -1231895 | M9: =SUM(K9:L9) -> -1231895
C10: Public safety | H10: -1556720 | I10: 325471 | J10: 99519 | K10: -1131730 | M10: =SUM(K10:L10) -> -1131730
C11: Public works | H11: -3232725 | I11: 96411 | J11: 1006528 | K11: -2129786 | M11: =SUM(K11:L11) -> -2129786
C12: Health and welfare | H12: -572268 | J12: 133509 | K12: -438759 | M12: =SUM(K12:L12) -> -438759
C13: Recreation and culture | H13: -351702 | I13: 1379 | J13: 21875 | K13: -328448 | M13: =SUM(K13:L13) -> -328448
D15: Total Government Activities | H15: =SUM(H9:H13) -> -7300172 | I15: =SUM(I9:I13) -> 584758 | J15: =SUM(J9:J13) -> 1454796 | K15: =SUM(K9:K13) -> -5260618 | M15: =SUM(M9:M13) -> -5260618
B17: Business-type Activities:
C18: Sewer | H18: -159840 | I18: 28571 | L18: -131269 | M18: =SUM(K18:L18) -> -131269
D20: Total Business-type Activities | H20: =H18 -> -159840 | I20: =SUM(I18:I18) -> 28571 | J20: =SUM(J18:J18) -> 0 | K20: =SUM(K18:K18) -> 0 | L20: =SUM(L18:L18) -> -131269 | M20: =SUM(M18:M18) -> -131269
D22: Total primary government | H22: =SUM(H15+H20) -> -7460012 | I22: =SUM(I15+I20) -> 613329 | J22: =SUM(J15+J20) -> 1454796 | K22: =SUM(K15+K20) -> -5260618 | L22: =SUM(L15+L20) -> -131269 | M22: =SUM(M15+M20) -> -5391887
F24: General Revenues:
G25: Taxes:
H26: Ad valorem | K26: 3477010 | M26: =SUM(K26:L26) -> 3477010
H27: Sales and use taxes | K27: 2539681 | M27: =SUM(K27:L27) -> 2539681
H28: Severance taxes | K28: 1093840 | M28: =SUM(K28:L28) -> 1093840
H29: Other | K29: 526606 | M29: =SUM(K29:L29) -> 526606
G30: License and permits | K30: 68548 | M30: =SUM(K30:L30) -> 68548
G31: Gaming revenues | K31: 2704 | M31: =SUM(K31:L31) -> 2704
G32: State revenue sharing | K32: 54937 | M32: =SUM(K32:L32) -> 54937
G33: Interest and investment income (losses) | K33: 435499 | M33: =SUM(K33:L33) -> 435499
G34: Miscellaneous | K34: 137111 | M34: =SUM(K34:L34) -> 137111
G35: Transfers (to) from other funds | K35: -115000 | L35: 115000 | M35: =SUM(K35:L35) -> 0
G37: Total General Revenues and transfers | K37: =SUM(K26:K35) -> 8220936 | L37: =SUM(L26:L35) -> 115000 | M37: =SUM(M26:M35) -> 8335936
G39: Change in Net Position | K39: =K37+K15 -> 2960318 | L39: =L37+L20 -> -16269 | M39: =M37+M22 -> 2944049
D41: Net Position- Beginning of Year (restated) | K41: 47422041 | L41: 380619 | M41: 47802660
D43: Net Position- End of Year | K43: =SUM(K39,K41) -> 50382359 | L43: =L41+L39 -> 364350 | M43: =M41+M39 -> 50746709

Sheet Richland
H1: Richland Parish 2014 Statement of Activities
H2: Issued: December 31, 2014
H5: PROGRAM REVENUES
A6: FUNCTIONS/PROGRAMS | G6: Expenses | H6: Charges for Services | I6: Operating Grants and Contributions | J6: Capital Grants and Contributions | K6: NET (EXPENSE) REVENUE AND CHANGES IN NET POSITION
B7: General government
C8: Legislative | G8: -267292 | K8: =SUM(G8:J8) -> -267292
C9: Judicial | G9: -110034 | H9: 29230 | I9: 15869 | K9: =SUM(G9:J9) -> -64935
C10: Elections | G10: -73570 | K10: =SUM(G10:J10) -> -73570
C11: Finance and administrative | G11: -336031 | H11: 152914 | K11: =SUM(G11:J11) -> -183117
C12: Other | G12: -444427 | H12: 15242 | K12: =SUM(G12:J12) -> -429185
B13: Public safety | G13: -325322 | H13: 18339 | I13: 226049 | K13: =SUM(G13:J13) -> -80934
B14: Public works | G14: -5911385 | H14: 19018 | I14: 1598024 | K14: =SUM(G14:J14) -> -4294343
B15: Health and welfare | G15: -289712 | K15: =SUM(G15:J15) -> -289712
B16: Culture and recreation | G16: -818110 | H16: 16624 | K16: =SUM(G16:J16) -> -801486
B17: Economic development and assistance | G17: -217738 | K17: =SUM(G17:J17) -> -217738
D19: Total Government Activities | G19: =SUM(G8:G17) -> -8793621 | H19: =SUM(H8:H17) -> 251367 | I19: =SUM(I8:I17) -> 1839942 | J19: =SUM(J8:J17) -> 0 | K19: =SUM(K8:K17) -> -6702312
E21: General Revenues:
F22: Taxes | K22: 6762999
F23: Intergovernmental | K23: 261639
F24: Unrestricted investment earnings and miscellaneous | K24: 52130
F26: Total General Revenues | K26: =SUM(K22:K24) -> 7076768
F28: Change in Net position | K28: =K26+K19 -> 374456
D30: Net position- beginning | K30: 10123791
D32: Net position- ending | K32: =K30+K28 -> 10498247

Sheet Sabine
H1: Sabine Parish 2014 Statement of Activities
H2: Issued: December 31, 2014
H3: PROGRAM REVENUES | K3: NET (EXPENSE) REVENUE AND CHANGES IN NET ASSETS
A4: FUNCTIONS/PROGRAMS | G4: Expenses | H4: Charges for Services | I4: Operating Grants and Contributions | J4: Capital Grants and Contributions | K4: 2014 | L4: 2013
A5: Governmental activities:
B6: General government
C7: Legislative | G7: -156568 | K7: =SUM(G7:J7) -> -156568 | L7: -127028
C8: Judicial | G8: -484801 | H8: 275518 | K8: =SUM(G8:J8) -> -209283 | L8: -324711
C9: Elections | G9: -23649 | K9: =SUM(G9:J9) -> -23649 | L9: -68164
C10: Finance and administrative | G10: -397032 | K10: =SUM(G10:J10) -> -397032 | L10: -382749
C11: Other | G11: -718404 | K11: =SUM(G11:J11) -> -718404 | L11: -662550
B12: Public safety | G12: -477323 | I12: 57170 | K12: =SUM(G12:J12) -> -420153 | L12: -143796
B13: Public works | G13: -6068819 | H13: 158574 | I13: 346508 | J13: 1045841 | K13: =SUM(G13:J13) -> -4517896 | L13: -7901402
B14: Health and welfare | G14: -193377 | K14: =SUM(G14:J14) -> -193377 | L14: -155557
B15: Economic development and assistance | G15: -25441 | K15: =SUM(G15:J15) -> -25441 | L15: -30591
B16: Debt service | G16: -6775 | K16: =SUM(G16:J16) -> -6775 | L16: -12512
D18: Total Government Activities | G18: =SUM(G7:G16) -> -8552189 | H18: =SUM(H7:H16) -> 434092 | I18: =SUM(I7:I16) -> 403678 | J18: =SUM(J7:J16) -> 1045841 | K18: =SUM(K7:K16) -> -6668578 | L18: =SUM(L7:L16) -> -9809060
E20: General Revenues:
F21: Taxes:
G22: Property taxes, levied for general purposes | K22: 3293654 | L22: 3214227
G23: Sales and use taxes, levied for general purposes | K23: 3397394 | L23: 3587239
F24: State grant programs | K24: 1601887 | L24: 1525642
F25: Interest and investment earnings | K25: 119321 | L25: 185917
F26: Miscellaneous | K26: 201183 | L26: 157299
F28: Total General Revenues and Special Items | K28: =SUM(K22:K26) -> 8613439 | L28: =SUM(L22:L26) -> 8670324
F30: Changes in Net position | K30: =K28+K18 -> 1944861 | L30: =L28+L18 -> -1138736
D32: Net position- beginning of year | K32: 23395424 | L32: 24534161
D34: Net position- end of year | K34: =SUM(K30+K32) -> 25340285 | L34: =L32+L30 -> 23395425

Sheet St. Charles
H1: St. Charles County 2014 Statement of Activities
H2: Issued: December 31, 2014
K4: NET (EXPENSE) REVENUE AND CHANGE IN NET POSITION
H5: PROGRAM REVENUES | K5: PRIMARY GOVERNMENT
A6: FUNCTIONS/PROGRAMS | G6: Expenses | H6: Charges for Services | I6: Operating Grants and Contributions | J6: Capital Grants and Contributions | K6: Governmental Activities | L6: Business-type Activities | M6: Total | N6: Component Units
A7: Primary Government:
B8: Government Activities:
C9: General government | G9: -18278012 | H9: 3529181 | I9: 5194070 | J9: 5192955 | K9: -4361806 | M9: =SUM(K9:L9) -> -4361806
C10: Public safety | G10: -8821956 | I10: 208520 | K10: -8613436 | M10: =SUM(K10:L10) -> -8613436
C11: Public works | G11: -25818325 | H11: 102722 | I11: 850993 | J11: 1873662 | K11: -22990948 | M11: =SUM(K11:L11) -> -22990948
C12: Health and welfare | G12: -5791088 | I12: 93481 | K12: -5697607 | M12: =SUM(K12:L12) -> -5697607
C13: Culture and recreation | G13: -4509617 | H13: 248514 | K13: -4261103 | M13: =SUM(K13:L13) -> -4261103
C14: Economic development and assistance | G14: -1763281 | I14: 944998 | K14: -818283 | M14: =SUM(K14:L14) -> -818283
C15: Interest and other charges on long-term debt | G15: -450422 | K15: =SUM(G15:J15) -> -450422 | M15: =SUM(K15:L15) -> -450422
C16: Transfers - capital contributions | J16: 36607 | K16: =SUM(G16:J16) -> 36607 | M16: =SUM(K16:L16) -> 36607
D18: Total Government Activities | G18: =SUM(G9:G16) -> -65432701 | H18: =SUM(H9:H16) -> 3880417 | I18: =SUM(I9:I16) -> 7292062 | J18: =SUM(J9:J16) -> 7103224 | K18: =SUM(K9:K16) -> -47156998 | M18: =SUM(M9:M16) -> -47156998 | N18: =SUM(N9:N15) -> 0
B20: Business-type Activities:
C21: Waterworks utility system | G21: -12003522 | H21: 11174372 | I21: 79394 | L21: -749756 | M21: =SUM(K21:L21) -> -749756
C22: Wastewater utility system | G22: -11543076 | H22: 8815790 | J22: 1248414 | L22: -1478872 | M22: =SUM(K22:L22) -> -1478872
C23: Solid waste collection and disposal | G23: -3713140 | H23: 3583537 | L23: -129603 | M23: =SUM(K23:L23) -> -129603
D25: Total Business-type Activities | G25: =SUM(G21:G23) -> -27259738 | H25: =SUM(H21:H23) -> 23573699 | I25: =SUM(I21:I23) -> 79394 | J25: =SUM(J21:J23) -> 1248414 | K25: =SUM(K21:K23) -> 0 | L25: =SUM(L21:L23) -> -2358231 | M25: =SUM(M21:M23) -> -2358231 | N25: =SUM(N14:N23) -> 0
D27: Total primary government | G27: =G25+G18 -> -92692439 | H27: =H25+H18 -> 27454116 | I27: =SUM(I18+I25) -> 7371456 | J27: =SUM(J18+J25) -> 8351638 | K27: =K25+K18 -> -47156998 | L27: =L25+L18 -> -2358231 | M27: =M25+M18 -> -49515229 | N27: =SUM(N17:N25) -> 0
A29: Component units:
B30: Communications district | G30: -1653659 | H30: 658326 | I30: 1150057 | N30: =SUM(G30:J30) -> 154724
B31: Library service district no. 1 | G31: -4757360 | H31: 46825 | I31: 88331 | N31: =SUM(G31:J31) -> -4622204
B32: Hospital service district | G32: -40286465 | H32: 22423686 | I32: 6912350 | J32: 714000 | N32: =SUM(G32:J32) -> -10236429
D34: Total component units | G34: =SUM(G30:G32) -> -46697484 | H34: =SUM(H30:H32) -> 23128837 | I34: =SUM(I30:I32) -> 8150738 | J34: =SUM(J30:J32) -> 714000 | K34: =SUM(K30:K32) -> 0 | L34: =SUM(L30:L32) -> 0 | M34: =SUM(M30:M32) -> 0 | N34: =SUM(N30:N32) -> -14703909
E36: General Revenues:
F37: Taxes:
G38: Ad valorem taxes | K38: 25644015 | L38: 15 | M38: =SUM(K38:L38) -> 25644030 | N38: 9023371
G39: Sales taxes | K39: 29753818 | M39: =SUM(K39:L39) -> 29753818
G40: Maintenance tax | M40: =SUM(K40:L40) -> 0 | N40: 2907938
G41: Alcoholic beverage tax | K41: 46431 | M41: =SUM(K41:L41) -> 46431
G42: Airport expansion agreement | K42: 974547 | M42: =SUM(K42:L42) -> 974547
G43: Cable TV franchise tax | K43: 823155 | M43: =SUM(K43:L43) -> 823155
F44: Investment earnings | K44: 268392 | L44: 32798 | M44: =SUM(K44:L44) -> 301190 | N44: 102078
F45: Miscellaneous | K45: 1200372 | L45: -3906 | M45: 1196466 | N45: 8929
F46: Transfers (to) from other funds | K46: -326134 | L46: 326134 | M46: =SUM(K46:L46) -> 0
F48: Total General Revenues and Transfers | K48: =SUM(K38:K46) -> 58384596 | L48: =SUM(L38:L46) -> 355041 | M48: =SUM(M38:M46) -> 58739637 | N48: =SUM(N38:N46) -> 12042316
F50: Change in Net Position | K50: =K48+K18 -> 11227598 | L50: =L48+L27 -> -2003190 | M50: =M48+M27 -> 9224408 | N50: =N48+N34 -> -2661593
D52: Net Assets- Beginning | K52: 251430030 | L52: 113608816 | M52: =SUM(K52:L52) -> 365038846 | N52: -2346383
D54: Net Assets- Ending | K54: =SUM(K50,K52) -> 262657628 | L54: =L52+L50 -> 111605626 | M54: =M52+M50 -> 374263254 | N54: =N52+N50 -> -5007976

Sheet St. Helena
J1: St. Helena County 2014 Statement of Activities
J2: Issued: December 31, 2014
M4: NET (EXPENSE) REVENUE AND CHANGE IN NET ASSETS
J5: PROGRAM REVENUES | N5: Discretely Presented Component Units
A6: FUNCTIONS/PROGRAMS | I6: Expenses | J6: Charges for Services | K6: Operating Grants and Contributions | L6: Capital Grants and Contributions | M6: Primary government governmental activities | N6: St. Helena Par Hospital Serv Dist 1 & Subsidiary | O6: Water Works Dist No. 2 of St. Helena Par | P6: Other Component Units | Q6: Total Component Units
A7: Primary Government:
B8: Government Activities:
C9: General government | I9: -1832157 | J9: 254480 | K9: 14000 | L9: 54122 | M9: =SUM(I9:L9) -> -1509555 | Q9: =SUM(N9:P9) -> 0
C10: Public safety | I10: -1065049 | J10: 113225 | K10: 5449 | L10: 190171 | M10: =SUM(I10:L10) -> -756204 | Q10: =SUM(N10:P10) -> 0
C11: Public works | I11: -2729174 | J11: 8975 | K11: 177542 | L11: 1317622 | M11: =SUM(I11:L11) -> -1225035 | Q11: =SUM(N11:P11) -> 0
C12: Health and welfare | I12: -274763 | J12: 4943 | K12: 135055 | L12: 202475 | M12: =SUM(I12:L12) -> 67710 | Q12: =SUM(N12:P12) -> 0
C13: Recreation | I13: -32456 | L13: 287463 | M13: =SUM(I13:L13) -> 255007 | Q13: =SUM(N13:P13) -> 0
C14: Economic development | I14: -81918 | M14: =SUM(I14:L14) -> -81918 | Q14: =SUM(N14:P14) -> 0
C15: Interest on long-term indebtedness | I15: -72581 | M15: =SUM(I15:L15) -> -72581 | Q15: =SUM(N15:P15) -> 0
E17: Total Government Activities | I17: =SUM(I9:I15) -> -6088098 | J17: =SUM(J9:J15) -> 381623 | K17: =SUM(K9:K15) -> 332046 | L17: =SUM(L9:L15) -> 2051853 | M17: =SUM(M9:M15) -> -3322576 | N17: =SUM(N9:N15) -> 0 | Q17: =SUM(Q9:Q15) -> 0
A19: Discretely Presented Component Units
B20: St. Helena Parish Hospital Serv Dist 1 & Subsidary | I20: -13776565 | J20: 14898874 | N20: =SUM(I20:L20) -> 1122309 | Q20: =N20 -> 1122309
B21: Water works district No. 2 of St. Helena Parish | I21: -845853 | J21: 973260 | O21: 127407 | Q21: =O21 -> 127407
B22: Other component units | I22: -360080 | J22: 30000 | L22: 1000 | P22: -329080 | Q22: =P22 -> -329080
E24: Total component units | I24: =SUM(I20:I22) -> -14982498 | J24: =SUM(J20:J22) -> 15902134 | K24: =SUM(K20:K22) -> 0 | L24: =SUM(L20:L22) -> 1000 | M24: =SUM(M20:M22) -> 0 | N24: =SUM(N20:N22) -> 1122309 | O24: =SUM(O20:O22) -> 127407 | P24: =SUM(P20:P22) -> -329080 | Q24: =SUM(Q20:Q22) -> 920636
G26: General Revenues:
H27: Taxes:
I28: Property taxes | M28: 1908025 | P28: 368324 | Q28: =SUM(N28:P28) -> 368324
I29: Sales taxes | M29: 2150736 | P29: 1333 | Q29: =SUM(N29:P29) -> 1333
I30: Other taxes | M30: 8553 | Q30: =SUM(N30:P30) -> 0
H31: Fire Insurance rebates | M31: 29134 | P31: 6619 | Q31: =SUM(N31:P31) -> 6619
H32: Intergovernmental: | Q32: =SUM(N32:P32) -> 0
I33: Gaming | M33: 902764 | Q33: =SUM(N33:P33) -> 0
I34: Severance Taxes | M34: 638004 | Q34: =SUM(N34:P34) -> 0
I35: State revenue sharing | M35: 81370 | Q35: =SUM(N35:P35) -> 0
H36: Investment earnings | M36: 25453 | N36: 1990 | O36: 3340 | P36: 771 | Q36: =SUM(N36:P36) -> 6101
H37: Recovery of bad debts | O37: 7248 | Q37: =SUM(N37:P37) -> 7248
H38: Miscellaneous | M38: 44305 | O38: 8240 | P38: 7899 | Q38: =SUM(N38:P38) -> 16139
H39: Payments (to) from other local governments | M39: -203357 | P39: 2142 | Q39: =SUM(N39:P39) -> 2142
H40: Gain (loss) on sale or Acquisition (Disposition) of assets | M40: 36354 | Q40: =SUM(N40:P40) -> 0
H42: Total General Revenues and transfers | M42: =SUM(M28:M40) -> 5621341 | N42: =SUM(N28:N40) -> 1990 | O42: =SUM(O28:O40) -> 18828 | P42: =SUM(P28:P40) -> 387088 | Q42: =SUM(Q28:Q40) -> 407906
H44: Change in Net Assets | M44: =M42+M17 -> 2298765 | N44: =N42+N24 -> 1124299 | O44: =O42+O24 -> 146235 | P44: =P42+P24 -> 58008 | Q44: =Q42+Q24+Q17 -> 1328542
H46: Net Position - beginning | M46: 19396743 | N46: 5270324 | O46: 3939541 | P46: 1171923 | Q46: 10381788
H48: Prior period adjustments | M48: -123837
E50: Net Assets- Beginning of Year (restated) | M50: =M46+M48 -> 19272906 | N50: =N46+N48 -> 5270324 | O50: =O46+O48 -> 3939541 | P50: =P46+P48 -> 1171923 | Q50: =Q46+Q48 -> 10381788
E52: Net Assets- End of Year | M52: =M50+M44 -> 21571671 | N52: =N50+N44 -> 6394623 | O52: =O50+O44 -> 4085776 | P52: =P50+P44 -> 1229931 | Q52: =Q50+Q44 -> 11710330

Sheet St. James
H1: St. James County 2014 Statement of Activities
H2: Issued: December 31, 2014
K4: NET (EXPENSE) REVENUE AND CHANGE IN NET ASSETS
H5: PROGRAM REVENUES | K5: PRIMARY GOVERNMENT | N5: COMPONENT UNIT
A6: FUNCTIONS/PROGRAMS | G6: Expenses | H6: Charges for Services | I6: Operating Grants and Contributions | J6: Capital Grants and Contributions | K6: Governmental Activities | L6: Business-type Activities | M6: Total | N6: Business-type Activities
A7: Primary Government:
B8: Government Activities:
C9: General government | G9: -9668333 | H9: 497 | I9: 539799 | J9: 7054640 | K9: -2073397 | M9: =SUM(K9:L9) -> -2073397
C10: Public safety | G10: -4037958 | H10: 242902 | I10: -6929 | J10: 16666 | K10: =SUM(G10:J10) -> -3785319 | M10: =SUM(K10:L10) -> -3785319
C11: Highways and streets | G11: -4602549 | I11: 729720 | J11: 640082 | K11: -3232747 | M11: =SUM(K11:L11) -> -3232747
C12: Sanitation | G12: -1885173 | H12: 598021 | I12: 61609 | K12: =SUM(G12:J12) -> -1225543 | M12: =SUM(K12:L12) -> -1225543
C13: Public housing | G13: -1520 | K13: =SUM(G13:J13) -> -1520 | M13: =SUM(K13:L13) -> -1520
C14: Public transportation | G14: -1050665 | H14: 78245 | I14: 542833 | K14: -429587 | M14: =SUM(K14:L14) -> -429587
C15: Health and welfare | G15: -4418589 | I15: 923370 | K15: -3495219 | M15: =SUM(K15:L15) -> -3495219
C16: Culture and recreation | G16: -2828449 | H16: 38514 | I16: 469593 | K16: -2320342 | M16: =SUM(K16:L16) -> -2320342
C17: Economic development and assistance | G17: -2300637 | I17: 1517741 | K17: -782896 | M17: =SUM(K17:L17) -> -782896
C18: Interest on long-term debt | G18: -271857 | K18: =SUM(G18:J18) -> -271857 | M18: =SUM(K18:L18) -> -271857
D20: Total Government Activities | G20: =SUM(G9:G18) -> -31065730 | H20: =SUM(H9:H18) -> 958179 | I20: =SUM(I9:I18) -> 4777736 | J20: =SUM(J9:J18) -> 7711388 | K20: =SUM(K9:K18) -> -17618427 | M20: =SUM(M9:M18) -> -17618427 | N20: =SUM(N9:N18) -> 0
B22: Business-type Activities:
C23: Gas and water | G23: -4949997 | H23: 5450860 | I23: -2635 | J23: 24287 | L23: 522515 | M23: =SUM(K23:L23) -> 522515
C24: Youth detention | G24: -443689 | H24: 47676 | I24: -600 | L24: =SUM(G24:J24) -> -396613 | M24: =SUM(K24:L24) -> -396613
D26: Total Business-type Activities | G26: =SUM(G23:G24) -> -5393686 | H26: =SUM(H23:H24) -> 5498536 | I26: =SUM(I23:I24) -> -3235 | J26: =SUM(J23:J24) -> 24287 | K26: =SUM(K23:K24) -> 0 | L26: =SUM(L23:L24) -> 125902 | M26: =SUM(M23:M24) -> 125902 | N26: =SUM(N17:N24) -> 0
D28: Total primary government | G28: =G26+G20 -> -36459416 | H28: =H26+H20 -> 6456715 | I28: =SUM(I20+I26) -> 4774501 | J28: =SUM(J20+J26) -> 7735675 | K28: =K26+K20 -> -17618427 | L28: =L26+L20 -> 125902 | M28: =M26+M20 -> -17492525 | N28: =SUM(N19:N26) -> 0
A30: Component units:
B31: St. James Parish Hospital | G31: -23781570 | H31: 21228237 | I31: 117520 | N31: =SUM(G31:J31) -> -2435813
D33: Total component units | G33: =SUM(G31:G31) -> -23781570 | H33: =SUM(H31:H31) -> 21228237 | I33: =SUM(I31:I31) -> 117520 | J33: =SUM(J31:J31) -> 0 | K33: =SUM(K31:K31) -> 0 | L33: =SUM(L31:L31) -> 0 | M33: =SUM(M31:M31) -> 0 | N33: =SUM(N31:N31) -> -2435813
E35: General Revenues:
F36: Taxes:
G37: Property taxes | K37: 16937947 | L37: 328319 | M37: =SUM(K37:L37) -> 17266266 | N37: 2507191
G38: Voluntary payments in lieu of taxes | K38: 356945 | M38: =SUM(K38:L38) -> 356945
G39: Sales and use taxes | K39: 6563038 | M39: =SUM(K39:L39) -> 6563038
G40: Alcoholic beverages | K40: 19291 | M40: =SUM(K40:L40) -> 19291
G41: Franchise fees | K41: 112635 | M41: =SUM(K41:L41) -> 112635
G42: Other | K42: 226886 | M42: =SUM(K42:L42) -> 226886
F43: Fines and forfeits | K43: 185502 | L43: 650 | M43: =SUM(K43:L43) -> 186152
F44: Unrestricted grants and contributions | K44: 537865 | M44: =SUM(K44:L44) -> 537865
F45: Interest on investments | K45: 68238 | L45: 5394 | M45: =SUM(K45:L45) -> 73632 | N45: 1302
F46: Other | K46: 2248504 | M46: =SUM(K46:L46) -> 2248504 | N46: 1065116
F47: Gain (loss) on sale of fixed assets | K47: -4494 | M47: =SUM(K47:L47) -> -4494 | N47: -11321
F48: Transfers | K48: 1443 | L48: 70856 | M48: =SUM(K48:L48) -> 72299
F50: Total General Revenues and Transfers | K50: =SUM(K37:K48) -> 27253800 | L50: =SUM(L37:L48) -> 405219 | M50: =SUM(M37:M48) -> 27659019 | N50: =SUM(N37:N48) -> 3562288
F52: Change in Net Assets before extraordinary item | K52: =K50+K20 -> 9635373 | L52: =L50+L28 -> 531121 | M52: =M50+M28 -> 10166494 | N52: =N50+N33 -> 1126475
F54: Extraordinary item - loss on impairment of capital asset | L54: -686937 | M54: =SUM(K54:L54) -> -686937
F56: Change in net assets | K56: =K52+K54 -> 9635373 | L56: =L52+L54 -> -155816 | M56: =M52+M54 -> 9479557 | N56: =N52+N54 -> 1126475
F58: Net position - beginning as previously reported | K58: 95700414 | L58: 22399554 | M58: =SUM(K58:L58) -> 118099968 | N58: 25231253
F60: Adjustment for implementation of GASB 65 | N60: -422408
D62: Net Assets- Beginning of Year, restated | K62: 95700414 | L62: 22399554 | M62: =SUM(K62:L62) -> 118099968 | N62: 24808845
D64: Net Assets- End of Year | K64: =K62+K56 -> 105335787 | L64: =L62+L56 -> 22243738 | M64: =M62+M56 -> 127579525 | N64: =N62+N56 -> 25935320

Sheet St. Mary
H1: St. Mary County 2014 Statement of Activities
H2: Issued: December 31, 2014
K4: NET (EXPENSE) REVENUE AND CHANGE IN NET ASSETS
H5: PROGRAM REVENUES | K5: PRIMARY GOVERNMENT
A6: FUNCTIONS/PROGRAMS | G6: Expenses | H6: Charges for Services | I6: Operating Grants and Contributions | J6: Capital Grants and Contributions | K6: Governmental Activities | L6: Business-type Activities | M6: Total
A7: Primary Government:
B8: Government Activities:
C9: General government | G9: -7177908 | H9: 1408912 | I9: 910763 | K9: =SUM(G9:J9) -> -4858233 | M9: =SUM(K9:L9) -> -4858233
C10: Public safety | G10: -5269357 | H10: 10110 | I10: 1340430 | J10: 50000 | K10: =SUM(G10:J10) -> -3868817 | M10: =SUM(K10:L10) -> -3868817
C11: Public works | G11: -10615442 | I11: 2881068 | J11: 1504912 | K11: =SUM(G11:J11) -> -6229462 | M11: =SUM(K11:L11) -> -6229462
C12: Sanitation | G12: -3916814 | H12: 1346585 | I12: 167228 | K12: =SUM(G12:J12) -> -2403001 | M12: =SUM(K12:L12) -> -2403001
C13: Culture and recreation | G13: -2211677 | H13: 57032 | I13: 81586 | J13: 387654 | K13: =SUM(G13:J13) -> -1685405 | M13: =SUM(K13:L13) -> -1685405
C14: Health and welfare | G14: -5544190 | H14: 280750 | I14: 4245875 | K14: =SUM(G14:J14) -> -1017565 | M14: =SUM(K14:L14) -> -1017565
C15: Urban redevelopment and housing | G15: -435461 | I15: 443511 | K15: =SUM(G15:J15) -> 8050 | M15: =SUM(K15:L15) -> 8050
C16: Economic development and assistance | G16: -242924 | K16: =SUM(G16:J16) -> -242924 | M16: =SUM(K16:L16) -> -242924
C17: Interest on long-term debt | G17: -700492 | K17: =SUM(G17:J17) -> -700492 | M17: =SUM(K17:L17) -> -700492
C18: Fees on long-term debt | G18: -20475 | K18: =SUM(G18:J18) -> -20475 | M18: =SUM(K18:L18) -> -20475
D20: Total Government Activities | G20: =SUM(G9:G18) -> -36134740 | H20: =SUM(H9:H18) -> 3103389 | I20: =SUM(I9:I18) -> 10070461 | J20: =SUM(J9:J18) -> 1942566 | K20: =SUM(K9:K18) -> -21018324 | M20: =SUM(M9:M18) -> -21018324
B22: Business-type Activities:
C23: Solid waste landfil | G23: -4333311 | H23: 3856466 | L23: =SUM(G23:J23) -> -476845 | M23: =SUM(L23) -> -476845
C24: Small animal control | G24: -337925 | H24: 138112 | L24: =SUM(G24:J24) -> -199813 | M24: =SUM(L24) -> -199813
C25: Kemper Williams Park | G25: -734357 | H25: 146440 | I25: 139256 | L25: =SUM(G25:J25) -> -448661 | M25: =SUM(K25:L25) -> -448661
D27: Total Business-type Activities | G27: =SUM(G23:G25) -> -5405593 | H27: =SUM(H23:H25) -> 4141018 | I27: =SUM(I23:I25) -> 139256 | J27: =SUM(J23:J25) -> 0 | K27: =SUM(K23:K25) -> 0 | L27: =SUM(L23:L25) -> -1125319 | M27: =SUM(M23:M25) -> -1125319
D29: Total primary government | G29: =G27+G20 -> -41540333 | H29: =H27+H20 -> 7244407 | I29: =SUM(I20+I27) -> 10209717 | J29: =SUM(J20+J27) -> 1942566 | K29: =K27+K20 -> -21018324 | L29: =L27+L20 -> -1125319 | M29: =M27+M20 -> -22143643
E32: General Revenues:
F33: Taxes:
G34: Sales and use | K34: 7291457 | M34: =SUM(K34:L34) -> 7291457
G35: Ad valorem taxes levied for general purposes | K35: 3518912 | M35: =SUM(K35:L35) -> 3518912
G36: Ad valorem taxes levied for debt service | K36: 620985 | M36: =SUM(K36:L36) -> 620985
G37: Severance taxes | K37: 985544 | M37: =SUM(K37:L37) -> 985544
G38: Other taxes, penalties, and interest, etc. | K38: 67454 | M38: =SUM(K38:L38) -> 67454
F39: Royalty road funds | K39: 9171434 | M39: =SUM(K39:L39) -> 9171434
F40: State shared revenue | K40: 543705 | M40: =SUM(K40:L40) -> 543705
F41: Investment earnings and interest | K41: 208368 | L41: 26548 | M41: =SUM(K41:L41) -> 234916
F42: Gain on sale of equipment | L42: 1067 | M42: =SUM(K42:L42) -> 1067
F43: Special item: payment from St. Mary Library Board | K43: 500000 | M43: =SUM(K43:L43) -> 500000
F44: Transfers: operating | K44: -1661385 | L44: 1661385 | M44: =SUM(K44:L44) -> 0
F46: Total General Revenues, Special items, and Transfers | K46: =SUM(K34:K44) -> 21246474 | L46: =SUM(L34:L44) -> 1689000 | M46: =SUM(M34:M44) -> 22935474
F48: Change in net position | K48: =K46+K20 -> 228150 | L48: =L46+L29 -> 563681 | M48: =M46+M29 -> 791831
D50: Net Assets- Beginning of Year, restated | K50: 100032791 | L50: 16851125 | M50: =SUM(K50:L50) -> 116883916
D52: Net Assets- End of Year | K52: =SUM(K50+K48) -> 100260941 | L52: =SUM(L50+L48) -> 17414806 | M52: =SUM(M50+M48) -> 117675747

Sheet St. Tammany
H1: St. Tammany County 2014 Statement of Activities
H2: Issued: December 31, 2014
K4: NET (EXPENSE) REVENUE AND CHANGE IN NET ASSETS
H5: PROGRAM REVENUES | K5: PRIMARY GOVERNMENT
A6: FUNCTIONS/PROGRAMS | G6: Expenses | H6: Charges for Services | I6: Operating Grants and Contributions | J6: Capital Grants and Contributions | K6: Governmental Activities | L6: Business-type Activities | M6: Total | N6: Component Units
A7: Primary Government:
B8: Government Activities:
C9: General government | G9: -24008909 | H9: 7612317 | I9: 560926 | J9: 22907 | K9: =SUM(G9:J9) -> -15812759 | M9: =SUM(K9:L9) -> -15812759
C10: Public safety | G10: -19458275 | H10: 2254057 | I10: 333132 | J10: 2020349 | K10: =SUM(G10:J10) -> -14850737 | M10: =SUM(K10:L10) -> -14850737
C11: Highways and streets | G11: -39608176 | H11: 3208490 | I11: 4100803 | J11: 3640367 | K11: =SUM(G11:J11) -> -28658516 | M11: =SUM(K11:L11) -> -28658516
C12: Sanitation | G12: -889591 | H12: 1607527 | I12: 77111 | J12: 2666981 | K12: =SUM(G12:J12) -> 3462028 | M12: =SUM(K12:L12) -> 3462028
C13: Health and welfare | G13: -10989796 | H13: 284709 | I13: 3038145 | J13: 4118 | K13: =SUM(G13:J13) -> -7662824 | M13: =SUM(K13:L13) -> -7662824
C14: Culture and recreation | G14: -10762156 | H14: 23397 | I14: 296931 | K14: =SUM(G14:J14) -> -10441828 | M14: =SUM(K14:L14) -> -10441828
C15: Economic development | G15: -1313786 | I15: 361434 | J15: 919412 | K15: =SUM(G15:J15) -> -32940 | M15: =SUM(K15:L15) -> -32940
C16: Interest on long-term debt | G16: -3252376 | K16: =SUM(G16:J16) -> -3252376 | M16: =SUM(K16:L16) -> -3252376
D18: Total Government Activities | G18: =SUM(G9:G16) -> -110283065 | H18: =SUM(H9:H16) -> 14990497 | I18: =SUM(I9:I16) -> 8768482 | J18: =SUM(J9:J16) -> 9274134 | K18: =SUM(K9:K16) -> -77249952 | M18: =SUM(M9:M16) -> -77249952 | N18: =SUM(N9:N16) -> 0
B20: Business-type Activities:
C21: Water/Sewer | G21: -11610098 | H21: 12531285 | J21: 91967 | L21: =SUM(G21:J21) -> 1013154 | M21: =SUM(K21:L21) -> 1013154
D23: Total Business-type Activities | G23: =SUM(G21:G21) -> -11610098 | H23: =SUM(H21:H21) -> 12531285 | I23: =SUM(I21:I21) -> 0 | J23: =SUM(J21:J21) -> 91967 | K23: =SUM(K21:K21) -> 0 | L23: =SUM(L21:L21) -> 1013154 | M23: =SUM(M21:M21) -> 1013154 | N23: =SUM(N21:N21) -> 0
D25: Total primary government | G25: =G23+G18 -> -121893163 | H25: =H23+H18 -> 27521782 | I25: =SUM(I18+I23) -> 8768482 | J25: =SUM(J18+J23) -> 9366101 | K25: =K23+K18 -> -77249952 | L25: =L23+L18 -> 1013154 | M25: =M23+M18 -> -76236798 | N25: =N23+N18 -> 0
A27: Component units:
B28: Total component units | G28: -83443018 | H28: 6440906 | I28: 453613 | J28: 23431 | N28: =SUM(G28:J28) -> -76525068
D30: Total component units | G30: =SUM(G28:G28) -> -83443018 | H30: =SUM(H28:H28) -> 6440906 | I30: =SUM(I28:I28) -> 453613 | J30: =SUM(J28:J28) -> 23431 | K30: =SUM(K28:K28) -> 0 | L30: =SUM(L28:L28) -> 0 | M30: =SUM(M28:M28) -> 0 | N30: =SUM(N28:N28) -> -76525068
E32: General Revenues:
G33: Property taxes, general (Ad valorem, parcel fees, etc.) | K33: 4524597 | M33: =SUM(K33:L33) -> 4524597
G34: Property taxes, special purpose (Ad valorem, parcel fees, etc.) | K34: 25307458 | M34: =SUM(K34:L34) -> 25307458 | N34: 62732460
G35: Sales and use taxes | K35: 65667400 | M35: =SUM(K35:L35) -> 65667400
G36: Franchise taxes | K36: 2322561 | M36: =SUM(K36:L36) -> 2322561
G37: Hotel/Motel tax | K37: 578665 | M37: =SUM(K37:L37) -> 578665 | N37: 393759
G38: Timber severance tax | K38: 93961 | M38: =SUM(K38:L38) -> 93961
G39: Mineral severance tax | K39: 9193 | M39: =SUM(K39:L39) -> 9193
G40: Alcohol tax | K40: 58355 | M40: =SUM(K40:L40) -> 58355
G41: Cigarette paper tax | K41: 10939 | M41: =SUM(K41:L41) -> 10939
G42: Gaming revenue tax | K42: 188055 | M42: =SUM(K42:L42) -> 188055
G43: Fire insurance tax | M43: =SUM(K43:L43) -> 0 | N43: 913330
G44: State revenue sharing (unrestricted) | K44: 277808 | M44: =SUM(K44:L44) -> 277808 | N44: 1349291
G45: Federal payment in lieu of ad valorem | K45: 72767 | M45: =SUM(K45:L45) -> 72767
G46: Investment earnings | K46: 3497663 | L46: 201031 | M46: =SUM(K46:L46) -> 3698694 | N46: 374156
G47: Sale of revocated property | K47: 53200 | M47: =SUM(K47:L47) -> 53200
G48: GNOE excess revenue | K48: 50000 | M48: =SUM(K48:L48) -> 50000
G49: Grants and contributions not restricted to specific programs | M49: =SUM(K49:L49) -> 0 | N49: 12909729
G50: Other general revenues | M50: =SUM(K50:L50) -> 0 | N50: 993477
F51: Extraordinary item -Reimbursement of federal awards | M51: =SUM(K51:L51) -> 0 | N51: -159125
F52: Transfers | K52: 292582 | L52: -292582 | M52: =SUM(K52:L52) -> 0
F54: Total General Revenues, extraordinary items and transfers | K54: =SUM(K33:K52) -> 103005204 | L54: =SUM(L33:L52) -> -91551 | M54: =SUM(M33:M52) -> 102913653 | N54: =SUM(N33:N52) -> 79507077
F56: Change in Net position | K56: =K54+K18 -> 25755252 | L56: =L54+L25 -> 921603 | M56: =M54+M25 -> 26676855 | N56: =N54+N30 -> 2982009
D58: Net Assets- Beginning | K58: 516773440 | L58: 11562774 | M58: =SUM(K58:L58) -> 528336214 | N58: 172588793
D60: Net Assets- Ending | K60: =SUM(K56,K58) -> 542528692 | L60: =L58+L56 -> 12484377 | M60: =M58+M56 -> 555013069 | N60: =N58+N56 -> 175570802

Sheet Tangipahoa
J1: Tangipahoa Parish 2014 Statement of Activities
J2: Issued: December 31, 2014
J4: PROGRAM REVENUES | M4: Net Revenues (Expenses) Revenues and Changes in Net Position
A5: FUNCTIONS/PROGRAMS | I5: Expenses | J5: Charges for Services | K5: Operating Grants and Contributions | L5: Capital Grants and Contributions | M5: Governmental Activities | N5: Component Units
A6: Primary Government:
B7: Government Activities:
C8: General government | I8: -6526544 | J8: 3517732 | K8: 705299 | L8: 386311 | M8: =SUM(I8:L8) -> -1917202
C9: Culture and recreation | I9: -1759244 | J9: 103130 | K9: 50405 | M9: =SUM(I9:L9) -> -1605709
C10: Public safety | I10: -3756340 | J10: 781417 | L10: 113526 | M10: =SUM(I10:L10) -> -2861397
C11: Public works | I11: -22867919 | J11: 3747317 | K11: 977985 | L11: 1731104 | M11: =SUM(I11:L11) -> -16411513
C12: Health and welfare | I12: -3113081 | K12: 2588765 | M12: =SUM(I12:L12) -> -524316
C13: Interest on long-term debt | I13: -113612 | M13: =SUM(I13:L13) -> -113612
E15: Total Government Activities | I15: =SUM(I8:I13) -> -38136740 | J15: =SUM(J8:J13) -> 8149596 | K15: =SUM(K8:K13) -> 4322454 | L15: =SUM(L8:L13) -> 2230941 | M15: =SUM(M8:M13) -> -23433749
B17: Component Units:
C18: Fire protection services | I18: -5301045 | J18: 238460 | K18: 193079 | N18: =SUM(I18:K18) -> -4869506
E20: Total component units | I20: =I18 -> -5301045 | J20: =J18 -> 238460 | K20: =K18 -> 193079 | L20: =L18 -> 0 | M20: 0 | N20: =SUM(N18:N18) -> -4869506
G22: General Revenues:
H23: Taxes:
I24: Sales taxes | M24: 18934034
I25: Ad valorem taxes | M25: 6550590 | N25: 4932312
I26: Franchise taxes | M26: 771121
I27: Severance taxes | M27: 207379
I28: Alcoholic beverage taxes | M28: 36632
H29: Occupational licenses | M29: 744199
H30: State revenue sharing | M30: 503884 | N30: 487091
H31: 2% Fire insurance rebate | N31: 315380
H32: Donations | M32: 10339
H33: Miscellaneous | M33: 187273 | N33: 84940
H34: Investment earnings | M34: 87344 | N34: 42014
H35: Gain from disposition of capital assets | M35: 16509
H36: Transfer and contributions | M36: -362162 | N36: 9031
H38: Total general revenues, transfers, and contributions | M38: =SUM(M22:M36) -> 27687142 | N38: =SUM(N22:N36) -> 5870768
H40: Change in Net Position | M40: =M38+M15 -> 4253393 | N40: =N38+N20 -> 1001262
E42: Net Position, beginning (as restated) | M42: 190420558 | N42: 18855127
E44: Net Assets- End of Year | M44: =M42+M40 -> 194673951 | N44: =N42+N40 -> 19856389

Sheet Tensas
J1: Tensas Parish 2014 Statement of Activities
J2: Issued: December 31, 2014
J5: PROGRAM REVENUES | M5: NET (EXPENSE) REVENUE AND CHANGES IN NET POSITION
A6: FUNCTIONS/PROGRAMS | I6: Expenses | J6: Charges for Services | K6: Operating Grants and Contributions | L6: Capital Grants and Contributions | M6: Governmental Activities
A7: Primary government:
A8: Governmental activities:
C9: General government
D10: Legislative | I10: -168641 | M10: =SUM(I10:L10) -> -168641
D11: Judicial | I11: -341137 | M11: =SUM(I11:L11) -> -341137
D12: Elections | I12: -28953 | M12: =SUM(I12:L12) -> -28953
D13: Finance and administrative | I13: -519235 | M13: =SUM(I13:L13) -> -519235
D14: Other general adminstrative | I14: -604464 | M14: =SUM(I14:L14) -> -604464
C15: Public safety | I15: -293277 | J15: 97296 | K15: 41372 | L15: 290213 | M15: =SUM(I15:L15) -> 135604
C16: Public works | I16: -2137142 | J16: 431989 | M16: =SUM(I16:L16) -> -1705153
C17: Health and welfare | I17: -577960 | M17: =SUM(I17:L17) -> -577960
C18: Culture and recreation | I18: -285685 | K18: 21875 | M18: =SUM(I18:L18) -> -263810
C19: Economic development | I19: -390386 | J19: 1770 | K19: 58500 | M19: =SUM(I19:L19) -> -330116
C20: Interest on long-term debt | I20: -40653 | M20: =SUM(I20:L20) -> -40653
E22: Total Government Activities | I22: =SUM(I10:I20) -> -5387533 | J22: =SUM(J10:J20) -> 531055 | K22: =SUM(K10:K20) -> 121747 | L22: =SUM(L10:L20) -> 290213 | M22: =SUM(M10:M20) -> -4444518
G24: General Revenues:
H25: Taxes:
I26: Ad valorem | M26: 1492974
I27: Sales | M27: 1652732
I28: Other taxes | M28: 249703
H29: Licenses and permits | M29: 66649
H30: State funds:
I31: Parish transportation | M31: 75743
I32: State revenue sharing | M32: 44564
I33: Fire insurance rebates | M33: 19973
H34: Investment income | M34: 29180
H35: Other revenues | M35: 261346
H36: Contract buyout | M36: 750000
H38: Total General Revenue | M38: =SUM(M26:M36) -> 4642864
H40: Change in Net position | M40: =M38+M22 -> 198346
E42: Net position- beginning of year | M42: 11112921
E44: Net position- end of year | M44: =M42+M40 -> 11311267

Sheet Terrebonne
J1: Terrebonne County 2014 Statement of Activities
J2: Issued: December 31, 2014
M4: NET (EXPENSE) REVENUE AND CHANGE IN NET ASSETS
J5: PROGRAM REVENUES | M5: PRIMARY GOVERNMENT
A6: FUNCTIONS/PROGRAMS | I6: Expenses | J6: Charges for Services | K6: Operating Grants and Contributions | L6: Capital Grants and Contributions | M6: Governmental Activities | N6: Business-type Activities | O6: Total | P6: Component Units
A7: Primary Government:
B8: Government Activities:
C9: General government | I9: -22999821 | J9: 9929607 | K9: 621619 | L9: 3275752 | M9: =SUM(I9:L9) -> -9172843 | O9: =SUM(M9:N9) -> -9172843
C10: Public safety | I10: -30201770 | J10: 2326686 | K10: 3525652 | L10: 9100 | M10: =SUM(I10:L10) -> -24340332 | O10: =SUM(M10:N10) -> -24340332
C11: Streets and drainage | I11: -28131936 | J11: 49731 | K11: 1450558 | L11: 18282499 | M11: =SUM(I11:L11) -> -8349148 | O11: =SUM(M11:N11) -> -8349148
C12: Health and welfare | I12: -12236783 | K12: 4890325 | M12: =SUM(I12:L12) -> -7346458 | O12: =SUM(M12:N12) -> -7346458
C13: Culture and recreation | I13: -2385729 | J13: 86742 | K13: 72694 | L13: 237831 | M13: =SUM(I13:L13) -> -1988462 | O13: =SUM(M13:N13) -> -1988462
C14: Education | I14: -101172 | M14: =SUM(I14:L14) -> -101172 | O14: =SUM(M14:N14) -> -101172
C15: Urban redevelopment and housing | I15: -939034 | K15: 675082 | M15: =SUM(I15:L15) -> -263952 | O15: =SUM(M15:N15) -> -263952
C16: Economic development and assistance | I16: -16169215 | K16: 15041481 | L16: 28184 | M16: =SUM(I16:L16) -> -1099550 | O16: =SUM(M16:N16) -> -1099550
C17: Conservation and development | I17: -296431 | L17: 392181 | M17: =SUM(I17:L17) -> 95750 | O17: =SUM(M17:N17) -> 95750
C18: Interest on long-term debt | I18: -4928181 | M18: =SUM(I18:L18) -> -4928181 | O18: =SUM(M18:N18) -> -4928181
E20: Total Government Activities | I20: =SUM(I9:I18) -> -118390072 | J20: =SUM(J9:J18) -> 12392766 | K20: =SUM(K9:K18) -> 26277411 | L20: =SUM(L9:L18) -> 22225547 | M20: =SUM(M9:M18) -> -57494348 | O20: =SUM(O9:O18) -> -57494348 | P20: =SUM(P9:P18) -> 0
B22: Business-type Activities:
C23: Electric and gas | I23: -40624795 | J23: 46395086 | N23: =SUM(I23:L23) -> 5770291 | O23: =SUM(M23:N23) -> 5770291
C24: Sewerage | I24: -9318611 | J24: 8133483 | L24: 609643 | N24: =SUM(I24:L24) -> -575485 | O24: =SUM(M24:N24) -> -575485
C25: Sanitation | I25: -13473382 | J25: 8263891 | K25: 332956 | N25: =SUM(I25:L25) -> -4876535 | O25: =SUM(M25:N25) -> -4876535
C26: Civic center | I26: -2304351 | J26: 482837 | N26: =SUM(I26:L26) -> -1821514 | O26: =SUM(M26:N26) -> -1821514
E28: Total Business-type Activities | I28: =SUM(I23:I26) -> -65721139 | J28: =SUM(J23:J26) -> 63275297 | K28: =SUM(K23:K26) -> 332956 | L28: =SUM(L23:L26) -> 609643 | M28: =SUM(M23:M26) -> 0 | N28: =SUM(N23:N26) -> -1503243 | O28: =SUM(O23:O26) -> -1503243 | P28: =SUM(P23:P26) -> 0
E30: Total primary government | I30: =I28+I20 -> -184111211 | J30: =J28+J20 -> 75668063 | K30: =SUM(K20+K28) -> 26610367 | L30: =SUM(L20+L28) -> 22835190 | M30: =M28+M20 -> -57494348 | N30: =N28+N20 -> -1503243 | O30: =O28+O20 -> -58997591 | P30: =P28+P20 -> 0
A32: Component units:
B33: General government | I33: -3197912 | J33: 1225172 | K33: 211112 | P33: =SUM(I33:L33) -> -1761628
B34: Judicial services | I34: -12738098 | J34: 8110174 | K34: 3621152 | P34: =SUM(I34:L34) -> -1006772
B35: Public safety | I35: -28826451 | J35: 1828136 | K35: 1570970 | L35: 8491164 | P35: =SUM(I35:L35) -> -16936181
B36: Health and welfare services | I36: -244954792 | J36: 236037701 | K36: 1188434 | L36: 435604 | P36: =SUM(I36:L36) -> -7293053
B37: Culture and recreation | I37: -12465925 | J37: 714595 | K37: 336345 | L37: 49067 | P37: =SUM(I37:L37) -> -11365918
B38: Economic development and assistance | I38: -7772757 | K38: 3245144 | L38: 2552088 | P38: =SUM(I38:L38) -> -1975525
B39: Utilities | I39: -15888446 | J39: 17775446 | L39: 1109797 | P39: =SUM(I39:L39) -> 2996797
E41: Total component units | I41: =SUM(I33:I39) -> -325844381 | J41: =SUM(J33:J39) -> 265691224 | K41: =SUM(K33:K39) -> 10173157 | L41: =SUM(L33:L39) -> 12637720 | M41: =SUM(M33:M39) -> 0 | N41: =SUM(N33:N39) -> 0 | O41: =SUM(O33:O39) -> 0 | P41: =SUM(P33:P39) -> -37342280
G43: General Revenues:
H44: Taxes:
I45: Property | M45: 26726303 | N45: 9718364 | O45: 36444667 | P45: 44055179
I46: Sales and use | M46: 44756815 | O46: 44756815 | P46: 12712611
I47: Franchise | M47: 1756724 | O47: =SUM(M47:N47) -> 1756724
I48: Occupancy | N48: 339074 | O48: 339074 | P48: 2891562
H49: Grants and contributions not restricted to specific programs | M49: 9745773 | O49: 9745773 | P49: 5144526
H50: Unrestricted investment earnings | M50: 772038 | N50: 633084 | O50: 1405122 | P50: 970397
H51: Miscellaneous | M51: 532437 | O51: 532437 | P51: 539545
H52: Transfers | M52: 2675391 | N52: -2675391 | O52: =SUM(M52:N52) -> 0
H54: Total General Revenues and Transfers | M54: =SUM(M45:M52) -> 86965481 | N54: =SUM(N45:N52) -> 8015131 | O54: =SUM(O45:O52) -> 94980612 | P54: =SUM(P45:P52) -> 66313820
H56: Change in Net Assets | M56: 29471133 | N56: 6511888 | O56: 35983021 | P56: 28971540
E58: Net Assets- Beginning | M58: 316367798 | N58: 183859508 | O58: =SUM(M58:N58) -> 500227306 | P58: 822810609
E60: Net Assets- Ending | M60: =SUM(M56,M58) -> 345838931 | N60: =N58+N56 -> 190371396 | O60: =O58+O56 -> 536210327 | P60: =P58+P56 -> 851782149

Sheet Union
J1: Union County 2014 Statement of Activities
J2: Issued: December 31, 2014
J4: PROGRAM REVENUES
A5: FUNCTIONS/PROGRAMS | I5: Expenses | J5: Charges for Services | K5: Operating Grants and Contributions | L5: Capital Grants and Contributions | M5: NET (EXPENSE) REVENUE AND CHANGE IN NET ASSETS
A6: Primary Government:
B7: Government Activities:
C8: General government | I8: -2049624 | J8: 146302 | K8: 41599 | M8: =SUM(I8:L8) -> -1861723
C9: Public safety | I9: -4377482 | J9: 2380646 | K9: 123557 | L9: 335225 | M9: =SUM(I9:L9) -> -1538054
C10: Public works | I10: -5704715 | J10: 1310783 | K10: 527598 | L10: 97460 | M10: =SUM(I10:L10) -> -3768874
C11: Health and welfare | I11: -1861820 | J11: 18509 | K11: 1452424 | L11: 28400 | M11: =SUM(I11:L11) -> -362487
C12: Culture and recreation | I12: -448971 | J12: 11385 | K12: 56554 | M12: =SUM(I12:L12) -> -381032
C13: Economic development and assistance | I13: -54593 | M13: =SUM(I13:L13) -> -54593
C14: Transportation | I14: -146467 | K14: 7350 | L14: 57230 | M14: =SUM(I14:L14) -> -81887
C15: Interest expense | I15: -21200 | M15: =SUM(I15:L15) -> -21200
C16: OPEB obligation | I16: -233477 | M16: =SUM(I16:L16) -> -233477
E18: Total Government Activities | I18: =SUM(I8:I16) -> -14898349 | J18: =SUM(J8:J16) -> 3867625 | K18: =SUM(K8:K16) -> 2209082 | L18: =SUM(L8:L16) -> 518315 | M18: =SUM(M8:M16) -> -8303327
G20: General Revenues:
H21: Property taxes levied for:
I22: General purposes | M22: 678193
I23: Public works | M23: 1727325
I24: Health and welfare | M24: 260332
I25: Culture and recreation | M25: 520221
H26: Sales and use taxes levied for public works | M26: 2448065
H27: Other taxes, penalties and interest | M27: 24678
H28: Grants and contributions not restricted to specific programs | M28: 963168
H29: Unrestricted investment earnings | M29: 2177
H30: Restricted investment earnings | M30: 1010
H31: Donations | M31: 1611
H32: Other | M32: 406267
H34: Total General Revenues | M34: =SUM(M22:M32) -> 7033047
H36: Change in Net Assets | M36: =M34+M18 -> -1270280
E38: Net Assets- Beginning of Year | M38: 21393990
E40: Net Assets- End of Year | M40: =SUM(M36,M38) -> 20123710

Sheet Vermilion
J1: Vermillion County 2014 Statement of Activities
J2: Issued: December 31, 2014
M5: NET (EXPENSE) REVENUE AND CHANGE IN NET ASSETS
J6: PROGRAM REVENUES | M6: PRIMARY GOVERNMENT | N6: Component Units
A7: ACTIVITIES | I7: Expenses | J7: Fees, fines, and charges for services | K7: Operating Grants and Contributions | L7: Capital Grants and Contributions | M7: Governmental Activities | N7: Criminal Court Fund | O7: Tourist Commission
A8: Primary Government:
B9: Government Activities:
C10: General government | I10: -3824064 | J10: 363 | K10: 58170 | M10: =SUM(I10:L10) -> -3765531
C11: Public works | I11: -11157407 | K11: 1896046 | L11: 8175269 | M11: =SUM(I11:L11) -> -1086092
C12: Public safety | I12: -3405434 | J12: 670042 | K12: 20745 | L12: 100621 | M12: =SUM(I12:L12) -> -2614026
C13: Sanitation and waste disposal | I13: -5660129 | J13: 854150 | M13: =SUM(I13:L13) -> -4805979
C14: Health and welfare | I14: -1718417 | J14: 38147 | K14: 279144 | M14: =SUM(I14:L14) -> -1401126
C15: Economic development | I15: -179403 | M15: =SUM(I15:L15) -> -179403
C16: Culture and recreation | I16: -101372 | M16: =SUM(I16:L16) -> -101372
C17: Interest on long-term debt | I17: -82753 | M17: =SUM(I17:L17) -> -82753
E19: Total Government Activities | I19: =SUM(I10:I17) -> -26128979 | J19: =SUM(J10:J17) -> 1562702 | K19: =SUM(K10:K17) -> 2254105 | L19: =SUM(L10:L17) -> 8275890 | M19: =SUM(M10:M17) -> -14036282 | N19: =SUM(N10:N17) -> 0 | O19: =SUM(O10:O17) -> 0
A21: Component units:
B22: Criminal court fund | I22: -880645 | J22: 216403 | K22: 212751 | N22: =SUM(I22:K22) -> -451491
B23: Tourist commission | I23: -580873 | K23: 450000 | O23: =SUM(I23:L23) -> -130873
E25: Total component units | I25: =SUM(I22:I23) -> -1461518 | J25: =SUM(J22:J23) -> 216403 | K25: =SUM(K22:K23) -> 662751 | L25: =SUM(L22:L23) -> 0 | M25: =SUM(M22:M23) -> 0 | N25: =SUM(N22:N23) -> -451491 | O25: =SUM(O22:O23) -> -130873
G27: General Revenues:
H28: Taxes:
I29: Property taxes, levied for general purposes | M29: 5551166
I30: Property taxes, levied for debt service | M30: 337234
I31: Sales and use taxes, levied for general purposes | M31: 12466647 | O31: 67745
I32: Severance tax | M32: 986599
I33: Franchise tax | M33: 150603
I34: Beer taxes | M34: 9774
H35: Grants and contributions not restricted to specific programs:
I36: State revenue sharing | M36: 364486
I37: Fire insurance rebate | M37: 238229
H38: Occupational licenses and other permits | M38: 617026
H39: Interest income | M39: 290358 | N39: 46 | O39: 408
H40: Miscellaneous | M40: 286203 | N40: 100 | O40: 43730
H41: Gain on sale of capital assets | M41: 1371494
H42: Appropriation of capital expenditures from other governmental entities | M42: 25000
H43: Appropriation of capital expenditures to other governmental entities | M43: -2639616
H44: Transfers | M44: -440000 | N44: 440000
H46: Total General Revenues and transfers | M46: =SUM(M29:M44) -> 19615203 | N46: =SUM(N29:N44) -> 440146 | O46: =SUM(O29:O44) -> 111883
H48: Change in Net Position | M48: =M46+M19 -> 5578921 | N48: =N46+N25 -> -11345 | O48: =O46+O25+O19 -> -18990
E50: Net Position, January 01, 2014 | M50: 135649977 | N50: 217747 | O50: 244164
E52: Net Position, December 31,2014 | M52: =M50+M48 -> 141228898 | N52: =N50+N48 -> 206402 | O52: =O50+O48 -> 225174

Sheet Vernon
J1: Vernon Parish 2014 Statement of Activities
J2: Issued: December 31, 2014
J5: PROGRAM REVENUES | M5: NET (EXPENSE) REVENUE AND CHANGES IN NET ASSETS
A6: FUNCTIONS/PROGRAMS | I6: Expenses | J6: Charges for Services | K6: Operating Grants and Contributions | L6: Capital Grants and Contributions | M6: 2014 | N6: 2013
A7: Governmental activities:
C8: General government
D9: Legislative | I9: -534105 | M9: =SUM(I9:L9) -> -534105 | N9: -514101
D10: Judicial | I10: -1647975 | J10: 705992 | K10: 77419 | M10: =SUM(I10:L10) -> -864564 | N10: -615918
D11: Elections | I11: -51780 | M11: =SUM(I11:L11) -> -51780 | N11: -83787
D12: Finance and administrative | I12: -4195643 | J12: 280732 | M12: =SUM(I12:L12) -> -3914911 | N12: -2315748
D13: Other | I13: -2512216 | M13: =SUM(I13:L13) -> -2512216 | N13: -3128836
C14: Public safety | I14: -2473429 | K14: 222225 | M14: =SUM(I14:L14) -> -2251204 | N14: -1294314
C15: Public works | I15: -9592270 | J15: 14804 | K15: 796694 | M15: =SUM(I15:L15) -> -8780772 | N15: -8972940
C16: Health and welfare | I16: -926148 | K16: 231680 | M16: =SUM(I16:L16) -> -694468 | N16: -633567
C17: Culture and recreation | I17: -2002736 | J17: 133210 | K17: 129460 | M17: =SUM(I17:L17) -> -1740066 | N17: -1918710
C18: Economic development and assistance | I18: -1037255 | K18: 61030 | L18: 47960 | M18: =SUM(I18:L18) -> -928265 | N18: -618124
C19: Debt service | I19: -392394 | M19: =SUM(I19:L19) -> -392394 | N19: -382172
E21: Total Government Activities | I21: =SUM(I9:I19) -> -25365951 | J21: =SUM(J9:J19) -> 1134738 | K21: =SUM(K9:K19) -> 1518508 | L21: =SUM(L9:L19) -> 47960 | M21: =SUM(M9:M19) -> -22664745 | N21: =SUM(N9:N19) -> -20478217
G23: General Revenues:
H24: Taxes:
I25: Property taxes, levied for general purposes | M25: 4699300 | N25: 5068036
I26: Property taxes, levied for debt services | M26: 623417 | N26: 587004
I27: Sales and use taxes, levied for general purposes | M27: 8659295 | N27: 8614270
H28: Grants and contributions not restricted to specific purposes:
I29: Federal grant programs | M29: 1450058 | N29: 786815
I30: State grant programs | M30: 2051064 | N30: 2129891
H31: Interest and investment earnings | M31: 116649 | N31: 187464
H32: Miscellaneous | M32: 3330271 | N32: 2416157
H34: Total General Revenues and Special Items | M34: =SUM(M25:M32) -> 20930054 | N34: =SUM(N25:N32) -> 19789637
H36: Change in Net position | M36: =M34+M21 -> -1734691 | N36: =N34+N21 -> -688580
E38: Net position- beginning | M38: 54804424 | N38: 55493004
E40: Net position- ending | M40: =M38+M36 -> 53069733 | N40: =N38+N36 -> 54804424

Sheet Washington
J1: Washington Parish 2014 Statement of Activities
J2: Issued: December 31, 2014
J4: PROGRAM REVENUES | M4: Net Revenues (Expenses) Revenues & Changes in Net Position
A5: FUNCTIONS/PROGRAMS | I5: Expenses | J5: Charges for Services | K5: Operating Grants and Contributions | L5: Capital Grants and Contributions | M5: Governmental Activities | N5: Business-type Activities | O5: Total
A6: Primary Government:
B7: Government Activities:
C8: General government | I8: -3943059 | J8: 741471 | K8: 536248 | M8: =SUM(I8:L8) -> -2665340 | O8: =SUM(M8:N8) -> -2665340
C9: Public safety | I9: -1167749 | L9: 495895 | M9: =SUM(I9:L9) -> -671854 | O9: =SUM(M9:N9) -> -671854
C10: Highways and streets | I10: -4298021 | K10: 595940 | L10: 444989 | M10: =SUM(I10:L10) -> -3257092 | O10: =SUM(M10:N10) -> -3257092
C11: Health and welfare | I11: -596346 | K11: 251042 | M11: =SUM(I11:L11) -> -345304 | O11: =SUM(I11:L11) -> -345304
C12: Culture and recreation | I12: -972826 | J12: 5700 | K12: 98211 | M12: =SUM(I12:L12) -> -868915 | O12: =SUM(I12:L12) -> -868915
C13: Sanitation | I13: -618377 | M13: =SUM(I13:L13) -> -618377 | O13: =SUM(I13:L13) -> -618377
C14: Hurricane relief and restoration | I14: -315188 | K14: 28165 | M14: =SUM(I14:L14) -> -287023 | O14: =SUM(I14:L14) -> -287023
C15: Interest on long-term debt | I15: -171735 | M15: =SUM(I15:L15) -> -171735 | O15: =SUM(I15:L15) -> -171735
E17: Total Government Activities | I17: =SUM(I8:I15) -> -12083301 | J17: =SUM(J8:J15) -> 747171 | K17: =SUM(K8:K15) -> 1509606 | L17: =SUM(L8:L15) -> 940884 | M17: =SUM(M8:M15) -> -8885640 | O17: =SUM(O8:O15) -> -8885640
B19: Business-type Activities:
C20: Revenues | N20: =SUM(I20:L20) -> 0 | O20: =SUM(M20:N20) -> 0
E22: Total business-type activities | I22: =I20 -> 0 | J22: =J20 -> 0 | K22: =K20 -> 0 | L22: =L20 -> 0 | M22: 0 | N22: =SUM(N20:N20) -> 0 | O22: =SUM(O20:O20) -> 0
E24: Total primary government | I24: =I22+I17 -> -12083301 | J24: =J22+J17 -> 747171 | K24: =K22+K17 -> 1509606 | L24: =L22+L17 -> 940884 | M24: =M22+M17 -> -8885640 | N24: =N22+N17 -> 0 | O24: =O22+O17 -> -8885640
G26: General Revenues:
H27: Property taxes, levied for general purpose | M27: 4740357 | O27: =SUM(M27:N27) -> 4740357
H28: Sales taxes | M28: 6238502 | O28: =SUM(M28:N28) -> 6238502
H29: State revenue sharing | M29: 222646 | O29: =SUM(M29:N29) -> 222646
H30: Timber severance | M30: 163935 | O30: =SUM(M30:N30) -> 163935
H31: Mineral severance | M31: 11979 | O31: =SUM(M31:N31) -> 11979
H32: Other tax | M32: 16838 | O32: =SUM(M32:N32) -> 16838
H33: Fire insurance rebate | M33: 187270 | O33: =SUM(M33:N33) -> 187270
H34: Occupational licenses | M34: 530335 | O34: =SUM(M34:N34) -> 530335
H35: Unrestricted interest | M35: 9345 | N35: 3907 | O35: =SUM(M35:N35) -> 13252
H36: Loss on disposal | M36: -44325 | O36: =SUM(M36:N36) -> -44325
H37: Miscellaneous | M37: 35130 | O37: =SUM(M37:N37) -> 35130
H39: Total general revenue | M39: =SUM(M26:M37) -> 12112012 | N39: =SUM(N26:N37) -> 3907 | O39: =SUM(O27:O37) -> 12115919
H41: Change in Net Position | M41: =M39+M24 -> 3226372 | N41: =N39+N24 -> 3907 | O41: =O39+O24 -> 3230279
E43: Net Position, beginning | M43: 41975631 | N43: 192351 | O43: 42167982
E45: Net Assets- End of Year | M45: =M43+M41 -> 45202003 | N45: =N43+N41 -> 196258 | O45: =O43+O41 -> 45398261

Sheet Webster
J1: Webster Parish 2014 Statement of Activities
J2: Issued: December 31, 2014
J5: PROGRAM REVENUES | M5: NET (EXPENSE) REVENUE AND CHANGES IN NET POSITION
A6: FUNCTIONS/PROGRAMS | I6: Expenses | J6: Charges for Services | K6: Operating Grants and Contributions | L6: Capital Grants and Contributions | M6: Governmental Activities | N6: Component Units
A7: Governmental activities:
C8: General government
D9: Legislative | I9: -254822 | M9: -254822
D10: Judicial | I10: -1694896 | J10: 410426 | M10: -1284470
D11: Elections | I11: -44592 | M11: -44592
D12: Finance and administrative | I12: -1147510 | M12: -1147510
D13: Other general government | I13: -669753 | K13: 18943 | M13: -650810
C14: Public safety | I14: -2033932 | K14: 46608 | L14: 23180 | M14: -1964144
C15: Public works | I15: -2616387 | K15: 517003 | M15: -2099384
C16: Health and welfare | I16: -1022670 | M16: -1022670
C17: Culture and recreation | I17: -2509130 | J17: 32990 | M17: -2476140
C18: Economic development and assistance | I18: -37713 | M18: -37713
C19: Interest on long-term debt | I19: -27114 | M19: -27114
E21: Total Government Activities | I21: -12058519 | J21: 443416 | K21: 582554 | L21: 23180 | M21: -11009369 | N21: 0
A23: Component Units:
C24: Community services | I24: -5026795 | J24: 64233 | K24: 4673345 | N24: -289217
C25: E-911 | I25: -429800 | J25: 428264 | N25: -1536
E27: Total Component Units | I27: -5456595 | J27: 492497 | K27: 4673345 | L27: 0 | M27: 0 | N27: -290753
G29: General Revenues:
H30: Taxes:
I31: Property taxes, levied for general purposes | M31: 5575330
I32: Property taxes, levied for debt service | M32: 130
I33: Sales taxes, levied for general purposes | M33: 3226199
H34: State revenue sharing | M34: 258818
H35: Severance tax | M35: 1132148
H36: Grants and contributions not restricted for a specific purpose | M36: 403360
H37: Fees, charges and commissions | M37: 131290
H38: Licenses and permits | M38: 407410
H39: Interest and investment earnings | M39: 566607 | N39: 2771
H40: Miscellaneous | M40: 667464 | N40: -57768
H42: Total General Revenues | M42: 12368756 | N42: -54997
H44: Changes in Net position | M44: 1359387 | N44: -345750
E46: Net position- beginning | M46: 22839936 | N46: 2944560
E48: Net position- ending | M48: 24199323 | N48: 2598810

Sheet West Baton Rouge
J1: West Baton Rouge County 2014 Statement of Activities
J2: Issued: December 31, 2014
J5: PROGRAM REVENUES
A6: FUNCTIONS/PROGRAMS | I6: Expenses | J6: Charges for Services | K6: Operating Grants and Contributions | L6: Total Governmental Activities
A7: Primary Government:
B8: Government Activities:
C9: General government | I9: -6083044 | J9: 2006024 | K9: 73532 | L9: -4003488
C10: Public safety | I10: -7164567 | K10: 1842947 | L10: -5321620
C11: Public works | I11: -8042557 | K11: 2417114 | L11: -5625443
C12: Culture and recreation | I12: -2737565 | J12: 176196 | K12: 26133 | L12: -2535236
C13: Health and welfare | I13: -1678495 | K13: 211246 | L13: -1467249
C14: Economic development | I14: -110747 | K14: 627122 | L14: 516375
C15: Urban housing | I15: -330153 | K15: 330153 | L15: 0
C16: Interest and fiscal charges on long-term debt | I16: -156132 | L16: -156132
E18: Total Primary Government | I18: -26303260 | J18: 2182220 | K18: 5528247 | L18: -18592793
G20: General Revenues:
H21: Taxes:
I22: Ad valorem | L22: 8631888
I23: Sales and use | L23: 11241723
I24: Video poker | L24: 1094197
I25: Other | L25: 20735
H26: Licenses and permits | L26: 942692
H27: Interest | L27: 220272
H28: Rent | L28: 80438
H29: Miscellaneous | L29: 513770
H31: Total General Revenues | L31: 22745715
H33: Change in Net Assets | L33: 4152922
E35: Net Assets- Beginning of Year | L35: 77175141
E37: Net Assets- End of Year | L37: 81328063

Sheet West Carroll
J1: West Carroll County 2014 Statement of Activities
J2: Issued: December 31, 2014
J4: PROGRAM REVENUES
I5: Expenses | J5: Charges for Services | K5: Operating Grants and Contributions | L5: Capital Grants and Contributions | M5: NET (EXPENSE) REVENUE AND CHANGE IN NET POSITION
B7: Government Activities:
C8: General government | I8: -810475 | J8: 97666 | M8: -712809
C9: Public safety | I9: -502093 | J9: 135575 | K9: 66859 | M9: -299659
C10: Public works | I10: -4051801 | J10: 353881 | K10: 247967 | M10: -3449953
C11: Health and welfare | I11: -2885350 | J11: 2494430 | K11: 305415 | M11: -85505
C12: Culture and recreation | I12: -3425 | M12: -3425
C13: Economic development and assistance | I13: -142390 | M13: -142390
C14: Transportation | I14: -164814 | J14: 17600 | K14: 360806 | M14: 213592
E16: Total Government Activities | I16: -8560348 | J16: 3099152 | K16: 981047 | L16: 0 | M16: -4480149
G18: General Revenues:
G19: Taxes:
H20: Ad valorem:
I21: General government | M21: 326757
I22: Public works | M22: 662487
H23: Sales and use taxes:
I24: General government | M24: 640960
I25: Public works | M25: 1922880
H26: Grants and contributions not restricted to specific programs | M26: 700435
H27: Unrestricted investment earnings | M27: 96662
H28: Other revenues | M28: 756153
H30: Total General Revenues | M30: 5106334
H32: Change in Net Assets | M32: 626185
E34: Net Assets- Beginning of Year | M34: 18491710
E36: Net Assets- End of Year | M36: 19117895

Sheet West Feliciana
J1: West Feliciana County 2014 Statement of Activities
J2: Issued: December 31, 2014
M4: NET (EXPENSE) REVENUE AND CHANGE IN NET ASSETS
J5: PROGRAM REVENUES | M5: PRIMARY GOVERNMENT | P5: Component Units
A6: FUNCTIONS/PROGRAMS | I6: Expenses | J6: Charges for Services | K6: Operating Grants and Contributions | L6: Capital Grants and Contributions | M6: Governmental Activities | N6: Business-type Activities | O6: Total | P6: Business-type Activities
A7: Primary Government:
B8: Government Activities:
C9: General government | I9: -1039304 | J9: 232409 | K9: 347405 | M9: =SUM(I9:L9) -> -459490 | O9: =SUM(M9:N9) -> -459490
C10: Culture and recreation | I10: -724535 | M10: =SUM(I10:L10) -> -724535 | O10: =SUM(M10:N10) -> -724535
C11: Economic development | I11: -106919 | M11: =SUM(I11:L11) -> -106919 | O11: =SUM(M11:N11) -> -106919
C12: Health and welfare | I12: -195029 | K12: 9546 | M12: =SUM(I12:L12) -> -185483 | O12: =SUM(M12:N12) -> -185483
C13: Public safety | I13: -122258 | J13: 67450 | M13: =SUM(I13:L13) -> -54808 | O13: =SUM(M13:N13) -> -54808
C14: Public works | I14: -1711425 | M14: =SUM(I14:L14) -> -1711425 | O14: =SUM(M14:N14) -> -1711425
C15: Interest expense | I15: -45832 | M15: =SUM(I15:L15) -> -45832 | O15: =SUM(M15:N15) -> -45832
E17: Total Government Activities | I17: =SUM(I9:I15) -> -3945302 | J17: =SUM(J9:J15) -> 299859 | K17: =SUM(K9:K15) -> 356951 | L17: =SUM(L9:L15) -> 0 | M17: =SUM(M9:M15) -> -3288492 | O17: =SUM(O9:O15) -> -3288492 | P17: =SUM(P9:P15) -> 0
B19: Business-type Activities:
C20: Enterprise- waterworks District No. 13 | I20: -725417 | J20: 737443 | K20: 15146 | N20: =SUM(I20:L20) -> 27172 | O20: =SUM(M20:N20) -> 27172
C21: Enterprise- hardwood sewer | I21: -23838 | J21: 16184 | N21: =SUM(I21:L21) -> -7654 | O21: =SUM(M21:N21) -> -7654
C22: Enterprise- solitude sewer | I22: -52094 | J22: 33915 | N22: =SUM(I22:L22) -> -18179 | O22: =SUM(M22:N22) -> -18179
C23: Enterprise- turner sewer | I23: -8461 | J23: 7103 | N23: =SUM(I23:L23) -> -1358 | O23: =SUM(M23:N23) -> -1358
C24: Enterprise- independence sewer | I24: -67180 | J24: 26600 | N24: =SUM(I24:L24) -> -40580 | O24: =SUM(M24:N24) -> -40580
E26: Total Business-type Activities | I26: =SUM(I20:I24) -> -876990 | J26: =SUM(J20:J24) -> 821245 | K26: =SUM(K20:K24) -> 15146 | L26: =SUM(L20:L24) -> 0 | M26: =SUM(M20:M24) -> 0 | N26: =SUM(N20:N24) -> -40599 | O26: =SUM(O20:O24) -> -40599 | P26: =SUM(P20:P24) -> 0
E28: Total primary government | I28: =I26+I17 -> -4822292 | J28: =J26+J17 -> 1121104 | K28: =SUM(K17+K26) -> 372097 | L28: =SUM(L17+L26) -> 0 | M28: =M26+M17 -> -3288492 | N28: =N26+N17 -> -40599 | O28: =O26+O17 -> -3329091 | P28: =P26+P17 -> 0
A30: Component units: | I30: -17910996 | J30: 17378972 | P30: =SUM(I29:L30) -> -532024
E32: Total component units | I32: =SUM(I30:I30) -> -17910996 | J32: =SUM(J30:J30) -> 17378972 | K32: =SUM(K30:K30) -> 0 | L32: =SUM(L30:L30) -> 0 | M32: =SUM(M30:M30) -> 0 | N32: =SUM(N30:N30) -> 0 | O32: =SUM(O30:O30) -> 0 | P32: =SUM(P30:P30) -> -532024
G34: General Revenues:
H35: Ad valorem taxes | M35: 118927 | O35: =SUM(M35:N35) -> 118927 | P35: 510035
H36: Sales taxes | M36: 778283 | O36: =SUM(M36:N36) -> 778283 | P36: 1417091
H37: Video poker | M37: 94834 | O37: =SUM(M37:N37) -> 94834
H38: Other taxes | M38: 20430 | O38: =SUM(M38:N38) -> 20430 | P38: 22117
H39: Other | M39: 36737 | O39: =SUM(M39:N39) -> 36737 | P39: 213301
H40: Transfer (to) from other funds | M40: -14108 | N40: 14108 | O40: =SUM(M40:N40) -> 0
H42: Total General Revenues and Transfers | M42: =SUM(M35:M40) -> 1035103 | N42: =SUM(N35:N40) -> 14108 | O42: =SUM(O35:O40) -> 1049211 | P42: =SUM(P35:P40) -> 2162544
H44: Change in Net Assets | M44: =SUM(M28+M42) -> -2253389 | N44: =SUM(N28+N42) -> -26491 | O44: =SUM(O28+O42) -> -2279880 | P44: =SUM(P32+P42) -> 1630520
E46: Net Assets- Beginning | M46: 29545574 | N46: 7735284 | O46: =SUM(M46:N46) -> 37280858 | P46: 27253154
E48: Net Assets- Ending | M48: =SUM(M44,M46) -> 27292185 | N48: =N46+N44 -> 7708793 | O48: =O46+O44 -> 35000978 | P48: =P46+P44 -> 28883674

Sheet Winn
J1: Winn Parish 2014 Statement of Activities
J2: Issued: December 31, 2014
J5: PROGRAM REVENUES | M5: 2014 | N5: 2013
A6: FUNCTIONS/PROGRAMS | I6: Expenses | J6: Charges for Services | K6: Operating Grants and Contributions | L6: Capital Grants and Contributions | M6: NET (EXPENSE) REVENUE AND CHANGES IN NET ASSETS | N6: NET (EXPENSE) REVENUE AND CHANGES IN NET ASSETS
A7: Governmental activities
C8: General government
D9: Legislative | I9: -88189 | M9: -88189 | N9: -88723
D10: Judicial | I10: -554766 | J10: 137629 | M10: -417137 | N10: -344342
D11: Elections | I11: -22766 | M11: -22766 | N11: -34883
D12: Finance and administrative | I12: -997608 | M12: -997608 | N12: -859216
D13: Other | I13: -14608 | M13: -14608
C14: Public safety | I14: -981253 | K14: 264153 | M14: -717100 | N14: -878749
C15: Public works | I15: -2044207 | J15: 11563 | K15: 324421 | M15: -1708223 | N15: -1421264
C16: Health and welfare | I16: -494697 | K16: 316131 | M16: -178566 | N16: -92245
C17: Culture and recreation | I17: -758426 | J17: 9443 | K17: 21875 | M17: -727108 | N17: -794367
C18: Economic development and assistance | I18: -693812 | K18: 213 | L18: 484747 | M18: -208852 | N18: -232243
C19: Debt Service | I19: -38485 | M19: -38485 | N19: -42979
E21: Total Government Activities | I21: -6688817 | J21: 158635 | K21: 926793 | L21: 484747 | M21: -5118642 | N21: -4789011
G23: General Revenues:
H24: Taxes:
I25: Property taxes, levied for general purposes | M25: 1532407 | N25: 1535765
I26: Sales and use taxes, levied for general purposes | M26: 1881436 | N26: 1896781
H27: Licenses and permits | M27: 114752 | N27: 94883
H28: Federal grant programs- unrestricted | M28: 40325 | N28: 68659
H29: State grant programs- unrestricted | M29: 1509053 | N29: 1083999
H30: Interest and investment earnings | M30: 22154 | N30: 42440
H31: Miscellaneous | M31: 241992 | N31: 130626
H33: Total General Revenues and Special Items | M33: 5342119 | N33: 4853153
H35: Change in Net position | M35: 223477 | N35: 64142
E37: Net position- beginning of year | M37: 7563478 | N37: 7499336
E39: Net position- end of year | M39: 7786955 | N39: 7563478

Sheet Governmental Cross Sectional
A1: 2014-SOA | C1: Taxes: | H1: Other Revenue: | T1: General Government: | AA1: Other Expenditures:
B2: Revenues- | I2: Intergovernmental Transfers and Grants (out if negetive): | S2: Expenditures-
A3: Key: | C3: Property/Ad Valorem | D3: Sales/Use (includes gaming taxes, hotel-motel etc) | E3: Severance | F3: Other Tax Revenue | G3: Total Tax Revenue (SUM) | H3: State Revenue Sharing | I3: Source Not Specified | J3: State | K3: Federal | L3: Local Transfer | M3: All Other Revenue | N3: Total Other Revenue (SUM) | O3: Total Program Revenue (SUM) | P3: Total Revenues (Sum) | Q3: Accuracy | R3: Accuracy | S3: General Government (not detailed) | T3: Legislative | U3: Judicial | V3: Elections | W3: Finance and Administration | X3: Other General Government | Y3: Total General Government (SUM) | Z3: Public Safety | AA3: Public Works | AB3: Economic Development and Assistance | AC3: Health and Welfare | AD3: Culture and Recreation | AE3: Interest and fiscal charges on long-term debt (debt service) | AF3: All Other Expenditures | AG3: Total Other Expenditures (SUM) | AH3: Total Expenditures (Sum) | AI3: Accuracy | AJ3: Accuracy
A4: Error Found in Statement
A5: Parish's Statement Not Available
B6: PARISH
B7: Acadia | C7: =Acadia!M24 -> 4784714 | D7: =Acadia!M25 -> 11822706 | F7: =Acadia!M26+Acadia!M27+Acadia!M28+Acadia!M29 -> 2030768 | G7: =SUM(C7:F7) -> 18638188 | I7: =Acadia!M30 -> 443266 | L7: =Acadia!M34 -> -515000 | M7: =Acadia!M31+Acadia!M32+Acadia!M33 -> 516063 | N7: =SUM(H7:M7) -> 444329 | P7: =SUM(N7,G7,O7) -> 19082517 | Q7: =IF(P7=R7,"ok","check") -> ok | R7: =Acadia!M36 -> 19082517 | S7: =Acadia!I9 -> -3174139 | Y7: =SUM(S7:X7) -> -3174139 | Z7: =Acadia!I10 -> -1842385 | AA7: =Acadia!I11 -> -5893248 | AB7: =Acadia!I12 -> -574712 | AC7: =Acadia!I13 -> -7186309 | AD7: =Acadia!I14 -> -340726 | AE7: =Acadia!I15 -> -394773 | AG7: =SUM(Z7:AF7) -> -16232153 | AH7: =SUM(AG7,Y7) -> -19406292 | AI7: =IF(AH7=AJ7,"ok","check") -> ok | AJ7: =Acadia!I17 -> -19406292
B8: Allen | C8: =Allen!M21 -> 3151619 | D8: =Allen!M22 -> 1871684 | F8: =Allen!M23+Allen!M24 -> 1135923 | G8: =SUM(C8:F8) -> 6159226 | H8: =Allen!M25 -> 175817 | M8: =Allen!M26+Allen!M27+Allen!M29 -> 1291743 | N8: =SUM(H8:M8) -> 1467560 | P8: =SUM(N8,G8,O8) -> 7626786 | Q8: =IF(P8=R8,"ok","check") -> ok | R8: =Allen!M31 -> 7626786 | S8: =Allen!I9 -> -2194302 | Y8: =SUM(S8:X8) -> -2194302 | Z8: =Allen!I10 -> -592121 | AA8: =Allen!I11 -> -6135280 | AB8: =Allen!I12 -> -302516 | AE8: =Allen!I14 -> -4853 | AF8: =Allen!I13 -> -719358 | AG8: =SUM(Z8:AF8) -> -7754128 | AH8: =SUM(AG8,Y8) -> -9948430 | AI8: =IF(AH8=AJ8,"ok","check") -> ok | AJ8: =Allen!I16 -> -9948430
B9: Ascension | G9: =SUM(C9:F9) -> 0 | N9: =SUM(H9:M9) -> 0 | P9: =SUM(N9,G9,O9) -> 0 | Q9: =IF(P9=R9,"ok","check") -> ok | S9: =Bienville!I7 -> 0 | Y9: =SUM(S9:X9) -> 0 | Z9: =Bienville!I8 -> 0 | AG9: =SUM(Z9:AF9) -> 0 | AH9: =SUM(AG9,Y9) -> 0 | AI9: =IF(AH9=AJ9,"ok","check") -> ok
B10: Assumption | C10: =Assumption!L33+Assumption!L34 -> 9207932 | D10: =Assumption!L35 -> 1071008 | F10: =Assumption!L36 -> 1890578 | G10: =SUM(C10:F10) -> 12169518 | I10: =Assumption!L38 -> 882766 | N10: =SUM(H10:M10) -> 882766 | P10: =SUM(N10,G10,O10) -> 13052284 | Q10: =IF(P10=R10,"ok","check") -> ok | R10: =Assumption!L40 -> 13052284 | T10: =Assumption!I10 -> 583006 | U10: =Assumption!I11 -> 970822 | V10: =Assumption!I12 -> 51593 | W10: =Assumption!I13 -> 351185 | X10: =Assumption!I14 -> 167869 | Y10: =SUM(S10:X10) -> 2124475 | Z10: =Assumption!I15 -> 3430554 | AA10: =Assumption!I16 -> 5847342 | AB10: =Assumption!I20 -> 221560 | AC10: =Assumption!I18 -> 2470140 | AD10: =Assumption!I19 -> 1276963 | AG10: =SUM(Z10:AF10) -> 13246559 | AH10: =SUM(AG10,Y10) -> 15371034 | AI10: =IF(AH10=AJ10,"ok","check") -> ok | AJ10: =Assumption!I23 -> 15371034
B11: Avoyelles | C11: =Avoyelles!M19 -> 2107549 | D11: =Avoyelles!M20 -> 4528838 | G11: =SUM(C11:F11) -> 6636387 | H11: =Avoyelles!M22 -> 206873 | J11: =Avoyelles!M24 -> 519014 | M11: =Avoyelles!M23+Avoyelles!M25+Avoyelles!M26+Avoyelles!M27+Avoyelles!M28 -> 424982 | N11: =SUM(H11:M11) -> 1150869 | P11: =SUM(N11,G11,O11) -> 7787256 | Q11: =IF(P11=R11,"ok","check") -> ok | R11: =Avoyelles!M30 -> 7787256 | S11: =Avoyelles!I8 -> -1411958 | Y11: =SUM(S11:X11) -> -1411958 | Z11: =Avoyelles!I9 -> -1006255 | AA11: =Avoyelles!I10 -> -4651624 | AB11: =Avoyelles!I13 -> -296694 | AC11: =Avoyelles!I11 -> -831081 | AD11: =Avoyelles!I12 -> -629145 | AG11: =SUM(Z11:AF11) -> -7414799 | AH11: =SUM(AG11,Y11) -> -8826757 | AI11: =IF(AH11=AJ11,"ok","check") -> ok | AJ11: =Avoyelles!I15 -> -8826757
B12: Beauregard | C12: =Beauregard!M26 -> 5571237 | D12: =Beauregard!M28 -> 8947813 | F12: =Beauregard!M27+Beauregard!M30 -> 1784022 | G12: =SUM(C12:F12) -> 16303072 | H12: =Beauregard!M29 -> 125274 | M12: =Beauregard!M31+Beauregard!M33+Beauregard!M34 -> 401922 | N12: =SUM(H12:M12) -> 527196 | P12: =SUM(N12,G12,O12) -> 16830268 | Q12: =IF(P12=R12,"ok","check") -> ok | R12: =Beauregard!M36 -> 16830268 | T12: =Beauregard!I9 -> -244689 | U12: =Beauregard!I10 -> -1065401 | V12: =Beauregard!I11 -> -77658 | W12: =Beauregard!I12 -> -474076 | X12: =Beauregard!I13 -> -793563 | Y12: =SUM(S12:X12) -> -2655387 | Z12: =Beauregard!I14 -> -2444391 | AA12: =Beauregard!I15 -> -8964712 | AC12: =Beauregard!I16 -> -530539 | AD12: =Beauregard!I17 -> -1412319 | AE12: =Beauregard!I20 -> -75859 | AF12: =Beauregard!I18+Beauregard!I19 -> -1630606 | AG12: =SUM(Z12:AF12) -> -15058426 | AH12: =SUM(AG12,Y12) -> -17713813 | AI12: =IF(AH12=AJ12,"ok","check") -> ok | AJ12: =Beauregard!I22 -> -17713813
B13: Bienville | C13: =Bienville!M22+Bienville!M23+Bienville!M24 -> 4445022 | D13: =Bienville!M25 -> 2345499 | F13: =Bienville!M26 -> 32162 | G13: =SUM(C13:F13) -> 6822683 | I13: =Bienville!M27+Bienville!M29 -> 1639885 | M13: =Bienville!M28+Bienville!M30 -> 105918 | N13: =SUM(H13:M13) -> 1745803 | P13: =SUM(N13,G13,O13) -> 8568486 | Q13: =IF(P13=R13,"ok","check") -> ok | R13: =Bienville!M32 -> 8568486 | S13: =Bienville!I9 -> -2320292 | Y13: =SUM(S13:X13) -> -2320292 | Z13: =Bienville!I10 -> -672115 | AA13: =Bienville!I11 -> -6139111 | AB13: =Bienville!I14 -> -64978 | AC13: =Bienville!I12 -> -541954 | AD13: =Bienville!I13 -> -30848 | AE13: =Bienville!I15 -> -396683 | AG13: =SUM(Z13:AF13) -> -7845689 | AH13: =SUM(AG13,Y13) -> -10165981 | AI13: =IF(AH13=AJ13,"ok","check") -> ok | AJ13: =Bienville!I17 -> -10165981
B14: Bossier | G14: =SUM(C14:F14) -> 0 | N14: =SUM(H14:M14) -> 0 | P14: =SUM(N14,G14,O14) -> 0 | Q14: =IF(P14=R14,"ok","check") -> ok | Y14: =SUM(S14:X14) -> 0 | AG14: =SUM(Z14:AF14) -> 0 | AH14: =SUM(AG14,Y14) -> 0 | AI14: =IF(AH14=AJ14,"ok","check") -> ok
B15: Caddo | C15: =Caddo!M34+Caddo!M35 -> 59560849 | D15: =Caddo!M36+Caddo!M37+Caddo!M40 -> 15864026 | G15: =SUM(C15:F15) -> 75424875 | I15: =Caddo!M41 -> 1273355 | M15: =Caddo!M42+Caddo!M43+Caddo!M46 -> 2720535 | N15: =SUM(H15:M15) -> 3993890 | P15: =SUM(N15,G15,O15) -> 79418765 | Q15: =IF(P15=R15,"ok","check") -> ok | R15: =Caddo!M48 -> 79418765 | S15: =Caddo!I9 -> -9616443 | Y15: =SUM(S15:X15) -> -9616443 | AA15: =Caddo!I12 -> -23738530 | AB15: =Caddo!I16 -> -4221537 | AC15: =Caddo!I11 -> -15373363 | AD15: =Caddo!I15 -> -15957204 | AE15: =Caddo!I17 -> -2126069 | AF15: =Caddo!I10+Caddo!I13+Caddo!I14 -> -31763746 | AG15: =SUM(Z15:AF15) -> -93180449 | AH15: =SUM(AG15, Y15) -> -102796892 | AI15: =IF(AH15=AJ15,"ok","check") -> ok | AJ15: =Caddo!I19 -> -102796892
B16: Calcasieu | G16: =SUM(C16:F16) -> 0 | N16: =SUM(H16:M16) -> 0 | P16: =SUM(N16,G16,O16) -> 0 | Q16: =IF(P16=R16,"ok","check") -> ok | Y16: =SUM(S16:X16) -> 0 | AG16: =SUM(Z16:AF16) -> 0 | AH16: =SUM(AG16,Y16) -> 0 | AI16: =IF(AH16=AJ16,"ok","check") -> ok
B17: Caldwell | C17: =Caldwell!M19+Caldwell!M20+Caldwell!M21+Caldwell!M23 -> 1737092 | D17: =Caldwell!M25+Caldwell!M26 -> 1952537 | F17: =Caldwell!M27 -> 9870 | G17: =SUM(C17:F17) -> 3699499 | M17: =Caldwell!M28+Caldwell!M29 -> 33960 | N17: =SUM(H17:M17) -> 33960 | P17: =SUM(N17,G17,O17) -> 3733459 | Q17: =IF(P17=R17,"ok","check") -> ok | R17: =Caldwell!M31 -> 3733459 | Y17: =SUM(S17:X17) -> 0 | AG17: =SUM(Z17:AF17) -> 0 | AH17: =SUM(AG17,Y17) -> 0 | AI17: =IF(AH17=AJ17,"ok","check") -> ok
B18: Cameron | C18: =Cameron!L26 -> 7216305 | F18: =Cameron!L27 -> 994588 | G18: =SUM(C18:F18) -> 8210893 | H18: =Cameron!L32 -> 40173 | J18: =Cameron!L31 -> 5217490 | M18: =Cameron!L28+Cameron!L29+Cameron!L33+Cameron!L34+Cameron!L35 -> 1216304 | N18: =SUM(H18:M18) -> 6473967 | P18: =SUM(N18,G18,O18) -> 14684860 | Q18: =IF(P18=R18,"ok","check") -> ok | R18: =Cameron!L37 -> 14684860 | T18: =Cameron!I10 -> -232074 | U18: =Cameron!I11 -> -1318873 | V18: =Cameron!I12 -> -6843 | W18: =Cameron!I13 -> -1601427 | X18: =Cameron!I14 -> -2668369 | Y18: =SUM(S18:X18) -> -5827586 | Z18: =Cameron!I16 -> -2803731 | AA18: =Cameron!I17 -> -6533293 | AB18: =Cameron!I20 -> -1848271 | AC18: =Cameron!I19 -> -512083 | AD18: =Cameron!I18 -> -1924589 | AE18: =Cameron!I15 -> -105744 | AG18: =SUM(Z18:AF18) -> -13727711 | AH18: =SUM(AG18,Y18) -> -19555297 | AI18: =IF(AH18=AJ18,"ok","check") -> ok | AJ18: =Cameron!I22 -> -19555297
B19: Catahoula | C19: =Catahoula!M19 -> 864032 | D19: =Catahoula!M20 -> 1753095 | F19: =Catahoula!M21 -> 5214 | G19: =SUM(C19:F19) -> 2622341 | I19: =Catahoula!M22 -> 337458 | M19: =Catahoula!M23+Catahoula!M24+Catahoula!M25 -> 9635 | N19: =SUM(H19:M19) -> 347093 | P19: =SUM(N19,G19,O19) -> 2969434 | Q19: =IF(P19=R19,"ok","check") -> ok | R19: =Catahoula!M27 -> 2969434 | S19: =Catahoula!I8 -> -722386 | Y19: =SUM(S19:X19) -> -722386 | Z19: =Catahoula!I9 -> -405469 | AA19: =Catahoula!I10 -> -1875439 | AB19: =Catahoula!I13 -> -2792 | AC19: =Catahoula!I11 -> -240465 | AD19: =Catahoula!I12 -> -352181 | AE19: =Catahoula!I14 -> -4485 | AG19: =SUM(Z19:AF19) -> -2880831 | AH19: =SUM(AG19,Y19) -> -3603217 | AI19: =IF(AH19=AJ19,"ok","check") -> ok | AJ19: =Catahoula!I16 -> -3603217
B20: Claiborne | C20: =Claiborne!M20+Claiborne!M21+Claiborne!M22 -> 3085488 | D20: =Claiborne!M23 -> 870929 | F20: =Claiborne!M24 -> 8821 | G20: =SUM(C20:F20) -> 3965238 | I20: =Claiborne!M25 -> 1613286 | M20: =Claiborne!M26+Claiborne!M27+Claiborne!M28+Claiborne!M29+Claiborne!M30 -> 304677 | N20: =SUM(H20:M20) -> 1917963 | P20: =SUM(N20,G20,O20) -> 5883201 | Q20: =IF(P20=R20,"ok","check") -> ok | R20: =Claiborne!M32 -> 5883201 | S20: =Claiborne!I7 -> -1522797 | Y20: =SUM(S20:X20) -> -1522797 | Z20: =Claiborne!I8 -> -317573 | AA20: =Claiborne!I9 -> -3489014 | AB20: =Claiborne!I12 -> -60013 | AC20: =Claiborne!I10 -> -643674 | AD20: =Claiborne!I11 -> -676727 | AE20: =Claiborne!I14 -> -41425 | AF20: =Claiborne!I13 -> -5200 | AG20: =SUM(Z20:AF20) -> -5233626 | AH20: =SUM(AG20,Y20) -> -6756423 | AI20: =IF(AH20=AJ20,"ok","check") -> ok | AJ20: =Claiborne!I16 -> -6756423
B21: Concordia | C21: =Concordia!M24 -> 1785913 | D21: =Concordia!M25 -> 2856287 | F21: =Concordia!M26 -> 35256 | G21: =SUM(C21:F21) -> 4677456 | H21: =Concordia!M28 -> 107518 | M21: =SUM(Concordia!M29+Concordia!M30+Concordia!M31+Concordia!M32+Concordia!M33+Concordia!M34+Concordia!M35) -> 1992362 | N21: =SUM(H21:M21) -> 2099880 | P21: =SUM(N21, G21, O21) -> 6777336 | Q21: =IF(P21=R21,"ok","check") -> ok | R21: =Concordia!M37 -> 6777336 | T21: =Concordia!I9 -> -236369 | U21: =Concordia!I10 -> -635894 | V21: =Concordia!I11 -> -45930 | W21: =Concordia!I12 -> -337662 | X21: =Concordia!I13 -> -774236 | Y21: =SUM(S21:X21) -> -2030091 | Z21: =Concordia!I14 -> -197180 | AA21: =Concordia!I15 -> -3094988 | AB21: =Concordia!I17 -> -94869 | AC21: =Concordia!I16 -> -275734 | AE21: =Concordia!I18 -> -384541 | AG21: =SUM(Z21:AF21) -> -4047312 | AH21: =SUM(AG21, Y21) -> -6077403 | AI21: =IF(AH21=AJ21,"ok","check") -> ok | AJ21: =Concordia!I20 -> -6077403
B22: DeSoto | C22: =DeSoto!M34 -> 12327537 | D22: =DeSoto!M35+DeSoto!M37+DeSoto!M38 -> 7586850 | F22: =DeSoto!M36 -> 1233958 | G22: =SUM(C22:F22) -> 21148345 | H22: =DeSoto!M40 -> 51600 | L22: =DeSoto!M43 -> -19350 | M22: =DeSoto!M39+DeSoto!M41+DeSoto!M42 -> 1529410 | N22: =SUM(H22:M22) -> 1561660 | P22: =SUM(N22, G22, O22) -> 22710005 | Q22: =IF(P22=R22,"ok","check") -> ok | R22: =DeSoto!M45 -> 22710005 | T22: =DeSoto!I10 -> -400475 | U22: =DeSoto!I11 -> -2693579 | V22: =DeSoto!I12 -> -101110 | W22: =DeSoto!I13 -> -2029058 | X22: =DeSoto!I14 -> -854448 | Y22: =SUM(S22:X22) -> -6078670 | Z22: =DeSoto!I15 -> -1096246 | AA22: =DeSoto!I16+DeSoto!I21 -> -11260411 | AB22: =DeSoto!I20 -> -3299353 | AC22: =DeSoto!I19 -> -2206951 | AD22: =DeSoto!I18 -> -279817 | AE22: =DeSoto!I23 -> -255 | AF22: =DeSoto!I17+DeSoto!I22 -> -4404809 | AG22: =SUM(Z22:AF22) -> -22547842 | AH22: =SUM(AG22, Y22) -> -28626512 | AI22: =IF(AH22=AJ22,"ok","check") -> ok | AJ22: =DeSoto!I25 -> -28626512
B23: East Baton Rouge | C23: ='East Baton Rouge'!M40 -> 98252896 | D23: ='East Baton Rouge'!M42+'East Baton Rouge'!M46 -> 232998426 | F23: ='East Baton Rouge'!M41+'East Baton Rouge'!M43+'East Baton Rouge'!M44+'East Baton Rouge'!M45+'East Baton Rouge'!M47 -> 42854679 | G23: =SUM(C23:F23) -> 374106001 | I23: ='East Baton Rouge'!M49 -> 5551706 | L23: ='East Baton Rouge'!M52 -> 886331 | M23: ='East Baton Rouge'!M48+'East Baton Rouge'!M50+'East Baton Rouge'!M51 -> 1244397 | N23: =SUM(H23:M23) -> 7682434 | P23: =SUM(N23,G23,O23) -> 381788435 | Q23: =IF(P23=R23,"ok","check") -> ok | R23: ='East Baton Rouge'!M54 -> 381788435 | S23: ='East Baton Rouge'!I9 -> -99148612 | Y23: =SUM(S23:X23) -> -99148612 | Z23: ='East Baton Rouge'!I10 -> -233011923 | AA23: ='East Baton Rouge'!I11 -> -66920723 | AC23: ='East Baton Rouge'!I13 -> -9796865 | AD23: ='East Baton Rouge'!I14 -> -43762277 | AE23: ='East Baton Rouge'!I16 -> -13413000 | AF23: ='East Baton Rouge'!I12+'East Baton Rouge'!I15 -> -46090050 | AG23: =SUM(Z23:AF23) -> -412994838 | AH23: =SUM(AG23,Y23) -> -512143450 | AI23: =IF(AH23=AJ23,"ok","check") -> ok | AJ23: ='East Baton Rouge'!I18 -> -512143450
B24: East Carroll | C24: ='East Carroll'!M32+'East Carroll'!M33 -> 2302676 | D24: ='East Carroll'!M34 -> 657398 | F24: ='East Carroll'!M36 -> 34249 | G24: =SUM(C24:F24) -> 2994323 | H24: ='East Carroll'!M35 -> 47309 | I24: ='East Carroll'!M37 -> 60182 | M24: ='East Carroll'!M38+'East Carroll'!M39+'East Carroll'!M40 -> 280500 | N24: =SUM(H24:M24) -> 387991 | P24: =SUM(N24,G24,O24) -> 3382314 | Q24: =IF(P24=R24,"ok","check") -> ok | R24: ='East Carroll'!M42 -> 3382314 | T24: ='East Carroll'!I10 -> -39938 | U24: ='East Carroll'!I11 -> -613097 | V24: ='East Carroll'!I12 -> -52551 | W24: ='East Carroll'!I13 -> -219715 | X24: ='East Carroll'!I14 -> -1092292 | Y24: =SUM(S24:X24) -> -2017593 | Z24: ='East Carroll'!I15 -> -452380 | AA24: ='East Carroll'!I16+'East Carroll'!I20 -> -1589908 | AB24: ='East Carroll'!I19 -> -6860 | AC24: ='East Carroll'!I17 -> -136634 | AD24: ='East Carroll'!I18 -> -349005 | AE24: ='East Carroll'!I21 -> -19777 | AG24: =SUM(Z24:AF24) -> -2554564 | AH24: =SUM(AG24,Y24) -> -4572157 | AI24: =IF(AH24=AJ24,"ok","check") -> ok | AJ24: ='East Carroll'!I23 -> -4572157
B25: East Feliciana | C25: ='East Feliciana'!M20 -> 836005.3 | D25: ='East Feliciana'!M22 -> 4076159.5 | F25: ='East Feliciana'!M21 -> 420876.36 | G25: =SUM(C25:F25) -> 5333041.2 | H25: ='East Feliciana'!M18 -> 406135.5 | M25: ='East Feliciana'!M23+'East Feliciana'!M24+'East Feliciana'!M25+'East Feliciana'!M26+'East Feliciana'!M27+'East Feliciana'!M28+'East Feliciana'!M29 -> 574781.7 | N25: =SUM(H25:M25) -> 980917.2 | P25: =SUM(N25,G25,O25) -> 6313958.4 | Q25: =IF(P25=R25,"ok","check") -> ok | R25: ='East Feliciana'!M31 -> 6313958.4 | S25: ='East Feliciana'!I8 -> -950109.55 | Y25: =SUM(S25:X25) -> -950109.55 | Z25: ='East Feliciana'!I12 -> -1169097.2 | AA25: ='East Feliciana'!I13 -> -2638111.1 | AB25: ='East Feliciana'!I10 -> -9587.67 | AC25: ='East Feliciana'!I11 -> -329817.02 | AD25: ='East Feliciana'!I9 -> -4586.94 | AG25: =SUM(Z25:AF25) -> -4151200 | AH25: =SUM(AG25,Y25) -> -5101309.5 | AI25: =IF(AH25=AJ25,"ok","check") -> ok | AJ25: ='East Feliciana'!I15 -> -5101309.5
B26: Evangeline | C26: =Evangeline!M28 -> 5857491 | D26: =Evangeline!M29 -> 3282902 | G26: =SUM(C26:F26) -> 9140393 | H26: =Evangeline!M32 -> 233286 | I26: =Evangeline!M31+Evangeline!M33+Evangeline!M34 -> 1386450 | M26: =Evangeline!M35+Evangeline!M36 -> 674401 | N26: =SUM(H26:M26) -> 2294137 | P26: =SUM(N26,G26,O26) -> 11434530 | Q26: =IF(P26=R26,"ok","check") -> ok | R26: =Evangeline!M38 -> 11434530 | S26: =Evangeline!I8 -> -2303564 | Y26: =SUM(S26:X26) -> -2303564 | Z26: =Evangeline!I9 -> -844114 | AA26: =Evangeline!I10 -> -7176279 | AB26: =Evangeline!I13 -> -213035 | AC26: =Evangeline!I11 -> -483095 | AD26: =Evangeline!I12 -> -1293548 | AE26: =Evangeline!I14 -> -1087451 | AG26: =SUM(Z26:AF26) -> -11097522 | AH26: =SUM(AG26,Y26) -> -13401086 | AI26: =IF(AH26=AJ26,"ok","check") -> ok | AJ26: =Evangeline!I16 -> -13401086
B27: Franklin | C27: =Franklin!M19 -> 3303526 | D27: =Franklin!M20 -> 3817919 | F27: =Franklin!M22+Franklin!M23 -> 96534 | G27: =SUM(C27:F27) -> 7217979 | I27: =Franklin!M24 -> 36450 | L27: =Franklin!M21 -> 176711 | M27: =Franklin!M25+Franklin!M26+Franklin!M27+Franklin!M28 -> 275767 | N27: =SUM(H27:M27) -> 488928 | P27: =SUM(N27,G27,O27) -> 7706907 | Q27: =IF(P27=R27,"ok","check") -> ok | R27: =Franklin!M30 -> 7706907 | S27: =Franklin!I8 -> -781880 | Y27: =SUM(S27:X27) -> -781880 | Z27: =Franklin!I9 -> -453160 | AA27: =Franklin!I10 -> -6091341 | AB27: =Franklin!I13 -> -4065049 | AC27: =Franklin!I11 -> -601056 | AD27: =Franklin!I12 -> -132615 | AG27: =SUM(Z27:AF27) -> -11343221 | AH27: =SUM(AG27,Y27) -> -12125101 | AI27: =IF(AH27=AJ27,"ok","check") -> ok | AJ27: =Franklin!I15 -> -12125101
B28: Grant | C28: ='Grant '!N37 -> 889307 | D28: ='Grant '!N38 -> 1159486 | F28: ='Grant '!N39+'Grant '!N40+'Grant '!N41+'Grant '!N42 -> 901965 | G28: =SUM(C28:F28) -> 2950758 | N28: =SUM(H28:M28) -> 0 | P28: =SUM(N28,G28,O28) -> 2950758 | Q28: =IF(P28=R28,"ok","check") -> ok | R28: ='Grant '!N44 -> 2950758 | T28: ='Grant '!I9 -> -213011 | U28: ='Grant '!I10 -> -606967 | W28: ='Grant '!I11 -> -235770 | X28: ='Grant '!I12 -> -279567 | Y28: =SUM(S28:X28) -> -1335315 | Z28: ='Grant '!I13 -> -328726 | AA28: ='Grant '!I15+'Grant '!I16+'Grant '!I18+'Grant '!I19 -> -2891669 | AB28: ='Grant '!I20 -> -34600 | AC28: ='Grant '!I21 -> -102862 | AD28: ='Grant '!I22 -> -11066 | AG28: =SUM(Z28:AF28) -> -3368923 | AH28: =SUM(Y28,AG28) -> -4704238 | AI28: =IF(AH28=AJ28,"ok","check") -> ok | AJ28: ='Grant '!I24 -> -4704238
B29: Iberia | C29: =Iberia!M25 -> 10403521 | D29: =Iberia!M26+Iberia!M27 -> 7385665 | F29: =Iberia!M28+Iberia!M30 -> 2071075 | G29: =SUM(C29:F29) -> 19860261 | H29: =Iberia!M32 -> 443269 | M29: =Iberia!M33+Iberia!M34 -> 544484 | N29: =SUM(H29:M29) -> 987753 | P29: =SUM(N29,G29,O29) -> 20848014 | Q29: =IF(P29=R29,"ok","check") -> ok | R29: =Iberia!M36 -> 20848014 | S29: =Iberia!I9 -> -5786600 | Y29: =SUM(S29:X29) -> -5786600 | Z29: =Iberia!I10 -> -4622943 | AA29: =Iberia!I11 -> -12090667 | AB29: =Iberia!I15 -> -425794 | AC29: =Iberia!I12 -> -6611112 | AD29: =Iberia!I13 -> -2835116 | AE29: =Iberia!I17 -> -359539 | AF29: =Iberia!I14+Iberia!I16 -> -4196496 | AG29: =SUM(Z29:AF29) -> -31141667 | AH29: =SUM(AG29,Y29) -> -36928267 | AI29: =IF(AH29=AJ29,"ok","check") -> ok | AJ29: =Iberia!I19 -> -36928267
B30: Iberville | C30: =Iberville!M33 -> 5872715 | D30: =Iberville!M34+Iberville!M35+Iberville!M37 -> 19585073 | F30: =Iberville!M36 -> 16419 | G30: =SUM(C30:F30) -> 25474207 | I30: =Iberville!M38 -> 1089548 | L30: =Iberville!M41 -> 81135 | M30: =Iberville!M39+Iberville!M40 -> 5278314 | N30: =SUM(H30:M30) -> 6448997 | P30: =SUM(N30,G30,O30) -> 31923204 | Q30: =IF(P30=R30,"ok","check") -> ok | R30: =Iberville!M44 -> 31923204 | S30: =Iberville!I9 -> -21155383 | Y30: =SUM(S30:X30) -> -21155383 | Z30: =Iberville!I10 -> -4093206 | AA30: =Iberville!I11 -> -12246757 | AB30: =Iberville!I13 -> -267660 | AC30: =Iberville!I12 -> -2311952 | AD30: =Iberville!I14 -> -824014 | AE30: =Iberville!I15 -> -691880 | AG30: =SUM(Z30:AF30) -> -20435469 | AH30: =SUM(AG30,Y30) -> -41590852 | AI30: =IF(AH30=AJ30,"ok","check") -> ok | AJ30: =Iberville!I17 -> -41590852
B31: Jackson | C31: =Jackson!M24 -> 4409812 | D31: =Jackson!M25 -> 2222337 | F31: =Jackson!M27+Jackson!M28 -> 958342 | G31: =SUM(C31:F31) -> 7590491 | L31: =Jackson!M26 -> 80284 | M31: =Jackson!M29+Jackson!M30+Jackson!M31 -> 274867 | N31: =SUM(H31:M31) -> 355151 | P31: =SUM(N31,G31,O31) -> 7945642 | Q31: =IF(P31=R31,"ok","check") -> ok | R31: =Jackson!M33 -> 7945642 | T31: =Jackson!I10 -> -120698 | U31: =Jackson!I11 -> -266805 | V31: =Jackson!I12 -> -24856 | W31: =Jackson!I13 -> -266474 | X31: =Jackson!I14 -> -530878 | Y31: =SUM(S31:X31) -> -1209711 | Z31: =Jackson!I15 -> -700715 | AA31: =Jackson!I16 -> -4985065 | AC31: =Jackson!I17 -> -255022 | AD31: =Jackson!I18 -> -1312896 | AG31: =SUM(Z31:AF31) -> -7253698 | AH31: =SUM(AG31,Y31) -> -8463409 | AI31: =IF(AH31=AJ31,"ok","check") -> ok | AJ31: =Jackson!I20 -> -8463409
B32: Jefferson | C32: =Jefferson!M41 -> 191583 | D32: =Jefferson!M44+Jefferson!M45+Jefferson!M46 -> 157184 | F32: =Jefferson!M42+Jefferson!M43+Jefferson!M48 -> 1609 | G32: =SUM(C32:F32) -> 350376 | L32: =Jefferson!M52 -> -1541 | M32: =SUM(Jefferson!M49+Jefferson!M50) -> 34460 | N32: =SUM(H32:M32) -> 32919 | P32: =SUM(N32,G32,O32) -> 383295 | Q32: =IF(P32=R32,"ok","check") -> ok | R32: =Jefferson!M54 -> 383295 | S32: =Jefferson!I9 -> -70717 | Y32: =SUM(S32:X32) -> -70717 | Z32: =Jefferson!I10 -> -100987 | AA32: =Jefferson!I11+Jefferson!I12 -> -151149 | AC32: =Jefferson!I13 -> -47945 | AD32: =Jefferson!I14 -> -48043 | AE32: =Jefferson!I17 -> -19721 | AF32: =Jefferson!I16 -> -9380 | AG32: =SUM(Z32:AF32) -> -377225 | AH32: =SUM(AG32,Y32) -> -447942 | AI32: =IF(AH32=AJ32,"ok","check") -> ok | AJ32: =Jefferson!I19 -> -447942
