Workbook

Sheet Acadia
D1: Acadia PARISH POLICE JURY
D2: Capital Assets
D3: For the Year Ended December 31, 2014
G5: Beginning Balance | H5: Increases | I5: Decreases | J5: Ending Balance | K5: Cross Sectional
A7: Governmental Activities:
B8: Capital assets, not being depreciated:
C9: Land | G9: 1329008 | J9: =SUM(G9:I9) -> 1329008 | K9: =SUM(J9) -> 1329008
C10: Construction in progress | G10: 10247945 | H10: 1234905 | I10: -10866347 | J10: =SUM(G10:I10) -> 616503 | K10: =SUM(J10) -> 616503
D12: Total capital assets, not being depreciated | G12: =SUM(G8:G11) -> 11576953 | H12: =SUM(H8:H11) -> 1234905 | I12: =SUM(I8:I11) -> -10866347 | J12: =SUM(J8:J11) -> 1945511
A14: Capital assets being depreciated:
B15: Buildings and improvements | G15: 24424668 | H15: 334646 | I15: -3155 | J15: =SUM(G15:I15) -> 24756159
B16: Machinery and equipment | G16: 12027545 | H16: 319975 | I16: -267123 | J16: =SUM(G16:I16) -> 12080397
B17: Improvements, other than buildings | G17: 764577 | H17: 9334 | J17: =SUM(G17:I17) -> 773911
B18: Infrastructure | G18: 37801628 | H18: 10763793 | I18: -139702 | J18: =SUM(G18:I18) -> 48425719
D20: Total capital assets being depreciated | G20: =SUM(G15:G19) -> 75018418 | H20: =SUM(H15:H19) -> 11427748 | I20: =SUM(I15:I19) -> -409980 | J20: =SUM(J15:J19) -> 86036186
A22: Less accumulated depreciation for:
B23: Buildings and improvements | G23: -6749388 | H23: -794092 | I23: 3155 | J23: =SUM(G23:I23) -> -7540325 | K23: =J15+J23 -> 17215834
B24: Machinery and equipment | G24: -6555117 | H24: -803154 | I24: 229407 | J24: =SUM(G24:I24) -> -7128864 | K24: =J16+J24 -> 4951533
B25: Improvements, other than buildings | G25: -405220 | H25: -9435 | J25: =SUM(G25:I25) -> -414655 | K25: =J17+J25 -> 359256
B26: Infrastructure | G26: -18415360 | H26: -1606267 | I26: 116485 | J26: =SUM(G26:I26) -> -19905142 | K26: =J18+J26 -> 28520577
D28: Total accumulated depreciation | G28: =SUM(G23:G27) -> -32125085 | H28: =SUM(H23:H27) -> -3212948 | I28: =SUM(I23:I27) -> 349047 | J28: =SUM(J23:J27) -> -34988986
B30: Total capital assets being depreciated, net | G30: =G20+G28 -> 42893333 | H30: =H20+H28 -> 8214800 | I30: =I20+I28 -> -60933 | J30: =J20+J28 -> 51047200
B32: Governmental activities capital assets, net | G32: =G30+G12 -> 54470286 | H32: =H30+H12 -> 9449705 | I32: =I30+I12 -> -10927280 | J32: =J30+J12 -> 52992711 | K32: =SUM(K23:K26,K9:K10) -> 52992711

Sheet Allen
D1: Acadia PARISH POLICE JURY
D2: Capital Assets
D3: For the Year Ended December 31, 2014
G5: Beginning Balance | H5: Increases | I5: Decreases | J5: Ending Balance | K5: Cross Sectional
A7: Governmental Activities:
B8: Capital assets, not being depreciated:
C9: Construction in progress | H9: 98703 | J9: 98703 | K9: =J9 -> 98703
C10: Land | G10: 572300 | J10: 572300 | K10: =J10 -> 572300
D12: Total capital assets, not being depreciated | G12: =SUM(G9:G10) -> 572300 | H12: =SUM(H9:H10) -> 98703 | I12: =SUM(I9:I10) -> 0 | J12: =SUM(J9:J10) -> 671003
A14: Capital assets being depreciated:
B15: Buildings | G15: 4547339 | H15: 48000 | J15: =SUM(G15:I15) -> 4595339
B16: Improvements, other than buildings | G16: 5853055 | H16: 2530 | J16: =SUM(G16:I16) -> 5855585
B17: Furniture and fixtures | G17: 390033 | H17: 41803 | J17: =SUM(G17:I17) -> 431836
B18: Vehicles | G18: 819449 | H18: 4800 | J18: =SUM(G18:I18) -> 824249
B19: Machinery and equipment | G19: 3254223 | H19: 266982 | I19: -39000 | J19: =SUM(G19:I19) -> 3482205
B20: Infrastructure | G20: 28219912 | J20: =SUM(G20:I20) -> 28219912
D21: Total capital assets being depreciated | G21: =SUM(G15:G20) -> 43084011 | H21: =SUM(H15:H20) -> 364115 | I21: =SUM(I15:I20) -> -39000 | J21: =SUM(J15:J20) -> 43409126
A23: Less accumulated depreciation for:
B24: Buildings | G24: 1787109 | H24: 102409 | J24: =SUM(G24:I24) -> 1889518 | K24: =SUM(J15-J24) -> 2705821
B25: Improvements, other than buildings | G25: 2181213 | H25: 195592 | J25: =SUM(G25:I25) -> 2376805 | K25: =SUM(J16-J25) -> 3478780
B26: Furniture and fixtures | G26: 311630 | H26: 31795 | J26: =SUM(G26:I26) -> 343425 | K26: =SUM(J17-J26) -> 88411
B27: Vehicles | G27: 618959 | H27: 48526 | J27: =SUM(G27:I27) -> 667485 | K27: =SUM(J18-J27) -> 156764
B28: Machinery and equipment | G28: 2229894 | H28: 192008 | I28: -39000 | J28: =SUM(G28:I28) -> 2382902 | K28: =SUM(J19-J28) -> 1099303
B29: Infrastructure | G29: 11861750 | H29: 584415 | J29: =SUM(G29:I29) -> 12446165 | K29: =SUM(J20-J29) -> 15773747
D30: Total accumulated depreciation | G30: =SUM(G24:G29) -> 18990555 | H30: =SUM(H24:H29) -> 1154745 | I30: =SUM(I24:I29) -> -39000 | J30: =SUM(J24:J29) -> 20106300
B32: Total capital assets being depreciated, net | G32: 24093456 | H32: -790630 | J32: 23302826
B35: Governmental activities capital assets, net | G35: =SUM(G32+G12) -> 24665756 | H35: =SUM(H32+H12) -> -691927 | I35: =SUM(I32+I12) -> 0 | J35: =SUM(J32+J12) -> 23973829 | K35: =SUM(K9:K29) -> 23973829

Sheet Ascension
D1: ASCENSION PARISH POLICE JURY
D2: Capital Assets
D3: For the Year Ended December 31, 2014
I5: Beginning Balance | J5: Increases | K5: Decreases | L5: Ending Balance | M5: Cross Sectional
A7: Governmental Activities:
B8: Capital assets, not being depreciated:
C9: Land | I9: 17314 | J9: 54 | K9: -41 | L9: =SUM(I9:K9) -> 17327 | M9: =SUM(L9) -> 17327
C10: Construction in progress | I10: 55786 | J10: 9349 | K10: -49635 | L10: =SUM(I10:K10) -> 15500 | M10: =SUM(L10) -> 15500
D12: Total capital assets, not being depreciated | I12: =SUM(I8:I11) -> 73100 | J12: =SUM(J8:J11) -> 9403 | K12: =SUM(K8:K11) -> -49676 | L12: =SUM(L8:L11) -> 32827
A14: Capital assets being depreciated:
B15: Buildings | I15: 62699 | J15: 41022 | K15: -491 | L15: =SUM(I15:K15) -> 103230
B16: Vehicles | I16: 13162 | J16: 1566 | K16: -884 | L16: =SUM(I16:K16) -> 13844
B17: Equipment | I17: 12086 | J17: 1795 | K17: -440 | L17: =SUM(I17:K17) -> 13441
B18: Furniture and fixtures | I18: 1127 | K18: -6 | L18: =SUM(I18:K18) -> 1121
B19: Library materials | I19: 2791 | J19: 453 | K19: -766 | L19: =SUM(I19:K19) -> 2478
B20: Infrastructure | I20: 216285 | J20: 16109 | K20: -3671 | L20: =SUM(I20:K20) -> 228723
D22: Total capital assets being depreciated | I22: =SUM(I15:I21) -> 308150 | J22: =SUM(J15:J21) -> 60945 | K22: =SUM(K15:K21) -> -6258 | L22: =SUM(L15:L20) -> 362837
A24: Less accumulated depreciation for:
B25: Buildings | I25: -20896 | J25: -2642 | K25: 0 | L25: =SUM(I25:K25) -> -23538 | M25: =SUM(L25,L15) -> 79692
B26: Vehicles | I26: -8988 | J26: -691 | K26: 826 | L26: =SUM(I26:K26) -> -8853 | M26: =SUM(L26,L16) -> 4991
B27: Equipment | I27: -9409 | J27: -939 | K27: 415 | L27: =SUM(I27:K27) -> -9933 | M27: =SUM(L27,L17) -> 3508
B28: Furniture and fixtures | I28: -645 | J28: -85 | K28: 6 | L28: =SUM(I28:K28) -> -724 | M28: =SUM(L28,L18) -> 397
B29: Library materials | I29: -1825 | J29: -496 | K29: 766 | L29: =SUM(I29:K29) -> -1555 | M29: =SUM(L29,L19) -> 923
B30: Infrastructure | I30: -129923 | J30: -10934 | K30: 3602 | L30: =SUM(I30:K30) -> -137255 | M30: =SUM(L30,L20) -> 91468
D32: Total accumulated depreciation | I32: =SUM(I25:I31) -> -171686 | J32: =SUM(J25:J31) -> -15787 | K32: =SUM(K25:K31) -> 5615 | L32: =SUM(L25:L31) -> -181858
B34: Total capital assets being depreciated, net | I34: =I22+I32 -> 136464 | J34: =J22+J32 -> 45158 | K34: =K22+K32 -> -643 | L34: =L22+L32 -> 180979
B36: Governmental activities capital assets, net | I36: =I32+I22+I12 -> 209564 | J36: =J32+J22+J12 -> 54561 | K36: =K32+K22+K12 -> -50319 | L36: =L32+L22+L12 -> 213806 | M36: =SUM(M25:M30,M9:M10) -> 213806
I39: Beginning Balance | J39: Increases | K39: Decreases | L39: Ending Balance
A40: Business-Type Activities:
B41: Capital assets, not being depreciated:
C42: Land | I42: 670 | J42: 0 | K42: 0 | L42: =SUM(I42:K42) -> 670 | M42: =SUM(L42) -> 670
C43: Construction in progress | I43: 271 | J43: 736 | K43: 0 | L43: =SUM(I43:K43) -> 1007 | M43: =SUM(L43) -> 1007
D45: Total capital assets, not being depreciated | I45: =SUM(I41:I44) -> 941 | J45: =SUM(J41:J44) -> 736 | K45: =SUM(K41:K44) -> 0 | L45: =SUM(L41:L44) -> 1677
B47: Capital assets, depreciable:
C48: Sewer systems | I48: 5779 | J48: 0 | K48: 0 | L48: =SUM(I48:K48) -> 5779
C49: Water systems | I49: 765 | K49: 0 | L49: =SUM(I49:K49) -> 765
C50: Machinery & Equipment | I50: 141 | J50: 40 | L50: =SUM(I50:K50) -> 181
C51: Lamar Dixon Expo Center | I51: 7299 | J51: 832 | K51: -24 | L51: =SUM(I51:K51) -> 8107
D53: Total capital assets, depreciable | I53: =SUM(I47:I51) -> 13984 | J53: =SUM(J47:J51) -> 872 | K53: =SUM(K47:K51) -> -24 | L53: =SUM(L47:L51) -> 14832
B55: Less accumulated depreciation for:
C56: Sewer systems | I56: -2053 | J56: -289 | L56: =SUM(I56:K56) -> -2342 | M56: =SUM(L56,L48) -> 3437
C57: Water systems | I57: -401 | J57: -14 | L57: =SUM(I57:K57) -> -415 | M57: =SUM(L57,L49) -> 350
C58: Machinery & Equipment | I58: -43 | J58: -47 | L58: =SUM(I58:K58) -> -90 | M58: =SUM(L58,L50) -> 91
C59: Lamar Dixon Expo Center | I59: -1535 | J59: -358 | L59: =SUM(I59:K59) -> -1893 | M59: =SUM(L59,L51) -> 6214
D61: Total accumulated depreciation | I61: =SUM(I56:I59) -> -4032 | J61: =SUM(J56:J59) -> -708 | K61: =SUM(K56:K59) -> 0 | L61: =SUM(L56:L59) -> -4740
D63: Total capital assets, depreciable, net | I63: =I53+I61 -> 9952 | J63: =J53+J61 -> 164 | K63: =K53+K61 -> -24 | L63: =L53+L61 -> 10092
D65: Business-type activities capital assets, net | I65: =I63+I45 -> 10893 | J65: =J63+J45 -> 900 | K65: =K63+K45 -> -24 | L65: =L63+L45 -> 11769 | M65: =SUM(M56:M59,M42:M43) -> 11769

Sheet Assumption
D1: Assumption PARISH POLICE JURY
D2: Capital Assets
D3: For the Year Ended December 31, 2014
I5: Beginning Balance | J5: Additions | K5: Deletions | L5: Reclassifications | M5: Balance | N5: Cross Sectional
A7: Primary Government
A8: Government Activities:
A9: Capital assets
B10: Land | I10: 2213381 | J10: 120812 | L10: 0 | M10: =SUM(I10:L10) -> 2334193 | N10: =M10 -> 2334193
B11: Buildings | I11: 20795365 | J11: 17305421 | K11: 11888135 | L11: 8283 | M11: 23864600
B12: Improvements other than buildings | I12: 11684883 | J12: 72243 | M12: 11757126
B13: Roads | I13: 16109402 | J13: 116674 | M13: 16226076
B14: Bridges | I14: 588844 | M14: 588844
B15: Equipments & other | I15: 7250922 | J15: 369706 | K15: -314616 | M15: 7306012
B16: Construction in progress | I16: 488571 | J16: 245918 | K16: -24425 | L16: -8283 | M16: 701781 | N16: =M16 -> 701781
C17: Total capital assets | I17: =SUM(I10:I16) -> 59131368 | J17: =SUM(J10:J16) -> 18230774 | K17: =SUM(K10:K16) -> 11549094 | L17: =SUM(L10:L16) -> 0 | M17: =SUM(M10:M16) -> 62778632
A19: Capital Assets being Depreciated | O19: % of capital assets being depreciated
B20: Buildings | I20: 20795365 | J20: 17305421 | K20: 11888135 | L20: 8283 | M20: 23864600 | O20: =M20/M25 -> 0.39945662
B21: Improvements other than buildings | I21: 11684883 | J21: 72243 | M21: 11757126 | O21: =M21/M25 -> 0.19679617
B22: Roads | I22: 16109402 | J22: 116674 | M22: 16226076 | O22: =M22/M25 -> 0.2715995
B23: Bridges | I23: 588844 | M23: 588844 | O23: =M23/M25 -> 0.0098563408
B24: Equipments & other | I24: 7250922 | J24: 369706 | K24: -314616 | M24: 7306012 | O24: =M24/M25 -> 0.12229138
C25: Total capital assets being Depreciated | M25: =SUM(M20:M24) -> 59742658 | O25: =SUM(O20:O24) -> 1
A27: Accumulated Depreciation
B28: Buildings | M28: =M34*O20 -> -8182736.2 | N28: =M20+M28 -> 15681864
B29: Improvements other than buildings | M29: =M34*O21 -> -4031304.1 | N29: =M21+M29 -> 7725821.9
B30: Roads | M30: =M34*O22 -> -5563625.6 | N30: =M22+M30 -> 10662450
B31: Bridges | M31: =M34*O23 -> -201903.87 | N31: =M23+M31 -> 386940.13
B32: Equipments & other | M32: =M34*O24 -> -2505098.3 | N32: =M24+M32 -> 4800913.7
A33: Accumulated Depreciation | M33: =SUM(M28:M32) -> -20484668
A34: Accumulated Depreciation | I34: -18320031 | J34: -2384701 | K34: 220064 | M34: -20484668
I36: =SUM(I17+I34) -> 40811337 | J36: =SUM(J17+J34) -> 15846073 | K36: =SUM(K17+K34) -> 11769158 | L36: =SUM(L17+L34) -> 0 | M36: =SUM(M17+M34) -> 42293964 | N36: =SUM(N10:N32) -> 42293964

Sheet Avoyelles
D1: AVOYELLES PARISH POLICE JURY
D2: Capital Assets
D3: For the Year Ended December 31, 2014
G5: Balance 01/01/14 | H5: Additions | I5: Decreases | J5: Balance 12/31/14 | K5: Cross Sectional
A7: Governmental Activities:
B8: Capital assets, not being depreciated:
C9: Land | G9: 584787 | H9: 29761 | I9: -24000 | J9: =SUM(G9:I9) -> 590548 | K9: =SUM(J9) -> 590548
C10: Construction in progress | G10: 1083069 | I10: -1083069 | J10: =SUM(G10:I10) -> 0 | K10: =SUM(J10) -> 0
D12: Total capital assets, not being depreciated | G12: =SUM(G8:G11) -> 1667856 | H12: =SUM(H8:H11) -> 29761 | I12: =SUM(I8:I11) -> -1107069 | J12: =SUM(J8:J11) -> 590548
A14: Capital assets being depreciated:
B15: Buildings and improvements | G15: 4177096 | H15: 1192787 | I15: 0 | J15: =SUM(G15:I15) -> 5369883
B16: Equipment, furniture and fixtures | G16: 644791 | I16: -19970 | J16: =SUM(G16:I16) -> 624821
B17: Infrastructure | G17: 75128 | H17: 3012 | J17: =SUM(G17:I17) -> 78140
B18: Heavy equipment | G18: 3265524 | H18: 177984 | I18: -7500 | J18: =SUM(G18:I18) -> 3436008
D20: Total capital assets being depreciated | G20: =SUM(G18+G17+G16+G15+G12) -> 9830395 | H20: =SUM(H18+H17+H16+H15+H12) -> 1403544 | I20: =SUM(I18+I17+I16+I15+I12) -> -1134539 | J20: =SUM(J18+J17+J16+J15+J12) -> 10099400
A22: Less accumulated depreciation for:
B23: Buildings and improvements | G23: 1448131 | H23: 189004 | I23: 0 | J23: =SUM(G23:I23) -> 1637135 | K23: =J15-J23 -> 3732748
B24: Equipment, furniture and fixtures | G24: 548224 | H24: 22478 | I24: -19970 | J24: =SUM(G24:I24) -> 550732 | K24: =J16-J24 -> 74089
B25: Infrastructure | G25: 31327 | H25: 9371 | J25: =SUM(G25:I25) -> 40698 | K25: =J17-J25 -> 37442
B26: Heavy equipment | G26: 2545493 | H26: 142982 | I26: -7500 | J26: =SUM(G26:I26) -> 2680975 | K26: =J18-J26 -> 755033
D28: Total accumulated depreciation | G28: =SUM(G23:G27) -> 4573175 | H28: =SUM(H23:H27) -> 363835 | I28: =SUM(I23:I27) -> -27470 | J28: =SUM(J23:J27) -> 4909540
B30: Governmental activities capital assets, net | G30: =SUM(G20-G28) -> 5257220 | H30: =SUM(H20-H28) -> 1039709 | I30: =SUM(I20-I28) -> -1107069 | J30: =SUM(J20-J28) -> 5189860 | K30: =SUM(K23:K26,K9:K10) -> 5189860

Sheet Beauregard
D1: BEAUREGARD PARISH POLICE JURY
D2: Capital Assets
D3: For the Year Ended December 31, 2014
I5: Beginning Balance | J5: Additions | K5: Deletions | L5: Transfers | M5: Ending Balance | N5: Cross Sectional
A7: Government Activities:
A8: Capital assets, not being depreciated:
B9: Land | I9: 688379 | M9: =SUM(I9:L9) -> 688379 | N9: =SUM(M9) -> 688379
B10: Construction in progress | I10: 790379 | J10: 2045679 | L10: -660829 | M10: =SUM(I10:L10) -> 2175229 | N10: =SUM(M10) -> 2175229
C11: Total assets not being depreciated | I11: =SUM(I9:I10) -> 1478758 | J11: =SUM(J9:J10) -> 2045679 | K11: =SUM(K9:K10) -> 0 | L11: =SUM(L9:L10) -> -660829 | M11: =SUM(M9:M10) -> 2863608
A13: Capital assets being depreciated:
B14: Buildings and improvements | I14: 17159998 | L14: 660829 | M14: =SUM(I14:L14) -> 17820827
B15: Infrastructure | I15: 42862850 | M15: =SUM(I15:L15) -> 42862850
B16: Furniture and equipment | I16: 11863318 | J16: 1053553 | K16: -405195 | M16: =SUM(I16:L16) -> 12511676
C17: Total capital assets being depreciated | I17: =SUM(I14:I16) -> 71886166 | J17: =SUM(J14:J16) -> 1053553 | K17: =SUM(K14:K16) -> -405195 | L17: =SUM(L14:L16) -> 660829 | M17: =SUM(M14:M16) -> 73195353
A19: Less accumulated depreciation for:
B20: Buildings and improvements | I20: -8136454 | J20: -498528 | M20: =SUM(I20:L20) -> -8634982 | N20: =SUM(M20,M14) -> 9185845
B21: Infrastructure | I21: -25807309 | J21: -1664107 | M21: =SUM(I21:L21) -> -27471416 | N21: =SUM(M21,M15) -> 15391434
B22: Furniture and equipment | I22: -7914003 | J22: -800319 | K22: 298985 | L22: 0 | M22: =SUM(I22:L22) -> -8415337 | N22: =M16+M22 -> 4096339
C23: Total accumulated depreciation | I23: =SUM(I20:I22) -> -41857766 | J23: =SUM(J20:J22) -> -2962954 | K23: =SUM(K20:K22) -> 298985 | L23: =SUM(L20:L22) -> 0 | M23: =SUM(M20:M22) -> -44521735
B24: Total capital assets being depreciated, net | I24: =I23+I17 -> 30028400 | J24: =J23+J17 -> -1909401 | K24: =K23+K17 -> -106210 | L24: =L23+L17 -> 660829 | M24: =M23+M17 -> 28673618
B25: Governmental activities capital assets, net | I25: =I11+I24 -> 31507158 | J25: =J11+J24 -> 136278 | K25: =K11+K24 -> -106210 | L25: =L11+L24 -> 0 | M25: =M11+M24 -> 31537226 | N25: =SUM(N20:N22,N9:N10) -> 31537226

Sheet Bienville
D1: BIENVILLE PARISH POLICE JURY
D2: Capital Assets
D3: For the Year Ended December 31, 2014
I5: Beginning Balance | J5: Increases | K5: Decreases | L5: Ending Balance | M5: Cross Sectional
A7: Governmental Activities:
B8: Capital assets, not being depreciated:
C9: Land | I9: 660250 | K9: 0 | L9: =SUM(I9:K9) -> 660250 | M9: =SUM(L9) -> 660250
D11: Total capital assets, not being depreciated | I11: =SUM(I8:I9) -> 660250 | J11: =SUM(J8:J9) -> 0 | K11: =SUM(K8:K9) -> 0 | L11: =SUM(L8:L9) -> 660250
M12: =SUM(L12) -> 0
A13: Capital assets being depreciated: | M13: =SUM(L13) -> 0
B14: Infrastructure | M14: =SUM(L14) -> 0
C15: Roads | I15: 21024140 | J15: 1168532 | L15: =SUM(I15:K15) -> 22192672
C16: Bridges | I16: 2537698 | L16: =SUM(I16:K16) -> 2537698
B17: Buildings and Improvements | I17: 16851833 | L17: =SUM(I17:K17) -> 16851833
B18: Office furniture and equipment | I18: 541664 | L18: =SUM(I18:K18) -> 541664
B19: Heavy Equipment | I19: 1577996 | J19: 232345 | K19: -37073 | L19: =SUM(I19:K19) -> 1773268
B20: Vehicles | I20: 1394770 | K20: -93323 | L20: =SUM(I20:K20) -> 1301447
B21: Miscellaneous equipment | I21: 514738 | L21: =SUM(I21:K21) -> 514738
D23: Total capital assets being depreciated | I23: =SUM(I14:I21) -> 44442839 | J23: =SUM(J14:J21) -> 1400877 | K23: =SUM(K14:K21) -> -130396 | L23: =SUM(L14:L21) -> 45713320
A25: Less accumulated depreciation for:
B26: Infrastructure
C27: Roads | I27: -15685746 | J27: -991200 | L27: =SUM(I27:K27) -> -16676946 | M27: =SUM(L27,L15) -> 5515726
C28: Bridges | I28: -1318814 | J28: -39480 | L28: =SUM(I28:K28) -> -1358294 | M28: =SUM(L28,L16) -> 1179404
B29: Buildings and Improvements | I29: -2930993 | J29: -365514 | L29: =SUM(I29:K29) -> -3296507 | M29: =SUM(L29,L17) -> 13555326
B30: Office furniture and equipment | I30: -126348 | J30: -103829 | L30: =SUM(I30:K30) -> -230177 | M30: =SUM(L30,L18) -> 311487
B31: Heavy Equipment | I31: -1150004 | J31: -95068 | K31: 37073 | L31: -1207999 | M31: =SUM(L31,L19) -> 565269
B32: Vehicles | I32: -709926 | J32: -92978 | K32: 93323 | L32: -709581 | M32: =SUM(L32,L20) -> 591866
B33: Miscellaneous equipment | I33: -367092 | J33: -22367 | L33: -389459 | M33: =SUM(L33,L21) -> 125279
M34: =SUM(L34,L22) -> 0
D35: Total accumulated depreciation | I35: =SUM(I26:I33) -> -22288923 | J35: =SUM(J26:J33) -> -1710436 | K35: =SUM(K26:K33) -> 130396 | L35: =SUM(L27:L33) -> -23868963
B37: Total capital assets being depreciated, net | I37: =I23+I35 -> 22153916 | J37: =J23+J35 -> -309559 | K37: =K23+K35 -> 0 | L37: =L23+L35 -> 21844357
M38: =SUM(L38,L26) -> 0
B39: Total capital assets (net) | I39: =I35+I23+I11 -> 22814166 | J39: =J35+J23+J11 -> -309559 | K39: =K35+K23+K11 -> 0 | L39: =L35+L23+L11 -> 22504607 | M39: =SUM(M9:M33) -> 22504607

Sheet Bossier
D1: BOSSIER PARISH POLICE JURY
D2: Capital Assets
D3: For the Year Ended December 31, 2014
I5: Beginning Balance | J5: Transfers | K5: Additions | L5: Deletions | M5: Ending Balance | N5: Cross Sectional
A7: Primary Government
A8: Government Activities:
A9: Capital assets, not being depreciated:
B10: Land | I10: 12207084 | J10: 0 | K10: 805670 | L10: -40496 | M10: =SUM(I10:L10) -> 12972258 | N10: =SUM(M10) -> 12972258
B11: Construction in progress | I11: 6042279 | J11: -3040380 | K11: 3270200 | M11: =SUM(I11:L11) -> 6272099 | N11: =SUM(M11) -> 6272099
C12: Total assets not being depreciated | I12: =SUM(I10:I11) -> 18249363 | J12: =SUM(J10:J11) -> -3040380 | K12: =SUM(K10:K11) -> 4075870 | L12: =SUM(L10:L11) -> -40496 | M12: =SUM(M10:M11) -> 19244357
A14: Capital assets being depreciated:
B15: Buildings and improvements | I15: 108060059 | J15: 67621 | K15: 144858 | M15: =SUM(I15:L15) -> 108272538
B16: Infrastructure | I16: 220251390 | J16: 2972759 | K16: 8222959 | M16: =SUM(I16:L16) -> 231447108
B17: Furniture, equipment and vehicles | I17: 10575576 | K17: 357500 | L17: -14236 | M17: =SUM(I17:L17) -> 10918840
B18: Library books and information material | I18: 4631676 | K18: 559810 | M18: =SUM(I18:L18) -> 5191486
C19: Total capital assets being depreciated | I19: =SUM(I15:I18) -> 343518701 | J19: =SUM(J15:J18) -> 3040380 | K19: =SUM(K15:K18) -> 9285127 | L19: =SUM(L15:L18) -> -14236 | M19: =SUM(M15:M18) -> 355829972
A21: Less accumulated depreciation for:
B22: Buildings and improvements | I22: -24025483 | K22: -2644445 | L22: 0 | M22: =SUM(I22:L22) -> -26669928 | N22: =SUM(M22,M15) -> 81602610
B23: Infrastructure | I23: -46703687 | K23: -5702147 | L23: 0 | M23: =SUM(I23:L23) -> -52405834 | N23: =SUM(M23,M16) -> 179041274
B24: Furniture, equipment and vehicles | I24: -6208523 | K24: -692827 | L24: 9965 | M24: =SUM(I24:L24) -> -6891385 | N24: =SUM(M24,M17) -> 4027455
B25: Library books and information material | I25: -3526904 | K25: -454178 | L25: 0 | M25: =SUM(I25:L25) -> -3981082 | N25: =M18+M25 -> 1210404
C26: Total accumulated depreciation | I26: =SUM(I22:I25) -> -80464597 | J26: =SUM(J22:J25) -> 0 | K26: =SUM(K22:K25) -> -9493597 | L26: =SUM(L22:L25) -> 9965 | M26: =SUM(M22:M25) -> -89948229
B28: Total capital assets being depreciated, net | I28: =I26+I19 -> 263054104 | J28: =J26+J19 -> 3040380 | K28: =K26+K19 -> -208470 | L28: =L26+L19 -> -4271 | M28: =M26+M19 -> 265881743
B30: Governmental activities capital assets, net | I30: =I12+I28 -> 281303467 | J30: =J12+J28 -> 0 | K30: =K12+K28 -> 3867400 | L30: =L12+L28 -> -44767 | M30: =M12+M28 -> 285126100 | N30: =SUM(N22:N25,N10:N11) -> 285126100
I33: Beginning Balance | J33: Transfers | K33: Additions | L33: Deletions | M33: Ending Balance
A35: Business-type Activities:
A36: Capital assets not being depreciated:
B37: Land | I37: 1301778 | J37: 0 | K37: 110034 | L37: 0 | M37: =SUM(I37:L37) -> 1411812 | N37: =SUM(M37) -> 1411812
B38: Goodwill | I38: 1226000 | M38: =SUM(I38:L38) -> 1226000 | N38: =M38 -> 1226000
B39: Construction in progress | I39: 3279798 | J39: -119742 | K39: 10471550 | M39: =SUM(I39:L39) -> 13631606 | N39: =SUM(M39) -> 13631606
C40: Total assets not being depreciated | I40: =SUM(I37:I39) -> 5807576 | J40: =SUM(J37:J39) -> -119742 | K40: =SUM(K37:K39) -> 10581584 | L40: =SUM(L37:L39) -> 0 | M40: =SUM(M37:M39) -> 16269418
A42: Capital assets being depreciated:
B43: Furniture, equipment and vehicles | I43: 34602 | J43: 119742 | K43: 43137 | L43: 0 | M43: =SUM(I43:L43) -> 197481
B44: Buildings and improvements | I44: 4953684 | L44: 0 | M44: =SUM(I44:L44) -> 4953684
C45: Total capital assets being depreciated | I45: =SUM(I43:I44) -> 4988286 | J45: =SUM(J43:J44) -> 119742 | K45: =SUM(K43:K44) -> 43137 | L45: =SUM(L43:L44) -> 0 | M45: =SUM(M43:M44) -> 5151165
A47: Less accumulated depreciation for:
B48: Furniture, equipment and vehicles | I48: -412 | K48: -4943 | L48: 0 | M48: =SUM(I48:L48) -> -5355 | N48: =SUM(M48,M43) -> 192126
B49: Buildings and improvements | I49: -333305 | K49: -202580 | L49: 0 | M49: =SUM(I49:L49) -> -535885 | N49: =SUM(M49,M44) -> 4417799
C50: Total accumulated depreciation | I50: =SUM(I48:I49) -> -333717 | J50: =SUM(J48:J49) -> 0 | K50: =SUM(K48:K49) -> -207523 | L50: =SUM(L48:L49) -> 0 | M50: =SUM(M48:M49) -> -541240
B52: Total capital assets being depreciated, net | I52: =SUM(I50,I45) -> 4654569 | J52: =SUM(J50,J45) -> 119742 | K52: =SUM(K50,K45) -> -164386 | L52: =SUM(L50,L45) -> 0 | M52: =SUM(M50,M45) -> 4609925
B54: Business-type activities capital assets, net | I54: =I40+I52 -> 10462145 | J54: =J40+J52 -> 0 | K54: =K40+K52 -> 10417198 | L54: =L40+L52 -> 0 | M54: =M40+M52 -> 20879343 | N54: =SUM(N48:N49,N37:N39) -> 20879343

Sheet Caddo
D1: CADDO PARISH POLICE JURY
D2: Capital Assets
D3: For the Year Ended December 31, 2014
I5: Balance December 31, 2013 | J5: Additions | K5: Reductions | L5: Balance December 31, 2014 | M5: Cross Sectional
A7: Government Activities:
A8: Capital assets, not being depreciated:
B9: Land and land improvements | I9: 14578409 | L9: =SUM(I9:K9) -> 14578409 | M9: =SUM(L9) -> 14578409
B10: Construction in progress | I10: 13982884 | J10: 4339309 | K10: -12386288 | L10: =SUM(I10:K10) -> 5935905 | M10: =L10 -> 5935905
C11: Total capital assets not being depreciated | I11: =SUM(I9:I10) -> 28561293 | J11: =SUM(J9:J10) -> 4339309 | K11: =SUM(K9:K10) -> -12386288 | L11: =SUM(L9:L10) -> 20514314
A13: Capital assets being depreciated:
B14: Buildings and structures | I14: 89865209 | J14: 11141211 | L14: =SUM(I14:K14) -> 101006420
B15: Equipment and vehicles | I15: 38304592 | J15: 3248899 | K15: -931135 | L15: =SUM(I15:K15) -> 40622356
B16: Infrastructure | I16: 386642046 | J16: 3287628 | K16: -97737 | L16: =SUM(I16:K16) -> 389831937
C17: Total capital assets being depreciated | I17: =SUM(I14:I16) -> 514811847 | J17: =SUM(J14:J16) -> 17677738 | K17: =SUM(K14:K16) -> -1028872 | L17: =SUM(L14:L16) -> 531460713
A19: Less accumulated depreciation for:
B20: Buildings and structures | I20: -36975522 | J20: -2452746 | L20: =SUM(I20:K20) -> -39428268 | M20: =SUM(L20,L14) -> 61578152
B21: Equipment and vehicles | I21: -26452998 | J21: -2802700 | K21: 921382 | L21: =SUM(I21:K21) -> -28334316 | M21: =SUM(L21,L15) -> 12288040
B22: Infrastructure | I22: -269675695 | J22: -10691375 | K22: 97738 | L22: =SUM(I22:K22) -> -280269332 | M22: =L16+L22 -> 109562605
C23: Total accumulated depreciation | I23: =SUM(I20:I22) -> -333104215 | J23: =SUM(J20:J22) -> -15946821 | K23: =SUM(K20:K22) -> 1019120 | L23: =SUM(L20:L22) -> -348031916
B24: Total capital assets being depreciated, net | I24: =I23+I17 -> 181707632 | J24: =J23+J17 -> 1730917 | K24: =K23+K17 -> -9752 | L24: =L23+L17 -> 183428797
B25: Capital assets, net | I25: =I11+I24 -> 210268925 | J25: =J11+J24 -> 6070226 | K25: =K11+K24 -> -12396040 | L25: =L11+L24 -> 203943111 | M25: =SUM(M20:M22,M9:M10) -> 203943111

Sheet Calcasieu
D1: CALCASIEU PARISH POLICE JURY
D2: Capital Assets
D3: For the Year Ended December 31, 2014
I5: Beginning Balance | J5: Increases | K5: Decreases | L5: Ending Balance | M5: Cross Sectional
A7: Governmental Activities:
B8: Capital assets, not being depreciated:
C9: Land and Right of Ways | I9: 17550185 | J9: 472081 | K9: 0 | L9: =SUM(I9:K9) -> 18022266 | M9: =SUM(L9) -> 18022266
C10: Construction in progress | I10: 17829886 | J10: 10772487 | K10: -21223434 | L10: =SUM(I10:K10) -> 7378939 | M10: =SUM(L10) -> 7378939
C11: Roads ** | I11: 383317282 | J11: 12100142 | L11: 395417424 | M11: =SUM(L11) -> 395417424
D13: Total capital assets, not being depreciated | I13: =SUM(I8:I11) -> 418697353 | J13: =SUM(J8:J11) -> 23344710 | K13: =SUM(K8:K11) -> -21223434 | L13: =SUM(L8:L11) -> 420818629
A15: Capital assets being depreciated:
B16: Buildings and Improvements | I16: 127634796 | J16: 5493622 | K16: 0 | L16: =SUM(I16:K16) -> 133128418
B17: Machinery and Equipment | I17: 32517962 | J17: 4282860 | K17: -2479025 | L17: =SUM(I17:K17) -> 34321797
B18: Bridges ++ | I18: 11812642 | J18: 2520325 | L18: =SUM(I18:K18) -> 14332967
D20: Total capital assets being depreciated | I20: =SUM(I16:I19) -> 171965400 | J20: =SUM(J16:J19) -> 12296807 | K20: =SUM(K16:K19) -> -2479025 | L20: =SUM(L16:L18) -> 181783182
A22: Less accumulated depreciation for:
B23: Buildings and Improvements | I23: -55088300 | J23: -3398276 | K23: 0 | L23: =SUM(I23:K23) -> -58486576 | M23: =SUM(L23,L16) -> 74641842
B24: Machinery and Equipment | I24: -20643251 | J24: -2810525 | K24: 2373838 | L24: =SUM(I24:K24) -> -21079938 | M24: =SUM(L24,L17) -> 13241859
B25: Bridges ++ | I25: -3897003 | J25: -330103 | L25: =SUM(I25:K25) -> -4227106 | M25: =SUM(L25,L18) -> 10105861
D27: Total accumulated depreciation | I27: =SUM(I23:I26) -> -79628554 | J27: =SUM(J23:J26) -> -6538904 | K27: =SUM(K23:K26) -> 2373838 | L27: =SUM(L23:L26) -> -83793620
B29: Total capital assets being depreciated, net | I29: =I20+I27 -> 92336846 | J29: =J20+J27 -> 5757903 | K29: =K20+K27 -> -105187 | L29: =L20+L27 -> 97989562
B31: Governmental activities capital assets, net | I31: =I27+I20+I13 -> 511034199 | J31: =J27+J20+J13 -> 29102613 | K31: =K27+K20+K13 -> -21328621 | L31: =L27+L20+L13 -> 518808191 | M31: =SUM(L31, L22) -> 518808191
B33: ** As further discussed in Note 1-C, the Parish has adopted the modified approach for valuing its infiastructure of road systems.
B34: (++) The beginning balance of $510,443,445 was restated to $511,034,199 to properly reflect the following: (1) Land and Right of Ways beginning balance of$ 17,544,546 was increased by $5,639 to $17,550,185 to correct a formula error; (2) Construction in Progress beginning balance of $16,852,520 was increased by $977,366 to $17,829,886 to properly state five construction in progress projects fiom the prior year; (3) Buildings and Improvement beginning balance of $127,781,779 was decreased by $146,983 to $127,634,796 in order to remove the effects of a duplicate asset reporting while Accumulated Depreciation for Buildings and Improvements beginning balance of $55,102,925 was also reduced by $14,625 to $55,088,300 for the same reason; (4) Machinery and Equipment beginning balance of $33,068,532 was decreased by $550,570 to $32,517,962 in order to reclassify the assets of two discretely presented component units while Accumulated Depreciation for Machinery and Equipment beginning balance of $20,952,735 was decreased by $309,484 to $20,643,251 for the same reason; and (5) Bridges beginning balance of $11,887,348 was reduced by $74,706 to $11,812,642 to remove the costs of an intersection that is considered a State asset while Accumulated Depreciation for Bridges beginning balance of $3,952,903 was also reduced by $55,900 to $3,897,003 for the same reason. In2014, the Parish completed construction of a water and sewer collection system on an Interstate 10 frontage road in the amount of $1,857,735. Upon completion of that project and in accordance with a cooperative endeavor agreement executed with the City of Sulphur, the construction in progress amount was deleted and the asset was transferred to the City of Sulphur who will own and maintain the system.
I36: Beginning Balance | J36: Increases | K36: Decreases | L36: Ending Balance
A37: Business-Type Activities:
B38: Capital assets, not being depreciated:
C39: Land | I39: 227920 | J39: 0 | K39: 0 | L39: =SUM(I39:K39) -> 227920 | M39: =SUM(L39) -> 227920
C40: Construction in progress | I40: 718820 | J40: 24850 | K40: -718820 | L40: =SUM(I40:K40) -> 24850 | M40: =SUM(L40) -> 24850
D42: Total capital assets, not being depreciated | I42: =SUM(I38:I41) -> 946740 | J42: =SUM(J38:J41) -> 24850 | K42: =SUM(K38:K41) -> -718820 | L42: =SUM(L38:L41) -> 252770
B44: Capital assets, depreciable:
C45: Non-Building Improvements | I45: 10218419 | J45: 203342 | K45: 0 | L45: =SUM(I45:K45) -> 10421761
C46: Building and Improvements | I46: 103393 | K46: 0 | L46: =SUM(I46:K46) -> 103393
C47: Infrastructure | I47: 3120287 | J47: 742479 | K47: 0 | L47: =SUM(I47:K47) -> 3862766
C48: Machinery and Equipment | I48: 243565 | J48: 6451 | L48: 250016
D50: Total capital assets, depreciable | I50: =SUM(I44:I48) -> 13685664 | J50: =SUM(J44:J48) -> 952272 | K50: =SUM(K44:K47) -> 0 | L50: =SUM(L44:L48) -> 14637936
B52: Less accumulated depreciation for:
C53: Non-Building Improvements | I53: -3337586 | J53: -285648 | L53: =SUM(I53:K53) -> -3623234 | M53: =SUM(L53,L45) -> 6798527
C54: Building and Improvements | I54: -83073 | J54: -2202 | L54: =SUM(I54:K54) -> -85275 | M54: =SUM(L54,L46) -> 18118
C55: Infrastructure | I55: -1759643 | J55: -139980 | L55: =SUM(I55:K55) -> -1899623 | M55: =SUM(L55,L47) -> 1963143
C56: Machinery and Equipment | I56: -204843 | J56: -5211 | L56: -210054 | M56: =SUM(L56,L48) -> 39962
D58: Total accumulated depreciation | I58: =SUM(I53:I56) -> -5385145 | J58: =SUM(J53:J56) -> -433041 | K58: =SUM(K53:K56) -> 0 | L58: =SUM(L53:L56) -> -5818186
D60: Total capital assets, depreciable, net | I60: =I50+I58 -> 8300519 | J60: =J50+J58 -> 519231 | K60: =K50+K58 -> 0 | L60: =L50+L58 -> 8819750
D62: Business-type activities capital assets, net | I62: =I60+I42 -> 9247259 | J62: =J60+J42 -> 544081 | K62: =K60+K42 -> -718820 | L62: =L60+L42 -> 9072520 | M62: =SUM(M53:M56,M39:M40) -> 9072520

Sheet Caldwell
D1: CALDWELL PARISH POLICE JURY
D2: Capital Assets
D3: For the Year Ended December 31, 2014
I5: Beginning Balance | J5: Transfers | K5: Additions | L5: Deletions | M5: Ending Balance | N5: Cross Sectional
A7: Primary Government
A8: Government Activities:
A9: Capital assets, not being depreciated:
B10: Land | I10: 420095 | J10: 0 | M10: =SUM(I10:L10) -> 420095 | N10: =SUM(M10) -> 420095
B11: Construction in progress | I11: 7932354 | J11: -797615 | K11: 3419059 | L11: -17920 | M11: =SUM(I11:L11) -> 10535878 | N11: =SUM(M11) -> 10535878
C12: Total assets not being depreciated | I12: 8352449 | J12: =SUM(J10:J11) -> -797615 | K12: =SUM(K10:K11) -> 3419059 | L12: =SUM(L10:L11) -> -17920 | M12: =SUM(M10:M11) -> 10955973
A14: Capital assets being depreciated:
B15: Infrastructure
C16: Roads | I16: 47897858 | M16: =SUM(I16:L16) -> 47897858
C17: Bridges | I17: 642997 | M17: =SUM(I17:L17) -> 642997
B18: Buildings and improvements | I18: 2977743 | K18: 6162 | M18: =SUM(I18:L18) -> 2983905
B19: Land improvements | I19: 716214 | M19: =SUM(I19:L19) -> 716214
B20: Heavy equipment | I20: 1460214 | K20: 37668 | M20: =SUM(I20:L20) -> 1497882
B21: Vehicles | I21: 1187227 | M21: =SUM(I21:L21) -> 1187227
B22: Public works equipment | I22: 285706 | M22: =SUM(I22:L22) -> 285706
B23: Office furniture and equipment | I23: 577716 | K23: 104432 | L23: -1100 | M23: =SUM(I23:L23) -> 681048
C24: Total capital assets being depreciated | I24: =SUM(I16:I23) -> 55745675 | J24: =SUM(J16:J23) -> 0 | K24: =SUM(K16:K23) -> 148262 | L24: =SUM(L16:L23) -> -1100 | M24: =SUM(M16:M23) -> 55892837
A26: Less accumulated depreciation for:
B27: Infrastructure
C28: Roads | I28: -46151263 | K28: -149999 | L28: 0 | M28: =SUM(I28:L28) -> -46301262 | N28: =SUM(M28,M16) -> 1596596
C29: Bridges | I29: -642062 | K29: -48 | M29: =SUM(I29:L29) -> -642110 | N29: =SUM(M29,M17) -> 887
B30: Buildings and improvements | I30: -2601609 | K30: -17717 | L30: 0 | M30: =SUM(I30:L30) -> -2619326 | N30: =SUM(M30,M18) -> 364579
B31: Land improvements | I31: -186334 | K31: -30959 | M31: =SUM(I31:L31) -> -217293 | N31: =SUM(M31,M19) -> 498921
B32: Heavy equipment | I32: -1169753 | K32: -53802 | M32: =SUM(I32:L32) -> -1223555 | N32: =SUM(M32,M20) -> 274327
B33: Vehicles | I33: -1073866 | K33: -41067 | M33: =SUM(I33:L33) -> -1114933 | N33: =SUM(M33,M21) -> 72294
B34: Public works equipment | I34: -105510 | K34: -23681 | M34: =SUM(I34:L34) -> -129191 | N34: =SUM(M34,M22) -> 156515
B35: Office furniture and equipment | I35: -448561 | K35: -44567 | L35: 1100 | M35: =SUM(I35:L35) -> -492028 | N35: =SUM(M35,M23) -> 189020
C36: Total accumulated depreciation | I36: =SUM(I27:I35) -> -52378958 | J36: =SUM(J27:J35) -> 0 | K36: =SUM(K27:K35) -> -361840 | L36: =SUM(L27:L35) -> 1100 | M36: =SUM(M27:M35) -> -52739698
B38: Total capital assets being depreciated, net | I38: =I36+I24 -> 3366717 | J38: =J36+J24 -> 0 | K38: =K36+K24 -> -213578 | L38: =L36+L24 -> 0 | M38: =M36+M24 -> 3153139
B40: Governmental activities capital assets, net | I40: =I12+I38 -> 11719166 | J40: =J12+J38 -> -797615 | K40: =K12+K38 -> 3205481 | L40: =L12+L38 -> -17920 | M40: =M12+M38 -> 14109112 | N40: =SUM(N27:N35,N10:N11) -> 14109112

Sheet Cameron
D1: Cameron PARISH POLICE JURY
D2: Capital Assets
D3: For the Year Ended December 31, 2014
I5: Beginning Balance | J5: Additions | K5: Deletions | L5: Ending Balance | M5: Cross Sectional
A7: Primary Government
A8: Government Activities:
B10: Land | I10: 1381390 | J10: 28000 | L10: =SUM(I10:K10) -> 1409390 | M10: =SUM(L10) -> 1409390
B11: Construction in progress | I11: 20795365 | J11: 17305421 | K11: -11888135 | L11: =SUM(I11:K11) -> 26212651 | M11: =SUM(L11) -> 26212651
B12: Building and improvements | I12: 35436534 | J12: 5051089 | K12: -1917928 | L12: =SUM(I12:K12) -> 38569695
B13: Books and videos | I13: 702647 | J13: 93863 | L13: =SUM(I13:K13) -> 796510
B14: Equipment and furniture | I14: 18144322 | J14: 1032315 | K14: -850576 | L14: =SUM(I14:K14) -> 18326061
B15: Infrastructure | I15: 54375215 | J15: 7071718 | L15: =SUM(I15:K15) -> 61446933
C16: Total capital assets at historical costs | I16: =SUM(I10:I15) -> 130835473 | J16: =SUM(J10:J15) -> 30582406 | K16: =SUM(K10:K15) -> -14656639 | L16: =SUM(L10:L15) -> 146761240
A18: Capital Assets being Depreciated | N18: % of Capital Assets being Depreciated | O18: Accumulated Depreciation
B19: Building and improvements | I19: 35436534 | J19: 5051089 | K19: -1917928 | L19: =SUM(I19:K19) -> 38569695 | N19: =L19/L23 -> 0.3237364 | O19: =L32*N19 -> -7379077.5
B20: Books and videos | I20: 702647 | J20: 93863 | L20: =SUM(I20:K20) -> 796510 | N20: =L20/L23 -> 0.006685541 | O20: =L32*N20 -> -152386.71
B21: Equipment and furniture | I21: 18144322 | J21: 1032315 | K21: -850576 | L21: =SUM(I21:K21) -> 18326061 | N21: =L21/L23 -> 0.15382058 | O21: =L32*N21 -> -3506105.6
B22: Infrastructure | I22: 54375215 | J22: 7071718 | L22: =SUM(I22:K22) -> 61446933 | N22: =L22/L23 -> 0.51575748 | O22: =L32*N22 -> -11755905
C23: Total Capital being Depreciated | I23: =SUM(I17:I22) -> 108658718 | J23: =SUM(J17:J22) -> 13248985 | K23: =SUM(K17:K22) -> -2768504 | L23: =SUM(L17:L22) -> 119139199 | N23: =SUM(N19:N22) -> 1 | O23: =SUM(O19:O22) -> -22793475
A25: Accumulated Depreciation
B26: Building and improvements | L26: -7379077 | M26: =L19+L26 -> 31190618
B27: Books and videos | L27: -152387 | M27: =L20+L27 -> 644123
B28: Equipment and furniture | L28: -3506106 | M28: =L21+L28 -> 14819955
B29: Infrastructure | L29: -11755905 | M29: =L22+L29 -> 49691028
C30: Total Accumulated Depreciation | L30: =SUM(L26:L29) -> -22793475
C32: Less accumulated depreciation | I32: -19081663 | J32: -4562388 | K32: -850576 | L32: -22793475
C34: Total capital assets, net | I34: =SUM(I16,I32) -> 111753810 | J34: =SUM(J16,J32) -> 26020018 | K34: =K16-K32 -> -13806063 | L34: =SUM(L16,L32) -> 123967765 | M34: =SUM(M10:M29) -> 123967765

Sheet Catahoula
D1: CATAHOULA PARISH POLICE JURY
D2: Capital Assets
D3: For the Year Ended December 31, 2014
I5: Beginning Balance | J5: Transfers | K5: Additions | L5: Deletions | M5: Ending Balance | N5: Cross Sectional
A7: Primary Government
A8: Government Activities:
A9: Capital assets, not being depreciated:
B10: Land | I10: 112200 | J10: 0 | M10: =SUM(I10:L10) -> 112200 | N10: =SUM(M10) -> 112200
B11: Construction in progress | K11: 33780 | M11: =SUM(I11:L11) -> 33780 | N11: =SUM(M11) -> 33780
C12: Total assets not being depreciated | I12: =SUM(I10:I11) -> 112200 | J12: =SUM(J10:J11) -> 0 | K12: =SUM(K10:K11) -> 33780 | L12: =SUM(L10:L11) -> 0 | M12: =SUM(M10:M11) -> 145980
A14: Capital assets being depreciated:
B15: Infrastructure | I15: 11389474 | K15: 125058 | M15: =SUM(I15:L15) -> 11514532
B16: Buildings | I16: 2983414 | K16: 13430 | M16: =SUM(I16:L16) -> 2996844
B17: Improvements | I17: 1558229 | L17: -14710 | M17: =SUM(I17:L17) -> 1543519
B18: Equipment | I18: 1471586 | K18: 9221 | L18: -64679 | M18: =SUM(I18:L18) -> 1416128
B19: Heavy equipment | I19: 926073 | K19: 65407 | M19: =SUM(I19:L19) -> 991480
B20: Vehicles | I20: 550399 | L20: -975 | M20: =SUM(I20:L20) -> 549424
B21: Books and periodicals | I21: 690885 | K21: 35230 | L21: -15247 | M21: =SUM(I21:L21) -> 710868
C22: Total capital assets being depreciated | I22: =SUM(I15:I21) -> 19570060 | J22: =SUM(J15:J21) -> 0 | K22: =SUM(K15:K21) -> 248346 | L22: =SUM(L15:L21) -> -95611 | M22: =SUM(M15:M21) -> 19722795
A24: Less accumulated depreciation for:
B25: Infrastructure - roads and bridges | I25: 8368120 | K25: 113919 | L25: 0 | M25: =SUM(I25:L25) -> 8482039 | N25: =M15-M25 -> 3032493
B26: Buildings | I26: 2553563 | K26: 18176 | L26: 0 | M26: =SUM(I26:L26) -> 2571739 | N26: =M16-M26 -> 425105
B27: Improvements | I27: 214205 | K27: 61531 | L27: -12749 | M27: =SUM(I27:L27) -> 262987 | N27: =M17-M27 -> 1280532
B28: Equipment | I28: 1140968 | J28: -80 | K28: 71408 | L28: -47474 | M28: =SUM(I28:L28) -> 1164822 | N28: =M18-M28 -> 251306
B29: Heavy equipment | I29: 630079 | K29: 51388 | M29: =SUM(I29:L29) -> 681467 | N29: =M19-M29 -> 310013
B30: Vehicles | I30: 300201 | J30: 80 | K30: 48564 | L30: -975 | M30: =SUM(I30:L30) -> 347870 | N30: =M20-M30 -> 201554
B31: Books and periodicals | I31: 612308 | K31: 29741 | L31: -15247 | M31: =SUM(I31:L31) -> 626802 | N31: =M21-M31 -> 84066
C32: Total accumulated depreciation | I32: =SUM(I25:I31) -> 13819444 | J32: =SUM(J25:J31) -> 0 | K32: =SUM(K25:K31) -> 394727 | L32: =SUM(L25:L31) -> -76445 | M32: =SUM(M25:M31) -> 14137726
B34: Total capital assets being depreciated, net | I34: =I22-I32 -> 5750616 | J34: =J22-J32 -> 0 | K34: =K22-K32 -> -146381 | L34: =L22-L32 -> -19166 | M34: =M22-M32 -> 5585069
B36: Governmental activities capital assets, net | I36: =I12+I34 -> 5862816 | J36: =J12+J34 -> 0 | K36: =K12+K34 -> -112601 | L36: =L12+L34 -> -19166 | M36: =M12+M34 -> 5731049 | N36: =SUM(N25:N31, N10:N12) -> 5731049

Sheet Claiborne
D1: CLAIBORNE PARISH POLICE JURY
D2: Capital Assets
D3: For the Year Ended December 31, 2014
I5: Beginning Balance | J5: Transfers | K5: Additions | L5: Deletions | M5: Ending Balance | N5: Cross Sectional
A7: Primary Government
A8: Government Activities:
A9: Capital assets, not being depreciated:
B10: Land
C11: Police Jury | I11: 49900 | K11: 170670 | M11: =SUM(I11:L11) -> 220570 | N11: =SUM(M11) -> 220570
C12: Library | I12: 3580 | M12: =SUM(I12:L12) -> 3580 | N12: =SUM(M12) -> 3580
C13: Office of Community Service | I13: 30000 | M13: =SUM(I13:L13) -> 30000 | N13: =SUM(M13) -> 30000
C14: Adjudicated property | I14: 15360 | J14: 2340 | K14: 667 | L14: -1729 | M14: =SUM(I14:L14) -> 16638 | N14: =SUM(M14) -> 16638
B15: Construction in progress | I15: 2341387 | K15: 845221 | L15: -3143346 | M15: =SUM(I15:L15) -> 43262 | N15: =SUM(M15) -> 43262
C16: Total assets not being depreciated | I16: =SUM(I10:I15) -> 2440227 | J16: =SUM(J10:J15) -> 2340 | K16: =SUM(K10:K15) -> 1016558 | L16: =SUM(L10:L15) -> -3145075 | M16: =SUM(M10:M15) -> 314050
A18: Capital assets being depreciated:
B19: Infrastructure
C20: Roads | I20: 15517189 | M20: =SUM(I20:L20) -> 15517189
C21: Bridges | I21: 1912668 | M21: =SUM(I21:L21) -> 1912668
B22: Land improvements | I22: 15995 | M22: =SUM(I22:L22) -> 15995
B23: Buildings and improvements | I23: 2549623 | K23: 240942 | L23: -200000 | M23: =SUM(I23:L23) -> 2590565
B24: Public works heavy equipment | I24: 2849685 | K24: 289996 | L24: -280508 | M24: =SUM(I24:L24) -> 2859173
B25: Public works other equipment | I25: 82575 | L25: -18500 | M25: =SUM(I25:L25) -> 64075
B26: Vehicles | I26: 232447 | L26: -14368 | M26: =SUM(I26:L26) -> 218079
B27: Other furniture and equipment | I27: 249691 | K27: 5650 | L27: -4500 | M27: =SUM(I27:L27) -> 250841
B28: Office of Emergency Preparedness and Homeland Security: | M28: =SUM(I28:L28) -> 0
C29: Vehicles | I29: 45517 | K29: 21514 | M29: =SUM(I29:L29) -> 67031
C30: Office of Community Service | I30: 50506 | M30: =SUM(I30:L30) -> 50506
C31: Buildings and improvements | I31: 13205 | M31: =SUM(I31:L31) -> 13205
B32: Office of Community Service | M32: =SUM(I32:L32) -> 0
C33: Land improvements | I33: 7800 | M33: =SUM(I33:L33) -> 7800
C34: Buildings and improvements | I34: 62156 | M34: =SUM(I34:L34) -> 62156
C35: Vehicles | I35: 452963 | L35: -70116 | M35: =SUM(I35:L35) -> 382847
C36: Office furniture and equipment | I36: 116327 | M36: =SUM(I36:L36) -> 116327
B37: Library | M37: =SUM(I37:L37) -> 0
C38: Building and improvement | I38: 790366 | K38: 3064878 | M38: =SUM(I38:L38) -> 3855244
C39: Vehicles | I39: 49901 | M39: =SUM(I39:L39) -> 49901
C40: Furniture and equipment | I40: 96154 | K40: 230967 | M40: =SUM(I40:L40) -> 327121
C41: Books and videos | I41: 759823 | K41: 40149 | L41: -62768 | M41: =SUM(I41:L41) -> 737204
C42: Total capital assets being depreciated | I42: =SUM(I19:I41) -> 25854591 | J42: =SUM(J19:J41) -> 0 | K42: =SUM(K19:K41) -> 3894096 | L42: =SUM(L19:L41) -> -650760 | M42: =SUM(M19:M41) -> 29097927
A44: Less accumulated depreciation for:
B45: Infrastructure
C46: Roads | I46: 14376010 | K46: 37185 | M46: =SUM(I46:L46) -> 14413195 | N46: =SUM(M20-M46) -> 1103994
C47: Bridges | I47: 1214453 | K47: 42681 | M47: =SUM(I47:L47) -> 1257134 | N47: =SUM(M21-M47) -> 655534
B48: Land improvements | I48: 14063 | K48: 799 | L48: 0 | M48: =SUM(I48:L48) -> 14862 | N48: =SUM(M22-M48) -> 1133
B49: Buildings and improvements | I49: 1681836 | J49: 60 | K49: 65704 | L49: -200000 | M49: =SUM(I49:L49) -> 1547600 | N49: =SUM(M23-M49) -> 1042965
B50: Public works heavy equipment | I50: 1744213 | K50: 190847 | L50: -259748 | M50: =SUM(I50:L50) -> 1675312 | N50: =SUM(M24-M50) -> 1183861
B51: Public works other equipment | I51: 58231 | K51: 3200 | L51: -18500 | M51: =SUM(I51:L51) -> 42931 | N51: =SUM(M25-M51) -> 21144
B52: Vehicles | I52: 100784 | K52: 15716 | L52: -6945 | M52: =SUM(I52:L52) -> 109555 | N52: =SUM(M26-M52) -> 108524
B53: Office furniture and equipment | I53: 84918 | K53: 24101 | L53: -4500 | M53: =SUM(I53:L53) -> 104519 | N53: =SUM(M27-M53) -> 146322
B54: Office of Emergency Preparedness and Homeland Security | M54: =SUM(I54:L54) -> 0 | N54: =SUM(M28-M54) -> 0
C55: Vehicles | I55: 43676 | K55: 2200 | M55: =SUM(I55:L55) -> 45876 | N55: =SUM(M29-M55) -> 21155
C56: Office furniture and equipment | I56: 45508 | K56: 3688 | M56: =SUM(I56:L56) -> 49196 | N56: =SUM(M30-M56) -> 1310
C57: Buildings and improvements | I57: 3025 | K57: 660 | M57: =SUM(I57:L57) -> 3685 | N57: =SUM(M31-M57) -> 9520
B58: Office of Community services | M58: =SUM(I58:L58) -> 0 | N58: =SUM(M32-M58) -> 0
C59: Land improvements | I59: 7800 | M59: =SUM(I59:L59) -> 7800 | N59: =SUM(M33-M59) -> 0
C60: Buildings and improvements | I60: 44719 | K60: 2072 | M60: =SUM(I60:L60) -> 46791 | N60: =SUM(M34-M60) -> 15365
C61: Vehicles | I61: 388599 | J61: -5619 | K61: 28996 | L61: -68958 | M61: =SUM(I61:L61) -> 343018 | N61: =SUM(M35-M61) -> 39829
C62: Office furniture and equipment | I62: 106686 | J62: 4070 | K62: 2698 | M62: =SUM(I62:L62) -> 113454 | N62: =SUM(M36-M62) -> 2873
B63: Library | M63: =SUM(I63:L63) -> 0 | N63: =SUM(M37-M63) -> 0
C64: Building and improvement | I64: 459597 | K64: 60398 | M64: =SUM(I64:L64) -> 519995 | N64: =SUM(M38-M64) -> 3335249
C65: Vehicles | I65: 49901 | M65: =SUM(I65:L65) -> 49901 | N65: =SUM(M39-M65) -> 0
C66: Furniture and equipment | I66: 51169 | J66: 778 | K66: 19755 | M66: =SUM(I66:L66) -> 71702 | N66: =SUM(M40-M66) -> 255419
C67: Books and videos | I67: 759823 | J67: 7656 | K67: 71241 | L67: -62768 | M67: =SUM(I67:L67) -> 775952 | N67: =SUM(M41-M67) -> -38748
C68: Total accumulated depreciation | I68: =SUM(I45:I67) -> 21235011 | J68: =SUM(J45:J67) -> 6945 | K68: =SUM(K45:K67) -> 571941 | L68: =SUM(L45:L67) -> -621419 | M68: =SUM(M45:M67) -> 21192478
B70: Total capital assets being depreciated, net | I70: =I42-I68 -> 4619580 | J70: =J42-J68 -> -6945 | K70: =K42-K68 -> 3322155 | L70: =L42-L68 -> -29341 | M70: =M42-M68 -> 7905449
B72: Governmental activities capital assets, net | I72: =I16+I70 -> 7059807 | J72: =J16+J70 -> -4605 | K72: =K16+K70 -> 4338713 | L72: =L16+L70 -> -3174416 | M72: =M16+M70 -> 8219499 | N72: =SUM(N45:N67,N10:N15) -> 8219499

Sheet Concordia
D1: Concordia PARISH POLICE JURY
D2: Capital Assets
D3: For the Year Ended December 31, 2014
I5: Beginning Balance | J5: Increases | K5: Decreases | L5: Ending Balance | M5: Cross Sectional
A7: Governmental Activities:
B8: Capital assets, not being depreciated:
C9: Land | I9: 7038 | K9: 0 | L9: =SUM(I9:K9) -> 7038 | M9: =SUM(L9) -> 7038
D10: Total capital assets, not being depreciated | I10: =SUM(I8:I9) -> 7038 | J10: =SUM(J8:J9) -> 0 | K10: =SUM(K8:K9) -> 0 | L10: =SUM(L8:L9) -> 7038
M11: =SUM(L11) -> 0
A12: Capital assets being depreciated: | M12: =SUM(L12) -> 0
B13: Buildings and Improvements | I13: 5929150 | J13: 77290 | L13: =SUM(I13:K13) -> 6006440
B14: Furniture and fixtures | I14: 441519 | K14: -4675 | L14: =SUM(I14:K14) -> 436844
B15: Machinery and equipment | I15: 2505252 | J15: 68817 | K15: -1375 | L15: =SUM(I15:K15) -> 2572694
B16: Transportation equipment | I16: 1049687 | L16: =SUM(I16:K16) -> 1049687
B17: Roads and bridges | I17: 12195458 | L17: =SUM(I17:K17) -> 12195458
M18: =SUM(L18) -> 0
D19: Total capital assets being depreciated | I19: =SUM(I13:I17) -> 22121066 | J19: =SUM(J13:J17) -> 146107 | K19: =SUM(K13:K17) -> -6050 | L19: =SUM(L13:L17) -> 22261123
A21: Less accumulated depreciation for: | O21: % of Total CA being Depreciated | P21: Accumulated Depreciation
B22: Buildings and Improvements | L22: -3251983.8 | M22: =L13+L22 -> 2754456.2 | O22: =L13/L19 -> 0.26981748 | P22: =L28*O22 -> -3251983.8
B23: Furniture and fixtures | L23: -236514 | M23: =L14+L23 -> 200330 | O23: =L14/L19 -> 0.019623628 | P23: =L28*O23 -> -236514.41
B24: Machinery and equipment | L24: -1392898 | M24: =L15+L24 -> 1179796 | O24: =L15/L19 -> 0.11556892 | P24: =L28*O24 -> -1392898.1
B25: Transportation equipment | L25: -568318 | M25: =L16+L25 -> 481369 | O25: =L16/L19 -> 0.047153371 | P25: =L28*O25 -> -568317.52
B26: Roads and bridges | L26: -6602818 | M26: =L17+L26 -> 5592640 | O26: =L17/L19 -> 0.5478366 | P26: =L28*O26 -> -6602818.2
D28: Total accumulated depreciation | I28: -11207573 | J28: -851009 | K28: 6050 | L28: -12052532 | O28: =SUM(O22:O26) -> 1 | P28: =SUM(P22:P26) -> -12052532
M29: =SUM(L29,L20) -> 0
B30: Total capital assets being depreciated, net | I30: =I19+I28 -> 10913493 | J30: =J19+J28 -> -704902 | K30: =K19+K28 -> 0 | L30: =L19+L28 -> 10208591
B32: Total capital assets (net) | I32: =I28+I19+I10 -> 10920531 | J32: =J28+J19+J10 -> -704902 | K32: =K28+K19+K10 -> 0 | L32: =L30+L10 -> 10215629 | M32: =SUM(M9:M26) -> 10215629

Sheet DeSoto
D1: DeSoto PARISH POLICE JURY
D2: Capital Assets
D3: For the Year Ended December 31, 2014
I5: Beginning Balance | J5: Additions | K5: Deletions | L5: Ending Balance | M5: Cross Sectional
A7: Primary Government
A8: Government Activities:
A9: Capital assets, not being depreciated:
B10: Land | I10: 1979943 | L10: =SUM(I10:K10) -> 1979943 | M10: =SUM(L10) -> 1979943
B11: Construction in progress | I11: 498894 | J11: 542003 | L11: =SUM(I11:K11) -> 1040897 | M11: =SUM(L11) -> 1040897
C12: Total assets not being depreciated | I12: =SUM(I10:I11) -> 2478837 | J12: =SUM(J10:J11) -> 542003 | K12: =SUM(K10:K11) -> 0 | L12: =SUM(L10:L11) -> 3020840
A14: Capital assets being depreciated:
B15: Buildings and improvements | I15: 26363585 | J15: 10457 | L15: =SUM(I15:K15) -> 26374042
B16: Land improvements - structures | I16: 5826378 | J16: 446963 | L16: =SUM(I16:K16) -> 6273341
B17: Furniture and equipment | I17: 12204954 | J17: 1319547 | L17: =SUM(I17:K17) -> 13524501
B18: Infrastructure | I18: 219055672 | L18: =SUM(I18:K18) -> 219055672
C19: Total capital assets being depreciated | I19: =SUM(I15:I18) -> 263450589 | J19: =SUM(J15:J18) -> 1776967 | K19: =SUM(K15:K18) -> 0 | L19: =SUM(L15:L18) -> 265227556
A21: Less accumulated depreciation for:
B22: Buildings and improvements | I22: 11767270 | J22: 666580 | K22: 0 | L22: =SUM(I22:K22) -> 12433850 | M22: =SUM(L15-L22) -> 13940192
B23: Land improvements - structures | I23: 347548 | J23: 285041 | K23: 0 | L23: =SUM(I23:K23) -> 632589 | M23: =SUM(L16-L23) -> 5640752
B24: Furniture and equipment | I24: 7078348 | J24: 1077580 | L24: =SUM(I24:K24) -> 8155928 | M24: =SUM(L17-L24) -> 5368573
B25: Infrastructure | I25: 171364654 | J25: 1879650 | L25: =SUM(I25:K25) -> 173244304 | M25: =SUM(L18-L25) -> 45811368
C26: Total accumulated depreciation | I26: =SUM(I22:I25) -> 190557820 | J26: =SUM(J22:J25) -> 3908851 | K26: =SUM(K22:K25) -> 0 | L26: =SUM(L22:L25) -> 194466671
B28: Total capital assets being depreciated, net | I28: =I19-I26 -> 72892769 | J28: =J19-J26 -> -2131884 | K28: =K19-K26 -> 0 | L28: =L19-L26 -> 70760885
B30: Governmental activities capital assets, net | I30: =I12+I28 -> 75371606 | J30: =J12+J28 -> -1589881 | K30: =K12+K28 -> 0 | L30: =L12+L28 -> 73781725 | M30: =SUM(M9:M29) -> 73781725
I32: Beginning Balance | J32: Increases | K32: Decreases | L32: Ending Balance
A33: Business-Type Activities:
B34: Capital assets, not being depreciated:
C35: Land | I35: 10175 | J35: 0 | K35: 0 | L35: =SUM(I35:K35) -> 10175 | M35: =SUM(L35) -> 10175
B37: Capital assets, depreciable:
C38: Sewer system | I38: 373375 | K38: 0 | L38: =SUM(I38:K38) -> 373375
C39: Treatment plant | I39: 101180 | K39: 0 | L39: =SUM(I39:K39) -> 101180
D41: Total capital assets, depreciable | I41: =SUM(I37:I39) -> 474555 | J41: =SUM(J37:J39) -> 0 | K41: =SUM(K37:K39) -> 0 | L41: =SUM(L37:L39) -> 474555
B43: Less accumulated depreciation for:
C44: Sewer system | I44: -373375 | L44: =SUM(I44:K44) -> -373375 | M44: =SUM(L44+L38) -> 0
C45: Treatment plant | I45: -101180 | L45: =SUM(I45:K45) -> -101180 | M45: =SUM(L45+L39) -> 0
D47: Total accumulated depreciation | I47: =SUM(I44:I45) -> -474555 | J47: =SUM(J44:J45) -> 0 | K47: =SUM(K44:K45) -> 0 | L47: =SUM(L44:L45) -> -474555
D49: Total capital assets, depreciable, net | I49: =I41+I47 -> 0 | J49: =J41+J47 -> 0 | K49: =K41+K47 -> 0 | L49: =L41+L47 -> 0
D51: Business-type activities capital assets, net | I51: =SUM(I49+I35) -> 10175 | J51: =SUM(J49-J41) -> 0 | K51: =SUM(K49-K41) -> 0 | L51: =SUM(L35+L49) -> 10175 | M51: =SUM(M35:M50) -> 10175

Sheet East Baton Rouge
D1: East Baton Rouge PARISH POLICE JURY
D2: Capital Assets
D3: For the Year Ended December 31, 2014
I5: Beginning Balance | J5: Increases | K5: Decreases | L5: Adjustments | M5: Ending Balance | N5: Cross Sectional
A7: Primary Government
A8: Government Activities:
A9: Capital assets, not being depreciated:
B10: Land and right-of-way | I10: 156885714 | J10: 1665773 | K10: -84801 | L10: 1767684 | M10: =SUM(I10:L10) -> 160234370 | N10: =SUM(M10) -> 160234370
B11: Construction work in progress | I11: 36499343 | J11: 21437704 | K11: 3270200 | L11: -9289197 | M11: =SUM(I11:L11) -> 51918050 | N11: =SUM(M11) -> 51918050
C12: Total assets not being depreciated | I12: =SUM(I10:I11) -> 193385057 | J12: =SUM(J10:J11) -> 23103477 | K12: =SUM(K10:K11) -> 3185399 | L12: =SUM(L10:L11) -> -7521513 | M12: =SUM(M10:M11) -> 212152420
A14: Capital assets being depreciated:
B15: Buildings | I15: 108060059 | J15: 67621 | K15: 144858 | M15: =SUM(I15:L15) -> 108272538
B16: Improvements (other than buildings)
C17: and infrastructure | I17: 220251390 | J17: 2972759 | K17: 8222959 | M17: =SUM(I17:L17) -> 231447108
B18: Equipment and equipment under lease | I18: 4631676 | K18: 559810 | M18: =SUM(I18:L18) -> 5191486
C19: Total capital assets being depreciated | I19: =SUM(I15:I18) -> 332943125 | J19: =SUM(J15:J18) -> 3040380 | K19: =SUM(K15:K18) -> 8927627 | L19: =SUM(L15:L18) -> 0 | M19: =SUM(M15:M18) -> 344911132
A21: Less accumulated depreciation for:
B22: Buildings | I22: -24025483 | K22: -2644445 | L22: 0 | M22: =SUM(I22:L22) -> -26669928 | N22: =SUM(M22,M15) -> 81602610
B23: Improvements (other than buildings)
C24: and infrastructure | I24: -6208523 | K24: -692827 | L24: 9965 | M24: =SUM(I24:L24) -> -6891385 | N24: =SUM(M24,M17) -> 224555723
B25: Equipment and equipment under lease | I25: -3526904 | K25: -454178 | L25: 0 | M25: =SUM(I25:L25) -> -3981082 | N25: =M18+M25 -> 1210404
C26: Total accumulated depreciation | I26: =SUM(I22:I25) -> -33760910 | J26: =SUM(J22:J25) -> 0 | K26: =SUM(K22:K25) -> -3791450 | L26: =SUM(L22:L25) -> 9965 | M26: =SUM(M22:M25) -> -37542395
B28: Total capital assets being depreciated, net | I28: =I26+I19 -> 299182215 | J28: =J26+J19 -> 3040380 | K28: =K26+K19 -> 5136177 | L28: =L26+L19 -> 9965 | M28: =M26+M19 -> 307368737
B30: Governmental activities capital assets, net | I30: =I12+I28 -> 492567272 | J30: =J12+J28 -> 26143857 | K30: =K12+K28 -> 8321576 | L30: =L12+L28 -> -7511548 | M30: =M12+M28 -> 519521157 | N30: =SUM(N10:N25) -> 519521157
I33: Beginning Balance | J33: Transfers | K33: Additions | L33: Deletions | M33: Ending Balance
A35: Business-type Activities:
A36: Capital assets not being depreciated:
B37: Land and right-of-way | I37: 1301778 | J37: 0 | K37: 110034 | L37: 0 | M37: =SUM(I37:L37) -> 1411812 | N37: =SUM(M37) -> 1411812
B38: Noise mitigation | I38: 1226000 | M38: =SUM(I38:L38) -> 1226000 | N38: =M38 -> 1226000
B39: Construction work in progress | I39: 3279798 | J39: -119742 | K39: 10471550 | M39: =SUM(I39:L39) -> 13631606 | N39: =SUM(M39) -> 13631606
C40: Total assets not being depreciated | I40: =SUM(I37:I39) -> 5807576 | J40: =SUM(J37:J39) -> -119742 | K40: =SUM(K37:K39) -> 10581584 | L40: =SUM(L37:L39) -> 0 | M40: =SUM(M37:M39) -> 16269418
A42: Capital assets being depreciated:
B43: Buildings | I43: 34602 | J43: 119742 | K43: 43137 | L43: 0 | M43: =SUM(I43:L43) -> 197481
B44: Improvements (other than buildings) | I44: 4953684 | L44: 0 | M44: =SUM(I44:L44) -> 4953684
C45: and infrastructure
B46: Equipment
C47: Total capital assets being depreciated | I47: =SUM(I43:I44) -> 4988286 | J47: =SUM(J43:J44) -> 119742 | K47: =SUM(K43:K44) -> 43137 | L47: =SUM(L43:L44) -> 0 | M47: =SUM(M43:M44) -> 5151165
A49: Less accumulated depreciation for:
B50: Buildings | I50: -412 | K50: -4943 | L50: 0 | M50: =SUM(I50:L50) -> -5355 | N50: =SUM(M50,M43) -> 192126
B51: Improvements (other than buildings) | I51: -333305 | K51: -202580 | L51: 0 | M51: =SUM(I51:L51) -> -535885 | N51: =SUM(M51,M44) -> 4417799
C52: and infrastructure
B53: Equipment
C54: Total accumulated depreciation | I54: =SUM(I50:I51) -> -333717 | J54: =SUM(J50:J51) -> 0 | K54: =SUM(K50:K51) -> -207523 | L54: =SUM(L50:L51) -> 0 | M54: =SUM(M50:M51) -> -541240
B56: Total capital assets being depreciated, net | I56: =SUM(I54,I47) -> 4654569 | J56: =SUM(J54,J47) -> 119742 | K56: =SUM(K54,K47) -> -164386 | L56: =SUM(L54,L47) -> 0 | M56: =SUM(M54,M47) -> 4609925
B58: Business-type activities capital assets, net | I58: =I40+I56 -> 10462145 | J58: =J40+J56 -> 0 | K58: =K40+K56 -> 10417198 | L58: =L40+L56 -> 0 | M58: =M40+M56 -> 20879343 | N58: =SUM(N50:N51,N37:N39) -> 20879343

Sheet East Carroll
D1: East Carroll PARISH POLICE JURY
D2: Capital Assets
D3: For the Year Ended December 31, 2014
I5: Beginning Balance | J5: Additions | K5: Deletions | L5: Ending Balance | M5: Cross Sectional
B7: Land | I7: 274665 | L7: =SUM(I7:K7) -> 274665 | M7: =SUM(L7) -> 274665
B8: Airport Land | I8: 101000 | L8: =SUM(I8:K8) -> 101000 | M8: =SUM(L8) -> 101000
B9: Construction in progress | I9: 261764 | J9: 3263 | L9: =SUM(I9:K9) -> 265027 | M9: =SUM(L9) -> 265027
C10: Total assets not being depreciated | I10: =SUM(I7:I9) -> 637429 | J10: =SUM(J7:J9) -> 3263 | K10: =SUM(K7:K9) -> 0 | L10: =SUM(L7:L9) -> 640692
B13: Buildings | I13: 2646828 | K13: -865 | L13: =SUM(I13:K13) -> 2645963
B14: Office equipment | I14: 427082 | J14: 4182 | K14: -118737 | L14: =SUM(I14:K14) -> 312527
B15: Furniture & fixtures | I15: 119551 | J15: 1200 | K15: -53352 | L15: =SUM(I15:K15) -> 67399
B16: Construction equipment | I16: 1727485 | J16: 673159 | K16: -467938 | L16: =SUM(I16:K16) -> 1932706
B17: Vehicles | I17: 2399424 | J17: 596645 | K17: -34695 | L17: =SUM(I17:K17) -> 2961374
B18: Books, periodicals & law books | I18: 342548 | L18: =SUM(I18:K18) -> 342548
B19: Infrastructure | L19: =SUM(I19:K19) -> 0
C20: Airport hangars | I20: 25000 | L20: =SUM(I20:K20) -> 25000
C21: Airport runway | I21: 1130666 | L21: =SUM(I21:K21) -> 1130666
C22: Road right-of-way | I22: 558234 | L22: =SUM(I22:K22) -> 558234
C23: Road surface | I23: 9140845 | L23: =SUM(I23:K23) -> 9140845
C24: Bridges | I24: 1759091 | L24: =SUM(I24:K24) -> 1759091
C25: Total capital assets being depreciated | I25: =SUM(I13:I24) -> 20276754 | J25: =SUM(J13:J24) -> 1275186 | K25: =SUM(K13:K24) -> -675587 | L25: =SUM(L13:L24) -> 20876353
A27: Less accumulated depreciation for:
B28: Buildings | I28: 1586519 | J28: 51488 | K28: -843 | L28: =SUM(I28:K28) -> 1637164 | M28: =SUM(L28,L13) -> 4283127
B29: Office equipment | I29: 349809 | J29: 25942 | K29: -117313 | L29: =SUM(I29:K29) -> 258438 | M29: =SUM(L29,L14) -> 570965
B30: Furniture & fixtures | I30: 84073 | J30: 6194 | K30: -51388 | L30: =SUM(I30:K30) -> 38879 | M30: =SUM(L30,L15) -> 106278
B31: Construction equipment | I31: 1199657 | J31: 140224 | K31: -466564 | L31: =SUM(I31:K31) -> 873317 | M31: =L16+L31 -> 2806023
B32: Vehicles | I32: 1969483 | J32: 148117 | K32: -31227 | L32: =SUM(I32:K32) -> 2086373 | M32: =L17+L32 -> 5047747
B33: Books, periodicals & law books | I33: 341650 | J33: 898 | L33: =SUM(I33:K33) -> 342548 | M33: =L18+L33 -> 685096
B34: Infrastructure | L34: =SUM(I34:K34) -> 0 | M34: =L19+L34 -> 0
C35: Airport hangars | I35: 24063 | J35: 625 | L35: =SUM(I35:K35) -> 24688 | M35: =L20+L35 -> 49688
C36: Airport runway | I36: 205040 | J36: 28267 | L36: =SUM(I36:K36) -> 233307 | M36: =L21+L36 -> 1363973
C37: Road surface | I37: 8432937 | J37: 35594 | L37: =SUM(I37:K37) -> 8468531 | M37: =L22+L37 -> 9026765
C38: Bridges | I38: 1166197 | J38: 28620 | L38: =SUM(I38:K38) -> 1194817 | M38: =L23+L38 -> 10335662
C39: Total accumulated depreciation | I39: =SUM(I28:I38) -> 15359428 | J39: =SUM(J28:J38) -> 465969 | K39: =SUM(K28:K38) -> -667335 | L39: =SUM(L28:L38) -> 15158062
B41: Total capital assets being depreciated, net | I41: =SUM(I25-I39) -> 4917326 | J41: =SUM(J25-J39) -> 809217 | K41: =SUM(K25-K39) -> -8252 | L41: =SUM(L25-L39) -> 5718291
B43: Governmental activities capital assets, net | I43: =I10+I41 -> 5554755 | J43: =J10+J41 -> 812480 | K43: =K10+K41 -> -8252 | L43: =L10+L41 -> 6358983 | M43: =SUM(M28:M38,M7:M9) -> 34916016
I46: Beginning Balance | J46: Additions | K46: Deletions | L46: Ending Balance
A48: Business-type Activities:
A49: Capital assets being depreciated:
B50: Office equipment | I50: 5810 | K50: -5810 | L50: =SUM(I50:K50) -> 0
B51: Furniture & fixtures | I51: 3131 | K51: 0 | L51: =SUM(I51:K51) -> 3131
B52: Vehicles | I52: 12365 | L52: =SUM(I52:K52) -> 12365
C53: Total capital assets being depreciated | I53: =SUM(I50:I52) -> 21306 | J53: =SUM(J50:J52) -> 0 | K53: =SUM(K50:K52) -> -5810 | L53: =SUM(L50:L52) -> 15496
A55: Less accumulated depreciation for:
B56: Office equipment | I56: 5810 | K56: -5810 | L56: =SUM(I56:K56) -> 0 | M56: =L50-L56 -> 0
B57: Furniture & fixtures | I57: 3130 | K57: 0 | L57: =SUM(I57:K57) -> 3130 | M57: =L51-L57 -> 1
B58: Vehicles | I58: 12366 | L58: =SUM(I58:K58) -> 12366 | M58: =L52-L58 -> -1
C59: Total accumulated depreciation | I59: =SUM(I56:I58) -> 21306 | J59: =SUM(J56:J58) -> 0 | K59: =SUM(K56:K58) -> -5810 | L59: =SUM(L56:L58) -> 15496
B62: Business-type activities capital assets, net | I62: =I59-I53 -> 0 | J62: =J59-J53 -> 0 | K62: =K59-K53 -> 0 | L62: =L59-L53 -> 0 | M62: =SUM(M47:M58) -> 0

Sheet East Feliciana
D1: EAST FELICIANA PARISH POLICE JURY
D2: Capital Assets
D3: For the Year Ended December 31, 2014
I5: Beginning Balance | J5: Additions | K5: Deletions | L5: Ending Balance | M5: Cross Sectional
A7: Governmental Activities:
B8: Capital assets, not being depreciated:
C9: Land | I9: 259230 | L9: 259230 | M9: 259230
D10: Total capital assets, not being depreciated | I10: =SUM(I9) -> 259230 | J10: =SUM(J9) -> 0 | K10: =SUM(K9) -> 0 | L10: =SUM(L9) -> 259230
A12: Capital assets being depreciated:
B13: Buildings | I13: 9627258.6 | J13: 316312.51 | L13: =SUM(I13:J13) -> 9943571.1
B14: Less: accumulated depreciation | I14: 4361370.5 | J14: 207415.32 | L14: =SUM(I14:J14) -> 4568785.8
D15: Net Buildings | I15: =SUM(I13-I14) -> 5265888.1 | J15: =SUM(J13-J14) -> 108897.19 | K15: =SUM(K13-K14) -> 0 | L15: =SUM(L13-L14) -> 5374785.3 | M15: =SUM(L13-L14) -> 5374785.3
B17: Equipment/Vehicles | I17: 4182495.3 | J17: 372417.55 | L17: =SUM(I17:J17) -> 4554912.8
B18: Less: accumulated depreciation | I18: 2351340 | J18: 195024.84 | L18: =SUM(I18:J18) -> 2546364.9
D19: Net Equipment/vehicles | I19: =SUM(I17-I18) -> 1831155.3 | J19: =SUM(J17-J18) -> 177392.71 | K19: =SUM(K17-K18) -> 0 | L19: =SUM(L17-L18) -> 2008548 | M19: =SUM(L17-L18) -> 2008548
B21: Streets/Bridges | I21: 1342103.2 | J21: 4562091.6 | L21: =SUM(I21:J21) -> 5904194.8
B22: Less: accumulated depreciation | I22: 385299.95 | J22: 299708.9 | L22: =SUM(I22:J22) -> 685008.85
D23: Net Furniture and fixtures | I23: =SUM(I21-I22) -> 956803.22 | J23: =SUM(J21-J22) -> 4262382.7 | K23: =SUM(K21-K22) -> 0 | L23: =SUM(L21-L22) -> 5219185.9 | M23: =SUM(L21-L22) -> 5219185.9
B24: Capital assets, being depreciated, net | I24: 8053846.6 | J24: 4548672.6 | L24: =SUM(I24:J24) -> 12602519
B25: Capital assets, net | I25: =SUM(I10+I24) -> 8313076.6 | J25: =SUM(J10+J24) -> 4548672.6 | K25: =SUM(K10+K24) -> 0 | L25: =SUM(L10+L24) -> 12861749 | M25: =SUM(M9:M23) -> 12861749

Sheet Evangeline
D1: Evangeline PARISH POLICE JURY
D2: Capital Assets
D3: For the Year Ended December 31, 2014
I5: Beginning Balance | J5: Additions | K5: Deletions | L5: Ending Balance | M5: Cross Sectional
A7: Primary Government
A8: Government Activities:
A9: Capital assets, not being depreciated:
B10: Land | I10: 876298 | L10: =SUM(I10:K10) -> 876298 | M10: =SUM(L10) -> 876298
B11: Construction in progress | I11: 3465939 | J11: 3717988 | K11: -3551647 | L11: =SUM(I11:K11) -> 3632280 | M11: =SUM(L11) -> 3632280
A12: Other capital assets: | L12: =SUM(I12:K12) -> 0 | M12: =SUM(L12) -> 0
B13: Buildings and improvements | I13: 11557845 | J13: 1892049 | L13: =SUM(I13:K13) -> 13449894
B14: Infrastructure | I14: 20765472 | J14: 726349 | L14: =SUM(I14:K14) -> 21491821
B15: Vehicles | I15: 704276 | L15: =SUM(I15:K15) -> 704276
B16: Equipment, furniture and fixtures | I16: 6383290 | J16: 15500 | L16: =SUM(I16:K16) -> 6398790
C17: Total capital assets | I17: =SUM(I10:I16) -> 43753120 | J17: =SUM(J10:J16) -> 6351886 | K17: =SUM(K10:K16) -> -3551647 | L17: =SUM(L10:L16) -> 46553359
A19: Less accumulated depreciation for:
B20: Buildings | I20: 4481261 | J20: 327407 | K20: 0 | L20: =SUM(I20:K20) -> 4808668 | M20: =L13-L20 -> 8641226
B21: Infrastructure | I21: 10056218 | J21: 1025012 | K21: 0 | L21: =SUM(I21:K21) -> 11081230 | M21: =L14-L21 -> 10410591
B22: Vehicles | I22: 579088 | J22: 45992 | L22: =SUM(I22:K22) -> 625080 | M22: =L15-L22 -> 79196
B23: Equipment, furniture and fixtures | I23: 3973056 | J23: 417960 | K23: 0 | L23: =SUM(I23:K23) -> 4391016 | M23: =L16-L23 -> 2007774
C24: Total accumulated depreciation | I24: =SUM(I20:I23) -> 19089623 | J24: =SUM(J20:J23) -> 1816371 | K24: =SUM(K20:K23) -> 0 | L24: =SUM(L20:L23) -> 20905994
B26: Governmental activities capital assets, net | I26: =I17-I24 -> 24663497 | J26: =J17-J24 -> 4535515 | K26: =K17-K24 -> -3551647 | L26: =L17-L24 -> 25647365 | M26: =SUM(M20:M23,M10:M16) -> 25647365
I29: Beginning Balance | J29: Additions | K29: Deletions | L29: Ending Balance | M29: Cross Sectional
A31: Business-type Activities:
A32: Capital assets being depreciated: | N32: % of CA being depreciated | O32: Accumulated Depreciation
B33: Sewer System | I33: 828812 | K33: 0 | L33: =SUM(I33:K33) -> 828812 | N33: =L33/L35 -> 0.97670346 | O33: =L40*N33 -> 572949.88
B34: Equipment, furniture and fixtures | I34: 19769 | L34: =SUM(I34:K34) -> 19769 | N34: =L34/L35 -> 0.023296539 | O34: =L40*N34 -> 13666.122
C35: Total capital assets | I35: =SUM(I33:I34) -> 848581 | J35: =SUM(J33:J34) -> 0 | K35: =SUM(K33:K34) -> 0 | L35: =SUM(L33:L34) -> 848581 | N35: =SUM(N33:N34) -> 1 | O35: =SUM(O33:O34) -> 586616
A37: Less accumulated depreciation for:
B38: Sewer System | L38: 572950 | M38: =L33-L38 -> 255862
B39: Equipment, furniture and fixtures | L39: 13666 | M39: =L34-L39 -> 6103
C40: Total accumulated depreciation | I40: -557482 | J40: 29134 | L40: 586616
B43: Business-type activities capital assets, net | I43: =SUM(I35+I40) -> 291099 | J43: =SUM(J35-J40) -> -29134 | K43: =SUM(K35-K40) -> 0 | L43: =SUM(L35-L40) -> 261965 | M43: =SUM(M33:M34:M40) -> 261965

Sheet Franklin
D1: Franklin PARISH POLICE JURY
D2: Capital Assets
D3: For the Year Ended December 31, 2014
I5: Beginning Balance | J5: Additions | K5: Deletions | L5: Ending balance | M5: Cross Sectional
A7: Primary Government
A8: Government Activities:
A9: Capital assets, not being depreciated:
B10: Land | I10: 390416 | L10: =SUM(I10:K10) -> 390416 | M10: =L10 -> 390416
B11: Construction in progess | I11: 686392 | J11: 1632281 | K11: -216623 | L11: =SUM(I11:K11) -> 2102050 | M11: =L11 -> 2102050
B12: Assets under Capital Lease | I12: 46969 | J12: 70000 | K12: -49969 | L12: 70000 | M12: =L12 -> 70000
C13: Total capital assets not being depreciated | I13: =SUM(I10:I12) -> 1123777 | J13: =SUM(J10:J12) -> 1702281 | K13: =SUM(K10:K12) -> -266592 | L13: =SUM(L10:L12) -> 2562466
A15: Capital assets being depreciated:
B16: Infrastructure - roads | I16: 87120216 | J16: 276051 | L16: =SUM(I16:K16) -> 87396267
B17: Infrastructure - bridges | I17: 3366140 | L17: =SUM(I17:K17) -> 3366140
B18: Buildings and improvements | I18: 4772535 | L18: =SUM(I18:K18) -> 4772535
B19: Improvements other than buildings | I19: 2593516 | L19: =SUM(I19:K19) -> 2593516
B20: Office furniture and equipment | I20: 60459 | J20: 3189 | L20: =SUM(I20:K20) -> 63648
B21: Heavy equipment | I21: 1458017 | J21: 468759 | K21: -153388 | L21: =SUM(I21:K21) -> 1773388
B22: Other equipment | I22: 401139 | J22: 94658 | L22: =SUM(I22:K22) -> 495797
B23: Vehicles | I23: 1200270 | J23: 23703 | L23: =SUM(I23:K23) -> 1223973
C24: Total capital assets being depreciated | I24: =SUM(I16:I23) -> 100972292 | J24: =SUM(J16:J23) -> 866360 | K24: =SUM(K16:K23) -> -153388 | L24: =SUM(L16:L23) -> 101685264
A26: Less accumulated depreciation for:
B27: Infrastructure - roads | I27: -75156647 | J27: -743606 | K27: - | L27: =SUM(I27:K27) -> -75900253 | M27: =SUM(L16+L27) -> 11496014
B28: Infrastructure - bridges | I28: -1622639 | J28: -43749 | K28: - | L28: =SUM(I28:K28) -> -1666388 | M28: =SUM(L17+L28) -> 1699752
B29: Buildings and improvements | I29: -3457134 | J29: -119343 | L29: =SUM(I29:K29) -> -3576477 | M29: =SUM(L18+L29) -> 1196058
B30: Improvements other than buildings | I30: -1669272 | J30: -111001 | K30: - | L30: =SUM(I30:K30) -> -1780273 | M30: =SUM(L19+L30) -> 813243
B31: Office furniture and equipment | I31: -59015 | J31: -1119 | L31: =SUM(I31:K31) -> -60134 | M31: =SUM(L20+L31) -> 3514
B32: Heavy equipment | I32: -892220 | J32: -123784 | K32: 29382 | L32: =SUM(I32:K32) -> -986622 | M32: =SUM(L21+L32) -> 786766
B33: Other equipment | I33: -354420 | J33: -32684 | L33: =SUM(I33:K33) -> -387104 | M33: =SUM(L22+L33) -> 108693
B34: Vehicles | I34: -1098166 | J34: -48533 | L34: =SUM(I34:K34) -> -1146699 | M34: =SUM(L23+L34) -> 77274
C35: Total accumulated depreciation | I35: =SUM(I27:I34) -> -84309513 | J35: =SUM(J27:J34) -> -1223819 | K35: =SUM(K27:K34) -> 29382 | L35: =SUM(L27:L34) -> -85503950
B36: Total capital assets being depreciated, net | I36: =SUM(I24+I35) -> 16662779 | J36: =SUM(J24+J35) -> -357459 | K36: =SUM(K24+K35) -> -124006 | L36: =SUM(L24+L35) -> 16181314
B38: Total capital assets, net | I38: =I13+I36 -> 17786556 | J38: =J13+J36 -> 1344822 | K38: =K13+K36 -> -390598 | L38: =L13+L36 -> 18743780 | M38: =SUM(M10:M34) -> 18743780

Sheet Grant
D1: Grant PARISH POLICE JURY
D2: Capital Assets
D3: For the Year Ended December 31, 2014
I5: Beginning Balance | J5: Additions | K5: Deletions | L5: Ending Balance | M5: Cross Sectional
A7: Primary Government
A8: Government Activities:
A9: Capital assets, not being depreciated:
B10: Construction in progress | I10: 37900 | J10: 22510 | L10: =SUM(I10:K10) -> 60410 | M10: =SUM(L10) -> 60410
B11: Land | I11: 203250 | L11: =SUM(I11:K11) -> 203250 | M11: =SUM(L11) -> 203250 | N11: Total CA not being depreciated
C12: Total | I12: =SUM(I10:I11) -> 241150 | J12: =SUM(J10:J11) -> 22510 | K12: =SUM(K10:K11) -> 0 | L12: =SUM(L10:L11) -> 263660 | N12: =SUM(L14:L17) -> 9913888
A13: Depreciable Capital Assets | L13: =SUM(I13:K13) -> 0 | M13: =SUM(L13) -> 0 | N13: % of CA | O13: Accumulayed Depreciation | P13: CA less Depreciation
B14: Buildings and improvements | I14: 2641293 | L14: =SUM(I14:K14) -> 2641293 | N14: =L14/N12 -> 0.26642353 | O14: =L18*N14 -> -1155349.6 | P14: =L14+O14 -> 1485943.4
B15: Furniture, fixtures and equipment | I15: 2575446 | J15: 101080 | K15: -66046 | L15: =SUM(I15:K15) -> 2610480 | N15: =L15/N12 -> 0.26331546 | O15: =L18*N15 -> -1141871.5 | P15: =L15+O15 -> 1468608.5
B16: Infrastructure | I16: 4452468 | L16: =SUM(I16:K16) -> 4452468 | N16: =L16/N12 -> 0.44911421 | O16: =L18*N16 -> -1947590.5 | P16: =L16+O16 -> 2504877.5
B17: Solid Waste Station | I17: 209647 | L17: =SUM(I17:K17) -> 209647 | N17: =L17/N12 -> 0.021146799 | O17: =L18*N17 -> -91703.412 | P17: =L17+17 -> 209664
B18: Accumulated Depreciation | I18: -4036526 | J18: -366035 | K18: 66046 | L18: =SUM(I18:K18) -> -4336515 | N18: =SUM(N14:N17) -> 1 | O18: =SUM(O14:O17) -> -4336515 | P18: =SUM(P14:P17) -> 5669093.4
C19: Total | I19: =SUM(I13:I18) -> 5842328 | J19: =SUM(J13:J18) -> -264955 | K19: =SUM(K13:K18) -> 0 | L19: =SUM(L13:L18) -> 5577373 | M19: =SUM(L19) -> 5577373
B22: Governmental activities capital assets, net | I22: =SUM(I19+I12) -> 6083478 | J22: =SUM(J19+J12) -> -242445 | K22: =SUM(K19+K12) -> 0 | L22: =SUM(P18+M10+M11) -> 5932753.4 | M22: =SUM(P18+M11+M10) -> 5932753.4
I25: Beginning Balance | J25: Additions | K25: Deletions | L25: Ending Balance | M25: Cross Sectional | N25: % of CA
N26: Total CA not being depreciated
A27: Business-type Activities: | N27: =SUM(L29:L31) -> 1512362
A28: Depreciable Capital Assets | N28: % of CA | O28: Accumulayed Depreciation | P28: CA less Depreciation
B29: Distribution System | I29: 1245902 | K29: 0 | L29: =SUM(I29:K29) -> 1245902 | N29: =L29/N27 -> 0.82381202 | O29: =L38*N29 -> -958196.36 | P29: =L29+O29 -> 287705.64
B30: Buildings | I30: 7878 | K30: -625 | L30: =SUM(I30:K30) -> 7253 | N30: =L30/N27 -> 0.0047958095 | O30: =L38*N30 -> -5578.1259 | P30: =L30+O30 -> 1674.8741
B31: Equipment | I31: 233158 | J31: 27643 | K31: -1594 | L31: =SUM(I31:K31) -> 259207 | N31: =L31/N27 -> 0.17139217 | O31: =L38*N31 -> -199350.51 | P31: =L31+O31 -> 59856.486
C32: Total assets being depreciated | I32: =SUM(I29:I31) -> 1486938 | J32: =SUM(J29:J31) -> 27643 | K32: =SUM(K29:K31) -> -2219 | L32: =SUM(L29:L31) -> 1512362 | M32: =SUM(L32) -> 1512362 | N32: =SUM(N28:N31) -> 1 | O32: =SUM(O28:O31) -> -1163125 | P32: =SUM(P28:P31) -> 349237
A34: Less accumulated depreciation for:
B35: Distribution System | L35: =L29+O29 -> 287705.64
B36: Buildings | L36: =L30+O30 -> 1674.8741
B37: Equipment | L37: =L31+O31 -> 59856.486
C38: Total accumulated depreciation | I38: -1129744 | L38: -1163125
C39: Total capital assets being depreciated, net | I39: =SUM(I29:I31) -> 1486938 | J39: =SUM(J37+J32) -> 27643 | K39: =SUM(K37+K32) -> -2219 | L39: =SUM(L38+L32) -> 349237
C40: Business-type activities capital assets, net | I40: =SUM(I38+I32) -> 357194 | J40: =SUM(J37+J32) -> 27643 | K40: =SUM(K37+K32) -> -2219 | L40: =SUM(L38+L32) -> 349237 | M40: =SUM(M32+O32) -> 349237

Sheet Iberia
D1: Iberia PARISH POLICE JURY
D2: Capital Assets
D3: For the Year Ended December 31, 2014
I5: Beginning Balance | J5: Additions | K5: Deletions | L5: Ending Balance | M5: Cross Sectional
B10: Land | I10: 2466687 | L10: =SUM(I10:K10) -> 2466687 | M10: =SUM(L10) -> 2466687
B11: Construction in progress | I11: 3089315 | J11: 2211603 | K11: -260819 | L11: =SUM(I11:K11) -> 5040099 | M11: =SUM(L11) -> 5040099
C12: Total assets not being depreciated | I12: =SUM(I10:I11) -> 5556002 | J12: =SUM(J10:J11) -> 2211603 | K12: =SUM(K10:K11) -> -260819 | L12: =SUM(L10:L11) -> 7506786
B15: Land Improvements | I15: 10470 | L15: =SUM(I15:K15) -> 10470
B16: Buildings and improvements | I16: 31908823 | L16: =SUM(I16:K16) -> 31908823
B17: Furniture and equipment | I17: 10092962 | J17: 691288 | K17: -108622 | L17: =SUM(I17:K17) -> 10675628
B18: Infrastructure | I18: 122899489 | L18: =SUM(I18:K18) -> 122899489
C19: Total capital assets being depreciated | I19: =SUM(I12:I18) -> 170467746 | J19: =SUM(J12:J18) -> 2902891 | K19: =SUM(K12:K18) -> -369441 | L19: =SUM(L12:L18) -> 173001196
A21: Less accumulated depreciation for:
B22: Land Improvements | I22: 7374 | J22: 524 | L22: =SUM(I22:K22) -> 7898 | M22: =SUM(L15-L22) -> 2572
B23: Buildings and improvements | I23: 17209476 | J23: 722890 | L23: =SUM(I23:K23) -> 17932366 | M23: =SUM(L16-L23) -> 13976457
B24: Furniture and equipment | I24: 6575721 | J24: 707711 | K24: -108622 | L24: =SUM(I24:K24) -> 7174810 | M24: =SUM(L17-L24) -> 3500818
B25: Infrastructure | I25: 50638189 | J25: 3027185 | L25: =SUM(I25:K25) -> 53665374 | M25: =SUM(L18-L25) -> 69234115
C26: Total accumulated depreciation | I26: =SUM(I22:I25) -> 74430760 | J26: =SUM(J22:J25) -> 4458310 | K26: =SUM(K22:K25) -> -108622 | L26: =SUM(L22:L25) -> 78780448
B28: Total capital assets being depreciated, net | I28: =SUM(I19-I26) -> 96036986 | J28: =SUM(J19-J26) -> -1555419 | K28: =SUM(K19-K26) -> -260819 | L28: =SUM(L19-L26) -> 94220748 | M28: =SUM(M10:M25) -> 94220748

Sheet Iberville
D1: IBERVILLE PARISH POLICE JURY
D2: Capital Assets
D3: For the Year Ended December 31, 2014
B5: Primary Government - Governmental Activities:
E6: Land | F6: Construction in Progress | G6: Buildings and Improvement | H6: Infrastructure | I6: Furniture and Equipment | J6: Total
C7: Cost at December 31, 2013 | E7: 2975825 | F7: 6218861 | G7: 40201920 | H7: 81534271 | I7: 28854339 | J7: =SUM(E7:I7) -> 159785216
D8: Additions | E8: 129555 | F8: 15990084 | G8: 264872 | H8: 2707633 | I8: 575079 | J8: =SUM(E8:I8) -> 19667223
D9: Deletions | E9: - | F9: - | G9: - | H9: - | I9: -696843 | J9: =SUM(E9:I9) -> -696843
C10: Cost at December 31, 2014 | E10: =SUM(E7:E9) -> 3105380 | F10: =SUM(F7:F9) -> 22208945 | G10: =SUM(G7:G9) -> 40466792 | H10: =SUM(H7:H9) -> 84241904 | I10: =SUM(I7:I9) -> 28732575 | J10: =SUM(J7:J9) -> 178755596
B12: Depreciation:
C13: Accumulated Depreciation
C14: at December 31, 2013 | E14: 0 | F14: 0 | G14: 8476893 | H14: 26291269 | I14: 24830661 | J14: 59598823
D15: Additions | E15: 0 | F15: 0 | G15: 994575 | H15: 2759266 | I15: 821932 | J15: 4575773
D16: Deletions | E16: 0 | F16: 0 | G16: - | H16: - | I16: -696843 | J16: -696843
C17: Accumulated Depreciation | F17: -
C18: at December 31, 2014 | E18: =SUM(E14:E16) -> 0 | F18: =SUM(F14:F16) -> 0 | G18: =SUM(G14:G16) -> 9471468 | H18: =SUM(H14:H16) -> 29050535 | I18: =SUM(I14:I16) -> 24955750 | J18: =SUM(J14:J16) -> 63477753
C21: Capital Assets net of
C22: Accumulated Depreciation
C23: at December 31, 2014 | G23: =SUM(G10- G18) -> 30995324 | H23: =SUM(H10- H18) -> 55191369 | I23: =SUM(I10- I18) -> 3776825 | J23: =SUM(J10- J18) -> 115277843
C25: Cross Sectional | E25: =E10 -> 3105380 | F25: =F10 -> 22208945 | G25: =SUM(G23) -> 30995324 | H25: =SUM(H23) -> 55191369 | I25: =SUM(I23) -> 3776825 | J25: =SUM(J23) -> 115277843
B27: Primary Government - Business Type Activities:
E28: Land | F28: Construction in Progress | G28: Buildings and Improvement | H28: Equipment | I28: Total
C29: Cost at December 31, 2013 | E29: 193511 | F29: 156733 | G29: 19047618 | H29: 1070643 | I29: =SUM(E29:H29) -> 20468505
D30: Additions | E30: - | F30: 530326 | G30: 151083 | H30: 244150 | I30: =SUM(F30:H30) -> 925559
D31: Transfer | E31: - | F31: -
D32: Deletions | E32: - | F32: - | G32: - | H32: -
C33: Cost at December 31, 2014 | E33: =SUM(E29:E32) -> 193511 | F33: =SUM(F29:F32) -> 687059 | G33: =SUM(G29:G32) -> 19198701 | H33: =SUM(H29:H32) -> 1314793 | I33: =SUM(I29:I32) -> 21394064
B35: Depreciation:
C36: Accumulated Depreciation
C37: at December 31, 2012 | E37: 0 | F37: 0 | G37: 8976189 | H37: 916130 | I37: =SUM(E37:H37) -> 9892319
D38: Additions | E38: - | F38: - | G38: 514310 | H38: 61666 | I38: =SUM(E38:H38) -> 575976
D39: Transfer | E39: - | F39: - | G39: - | I39: -
D40: Deletions | E40: - | F40: - | G40: 0 | I40: 0
C41: Accumulated Depreciation
C42: at December 31, 2013 | E42: =SUM(E37:E40) -> 0 | F42: =SUM(F37:F40) -> 0 | G42: =SUM(G37:G40) -> 9490499 | H42: =SUM(H37:H41) -> 977796 | I42: =SUM(I37:I40) -> 10468295
C44: Capital Assets net of
C45: Accumulated Depreciation
C46: at December 31, 2013 | E46: =SUM(E33-E42) -> 193511 | F46: =SUM(F33-F42) -> 687059 | G46: =SUM(G33-G42) -> 9708202 | H46: =SUM(H33-H42) -> 336997 | I46: =SUM(I33-I42) -> 10925769
C49: Cross Sectional | E49: =SUM(E46) -> 193511 | F49: =SUM(F46) -> 687059 | G49: =SUM(G46) -> 9708202 | H49: =SUM(H46) -> 336997 | I49: =SUM(I46) -> 10925769

Sheet Jackson
D1: Jackson PARISH POLICE JURY
D2: Capital Assets
D3: For the Year Ended December 31, 2014
I5: Beginning Balance | J5: Additions | K5: Deletions | L5: Ending balance | M5: Cross Sectional
A7: Primary Government
A8: Government Activities:
A9: Capital assets, not being depreciated:
B10: Land | I10: 427562 | J10: 6350 | L10: =SUM(I10:K10) -> 433912 | M10: =L10 -> 433912
B11: Construction in progess | I11: 689578 | J11: 934357 | K11: -1598026 | L11: =SUM(I11:K11) -> 25909 | M11: =L11 -> 25909
C12: Total capital assets not being depreciated | I12: =SUM(I10:I11) -> 1117140 | J12: =SUM(J10:J11) -> 940707 | K12: =SUM(K10:K11) -> -1598026 | L12: =SUM(L10:L11) -> 459821
A14: Capital assets being depreciated:
B15: Buildings and improvements | I15: 7482614 | J15: 1598026 | L15: =SUM(I15:K15) -> 9080640
B16: Vehicles | I16: 2271290 | J16: 376664 | K16: -37420 | L16: =SUM(I16:K16) -> 2610534
B17: Equipment/machinery/furniture | I17: 4005476 | J17: 204759 | K17: -343215 | L17: =SUM(I17:K17) -> 3867020
B18: Infrastructure/Roads | I18: 17722469 | J18: 875163 | L18: =SUM(I18:K18) -> 18597632
C19: Total capital assets being depreciated | I19: =SUM(I15:I18) -> 31481849 | J19: =SUM(J15:J18) -> 3054612 | K19: =SUM(K15:K18) -> -380635 | L19: =SUM(L15:L18) -> 34155826
A21: Less accumulated depreciation for:
B22: Buildings and improvements | I22: 2529070 | J22: 205726 | K22: - | L22: =SUM(I22:K22) -> 2734796 | M22: =SUM(L15-L22) -> 6345844
B23: Vehicles | I23: 1659257 | J23: 144921 | K23: -37420 | L23: =SUM(I23:K23) -> 1766758 | M23: =SUM(L16-L23) -> 843776
B24: Equipment/machinery/furniture | I24: 2005948 | J24: 469734 | K24: -336920 | L24: =SUM(I24:K24) -> 2138762 | M24: =SUM(L17-L24) -> 1728258
B25: Infrastructure/Roads | I25: 10005086 | J25: 1518891 | K25: - | L25: =SUM(I25:K25) -> 11523977 | M25: =SUM(L18-L25) -> 7073655
C26: Total accumulated depreciation | I26: =SUM(I22:I25) -> 16199361 | J26: =SUM(J22:J25) -> 2339272 | K26: =SUM(K22:K25) -> -374340 | L26: =SUM(L22:L25) -> 18164293
B27: Total capital assets being depreciated, net | I27: =SUM(I19-I26) -> 15282488 | J27: =SUM(J19-J26) -> 715340 | K27: =SUM(K19-K26) -> -6295 | L27: =SUM(L19-L26) -> 15991533
B29: Total capital assets, net | I29: =I12+I27 -> 16399628 | J29: =J12+J27 -> 1656047 | K29: =K12+K27 -> -1604321 | L29: =L12+L27 -> 16451354 | M29: =SUM(M10:M25) -> 16451354

Sheet Jefferson Davis
D1: Jefferson Davis PARISH POLICE JURY
D2: Capital Assets
D3: For the Year Ended December 31, 2014
I5: Beginning Balance | J5: Additions | K5: Deletions | L5: Transfers | M5: Ending Balance | N5: Cross Sectional
A7: Primary Government
A8: Government Activities:
A9: Capital assets, not being depreciated:
B10: Land | I10: 525705 | J10: 321202 | M10: =SUM(I10:L10) -> 846907 | N10: =SUM(M10) -> 846907
B11: Construction in progress | I11: 88007 | J11: 698039 | K11: -18802 | M11: =SUM(I11:L11) -> 767244 | N11: =SUM(M11) -> 767244
C12: Total assets not being depreciated | I12: =SUM(I10:I11) -> 613712 | J12: =SUM(J10:J11) -> 1019241 | K12: =SUM(K10:K11) -> -18802 | L12: =SUM(L10:L11) -> 0 | M12: =SUM(M10:M11) -> 1614151
A14: Capital assets being depreciated:
B15: Buildings and improvements | I15: 12654039 | J15: 109075 | M15: =SUM(I15:L15) -> 12763114
B16: Vehicles | I16: 5457874 | J16: 669304 | K16: -149769 | M16: =SUM(I16:L16) -> 5977409
B17: Maintenance equipment | I17: 2229143 | J17: 174097 | K17: -116384 | M17: =SUM(I17:L17) -> 2286856
B18: Machinery and equipment | I18: 1619277 | J18: 31966 | K18: -9101 | M18: =SUM(I18:L18) -> 1642142
B19: Office furniture and equipment | I19: 338935 | J19: 15005 | K19: -2425 | M19: =SUM(I19:L19) -> 351515
B20: Sewer and sewer improvements | I20: 318782 | M20: =SUM(I20:L20) -> 318782
B21: Infrastructure | I21: 23902567 | J21: 311211 | M21: =SUM(I21:L21) -> 24213778
C22: Total capital assets being depreciated | I22: =SUM(I15:I21) -> 46520617 | J22: =SUM(J15:J21) -> 1310658 | K22: =SUM(K15:K21) -> -277679 | L22: =SUM(L15:L21) -> 0 | M22: =SUM(M15:M21) -> 47553596
A24: Less accumulated depreciation for:
B25: Buildings and improvements | I25: 4025023 | J25: 407679 | L25: 0 | M25: =SUM(I25:L25) -> 4432702 | N25: =M15-M25 -> 8330412
B26: Vehicles | I26: 2805389 | J26: 378796 | K26: -149769 | L26: 0 | M26: =SUM(I26:L26) -> 3034416 | N26: =M16-M26 -> 2942993
B27: Maintenance equipment | I27: 1246089 | J27: 148275 | K27: -76326 | M27: =SUM(I27:L27) -> 1318038 | N27: =M17-M27 -> 968818
B28: Machinery and equipment | I28: 1274212 | J28: 79503 | K28: -9051 | M28: =SUM(I28:L28) -> 1344664 | N28: =M18-M28 -> 297478
B29: Office furniture and equipment | I29: 268608 | J29: 27376 | K29: -2425 | M29: =SUM(I29:L29) -> 293559 | N29: =M19-M29 -> 57956
B30: Sewer and sewer improvements | I30: 71628 | J30: 7970 | M30: =SUM(I30:L30) -> 79598 | N30: =M20-M30 -> 239184
B31: Infrastrucuture | I31: 3878466 | J31: 802770 | M31: =SUM(I31:L31) -> 4681236 | N31: =M21-M31 -> 19532542
C32: Total accumulated depreciation | I32: =SUM(I25:I31) -> 13569415 | J32: =SUM(J25:J31) -> 1852369 | K32: =SUM(K25:K31) -> -237571 | L32: =SUM(L25:L31) -> 0 | M32: =SUM(M25:M31) -> 15184213
B34: Total capital assets being depreciated, net | I34: =I22-I32 -> 32951202 | J34: =J22-J32 -> -541711 | K34: =K22-K32 -> -40108 | L34: =L22-L32 -> 0 | M34: =M22-M32 -> 32369383
B36: Governmental activities capital assets, net | I36: =I12+I34 -> 33564914 | J36: =J12+J34 -> 477530 | K36: =K12+K34 -> -58910 | L36: =L12+L34 -> 0 | M36: =M12+M34 -> 33983534 | N36: =SUM(N25:N31, N10:N12) -> 33983534

Sheet Jefferson
D1: Jefferson PARISH POLICE JURY
D2: Capital Assets
D3: For the Year Ended December 31, 2014
I5: Beginning Balance | J5: Increases | K5: Deletions | L5: Completed Construction | M5: Transfers (To) From Other Funds | N5: Ending Balance | O5: Cross Sectional
B10: Land and land improvements | I10: 64274 | L10: 2723 | N10: =SUM(I10:M10) -> 66997 | O10: =SUM(N10) -> 66997
B11: Construction in progress | I11: 178907 | J11: 113751 | L11: -112451 | M11: -13502 | N11: =SUM(I11:M11) -> 166705 | O11: =SUM(N11) -> 166705
C12: Total assets not being depreciated | I12: =SUM(I10:I11) -> 243181 | J12: =SUM(J10:J11) -> 113751 | K12: =SUM(K10:K11) -> 0 | L12: =SUM(L10:L11) -> -109728 | M12: =SUM(M10:M11) -> -13502 | N12: =SUM(N10:N11) -> 233702
B15: Buildings | I15: 380988 | L15: 4122 | N15: =SUM(I15:M15) -> 385110
B16: Improvements other than buildings | I16: 187562 | L16: 4098 | N16: =SUM(I16:M16) -> 191660
B17: Vehicles | I17: 58592 | J17: 2939 | K17: -2659 | M17: 613 | N17: =SUM(I17:M17) -> 59485
B18: Machinery & equipment | I18: 249860 | J18: 2196 | K18: -988 | L18: 6697 | M18: 87 | N18: =SUM(I18:M18) -> 257852
B19: Vehicles | I19: 2995478 | L19: 94811 | N19: =SUM(I19:M19) -> 3090289
C20: Total capital assets being depreciated | I20: =SUM(I15:I19) -> 3872480 | J20: =SUM(J15:J19) -> 5135 | K20: =SUM(K15:K19) -> -3647 | L20: =SUM(L15:L19) -> 109728 | M20: =SUM(M15:M19) -> 700 | N20: =SUM(N15:N19) -> 3984396
A22: Less accumulated depreciation for:
B23: Buildings | I23: 169192 | J23: 11214 | N23: =SUM(I23:M23) -> 180406 | O23: =SUM(N23,N15) -> 565516
B24: Improvements other than buildings | I24: 76590 | J24: 7734 | N24: =SUM(I24:M24) -> 84324 | O24: =SUM(N24,N16) -> 275984
B25: Vehicles | I25: 44253 | J25: 5674 | K25: -2444 | M25: 601 | N25: =SUM(I25:M25) -> 48084 | O25: =SUM(N25,N17) -> 107569
B26: Machinery & equipment | I26: 204750 | J26: 3811 | K26: -903 | M26: 39 | N26: =SUM(I26:M26) -> 207697 | O26: =N18+N26 -> 465549
B27: Infrastructure | I27: 2446874 | J27: 24250 | N27: =SUM(I27:M27) -> 2471124 | O27: =N19+N27 -> 5561413
C28: Total accumulated depreciation | I28: =SUM(I23:I27) -> 2941659 | J28: =SUM(J23:J27) -> 52683 | K28: =SUM(K23:K27) -> -3347 | L28: =SUM(L23:L27) -> 0 | M28: =SUM(M23:M27) -> 640 | N28: =SUM(N23:N27) -> 2991635
B30: Total capital assets being depreciated, net | I30: =SUM(I20-I28) -> 930821 | J30: =SUM(J20-J28) -> -47548 | K30: =SUM(K20-K28) -> -300 | L30: =SUM(L20-L28) -> 109728 | M30: =SUM(M20-M28) -> 60 | N30: =SUM(N20-N28) -> 992761
B32: Governmental activities capital assets, net | I32: =I12+I30 -> 1174002 | J32: =J12+J30 -> 66203 | K32: =K12+K30 -> -300 | L32: =L12+L30 -> 0 | M32: =M12+M30 -> -13442 | N32: =N12+N30 -> 1226463 | O32: =SUM(O23:O27,O10:O11) -> 7209733
I35: Beginning Balance | J35: Increases | K35: Decreases | L35: Completed Construction | M35: Transfers (To) From Other Funds | N35: Ending Balance
A37: Business-type Activities:
A39: Capital assets not being depreciated:
B40: Land and Land improvements | I40: 13591 | N40: =SUM(I40:M40) -> 13591 | O40: =SUM(N40) -> 13591
B41: Construction in progress | I41: 3112 | J41: 7900 | L41: -5256 | N41: =SUM(I41:M41) -> 5756 | O41: =SUM(N41) -> 5756
C42: Total capital assets being depreciated | I42: =SUM(I40:I41) -> 16703 | J42: =SUM(J40:J41) -> 7900 | K42: =SUM(K40:K41) -> 0 | L42: =SUM(L40:L41) -> -5256 | M42: =SUM(M40:M41) -> 0 | N42: =SUM(N40:N41) -> 19347
A44: Capital assets being depreciated:
B45: Buildings | I45: 23293 | N45: =SUM(I45:M45) -> 23293
B46: Collection and distribution systems | I46: 628662 | L46: 5068 | M46: 13231 | N46: =SUM(I46:M46) -> 646961
B47: Plants | I47: 260269 | N47: =SUM(I47:M47) -> 260269
B48: Improvements other than buildings | I48: 15756 | J48: 272 | L48: 188 | N48: =SUM(I48:M48) -> 16216
B49: Machinery & equipment | I49: 8779 | J49: 552 | K49: -74 | M49: -87 | N49: =SUM(I49:M49) -> 9170
B50: Vehicles | I50: 11646 | M50: 39 | N50: =SUM(I50:M50) -> 11685
C51: Total capital assets being depreciated | I51: =SUM(I45:I50) -> 948405 | J51: =SUM(J45:J50) -> 824 | K51: =SUM(K45:K50) -> -74 | L51: =SUM(L45:L50) -> 5256 | M51: =SUM(M45:M50) -> 13183 | N51: =SUM(N45:N50) -> 967594
A53: Less accumulated depreciation for:
B54: Buildings | I54: 9992 | J54: 434 | N54: =SUM(I54:M54) -> 10426 | O54: =SUM(N45-N54) -> 12867
B55: Collection and distribution systems | I55: 271863 | J55: 14453 | K55: 0 | N55: =SUM(I55:M55) -> 286316 | O55: =SUM(N46-N55) -> 360645
B56: Plant | I56: 115430 | J56: 5573 | N56: =SUM(I56:M56) -> 121003 | O56: =SUM(N47-N56) -> 139266
B57: Improvements other than buildings | I57: 4834 | J57: 742 | N57: =SUM(I57:M57) -> 5576 | O57: =SUM(N48-N57) -> 10640
B58: Machiney & equipment | I58: 8016 | J58: 278 | K58: -60 | M58: -87 | N58: =SUM(I58:M58) -> 8147 | O58: =SUM(N49-N58) -> 1023
B59: Vehicles | I59: 8316 | J59: 1000 | M59: -601 | N59: =SUM(I59:M59) -> 8715 | O59: =SUM(N50-N59) -> 2970
C60: Total accumulated depreciation | I60: =SUM(I54:I59) -> 418451 | J60: =SUM(J54:J59) -> 22480 | K60: =SUM(K54:K59) -> -60 | L60: =SUM(L54:L59) -> 0 | M60: =SUM(M54:M59) -> -688 | N60: =SUM(N54:N59) -> 440183
C62: Total capital assets bring depreciated, net | I62: =SUM(I51-I60) -> 529954 | J62: =SUM(J51-J60) -> -21656 | K62: =SUM(K51-K60) -> -14 | L62: =SUM(L51-L60) -> 5256 | M62: =SUM(M51-M60) -> 13871 | N62: =SUM(N51-N60) -> 527411
B63: Business-type activities capital assets, net | I63: =SUM(I62+I42) -> 546657 | J63: =SUM(J62+J42) -> -13756 | K63: =SUM(K62+K42) -> -14 | L63: =SUM(L62+L42) -> 0 | M63: =SUM(M62+M42) -> 13871 | N63: =SUM(N62+N42) -> 546758 | O63: =SUM(O40:O59) -> 546758

Sheet Lafayette
D1: Lafayette PARISH POLICE JURY
D2: Capital Assets
D3: For the Year Ended December 31, 2014
I5: Beginning Balance | J5: Increases | K5: Deletions | L5: Ending Balance | M5: Cross Sectional
A8: Governmental activities:
A9: Capital assets not being depreciated:
B10: Land | I10: 38517490 | J10: 1782986 | K10: -5000 | L10: =SUM(I10:K10) -> 40295476 | M10: =SUM(L10) -> 40295476
B11: Construction in progress | I11: 31680505 | J11: 20908184 | K11: -22974713 | L11: =SUM(I11:K11) -> 29613976 | M11: =SUM(L11) -> 29613976
C12: Total assets not being depreciated | I12: =SUM(I10:I11) -> 70197995 | J12: =SUM(J10:J11) -> 22691170 | K12: =SUM(K10:K11) -> -22979713 | L12: =SUM(L10:L11) -> 69909452
A14: Other capital assets:
B15: Land improvements | I15: 6651519 | J15: 530490 | L15: =SUM(I15:K15) -> 7182009
B16: Buildings and improvements | I16: 174213423 | J16: 13773117 | K16: -376693 | L16: =SUM(I16:K16) -> 187609847
B17: Vehicles | I17: 52854330 | J17: 3184177 | K17: -1956743 | L17: =SUM(I17:K17) -> 54081764
B18: Movables | I18: 35200471 | J18: 3612969 | K18: -2423396 | L18: =SUM(I18:K18) -> 36390044
B19: Infrastructure | I19: 658827392 | J19: 12172103 | L19: =SUM(I19:K19) -> 670999495
C20: Total capital assets being depreciated | I20: =SUM(I12:I19) -> 997945130 | J20: =SUM(J12:J19) -> 55964026 | K20: =SUM(K12:K19) -> -27736545 | L20: =SUM(L12:L19) -> 1026172611
A22: Less accumulated depreciation for:
B23: Land improvements | I23: 787655 | J23: 271568 | L23: =SUM(I23:K23) -> 1059223 | M23: =SUM(L15-L23) -> 6122786
B24: Buildings and improvements | I24: 81130589 | J24: 3736188 | K24: -102266 | L24: =SUM(I24:K24) -> 84764511 | M24: =SUM(L16-L24) -> 102845336
B25: Vehicles | I25: 32474188 | J25: 3637055 | K25: -1616012 | L25: =SUM(I25:K25) -> 34495231 | M25: =SUM(L17-L25) -> 19586533
B26: Moveables | I26: 23411200 | J26: 2680669 | K26: -2336280 | L26: =SUM(I26:K26) -> 23755589 | M26: =SUM(L18-L26) -> 12634455
B27: Infrastructure | I27: 272701745 | J27: 17269060 | L27: =SUM(I27:K27) -> 289970805 | M27: =SUM(L19-L27) -> 381028690
C28: Total accumulated depreciation | I28: =SUM(I23:I27) -> 410505377 | J28: =SUM(J23:J27) -> 27594540 | K28: =SUM(K23:K27) -> -4054558 | L28: =SUM(L23:L27) -> 434045359
B30: Governmental activities capital assets, net | I30: =SUM(I20-I28) -> 587439753 | J30: =SUM(J20-J28) -> 28369486 | K30: =SUM(K20-K28) -> -23681987 | L30: =SUM(L20-L28) -> 592127252 | M30: =SUM(M10:M27) -> 592127252
I34: Beginning Balance | J34: Increases | K34: Decreases | L34: Ending Balance
A36: Business-type Activities:
A38: Capital assets not being depreciated:
B39: Land | I39: 21168445 | J39: 1094758 | L39: =SUM(I39:K39) -> 22263203 | M39: =SUM(L39) -> 22263203
B40: Construction in progress | I40: 44390674 | J40: 76911040 | K40: -44847912 | L40: =SUM(I40:K40) -> 76453802 | M40: =SUM(L40) -> 76453802
C41: Total capital assets being depreciated | I41: =SUM(I39:I40) -> 65559119 | J41: =SUM(J39:J40) -> 78005798 | K41: =SUM(K39:K40) -> -44847912 | L41: =SUM(L39:L40) -> 98717005
A43: Capital assets being depreciated:
B44: Buildings and improvements | I44: 3159649 | L44: =SUM(I44:K44) -> 3159649
B45: Electric plant | I45: 705946776 | J45: 27960423 | K45: -1692384 | L45: =SUM(I45:K45) -> 732214815
B46: Water plant | I46: 148156908 | J46: 3719264 | K46: -286509 | L46: =SUM(I46:K46) -> 151589663
B47: Sewer plant | I47: 218862854 | J47: 5622077 | K47: -500013 | L47: =SUM(I47:K47) -> 223984918
B48: Fiber optics | I48: 126805747 | J48: 6773905 | K48: -177038 | L48: =SUM(I48:K48) -> 133402614
B49: Equipment | I49: 18535569 | J49: 113631 | K49: -8772 | L49: =SUM(I49:K49) -> 18640428
C50: Total capital assets being depreciated | I50: =SUM(I41:I49) -> 1287026622 | J50: =SUM(J41:J49) -> 122195098 | K50: =SUM(K41:K49) -> -47512628 | L50: =SUM(L41:L49) -> 1361709092
A52: Less accumulated depreciation for:
B53: Buildings and improvements | I53: 2931532 | J53: 8405 | L53: =SUM(I53:K53) -> 2939937 | M53: =SUM(L44-L53) -> 219712
B54: Electric plant | I54: 390136012 | J54: 16499758 | K54: -1372873 | L54: =SUM(I54:K54) -> 405262897 | M54: =SUM(L45-L54) -> 326951918
B55: Water plant | I55: 54334042 | J55: 3947778 | K55: -248182 | L55: =SUM(I55:K55) -> 58033638 | M55: =SUM(L46-L55) -> 93556025
B56: Sewer plant | I56: 65545535 | J56: 4714518 | K56: -516957 | L56: =SUM(I56:K56) -> 69743096 | M56: =SUM(L47-L56) -> 154241822
B57: Fiber optics | I57: 41123639 | J57: 10452328 | K57: -53788 | L57: =SUM(I57:K57) -> 51522179 | M57: =SUM(L48-L57) -> 81880435
B58: Equipment | I58: 4091376 | J58: 619550 | K58: -7077 | L58: =SUM(I58:K58) -> 4703849 | M58: =SUM(L49-L58) -> 13936579
C59: Total accumulated depreciation | I59: =SUM(I53:I58) -> 558162136 | J59: =SUM(J53:J58) -> 36242337 | K59: =SUM(K53:K58) -> -2198877 | L59: =SUM(L53:L58) -> 592205596
C61: Business-type activities capital assets, net | I61: =SUM(I50-I59) -> 728864486 | J61: =SUM(J50-J59) -> 85952761 | K61: =SUM(K50-K59) -> -45313751 | L61: =SUM(L50-L59) -> 769503496 | M61: =SUM(M39:M58) -> 769503496

Sheet Lafourche
D1: Laforche PARISH POLICE JURY
D2: Capital Assets
D3: For the Year Ended December 31, 2014
I5: Beginning Balance | J5: Increases | K5: Deletions & Adjustments | L5: Ending Balance | M5: Cross Sectional
A8: Governmental activities:
A9: Capital assets not being depreciated:
B10: Land | I10: 1315603 | K10: -18327 | L10: =SUM(I10:K10) -> 1297276 | M10: =SUM(L10) -> 1297276
B11: Construction in progress | I11: 23784976 | J11: 20685900 | K11: -5955299 | L11: =SUM(I11:K11) -> 38515577 | M11: =SUM(L11) -> 38515577
C12: Total assets not being depreciated | I12: =SUM(I10:I11) -> 25100579 | J12: =SUM(J10:J11) -> 20685900 | K12: =SUM(K10:K11) -> -5973626 | L12: =SUM(L10:L11) -> 39812853
A14: Other capital assets:
B15: Buildings | I15: 31297591 | J15: 221815 | K15: -1542838 | L15: =SUM(I15:K15) -> 29976568
B16: Infrastructure | I16: 107706220 | J16: 1339825 | K16: 7301 | L16: =SUM(I16:K16) -> 109053346
B17: Drainage & Other Improvements | I17: 2620893 | J17: 250985 | L17: =SUM(I17:K17) -> 2871878
B18: Pumps & Sewage | I18: 37298577 | J18: 3863445 | K18: -11191 | L18: =SUM(I18:K18) -> 41150831
B19: Equipment & Furniture | I19: 7510173 | J19: 476481 | K19: -128406 | L19: =SUM(I19:K19) -> 7858248
B20: Vehicles & Equipment | I20: 9807167 | J20: 1026194 | K20: -103847 | L20: =SUM(I20:K20) -> 10729514
C21: Total capital assets being depreciated | I21: =SUM(I15:I20) -> 196240621 | J21: =SUM(J15:J20) -> 7178745 | K21: =SUM(K15:K20) -> -1778981 | L21: =SUM(L15:L20) -> 201640385
D23: Total Cost of Capital Assets | I23: =SUM(I21+I12) -> 221341200 | J23: =SUM(J21+J12) -> 27864645 | K23: =SUM(K21+K12) -> -7752607 | L23: =SUM(L21+L12) -> 241453238
A25: Less accumulated depreciation for:
B26: Buildings | I26: -6868054 | J26: -743074 | K26: 63120 | L26: =SUM(I26:K26) -> -7548008 | M26: =SUM(L15+L26) -> 22428560
B27: Infrastructure | I27: -89548006 | J27: -4157823 | K27: 3777 | L27: =SUM(I27:K27) -> -93702052 | M27: =SUM(L16+L27) -> 15351294
B28: Drainage & Other Improvements | I28: -1351227 | J28: -196423 | L28: =SUM(I28:K28) -> -1547650 | M28: =SUM(L17+L28) -> 1324228
B29: Pumps & Sewage | I29: -29861782 | J29: -667226 | K29: 3872 | L29: =SUM(I29:K29) -> -30525136 | M29: =SUM(L18+L29) -> 10625695
B30: Equipment & Furniture | I30: -4184846 | J30: -350955 | K30: -244925 | L30: =SUM(I30:K30) -> -4780726 | M30: =SUM(L19+L30) -> 3077522
B31: Vehicles & Equipment | I31: -6474800 | J31: -580091 | K31: -82279 | L31: =SUM(I31:K31) -> -7137170 | M31: =SUM(L20+L31) -> 3592344
C32: Total accumulated depreciation | I32: =SUM(I26:I31) -> -138288715 | J32: =SUM(J26:J31) -> -6695592 | K32: =SUM(K26:K31) -> -256435 | L32: =SUM(L26:L31) -> -145240742
C34: Net Depreciable Capital Assets | I34: =SUM(I21+I32) -> 57951906 | L34: =SUM(L21+L32) -> 56399643
C36: Net Capital Assets | I36: 83052485 | L36: =SUM(L23+L32) -> 96212496 | M36: =SUM(M10:M31) -> 96212496

Sheet Laforche
D1: Laforche PARISH POLICE JURY
D2: Capital Assets
D3: For the Year Ended December 31, 2014
I5: Beginning Balance | J5: Increases | K5: Deletions & Adjustments | L5: Ending Balance | M5: Cross Sectional
A6: Governmental activities:
A7: Capital assets not being depreciated:
B8: Land | I8: 1315603 | K8: -18327 | L8: =SUM(I8:K8) -> 1297276 | M8: =SUM(L8) -> 1297276
B9: Construction in progress | I9: 23784976 | J9: 20685900 | K9: -5955299 | L9: =SUM(I9:K9) -> 38515577 | M9: =SUM(L9) -> 38515577
C10: Total assets not being depreciated | I10: =SUM(I8:I9) -> 25100579 | J10: =SUM(J8:J9) -> 20685900 | K10: =SUM(K8:K9) -> -5973626 | L10: =SUM(L8:L9) -> 39812853
A12: Other capital assets:
B13: Buildings | I13: 31297591 | J13: 221815 | K13: -1542838 | L13: =SUM(I13:K13) -> 29976568
B14: Infrastructure | I14: 107706220 | J14: 1339825 | K14: 7301 | L14: =SUM(I14:K14) -> 109053346
B15: Drainage & Other Improvements | I15: 2620893 | J15: 250985 | L15: =SUM(I15:K15) -> 2871878
B16: Pumps & Sewage | I16: 37298577 | J16: 3863445 | K16: -11191 | L16: =SUM(I16:K16) -> 41150831
B17: Equipment & Furniture | I17: 7510173 | J17: 476481 | K17: -128406 | L17: =SUM(I17:K17) -> 7858248
B18: Vehicles & Equipment | I18: 9807167 | J18: 1026194 | K18: -103847 | L18: =SUM(I18:K18) -> 10729514
C19: Total capital assets being depreciated | I19: =SUM(I13:I18) -> 196240621 | J19: =SUM(J13:J18) -> 7178745 | K19: =SUM(K13:K18) -> -1778981 | L19: =SUM(L13:L18) -> 201640385
D21: Total Cost of Capital Assets | I21: =SUM(I19+I10) -> 221341200 | J21: =SUM(J19+J10) -> 27864645 | K21: =SUM(K19+K10) -> -7752607 | L21: =SUM(L19+L10) -> 241453238
A23: Less accumulated depreciation for:
B24: Buildings | I24: -6868054 | J24: -743074 | K24: 63120 | L24: =SUM(I24:K24) -> -7548008 | M24: =SUM(L13+L24) -> 22428560
B25: Infrastructure | I25: -89548006 | J25: -4157823 | K25: 3777 | L25: =SUM(I25:K25) -> -93702052 | M25: =SUM(L14+L25) -> 15351294
B26: Drainage & Other Improvements | I26: -1351227 | J26: -196423 | L26: =SUM(I26:K26) -> -1547650 | M26: =SUM(L15+L26) -> 1324228
B27: Pumps & Sewage | I27: -29861782 | J27: -667226 | K27: 3872 | L27: =SUM(I27:K27) -> -30525136 | M27: =SUM(L16+L27) -> 10625695
B28: Equipment & Furniture | I28: -4184846 | J28: -350955 | K28: -244925 | L28: =SUM(I28:K28) -> -4780726 | M28: =SUM(L17+L28) -> 3077522
B29: Vehicles & Equipment | I29: -6474800 | J29: -580091 | K29: -82279 | L29: =SUM(I29:K29) -> -7137170 | M29: =SUM(L18+L29) -> 3592344
C30: Total accumulated depreciation | I30: =SUM(I24:I29) -> -138288715 | J30: =SUM(J24:J29) -> -6695592 | K30: =SUM(K24:K29) -> -256435 | L30: =SUM(L24:L29) -> -145240742
C32: Net Depreciable Capital Assets | I32: =SUM(I19+I30) -> 57951906 | L32: =SUM(L19+L30) -> 56399643
C34: Net Capital Assets | I34: 83052485 | L34: =SUM(L21+L30) -> 96212496 | M34: =SUM(M8:M29) -> 96212496

Sheet LaSalle
D1: LaSalle PARISH POLICE JURY
D2: Capital Assets
D3: For the Year Ended December 31, 2014
I5: Beginning Balance | J5: Additions | K5: Deletions | L5: Ending Balance | M5: Cross Sectional
A6: Police Jury:
A7: Capital assets not being depreciated:
B8: Land | I8: 477208 | L8: =SUM(I8:K8) -> 477208 | M8: =SUM(L8) -> 477208
B9: Construction in progress | J9: 955258 | L9: =SUM(I9:K9) -> 955258 | M9: =SUM(L9) -> 955258
C10: Total assets not being depreciated | I10: =SUM(I8:I9) -> 477208 | J10: =SUM(J8:J9) -> 955258 | K10: =SUM(K8:K9) -> 0 | L10: =SUM(L8:L9) -> 1432466
A12: Other capital assets:
B13: Infrastructure - roads and bridges | I13: 77243445 | J13: 271465 | L13: =SUM(I13:K13) -> 77514910
B14: Buildings and improvements | I14: 2369699 | L14: =SUM(I14:K14) -> 2369699
B15: Office furniture and equipment | I15: 336480 | J15: 451609 | L15: =SUM(I15:K15) -> 788089
B16: Heavy equipment | I16: 2357074 | L16: =SUM(I16:K16) -> 2357074
B17: Other equipment | I17: 96836 | J17: 5945 | L17: =SUM(I17:K17) -> 102781
B18: Vehicles | I18: 297197 | J18: 26684 | L18: =SUM(I18:K18) -> 323881
B19: Books | I19: 0 | J19: 0 | K19: 0 | L19: =SUM(I19:K19) -> 0
C20: Total capital assets being depreciated | I20: =SUM(I13:I19) -> 82700731 | J20: =SUM(J13:J19) -> 755703 | K20: =SUM(K13:K18) -> 0 | L20: =SUM(L13:L19) -> 83456434
B21: Total police jury capital assets | I21: =SUM(I20+I10) -> 83177939 | J21: =SUM(J20+J10) -> 1710961 | K21: =SUM(K20+K10) -> 0 | L21: =SUM(L20+L10) -> 84888900
A23: Library:
A24: Capital assets not being depreciated:
B25: Land | I25: 23810 | L25: =SUM(I25:K25) -> 23810 | M25: =SUM(L25) -> 23810
B26: Construction in progress | L26: =SUM(I26:K26) -> 0
C27: Total assets not being depreciated | I27: =SUM(I25:I26) -> 23810 | J27: =SUM(J25:J26) -> 0 | K27: =SUM(K25:K26) -> 0 | L27: =SUM(L25:L26) -> 23810
B28: Capital assets not being depreciated:
C29: Books | I29: 514238 | J29: 45167 | K29: -42744 | L29: =SUM(I29:K29) -> 516661 | M29: =SUM(L29) -> 516661
C30: Vehicles | I30: 44382 | L30: =SUM(I30:K30) -> 44382 | M30: =SUM(L30) -> 44382
C31: Buildings | I31: 813566 | L31: =SUM(I31:K31) -> 813566 | M31: =SUM(L31) -> 813566
C32: Furniture | I32: 135262 | L32: =SUM(I32:K32) -> 135262 | M32: =SUM(L32) -> 135262
C33: Equipment | I33: 65071 | L33: =SUM(I33:K33) -> 65071 | M33: =SUM(L33) -> 65071
D34: Total library assets being depreciated | I34: =SUM(I29:I33) -> 1572519 | J34: =SUM(J29:J33) -> 45167 | K34: =SUM(K29:K33) -> -42744 | L34: =SUM(L29:L33) -> 1574942
C35: Total library capital assets | I35: =SUM(I34+I27) -> 1596329 | J35: =SUM(J34+J27) -> 45167 | K35: =SUM(K34+K27) -> -42744 | L35: =SUM(L34+L27) -> 1598752
B37: Total capital assets bring depreciated | I37: 84273250 | J37: 800870 | K37: -42744 | L37: 85031376
B38: Total capital assets | I38: =SUM(I21+I35) -> 84774268 | J38: =SUM(J21+J35) -> 1756128 | K38: =SUM(K21+K35) -> -42744 | L38: =SUM(L21+L35) -> 86487652
A40: Less accumulated depreciation for:
B41: Infrastructure - roads and bridges | I41: -74544686 | J41: -147645 | L41: =SUM(I41:K41) -> -74692331 | M41: =SUM(L41+L13) -> 2822579
B42: Buildings and improvements | I42: -1487371 | J42: -68025 | L42: =SUM(I42:K42) -> -1555396 | M42: =SUM(L42+L14) -> 814303
B43: Office furniture and equipment | I43: -139378 | J43: -80102 | L43: =SUM(I43:K43) -> -219480 | M43: =SUM(L43+L15) -> 568609
B44: Heavy equipment | I44: -1940729 | J44: -101680 | L44: =SUM(I44:K44) -> -2042409 | M44: =SUM(L44+L16) -> 314665
B45: Other equipment | I45: -276614 | J45: -21231 | L45: =SUM(I45:K45) -> -297845 | M45: =SUM(L45+L17) -> -195064
B46: Vehicles | I46: -178783 | J46: -47695 | L46: =SUM(I46:K46) -> -226478 | M46: =SUM(L46+L18) -> 97403
B47: Books | I47: -366233 | J47: -34881 | K47: 42744 | L47: =SUM(I47:K47) -> -358370 | M47: =SUM(L47+L19) -> -358370
C48: Total accumulated depreciation | I48: =SUM(I41:I47) -> -78933794 | J48: =SUM(J41:J47) -> -501259 | K48: =SUM(K41:K47) -> 42744 | L48: =SUM(L41:L47) -> -79392309
B50: Total capital assets being depreciated (net) | I50: =SUM(I48+I37) -> 5339456 | J50: =SUM(J48+J37) -> 299611 | K50: =SUM(K48+K37) -> 0 | L50: =SUM(L48+L37) -> 5639067
B52: Total capital assets (net) | I52: =SUM(I48+I38) -> 5840474 | J52: =SUM(J48+J38) -> 1254869 | K52: =SUM(K48+K38) -> 0 | L52: =SUM(L48+L38) -> 7095343 | M52: =SUM(M8:M47) -> 7095343

Sheet Livingston
D1: LIVINGSTON PARISH POLICE JURY
D2: Capital Assets
D3: For the Year Ended December 31, 2014
I5: Balance January 1, 2014 | L5: Balance December 31, 2014 | M5: Cross Sectional
J6: Increases | K6: Decreases
A7: Governmental Activities
A8: Capital Assets Not Being Depreciated
B9: Land | I9: 5844429 | L9: =SUM(I9:K9) -> 5844429 | M9: =SUM(L9) -> 5844429
B10: Construction in progress | I10: 15111097 | J10: 10247963 | K10: -19652271 | L10: =SUM(I10:K10) -> 5706789 | M10: =SUM(L10) -> 5706789
C11: Total Capital assets not being depreciated | I11: =SUM(I9:I10) -> 20955526 | J11: =SUM(J9:J10) -> 10247963 | K11: =SUM(K9:K10) -> -19652271 | L11: =SUM(L9:L10) -> 11551218
A12: Capital Assets Being Depreciated
B13: Buildings | I13: 54813717 | J13: 19655722 | L13: =SUM(I13:K13) -> 74469439
B14: Recreational Facilities | I14: 3758232 | L14: =SUM(I14:K14) -> 3758232
B15: Machinery and Equipment | I15: 6238993 | J15: 859063 | K15: -104284 | L15: =SUM(I15:K15) -> 6993772
B16: Sewer System | I16: 2126234 | L16: =SUM(I16:K16) -> 2126234
B17: Infrastructure | I17: 146362543 | L17: =SUM(I17:K17) -> 146362543
B18: Furniture and Fixtures | I18: 250660 | L18: =SUM(I18:K18) -> 250660
C19: Total Capital Assets Being Depreciated | I19: =SUM(I13:I18) -> 213550379 | J19: =SUM(J13:J18) -> 20514785 | K19: =SUM(K13:K18) -> -104284 | L19: =SUM(L13:L18) -> 233960880
A20: Less accumulated depreciation for:
B21: Buildings | I21: -9383769 | J21: -1474060 | L21: =SUM(I21:K21) -> -10857829 | M21: =SUM(L21,L13) -> 63611610
B22: Recreational Facilities | I22: -306172 | J22: -141749 | L22: =SUM(I22:K22) -> -447921 | M22: =SUM(L22,L14) -> 3310311
B23: Machinery and Equipment | I23: -4700048 | J23: -557567 | K23: 104284 | L23: =SUM(I23:K23) -> -5153331 | M23: =SUM(L23,L15) -> 1840441
B24: Sewer System | I24: -9181136 | J24: -9150261 | L24: =SUM(I24:K24) -> -18331397 | M24: =SUM(L24,L16) -> -16205163
B25: Infrastructure | I25: -66993722 | J25: -28940 | L25: =SUM(I25:K25) -> -67022662 | M25: =SUM(L25,L17) -> 79339881
B26: Furniture and Fixtures | I26: -268530 | J26: -93956 | L26: =SUM(I26:K26) -> -362486 | M26: =SUM(L26,L18) -> -111826
C27: Total accumulated depreciation | I27: =SUM(I21:I26) -> -90833377 | J27: =SUM(J21:J26) -> -11446533 | K27: =SUM(K21:K26) -> 104284 | L27: =SUM(L21:L26) -> -102175626
C28: Total Capital Assets Being Depreciated, Net | I28: =SUM(I27+I19) -> 122717002 | J28: =SUM(J27+J19) -> 9068252 | K28: =SUM(K27+K19) -> 0 | L28: =SUM(L27+L19) -> 131785254
C29: Capital Assets, net | I29: =I11+I28 -> 143672528 | J29: =J11+J28 -> 19316215 | K29: =K11+K28 -> -19652271 | L29: =L11+L28 -> 143336472 | M29: =SUM(M21:M26,M9:M10) -> 143336472
A32: Business-Type activities
A33: Capital Assets Not Being Depreciated
B34: Land | I34: 13243 | L34: =SUM(I34:K34) -> 13243 | M34: =SUM(L34) -> 13243
B35: Construction in progress | I35: 177483 | K35: -126364 | L35: 51119 | M35: =SUM(L35) -> 51119
C36: Total Capital assets not being depreciated | I36: =SUM(I34:I35) -> 190726 | J36: =SUM(J34:J35) -> 0 | K36: =SUM(K34:K35) -> -126364 | L36: =SUM(L34:L35) -> 64362
A37: Capital Assets Being Depreciated
B38: Utility system | I38: 9945658 | L38: =SUM(I38:K38) -> 9945658
C39: Total Capital Assets being Depreciated | I39: =SUM(I38:I38) -> 9945658 | J39: =SUM(J38:J38) -> 0 | K39: =SUM(K38:K38) -> 0 | L39: =SUM(L38:L38) -> 9945658
A40: Less accumulated depreciation for:
B41: Utility System | I41: -1838904 | J41: -295114 | L41: =SUM(I41:K41) -> -2134018 | M41: =SUM(L41,L38) -> 7811640
C42: Total accumulated depreciation | I42: =SUM(I41:I41) -> -1838904 | J42: =SUM(J41:J41) -> -295114 | K42: =SUM(K41:K41) -> 0 | L42: =SUM(L41:L41) -> -2134018
C43: Total depreciable capital assets, net | I43: =SUM(I39+I42) -> 8106754 | J43: =SUM(J39+J42) -> -295114 | K43: =SUM(K39+K42) -> 0 | L43: =SUM(L39+L42) -> 7811640
C44: Capital Assets, net | I44: =I36+I43 -> 8297480 | J44: =J36+J43 -> -295114 | K44: =K36+K43 -> -126364 | L44: =L36+L43 -> 7876002 | M44: =SUM(M41,M34:M35) -> 7876002

Sheet Madison
D1: MADISON PARISH POLICE JURY
D2: Capital Assets
D3: For the Year Ended December 31, 2014
I5: Balance Beginning | L5: Balance Ending | M5: Cross Sectional
J6: Additions | K6: Deletions
A7: Governmental Activities
A8: Not subject to depreciation
B9: Land | I9: 188750 | L9: =SUM(I9:K9) -> 188750 | M9: =SUM(L9) -> 188750
B10: Quebec road | I10: 3771405 | L10: =SUM(I10:K10) -> 3771405 | M10: =L10 -> 3771405
A11: Depreciable capital assets
B12: Health unit | I12: 1509539 | J12: 179096 | L12: =SUM(I12:K12) -> 1688635 | M12: =L12 -> 1688635
B13: Buildings and improvements | I13: 5989425 | J13: 68854 | K13: -53000 | L13: =SUM(I13:K13) -> 6005279
B14: Furniture and equipment | I14: 3385565 | J14: 92637 | L14: =SUM(I14:K14) -> 3478202
B15: Books and periodicals | I15: 486150 | J15: 45803 | K15: -14854 | L15: =SUM(I15:K15) -> 517099
C16: Total | I16: =SUM(I9:I15) -> 15330834 | J16: =SUM(J9:J15) -> 386390 | K16: =SUM(K9:K15) -> -67854 | L16: =SUM(L9:L15) -> 15649370
A17: Less accumulated depreciation
B18: Buildings and improvements | I18: 4417219 | J18: 142680 | L18: =SUM(I18:K18) -> 4559899 | M18: =L13-L18 -> 1445380
B19: Furniture and equipment | I19: 2359532 | J19: 229228 | L19: =SUM(I19:K19) -> 2588760 | M19: =L14-L19 -> 889442
B20: Books and periodicals | I20: 376716 | J20: 51710 | K20: -14854 | L20: =SUM(I20:K20) -> 413572 | M20: =L15-L20 -> 103527
C21: Total | I21: =SUM(I18:I20) -> 7153467 | J21: =SUM(J18:J20) -> 423618 | K21: =SUM(K18:K20) -> -14854 | L21: =SUM(L18:L20) -> 7562231
B22: Governmental activities capital assets, net | I22: =I16-I21 -> 8177367 | J22: =J16-J21 -> -37228 | K22: =K16-K21 -> -53000 | L22: =L16-L21 -> 8087139 | M22: =SUM(M9:M20) -> 8087139

Sheet Morehouse
D1: MOREHOUSE PARISH POLICE JURY
D2: Capital Assets
D3: For the Year Ended December 31, 2014
I5: Balance January 1, 2014 | J5: Additions | K5: Deletions | L5: Prior Period Adjustment | M5: Balance December, 31, 2014 | N5: Cross sectional
A7: Capital assets, not being depreciated
B8: Land | I8: 778626 | M8: =SUM(I8:L8) -> 778626 | N8: =M8 -> 778626
A9: Capital assets being depreciated
B10: Buildings and improvements | I10: 16600626 | M10: =SUM(I10:L10) -> 16600626
B11: Machinery and equipment | I11: 3087145 | J11: 776290 | K11: -601819 | M11: =SUM(I11:L11) -> 3261616
B12: Total capital assets, being depreciated | I12: =SUM(I10:I11) -> 19687771 | J12: =SUM(J10:J11) -> 776290 | K12: =SUM(K10:K11) -> -601819 | L12: =SUM(L10:L11) -> 0 | M12: =SUM(M10:M11) -> 19862242
A13: Less accumulated depreciation for:
B14: Buildings and improvements | I14: 4614099 | J14: 411646 | M14: =SUM(I14:L14) -> 5025745 | N14: =M10-M14 -> 11574881
B15: Machinery and equipment | I15: 2207877 | J15: 274728 | K15: -272249 | L15: 10350 | M15: =SUM(I15:L15) -> 2220706 | N15: =M11-M15 -> 1040910
B16: Total accumulated depreciation | I16: 6821976 | J16: 686374 | K16: =SUM(K14:K15) -> -272249 | L16: 10350 | M16: =SUM(I16:L16) -> 7246451
D18: Total capital assets being depreciated, net | I18: =SUM(I12-I16) -> 12865795 | J18: =SUM(J12-J16) -> 89916 | K18: =SUM(K12-K16) -> -329570 | L18: =SUM(L12-L16) -> -10350 | M18: =SUM(M12-M16) -> 12615791
D20: Total Capital Assets | I20: =SUM(I8+I18) -> 13644421 | J20: =SUM(J8+J18) -> 89916 | K20: =SUM(K8+K18) -> -329570 | L20: =SUM(L8+L18) -> -10350 | M20: =SUM(M8+M18) -> 13394417 | N20: =SUM(N8+N14+N15) -> 13394417

Sheet Natchitoches
D1: NATCHITOCHES PARISH POLICE JURY
D2: Capital Assets
D3: For the Year Ended December 31, 2014
I5: Beginning Balance | L5: Ending Balance | M5: Cross Sectional
J6: Increases | K6: Decreases
A7: Governmental Activities
A8: General Fund:
A9: Capital assets; not depreciated
B10: Land | I10: 5633750 | J10: 25000 | L10: =SUM(I10:K10) -> 5658750 | M10: =L10 -> 5658750
A11: Capital assets; depreciated
B12: Building | I12: 5323057 | J12: 364820 | L12: =SUM(I12:K12) -> 5687877
B13: Machinery & Equipment | I13: 1993825 | J13: 379986 | K13: -8027 | L13: =SUM(I13:K13) -> 2365784
B14: Vehicles | I14: 5239934 | J14: 251871 | K14: -43664 | L14: =SUM(I14:K14) -> 5448141
B15: Other Assets | I15: 848117 | J15: 42348 | L15: =SUM(I15:K15) -> 890465
B16: Streets | I16: 92561315 | L16: =SUM(I16:K16) -> 92561315
B17: Other Infrastructure | I17: 6148994 | J17: 494122 | L17: =SUM(I17:K17) -> 6643116
C18: Total assets | I18: =SUM(I10:I17) -> 117748992 | J18: =SUM(J10:J17) -> 1558147 | K18: =SUM(K10:K17) -> -51691 | L18: =SUM(L10:L17) -> 119255448
A20: Accumulated depreciation:
B21: Building | I21: 2124583 | J21: 129785 | L21: =SUM(I21:K21) -> 2254368 | M21: =L12-L21 -> 3433509
B22: Machinery & Equipment | I22: 1456247 | J22: 169575 | K22: -8027 | L22: =SUM(I22:K22) -> 1617795 | M22: =L13-L22 -> 747989
B23: Vehicles | I23: 3328795 | J23: 332525 | K23: -43664 | L23: =SUM(I23:K23) -> 3617656 | M23: =L14-L23 -> 1830485
B24: Other Assets | I24: 353713 | J24: 62210 | L24: =SUM(I24:K24) -> 415923 | M24: =L15-L24 -> 474542
B25: Streets | I25: 85678613 | J25: 522680 | L25: =SUM(I25:K25) -> 86201293 | M25: =L16-L25 -> 6360022
B26: Other Infrastructure | I26: 4768409 | J26: 133602 | L26: =SUM(I26:K26) -> 4902011 | M26: =L17-L26 -> 1741105
C27: Total accumulated depreciation | I27: =SUM(I21:I26) -> 97710360 | J27: =SUM(J21:J26) -> 1350377 | K27: =SUM(K21:K25) -> -51691 | L27: =SUM(L21:L26) -> 99009046
A29: Airport Fund
A30: Capital assets; not depreciated-
B31: Land | I31: 335500 | L31: =SUM(I31:K31) -> 335500 | M31: =L31 -> 335500
A32: Capital assets; depreciated-
B33: Buildings | I33: 1490367 | L33: =SUM(I33:K33) -> 1490367
B34: Other Infrastructure | I34: 3456278 | L34: =SUM(I34:K34) -> 3456278
B35: Machinery & Equiptment | I35: 157024 | J35: 10500 | L35: =SUM(I35:K35) -> 167524
B36: Furniture & Fixtures | I36: 15103 | L36: =SUM(I36:K36) -> 15103
B37: Vehicles | I37: 45590 | L37: =SUM(I37:K37) -> 45590
C38: Total assets | I38: =SUM(I31:I37) -> 5499862 | J38: =SUM(J31:J36) -> 10500 | K38: =SUM(K31:K36) -> 0 | L38: =SUM(L31:L37) -> 5510362
A40: Accumulated depreciation:
B41: Buildings | I41: 337247 | J41: 37259 | L41: =SUM(I41:K41) -> 374506 | M41: =SUM(L33-L41) -> 1115861
B42: Other Infrastructure | I42: 921087 | J42: 93126 | L42: =SUM(I42:K42) -> 1014213 | M42: =SUM(L34-L42) -> 2442065
B43: Machinery & Equipment | I43: 108190 | J43: 20495 | L43: =SUM(I43:K43) -> 128685 | M43: =SUM(L35-L43) -> 38839
B44: Furniture & Fixtures | I44: 10070 | J44: 3021 | L44: =SUM(I44:K44) -> 13091 | M44: =SUM(L36-L44) -> 2012
B45: Vehicles | I45: 25239 | J45: 4608 | L45: =SUM(I45:K45) -> 29847 | M45: =SUM(L37-L45) -> 15743
C46: Total accumulated depreciation | I46: =SUM(I41:I45) -> 1401833 | J46: =SUM(J41:J45) -> 158509 | K46: =SUM(K41:K45) -> 0 | L46: =SUM(L41:L45) -> 1560342
A48: Convention Center Fund-
A49: Capital assets; not depreciated-
B50: Land | I50: 881623 | L50: =SUM(I50:K50) -> 881623 | M50: =L50 -> 881623
A51: Capital Assets; depreciated
B52: Buildings | I52: 9477819 | L52: =SUM(I52:K52) -> 9477819
B53: Vehicles | I53: 22935 | L53: =SUM(I53:K53) -> 22935
B54: Machinery & Equipment | I54: 209864 | L54: =SUM(I54:K54) -> 209864
B55: Furniture & Fixtures | L55: =SUM(I55:K55) -> 0
C56: Total assets | I56: =SUM(I50:I55) -> 10592241 | J56: =SUM(J50:J55) -> 0 | K56: =SUM(K50:K55) -> 0 | L56: =SUM(L50:L55) -> 10592241
A58: Accumulated depreciation:
B59: Buildings | I59: 1381370 | J59: 261320 | L59: =SUM(I59:K59) -> 1642690 | M59: =SUM(L52-L59) -> 7835129
B60: Vehicles | I60: 22935 | L60: =SUM(I60:K60) -> 22935 | M60: =SUM(L53-L60) -> 0
B61: Machinery & Equipment | I61: 194727 | J61: 4485 | L61: =SUM(I61:K61) -> 199212 | M61: =SUM(L54-L61) -> 10652
B62: Furniture & Fixtures | L62: =SUM(I62:K62) -> 0 | M62: =SUM(L55-L62) -> 0
C63: Total accumulated depreciation | I63: =SUM(I59:I62) -> 1599032 | J63: =SUM(J59:J62) -> 265805 | K63: =SUM(K59:K62) -> 0 | L63: =SUM(L59:L62) -> 1864837
A65: Sabine Bank/Industrial Park/Pilgrim's-
A66: Capital assets; not depreciated:
B67: Land | I67: 757989 | L67: =SUM(I67:K67) -> 757989 | M67: =L67 -> 757989
A68: Capital Assets; depreciated
B69: Other Infrastructure | I69: 1091762 | L69: =SUM(I69:K69) -> 1091762
C70: Total assets | I70: =SUM(I67:I69) -> 1849751 | J70: =SUM(J67:J69) -> 0 | K70: =SUM(K67:K69) -> 0 | L70: =SUM(L67:L69) -> 1849751
A72: Accumulated depreciation:
B73: Other infrastructure | I73: 113764 | J73: 54588 | L73: =SUM(I73:K73) -> 168352 | M73: =SUM(L69-L73) -> 923410
C74: Total accumulated depreciation | I74: =SUM(I73) -> 113764 | J74: =SUM(J73) -> 54588 | K74: =SUM(K73) -> 0 | L74: =SUM(L73) -> 168352
B75: Total governmental activites | I75: =SUM(I74+I70+I63+I56+I46+I38+I27+I18) -> 236515835 | J75: =SUM(J74+J70+J63+J56+J46+J38+J27+J18) -> 3397926 | K75: =SUM(K74+K70+K63+K56+K46+K38+K27+K18) -> -103382 | L75: =SUM(L74+L63+L46+L27) -> 102602577
A78: Rehab Water Treatment Plant- Constructure in Progress | I78: 4370769 | J78: 787566 | K78: -5158335 | L78: =SUM(I78:K78) -> 0 | M78: =L78 -> 0
L79: =SUM(I79:K79) -> 0 | M79: =L79 -> 0
A80: Central Fire Station Bay Renovation-Construction in Progress | I80: 91278 | J80: 48116 | K80: -139394 | L80: =SUM(I80:K80) -> 0 | M80: =L80 -> 0
L81: =SUM(I81:K81) -> 0 | M81: =L81 -> 0
A82: Airport Taxiway & Apron- Construction in Progress | I82: 126499 | J82: 1354346 | L82: =SUM(I82:K82) -> 1480845 | M82: =L82 -> 1480845
L83: =SUM(I83:K83) -> 0 | M83: =L83 -> 0
A84: Hotel Land Development- Construction in Progress | I84: 494122 | K84: -494122 | L84: =SUM(I84:K84) -> 0 | M84: =L84 -> 0
L85: =SUM(I85:K85) -> 0 | M85: =L85 -> 0
A86: Old Public Works Rehab-Construction in Progress | J86: 23248 | L86: =SUM(I86:K86) -> 23248 | M86: =L86 -> 23248
L87: =SUM(I87:K87) -> 0 | M87: =L87 -> 0
A88: Sampite Park Rehab- Construction in Progress | J88: 84117 | L88: =SUM(I88:K88) -> 84117 | M88: =L88 -> 84117
L89: =SUM(I89:K89) -> 0 | M89: =L89 -> 0
A90: Tennis Courts- Construction in Progress | J90: 99993 | L90: =SUM(I90:K90) -> 99993 | M90: =L90 -> 99993
C92: Total Assets- Governmental Funds | I92: =SUM(I90+I88+I86+I82+I80+I78+I70+I56+I84+I38+I18) -> 140773514 | J92: =SUM(J90+J88+J86+J82+J80+J78+J70+J56+J84+J38+J18) -> 3966033 | K92: =SUM(K90+K88+K86+K82+K80+K78+K70+K56+K84+K38+K18) -> -5843542 | L92: =SUM(L90+L88+L86+L82+L80+L78+L70+L56+L84+L38+L18) -> 138896005
C93: Total Accumulated Depn. | I93: =SUM(I74+I63+I46+I27) -> 100824989 | J93: =SUM(J74+J63+J46+J27) -> 1829279 | K93: =SUM(K74+K63+K46+K27) -> -51691 | L93: =SUM(L74+L63+L46+L27) -> 102602577
C94: Total Net Assets | I94: =SUM(I92-I93) -> 39948525 | J94: =SUM(J92-J93) -> 2136754 | K94: =SUM(K92-K93) -> -5791851 | L94: =SUM(L92-L93) -> 36293428 | M94: =SUM(M10:M90) -> 36293428

Sheet Orleans
D1: ORLEANS PARISH POLICE JURY
D2: Capital Assets
D3: For the Year Ended December 31, 2014
I5: Balance January 1, 2014 | J5: Additions | K5: Deletions and adjustments | L5: Transfers | M5: Balance December 31, 2014 | N5: Cross Sectional
A7: Nondepreciable capital assets
B8: Land | I8: 94474 | M8: =SUM(I8:L8) -> 94474 | N8: =M8 -> 94474
B9: Construction in progress | I9: 447135 | J9: 134698 | K9: -2829 | L9: -69252 | M9: =SUM(I9:L9) -> 509752 | N9: =M9 -> 509752
C10: Total nondepreciable capital assets | I10: =SUM(I8:I9) -> 541609 | J10: =SUM(J8:J9) -> 134698 | K10: =SUM(K8:K9) -> -2829 | L10: =SUM(L8:L9) -> -69252 | M10: =SUM(M8:M9) -> 604226
A12: Depreciable capital assets
B13: Infrastructure | I13: 2480575 | J13: 15967 | K13: -13650 | M13: =SUM(I13:L13) -> 2482892
B14: Buildings and Improvements | I14: 366189 | J14: 51337 | K14: -1816 | M14: =SUM(I14:L14) -> 415710
B15: Equipment and vehicles | I15: 105073 | J15: 3030 | K15: -4013 | M15: =SUM(I15:L15) -> 104090
B16: Other | I16: 40492 | M16: =SUM(I16:L16) -> 40492
C17: Total depreciable capital assets | I17: =SUM(I13:I16) -> 2992329 | J17: =SUM(J13:J16) -> 70334 | K17: =SUM(K13:K16) -> -19479 | L17: =SUM(L13:L16) -> 0 | M17: =SUM(M13:M16) -> 3043184
A19: Less accumulated depreciation for:
B20: Infrastructure | I20: 1755539 | J20: 56643 | K20: -4245 | M20: =SUM(I20:L20) -> 1807937 | N20: =M13-M20 -> 674955
B21: Buildings and improvements | I21: 112153 | J21: 11809 | K21: -219 | M21: =SUM(I21:L21) -> 123743 | N21: =M14-M21 -> 291967
B22: Equipment and vehicles | I22: 85954 | J22: 6228 | K22: -3669 | M22: =SUM(I22:L22) -> 88513 | N22: =M15-M22 -> 15577
B23: Other | I23: 30182 | J23: 1355 | M23: =SUM(I23:L23) -> 31537 | N23: =M16-M23 -> 8955
C24: Total accumulated depreciation | I24: =SUM(I20:I23) -> 1983828 | J24: =SUM(J20:J23) -> 76035 | K24: =SUM(K20:K23) -> -8133 | L24: =SUM(L20:L23) -> 0 | M24: =SUM(M20:M23) -> 2051730
B25: Total depreciable capital assets, net | I25: =I17-I24 -> 1008501 | J25: =J17-J24 -> -5701 | K25: =K17-K24 -> -11346 | L25: =L17-L24 -> 0 | M25: =M17-M24 -> 991454
B26: Total | I26: =I25+I10 -> 1550110 | J26: =J25+J10 -> 128997 | K26: =K25+K10 -> -14175 | L26: =L25+L10 -> -69252 | M26: =M25+M10 -> 1595680 | N26: =SUM(N8:N23) -> 1595680

Sheet Ouachita
D1: OUACHITA PARISH POLICE JURY
D2: Capital Assets
D3: For the Year Ended December 31, 2014
J5: Governmental Activities
I6: Balance January 1, 2013 | J6: Additions and Transfers | K6: Deletions and Transfers | L6: Balance December 31, 2013 | M6: Cross Sectional
A8: Capital assets, not being depreciated
B9: Land | I9: 8970022 | J9: 3331225 | K9: -56700 | L9: =SUM(I9:K9) -> 12244547 | M9: =SUM(L9) -> 12244547
B10: Construction in progress | I10: 10039664 | J10: 2464320 | K10: -1968788 | L10: =SUM(I10:K10) -> 10535196 | M10: =SUM(L10) -> 10535196
C11: Total Capital assets, not being depreciated | I11: =SUM(I9:I10) -> 19009686 | J11: =SUM(J9:J10) -> 5795545 | K11: =SUM(K9:K10) -> -2025488 | L11: =SUM(L9:L10) -> 22779743
A13: Capital assets being depreciated
B14: Buildings | I14: 58214797 | J14: 891093 | K14: -176916 | L14: =SUM(I14:K14) -> 58928974
B15: Furniture, fixtures and equipment | I15: 31751901 | J15: 4112137 | K15: -2829773 | L15: =SUM(I15:K15) -> 33034265
B16: Books | I16: 4764377 | J16: 524723 | K16: -981434 | L16: =SUM(I16:K16) -> 4307666
B17: Infrastructure:
C18: Roads | I18: 255470233 | J18: 550107 | L18: =SUM(I18:K18) -> 256020340
C19: Bridges | I19: 6541105 | L19: =SUM(I19:K19) -> 6541105
C20: Drainage | I20: 2057129 | J20: 399042 | L20: =SUM(I20:K20) -> 2456171
C21: Total capital assets, being depreciated | I21: =SUM(I14:I20) -> 358799542 | J21: =SUM(J14:J20) -> 6477102 | K21: =SUM(K14:K20) -> -3988123 | L21: =SUM(L14:L20) -> 361288521
A23: Total capital assets before being accumulated depreciated
A25: Less accumulated depreciation
B26: Buildings | I26: 20831668 | J26: 1345271 | K26: -85870 | L26: =SUM(I26:K26) -> 22091069 | M26: =L14-L26 -> 36837905
B27: Furniture, fixtures and equipment | I27: 21907034 | J27: 1997788 | K27: -2681571 | L27: =SUM(I27:K27) -> 21223251 | M27: =L15-L27 -> 11811014
B28: Books | I28: 3240104 | J28: 510122 | K28: -981434 | L28: =SUM(I28:K28) -> 2768792 | M28: =L16-L28 -> 1538874
B29: Infrastructure:
C30: Roads | I30: 147640273 | J30: 6378009 | L30: =SUM(I30:K30) -> 154018282 | M30: =L18-L30 -> 102002058
C31: Bridges | I31: 2616159 | J31: 87215 | L31: =SUM(I31:K31) -> 2703374 | M31: =L19-L31 -> 3837731
C32: Drainage | I32: 214635 | J32: 82285 | L32: =SUM(I32:K32) -> 296920 | M32: =L20-L32 -> 2159251
C33: Total accumulated depreciation | I33: =SUM(I26:I32) -> 196449873 | J33: =SUM(J26:J32) -> 10400690 | K33: =SUM(K26:K32) -> -3748875 | L33: =SUM(L26:L32) -> 203101688
B34: Governmental activities capital assets, net | I34: =I21-I33+I11 -> 181359355 | J34: =J21-J33+J11 -> 1871957 | K34: =K21-K33+K11 -> -2264736 | L34: =L21-L33+L11 -> 180966576 | M34: =SUM(M26:M32,M9:M10) -> 180966576
I36: Beginning capital assets were adjusted by $259,155 to reflect land that had been
I37: previously omitted.

Sheet Plaquemines
D1: PLAQUEMINES PARISH POLICE JURY
D2: Capital Assets
D3: For the Year Ended December 31, 2014
I5: Beginning Balance | J5: Additions | K5: Deductions | L5: Ending Balance | M5: Cross Sectional
A6: Governmental-Type Activities:
A7: Capital assets, not being depreciated:
B8: Land | I8: 13511734 | J8: 11830 | L8: =SUM(I8:K8) -> 13523564 | M8: =L8 -> 13523564
B9: Construction in progress | I9: 99533090 | J9: 54504910 | K9: -19198695 | L9: =SUM(I9:K9) -> 134839305 | M9: =L9 -> 134839305
B10: Construction in progress-FEMA Projects | I10: 26334104 | J10: 4721929 | K10: -18563822 | L10: =SUM(I10:K10) -> 12492211 | M10: =L10 -> 12492211
C11: Total capital assets not being depreciated | I11: =SUM(I8:I10) -> 139378928 | J11: =SUM(J8:J10) -> 59238669 | K11: =SUM(K8:K10) -> -37762517 | L11: =SUM(L8:L10) -> 160855080
A13: Capital assets, being depreciated:
B14: Buildings and improvements | I14: 160092363 | J14: 2437172 | K14: -992161 | L14: =SUM(I14:K14) -> 161537374
B15: Improvements other than buildings | I15: 75267749 | J15: 11154287 | K15: -817927 | L15: =SUM(I15:K15) -> 85604109
B16: Machinery and Equipment | I16: 40670939 | J16: 3479043 | K16: -587784 | L16: =SUM(I16:K16) -> 43562198
B17: Infrastructure | I17: 243202572 | J17: 10500925 | K17: -887919 | L17: =SUM(I17:K17) -> 252815578
C18: Total capital assets being depreciated | I18: =SUM(I14:I17) -> 519233623 | J18: =SUM(J14:J17) -> 27571427 | K18: =SUM(K14:K17) -> -3285791 | L18: =SUM(L14:L17) -> 543519259
A20: Less accumulated depreciation
B21: Buildings and improvements | I21: -30110000 | J21: -4314853 | K21: 232764 | L21: =SUM(I21:K21) -> -34192089 | M21: =L14+L21 -> 127345285
B22: Improvements other than buildings | I22: -6941563 | J22: -2559043 | L22: =SUM(I22:K22) -> -9500606 | M22: =L15+L22 -> 76103503
B23: Machinery and Equipment | I23: -19027118 | J23: -2269387 | K23: 159170 | L23: =SUM(I23:K23) -> -21137335 | M23: =L16+L23 -> 22424863
B24: Infrastructure | I24: -164703275 | J24: -1915548 | L24: =SUM(I24:K24) -> -166618823 | M24: =L17+L24 -> 86196755
C25: Total accumulated depreciation | I25: =SUM(I21:I24) -> -220781956 | J25: =SUM(J21:J24) -> -11058831 | K25: =SUM(K21:K24) -> 391934 | L25: =SUM(L21:L24) -> -231448853
A27: Total Capital Assets, being depreciated, net | I27: =I18+I25 -> 298451667 | J27: =J18+J25 -> 16512596 | K27: =K18+K25 -> -2893857 | L27: =L18+L25 -> 312070406
A28: Governmental Activities, net | I28: =I11+I27 -> 437830595 | J28: =J11+J27 -> 75751265 | K28: =K11+K27 -> -40656374 | L28: =L11+L27 -> 472925486 | M28: =SUM(M8:M25) -> 472925486
A31: Business-Type Activities:
A32: Capital assets, not being depreciated:
B33: Land | I33: 52000 | L33: =SUM(I33:K33) -> 52000 | M33: =L33 -> 52000
B34: Construction in Progress | I34: 31001463 | J34: 17745591 | K34: -21034707 | L34: =SUM(I34:K34) -> 27712347 | M34: =L34 -> 27712347
A35: Total capital assets not being depreciated | I35: =SUM(I33:I34) -> 31053463 | J35: =SUM(J33:J34) -> 17745591 | K35: =SUM(K33:K34) -> -21034707 | L35: =SUM(L33:L34) -> 27764347
A37: Capital assets being depreciated
B38: Buildings and Improvements | I38: 22835523 | J38: 13330522 | L38: =SUM(I38:K38) -> 36166045
B39: Improvements other than buildings | I39: 84439845 | J39: 7641048 | K39: -344619 | L39: =SUM(I39:K39) -> 91736274
B40: Machinery and Equipment | I40: 3331244 | J40: 598702 | K40: -97932 | L40: =SUM(I40:K40) -> 3832014
B41: Infrastructure | I41: 5670859 | J41: 635064 | K41: -1853999 | L41: =SUM(I41:K41) -> 4451924
C42: Total capital assets being depreciated | I42: =SUM(I38:I41) -> 116277471 | J42: =SUM(J38:J41) -> 22205336 | K42: =SUM(K38:K41) -> -2296550 | L42: =SUM(L38:L41) -> 136186257
A44: Less accumulated depreciation for
B45: Buildings and Improvements | I45: -9668015 | J45: -520059 | L45: =SUM(I45:K45) -> -10188074 | M45: =L38+L45 -> 25977971
B46: Improvements other than buildings | I46: -44526710 | J46: -3121626 | K46: -17855 | L46: =SUM(I46:K46) -> -47666191 | M46: =L39+L46 -> 44070083
B47: Machinery and Equipment | I47: -2311864 | J47: -179537 | K47: 25645 | L47: =SUM(I47:K47) -> -2465756 | M47: =L40+L47 -> 1366258
B48: Infrastructure | J48: -119833 | L48: =SUM(I48:K48) -> -119833 | M48: =L41+L48 -> 4332091
C49: Total accumulated depreciation | I49: =SUM(I45:I47) -> -56506589 | J49: =SUM(J45:J48) -> -3941055 | K49: =SUM(K45:K47) -> 7790 | L49: =SUM(L45:L48) -> -60439854
A51: Total capital assets being depreciated, net | I51: =I42+I49 -> 59770882 | J51: =J42+J49 -> 18264281 | K51: =K42+K49 -> -2288760 | L51: =L42+L49 -> 75746403
A53: Business-type activities, net | I53: =I35+I51 -> 90824345 | J53: =J35+J51 -> 36009872 | K53: =K35+K51 -> -23323467 | L53: =L35+L51 -> 103510750 | M53: =SUM(M33:M51) -> 103510750

Sheet Pointe Coupee
D1: POINTE COUPEE PARISH POLICE JURY
D2: Capital Assets
D3: For the Year Ended December 31, 2014
I5: Beginning Balance | J5: Increases | K5: Decreases | L5: Ending Balance | M5: Cross Sectional
A6: Governmental Activities:
A7: Capital assets, not being depreciated:
B8: Land | I8: 841274 | K8: 0 | L8: =SUM(I8:K8) -> 841274 | M8: =L8 -> 841274
B9: Construction in progress | I9: 2713183 | J9: 618895 | K9: -2713181 | L9: =SUM(I9:K9) -> 618897 | M9: =L9 -> 618897
C10: Total capital assets not being depreciated | I10: =SUM(I8:I9) -> 3554457 | J10: =SUM(J8:J9) -> 618895 | K10: =SUM(K8:K9) -> -2713181 | L10: =SUM(L8:L9) -> 1460171
A12: Capital assets, being depreciated:
B13: Buildings and improvements | I13: 8917113 | J13: 216049 | K13: 0 | L13: =SUM(I13:K13) -> 9133162
B14: Library collection | I14: 2832496 | J14: 127858 | K14: -4624 | L14: =SUM(I14:K14) -> 2955730
B15: Equipment, furnishings, and vehicles | I15: 7024983 | J15: 117328 | L15: =SUM(I15:K15) -> 7142311
B16: Infrastructure | I16: 10560782 | J16: 2699614 | L16: =SUM(I16:K16) -> 13260396
C17: Total capital assets being depreciated | I17: =SUM(I13:I16) -> 29335374 | J17: =SUM(J13:J16) -> 3160849 | K17: =SUM(K13:K16) -> -4624 | L17: =SUM(L13:L16) -> 32491599
A19: Less accumulated depreciation for
B20: Buildings and improvements | I20: -4010421 | J20: -227027 | K20: 0 | L20: =SUM(I20:K20) -> -4237448 | M20: =L13+L20 -> 4895714
B21: Library collection | I21: -2323621 | J21: -147451 | K21: 4624 | L21: =SUM(I21:K21) -> -2466448 | M21: =L14+L21 -> 489282
B22: Equipment, furnishings, and vehicles | I22: -6687304 | J22: -133954 | L22: =SUM(I22:K22) -> -6821258 | M22: =L15+L22 -> 321053
B23: Infrastructure | I23: -2713733 | J23: -710849 | L23: =SUM(I23:K23) -> -3424582 | M23: =L16+L23 -> 9835814
C24: Total accumulated depreciation | I24: =SUM(I20:I23) -> -15735079 | J24: =SUM(J20:J23) -> -1219281 | K24: =SUM(K20:K23) -> 4624 | L24: =SUM(L20:L23) -> -16949736
A26: Total Capital Assets, being depreciated, net | I26: =I17+I24 -> 13600295 | J26: =J17+J24 -> 1941568 | K26: =K17+K24 -> 0 | L26: =L17+L24 -> 15541863
A27: Governmental Activities capital assets, net | I27: =I10+I26 -> 17154752 | J27: =J10+J26 -> 2560463 | K27: =K10+K26 -> -2713181 | L27: =L10+L26 -> 17002034 | M27: =SUM(M8:M25) -> 17002034
A30: Business-Type Activities:
A31: Capital assets, not being depreciated:
B32: Land | I32: 45233 | L32: =SUM(I32:K32) -> 45233 | M32: =L32 -> 45233
A34: Capital assets being depreciated
B35: Utility systems and related equipment | I35: 7760431 | J35: 163582 | L35: =SUM(I35:K35) -> 7924013
B36: Less accumulated depreciation | I36: -5642893 | J36: -219896 | L36: =SUM(I36:K36) -> -5862789 | M36: =L35+L36 -> 2061224
A38: Total capital assets being depreciated, net | I38: =SUM(I35:I36) -> 2117538 | J38: =SUM(J35:J36) -> -56314 | K38: =SUM(K35:K36) -> 0 | L38: =SUM(L35:L36) -> 2061224
A40: Business-type activities capital assets, net | I40: =SUM(I38,I32) -> 2162771 | J40: =SUM(J38,J32) -> -56314 | K40: =SUM(K38,K32) -> 0 | L40: =SUM(L38,L32) -> 2106457 | M40: =SUM(M32:M38) -> 2106457

Sheet Rapides
D1: RAPIDES PARISH POLICE JURY
D2: Capital Assets
D3: For the Year Ended December 31, 2014
C5: Primary Government - Governmental Activities:
E6: Land | F6: Construction in Progress | G6: Buildings and Improvements | H6: Furniture and Equipment | I6: Infrastructure | J6: Total
C7: Beginning balance | E7: 1689373 | F7: 1375268 | G7: 26116897 | H7: 22002622 | I7: 346773509 | J7: =SUM(E7:I7) -> 397957669
D8: Additions | E8: 302625 | F8: 4503009 | G8: 311488 | H8: 2287785 | J8: =SUM(E8:I8) -> 7404907
D9: Deletions | F9: -1375268 | G9: -586081 | H9: -418174 | J9: =SUM(E9:I9) -> -2379523
C10: Ending balance | E10: =SUM(E7:E9) -> 1991998 | F10: =SUM(F7:F9) -> 4503009 | G10: =SUM(G7:G9) -> 25842304 | H10: =SUM(H7:H9) -> 23872233 | I10: =SUM(I7:I9) -> 346773509 | J10: =SUM(E10:I10) -> 402983053
B12: Accumulated depreciation:
C13: Beginning balance | E13: 0 | F13: 0 | G13: -15260169 | H13: -14939214 | I13: -316654120 | J13: =SUM(E13:I13) -> -346853503
D14: Additions | E14: 0 | F14: 0 | G14: -600823 | H14: -1313291 | I14: -999867 | J14: =SUM(E14:I14) -> -2913981
D15: Deletions | E15: 0 | F15: 0 | G15: 41716 | H15: 414671 | I15: 438988 | J15: =SUM(E15:I15) -> 895375
C16: Ending balance | E16: =SUM(E13:E15) -> 0 | F16: =SUM(F13:F15) -> 0 | G16: =SUM(G13:G15) -> -15819276 | H16: =SUM(H13:H15) -> -15837834 | I16: =SUM(I13:I15) -> -317214999 | J16: =SUM(J13:J15) -> -348872109
C18: Ending balance, net | E18: =SUM(E16,E10) -> 1991998 | F18: =SUM(F16,F10) -> 4503009 | G18: =SUM(G16,G10) -> 10023028 | H18: =SUM(H16,H10) -> 8034399 | I18: =SUM(I16,I10) -> 29558510 | J18: =SUM(J16,J10) -> 54110944
C20: Cross Sectional | E20: =E10 -> 1991998 | F20: =F10 -> 4503009 | G20: =G10+G16 -> 10023028 | H20: =H10+H16 -> 8034399 | I20: =I10+I16 -> 29558510 | J20: =J10+J16 -> 54110944

Sheet Red River
D1: RED RIVER PARISH POLICE JURY
D2: Capital Assets
D3: For the Year Ended December 31, 2014
I5: Balance at December 31, 2013 | J5: Additions | K5: Retirements | L5: Balance at December 31, 2014 | M5: Cross Sectional
A7: Capital assets, not being depreciated:
B8: Land | I8: 301537 | K8: 0 | L8: =SUM(I8:K8) -> 301537 | M8: =L8 -> 301537
B9: Construction in progress | I9: 1874046 | J9: 536075 | K9: -1618106 | L9: =SUM(I9:K9) -> 792015 | M9: =L9 -> 792015
C10: Total capital assets not being depreciated | I10: =SUM(I8:I9) -> 2175583 | J10: =SUM(J8:J9) -> 536075 | K10: =SUM(K8:K9) -> -1618106 | L10: =SUM(L8:L9) -> 1093552
A12: Capital assets, being depreciated:
B13: Buildings and building improvements | I13: 8371081 | J13: 2426416 | K13: 0 | L13: =SUM(I13:K13) -> 10797497
B14: Less accumulated depreciation | I14: -5743040 | J14: -324814 | L14: =SUM(I14:K14) -> -6067854 | M14: =L13+L14 -> 4729643
C15: Total buildings and building improvements | I15: =SUM(I13:I14) -> 2628041 | J15: =SUM(J13:J14) -> 2101602 | K15: =SUM(K13:K14) -> 0 | L15: =SUM(L13:L14) -> 4729643
B17: Streets, parking lots and other improvements | I17: 9574881 | J17: 1201362 | K17: 0 | L17: =SUM(I17:K17) -> 10776243
B18: Less accumulated depreciation | I18: -1497925 | J18: -998348 | L18: =SUM(I18:K18) -> -2496273 | M18: =L17+L18 -> 8279970
C19: Total streets, parking lots and other improvements | I19: =SUM(I17:I18) -> 8076956 | J19: =SUM(J17:J18) -> 203014 | K19: =SUM(K17:K18) -> 0 | L19: =SUM(L17:L18) -> 8279970
B21: Furniture, equipment, and vehicles | I21: 3591775 | J21: 293414 | K21: -808267 | L21: =SUM(I21:K21) -> 3076922
B22: Less accumulated depreciation | I22: -2309915 | J22: -454051 | K22: 808267 | L22: =SUM(I22:K22) -> -1955699 | M22: =L21+L22 -> 1121223
C23: Total furniture, equipment, and vehicles | I23: =SUM(I21:I22) -> 1281860 | J23: =SUM(J21:J22) -> -160637 | K23: =SUM(K21:K22) -> 0 | L23: =SUM(L21:L22) -> 1121223
B25: Library books and information materials | I25: 198739 | J25: 17789 | L25: =SUM(I25:K25) -> 216528
B26: Less accumulated depreciation | I26: -125118 | J26: -17504 | L26: =SUM(I26:K26) -> -142622 | M26: =L25+L26 -> 73906
C27: Total library books and information materials | I27: =SUM(I25:I26) -> 73621 | J27: =SUM(J25:J26) -> 285 | K27: =SUM(K25:K26) -> 0 | L27: =SUM(L25:L26) -> 73906
A29: Total capital assets being depreciated | I29: =I27+I23+I19+I15 -> 12060478 | J29: =J27+J23+J19+J15 -> 2144264 | K29: =K27+K23+K19+K15 -> 0 | L29: =L27+L23+L19+L15 -> 14204742 | N29: The difference between the numbers here and the unmbers was reported to have been a typo by Tommy Naquin with Postlewaithe & Netterville (225-408-4710) on 03/04/2015.
A31: Governmental activities total capital assets, net | I31: =I29+I10 -> 14236061 | J31: =J29+J10 -> 2680339 | K31: =K29+K10 -> -1618106 | L31: =L29+L10 -> 15298294 | M31: =SUM(M8:M29) -> 15298294
A33: Business-type Activities
A34: Capital assets, being depreciated
B35: Sewer system | I35: 1205548 | L35: =SUM(I34:I35) -> 1205548
B36: Less accumulated depreciated | I36: -850557 | J36: -92111 | L36: =SUM(I36:K36) -> -942668 | M36: =SUM(L35+L36) -> 262880
C37: Total Sewer system | I37: =SUM(I35:I36) -> 354991 | J37: =SUM(J35:J36) -> -92111 | K37: =SUM(K35:K36) -> 0 | L37: =SUM(L35:L36) -> 262880
C39: Total capital assets, being depreciated | I39: =SUM(I37) -> 354991 | J39: =SUM(J37) -> -92111 | K39: =SUM(K37) -> 0 | L39: =SUM(L37) -> 262880 | M39: =M36 -> 262880
A41: Business-type activities
C42: Total capital assets, net | I42: =SUM(I39) -> 354991 | J42: =SUM(J39) -> -92111 | K42: =SUM(K39) -> 0 | L42: =SUM(L39) -> 262880
A43: Primary government
C44: Total capital assets, net | I44: =SUM(I31+I42) -> 14591052 | J44: =SUM(J31+J42) -> 2588228 | K44: =SUM(K31+K42) -> -1618106 | L44: =SUM(L31+L42) -> 15561174 | M44: =SUM(M36+M26+M22+M18+M14+M9+M8) -> 15561174

Sheet Richland
D1: RICHLAND PARISH POLICE JURY
D2: Capital Assets
D3: For the Year Ended December 31, 2014
I5: Beginning, January 1, 2014 | J5: Additions | K5: Deletions | L5: Balance- Deceomber 31, 2014 | M5: Cross Sectional
A8: Capital assets, not being depreciated:
B9: Land | I9: 300273 | J9: 11250 | L9: =SUM(I9:K9) -> 311523 | M9: =L9 -> 311523
A11: Capital assets, being depreciated:
B12: Buildings and improvements | I12: 2957411 | J12: 149370 | L12: =SUM(I12:K12) -> 3106781
B13: Machinery and equipment | I13: 3861837 | J13: 316655 | K13: -202617 | L13: =SUM(I13:K13) -> 3975875
C14: Total capital assets being depreciated | I14: =SUM(I12:I13) -> 6819248 | J14: =SUM(J12:J13) -> 466025 | K14: =SUM(K12:K13) -> -202617 | L14: =SUM(L12:L13) -> 7082656
A16: Less accumulated depreciation for
B17: Buildings and improvements | I17: 1387908 | J17: 39885 | L17: =SUM(I17:K17) -> 1427793 | M17: =L12-L17 -> 1678988
B18: Machinery and Equipment | I18: 3293593 | J18: 249341 | K18: -196350 | L18: =SUM(I18:K18) -> 3346584 | M18: =L13-L18 -> 629291
C19: Total accumulated depreciation | I19: =SUM(I17:I18) -> 4681501 | J19: =SUM(J17:J18) -> 289226 | K19: =SUM(K17:K18) -> -196350 | L19: =SUM(L17:L18) -> 4774377
A21: Total Capital Assets, being depreciated | I21: =I14-I19 -> 2137747 | J21: =J14-J19 -> 176799 | K21: =K14-K19 -> -6267 | L21: =L14-L19 -> 2308279
A23: Total Capital Assets, net | I23: =SUM(I9+I21) -> 2438020 | J23: =SUM(J9+J21) -> 188049 | K23: =SUM(K9+K21) -> -6267 | L23: =SUM(L9+L21) -> 2619802 | M23: =SUM(M8:M19) -> 2619802

Sheet Sabine
D1: SABINE PARISH POLICE JURY
D2: Capital Assets
D3: For the Year Ended December 31, 2014
I5: Beginning Balance | J5: Additions | K5: Deductions | L5: Ending Balance | M5: Cross Sectional
B6: Land | I6: 639576 | L6: =SUM(I6:K6) -> 639576 | M6: =L6 -> 639576
B7: Construction in progress | I7: 540422 | J7: 2289249 | K7: -547878 | L7: =SUM(I7:K7) -> 2281793 | M7: =L7 -> 2281793
B8: Buildings | I8: 2793368 | J8: 547878 | K8: -1865 | L8: 3339381
B9: Machinery and equipment | I9: 5970950 | J9: 206973 | L9: =SUM(I9:K9) -> 6177923
B10: Furniture and fixtures | I10: 92022 | J10: 1889 | K10: -350 | L10: =SUM(I10:K10) -> 93561
B11: Infrastructure | I11: 66139545 | J11: 268800 | L11: =SUM(I11:K11) -> 66408345
C12: Total capital assets | I12: =SUM(I6:I11) -> 76175883 | J12: =SUM(J6:J11) -> 3314789 | K12: =SUM(K6:K11) -> -550093 | L12: =SUM(L6:L11) -> 78940579
A14: Depreciation
B15: Buildings | I15: -1073133 | J15: -68823 | K15: 1865 | L15: =SUM(I15:K15) -> -1140091 | M15: =L8+L15 -> 2199290
B16: Machinery and Equipment | I16: -2901475 | J16: -332973 | L16: =SUM(I16:K16) -> -3234448 | M16: =L9+L16 -> 2943475
B17: Furniture and fixtures | I17: -76694 | J17: -4644 | K17: 350 | L17: =SUM(I17:K17) -> -80988 | M17: =L10+L17 -> 12573
B18: Infrastructure | I18: -59529158 | J18: -1078349 | L18: =SUM(I18:K18) -> -60607507 | M18: =L11+L18 -> 5800838
C19: Total accumulated depreciation | I19: =SUM(I15:I18) -> -63580460 | J19: =SUM(J15:J18) -> -1484789 | K19: =SUM(K15:K18) -> 2215 | L19: =SUM(L15:L18) -> -65063034
A21: Net capital assets | I21: =SUM(I12+I19) -> 12595423 | J21: =SUM(J12+J19) -> 1830000 | K21: =SUM(K12+K19) -> -547878 | L21: =SUM(L12+L19) -> 13877545 | M21: =SUM(M6:M18) -> 13877545

Sheet St. Bernard
D1: ST. BERNARD PARISH POLICE JURY
D2: Capital Assets
D3: For the Year Ended December 31, 2014
I5: Balance January 1, 2014 | J5: Additions | K5: Deletions and adjustments | L5: Balance December 31, 2014 | M5: Cross Sectional
A6: Governmental-Type Activities:
A7: Nondepreciable capital assets
B8: Land | I8: 19245801 | J8: 580238 | L8: 19826039 | M8: =L8 -> 19826039
B9: Construction in progress | I9: 23876204 | J9: 23806841 | K9: -30753268 | L9: =SUM(I9:K9) -> 16929777 | M9: =L9 -> 16929777
C10: Total nondepreciable capital assets | I10: =SUM(I8:I9) -> 43122005 | J10: =SUM(J8:J9) -> 24387079 | K10: =SUM(K8:K9) -> -30753268 | L10: =SUM(L8:L9) -> 36755816
A12: Depreciable capital assets | N12: Depreciation
B13: Land improvements | I13: 20167 | J13: 842787 | L13: =SUM(I13:K13) -> 862954 | N13: =(L13/L19)*L21 -> 0
B14: Buildings and improvements | I14: 129702340 | J14: 2424717 | L14: =SUM(I14:K14) -> 132127057 | N14: =(L14/L19)*L21 -> 0
B15: Furniture, fixtures, and equipment | I15: 381929 | J15: 58906 | L15: =SUM(I15:K15) -> 440835 | N15: =(L15/L19)*L21 -> 0
B16: Machinery and equipment | I16: 17732336 | J16: 1386783 | L16: =SUM(I16:K16) -> 19119119 | N16: =(L16/L19)*L21 -> 0
B17: Road system | I17: 246667208 | J17: 14240017 | L17: =SUM(I17:K17) -> 260907225 | N17: =(L17/L19)*L21 -> 0
B18: Bridges | I18: 1363360 | L18: =SUM(I18:K18) -> 1363360 | N18: =(L18/L19)*L21 -> 0
C19: Total depreciable capital assets | I19: =SUM(I13:I18) -> 395867340 | J19: =SUM(J13:J18) -> 18953210 | K19: =SUM(K13:K18) -> 0 | L19: =SUM(L13:L18) -> 414820550
A21: Less: accumulated depreciation | N21: =SUM(N13:N18) -> 0
C22: Buildings
C23: Furniture, fixtures, and equipment
C24: Machinery and equipment
C25: Infrastructure
C26: Total accumulated depreciation | I26: -52848854 | J26: -13869602 | L26: =SUM(I26:K26) -> -66718456
C28: Total depreciable capital assets, net | I28: =SUM(I26+I19) -> 343018486 | J28: =SUM(J26+J19) -> 5083608 | K28: =SUM(K26+K19) -> 0 | L28: =SUM(L26+L19) -> 348102094
C29: Total governmental activities capital assets, net | I29: =SUM(I28+I10) -> 386140491 | J29: =SUM(J28+J10) -> 29470687 | K29: =SUM(K28+K10) -> -30753268 | L29: =SUM(L28+L10) -> 384857910
A32: Business-Type Activities:
A33: Nondepreciable capital assets
B34: Land | I34: 221036 | L34: =SUM(I34:K34) -> 221036 | M34: =L34 -> 221036
B35: Construction in progress | I35: 50611062 | J35: 4307968 | L35: =SUM(I35:K35) -> 54919030 | M35: =L35 -> 54919030
C36: Total nondepreciable capital assets | I36: =SUM(I34:I35) -> 50832098 | J36: =SUM(J35:J35) -> 4307968 | K36: =SUM(K35:K35) -> 0 | L36: =SUM(L34:L35) -> 55140066
A38: Depreciable capital assets | N38: Depreciation
B39: Buildings | I39: 73971568 | J39: 13270713 | L39: =SUM(I39:K39) -> 87242281 | N39: =(L39/L43)*L45 -> 0
B40: Furniture, fixtures, and equipment | I40: 36492 | L40: =SUM(I40:K40) -> 36492 | N40: =(L40/L43)*L45 -> 0
B41: Machinery and equipment | I41: 1613475 | J41: 53747 | L41: =SUM(I41:K41) -> 1667222 | N41: =(L41/L43)*L45 -> 0
B42: Infrastructure | I42: 187779692 | J42: 164914 | L42: =SUM(I42:K42) -> 187944606 | N42: =(L42/L43)*L45 -> 0
C43: Total depreciable capital assets | I43: =SUM(I39:I42) -> 263401227 | J43: =SUM(J39:J42) -> 13489374 | K43: =SUM(K39:K42) -> 0 | L43: =SUM(L39:L42) -> 276890601
A45: Less: accumulated depreciation | N45: =SUM(N39:N42) -> 0
B46: Buildings
B47: Furniture, fixtures, and equipment
B48: Machinery and equipment
B49: Infrastructure
C50: Total accumulated depreciation | I50: -109267170 | J50: -5280768 | L50: =SUM(I50:K50) -> -114547938
C52: Total depreciable capital assets, net | I52: =SUM(I43+I50) -> 154134057 | J52: =SUM(J43+J50) -> 8208606 | K52: =SUM(K43+K50) -> 0 | L52: =SUM(L43+L50) -> 162342663
C53: Total business-type activities capital assets, net | I53: =I36+I52 -> 204966155 | J53: =J36+J52 -> 12516574 | K53: =K36+K52 -> 0 | L53: =L36+L52 -> 217482729 | M53: =SUM(M34:M45) -> 55140066

Sheet St. Charles
D1: ST. CHARLES PARISH
D2: Capital Assets
D3: For the Year Ended December 31, 2014
I5: Balance at December 31, 2014 | J5: Additions | K5: Deletions | L5: Adjustments | M5: Balance at December 31, 2014 | N5: Cross Sectional
A6: Governmental Activities
A7: Capital assets, not being depreciated:
A8: Land | I8: 10141106 | J8: 343705 | M8: =SUM(I8:L8) -> 10484811 | N8: =M8 -> 10484811
A9: Infrastructure | I9: 14855447 | M9: =SUM(I9:L9) -> 14855447 | N9: =M9 -> 14855447
A10: Construction in progress | I10: 50057093 | J10: 12958051 | K10: -28832852 | L10: 2932 | M10: =SUM(I10:L10) -> 34185224 | N10: =M10 -> 34185224
B11: Total assets not being depreciated | I11: =SUM(I8:I10) -> 75053646 | J11: =SUM(J8:J10) -> 13301756 | K11: =SUM(K8:K10) -> -28832852 | L11: =SUM(L8:L10) -> 2932 | M11: =SUM(M8:M10) -> 59525482
A13: Capital assets, being depreciated:
A14: Buildings | I14: 32339120 | J14: 18738719 | K14: -68896 | M14: =SUM(I14:L14) -> 51008943
A15: Improvements other than buildings | I15: 76707234 | J15: 7356685 | K15: -8600 | L15: 1851 | M15: =SUM(I15:L15) -> 84057170
A16: Machinery and equipment | I16: 36753395 | J16: 2756716 | K16: -87058 | L16: -10266 | M16: =SUM(I16:L16) -> 39412787
A17: Infrastructure | I17: 110480961 | K17: -634576 | L17: 1575726 | M17: =SUM(I17:L17) -> 111422111
C18: Total capital assets being depreciated | I18: =SUM(I14:I17) -> 256280710 | J18: =SUM(J14:J17) -> 28852120 | K18: =SUM(K14:K17) -> -799130 | L18: =SUM(L14:L17) -> 1567311 | M18: =SUM(M14:M17) -> 285901011
A20: Less accumulated depreciation for:
A21: Buildings | I21: -12058376 | J21: -1013758 | K21: 32915 | L21: -42242 | M21: =SUM(I21:L21) -> -13081461 | N21: =M14+M21 -> 37927482
A22: Improvements other than buildings | I22: -32566310 | J22: -4469312 | K22: 8600 | L22: 11539 | M22: =SUM(I22:L22) -> -37015483 | N22: =M15+M22 -> 47041687
A23: Machinery and equipment | I23: -26858102 | J23: -2216937 | K23: 93794 | L23: -35906 | M23: =SUM(I23:L23) -> -29017151 | N23: =M16+M23 -> 10395636
A24: Infrastructure | I24: -65587399 | J24: -3297251 | K24: 187075 | L24: 2553 | M24: =SUM(I24:L24) -> -68695022 | N24: =M17+M24 -> 42727089
C25: Total accumulated depreciation | I25: =SUM(I21:I24) -> -137070187 | J25: =SUM(J21:J24) -> -10997258 | K25: =SUM(K21:K24) -> 322384 | L25: =SUM(L21:L24) -> -64056 | M25: =SUM(M21:M24) -> -147809117
A27: Total capital assets being depreciated, net | I27: =SUM(I18+I25) -> 119210523 | J27: =SUM(J18+J25) -> 17854862 | K27: =SUM(K18+K25) -> -476746 | L27: =SUM(L18+L25) -> 1503255 | M27: =SUM(M18+M25) -> 138091894
A29: Total governmental activities capital assets, net | I29: =I11+I27 -> 194264169 | J29: =J11+J27 -> 31156618 | K29: =K11+K27 -> -29309598 | L29: =L11+L27 -> 1506187 | M29: =M11+M27 -> 197617376 | N29: =SUM(N8:N27) -> 197617376
A32: Business-type Activities
A33: Land | I33: 824777 | M33: =SUM(I33:L33) -> 824777 | N33: =M33 -> 824777
A34: Construction in progress | I34: 5726853 | J34: 1286520 | K34: -3068635 | M34: =SUM(I34:L34) -> 3944738 | N34: =M34 -> 3944738
B35: Total assets not being depreciated | I35: =SUM(I33:I34) -> 6551630 | J35: =SUM(J33:J34) -> 1286520 | K35: =SUM(K33:K34) -> -3068635 | L35: =SUM(L33:L34) -> 0 | M35: =SUM(M33:M34) -> 4769515
A37: Capital assets, being depreciated:
A38: Buildings and improvements | I38: 207957654 | J38: 5135156 | K38: -17628 | L38: 567731 | M38: =SUM(I38:L38) -> 213642913
A39: Machinery and equipment | I39: 15333137 | J39: 387981 | K39: -18000 | L39: -111977 | M39: =SUM(I39:L39) -> 15591141
C40: Total capital assets being depreciated | I40: =SUM(I38:I39) -> 223290791 | J40: =SUM(J38:J39) -> 5523137 | K40: =SUM(K38:K39) -> -35628 | L40: =SUM(L38:L39) -> 455754 | M40: =SUM(M38:M39) -> 229234054
A42: Less accumulated depreciation for:
A43: Buildings and improvements | I43: -81748123 | J43: -5470809 | K43: 3673 | L43: -6500 | M43: =SUM(I43:L43) -> -87221759 | N43: =M38+M43 -> 126421154
A44: Machinery and equipment | I44: -13294233 | J44: -652496 | K44: 18000 | L44: 112199 | M44: =SUM(I44:L44) -> -13816530 | N44: =M39+M44 -> 1774611
C45: Total accumulated depreciation | I45: =SUM(I43:I44) -> -95042356 | J45: =SUM(J43:J44) -> -6123305 | K45: =SUM(K43:K44) -> 21673 | L45: =SUM(L43:L44) -> 105699 | M45: =SUM(M43:M44) -> -101038289
A47: Total capital assets being depreciated, net | I47: =SUM(I40+I45) -> 128248435 | J47: =SUM(J40+J45) -> -600168 | K47: =SUM(K40+K45) -> -13955 | L47: =SUM(L40+L45) -> 561453 | M47: =SUM(M40+M45) -> 128195765
A49: Total business type activities capital assets, net | I49: =I35+I47 -> 134800065 | J49: =J35+J47 -> 686352 | K49: =K35+K47 -> -3082590 | L49: =L35+L47 -> 561453 | M49: =M35+M47 -> 132965280 | N49: =SUM(N33:N47) -> 132965280

Sheet St. Helena
D1: ST. HELENA PARISH POLICE JURY
D2: Capital Assets
D3: For the Year Ended December 31, 2014
I5: Beginning Balance | J5: Increases | K5: Decreases | L5: Adjustments | M5: Ending Balance | N5: Cross Sectional
A6: Governmental Activities Capital Assets:
A7: Capital assets, not being depreciated:
B8: Land | I8: 227865 | J8: 7171 | M8: =SUM(I8:L8) -> 235036 | N8: =M8 -> 235036
B9: Construction in progress | I9: 1476353 | J9: 1328450 | K9: -700436 | M9: =SUM(I9:L9) -> 2104367 | N9: =M9 -> 2104367
C10: Total assets not being depreciated | I10: =SUM(I8:I9) -> 1704218 | J10: =SUM(J8:J9) -> 1335621 | K10: =SUM(K8:K9) -> -700436 | L10: =SUM(L8:L9) -> 0 | M10: =SUM(M8:M9) -> 2339403
A12: Capital assets, being depreciated:
B13: Buildings and improvements | I13: 4411952 | J13: 1395319 | M13: =SUM(I13:L13) -> 5807271
B14: Machinery and Improvements | I14: 6225882 | J14: 410669 | K14: -52894 | M14: =SUM(I14:L14) -> 6583657
B15: Infrastructure | I15: 6851788 | J15: 3685987 | M15: =SUM(I15:L15) -> 10537775
C16: Total capital assets being depreciated | I16: =SUM(I13:I15) -> 17489622 | J16: =SUM(J13:J15) -> 5491975 | K16: =SUM(K13:K15) -> -52894 | L16: =SUM(L13:L15) -> 0 | M16: =SUM(M13:M15) -> 22928703
A18: Less accumulated depreciation for
B19: Buildings and improvements | I19: -1917855 | J19: -119046 | M19: =SUM(I19:L19) -> -2036901 | N19: =M13+M19 -> 3770370
B20: Machinery and Equipment | I20: -3667007 | J20: -497192 | K20: 43073 | M20: =SUM(I20:L20) -> -4121126 | N20: =M14+M20 -> 2462531
B21: Infrastructure | I21: -1069772 | J21: -172842 | M21: =SUM(I21:L21) -> -1242614 | N21: =M15+M21 -> 9295161
C22: Total accumulated depreciation | I22: =SUM(I19:I21) -> -6654634 | J22: =SUM(J19:J21) -> -789080 | K22: =SUM(K19:K21) -> 43073 | L22: =SUM(L19:L21) -> 0 | M22: =SUM(M19:M21) -> -7400641
A24: Total Capital Assets, being depreciated, net | I24: =I16+I22 -> 10834988 | J24: =J16+J22 -> 4702895 | K24: =K16+K22 -> -9821 | L24: =L16+L22 -> 0 | M24: =M16+M22 -> 15528062
A25: Total Governmental activities capital assets, net | I25: =I10+I24 -> 12539206 | J25: =J10+J24 -> 6038516 | K25: =K10+K24 -> -710257 | L25: =L10+L24 -> 0 | M25: =M10+M24 -> 17867465 | N25: =SUM(N8:N23) -> 17867465

Sheet St. James
D1: ST. JAMES PARISH POLICE JURY
D2: Capital Assets
D3: For the Year Ended December 31, 2014
I5: Beginning Balance | J5: Increases | K5: Decreases | L5: Ending Balance | M5: Cross Sectional
A6: Governmental Activities:
A7: Capital assets, not being depreciated:
B8: Land | I8: 17858242 | J8: 3482122 | L8: =SUM(I8:K8) -> 21340364 | M8: =L8 -> 21340364
B9: Construction in progress | I9: 1874609 | J9: 5365677 | K9: -64331 | L9: =SUM(I9:K9) -> 7175955 | M9: =L9 -> 7175955
C10: Total assets not being depreciated | I10: =SUM(I8:I9) -> 19732851 | J10: =SUM(J8:J9) -> 8847799 | K10: =SUM(K8:K9) -> -64331 | L10: =SUM(L8:L9) -> 28516319
A12: Capital assets, being depreciated
A13: Buildings | I13: 21171854 | J13: 89220 | L13: =SUM(I13:K13) -> 21261074
A14: Improvements other than buildings | I14: 4547372 | J14: 140940 | L14: =SUM(I14:K14) -> 4688312
A15: Machinery and equipment | I15: 14490156 | J15: 738481 | K15: -222693 | L15: =SUM(I15:K15) -> 15005944
A16: Library collection | I16: 1866846 | J16: 70474 | K16: -29817 | L16: =SUM(I16:K16) -> 1907503
A17: Infrastructure | I17: 57551183 | J17: 640080 | L17: =SUM(I17:K17) -> 58191263
B18: Total capital assets being depreciated | I18: =SUM(I13:I17) -> 99627411 | J18: =SUM(J13:J17) -> 1679195 | K18: =SUM(K13:K17) -> -252510 | L18: =SUM(L13:L17) -> 101054096
A20: Less accumulated depreciation for
A21: Buildings | I21: -6691598 | J21: -665373 | L21: =SUM(I21:K21) -> -7356971 | M21: =L13+L21 -> 13904103
A22: Improvements other than buildings | I22: -1308567 | J22: -190926 | L22: =SUM(I22:K22) -> -1499493 | M22: =L14+L22 -> 3188819
A23: Machinery and equipment | I23: -8422457 | J23: -1194261 | K23: 218199 | L23: =SUM(I23:K23) -> -9398519 | M23: =L15+L23 -> 5607425
A24: Library collection | I24: -1792962 | J24: -73884 | K24: 29817 | L24: =SUM(I24:K24) -> -1837029 | M24: =L16+L24 -> 70474
A25: Infrastructure | I25: -44865294 | J25: -1485746 | L25: -46351040 | M25: =L17+L25 -> 11840223
A26: Total accumulated depreciation | I26: =SUM(I21:I25) -> -63080878 | J26: =SUM(J21:J25) -> -3610190 | K26: =SUM(K21:K25) -> 248016 | L26: =SUM(L21:L25) -> -66443052
A28: Total capital assets, being depreciated, net | I28: =SUM(I26+I18) -> 36546533 | J28: =SUM(J26+J18) -> -1930995 | K28: =SUM(K26+K18) -> -4494 | L28: =SUM(L26+L18) -> 34611044
A29: Governmental activities capital assets, net | I29: =SUM(I10+I18+I26) -> 56279384 | J29: =SUM(J10+J18+J26) -> 6916804 | K29: =SUM(K10+K18+K26) -> -68825 | L29: =SUM(L10+L18+L26) -> 63127363 | M29: =SUM(M8:M25) -> 63127363
A31: Business-type activities:
A32: Capital assets, not being depreciated
A33: Land | I33: 1040000 | J33: 10000 | L33: =SUM(I33:K33) -> 1050000 | M33: =L33 -> 1050000
A34: Construction in progress | I34: 23713 | J34: 23767 | L34: =SUM(I34:K34) -> 47480 | M34: =L34 -> 47480
A35: Total capital assets, not being depreciated | I35: =SUM(I33:I34) -> 1063713 | J35: =SUM(J33:J34) -> 33767 | K35: =SUM(K33:K34) -> 0 | L35: =SUM(L33:L34) -> 1097480
A37: Capital assets, being depreciated
A38: Buildings | I38: 6748107 | K38: -686937 | L38: =SUM(I38:K38) -> 6061170
A39: Gas distribution system | I39: 2098948 | L39: =SUM(I39:K39) -> 2098948
A40: Water distribution system | I40: 21854558 | L40: =SUM(I40:K40) -> 21854558
A41: Office furniture, fixtures, and equipment | I41: 743617 | J41: 10750 | K41: -3294 | L41: =SUM(I41:K41) -> 751073
A42: Transportation equipment | I42: 463668 | J42: 130217 | L42: =SUM(I42:K42) -> 593885
A43: Total capital assets, being depcreciated | I43: =SUM(I38:I42) -> 31908898 | J43: =SUM(J38:J42) -> 140967 | K43: =SUM(K38:K42) -> -690231 | L43: =SUM(L38:L42) -> 31359634
A45: Less accumulated depreciation for
A46: Buildings | I46: -5332460 | J46: -188709 | L46: =SUM(I46:K46) -> -5521169 | M46: =SUM(L38+L46) -> 540001
A47: Gas distribution system | I47: -1569488 | J47: -22122 | L47: =SUM(I47:K47) -> -1591610 | M47: =SUM(L39+L47) -> 507338
A48: Water distribution system | I48: -10495825 | J48: -608504 | L48: =SUM(I48:K48) -> -11104329 | M48: =SUM(L40+L48) -> 10750229
A49: Office furniture, fixtures, and equipment | I49: -731425 | J49: -5447 | K49: 3294 | L49: =SUM(I49:K49) -> -733578 | M49: =SUM(L41+L49) -> 17495
A50: Transportation equipment | I50: -323149 | J50: -47166 | L50: =SUM(I50:K50) -> -370315 | M50: =SUM(L42+L50) -> 223570
A51: Total accumulated depreciation | I51: =SUM(I46:I50) -> -18452347 | J51: =SUM(J46:J50) -> -871948 | K51: =SUM(K46:K50) -> 3294 | L51: =SUM(L46:L50) -> -19321001
A53: Total capital assets, being depreciated, net | I53: =SUM(I43+I51) -> 13456551 | J53: =SUM(J43+J51) -> -730981 | K53: =SUM(K43+K51) -> -686937 | L53: =SUM(L43+L51) -> 12038633
A55: Business-type activities capital assets, net | I55: =SUM(I35+I53) -> 14520264 | J55: =SUM(J35+J53) -> -697214 | K55: =SUM(K35+K53) -> -686937 | L55: =SUM(L35+L53) -> 13136113 | M55: =SUM(M33:M50) -> 13136113

Sheet St. John the Baptist
D1: ST. JOHN THE BAPTIST PARISH POLICE JURY
D2: Capital Assets
D3: For the Year Ended December 31, 2014
I5: 41640 | J5: Additions | K5: Reductions | L5: Decmber 31, 2013 | M5: Cross Sectional
A6: Governmental Activities
A7: Capital assets, not being depreciated:
B8: Land | I8: 3976254 | L8: =SUM(I8:K8) -> 3976254 | M8: =L8 -> 3976254
B9: Construction in progress | I9: 4747061 | J9: 11240834 | K9: -4281743 | L9: =SUM(I9:K9) -> 11706152 | M9: =L9 -> 11706152
B10: Total assets not being depreciated | I10: =SUM(I8:I9) -> 8723315 | J10: =SUM(J8:J9) -> 11240834 | K10: =SUM(K8:K9) -> -4281743 | L10: =SUM(L8:L9) -> 15682406
A12: Capital assets, being depreciated:
B13: Buildings and building improvements | I13: 33452568 | J13: 442278 | L13: =SUM(I13:K13) -> 33894846
B14: Infrastructure | I14: 170187720 | J14: 3732460 | L14: =SUM(I14:K14) -> 173920180
B15: Drainage system | I15: 21203204 | J15: 218262 | L15: =SUM(I15:K15) -> 21421466
B16: Furniture, fixtures, and equipment | I16: 9850887 | J16: 1477011 | K16: -62500 | L16: =SUM(I16:K16) -> 11265398
B17: Vehicles | I17: 9383657 | J17: 321804 | L17: =SUM(I17:K17) -> 9705461
B18: Total capital assets being depreciated | I18: =SUM(I13:I17) -> 244078036 | J18: =SUM(J13:J17) -> 6191815 | K18: =SUM(K13:K17) -> -62500 | L18: =SUM(L13:L17) -> 250207351
A20: Less accumulated depreciation for:
B21: Buildings and building improvements | I21: 8967784 | J21: 1072690 | L21: =SUM(I21:K21) -> 10040474 | M21: =L13-L21 -> 23854372
B22: Infrastructure | I22: 145516818 | J22: 1821450 | L22: =SUM(I22:K22) -> 147338268 | M22: =L14-L22 -> 26581912
B23: Drainage system | I23: 6158721 | J23: 524443 | L23: =SUM(I23:K23) -> 6683164 | M23: =L15-L23 -> 14738302
B24: Furniture, fixtures, and equipment | I24: 7680022 | J24: 471179 | K24: -62500 | L24: =SUM(I24:K24) -> 8088701 | M24: =L16-L24 -> 3176697
B25: Vehicles | I25: 7093783 | J25: 467724 | L25: =SUM(I25:K25) -> 7561507 | M25: =L17-L25 -> 2143954
B26: Total accumulated depreciation | I26: =SUM(I21:I25) -> 175417128 | J26: =SUM(J21:J25) -> 4357486 | K26: =SUM(K21:K25) -> -62500 | L26: =SUM(L21:L25) -> 179712114
A27: Total capital assets being depreciated, net | I27: =SUM(I18-I26) -> 68660908 | J27: =SUM(J18-J26) -> 1834329 | K27: =SUM(K18-K26) -> 0 | L27: =SUM(L18-L26) -> 70495237
A28: Total governmental activities capital assets, net | I28: =SUM(I10+I27) -> 77384223 | J28: =SUM(J10+J27) -> 13075163 | K28: =SUM(K10+K27) -> -4281743 | L28: =SUM(L10+L27) -> 86177643 | M28: =SUM(M8:M26) -> 86177643
A31: Business-Type Activities:
A32: Capital assets, not being depreciated:
B33: Land | I33: 1678616 | L33: =SUM(I33:K33) -> 1678616 | M33: =L33 -> 1678616
B34: Construction in progress | I34: 352803 | J34: 1650999 | K34: -516073 | L34: =SUM(I34:K34) -> 1487729 | M34: =L34 -> 1487729
C35: Total capital assets not being depreciated | I35: =SUM(I33:I34) -> 2031419 | J35: =SUM(J33:J34) -> 1650999 | K35: =SUM(K33:K34) -> -516073 | L35: =SUM(L33:L34) -> 3166345
A37: Capital assets, being depreciated
A38: Buildings and building improvements | I38: 14404866 | J38: 117892 | L38: =SUM(I38:K38) -> 14522758
A39: Systems-water and sewer | I39: 205932575 | J39: 2353419 | L39: =SUM(I39:K39) -> 208285994
A40: Furniture, fixtures, and equipment | I40: 5491295 | J40: 228274 | K40: -15299 | L40: =SUM(I40:K40) -> 5704270
A41: Vehicles | I41: 1859327 | J41: 67885 | L41: =SUM(I41:K41) -> 1927212
A42: Total capital assets, being depreciated | I42: =SUM(I38:I41) -> 227688063 | J42: =SUM(J38:J41) -> 2767470 | K42: =SUM(K38:K41) -> -15299 | L42: =SUM(I42:K42) -> 230440234
A44: Less accumulated depreciation for
A45: Buildings and building improvements | I45: 2315498 | J45: 386651 | L45: =SUM(I45:K45) -> 2702149 | M45: =L38-L45 -> 11820609
A46: Systems-water and sewer | I46: 94478756 | J46: 4468553 | L46: =SUM(I46:K46) -> 98947309 | M46: =L39-L46 -> 109338685
A47: Furniture, fixtures, and equipment | I47: 2451159 | J47: 74055 | K47: -1018 | L47: =SUM(I47:K47) -> 2524196 | M47: =L40-L47 -> 3180074
A48: Vehicles | I48: 1507310 | J48: 242427 | L48: =SUM(I48:K48) -> 1749737 | M48: =L41-L48 -> 177475
A49: Total accumulated depreciation | I49: =SUM(I45:I48) -> 100752723 | J49: =SUM(J45:J48) -> 5171686 | K49: =SUM(K45:K48) -> -1018 | L49: =SUM(I49:K49) -> 105923391
A50: Total capital assets, being depreciated, net | I50: =SUM(I42-I49) -> 126935340 | J50: =SUM(J42-J49) -> -2404216 | K50: =SUM(K42-K49) -> -14281 | L50: =SUM(L42-L49) -> 124516843
A51: Total business-type activities capital assets, net | I51: =SUM(I35+I50) -> 128966759 | J51: =SUM(J35+J50) -> -753217 | K51: =SUM(K35+K50) -> -530354 | L51: =SUM(L35+L50) -> 127683188 | M51: =SUM(M33:M49) -> 127683188

Sheet St. Landry
D1: ST. LANDRY PARISH POLICE JURY
D2: Capital Assets
D3: For the Year Ended December 31, 2014
I5: Balance 01/01/14 | J5: Additions | K5: Deletions | L5: Balance 12/31/14 | M5: Cross Sectional
A6: Primary Government
A7: Governmental Activities:
A8: Capital assets, not being depreciated:
B9: Land | I9: 499243 | L9: =SUM(I9:K9) -> 499243 | M9: =L9 -> 499243
B10: Construction in progress- infrastructure | J10: 9080748 | L10: =SUM(I10:K10) -> 9080748 | M10: =L10 -> 9080748
I11: =SUM(I9:I10) -> 499243 | J11: =SUM(J9:J10) -> 9080748 | K11: =SUM(K9:K10) -> 0 | L11: =SUM(L9:L10) -> 9579991
A12: Capital assets, being depreciated:
B13: Buildings and improvements | I13: 14525602 | L13: =SUM(I13:K13) -> 14525602
B14: Vehicles | I14: 432982 | J14: 129740 | K14: -41955 | L14: =SUM(I14:K14) -> 520767
B15: Equipment, furniture and fixtures | I15: 4468333 | J15: 84577 | K15: -113665 | L15: =SUM(I15:K15) -> 4439245
B16: Improvements other than buildings | I16: 6342054 | J16: 277583 | L16: =SUM(I16:K16) -> 6619637
I17: =SUM(I13:I16) -> 25768971 | J17: =SUM(J13:J16) -> 491900 | K17: =SUM(K13:K16) -> -155620 | L17: =SUM(I17:K17) -> 26105251
A18: Less accumulated depreciation for
B19: Buildings and improvements | I19: -10607972 | J19: -252767 | L19: =SUM(I19:K19) -> -10860739 | M19: =L13+L19 -> 3664863
B20: Vehicles | I20: -193387 | J20: -76444 | K20: 36687 | L20: =SUM(I20:K20) -> -233144 | M20: =L14+L20 -> 287623
B21: Equipment, furniture and fixtures | I21: -3162472 | J21: -376642 | K21: 113665 | L21: =SUM(I21:K21) -> -3425449 | M21: =L15+L21 -> 1013796
B22: Improvements other than buildings | I22: -2798068 | J22: -286695 | L22: =SUM(I22:K22) -> -3084763 | M22: =L16+L22 -> 3534874
I23: =SUM(I19:I22) -> -16761899 | J23: =SUM(J19:J22) -> -992548 | K23: =SUM(K19:K22) -> 150352 | L23: =SUM(L19:L22) -> -17604095
A24: Total Capital Assets being depreciated, net | I24: =SUM(I17+I23) -> 9007072 | J24: =SUM(J17+J23) -> -500648 | K24: =SUM(K17+K23) -> -5268 | L24: =SUM(L17+L23) -> 8501156
A25: Governmental activities capital assets, net | I25: =SUM(I11+I17+I23) -> 9506315 | J25: =SUM(J11+J17+J23) -> 8580100 | K25: =SUM(K11+K17+K23) -> -5268 | L25: =SUM(L11+L17+L23) -> 18081147 | M25: =SUM(M9:M23) -> 18081147

Sheet St. Martin
D1: ST. MARTIN PARISH POLICE JURY
D2: Capital Assets
D3: For the Year Ended December 31, 2014
I5: Beginning Balance | J5: Acquisitions | K5: Dispositions | L5: Ending Balance | M5: Cross Sectional
A6: Primary Government
A7: Governmental-Type Activities:
A8: Capital assets, not being depreciated:
B9: Land | I9: 1515115 | J9: 45000 | L9: =SUM(I9:K9) -> 1560115 | M9: =L9 -> 1560115
B10: Construction in progress | I10: 9423016 | J10: 1213143 | K10: -9423016 | L10: =SUM(I10:K10) -> 1213143 | M10: =L10 -> 1213143
C11: Total assets not being depreciated | I11: =SUM(I9:I10) -> 10938131 | J11: =SUM(J9:J10) -> 1258143 | K11: =SUM(K9:K10) -> -9423016 | L11: =SUM(L9:L10) -> 2773258
A13: Capital assets, being depreciated:
B14: Buildings and improvements | I14: 30662464 | J14: 5653809 | L14: =SUM(I14:K14) -> 36316273
B15: Machinery and equipment | I15: 14905054 | J15: 1163510 | K15: -736740 | L15: =SUM(I15:K15) -> 15331824
B16: Improvements, other than buildings | I16: 1781934 | L16: =SUM(I16:K16) -> 1781934
B17: Roads and bridges | I17: 38203364 | J17: 5603654 | L17: =SUM(I17:K17) -> 43807018
C18: Total capital assets being depreciated | I18: =SUM(I14:I17) -> 85552816 | J18: =SUM(J14:J17) -> 12420973 | K18: =SUM(K14:K17) -> -736740 | L18: =SUM(L14:L17) -> 97237049
A20: Less accumulated depreciation for
B21: Buildings | I21: 7355299 | J21: 907907 | L21: =SUM(I21:K21) -> 8263206 | M21: =L14-L21 -> 28053067
B22: Machinery and Equipment | I22: 9398641 | J22: 1460174 | K22: -736740 | L22: =SUM(I22:K22) -> 10122075 | M22: =L15-L22 -> 5209749
B23: Improvements, other than buildings | I23: 676310 | J23: 71277 | L23: =SUM(I23:K23) -> 747587 | M23: =L16-L23 -> 1034347
B24: Roads and bridges | I24: 8699862 | J24: 1443588 | L24: =SUM(I24:K24) -> 10143450 | M24: =L17-L24 -> 33663568
C25: Total accumulated depreciation | I25: =SUM(I21:I24) -> 26130112 | J25: =SUM(J21:J24) -> 3882946 | K25: =SUM(K21:K24) -> -736740 | L25: =SUM(L21:L24) -> 29276318
A27: Total Capital Assets being depreciated, net | I27: =I18-I25 -> 59422704 | J27: =J18-J25 -> 8538027 | K27: =K18-K25 -> 0 | L27: =L18-L25 -> 67960731
A28: Governmental activities capital assets, net | I28: =I11+I27 -> 70360835 | J28: =J11+J27 -> 9796170 | K28: =K11+K27 -> -9423016 | L28: =L11+L27 -> 70733989 | M28: =SUM(M9:M26) -> 70733989

Sheet St Mary
E1: ST. TAMMANY PARISH POLICE JURY
E2: Capital Assets
E3: For the Year Ended December 31, 2014
A6: Primary Government | J6: Beginning Balance | K6: Increases | L6: Decreases | M6: Transfers | N6: Ending Balance | O6: Cross Sectional
A7: Governmental Activities
B8: Capital assets, not being depreciated:
C9: Land | J9: 1870876 | N9: =SUM(J9:M9) -> 1870876 | O9: =N9 -> 1870876
C10: Construction in progress | J10: 1887343 | K10: 3329766 | M10: -2317559 | N10: =SUM(J10:M10) -> 2899550 | O10: =N10 -> 2899550
D11: Total capital assets not being depreciated | J11: =SUM(J9:J10) -> 3758219 | K11: =SUM(K9:K10) -> 3329766 | L11: =SUM(L9:L10) -> 0 | M11: =SUM(M9:M10) -> -2317559 | N11: =SUM(N9:N10) -> 4770426
B13: Other capital assets:
C14: Infrastructure | J14: 130789018 | K14: 188924 | N14: =SUM(J14:M14) -> 130977942
C15: Buildings | J15: 17516962 | N15: =SUM(J15:M15) -> 17516962
C16: Equipment and furniture | J16: 11507452 | K16: 772020 | L16: -1032106 | N16: =SUM(J16:M16) -> 11247366
C17: Improvements | J17: 21701903 | M17: 2317559 | N17: =SUM(J17:M17) -> 24019462
D18: Total capital assets being depreciated | J18: =SUM(J14:J17) -> 181515335 | K18: =SUM(K14:K17) -> 960944 | L18: =SUM(L14:L17) -> -1032106 | M18: =SUM(M14:M17) -> 2317559 | N18: =SUM(N14:N17) -> 183761732
B20: Less accumulated depreciation for:
C21: Infrastructure | J21: -52228358 | K21: -3189061 | N21: =SUM(J21:M21) -> -55417419 | O21: =N14+N21 -> 75560523
C22: Buildings | J22: -6996508 | K22: -472223 | N22: =SUM(J22:M22) -> -7468731 | O22: =N15+N22 -> 10048231
C23: Equipment and furniture | J23: -9484427 | K23: -584895 | L23: 1032106 | N23: =SUM(J23:M23) -> -9037216 | O23: =N16+N23 -> 2210150
C24: Improvements | J24: -7956919 | K24: -1032266 | N24: =SUM(J24:M24) -> -8989185 | O24: =N17+N24 -> 15030277
D25: Total accumulated depreciation | J25: =SUM(J21:J24) -> -76666212 | K25: =SUM(K21:K24) -> -5278445 | L25: =SUM(L21:L24) -> 1032106 | M25: =SUM(M21:M24) -> 0 | N25: =SUM(N21:N24) -> -80912551
D26: Other capital assets, net | J26: =SUM(J18+J25) -> 104849123 | K26: =SUM(K18+K25) -> -4317501 | L26: =SUM(L18+L25) -> 0 | M26: =SUM(M18+M25) -> 2317559 | N26: =SUM(N18+N25) -> 102849181
D27: Governmental capital assets, net | J27: =SUM(J11+J26) -> 108607342 | K27: =SUM(K11+K26) -> -987735 | L27: =SUM(L11+L26) -> 0 | M27: =SUM(M11+M26) -> 0 | N27: =SUM(N11+N26) -> 107619607 | O27: =SUM(O9:O26) -> 107619607
A29: Business-type Activities
B30: Capital assets, not being depreciated
C31: Construction in Progress | J31: 314569 | K31: 978058 | M31: -1242559 | N31: =SUM(J31:M31) -> 50068 | O31: =N31 -> 50068
C32: Land | J32: 2052372 | N32: =SUM(J32:M32) -> 2052372 | O32: =N32 -> 2052372
C33: Land improvements | J33: 1750227 | N33: =SUM(J33:M33) -> 1750227 | O33: =N33 -> 1750227
D34: Total capital assets not being depreciated | J34: =SUM(J31:J33) -> 4117168 | K34: =SUM(K31:K33) -> 978058 | L34: =SUM(L31:L33) -> 0 | M34: =SUM(M31:M33) -> -1242559 | N34: =SUM(N31:N33) -> 3852667
B36: Other capital asets:
C37: Buildings | J37: 4455578 | N37: =SUM(J37:M37) -> 4455578
C38: Equipment | J38: 8048427 | K38: 303955 | L38: -537371 | N38: =SUM(J38:M38) -> 7815011
C39: Improvements | J39: 17479387 | M39: 1242559 | N39: =SUM(J39:M39) -> 18721946
E40: Total capital assets being depreciated | J40: =SUM(J37:J39) -> 29983392 | K40: =SUM(K37:K39) -> 303955 | L40: =SUM(L37:L39) -> -537371 | M40: =SUM(M37:M39) -> 1242559 | N40: =SUM(N37:N39) -> 30992535
B42: Less accumulated depreciation for
C43: Buildings | J43: -4303340 | K43: -9288 | N43: =SUM(J43:M43) -> -4312628 | O43: =SUM(N43+N37) -> 142950
C44: Equipment | J44: -5983387 | K44: -424578 | L44: 537371 | N44: =SUM(J44:M44) -> -5870594 | O44: =SUM(N44+N38) -> 1944417
C45: Improvements | J45: -2730605 | K45: -597434 | N45: =SUM(J45:M45) -> -3328039 | O45: =SUM(N45+N39) -> 15393907
D46: Total accumulated depreciation | J46: =SUM(J43:J45) -> -13017332 | K46: =SUM(K43:K45) -> -1031300 | L46: =SUM(L43:L45) -> 537371 | M46: 0 | N46: =SUM(N43:N45) -> -13511261
D47: Other capital assets, net | J47: =SUM(J40+J46) -> 16966060 | K47: =SUM(K40+K46) -> -727345 | L47: =SUM(L40+L46) -> 0 | M47: =SUM(M40+M46) -> 1242559 | N47: =SUM(N40+N46) -> 17481274
D48: Business-type activities capital assets, net | J48: =SUM(J34+J47) -> 21083228 | K48: =SUM(K34+K47) -> 250713 | L48: =SUM(L34+L47) -> 0 | M48: =SUM(M34+M47) -> 0 | N48: =SUM(N34+N47) -> 21333941 | O48: =SUM(O31:O45) -> 21333941

Sheet St. Tammany
E1: ST. TAMMANY PARISH POLICE JURY
E2: Capital Assets
E3: For the Year Ended December 31, 2014
J5: Beginning Balance | K5: Increases | L5: Decreases | M5: Re-classes | N5: Ending Balance | O5: Cross Sectional
B7: Primary Government
B8: Governmental Activities
B9: Capital assets, not being depreciated:
B10: Land | J10: 46540187 | K10: 717211 | L10: -250935 | M10: -2486085 | N10: =SUM(J10:M10) -> 44520378 | O10: =N10 -> 44520378
B11: Land improvements-non-exhaustible | J11: 1873523 | M11: 488760 | N11: =SUM(J11:M11) -> 2362283 | O11: =N11 -> 2362283
B12: Construction in progress | J12: 218211 | K12: 3669895 | L12: -8102 | M12: -1700165 | N12: =SUM(J12:M12) -> 2179839 | O12: =N12 -> 2179839
B13: Infrastructure:
C14: Land | J14: 19688589 | K14: 2233259 | L14: -22728 | N14: =SUM(J14:M14) -> 21899120 | O14: =N14 -> 21899120
C15: Land Improvements-non-exhaustible | J15: 16208627 | K15: 723728 | M15: 2462960 | N15: =SUM(J15:M15) -> 19395315 | O15: =N15 -> 19395315
C16: Construction in progress | J16: 18860443 | K16: 24651548 | M16: -18555412 | N16: =SUM(J16:M16) -> 24956579 | O16: =N16 -> 24956579
C17: Total capital assets not being depreciated | J17: =SUM(J10:J16) -> 103389580 | K17: =SUM(K10:K16) -> 31995641 | L17: =SUM(L10:L16) -> -281765 | M17: =SUM(M10:M16) -> -19789942 | N17: =SUM(N10:N16) -> 115313514
B18: Capital assets, being depreciated:
B19: Land Improvements | J19: 4897831 | N19: =SUM(J19:M19) -> 4897831
B20: Buildings | J20: 99024270 | M20: 191090 | N20: =SUM(J20:M20) -> 99215360
B21: Building improvements | J21: 5878284 | K21: 56401 | M21: 60499 | N21: =SUM(J21:M21) -> 5995184
B22: Water and sewer systems | J22: 632317 | N22: =SUM(J22:M22) -> 632317
B23: Vehicles | J23: 4222812 | K23: 62143 | L23: -231982 | N23: =SUM(J23:M23) -> 4052973
B24: Machinery and equipment | J24: 23321474 | K24: 1355142 | L24: -161437 | N24: =SUM(J24:M24) -> 24515179
B25: Office/other equipment | J25: 9841194 | K25: 349714 | M25: 765599 | N25: =SUM(J25:M25) -> 10956507
B26: Infrastructure:
C27: Roads | J27: 268801448 | K27: 1472270 | L27: -339000 | M27: 11012240 | N27: =SUM(J27:M27) -> 280946958
C28: Other | J28: 30685951 | M28: 7523248 | N28: =SUM(J28:M28) -> 38209199
D29: Total capital assets being depreciated | J29: =SUM(J19:J28) -> 447305581 | K29: =SUM(K19:K28) -> 3295670 | L29: =SUM(L19:L28) -> -732419 | M29: =SUM(M19:M28) -> 19552676 | N29: =SUM(N19:N28) -> 469421508
B30: Less accumulated depreciation for:
B31: Land Improvements | J31: -1720722 | K31: -338043 | N31: =SUM(J31:M31) -> -2058765 | O31: =N19+N31 -> 2839066
B32: Buildings | J32: -26307468 | K32: -2482084 | N32: =SUM(J32:M32) -> -28789552 | O32: =N20+N32 -> 70425808
B33: Building improvements | J33: -1070900 | K33: -278848 | N33: =SUM(J33:M33) -> -1349748 | O33: =N21+N33 -> 4645436
B34: Water and sewer systems | J34: -127651 | K34: -25293 | N34: =SUM(J34:M34) -> -152944 | O34: =N22+N34 -> 479373
B35: Vehicles | J35: -3774958 | K35: -153848 | L35: 231982 | N35: =SUM(J35:M35) -> -3696824 | O35: =N23+N35 -> 356149
B36: Machinery and equipment | J36: -18668658 | K36: -1263712 | L36: 159837 | N36: =SUM(J36:M36) -> -19772533 | O36: =N24+N36 -> 4742646
B37: Office/other equipment | J37: -7102222 | K37: -913379 | N37: =SUM(J37:M37) -> -8015601 | O37: =N25+N37 -> 2940906
B38: Infrastructure:
C39: Roads | J39: -96310441 | K39: -9772907 | L39: 58650 | N39: =SUM(J39:M39) -> -106024698 | O39: =N27+N39 -> 174922260
C40: Other | J40: -4943508 | K40: -1244842 | N40: =SUM(J40:M40) -> -6188350 | O40: =N28+N40 -> 32020849
D41: Total accumulated depreciation | J41: =SUM(J31:J40) -> -160026528 | K41: =SUM(K31:K40) -> -16472956 | L41: =SUM(L31:L40) -> 450469 | M41: =SUM(M31:M40) -> 0 | N41: =SUM(N31:N40) -> -176049015
B42: Total capital assets being depreciated, net | J42: =SUM(J29+J41) -> 287279053 | K42: =SUM(K29+K41) -> -13177286 | L42: =SUM(L29+L41) -> -281950 | M42: =SUM(M29+M41) -> 19552676 | N42: =SUM(N29+N41) -> 293372493
A44: Internal Service Fund
B45: Capital assets, not being depreciated:
B46: Land | J46: 1718617 | N46: =SUM(J46:M46) -> 1718617 | O46: =N46 -> 1718617
C47: Total capital assets not being depreciated | J47: =SUM(J46:J46) -> 1718617 | K47: =SUM(K46:K46) -> 0 | L47: 0 | M47: =SUM(M46:M46) -> 0 | N47: =SUM(J47:M47) -> 1718617
B48: Capital assets, being depreciated:
B49: Land Improvements | J49: 455413 | N49: =SUM(J49:M49) -> 455413
B50: Buildings | J50: 23637722 | N50: =SUM(J50:M50) -> 23637722
B51: Building Improvements | J51: 5721577 | M51: 159799 | N51: =SUM(J51:M51) -> 5881376
B52: Vehicles | J52: 239560 | L52: -12896 | N52: =SUM(J52:M52) -> 226664
B53: Machinery and equipment | J53: 9999 | N53: =SUM(J53:M53) -> 9999
B54: Office/other equipment | J54: 1730689 | K54: 463567 | M54: 25950 | N54: =SUM(J54:M54) -> 2220206
D55: Total capital assets being depreciated | J55: =SUM(J49:J54) -> 31794960 | K55: =SUM(K49:K54) -> 463567 | L55: =SUM(L49:L54) -> -12896 | M55: =SUM(M49:M54) -> 185749 | N55: =SUM(N49:N54) -> 32431380
B56: Less accumulated depreciation for:
B57: Land Improvements | J57: -168073 | K57: -22770 | N57: =SUM(J57:M57) -> -190843 | O57: =N49+N57 -> 264570
B58: Buildings | J58: -7761154 | K58: -594011 | N58: =SUM(J58:M58) -> -8355165 | O58: =N50+N58 -> 15282557
B59: Building Improvements | J59: -1475219 | K59: -289493 | N59: =SUM(J59:M59) -> -1764712 | O59: =N51+N59 -> 4116664
B60: Vehicles | J60: -195557 | K60: -18681 | L60: 12896 | N60: =SUM(J60:M60) -> -201342 | O60: =N52+N60 -> 25322
B61: Machinery and equipment | J61: -3809 | K61: -1429 | N61: =SUM(J61:M61) -> -5238 | O61: =N53+N61 -> 4761
B62: Office/Other Equipment | J62: -1051854 | K62: -176995 | N62: =SUM(J62:M62) -> -1228849 | O62: =N54+N62 -> 991357
C63: Toal accumulated depreciation | J63: =SUM(J57:J62) -> -10655666 | K63: =SUM(K57:K62) -> -1103379 | L63: =SUM(L57:L62) -> 12896 | M63: =SUM(M57:M62) -> 0 | N63: =SUM(N57:N62) -> -11746149
D64: Total capital assets being depreciated, net | J64: =SUM(J55+J63) -> 21139294 | K64: =SUM(K55+K63) -> -639812 | L64: =SUM(L55+L63) -> 0 | M64: =SUM(M55+M63) -> 185749 | N64: =SUM(N55+N63) -> 20685231
D65: Total Capital Assets Internal Service Funds, net | J65: =SUM(J47+J55+J63) -> 22857911 | K65: =SUM(K47+K55+K63) -> -639812 | L65: =SUM(L47+L55+L63) -> 0 | M65: =SUM(M47+M55+M63) -> 185749 | N65: =SUM(N47+N55+N63) -> 22403848
D66: Total Capital Assets Governmental Activities, net | J66: =SUM(J17+J29+J41+J47+J55+J63) -> 413526544 | K66: =SUM(K17+K29+K41+K47+K55+K63) -> 18178543 | L66: =SUM(L17+L29+L41+L47+L55+L63) -> -563715 | M66: =SUM(M17+M29+M41+M47+M55+M63) -> -51517 | N66: =SUM(N17+N29+N41+N47+N55+N63) -> 431089855 | O66: =SUM(O10:O62) -> 431089855
A68: Business-type Activities
B69: Capital assets, not being depreciated
C70: Land | J70: 575567 | N70: =SUM(J70:M70) -> 575567 | O70: =N70 -> 575567
C71: Construction in Progress | J71: 591451 | K71: 564016 | M71: -26195 | N71: =SUM(J71:M71) -> 1129272 | O71: =N71 -> 1129272
C72: Total capital assets not being depreciated | J72: =SUM(J70:J71) -> 1167018 | K72: =SUM(K70:K71) -> 564016 | L72: =SUM(L70:L71) -> 0 | M72: =SUM(M70:M71) -> -26195 | N72: =SUM(N70:N71) -> 1704839
B73: Capital assets being depreciated
C74: Land Improvements | J74: 50707 | N74: =SUM(J74:M74) -> 50707
C75: Buildings | J75: 13376 | N75: =SUM(J75:M75) -> 13376
C76: Vehicles | J76: 482206 | K76: 78808 | L76: -1000 | N76: =SUM(J76:M76) -> 560014
C77: Machinery and Equipment | J77: 526769 | K77: 39912 | N77: =SUM(J77:M77) -> 566681
C78: Office/Other Equipment | J78: 6354 | N78: =SUM(J78:M78) -> 6354
C79: Infrastructure | N79: =SUM(J79:M79) -> 0
D80: Sewer equipment, lines and pumps | J80: 35017722 | K80: 84664 | M80: 26195 | N80: =SUM(J80:M80) -> 35128581
D81: Water equipment, lines and wells | J81: 17346057 | K81: 57283 | M81: 51517 | N81: =SUM(J81:M81) -> 17454857
E82: Total capital assets being depreciated | J82: =SUM(J74:J81) -> 53443191 | K82: =SUM(K74:K81) -> 260667 | L82: =SUM(L74:L81) -> -1000 | M82: =SUM(M74:M81) -> 77712 | N82: =SUM(N74:N81) -> 53780570
B83: Less accumulated depreciation for
C84: Land improvements | J84: -9014 | K84: -2536 | N84: =SUM(J84:M84) -> -11550 | O84: =SUM(N84+N74) -> 39157
C85: Buildings | J85: -2185 | K85: -535 | N85: =SUM(J85:M85) -> -2720 | O85: =SUM(N85+N75) -> 10656
C86: Vehicles | J86: -222108 | K86: -65024 | L86: 1000 | N86: =SUM(J86:M86) -> -286132 | O86: =SUM(N86+N76) -> 273882
C87: Machinery and Equipment | J87: -300627 | K87: -53895 | N87: =SUM(J87:M87) -> -354522 | O87: =SUM(N87+N77) -> 212159
C88: Office/Other Equipment | J88: -756 | K88: -908 | N88: =SUM(J88:M88) -> -1664 | O88: =SUM(N88+N78) -> 4690
C89: Infrastructure: | O89: =SUM(N89+N79) -> 0
D90: Sewer equipment, lines and pumps | J90: -10325819 | K90: -1683765 | N90: =SUM(J90:M90) -> -12009584 | O90: =SUM(N90+N80) -> 23118997
D91: Water equipment, lines and wells | J91: -3096165 | K91: -648106 | N91: =SUM(J91:M91) -> -3744271 | O91: =SUM(N91+N81) -> 13710586
D92: Total accumulated depreciation | J92: =SUM(J84:J91) -> -13956674 | K92: =SUM(K84:K91) -> -2454769 | L92: =SUM(L84:L91) -> 1000 | M92: 0 | N92: =SUM(N84:N91) -> -16410443
B93: Total capital assets being depreciated, net | J93: =SUM(J82+J92) -> 39486517 | K93: =SUM(K82+K92) -> -2194102 | L93: =SUM(L82+L92) -> 0 | M93: =SUM(M82+M92) -> 77712 | N93: =SUM(N82+N92) -> 37370127
B94: Total capital assets business-type activities, net | J94: =SUM(J72+J93) -> 40653535 | K94: =SUM(K72+K93) -> -1630086 | L94: =SUM(L72+L93) -> 0 | M94: =SUM(M72+M93) -> 51517 | N94: =SUM(N72+N93) -> 39074966 | O94: =SUM(O70:O91) -> 39074966
B95: Total capital assets- primary government, net | J95: =SUM(J94+J66) -> 454180079 | K95: =SUM(K66+K94) -> 16548457 | L95: =SUM(L66+L94) -> -563715 | M95: =SUM(M66+M94) -> 0 | N95: =SUM(N66+N94) -> 470164821

Sheet Tangipahoa
D1: TANGIPAHOA PARISH POLICE JURY
D2: Capital Assets
D3: For the Year Ended December 31, 2014
I5: Balance 12/31/13 | J5: Increase | K5: Decreases | L5: Balance 12/31/14 | M5: Cross Sectional
A6: Governmental Activities:
A7: Capital assets, not being depreciated:
C8: Land | I8: 2938462 | K8: -27818 | L8: =SUM(I8:K8) -> 2910644 | M8: =L8 -> 2910644
C9: Infrastructure (Land and Base) | I9: 70889285 | J9: 1123180 | L9: =SUM(I9:K9) -> 72012465 | M9: =L9 -> 72012465
C10: Construction in progress | I10: 9985749 | J10: 7896115 | K10: -15364106 | L10: =SUM(I10:K10) -> 2517758 | M10: =L10 -> 2517758
D11: Total assets not being depreciated | I11: =SUM(I8:I10) -> 83813496 | J11: =SUM(J8:J10) -> 9019295 | K11: =SUM(K8:K10) -> -15391924 | L11: =SUM(L8:L10) -> 77440867
A13: Capital assets, being depreciated:
B14: Buildings | I14: 40157566 | J14: 8902220 | K14: -30000 | L14: =SUM(I14:K14) -> 49029786
B15: Infrastructure | I15: 114068116 | J15: 6157196 | K15: -1431407 | L15: =SUM(I15:K15) -> 118793905
B16: Equipment | I16: 15638590 | J16: 1215945 | K16: -22794 | L16: =SUM(I16:K16) -> 16831741
D17: Total capital assets being depreciated | I17: =SUM(I14:I16) -> 169864272 | J17: =SUM(J14:J16) -> 16275361 | K17: =SUM(K14:K16) -> -1484201 | L17: =SUM(I17:K17) -> 184655432
A19: Less accumulated depreciation for
B20: Buildings | I20: 11979763 | J20: 1064523 | K20: -24328 | L20: =SUM(I20:K20) -> 13019958 | M20: =L14-L20 -> 36009828
B21: Infrastructure | I21: 54209407 | J21: 4237664 | K21: -723116 | L21: =SUM(I21:K21) -> 57723955 | M21: =L15-L21 -> 61069950
B22: Equipment | I22: 9358504 | J22: 1386261 | K22: -20515 | L22: =SUM(I22:K22) -> 10724250 | M22: =L16-L22 -> 6107491
D23: Total accumulated depreciation | I23: =SUM(I20:I22) -> 75547674 | J23: =SUM(J20:J22) -> 6688448 | K23: =SUM(K20:K22) -> -767959 | L23: =SUM(I23:K23) -> 81468163
A25: Total Capital Assets being depreciated, net | I25: =I17-I23 -> 94316598 | J25: =J17-J23 -> 9586913 | K25: =K17-K23 -> -716242 | L25: =L17-L23 -> 103187269
A26: Total Governmental activities, capital assets, net | I26: =I11+I25 -> 178130094 | J26: =J11+J25 -> 18606208 | K26: =K11+K25 -> -16108166 | L26: =L11+L25 -> 180628136 | M26: =SUM(M8:M24) -> 180628136

Sheet Tensas
D1: TENSAS PARISH POLICE JURY
D2: Capital Assets
D3: For the Year Ended December 31, 2014
I5: Balance, beginning | J5: Increase | K5: Decreases | L5: Balance, ending | M5: Cross Sectional
A6: Governmental-Type Activities:
A7: Capital assets, not being depreciated:
C8: Land | I8: 743698 | L8: =SUM(I8:K8) -> 743698 | M8: =L8 -> 743698
A10: Capital assets, being depreciated:
B11: Buildings | I11: 8329544 | J11: 560403 | L11: =SUM(I11:K11) -> 8889947
B12: Furniture, fixtures, and equipment | I12: 4385403 | J12: 20440 | L12: =SUM(I12:K12) -> 4405843
D13: Total capital assets being depreciated | I13: =SUM(I11:I12) -> 12714947 | J13: =SUM(J11:J12) -> 580843 | K13: =SUM(K11:K12) -> 0 | L13: =SUM(I13:K13) -> 13295790
A15: Primary Government
A16: Less accumulated depreciation
B17: Buildings | I17: -1383846 | J17: -232621 | L17: =SUM(I17:K17) -> -1616467 | M17: =L11+L17 -> 7273480
B18: Furniture, fixtures, and equipment | I18: -3506888 | J18: -261185 | L18: =SUM(I18:K18) -> -3768073 | M18: =L12+L18 -> 637770
D19: Total accumulated depreciation | I19: =SUM(I17:I18) -> -4890734 | J19: =SUM(J17:J18) -> -493806 | K19: =SUM(K17:K18) -> 0 | L19: =SUM(I19:K19) -> -5384540
A21: Total accumulated depreciation | I21: =SUM(I13+I19) -> 7824213 | J21: =SUM(J13+J19) -> 87037 | K21: =SUM(K13+K19) -> 0 | L21: =SUM(L13+L19) -> 7911250
A22: Total depreciable capital assets, net
A23: Governmental activities, capital assets, net | I23: =SUM(I21+I8) -> 8567911 | J23: =SUM(J21+J8) -> 87037 | K23: =SUM(K21+K8) -> 0 | L23: =SUM(L21+L8) -> 8654948 | M23: =SUM(M8:M20) -> 8654948

Sheet Terrebonne
E1: TERREBONNE PARISH POLICE JURY
E2: Capital Assets
E3: For the Year Ended December 31, 2014
J5: Balance 01/01/14 | K5: Additions | L5: Adjustments and Deletions | M5: Balance 12/31/14 | N5: Cross Sectional
B6: Capital assets, not being depreciated:
B7: Land | J7: 4988188 | K7: 1481815 | M7: =SUM(J7:L7) -> 6470003 | N7: =M7 -> 6470003
B8: Construction in progress | J8: 44105622 | K8: 26852469 | L8: -13586222 | M8: =SUM(J8:L8) -> 57371869 | N8: =M8 -> 57371869
C9: Total capital assets not being depreciated | J9: =SUM(J7:J8) -> 49093810 | K9: =SUM(K7:K8) -> 28334284 | L9: =SUM(L7:L8) -> -13586222 | M9: =SUM(M7:M8) -> 63841872
B10: Capital assets, being depreciated:
B11: Buildings | J11: 49731598 | K11: 3643337 | M11: =SUM(J11:L11) -> 53374935
B12: Equipment | J12: 62127101 | K12: 2850371 | L12: -203307 | M12: =SUM(J12:L12) -> 64774165
B13: Infrastructure: | J13: 266071498 | K13: 15202926 | M13: =SUM(J13:L13) -> 281274424
D14: Total capital assets being depreciated | J14: =SUM(J11:J13) -> 377930197 | K14: =SUM(K11:K13) -> 21696634 | L14: =SUM(L11:L13) -> -203307 | M14: =SUM(M11:M13) -> 399423524
B15: Less accumulated depreciation for:
B16: Buildings | J16: -21302542 | K16: -1277885 | M16: =SUM(J16:L16) -> -22580427 | N16: =M11+M16 -> 30794508
B17: Equipment | J17: -41432722 | K17: -3193802 | L17: 203307 | M17: =SUM(J17:L17) -> -44423217 | N17: =M12+M17 -> 20350948
B18: Infrastructure: | J18: -66562976 | K18: -7857284 | M18: =SUM(J18:L18) -> -74420260 | N18: =M13+M18 -> 206854164
D19: Total accumulated depreciation | J19: =SUM(J16:J18) -> -129298240 | K19: =SUM(K16:K18) -> -12328971 | L19: =SUM(L16:L18) -> 203307 | M19: =SUM(M16:M18) -> -141423904
B20: Total capital assets being depreciated, net | J20: =SUM(J14+J19) -> 248631957 | K20: =SUM(K14+K19) -> 9367663 | L20: =SUM(L14+L19) -> 0 | M20: =SUM(M14+M19) -> 257999620
B21: Total governmental activities capital assets, net | J21: =SUM(J9+J14+J19) -> 297725767 | K21: =SUM(K9+K14+K19) -> 37701947 | L21: =SUM(L9+L14+L19) -> -13586222 | M21: =SUM(M9+M14+M19) -> 321841492 | N21: =SUM(N7:N19) -> 321841492
A24: Business-type Activities
B25: Capital assets, not being depreciated:
B26: Land | J26: 3767923 | L26: -75000 | M26: =SUM(J26:L26) -> 3692923 | N26: =M26 -> 3692923
B27: Construction in progress | J27: 11900470 | K27: 4371934 | L27: -13486537 | M27: =SUM(J27:L27) -> 2785867 | N27: =M27 -> 2785867
C28: Total capital assets not being depreciated | J28: =SUM(J26:J27) -> 15668393 | K28: =SUM(K26:K27) -> 4371934 | L28: =SUM(L26:L27) -> -13561537 | M28: =SUM(J28:L28) -> 6478790
B29: Capital assets, being depreciated:
B30: Electric system and buildings | J30: 98846543 | K30: 2732823 | M30: =SUM(J30:L30) -> 101579366
B31: Gas distributions system and buildings | J31: 30483768 | K31: 413574 | L31: -20442 | M31: =SUM(J31:L31) -> 30876900
B32: Sewer system and buildings | J32: 122038036 | K32: 14649646 | L32: -25518 | M32: =SUM(J32:L32) -> 136662164
B33: Sanitation and buildings | J33: 8591365 | K33: 15422 | M33: =SUM(J33:L33) -> 8606787
B34: Civic center buildings and equipment | J34: 19284926 | K34: 11760 | M34: =SUM(J34:L34) -> 19296686
B35: Machinery and equipment | J35: 8365837 | K35: 359928 | M35: =SUM(J35:L35) -> 8725765
D36: Total capital assets being depreciated | J36: =SUM(J30:J35) -> 287610475 | K36: =SUM(K30:K35) -> 18183153 | L36: =SUM(L30:L35) -> -45960 | M36: =SUM(M30:M35) -> 305747668
B37: Less accumulated depreciation for:
B38: Electric system and buildings | J38: -68533348 | K38: -2215489 | M38: =SUM(J38:L38) -> -70748837 | N38: =M30+M38 -> 30830529
B39: Gas distributions system and buildings | J39: -14440087 | K39: -1091906 | L39: 20442 | M39: =SUM(J39:L39) -> -15511551 | N39: =M31+M39 -> 15365349
B40: Sewer system and buildings | J40: -54883444 | K40: -3082540 | L40: 25518 | M40: =SUM(J40:L40) -> -57940466 | N40: =M32+M40 -> 78721698
B41: Sanitation | J41: -1156295 | K41: -221884 | M41: =SUM(J41:L41) -> -1378179 | N41: =M33+M41 -> 7228608
B42: Civic center buildings and equipment | J42: -7889182 | K42: -516853 | M42: =SUM(J42:L42) -> -8406035 | N42: =M34+M42 -> 10890651
B43: Machinery and equipment | J43: -5273391 | K43: -333331 | M43: =SUM(J43:L43) -> -5606722 | N43: =M35+M43 -> 3119043
D44: Total accumulated depreciation | J44: =SUM(J38:J43) -> -152175747 | K44: =SUM(K38:K43) -> -7462003 | L44: =SUM(L38:L43) -> 45960 | M44: =SUM(J44:L44) -> -159591790
B45: Total capital assets being depreciated, net being depreciated, net | J45: =SUM(J36+J44) -> 135434728 | K45: =SUM(K36+K44) -> 10721150 | L45: =SUM(L36+L44) -> 0 | M45: =SUM(M36+M44) -> 146155878
B46: Total business-type activities capital assets, net | J46: =SUM(J28+J36+J44) -> 151103121 | K46: =SUM(K28+K36+K44) -> 15093084 | L46: =SUM(L28+L36+L44) -> -13561537 | M46: =SUM(M28+M36+M44) -> 152634668 | N46: =SUM(N26:N43) -> 152634668

Sheet Union
D1: UNION PARISH POLICE JURY
D2: Capital Assets
D3: For the Year Ended December 31, 2014
I5: Beginning Balance | J5: Additions | K5: Deletions | L5: Ending Balance | M5: Cross Sectional
A6: Governmental-Type Activities:
A7: Capital assets, not being depreciated:
B8: Land | I8: 760833 | J8: 202055 | L8: =SUM(I8:K8) -> 962888 | M8: =L8 -> 962888
B9: Construction in progress | I9: 1119052 | K9: -1119052 | L9: =SUM(I9:K9) -> 0 | M9: =L9 -> 0
C10: Total assets not being depreciated | I10: =SUM(I8:I9) -> 1879885 | J10: =SUM(J8:J9) -> 202055 | K10: =SUM(K8:K9) -> -1119052 | L10: =SUM(L8:L9) -> 962888
A12: Capital assets, being depreciated:
B13: Land improvements | I13: 1793309 | L13: =SUM(I13:K13) -> 1793309
B14: Buildings and improvements | I14: 9278634 | J14: 6771 | L14: =SUM(I14:K14) -> 9285405
B15: Other improvements | I15: 678680 | J15: 1159405 | L15: =SUM(I15:K15) -> 1838085
B16: Fire, sewer and water system improvements | I16: 1885608 | L16: =SUM(I16:K16) -> 1885608
B17: Public works equipment | I17: 6497122 | J17: 537771 | K17: -263283 | L17: =SUM(I17:K17) -> 6771610
B18: Vehicles | I18: 2279003 | J18: 135395 | K18: -282440 | L18: =SUM(I18:K18) -> 2131958
B19: Office furniture and equipment | I19: 699030 | L19: =SUM(I19:K19) -> 699030
B20: Library:
C21: Building and improvements | I21: 227302 | L21: =SUM(I21:K21) -> 227302
C22: Vehicle | I22: 192815 | K22: -87285 | L22: =SUM(I22:K22) -> 105530
C23: Office furniture and equipment | I23: 128378 | L23: =SUM(I23:K23) -> 128378
C24: Books and videos | I24: 705171 | J24: 69432 | K24: -34253 | L24: =SUM(I24:K24) -> 740350
C25: Total capital assets being depreciated | I25: =SUM(I13:I24) -> 24365052 | J25: =SUM(J13:J24) -> 1908774 | K25: =SUM(K13:K24) -> -667261 | L25: =SUM(L13:L24) -> 25606565
A27: Less accumulated depreciation for
B28: Land improvements | I28: 595351 | J28: 59349 | L28: =SUM(I28:K28) -> 654700 | M28: =L13-L28 -> 1138609
B29: Buildings and improvements | I29: 4032116 | J29: 231400 | L29: =SUM(I29:K29) -> 4263516 | M29: =L14-L29 -> 5021889
B30: Other improvements | I30: 6992 | J30: 62184 | L30: =SUM(I30:K30) -> 69176 | M30: =L15-L30 -> 1768909
B31: Fire, sewer and water system improvements | I31: 1119446 | J31: 102633 | L31: =SUM(I31:K31) -> 1222079 | M31: =L16-L31 -> 663529
B32: Public works equipment | I32: 4540029 | J32: 336814 | K32: -263283 | L32: =SUM(I32:K32) -> 4613560 | M32: =L17-L32 -> 2158050
B33: Vehicles | I33: 2054332 | J33: 99042 | K33: -282440 | L33: =SUM(I33:K33) -> 1870934 | M33: =L18-L33 -> 261024
B34: Office furniture and equipment | I34: 658654 | J34: 12314 | L34: =SUM(I34:K34) -> 670968 | M34: =L19-L34 -> 28062
B35: Library:
C36: Building and improvements | I36: 186532 | J36: 4227 | L36: =SUM(I36:K36) -> 190759 | M36: =L21-L36 -> 36543
C37: Vehicle | I37: 140050 | J37: 10553 | K37: -87285 | L37: =SUM(I37:K37) -> 63318 | M37: =L22-L37 -> 42212
C38: Office furniture and equipment | I38: 127123 | J38: 1255 | L38: =SUM(I38:K38) -> 128378 | M38: =L23-L38 -> 0
C39: Books and videos | I39: 576465 | J39: 51963 | K39: -34253 | L39: =SUM(I39:K39) -> 594175 | M39: =L24-L39 -> 146175
C40: Total accumulated depreciation | I40: =SUM(I28:I39) -> 14037090 | J40: =SUM(J28:J39) -> 971734 | K40: =SUM(K28:K39) -> -667261 | L40: =SUM(L28:L39) -> 14341563
A42: Total Capital Assets being depreciated, net | I42: =I25-I40 -> 10327962 | J42: =J25-J40 -> 937040 | K42: =K25-K40 -> 0 | L42: =L25-L40 -> 11265002
A43: Total capital assets, net | I43: =I10+I42 -> 12207847 | J43: =J10+J42 -> 1139095 | K43: =K10+K42 -> -1119052 | L43: =L10+L42 -> 12227890 | M43: =SUM(M8:M41) -> 12227890

Sheet Vermillion
D1: VERMILLION PARISH POLICE JURY
D2: Capital Assets
D3: For the Year Ended December 31, 2014
I5: Balance 01/01/14 | J5: Increases | K5: Decreases | L5: Balance 12/31/14 | M5: Cross Sectional
A6: Governmental activities
A7: Capital assets, not being depreciated:
B8: Polic Jury:
B9: Land | I9: 1893204 | J9: 434192 | L9: =SUM(I9:K9) -> 2327396 | M9: =L9 -> 2327396
B10: Construction in progress | I10: 3747744 | J10: 2496772 | K10: -3287878 | L10: =SUM(I10:K10) -> 2956638 | M10: =L10 -> 2956638
C11: Total assets not being depreciated | I11: =SUM(I9:I10) -> 5640948 | J11: =SUM(J9:J10) -> 2930964 | K11: =SUM(K9:K10) -> -3287878 | L11: =SUM(L9:L10) -> 5284034
A13: Capital assets, being depreciated:
B14: Police Jury:
C15: Buildings and improvements | I15: 19689083 | J15: 59261 | L15: =SUM(I15:K15) -> 19748344
C16: Furniture and equipment | I16: 23749110 | J16: 883673 | K16: -2924706 | L16: =SUM(I16:K16) -> 21708077
B17: Infrastructure:
C18: Road surfaces | I18: 134347023 | J18: 1246503 | L18: =SUM(I18:K18) -> 135593526
C19: Bridges and drainage improvements | I19: 14509678 | J19: 2628332 | L19: =SUM(I19:K19) -> 17138010
C20: Total capital assets being depreciated | I20: =SUM(I15:I19) -> 192294894 | J20: =SUM(J15:J19) -> 4817769 | K20: =SUM(K15:K19) -> -2924706 | L20: =SUM(L15:L19) -> 194187957
A22: Less accumulated depreciation for
B23: Police Jury:
C24: Building improvements | I24: 10257720 | J24: 452504 | L24: =SUM(I24:K24) -> 10710224 | M24: =L15-L24 -> 9038120
C25: Furniture and equipment | I25: 18181315 | J25: 810719 | K25: -1821303 | L25: =SUM(I25:K25) -> 17170731 | M25: =L16-L25 -> 4537346
B26: Infrastructure:
C27: Road surfaces | I27: 82749167 | J27: 2451748 | L27: =SUM(I27:K27) -> 85200915 | M27: =L18-L27 -> 50392611
C28: Bridges and drainage improvements | I28: 4247386 | J28: 338349 | L28: =SUM(I28:K28) -> 4585735 | M28: =L19-L28 -> 12552275
C29: Total accumulated depreciation | I29: =SUM(I24:I28) -> 115435588 | J29: =SUM(J24:J28) -> 4053320 | K29: =SUM(K24:K28) -> -1821303 | L29: =SUM(L24:L28) -> 117667605
A31: Total Capital Assets being depreciated, net | I31: =I20-I29 -> 76859306 | J31: =J20-J29 -> 764449 | K31: =K20-K29 -> -1103403 | L31: =L20-L29 -> 76520352
A32: Governmental activities capital assets, net | I32: =I11+I31 -> 82500254 | J32: =J11+J31 -> 3695413 | K32: =K11+K31 -> -4391281 | L32: =L11+L31 -> 81804386 | M32: =SUM(M9:M30) -> 81804386

Sheet Vernon
B1: VERNON PARISH POLICE JURY
B2: Capital Assets
B3: For the Year Ended December 31, 2014
A5: Primary Government - Governmental Activities:
C6: Land | D6: Construction in Progress | E6: Buildings and improvements | F6: Machinery and Equipment | G6: Infrastructure | H6: Library Book Collections | I6: Total
A7: Beginning balance | C7: 1695977 | E7: 12177793 | F7: 21253699 | G7: 50167390 | H7: 1915457 | I7: =SUM(C7:H7) -> 87210316
B8: Additions | D8: 7715076 | E8: 92628 | F8: 833179 | G8: 2692704 | H8: 218107 | I8: =SUM(C8:H8) -> 11551694
B9: Deletions | E9: 0 | F9: -98067 | I9: =SUM(C9:H9) -> -98067
A10: Ending balance | C10: =SUM(C7:C9) -> 1695977 | D10: =SUM(D7:D9) -> 7715076 | E10: =SUM(E7:E9) -> 12270421 | F10: =SUM(F7:F9) -> 21988811 | G10: =SUM(G7:G9) -> 52860094 | H10: =SUM(H7:H9) -> 2133564 | I10: =SUM(C10:H10) -> 98663943
A12: Less accumulated depreciation | C12: 0 | E12: -6099390 | F12: -13315237 | G12: -24687392 | H12: -1546240 | I12: =SUM(C12:H12) -> -45648259
A14: Capital assets, net | C14: =SUM(C10+C12) -> 1695977 | D14: =SUM(D10+D12) -> 7715076 | E14: =SUM(E10+E12) -> 6171031 | F14: =SUM(F10+F12) -> 8673574 | G14: =SUM(G10+G12) -> 28172702 | H14: =SUM(H10+H12) -> 587324 | I14: =SUM(I12,I10) -> 53015684 | J14: =SUM(J7:J13) -> 0
A16: Cross sectional | C16: =C10 -> 1695977 | D16: =D10 -> 7715076 | E16: =E10+E12 -> 6171031 | F16: =F10+F12 -> 8673574 | G16: =G10+G12 -> 28172702 | H16: =H10+H12 -> 587324 | I16: =SUM(I10+I12) -> 53015684

Sheet Washington
D1: WASHINGTON PARISH POLICE JURY
D2: Capital Assets
D3: For the Year Ended December 31, 2014
I5: Balance 12/31/13 | J5: Increases | K5: Decreases | L5: Balance 12/31/14 | M5: Cross Sectional
A6: Governmental-Type Activities:
A7: Capital assets, not being depreciated:
B8: Land | I8: 2560211 | J8: 1500 | K8: -26542 | L8: =SUM(I8:K8) -> 2535169 | M8: =L8 -> 2535169
B9: Construction in progress | I9: 217385 | J9: 448951 | K9: -208251 | L9: =SUM(I9:K9) -> 458085 | M9: =L9 -> 458085
C10: Total capital assets not being depreciated | I10: =SUM(I8:I9) -> 2777596 | J10: =SUM(J8:J9) -> 450451 | K10: =SUM(K8:K9) -> -234793 | L10: =SUM(L8:L9) -> 2993254
A12: Other capital assets:
B13: Buildings | I13: 10756300 | J13: 25912 | L13: =SUM(I13:K13) -> 10782212
B14: Equipment | I14: 6616011 | J14: 136913 | K14: -48422 | L14: =SUM(I14:K14) -> 6704502
B15: Books | I15: 1391013 | L15: =SUM(I15:K15) -> 1391013
B16: Asphalt roads | I16: 20989059 | L16: =SUM(I16:K16) -> 20989059
B17: 3-shot roads | I17: 6374774 | J17: 793346 | K17: -15704 | L17: =SUM(I17:K17) -> 7152416
B18: Bridges and culvets | I18: 21631465 | J18: 1652780 | K18: -79251 | L18: =SUM(I18:K18) -> 23204994
I19: =SUM(I13:I18) -> 67758622 | J19: =SUM(J13:J18) -> 2608951 | K19: =SUM(K13:K18) -> -143377 | L19: =SUM(L13:L18) -> 70224196
A20: Less accumulated depreciation for:
B21: Buildings | I21: -4406658 | J21: -262117 | L21: =SUM(I21:K21) -> -4668775 | M21: =L13+L21 -> 6113437
B22: Equipment | I22: -5220775 | J22: -472516 | K22: 40135 | L22: =SUM(I22:K22) -> -5653156 | M22: =L14+L22 -> 1051346
B23: Books | I23: -1389038 | J23: -1821 | L23: =SUM(I23:K23) -> -1390859 | M23: =L15+L23 -> 154
B24: Asphalt roads | I24: -12453466 | J24: -1399271 | L24: =SUM(I24:K24) -> -13852737 | M24: =L16+L24 -> 7136322
